Workbook

Sheet 底稿目录
A1: 底稿开列时，可先在以下单元格填写有关内容，以便其他底稿引用有关数据：
A2: 被审计单位： | D2: 序号 | E2: 内容 | F2: 索引号 | G2: 备注
A3: 截止日：202X年12月31日 | D3: 1 | E3: 货币资金分析表 | F3: E1-14
A4: 编制人： | D4: 2 | E4: 利息收入月度分析 | F4: E1-15
A5: 编制日期： | D5: 3 | E5: 自定义底稿 | F5: E1-16
A6: 复核人： | D6: 4 | E6: 自定义底稿 | F6: E1-17
A7: 复核日期：

Sheet 货币资金分析表E1-14
A1: 致同会计师事务所
A2: 货币资金分析表
A3: =底稿目录!A2 -> 被审计单位： | D3: =底稿目录!A4 -> 编制人： | H3: =底稿目录!A5 -> 编制日期： | J3: 索引号： | K3: =底稿目录!F3 -> E1-14
A4: =底稿目录!A3 -> 截止日：202X年12月31日 | D4: =底稿目录!A6 -> 复核人： | H4: =底稿目录!A7 -> 复核日期： | J4: 页 次：
A5: 一、审计目标:
A6: 1.资产负债表中记录的货币资金是存在的，且已记录于恰当的账户；
A7: 2.所有应当记录的货币资金均已记录，所有应当包括在财务报表中的相关披露均已包括；
A8: 3.货币资金以恰当的金额包括在财务报表中，与之相关的计价或分摊调整已恰当记录，相关披露已得到恰当计量和描述
A9: 二、审计过程：
A10: 1.计算银行存款占资产总额、定期存款占银行存款的比例；若二者比例偏高应进一步了解银行存款或定期存款比例偏高的原因，并取得相应支持文件。
A11: 2.计算定期存款及存放于非银行金融机构的存款占银行存款的比例，分析这些资金的安全性，注意被审计单位是否存在高息资金拆借。
A12: （一）货币资金构成分析表
A13: 序号 | B13: 货币资金项目 | C13: 46022 | E13: 45657 | G13: 45291 | I13: 变动情况 | K13: 变动原因
C14: 金额 | D14: 结构比 | E14: 金额 | F14: 结构比 | G14: 金额 | H14: 结构比 | I14: 本期变动 | J14: 上期变动
A15: 1 | B15: 库存现金 | D15: =IF(C15=0,0,C15/$C$18) -> 0 | F15: =IF(E15=0,0,E15/$E$18) -> 0 | H15: =IF(G15=0,0,G15/$G$18) -> 0 | I15: =IF(E15=0,1,(C15-E15)/E15) -> 1 | J15: =IF(G15=0,1,(E15-G15)/G15) -> 1
A16: 2 | B16: 银行存款 | D16: =IF(C16=0,0,C16/$C$18) -> 0 | F16: =IF(E16=0,0,E16/$E$18) -> 0 | H16: =IF(G16=0,0,G16/$G$18) -> 0 | I16: =IF(E16=0,1,(C16-E16)/E16) -> 1 | J16: =IF(G16=0,1,(E16-G16)/G16) -> 1
A17: 3 | B17: 其他货币资金 | D17: =IF(C17=0,0,C17/$C$18) -> 0 | F17: =IF(E17=0,0,E17/$E$18) -> 0 | H17: =IF(G17=0,0,G17/$G$18) -> 0 | I17: =IF(E17=0,1,(C17-E17)/E17) -> 1 | J17: =IF(G17=0,1,(E17-G17)/G17) -> 1
A18: 合计 | C18: =SUM(C15:C17) -> 0 | D18: =IF(C18=0,0,C18/$C$18) -> 0 | E18: =SUM(E15:E17) -> 0 | F18: =IF(E18=0,0,E18/$E$18) -> 0 | G18: =SUM(G15:G17) -> 0 | H18: =IF(G18=0,0,G18/$G$18) -> 0 | I18: =IF(E18=0,1,(C18-E18)/E18) -> 1 | J18: =IF(G18=0,1,(E18-G18)/G18) -> 1
A19: （二）其他货币资金分析表
A20: 序号 | B20: 货币资金项目 | C20: 46022 | E20: 45657 | G20: 45291 | I20: 变动情况 | K20: 变动原因
C21: 金额 | D21: 结构比 | E21: 金额 | F21: 结构比 | G21: 金额 | H21: 结构比 | I21: 本期变动 | J21: 上期变动
A22: 1 | B22: 银行汇票存款 | D22: =IF(C22=0,0,C22/$C$29) -> 0 | F22: =IF(E22=0,0,E22/$E$29) -> 0 | H22: =IF(G22=0,0,G22/$G$29) -> 0 | I22: =IF(E22=0,1,(C22-E22)/E22) -> 1 | J22: =IF(G22=0,1,(E22-G22)/G22) -> 1
A23: 2 | B23: 银行本票存款 | D23: =IF(C23=0,0,C23/$C$29) -> 0 | F23: =IF(E23=0,0,E23/$E$29) -> 0 | H23: =IF(G23=0,0,G23/$G$29) -> 0 | I23: =IF(E23=0,1,(C23-E23)/E23) -> 1 | J23: =IF(G23=0,1,(E23-G23)/G23) -> 1
A24: 3 | B24: 信用证保证金存款 | D24: =IF(C24=0,0,C24/$C$29) -> 0 | F24: =IF(E24=0,0,E24/$E$29) -> 0 | H24: =IF(G24=0,0,G24/$G$29) -> 0 | I24: =IF(E24=0,1,(C24-E24)/E24) -> 1 | J24: =IF(G24=0,1,(E24-G24)/G24) -> 1
A25: 4 | B25: 外埠存款 | D25: =IF(C25=0,0,C25/$C$29) -> 0 | F25: =IF(E25=0,0,E25/$E$29) -> 0 | H25: =IF(G25=0,0,G25/$G$29) -> 0 | I25: =IF(E25=0,1,(C25-E25)/E25) -> 1 | J25: =IF(G25=0,1,(E25-G25)/G25) -> 1
A26: 5 | B26: 存出投资款 | D26: =IF(C26=0,0,C26/$C$29) -> 0 | F26: =IF(E26=0,0,E26/$E$29) -> 0 | H26: =IF(G26=0,0,G26/$G$29) -> 0 | I26: =IF(E26=0,1,(C26-E26)/E26) -> 1 | J26: =IF(G26=0,1,(E26-G26)/G26) -> 1
A27: 6 | B27: 信用卡存款 | D27: =IF(C27=0,0,C27/$C$29) -> 0 | F27: =IF(E27=0,0,E27/$E$29) -> 0 | H27: =IF(G27=0,0,G27/$G$29) -> 0 | I27: =IF(E27=0,1,(C27-E27)/E27) -> 1 | J27: =IF(G27=0,1,(E27-G27)/G27) -> 1
A28: 7 | B28: 支付宝、微信及其他 | D28: =IF(C28=0,0,C28/$C$29) -> 0 | F28: =IF(E28=0,0,E28/$E$29) -> 0 | H28: =IF(G28=0,0,G28/$G$29) -> 0 | I28: =IF(E28=0,1,(C28-E28)/E28) -> 1 | J28: =IF(G28=0,1,(E28-G28)/G28) -> 1
A29: 合计 | C29: =SUM(C22:C28) -> 0 | D29: =IF(C29=0,0,C29/$C$18) -> 0 | E29: =SUM(E22:E28) -> 0 | F29: =IF(E29=0,0,E29/$E$18) -> 0 | G29: =SUM(G22:G28) -> 0 | H29: =IF(G29=0,0,G29/$G$18) -> 0 | I29: =IF(E29=0,1,(C29-E29)/E29) -> 1 | J29: =IF(G29=0,1,(E29-G29)/G29) -> 1
A30: 其他货币资金中银行承兑汇票保证金测算见应付票据底稿<F3-2>
A32: （三）货币资金项目比例分析表
A33: 序号 | B33: 项目 | C33: =C13 -> 46022 | D33: =E13 -> 45657 | E33: =G13 -> 45291 | F33: 本期变动 | G33: 上期变动 | H33: 差异原因及合理性解释
A34: 1 | B34: 银行存款÷资产总额 | F34: =IF(D34=0,1,(C34-D34)/D34) -> 1 | G34: =IF(E34=0,1,(D34-E34)/E34) -> 1
A35: 2 | B35: 定期存款÷银行存款 | F35: =IF(D35=0,1,(C35-D35)/D35) -> 1 | G35: =IF(E35=0,1,(D35-E35)/E35) -> 1
A36: 3 | B36: （定期存款+大额存单）÷银行存款 | F36: =IF(D36=0,1,(C36-D36)/D36) -> 1 | G36: =IF(E36=0,1,(D36-E36)/E36) -> 1
A37: 4 | B37: 受限货币资金÷货币资金 | F37: =IF(D37=0,1,(C37-D37)/D37) -> 1 | G37: =IF(E37=0,1,(D37-E37)/E37) -> 1
A38: 5 | B38: 存放财务公司款项÷货币资金 | F38: =IF(D38=0,1,(C38-D38)/D38) -> 1 | G38: =IF(E38=0,1,(D38-E38)/E38) -> 1
A39: 6 | B39: 货币资金÷贷款总额 | F39: =IF(D39=0,1,(C39-D39)/D39) -> 1 | G39: =IF(E39=0,1,(D39-E39)/E39) -> 1
A40: 7 | B40: 定期存款÷贷款总额 | F40: =IF(D40=0,1,(C40-D40)/D40) -> 1 | G40: =IF(E40=0,1,(D40-E40)/E40) -> 1
A41: 8 | B41: …… | F41: =IF(D41=0,1,(C41-D41)/D41) -> 1 | G41: =IF(E41=0,1,(D41-E41)/E41) -> 1
A43: 三、审计说明：
A44: 1.货币资金期初、期末的变化与被审计单位融资政策一致性：
A45: 2.公司期末现金余额是否合理？
A46: 3.货币资金余额持续较高、“存贷双高”（若存在）的合理性？
A47: 4.定期存款及存放于非银行金融机构、外埠存款、存出投资款等资金的安全性：
A48: 5.定期存款的商业理由及合理性？
A50: 四、审计结论：
A51: 提示：
A52: 如果定期存款占银行存款的比例偏高，或同时负债比例偏高，注册会计师需要向管理层询问定期存款存在的商业理由并评估其合理性；

Sheet 利息收入月度分析E1-15
A1: 致同会计师事务所
A2: 利息收入月度分析
A3: =底稿目录!A2 -> 被审计单位： | H3: =底稿目录!A4 -> 编制人： | O3: =底稿目录!A5 -> 编制日期： | U3: 索引号： | V3: =底稿目录!F4 -> E1-15
A4: =底稿目录!A3 -> 截止日：202X年12月31日 | H4: =底稿目录!A6 -> 复核人： | O4: =底稿目录!A7 -> 复核日期： | U4: 页次：
A5: 一、审计目标：
A6: 1.资产负债表中记录的货币资金是存在的，且已记录于恰当的账户；
A7: 2.所有应当记录的货币资金均已记录，所有应当包括在财务报表中的相关披露均已包括；
A8: 3.货币资金以恰当的金额包括在财务报表中，与之相关的计价或分摊调整已恰当记录，相关披露已得到恰当计量和描述
A9: 二、审计过程：
A10: 月份 | B10: 活期存款 | I10: 七天通知存款 | M10: 大额存单 | S10: 利息收入合计 | T10: 账面利息收入 | U10: 差异 | V10: 备注
B11: XX银行 | E11: XX银行 | H11: … | I11: XX银行 | L11: 利息收入 | M11: XX银行 | O11: XX银行 | Q11: 利息收入 | R11: …
B12: 年利率 | D12: 0.0005 | E12: 年利率 | G12: 0.0005 | I12: 银行账号1 | J12: 年化利率 | K12: … | M12: 银行账号1 | N12: 年化利率 | O12: 银行账号1 | P12: 年化利率
B13: 银行账号1 | C13: 银行账号2 | D13: 利息收入 | E13: 银行账号1 | F13: 银行账号2 | G13: 利息收入
A14: 1月 | D14: =SUM(B14:C14)*$D$12/12 -> 0 | G14: =SUM(E14:F14)*$G$12/12 -> 0 | L14: =I14*J14/12 -> 0 | Q14: =(M14*N14+O14*P14)/12 -> 0 | S14: =D14+G14+L14+Q14 -> 0 | U14: =S14-T14 -> 0
A15: 2月 | D15: =SUM(B15:C15)*$D$12/12 -> 0 | G15: =SUM(E15:F15)*$G$12/12 -> 0 | L15: =I15*J15/12 -> 0 | Q15: =(M15*N15+O15*P15)/12 -> 0 | S15: =D15+G15+L15+Q15 -> 0 | U15: =S15-T15 -> 0
A16: 3月 | D16: =SUM(B16:C16)*$D$12/12 -> 0 | G16: =SUM(E16:F16)*$G$12/12 -> 0 | L16: =I16*J16/12 -> 0 | Q16: =(M16*N16+O16*P16)/12 -> 0 | S16: =D16+G16+L16+Q16 -> 0 | U16: =S16-T16 -> 0
A17: 4月 | D17: =SUM(B17:C17)*$D$12/12 -> 0 | G17: =SUM(E17:F17)*$G$12/12 -> 0 | L17: =I17*J17/12 -> 0 | Q17: =(M17*N17+O17*P17)/12 -> 0 | S17: =D17+G17+L17+Q17 -> 0 | U17: =S17-T17 -> 0
A18: 5月 | D18: =SUM(B18:C18)*$D$12/12 -> 0 | G18: =SUM(E18:F18)*$G$12/12 -> 0 | L18: =I18*J18/12 -> 0 | Q18: =(M18*N18+O18*P18)/12 -> 0 | S18: =D18+G18+L18+Q18 -> 0 | U18: =S18-T18 -> 0
A19: 6月 | D19: =SUM(B19:C19)*$D$12/12 -> 0 | G19: =SUM(E19:F19)*$G$12/12 -> 0 | L19: =I19*J19/12 -> 0 | Q19: =(M19*N19+O19*P19)/12 -> 0 | S19: =D19+G19+L19+Q19 -> 0 | U19: =S19-T19 -> 0
A20: 7月 | D20: =SUM(B20:C20)*$D$12/12 -> 0 | G20: =SUM(E20:F20)*$G$12/12 -> 0 | L20: =I20*J20/12 -> 0 | Q20: =(M20*N20+O20*P20)/12 -> 0 | S20: =D20+G20+L20+Q20 -> 0 | U20: =S20-T20 -> 0
A21: 8月 | D21: =SUM(B21:C21)*$D$12/12 -> 0 | G21: =SUM(E21:F21)*$G$12/12 -> 0 | L21: =I21*J21/12 -> 0 | Q21: =(M21*N21+O21*P21)/12 -> 0 | S21: =D21+G21+L21+Q21 -> 0 | U21: =S21-T21 -> 0
A22: 9月 | D22: =SUM(B22:C22)*$D$12/12 -> 0 | G22: =SUM(E22:F22)*$G$12/12 -> 0 | L22: =I22*J22/12 -> 0 | Q22: =(M22*N22+O22*P22)/12 -> 0 | S22: =D22+G22+L22+Q22 -> 0 | U22: =S22-T22 -> 0
A23: 10月 | D23: =SUM(B23:C23)*$D$12/12 -> 0 | G23: =SUM(E23:F23)*$G$12/12 -> 0 | L23: =I23*J23/12 -> 0 | Q23: =(M23*N23+O23*P23)/12 -> 0 | S23: =D23+G23+L23+Q23 -> 0 | U23: =S23-T23 -> 0
A24: 11月 | D24: =SUM(B24:C24)*$D$12/12 -> 0 | G24: =SUM(E24:F24)*$G$12/12 -> 0 | L24: =I24*J24/12 -> 0 | Q24: =(M24*N24+O24*P24)/12 -> 0 | S24: =D24+G24+L24+Q24 -> 0 | U24: =S24-T24 -> 0
A25: 12月 | D25: =SUM(B25:C25)*$D$12/12 -> 0 | G25: =SUM(E25:F25)*$G$12/12 -> 0 | L25: =I25*J25/12 -> 0 | Q25: =(M25*N25+O25*P25)/12 -> 0 | S25: =D25+G25+L25+Q25 -> 0 | U25: =S25-T25 -> 0
A26: 合计 | B26: —— | C26: —— | D26: =SUM(D14:D25) -> 0 | E26: —— | F26: —— | G26: =SUM(G14:G25) -> 0 | H26: —— | I26: —— | J26: —— | K26: —— | L26: =SUM(L14:L25) -> 0 | M26: —— | N26: —— | O26: —— | P26: —— | Q26: =SUM(Q14:Q25) -> 0 | R26: —— | S26: =SUM(S14:S25) -> 0 | T26: =SUM(T14:T25) -> 0 | U26: =SUM(U14:U25) -> 0 | V26: ——
A28: 三、审计说明：
A29: 如果按月测算利息收入与账面利息收入存在较大差异，应进一步测算每日余额应收利息收入并与账面利息收入核对是否异常，详见<E1-30>
A31: 四、审计结论：
A33: 提示：
A34: 1.如果账面利息收入远大于根据定期存款计算应得利息，很可能表明被审计单位存在账外定期存款；如果账面利息收入远小于根据定期存款计算的应得利息，很可能表明被审计单位存在转移利息收入、或挪用、虚构定期存款情况；
A35: 2.计算银行存款每日余额应收利息收入，分析比较被审计单位银行存款应收利息收入与实际利息收入的差异是否恰当，评估利息收入的合理性，检查是否存在高息资金拆借，确认银行存款余额是否存在，利息收入是否已经完整记录，判断是否存在体外资金循环的情形。

Sheet 货币资金分析表F1-6 (修订前)
A1: 致同会计师事务所
A2: 货币资金分析表
A3: =底稿目录!A2 -> 被审计单位： | D3: =底稿目录!A4 -> 编制人： | H3: =底稿目录!A5 -> 编制日期： | J3: 索引号： | K3: F1-6
A4: =底稿目录!A3 -> 截止日：202X年12月31日 | D4: =底稿目录!A6 -> 复核人： | H4: =底稿目录!A7 -> 复核日期： | J4: 页 次：
A5: 一、审计目标:
A6: 1 | B6: 比较期初、期末银行存款余额，分析其变动原因。
A7: 2 | B7: 比较银行存款年度借贷方发生额与经营活动、筹资活动、投资活动的现金流量是否匹配，并分析原因。
A8: 二、审计过程：
A9: 1 | B9: 比较期初、期末货币资金余额（现金、银行存款、其他货币资金），了解被审计单位融资政策等，分析其变动原因，必要时与客户适当人员讨论。
A10: 2 | B10: 计算银行存款占资产总额、定期存款占银行存款的比例；若二者比例偏高，或二者比例偏高的同时，负债比例偏高或金额偏大，则应进一步了解银行存款或定期存款比例偏高的原因，并取得相应支持文件。
A11: 3 | B11: 计算定期存款及存放于非银行金融机构的存款占银行存款的比例，分析这些资金的安全性，注意被审计单位是否存在高息资金拆借。
A12: 4 | B12: 计算外埠存款、存出投资款占货币资金的比例，分析这些其他货币资金的安全性。
A13: 删除 | B13: 结合对利息收入和银行手续费的审计，分析被审计单位货币资金余额和交易的合理性。
A14: 删除 | B14: 比较银行存款年度借贷方发生额与经营活动、筹资活动、投资活动的现金流量是否匹配；若银行存款的发生额与经营活动产生的现金流量不匹配，应进一步查明原因，并获取相关支持文件。
A15: （一） | B15: 货币资金构成分析表
A16: 序号 | B16: 货币资金项目 | C16: 46022 | E16: 45657 | G16: 45291 | I16: 变动情况 | K16: 变动原因
C17: 金额 | D17: 结构比 | E17: 金额 | F17: 结构比 | G17: 金额 | H17: 结构比 | I17: 本期变动 | J17: 上期变动
A18: 1 | B18: 库存现金 | D18: =IF(C18=0,0,C18/$C$21) -> 0 | F18: =IF(E18=0,0,E18/$E$21) -> 0 | H18: =IF(G18=0,0,G18/$G$21) -> 0 | I18: =IF(E18=0,1,(C18-E18)/E18) -> 1 | J18: =IF(G18=0,1,(E18-G18)/G18) -> 1
A19: 2 | B19: 银行存款 | D19: =IF(C19=0,0,C19/$C$21) -> 0 | F19: =IF(E19=0,0,E19/$E$21) -> 0 | H19: =IF(G19=0,0,G19/$G$21) -> 0 | I19: =IF(E19=0,1,(C19-E19)/E19) -> 1 | J19: =IF(G19=0,1,(E19-G19)/G19) -> 1
A20: 3 | B20: 其他货币资金 | D20: =IF(C20=0,0,C20/$C$21) -> 0 | F20: =IF(E20=0,0,E20/$E$21) -> 0 | H20: =IF(G20=0,0,G20/$G$21) -> 0 | I20: =IF(E20=0,1,(C20-E20)/E20) -> 1 | J20: =IF(G20=0,1,(E20-G20)/G20) -> 1
A21: 合计 | C21: =SUM(C18:C20) -> 0 | D21: =IF(C21=0,0,C21/$C$21) -> 0 | E21: =SUM(E18:E20) -> 0 | F21: =IF(E21=0,0,E21/$E$21) -> 0 | G21: =SUM(G18:G20) -> 0 | H21: =IF(G21=0,0,G21/$G$21) -> 0 | I21: =IF(E21=0,1,(C21-E21)/E21) -> 1 | J21: =IF(G21=0,1,(E21-G21)/G21) -> 1
A22: （二） | B22: 货币资金项目比例分析表
A23: 序号 | B23: 项目 | C23: =C16 -> 46022 | D23: =E16 -> 45657 | E23: =G16 -> 45291 | F23: 本期变动 | G23: 上期变动 | H23: 差异原因及合理性解释
A24: 1 | B24: 银行存款÷资产总额 | F24: =IF(D24=0,1,(C24-D24)/D24) -> 1 | G24: =IF(E24=0,1,(D24-E24)/E24) -> 1
A25: 2 | B25: 定期存款÷银行存款 | F25: =IF(D25=0,1,(C25-D25)/D25) -> 1 | G25: =IF(E25=0,1,(D25-E25)/E25) -> 1
A26: 3 | B26: 负债总额÷资产总额 | F26: =IF(D26=0,1,(C26-D26)/D26) -> 1 | G26: =IF(E26=0,1,(D26-E26)/E26) -> 1
A27: 4 | B27: （定期存款+存放于非银行金融机构的存款）÷银行存款 | F27: =IF(D27=0,1,(C27-D27)/D27) -> 1 | G27: =IF(E27=0,1,(D27-E27)/E27) -> 1
A28: 5 | B28: （外埠存款+存出投资款）÷货币资金 | F28: =IF(D28=0,1,(C28-D28)/D28) -> 1 | G28: =IF(E28=0,1,(D28-E28)/E28) -> 1
B29: 定期存款的商业理由及合理性？
B30: 货币资金余额持续较高、“存贷双高”（若存在）的合理性？
A32: （三） | B32: 银行存款发生额与经营活动、筹资活动、投资活动的现金流量匹配分析 | F32: 移到现金流量表
A33: 流入分析 | G33: 流出分析
A34: 项目 | C34: 本期金额 | D34: 上期金额 | E34: 备注 | G34: 项目 | I34: 本期金额 | J34: 上期金额 | K34: 备注
A35: 1、现金流入 | C35: =C36+C37+C38 -> 0 | D35: =D36+D37+D38 -> 0 | G35: 1、现金流出 | I35: =I36+I37+I38 -> 0 | J35: =J36+J37+J38 -> 0
A36: 其中：经营活动 | G36: 其中：经营活动
A37: 筹资活动 | G37: 筹资活动
A38: 投资活动 | G38: 投资活动
A39: 2、银行存款借方 | G39: 2、银行存款贷方
A40: 借方发生总额 | G40: 贷方发生总额
A41: 减：银行存款跨行转账发生额 | G41: 减：银行存款跨行转账发生额
A42: 减：现金转存 | G42: 减：提取现金
A43: 应计入流入现金流量额 | C43: =C40-C41-C42 -> 0 | D43: =D40-D41-D42 -> 0 | G43: 应计入流出现金流量额 | I43: =I40-I41-I42 -> 0 | J43: =J40-J41-J42 -> 0
A44: 3、差异 | C44: =C35-C43 -> 0 | D44: =D35-D43 -> 0 | G44: 3、差异 | I44: =I35-I43 -> 0 | J44: =J35-J43 -> 0
A45: （四） | B45: 存款规模与利息收入匹配性分析
B46: 活期存款利息测算：1、取得活期银行存款每日余额；2、按活期银行存款日利率测算每日利息；累计每日利息得到活期存款本期应计利息。
B47: 定期存款利息测算：1、取得定期存款明细；2、按定期存款利率（或活期存款利率）及存期测算定期存款利息。
B48: 利息收入来源 | C48: 金额 | D48: 起息日 | E48: 截止日 | F48: 应计利息天数 | G48: 日利率 | H48: 应计利息 | I48: 备注
B49: 活期存款
B50: 定期存款 | H50: =F50*G50 -> 0
B52: 重大融资成分
B53: 合计 | H53: =SUM(H49:H52) -> 0
B54: 财务费用-利息收入
B55: 差异 | H55: =H53-H54 -> 0
B56: 财务费用-利息收入核算银行存款利息收入和按CAS 14（2017）核算的利息收入，其他金融资产利息收入在投资收益列示。
A58: （五） | B58: 账户数量及销户情况分析
B59: 账户数量是否与业务规模、业务实际需要相匹配？
B60: 本期是否存在销户情况，销户原因是否合理？
A62: 三、审计说明：
A63: 1 | B63: 货币资金期初、期末的变化与被审计单位融资政策是否一致；
A64: 2 | B64: 是否存在“存贷双高”现象，及其原因；
A65: 3 | B65: 定期存款及存放于非银行金融机构、外埠存款、存出投资款等资金的安全性；
A66: 4 | B66: 银行存款年度借贷方发生额与经营活动、筹资活动、投资活动的现金流量是否匹配；
A67: 5 | B67: 计算银行存款每日余额应收利息收入，分析比较被审计单位银行存款应收利息收入与实际利息收入的差异是否恰当，评估利息收入的合理性，检查是否存在高息资金拆借，
B68: 确认银行存款余额是否存在，利息收入是否已经完整记录，判断是否存在体外资金循环的情形。
A69: 四、审计结论：
A73: 一、编制说明：
B74: 如果被审计单位有定期存款，注册会计师可以考虑实施以下审计程序：
B75: （1）如果定期存款占银行存款的比例偏高，或同时负债比例偏高，注册会计师需要向管理层询问定期存款存在的商业理由并评估其合理性；
B76: （2）获取定期存款明细表，检查是否与账面记录金额一致，存款人是否为被审计单位，定期存款是否被质押或限制使用；
B77: （3）在监盘库存现金的同时，监盘定期存款凭据，或实地观察被审计单位登录网银系统查询定期存款信息并将查询信息截屏保存。如果被审计单位在资产负债表日有大额定期存款，基于对风险的判断考虑选择在资产负债表日实施监盘；
B78: （4）对存款期限跨越审计基准日的未质押的定期存款，检查开户证实书原件而非复印件，以防止被审计单位提供的复印件是未质押或未提现前原件的复印件，特别关注被审计单位在定期存单到期之前，是否存在先质押贷款或提前套现，再用质押贷款所得货币资金或套取的货币资金虚增收入、或挪作他用或从事其他违规业务。在检查时，还要认真核对相关信息，包括存款人、金额、期限等，如有异常，需实施进一步审计程序；
B79: （5）对已质押的定期存款，检查定期存单复印件，并与相应的质押合同核对，核对存款人、金额、期限等相关信息。对于质押借款的定期存单，关注定期存单对应的质押借款有无入账，对于超过借款期限但仍处于质押状态的定期存款，还应关注相关借款的偿还情况，了解相关质权是否已被行使；对于为他人担保的定期存单，关注担保是否逾期及相关质权是否已被行使；
B80: （6）函证定期存款相关信息，按照《中国注册会计师审计准则第1312号--函证》的要求实施函证程序；
B81: （7）结合财务费用和投资收益审计，分析利息收入的合理性，判断定期存款是否真实存在，或是否存在体外资金循环的情形。如果账面利息收入远大于根据定期存款计算应得利息，很可能表明被审计单位存在账外定期存款。如果账面利息收入远小于根据定期存款计算的应得利息，很可能表明被审计单位存在转移利息收入、或挪用、虚构定期存款情况；
B82: （8）对于在报告期内到期结转的定期存款、资产负债表日后已提取的定期存款，检查、核对相应的兑付凭证、银行对账单或网银记录等；
B83: （9）关注被审计单位是否在财务报表附注中对定期存款及其受限情况（如有）给予充分披露。
A85: 二、参考结论：
A86: A、 | B86: 未见异常。
A87: B、 | B87: 除以下重大不符事项应当作为调整事项予以调整外，其余未见异常。
A88: C、 | B88: 由于存在以下重大未调整事项（或审计范围受到限制无法获取充分、适当证据），不可确认。
