Workbook
Name _1、: #REF!
Name _1、受本循环影响的相关交易和账户余额: #REF!
Name _2、主要业务活动: #REF!
Name _2、注册会计师通常应在本循环中了解与上述业务活动相关的内部控制_如果计划在其他业务循环中对上述: #REF!
Name a暗暗: [1]企业表一!$F$20
Name CarryKnown: #REF!
Name CarryKnownTable: #REF!
Name CarryLikely: #REF!
Name CarryLikelyTable: #REF!
Name Carryover_Effect_of_Prior_Year: #REF!
Name CarryoverTitle: #REF!
Name CC_Instruction: #REF!
Name CE_CarryKnownProtection: #REF!
Name CE_CarryKnownTable: #REF!
Name CE_CarryLikely1Protection: #REF!
Name CE_CarryLikely1Table: #REF!
Name CE_CarryLikely2Protection: #REF!
Name CE_CarryLikely2Table: #REF!
Name CE_CarryTaxable: #REF!
Name CE_Desc: #REF!
Name CE_Income: #REF!
Name CE_KeepFormat: #REF!
Name CE_KnownChange: #REF!
Name CE_KnownFormulaProtection: #REF!
Name CE_KnownImpact: #REF!
Name CE_Likely1Change: #REF!
Name CE_Likely1FormulaProtection: #REF!
Name CE_Likely1Impact: #REF!
Name CE_Likely2Change: #REF!
Name CE_Likely2FormulaProtection: #REF!
Name CE_Likely2Impact: #REF!
Name CE_SheetCorrect: #REF!
Name CE_StatementImpact: #REF!
Name CE_TotalProtection: #REF!
Name CE_WholeSheet: #REF!
Name CE_XF1: #REF!
Name CE_XF1Rng1: #REF!
Name CE_XF1Rng2: #REF!
Name CE_XF2: #REF!
Name CE_XF2Rng1: #REF!
Name CE_XF2Rng2: #REF!
Name CE_XF3: #REF!
Name CE_XF3Rng1: #REF!
Name CE_XF3Rng2: #REF!
Name ChecklistQuestion1: #REF!
Name ChecklistQuestion2: #REF!
Name ChecklistQuestion3: #REF!
Name Conclusions1: #REF!
Name Conclusions2: #REF!
Name Conclusions3: #REF!
Name Conclusions4: #REF!
Name CorrectKey: #REF!
Name Current_Year_Known_and_Likely_Misstatements: #REF!
Name CY_all_Assets: #REF!
Name CY_all_Equity: #REF!
Name CY_all_Income: #REF!
Name CY_all_Liabs: #REF!
Name CY_all_RetEarn_bf: #REF!
Name CY_knw_Assets: #REF!
Name CY_knw_Equity: #REF!

Sheet 底稿目录
A1: 底稿开列时，可先在以下单元格填写有关内容，以便其他底稿引用有关数据：
A2: 被审计单位：
A3: 截止日：202X年12月31日
A4: 编制人： | D4: 序号 | E4: 内容 | F4: 索引号 | G4: 备注
A5: 编制日期： | D5: 1 | E5: 应付股利实质性程序表 | F5: M1A
A6: 复核人： | D6: 2 | E6: 审定表 | F6: M1-1
A7: 复核日期： | D7: 3 | E7: 附注披露信息(上市公司) | H7: 无需打印
A8: 项目类型（以下内容请根据实际情况修改）： | D8: 4 | E8: 附注披露信息(国企) | H8: 无需打印
A9: 普通股股利 | D9: 5 | E9: 明细表 | F9: M1-2
A10: 划分为权益工具的优先股股利 | D10: 6 | E10: 调整分录汇总 | F10: M1-3
A11: 划分为权益工具的永续债股利 | D11: 7 | E11: 外币汇率测算表 | F11: M1-4
A12: … | D12: 8 | E12: 应付股利（利润）测算表 | F12: M1-5
D13: 9 | E13: 应付股利（利润）检查表 | F13: M1-6
A14: 关于工作底稿与审计程序索引号对应的说明
A15: 1.编制的审计工作底稿应与审计程序对应。审计项目组应根据被审计单位实际情况和风险评估情况在实质性程序表中裁剪、修改或增加审计程序，根据实际执行的审计程序完成相应审计工作底稿，编制的工作底稿中应按自然顺序依次编制索引号，并通过唯一的索引号将与实质性程序表中的程序对应关联（即将工作底稿的索引号填入实质性程序表中的底稿索引号列）。
A19: 2.获取的支持性证据应与审计底稿或程序对应。审计项目组在完成底稿时获取的支持性证据应根据底稿索引号编制下一级按自然顺序排序的索引号（如D1-2-1、D1-2-2、……），并在底稿中说明引用的支持性证据、关联索引号。
A22: 3.工作底稿索引号的编码规则：实质性程序索引号按循环从“D”到“N”,循环内账户以顺序号排列，模板中底稿索引号按账户顺序+自然数顺序（即模板中索引号按二级自然顺序排列，如D1-1、D1-2、D1-3、……D1-N）。

Sheet 应付股利实质性程序表M1
A1: 致同会计师事务所
A2: 应付股利（利润）实质性程序
A3: =底稿目录!A2 -> 被审计单位： | C3: =底稿目录!A4 -> 编制人： | E3: =底稿目录!A5 -> 编制日期： | H3: 索引号： | I3: =底稿目录!F5 -> M1A
A4: =底稿目录!A3 -> 截止日：202X年12月31日 | C4: =底稿目录!A6 -> 复核人： | E4: =底稿目录!A7 -> 复核日期： | H4: 页 次：
A5: 一、本账户涉及的科目
A6: 应付股利
A7: 二、审计目标与认定的对应关系
A8: 审计目标 | G8: 财务报表的认定
A9: A. 资产负债表中记录的应付股利（利润）是存在的，且已经记录在恰当的账户中 | G9: 存在
A10: B. 所有应记录的应付股利（利润）均已记录，所有应当包括在财务报表中的相关披露均已包括 | G10: 完整性
A11: C. 记录的应付股利（利润）是被审计单位应当履行的偿还义务 | G11: 权利和义务
A12: D. 应付股利（利润）以恰当的金额包括在财务报表中，与之相关的计价或分摊调整已恰当记录，相关披露已得到恰当计量和描述 | G12: 准确性、计价和分摊
A13: E. 应付股利（利润）已被恰当地汇总或分解且表述清楚，相关披露在按照企业会计准则的编制基础下是相关的、可理解的 | G13: 列报
A14: 三、审计目标与审计程序的对应关系
A15: 序号 | B15: 审计程序 | C15: 程序分类 | D15: 财务报表的认定 | I15: 底稿索引号
D16: 存在 | E16: 完整性 | F16: 权利和 义务 | G16: 准确性、计价和分摊 | H16: 列报 | J16: 根据被审计单位实际情况和风险评估情况裁剪、修改或增加审计程序
A17: 1 | B17: 获取或编制应付股（利润）利明细表，完成以下工作，并编制审定表 （1）复核加计是否正确，与总账、明细账合计数核对是否相符，期初余额与上期审定期末余额是否相符； （4）非记账本位币的，检查其折算汇率是否正确，会计处理是否正确。 | C17: 常规★ | D17: √ | E17: √ | G17: √ | I17: M1-1 /M1-2 /M1-4
A18: 2 | B18: 在使用手工编制、自定义信息报告、系统生成的非固定格式报告等由被审计单位生成的信息时，测试有关信息准确性和完整性，并考虑针对编制和维护由被审计单位生成的信息的相关控制实施控制测试，以评价该信息是否能够为实现审计目的提供基础。 | C18: 常规★ | E18: √ | G18: √ | I18: T1/ | J18: 可参见《审计手册》4.2.6，由被审计单位生成的信息可能是由系统生成的、或手工编制的、或二者兼而有之的方式生成的。例如，由被审计单位生成的信息可能包括： • 不涉及自定义的、由系统生成的报告（如，固定格式报告）； • 可能通过人工自定义的、由系统生成的报告，例如，（计算机）查询信息或特别定制的报告； • 手工编制的信息，例如，汇总信息的电子表格或用以支持分配、计算以及调节的电子表格； • 其他系统生成或手工编制的信息，例如，由被审计单位编制的客户发票； • 通过影印、拍摄、扫描或其他方式转换成电子形式的文件记录。
A19: 3 | B19: 对期初余额的审计，取得应付股利（利润）期初余额明细表复核加计是否正确，与总账、明细账合计数是否相符，检查上期应付股利相关董事会/股东会决议文件、本期支付情况等。（适用于首次承接） | C19: 备选 | D19: √ | E19: √ | F19: √ | G19: √ | I19: M1- | J19: 由被审计单位生成的信息不包括： • 总分类账或明细分类账、试算平衡表、或经审计的财务报表； • 第三方（除了服务机构）的报表或报告，例如，原始银行对账单，或函证的回函； • 外部数据（例如，第三方发布的数据，如，定价来源）。
A20: 4 | B20: 审阅公司章程、股东会(或股东大会)和董事会会议纪要中有关股利的规定，是否包括：现金股利、股票股利、股票分割；权益回购；已出售的权益性工具。了解股利分配标准和发放方式是否符合有关规定并经法定程序批准、金额是否正确。 | C20: 常规★ | D20: √ | E20: √ | F20: √ | I20: M1-5
A21: 5 | B21: 对本期发生的应付股利（利润）的增减变动，检查支持性文件，确定会计处理是否正确。 | C21: 常规★ | D21: √ | F21: √ | G21: √ | I21: M1-6
A22: 6 | B22: 实施函证程序： （1）以积极方式对应付股利账款进行函证，设计询证函、发函前核实被函证单位信息； （2）注册会计师独立收发询证函； （3）编制函证结果汇总表，检查发函、回函物流信息和轨迹、比对回函印章和签字等以核实回函的真实性，检查回函是否相符，对不符事项查明原因确定是否存在错报； （4）如果未收到回函，应当考虑与被询证者联系，要求对方作出回应或再次寄发询证函，无法收到的回函实施替代程序； （5）如果管理层不允许寄发询证函的，询问管理层不允许寄发的原因，并就其原因的正当、合理性收集证据；考虑实施替代审计程序以获取相关、可靠的审计证据； （6）如果管理层不允许寄发询证函的原因不合理、或者认为回函不可靠，评价对评估的重大错报风险以及其他审计程序的性质、时间安排和范围的影响，并确定其对审计工作和审计意见的影响。 | C22: 常规★ | D22: √ | E22: √ | F22: √ | G22: √
A23: 7 | B23: 根据评估的舞弊风险等因素增加的审计程序。 | C23: IPO/上市/新三板/重组/舞弊应对
A24: 8 | B24: 检查应付股利是否已按企业会计准则或其他适用的规定在财务报表中做出恰当列报和披露。 | C24: 常规★ | H24: √ | I24: A1-1/A1-15 /A1-16

Sheet 审定表M1-1
A1: 致同会计师事务所
A2: 应付股利（利润）审定表
A3: =底稿目录!A2 -> 被审计单位： | E3: =底稿目录!A4 -> 编制人： | H3: =底稿目录!A5 -> 编制日期： | K3: 索引号： | L3: =底稿目录!F6 -> M1-1
A4: =底稿目录!A3 -> 截止日：202X年12月31日 | E4: =底稿目录!A6 -> 复核人： | H4: =底稿目录!A7 -> 复核日期： | K4: 页 次：
A5: 项目名称 | B5: 期初数 | F5: 期末数 | J5: 本期审定数与上期 审定数的比较 | L5: 原因分析
B6: 未审数 | C6: 账项调整 | D6: 重分类调整 | E6: 审定数 | F6: 未审数 | G6: 账项调整 | H6: 重分类调整 | I6: 审定数 | J6: 变动额 | K6: 变动率
A7: =底稿目录!A9 -> 普通股股利 | B7: ='明细表M1-2'!D25 -> 0 | C7: ='明细表M1-2'!H25 -> 0 | D7: ='明细表M1-2'!I25 -> 0 | E7: ='明细表M1-2'!N25 -> 0 | F7: ='明细表M1-2'!G25 -> 0 | G7: ='明细表M1-2'!J25+'明细表M1-2'!K25 -> 0 | H7: ='明细表M1-2'!L25+'明细表M1-2'!M25 -> 0 | I7: ='明细表M1-2'!Q25 -> 0 | J7: =I7-E7 -> 0 | K7: =IF(AND(E7=0,J7=0),0,IF(AND(E7=0,J7>0),1,J7/E7)) -> 0
A8: =底稿目录!A10 -> 划分为权益工具的优先股股利 | B8: ='明细表M1-2'!D26 -> 0 | C8: ='明细表M1-2'!H26 -> 0 | D8: ='明细表M1-2'!I26 -> 0 | E8: ='明细表M1-2'!N26 -> 0 | F8: ='明细表M1-2'!G26 -> 0 | G8: ='明细表M1-2'!J26+'明细表M1-2'!K26 -> 0 | H8: ='明细表M1-2'!L26+'明细表M1-2'!M26 -> 0 | I8: ='明细表M1-2'!Q26 -> 0 | J8: =I8-E8 -> 0 | K8: =IF(AND(E8=0,J8=0),0,IF(AND(E8=0,J8>0),1,J8/E8)) -> 0
A9: =底稿目录!A11 -> 划分为权益工具的永续债股利 | B9: ='明细表M1-2'!D27 -> 0 | C9: ='明细表M1-2'!H27 -> 0 | D9: ='明细表M1-2'!I27 -> 0 | E9: ='明细表M1-2'!N27 -> 0 | F9: ='明细表M1-2'!G27 -> 0 | G9: ='明细表M1-2'!J27+'明细表M1-2'!K27 -> 0 | H9: ='明细表M1-2'!L27+'明细表M1-2'!M27 -> 0 | I9: ='明细表M1-2'!Q27 -> 0 | J9: =I9-E9 -> 0 | K9: =IF(AND(E9=0,J9=0),0,IF(AND(E9=0,J9>0),1,J9/E9)) -> 0
A10: =底稿目录!A12 -> … | B10: ='明细表M1-2'!D28 -> 0 | C10: ='明细表M1-2'!H28 -> 0 | D10: ='明细表M1-2'!I28 -> 0 | E10: ='明细表M1-2'!N28 -> 0 | F10: ='明细表M1-2'!G28 -> 0 | G10: ='明细表M1-2'!J28+'明细表M1-2'!K28 -> 0 | H10: ='明细表M1-2'!L28+'明细表M1-2'!M28 -> 0 | I10: ='明细表M1-2'!Q28 -> 0 | J10: =I10-E10 -> 0 | K10: =IF(AND(E10=0,J10=0),0,IF(AND(E10=0,J10>0),1,J10/E10)) -> 0
A11: =底稿目录!A13 -> 0 | B11: ='明细表M1-2'!D29 -> 0 | C11: ='明细表M1-2'!H29 -> 0 | D11: ='明细表M1-2'!I29 -> 0 | E11: ='明细表M1-2'!N29 -> 0 | F11: ='明细表M1-2'!G29 -> 0 | G11: ='明细表M1-2'!J29+'明细表M1-2'!K29 -> 0 | H11: ='明细表M1-2'!L29+'明细表M1-2'!M29 -> 0 | I11: ='明细表M1-2'!Q29 -> 0 | J11: =I11-E11 -> 0 | K11: =IF(AND(E11=0,J11=0),0,IF(AND(E11=0,J11>0),1,J11/E11)) -> 0
A12: =底稿目录!A16 -> 0 | B12: ='明细表M1-2'!D31 -> 0 | C12: ='明细表M1-2'!H31 -> 0 | D12: ='明细表M1-2'!I31 -> 0 | E12: ='明细表M1-2'!N31 -> 0 | F12: ='明细表M1-2'!G31 -> 0 | G12: ='明细表M1-2'!J31+'明细表M1-2'!K31 -> 0 | H12: ='明细表M1-2'!L31+'明细表M1-2'!M31 -> 0 | I12: ='明细表M1-2'!Q31 -> 0 | J12: =I12-E12 -> 0 | K12: =IF(AND(E12=0,J12=0),0,IF(AND(E12=0,J12>0),1,J12/E12)) -> 0
A13: ='明细表M1-2'!A23 -> 合计 | B13: =SUM(B7:B12) -> 0 | C13: =SUM(C7:C12) -> 0 | D13: =SUM(D7:D12) -> 0 | E13: =SUM(E7:E12) -> 0 | F13: =SUM(F7:F12) -> 0 | G13: =SUM(G7:G12) -> 0 | H13: =SUM(H7:H12) -> 0 | I13: =SUM(I7:I12) -> 0 | J13: =SUM(J7:J12) -> 0 | K13: =IF(AND(E13=0,J13=0),0,IF(AND(E13=0,J13>0),1,J13/E13)) -> 0
A14: 试算平衡表数
A15: 差异数 | E15: =E13-E14 -> 0 | I15: =I13-I14 -> 0
A16: 1、审计说明
A17: （1）应付股利（利润）期末余额较期初余额增加（负数为减少）：
A18: 主要原因（比例超过30%的）：
A19: （2）欠付股利的原因说明。
A20: （3）与经审计的财务报表核对
B21: 期末数 | C21: 期初数 | D21: 索引号
A22: 应付利息审定数
A23: 应付股利审定数 | B23: =I13 -> 0 | C23: =E13 -> 0
A24: 其他应付款审定数
A25: 其他应付款合计数 | B25: =SUM(B22:B24) -> 0 | C25: =SUM(C22:C24) -> 0
A26: 报表数
A27: 差异 | B27: =B25-B26 -> 0 | C27: =C25-C26 -> 0
A29: 2、审计结论
A31: 提示：
A32: 1.董事会或类似机构通过的利润分配方案中拟分配的现金股利或利润，不做账务处理，但应在附注中披露。
A52: 5、说明基于获取的审计证据，在有关认定方面，是否发现重大错报或存在重大异常。
A53: 参考结论：
A54: A、 | B54: 未见异常，可以确认。
A55: B、 | B55: 经审计调整后可确认。
A56: C、 | B56: 由于存在上述重大未调整事项（或审计范围受到限制无法获取充分、适当证据），不可确认。

Sheet 附注披露信息（上市公司）
A1: 致同会计师事务所
A2: 应付股利（利润）附注披露信息（上市公司）
A3: =底稿目录!A2 -> 被审计单位： | B3: =底稿目录!A4 -> 编制人： | D3: =底稿目录!A5 -> 编制日期： | E3: 索引号： | F3: M1-1
A4: =底稿目录!A3 -> 截止日：202X年12月31日 | B4: =底稿目录!A6 -> 复核人： | D4: =底稿目录!A7 -> 复核日期： | E4: 页次：
A5: 应付股利
A6: 【其他应付款、应付股利与应付利息的合计数披露详见M4-1】
A7: 项目（或股东名称） | B7: 期末余额 | C7: 上年年末余额
A8: 普通股股利 | B8: ='审定表M1-1'!I7 -> 0 | C8: ='审定表M1-1'!E7 -> 0
A9: 划分为权益工具的优先股\永续债股利 | B9: =SUM(B10:B12) -> 0 | C9: =SUM(C10:C12) -> 0
A10: 其中：工具1
A11: 工具2
A14: 合 计 | B14: =B8+B9+B13 -> 0 | C14: =C8+C9+C13 -> 0
A15: 重要的超过1年未支付的应付股利：
A16: 股东名称 | B16: 应付股利金额 | C16: 未支付原因
A17: 可无限量添加行
A20: 合计 | B20: =SUM(B17:B19) -> 0

Sheet 附注披露信息（国有企业）
A1: 致同会计师事务所
A2: 应付股利（利润）附注披露信息（国有企业）
A3: =底稿目录!A2 -> 被审计单位： | B3: =底稿目录!A4 -> 编制人： | C3: =底稿目录!A5 -> 编制日期： | D3: 索引号：M1-1
A4: =底稿目录!A3 -> 截止日：202X年12月31日 | B4: =底稿目录!A6 -> 复核人： | C4: =底稿目录!A7 -> 复核日期： | D4: 页次：
A5: 应付股利
A6: 【其他应付款、应付股利与应付利息的合计数披露详见M4-1】
A8: 项 目 | B8: 期末余额 | C8: 期初余额
A9: 普通股股利 | B9: ='审定表M1-1'!I7 -> 0 | C9: ='审定表M1-1'!E7 -> 0
A10: 划分为权益工具的优先股\永续债股利 | B10: ='审定表M1-1'!I8+'审定表M1-1'!I9 -> 0 | C10: ='审定表M1-1'!E8+'审定表M1-1'!E9 -> 0
A11: 其他
A12: 合 计 | B12: =SUM(B9:B11) -> 0 | C12: =SUM(C9:C11) -> 0
A13: 注：包括重要的超过1 年未支付的应付股利，应披露未支付原因。

Sheet 明细表M1-2
A1: 致同会计师事务所
A2: 应付股利（利润）明细表
A3: =底稿目录!A2 -> 被审计单位： | G3: =底稿目录!A4 -> 编制人： | N3: =底稿目录!A5 -> 编制日期： | T3: 索引号： | U3: =底稿目录!F9 -> M1-2
A4: =底稿目录!A3 -> 截止日：202X年12月31日 | G4: =底稿目录!A6 -> 复核人： | N4: =底稿目录!A7 -> 复核日期： | T4: 页 次：
A5: 一、审计目标:
A6: 1.资产负债表中记录的应付股利（利润）是存在的，且已经记录在恰当的账户中；
A7: 2.所有应记录的应付股利（利润）均已记录，所有应当包括在财务报表中的相关披露均已包括；
A8: 3.应付股利（利润）以恰当的金额包括在财务报表中，与之相关的计价或分摊调整已恰当记录，相关披露已得到恰当计量和描述 ；
A9: 二、审计过程：
A10: 1.审阅股东会、董事会会议记录中相关规定。收集与应付股利（利润）账户变动有关的董股东（大）会决议、事会会议纪要、协议等文件资料。
A11: 2.检查应付股利的计提是否根据董事会或股东会(或股东大会)决定的利润分配方案，从税后可供分配利润中计算确定，如果存在未支付的股利关注未及时付出的原因。
A12: 股东名称 | B12: 公司代码 | C12: 股东类型 | D12: 未审数 | H12: 期初调整 | J12: 账项调整 | L12: 重分类调整 | N12: 审定数 | R12: 期末账龄 | S12: 超过1年未支付的原因 | T12: 相关文件索引号 | U12: 备注
D13: 期初数 | E13: 本期增加 | F13: 本期减少 | G13: 期末数 | H13: 账项调整 | I13: 重分类调整 | J13: 本期增加 | K13: 本期减少 | L13: 本期增加 | M13: 本期减少 | N13: 期初数 | O13: 本期增加 | P13: 本期减少 | Q13: 期末数
G14: =D14+E14-F14 -> 0 | N14: =D14+H14+I14 -> 0 | O14: =E14+J14+L14 -> 0 | P14: =F14+K14+M14 -> 0 | Q14: =N14+O14-P14 -> 0
G15: =D15+E15-F15 -> 0 | N15: =D15+H15+I15 -> 0 | O15: =E15+J15+L15 -> 0 | P15: =F15+K15+M15 -> 0 | Q15: =N15+O15-P15 -> 0
G16: =D16+E16-F16 -> 0 | N16: =D16+H16+I16 -> 0 | O16: =E16+J16+L16 -> 0 | P16: =F16+K16+M16 -> 0 | Q16: =N16+O16-P16 -> 0
G17: =D17+E17-F17 -> 0 | N17: =D17+H17+I17 -> 0 | O17: =E17+J17+L17 -> 0 | P17: =F17+K17+M17 -> 0 | Q17: =N17+O17-P17 -> 0
G18: =D18+E18-F18 -> 0 | N18: =D18+H18+I18 -> 0 | O18: =E18+J18+L18 -> 0 | P18: =F18+K18+M18 -> 0 | Q18: =N18+O18-P18 -> 0
G19: =D19+E19-F19 -> 0 | N19: =D19+H19+I19 -> 0 | O19: =E19+J19+L19 -> 0 | P19: =F19+K19+M19 -> 0 | Q19: =N19+O19-P19 -> 0
G20: =D20+E20-F20 -> 0 | N20: =D20+H20+I20 -> 0 | O20: =E20+J20+L20 -> 0 | P20: =F20+K20+M20 -> 0 | Q20: =N20+O20-P20 -> 0
G21: =D21+E21-F21 -> 0 | N21: =D21+H21+I21 -> 0 | O21: =E21+J21+L21 -> 0 | P21: =F21+K21+M21 -> 0 | Q21: =N21+O21-P21 -> 0
G22: =D22+E22-F22 -> 0 | N22: =D22+H22+I22 -> 0 | O22: =E22+J22+L22 -> 0 | P22: =F22+K22+M22 -> 0 | Q22: =N22+O22-P22 -> 0
A23: 合计 | D23: =SUM(D14:D22) -> 0 | E23: =SUM(E14:E22) -> 0 | F23: =SUM(F14:F22) -> 0 | G23: =SUM(G14:G22) -> 0 | H23: =SUM(H14:H22) -> 0 | I23: =SUM(I14:I22) -> 0 | J23: =SUM(J14:J22) -> 0 | K23: =SUM(K14:K22) -> 0 | ... Q23: =SUM(Q14:Q22) -> 0
A24: 其中：
A25: =底稿目录!A9 -> 普通股股利 | D25: =SUMPRODUCT(($C$14:$C$22=$A25)*(D$14:D$22)) -> 0 | E25: =SUMPRODUCT(($C$14:$C$22=$A25)*(E$14:E$22)) -> 0 | F25: =SUMPRODUCT(($C$14:$C$22=$A25)*(F$14:F$22)) -> 0 | G25: =SUMPRODUCT(($C$14:$C$22=$A25)*(G$14:G$22)) -> 0 | H25: =SUMPRODUCT(($C$14:$C$22=$A25)*(H$14:H$22)) -> 0 | I25: =SUMPRODUCT(($C$14:$C$22=$A25)*(I$14:I$22)) -> 0 | J25: =SUMPRODUCT(($C$14:$C$22=$A25)*(J$14:J$22)) -> 0 | K25: =SUMPRODUCT(($C$14:$C$22=$A25)*(K$14:K$22)) -> 0 | ... Q25: =SUMPRODUCT(($C$14:$C$22=$A25)*(Q$14:Q$22)) -> 0
A26: =底稿目录!A10 -> 划分为权益工具的优先股股利 | D26: =SUMPRODUCT(($C$14:$C$22=$A26)*(D$14:D$22)) -> 0 | E26: =SUMPRODUCT(($C$14:$C$22=$A26)*(E$14:E$22)) -> 0 | F26: =SUMPRODUCT(($C$14:$C$22=$A26)*(F$14:F$22)) -> 0 | G26: =SUMPRODUCT(($C$14:$C$22=$A26)*(G$14:G$22)) -> 0 | H26: =SUMPRODUCT(($C$14:$C$22=$A26)*(H$14:H$22)) -> 0 | I26: =SUMPRODUCT(($C$14:$C$22=$A26)*(I$14:I$22)) -> 0 | J26: =SUMPRODUCT(($C$14:$C$22=$A26)*(J$14:J$22)) -> 0 | K26: =SUMPRODUCT(($C$14:$C$22=$A26)*(K$14:K$22)) -> 0 | ... Q26: =SUMPRODUCT(($C$14:$C$22=$A26)*(Q$14:Q$22)) -> 0
A27: =底稿目录!A11 -> 划分为权益工具的永续债股利 | D27: =SUMPRODUCT(($C$14:$C$22=$A27)*(D$14:D$22)) -> 0 | E27: =SUMPRODUCT(($C$14:$C$22=$A27)*(E$14:E$22)) -> 0 | F27: =SUMPRODUCT(($C$14:$C$22=$A27)*(F$14:F$22)) -> 0 | G27: =SUMPRODUCT(($C$14:$C$22=$A27)*(G$14:G$22)) -> 0 | H27: =SUMPRODUCT(($C$14:$C$22=$A27)*(H$14:H$22)) -> 0 | I27: =SUMPRODUCT(($C$14:$C$22=$A27)*(I$14:I$22)) -> 0 | J27: =SUMPRODUCT(($C$14:$C$22=$A27)*(J$14:J$22)) -> 0 | K27: =SUMPRODUCT(($C$14:$C$22=$A27)*(K$14:K$22)) -> 0 | ... Q27: =SUMPRODUCT(($C$14:$C$22=$A27)*(Q$14:Q$22)) -> 0
A28: =底稿目录!A12 -> … | D28: =SUMPRODUCT(($C$14:$C$22=$A28)*(D$14:D$22)) -> 0 | E28: =SUMPRODUCT(($C$14:$C$22=$A28)*(E$14:E$22)) -> 0 | F28: =SUMPRODUCT(($C$14:$C$22=$A28)*(F$14:F$22)) -> 0 | G28: =SUMPRODUCT(($C$14:$C$22=$A28)*(G$14:G$22)) -> 0 | H28: =SUMPRODUCT(($C$14:$C$22=$A28)*(H$14:H$22)) -> 0 | I28: =SUMPRODUCT(($C$14:$C$22=$A28)*(I$14:I$22)) -> 0 | J28: =SUMPRODUCT(($C$14:$C$22=$A28)*(J$14:J$22)) -> 0 | K28: =SUMPRODUCT(($C$14:$C$22=$A28)*(K$14:K$22)) -> 0 | ... Q28: =SUMPRODUCT(($C$14:$C$22=$A28)*(Q$14:Q$22)) -> 0
A29: =底稿目录!A13 -> 0 | D29: =SUMPRODUCT(($C$14:$C$22=$A29)*(D$14:D$22)) -> 0 | E29: =SUMPRODUCT(($C$14:$C$22=$A29)*(E$14:E$22)) -> 0 | F29: =SUMPRODUCT(($C$14:$C$22=$A29)*(F$14:F$22)) -> 0 | G29: =SUMPRODUCT(($C$14:$C$22=$A29)*(G$14:G$22)) -> 0 | H29: =SUMPRODUCT(($C$14:$C$22=$A29)*(H$14:H$22)) -> 0 | I29: =SUMPRODUCT(($C$14:$C$22=$A29)*(I$14:I$22)) -> 0 | J29: =SUMPRODUCT(($C$14:$C$22=$A29)*(J$14:J$22)) -> 0 | K29: =SUMPRODUCT(($C$14:$C$22=$A29)*(K$14:K$22)) -> 0 | ... Q29: =SUMPRODUCT(($C$14:$C$22=$A29)*(Q$14:Q$22)) -> 0
A31: 三、审计说明：
A33: 四、审计结论：
A35: 提示：
A36: 1、企业根据股东大会或类似机构审议批准的利润分配方案，按应支付的现金股利或利润，借记“利润分配”科目，贷记本科目。
A37: 2、审计说明可以概述：（1）程序的测试情况、结果；（2）拟调整事项及其调整分录、未调整事项及其影响，审计范围受到限制情况及其影响。
A38: 3、审计结论可参考：A、未见异常。B、除上述重大不符事项应当作为调整事项予以调整外，其余未见异常。C、由于存在以下重大未调整事项(或审计范围受到限制无法获取充分、适当证据），不可确认。

Sheet 调整分录汇总M1-3
A1: 致同会计师事务所
A2: 应付股利（利润）调整分录汇总表
A3: =底稿目录!A2 -> 被审计单位： | C3: =底稿目录!A4 -> 编制人： | F3: =底稿目录!A5 -> 编制日期： | I3: 索引号： | J3: =底稿目录!F10 -> M1-3
A4: =底稿目录!A3 -> 截止日：202X年12月31日 | C4: =底稿目录!A6 -> 复核人： | F4: =底稿目录!A7 -> 复核日期： | I4: 页 次：
A5: 调整事项说明 | B5: 类别（报表调整/账项调整/其他） | C5: 报表项目 | D5: 科目名称 | E5: 附注项目 | F5: …… | G5: 借方调整金额 | H5: 贷方调整金额 | I5: 索引 | J5: 备注
A24: 【注：本底稿适用于调整分录较多、较复杂的项目，且仅列示与本报表项目相关的审计调整。项目组可根据项目实际情况选择是否使用该底稿。】

Sheet 外币汇率测算表M1-4
A1: 致同会计师事务所
A2: 外币汇率测算表
A3: =底稿目录!A2 -> 被审计单位： | C3: =底稿目录!A4 -> 编制人： | E3: =底稿目录!A5 -> 编制日期： | F3: 索引号： | G3: =底稿目录!F11 -> M1-4
A4: =底稿目录!A3 -> 截止日：202X年12月31日 | C4: =底稿目录!A6 -> 复核人： | E4: =底稿目录!A7 -> 复核日期： | F4: 页 次：
A5: 一、审计目标:
A6: 1.应付股利（利润）以恰当的金额包括在财务报表中，与之相关的计价或分摊调整已恰当记录，相关披露已得到恰当计量和描述
A7: 二、审计过程：
A8: 股本名称 | B8: 币种 | C8: 期末应付股利（利润）金额
C9: 原币金额 | D9: 折算汇率 | E9: 折合人民币 | F9: 账面数 | G9: 差额
E10: =C10*D10 -> 0 | G10: =E10-F10 -> 0
E11: =C11*D11 -> 0 | G11: =E11-F11 -> 0
E12: =C12*D12 -> 0 | G12: =E12-F12 -> 0
E13: =C13*D13 -> 0 | G13: =E13-F13 -> 0
E14: =C14*D14 -> 0 | G14: =E14-F14 -> 0
E15: =C15*D15 -> 0 | G15: =E15-F15 -> 0
A16: 合计 | C16: =SUM(C10:C15) -> 0 | E16: =SUM(E10:E15) -> 0 | F16: =SUM(F10:F15) -> 0 | G16: =SUM(G10:G15) -> 0
A17: 三、审计说明：
A19: 四、审计结论：

Sheet 应付股利（利润）测算表M1-5
A1: 致同会计师事务所
A2: 应付股利（利润）测算表
A3: =底稿目录!A2 -> 被审计单位： | C3: =底稿目录!A4 -> 编制人： | F3: =底稿目录!A5 -> 编制日期： | G3: 索引号： | H3: =底稿目录!F12 -> M1-5
A4: =底稿目录!A3 -> 截止日：202X年12月31日 | C4: =底稿目录!A6 -> 复核人： | F4: =底稿目录!A7 -> 复核日期： | G4: 页 次：
A5: 一、审计目标:
A6: 1.应付股利（利润）以恰当的金额包括在财务报表中，与之相关的计价或分摊调整已恰当记录，相关披露已得到恰当计量和描述
A7: 二、审计过程：
A8: 检查应付股利（利润）的计提是否根据董事会或股东会(或股东大会)决定的利润分配方案，从税后可供分配利润中计算确定。
A9: 股东名称 | B9: 股东会决议分配基数 | C9: 分配比例 | D9: 分配额 | E9: 实际分配额 | F9: 差异 | G9: 差异原因 | H9: 备注
D10: =B10*C10 -> 0 | F10: =D10-E10 -> 0
D11: =B11*C11 -> 0 | F11: =D11-E11 -> 0
D12: =B12*C12 -> 0 | F12: =D12-E12 -> 0
D13: =B13*C13 -> 0 | F13: =D13-E13 -> 0
D14: =B14*C14 -> 0 | F14: =D14-E14 -> 0
D15: =B15*C15 -> 0 | F15: =D15-E15 -> 0
D16: =B16*C16 -> 0 | F16: =D16-E16 -> 0
D17: =B17*C17 -> 0 | F17: =D17-E17 -> 0
A18: 合计 | B18: =SUM(B10:B17) -> 0 | C18: =SUM(C10:C17) -> 0 | D18: =SUM(D10:D17) -> 0 | E18: =SUM(E10:E17) -> 0 | F18: =SUM(F10:F17) -> 0
A19: 三、审计说明：
A22: 四、审计结论：
A26: 编制说明：
A27: 1、企业根据股东大会或类似机构审议批准的利润分配方案，按应支付的现金股利或利润，借记“利润分配”科目，贷记本科目。

Sheet 应付股利（利润）检查表M1-6
A1: 致同会计师事务所
A2: 应付股利（利润）检查表
A3: =底稿目录!A2 -> 被审计单位： | E3: =底稿目录!A4 -> 编制人： | H3: =底稿目录!A5 -> 编制日期： | O3: 索引号： | P3: =底稿目录!F13 -> M1-6
A4: =底稿目录!A3 -> 截止日：202X年12月31日 | E4: =底稿目录!A6 -> 复核人： | H4: =底稿目录!A7 -> 复核日期： | O4: 页 次：
A5: 一、测试目标：
A6: 1.资产负债表中记录的应付股利（利润）是存在的，且已经记录在恰当的账户中；
A7: 2.应付股利（利润）以恰当的金额包括在财务报表中，与之相关的计价或分摊调整已恰当记录，相关披露已得到恰当计量和描述
A8: 二、测试：
A9: 测试内容说明：1.原始凭证是否齐全； 2.记账凭证与原始凭证是否相符；3.账务处理是否正确；4.是否记录于恰当的会计期间；5.……
A10: 记账凭证 | H10: 支持性文件 | I10: 核对内容 | N10: 索引号 | O10: 是否异常 | P10: 备注说明
A11: 日期 | B11: 凭证编号 | C11: 业务内容 | D11: 对方科目 | E11: 对方明细科目 | F11: 借方金额 | G11: 贷方金额 | I11: 1 | J11: 2 | K11: 3 | L11: 4 | M11: 5
A20: 合计 | F20: =SUM(F12:F19) -> 0 | G20: =SUM(G12:G19) -> 0
A21: 三、审计说明：
A22: 1.本期发生额、期末余额检查比例： | D22: 方向 | E22: 账面金额 | F22: 检查金额 | G22: 检查比例 | H22: 如果检查比例较低应扩大检查样本量或说明原因
D23: 本期借方 | E23: ='明细表M1-2'!P23 -> 0 | F23: =F20 -> 0 | G23: =ROUND(F23/E23,4) -> #DIV/0!
D24: 本期贷方 | E24: ='明细表M1-2'!O23 -> 0 | F24: =G20 -> 0 | G24: =ROUND(F24/E24,2) -> #DIV/0!
A25: 2.……
A26: 四、审计结论：

Sheet GT_Custom
A1: C1 | B1: Custom 1
A2: C2 | B2: Custom 2
A3: C3 | B3: Custom 3
A4: C4 | B4: Custom 4
A5: C5 | B5: Custom 5
A6: C6 | B6: Custom 6
A7: C7 | B7: Custom 7
A8: C8 | B8: Custom 8
