Workbook

Sheet 底稿目录
A1: 底稿开列时，可先在以下单元格填写有关内容，以便其他底稿引用有关数据：
A2: 被审计单位：
A3: 截止日：202X年12月31日 | D3: 序号 | E3: 内容 | F3: 索引号 | G3: 备注
A4: 编制人： | D4: 1 | E4: 库存股实质性程序表 | F4: M3A
A5: 编制日期： | D5: 2 | E5: 审定表 | F5: M3-1
A6: 复核人： | D6: 3 | E6: 附注披露信息(上市公司) | H6: 无需打印
A7: 复核日期： | D7: 4 | E7: 明细表 | F7: M3-2
D8: 5 | E8: 调整分录汇总 | F8: M3-3
A9: 关于工作底稿与审计程序索引号对应的说明 | D9: 6 | E9: 外币汇率测算表 | F9: M3-4
A10: 1.编制的审计工作底稿应与审计程序对应。审计项目组应根据被审计单位实际情况和风险评估情况在实质性程序表中裁剪、修改或增加审计程序，根据实际执行的审计程序完成相应审计工作底稿，编制的工作底稿中应按自然顺序依次编制索引号，并通过唯一的索引号将与实质性程序表中的程序对应关联（即将工作底稿的索引号填入实质性程序表中的底稿索引号列）。 | D10: 7 | E10: 库存股检查表 | F10: M3-5
A14: 2.获取的支持性证据应与审计底稿或程序对应。审计项目组在完成底稿时获取的支持性证据应根据底稿索引号编制下一级按自然顺序排序的索引号（如D1-2-1、D1-2-2、……），并在底稿中说明引用的支持性证据、关联索引号。
A17: 3.工作底稿索引号的编码规则：实质性程序索引号按循环从“D”到“N”,循环内账户以顺序号排列，模板中底稿索引号按账户顺序+自然数顺序（即模板中索引号按二级自然顺序排列，如D1-1、D1-2、D1-3、……D1-N）。

Sheet  库存股实质性程序表 M3A
A1: 致同会计师事务所
A2: 库存股实质性程序
A3: =底稿目录!A2 -> 被审计单位： | C3: =底稿目录!A4 -> 编制人： | E3: =底稿目录!A5 -> 编制日期： | H3: 索引号： | I3: =底稿目录!F4 -> M3A
A4: =底稿目录!A3 -> 截止日：202X年12月31日 | C4: =底稿目录!A6 -> 复核人： | E4: =底稿目录!A7 -> 复核日期： | H4: 页 次：
A5: 一、本账户涉及的科目
A6: 库存股
A7: 二、审计目标与认定的对应关系
A8: 审计目标 | G8: 财务报表的认定
A9: A. 资产负债表中记录的实收资本是存在的，且已经记录在恰当的账户中 | G9: 存在
A10: B. 所有应记录的实收资本均已记录，所有应当包括在财务报表中的相关披露均已包括 | G10: 完整性
A11: C. 记录的实收资本由被审计单位拥有或控制 | G11: 权利和义务
A12: D. 实收资本以恰当的金额包括在财务报表中，与之相关的计价或分摊调整已恰当记录，相关披露已得到恰当计量和描述 | G12: 准确性、计价和分摊
A13: E. 实收资本已被恰当地汇总或分解且表述清楚，相关披露在按照企业会计准则的编制基础下是相关的、可理解的 | G13: 列报
A14: 三、计划实施的实质性程序
A15: 序号 | B15: 审计程序 | C15: 程序分类 | D15: 财务报表的认定 | I15: 底稿索引号
D16: 存在 | E16: 完整性 | F16: 权利和 义务 | G16: 准确性、计价和分摊 | H16: 列报 | J16: 根据被审计单位实际情况和风险评估情况裁剪、修改或增加审计程序
A17: 1 | B17: 获取或编制库存股明细表，并完成以下工作，并编制审定表 （1）复核加计是否正确，与总账、明细账合计数核对是否相符，期初余额与上期审定期末余额是否相符； （2）以非记账本位币出资的，检查其折算汇率是否符合规定，折算差额的会计处理是否正确。 | C17: 常规★ | D17: √ | E17: √ | G17: √ | I17: M3-1 /M3-2 /M3-4
A18: 2 | B18: 在使用手工编制、自定义信息报告、系统生成的非固定格式报告等由被审计单位生成的信息时，测试有关信息准确性和完整性，并考虑针对编制和维护由被审计单位生成的信息的相关控制实施控制测试，以评价该信息是否能够为实现审计目的提供基础。 | C18: 常规★ | E18: √ | G18: √ | I18: T1/ | J18: 可参见《审计手册》4.2.6，由被审计单位生成的信息可能是由系统生成的、或手工编制的、或二者兼而有之的方式生成的。例如，由被审计单位生成的信息可能包括： • 不涉及自定义的、由系统生成的报告（如，固定格式报告）； • 可能通过人工自定义的、由系统生成的报告，例如，（计算机）查询信息或特别定制的报告； • 手工编制的信息，例如，汇总信息的电子表格或用以支持分配、计算以及调节的电子表格； • 其他系统生成或手工编制的信息，例如，由被审计单位编制的客户发票； • 通过影印、拍摄、扫描或其他方式转换成电子形式的文件记录。
A19: 3 | B19: 对期初余额的审计，取得库存股期初余额明细表复核加计是否正确，与总账、明细账合计数是否相符，取得期初库存股形成的相关决议、文件，检查上期库存股在本期注销情况。（适用于首次承接） | C19: 备选 | D19: √ | E19: √ | F19: √ | G19: √ | J19: 由被审计单位生成的信息不包括： • 总分类账或明细分类账、试算平衡表、或经审计的财务报表； • 第三方（除了服务机构）的报表或报告，例如，原始银行对账单，或函证的回函； • 外部数据（例如，第三方发布的数据，如，定价来源）。
A20: 4 | B20: 对本期库存股发生的增减变动： （1）获取公司回购股份的股东（大）会/董事会决议、审批文件等，检查回购股份手续是否完整，是否符合法律规定。 （2）检查回购股份交易的记账凭证和原始凭证，检查会计处理是否正确。 （3）检查注销股份的相关流程是否合规、会计处理是否正确。 | C20: 常规★ | D20: √ | E20: √ | F20: √ | I20: M3-5
A21: 5 | B21: 复核普通股基本每股收益和稀释每股收益计算的准确性，将金额和股数与财务报表核对 | C21: 备选 | G21: √
A22: 6 | B22: 根据评估的舞弊风险等因素增加的审计程序。 | C22: IPO/上市/新三板/重组/舞弊应对
A23: 7 | B23: 检查库存股是否已按企业会计准则或其他适用的规定在财务报表中做出恰当列报和披露。 | C23: 常规★ | H23: √ | I23: A1-1/A1-15 /A1-16

Sheet 审定表M3-1
A1: 致同会计师事务所
A2: 库存股审定表
A3: =底稿目录!A2 -> 被审计单位： | C3: =底稿目录!A4 -> 编制人： | H3: =底稿目录!A5 -> 编制日期： | K3: 索引： | L3: =底稿目录!F5 -> M3-1
A4: =底稿目录!A3 -> 截止日：202X年12月31日 | C4: =底稿目录!A6 -> 复核人： | H4: =底稿目录!A7 -> 复核日期： | K4: 页次：
A5: 库存股类别 | B5: 期初数 | F5: 期末数 | J5: 本期审定数与上期 审定数的比较 | L5: 原因分析
B6: 未审数 | C6: 账项调整 | D6: 重分类调整 | E6: 审定数 | F6: 未审数 | G6: 账项调整 | H6: 重分类调整 | I6: 审定数 | J6: 变动额 | K6: 变动率
A7: ='明细表M3-2'!A15 -> 减资回购股份 | B7: ='明细表M3-2'!B15 -> 0 | C7: ='明细表M3-2'!G15 -> 0 | D7: ='明细表M3-2'!H15 -> 0 | E7: ='明细表M3-2'!M15 -> 0 | F7: ='明细表M3-2'!F15 -> 0 | G7: ='明细表M3-2'!G15+'明细表M3-2'!I15-'明细表M3-2'!J15 -> 0 | H7: ='明细表M3-2'!H15+'明细表M3-2'!K15-'明细表M3-2'!L15 -> 0 | I7: ='明细表M3-2'!P15 -> 0 | J7: =I7-E7 -> 0 | K7: =IF(AND(E7=0,J7=0),0,IF(AND(E7=0,J7>0),1,J7/E7)) -> 0
A8: ='明细表M3-2'!A16 -> 奖励员工回购股份 | B8: ='明细表M3-2'!B16 -> 0 | C8: ='明细表M3-2'!G16 -> 0 | D8: ='明细表M3-2'!H16 -> 0 | E8: ='明细表M3-2'!M16 -> 0 | F8: ='明细表M3-2'!F16 -> 0 | G8: ='明细表M3-2'!G16+'明细表M3-2'!I16-'明细表M3-2'!J16 -> 0 | H8: ='明细表M3-2'!H16+'明细表M3-2'!K16-'明细表M3-2'!L16 -> 0 | I8: ='明细表M3-2'!P16 -> 0 | J8: =I8-E8 -> 0 | K8: =IF(AND(E8=0,J8=0),0,IF(AND(E8=0,J8>0),1,J8/E8)) -> 0
A9: ='明细表M3-2'!A17 -> 对合并、分立决议有异议回购股份 | B9: ='明细表M3-2'!B17 -> 0 | C9: ='明细表M3-2'!G17 -> 0 | D9: ='明细表M3-2'!H17 -> 0 | E9: ='明细表M3-2'!M17 -> 0 | F9: ='明细表M3-2'!F17 -> 0 | G9: ='明细表M3-2'!G17+'明细表M3-2'!I17-'明细表M3-2'!J17 -> 0 | H9: ='明细表M3-2'!H17+'明细表M3-2'!K17-'明细表M3-2'!L17 -> 0 | I9: ='明细表M3-2'!P17 -> 0 | J9: =I9-E9 -> 0 | K9: =IF(AND(E9=0,J9=0),0,IF(AND(E9=0,J9>0),1,J9/E9)) -> 0
A10: ='明细表M3-2'!A18 -> 母子公司交叉持股 | B10: ='明细表M3-2'!B18 -> 0 | C10: ='明细表M3-2'!G18 -> 0 | D10: ='明细表M3-2'!H18 -> 0 | E10: ='明细表M3-2'!M18 -> 0 | F10: ='明细表M3-2'!F18 -> 0 | G10: ='明细表M3-2'!G18+'明细表M3-2'!I18-'明细表M3-2'!J18 -> 0 | H10: ='明细表M3-2'!H18+'明细表M3-2'!K18-'明细表M3-2'!L18 -> 0 | I10: ='明细表M3-2'!P18 -> 0 | J10: =I10-E10 -> 0 | K10: =IF(AND(E10=0,J10=0),0,IF(AND(E10=0,J10>0),1,J10/E10)) -> 0
A11: ='明细表M3-2'!A19 -> 0 | B11: ='明细表M3-2'!B19 -> 0 | C11: ='明细表M3-2'!G19 -> 0 | D11: ='明细表M3-2'!H19 -> 0 | E11: ='明细表M3-2'!M19 -> 0 | F11: ='明细表M3-2'!F19 -> 0 | G11: ='明细表M3-2'!G19+'明细表M3-2'!I19-'明细表M3-2'!J19 -> 0 | H11: ='明细表M3-2'!H19+'明细表M3-2'!K19-'明细表M3-2'!L19 -> 0 | I11: ='明细表M3-2'!P19 -> 0 | J11: =I11-E11 -> 0 | K11: =IF(AND(E11=0,J11=0),0,IF(AND(E11=0,J11>0),1,J11/E11)) -> 0
A12: ='明细表M3-2'!A20 -> 0 | B12: ='明细表M3-2'!B20 -> 0 | C12: ='明细表M3-2'!G20 -> 0 | D12: ='明细表M3-2'!H20 -> 0 | E12: ='明细表M3-2'!M20 -> 0 | F12: ='明细表M3-2'!F20 -> 0 | G12: ='明细表M3-2'!G20+'明细表M3-2'!I20-'明细表M3-2'!J20 -> 0 | H12: ='明细表M3-2'!H20+'明细表M3-2'!K20-'明细表M3-2'!L20 -> 0 | I12: ='明细表M3-2'!P20 -> 0 | J12: =I12-E12 -> 0 | K12: =IF(AND(E12=0,J12=0),0,IF(AND(E12=0,J12>0),1,J12/E12)) -> 0
A13: ='明细表M3-2'!A21 -> 0 | B13: ='明细表M3-2'!B21 -> 0 | C13: ='明细表M3-2'!G21 -> 0 | D13: ='明细表M3-2'!H21 -> 0 | E13: ='明细表M3-2'!M21 -> 0 | F13: ='明细表M3-2'!F21 -> 0 | G13: ='明细表M3-2'!G21+'明细表M3-2'!I21-'明细表M3-2'!J21 -> 0 | H13: ='明细表M3-2'!H21+'明细表M3-2'!K21-'明细表M3-2'!L21 -> 0 | I13: ='明细表M3-2'!P21 -> 0 | J13: =I13-E13 -> 0 | K13: =IF(AND(E13=0,J13=0),0,IF(AND(E13=0,J13>0),1,J13/E13)) -> 0
A14: ='明细表M3-2'!A22 -> 0 | B14: ='明细表M3-2'!B22 -> 0 | C14: ='明细表M3-2'!G22 -> 0 | D14: ='明细表M3-2'!H22 -> 0 | E14: ='明细表M3-2'!M22 -> 0 | F14: ='明细表M3-2'!F22 -> 0 | G14: ='明细表M3-2'!G22+'明细表M3-2'!I22-'明细表M3-2'!J22 -> 0 | H14: ='明细表M3-2'!H22+'明细表M3-2'!K22-'明细表M3-2'!L22 -> 0 | I14: ='明细表M3-2'!P22 -> 0 | J14: =I14-E14 -> 0 | K14: =IF(AND(E14=0,J14=0),0,IF(AND(E14=0,J14>0),1,J14/E14)) -> 0
A15: ='明细表M3-2'!A23 -> 0 | B15: ='明细表M3-2'!B23 -> 0 | C15: ='明细表M3-2'!G23 -> 0 | D15: ='明细表M3-2'!H23 -> 0 | E15: ='明细表M3-2'!M23 -> 0 | F15: ='明细表M3-2'!F23 -> 0 | G15: ='明细表M3-2'!G23+'明细表M3-2'!I23-'明细表M3-2'!J23 -> 0 | H15: ='明细表M3-2'!H23+'明细表M3-2'!K23-'明细表M3-2'!L23 -> 0 | I15: ='明细表M3-2'!P23 -> 0 | J15: =I15-E15 -> 0 | K15: =IF(AND(E15=0,J15=0),0,IF(AND(E15=0,J15>0),1,J15/E15)) -> 0
A16: ='明细表M3-2'!A24 -> 0 | B16: ='明细表M3-2'!B24 -> 0 | C16: ='明细表M3-2'!G24 -> 0 | D16: ='明细表M3-2'!H24 -> 0 | E16: ='明细表M3-2'!M24 -> 0 | F16: ='明细表M3-2'!F24 -> 0 | G16: ='明细表M3-2'!G24+'明细表M3-2'!I24-'明细表M3-2'!J24 -> 0 | H16: ='明细表M3-2'!H24+'明细表M3-2'!K24-'明细表M3-2'!L24 -> 0 | I16: ='明细表M3-2'!P24 -> 0 | J16: =I16-E16 -> 0 | K16: =IF(AND(E16=0,J16=0),0,IF(AND(E16=0,J16>0),1,J16/E16)) -> 0
A17: 合计 | B17: =SUM(B7:B16) -> 0 | C17: =SUM(C7:C16) -> 0 | D17: =SUM(D7:D16) -> 0 | E17: =SUM(E7:E16) -> 0 | F17: =SUM(F7:F16) -> 0 | G17: =SUM(G7:G16) -> 0 | H17: =SUM(H7:H16) -> 0 | I17: =SUM(I7:I16) -> 0 | J17: =I17-E17 -> 0 | K17: =IF(AND(E17=0,J17=0),0,IF(AND(E17=0,J17>0),1,J17/E17)) -> 0
A18: 试算平衡表数
A19: 差异数 | E19: =E17-E18 -> 0 | I19: =I17-I18 -> 0
A20: 1、审计说明
A21: （1）期末余额较期初余额增加（负数为减少）：
A22: 主要原因（比例超过30%的）：
A25: （2）情况说明。
A28: 2、审计结论
A32: 提示：
A33: 限制性股票应重分类为其他应付款并以公允价值计量。除了解锁后的限制因素外，限制性股票的公允价值应以普通股市价为基础进行计量。限制性股票的公允价值=授予日流通股的市价（收盘价）-解锁后的限制性因素成本。

Sheet 附注披露信息（上市公司）
A1: 致同会计师事务所
A2: 库存股附注披露信息（上市公司）
A3: =底稿目录!A2 -> 被审计单位： | B3: =底稿目录!A4 -> 编制人： | C3: =底稿目录!A5 -> 编制日期： | E3: 索引号：
A4: =底稿目录!A3 -> 截止日：202X年12月31日 | B4: =底稿目录!A6 -> 复核人： | C4: =底稿目录!A7 -> 复核日期： | E4: 页次：
A5: 库存股
A6: 项 目 | B6: 期初余额 | C6: 本期增加 | D6: 本期减少 | E6: 期末余额
A7: 股份总数
A8: 股份总数
A10: 合 计
A11: 说明：
A12: （1）库存股变动情况及原因。回购本公司股份的原因及对应的库存股成本确定方法；
A13: （2）因库存股注销而减少的股本；
A14: （3）注销的库存股成本高于对应股本成本的，披露依次冲减的资本公积、盈余公积、未分配利润的金额；注销的库存股成本低于对应股本成本的，披露增加的资本公积金额；
A15: （4）库存股转让时，转让收入高于库存股成本的，披露增加的资本公积金额；转让收入低于库存股成本的，披露依次冲减的资本公积、盈余公积、未分配利润的金额；
A16: （5）因实行股权激励回购本公司股份的，应披露本期回购股份占本公司已发行股份的总比例和累计库存股占已发行股份的总比例。

Sheet 明细表M3-2
A1: 致同会计师事务所
A2: 库存股明细表
A3: =底稿目录!A2 -> 被审计单位： | D3: =底稿目录!A4 -> 编制人： | K3: =底稿目录!A5 -> 编制日期： | R3: 索引号： | S3: =底稿目录!F7 -> M3-2
A4: =底稿目录!A3 -> 截止日：202X年12月31日 | D4: =底稿目录!A6 -> 复核人： | K4: =底稿目录!A7 -> 复核日期： | R4: 页次：
A5: 一、审计目标:
A6: 1.资产负债表中记录的库存股是存在的，且已经记录在恰当的账户中；
A7: 2.所有应记录的库存股均已记录，所有应当包括在财务报表中的相关披露均已包括；
A8: 3.库存股以恰当的金额包括在财务报表中，与之相关的计价或分摊调整已恰当记录，相关披露已得到恰当计量和描述 ；
A9: 二、审计过程：
A10: 1.检查股票回购的交易活动。检查的内容包括已发行股票的登记簿、回购的股票、银行对账单、会计账面记录等；
A11: 2.以回购股票以及其他法定程序报经批准减资的，检查股东会决议以及相关的法律文件，手续是否办理，检查其是否按注销的股票面值总额和所注销的库存股的账面余额，冲减资本公积，会计处理是否正确；
A12: 库存股类别 | B12: 未审数 | G12: 期初调整 | I12: 账项调整 | K12: 重分类调整 | M12: 审定数 | Q12: 相关决议索引号 | R12: 相关会计处理是否正确 | S12: 备注
B13: 期初数 | C13: 本期增加 | D13: 本期减少 | F13: 期末数 | G13: 账项调整 | H13: 重分类调整 | I13: 本期增加 | J13: 本期减少 | K13: 本期增加 | L13: 本期减少 | M13: 期初数 | N13: 本期增加 | O13: 本期减少 | P13: 期末数
D14: 转让 | E14: 注销
A15: 减资回购股份 | F15: =B15+C15-D15-E15 -> 0 | M15: =B15+G15+H15 -> 0 | N15: =C15+I15+K15 -> 0 | O15: =D15+E15+J15+L15 -> 0 | P15: =M15+N15-O15 -> 0
A16: 奖励员工回购股份 | F16: =B16+C16-D16-E16 -> 0 | M16: =B16+G16+H16 -> 0 | N16: =C16+I16+K16 -> 0 | O16: =D16+E16+J16+L16 -> 0 | P16: =M16+N16-O16 -> 0
A17: 对合并、分立决议有异议回购股份 | F17: =B17+C17-D17-E17 -> 0 | M17: =B17+G17+H17 -> 0 | N17: =C17+I17+K17 -> 0 | O17: =D17+E17+J17+L17 -> 0 | P17: =M17+N17-O17 -> 0
A18: 母子公司交叉持股 | F18: =B18+C18-D18-E18 -> 0 | M18: =B18+G18+H18 -> 0 | N18: =C18+I18+K18 -> 0 | O18: =D18+E18+J18+L18 -> 0 | P18: =M18+N18-O18 -> 0
F19: =B19+C19-D19-E19 -> 0 | M19: =B19+G19+H19 -> 0 | N19: =C19+I19+K19 -> 0 | O19: =D19+E19+J19+L19 -> 0 | P19: =M19+N19-O19 -> 0
F20: =B20+C20-D20-E20 -> 0 | M20: =B20+G20+H20 -> 0 | N20: =C20+I20+K20 -> 0 | O20: =D20+E20+J20+L20 -> 0 | P20: =M20+N20-O20 -> 0
F21: =B21+C21-D21-E21 -> 0 | M21: =B21+G21+H21 -> 0 | N21: =C21+I21+K21 -> 0 | O21: =D21+E21+J21+L21 -> 0 | P21: =M21+N21-O21 -> 0
F22: =B22+C22-D22-E22 -> 0 | M22: =B22+G22+H22 -> 0 | N22: =C22+I22+K22 -> 0 | O22: =D22+E22+J22+L22 -> 0 | P22: =M22+N22-O22 -> 0
F23: =B23+C23-D23-E23 -> 0 | M23: =B23+G23+H23 -> 0 | N23: =C23+I23+K23 -> 0 | O23: =D23+E23+J23+L23 -> 0 | P23: =M23+N23-O23 -> 0
F24: =B24+C24-D24-E24 -> 0 | M24: =B24+G24+H24 -> 0 | N24: =C24+I24+K24 -> 0 | O24: =D24+E24+J24+L24 -> 0 | P24: =M24+N24-O24 -> 0
A25: 合计 | B25: =SUM(B15:B24) -> 0 | C25: =SUM(C15:C24) -> 0 | D25: =SUM(D15:D24) -> 0 | E25: =SUM(E15:E24) -> 0 | F25: =SUM(F15:F24) -> 0 | G25: =SUM(G15:G24) -> 0 | H25: =SUM(H15:H24) -> 0 | I25: =SUM(I15:I24) -> 0 | ... P25: =SUM(P15:P24) -> 0
A26: 三、审计说明：
A27: 1.回购本公司股份的原因及对应的库存股成本确定方法：_____________________
A28: 2.因库存股注销而减少的股本：___________________
A29: 3.本期注销的库存股成本高于对应股本成本______________元，依次冲减资本公积___________元、盈余公积___________元、未分配利润___________元。
A30: 4.本期注销的库存股成本低于对应股本成本______________元，增加资本公积_______________元。
A31: 5.本期库存股转让时，转让收入高于库存股成本__________元，增加资本公积_______________元。
A32: 6.本期库存股转让时，转让收入低于库存股成本__________元，依次冲减资本公积___________元、盈余公积____________元、未分配利润__________元。
A33: 7.本期因实行股权激励回购本公司股份，回购股份占本公司已发行股份的总比例为___________%，累计库存股占已发行股份的总比例________________%。
A34: 四、审计结论：
A38: 编制说明：
A39: 1、本科目核算企业收购、转让或注销的本公司股份金额。
A40: 2、公司回购的股份在注销或者转让之前,作为库存股管理,回购股份的全部支出转作库存股成本。
... A56: 12、审计结论可参考：A、未见异常。B、除上述重大不符事项应当作为调整事项予以调整外，其余未见异常。C、由于存在以下重大未调整事项(或审计范围受到限制无法获取充分、适当证据），不可确认。

Sheet 调整分录汇总M3-3
A1: 致同会计师事务所
A2: 库存股调整分录汇总表
A3: 客户名称： | C3: =底稿目录!A4 -> 编制人： | E3: =底稿目录!A5 -> 编制日期： | I3: 索引号： | J3: =底稿目录!F8 -> M3-3
A4: 截止日：201X年12月31日 | C4: =底稿目录!A6 -> 复核人： | E4: =底稿目录!A7 -> 复核日期： | I4: 页 次：
A5: 调整事项说明 | B5: 类别（报表调整/账项调整/其他） | C5: 报表项目 | D5: 科目名称 | E5: 附注项目 | F5: …… | G5: 借方调整金额 | H5: 贷方调整金额 | I5: 索引 | J5: 备注

Sheet 外币投资汇率测算表M3-4
A1: 致同会计师事务所
A2: 外币投资汇率测算表
A3: =底稿目录!A2 -> 被审计单位： | C3: =底稿目录!A4 -> 编制人： | E3: =底稿目录!A5 -> 编制日期： | F3: 索引号： | G3: =底稿目录!F9 -> M3-4
A4: =底稿目录!A3 -> 截止日：202X年12月31日 | C4: =底稿目录!A6 -> 复核人： | E4: =底稿目录!A7 -> 复核日期： | F4: 页 次：
A5: 一、审计目标:
A6: 1.库存股以恰当的金额包括在财务报表中，与之相关的计价或分摊调整已恰当记录，相关披露已得到恰当计量和描述。
A7: 二、审计过程：
A8: 投资者 | B8: 币种 | C8: 期末投资额
C9: 原币金额 | D9: 折算汇率 | E9: 折合人民币 | F9: 账面数 | G9: 差额
E10: =C10*D10 -> 0 | G10: =E10-F10 -> 0
E11: =C11*D11 -> 0 | G11: =E11-F11 -> 0
E12: =C12*D12 -> 0 | G12: =E12-F12 -> 0
E13: =C13*D13 -> 0 | G13: =E13-F13 -> 0
E14: =C14*D14 -> 0 | G14: =E14-F14 -> 0
E15: =C15*D15 -> 0 | G15: =E15-F15 -> 0
A16: 合计 | C16: =SUM(C10:C15) -> 0 | E16: =SUM(E10:E15) -> 0 | F16: =SUM(F10:F15) -> 0 | G16: =SUM(G10:G15) -> 0
A17: 三、审计说明：
A19: 四、审计结论：

Sheet 库存股检查表M3-5
A1: 致同会计师事务所
A2: 库存股检查表
A3: =底稿目录!A2 -> 被审计单位： | E3: =底稿目录!A4 -> 编制人： | H3: =底稿目录!A5 -> 编制日期： | O3: 索引号： | P3: =底稿目录!F10 -> M3-5
A4: =底稿目录!A3 -> 截止日：202X年12月31日 | E4: =底稿目录!A6 -> 复核人： | H4: =底稿目录!A7 -> 复核日期： | O4: 页 次：
A5: 一、测试目标：
A6: 1.资产负债表中记录的库存股是存在的。 | E6: 2.记录的库存股由被审计单位拥有或控制
A7: 2.库存股以恰当的金额包括在财务报表中，与之相关的计价或分摊调整已恰当记录，相关披露已得到恰当计量和描述。
A8: 三、测试：
A9: 测试内容说明：1.原始凭证是否齐全； 2.记账凭证与原始凭证是否相符；3.账务处理是否正确；4.是否记录于恰当的会计期间；5.……
A10: 记账凭证 | H10: 支持性文件 | I10: 核对内容 | N10: 索引号 | O10: 是否异常 | P10: 备注说明
A11: 日期 | B11: 凭证编号 | C11: 业务内容 | D11: 对方科目 | E11: 对方明细科目 | F11: 借方金额 | G11: 贷方金额 | I11: 1 | J11: 2 | K11: 3 | L11: 4 | M11: 5
A17: 合计 | F17: =SUM(F12:F16) -> 0 | G17: =SUM(G12:G16) -> 0
A18: 本期发生额 | F18: ='明细表M3-2'!O25 -> 0 | G18: ='明细表M3-2'!N25 -> 0
A19: 检查比例 | F19: =F17/F18 -> #DIV/0! | G19: =G17/G18 -> #DIV/0!
A20: 四、审计说明：
A23: 五、审计结论：

Sheet 参考－会计规定
A1: 4201库存股
A2: 一、本科目核算企业收购、转让或注销的本公司股份金额。
A3: 二、库存股的主要账务处理。
A4: （一）企业为减少注册资本而收购本公司股份的，应按实际支付的金额，借记本科目，贷记“银行存款”等科目。
A5: （二）为奖励本公司职工而收购本公司股份的，应按实际支付的金额，借记本科目，贷记“银行存款”等科目，同时做备查登记。
A6: 将收购的股份奖励给本公司职工属于以权益结算的股份支付，如有实际收到的金额，借记“银行存款”科目，按根据职工获取奖励股份的实际情况确定的金额，借记“资本公积——其他资本公积”科目，按奖励库存股的账面余额，贷记本科目，按其差额，贷记或借记“资本公积——股本溢价”科目。
A7: （三）股东因对股东大会作出的公司合并、分立决议持有异议而要求企业收购本公司股份的，企业应按实际支付的金额，借记本科目，贷记“银行存款”等科目。
A8: （四）转让库存股，应按实际收到的金额，借记“银行存款”等科目，按转让库存股的账面余额，贷记本科目，按其差额，贷记“资本公积——股本溢价”科目；为借方差额的，借记“资本公积——股本溢价”科目，股本溢价不足冲减的，应借记“盈余公积”、“利润分配——未分配利润”科目。
A9: （五）注销库存股，应按股票面值和注销股数计算的股票面值总额，借记“股本”科目，按注销库存股的账面余额，贷记本科目，按其差额，借记“资本公积——股本溢价”科目，股本溢价不足冲减的，应借记“盈余公积”、“利润分配——未分配利润”科目。
A10: 三、本科目期末借方余额，反映企业持有尚未转让或注销的本公司股份金额。
A12: 《公司法》20181026
A13: 第一百六十二条公司不得收购本公司股份。但是，有下列情形之一的除外：
... A33: (三)库存股不得参与公司利润分配,股份有限公司应当将其作为所有者权益的备抵项目反映。

Sheet GT_Custom
A1: C1 | B1: Custom 1
A2: C2 | B2: Custom 2
A3: C3 | B3: Custom 3
A4: C4 | B4: Custom 4
A5: C5 | B5: Custom 5
A6: C6 | B6: Custom 6
A7: C7 | B7: Custom 7
A8: C8 | B8: Custom 8
