Workbook

Sheet 底稿目录
A1: 底稿开列时，可先在以下单元格填写有关内容，以便其他底稿引用有关数据：
A2: 被审计单位：
A3: 截止日：202X年12月31日 | D3: 序号 | E3: 内容 | F3: 索引号 | G3: 备注
A4: 编制人： | D4: 1 | E4: 盈余公积实质性程序表 | F4: M5A
A5: 编制日期： | D5: 2 | E5: 审定表 | F5: M5-1
A6: 复核人： | D6: 3 | E6: 附注披露信息(上市公司) | H6: 无需打印
A7: 复核日期： | D7: 4 | E7: 附注披露信息(国企) | H7: 无需打印
D8: 5 | E8: 明细表 | F8: M5-2
A9: 关于工作底稿与审计程序索引号对应的说明 | D9: 6 | E9: 调整分录汇总 | F9: M5-3
A10: 1.编制的审计工作底稿应与审计程序对应。审计项目组应根据被审计单位实际情况和风险评估情况在实质性程序表中裁剪、修改或增加审计程序，根据实际执行的审计程序完成相应审计工作底稿，编制的工作底稿中应按自然顺序依次编制索引号，并通过唯一的索引号将与实质性程序表中的程序对应关联（即将工作底稿的索引号填入实质性程序表中的底稿索引号列）。 | D10: 7 | E10: 盈余公积计提检查表 | F10: M5-4
D11: 8 | E11: 盈余公积检查表 | F11: M5-5
A14: 2.获取的支持性证据应与审计底稿或程序对应。审计项目组在完成底稿时获取的支持性证据应根据底稿索引号编制下一级按自然顺序排序的索引号（如D1-2-1、D1-2-2、……），并在底稿中说明引用的支持性证据、关联索引号。
A17: 3.工作底稿索引号的编码规则：实质性程序索引号按循环从“D”到“N”,循环内账户以顺序号排列，模板中底稿索引号按账户顺序+自然数顺序（即模板中索引号按二级自然顺序排列，如D1-1、D1-2、D1-3、……D1-N）。

Sheet 盈余公积实质性程序表 M5A
A1: 致同会计师事务所
A2: 盈余公积实质性程序
A3: =底稿目录!A2 -> 被审计单位： | C3: =底稿目录!A4 -> 编制人： | E3: =底稿目录!A5 -> 编制日期： | H3: 索引号： | I3: =底稿目录!F4 -> M5A
A4: =底稿目录!A3 -> 截止日：202X年12月31日 | C4: =底稿目录!A6 -> 复核人： | E4: =底稿目录!A7 -> 复核日期： | H4: 页 次：
A5: 一、本账户涉及的科目
A6: 盈余公积
A7: 二、审计目标与认定的对应关系
A8: 审计目标 | G8: 财务报表的认定
A9: A. 资产负债表中记录的资本公积是存在的，且已经记录在恰当的账户中 | G9: 存在
A10: B. 所有应记录的资本公积均已记录，所有应当包括在财务报表中的相关披露均已包括 | G10: 完整性
A11: C. 记录的资本公积由被审计单位拥有或控制 | G11: 权利和义务
A12: D. 资本公积以恰当的金额包括在财务报表中，与之相关的计价或分摊调整已恰当记录，相关披露已得到恰当计量和描述 | G12: 准确性、计价和分摊
A13: E. 资本公积已被恰当地汇总或分解且表述清楚，相关披露在按照企业会计准则的编制基础下是相关的、可理解的 | G13: 列报
A14: 三、计划实施的实质性程序
A15: 序号 | B15: 审计程序 | C15: 程序分类 | D15: 财务报表的认定 | I15: 底稿索引号
D16: 存在 | E16: 完整性 | F16: 权利和 义务 | G16: 准确性、计价和分摊 | H16: 列报 | J16: 根据被审计单位实际情况和风险评估情况裁剪、修改或增加审计程序
A17: 1 | B17: 获取或编制盈余公积明细表，完成以下工作，并编制审定表 复核加计是否正确，与总账、明细账合计数核对是否相符，期初余额与上期审定期末余额是否相符； | C17: 常规★ | D17: √ | E17: √ | G17: √ | I17: M5-1 /M5-2
A18: 2 | B18: 在使用手工编制、自定义信息报告、系统生成的非固定格式报告等由被审计单位生成的信息时，测试有关信息准确性和完整性，并考虑针对编制和维护由被审计单位生成的信息的相关控制实施控制测试，以评价该信息是否能够为实现审计目的提供基础。 | C18: 常规★ | E18: √ | G18: √ | I18: T1/ | J18: 可参见《审计手册》4.2.6，由被审计单位生成的信息可能是由系统生成的、或手工编制的、或二者兼而有之的方式生成的。例如，由被审计单位生成的信息可能包括： • 不涉及自定义的、由系统生成的报告（如，固定格式报告）； • 可能通过人工自定义的、由系统生成的报告，例如，（计算机）查询信息或特别定制的报告； • 手工编制的信息，例如，汇总信息的电子表格或用以支持分配、计算以及调节的电子表格； • 其他系统生成或手工编制的信息，例如，由被审计单位编制的客户发票； • 通过影印、拍摄、扫描或其他方式转换成电子形式的文件记录。
A19: 3 | B19: 对于上期盈余公积期末余额，取得盈余公积明细表复核加计是否正确，与总账、明细账合计数是否相符，检查被审计单位盈余公积计提政策等文件。（适用于首次承接） | C19: 备选 | D19: √ | E19: √ | F19: √ | G19: √ | J19: 由被审计单位生成的信息不包括： • 总分类账或明细分类账、试算平衡表、或经审计的财务报表； • 第三方（除了服务机构）的报表或报告，例如，原始银行对账单，或函证的回函； • 外部数据（例如，第三方发布的数据，如，定价来源）。
A20: 4 | B20: 对本期盈余公积发生的增减变动： （1）检查法定盈余公积和任意盈余公积的计提顺序、计提基数、计提比例是否符合有关规定，判断其分类为盈余公积是否恰当，会计处理是否正确 （2）检查盈余公积的减少是否符合有关规定，取得董事会会议纪要、股东(大)会决议，检查有关会计处理是否正确 | C20: 常规★ | D20: √ | E20: √ | F20: √ | I20: M5-4 /M5-5
A21: 5 | B21: 针对中外合作经营企业应对利润归还投资的，检查与归还投资变动有关的公司章程、合同、董事会会议纪要、政府部门的批准文件等资料，查明其是否合规、合法，并更新永久性档案，并对已归还投资的发生额逐项审计至原始凭证，检查应用的折算汇率和会计处理是否正确。 | C21: 备选 | D21: √ | E21: √ | F21: √
A22: 6 | B22: 根据评估的舞弊风险等因素增加的审计程序。 | C22: IPO/上市/新三板/重组/舞弊应对 | D22: √ | E22: √
A23: 7 | B23: 检查盈余公积是否已按企业会计准则或其他适用的规定在财务报表中做出恰当列报和披露。 | C23: 常规★ | H23: √ | I23: A1-1/A1-15 /A1-16

Sheet 审定表M5-1
A1: 致同会计师事务所
A2: 盈余公积审定表
A3: =底稿目录!A2 -> 被审计单位： | E3: =底稿目录!A4 -> 编制人： | I3: =底稿目录!A5 -> 编制日期： | K3: 索引号： | L3: =底稿目录!F5 -> M5-1
A4: =底稿目录!A3 -> 截止日：202X年12月31日 | E4: =底稿目录!A6 -> 复核人： | I4: =底稿目录!A7 -> 复核日期： | K4: 页 次：
A5: 项目名称 | B5: 期初数 | F5: 期末数 | J5: 本期审定数与上期 审定数的比较 | L5: 原因分析
B6: 未审数 | C6: 账项调整 | D6: 重分类调整 | E6: 审定数 | F6: 未审数 | G6: 账项调整 | H6: 重分类调整 | I6: 审定数 | J6: 变动额 | K6: 变动率
A7: 法定盈余公积 | B7: ='明细表M5-2'!B12 -> 0 | C7: ='明细表M5-2'!H12 -> 0 | D7: ='明细表M5-2'!I12 -> 0 | E7: ='明细表M5-2'!N12 -> 0 | F7: ='明细表M5-2'!G12 -> 0 | G7: ='明细表M5-2'!H12+'明细表M5-2'!J12-'明细表M5-2'!K12 -> 0 | H7: ='明细表M5-2'!I12+'明细表M5-2'!L12-'明细表M5-2'!M12 -> 0 | I7: ='明细表M5-2'!Q12 -> 0 | J7: =I7-E7 -> 0 | K7: =IF(AND(B7=0,J7=0),0,IF(AND(B7=0,J7>0),1,J7/B7)) -> 0
A8: 任意盈余公积 | B8: ='明细表M5-2'!B13 -> 0 | C8: ='明细表M5-2'!H13 -> 0 | D8: ='明细表M5-2'!I13 -> 0 | E8: ='明细表M5-2'!N13 -> 0 | F8: ='明细表M5-2'!G13 -> 0 | G8: ='明细表M5-2'!H13+'明细表M5-2'!J13-'明细表M5-2'!K13 -> 0 | H8: ='明细表M5-2'!I13+'明细表M5-2'!L13-'明细表M5-2'!M13 -> 0 | I8: ='明细表M5-2'!Q13 -> 0 | J8: =I8-E8 -> 0 | K8: =IF(AND(B8=0,J8=0),0,IF(AND(B8=0,J8>0),1,J8/B8)) -> 0
A9: 利润归还投资 | B9: ='明细表M5-2'!B14 -> 0 | C9: ='明细表M5-2'!H14 -> 0 | D9: ='明细表M5-2'!I14 -> 0 | E9: ='明细表M5-2'!N14 -> 0 | F9: ='明细表M5-2'!G14 -> 0 | G9: ='明细表M5-2'!H14+'明细表M5-2'!J14-'明细表M5-2'!K14 -> 0 | H9: ='明细表M5-2'!I14+'明细表M5-2'!L14-'明细表M5-2'!M14 -> 0 | I9: ='明细表M5-2'!Q14 -> 0 | J9: =I9-E9 -> 0 | K9: =IF(AND(B9=0,J9=0),0,IF(AND(B9=0,J9>0),1,J9/B9)) -> 0
A10: 其他 | B10: ='明细表M5-2'!B15 -> 0 | C10: ='明细表M5-2'!H15 -> 0 | D10: ='明细表M5-2'!I15 -> 0 | E10: ='明细表M5-2'!N15 -> 0 | F10: ='明细表M5-2'!G15 -> 0 | G10: ='明细表M5-2'!H15+'明细表M5-2'!J15-'明细表M5-2'!K15 -> 0 | H10: ='明细表M5-2'!I15+'明细表M5-2'!L15-'明细表M5-2'!M15 -> 0 | I10: ='明细表M5-2'!Q15 -> 0 | J10: =I10-E10 -> 0 | K10: =IF(AND(B10=0,J10=0),0,IF(AND(B10=0,J10>0),1,J10/B10)) -> 0
A11: 合计 | B11: =SUM(B7:B10) -> 0 | C11: =SUM(C7:C10) -> 0 | D11: =SUM(D7:D10) -> 0 | E11: =SUM(E7:E10) -> 0 | F11: =SUM(F7:F10) -> 0 | G11: =SUM(G7:G10) -> 0 | H11: =SUM(H7:H10) -> 0 | I11: =SUM(I7:I10) -> 0 | J11: =I11-E11 -> 0 | K11: =IF(AND(B11=0,J11=0),0,IF(AND(B11=0,J11>0),1,J11/B11)) -> 0
A12: 试算平衡表数
A13: 差异数 | E13: =E11-E12 -> 0 | I13: =I11-I12 -> 0
A14: 1、审计说明
A15: （1）期末余额较期初余额增加（负数为减少）：
A16: 主要原因（比例超过30%的）：
A19: （2）用盈余公积转增股本、弥补亏损、分派股利的情况说明。
A23: 2、审计结论

Sheet 附注披露信息（上市公司）
A1: 致同会计师事务所
A2: 盈余公积附注披露信息（上市公司）
A3: =底稿目录!A2 -> 被审计单位： | B3: =底稿目录!A4 -> 编制人： | C3: =底稿目录!A5 -> 编制日期： | D3: 索引号： | E3: M5-1
A4: =底稿目录!A3 -> 截止日：202X年12月31日 | B4: =底稿目录!A6 -> 复核人： | C4: =底稿目录!A7 -> 复核日期： | D4: 页次：
A5: 盈余公积
A6: 项 目 | B6: 期初余额 | C6: 本期增加 | D6: 本期减少 | E6: 期末余额
A7: 法定盈余公积 | B7: ='明细表M5-2'!N12 -> 0 | C7: ='明细表M5-2'!O12 -> 0 | D7: ='明细表M5-2'!P12 -> 0 | E7: =B7+C7-D7 -> 0
A8: 任意盈余公积 | B8: ='明细表M5-2'!N13 -> 0 | C8: ='明细表M5-2'!O13 -> 0 | D8: ='明细表M5-2'!P13 -> 0 | E8: =B8+C8-D8 -> 0
A9: 利润归还投资 | B9: ='明细表M5-2'!N14 -> 0 | C9: ='明细表M5-2'!O14 -> 0 | D9: ='明细表M5-2'!P14 -> 0 | E9: =B9+C9-D9 -> 0
A10: 其他 | B10: ='明细表M5-2'!N15 -> 0 | C10: ='明细表M5-2'!O15 -> 0 | D10: ='明细表M5-2'!P15 -> 0 | E10: =B10+C10-D10 -> 0
A11: 合 计 | B11: =SUM(B7:B10) -> 0 | C11: =SUM(C7:C10) -> 0 | D11: =SUM(D7:D10) -> 0 | E11: =SUM(E7:E10) -> 0
A12: 说明：（盈余公积的变动情况、变动原因。用盈余公积转增股本、弥补亏损、分派股利的，应说明有关决议。）

Sheet 附注披露信息（国有企业）
A1: 致同会计师事务所
A2: 盈余公积附注披露信息（国有企业）
A3: =底稿目录!A2 -> 被审计单位： | B3: =底稿目录!A4 -> 编制人： | C3: =底稿目录!A5 -> 编制日期： | D3: 索引号： | E3: M5-1
A4: =底稿目录!A3 -> 截止日：202X年12月31日 | B4: =底稿目录!A6 -> 复核人： | C4: =底稿目录!A7 -> 复核日期： | D4: 页次：
A5: 盈余公积
A6: 项 目 | B6: 期初余额 | C6: 本期增加 | D6: 本期减少 | E6: 期末余额
A7: 法定盈余公积金 | B7: ='明细表M5-2'!N12 -> 0 | C7: ='明细表M5-2'!O12 -> 0 | D7: ='明细表M5-2'!P12 -> 0 | E7: =B7+C7-D7 -> 0
A8: 任意盈余公积金 | B8: ='明细表M5-2'!N13 -> 0 | C8: ='明细表M5-2'!O13 -> 0 | D8: ='明细表M5-2'!P13 -> 0 | E8: =B8+C8-D8 -> 0
A9: 利润归还投资 | B9: ='明细表M5-2'!N14 -> 0 | C9: ='明细表M5-2'!O14 -> 0 | D9: ='明细表M5-2'!P14 -> 0 | E9: =B9+C9-D9 -> 0
A10: 其他 | B10: ='明细表M5-2'!N15 -> 0 | C10: ='明细表M5-2'!O15 -> 0 | D10: ='明细表M5-2'!P15 -> 0 | E10: =B10+C10-D10 -> 0
A11: 合 计 | B11: =SUM(B7:B10) -> 0 | C11: =SUM(C7:C10) -> 0 | D11: =SUM(D7:D10) -> 0 | E11: =SUM(E7:E10) -> 0
A12: （逐项说明盈余公积增加、减少需要原因、依据及金额）

Sheet 明细表M5-2
A1: 致同会计师事务所
A2: 盈余公积明细表
A3: =底稿目录!A2 -> 被审计单位： | E3: =底稿目录!A4 -> 编制人： | K3: =底稿目录!A5 -> 编制日期： | P3: 索引号： | Q3: =底稿目录!F8 -> M5-2
A4: =底稿目录!A3 -> 截止日：202X年12月31日 | E4: =底稿目录!A6 -> 复核人： | K4: =底稿目录!A7 -> 复核日期： | P4: 页 次：
A5: 一、审计目标:
A6: 1.资产负债表中记录的资本公积是存在的。
A7: 2.资本公积以恰当的金额包括在财务报表中，与之相关的计价或分摊调整已恰当记录，相关披露已得到恰当计量和描述。
A8: 二、审计过程：
A9: 明细项目 | B9: 未审数 | H9: 期初调整 | J9: 账项调整 | L9: 重分类调整 | N9: 审定数
B10: 期初数 | C10: 本期增加 | E10: 本期减少 | G10: 期末数 | H10: 账项调整 | I10: 重分类调整 | J10: 本期增加 | K10: 本期减少 | L10: 本期增加 | M10: 本期减少 | N10: 期初数 | O10: 本期增加 | P10: 本期减少 | Q10: 期末数
C11: 金额 | D11: 增加方式 | E11: 金额 | F11: 减少方式
A12: 法定盈余公积 | G12: =B12+C12-E12 -> 0 | N12: =B12+H12+I12 -> 0 | O12: =C12+J12+L12 -> 0 | P12: =E12+K12+M12 -> 0 | Q12: =N12+O12-P12 -> 0
A13: 任意盈余公积 | G13: =B13+C13-E13 -> 0 | N13: =B13+H13+I13 -> 0 | O13: =C13+J13+L13 -> 0 | P13: =E13+K13+M13 -> 0 | Q13: =N13+O13-P13 -> 0
A14: 利润归还投资 | G14: =B14+C14-E14 -> 0 | N14: =B14+H14+I14 -> 0 | O14: =C14+J14+L14 -> 0 | P14: =E14+K14+M14 -> 0 | Q14: =N14+O14-P14 -> 0
A15: 其他 | G15: =B15+C15-E15 -> 0 | N15: =B15+H15+I15 -> 0 | O15: =C15+J15+L15 -> 0 | P15: =E15+K15+M15 -> 0 | Q15: =N15+O15-P15 -> 0
A16: 合计 | B16: =SUM(B12:B15) -> 0 | C16: =SUM(C12:C15) -> 0 | E16: =SUM(E12:E15) -> 0 | G16: =SUM(G12:G15) -> 0 | H16: =SUM(H12:H15) -> 0 | I16: =SUM(I12:I15) -> 0 | J16: =SUM(J12:J15) -> 0 | K16: =SUM(K12:K15) -> 0 | L16: =SUM(L12:L15) -> 0 | M16: =SUM(M12:M15) -> 0 | N16: =SUM(N12:N15) -> 0 | ... Q16: =SUM(Q12:Q15) -> 0
A17: 三、审计说明：
A19: 四、审计结论：
A23: 提示：
A24: 1.本科目应当分别“法定盈余公积”、“任意盈余公积”进行明细核算。中外合作经营在合作期间归还投资者的投资，应在本科目设置“利润归还投资”明细科目进行核算。
A25: 2.《公司法》第一百六十七条 公司分配当年税后利润时，应当提取利润的百分之十列入公司法定公积金。
A26: 公司法定公积金累计额为公司注册资本的百分之五十以上的，可以不再提取。
A27: 公司从税后利润中提取法定公积金后，经股东会或者股东大会决议，还可以从税后利润中提取任意公积金。
A28: 3.第一百六十九条 公司的公积金用于弥补公司的亏损、扩大公司生产经营或者转为增加公司资本。
A29: 法定公积金转为资本时，所留存的该项公积金不得少于转增前公司注册资本的百分之二十五。
A30: 4.关于《公司法》施行后有关企业财务处理问题的通知：
A31: 从2006年1月1日起，按照《公司法》组建的企业根据《公司法》第167条进行利润分配，不再提取公益金；
A32: 同时，为了保持企业间财务政策的一致性，国有企业以及其他企业一并停止实行公益金制度。
... A38: 7.审计结论可参考：A、未见异常。B、除上述重大不符事项应当作为调整事项予以调整外，其余未见异常。C、由于存在以下重大未调整事项(或审计范围受到限制无法获取充分、适当证据），不可确认。

Sheet 调整分录汇总M5-3
A1: 致同会计师事务所
A2: 盈余公积调整分录汇总表
A3: =底稿目录!A2 -> 被审计单位： | D3: =底稿目录!A4 -> 编制人： | G3: =底稿目录!A5 -> 编制日期： | I3: 索引号： | J3: =底稿目录!F9 -> M5-3
A4: =底稿目录!A3 -> 截止日：202X年12月31日 | D4: =底稿目录!A6 -> 复核人： | G4: =底稿目录!A7 -> 复核日期： | I4: 页 次：
A5: 调整事项说明 | B5: 类别（报表调整/账项调整/其他） | C5: 报表项目 | D5: 科目名称 | E5: 附注项目 | F5: …… | G5: 借方调整金额 | H5: 贷方调整金额 | I5: 索引 | J5: 备注

Sheet 盈余公积计提检查表M5-4
A1: 致同会计师事务所
A2: 盈余公积计提检查表
A3: =底稿目录!A2 -> 被审计单位： | B3: =底稿目录!A4 -> 编制人： | C3: =底稿目录!A5 -> 编制日期： | D3: 索引号：M5-4
A4: =底稿目录!A3 -> 截止日：202X年12月31日 | B4: =底稿目录!A6 -> 复核人： | C4: =底稿目录!A7 -> 复核日期： | D4: 页次：
A5: 一、审计目标:
A6: 1.资本公积以恰当的金额包括在财务报表中，与之相关的计价或分摊调整已恰当记录，相关披露已得到恰当计量和描述 ；
A7: 二、审计过程：
A8: 项 目 内 容 | B8: 未审金额 | C8: 审计调整 | D8: 审 定
A9: 一、本期净利润： | D9: =B9+C9 -> 0
A10: 减：弥补亏损 | D10: =B10+C10 -> 0
A11: 二、弥补亏损后盈余公积计提基数 | B11: =B9-B10 -> 0 | C11: =C9-C10 -> 0 | D11: =B11+C11 -> 0
A12: 计提比例 | B12: 0.1 | D12: 0.1
A13: 三、本期应提取盈余公积 | B13: =B11*B12 -> 0 | C13: =C11*C12 -> 0 | D13: =D11*D12 -> 0
A14: 三、审计说明：
A16: 四、审计结论：
A21: 编制说明：
A22: 1、本科目核算企业从净利润中提取的盈余公积。
A23: 2、本科目应当分别“法定盈余公积”、“任意盈余公积”进行明细核算。外商投资企业还应分别“储备基金”、“企业发展基金”进行明细核算。
A24: 中外合作经营在合作期间归还投资者的投资，应在本科目设置“利润归还投资”明细科目进行核算。
A26: 3、《公司法》第一百六十七条 公司分配当年税后利润时，应当提取利润的百分之十列入公司法定公积金。
A27: 公司法定公积金累计额为公司注册资本的百分之五十以上的，可以不再提取。
A28: 公司从税后利润中提取法定公积金后，经股东会或者股东大会决议，还可以从税后利润中提取任意公积金。
A29: 4、第一百六十九条 公司的公积金用于弥补公司的亏损、扩大公司生产经营或者转为增加公司资本。
A30: 法定公积金转为资本时，所留存的该项公积金不得少于转增前公司注册资本的百分之二十五。
A32: 5、关于《公司法》施行后有关企业财务处理问题的通知：
... A42: 职工奖励及福利基金的提取比例由外资企业自行确定。

Sheet 盈余公积检查表M5-5
A1: 致同会计师事务所
A2: 盈余公积检查表
A3: =底稿目录!A2 -> 被审计单位： | E3: =底稿目录!A4 -> 编制人： | H3: =底稿目录!A5 -> 编制日期： | O3: 索引号： | P3: =底稿目录!F11 -> M5-5
A4: =底稿目录!A3 -> 截止日：202X年12月31日 | E4: =底稿目录!A6 -> 复核人： | H4: =底稿目录!A7 -> 复核日期： | O4: 页 次：
A5: 一、测试目标：
A6: 通过凭证抽查，验证盈余公积的存在/发生、计价和分摊。
A7: 二、测试：
A8: 测试内容说明：1.原始凭证是否齐全； 2.记账凭证与原始凭证是否相符；3.账务处理是否正确；4.是否记录于恰当的会计期间；5.……
A9: 记账凭证 | H9: 支持性文件 | I9: 核对内容 | N9: 索引号 | O9: 是否异常 | P9: 备注说明
A10: 日期 | B10: 凭证编号 | C10: 业务内容 | D10: 对方科目 | E10: 对方明细科目 | F10: 借方金额 | G10: 贷方金额 | I10: 1 | J10: 2 | K10: 3 | L10: 4 | M10: 5
A18: 合计 | F18: =SUM(F11:F17) -> 0 | G18: =SUM(G11:G17) -> 0
A19: 本期发生额 | F19: ='明细表M5-2'!P16 -> 0 | G19: ='明细表M5-2'!O16 -> 0
A20: 检查比例 | F20: =F18/F19 -> #DIV/0! | G20: =G18/G19 -> #DIV/0!
A21: 四、审计说明：
A25: 五、审计结论：
A29: 编制说明：
A30: 1、概述：（1）程序的测试情况、结果；
A31: （2）拟调整事项及其调整分录、未调整事项及其影响，审计范围受到限制情况及其影响。
A32: 参考结论：
A33: A、 | B33: 未见异常。
A34: B、 | B34: 除以下重大不符事项应当作为调整事项予以调整外，其余未见异常。
A35: C、 | B35: 由于存在以下重大未调整事项（或审计范围受到限制无法获取充分、适当证据），不可确认。

Sheet GT_Custom
A1: C1 | B1: Custom 1
A2: C2 | B2: Custom 2
A3: C3 | B3: Custom 3
A4: C4 | B4: Custom 4
A5: C5 | B5: Custom 5
A6: C6 | B6: Custom 6
A7: C7 | B7: Custom 7
A8: C8 | B8: Custom 8
