Workbook

Sheet 底稿目录
A1: 底稿开列时，可先在以下单元格填写有关内容，以便其他底稿引用有关数据：
A2: 被审计单位：
A3: 截止日：202X年12月31日 | D3: 序号 | E3: 内容 | F3: 索引号 | G3: 备注
A4: 编制人： | D4: 1 | E4: 专项储备实质性程序表 | F4: M7A
A5: 编制日期： | D5: 2 | E5: 审定表 | F5: M7-1
A6: 复核人： | D6: 3 | E6: 附注披露信息(上市公司) | H6: 无需打印
A7: 复核日期： | D7: 4 | E7: 附注披露信息(国企) | H7: 无需打印
D8: 5 | E8: 明细表 | F8: M7-2
A9: 关于工作底稿与审计程序索引号对应的说明 | D9: 6 | E9: 调整分录汇总 | F9: M7-3
A10: 1.编制的审计工作底稿应与审计程序对应。审计项目组应根据被审计单位实际情况和风险评估情况在实质性程序表中裁剪、修改或增加审计程序，根据实际执行的审计程序完成相应审计工作底稿，编制的工作底稿中应按自然顺序依次编制索引号，并通过唯一的索引号将与实质性程序表中的程序对应关联（即将工作底稿的索引号填入实质性程序表中的底稿索引号列）。 | D10: 7 | E10: 专项储备计提测试表 | F10: M7-4
D11: 8 | E11: 专项储备支出检查表 | F11: M7-5
A14: 2.获取的支持性证据应与审计底稿或程序对应。审计项目组在完成底稿时获取的支持性证据应根据底稿索引号编制下一级按自然顺序排序的索引号（如D1-2-1、D1-2-2、……），并在底稿中说明引用的支持性证据、关联索引号。
A17: 3.工作底稿索引号的编码规则：实质性程序索引号按循环从“D”到“N”,循环内账户以顺序号排列，模板中底稿索引号按账户顺序+自然数顺序（即模板中索引号按二级自然顺序排列，如D1-1、D1-2、D1-3、……D1-N）。

Sheet  专项储备实质性程序表 M7A 
A1: 致同会计师事务所
A2: 专项储备实质性程序
A3: =底稿目录!A2 -> 被审计单位： | C3: =底稿目录!A4 -> 编制人： | E3: =底稿目录!A5 -> 编制日期： | H3: 索引号： | I3: =底稿目录!F4 -> M7A
A4: =底稿目录!A3 -> 截止日：202X年12月31日 | C4: =底稿目录!A6 -> 复核人： | E4: =底稿目录!A7 -> 复核日期： | H4: 页 次：
A5: 一、本账户涉及的科目
A6: 专项储备
A7: 二、审计目标与认定的对应关系
A8: 审计目标 | G8: 财务报表的认定
A9: A. 资产负债表中记录的专项储备是存在的，且已经记录在恰当的账户中 | G9: 存在
A10: B. 所有应记录的专项储备均已记录，所有应当包括在财务报表中的相关披露均已包括 | G10: 完整性
A11: C. 记录的专项储备由被审计单位拥有或控制 | G11: 权利和义务
A12: D. 专项储备以恰当的金额包括在财务报表中，与之相关的计价或分摊调整已恰当记录，相关披露已得到恰当计量和描述 | G12: 准确性、计价和分摊
A13: E. 专项储备已被恰当地汇总或分解且表述清楚，相关披露在按照企业会计准则的编制基础下是相关的、可理解的 | G13: 列报
A14: 三、计划实施的实质性程序
A15: 序号 | B15: 审计程序 | C15: 程序分类 | D15: 财务报表的认定 | I15: 底稿索引号
D16: 存在 | E16: 完整性 | F16: 权利和义务 | G16: 准确性、计价和分摊 | H16: 列报 | J16: 根据被审计单位实际情况和风险评估情况裁剪、修改或增加审计程序
A17: 1 | B17: 获取或编制专项储备明细表，完成以下工作，并编制审定表 复核加计是否正确，与总账、明细账合计数核对是否相符，期初余额与上期审定期末余额是否相符； | C17: 常规★ | D17: √ | E17: √ | G17: √ | I17: M7-1 /M7-2
A18: 2 | B18: 在使用手工编制、自定义信息报告、系统生成的非固定格式报告等由被审计单位生成的信息时，测试有关信息准确性和完整性，并考虑针对编制和维护由被审计单位生成的信息的相关控制实施控制测试，以评价该信息是否能够为实现审计目的提供基础。 | C18: 常规★ | E18: √ | G18: √ | I18: T1/ | J18: 可参见《审计手册》4.2.6，由被审计单位生成的信息可能是由系统生成的、或手工编制的、或二者兼而有之的方式生成的。例如，由被审计单位生成的信息可能包括： • 不涉及自定义的、由系统生成的报告（如，固定格式报告）； • 可能通过人工自定义的、由系统生成的报告，例如，（计算机）查询信息或特别定制的报告； • 手工编制的信息，例如，汇总信息的电子表格或用以支持分配、计算以及调节的电子表格； • 其他系统生成或手工编制的信息，例如，由被审计单位编制的客户发票； • 通过影印、拍摄、扫描或其他方式转换成电子形式的文件记录。
A19: 3 | B19: 对于上期盈余公积期末余额，取得盈余公积明细表复核加计是否正确，与总账、明细账合计数是否相符，检查被审计单位专项储备计提政策等文件、前期计提的专项储备在本期使用情况。（适用于首次承接） | C19: 备选 | D19: √ | E19: √ | F19: √ | G19: √ | J19: 由被审计单位生成的信息不包括： • 总分类账或明细分类账、试算平衡表、或经审计的财务报表； • 第三方（除了服务机构）的报表或报告，例如，原始银行对账单，或函证的回函； • 外部数据（例如，第三方发布的数据，如，定价来源）。
A20: 4 | B20: 获取安全生产费、维简费和其他具有类似性质费用的计提及标准的相关文件，检查是否已按照相关行业规定计提专项储备，判断其分类为是否恰当、计提金额是否正确、会计处理是否正确。 | C20: 常规★ | D20: √ | E20: √ | F20: √ | G20: √ | H20: √ | I20: M7-4
A21: 5 | B21: 检查专项储备使用是否符合有关规定，资本性资产与费用性支出分类是否恰当、会计处理是否正确 | C21: 常规★ | D21: √ | F21: √ | I21: M7-5
A22: 6 | B22: 检查专项储备是否已按企业会计准则或其他适用的规定在财务报表中做出恰当列报和披露。 | C22: 常规★ | H22: √ | I22: A1-1/A1-15 /A1-16

Sheet 审定表M7-1
A1: 致同会计师事务所
A2: 专项储备审定表
A3: =底稿目录!A2 -> 被审计单位： | D3: =底稿目录!A4 -> 编制人： | G3: =底稿目录!A5 -> 编制日期： | K3: 索引号： | L3: M7-1
A4: =底稿目录!A3 -> 截止日：202X年12月31日 | D4: =底稿目录!A6 -> 复核人： | G4: =底稿目录!A7 -> 复核日期： | K4: 页 次：
A5: 项目名称 | B5: 期初数 | F5: 期末数 | J5: 本期审定数与上期 审定数的比较 | L5: 原因分析
B6: 未审数 | C6: 账项调整 | D6: 重分类调整 | E6: 审定数 | F6: 未审数 | G6: 账项调整 | H6: 重分类调整 | I6: 审定数 | J6: 变动额 | K6: 变动率
A7: 安全生产费 | B7: ='明细表M7-2'!B10 -> 0 | C7: ='明细表M7-2'!F10 -> 0 | D7: ='明细表M7-2'!G10 -> 0 | E7: ='明细表M7-2'!L10 -> 0 | F7: ='明细表M7-2'!E10 -> 0 | G7: ='明细表M7-2'!F10+'明细表M7-2'!H10-'明细表M7-2'!I10 -> 0 | H7: ='明细表M7-2'!G10+'明细表M7-2'!J10-'明细表M7-2'!K10 -> 0 | I7: ='明细表M7-2'!O10 -> 0 | J7: =I7-E7 -> 0 | K7: =IF(AND(E7=0,J7=0),0,IF(AND(E7=0,J7>0),1,J7/E7)) -> 0
A8: 维简费 | B8: ='明细表M7-2'!B11 -> 0 | C8: ='明细表M7-2'!F11 -> 0 | D8: ='明细表M7-2'!G11 -> 0 | E8: ='明细表M7-2'!L11 -> 0 | F8: ='明细表M7-2'!E11 -> 0 | G8: ='明细表M7-2'!F11+'明细表M7-2'!H11-'明细表M7-2'!I11 -> 0 | H8: ='明细表M7-2'!G11+'明细表M7-2'!J11-'明细表M7-2'!K11 -> 0 | I8: ='明细表M7-2'!O11 -> 0 | J8: =I8-E8 -> 0 | K8: =IF(AND(E8=0,J8=0),0,IF(AND(E8=0,J8>0),1,J8/E8)) -> 0
A9: 其他 | B9: ='明细表M7-2'!B12 -> 0 | C9: ='明细表M7-2'!F12 -> 0 | D9: ='明细表M7-2'!G12 -> 0 | E9: ='明细表M7-2'!L12 -> 0 | F9: ='明细表M7-2'!E12 -> 0 | G9: ='明细表M7-2'!F12+'明细表M7-2'!H12-'明细表M7-2'!I12 -> 0 | H9: ='明细表M7-2'!G12+'明细表M7-2'!J12-'明细表M7-2'!K12 -> 0 | I9: ='明细表M7-2'!O12 -> 0 | J9: =I9-E9 -> 0 | K9: =IF(AND(E9=0,J9=0),0,IF(AND(E9=0,J9>0),1,J9/E9)) -> 0
B10: ='明细表M7-2'!B13 -> 0 | C10: ='明细表M7-2'!F13 -> 0 | D10: ='明细表M7-2'!G13 -> 0 | E10: ='明细表M7-2'!L13 -> 0 | F10: ='明细表M7-2'!E13 -> 0 | G10: ='明细表M7-2'!F13+'明细表M7-2'!H13-'明细表M7-2'!I13 -> 0 | H10: ='明细表M7-2'!G13+'明细表M7-2'!J13-'明细表M7-2'!K13 -> 0 | I10: ='明细表M7-2'!O13 -> 0 | J10: =I10-E10 -> 0 | K10: =IF(AND(E10=0,J10=0),0,IF(AND(E10=0,J10>0),1,J10/E10)) -> 0
B11: ='明细表M7-2'!B14 -> 0 | C11: ='明细表M7-2'!F14 -> 0 | D11: ='明细表M7-2'!G14 -> 0 | E11: ='明细表M7-2'!L14 -> 0 | F11: ='明细表M7-2'!E14 -> 0 | G11: ='明细表M7-2'!F14+'明细表M7-2'!H14-'明细表M7-2'!I14 -> 0 | H11: ='明细表M7-2'!G14+'明细表M7-2'!J14-'明细表M7-2'!K14 -> 0 | I11: ='明细表M7-2'!O14 -> 0 | J11: =I11-E11 -> 0 | K11: =IF(AND(E11=0,J11=0),0,IF(AND(E11=0,J11>0),1,J11/E11)) -> 0
B12: ='明细表M7-2'!B15 -> 0 | C12: ='明细表M7-2'!F15 -> 0 | D12: ='明细表M7-2'!G15 -> 0 | E12: ='明细表M7-2'!L15 -> 0 | F12: ='明细表M7-2'!E15 -> 0 | G12: ='明细表M7-2'!F15+'明细表M7-2'!H15-'明细表M7-2'!I15 -> 0 | H12: ='明细表M7-2'!G15+'明细表M7-2'!J15-'明细表M7-2'!K15 -> 0 | I12: ='明细表M7-2'!O15 -> 0 | J12: =I12-E12 -> 0 | K12: =IF(AND(E12=0,J12=0),0,IF(AND(E12=0,J12>0),1,J12/E12)) -> 0
A13: 合计 | B13: =SUM(B7:B12) -> 0 | C13: =SUM(C7:C12) -> 0 | D13: =SUM(D7:D12) -> 0 | E13: =SUM(E7:E12) -> 0 | F13: =SUM(F7:F12) -> 0 | G13: =SUM(G7:G12) -> 0 | H13: =SUM(H7:H12) -> 0 | I13: =SUM(I7:I12) -> 0 | J13: =I13-E13 -> 0 | K13: =IF(AND(E13=0,J13=0),0,IF(AND(E13=0,J13>0),1,J13/E13)) -> 0
A14: 试算平衡表数
A15: 差异数 | E15: =E13-E14 -> 0 | I15: =I13-I14 -> 0
A16: 1、审计说明
A17: （1）期末余额较期初余额增加（负数为减少）：
A18: 主要原因（比例超过30%的）：
A21: （2）专项储备变动的原因、依据；
A24: 2、审计结论

Sheet 附注披露信息（上市公司）
A1: 致同会计师事务所
A2: 专项储备附注披露信息（上市公司）
A3: =底稿目录!A2 -> 被审计单位： | B3: =底稿目录!A4 -> 编制人： | D3: =底稿目录!A5 -> 编制日期： | F3: 索引号：
A4: =底稿目录!A3 -> 截止日：202X年12月31日 | B4: =底稿目录!A6 -> 复核人： | D4: =底稿目录!A7 -> 复核日期： | F4: 页次：
A5: 专项储备
A6: 项 目 | B6: 期初余额 | C6: 本期增加 | D6: 本期减少 | E6: 期末余额
A7: 安全生产费 | B7: ='明细表M7-2'!L10 -> 0 | C7: ='明细表M7-2'!M10 -> 0 | D7: ='明细表M7-2'!N10 -> 0 | E7: =B7+C7-D7 -> 0
A8: 维简费 | B8: ='明细表M7-2'!L11 -> 0 | C8: ='明细表M7-2'!M11 -> 0 | D8: ='明细表M7-2'!N11 -> 0 | E8: =B8+C8-D8 -> 0
A9: 其他（请注明） | B9: ='明细表M7-2'!L12 -> 0 | C9: ='明细表M7-2'!M12 -> 0 | D9: ='明细表M7-2'!N12 -> 0 | E9: =B9+C9-D9 -> 0
A10: 合 计 | B10: =SUM(B7:B9) -> 0 | C10: =SUM(C7:C9) -> 0 | D10: =SUM(D7:D9) -> 0 | E10: =SUM(E7:E9) -> 0
A11: 说明：专项储备的变动情况、变动原因。

Sheet 附注披露信息（国有企业）
A1: 致同会计师事务所
A2: 专项储备附注披露信息（国有企业）
A3: =底稿目录!A2 -> 被审计单位： | B3: =底稿目录!A4 -> 编制人： | D3: =底稿目录!A5 -> 编制日期： | F3: 索引号：
A4: =底稿目录!A3 -> 截止日：202X年12月31日 | B4: =底稿目录!A6 -> 复核人： | D4: =底稿目录!A7 -> 复核日期： | F4: 页次：
A5: 专项储备
A6: 项 目 | B6: 期初余额 | C6: 本期增加 | D6: 本期减少 | E6: 期末余额 | F6: 备注
A7: 安全生产费 | B7: ='明细表M7-2'!L10 -> 0 | C7: ='明细表M7-2'!M10 -> 0 | D7: ='明细表M7-2'!N10 -> 0 | E7: =B7+C7-D7 -> 0
A8: 维简费 | B8: ='明细表M7-2'!L11 -> 0 | C8: ='明细表M7-2'!M11 -> 0 | D8: ='明细表M7-2'!N11 -> 0 | E8: =B8+C8-D8 -> 0
A9: 其他（请注明） | B9: ='明细表M7-2'!L12 -> 0 | C9: ='明细表M7-2'!M12 -> 0 | D9: ='明细表M7-2'!N12 -> 0 | E9: =B9+C9-D9 -> 0
A10: 合 计 | B10: =SUM(B7:B9) -> 0 | C10: =SUM(C7:C9) -> 0 | D10: =SUM(D7:D9) -> 0 | E10: =SUM(E7:E9) -> 0
A11: 说明：（对少数股东权益的影响）

Sheet 明细表M7-2
A1: 致同会计师事务所
A2: 专项储备明细表
A3: =底稿目录!A2 -> 被审计单位： | H3: =底稿目录!A4 -> 编制人： | M3: =底稿目录!A5 -> 编制日期： | Q3: 索引号： | R3: =底稿目录!F8 -> M7-2
A4: =底稿目录!A3 -> 截止日：202X年12月31日 | H4: =底稿目录!A6 -> 复核人： | M4: =底稿目录!A7 -> 复核日期： | Q4: 页 次：
A5: 一、审计目标:
A6: 1.专项储备以恰当的金额包括在财务报表中，与之相关的计价或分摊调整已恰当记录，相关披露已得到恰当计量和描述。
A7: 二、审计过程：
A8: 项目 | B8: 未审数 | F8: 期初调整 | H8: 账项调整 | J8: 重分类调整 | L8: 审定数 | P8: 文件依据 | Q8: 索引号 | R8: 备注
B9: 期初数 | C9: 本期增加 | D9: 本期减少 | E9: 期末数 | F9: 账项调整 | G9: 重分类调整 | H9: 本期增加 | I9: 本期减少 | J9: 本期增加 | K9: 本期减少 | L9: 期初数 | M9: 本期增加 | N9: 本期减少 | O9: 期末数
A10: 安全生产费 | E10: =B10+C10-D10 -> 0 | L10: =B10+F10+G10 -> 0 | M10: =C10+H10+J10 -> 0 | N10: =D10+I10+K10 -> 0 | O10: =L10+M10-N10 -> 0
A11: 维简费 | E11: =B11+C11-D11 -> 0 | L11: =B11+F11+G11 -> 0 | M11: =C11+H11+J11 -> 0 | N11: =D11+I11+K11 -> 0 | O11: =L11+M11-N11 -> 0
A12: 其他（请注明） | E12: =B12+C12-D12 -> 0 | L12: =B12+F12+G12 -> 0 | M12: =C12+H12+J12 -> 0 | N12: =D12+I12+K12 -> 0 | O12: =L12+M12-N12 -> 0
E13: =B13+C13-D13 -> 0 | L13: =B13+F13+G13 -> 0 | M13: =C13+H13+J13 -> 0 | N13: =D13+I13+K13 -> 0 | O13: =L13+M13-N13 -> 0
E14: =B14+C14-D14 -> 0 | L14: =B14+F14+G14 -> 0 | M14: =C14+H14+J14 -> 0 | N14: =D14+I14+K14 -> 0 | O14: =L14+M14-N14 -> 0
E15: =B15+C15-D15 -> 0 | L15: =B15+F15+G15 -> 0 | M15: =C15+H15+J15 -> 0 | N15: =D15+I15+K15 -> 0 | O15: =L15+M15-N15 -> 0
E16: =B16+C16-D16 -> 0 | L16: =B16+F16+G16 -> 0 | M16: =C16+H16+J16 -> 0 | N16: =D16+I16+K16 -> 0 | O16: =L16+M16-N16 -> 0
A17: 合计 | B17: =SUM(B10:B16) -> 0 | C17: =SUM(C10:C16) -> 0 | D17: =SUM(D10:D16) -> 0 | E17: =SUM(E10:E16) -> 0 | F17: =SUM(F10:F16) -> 0 | G17: =SUM(G10:G16) -> 0 | H17: =SUM(H10:H16) -> 0 | I17: =SUM(I10:I16) -> 0 | ... O17: =SUM(O10:O16) -> 0
A18: 三、审计说明：
A20: 四、审计结论：
A23: 1、审计说明可以概述：（1）程序的测试情况、结果；（2）拟调整事项及其调整分录、未调整事项及其影响，审计范围受到限制情况及其影响。
A24: 2、审计结论可参考：A、未见异常。B、除上述重大不符事项应当作为调整事项予以调整外，其余未见异常。C、由于存在以下重大未调整事项(或审计范围受到限制无法获取充分、适当证据），不可确认。

Sheet 调整分录汇总M7-3
A1: 致同会计师事务所
A2: 专项储备调整分录汇总表
A3: =底稿目录!A2 -> 被审计单位： | D3: =底稿目录!A4 -> 编制人： | G3: =底稿目录!A5 -> 编制日期： | I3: 索引号： | J3: =底稿目录!F9 -> M7-3
A4: =底稿目录!A3 -> 截止日：202X年12月31日 | D4: =底稿目录!A6 -> 复核人： | G4: =底稿目录!A7 -> 复核日期： | I4: 页 次：
A5: 调整事项说明 | B5: 类别（报表调整/账项调整/其他） | C5: 报表项目 | D5: 科目名称 | E5: 附注项目 | F5: …… | G5: 借方调整金额 | H5: 贷方调整金额 | I5: 索引 | J5: 备注

Sheet 专项储备计提测试表M7-4
A1: 致同会计师事务所
A2: 专项储备计提测试表
A3: =底稿目录!A2 -> 被审计单位： | D3: =底稿目录!A4 -> 编制人： | G3: =底稿目录!A5 -> 编制日期： | R3: 索引号： | S3: =底稿目录!F10 -> M7-4
A4: =底稿目录!A3 -> 截止日：202X年12月31日 | D4: =底稿目录!A6 -> 复核人： | G4: =底稿目录!A7 -> 复核日期： | R4: 页 次：
A5: 一、审计目标：
A6: 专项储备以恰当的金额包括在财务报表中，与之相关的计价或分摊调整已恰当记录，相关披露已得到恰当计量和描述
A7: 二、审计过程：
A8: 1.审查安全生产费、维简费和其他具有类似性质的费用的计提是否符合有关规定，且提取标准符合下列规定：矿山企业安全费用依据开采的原矿产量按月提取；建筑施工企业以建筑安装工程造价为计提依据；危险品生产企业以本年度实际销售收入为计提依据，采取超额累退方式按照标准逐月提取。
A9: 2.审查安全生产费、维简费和其他具有类似性质的费用的计提相关的会计处理是否符合规定；
A10: 明细项目内容 | B10: 本期增加额 | D10: 提取 | G10: 应计金额 | H10: 差异 | I10: 差异原因 | J10: 相关依据索引号 | K10: 相关数据来源索引号 | L10: 对应凭证检查情况 | S10: 备注说明
B11: 计提 | C11: 其它 | D11: 标准 | E11: 基数 | F11: 比例（注） | L11: 日期 | M11: 凭证编号 | N11: 业务内容 | O11: 对方科目 | P11: 对方明细科目 | Q11: 借方金额 | R11: 贷方金额
A12: 1、安全生产费 | G12: =E12*F12 -> 0 | H12: =B12-G12 -> 0
G13: =E13*F13 -> 0 | H13: =B13-G13 -> 0
G14: =E14*F14 -> 0 | H14: =B14-G14 -> 0
A15: 2、维简费 | G15: =E15*F15 -> 0 | H15: =B15-G15 -> 0
G16: =E16*F16 -> 0 | H16: =B16-G16 -> 0
G17: =E17*F17 -> 0 | H17: =B17-G17 -> 0
A18: 3、其他 | G18: =E18*F18 -> 0 | H18: =B18-G18 -> 0
G19: =E19*F19 -> 0 | H19: =B19-G19 -> 0
G20: =E20*F20 -> 0 | H20: =B20-G20 -> 0
A21: 合 计 | B21: =SUM(B12:B20) -> 0 | C21: =SUM(C12:C20) -> 0 | G21: =SUM(G12:G20) -> 0 | H21: =SUM(H12:H20) -> 0
A22: 三、审计说明：
A25: 四、审计结论：
A28: 提示：
A29: 高危行业企业按照国家规定提取的安全生产费，应当计入相关产品的成本或当期损益，同时计入“专项储备”科目。企业使用提取的安全生产费时，属于费用性支出的，直接冲减专
A30: 项储备。企业使用提取的安全生产费形成固定资产的，应当通过“在建工程”科目归集所发生的支出，待安全项目完工达到预定可使用状态时确认为固定资产；同时，按照形成固定资产
A31: 的成本冲减专项储备，并确认相同金额的累计折旧。该固定资产在以后期间不再计提折旧。
A32: “专项储备”科目期末余额在资产负债表所有者权益项下“减：库存股”和“盈余公积”之间增设“专项储备”项目反映。企业提取的维简费和其他具有类似性质的费用，比照上述规定处理。企
A33: 业未按上述规定进行会计处理的，应当进行追溯调整。

Sheet 专项储备支出检查表M7-5
A1: 致同会计师事务所
A2: 专项储备支出检查表
A3: =底稿目录!A2 -> 被审计单位： | D3: =底稿目录!A4 -> 编制人： | G3: =底稿目录!A5 -> 编制日期： | O3: 索引号： | P3: =底稿目录!F11 -> M7-5
A4: =底稿目录!A3 -> 截止日：202X年12月31日 | D4: =底稿目录!A6 -> 复核人： | G4: =底稿目录!A7 -> 复核日期： | O4: 页 次：
A5: 一、审计目标：
A6: 1.专项储备以恰当的金额包括在财务报表中，与之相关的计价或分摊调整已恰当记录，相关披露已得到恰当计量和描述 。
A7: 二、审计过程：
A8: 1.审查安全生产费、维简费和其他项目的使用是否符合有关规定，检查会计处理是否正确。 | F8: 2.如存在重大的非预期差异，与适当客户人员讨论；
A9: 3.考虑可信度，并在适当情况下进行证实。 | F9: 4.确定执行上述程序的结果是否表明需要补充必要的审计程序，如果是，执行适当的应对程序。
A10: 测试内容说明：1.原始凭证是否齐全； 2.记账凭证与原始凭证是否相符；3.账务处理是否正确；4.是否记录于恰当的会计期间；5.……
A11: 资本性支出使用检查；
A12: 记账凭证 | G12: 支持性文件 | H12: 核对内容 | M12: 索引号 | N12: 是否属于规定使用范围 | O12: 管理层使用计划索引 | P12: 对应的固定资产是否已全额计提折旧
A13: 日期 | B13: 凭证编号 | C13: 业务内容 | D13: 对方科目 | E13: 对方明细科目 | F13: 借/贷方金额 | H13: 1 | I13: 2 | J13: 3 | K13: 4 | L13: 5
A20: 合计 | F20: =SUM(F14:F19) -> 0
A21: 费用性支出使用检查:
A22: 记账凭证 | G22: 支持性文件 | H22: 核对内容 | M22: 索引号 | N22: 是否属于规定使用范围 | O22: 管理层使用计划索引
A23: 日期 | B23: 凭证编号 | C23: 业务内容 | D23: 对方科目 | E23: 对方明细科目 | F23: 借/贷方金额 | H23: 1 | I23: 2 | J23: 3 | K23: 4 | L23: 5
A30: 合计 | F30: =SUM(F24:F29) -> 0
A31: 三、审计说明：
A32: 1.本期使用金额检查比例： | C32: 账面金额 | D32: 检查金额 | E32: 检查比例 | F32: 如果检查比例较低应扩大检查样本量或说明原因
C33: ='明细表M7-2'!N17 -> 0 | D33: =F30+F20 -> 0 | E33: =ROUND(D33/C33,4) -> #DIV/0!
A34: 2.……
A35: 四、审计结论：
A37: 编制说明：
A38: 高危行业企业按照国家规定提取的安全生产费，应当计入相关产品的成本或当期损益，同时计入“专项储备”科目。企业使用提取的安全生产费时，属于费用性支出的，直接冲减专
A39: 项储备。企业使用提取的安全生产费形成固定资产的，应当通过“在建工程”科目归集所发生的支出，待安全项目完工达到预定可使用状态时确认为固定资产；同时，按照形成固定资产
A40: 的成本冲减专项储备，并确认相同金额的累计折旧。该固定资产在以后期间不再计提折旧。
A41: “专项储备”科目期末余额在资产负债表所有者权益项下“减：库存股”和“盈余公积”之间增设“专项储备”项目反映。企业提取的维简费和其他具有类似性质的费用，比照上述规定处理。企
A42: 业未按上述规定进行会计处理的，应当进行追溯调整。

Sheet GT_Custom
A1: C1 | B1: Custom 1
A2: C2 | B2: Custom 2
A3: C3 | B3: Custom 3
A4: C4 | B4: Custom 4
A5: C5 | B5: Custom 5
A6: C6 | B6: Custom 6
A7: C7 | B7: Custom 7
A8: C8 | B8: Custom 8
