Workbook

Sheet 附注披露信息(上市公司）D2-1
A1: 致同会计师事务所
A2: 附注披露信息（上市公司）
A3: =#REF! -> #REF! | C3: =#REF! -> #REF! | E3: =#REF! -> #REF! | F3: 索引：D2-1
A4: =#REF! -> #REF! | C4: =#REF! -> #REF! | E4: =#REF! -> #REF! | F4: 页次：
A5: 附注披露信息：
A6: 应收账款（以下不适用的，请删除）
A7: （1）应收账款按种类披露
A8: 种类 | B8: 期末数
B9: 金 额 | C9: 比例% | D9: 坏账准备 | E9: 计提比例% | F9: 净额
A10: 单项计提坏账准备的应收账款 | B10: =#REF! -> #REF! | C10: =B10/$B$17 -> #REF! | D10: =#REF! -> #REF! | E10: =IF(B10=0,,D10/B10) -> #REF! | F10: =B10-D10 -> #REF!
A11: 按组合计提坏账准备的应收账款
A12: 其中：账龄组合 | B12: =#REF! -> #REF! | C12: =B12/$B$17 -> #REF! | D12: =#REF! -> #REF! | E12: =IF(B12=0,,D12/B12) -> #REF! | F12: =B12-D12 -> #REF!
A13: 客户类型组合 | B13: =#REF! -> #REF! | C13: =B13/$B$17 -> #REF! | D13: =#REF! -> #REF! | E13: =IF(B13=0,,D13/B13) -> #REF! | F13: =B13-D13 -> #REF!
A14: 产品类型组合 | C14: =B14/$B$17 -> #REF! | E14: =IF(B14=0,,D14/B14) -> 0 | F14: =B14-D14 -> 0
A15: ……组合 | C15: =B15/$B$17 -> #REF! | E15: =IF(B15=0,,D15/B15) -> 0 | F15: =B15-D15 -> 0
A16: 组合小计 | B16: =SUM(B12:B15) -> #REF! | C16: =B16/$B$17 -> #REF! | D16: =SUM(D12:D15) -> #REF! | E16: =IF(B16=0,,D16/B16) -> #REF! | F16: =SUM(F12:F15) -> #REF!
A17: 合 计 | B17: =SUM(B10+B16) -> #REF! | C17: =B17/B17 -> #REF! | D17: =SUM(D10+D16) -> #REF! | E17: =IF(B17=0,,D17/B17) -> #REF! | F17: =SUM(F10+F16) -> #REF!
A18: 应收账款按种类披露（续）
A19: 种类 | B19: 期初数
B20: 金 额 | C20: 比例% | D20: 坏账准备 | E20: 计提比例% | F20: 净额
A21: 单项计提坏账准备的应收账款 | C21: =IF($B$28=0,0,B21/$B$28) -> 0 | E21: =IF(B21=0,0,D21/B21) -> 0 | F21: =B21-D21 -> 0
A22: 按组合计提坏账准备的应收账款
A23: 其中：账龄组合 | C23: =IF($B$28=0,0,B23/$B$28) -> 0 | E23: =IF(B23=0,0,D23/B23) -> 0 | F23: =B23-D23 -> 0
A24: 客户类型组合 | C24: =IF($B$28=0,0,B24/$B$28) -> 0 | E24: =IF(B24=0,0,D24/B24) -> 0 | F24: =B24-D24 -> 0
A25: 产品类型组合 | C25: =IF($B$28=0,0,B25/$B$28) -> 0 | E25: =IF(B25=0,0,D25/B25) -> 0 | F25: =B25-D25 -> 0
A26: ……组合 | C26: =IF($B$28=0,0,B26/$B$28) -> 0 | E26: =IF(B26=0,0,D26/B26) -> 0 | F26: =SUM(F23:F25) -> 0
A27: 组合小计 | B27: =SUM(B23:B26) -> 0 | C27: =SUM(C23:C26) -> 0 | D27: =SUM(D23:D26) -> 0 | E27: =SUM(E23:E26) -> 0 | F27: =B27-D27 -> 0
A28: 合 计 | B28: =SUM(B21+B27) -> 0 | C28: =SUM(C21+C27) -> 0 | D28: =SUM(D21+D27) -> 0 | E28: =SUM(E21+E27) -> 0 | F28: =SUM(F21+F27) -> 0
A29: 注：填写组合名称。账面余额中的比例按期末该类应收账款除以应收账款合计数计算，坏账准备比例按该类应收账款期末已计提坏账准备除以期末该类应收账款余额计算。
A30: 说明：
A31: ①期末单项计提坏账准备的应收账款
A32: 应收账款（按单位） | B32: 账面余额 | C32: 坏账准备 | D32: 计提比例% | E32: 计提理由
D33: =IF(B33=0,0,C33/B33) -> 0
D34: =IF(B34=0,0,C34/B34) -> 0
D35: =IF(B35=0,0,C35/B35) -> 0
D36: =IF(B36=0,0,C36/B36) -> 0
D37: =IF(B37=0,0,C37/B37) -> 0
A38: 合 计 | B38: =SUM(B33:B37) -> 0 | C38: =SUM(C33:C37) -> 0 | D38: =IF(B38=0,0,C38/B38) -> 0
A39: ②按账龄组合计提坏账准备的应收账款：（不适用的删除）
A40: 账 龄 | B40: 期末数
B41: 金 额 | C41: 比例% | D41: 坏账准备 | E41: 计提比例% | F41: 净额
A42: =#REF! -> #REF! | B42: =#REF! -> #REF! | C42: =IF(B42=0,0,B42/$B$48) -> #REF! | D42: =#REF! -> #REF! | E42: =IF(D42=0,0,D42/B42) -> #REF! | F42: =B42-D42 -> #REF!
A43: =#REF! -> #REF! | B43: =#REF! -> #REF! | C43: =IF(B43=0,0,B43/$B$48) -> #REF! | D43: =#REF! -> #REF! | E43: =IF(D43=0,0,D43/B43) -> #REF! | F43: =B43-D43 -> #REF!
A44: =#REF! -> #REF! | B44: =#REF! -> #REF! | C44: =IF(B44=0,0,B44/$B$48) -> #REF! | D44: =#REF! -> #REF! | E44: =IF(D44=0,0,D44/B44) -> #REF! | F44: =B44-D44 -> #REF!
A45: =#REF! -> #REF! | B45: =#REF! -> #REF! | C45: =IF(B45=0,0,B45/$B$48) -> #REF! | D45: =#REF! -> #REF! | E45: =IF(D45=0,0,D45/B45) -> #REF! | F45: =B45-D45 -> #REF!
A46: =#REF! -> #REF! | B46: =#REF! -> #REF! | C46: =IF(B46=0,0,B46/$B$48) -> #REF! | D46: =#REF! -> #REF! | E46: =IF(D46=0,0,D46/B46) -> #REF!
A47: =#REF! -> #REF! | B47: =#REF! -> #REF! | C47: =IF(B47=0,0,B47/$B$48) -> #REF! | D47: =#REF! -> #REF! | E47: =IF(D47=0,0,D47/B47) -> #REF! | F47: =B47-D47 -> #REF!
A48: 合 计 | B48: =SUM(B42:B47) -> #REF! | C48: =SUM(C42:C47) -> #REF! | D48: =SUM(D42:D47) -> #REF! | E48: =IF(D48=0,0,D48/B48) -> #REF! | F48: =SUM(F42:F47) -> #REF!
A49: （可根据企业具体会计政策，相应修改账龄组合的划分）
A50: 账 龄 | B50: 期初数
B51: 金 额 | C51: 比例% | D51: 坏账准备 | E51: 计提比例% | F51: 净额
C52: =IF(B52=0,0,B52/$B$58) -> 0 | E52: =IF(D52=0,0,D52/B52) -> 0 | F52: =B52-D52 -> 0
C53: =IF(B53=0,0,B53/$B$58) -> 0 | E53: =IF(D53=0,0,D53/B53) -> 0 | F53: =B53-D53 -> 0
C54: =IF(B54=0,0,B54/$B$58) -> 0 | E54: =IF(D54=0,0,D54/B54) -> 0 | F54: =B54-D54 -> 0
C55: =IF(B55=0,0,B55/$B$58) -> 0 | E55: =IF(D55=0,0,D55/B55) -> 0 | F55: =B55-D55 -> 0
C56: =IF(B56=0,0,B56/$B$58) -> 0 | E56: =IF(D56=0,0,D56/B56) -> 0
C57: =IF(B57=0,0,B57/$B$58) -> 0 | E57: =IF(D57=0,0,D57/B57) -> 0 | F57: =B57-D57 -> 0
A58: 合 计 | B58: =SUM(B52:B57) -> 0 | C58: =IF(B58=0,0,B58/$B$58) -> 0 | D58: =SUM(D52:D57) -> 0 | E58: =IF(D58=0,0,D58/B58) -> 0 | F58: =SUM(F52:F57) -> 0
A59: ③组合中，采用客户类型组合计提坏账准备的应收账款：（不适用的删除）
A60: 组合名称 | B60: 账面余额 | C60: 坏账准备 | D60: 计提比例
A61: 组合1（注明具体组合名称） | D61: =IF(B61=0,0,C61/B61) -> 0
A62: 组合2（注明具体组合名称） | D62: =IF(B62=0,0,C62/B62) -> 0
A63: …… | D63: =IF(B63=0,0,C63/B63) -> 0
A64: 合 计 | B64: =SUM(B61:B63) -> 0 | C64: =SUM(C61:C63) -> 0 | D64: =IF(B64=0,0,C64/B64) -> 0
A65: ④组合中，采用产品类型组合计提坏账准备的应收账款：（不适用的删除）
A66: 组合名称 | B66: 账面余额 | C66: 坏账准备 | D66: 计提比例
A67: 组合1（注明具体组合名称） | D67: =IF(B67=0,0,C67/B67) -> 0
A68: 组合2（注明具体组合名称） | D68: =IF(B68=0,0,C68/B68) -> 0
A69: …… | D69: =IF(B69=0,0,C69/B69) -> 0
A70: 合 计 | B70: =SUM(B67:B69) -> 0 | C70: =SUM(C67:C69) -> 0 | D70: =IF(B70=0,0,C70/B70) -> 0
A71: ⑤组合中，采用……组合计提坏账准备的应收账款：（不适用的删除）
A72: 组合名称 | B72: 账面余额 | C72: 坏账准备 | D72: 计提比例
A73: 组合1（注明具体组合名称） | D73: =IF(B73=0,0,C73/B73) -> 0
A74: 组合2（注明具体组合名称） | D74: =IF(B74=0,0,C74/B74) -> 0
A75: …… | D75: =IF(B75=0,0,C75/B75) -> 0
A76: 合 计 | B76: =SUM(B73:B75) -> 0 | C76: =SUM(C73:C75) -> 0 | D76: =IF(B76=0,0,C76/B76) -> 0
A77: 注：填写具体组合名称。
A78: （2）本期计提、收回或转回的坏账准备情况
B79: 坏账准备金额
A80: 期初数
A81: 本期计提
A82: 本期收回或转回
A83: 本期核销
A84: [本期转销]
A85: [其他]
A86: 期末数 | B86: =B80+B81-B82-B83-B84-B85 -> 0
A87: 其中，本期坏账准备转回或收回金额重要的：
A88: 单位名称 | B88: 转回原因 | C88: 收回方式 | D88: 原确定坏账准备的依据 | E88: 转回或收回金额
A94: 合 计 | E94: =SUM(E89:E93) -> 0
A95: 注：本期坏账准备收回或转回金额重要的，应披露转回原因、收回方式、确定原坏账准备计提比例的依据及其合理性；
A96: （3）本期实际核销的应收账款情况
A97: 项目 | B97: 核销金额
A98: 实际核销的应收账款 | B98: =#REF! -> #REF!
A99: 其中，重要的应收账款核销情况（逐项披露）：
A100: 单位名称 | B100: 应收账款的性质 | C100: 核销金额 | D100: 核销原因 | E100: 履行的核销程序 | F100: 是否由关联交易产生
A104: 合 计 | C104: =SUM(C101:C103) -> 0
A105: （对于其中重要的应收账款，应逐项披露款项性质、核销原因、履行的核销程序及核销金额。实际核销的款项由关联交易产生的，应单独披露；）
A106: 说明：
A107: （4）按欠款方归集的应收账款期末余额前五名单位情况
A108: 单位名称 | B108: 款项性质 | C108: 应收账款期末余额 | D108: 账龄 | E108: 占应收账款期末余额合计数的比例(%) | F108: 坏账准备期末余额
...

Sheet 附注披露信息（国企）D2-1
A1: 致同会计师事务所
A2: 附注披露信息（国企）
A3: =#REF! -> #REF! | C3: =#REF! -> #REF! | E3: =#REF! -> #REF! | G3: 索引：D2-1
A4: =#REF! -> #REF! | C4: =#REF! -> #REF! | E4: =#REF! -> #REF! | G4: 页次：1
A5: 附注披露信息：
A6: 应收账款
A7: 应收账款按种类披露
A8: 种 类 | B8: 期末数
B9: 账面余额 | C9: 比例% | D9: 坏账准备 | E9: 比例%
A10: 单项计提坏账准备的应收账款 | B10: =#REF! -> #REF! | C10: =IF($B$17=0,0,B10/$B$17) -> #REF! | D10: =#REF! -> #REF! | E10: =IF(B10=0,0,D10/B10) -> #REF!
A11: 按组合计提坏账准备的应收账款
A12: 其中：账龄组合 | B12: =#REF! -> #REF! | C12: =IF($B$17=0,0,B12/$B$17) -> #REF! | D12: =#REF! -> #REF! | E12: =IF(B12=0,0,D12/B12) -> #REF!
A13: 客户类型组合 | B13: =#REF! -> #REF! | C13: =IF($B$17=0,0,B13/$B$17) -> #REF! | D13: =#REF! -> #REF! | E13: =IF(B13=0,0,D13/B13) -> #REF!
A14: 产品类型组合 | C14: =IF($B$17=0,0,B14/$B$17) -> #REF! | E14: =IF(B14=0,0,D14/B14) -> 0
A15: ……组合 | C15: =IF($B$17=0,0,B15/$B$17) -> #REF! | E15: =IF(B15=0,0,D15/B15) -> 0
A16: 组合小计 | B16: =SUM(B12:B15) -> #REF! | C16: =IF($B$17=0,0,B16/$B$17) -> #REF! | D16: =SUM(D12:D15) -> #REF! | E16: =IF(B16=0,0,D16/B16) -> #REF!
A17: 合 计 | B17: =SUM(B10+B16) -> #REF! | C17: =SUM(C10+C16) -> #REF! | D17: =SUM(D10+D16) -> #REF! | E17: =IF(B17=0,0,D17/B17) -> #REF!
A18: 应收账款按种类披露（续）
A19: 种 类 | B19: 年初数
B20: 账面余额 | C20: 比例% | D20: 坏账准备 | E20: 比例%
A21: 单项计提坏账准备的应收账款 | C21: =IF($B$28=0,0,B21/$B$28) -> 0 | E21: =IF(B21=0,0,D21/B21) -> 0
A22: 按组合计提坏账准备的应收账款
A23: 其中：账龄组合 | C23: =IF($B$28=0,0,B23/$B$28) -> 0 | E23: =IF(B23=0,0,D23/B23) -> 0
A24: 客户类型组合 | C24: =IF($B$28=0,0,B24/$B$28) -> 0 | E24: =IF(B24=0,0,D24/B24) -> 0
A25: 产品类型组合 | C25: =IF($B$28=0,0,B25/$B$28) -> 0 | E25: =IF(B25=0,0,D25/B25) -> 0
A26: ……组合 | C26: =IF($B$28=0,0,B26/$B$28) -> 0 | E26: =IF(B26=0,0,D26/B26) -> 0
A27: 组合小计 | B27: =SUM(B23:B26) -> 0 | C27: =IF($B$28=0,0,B27/$B$28) -> 0 | D27: =SUM(D23:D26) -> 0 | E27: =IF(B27=0,0,D27/B27) -> 0
A28: 合 计 | B28: =SUM(B21+B26+B27) -> 0 | C28: =SUM(C21+C26+C27) -> 0 | D28: =SUM(D21+D26+D27) -> 0 | E28: =IF(B28=0,0,D28/B28) -> 0
A29: （注：①填写组合名称。②账面余额中的比例按年末该类应收账款除以应收账款余额合计数计算，坏账准备比例按该类应收账款年末已计提坏账准备除以年末该类应收账款余额计算。）
A30: （1）按组合计提坏账准备的应收账款
A31: A、采用账龄分析法计提坏账准备的应收账款
A32: 账 龄 | B32: 期末数 | E32: 年初数
B33: 账面余额 | D33: 坏账准备 | E33: 账面余额 | G33: 坏账准备
B34: 金额 | C34: 比例(%) | E34: 金额 | F34: 比例(%)
A35: =#REF! -> #REF! | B35: =#REF! -> #REF! | C35: =IF(B35=0,0,B35/$B$41) -> #REF! | D35: =#REF! -> #REF! | F35: =IF(E35=0,0,E35/$E$41) -> 0
A36: =#REF! -> #REF! | B36: =#REF! -> #REF! | C36: =IF(B36=0,0,B36/$B$41) -> #REF! | D36: =#REF! -> #REF! | F36: =IF(E36=0,0,E36/$E$41) -> 0
A37: =#REF! -> #REF! | B37: =#REF! -> #REF! | C37: =IF(B37=0,0,B37/$B$41) -> #REF! | D37: =#REF! -> #REF! | F37: =IF(E37=0,0,E37/$E$41) -> 0
A38: =#REF! -> #REF! | B38: =#REF! -> #REF! | C38: =IF(B38=0,0,B38/$B$41) -> #REF! | D38: =#REF! -> #REF! | F38: =IF(E38=0,0,E38/$E$41) -> 0
A39: =#REF! -> #REF! | B39: =#REF! -> #REF! | C39: =IF(B39=0,0,B39/$B$41) -> #REF! | D39: =#REF! -> #REF! | F39: =IF(E39=0,0,E39/$E$41) -> 0
A40: =#REF! -> #REF! | B40: =#REF! -> #REF! | C40: =IF(B40=0,0,B40/$B$41) -> #REF! | D40: =#REF! -> #REF! | F40: =IF(E40=0,0,E40/$E$41) -> 0
A41: 合 计 | B41: =SUM(B35:B40) -> #REF! | C41: =IF(B41=0,0,B41/$B$41) -> #REF! | D41: =SUM(D35:D40) -> #REF! | E41: =SUM(E35:E40) -> 0 | F41: =IF(E41=0,0,E41/$E$41) -> 0 | G41: =SUM(G35:G40) -> 0
A42: （可根据企业具体会计政策，相应修改账龄组合的划分）
A43: B、采用客户类型组合计提坏账准备的应收账款
A44: 组合名称 | B44: 期末数 | E44: 年初数
B45: 账面余额 | C45: 计提比例(%) | D45: 坏账准备 | E45: 账面余额 | F45: 计提比例(%) | G45: 坏账准备
A46: 组合1 | C46: =IF(B46=0,0,B46/$B$49) -> 0 | F46: =IF(E46=0,0,E46/$E$49) -> 0
A47: 组合2 | C47: =IF(B47=0,0,B47/$B$49) -> 0 | F47: =IF(E47=0,0,E47/$E$49) -> 0
A48: …… | C48: =IF(B48=0,0,B48/$B$49) -> 0 | F48: =IF(E48=0,0,E48/$E$49) -> 0
A49: 合 计 | B49: =SUM(B46:B48) -> 0 | C49: =IF(B49=0,0,D49/B49) -> 0 | D49: =SUM(D46:D48) -> 0 | E49: =SUM(E46:E48) -> 0 | F49: =IF(E49=0,0,G49/E49) -> 0 | G49: =SUM(G46:G48) -> 0
A50: 注：填写具体组合名称。
A51: C、采用产品类型组合计提坏账准备的应收账款
A52: 组合名称 | B52: 期末数 | E52: 年初数
B53: 账面余额 | C53: 计提比例(%) | D53: 坏账准备 | E53: 账面余额 | F53: 计提比例(%) | G53: 坏账准备
A54: 组合1 | C54: =IF(B54=0,0,B54/$B$57) -> 0 | F54: =IF(E54=0,0,E54/$E$57) -> 0
A55: 组合2 | C55: =IF(B55=0,0,B55/$B$57) -> 0 | F55: =IF(E55=0,0,E55/$E$57) -> 0
A56: …… | C56: =IF(B56=0,0,B56/$B$57) -> 0 | F56: =IF(E56=0,0,E56/$E$57) -> 0
A57: 合 计 | B57: =SUM(B54:B56) -> 0 | C57: =IF(B57=0,0,D57/B57) -> 0 | D57: =SUM(D54:D56) -> 0 | E57: =SUM(E54:E56) -> 0 | F57: =IF(E57=0,0,G57/E57) -> 0 | G57: =SUM(G54:G56) -> 0
A58: 注：填写具体组合名称。
A59: D、采用……组合计提坏账准备的应收账款
A60: 组合名称 | B60: 期末数 | E60: 年初数
B61: 账面余额 | C61: 计提比例(%) | D61: 坏账准备 | E61: 账面余额 | F61: 计提比例(%) | G61: 坏账准备
A62: 组合1 | C62: =IF(B62=0,0,B62/$B$65) -> 0 | F62: =IF(E62=0,0,E62/$E$65) -> 0
A63: 组合2 | C63: =IF(B63=0,0,B63/$B$65) -> 0 | F63: =IF(E63=0,0,E63/$E$65) -> 0
A64: …… | C64: =IF(B64=0,0,B64/$B$65) -> 0 | F64: =IF(E64=0,0,E64/$E$65) -> 0
A65: 合 计 | B65: =SUM(B62:B64) -> 0 | C65: =IF(B65=0,0,D65/B65) -> 0 | D65: =SUM(D62:D64) -> 0 | E65: =SUM(E62:E64) -> 0 | F65: =IF(E65=0,0,G65/E65) -> 0 | G65: =SUM(G62:G64) -> 0
A66: 注：填写具体组合名称。
A67: （2）单项计提坏账准备的应收账款
A68: 债务人名称 | B68: 账面余额 | C68: 坏账准备 | D68: 账龄 | E68: 计提比例 | F68: 计提理由
E69: =IF(B69=0,0,C69/B69) -> 0
E70: =IF(B70=0,0,C70/B70) -> 0
E71: =IF(B71=0,0,C71/B71) -> 0
E72: =IF(B72=0,0,C72/B72) -> 0
E73: =IF(B73=0,0,C73/B73) -> 0
A74: 合 计 | B74: =SUM(B69:B73) -> 0 | C74: =SUM(C69:C73) -> 0
A75: （3）本期转回或收回情况（非上市公司可参照选择披露）
A76: 债务人名称 | B76: 转回或收回原因 | C76: 确定原坏账准备的依据 | D76: 转回或收回前累计已计提坏账准备金额 | E76: 转回或收回金额
A77: =#REF! -> #REF! | B77: =#REF! -> #REF! | C77: =#REF! -> #REF! | D77: =#REF! -> #REF! | E77: =#REF! -> #REF!
A78: =#REF! -> #REF! | B78: =#REF! -> #REF! | C78: =#REF! -> #REF! | D78: =#REF! -> #REF! | E78: =#REF! -> #REF!
A79: =#REF! -> #REF! | B79: =#REF! -> #REF! | C79: =#REF! -> #REF! | D79: =#REF! -> #REF! | E79: =#REF! -> #REF!
A80: 合计 | D80: =SUM(D77:D79) -> #REF! | E80: =SUM(E77:E79) -> #REF!
A81: （注：本表列报本报告期前已全额计提坏账准备，或计提减值准备的比例较大，但在本期又全额收回或转回，或在本期收回或转回比例较大的应收账款。对本期通过重组等方式收回的金额重大的应收账款，则应逐笔列报，金额不重大的，可汇总列报。）
A82: （4）本报告期实际核销的应收账款（非上市公司可参照选择披露）
A83: 债务人名称 | B83: 应收账款性质 | C83: 核销金额 | D83: 核销原因 | E83: 是否因关联交易产生
A84: =#REF! -> #REF! | B84: =#REF! -> #REF! | C84: =#REF! -> #REF! | D84: =#REF! -> #REF! | E84: =#REF! -> #REF!
A85: =#REF! -> #REF! | B85: =#REF! -> #REF! | C85: =#REF! -> #REF! | D85: =#REF! -> #REF! | E85: =#REF! -> #REF!
A86: =#REF! -> #REF! | B86: =#REF! -> #REF! | C86: =#REF! -> #REF! | D86: =#REF! -> #REF! | E86: =#REF! -> #REF!
A87: 合计 | B87: -- | C87: =SUM(C84:C86) -> #REF! | D87: -- | E87: --
A88: （5）由金融资产转移而终止确认的应收账款情况
A89: 单位名称 | B89: 终止确认金额 | C89: 与终止确认相关的利得或损失（损失以“-”填列）
A90: =#REF! -> #REF! | B90: =#REF! -> #REF! | C90: =#REF! -> #REF!
A91: =#REF! -> #REF! | B91: =#REF! -> #REF! | C91: =#REF! -> #REF!
A93: 合 计 | B93: =SUM(B90:B92) -> #REF! | C93: =SUM(C90:C92) -> #REF!
A94: （6）应收账款转移，如证券化、保理等，继续涉入形成的资产、负债的金额
A95: 项 目 | B95: 期末金额
A96: 资产：
A98: 资产小计 | B98: =SUM(B97:B97) -> 0
A99: 负债：
A101: 负债小计 | B101: =SUM(B100:B100) -> 0
A102: 说明：（资产转移方式；未全部终止确认的被转移金融资产与相关负债之间的关系，已终止确认的金融资产继续涉入的性质及相关风险的信息。）

Sheet 应收账款分析表D2-5
A1: 致同会计师事务所
A2: 应收账款分析表
A3: =[4]底稿目录!$A$2 -> 被审计单位名称： | C3: =[4]底稿目录!$A$4 -> 编制人： | E3: =[4]底稿目录!$A$5 -> 编制日期： | G3: 索引号： | H3: D2-5
A4: =[4]底稿目录!$A$3 -> 截止日：202X年12月31日 | C4: =[4]底稿目录!$A$6 -> 复核人： | E4: =[4]底稿目录!$A$7 -> 复核日期： | G4: 页次：
A5: 一、审计目标
A6: 1.资产负债表中记录的应收账款是存在的。2.所有应当记录的应收账款均已记录。3. 应收账款以恰当的金额包括在财务报表中，与之相关的计价调整已恰当记录。
A7: 二、审计过程
A8: 1.……
A10: （一）应收账款重要指标分析
A11: 见<D4-6>营业收入重要指标分析底稿
A12: （二）应收账款借方发生额与收入核对
A13: 项目 | B13: 金额 | C13: 数据来源 | D13: 备注
A14: 本期主营业务收入
A15: 增值税率
A16: 收入价税合计 | B16: =B14*(1+B15) -> 0
A17: 本期应收账款借方发生额合计
A18: 收入价税合计与应收账款借方发生额差异 | B18: =B16-B17 -> 0
A19: 差异原因
A20: （三）应收账款贷方发生额分析
B21: 金额 | C21: 数据来源 | D21: 与对方科目核对 | E21: 说明
A22: 本期贷方发生额合计 | C22: 应收账款总账 | D22: N/A | E22: N/A
A23: 其中：银行存款收回款项 | E23: 与银行存款借方发生额核对
A24: 计入应收票据 | E24: 与应收票据借方发生额核对
A25: ……
A26: 差异原因
A27: （四）期末应收账款前十名分析
A28: 客户名称 | B28: 期末账面余额 | C28: 期初账面余额 | D28: 变动金额 | E28: 变动比例 | F28: 账龄 | G28: 信用期 | H28: 逾期金额
A29: 客户1 | D29: =B29-C29 -> 0 | E29: =D29/C29 -> #DIV/0!
A30: 客户2 | D30: =B30-C30 -> 0 | E30: =D30/C30 -> #DIV/0!
A31: 客户3 | D31: =B31-C31 -> 0 | E31: =D31/C31 -> #DIV/0!
A32: 客户4 | D32: =B32-C32 -> 0 | E32: =D32/C32 -> #DIV/0!
A33: 客户5 | D33: =B33-C33 -> 0 | E33: =D33/C33 -> #DIV/0!
A34: 客户6 | D34: =B34-C34 -> 0 | E34: =D34/C34 -> #DIV/0!
A35: 客户7 | D35: =B35-C35 -> 0 | E35: =D35/C35 -> #DIV/0!
A36: 客户8 | D36: =B36-C36 -> 0 | E36: =D36/C36 -> #DIV/0!
A37: 客户9 | D37: =B37-C37 -> 0 | E37: =D37/C37 -> #DIV/0!
A38: 客户10 | D38: =B38-C38 -> 0 | E38: =D38/C38 -> #DIV/0!
A39: 合计 | B39: =SUM(B29:B38) -> 0 | C39: =SUM(C29:C38) -> 0 | D39: =SUM(D29:D38) -> 0 | E39: =D39/C39 -> #DIV/0! | H39: =SUM(H29:H38) -> 0
A40: （五）近两年账龄结构分析
A41: 账龄 | B41: 期末账面余额 | C41: 各账龄占比 | D41: 期初账面余额 | E41: 各账龄占比 | F41: 变动金额 | G41: 变动比例 | H41: 原因分析
A42: 1年以内 | C42: =IF($B$48=0,"",B42/$B$48) | E42: =IF($D$48=0,"",D42/$D$48) | F42: =B42-D42 -> 0 | G42: =F42/D42 -> #DIV/0!
A43: 1-2年 | C43: =IF($B$48=0,"",B43/$B$48) | E43: =IF($D$48=0,"",D43/$D$48) | F43: =B43-D43 -> 0 | G43: =F43/D43 -> #DIV/0!
A44: 2-3年 | C44: =IF($B$48=0,"",B44/$B$48) | E44: =IF($D$48=0,"",D44/$D$48) | F44: =B44-D44 -> 0 | G44: =F44/D44 -> #DIV/0!
A45: 3-4年 | C45: =IF($B$48=0,"",B45/$B$48) | E45: =IF($D$48=0,"",D45/$D$48) | F45: =B45-D45 -> 0 | G45: =F45/D45 -> #DIV/0!
A46: 4-5年 | C46: =IF($B$48=0,"",B46/$B$48) | E46: =IF($D$48=0,"",D46/$D$48) | F46: =B46-D46 -> 0 | G46: =F46/D46 -> #DIV/0!
A47: 5年以上 | C47: =IF($B$48=0,"",B47/$B$48) | E47: =IF($D$48=0,"",D47/$D$48) | F47: =B47-D47 -> 0 | G47: =F47/D47 -> #DIV/0!
A48: 合计 | B48: =SUM(B42:B47) -> 0 | C48: =IF($B$48=0,"",B48/$B$48) | D48: =SUM(D42:D47) -> 0 | E48: =SUM(E42:E47) -> 0 | F48: =SUM(F42:F47) -> 0 | G48: =F48/D48 -> #DIV/0!
A49: 三、审计说明
A53: 四、审计结论

Sheet GT_Custom
A1: C1 | B1: Custom 1
A2: C2 | B2: Custom 2
A3: C3 | B3: Custom 3
A4: C4 | B4: Custom 4
A5: C5 | B5: Custom 5
A6: C6 | B6: Custom 6
A7: C7 | B7: Custom 7
A8: C8 | B8: Custom 8
