Workbook

Sheet 底稿目录
A1: 底稿开列时，可先在以下单元格填写有关内容，以便其他底稿引用有关数据： | B1: 目录
A2: 被审计单位：
A3: 会计期间：202X年度 | B3: 序号 | C3: 内容 | D3: 索引号 | E3: 备注
A4: 编制人： | B4: 1 | C4: 研发费用实质性程序 | D4: I6A
A5: 编制日期： | B5: 2 | C5: 研发费用审定表 | D5: I6-1
A6: 复核人： | B6: 3 | C6: 研发费用附注披露表（上市公司） | E6: 无需打印
A7: 复核日期： | B7: 4 | C7: 研发费用附注披露表（国有企业） | E7: 无需打印
B8: 5 | C8: 研发费用明细表 | D8: I6-2
A9: 关于工作底稿与审计程序索引号对应的说明 | B9: 6 | C9: 调整分录汇总 | D9: I6-3 | E9: 备选
A10: 1.编制的审计工作底稿应与审计程序对应。审计项目组应根据被审计单位实际情况和风险评估情况在实质性程序表中裁剪、修改或增加审计程序，根据实际执行的审计程序完成相应审计工作底稿，编制的工作底稿中应按自然顺序依次编制索引号，并通过唯一的索引号将与实质性程序表中的程序对应关联（即将工作底稿的索引号填入实质性程序表中的底稿索引号列）。 | B10: 7 | C10: 会计政策检查 | D10: I2-4 | E10: 提示：该部分底稿模板在开发支出底稿中，如果被审计单位既有开发支出又有研发费用可在开发支出中综合完成研发相关的主要底稿，研发费用交叉索引；如果被审计单位研发活动全部计入研发费用可将该部分底稿从开发支出底稿模板中移至研发费用中完成。
B11: 8 | C11: 实质性分析 | D11: I2-5
B12: 9 | C12: 研发项目资本化时点判断 | D12: I2-6
B13: 10 | C13: 研发项目构成明细表 | D13: I2-7
A14: 2.获取的支持性证据应与审计底稿或程序对应。审计项目组在完成底稿时获取的支持性证据应根据底稿索引号编制下一级按自然顺序排序的索引号（如D1-2-1、D1-2-2、……），并在底稿中说明引用的支持性证据、关联索引号。 | B14: 11 | C14: 研发材料投入检查表 | D14: I2-8
B15: 12 | C15: 研发人员认定检查表 | D15: I2-9
B16: 13 | C16: 研发人员工时检查表 | D16: I2-10
A17: 3.工作底稿索引号的编码规则：实质性程序索引号按循环从“D”到“N”,循环内账户以顺序号排列，模板中底稿索引号按账户顺序+自然数顺序（即模板中索引号按二级自然顺序排列，如D1-1、D1-2、D1-3、……D1-N）。 | B17: 14 | C17: 委外研发检查表 | D17: I2-11
B18: 15 | C18: 其他针对性检查表 | D18: I6-4
B19: 16 | C19: 截止性测试（账到单据） | D19: I6-5
B20: 17 | C20: 截止性测试（单据到账） | D20: I6-6

Sheet 研发费用实质性程序 I6A
A1: 致同会计师事务所
A2: 研发费用实质性程序
A3: =底稿目录!A2 -> 被审计单位： | C3: =底稿目录!A4 -> 编制人： | E3: =底稿目录!A5 -> 编制日期： | H3: 索引号： | I3: =底稿目录!D4 -> I6A
A4: =底稿目录!A3 -> 会计期间：202X年度 | C4: =底稿目录!A6 -> 复核人： | E4: =底稿目录!A7 -> 复核日期： | H4: 页 次：
A5: 一、本账户涉及的科目
A6: 研发费用
A7: 二、审计目标与认定的对应关系
A8: 审计目标 | G8: 财务报表的认定
A9: A. 利润表中记录的研发费用已发生，且与被审计单位有关，已记录于恰当的账户 | G9: 发生
A10: B. 所有应当记录的研发费用均已记录，所有应当包括在财务报表中的相关披露均已包括 | G10: 完整性
A11: C. 与研发费用有关的金额及其他数据已恰当记录，相关披露已得到恰当计量和描述 | G11: 准确性
A12: D. 研发费用已记录于正确的会计期间 | G12: 截止
A13: E. 研发费用已被恰当地汇总或分解且表述清楚，相关披露在按照企业会计准则的编制基础下是相关的、可理解的 | G13: 列报
A14: 三、计划实施的实质性程序
A15: 序号 | B15: 审计程序 | C15: 程序分类 | D15: 财务报表的认定 | I15: 底稿索引号
D16: 发生 | E16: 完整性 | F16: 准确性 | G16: 截止 | H16: 列报 | J16: 根据被审计单位实际情况和风险评估情况裁剪、修改或增加审计程序
A17: 1 | B17: 获取或编制研发费用细表，复核加计是否正确，并与总账数和明细账合计数核对是否相符，编制审定表，结合研发费用报表数核对是否相符。 | C17: 常规★ | D17: √ | E17: √ | F17: √ | I17: I6-1 /I6-2
A18: 2 | B18: 在使用手工编制、自定义信息报告、系统生成的非固定格式报告等由被审计单位生成的信息时，测试有关信息准确性和完整性，并考虑针对编制和维护由被审计单位生成的信息的相关控制实施控制测试，以评价该信息是否能够为实现审计目的提供基础。 | C18: 常规★ | E18: √ | F18: √ | I18: T1 | J18: 可参见《审计手册》4.2.6，由被审计单位生成的信息可能是由系统生成的、或手工编制的、或二者兼而有之的方式生成的。例如，由被审计单位生成的信息可能包括： • 不涉及自定义的、由系统生成的报告（如，固定格式报告）； • 可能通过人工自定义的、由系统生成的报告，例如，（计算机）查询信息或特别定制的报告； • 手工编制的信息，例如，汇总信息的电子表格或用以支持分配、计算以及调节的电子表格； • 其他系统生成或手工编制的信息，例如，由被审计单位编制的客户发票； • 通过影印、拍摄、扫描或其他方式转换成电子形式的文件记录。
A19: 3 | B19: 结合开发支出期初余额审计和研发费用本期审计，确定研发费用前期期末的截止是否恰当。（适用于首次承接） | C19: 备选 | G19: √ | J19: 由被审计单位生成的信息不包括： • 总分类账或明细分类账、试算平衡表、或经审计的财务报表； • 第三方（除了服务机构）的报表或报告，例如，原始银行对账单，或函证的回函； • 外部数据（例如，第三方发布的数据，如，定价来源）。
A20: 4 | B20: 关注会计政策、会计估计合理性、一贯性，关注其是否利用会计政策和会计估计及其变更操纵利润： （1）检查研发支出资本化的时点、条件等会计政策是否符合会计准则要求，是否符合研发业务特点，是否符合行业惯例；检查研究阶段和开发阶段界定时点是否合理，开发完成的时点的界定是否合理； （2）将被审计单位本期的会计政策、会计估计与前期进行对比，分析其是否前后一致。对于存在会计政策、会计估计变更的情形，判断是否合理，会计处理是否正确； （3）与同行业其他公司的会计政策、会计估计进行对比，关注其是否利用会计政策和会计估计变更操纵利润； | C20: 常规★ | D20: √ | E20: √ | F20: √ | I20: I2-4 | J20: 提示：I2-4至I2-11稿模板在开发支出底稿中，如果被审计单位既有开发支出又有研发费用可在开发支出中综合完成研发相关的主要底稿，研发费用交叉索引；如果被审计单位研发活动全部计入研发费用可将该部分底稿从开发支出底稿模板中移至研发费用中完成。
A21: 5 | B21: 实施分析性程序： （1）将本期明细表与上期审定数据、本期各明细项目占主营业务收入的比重与上年同期的占比进行比较，分析两期波动的原因及合理性； （2）计算各类费用增长率，与主营业务收入增长率进行比较，并与同行业公司进行比较，分析总体合理性； （3）分析明细中是否存在不符合往年常态的项目，不符合企业经营状况，存在异常变动的项目，检查相关支持性文件； （4）计算人均经费、平均薪酬等，与上年同期数据进行比较，并与同行业公司进行比较； （5）将费用实际金额与预算金额进行比较，对具体费用项目与相关财务数据及非财务数据的匹配性进行测试。 | C21: 常规★ | D21: √ | E21: √ | F21: √ | I21: I2-5
A22: 6 | B22: 对于研发项目资本化时点的判断，根据具体情况，需要检查的支持性文件包括但不限于： （1）获取有关协议和董事会纪要、可行性研究报告等文件，检查企业研发活动的立项情况，确定研发项目处于研究阶段还是开发阶段； （2）关注资本化的条件和依据，检查研究阶段和开发阶段界定时点是否合理，开发完成的时点的界定是否合理；检查开发阶段的支出资本化，是否满足准则规定的“五个条件”，并获取通过研发活动明显增强盈利能力、明显改善资产质量的证据（如研发形成专利，开发出新的产品，产品档次明显提升等）；对于确实无法区分研究阶段的支出和开发阶段的支出，检查是否将其所发生的研发支出全部费用化。 | C22: 常规★ | D22: √ | E22: √ | F22: √ | G22: √ | I22: I2-6
A23: 7 | B23: 取得或编制研发项目支出构成明细表，判断研发支出构成是否合理。 | C23: 常规★ | D23: √ | F23: √ | I23: I2-7
A24: 8 | B24: 对于研发材料投入，根据具体情况，需要检查的支持性文件包括但不限于： （1）获取研发领料单，检查其审批流程是否完整、领用部门是否为研发部门； （2）抽取样本检查领料单与研发项目的对应关系，验证其合理性； （3）检查研发材料实际使用情况，是否存在挪用于生产或其他用途； （4）研发形成产品或副产品的，检查其成本是否已从研发费用中转出 | C24: 常规★ | D24: √ | E24: √ | F24: √ | G24: √ | I24: I2-8
A25: 9 | B25: 对于研发人员认定，根据具体情况，需要检查的支持性文件包括但不限于： （1）获取研发人员花名册、劳动合同、工作职责、工时记录，核实研发人员身份真实性； （2）核实研发人员专业背景和工作经历是否与发行人研发活动相匹配等情形，重点关注相关人员是否具备从事研发活动的能力，是否真正从事研发活动并作出实际贡献，是否属于发行人研发工作所需的必要人员，发行人研发人员数量和占比是否符合行业特点； （3）核实研发人员学历、专业、从业和任职年限、全时与非全时分布等是否符合行业特点；研发人员普遍任职年限较短的，应关注原因及对发行人研发能力的影响；研发人员主要由非全时人员或未签订劳动合同人员构成的，应关注其合理性。 | C25: 常规★ | D25: √ | E25: √ | F25: √ | G25: √ | I25: I2-9
A26: 10 | B26: 对于研发工时，根据具体情况，需要检查的支持性文件包括但不限于： （1）获取研发人员工资计提表，检查研发人员认定、工时统计、薪酬分摊是否准确合理； （2）检查研发人员考勤记录等，验证其是否真实参与研发活动； （3）结合应付职工薪酬审计，将薪酬计提与支付记录、社保缴纳记录等进行核对； （4）检查是否存在非研发人员（如高管）薪酬计入研发费用，若存在，检查其工时记录及分摊的合理性。 | C26: 常规★ | D26: √ | E26: √ | F26: √ | G26: √ | I26: I2-10
A27: 11 | B27: 对于委托研发，根据具体情况，需要检查的支持性文件包括但不限于： （1）检查委托开发合同，关注研发成果所有权归属，判断支出应计入研发费用还是营业成本； （2）检查付款审批记录、发票、验收证明等支持性文件； （3）对受托方执行函证程序，确认交易真实性、金额准确性。 | C27: 常规★ | D27: √ | E27: √ | F27: √ | G27: √ | I27: I2-11
A28: 12 | B28: 对于存在委外研发、在研发过程中产出的产品或副产品、按照客户需求进行定制化研发、履行定制化研发合同过程中发生的研发支出、承担由国家或指定方拨付款项的研发项目等情形，重点核查相关会计处理是否符合《企业会计准则》相关规定。 | C28: 备选 | D28: √ | F28: √
A29: 13 | B29: 检查本期新增其他研发费用的记账凭证和相关支持性文件，关注会计处理是否正确、划分为研发费用是否合理。 | C29: 常规★ | D29: √ | F29: √ | I29: I6-5
A30: 14 | B30: 研发费用的截止测试： （1）获取资产负债表日前后若干天、一定金额以上的会计记录，与相关支出凭单等信息核对，确定研发费用是否记入了恰当的期间。 （2）获取资产负债表日前后若干天、一定金额以上的相关支出凭单等，与会计记录信息核对，确定是否存在研发费用跨期。 | C30: 常规★ | G30: √ | I30: I6-6 /I6-7
A31: 15 | B31: 根据评估的舞弊风险等因素增加的审计程序。 | C31: IPO/上市/新三板/重组/舞弊应对
A32: 16 | B32: 检查研发费用是否已按企业会计准则或其他适用的规定在财务报表中做出恰当列报和披露。 | C32: 常规★ | H32: √ | I32: A1-1/A1-15 /A1-16

Sheet 附注披露（上市公司）
A1: 致同会计师事务所
A2: 研发费用附注披露表（上市公司）
A3: =底稿目录!A2 -> 被审计单位： | C3: =底稿目录!A4 -> 编制人： | E3: =底稿目录!A5 -> 编制日期：
A4: =底稿目录!A3 -> 会计期间：202X年度 | C4: =底稿目录!A6 -> 复核人： | E4: =底稿目录!A7 -> 复核日期：
A5: 研发费用（按费用性质列示）
A6: 项目 | B6: 本期发生额 | C6: 上期发生额
A7: ='明细表I6-2'!X9 -> 0 | B7: =SUMIF('明细表I6-2'!$X:$X,$A7,'明细表I6-2'!$Q:$Q) -> 0 | C7: =SUMIF('明细表I6-2'!$X:$X,$A7,'明细表I6-2'!$W:$W) -> 0
A8: ='明细表I6-2'!X10 -> 0 | B8: =SUMIF('明细表I6-2'!$X:$X,$A8,'明细表I6-2'!$Q:$Q) -> 0 | C8: =SUMIF('明细表I6-2'!$X:$X,$A8,'明细表I6-2'!$W:$W) -> 0
A9: ='明细表I6-2'!X11 -> 0 | B9: =SUMIF('明细表I6-2'!$X:$X,$A9,'明细表I6-2'!$Q:$Q) -> 0 | C9: =SUMIF('明细表I6-2'!$X:$X,$A9,'明细表I6-2'!$W:$W) -> 0
A10: ='明细表I6-2'!X12 -> 0 | B10: =SUMIF('明细表I6-2'!$X:$X,$A10,'明细表I6-2'!$Q:$Q) -> 0 | C10: =SUMIF('明细表I6-2'!$X:$X,$A10,'明细表I6-2'!$W:$W) -> 0
A11: ='明细表I6-2'!X13 -> 0 | B11: =SUMIF('明细表I6-2'!$X:$X,$A11,'明细表I6-2'!$Q:$Q) -> 0 | C11: =SUMIF('明细表I6-2'!$X:$X,$A11,'明细表I6-2'!$W:$W) -> 0
A12: ='明细表I6-2'!X14 -> 0 | B12: =SUMIF('明细表I6-2'!$X:$X,$A12,'明细表I6-2'!$Q:$Q) -> 0 | C12: =SUMIF('明细表I6-2'!$X:$X,$A12,'明细表I6-2'!$W:$W) -> 0
A13: ='明细表I6-2'!X15 -> 0 | B13: =SUMIF('明细表I6-2'!$X:$X,$A13,'明细表I6-2'!$Q:$Q) -> 0 | C13: =SUMIF('明细表I6-2'!$X:$X,$A13,'明细表I6-2'!$W:$W) -> 0
A14: ='明细表I6-2'!X16 -> 0 | B14: =SUMIF('明细表I6-2'!$X:$X,$A14,'明细表I6-2'!$Q:$Q) -> 0 | C14: =SUMIF('明细表I6-2'!$X:$X,$A14,'明细表I6-2'!$W:$W) -> 0
A15: ='明细表I6-2'!X17 -> 0 | B15: =SUMIF('明细表I6-2'!$X:$X,$A15,'明细表I6-2'!$Q:$Q) -> 0 | C15: =SUMIF('明细表I6-2'!$X:$X,$A15,'明细表I6-2'!$W:$W) -> 0
A16: 合 计 | B16: =SUM(B7:B15) -> 0 | C16: =SUM(C7:C15) -> 0
A17: 【增减变动因素可根据实际情况自行添加】
A18: 【提示：根据财会〔2019〕6号，“研发费用”项目，反映企业进行研究与开发过程中发生的费用化支出，以及计入管理费用的自行开发无形资产的摊销。】
A19: 【提示：注意与附注“研发支出”对应。】

Sheet 附注披露（国有企业）
A1: 致同会计师事务所
A2: 研发费用附注披露表（国有企业）
A3: =底稿目录!A2 -> 被审计单位： | C3: =底稿目录!A4 -> 编制人： | D3: =底稿目录!A5 -> 编制日期：
A4: =底稿目录!A3 -> 会计期间：202X年度 | C4: =底稿目录!A6 -> 复核人： | D4: =底稿目录!A7 -> 复核日期：
A5: 研发费用（按费用性质列示）
A6: 项目 | B6: 本期发生额 | C6: 上期发生额
A7: ='明细表I6-2'!X9 -> 0 | B7: =SUMIF('明细表I6-2'!$X:$X,$A7,'明细表I6-2'!$Q:$Q) -> 0 | C7: =SUMIF('明细表I6-2'!$X:$X,$A7,'明细表I6-2'!$W:$W) -> 0
A8: ='明细表I6-2'!X10 -> 0 | B8: =SUMIF('明细表I6-2'!$X:$X,$A8,'明细表I6-2'!$Q:$Q) -> 0 | C8: =SUMIF('明细表I6-2'!$X:$X,$A8,'明细表I6-2'!$W:$W) -> 0
A9: ='明细表I6-2'!X11 -> 0 | B9: =SUMIF('明细表I6-2'!$X:$X,$A9,'明细表I6-2'!$Q:$Q) -> 0 | C9: =SUMIF('明细表I6-2'!$X:$X,$A9,'明细表I6-2'!$W:$W) -> 0
A10: ='明细表I6-2'!X12 -> 0 | B10: =SUMIF('明细表I6-2'!$X:$X,$A10,'明细表I6-2'!$Q:$Q) -> 0 | C10: =SUMIF('明细表I6-2'!$X:$X,$A10,'明细表I6-2'!$W:$W) -> 0
A11: ='明细表I6-2'!X13 -> 0 | B11: =SUMIF('明细表I6-2'!$X:$X,$A11,'明细表I6-2'!$Q:$Q) -> 0 | C11: =SUMIF('明细表I6-2'!$X:$X,$A11,'明细表I6-2'!$W:$W) -> 0
A12: ='明细表I6-2'!X14 -> 0 | B12: =SUMIF('明细表I6-2'!$X:$X,$A12,'明细表I6-2'!$Q:$Q) -> 0 | C12: =SUMIF('明细表I6-2'!$X:$X,$A12,'明细表I6-2'!$W:$W) -> 0
A13: ='明细表I6-2'!X15 -> 0 | B13: =SUMIF('明细表I6-2'!$X:$X,$A13,'明细表I6-2'!$Q:$Q) -> 0 | C13: =SUMIF('明细表I6-2'!$X:$X,$A13,'明细表I6-2'!$W:$W) -> 0
A14: ='明细表I6-2'!X16 -> 0 | B14: =SUMIF('明细表I6-2'!$X:$X,$A14,'明细表I6-2'!$Q:$Q) -> 0 | C14: =SUMIF('明细表I6-2'!$X:$X,$A14,'明细表I6-2'!$W:$W) -> 0
A15: ='明细表I6-2'!X17 -> 0 | B15: =SUMIF('明细表I6-2'!$X:$X,$A15,'明细表I6-2'!$Q:$Q) -> 0 | C15: =SUMIF('明细表I6-2'!$X:$X,$A15,'明细表I6-2'!$W:$W) -> 0
A16: 合 计 | B16: =SUM(B7:B15) -> 0 | C16: =SUM(C7:C15) -> 0

Sheet 审定表I6-1
A1: 致同会计师事务所
A2: 研发费用审定表
A3: =底稿目录!A2 -> 被审计单位： | E3: =底稿目录!A4 -> 编制人： | G3: =底稿目录!A5 -> 编制日期： | J3: 索引号： | K3: =底稿目录!D5 -> I6-1
A4: =底稿目录!A3 -> 会计期间：202X年度 | E4: =底稿目录!A6 -> 复核人： | G4: =底稿目录!A7 -> 复核日期： | J4: 页次：
A5: 类别 | B5: 上期数 | F5: 本期数 | J5: 本期审定数与上期 审定数的比较
B6: 未审数 | C6: 账项调整 | D6: 重分类调整 | E6: 审定数 | F6: 未审数 | G6: 账项调整 | H6: 重分类调整 | I6: 审定数 | J6: 变动额 | K6: 变动率
A7: ='明细表I6-2'!A9 -> 人工费 | B7: ='明细表I6-2'!T9 -> 0 | C7: ='明细表I6-2'!U9 -> 0 | D7: ='明细表I6-2'!V9 -> 0 | E7: =B7+C7+D7 -> 0 | F7: ='明细表I6-2'!N9 -> 0 | G7: ='明细表I6-2'!O9 -> 0 | H7: ='明细表I6-2'!P9 -> 0 | I7: =F7+G7+H7 -> 0 | J7: =I7-E7 -> 0 | K7: =IF(AND(E7=0,J7=0),0,IF(AND(E7=0,J7>0),1,J7/E7)) -> 0
A8: ='明细表I6-2'!A10 -> 材料费 | B8: ='明细表I6-2'!T10 -> 0 | C8: ='明细表I6-2'!U10 -> 0 | D8: ='明细表I6-2'!V10 -> 0 | E8: =B8+C8+D8 -> 0 | F8: ='明细表I6-2'!N10 -> 0 | G8: ='明细表I6-2'!O10 -> 0 | H8: ='明细表I6-2'!P10 -> 0 | I8: =F8+G8+H8 -> 0 | J8: =I8-E8 -> 0 | K8: =IF(AND(E8=0,J8=0),0,IF(AND(E8=0,J8>0),1,J8/E8)) -> 0
A9: ='明细表I6-2'!A11 -> 制造费用分摊 | B9: ='明细表I6-2'!T11 -> 0 | C9: ='明细表I6-2'!U11 -> 0 | D9: ='明细表I6-2'!V11 -> 0 | E9: =B9+C9+D9 -> 0 | F9: ='明细表I6-2'!N11 -> 0 | G9: ='明细表I6-2'!O11 -> 0 | H9: ='明细表I6-2'!P11 -> 0 | I9: =F9+G9+H9 -> 0 | J9: =I9-E9 -> 0 | K9: =IF(AND(E9=0,J9=0),0,IF(AND(E9=0,J9>0),1,J9/E9)) -> 0
A10: ='明细表I6-2'!A12 -> 无形资产摊销 | B10: ='明细表I6-2'!T12 -> 0 | C10: ='明细表I6-2'!U12 -> 0 | D10: ='明细表I6-2'!V12 -> 0 | E10: =B10+C10+D10 -> 0 | F10: ='明细表I6-2'!N12 -> 0 | G10: ='明细表I6-2'!O12 -> 0 | H10: ='明细表I6-2'!P12 -> 0 | I10: =F10+G10+H10 -> 0 | J10: =I10-E10 -> 0 | K10: =IF(AND(E10=0,J10=0),0,IF(AND(E10=0,J10>0),1,J10/E10)) -> 0
A11: ='明细表I6-2'!A13 -> 0 | B11: ='明细表I6-2'!T13 -> 0 | C11: ='明细表I6-2'!U13 -> 0 | D11: ='明细表I6-2'!V13 -> 0 | E11: =B11+C11+D11 -> 0 | F11: ='明细表I6-2'!N13 -> 0 | G11: ='明细表I6-2'!O13 -> 0 | H11: ='明细表I6-2'!P13 -> 0 | I11: =F11+G11+H11 -> 0 | J11: =I11-E11 -> 0 | K11: =IF(AND(E11=0,J11=0),0,IF(AND(E11=0,J11>0),1,J11/E11)) -> 0
A12: ='明细表I6-2'!A14 -> 0 | B12: ='明细表I6-2'!T14 -> 0 | C12: ='明细表I6-2'!U14 -> 0 | D12: ='明细表I6-2'!V14 -> 0 | E12: =B12+C12+D12 -> 0 | F12: ='明细表I6-2'!N14 -> 0 | G12: ='明细表I6-2'!O14 -> 0 | H12: ='明细表I6-2'!P14 -> 0 | I12: =F12+G12+H12 -> 0 | J12: =I12-E12 -> 0 | K12: =IF(AND(E12=0,J12=0),0,IF(AND(E12=0,J12>0),1,J12/E12)) -> 0
A13: ='明细表I6-2'!A15 -> 0 | B13: ='明细表I6-2'!T15 -> 0 | C13: ='明细表I6-2'!U15 -> 0 | D13: ='明细表I6-2'!V15 -> 0 | E13: =B13+C13+D13 -> 0 | F13: ='明细表I6-2'!N15 -> 0 | G13: ='明细表I6-2'!O15 -> 0 | H13: ='明细表I6-2'!P15 -> 0 | I13: =F13+G13+H13 -> 0 | J13: =I13-E13 -> 0 | K13: =IF(AND(E13=0,J13=0),0,IF(AND(E13=0,J13>0),1,J13/E13)) -> 0
A14: ='明细表I6-2'!A16 -> 0 | B14: ='明细表I6-2'!T16 -> 0 | C14: ='明细表I6-2'!U16 -> 0 | D14: ='明细表I6-2'!V16 -> 0 | E14: =B14+C14+D14 -> 0 | F14: ='明细表I6-2'!N16 -> 0 | G14: ='明细表I6-2'!O16 -> 0 | H14: ='明细表I6-2'!P16 -> 0 | I14: =F14+G14+H14 -> 0 | J14: =I14-E14 -> 0 | K14: =IF(AND(E14=0,J14=0),0,IF(AND(E14=0,J14>0),1,J14/E14)) -> 0
A15: ='明细表I6-2'!A17 -> 0 | B15: ='明细表I6-2'!T17 -> 0 | C15: ='明细表I6-2'!U17 -> 0 | D15: ='明细表I6-2'!V17 -> 0 | E15: =B15+C15+D15 -> 0 | F15: ='明细表I6-2'!N17 -> 0 | G15: ='明细表I6-2'!O17 -> 0 | H15: ='明细表I6-2'!P17 -> 0 | I15: =F15+G15+H15 -> 0 | J15: =I15-E15 -> 0 | K15: =IF(AND(E15=0,J15=0),0,IF(AND(E15=0,J15>0),1,J15/E15)) -> 0
A16: ='明细表I6-2'!A18 -> 0 | B16: ='明细表I6-2'!T18 -> 0 | C16: ='明细表I6-2'!U18 -> 0 | D16: ='明细表I6-2'!V18 -> 0 | E16: =B16+C16+D16 -> 0 | F16: ='明细表I6-2'!N18 -> 0 | G16: ='明细表I6-2'!O18 -> 0 | H16: ='明细表I6-2'!P18 -> 0 | I16: =F16+G16+H16 -> 0 | J16: =I16-E16 -> 0 | K16: =IF(AND(E16=0,J16=0),0,IF(AND(E16=0,J16>0),1,J16/E16)) -> 0
A17: 合计 | B17: =SUM(B7:B16) -> 0 | C17: =SUM(C7:C16) -> 0 | D17: =SUM(D7:D16) -> 0 | E17: =SUM(E7:E16) -> 0 | F17: =SUM(F7:F16) -> 0 | G17: =SUM(G7:G16) -> 0 | H17: =SUM(H7:H16) -> 0 | I17: =SUM(I7:I16) -> 0 | J17: =I17-E17 -> 0 | K17: =IF(AND(E17=0,J17=0),0,IF(AND(E17=0,J17>0),1,J17/E17)) -> 0
A18: TB数据：
A19: 差异 | B19: =B17-B18 -> 0 | C19: =C17-C18 -> 0 | D19: =D17-D18 -> 0 | E19: =E17-E18 -> 0 | F19: =F17-F18 -> 0 | G19: =G17-G18 -> 0 | H19: =H17-H18 -> 0 | I19: =I17-I18 -> 0 | ... K19: =K17-K18 -> 0
A20: 1.审计说明
A21: （1）研发费用本期较上期增加（负数为减少）：
A22: 主要原因（比例超过30%的）：
A23: （2）重大事项说明。
A25: 2.审计结论：
A27: 注：具体披露要求可参考《企业会计准则30号-财务报表列报》和证监会的有关规定。

Sheet 明细表I6-2
A1: 致同会计师事务所
A2: 研发费用明细表
A3: =底稿目录!A2 -> 被审计单位： | H3: =底稿目录!A4 -> 编制人： | O3: =底稿目录!A5 -> 编制日期： | Y3: 索引号： | Z3: =底稿目录!D8 -> I6-2
A4: =底稿目录!A3 -> 会计期间：202X年度 | H4: =底稿目录!A6 -> 复核人： | O4: =底稿目录!A7 -> 复核日期： | Y4: 页次：
A5: 一、审计目标:
A6: 1.所有应当记录的研发费用均已记录，所有应当包括在财务报表中的相关披露均已包括； | J6: 2.与研发费用有关的金额及其他数据已恰当记录，相关披露已得到恰当计量和描述。
A7: 二、审计过程：
A8: 类别 | B8: 1月 | C8: 2月 | D8: 3月 | E8: 4月 | F8: 5月 | G8: 6月 | H8: 7月 | I8: 8月 | J8: 9月 | K8: 10月 | L8: 11月 | M8: 12月 | N8: 本期未审合计 | O8: 账项调整 | P8: 重分类调整 | Q8: 本期审定数 | R8: 各项目占比 | S8: 与相关科目勾稽 | T8: 上期未审数 | U8: 上期账项调整 | V8: 上期重分类调整 | W8: 上期审定数 | X8: 个别报表下的重分类 | Y8: 合并报表下的重分类 | Z8: 备注
A9: 人工费 | N9: =SUM(B9:M9) -> 0 | Q9: =N9+O9+P9 -> 0 | R9: =IF(Q9=0,0,Q9/$Q$19) -> 0 | S9: 开发支出等 | W9: =T9+U9+V9 -> 0
A10: 材料费 | N10: =SUM(B10:M10) -> 0 | Q10: =N10+O10+P10 -> 0 | R10: =IF(Q10=0,0,Q10/$Q$19) -> 0 | W10: =T10+U10+V10 -> 0
A11: 制造费用分摊 | N11: =SUM(B11:M11) -> 0 | Q11: =N11+O11+P11 -> 0 | R11: =IF(Q11=0,0,Q11/$Q$19) -> 0 | W11: =T11+U11+V11 -> 0
A12: 无形资产摊销 | N12: =SUM(B12:M12) -> 0 | Q12: =N12+O12+P12 -> 0 | R12: =IF(Q12=0,0,Q12/$Q$19) -> 0 | W12: =T12+U12+V12 -> 0
N13: =SUM(B13:M13) -> 0 | Q13: =N13+O13+P13 -> 0 | R13: =IF(Q13=0,0,Q13/$Q$19) -> 0 | W13: =T13+U13+V13 -> 0
N14: =SUM(B14:M14) -> 0 | Q14: =N14+O14+P14 -> 0 | R14: =IF(Q14=0,0,Q14/$Q$19) -> 0 | W14: =T14+U14+V14 -> 0
N15: =SUM(B15:M15) -> 0 | Q15: =N15+O15+P15 -> 0 | R15: =IF(Q15=0,0,Q15/$Q$19) -> 0 | W15: =T15+U15+V15 -> 0
N16: =SUM(B16:M16) -> 0 | Q16: =N16+O16+P16 -> 0 | R16: =IF(Q16=0,0,Q16/$Q$19) -> 0 | W16: =T16+U16+V16 -> 0
N17: =SUM(B17:M17) -> 0 | Q17: =N17+O17+P17 -> 0 | R17: =IF(Q17=0,0,Q17/$Q$19) -> 0 | W17: =T17+U17+V17 -> 0
N18: =SUM(B18:M18) -> 0 | Q18: =N18+O18+P18 -> 0 | R18: =IF(Q18=0,0,Q18/$Q$19) -> 0 | W18: =T18+U18+V18 -> 0
A19: 合计 | B19: =SUM(B9:B18) -> 0 | C19: =SUM(C9:C18) -> 0 | D19: =SUM(D9:D18) -> 0 | E19: =SUM(E9:E18) -> 0 | F19: =SUM(F9:F18) -> 0 | G19: =SUM(G9:G18) -> 0 | H19: =SUM(H9:H18) -> 0 | I19: =SUM(I9:I18) -> 0 | ... Y19: =SUM(Y9:Y18) -> 0
A20: 各月比例 | B20: =IF($N$19=0,0,B19/$N$19) -> 0 | C20: =IF($N$19=0,0,C19/$N$19) -> 0 | D20: =IF($N$19=0,0,D19/$N$19) -> 0 | E20: =IF($N$19=0,0,E19/$N$19) -> 0 | F20: =IF($N$19=0,0,F19/$N$19) -> 0 | G20: =IF($N$19=0,0,G19/$N$19) -> 0 | H20: =IF($N$19=0,0,H19/$N$19) -> 0 | I20: =IF($N$19=0,0,I19/$N$19) -> 0 | ... N20: =IF($N$19=0,0,N19/$N$19) -> 0
A21: 三、审计说明：
A22: 注：以下底稿模板在开发支出底稿中，如果被审计单位既有开发支出又有研发费用可在开发支出中综合完成研发相关的主要底稿，研发费用交叉索引；如果被审计单位研发活动全部计入研发费用可将该部分底稿从开发支出底稿模板中移至研发费用中完成。
A23: 1.分析复核会计政策、会计估计合理性、一贯性，关注被审计单位是否利用会计政策和会计估计及其变更操纵利润。详见<会计政策检查I2-4>
A24: 2.分析研发费用变动情况、与收入占比、人均经费、与预算比较等。详见<实质性分析I2-5>
A25: 2.检查相关支持性文件，判断研发项目资本化时点的准确性。详见<研发项目资本化时点判断I2-6>
A26: 3.获取或编制研发项目支出构成明细表，详见<研发项目构成明细表I2-7>
A27: 3.检查研发材料投入，详见<研发材料投入检查表I2-8>
A28: 4.检查研发人员认定，详见<研发人员认定检查表I2-9>
A29: 5.检查研发工时投入，详见<研发人员工时检查表I2-10>
A30: 6.检查委外研发情况，详见<委外研发检查表I2-11>
A31: ……
A33: 四、审计结论：
... A44: 3、备注栏可填写项目内容及异常情况说明。

Sheet 调整分录汇总I6-3
A1: 致同会计师事务所
A2: 研发费用调整分录汇总表
A3: =底稿目录!A2 -> 被审计单位： | D3: =底稿目录!A4 -> 编制人： | F3: =底稿目录!A5 -> 编制日期： | I3: 索引号： | J3: =底稿目录!D9 -> I6-3
A4: =底稿目录!A3 -> 会计期间：202X年度 | D4: =底稿目录!A6 -> 复核人： | F4: =底稿目录!A7 -> 复核日期： | I4: 页次：
A5: 调整事项说明 | B5: 类别（报表调整/账项调整/其他） | C5: 报表项目 | D5: 科目名称 | E5: 附注项目 | F5: …… | G5: 借方调整金额 | H5: 贷方调整金额 | I5: 索引 | J5: 备注
A21: 【注：本底稿适用于调整分录较多、较复杂的项目，且仅列示与本报表项目相关的审计调整。项目组可根据项目实际情况选择是否使用该底稿。】

Sheet 其他针对性检查表I6-4
A1: 致同会计师事务所
A2: 研发费用针对性检查表
A3: =底稿目录!A2 -> 被审计单位： | D3: =底稿目录!A4 -> 编制人： | G3: =底稿目录!A5 -> 编制日期： | O3: 索引号： | P3: =底稿目录!D18 -> I6-4
A4: =底稿目录!A3 -> 会计期间：202X年度 | D4: =底稿目录!A6 -> 复核人： | G4: =底稿目录!A7 -> 复核日期： | O4: 页 次：
A5: 一、测试目标：
A6: 1.利润表中记录的研发费用已发生，且与被审计单位有关，已记录于恰当的账户。
A7: 2.与研发费用有关的金额及其他数据已恰当记录，相关披露已得到恰当计量和描述。
A8: 二、样本选取标准与规模：
A9: 测试总体： | B9: 如借方发生额所有凭证共XX笔金额XX | G9: 特定样本： | H9: XX金额以上（大额）、关联方/关联交易形成的款项、XX异常款项全部测试，共XX笔；
A10: 抽样总体： | B10: 测试总体扣除特定样本以外的样本，共XX笔、金额XX | G10: 确定的抽样样本量： | H10: 抽取XX笔（如果使用了样本计算器计算样本量，样本量计算过程见<XX>底稿）
A11: 抽样方法： | B11: 随机选样/系统选样/货币单元抽样/随意选样（非统计抽样适用） | G11: 抽样过程： | H11: 使用IDEA（XX抽样工具）选择XX数量、金额XX的样本进行测试，抽样工具中的样本选择过程和结果见<XX>底稿
A12: 三、测试：
A13: 测试内容说明：1.原始凭证是否齐全； 2.记账凭证与原始凭证是否相符；3.账务处理是否正确；4.是否记录于恰当的会计期间；5.……
A14: 1.本期其他费用发生额检查
A15: 记账凭证 | H15: 支持性文件 | I15: 核对内容 | N15: 索引号 | O15: 是否异常 | P15: 备注说明
A16: 研发项目明细 | B16: 日期 | C16: 凭证编号 | D16: 业务内容 | E16: 对方科目 | F16: 对方明细科目 | G16: 借方金额 | I16: 1 | J16: 2 | K16: 3 | L16: 4 | M16: 5
A31: 合计 | G31: =SUM(G17:G30) -> 0
A32: 本期发生额 | G32: ='明细表I6-2'!Q19 -> 0
A33: 检查比例 | G33: =G31/G32 -> #DIV/0!
A34: 四、审计说明：
A37: 五、审计结论：

Sheet 截止性测试（账到单据）I6-5
A1: 致同会计师事务所
A2: 研发费用截止测试
A3: =底稿目录!A2 -> 被审计单位： | D3: =底稿目录!A4 -> 编制人： | F3: =底稿目录!A5 -> 编制日期： | I3: 索引号： | J3: =底稿目录!D19 -> I6-5
A4: =底稿目录!A3 -> 会计期间：202X年度 | D4: =底稿目录!A6 -> 复核人： | F4: =底稿目录!A7 -> 复核日期： | I4: 页 次：
A5: 一、审计目标：
A6: 确认研发费用已记录于正确的会计期间。
A7: 二、样本选取标准与规模：
A8: 1.获取资产负债表日前（______）天、后（______）天，且金额大于______元的研发费用记账凭证与支出凭单等核对确认研发费用是否记入了恰当的期间；
A9: 2.对于首次承接的客户，执行前期期末的截止性测试。（适用于首次承接）
A10: 提示：如果存在跨期舞弊风险或者所检查样本中发现有跨期的，应扩大测试期间和样本，甚至可以考虑将截止测试期间延长至审计报告日。同时考虑是否存在内控缺陷。
A11: 三、测试：
A12: 序号 | B12: 记账凭证 | F12: 支出凭单 | I12: 是否跨期 | J12: 跨期金额
B13: 日期 | C13: 编号 | D13: 金额 | E13: 摘要 | F13: 凭单编号 | G13: 凭单日期 | H13: 金额
A14: 1
A15: 2
A16: 3
A17: 4
A18: 5
A19: 6
A20: 7
A21: 8
A22: 9
A23: 10
A24: ……
A25: ——————截止日期：20XX年12月31日——————
A26: 1
A27: 2
A28: 3
A29: 4
A30: 5
A31: 6
A32: 7
A33: 8
A34: 9
A35: 10
A36: ……
A37: 四、审计说明：
A40: 五、审计结论
A43: 提示：如果存在跨期舞弊风险或者所检查样本中发现有跨期的，应扩大测试期间和样本，甚至可以考虑将截止测试期间延长至审计报告日。同时考虑是否存在内控缺陷。

Sheet 截止性测试（单据到账）I6-6
A1: 致同会计师事务所
A2: 研发费用截止测试
A3: =底稿目录!A2 -> 被审计单位： | D3: =底稿目录!A4 -> 编制人： | F3: =底稿目录!A5 -> 编制日期： | I3: 索引号： | J3: =底稿目录!D20 -> I6-6
A4: =底稿目录!A3 -> 会计期间：202X年度 | D4: =底稿目录!A6 -> 复核人： | F4: =底稿目录!A7 -> 复核日期： | I4: 页 次：
A5: 一、审计目标：
A6: 确认研发费用已记录于正确的会计期间。
A7: 二、样本选取标准与规模：
A8: 1.抽取资产负债表日前（______）天、后（______）天，且金额大于______元的支出凭单等与研发费用记账凭证核对确认研发费用是否记入了恰当的期间；
A9: 2.对于首次承接的客户，执行前期期末的截止性测试。（适用于首次承接）
A10: 提示：如果存在跨期舞弊风险或者所检查样本中发现有跨期的，应扩大测试期间和样本，甚至可以考虑将截止测试期间延长至审计报告日。同时考虑是否存在内控缺陷。
A11: 三、测试：
A12: 序号 | B12: 支出凭单 | E12: 记账凭证 | I12: 是否跨期 | J12: 跨期金额
B13: 凭单编号 | C13: 凭单日期 | D13: 金额 | E13: 日期 | F13: 凭证号 | G13: 金额 | H13: 摘要
A14: 1
A15: 2
A16: 3
A17: 4
A18: 5
A19: 6
A20: 7
A21: 8
A22: 9
A23: 10
A24: ——————截止日期：20XX年12月31日——————
A25: 1
A26: 2
A27: 3
A28: 4
A29: 5
A30: 6
A31: 7
A32: 8
A33: 9
A34: 10
A35: 四、审计说明：
A38: 五、审计结论
A41: 提示：如果存在跨期舞弊风险或者所检查样本中发现有跨期的，应扩大测试期间和样本，甚至可以考虑将截止测试期间延长至审计报告日。同时考虑是否存在内控缺陷。

Sheet GT_Custom
A1: C1 | B1: Custom 1
A2: C2 | B2: Custom 2
A3: C3 | B3: Custom 3
A4: C4 | B4: Custom 4
A5: C5 | B5: Custom 5
A6: C6 | B6: Custom 6
A7: C7 | B7: Custom 7
A8: C8 | B8: Custom 8
