Workbook
Name AS2DocOpenMode: "AS2DocumentEdit"

Sheet 底稿目录
A1: 底稿开列时，可先在以下单元格填写有关内容，以便其他底稿引用有关数据：
A2: 被审计单位：
A3: 会计期间：202X年度 | D3: 序号 | E3: 内容 | F3: 索引号 | G3: 备注
A4: 编制人： | D4: 1 | E4: 实质性程序表 | F4: K10A
A5: 编制日期： | D5: 2 | E5: 审定表 | F5: K10-1
A6: 复核人： | D6: 3 | E6: 附注披露信息（上市公司） | H6: 无需打印
A7: 复核日期： | D7: 4 | E7: 附注披露信息（国企） | H7: 无需打印
D8: 5 | E8: 明细表 | F8: K10-2
A9: 关于工作底稿与审计程序索引号对应的说明 | D9: 6 | E9: 调整分录汇总 | F9: K10-3
A10: 1.编制的审计工作底稿应与审计程序对应。审计项目组应根据被审计单位实际情况和风险评估情况在实质性程序表中裁剪、修改或增加审计程序，根据实际执行的审计程序完成相应审计工作底稿，编制的工作底稿中应按自然顺序依次编制索引号，并通过唯一的索引号将与实质性程序表中的程序对应关联（即将工作底稿的索引号填入实质性程序表中的底稿索引号列）。 | D10: 7 | E10: 政府补助核对表 | F10: K10-4
D11: 8 | E11: 应收政府补助检查表 | F11: K10-5
D12: 9 | E12: 其他收益检查表 | F12: K10-6
A14: 2.获取的支持性证据应与审计底稿或程序对应。审计项目组在完成底稿时获取的支持性证据应根据底稿索引号编制下一级按自然顺序排序的索引号（如D1-2-1、D1-2-2、……），并在底稿中说明引用的支持性证据、关联索引号。
A17: 3.工作底稿索引号的编码规则：实质性程序索引号按循环从“D”到“N”,循环内账户以顺序号排列，模板中底稿索引号按账户顺序+自然数顺序（即模板中索引号按二级自然顺序排列，如D1-1、D1-2、D1-3、……D1-N）。

Sheet 实质性程序表K10A
A1: 致同会计师事务所
A2: 其他收益实质性程序表
A3: =底稿目录!A2 -> 被审计单位： | C3: =底稿目录!A4 -> 编制人： | E3: =底稿目录!A5 -> 编制日期： | H3: 索引号： | I3: =底稿目录!F4 -> K10A
A4: =底稿目录!A3 -> 会计期间：202X年度 | C4: =底稿目录!A6 -> 复核人： | E4: =底稿目录!A7 -> 复核日期： | H4: 页 次：
A5: 一、本账户涉及的科目
A6: 其他收益
A7: 二、审计目标与认定的对应关系
A8: 审计目标 | G8: 财务报表的认定
A9: A. 利润表中记录的其他收益已发生，且与被审计单位有关，已记录于恰当的账户 | G9: 发生
A10: B. 所有应当记录的其他收益均已记录，所有应当包括在财务报表中的相关披露均已包括 | G10: 完整性
A11: C. 与其他收益有关的金额及其他数据已恰当记录，相关披露已得到恰当计量和描述 | G11: 准确性
A12: D. 其他收益已记录于正确的会计期间 | G12: 截止
A13: E. 已被恰当地汇总或分解且表述清楚，相关披露在按照企业会计准则的编制基础下是相关的、可理解的 | G13: 列报
A14: 三、计划实施的实质性程序
A15: 序号 | B15: 审计程序 | C15: 程序分类 | D15: 审计程序 | I15: 底稿索引号
D16: 发生 | E16: 完整性 | F16: 准确性 | G16: 截止 | H16: 列报 | J16: 根据被审计单位实际情况和风险评估情况裁剪、修改或增加审计程序
A17: 1 | B17: 获取或编制其他收益明细表，复核加计是否正确，并与总账数和明细账合计数核对是否相符，编制审定表；了解其他收益核算的内容，判断其分类为其他收益是否恰当。 | C17: 常规★ | D17: √ | E17: √ | F17: √ | I17: K10-1 /K10-2
A18: 2 | B18: 在使用手工编制、自定义信息报告、系统生成的非固定格式报告等由被审计单位生成的信息时，测试有关信息准确性和完整性，并考虑针对编制和维护由被审计单位生成的信息的相关控制实施控制测试，以评价该信息是否能够为实现审计目的提供基础。 | C18: 常规★ | E18: √ | F18: √ | I18: T1 | J18: 可参见《审计手册》4.2.6，由被审计单位生成的信息可能是由系统生成的、或手工编制的、或二者兼而有之的方式生成的。例如，由被审计单位生成的信息可能包括： • 不涉及自定义的、由系统生成的报告（如，固定格式报告）； • 可能通过人工自定义的、由系统生成的报告，例如，（计算机）查询信息或特别定制的报告； • 手工编制的信息，例如，汇总信息的电子表格或用以支持分配、计算以及调节的电子表格； • 其他系统生成或手工编制的信息，例如，由被审计单位编制的客户发票； • 通过影印、拍摄、扫描或其他方式转换成电子形式的文件记录。
A19: 3 | B19: 对上期发生额的审计：结合本期审计确定其他收益的上期金额的截止是否恰当。（适用于首次承接） | C19: 备选 | G19: √ | J19: 由被审计单位生成的信息不包括： • 总分类账或明细分类账、试算平衡表、或经审计的财务报表； • 第三方（除了服务机构）的报表或报告，例如，原始银行对账单，或函证的回函； • 外部数据（例如，第三方发布的数据，如，定价来源）。
A20: 4 | B20: 关注会计政策、会计估计合理性、一贯性。关注其是否利用会计政策和会计估计及其变更操纵利润。 | C20: 常规★ | D20: √ | E20: √ | F20: √ | I20: K10-1 /K10-2
A21: 5 | B21: 检查政府补助相关原始凭证，确定业务的真实性、入账金额及会计处理是否正确： （1）获取并检查政府补助文件等支持性文件，判断政府补助是否与日常活动相关、款项是否收到、分类是否正确、会计处理是否适当，同类政府补助是否采用一样的处理方法，如都采用总额法或都采用净额法； （2）如存在验收条件的，获取验收报告等相关材料，检查审核资金使用范围是否符合相关文件规定，分析公司是否满足政府补助的确认条件； （3）将政府补助金额与递延收益、营业外收入、其他应收款等科目进行核对。 | C21: 常规★ | D21: √ | F21: √ | G21: √ | I21: K10-4 /K10-6
A22: 6 | B22: 对重大、异常政府补助： （1）核对补助事项、查验资金来源，按照政府补助的定义认真核对公司认定的政府补助事项、并对补助资产的来源单位及其与政府文件规定的一致性进行查验； （2）关注政府补助的发放主体是否具备相应的权力和资质、补助文件中索引的政策依据是否适当，被审计单位申请政府补助的流程是否合法合规、是否已经履行完毕补助文件中的要求、实际收取资金前是否需要政府部门的实质性审核、历史上同类政府补助的实际发放情况； （3）政府补助文件规定不明确或存在明显不合理迹象时，与相关政府部门沟通或执行函证程序，或在必要时聘请律师或其他外部专家提供意见。 | C22: 备选 | D22: √ | F22: √ | G22: √
A23: 7 | B23: 对于在资产负债表日按照应收金额确认的政府补助，结合其他应收款审计： （1）查验正式发布的财政资金管理办法中的（定额）测算公式，或检查政府补助批文是否标明确切金额，分析政府补助金额是否存在重大不确定性； （2）检查政府部门正式发布的财政扶持项目及其财政资金管理办法的适用范围，是否是普惠性的（任何符合规定条件的企业均可申请），而不是专门针对特定企业制定的； （3）检查补助款批文中承诺的拨付期限，以及款项拨付对应的财政预算，分析政府补助在规定期限内的可收回性； （4）必要时结合其他应收款函证政府补助金额。 | C23: 备选 | D23: √ | F23: √ | G23: √ | I23: K10-5
A24: 8 | B24: 检查以单项或多项非金融资产清偿债务的原始凭证，相应的债务重组会计处理是否正确，是否将所清偿债务账面价值与转让资产账面价值之间的差额计入其他收益 | C24: 备选 | D24: √ | E24: √ | F24: √ | I24: S5
A25: 11 | B25: 根据评估的舞弊风险等因素增加的审计程序。 | C25: IPO/上市/新三板/重组/舞弊应对
A26: 12 | B26: 检查其他收益是否已按企业会计准则或其他适用的规定在财务报表中做出恰当列报和披露。 | C26: 常规★ | H26: √ | I26: A1-1/A1-15 /A1-16

Sheet 审定表K10-1
A1: 致同会计师事务所
A2: 其他收益审定表
A3: =底稿目录!A2 -> 被审计单位： | C3: =底稿目录!A4 -> 编制人： | H3: =底稿目录!A5 -> 编制日期： | J3: 索引号： | K3: =底稿目录!F5 -> K10-1
A4: =底稿目录!A3 -> 会计期间：202X年度 | C4: =底稿目录!A6 -> 复核人： | H4: =底稿目录!A7 -> 复核日期： | J4: 页 次：
A5: 项目（产生其他收益的来源） | B5: 本期未审数 | C5: 审计调整 | D5: 重分类调整 | E5: 本期审定数 | F5: 索引号 | G5: 上期未审数 | H5: 审计调整 | I5: 重分类调整 | J5: 上期审定数 | K5: 备注
A6: ='明细表K10-2'!A11 -> 总额法下与日常活动相关的政府补助 | B6: ='明细表K10-2'!D11 -> 0 | C6: ='明细表K10-2'!E11 -> 0 | D6: ='明细表K10-2'!F11 -> 0 | E6: =B6+C6+D6 -> 0 | G6: ='明细表K10-2'!H11 -> 0 | H6: ='明细表K10-2'!I11 -> 0 | I6: ='明细表K10-2'!J11 -> 0 | J6: =G6+H6+I6 -> 0
A7: ='明细表K10-2'!A12 -> 增值税进项税额加计抵减（实际缴纳时） | B7: ='明细表K10-2'!D12 -> 0 | C7: ='明细表K10-2'!E12 -> 0 | D7: ='明细表K10-2'!F12 -> 0 | E7: =B7+C7+D7 -> 0 | G7: ='明细表K10-2'!H12 -> 0 | H7: ='明细表K10-2'!I12 -> 0 | I7: ='明细表K10-2'!J12 -> 0 | J7: =G7+H7+I7 -> 0
A8: ='明细表K10-2'!A13 -> 增值税直接减免 | B8: ='明细表K10-2'!D13 -> 0 | C8: ='明细表K10-2'!E13 -> 0 | D8: ='明细表K10-2'!F13 -> 0 | E8: =B8+C8+D8 -> 0 | G8: ='明细表K10-2'!H13 -> 0 | H8: ='明细表K10-2'!I13 -> 0 | I8: ='明细表K10-2'!J13 -> 0 | J8: =G8+H8+I8 -> 0
A9: ='明细表K10-2'!A14 -> 个人所得税扣缴税款手续费返还 | B9: ='明细表K10-2'!D14 -> 0 | C9: ='明细表K10-2'!E14 -> 0 | D9: ='明细表K10-2'!F14 -> 0 | E9: =B9+C9+D9 -> 0 | G9: ='明细表K10-2'!H14 -> 0 | H9: ='明细表K10-2'!I14 -> 0 | I9: ='明细表K10-2'!J14 -> 0 | J9: =G9+H9+I9 -> 0
A10: ='明细表K10-2'!A15 -> 债务人以非金融资产清偿债务损益 | B10: ='明细表K10-2'!D15 -> 0 | C10: ='明细表K10-2'!E15 -> 0 | D10: ='明细表K10-2'!F15 -> 0 | E10: =B10+C10+D10 -> 0 | G10: ='明细表K10-2'!H15 -> 0 | H10: ='明细表K10-2'!I15 -> 0 | I10: ='明细表K10-2'!J15 -> 0 | J10: =G10+H10+I10 -> 0
A11: ='明细表K10-2'!A16 -> …… | B11: ='明细表K10-2'!D16 -> 0 | C11: ='明细表K10-2'!E16 -> 0 | D11: ='明细表K10-2'!F16 -> 0 | E11: =B11+C11+D11 -> 0 | G11: ='明细表K10-2'!H16 -> 0 | H11: ='明细表K10-2'!I16 -> 0 | I11: ='明细表K10-2'!J16 -> 0 | J11: =G11+H11+I11 -> 0
A12: 合计 | B12: =SUM(B6:B11) -> 0 | C12: =SUM(C6:C11) -> 0 | D12: =SUM(D6:D11) -> 0 | E12: =SUM(E6:E11) -> 0 | G12: =SUM(G6:G11) -> 0 | H12: =SUM(H6:H11) -> 0 | I12: =SUM(I6:I11) -> 0 | J12: =SUM(J6:J11) -> 0
A13: 试算平衡表数
A14: 差异数 | E14: =E12-E13 -> 0 | J14: =J12-J13 -> 0
A15: 1.审计说明
A18: 2.审计结论
A20: 提示：
A21: 1.关注非经常性损益列报准确性。一般情况下，非经常性损益包含与自然灾害等相关的政府补助；另外，管理层无法合理预期是否受到以及受到的金额的税收返还（例如个人所得税的手续费返还），也应作为非经常性损益。
A22: 2、审计说明可以概述：（1）程序的测试情况、结果；（2）拟调整事项及其调整分录、未调整事项及其影响，审计范围受到限制情况及其影响。 | B22: 3、审计说明可以概述：（1）程序的测试情况、结果；（2）拟调整事项及其调整分录、未调整事项及其影响，审计范围受到限制情况及其影响。 | C22: 3、审计说明可以概述：（1）程序的测试情况、结果；（2）拟调整事项及其调整分录、未调整事项及其影响，审计范围受到限制情况及其影响。 | D22: 3、审计说明可以概述：（1）程序的测试情况、结果；（2）拟调整事项及其调整分录、未调整事项及其影响，审计范围受到限制情况及其影响。 | E22: 3、审计说明可以概述：（1）程序的测试情况、结果；（2）拟调整事项及其调整分录、未调整事项及其影响，审计范围受到限制情况及其影响。 | F22: 3、审计说明可以概述：（1）程序的测试情况、结果；（2）拟调整事项及其调整分录、未调整事项及其影响，审计范围受到限制情况及其影响。 | G22: 3、审计说明可以概述：（1）程序的测试情况、结果；（2）拟调整事项及其调整分录、未调整事项及其影响，审计范围受到限制情况及其影响。 | H22: 3、审计说明可以概述：（1）程序的测试情况、结果；（2）拟调整事项及其调整分录、未调整事项及其影响，审计范围受到限制情况及其影响。 | I22: 3、审计说明可以概述：（1）程序的测试情况、结果；（2）拟调整事项及其调整分录、未调整事项及其影响，审计范围受到限制情况及其影响。 | J22: 3、审计说明可以概述：（1）程序的测试情况、结果；（2）拟调整事项及其调整分录、未调整事项及其影响，审计范围受到限制情况及其影响。 | K22: 3、审计说明可以概述：（1）程序的测试情况、结果；（2）拟调整事项及其调整分录、未调整事项及其影响，审计范围受到限制情况及其影响。
A23: 3、审计结论可参考：A、未见异常。 B、除上述重大不符事项应当作为调整事项予以调整外，其余未见异常。 C、由于存在以下重大未调整事项（或审计范围受到限制无法获取充分、适当证据），不可确认。 | B23: 4、审计结论可参考：A、未见异常。 B、除上述重大不符事项应当作为调整事项予以调整外，其余未见异常。 C、由于存在以下重大未调整事项（或审计范围受到限制无法获取充分、适当证据），不可确认。 | C23: 4、审计结论可参考：A、未见异常。 B、除上述重大不符事项应当作为调整事项予以调整外，其余未见异常。 C、由于存在以下重大未调整事项（或审计范围受到限制无法获取充分、适当证据），不可确认。 | D23: 4、审计结论可参考：A、未见异常。 B、除上述重大不符事项应当作为调整事项予以调整外，其余未见异常。 C、由于存在以下重大未调整事项（或审计范围受到限制无法获取充分、适当证据），不可确认。 | E23: 4、审计结论可参考：A、未见异常。 B、除上述重大不符事项应当作为调整事项予以调整外，其余未见异常。 C、由于存在以下重大未调整事项（或审计范围受到限制无法获取充分、适当证据），不可确认。 | F23: 4、审计结论可参考：A、未见异常。 B、除上述重大不符事项应当作为调整事项予以调整外，其余未见异常。 C、由于存在以下重大未调整事项（或审计范围受到限制无法获取充分、适当证据），不可确认。 | G23: 4、审计结论可参考：A、未见异常。 B、除上述重大不符事项应当作为调整事项予以调整外，其余未见异常。 C、由于存在以下重大未调整事项（或审计范围受到限制无法获取充分、适当证据），不可确认。 | H23: 4、审计结论可参考：A、未见异常。 B、除上述重大不符事项应当作为调整事项予以调整外，其余未见异常。 C、由于存在以下重大未调整事项（或审计范围受到限制无法获取充分、适当证据），不可确认。 | I23: 4、审计结论可参考：A、未见异常。 B、除上述重大不符事项应当作为调整事项予以调整外，其余未见异常。 C、由于存在以下重大未调整事项（或审计范围受到限制无法获取充分、适当证据），不可确认。 | J23: 4、审计结论可参考：A、未见异常。 B、除上述重大不符事项应当作为调整事项予以调整外，其余未见异常。 C、由于存在以下重大未调整事项（或审计范围受到限制无法获取充分、适当证据），不可确认。 | K23: 4、审计结论可参考：A、未见异常。 B、除上述重大不符事项应当作为调整事项予以调整外，其余未见异常。 C、由于存在以下重大未调整事项（或审计范围受到限制无法获取充分、适当证据），不可确认。

Sheet 附注披露信息（上市公司）
A1: 致同会计师事务所
A2: 其他收益附注披露信息
A3: =底稿目录!A2 -> 被审计单位： | B3: =底稿目录!A4 -> 编制人： | C3: =底稿目录!A5 -> 编制日期： | D3: 索引号： | E3: =底稿目录!F6 -> 0
A4: =底稿目录!A3 -> 会计期间：202X年度 | B4: =底稿目录!A6 -> 复核人： | C4: =底稿目录!A7 -> 复核日期： | D4: 页次：
A5: 附注披露信息（上市公司）：
A6: 其他收益【提示：与日常活动相关的政府补助，采用总额法时计入其他收益。】
A7: 项目 | B7: 本期发生额 | C7: 上期发生额
A8: ='明细表K10-2'!A11 -> 总额法下与日常活动相关的政府补助 | B8: ='明细表K10-2'!G11 -> 0 | C8: ='明细表K10-2'!K11 -> 0
A9: ='明细表K10-2'!A12 -> 增值税进项税额加计抵减（实际缴纳时） | B9: ='明细表K10-2'!G12 -> 0 | C9: ='明细表K10-2'!K12 -> 0
A10: ='明细表K10-2'!A13 -> 增值税直接减免 | B10: ='明细表K10-2'!G13 -> 0 | C10: ='明细表K10-2'!K13 -> 0
A11: ='明细表K10-2'!A14 -> 个人所得税扣缴税款手续费返还 | B11: ='明细表K10-2'!G14 -> 0 | C11: ='明细表K10-2'!K14 -> 0
A12: ='明细表K10-2'!A15 -> 债务人以非金融资产清偿债务损益 | B12: ='明细表K10-2'!G15 -> 0 | C12: ='明细表K10-2'!K15 -> 0
A13: ='明细表K10-2'!A16 -> …… | B13: ='明细表K10-2'!G16 -> 0 | C13: ='明细表K10-2'!K16 -> 0
A14: 合 计 | B14: =SUM(B8:B13) -> 0 | C14: =SUM(C8:C13) -> 0
A15: 说明：
A16: 政府补助的具体信息，详见附附注八、政府补助。
A18: 【提示：（1）与日常活动相关的政府补助，采用总额法时计入其他收益；（2）填列企业作为个人所得税的扣缴义务人，根据《中华人民共和国个人所得税法》收到的扣缴税款手续费；（3）进项税加计扣除；在“实际缴纳增值税时”，将增值税进项税额加计扣除金额计入“其他收益”科目（4）债务重组中，债务人以非金融资产（存货、固定资产、无形资产等）清偿债务的，所清偿债务账面价值与存货等账面价值之间的差额，记入“其他收益”；（5）企业超比例安排残疾人就业或者为安排残疾人就业做出显著成绩，按规定收到的奖励，计入“其他收益”科目；（6）对于小微企业达到增值税制度规定的免征增值税条件时，应当按照《增值税会计处理规定》（财会〔2016〕22号）的相关规定进行会计处理，将有关应交增值税转入“其他收益”科目；（7）对于当期直接减免的增值税，企业应当根据《增值税会计处理规定》（财会〔2016〕22号）的相关规定进行会计处理，借记“应交税费——应交增值税（减免税款）”科目，贷记“其他收益”科目。】

Sheet 附注披露信息（国企）
A1: 致同会计师事务所
A2: 其他收益附注披露信息
A3: =底稿目录!A2 -> 被审计单位： | B3: =底稿目录!A4 -> 编制人： | C3: =底稿目录!A5 -> 编制日期： | D3: 索引号： | E3: =底稿目录!F7 -> 0
A4: =底稿目录!A3 -> 会计期间：202X年度 | B4: =底稿目录!A6 -> 复核人： | C4: =底稿目录!A7 -> 复核日期： | D4: 页次：
A5: 附注披露信息（国企）：
A6: 其他收益【提示：与日常活动相关的政府补助，采用总额法时计入其他收益。】
A7: 项 目 | B7: 本期发生额 | C7: 上期发生额
A8: ='明细表K10-2'!A11 -> 总额法下与日常活动相关的政府补助 | B8: ='明细表K10-2'!G11 -> 0 | C8: ='明细表K10-2'!K11 -> 0
A9: ='明细表K10-2'!A12 -> 增值税进项税额加计抵减（实际缴纳时） | B9: ='明细表K10-2'!G12 -> 0 | C9: ='明细表K10-2'!K12 -> 0
A10: ='明细表K10-2'!A13 -> 增值税直接减免 | B10: ='明细表K10-2'!G13 -> 0 | C10: ='明细表K10-2'!K13 -> 0
A11: ='明细表K10-2'!A14 -> 个人所得税扣缴税款手续费返还 | B11: ='明细表K10-2'!G14 -> 0 | C11: ='明细表K10-2'!K14 -> 0
A12: ='明细表K10-2'!A15 -> 债务人以非金融资产清偿债务损益 | B12: ='明细表K10-2'!G15 -> 0 | C12: ='明细表K10-2'!K15 -> 0
A13: ='明细表K10-2'!A16 -> …… | B13: ='明细表K10-2'!G16 -> 0 | C13: ='明细表K10-2'!K16 -> 0
A14: 合 计 | B14: =SUM(B8:B13) -> 0 | C14: =SUM(C8:C13) -> 0
A15: 【提示：（1）与日常活动相关的政府补助，采用总额法时计入其他收益；（2）填列企业作为个人所得税的扣缴义务人，根据《中华人民共和国个人所得税法》收到的扣缴税款手续费；（3）进项税加计扣除；（4）债务重组中，债务人以非金融资产（存货、固定资产、无形资产等）清偿债务的，所清偿债务账面价值与存货等账面价值之间的差额，记入“其他收益”；（5）企业超比例安排残疾人就业或者为安排残疾人就业做出显著成绩，按规定收到的奖励，计入“其他收益”科目；（6）对于小微企业达到增值税制度规定的免征增值税条件时，应当按照《增值税会计处理规定》（财会〔2016〕22号）的相关规定进行会计处理，将有关应交增值税转入“其他收益”科目；（7）对于当期直接减免的增值税，企业应当根据《增值税会计处理规定》（财会〔2016〕22号）的相关规定进行会计处理，借记“应交税金——应交增值税（减免税款）”科目，贷记“其他收益”科目。】

Sheet 明细表K10-2
A1: 致同会计师事务所
A2: 其他收益明细表
A3: =底稿目录!A2 -> 被审计单位： | D3: =底稿目录!A4 -> 编制人： | H3: =底稿目录!A5 -> 编制日期： | K3: 索引号： | L3: =底稿目录!F8 -> K10-2
A4: =底稿目录!A3 -> 会计期间：202X年度 | D4: =底稿目录!A6 -> 复核人： | H4: =底稿目录!A7 -> 复核日期： | K4: 页 次：
A5: 一、审计目标：
A6: 1.利润表中记录的其他收益已发生，且与被审计单位有关，已记录于恰当的账户 | E6: 2.所有应当记录的其他收益均已记录，所有应当包括在财务报表中的相关披露均已包括；
A7: 3.与其他收益有关的金额及其他数据已恰当记录，相关披露已得到恰当计量和描述。
A8: 二、审计过程:
A9: 项目（产生其他收益的来源） | B9: 类型 | C9: 判断依据 | D9: 本期未审数 | E9: 本期审计调整 | G9: 期末审定数 | H9: 上年同期未审数 | I9: 上年同期审计调整 | K9: 上年同期审定数 | L9: 文件索引号
E10: 账项调整 | F10: 重分类调整 | I10: 账项调整 | J10: 重分类调整
A11: 总额法下与日常活动相关的政府补助 | G11: =D11+E11+F11 -> 0 | K11: =H11+I11+J11 -> 0
A12: 增值税进项税额加计抵减（实际缴纳时） | G12: =D12+E12+F12 -> 0 | K12: =H12+I12+J12 -> 0
A13: 增值税直接减免 | G13: =D13+E13+F13 -> 0 | K13: =H13+I13+J13 -> 0
A14: 个人所得税扣缴税款手续费返还 | G14: =D14+E14+F14 -> 0 | K14: =H14+I14+J14 -> 0
A15: 债务人以非金融资产清偿债务损益 | G15: =D15+E15+F15 -> 0 | K15: =H15+I15+J15 -> 0
A16: …… | G16: =D16+E16+F16 -> 0 | K16: =H16+I16+J16 -> 0
A17: 合计 | D17: =SUM(D11:D16) -> 0 | E17: =SUM(E11:E16) -> 0 | F17: =SUM(F11:F16) -> 0 | G17: =SUM(G11:G16) -> 0 | H17: =SUM(H11:H16) -> 0 | I17: =SUM(I11:I16) -> 0 | J17: =SUM(J11:J16) -> 0 | K17: =SUM(K11:K16) -> 0
A18: 三、审计说明：
A20: 四、审计结论：
A24: 检查政府部门正式发布的财政扶持项目及其财政资金管理办法的适用范围，是否是普惠性的（任何符合规定条件的企业均可申请），而不是专门针对特定企业制定的；
A25: 编制说明：
A26: CAS 16 （2017）：与企业日常活动相关的政府补助，应当按照经济业务实质，计入其他收益或冲减相关成本费用。与企业日常活动无关的政府补助，应当计入营业外收支。
A27: 财政部-关于2018年度一般企业财务报表格式有关问题的解读：个人所得税手续费返还应作为其他与日常活动相关的项目在利润表的“其他收益”项目中填列。

Sheet 调整分录汇总K10-3
A1: 致同会计师事务所
A2: 其他收益调整分录汇总表
A3: =底稿目录!A2 -> 被审计单位： | C3: =底稿目录!A4 -> 编制人： | F3: =底稿目录!A5 -> 编制日期： | I3: 索引： | J3: =底稿目录!F9 -> K10-3
A4: =底稿目录!A3 -> 会计期间：202X年度 | C4: =底稿目录!A6 -> 复核人： | F4: =底稿目录!A7 -> 复核日期： | I4: 页次： | J4: 1
A5: 调整事项说明 | B5: 类别（报表调整/账项调整/其他） | C5: 报表项目 | D5: 科目名称 | E5: 附注项目 | F5: …… | G5: 借方调整金额 | H5: 贷方调整金额 | I5: 索引 | J5: 备注
A23: 提示：本底稿适用于调整分录较多、较复杂的项目，且仅列示与本报表项目相关的审计调整。项目组可根据项目实际情况选择是否使用该底稿。

Sheet 政府补助核对表K10-4
A1: 致同会计师事务所
A2: 政府补助核对表
A3: =底稿目录!A2 -> 被审计单位： | E3: =底稿目录!A4 -> 编制人： | K3: =底稿目录!A5 -> 编制日期： | R3: 索引号： | S3: =底稿目录!F10 -> K10-4
A4: =底稿目录!A3 -> 会计期间：202X年度 | E4: =底稿目录!A6 -> 复核人： | K4: =底稿目录!A7 -> 复核日期： | R4: 页 次：
A5: 一、审计目标：
A6: 1.利润表中记录的其他收益已发生，且与被审计单位有关，已记录于恰当的账户； | H6: 2. 与其他收益有关的金额及其他数据已恰当记录，相关披露已得到恰当计量和描述；
A7: 3. 其他收益已记录于正确的会计期间
A8: 二、审计过程：
A9: 补助项目名称 | B9: 补助金额 | C9: 总额法/净额法 | D9: 补助期间 | F9: 直接计入损益 | I9: 计入递延收益与递延收益分摊 | Q9: 补助金额是否收到 | R9: 计入应收政府补助金额 | S9: 索引号
D10: 开始日 | E10: 结束日 | F10: 直接冲减当期成本费用/相关资产账面价值 | G10: 直接计入当期其他收益金额 | H10: 直接计入当期营业外收入金额 | I10: 本期新增计入递延收益 | J10: 期初递延收益余额 | K10: 摊销冲减当期成本费用/相关资产账面价值 | L10: 摊销结转至当期其他收益金额 | M10: 摊销结转至当期营业外收入金额 | N10: 本期返还 | O10: 其他转出 | P10: 期末递延收益余额
A11: 一、与资产相关的政府补助
P12: =I12+J12-K12-L12-M12-N12-O12 -> 0
P13: =I13+J13-K13-L13-M13-N13-O13 -> 0
P14: =I14+J14-K14-L14-M14-N14-O14 -> 0
P15: =I15+J15-K15-L15-M15-N15-O15 -> 0
A16: 小计 | B16: =SUM(B12:B15) -> 0 | F16: =SUM(F12:F15) -> 0 | G16: =SUM(G12:G15) -> 0 | H16: =SUM(H12:H15) -> 0 | I16: =SUM(I12:I15) -> 0 | J16: =SUM(J12:J15) -> 0 | K16: =SUM(K12:K15) -> 0 | L16: =SUM(L12:L15) -> 0 | M16: =SUM(M12:M15) -> 0 | ... P16: =SUM(P12:P15) -> 0 | R16: =SUM(R12:R15) -> 0
A17: 二、与收益相关的政府补助
P18: =I18+J18-K18-L18-M18-N18-O18 -> 0
P19: =I19+J19-K19-L19-M19-N19-O19 -> 0
P20: =I20+J20-K20-L20-M20-N20-O20 -> 0
P21: =I21+J21-K21-L21-M21-N21-O21 -> 0
A22: 小计 | B22: =SUM(B18:B21) -> 0 | F22: =SUM(F18:F21) -> 0 | G22: =SUM(G18:G21) -> 0 | H22: =SUM(H18:H21) -> 0 | I22: =SUM(I18:I21) -> 0 | J22: =SUM(J18:J21) -> 0 | K22: =SUM(K18:K21) -> 0 | L22: =SUM(L18:L21) -> 0 | M22: =SUM(M18:M21) -> 0 | ... P22: =SUM(P18:P21) -> 0 | R22: =SUM(R18:R21) -> 0
A23: 合计 | B23: =B22+B16 -> 0 | F23: =F22+F16 -> 0 | G23: =G22+G16 -> 0 | H23: =H22+H16 -> 0 | I23: =I22+I16 -> 0 | J23: =J22+J16 -> 0 | K23: =K22+K16 -> 0 | L23: =L22+L16 -> 0 | M23: =M22+M16 -> 0 | ... P23: =P22+P16 -> 0 | R23: =R22+R16 -> 0
A24: 三、审计说明：
A25: 1.对政府补助考虑计量方法选择的理由和合理性：
A27: 2.对政府补助计量方法考虑会计政策的一致性：
A28: 3.政府补助与相关科目核对：
A29: 项目 | D29: 金额 | E29: 差异 | F29: 项目 | I29: 金额 | J29: 差异
A30: 成本费用中因政府补助冲减 | E30: =D30-F23-K23 -> 0 | F30: 递延收益本期摊销 | J30: =I30-K23-L23-M23 -> 0
A31: 其他收益-政府补助 | E31: =D31-G23-L23 -> 0 | F31: 递延收益期末余额 | J31: =I31-P23 -> 0
A32: 营业外收入-政府补助 | E32: =D32-H23-M23 -> 0 | F32: 其他应收款-政府补助 | J32: =I32-R23 -> 0
A33: 递延收益本期增加 | E33: =D33-J23 -> 0
A34: 4.递延收益摊销测算见递延收益底稿<K7-4>
A36: 四、审计结论：

Sheet 应收政府补助检查表K10-5
A1: 致同会计师事务所
A2: 应收政府补助检查表
A3: =底稿目录!A2 -> 被审计单位： | C3: =底稿目录!A4 -> 编制人： | E3: =底稿目录!A5 -> 编制日期： | G3: 索引号： | H3: =底稿目录!F11 -> K10-5
A4: =底稿目录!A3 -> 会计期间：202X年度 | C4: =底稿目录!A6 -> 复核人： | E4: =底稿目录!A7 -> 复核日期： | G4: 页 次：
A5: 一、审计目标
A6: 利润表中记录的其他收益已发生，且与被审计单位有关，已记录于恰当的账户
A7: 二、审计过程
A8: （一）确认的应收政府补助明细
A9: 政府补助项目名称 | B9: 应收政府补助未审金额 | C9: 应收政府补助审定金额 | D9: 账龄 | E9: 政府补助的发文单位 | F9: 预计收取的时间及依据 | G9: 政府补助文件索引号 | H9: 是否满足政府补助确认条件
A15: 合计 | B15: =SUM(B10:B14) -> 0 | C15: =SUM(C10:C14) -> 0
A17: （二）合理保证的分析（能够满足条件且能够收到）
A18: 政府补助项目名称 | B18: 政府补助文件主要内容 | D18: 存在合理保证的分析要点 | F18: 审计证据 | G18: 结论
D19: （1）发放主体是否具备相应的权力和资质； （2）补助文件中索引的政策依据是否适用； （3）企业申请政府补助的流程是否合法合规； （4）是否已经履行完毕补助文件中的要求； （5）实际收取资金前是否需要实质性审核； （6）历史上同类型政府补助的实际发放情况等 | F19: 政府补助文件； 内部会议纪要； 相关权力机构决议； 相关政府部门的书面承诺； 合理保证的分析及书面声明等
A25: 三、审计说明
A28: 四、审计结论
A30: 提示：
A31: 1.政府补助同时满足下列条件的，才能予以确认： （1）企业能够满足政府补助所附条件；（2）企业能够收到政府补助。
A32: 2.证监会《上市公司执行企业会计准则监管问题解答》（2013年第1期，总第8期）：对期末有确凿证据表明能够符合财政扶持政策规定的相关条件且预计能够收到财政扶持资金时，可以按应收金额计量。
A33: 3.对于在资产负债表日按照应收金额确认的政府补助，执行以下程序：
A34: 3.1查验正式发布的财政资金管理办法中的（定额）测算公式，或检查政府补助批文是否标明确切金额，分析政府补助金额是否存在重大不确定性；
A35: 3.2检查政府部门正式发布的财政扶持项目及其财政资金管理办法的适用范围，是否是普惠性的（任何符合规定条件的企业均可申请），而不是专门针对特定企业制定的；
A36: 3.3检查补助款批文中承诺的拨付期限，以及款项拨付对应的财政预算，分析政府补助在规定期限内的可收回性。

Sheet 其他收益检查表K10-6
A1: 致同会计师事务所
A2: 其他收益检查表
A3: =底稿目录!A2 -> 被审计单位： | F3: =底稿目录!A4 -> 编制人： | I3: =底稿目录!A5 -> 编制日期： | P3: 索引号： | Q3: =底稿目录!F12 -> K10-6
A4: =底稿目录!A3 -> 会计期间：202X年度 | F4: =底稿目录!A6 -> 复核人： | I4: =底稿目录!A7 -> 复核日期： | P4: 页次：
A5: 一、审计目标：
A6: 1.利润表中记录的其他收益已发生，且与被审计单位有关，已记录于恰当的账户。 | H6: 2.所有应当记录的其他收益均已记录，所有应当包括在财务报表中的相关披露均已包括。
A7: 3.与其他收益有关的金额及其他数据已恰当记录，相关披露已得到恰当计量和描述。 | H7: 4.其他收益已记录于正确的会计期间。
A8: 二、测试： | C8: 测试原因：大额（）关联方（）大额交易频繁（）异常（）其他（）
A9: 测试内容说明：1.原始凭证是否齐全； 2.记账凭证与原始凭证是否相符；3.账务处理是否正确；4.是否记录于恰当的会计期间；5.……
A10: 其他收益项目 | B10: 记账凭证 | H10: 支持性文件 | J10: 核对内容 | O10: 索引号 | P10: 是否异常 | Q10: 备注说明
B11: 日期 | C11: 凭证编号 | D11: 业务内容 | E11: 对方科目 | F11: 对方明细科目 | G11: 贷方金额 | J11: 1 | K11: 2 | L11: 3 | M11: 4 | N11: 5
H12: 银行回单、XXX文件、验收报告……
A22: 合计 | G22: =SUM(G12:G21) -> 0
A23: 本期发生额 | G23: ='明细表K10-2'!G17 -> 0
A24: 检查比例 | G24: =G22/G23 -> #DIV/0!
A25: 三、审计说明：
A29: 四、审计结论：
A31: 提示：
A32: 1.获取并检查政府补助相关文件，判断政府补助是否与日常活动相关，分类是否正确，处理是否适当，同类政府补助是否采用一样的处理方法，如都采用总额法或都采用净额法。
A33: 2.核对补助事项、查验资金来源，按照政府补助的定义认真核对公司认定的政府补助事项、并对补助资产的来源单位及其与政府文件规定的一致性进行查验。
A34: 3.查验公司项目验收报告等相关材料，检查审核资金使用范围是否符合相关文件规定，分析公司是否满足政府补助的确认条件。
A35: 4.政府补助文件规定不明确或存在明显不合理迹象时，与相关政府部门沟通或执行函证程序，或在必要时聘请律师或其他外部专家提供意见。

Sheet GT_Custom
A1: C1 | B1: Custom 1
A2: C2 | B2: Custom 2
A3: C3 | B3: Custom 3
A4: C4 | B4: Custom 4
A5: C5 | B5: Custom 5
A6: C6 | B6: Custom 6
A7: C7 | B7: Custom 7
A8: C8 | B8: Custom 8
