Workbook

Sheet 底稿目录
A1: 底稿开列时，可先在以下单元格填写有关内容，以便其他底稿引用有关数据：
A2: 被审计单位： | B2: 目录
A3: 会计期间：202X年度
A4: 编制人： | B4: 序号 | C4: 内容 | D4: 索引号 | E4: 备注
A5: 编制日期： | B5: 1 | C5: 实质性程序表 | D5: K11A
A6: 复核人： | B6: 2 | C6: 审定表 | D6: K11-1
A7: 复核日期： | B7: 3 | C7: 附注披露信息（上市公司） | F7: 无需打印
B8: 4 | C8: 附注披露信息(国企） | F8: 无需打印
A9: 关于工作底稿与审计程序索引号对应的说明 | B9: 5 | C9: 明细表 | D9: K11-2
A10: 1.编制的审计工作底稿应与审计程序对应。审计项目组应根据被审计单位实际情况和风险评估情况在实质性程序表中裁剪、修改或增加审计程序，根据实际执行的审计程序完成相应审计工作底稿，编制的工作底稿中应按自然顺序依次编制索引号，并通过唯一的索引号将与实质性程序表中的程序对应关联（即将工作底稿的索引号填入实质性程序表中的底稿索引号列）。 | B10: 6 | C10: 调整分录汇总 | D10: K11-3
A14: 2.获取的支持性证据应与审计底稿或程序对应。审计项目组在完成底稿时获取的支持性证据应根据底稿索引号编制下一级按自然顺序排序的索引号（如D1-2-1、D1-2-2、……），并在底稿中说明引用的支持性证据、关联索引号。
A17: 3.工作底稿索引号的编码规则：实质性程序索引号按循环从“D”到“N”,循环内账户以顺序号排列，模板中底稿索引号按账户顺序+自然数顺序（即模板中索引号按二级自然顺序排列，如D1-1、D1-2、D1-3、……D1-N）。

Sheet 实质性程序表 K11A
A1: 致同会计师事务所
A2: 资产减值损失实质性程序
A3: =底稿目录!A2 -> 被审计单位： | C3: =底稿目录!A4 -> 编制人： | E3: =底稿目录!A5 -> 编制日期： | H3: 索引号： | I3: =底稿目录!D5 -> K11A
A4: =底稿目录!A3 -> 会计期间：202X年度 | C4: =底稿目录!A6 -> 复核人： | E4: =底稿目录!A7 -> 复核日期： | H4: 页次：
A5: 一、本账户涉及的科目
A6: 资产减值损失
A7: 二、审计目标与认定的对应关系
A8: 审计目标 | G8: 财务报表的认定
A9: A. 利润表中记录的资产减值损失已发生，且与被审计单位有关，已记录于恰当的账户 | G9: 发生
A10: B. 所有应当记录的资产减值损失均已记录，所有应当包括在财务报表中的相关披露均已包括 | G10: 完整性
A11: C. 与资产减值损失有关的金额及其他数据已恰当记录，相关披露已得到恰当计量和描述 | G11: 准确性
A12: D. 资产减值损失已记录于正确的会计期间 | G12: 截止
A13: E. 已被恰当地汇总或分解且表述清楚，相关披露在按照企业会计准则的编制基础下是相关的、可理解的 | G13: 列报
A14: 三、计划实施的实质性程序
A15: 序号 | B15: 审计程序 | C15: 程序分类 | D15: 审计程序 | I15: 底稿索引号
D16: 发生 | E16: 完整性 | F16: 准确性 | G16: 截止 | H16: 列报 | J16: 根据被审计单位实际情况和风险评估情况裁剪、修改或增加审计程序
A17: 1 | B17: 获取或编制明细表、执行下列程序，并编制审定表：复核加计正确；将总金额与总账、明细账合计数核对相符；分析两期波动的原因及合理性。 | C17: 常规★ | D17: √ | E17: √ | F17: √ | I17: K11-1 /K11-2
A18: 2 | B18: 在使用手工编制、自定义信息报告、系统生成的非固定格式报告等由被审计单位生成的信息时，测试有关信息准确性和完整性，并考虑针对编制和维护由被审计单位生成的信息的相关控制实施控制测试，以评价该信息是否能够为实现审计目的提供基础。 | C18: 常规★ | E18: √ | F18: √ | I18: T1 | J18: 可参见《审计手册》4.2.6，由被审计单位生成的信息可能是由系统生成的、或手工编制的、或二者兼而有之的方式生成的。例如，由被审计单位生成的信息可能包括： • 不涉及自定义的、由系统生成的报告（如，固定格式报告）； • 可能通过人工自定义的、由系统生成的报告，例如，（计算机）查询信息或特别定制的报告； • 手工编制的信息，例如，汇总信息的电子表格或用以支持分配、计算以及调节的电子表格； • 其他系统生成或手工编制的信息，例如，由被审计单位编制的客户发票； • 通过影印、拍摄、扫描或其他方式转换成电子形式的文件记录。
A19: 3 | B19: 关注会计政策、会计估计合理性、一贯性。关注其是否利用会计政策和会计估计及其变更操纵利润。 | C19: 常规★ | D19: √ | E19: √ | F19: √ | I19: K11-1 /K11-2 | J19: 由被审计单位生成的信息不包括： • 总分类账或明细分类账、试算平衡表、或经审计的财务报表； • 第三方（除了服务机构）的报表或报告，例如，原始银行对账单，或函证的回函； • 外部数据（例如，第三方发布的数据，如，定价来源）。
A20: 5 | B20: 将资产减值损失明细发生额与本期存货跌价准备、固定资产减值准备等相关科目进行交叉勾稽。 | C20: 常规★ | D20: √ | E20: √ | F20: √ | G20: √ | I20: K11-2
A21: 7 | B21: 考虑是否存在超出被审计单位正常经营活动的重大、异常交易等，根据评估的舞弊风险等因素增加的审计程序。 | C21: IPO/上市/新三板/重组/舞弊应对
A22: 8 | B22: 检查资产减值损失是否已按企业会计准则或其他适用的规定在财务报表中做出恰当列报和披露。 | C22: 常规★ | H22: √ | I22: A1-1/A1-15 /A1-16

Sheet 审定表K11-1
A1: 致同会计师事务所
A2: 资产减值损失审定表
A3: =底稿目录!A2 -> 被审计单位： | C3: =底稿目录!A4 -> 编制人： | F3: =底稿目录!A5 -> 编制日期： | I3: 索引： | J3: =底稿目录!D6 -> K11-1
A4: =底稿目录!A3 -> 会计期间：202X年度 | C4: =底稿目录!A6 -> 复核人： | F4: =底稿目录!A7 -> 复核日期： | I4: 页次： | J4: 1
A5: 项目 | B5: 上期数 | E5: 本期数 | H5: 本期审定数与上期 审定数的比较 | J5: 原因分析
B6: 未审数 | C6: 账项调整 | D6: 审定数 | E6: 未审数 | F6: 账项调整 | G6: 审定数 | H6: 变动额 | I6: 变动率
A7: ='明细表K11-2'!B11 -> 合同资产减值损失 | B7: ='明细表K11-2'!F11 -> 0 | C7: ='明细表K11-2'!G11 -> 0 | D7: ='明细表K11-2'!H11 -> 0 | E7: ='明细表K11-2'!C11 -> 0 | F7: ='明细表K11-2'!D11 -> 0 | G7: ='明细表K11-2'!E11 -> 0 | H7: =G7-D7 -> 0 | I7: =IF(AND(D7=0,G7=0),0,IF(AND(D7=0,G7>0),1,H7/D7)) -> 0
A8: ='明细表K11-2'!B12 -> 存货跌价损失 | B8: ='明细表K11-2'!F12 -> 0 | C8: ='明细表K11-2'!G12 -> 0 | D8: ='明细表K11-2'!H12 -> 0 | E8: ='明细表K11-2'!C12 -> 0 | F8: ='明细表K11-2'!D12 -> 0 | G8: ='明细表K11-2'!E12 -> 0 | H8: =G8-D8 -> 0 | I8: =IF(AND(D8=0,G8=0),0,IF(AND(D8=0,G8>0),1,H8/D8)) -> 0
A9: ='明细表K11-2'!B13 -> 合同取得成本减值损失 | B9: ='明细表K11-2'!F13 -> 0 | C9: ='明细表K11-2'!G13 -> 0 | D9: ='明细表K11-2'!H13 -> 0 | E9: ='明细表K11-2'!C13 -> 0 | F9: ='明细表K11-2'!D13 -> 0 | G9: ='明细表K11-2'!E13 -> 0 | H9: =G9-D9 -> 0 | I9: =IF(AND(D9=0,G9=0),0,IF(AND(D9=0,G9>0),1,H9/D9)) -> 0
A10: ='明细表K11-2'!B14 -> 合同履约成本减值损失 | B10: ='明细表K11-2'!F14 -> 0 | C10: ='明细表K11-2'!G14 -> 0 | D10: ='明细表K11-2'!H14 -> 0 | E10: ='明细表K11-2'!C14 -> 0 | F10: ='明细表K11-2'!D14 -> 0 | G10: ='明细表K11-2'!E14 -> 0 | H10: =G10-D10 -> 0 | I10: =IF(AND(D10=0,G10=0),0,IF(AND(D10=0,G10>0),1,H10/D10)) -> 0
A11: ='明细表K11-2'!B15 -> 持有待售资产减值损失 | B11: ='明细表K11-2'!F15 -> 0 | C11: ='明细表K11-2'!G15 -> 0 | D11: ='明细表K11-2'!H15 -> 0 | E11: ='明细表K11-2'!C15 -> 0 | F11: ='明细表K11-2'!D15 -> 0 | G11: ='明细表K11-2'!E15 -> 0 | H11: =G11-D11 -> 0 | I11: =IF(AND(D11=0,G11=0),0,IF(AND(D11=0,G11>0),1,H11/D11)) -> 0
A12: ='明细表K11-2'!B16 -> 其他权益工具投资减值损失 | B12: ='明细表K11-2'!F16 -> 0 | C12: ='明细表K11-2'!G16 -> 0 | D12: ='明细表K11-2'!H16 -> 0 | E12: ='明细表K11-2'!C16 -> 0 | F12: ='明细表K11-2'!D16 -> 0 | G12: ='明细表K11-2'!E16 -> 0 | H12: =G12-D12 -> 0 | I12: =IF(AND(D12=0,G12=0),0,IF(AND(D12=0,G12>0),1,H12/D12)) -> 0
A13: ='明细表K11-2'!B17 -> 其他非流动金融资产减值损失 | B13: ='明细表K11-2'!F17 -> 0 | C13: ='明细表K11-2'!G17 -> 0 | D13: ='明细表K11-2'!H17 -> 0 | E13: ='明细表K11-2'!C17 -> 0 | F13: ='明细表K11-2'!D17 -> 0 | G13: ='明细表K11-2'!E17 -> 0 | H13: =G13-D13 -> 0 | I13: =IF(AND(D13=0,G13=0),0,IF(AND(D13=0,G13>0),1,H13/D13)) -> 0
A14: ='明细表K11-2'!B18 -> 长期股权投资减值损失 | B14: ='明细表K11-2'!F18 -> 0 | C14: ='明细表K11-2'!G18 -> 0 | D14: ='明细表K11-2'!H18 -> 0 | E14: ='明细表K11-2'!C18 -> 0 | F14: ='明细表K11-2'!D18 -> 0 | G14: ='明细表K11-2'!E18 -> 0 | H14: =G14-D14 -> 0 | I14: =IF(AND(D14=0,G14=0),0,IF(AND(D14=0,G14>0),1,H14/D14)) -> 0
A15: ='明细表K11-2'!B19 -> 投资性房地产减值损失 | B15: ='明细表K11-2'!F19 -> 0 | C15: ='明细表K11-2'!G19 -> 0 | D15: ='明细表K11-2'!H19 -> 0 | E15: ='明细表K11-2'!C19 -> 0 | F15: ='明细表K11-2'!D19 -> 0 | G15: ='明细表K11-2'!E19 -> 0 | H15: =G15-D15 -> 0 | I15: =IF(AND(D15=0,G15=0),0,IF(AND(D15=0,G15>0),1,H15/D15)) -> 0
A16: ='明细表K11-2'!B20 -> 固定资产减值损失 | B16: ='明细表K11-2'!F20 -> 0 | C16: ='明细表K11-2'!G20 -> 0 | D16: ='明细表K11-2'!H20 -> 0 | E16: ='明细表K11-2'!C20 -> 0 | F16: ='明细表K11-2'!D20 -> 0 | G16: ='明细表K11-2'!E20 -> 0 | H16: =G16-D16 -> 0 | I16: =IF(AND(D16=0,G16=0),0,IF(AND(D16=0,G16>0),1,H16/D16)) -> 0
A17: ='明细表K11-2'!B21 -> 工程物资减值损失 | B17: ='明细表K11-2'!F21 -> 0 | C17: ='明细表K11-2'!G21 -> 0 | D17: ='明细表K11-2'!H21 -> 0 | E17: ='明细表K11-2'!C21 -> 0 | F17: ='明细表K11-2'!D21 -> 0 | G17: ='明细表K11-2'!E21 -> 0 | H17: =G17-D17 -> 0 | I17: =IF(AND(D17=0,G17=0),0,IF(AND(D17=0,G17>0),1,H17/D17)) -> 0
A18: ='明细表K11-2'!B22 -> 在建工程减值损失 | B18: ='明细表K11-2'!F22 -> 0 | C18: ='明细表K11-2'!G22 -> 0 | D18: ='明细表K11-2'!H22 -> 0 | E18: ='明细表K11-2'!C22 -> 0 | F18: ='明细表K11-2'!D22 -> 0 | G18: ='明细表K11-2'!E22 -> 0 | H18: =G18-D18 -> 0 | I18: =IF(AND(D18=0,G18=0),0,IF(AND(D18=0,G18>0),1,H18/D18)) -> 0
... A23: ='明细表K11-2'!B27 -> 商誉减值损失 | B23: ='明细表K11-2'!F27 -> 0 | C23: ='明细表K11-2'!G27 -> 0 | D23: ='明细表K11-2'!H27 -> 0 | E23: ='明细表K11-2'!C27 -> 0 | F23: ='明细表K11-2'!D27 -> 0 | G23: ='明细表K11-2'!E27 -> 0 | H23: =G23-D23 -> 0 | I23: =IF(AND(D23=0,G23=0),0,IF(AND(D23=0,G23>0),1,H23/D23)) -> 0
A24: 其他 | B24: ='明细表K11-2'!F28 -> 0 | C24: ='明细表K11-2'!G28 -> 0 | D24: ='明细表K11-2'!H28 -> 0 | E24: ='明细表K11-2'!C28 -> 0 | F24: ='明细表K11-2'!D28 -> 0 | G24: ='明细表K11-2'!E28 -> 0 | H24: =G24-D24 -> 0 | I24: =IF(AND(D24=0,G24=0),0,IF(AND(D24=0,G24>0),1,H24/D24)) -> 0
A25: ...... | B25: ='明细表K11-2'!F29 -> 0 | C25: ='明细表K11-2'!G29 -> 0 | D25: ='明细表K11-2'!H29 -> 0 | E25: ='明细表K11-2'!C29 -> 0 | F25: ='明细表K11-2'!D29 -> 0 | G25: ='明细表K11-2'!E29 -> 0 | H25: =G25-D25 -> 0 | I25: =IF(AND(D25=0,G25=0),0,IF(AND(D25=0,G25>0),1,H25/D25)) -> 0
A26: 合计 | B26: =SUM(B7:B25) -> 0 | C26: =SUM(C7:C25) -> 0 | D26: =SUM(D7:D25) -> 0 | E26: =SUM(E7:E25) -> 0 | F26: =SUM(F7:F25) -> 0 | G26: =SUM(G7:G25) -> 0 | H26: =G26-D26 -> 0 | I26: =IF(AND(D26=0,G26=0),0,IF(AND(D26=0,G26>0),1,H26/D26)) -> 0
A27: TB数据：
A28: 差异： | B28: =B26-B27 -> 0 | C28: =C26-C27 -> 0 | D28: =D26-D27 -> 0 | E28: =E26-E27 -> 0 | F28: =F26-F27 -> 0 | G28: =G26-G27 -> 0
A29: 1.审计说明
A30: （1）资产减值损失本期较上期增加（负数为减少）：
A31: 主要原因（比例超过30%的）：
A33: （2）情况说明。
A35: 2.审计结论

Sheet 附注披露信息（上市公司）
A1: 致同会计师事务所
A2: 附注披露信息（上市公司）
A3: =底稿目录!A2 -> 被审计单位： | B3: =底稿目录!A4 -> 编制人： | C3: =底稿目录!A5 -> 编制日期： | D3: 索引： | E3: =底稿目录!D7 -> 0
A4: =底稿目录!A3 -> 会计期间：202X年度 | B4: =底稿目录!A6 -> 复核人： | C4: =底稿目录!A7 -> 复核日期： | D4: 页次： | E4: 1
A5: 资产减值损失（注：损失以“—”号填列，以下不存在的项目可以删除）
A6: 项 目 | B6: 本期发生额 | C6: 上期发生额
A7: ='审定表K11-1'!A7 -> 合同资产减值损失 | B7: ='审定表K11-1'!G7 -> 0 | C7: ='审定表K11-1'!D7 -> 0
A8: ='审定表K11-1'!A8 -> 存货跌价损失 | B8: ='审定表K11-1'!G8 -> 0 | C8: ='审定表K11-1'!D8 -> 0
A9: ='审定表K11-1'!A9 -> 合同取得成本减值损失 | B9: ='审定表K11-1'!G9 -> 0 | C9: ='审定表K11-1'!D9 -> 0
A10: ='审定表K11-1'!A10 -> 合同履约成本减值损失 | B10: ='审定表K11-1'!G10 -> 0 | C10: ='审定表K11-1'!D10 -> 0
A11: ='审定表K11-1'!A11 -> 持有待售资产减值损失 | B11: ='审定表K11-1'!G11 -> 0 | C11: ='审定表K11-1'!D11 -> 0
A12: ='审定表K11-1'!A12 -> 其他权益工具投资减值损失 | B12: ='审定表K11-1'!G12 -> 0 | C12: ='审定表K11-1'!D12 -> 0
A13: ='审定表K11-1'!A13 -> 其他非流动金融资产减值损失 | B13: ='审定表K11-1'!G13 -> 0 | C13: ='审定表K11-1'!D13 -> 0
A14: ='审定表K11-1'!A14 -> 长期股权投资减值损失 | B14: ='审定表K11-1'!G14 -> 0 | C14: ='审定表K11-1'!D14 -> 0
A15: ='审定表K11-1'!A15 -> 投资性房地产减值损失 | B15: ='审定表K11-1'!G15 -> 0 | C15: ='审定表K11-1'!D15 -> 0
A16: ='审定表K11-1'!A16 -> 固定资产减值损失 | B16: ='审定表K11-1'!G16 -> 0 | C16: ='审定表K11-1'!D16 -> 0
A17: ='审定表K11-1'!A17 -> 工程物资减值损失 | B17: ='审定表K11-1'!G17 -> 0 | C17: ='审定表K11-1'!D17 -> 0
A18: ='审定表K11-1'!A18 -> 在建工程减值损失 | B18: ='审定表K11-1'!G18 -> 0 | C18: ='审定表K11-1'!D18 -> 0
... A25: ='审定表K11-1'!A25 -> ...... | B25: ='审定表K11-1'!G25 -> 0 | C25: ='审定表K11-1'!D25 -> 0
A26: 合 计 | B26: =SUM(B7:B25) -> 0 | C26: =SUM(C7:C25) -> 0
A27: 说明：
A30: 注：本科目明细表按照正数填列、披露表按照负数填列。

Sheet 附注披露信息（国企）
A1: 致同会计师事务所
A2: 附注披露信息(国企)
A3: =底稿目录!A2 -> 被审计单位： | B3: =底稿目录!A4 -> 编制人： | C3: =底稿目录!A5 -> 编制日期： | D3: 索引： | E3: =底稿目录!D8 -> 0
A4: =底稿目录!A3 -> 会计期间：202X年度 | B4: =底稿目录!A6 -> 复核人： | C4: =底稿目录!A7 -> 复核日期： | D4: 页次： | E4: 1
A5: 资产减值损失（注：损失以“—”号填列，以下不存在的项目可以删除）
A6: 项 目 | B6: 本期发生额 | C6: 上期发生额
A7: ='审定表K11-1'!A7 -> 合同资产减值损失 | B7: ='审定表K11-1'!G7 -> 0 | C7: ='审定表K11-1'!D7 -> 0
A8: ='审定表K11-1'!A8 -> 存货跌价损失 | B8: ='审定表K11-1'!G8 -> 0 | C8: ='审定表K11-1'!D8 -> 0
A9: ='审定表K11-1'!A9 -> 合同取得成本减值损失 | B9: ='审定表K11-1'!G9 -> 0 | C9: ='审定表K11-1'!D9 -> 0
A10: ='审定表K11-1'!A10 -> 合同履约成本减值损失 | B10: ='审定表K11-1'!G10 -> 0 | C10: ='审定表K11-1'!D10 -> 0
A11: ='审定表K11-1'!A11 -> 持有待售资产减值损失 | B11: ='审定表K11-1'!G11 -> 0 | C11: ='审定表K11-1'!D11 -> 0
A12: ='审定表K11-1'!A12 -> 其他权益工具投资减值损失 | B12: ='审定表K11-1'!G12 -> 0 | C12: ='审定表K11-1'!D12 -> 0
A13: ='审定表K11-1'!A13 -> 其他非流动金融资产减值损失 | B13: ='审定表K11-1'!G13 -> 0 | C13: ='审定表K11-1'!D13 -> 0
A14: ='审定表K11-1'!A14 -> 长期股权投资减值损失 | B14: ='审定表K11-1'!G14 -> 0 | C14: ='审定表K11-1'!D14 -> 0
A15: ='审定表K11-1'!A15 -> 投资性房地产减值损失 | B15: ='审定表K11-1'!G15 -> 0 | C15: ='审定表K11-1'!D15 -> 0
A16: ='审定表K11-1'!A16 -> 固定资产减值损失 | B16: ='审定表K11-1'!G16 -> 0 | C16: ='审定表K11-1'!D16 -> 0
A17: ='审定表K11-1'!A17 -> 工程物资减值损失 | B17: ='审定表K11-1'!G17 -> 0 | C17: ='审定表K11-1'!D17 -> 0
A18: ='审定表K11-1'!A18 -> 在建工程减值损失 | B18: ='审定表K11-1'!G18 -> 0 | C18: ='审定表K11-1'!D18 -> 0
... A25: ='审定表K11-1'!A25 -> ...... | B25: ='审定表K11-1'!G25 -> 0 | C25: ='审定表K11-1'!D25 -> 0
A26: 合 计 | B26: =SUM(B7:B25) -> 0 | C26: =SUM(C7:C25) -> 0
A29: 注：本科目明细表按照正数填列、披露表按照负数填列。

Sheet 明细表K11-2
A1: 致同会计师事务所
A2: 资产减值损失明细表
A3: =底稿目录!A2 -> 被审计单位： | D3: =底稿目录!A4 -> 编制人： | I3: =底稿目录!A5 -> 编制日期： | P3: 索引号： | Q3: =底稿目录!D9 -> K11-2
A4: =底稿目录!A3 -> 会计期间：202X年度 | D4: =底稿目录!A6 -> 复核人： | I4: =底稿目录!A7 -> 复核日期： | P4: 页次：
A5: 一、审计目标:
A6: 1.利润表中记录的资产减值损失已发生，且与被审计单位有关，已记录于恰当的账户; | H6: 2.所有应当记录的资产减值损失均已记录，所有应当包括在财务报表中的相关披露均已包括;
A7: 3.与资产减值损失有关的金额及其他数据已恰当记录，相关披露已得到恰当计量和描述。
A8: 二、审计过程：
A9: 序号 | B9: 资产减值损失项目内容 | C9: 本期未审合计 | D9: 账项调整 | E9: 本期审定金额 | F9: 上期未审合计 | G9: 账项调整 | H9: 上期审定金额 | I9: 对应科目 | J9: 对应科目-减值准备发生额 | Q9: 核对
J10: 期初金额 | K10: 本期计提 | L10: 本期转回 | M10: 本期转销 | N10: 期末金额 | O10: 本期计入资产减值损失金额 | P10: 索引号
A11: 1 | B11: 合同资产减值损失 | E11: =C11+D11 -> 0 | H11: =F11+G11 -> 0 | I11: 合同资产坏账准备 | N11: =J11+K11-L11-M11 -> 0 | O11: =K11-L11 -> 0 | Q11: =IF((E11-O11)=0,"OK",(E11-O11)) -> OK
A12: 2 | B12: 存货跌价损失 | E12: =C12+D12 -> 0 | H12: =F12+G12 -> 0 | I12: 存货跌价准备 | N12: =J12+K12-L12-M12 -> 0 | O12: =K12-L12 -> 0 | Q12: =IF((E12-O12)=0,"OK",(E12-O12)) -> OK
A13: 3 | B13: 合同取得成本减值损失 | E13: =C13+D13 -> 0 | H13: =F13+G13 -> 0 | I13: 合同取得成本相关资产减值准备 | N13: =J13+K13-L13-M13 -> 0 | O13: =K13-L13 -> 0 | Q13: =IF((E13-O13)=0,"OK",(E13-O13)) -> OK
A14: 4 | B14: 合同履约成本减值损失 | E14: =C14+D14 -> 0 | H14: =F14+G14 -> 0 | I14: 合同履约成本相关资产减值准备 | N14: =J14+K14-L14-M14 -> 0 | O14: =K14-L14 -> 0 | Q14: =IF((E14-O14)=0,"OK",(E14-O14)) -> OK
A15: 5 | B15: 持有待售资产减值损失 | E15: =C15+D15 -> 0 | H15: =F15+G15 -> 0 | I15: 持有待售资产减值准备 | N15: =J15+K15-L15-M15 -> 0 | O15: =K15-L15 -> 0 | Q15: =IF((E15-O15)=0,"OK",(E15-O15)) -> OK
A16: 6 | B16: 其他权益工具投资减值损失 | E16: =C16+D16 -> 0 | H16: =F16+G16 -> 0 | I16: 其他权益工具投资减值准备 | N16: =J16+K16-L16-M16 -> 0 | O16: =K16-L16 -> 0 | Q16: =IF((E16-O16)=0,"OK",(E16-O16)) -> OK
A17: 7 | B17: 其他非流动金融资产减值损失 | E17: =C17+D17 -> 0 | H17: =F17+G17 -> 0 | I17: 其他非流动金融资产减值准备 | N17: =J17+K17-L17-M17 -> 0 | O17: =K17-L17 -> 0 | Q17: =IF((E17-O17)=0,"OK",(E17-O17)) -> OK
A18: 8 | B18: 长期股权投资减值损失 | E18: =C18+D18 -> 0 | H18: =F18+G18 -> 0 | I18: 长期股权投资减值准备 | N18: =J18+K18-L18-M18 -> 0 | O18: =K18-L18 -> 0 | Q18: =IF((E18-O18)=0,"OK",(E18-O18)) -> OK
A19: 9 | B19: 投资性房地产减值损失 | E19: =C19+D19 -> 0 | H19: =F19+G19 -> 0 | I19: 投资性房地产减值准备 | N19: =J19+K19-L19-M19 -> 0 | O19: =K19-L19 -> 0 | Q19: =IF((E19-O19)=0,"OK",(E19-O19)) -> OK
A20: 10 | B20: 固定资产减值损失 | E20: =C20+D20 -> 0 | H20: =F20+G20 -> 0 | I20: 固定资产减值准备 | N20: =J20+K20-L20-M20 -> 0 | O20: =K20-L20 -> 0 | Q20: =IF((E20-O20)=0,"OK",(E20-O20)) -> OK
A21: 11 | B21: 工程物资减值损失 | E21: =C21+D21 -> 0 | H21: =F21+G21 -> 0 | I21: 工程物资减值准备 | N21: =J21+K21-L21-M21 -> 0 | O21: =K21-L21 -> 0 | Q21: =IF((E21-O21)=0,"OK",(E21-O21)) -> OK
A22: 12 | B22: 在建工程减值损失 | E22: =C22+D22 -> 0 | H22: =F22+G22 -> 0 | I22: 在建工程减值准备 | N22: =J22+K22-L22-M22 -> 0 | O22: =K22-L22 -> 0 | Q22: =IF((E22-O22)=0,"OK",(E22-O22)) -> OK
... A27: 17 | B27: 商誉减值损失 | E27: =C27+D27 -> 0 | H27: =F27+G27 -> 0 | I27: 商誉减值准备 | N27: =J27+K27-L27-M27 -> 0 | O27: =K27-L27 -> 0 | Q27: =IF((E27-O27)=0,"OK",(E27-O27)) -> OK
A28: 18 | B28: 其他 | E28: =C28+D28 -> 0 | H28: =F28+G28 -> 0 | N28: =J28+K28-L28-M28 -> 0 | O28: =K28-L28 -> 0 | Q28: =IF((E28-O28)=0,"OK",(E28-O28)) -> OK
A29: 19 | B29: ...... | E29: =C29+D29 -> 0 | H29: =F29+G29 -> 0 | N29: =J29+K29-L29-M29 -> 0 | O29: =K29-L29 -> 0 | Q29: =IF((E29-O29)=0,"OK",(E29-O29)) -> OK
A30: 合计 | C30: =SUM(C11:C29) -> 0 | D30: =SUM(D11:D29) -> 0 | E30: =SUM(E11:E29) -> 0 | F30: =SUM(F11:F29) -> 0 | G30: =SUM(G11:G29) -> 0 | H30: =SUM(H11:H29) -> 0 | I30: 合计 | J30: =SUM(J16:J29) -> 0 | K30: =SUM(K16:K29) -> 0 | L30: =SUM(L16:L29) -> 0 | M30: =SUM(M16:M29) -> 0 | N30: =SUM(N16:N29) -> 0 | O30: =SUM(O16:O29) -> 0
A31: 三、审计说明：
A32: 1.明细账、总账、报表数核对一致。
A33: 2……
A35: 四、审计结论：
A40: 编制说明：
A41: 1、本科目核算企业计提各项资产减值准备所形成的损失。
A42: 2、本科目明细表按照正数填列、披露表按照负数填列。
A43: 3、企业的应收款项、存货、长期股权投资、持有至到期投资、固定资产、无形资产、贷款等资产发生减值的，
A44: 按应减记的金额，借记本科目，贷记“坏账准备”、“存货跌价准备”、“长期股权投资减值准备”、“持有至到期投资
A45: 减值准备”、“固定资产减值准备”、“无形资产减值准备”、“贷款损失准备”等科目。
A46: 在建工程、工程物资、生产性生物资产、商誉、抵债资产、损余物资、采用成本模式计量的投资性房地产等
A47: 资产发生减值的，应当设置相应的减值准备科目，比照上述规定进行处理。
... A50: “贷款损失准备”等科目，贷记本科目。

Sheet 调整分录汇总K11-3
A1: 致同会计师事务所
A2: 资产减值损失调整分录汇总表
A3: =底稿目录!A2 -> 被审计单位： | C3: =底稿目录!A4 -> 编制人： | F3: =底稿目录!A5 -> 编制日期： | I3: 索引号： | J3: =底稿目录!D10 -> K11-3
A4: =底稿目录!A3 -> 会计期间：202X年度 | C4: =底稿目录!A6 -> 复核人： | F4: =底稿目录!A7 -> 复核日期： | I4: 页次：
A5: 调整事项说明 | B5: 类别（报表调整/账项调整/其他） | C5: 报表项目 | D5: 科目名称 | E5: 附注项目 | F5: …… | G5: 借方调整金额 | H5: 贷方调整金额 | I5: 索引 | J5: 备注
A22: 提示：本底稿适用于调整分录较多、较复杂的项目，且仅列示与本报表项目相关的审计调整。项目组可根据项目实际情况选择是否使用该底稿。
