Workbook

Sheet 底稿目录
A1: 底稿开列时，可先在以下单元格填写有关内容，以便其他底稿引用有关数据：
A2: 被审计单位：
A3: 会计期间：202X年度 | D3: 序号 | E3: 内容 | F3: 索引号 | G3: 备注
A4: 编制人： | D4: 1 | E4: 实质性程序表 | F4: K13A
A5: 编制日期： | D5: 2 | E5: 审定表 | F5: K13-1
A6: 复核人： | D6: 3 | E6: 附注披露信息（上市公司） | H6: 无需打印
A7: 复核日期： | D7: 4 | E7: 附注披露信息（国企） | H7: 无需打印
D8: 5 | E8: 明细表 | F8: K13-2
A9: 关于工作底稿与审计程序索引号对应的说明 | D9: 6 | E9: 调整分录汇总 | F9: K13-3 | G9: 备选
A10: 1.编制的审计工作底稿应与审计程序对应。审计项目组应根据被审计单位实际情况和风险评估情况在实质性程序表中裁剪、修改或增加审计程序，根据实际执行的审计程序完成相应审计工作底稿，编制的工作底稿中应按自然顺序依次编制索引号，并通过唯一的索引号将与实质性程序表中的程序对应关联（即将工作底稿的索引号填入实质性程序表中的底稿索引号列）。 | D10: 7 | E10: 营业外支出检查表 | F10: K13-4
A14: 2.获取的支持性证据应与审计底稿或程序对应。审计项目组在完成底稿时获取的支持性证据应根据底稿索引号编制下一级按自然顺序排序的索引号（如D1-2-1、D1-2-2、……），并在底稿中说明引用的支持性证据、关联索引号。
A17: 3.工作底稿索引号的编码规则：实质性程序索引号按循环从“D”到“N”,循环内账户以顺序号排列，模板中底稿索引号按账户顺序+自然数顺序（即模板中索引号按二级自然顺序排列，如D1-1、D1-2、D1-3、……D1-N）。

Sheet 实质性程序表K13A
A1: 致同会计师事务所
A2: 营业外支出实质性程序表
A3: =底稿目录!A2 -> 被审计单位： | C3: =底稿目录!A4 -> 编制人： | E3: =底稿目录!A5 -> 编制日期： | H3: 索引号： | I3: =底稿目录!F4 -> K13A
A4: =底稿目录!A3 -> 会计期间：202X年度 | C4: =底稿目录!A6 -> 复核人： | E4: =底稿目录!A7 -> 复核日期： | H4: 页 次：
A5: 一、本账户涉及的科目
A6: 营业外支出
A7: 二、审计目标与认定的对应关系
A8: 审计目标 | G8: 财务报表的认定
A9: A. 利润表中记录的营业外支出已发生，且与被审计单位有关，已记录于恰当的账户 | G9: 发生
A10: B. 所有应当记录的营业外支出均已记录，所有应当包括在财务报表中的相关披露均已包括 | G10: 完整性
A11: C. 与营业外支出有关的金额及其他数据已恰当记录，相关披露已得到恰当计量和描述 | G11: 准确性
A12: D. 营业外支出已记录于正确的会计期间 | G12: 截止
A13: E. 已被恰当地汇总或分解且表述清楚，相关披露在按照企业会计准则的编制基础下是相关的、可理解的 | G13: 列报
A14: 三、计划实施的实质性程序
A15: 序号 | B15: 审计程序 | C15: 程序分类 | D15: 审计程序 | I15: 底稿索引号
D16: 发生 | E16: 完整性 | F16: 准确性 | G16: 截止 | H16: 列报 | J16: 根据被审计单位实际情况和风险评估情况裁剪、修改或增加审计程序
A17: 1 | B17: 获取或编制明细表、执行下列程序，并编制审定表：复核加计正确；将总金额与总账、明细账合计数核对相符。 | C17: 常规★ | D17: √ | E17: √ | F17: √ | I17: K13-1 /K13-2
A18: 2 | B18: 在使用手工编制、自定义信息报告、系统生成的非固定格式报告等由被审计单位生成的信息时，测试有关信息准确性和完整性，并考虑针对编制和维护由被审计单位生成的信息的相关控制实施控制测试，以评价该信息是否能够为实现审计目的提供基础。 | C18: 常规★ | E18: √ | F18: √ | I18: T1 | J18: 可参见《审计手册》4.2.6，由被审计单位生成的信息可能是由系统生成的、或手工编制的、或二者兼而有之的方式生成的。例如，由被审计单位生成的信息可能包括： • 不涉及自定义的、由系统生成的报告（如，固定格式报告）； • 可能通过人工自定义的、由系统生成的报告，例如，（计算机）查询信息或特别定制的报告； • 手工编制的信息，例如，汇总信息的电子表格或用以支持分配、计算以及调节的电子表格； • 其他系统生成或手工编制的信息，例如，由被审计单位编制的客户发票； • 通过影印、拍摄、扫描或其他方式转换成电子形式的文件记录。
A19: 3 | B19: 对上期发生额的审计：结合本期审计确定营业外支出的上期金额的截止是否恰当。（适用于首次承接） | C19: 备选 | G19: √ | J19: 由被审计单位生成的信息不包括： • 总分类账或明细分类账、试算平衡表、或经审计的财务报表； • 第三方（除了服务机构）的报表或报告，例如，原始银行对账单，或函证的回函； • 外部数据（例如，第三方发布的数据，如，定价来源）。
A20: 4 | B20: 关注会计政策、会计估计合理性、一贯性。关注其是否利用会计政策和会计估计及其变更操纵利润。 | C20: 常规★ | D20: √ | E20: √ | F20: √ | I20: K13-1 /K13-2
A21: 5 | B21: 分析总体合理性： （1）分析本期营业外支出明细占比情况、与上期发生额比较，分析异常波动原因；关注明细项中是否存在不符合往年常态的项目，不符合企业经营状况，存在异常变动的项目，检查相关支持性文件； （2）分析本期营业外支出明细各月金额及其占比，分析异常波动原因； | C21: 常规★ | D21: √ | E21: √ | F21: √ | I21: K13-2
A22: 6 | B22: 结合固定资产、预计负债等相关科目审计，检查支持性文件，确定入账金额及会计处理是否正确。 | C22: 常规★ | D22: √ | E22: √ | F22: √ | G22: √
B23: 检查与营业外支出有关的的记账凭证和相应的支持性证据以确定交易的真实性，是否按规定进行相应的会计处理和披露。 | C23: 常规★ | D23: √ | F23: √ | G23: √ | I23: K13-4
A24: 7 | B24: 考虑是否存在超出被审计单位正常经营活动的重大、异常交易等，根据评估的舞弊风险等因素增加的审计程序。 | C24: IPO/上市/新三板/重组/舞弊应对
A25: 8 | B25: 检查营业外支出是否已按企业会计准则或其他适用的规定在财务报表中做出恰当列报和披露。 | C25: 常规★ | H25: √ | I25: A1-1/A1-15 /A1-16

Sheet 审定表K13-1
A1: 致同会计师事务所
A2: 营业外支出审定表
A3: =底稿目录!A2 -> 被审计单位： | C3: =底稿目录!A4 -> 编制人： | G3: =底稿目录!A5 -> 编制日期： | J3: 索引号： | K3: =底稿目录!F5 -> K13-1
A4: =底稿目录!A3 -> 会计期间：202X年度 | C4: =底稿目录!A6 -> 复核人： | G4: =底稿目录!A7 -> 复核日期： | J4: 页次：
A5: 项目名称 | B5: 本期未审数 | C5: 账项调整 | D5: 重分类调整 | E5: 本期审定数 | F5: 索引号 | G5: 上期未审数 | H5: 账项调整 | I5: 重分类调整 | J5: 上期审定数 | K5: 备注
A6: ='明细表K13-2'!A9 -> 非流动资产毁损报废（扣保险赔款） | B6: ='明细表K13-2'!N9 -> 0 | C6: ='明细表K13-2'!O9 -> 0 | D6: ='明细表K13-2'!P9 -> 0 | E6: =B6+C6+D6 -> 0 | G6: ='明细表K13-2'!U9 -> 0 | H6: ='明细表K13-2'!V9 -> 0 | I6: ='明细表K13-2'!W9 -> 0 | J6: =G6+H6+I6 -> 0
A7: ='明细表K13-2'!A10 -> 公益性捐赠 | B7: ='明细表K13-2'!N10 -> 0 | C7: ='明细表K13-2'!O10 -> 0 | D7: ='明细表K13-2'!P10 -> 0 | E7: =B7+C7+D7 -> 0 | G7: ='明细表K13-2'!U10 -> 0 | H7: ='明细表K13-2'!V10 -> 0 | I7: ='明细表K13-2'!W10 -> 0 | J7: =G7+H7+I7 -> 0
A8: ='明细表K13-2'!A11 -> 盘亏损失（不包括存货盘亏） | B8: ='明细表K13-2'!N11 -> 0 | C8: ='明细表K13-2'!O11 -> 0 | D8: ='明细表K13-2'!P11 -> 0 | E8: =B8+C8+D8 -> 0 | G8: ='明细表K13-2'!U11 -> 0 | H8: ='明细表K13-2'!V11 -> 0 | I8: ='明细表K13-2'!W11 -> 0 | J8: =G8+H8+I8 -> 0
A9: ='明细表K13-2'!A12 -> 非常损失（如自然灾害等非常原因造成的存货毁损） | B9: ='明细表K13-2'!N12 -> 0 | C9: ='明细表K13-2'!O12 -> 0 | D9: ='明细表K13-2'!P12 -> 0 | E9: =B9+C9+D9 -> 0 | G9: ='明细表K13-2'!U12 -> 0 | H9: ='明细表K13-2'!V12 -> 0 | I9: ='明细表K13-2'!W12 -> 0 | J9: =G9+H9+I9 -> 0
A10: ='明细表K13-2'!A13 -> 碳排放配额使用和注销损失 | B10: ='明细表K13-2'!N13 -> 0 | C10: ='明细表K13-2'!O13 -> 0 | D10: ='明细表K13-2'!P13 -> 0 | E10: =B10+C10+D10 -> 0 | G10: ='明细表K13-2'!U13 -> 0 | H10: ='明细表K13-2'!V13 -> 0 | I10: ='明细表K13-2'!W13 -> 0 | J10: =G10+H10+I10 -> 0
A11: ='明细表K13-2'!A14 -> 其他 | B11: ='明细表K13-2'!N14 -> 0 | C11: ='明细表K13-2'!O14 -> 0 | D11: ='明细表K13-2'!P14 -> 0 | E11: =B11+C11+D11 -> 0 | G11: ='明细表K13-2'!U14 -> 0 | H11: ='明细表K13-2'!V14 -> 0 | I11: ='明细表K13-2'!W14 -> 0 | J11: =G11+H11+I11 -> 0
B12: ='明细表K13-2'!N15 -> 0 | C12: ='明细表K13-2'!O15 -> 0 | D12: ='明细表K13-2'!P15 -> 0 | E12: =B12+C12+D12 -> 0 | G12: ='明细表K13-2'!U15 -> 0 | H12: ='明细表K13-2'!V15 -> 0 | I12: ='明细表K13-2'!W15 -> 0 | J12: =G12+H12+I12 -> 0
A13: 合计 | B13: =SUM(B6:B12) -> 0 | C13: =SUM(C6:C12) -> 0 | D13: =SUM(D6:D12) -> 0 | E13: =SUM(E6:E12) -> 0 | G13: =SUM(G6:G12) -> 0 | H13: =SUM(H6:H12) -> 0 | I13: =SUM(I6:I12) -> 0 | J13: =SUM(J6:J12) -> 0
A14: 试算平衡表数
A15: 差异数 | E15: =E13-E14 -> 0 | J15: =J13-J14 -> 0
A17: 提示：关注非经常性损益列报的正确性。非经常性损益是指公司发生的与生产经营无直接关系，以及虽与生产经营相关，但由于其性质、金额或发生频率，影响了真实、公允地评价公司当期经营成果和获利能力的各项收入、支出，通常与自然灾害、搬迁、捐赠等相关的收益或损失应列报为非经常性损益。

Sheet 附注披露信息（上市公司）
A1: 致同会计师事务所
A2: 营业外支出附注披露信息
A3: =底稿目录!A2 -> 被审计单位： | B3: =底稿目录!A4 -> 编制人： | C3: =底稿目录!A5 -> 编制日期： | D3: 索引号： | E3: =底稿目录!F6 -> 0
A4: =底稿目录!A3 -> 会计期间：202X年度 | B4: =底稿目录!A6 -> 复核人： | C4: =底稿目录!A7 -> 复核日期： | D4: 页次：
A5: 营业外支出附注披露信息（上市公司通用）
A6: 营业外支出（注：以下不存在的项目可以删除）
A7: 项 目 | B7: 本期发生额 | C7: 上期发生额 | D7: 计入当期非经常性损益的金额
A8: ='审定表K13-1'!A6 -> 非流动资产毁损报废（扣保险赔款） | B8: ='审定表K13-1'!E6 -> 0 | C8: ='审定表K13-1'!J6 -> 0 | D8: ='明细表K13-2'!R9 -> 0
A9: ='审定表K13-1'!A7 -> 公益性捐赠 | B9: ='审定表K13-1'!E7 -> 0 | C9: ='审定表K13-1'!J7 -> 0 | D9: ='明细表K13-2'!R10 -> 0
A10: ='审定表K13-1'!A8 -> 盘亏损失（不包括存货盘亏） | B10: ='审定表K13-1'!E8 -> 0 | C10: ='审定表K13-1'!J8 -> 0 | D10: ='明细表K13-2'!R11 -> 0
A11: ='审定表K13-1'!A9 -> 非常损失（如自然灾害等非常原因造成的存货毁损） | B11: ='审定表K13-1'!E9 -> 0 | C11: ='审定表K13-1'!J9 -> 0 | D11: ='明细表K13-2'!R12 -> 0
A12: ='审定表K13-1'!A10 -> 碳排放配额使用和注销损失 | B12: ='审定表K13-1'!E10 -> 0 | C12: ='审定表K13-1'!J10 -> 0 | D12: ='明细表K13-2'!R14 -> 0
A13: ='审定表K13-1'!A11 -> 其他 | B13: ='审定表K13-1'!E11 -> 0 | C13: ='审定表K13-1'!J11 -> 0 | D13: ='明细表K13-2'!R15 -> 0
A14: 合 计 | B14: =SUM(B8:B13) -> 0 | C14: =SUM(C8:C13) -> 0 | D14: =SUM(D8:D13) -> 0
A15: 说明：
A16: 【1、“营业外支出”，反映企业发生的营业利润以外的支出，主要包括公益性捐赠支出、非常损失、盘亏损失、非流动资产毁损报废损失等。不包括存货盘亏损失。】
A17: 【2、企业未按规定缴纳残疾人就业保障金，按规定缴纳的滞纳金，计入“营业外支出”科目。】

Sheet 附注披露信息（国企）
A1: 致同会计师事务所
A2: 营业外支出附注披露信息
A3: =底稿目录!A2 -> 被审计单位： | B3: =底稿目录!A4 -> 编制人： | C3: =底稿目录!A5 -> 编制日期： | D3: 索引号： | E3: =底稿目录!F7 -> 0
A4: =底稿目录!A3 -> 会计期间：202X年度 | B4: =底稿目录!A6 -> 复核人： | C4: =底稿目录!A7 -> 复核日期： | D4: 页次：
A5: 营业外支出附注披露信息（国企）
A6: 营业外支出
A7: 项 目 | B7: 本期发生额 | C7: 上期发生额 | D7: 计入当期非经常性损益的金额
A8: ='审定表K13-1'!A6 -> 非流动资产毁损报废（扣保险赔款） | B8: ='审定表K13-1'!E6 -> 0 | C8: ='审定表K13-1'!J6 -> 0 | D8: ='明细表K13-2'!R9 -> 0
A9: ='审定表K13-1'!A7 -> 公益性捐赠 | B9: ='审定表K13-1'!E7 -> 0 | C9: ='审定表K13-1'!J7 -> 0 | D9: ='明细表K13-2'!R10 -> 0
A10: ='审定表K13-1'!A8 -> 盘亏损失（不包括存货盘亏） | B10: ='审定表K13-1'!E8 -> 0 | C10: ='审定表K13-1'!J8 -> 0 | D10: ='明细表K13-2'!R11 -> 0
A11: ='审定表K13-1'!A9 -> 非常损失（如自然灾害等非常原因造成的存货毁损） | B11: ='审定表K13-1'!E9 -> 0 | C11: ='审定表K13-1'!J9 -> 0 | D11: ='明细表K13-2'!R12 -> 0
A12: ='审定表K13-1'!A10 -> 碳排放配额使用和注销损失 | B12: ='审定表K13-1'!E10 -> 0 | C12: ='审定表K13-1'!J10 -> 0 | D12: ='明细表K13-2'!R13 -> 0
A13: 其他 | B13: ='审定表K13-1'!E11 -> 0 | C13: ='审定表K13-1'!J11 -> 0 | D13: ='明细表K13-2'!R14 -> 0
A14: …… | B14: ='审定表K13-1'!E12 -> 0 | C14: ='审定表K13-1'!J12 -> 0 | D14: ='明细表K13-2'!R15 -> 0
A15: 合 计 | B15: =SUM(B8:B14) -> 0 | C15: =SUM(C8:C14) -> 0 | D15: =SUM(D8:D14) -> 0
A16: （注：企业可根据实际情况，单独披露金额较大的项目。）
A17: 【提示：“营业外支出”反映企业发生的营业利润以外的支出，主要包括对外捐赠支出、非流动资产毁损报废损失、非常损失、盘亏损失等。】
A18: 【提示：企业未按规定缴纳残疾人就业保障金，按规定缴纳的滞纳金，计入“营业外支出”科目。】

Sheet 明细表K13-2
A1: 致同会计师事务所
A2: 营业外支出明细表
A3: =底稿目录!A2 -> 被审计单位： | H3: =底稿目录!A4 -> 编制人： | Q3: =底稿目录!A5 -> 编制日期： | Y3: 索引号： | Z3: =底稿目录!F8 -> K13-2
A4: =底稿目录!A3 -> 会计期间：202X年度 | H4: =底稿目录!A6 -> 复核人： | Q4: =底稿目录!A7 -> 复核日期： | Y4: 页次：
A5: 一、审计目标：
A6: 1.利润表中记录的营业外支出已发生，且与被审计单位有关，已记录于恰当的账户。 | H6: 2.所有应当记录的营业外支出均已记录，所有应当包括在财务报表中的相关披露均已包括。 | Q6: 3.与营业外支出有关的金额及其他数据已恰当记录，相关披露已得到恰当计量和描述。
A7: 二、审计过程:
A8: 项目 | B8: 1月 | C8: 2月 | D8: 3月 | E8: 4月 | F8: 5月 | G8: 6月 | H8: 7月 | I8: 8月 | J8: 9月 | K8: 10月 | L8: 11月 | M8: 12月 | N8: 本期合计 | O8: 账项调整 | P8: 重分类调整 | Q8: 期末审定数 | R8: 计入当期非经常性损益的金额 | S8: 与相关科目勾稽 | T8: 结构比 | U8: 上年同期发生数 | V8: 账项调整 | W8: 重分类调整 | X8: 期初审定数 | Y8: 结构比 | Z8: 增长比例
A9: 非流动资产毁损报废（扣保险赔款） | N9: =SUM(B9:M9) -> 0 | Q9: =N9+O9+P9 -> 0 | T9: =IF($Q$16=0,0,Q9/$Q$16) -> 0 | X9: =U9+V9+W9 -> 0 | Y9: =IF($X$16=0,0,X9/$X$16) -> 0 | Z9: =IF(AND(X9=0,Q9>0),1,IF(AND(X9=0,Q9=0),0,(Q9-X9)/X9)) -> 0
A10: 公益性捐赠 | N10: =SUM(B10:M10) -> 0 | Q10: =N10+O10+P10 -> 0 | T10: =IF($Q$16=0,0,Q10/$Q$16) -> 0 | X10: =U10+V10+W10 -> 0 | Y10: =IF($X$16=0,0,X10/$X$16) -> 0 | Z10: =IF(AND(X10=0,Q10>0),1,IF(AND(X10=0,Q10=0),0,(Q10-X10)/X10)) -> 0
A11: 盘亏损失（不包括存货盘亏） | N11: =SUM(B11:M11) -> 0 | Q11: =N11+O11+P11 -> 0 | T11: =IF($Q$16=0,0,Q11/$Q$16) -> 0 | X11: =U11+V11+W11 -> 0 | Y11: =IF($X$16=0,0,X11/$X$16) -> 0 | Z11: =IF(AND(X11=0,Q11>0),1,IF(AND(X11=0,Q11=0),0,(Q11-X11)/X11)) -> 0
A12: 非常损失（如自然灾害等非常原因造成的存货毁损） | N12: =SUM(B12:M12) -> 0 | Q12: =N12+O12+P12 -> 0 | T12: =IF($Q$16=0,0,Q12/$Q$16) -> 0 | X12: =U12+V12+W12 -> 0 | Y12: =IF($X$16=0,0,X12/$X$16) -> 0 | Z12: =IF(AND(X12=0,Q12>0),1,IF(AND(X12=0,Q12=0),0,(Q12-X12)/X12)) -> 0
A13: 碳排放配额使用和注销损失 | N13: =SUM(B13:M13) -> 0 | Q13: =N13+O13+P13 -> 0 | T13: =IF($Q$16=0,0,Q13/$Q$16) -> 0 | X13: =U13+V13+W13 -> 0 | Y13: =IF($X$16=0,0,X13/$X$16) -> 0 | Z13: =IF(AND(X13=0,Q13>0),1,IF(AND(X13=0,Q13=0),0,(Q13-X13)/X13)) -> 0
A14: 其他 | N14: =SUM(B14:M14) -> 0 | Q14: =N14+O14+P14 -> 0 | T14: =IF($Q$16=0,0,Q14/$Q$16) -> 0 | X14: =U14+V14+W14 -> 0 | Y14: =IF($X$16=0,0,X14/$X$16) -> 0 | Z14: =IF(AND(X14=0,Q14>0),1,IF(AND(X14=0,Q14=0),0,(Q14-X14)/X14)) -> 0
A15: …… | N15: =SUM(B15:M15) -> 0 | Q15: =N15+O15+P15 -> 0 | T15: =IF($Q$16=0,0,Q15/$Q$16) -> 0 | X15: =U15+V15+W15 -> 0 | Y15: =IF($X$16=0,0,X15/$X$16) -> 0 | Z15: =IF(AND(X15=0,Q15>0),1,IF(AND(X15=0,Q15=0),0,(Q15-X15)/X15)) -> 0
A16: 合计 | B16: =SUM(B9:B15) -> 0 | C16: =SUM(C9:C15) -> 0 | D16: =SUM(D9:D15) -> 0 | E16: =SUM(E9:E15) -> 0 | F16: =SUM(F9:F15) -> 0 | G16: =SUM(G9:G15) -> 0 | H16: =SUM(H9:H15) -> 0 | I16: =SUM(I9:I15) -> 0 | ... S16: =SUM(S9:S15) -> 0 | T16: =IF($Q$16=0,0,Q16/$Q$16) -> 0 | U16: =SUM(U9:U15) -> 0 | V16: =SUM(V9:V15) -> 0 | W16: =SUM(W9:W15) -> 0 | X16: =SUM(X9:X15) -> 0 | Y16: =IF($X$16=0,0,X16/$X$16) -> 0 | Z16: =IF(AND(X16=0,Q16>0),1,IF(AND(X16=0,Q16=0),0,(Q16-X16)/X16)) -> 0
A17: 各月比例 | B17: =IF($N$16=0,0,B16/$N$16) -> 0 | C17: =IF($N$16=0,0,C16/$N$16) -> 0 | D17: =IF($N$16=0,0,D16/$N$16) -> 0 | E17: =IF($N$16=0,0,E16/$N$16) -> 0 | F17: =IF($N$16=0,0,F16/$N$16) -> 0 | G17: =IF($N$16=0,0,G16/$N$16) -> 0 | H17: =IF($N$16=0,0,H16/$N$16) -> 0 | I17: =IF($N$16=0,0,I16/$N$16) -> 0 | ... N17: =IF($N$16=0,0,N16/$N$16) -> 0
A18: 三、审计说明：
A21: 四、审计结论：
A25: 编制说明：
A26: 1、本科目核算企业发生的各项营业外支出，包括非流动资产处置损失、非货币性资产交换损失、债务重组损失、公益性捐赠支出、非常损失、盘亏损失等。

Sheet 调整分录汇总K13-3
A1: 致同会计师事务所
A2: 营业外支出调整分录汇总表
A3: =底稿目录!A2 -> 被审计单位： | C3: =底稿目录!A4 -> 编制人： | G3: =底稿目录!A5 -> 编制日期： | I3: 索引： | J3: =底稿目录!F9 -> K13-3
A4: =底稿目录!A3 -> 会计期间：202X年度 | C4: =底稿目录!A6 -> 复核人： | G4: =底稿目录!A7 -> 复核日期： | I4: 页次：
A5: 调整事项说明 | B5: 类别（报表调整/账项调整/其他） | C5: 报表项目 | D5: 科目名称 | E5: 附注项目 | F5: …… | G5: 借方调整金额 | H5: 贷方调整金额 | I5: 索引 | J5: 备注
A23: 提示：本底稿适用于调整分录较多、较复杂的项目，且仅列示与本报表项目相关的审计调整。项目组可根据项目实际情况选择是否使用该底稿。

Sheet 营业外支出检查表K13-4
A1: 致同会计师事务所
A2: 营业外支出检查表
A3: =底稿目录!A2 -> 被审计单位： | F3: =底稿目录!A4 -> 编制人： | I3: =底稿目录!A5 -> 编制日期： | P3: 索引号： | Q3: =底稿目录!F10 -> K13-4
A4: =底稿目录!A3 -> 会计期间：202X年度 | F4: =底稿目录!A6 -> 复核人： | I4: =底稿目录!A7 -> 复核日期： | P4: 页 次：
A5: 一、测试目标：
A6: 1.所有应当记录的营业外支出均已记录，所有应当包括在财务报表中的相关披露均已包括;
A7: 2.与营业外支出有关的金额及其他数据已恰当记录，相关披露已得到恰当计量和描述； 3. 营业外支出已记录于正确的会计期间
A8: 二、测试： | C8: 测试原因：大额（）关联方（）大额交易频繁（）异常（）其他（）
A9: 测试内容说明：1.原始凭证是否齐全； 2.记账凭证与原始凭证是否相符；3.账务处理是否正确；4.是否记录于恰当的会计期间；5.……
A10: 明细项目 | B10: 记账凭证 | H10: 支持性文件 | J10: 核对内容 | O10: 索引号 | P10: 是否异常 | Q10: 备注说明
B11: 日期 | C11: 凭证编号 | D11: 业务内容 | E11: 对方科目 | F11: 对方明细科目 | G11: 借方金额 | J11: 1 | K11: 2 | L11: 3 | M11: 4 | N11: 5
H12: 付款审批单、支出凭单、银行回单……
A22: 合计 | G22: =SUM(G12:G21) -> 0
A23: 本期发生额 | G23: ='明细表K13-2'!Q16 -> 0
A24: 检查比例 | G24: =G22/G23 -> #DIV/0!
A25: 三、审计说明：
A28: 四、审计结论：

Sheet GT_Custom
A1: C1 | B1: Custom 1
A2: C2 | B2: Custom 2
A3: C3 | B3: Custom 3
A4: C4 | B4: Custom 4
A5: C5 | B5: Custom 5
A6: C6 | B6: Custom 6
A7: C7 | B7: Custom 7
A8: C8 | B8: Custom 8
