Workbook

Sheet 底稿目录
A1: 底稿开列时，可先在以下单元格填写有关内容，以便其他底稿引用有关数据：
A2: 被审计单位：
A3: 截止日：202X年12月31日 | D3: 序号 | E3: 内容 | F3: 索引号 | G3: 备注
A4: 编制人： | D4: 1 | E4: 实质性程序表 | F4: K3A
A5: 编制日期： | D5: 2 | E5: 审定表 | F5: K3-1
A6: 复核人： | D6: 3 | E6: 附注披露信息(上市公司) | H6: 无需打印
A7: 复核日期： | D7: 4 | E7: 附注披露信息(国企) | H7: 无需打印
A8: 款项性质类别设置（以下内容请根据实际情况修改）： | D8: 5 | E8: 明细表 | F8: K3-2
A9: 押金 | D9: 6 | E9: 调整分录汇总 | F9: K3-3
A10: 保证金 | D10: 7 | E10: 大额其他应付款情况分析表 | F10: K3-4
A11: 其他 | D11: 8 | E11: 函证结果汇总表 | F11: K0-1
A12: …… | D12: 9 | E12: 核实被函证单位信息 | F12: K0-2
D13: 10 | E13: 跟函函证过程控制 | F13: K0-3
D14: 11 | E14: 函证差异调节表 | F14: K0-4
D15: 12 | E15: 其他应付款替代程序检查表 | F15: K0-6
D16: 13 | E16: 邮件传真回函可靠性验证 | F16: K0-7
A17: 关联方类别设置（以下内容请根据实际情况修改）： | D17: 14 | E17: 函证程序舞弊风险评价表 | F17: K0-8
A18: 关联方（合并范围内） | D18: 16 | E18: 长期挂账检查表 | F18: K3-5
A19: 关联方（合并范围外） | D19: 17 | E19: 关联方及交易检查表 | F19: K3-6
A20: 非关联方 | D20: 18 | E20: 其他应付款检查表 | F20: K3-7
A21: ……
A26: 关于工作底稿与审计程序索引号对应的说明
A27: 1.编制的审计工作底稿应与审计程序对应。审计项目组应根据被审计单位实际情况和风险评估情况在实质性程序表中裁剪、修改或增加审计程序，根据实际执行的审计程序完成相应审计工作底稿，编制的工作底稿中应按自然顺序依次编制索引号，并通过唯一的索引号将与实质性程序表中的程序对应关联（即将工作底稿的索引号填入实质性程序表中的底稿索引号列）。
A31: 2.获取的支持性证据应与审计底稿或程序对应。审计项目组在完成底稿时获取的支持性证据应根据底稿索引号编制下一级按自然顺序排序的索引号（如D1-2-1、D1-2-2、……），并在底稿中说明引用的支持性证据、关联索引号。
A34: 3.工作底稿索引号的编码规则：实质性程序索引号按循环从“D”到“N”,循环内账户以顺序号排列，模板中底稿索引号按账户顺序+自然数顺序（即模板中索引号按二级自然顺序排列，如D1-1、D1-2、D1-3、……D1-N）。

Sheet 实质性程序表K3A
A1: 致同会计师事务所
A2: 其他应付款实质性程序
A3: =底稿目录!A2 -> 被审计单位： | C3: =底稿目录!A4 -> 编制人： | E3: =底稿目录!A5 -> 编制日期： | H3: 索引号： | I3: =底稿目录!F4 -> K3A
A4: 会计期间：202X年度 | C4: =底稿目录!A6 -> 复核人： | E4: =底稿目录!A7 -> 复核日期： | H4: 页 次：
A5: 一、本账户涉及的科目
A6: 其他应付款
A7: 二、审计目标与认定的对应关系
A8: 审计目标 | G8: 财务报表的认定
A9: A. 资产负债表中记录的其他应付款是存在的，且已记录于恰当的账户 | G9: 存在
A10: B. 所有应记录的其他应付款均已记录，所有应当包括在财务报表中的相关披露均已包括 | G10: 完整性
A11: C. 记录的其他应付款是被审计单位应当履行的偿还义务 | G11: 权利和义务
A12: D. 其他应付款以恰当的金额包括在财务报表中，与之相关的计价或分摊调整已恰当记录，相关披露已得到恰当计量和描述 | G12: 准确性、计价和分摊
A13: E. 其他应付款已被恰当地汇总或分解且表述清楚，相关披露在按照企业会计准则的编制基础下是相关的、可理解的 | G13: 列报
A14: 三、计划实施的实质性程序
A15: 序号 | B15: 审计程序 | C15: 程序分类 | D15: 财务报表的认定 | I15: 底稿索引号
D16: 存在 | E16: 完整性 | F16: 权利和 义务 | G16: 准确性、计价和分摊 | H16: 列报 | J16: 根据被审计单位实际情况和风险评估情况裁剪、修改或增加审计程序
A17: 1 | B17: 获取或编制明细表、执行下列程序，并编制审定表： （1）复核加计正确，并与总账数和明细账合计数核对是否相符，期初余额与上期审定期末余额是否相符； （2）获取管理层编制的预付账款账龄分析表，检查账龄划分是否正确； （3）结合应收账款、其他应收款等明细余额，检查是否有同时挂账的项目，核算内容是否重复，分析有借方余额的项目，查明原因，必要时作出适当调整。 （4）检查非记账本位币其他应付款的折算汇率及折算是否正确。（如适用） （5）分析期末余期与期初余额各款项性质占比变动是否合理、账龄的结构是否合理； | C17: 常规★ | D17: √ | E17: √ | G17: √ | I17: K3-1 /K3-2
A18: 2 | B18: 在使用手工编制、自定义信息报告、系统生成的非固定格式报告等由被审计单位生成的信息时，测试有关信息准确性和完整性，并考虑针对编制和维护由被审计单位生成的信息的相关控制实施控制测试，以评价该信息是否能够为实现审计目的提供基础。 | C18: 常规★ | E18: √ | G18: √ | I18: T1 /K0-2 / | J18: 可参见《审计手册》4.2.6，由被审计单位生成的信息可能是由系统生成的、或手工编制的、或二者兼而有之的方式生成的。例如，由被审计单位生成的信息可能包括： • 不涉及自定义的、由系统生成的报告（如，固定格式报告）； • 可能通过人工自定义的、由系统生成的报告，例如，（计算机）查询信息或特别定制的报告； • 手工编制的信息，例如，汇总信息的电子表格或用以支持分配、计算以及调节的电子表格； • 其他系统生成或手工编制的信息，例如，由被审计单位编制的客户发票； • 通过影印、拍摄、扫描或其他方式转换成电子形式的文件记录。
A19: 3 | B19: 对期初余额的审计，获取上期期末的其他应付款明细，复核加计正确，总账与明细账核对一致；识别重大的明细项目、查找异常项目并了解该明细项目的核算目的和用途；检查上期其他应付款在本期支付情况；函证期初余额以及其他必要追加的审计程序。（适用于首次承接） | C19: 备选 | D19: √ | E19: √ | F19: √ | G19: √ | J19: 由被审计单位生成的信息不包括： • 总分类账或明细分类账、试算平衡表、或经审计的财务报表； • 第三方（除了服务机构）的报表或报告，例如，原始银行对账单，或函证的回函； • 外部数据（例如，第三方发布的数据，如，定价来源）。
A20: 4 | B20: 关注会计政策、会计估计合理性、一贯性。关注其是否利用会计政策和会计估计及其变更操纵利润。 | C20: 常规★ | D20: √ | E20: √ | G20: √ | I20: F1-1 /F1-2
A21: 5 | B21: 分析主要债权人其他应收款期末余额，关注期末大额其他应付款商业合理性、真实性、期后支付情况。关注大额代收、代付性质款项，是否具有合理的交易目的等。 | C21: 常规★ | D21: √ | G21: √ | I21: K3-4
A22: 6 | B22: 实施函证程序： （1）以积极方式对其他应付款进行函证，设计询证函、发函前核实被函证单位信息； （2）注册会计师独立收发询证函； （3）编制函证结果汇总表，检查发函、回函物流信息和轨迹、比对回函印章和签字以核实回函的真实性，检查回函是否相符，对不符事项查明原因确定是否存在错报； （4）如果未收到回函，应当考虑与被询证者联系，要求对方作出回应或再次寄发询证函，无法收到回函的实施替代程序； （5）如果管理层不允许寄发询证函的，询问管理层不允许寄发的原因，并就其原因的正当、合理性收集证据；考虑实施替代审计程序以获取相关、可靠的审计证据； （6）如果管理层不允许寄发询证函的原因不合理、或者认为回函不可靠，评价对评估的重大错报风险以及其他审计程序的性质、时间安排和范围的影响，并确定其对审计工作和审计意见的影响。 | C22: 常规★ | D22: √ | E22: √ | F22: √ | G22: √ | I22: K0
A23: 7 | B23: 针对报告期内账龄较长的其他应付款：应当分析账龄较长的原因，是否双方有纠纷等，考虑负债计提是否充分；是否存在无需支付（如不合理的往来款挂账）的情况，确认会计处理是否正确，必要时进行函证。 | C23: 常规★ | D23: √ | G23: √ | I23: K3-5
A24: 8 | B24: 检查关联方款项： （1）了解交易的商业理由、交易事项的目的、价格和条件，考虑对关联方其他应付款的合理性、合法性；结合费用科目审计，关注是否存在关联方代被审计单位支付成本费用的等情况；关注是否存在向大股东或实际控制人及其关联方借款，资金占用费计算是否公允； （2）检查对关联方其他应收账款的真实性相关的支持性文件、检查会计处理是否正确； （3）向关联方函证往来余额，必要时函证交易的条件和发生额（包括担保和其他重要信息）； （4）必要时，向与交易相关的人员和机构（如银行、律师）函证或与其讨论有关信息； （5）考虑是否存在未识别的关联方，关联交易和余额披露是否正确。 | C24: 常规★ | D24: √ | E24: √ | F24: √ | G24: √ | H24: √ | I24: K3-6 /K3-7 /K0
A25: 9 | B25: 检查与其他应付款有关的的记账凭证和相应的支持性证据以确定交易的真实性，是否按规定进行相应的会计处理和披露。 | C25: 常规★ | D25: √ | F25: √ | G25: √ | I25: K3-19
A26: 10 | B26: 考虑是否存在超出被审计单位正常经营活动的重大、异常交易等，根据评估的舞弊风险等因素增加的审计程序。 | C26: IPO/上市/新三板/重组/舞弊应对
A27: 11 | B27: 检查其他应付款是否已按企业会计准则或其他适用的规定在财务报表中做出恰当列报和披露。 | C27: 常规★ | H27: √ | I27: A1-1/A1-15 /A1-16

Sheet 审定表K3-1
A1: 致同会计师事务所
A2: 其他应付款审定表
A3: =底稿目录!A2 -> 被审计单位： | E3: =底稿目录!A4 -> 编制人： | H3: =底稿目录!A5 -> 编制日期： | J3: 索引： | K3: =底稿目录!F5 -> K3-1
A4: =底稿目录!A3 -> 截止日：202X年12月31日 | E4: =底稿目录!A6 -> 复核人： | H4: =底稿目录!A7 -> 复核日期： | J4: 页次： | K4: 1
A5: 一、按照性质分类
A6: 项目 | B6: 期初数 | F6: 期末数 | J6: 本期审定数与上期 审定数的比较
B7: 未审数 | C7: 账项调整 | D7: 重分类调整 | E7: 审定数 | F7: 未审数 | G7: 账项调整 | H7: 重分类调整 | I7: 审定数 | J7: 变动额 | K7: 变动率
A8: =底稿目录!A9 -> 押金 | B8: =SUMIF('明细表K3-2'!$D$10:$D$30,'审定表K3-1'!A8,'明细表K3-2'!$E$10:$E$30) -> 0 | C8: =SUMIF('明细表K3-2'!$D$10:$D$30,'审定表K3-1'!A8,'明细表K3-2'!$F$10:$F$30) -> 0 | D8: =SUMIF('明细表K3-2'!$D$10:$D$30,'审定表K3-1'!A8,'明细表K3-2'!$G$10:$G$30) -> 0 | E8: =B8+C8+D8 -> 0 | F8: =SUMIF('明细表K3-2'!$D$10:$D$30,'审定表K3-1'!A8,'明细表K3-2'!$O$10:$O$30) -> 0 | G8: =SUMIF('明细表K3-2'!$D$10:$D$30,'审定表K3-1'!A8,'明细表K3-2'!$R$10:$R$30) -> 0 | H8: =SUMIF('明细表K3-2'!$D$10:$D$30,'审定表K3-1'!A8,'明细表K3-2'!$S$10:$S$30) -> 0 | I8: =F8+G8+H8 -> 0 | J8: =I8-E8 -> 0 | K8: =IF(AND(E8=0,J8=0),0,IF(AND(E8=0,J8>0),1,J8/E8)) -> 0
A9: =底稿目录!A10 -> 保证金 | B9: =SUMIF('明细表K3-2'!$D$10:$D$30,'审定表K3-1'!A9,'明细表K3-2'!$E$10:$E$30) -> 0 | C9: =SUMIF('明细表K3-2'!$D$10:$D$30,'审定表K3-1'!A9,'明细表K3-2'!$F$10:$F$30) -> 0 | D9: =SUMIF('明细表K3-2'!$D$10:$D$30,'审定表K3-1'!A9,'明细表K3-2'!$G$10:$G$30) -> 0 | E9: =B9+C9+D9 -> 0 | F9: =SUMIF('明细表K3-2'!$D$10:$D$30,'审定表K3-1'!A9,'明细表K3-2'!$O$10:$O$30) -> 0 | G9: =SUMIF('明细表K3-2'!$D$10:$D$30,'审定表K3-1'!A9,'明细表K3-2'!$R$10:$R$30) -> 0 | H9: =SUMIF('明细表K3-2'!$D$10:$D$30,'审定表K3-1'!A9,'明细表K3-2'!$S$10:$S$30) -> 0 | I9: =F9+G9+H9 -> 0 | J9: =I9-E9 -> 0 | K9: =IF(AND(E9=0,J9=0),0,IF(AND(E9=0,J9>0),1,J9/E9)) -> 0
A10: =底稿目录!A11 -> 其他 | B10: =SUMIF('明细表K3-2'!$D$10:$D$30,'审定表K3-1'!A10,'明细表K3-2'!$E$10:$E$30) -> 0 | C10: =SUMIF('明细表K3-2'!$D$10:$D$30,'审定表K3-1'!A10,'明细表K3-2'!$F$10:$F$30) -> 0 | D10: =SUMIF('明细表K3-2'!$D$10:$D$30,'审定表K3-1'!A10,'明细表K3-2'!$G$10:$G$30) -> 0 | E10: =B10+C10+D10 -> 0 | F10: =SUMIF('明细表K3-2'!$D$10:$D$30,'审定表K3-1'!A10,'明细表K3-2'!$O$10:$O$30) -> 0 | G10: =SUMIF('明细表K3-2'!$D$10:$D$30,'审定表K3-1'!A10,'明细表K3-2'!$R$10:$R$30) -> 0 | H10: =SUMIF('明细表K3-2'!$D$10:$D$30,'审定表K3-1'!A10,'明细表K3-2'!$S$10:$S$30) -> 0 | I10: =F10+G10+H10 -> 0 | J10: =I10-E10 -> 0 | K10: =IF(AND(E10=0,J10=0),0,IF(AND(E10=0,J10>0),1,J10/E10)) -> 0
A11: 合计 | B11: =SUM(B8:B10) -> 0 | C11: =SUM(C8:C10) -> 0 | D11: =SUM(D8:D10) -> 0 | E11: =SUM(E8:E10) -> 0 | F11: =SUM(F8:F10) -> 0 | G11: =SUM(G8:G10) -> 0 | H11: =SUM(H8:H10) -> 0 | I11: =SUM(I8:I10) -> 0 | J11: =SUM(J8:J10) -> 0 | K11: =IF(AND(E11=0,J11=0),0,IF(AND(E11=0,J11>0),1,J11/E11)) -> 0
A12: TB数据：
A13: 差异： | B13: =B11-B12 -> 0 | C13: =C11-C12 -> 0 | D13: =D11-D12 -> 0 | E13: =E11-E12 -> 0 | F13: =F11-F12 -> 0 | G13: =G11-G12 -> 0 | H13: =H11-H12 -> 0 | I13: =I11-I12 -> 0
A14: 二、按照账龄分类
A15: 项目 | B15: 期初数 | F15: 期末数 | J15: 本期审定数与上期 审定数的比较
B16: 未审数 | C16: 账项调整 | D16: 重分类调整 | E16: 审定数 | F16: 未审数 | G16: 账项调整 | H16: 重分类调整 | I16: 审定数 | J16: 变动额 | K16: 变动率
A17: 1年以内（含1年） | E17: ='明细表K3-2'!I31 -> 0 | I17: ='明细表K3-2'!U31 -> 0 | J17: =I17-E17 -> 0 | K17: =IF(AND(E17=0,J17=0),0,IF(AND(E17=0,J17>0),1,J17/E17)) -> 0
A18: 1至2年（含2年） | E18: ='明细表K3-2'!J31 -> 0 | I18: ='明细表K3-2'!V31 -> 0 | J18: =I18-E18 -> 0 | K18: =IF(AND(E18=0,J18=0),0,IF(AND(E18=0,J18>0),1,J18/E18)) -> 0
A19: 2至3年（含3年） | E19: ='明细表K3-2'!K31 -> 0 | I19: ='明细表K3-2'!W31 -> 0 | J19: =I19-E19 -> 0 | K19: =IF(AND(E19=0,J19=0),0,IF(AND(E19=0,J19>0),1,J19/E19)) -> 0
A20: 3年以上 | E20: ='明细表K3-2'!L31 -> 0 | I20: ='明细表K3-2'!X31 -> 0 | J20: =I20-E20 -> 0 | K20: =IF(AND(E20=0,J20=0),0,IF(AND(E20=0,J20>0),1,J20/E20)) -> 0
A22: 合计 | B22: =SUM(B17:B21) -> 0 | C22: =SUM(C17:C21) -> 0 | D22: =SUM(D17:D21) -> 0 | E22: =SUM(E17:E21) -> 0 | F22: =SUM(F17:F21) -> 0 | G22: =SUM(G17:G21) -> 0 | H22: =SUM(H17:H21) -> 0 | I22: =SUM(I17:I21) -> 0 | J22: =SUM(J17:J21) -> 0 | K22: =IF(AND(E22=0,J22=0),0,IF(AND(E22=0,J22>0),1,J22/E22)) -> 0
A23: TB数据：
A24: 差异： | B24: =B22-B23 -> 0 | C24: =C22-C23 -> 0 | D24: =D22-D23 -> 0 | E24: =E22-E23 -> 0 | F24: =F22-F23 -> 0 | G24: =G22-G23 -> 0 | H24: =H22-H23 -> 0 | I24: =I22-I23 -> 0
A25: 1.审计说明 | F25: （3）与经审计的财务报表核对
A26: （1）其他应付款本期较上期增加（负数为减少）： | G26: 期末数 | H26: 期初数 | I26: 索引号
A27: 主要原因（比例超过30%的）： | F27: 应付利息审定数 | I27: P2
A28: （2）情况说明。 | F28: 应付股利审定数 | I28: Q1
F29: 其他应付款审定数 | G29: =I11 -> 0 | H29: =E11 -> 0
F30: 其他应付款合计数 | G30: =SUM(G27:G29) -> 0 | H30: =SUM(H27:H29) -> 0
F31: 报表数 | I31: A3-1
F32: 差异 | G32: =G30-G31 -> 0 | H32: =H30-H31 -> 0
A34: 2.审计结论

Sheet 附注披露信息(上市公司)
A1: 致同会计师事务所
A2: 其他应付款附注披露信息（上市公司）
A3: =底稿目录!A2 -> 被审计单位： | B3: =底稿目录!A4 -> 编制人： | C3: =底稿目录!A5 -> 编制日期： | D3: 索引号： | E3: =底稿目录!F6 -> 0
A4: =底稿目录!A3 -> 截止日：202X年12月31日 | B4: =底稿目录!A6 -> 复核人： | C4: =底稿目录!A7 -> 复核日期： | D4: 页次：
A5: 其他应付款
A6: 项目 | B6: 期末数 | C6: 期初数
A7: 应付利息
A8: 应付股利
A9: 其他应付款 | B9: =B17 -> 0 | C9: =C17 -> 0
A10: 合计 | B10: =SUM(B7:B9) -> 0 | C10: =SUM(C7:C9) -> 0
A11: （1）其他应付款（按款项性质列示）
A12: 项 目 | B12: 期末数 | C12: 上年年末数
A13: 押金 | B13: ='审定表K3-1'!I8 -> 0 | C13: ='审定表K3-1'!E8 -> 0
A14: 保证金 | B14: ='审定表K3-1'!I9 -> 0 | C14: ='审定表K3-1'!E9 -> 0
A15: 其他 | B15: ='审定表K3-1'!I10 -> 0 | C15: ='审定表K3-1'!E10 -> 0
A16: 可无限量添加行
A17: 合 计 | B17: =SUM(B13:B16) -> 0 | C17: =SUM(C13:C16) -> 0
A18: 其中，账龄超过1年的重要其他应付款
A19: 项目 | B19: 金额 | C19: 未偿还或未结转的原因
A20: ='长期挂账检查表K3-5'!A9 -> 0 | B20: ='长期挂账检查表K3-5'!I9 -> 0 | C20: ='长期挂账检查表K3-5'!E9 -> 0
A21: ='长期挂账检查表K3-5'!A12 -> 0 | B21: ='长期挂账检查表K3-5'!I12 -> 0 | C21: ='长期挂账检查表K3-5'!E12 -> 0
A22: ='长期挂账检查表K3-5'!A13 -> 0 | B22: ='长期挂账检查表K3-5'!I13 -> 0 | C22: ='长期挂账检查表K3-5'!E13 -> 0
A23: 合 计 | B23: =SUM(B20:B22) -> 0

Sheet 附注披露信息(国企)
A1: 致同会计师事务所
A2: 其他应付款附注披露信息（国企）
A3: =底稿目录!A2 -> 被审计单位： | B3: =底稿目录!A4 -> 编制人： | C3: =底稿目录!A5 -> 编制日期： | D3: 索引号： | E3: =底稿目录!F7 -> 0
A4: =底稿目录!A3 -> 截止日：202X年12月31日 | B4: =底稿目录!A6 -> 复核人： | C4: =底稿目录!A7 -> 复核日期： | D4: 页次：
A5: 其他应付款
A6: 项目 | B6: 期末数 | C6: 期初数
A7: 应付利息
A8: 应付股利
A9: 其他应付款 | B9: =B17 -> 0 | C9: =C17 -> 0
A10: 合计 | B10: =SUM(B7:B9) -> 0 | C10: =SUM(C7:C9) -> 0
A11: （1）其他应付款（按款项性质列示）
A12: 账 龄 | B12: 期末余额 | C12: 期初余额
A13: 押金 | B13: ='审定表K3-1'!I8 -> 0 | C13: ='审定表K3-1'!E8 -> 0
A14: 保证金 | B14: ='审定表K3-1'!I9 -> 0 | C14: ='审定表K3-1'!E9 -> 0
A15: 其他 | B15: ='审定表K3-1'!I10 -> 0 | C15: ='审定表K3-1'!E10 -> 0
A16: 可无限量添加行
A17: 合 计 | B17: =SUM(B13:B16) -> 0 | C17: =SUM(C13:C16) -> 0
A18: 其中，账龄超过1年的重要其他应付款
A19: 债权单位名称 | B19: 期末余额 | C19: 未偿还原因
A20: ='长期挂账检查表K3-5'!A9 -> 0 | B20: ='长期挂账检查表K3-5'!I9 -> 0 | C20: ='长期挂账检查表K3-5'!E9 -> 0
A21: ='长期挂账检查表K3-5'!A12 -> 0 | B21: ='长期挂账检查表K3-5'!I12 -> 0 | C21: ='长期挂账检查表K3-5'!E12 -> 0
A22: ='长期挂账检查表K3-5'!A13 -> 0 | B22: ='长期挂账检查表K3-5'!I13 -> 0 | C22: ='长期挂账检查表K3-5'!E13 -> 0
A23: 合计 | B23: =SUM(B20:B22) -> 0

Sheet 明细表K3-2
A1: 致同会计师事务所
A2: 其他应付款明细表
A3: =底稿目录!A2 -> 被审计单位： | I3: =底稿目录!A4 -> 编制人： | R3: =底稿目录!A5 -> 编制日期： | Z3: 索引号： | AA3: =底稿目录!F8 -> K3-2
A4: =底稿目录!A3 -> 截止日：202X年12月31日 | I4: =底稿目录!A6 -> 复核人： | R4: =底稿目录!A7 -> 复核日期： | Z4: 页次：
A5: 一、审计目标:
A6: 1.资产负债表中记录的其他应付款是存在的，且已记录于恰当的账户。 | F6: 2.所有应记录的其他应付款均已记录，所有应当包括在财务报表中的相关披露均已包括。 | M6: 3.其他应付款以恰当的金额包括在财务报表中，与之相关的计价或分摊调整已恰当记录，相关披露已得到恰当计量和描述。
A7: 二、审计过程：
A8: 债权人名称 | B8: 公司代码 | C8: 关联方类型 | D8: 款项性质 | E8: 期初未审数 | F8: 期初账项调整 | G8: 期初重分类调整 | H8: 期初审定 | I8: 期初审定账龄 | M8: 借方发生 | N8: 贷方发生 | O8: 期末余额 | P8: 被审计单位重分类调整 | Q8: 期末未审余额 | R8: 账项调整 | S8: 重分类调整 | T8: 审定数 | U8: 审定账龄 | Y8: 是否函证 | Z8: 期后付款 | AA8: 备注
C9: 关联方类型 | D9: 款项性质 | I9: 1年以内 | J9: 1-2年 | K9: 2-3年 | L9: 3年以上 | Q9: 期末余额 | U9: 1年以内 | V9: 1-2年 | W9: 2-3年 | X9: 3年以上
H10: =E10+F10+G10 -> 0 | O10: =E10-M10+N10 -> 0 | Q10: =O10+P10 -> 0 | T10: =O10+R10+S10 -> 0
H11: =E11+F11+G11 -> 0 | O11: =E11-M11+N11 -> 0 | Q11: =O11+P11 -> 0 | T11: =O11+R11+S11 -> 0
H12: =E12+F12+G12 -> 0 | O12: =E12-M12+N12 -> 0 | Q12: =O12+P12 -> 0 | T12: =O12+R12+S12 -> 0
H13: =E13+F13+G13 -> 0 | O13: =E13-M13+N13 -> 0 | Q13: =O13+P13 -> 0 | T13: =O13+R13+S13 -> 0
H14: =E14+F14+G14 -> 0 | O14: =E14-M14+N14 -> 0 | Q14: =O14+P14 -> 0 | T14: =O14+R14+S14 -> 0
H15: =E15+F15+G15 -> 0 | O15: =E15-M15+N15 -> 0 | Q15: =O15+P15 -> 0 | T15: =O15+R15+S15 -> 0
H16: =E16+F16+G16 -> 0 | O16: =E16-M16+N16 -> 0 | Q16: =O16+P16 -> 0 | T16: =O16+R16+S16 -> 0
H17: =E17+F17+G17 -> 0 | O17: =E17-M17+N17 -> 0 | Q17: =O17+P17 -> 0 | T17: =O17+R17+S17 -> 0
H18: =E18+F18+G18 -> 0 | O18: =E18-M18+N18 -> 0 | Q18: =O18+P18 -> 0 | T18: =O18+R18+S18 -> 0
H19: =E19+F19+G19 -> 0 | O19: =E19-M19+N19 -> 0 | Q19: =O19+P19 -> 0 | T19: =O19+R19+S19 -> 0
H20: =E20+F20+G20 -> 0 | O20: =E20-M20+N20 -> 0 | Q20: =O20+P20 -> 0 | T20: =O20+R20+S20 -> 0
H21: =E21+F21+G21 -> 0 | O21: =E21-M21+N21 -> 0 | Q21: =O21+P21 -> 0 | T21: =O21+R21+S21 -> 0
... H30: =E30+F30+G30 -> 0 | O30: =E30-M30+N30 -> 0 | Q30: =O30+P30 -> 0 | T30: =O30+R30+S30 -> 0
A31: 合计 | E31: =SUM(E10:E30) -> 0 | F31: =SUM(F10:F30) -> 0 | G31: =SUM(G10:G30) -> 0 | H31: =SUM(H10:H30) -> 0 | I31: =SUM(I10:I30) -> 0 | J31: =SUM(J10:J30) -> 0 | K31: =SUM(K10:K30) -> 0 | L31: =SUM(L10:L30) -> 0 | ... X31: =SUM(X10:X30) -> 0 | Z31: =SUM(Z10:Z30) -> 0
A32: 账龄占比 | H32: =IF((ROUND(H31-I31-J31-K31-L31,2))=0,"OK","账龄与审定不匹配") -> OK | I32: =IF(I31=0,"",I31/$H$31) | J32: =IF(J31=0,"",J31/$H$31) | K32: =IF(K31=0,"",K31/$H$31) | L32: =IF(L31=0,"",L31/$H$31) | T32: =IF((ROUND(T31-U31-V31-W31-X31,2))=0,"OK","账龄与审定不匹配") -> OK | U32: =IF(U31=0,"",U31/$T$31) | V32: =IF(V31=0,"",V31/$T$31) | W32: =IF(W31=0,"",W31/$T$31) | X32: =IF(X31=0,"",X31/$T$31)
A33: 账龄逻辑校验 | T33: =T31-SUM(U31:X31) -> 0 | V33: =IF(V31<=I31,TRUE,FALSE) -> TRUE | W33: =IF(W31<=J31,TRUE,FALSE) -> TRUE | X33: =IF(X31<=(K31+L31),TRUE,FALSE) -> TRUE
A34: 三、审计说明：
A35: 1.期初数与上期审定数一致,期末总账、明细账、报表相符。
A36: 2.与期初相比，期末余额变动较大的原因：
A37: 3.**其他应付款发生额大，其主要原因列示如下：
A38: 4.超过1年的大额其他应付款，其性质及发生原因如下：
A39: 5.检查其他应收款、其他应付款各明细项目的性质，对于大额的代收、代付性质款项，检查相关合同、银行单据等支持性文件，必要时与客户取得沟通，向客户函证等，判断是否具有合理的交易目的。
A40: 四、审计结论：
A42: 提示
A43: 1.审计说明可以概述：（1）程序的测试情况、结果；（2）拟调整事项及其调整分录、未调整事项及其影响，审计范围受到限制情况及其影响。
A44: 2.审计结论可参考：A、未见异常。 B、除上述重大不符事项应当作为调整事项予以调整外，其余未见异常。 C、由于存在以下重大未调整事项（或审计范围受到限制无法获取充分、适当证据），不可确认。

Sheet 调整分录汇总K3-3
A1: 致同会计师事务所
A2: 其他应付款调整分录汇总表
A3: =底稿目录!A2 -> 被审计单位： | C3: =底稿目录!A4 -> 编制人： | F3: =底稿目录!A5 -> 编制日期： | I3: 索引号： | J3: =底稿目录!F9 -> K3-3
A4: =底稿目录!A3 -> 截止日：202X年12月31日 | C4: =底稿目录!A6 -> 复核人： | F4: =底稿目录!A7 -> 复核日期： | I4: 页次：
A5: 调整事项说明 | B5: 类别（报表调整/账项调整/其他） | C5: 报表项目 | D5: 科目名称 | E5: 附注项目 | F5: …… | G5: 借方调整金额 | H5: 贷方调整金额 | I5: 索引 | J5: 备注
A21: 提示：本底稿适用于调整分录较多、较复杂的项目，且仅列示与本报表项目相关的审计调整。项目组可根据项目实际情况选择是否使用该底稿。

Sheet 大额其他应付款情况分析表K3-4
A1: 致同会计师事务所
A2: 大额其他应付款情况分析表
A3: =底稿目录!A2 -> 被审计单位： | E3: =底稿目录!A4 -> 编制人： | G3: =底稿目录!A5 -> 编制日期： | I3: 索引号： | J3: =底稿目录!F10 -> K3-4
A4: =底稿目录!A3 -> 截止日：202X年12月31日 | E4: =底稿目录!A6 -> 复核人： | G4: =底稿目录!A7 -> 复核日期： | I4: 页 次：
A5: 一、审计目标:
A6: 1.资产负债表中记录的其他应付款是存在的，且已记录于恰当的账户。
A7: 2.所有应记录的其他应付款均已记录，所有应当包括在财务报表中的相关披露均已包括。
A8: 3.其他应付款以恰当的金额包括在财务报表中，与之相关的计价或分摊调整已恰当记录，相关披露已得到恰当计量和描述。
A9: 二、审计过程：
A10: 其他应付款前10名查验汇总表
A11: 债权人名称 | B11: 期初余额 | C11: 本期借方 | D11: 本期贷方 | E11: 期末余额 | F11: 账龄 | G11: 经济业务说明 | H11: 关联方（√） | I11: 协议或合同索引 | J11: 期后付款金额
E12: =B12-C12+D12 -> 0
E13: =B13-C13+D13 -> 0
E14: =B14-C14+D14 -> 0
E15: =B15-C15+D15 -> 0
E16: =B16-C16+D16 -> 0
E17: =B17-C17+D17 -> 0
E18: =B18-C18+D18 -> 0
E19: =B19-C19+D19 -> 0
E20: =B20-C20+D20 -> 0
E21: =B21-C21+D21 -> 0
A22: 合计 | B22: =SUM(B12:B21) -> 0 | C22: =SUM(C12:C21) -> 0 | D22: =SUM(D12:D21) -> 0 | E22: =SUM(E12:E21) -> 0 | J22: =SUM(J12:J21) -> 0
A23: 三、审计说明：
A24: 1.针对期后付款的凭证检查，详见凭证检查表K3-
A27: 四、审计结论：

Sheet 长期挂账检查表K3-5
A1: 致同会计师事务所
A2: 账龄1年以上的其他应付款检查表
A3: =底稿目录!A2 -> 被审计单位： | D3: =底稿目录!A4 -> 编制人： | H3: =底稿目录!A5 -> 编制日期： | J3: 索引号： | K3: =底稿目录!F18 -> K3-5
A4: =底稿目录!A3 -> 截止日：202X年12月31日 | D4: =底稿目录!A6 -> 复核人： | H4: =底稿目录!A7 -> 复核日期： | J4: 页 次：
A5: 一、审计目标
A6: 1.资产负债表中记录的其他应付款是存在的，且已记录于恰当的账户。 | E6: 2.其他应付款以恰当的金额包括在财务报表中，与之相关的计价或分摊调整已恰当记录，相关披露已得到恰当计量和描述。
A7: 二、审计过程
A8: 债权人名称 | B8: 期末余额 | C8: 账龄 | D8: 经济业务说明 | E8: 未偿还或未结转的原因 | F8: 是否无法支付 | G8: 是否诉讼 | H8: 支付计划 | I8: 审定余额 | J8: 期后付款金额 | K8: 备注
A14: 合计 | B14: =SUM(B9:B13) -> 0 | I14: =SUM(I9:I13) -> 0 | J14: =SUM(J9:J13) -> 0
A15: 三、审计说明
A16: 1.针对期后付款的凭证检查，详见凭证检查表K3-
A18: 四、审计结论

Sheet 关联方及交易检查表K3-6
A1: 致同会计师事务所
A2: 关联方及交易检查表
A3: =底稿目录!A2 -> 被审计单位： | D3: =底稿目录!A4 -> 编制人： | G3: =底稿目录!A5 -> 编制日期： | I3: 索引号： | J3: =底稿目录!F19 -> K3-6
A4: =底稿目录!A3 -> 截止日：202X年12月31日 | D4: =底稿目录!A6 -> 复核人： | G4: =底稿目录!A7 -> 复核日期： | I4: 页 次：
A5: 关注对关联方的其他应收款的真实性、合理性、合法性、会计处理是否正确，考虑是否存在未识别的关联方，检查关联交易和余额披露是否正确。
A6: 关联方名称 | B6: 关联关系 | C6: 期初余额 | D6: 借方发生额 | E6: 贷方发生额 | F6: 期末余额 | G6: 发生时间及账龄 | H6: 发生原因 （款项性质） | I6: 期后付款金额 | J6: 索引号
A7: 债务人（股东）1
A8: 债务人（股东）2
A9: …… | F9: =C9+E9-D9 -> 0
A10: 小计 | C10: =SUM(C7:C9) -> 0 | D10: =SUM(D7:D9) -> 0 | E10: =SUM(E7:E9) -> 0 | F10: =SUM(F7:F9) -> 0
A11: 1、审计说明：
A12: 1.针对期后付款的凭证检查，详见凭证检查表K3-
A14: 2、审计结论：
B17: 勿删、勿改
B18: 实际控制人
B19: 控股股东
B20: 控股股东、实际控制人的附属企业
B21: 持有5%以上股份的法人或其他组织
B22: 联营企业
B23: 合营企业
B24: 董高监等关键管理人员
B25: 其他关联方

Sheet 其他应付款检查表K3-7
A1: 致同会计师事务所
A2: 其他应付款检查表
A3: =底稿目录!A2 -> 被审计单位： | G3: =底稿目录!A4 -> 编制人： | K3: =底稿目录!A5 -> 编制日期： | P3: 索引号： | Q3: =底稿目录!F20 -> K3-7
A4: =底稿目录!A3 -> 截止日：202X年12月31日 | G4: =底稿目录!A6 -> 复核人： | K4: =底稿目录!A7 -> 复核日期： | P4: 页次：
A5: 一、审计目标：
A6: 1.资产负债表中记录的其他应付款是存在的，且已经记录在恰当的账户中； | F6: 2.记录的其他应付款是被审计单位应当履行的偿还义务；
A7: 3.其他应付款以恰当的金额包括在财务报表中，与之相关的计价或分摊调整已恰当记录，相关披露已得到恰当计量和描述。
A8: 二、样本选取标准与规模：
A9: 测试总体： | B9: 如借方发生额所有凭证共XX笔金额XX、贷方发生额所有凭证共XX笔金额XX | G9: 特定样本： | H9: XX金额以上（大额）、关联方/关联交易形成的款项、XX异常款项全部测试，共XX笔；
A10: 抽样总体： | B10: 测试总体扣除特定样本以外的样本，共XX笔、金额XX | G10: 确定的抽样样本量： | H10: 抽取XX笔（如果使用了样本计算器计算样本量，样本量计算过程见<XX>底稿）
A11: 抽样方法： | B11: 随机选样/系统选样/货币单元抽样/随意选样（非统计抽样适用） | G11: 抽样过程： | H11: 使用IDEA（XX抽样工具）选择XX数量、金额XX的样本进行测试，抽样工具中的样本选择过程和结果见<XX>底稿
A12: 三、测试：
A13: 测试内容说明：1.原始凭证是否齐全； 2.记账凭证与原始凭证是否相符；3.账务处理是否正确；4.是否记录于恰当的会计期间；5.……
A14: 1.本期发生额检查
A15: 记账凭证 | I15: 支持性文件 | J15: 核对内容 | O15: 索引号 | P15: 是否异常 | Q15: 备注说明
A16: 债权人名称 | B16: 日期 | C16: 凭证编号 | D16: 业务内容 | E16: 对方科目 | F16: 对方明细科目 | G16: 借方金额 | H16: 贷方金额 | J16: 1 | K16: 2 | L16: 3 | M16: 4 | N16: 5
A37: 合计 | G37: =SUM(G17:G36) -> 0 | H37: =SUM(H17:H36) -> 0
A38: 2.期后付款检查表
A39: 记账凭证 | H39: 支持性文件 | J39: 核对内容 | O39: 索引号 | P39: 是否异常 | Q39: 备注说明
A40: 债权人名称 | B40: 日期 | C40: 凭证编号 | D40: 业务内容 | E40: 对方科目 | F40: 对方明细科目 | G40: 借方金额 | J40: 1 | K40: 2 | L40: 3 | M40: 4 | N40: 5
A50: 合计 | G50: =SUM(G41:G49) -> 0
A51: 四、审计说明：
A52: 1.本期发生额、期末余额检查比例： | D52: 方向 | E52: 账面金额 | F52: 检查金额 | G52: 检查比例 | H52: 如果检查比例较低应扩大检查样本量或说明原因
D53: 本期借方 | E53: ='明细表K3-2'!M31 -> 0 | F53: =G37 -> 0 | G53: =ROUND(F53/E53,4) -> #DIV/0!
D54: 本期贷方 | E54: ='明细表K3-2'!N31 -> 0 | F54: =H37 -> 0 | G54: =ROUND(F54/E54,2) -> #DIV/0!
D55: 期末余额 | E55: ='明细表K3-2'!T31 -> 0 | F55: =G50 -> 0 | G55: =ROUND(F55/E55,2) -> #DIV/0!
A56: 2.……
A57: 五、审计结论：

Sheet GT_Custom
A1: C1 | B1: Custom 1
A2: C2 | B2: Custom 2
A3: C3 | B3: Custom 3
A4: C4 | B4: Custom 4
A5: C5 | B5: Custom 5
A6: C6 | B6: Custom 6
A7: C7 | B7: Custom 7
A8: C8 | B8: Custom 8
