Workbook

Sheet 底稿目录
A1: 底稿开列时，可先在以下单元格填写有关内容，以便其他底稿引用有关数据：
A2: 被审计单位： | B2: 目录
A3: 截止日：202X年12月31日
A4: 编制人： | B4: 序号 | C4: 内容 | D4: 索引号 | E4: 备注
A5: 编制日期： | B5: 1 | C5: 实质性程序表 | D5: K4A
A6: 复核人： | B6: 2 | C6: 审定表 | D6: K4-1
A7: 复核日期： | B7: 3 | C7: 附注披露信息（上市公司） | F7: 无需打印
B8: 4 | C8: 附注披露信息（国企） | F8: 无需打印
A9: 关于工作底稿与审计程序索引号对应的说明 | B9: 5 | C9: 明细表 | D9: K4-2
A10: 1.编制的审计工作底稿应与审计程序对应。审计项目组应根据被审计单位实际情况和风险评估情况在实质性程序表中裁剪、修改或增加审计程序，根据实际执行的审计程序完成相应审计工作底稿，编制的工作底稿中应按自然顺序依次编制索引号，并通过唯一的索引号将与实质性程序表中的程序对应关联（即将工作底稿的索引号填入实质性程序表中的底稿索引号列）。 | B10: 6 | C10: 调整分录汇总 | D10: K4-3 | E10: 备选
B11: 7 | C11: 其他流动负债检查表 | D11: K4-4
A14: 2.获取的支持性证据应与审计底稿或程序对应。审计项目组在完成底稿时获取的支持性证据应根据底稿索引号编制下一级按自然顺序排序的索引号（如D1-2-1、D1-2-2、……），并在底稿中说明引用的支持性证据、关联索引号。
A17: 3.工作底稿索引号的编码规则：实质性程序索引号按循环从“D”到“N”,循环内账户以顺序号排列，模板中底稿索引号按账户顺序+自然数顺序（即模板中索引号按二级自然顺序排列，如D1-1、D1-2、D1-3、……D1-N）。

Sheet 实质性程序表 K4A
A1: 致同会计师事务所
A2: 其他流动负债实质性程序
A3: =底稿目录!A2 -> 被审计单位： | C3: =底稿目录!A4 -> 编制人： | E3: =底稿目录!A5 -> 编制日期： | H3: 索引号： | I3: =底稿目录!D5 -> K4A
A4: =底稿目录!A3 -> 截止日：202X年12月31日 | C4: =底稿目录!A6 -> 复核人： | E4: =底稿目录!A7 -> 复核日期： | H4: 页 次：
A5: 一、本账户涉及的科目
A6: 其他流动负债
A7: 二、审计目标与认定的对应关系
A8: 审计目标 | G8: 财务报表的认定
A9: A. 资产负债表中记录的其他流动负债是存在的，且已记录于恰当的账户 | G9: 存在
A10: B. 所有应记录的其他流动负债均已记录，所有应当包括在财务报表中的相关披露均已包括 | G10: 完整性
A11: C. 记录的其他流动负债是被审计单位应当履行的偿还义务 | G11: 权利和义务
A12: D. 其他流动负债以恰当的金额包括在财务报表中，与之相关的计价或分摊调整已恰当记录，相关披露已得到恰当计量和描述 | G12: 准确性、计价和分摊
A13: E. 其他流动负债已被恰当地汇总或分解且表述清楚，相关披露在按照企业会计准则的编制基础下是相关的、可理解的 | G13: 列报
A14: 三、计划实施的实质性程序
A15: 序号 | B15: 审计程序 | C15: 程序分类 | D15: 财务报表的认定 | I15: 底稿索引号
D16: 存在 | E16: 完整性 | F16: 权利和 义务 | G16: 准确性、计价和分摊 | H16: 列报 | J16: 根据被审计单位实际情况和风险评估情况裁剪、修改或增加审计程序
A17: 1 | B17: 获取或编制明细表、执行下列程序，并编制审定表： （1）复核加计正确，并与总账数和明细账合计数核对是否相符，期初余额与上期审定期末余额是否相符； （2）识别重大的账户、识别账户中单项重大的明细项目； （3）了解明细项目的核算目的和用途； | C17: 常规★ | D17: √ | E17: √ | G17: √ | I17: K4-1 /K4-2
A18: 2 | B18: 在使用手工编制、自定义信息报告、系统生成的非固定格式报告等由被审计单位生成的信息时，测试有关信息准确性和完整性，并考虑针对编制和维护由被审计单位生成的信息的相关控制实施控制测试，以评价该信息是否能够为实现审计目的提供基础。 | C18: 常规★ | E18: √ | G18: √ | I18: T1 | J18: 可参见《审计手册》4.2.6，由被审计单位生成的信息可能是由系统生成的、或手工编制的、或二者兼而有之的方式生成的。例如，由被审计单位生成的信息可能包括： • 不涉及自定义的、由系统生成的报告（如，固定格式报告）； • 可能通过人工自定义的、由系统生成的报告，例如，（计算机）查询信息或特别定制的报告； • 手工编制的信息，例如，汇总信息的电子表格或用以支持分配、计算以及调节的电子表格； • 其他系统生成或手工编制的信息，例如，由被审计单位编制的客户发票； • 通过影印、拍摄、扫描或其他方式转换成电子形式的文件记录。
A19: 3 | B19: 获取上期期末的其他流动负债明细，复核加计正确，总账与明细账核对一致；识别重大的明细项目、查找异常项目并了解该明细项目的核算目的和用途；将个别重大负债与其支持文件核对；检查期初其他流动负债在本期支付、转销情况，考虑是否需要函证期初余额以及其他必要追加的审计程序。（适用于首次承接） | C19: 备选 | D19: √ | E19: √ | F19: √ | G19: √ | J19: 由被审计单位生成的信息不包括： • 总分类账或明细分类账、试算平衡表、或经审计的财务报表； • 第三方（除了服务机构）的报表或报告，例如，原始银行对账单，或函证的回函； • 外部数据（例如，第三方发布的数据，如，定价来源）。
A20: 4 | B20: 关注会计政策、会计估计合理性、一贯性。关注其是否利用会计政策和会计估计及其变更操纵利润。 | C20: 常规★ | D20: √ | E20: √ | G20: √ | I20: K4-1 /K4-2
A21: 5 | B21: 检查关联交易： （1）了解关联交易的商业理由、交易事项的目的、价格和条件，考虑对关联交易形成的其他流动负债的合理性、合法性； （2）检查对关联交易形成的其他流动负债的真实性相关的支持性文件、检查会计处理是否正确； （3）考虑向关联方或其他注册会计师函证重大的关联交易和余额（包括担保和其他重要信息）； （4）必要时，向与交易相关的人员和机构（如银行、律师）函证或与其讨论有关信息； （5）考虑是否存在未识别的关联方，关联交易和余额披露是否正确。 | C21: 常规★ | D21: √ | E21: √ | F21: √ | G21: √ | H21: √
A22: 6 | B22: 检查与其他流动负债有关的的记账凭证和相应的支持性证据以确定交易的真实性，是否按规定进行相应的会计处理和披露。 | C22: 常规★ | D22: √ | F22: √ | G22: √ | I22: K4-4
A23: 7 | B23: 考虑是否存在超出被审计单位正常经营活动的重大、异常交易等，根据评估的舞弊风险等因素增加的审计程序。 | C23: IPO/上市/新三板/重组/舞弊应对
A24: 8 | B24: 检查其他流动负债是否已按企业会计准则或其他适用的规定在财务报表中做出恰当列报和披露。 | C24: 常规★ | H24: √ | I24: A 1-1/A1-15 /A1-16

Sheet 审定表 K4-1
A1: 致同会计师事务所
A2: 其他流动负债审定表
A3: =底稿目录!A2 -> 被审计单位： | D3: =底稿目录!A4 -> 编制人： | H3: =底稿目录!A5 -> 编制日期： | K3: 索引： | L3: =底稿目录!D6 -> K4-1
A4: =底稿目录!A3 -> 截止日：202X年12月31日 | D4: =底稿目录!A6 -> 复核人： | H4: =底稿目录!A7 -> 复核日期： | K4: 页次：
A5: 项目 | B5: 期初数 | F5: 期末数 | J5: 本期审定数与上期 审定数的比较 | L5: 原因分析
B6: 未审数 | C6: 账项调整 | D6: 重分类调整 | E6: 审定数 | F6: 未审数 | G6: 账项调整 | H6: 重分类调整 | I6: 审定数 | J6: 变动额 | K6: 变动率
A7: ='明细表 K4-2'!A11 -> 短期应付债券 | B7: ='明细表 K4-2'!B11 -> 0 | C7: ='明细表 K4-2'!F11 -> 0 | D7: ='明细表 K4-2'!G11 -> 0 | E7: =B7+C7+D7 -> 0 | F7: ='明细表 K4-2'!E11 -> 0 | G7: ='明细表 K4-2'!F11+'明细表 K4-2'!H11-'明细表 K4-2'!I11 -> 0 | H7: ='明细表 K4-2'!G11+'明细表 K4-2'!J11-'明细表 K4-2'!K11 -> 0 | I7: =F7+G7+H7 -> 0 | J7: =I7-E7 -> 0 | K7: =IF(AND(E7=0,J7=0),0,IF(AND(E7=0,J7>0),1,J7/E7)) -> 0
A8: ='明细表 K4-2'!A12 -> 政府补助 | B8: ='明细表 K4-2'!B12 -> 0 | C8: ='明细表 K4-2'!F12 -> 0 | D8: ='明细表 K4-2'!G12 -> 0 | E8: =B8+C8+D8 -> 0 | F8: ='明细表 K4-2'!E12 -> 0 | G8: ='明细表 K4-2'!F12+'明细表 K4-2'!H12-'明细表 K4-2'!I12 -> 0 | H8: ='明细表 K4-2'!G12+'明细表 K4-2'!J12-'明细表 K4-2'!K12 -> 0 | I8: =F8+G8+H8 -> 0 | J8: =I8-E8 -> 0 | K8: =IF(AND(E8=0,J8=0),0,IF(AND(E8=0,J8>0),1,J8/E8)) -> 0
A9: ='明细表 K4-2'!A13 -> 待转销项税额 | B9: ='明细表 K4-2'!B13 -> 0 | C9: ='明细表 K4-2'!F13 -> 0 | D9: ='明细表 K4-2'!G13 -> 0 | E9: =B9+C9+D9 -> 0 | F9: ='明细表 K4-2'!E13 -> 0 | G9: ='明细表 K4-2'!F13+'明细表 K4-2'!H13-'明细表 K4-2'!I13 -> 0 | H9: ='明细表 K4-2'!G13+'明细表 K4-2'!J13-'明细表 K4-2'!K13 -> 0 | I9: =F9+G9+H9 -> 0 | J9: =I9-E9 -> 0 | K9: =IF(AND(E9=0,J9=0),0,IF(AND(E9=0,J9>0),1,J9/E9)) -> 0
A10: ='明细表 K4-2'!A14 -> 应付退货款 | B10: ='明细表 K4-2'!B14 -> 0 | C10: ='明细表 K4-2'!F14 -> 0 | D10: ='明细表 K4-2'!G14 -> 0 | E10: =B10+C10+D10 -> 0 | F10: ='明细表 K4-2'!E14 -> 0 | G10: ='明细表 K4-2'!F14+'明细表 K4-2'!H14-'明细表 K4-2'!I14 -> 0 | H10: ='明细表 K4-2'!G14+'明细表 K4-2'!J14-'明细表 K4-2'!K14 -> 0 | I10: =F10+G10+H10 -> 0 | J10: =I10-E10 -> 0 | K10: =IF(AND(E10=0,J10=0),0,IF(AND(E10=0,J10>0),1,J10/E10)) -> 0
A11: ='明细表 K4-2'!A15 -> 0 | B11: ='明细表 K4-2'!B15 -> 0 | C11: ='明细表 K4-2'!F15 -> 0 | D11: ='明细表 K4-2'!G15 -> 0 | E11: =B11+C11+D11 -> 0 | F11: ='明细表 K4-2'!E15 -> 0 | G11: ='明细表 K4-2'!F15+'明细表 K4-2'!H15-'明细表 K4-2'!I15 -> 0 | H11: ='明细表 K4-2'!G15+'明细表 K4-2'!J15-'明细表 K4-2'!K15 -> 0 | I11: =F11+G11+H11 -> 0 | J11: =I11-E11 -> 0 | K11: =IF(AND(E11=0,J11=0),0,IF(AND(E11=0,J11>0),1,J11/E11)) -> 0
A12: 合计 | B12: =SUM(B7:B11) -> 0 | C12: =SUM(C7:C11) -> 0 | D12: =SUM(D7:D11) -> 0 | E12: =SUM(E7:E11) -> 0 | F12: =SUM(F7:F11) -> 0 | G12: =SUM(G7:G11) -> 0 | H12: =SUM(H7:H11) -> 0 | I12: =SUM(I7:I11) -> 0 | J12: =I12-E12 -> 0 | K12: =IF(AND(E12=0,J12=0),0,IF(AND(E12=0,J12>0),1,J12/E12)) -> 0
A13: TB数据：
A14: 差异： | B14: =B12-B13 -> 0 | C14: =C12-C13 -> 0 | D14: =D12-D13 -> 0 | E14: =E12-E13 -> 0 | F14: =F12-F13 -> 0 | G14: =G12-G13 -> 0 | H14: =H12-H13 -> 0 | I14: =I12-I13 -> 0
A15: 1.审计说明
A16: （1）其他流动负债本期较上期增加（负数为减少）：
A17: 主要原因（比例超过30%的）：
A19: （2）情况说明。
A20: 2.审计结论

Sheet 附注披露信息（上市公司）
A1: 致同会计师事务所
A2: 附注披露信息（上市公司）
A3: =底稿目录!A2 -> 被审计单位： | B3: =底稿目录!A4 -> 编制人： | D3: =底稿目录!A5 -> 编制日期： | G3: 索引号： | H3: =底稿目录!D7 -> 0
A4: =底稿目录!A3 -> 截止日：202X年12月31日 | B4: =底稿目录!A6 -> 复核人： | D4: =底稿目录!A7 -> 复核日期： | G4: 页次：
A5: 其他流动负债
A6: 项 目 | B6: 期末数 | C6: 上年年末数
A7: ='明细表 K4-2'!A11 -> 短期应付债券 | B7: ='明细表 K4-2'!O11 -> 0 | C7: ='明细表 K4-2'!L11 -> 0
A8: ='明细表 K4-2'!A12 -> 政府补助 | B8: ='明细表 K4-2'!O12 -> 0 | C8: ='明细表 K4-2'!L12 -> 0
A9: ='明细表 K4-2'!A13 -> 待转销项税额 | B9: ='明细表 K4-2'!O13 -> 0 | C9: ='明细表 K4-2'!L13 -> 0
A10: ='明细表 K4-2'!A14 -> 应付退货款 | B10: ='明细表 K4-2'!O14 -> 0 | C10: ='明细表 K4-2'!L14 -> 0
A11: ='明细表 K4-2'!A15 -> 0 | B11: ='明细表 K4-2'!O15 -> 0 | C11: ='明细表 K4-2'!L15 -> 0
A12: 合 计 | B12: =SUM(B7:B11) -> 0 | C12: =SUM(C7:C11) -> 0
A13: 说明：
A14: 【公司根据《企业会计准则》规定计入“递延收益”科目的金额，应按如下原则确定所属的报表项目：
A15: （1）受益期预计在一年以内（含一年）的，应在“其他流动负债”项目列报；
A16: （2）自资产负债表日起算的受益期限超过一年的，在“递延收益”目中列报。】
A17: 【待转销项税额属于其他非流动负债的，在“其他非流动负债”科目列示。】
A18: （1）短期应付债券
A19: 债券名称 | B19: 面值 | C19: 票面利率 | D19: 发行日期 | E19: 债券期限 | F19: 发行金额
A23: 小 计 | B23: =SUM(B20:B22) -> 0 | F23: =SUM(F20:F22) -> 0
A24: 短期应付债券（续）
A25: 债券名称 | B25: 上年年末数 | C25: 本期发行 | D25: 按面值计提利息 | E25: 溢折价摊销 | F25: 本期偿还 | G25: 期末数 | H25: 是否违约
G26: =B26+C26+D26-E26-F26 -> 0
G27: =B27+C27+D27-E27-F27 -> 0
G28: =B28+C28+D28-E28-F28 -> 0
A29: 合 计 | B29: =SUM(B26:B28) -> 0 | C29: =SUM(C26:C28) -> 0 | D29: =SUM(D26:D28) -> 0 | E29: =SUM(E26:E28) -> 0 | F29: =SUM(F26:F28) -> 0 | G29: =SUM(G26:G28) -> 0
A30: 说明：
A31: （2）递延收益-政府补助情况
A32: 补助项目 | B32: 上年年末数 | C32: 本期增加 | D32: 本期减少 | E32: 期末数 | F32: 形成原因
E33: =B33+C33-D33 -> 0
E34: =B34+C34-D34 -> 0
E35: =B35+C35-D35 -> 0
A36: 合 计 | B36: =SUM(B33:B35) -> 0 | C36: =SUM(C33:C35) -> 0 | D36: =SUM(D33:D35) -> 0 | E36: =SUM(E33:E35) -> 0
A37: 说明：计入递延收益的政府补助详见附注五、84、政府补助

Sheet 附注披露信息（国企）
A1: 致同会计师事务所
A2: 附注披露信息(国企)
A3: =底稿目录!A2 -> 被审计单位： | B3: =底稿目录!A4 -> 编制人： | C3: =底稿目录!A5 -> 编制日期： | D3: 索引号： | E3: =底稿目录!D8 -> 0
A4: =底稿目录!A3 -> 截止日：202X年12月31日 | B4: =底稿目录!A6 -> 复核人： | C4: =底稿目录!A7 -> 复核日期： | D4: 页次：
A5: 其他流动负债
A6: 项 目 | B6: 期末余额 | C6: 期初余额
A7: ='明细表 K4-2'!A11 -> 短期应付债券 | B7: ='明细表 K4-2'!O11 -> 0 | C7: ='明细表 K4-2'!L11 -> 0
A8: ='明细表 K4-2'!A12 -> 政府补助 | B8: ='明细表 K4-2'!O12 -> 0 | C8: ='明细表 K4-2'!L12 -> 0
A9: ='明细表 K4-2'!A13 -> 待转销项税额 | B9: ='明细表 K4-2'!O13 -> 0 | C9: ='明细表 K4-2'!L13 -> 0
A10: ='明细表 K4-2'!A14 -> 应付退货款 | B10: ='明细表 K4-2'!O14 -> 0 | C10: ='明细表 K4-2'!L14 -> 0
A11: ='明细表 K4-2'!A15 -> 0 | B11: ='明细表 K4-2'!O15 -> 0 | C11: ='明细表 K4-2'!L15 -> 0
A12: 合 计 | B12: =SUM(B7:B11) -> 0 | C12: =SUM(C7:C11) -> 0
A13: 注：发行债券应披露债券名称，债券面值，发行日期，债券期限，发行金额，期初余额，本期发行金额，按面值计提利息，溢折价摊销，本期偿还的金额，期末余额等相关信息。
A14: 【待转销项税额属于其他非流动负债的，在“其他非流动负债”科目列示。】

Sheet 明细表 K4-2
A1: 致同会计师事务所
A2: 其他流动负债明细表
A3: =底稿目录!A2 -> 被审计单位： | D3: =底稿目录!A4 -> 编制人： | J3: =底稿目录!A5 -> 编制日期： | O3: 索引号： | P3: =底稿目录!D9 -> K4-2
A4: =底稿目录!A3 -> 截止日：202X年12月31日 | D4: =底稿目录!A6 -> 复核人： | J4: =底稿目录!A7 -> 复核日期： | O4: 页次：
A5: 一、审计目标:
A6: 1.资产负债表中记录的其他流动负债是存在的，且已记录于恰当的账户。 | G6: 2.所有应记录的其他流动负债均已记录，所有应当包括在财务报表中的相关披露均已包括。
A7: 3.其他流动负债以恰当的金额包括在财务报表中，与之相关的计价或分摊调整已恰当记录，相关披露已得到恰当计量和描述。
A8: 二、审计过程：
A9: 项目 | B9: 未审数 | F9: 期初调整 | H9: 账项调整 | J9: 重分类调整 | L9: 审定数 | P9: 备注
B10: 期初数 | C10: 本期增加 | D10: 本期减少 | E10: 期末数 | F10: 账项调整 | G10: 重分类调整 | H10: 本期增加 | I10: 本期减少 | J10: 本期增加 | K10: 本期减少 | L10: 期初数 | M10: 本期增加 | N10: 本期减少 | O10: 期末数
A11: 短期应付债券 | E11: =B11+C11-D11 -> 0 | L11: =B11+F11+G11 -> 0 | M11: =C11+H11+J11 -> 0 | N11: =D11+I11+K11 -> 0 | O11: =L11+M11-N11 -> 0
A12: 政府补助 | E12: =B12+C12-D12 -> 0 | L12: =B12+F12+G12 -> 0 | M12: =C12+H12+J12 -> 0 | N12: =D12+I12+K12 -> 0 | O12: =L12+M12-N12 -> 0
A13: 待转销项税额 | E13: =B13+C13-D13 -> 0 | L13: =B13+F13+G13 -> 0 | M13: =C13+H13+J13 -> 0 | N13: =D13+I13+K13 -> 0 | O13: =L13+M13-N13 -> 0
A14: 应付退货款 | E14: =B14+C14-D14 -> 0 | L14: =B14+F14+G14 -> 0 | M14: =C14+H14+J14 -> 0 | N14: =D14+I14+K14 -> 0 | O14: =L14+M14-N14 -> 0
E15: =B15+C15-D15 -> 0 | L15: =B15+F15+G15 -> 0 | M15: =C15+H15+J15 -> 0 | N15: =D15+I15+K15 -> 0 | O15: =L15+M15-N15 -> 0
A16: 合计 | B16: =SUM(B11:B15) -> 0 | C16: =SUM(C11:C15) -> 0 | D16: =SUM(D11:D15) -> 0 | E16: =SUM(E11:E15) -> 0 | F16: =SUM(F11:F15) -> 0 | G16: =SUM(G11:G15) -> 0 | H16: =SUM(H11:H15) -> 0 | I16: =SUM(I11:I15) -> 0 | ... O16: =SUM(O11:O15) -> 0
A17: 三、审计说明：
A20: 四、审计结论：
A24: 编制说明：
A25: 财会〔2018〕15号：预计负债”科目下的“应付退货款”明细科目，在一年或一个正常营业周期内清偿的项目在其他流动负债反映。

Sheet 调整分录汇总 K4-3
A1: 致同会计师事务所
A2: 其他流动负债调整分录汇总表
A3: =底稿目录!A2 -> 被审计单位： | C3: =底稿目录!A4 -> 编制人： | F3: =底稿目录!A5 -> 编制日期： | I3: 索引号： | J3: =底稿目录!D10 -> K4-3
A4: =底稿目录!A3 -> 截止日：202X年12月31日 | C4: =底稿目录!A6 -> 复核人： | F4: =底稿目录!A7 -> 复核日期： | I4: 页次：
A5: 调整事项说明 | B5: 类别（报表调整/账项调整/其他） | C5: 报表项目 | D5: 科目名称 | E5: 附注项目 | F5: …… | G5: 借方调整金额 | H5: 贷方调整金额 | I5: 索引 | J5: 备注
A21: 提示：本底稿适用于调整分录较多、较复杂的项目，且仅列示与本报表项目相关的审计调整。项目组可根据项目实际情况选择是否使用该底稿。

Sheet 其他流动负债检查表 K4-4
A1: 致同会计师事务所
A2: 其他流动负债检查表
A3: =底稿目录!A2 -> 被审计单位： | E3: =底稿目录!A4 -> 编制人： | I3: =底稿目录!A5 -> 编制日期： | P3: 索引号： | Q3: =底稿目录!D11 -> K4-4
A4: =底稿目录!A3 -> 截止日：202X年12月31日 | E4: =底稿目录!A6 -> 复核人： | I4: =底稿目录!A7 -> 复核日期： | P4: 页次：
A5: 一、审计目标：
A6: 1.资产负债表中记录的其他流动负债是存在的，且已经记录在恰当的账户中； | F6: 2.记录的其他流动负债是被审计单位应当履行的偿还义务；
A7: 3.其他流动负债以恰当的金额包括在财务报表中，与之相关的计价或分摊调整已恰当记录，相关披露已得到恰当计量和描述。
A8: 二、样本选取标准与规模：
A9: 测试总体： | B9: 如借方发生额所有凭证共XX笔金额XX、贷方发生额所有凭证共XX笔金额XX | G9: 特定样本： | H9: XX金额以上（大额）、关联方/关联交易形成的款项、XX异常款项全部测试，共XX笔；
A10: 抽样总体： | B10: 测试总体扣除特定样本以外的样本，共XX笔、金额XX | G10: 确定的抽样样本量： | I10: 抽取XX笔（如果使用了样本计算器计算样本量，样本量计算过程见<XX>底稿）
A11: 抽样方法： | B11: 随机选样/系统选样/货币单元抽样/随意选样（非统计抽样适用） | G11: 抽样过程： | H11: 使用IDEA（XX抽样工具）选择XX数量、金额XX的样本进行测试，抽样工具中的样本选择过程和结果见<XX>底稿
A12: 三、测试：
A13: 测试内容说明：1.原始凭证是否齐全； 2.记账凭证与原始凭证是否相符；3.账务处理是否正确；4.是否记录于恰当的会计期间；5.……
A14: 明细项目 | B14: 记账凭证 | I14: 支持性文件 | J14: 核对内容 | O14: 索引号 | P14: 是否异常 | Q14: 备注说明
B15: 日期 | C15: 凭证编号 | D15: 业务内容 | E15: 对方科目 | F15: 对方明细科目 | G15: 借方金额 | H15: 贷方金额 | J15: 1 | K15: 2 | L15: 3 | M15: 4 | N15: 5
A29: 合计 | G29: =SUM(G16:G28) -> 0 | H29: =SUM(H16:H28) -> 0
A30: 四、审计说明：
A31: 1.本期发生额、期末余额检查比例： | D31: 方向 | E31: 账面金额 | F31: 检查金额 | G31: 检查比例 | H31: 如果检查比例较低应扩大检查样本量或说明原因
D32: 本期借方 | E32: ='明细表 K4-2'!N16 -> 0 | F32: =G29 -> 0 | G32: =ROUND(F32/E32,4) -> #DIV/0!
D33: 本期贷方 | E33: ='明细表 K4-2'!M16 -> 0 | F33: =H29 -> 0 | G33: =ROUND(F33/E33,2) -> #DIV/0!
A34: 2.……
A36: 五、审计结论：
