Workbook

Sheet 底稿目录
A1: 底稿开列时，可先在以下单元格填写有关内容，以便其他底稿引用有关数据：
A2: 被审计单位：
A3: 截止日：202X年12月31日
A4: 编制人： | B4: 序号 | C4: 内容 | D4: 索引号 | E4: 备注
A5: 编制日期： | B5: 1 | C5: 实质性程序表 | D5: K5A
A6: 复核人： | B6: 2 | C6: 审定表 | D6: K5-1
A7: 复核日期： | B7: 3 | C7: 附注披露信息（上市公司) | F7: 无需打印
B8: 4 | C8: 附注披露信息（国企） | F8: 无需打印
A9: 关于工作底稿与审计程序索引号对应的说明 | B9: 5 | C9: 明细表 | D9: K5-2
A10: 1.编制的审计工作底稿应与审计程序对应。审计项目组应根据被审计单位实际情况和风险评估情况在实质性程序表中裁剪、修改或增加审计程序，根据实际执行的审计程序完成相应审计工作底稿，编制的工作底稿中应按自然顺序依次编制索引号，并通过唯一的索引号将与实质性程序表中的程序对应关联（即将工作底稿的索引号填入实质性程序表中的底稿索引号列）。 | B10: 6 | C10: 调整分录汇总 | D10: K5-3 | E10: 备选
B11: 8 | C11: 产品质量保修检查表 | D11: K5-4
B12: 7 | C12: 弃置费用检查表 | D12: K5-5
B13: 9 | C13: 未决诉讼检查表 | D13: K5-6
A14: 2.获取的支持性证据应与审计底稿或程序对应。审计项目组在完成底稿时获取的支持性证据应根据底稿索引号编制下一级按自然顺序排序的索引号（如D1-2-1、D1-2-2、……），并在底稿中说明引用的支持性证据、关联索引号。 | B14: 10 | C14: 预计负债检查表 | D14: K5-7
A17: 3.工作底稿索引号的编码规则：实质性程序索引号按循环从“D”到“N”,循环内账户以顺序号排列，模板中底稿索引号按账户顺序+自然数顺序（即模板中索引号按二级自然顺序排列，如D1-1、D1-2、D1-3、……D1-N）。

Sheet 实质性程序表 K5A
A1: 致同会计师事务所
A2: 预计负债实质性程序
A3: =底稿目录!A2 -> 被审计单位： | C3: =底稿目录!A4 -> 编制人： | E3: =底稿目录!A5 -> 编制日期： | H3: 索引号： | I3: =底稿目录!D5 -> K5A
A4: =底稿目录!A3 -> 截止日：202X年12月31日 | C4: =底稿目录!A6 -> 复核人： | E4: =底稿目录!A7 -> 复核日期： | H4: 页次：
A5: 一、本账户涉及的科目
A6: 预计负债
A7: 二、审计目标与认定的对应关系
A8: 审计目标 | G8: 财务报表的认定
A9: A. 资产负债表中记录的预计负债是存在的，且已记录于恰当的账户 | G9: 存在
A10: B. 所有应记录的预计负债均已记录，所有应当包括在财务报表中的相关披露均已包括 | G10: 完整性
A11: C. 记录的预计负债是被审计单位应当履行的偿还义务 | G11: 权利和义务
A12: D. 预计负债以恰当的金额包括在财务报表中，与之相关的计价或分摊调整已恰当记录，相关披露已得到恰当计量和描述 | G12: 准确性、计价和分摊
A13: E. 预计负债已被恰当地汇总或分解且表述清楚，相关披露在按照企业会计准则的编制基础下是相关的、可理解的 | G13: 列报
A14: 三、计划实施的实质性程序
A15: 序号 | B15: 审计程序 | C15: 程序分类 | D15: 财务报表的认定 | I15: 底稿索引号
D16: 存在 | E16: 完整性 | F16: 权利和 义务 | G16: 准确性、计价和分摊 | H16: 列报 | J16: 根据被审计单位实际情况和风险评估情况裁剪、修改或增加审计程序
A17: 1 | B17: 获取或编制明细表、执行下列程序，并编制审定表： （1）复核加计正确，并与总账数和明细账合计数核对是否相符，期初余额与上期审定期末余额是否相符； （2）识别重大的账户、识别账户中单项重大的明细项目； （3）了解明细项目的核算目的和用途； | C17: 常规★ | D17: √ | E17: √ | G17: √ | I17: K5-1 /K5-2
A18: 2 | B18: 在使用手工编制、自定义信息报告、系统生成的非固定格式报告等由被审计单位生成的信息时，测试有关信息准确性和完整性，并考虑针对编制和维护由被审计单位生成的信息的相关控制实施控制测试，以评价该信息是否能够为实现审计目的提供基础。 | C18: 常规★ | E18: √ | G18: √ | I18: T1 | J18: 可参见《审计手册》4.2.6，由被审计单位生成的信息可能是由系统生成的、或手工编制的、或二者兼而有之的方式生成的。例如，由被审计单位生成的信息可能包括： • 不涉及自定义的、由系统生成的报告（如，固定格式报告）； • 可能通过人工自定义的、由系统生成的报告，例如，（计算机）查询信息或特别定制的报告； • 手工编制的信息，例如，汇总信息的电子表格或用以支持分配、计算以及调节的电子表格； • 其他系统生成或手工编制的信息，例如，由被审计单位编制的客户发票； • 通过影印、拍摄、扫描或其他方式转换成电子形式的文件记录。
A19: 3 | B19: 获取上期期末的预计负债明细，复核加计正确，总账与明细账核对一致；识别重大的明细项目、查找异常项目并了解该明细项目的核算目的和用途；将个别重大负债与其支持文件核对；检查期初预计负债在本期支付、转销情况，考虑是否需要函证期初余额以及其他必要追加的审计程序。（适用于首次承接） | C19: 备选 | D19: √ | E19: √ | F19: √ | G19: √ | J19: 由被审计单位生成的信息不包括： • 总分类账或明细分类账、试算平衡表、或经审计的财务报表； • 第三方（除了服务机构）的报表或报告，例如，原始银行对账单，或函证的回函； • 外部数据（例如，第三方发布的数据，如，定价来源）。
A20: 4 | B20: 关注会计政策、会计估计合理性、一贯性；关注其是否利用会计政策和会计估计及其变更操纵利润；对涉及重大会计估计的事项完成S类会计估计和相关披露底稿。 | C20: 常规★ | D20: √ | E20: √ | G20: √ | I20: K5-1 /K5-2 /S
A21: 5 | B21: 应付退货款：在营业收入中取得并检查产品退货政策及计提的相关支持性资料，重新测试应付退货金额，与账面金额进行比较，根据历史资料及期后发生产品退货的情况，评估被审计单位产品产品退货的计提比例和金额是否合理，计入预计负债金额核对一致。 | C21: 备选 | D21: √ | E21: √ | F21: √ | G21: √ | I21: D4-19
A22: 6 | B22: 产品质量保证： （1）取得并检查产品质量保修政策、以及本期产品质量保证金计提的相关支持性资料，检查质量保证分类是否正确、计算依据是否充分； （2）根据历史资料及期后发生质量保修的情况，评估被审计单位产品质量保证金的计提比例和金额是否合理； （3）重新测算质量保证金并与账面金额进行比较，评估差异金额是否在可接受的范围内。 | C22: 备选 | D22: √ | E22: √ | F22: √ | G22: √ | I22: K5-4
A23: 7 | B23: 弃置费用： （1）询问被审计单位有关环保政策和程序，取得环保监管部门的相关文件、与被审计单位往来函件，识别需要反映的环保整治义务，检查其是否满足预计负债确认的条件； （2）取得弃置费用计提的相关资料和依据，复核计提是否充分、合理，涉及到的关键假设是否一致、是否发生变化、是否合理，弃置费用计算是否正确； | C23: 备选 | D23: √ | E23: √ | F23: √ | G23: √ | I23: K5-5
A24: 8 | B24: 未决诉讼： （1）查阅董事会和股东大会有关会议记录，对常年法律顾问进行函证，检查是否存在未确认、未披露的诉讼事项； （2）根据获取诉状、判决书、律师函等文件，了解诉讼进展情况和可能的结果，检查确认的赔偿金额是否合理、披露是否完整； （3）必要时与被审计单位法务负责人、律师访谈诉讼和索赔事项的可能结果，获取管理层和治理层（如适用）就诉讼和索赔事项的书面声明，必要时利用法律专家工作，取得法律意见书； （4）结合业务管理费中的诉讼费、法务费的审计，了解支出的用途，并结合外部媒体报道，检查是否存在未披露的未决诉讼。 | C24: 备选 | D24: √ | E24: √ | F24: √ | G24: √ | H24: √ | I24: K5-6
A25: 9 | B25: 对外提供担保：向被审计单位询问，结合银行函证、诉讼等其他事项了解被审计单位是否存在提供担保事项(性质、金额、时间)以及存在或有损失的可能性，检查其是否满足预计负债确认的条件，如是，确认的金额和会计处理是否正确。 | C25: 备选 | D25: √ | E25: √ | F25: √ | G25: √
A26: 10 | B26: 结合营业收入、营业外支出、销售费用、管理费用、固定资产、财务费用等报表账户的审计，检查应付退货款、质量保证、弃置义务、未决诉讼、担保等记录和披露完整；检查是否存在重组义务、待执行的亏损合同等其他可能出现预计负债的情况，检查其是否满足预计负债确认的条件，如是，确认的金额和会计处理是否正确。 | C26: 常规★ | E26: √
A27: 11 | B27: 检查关联方交易： （1）了解关联交易的商业理由、交易事项的目的、价格和条件，考虑对关联方担保事项、预计负债的完整性、合理性、合法性； （2）检查对关联方预计负债的真实性相关的支持性文件、检查会计处理是否正确； （3）考虑向关联方或其他注册会计师函证重大的关联采购交易和余额（包括担保和其他重要信息）； （4）必要时，向与交易相关的人员和机构（如银行、律师）函证或与其讨论有关信息； （5）考虑是否存在未识别的关联方，关联交易和余额披露是否正确。 | C27: 常规★ | D27: √ | E27: √ | F27: √ | G27: √ | H27: √
A28: 12 | B28: 检查与预计负债有关的的记账凭证和相应的支持性证据以确定交易的真实性，是否按规定进行相应的会计处理和披露。 | C28: 常规★ | D28: √ | F28: √ | G28: √ | I28: K5-7
A29: 13 | B29: 考虑是否存在超出被审计单位正常经营活动的重大、异常交易等，根据评估的舞弊风险等因素增加的审计程序。 | C29: IPO/上市/新三板/重组/舞弊应对
A30: 14 | B30: 检查预计负债是否已按企业会计准则或其他适用的规定在财务报表中做出恰当列报和披露。 | C30: 常规★ | H30: √ | I30: A 1-1/A1-15 /A1-16

Sheet 审定表 K5-1
A1: 致同会计师事务所
A2: 预计负债审定表
A3: =底稿目录!A2 -> 被审计单位： | D3: =底稿目录!A4 -> 编制人： | I3: =底稿目录!A5 -> 编制日期： | K3: 索引： | L3: =底稿目录!D6 -> K5-1
A4: =底稿目录!A3 -> 截止日：202X年12月31日 | D4: =底稿目录!A6 -> 复核人： | I4: =底稿目录!A7 -> 复核日期： | K4: 页次： | L4: 1
A5: 项目 | B5: 期初数 | F5: 期末数 | J5: 本期审定数与上期 审定数的比较 | L5: 原因分析
B6: 未审数 | C6: 账项调整 | D6: 重分类调整 | E6: 审定数 | F6: 未审数 | G6: 账项调整 | H6: 重分类调整 | I6: 审定数 | J6: 变动额 | K6: 变动率
A7: ='明细表 K5-2'!A13 -> 弃置费用 | B7: ='明细表 K5-2'!C13 -> 0 | C7: ='明细表 K5-2'!G13 -> 0 | D7: ='明细表 K5-2'!H13 -> 0 | E7: =B7+C7+D7 -> 0 | F7: ='明细表 K5-2'!F13 -> 0 | G7: ='明细表 K5-2'!G13+'明细表 K5-2'!I13-'明细表 K5-2'!J13 -> 0 | H7: ='明细表 K5-2'!H13+'明细表 K5-2'!K13-'明细表 K5-2'!L13 -> 0 | I7: =F7+G7+H7 -> 0 | J7: =I7-E7 -> 0 | K7: =IF(AND(E7=0,J7=0),0,IF(AND(E7=0,J7>0),1,J7/E7)) -> 0
A8: ='明细表 K5-2'!A14 -> 对外提供担保 | B8: ='明细表 K5-2'!C14 -> 0 | C8: ='明细表 K5-2'!G14 -> 0 | D8: ='明细表 K5-2'!H14 -> 0 | E8: =B8+C8+D8 -> 0 | F8: ='明细表 K5-2'!F14 -> 0 | G8: ='明细表 K5-2'!G14+'明细表 K5-2'!I14-'明细表 K5-2'!J14 -> 0 | H8: ='明细表 K5-2'!H14+'明细表 K5-2'!K14-'明细表 K5-2'!L14 -> 0 | I8: =F8+G8+H8 -> 0 | J8: =I8-E8 -> 0 | K8: =IF(AND(E8=0,J8=0),0,IF(AND(E8=0,J8>0),1,J8/E8)) -> 0
A9: ='明细表 K5-2'!A15 -> 未决诉讼 | B9: ='明细表 K5-2'!C15 -> 0 | C9: ='明细表 K5-2'!G15 -> 0 | D9: ='明细表 K5-2'!H15 -> 0 | E9: =B9+C9+D9 -> 0 | F9: ='明细表 K5-2'!F15 -> 0 | G9: ='明细表 K5-2'!G15+'明细表 K5-2'!I15-'明细表 K5-2'!J15 -> 0 | H9: ='明细表 K5-2'!H15+'明细表 K5-2'!K15-'明细表 K5-2'!L15 -> 0 | I9: =F9+G9+H9 -> 0 | J9: =I9-E9 -> 0 | K9: =IF(AND(E9=0,J9=0),0,IF(AND(E9=0,J9>0),1,J9/E9)) -> 0
A10: ='明细表 K5-2'!A16 -> 产品质量保证 | B10: ='明细表 K5-2'!C16 -> 0 | C10: ='明细表 K5-2'!G16 -> 0 | D10: ='明细表 K5-2'!H16 -> 0 | E10: =B10+C10+D10 -> 0 | F10: ='明细表 K5-2'!F16 -> 0 | G10: ='明细表 K5-2'!G16+'明细表 K5-2'!I16-'明细表 K5-2'!J16 -> 0 | H10: ='明细表 K5-2'!H16+'明细表 K5-2'!K16-'明细表 K5-2'!L16 -> 0 | I10: =F10+G10+H10 -> 0 | J10: =I10-E10 -> 0 | K10: =IF(AND(E10=0,J10=0),0,IF(AND(E10=0,J10>0),1,J10/E10)) -> 0
A11: ='明细表 K5-2'!A17 -> 重组义务 | B11: ='明细表 K5-2'!C17 -> 0 | C11: ='明细表 K5-2'!G17 -> 0 | D11: ='明细表 K5-2'!H17 -> 0 | E11: =B11+C11+D11 -> 0 | F11: ='明细表 K5-2'!F17 -> 0 | G11: ='明细表 K5-2'!G17+'明细表 K5-2'!I17-'明细表 K5-2'!J17 -> 0 | H11: ='明细表 K5-2'!H17+'明细表 K5-2'!K17-'明细表 K5-2'!L17 -> 0 | I11: =F11+G11+H11 -> 0 | J11: =I11-E11 -> 0 | K11: =IF(AND(E11=0,J11=0),0,IF(AND(E11=0,J11>0),1,J11/E11)) -> 0
A12: ='明细表 K5-2'!A18 -> 待执行的亏损合同 | B12: ='明细表 K5-2'!C18 -> 0 | C12: ='明细表 K5-2'!G18 -> 0 | D12: ='明细表 K5-2'!H18 -> 0 | E12: =B12+C12+D12 -> 0 | F12: ='明细表 K5-2'!F18 -> 0 | G12: ='明细表 K5-2'!G18+'明细表 K5-2'!I18-'明细表 K5-2'!J18 -> 0 | H12: ='明细表 K5-2'!H18+'明细表 K5-2'!K18-'明细表 K5-2'!L18 -> 0 | I12: =F12+G12+H12 -> 0 | J12: =I12-E12 -> 0 | K12: =IF(AND(E12=0,J12=0),0,IF(AND(E12=0,J12>0),1,J12/E12)) -> 0
A13: ='明细表 K5-2'!A19 -> 应付退货款 | B13: ='明细表 K5-2'!C19 -> 0 | C13: ='明细表 K5-2'!G19 -> 0 | D13: ='明细表 K5-2'!H19 -> 0 | E13: =B13+C13+D13 -> 0 | F13: ='明细表 K5-2'!F19 -> 0 | G13: ='明细表 K5-2'!G19+'明细表 K5-2'!I19-'明细表 K5-2'!J19 -> 0 | H13: ='明细表 K5-2'!H19+'明细表 K5-2'!K19-'明细表 K5-2'!L19 -> 0 | I13: =F13+G13+H13 -> 0 | J13: =I13-E13 -> 0 | K13: =IF(AND(E13=0,J13=0),0,IF(AND(E13=0,J13>0),1,J13/E13)) -> 0
A14: ='明细表 K5-2'!A20 -> 其他 | B14: ='明细表 K5-2'!C20 -> 0 | C14: ='明细表 K5-2'!G20 -> 0 | D14: ='明细表 K5-2'!H20 -> 0 | E14: =B14+C14+D14 -> 0 | F14: ='明细表 K5-2'!F20 -> 0 | G14: ='明细表 K5-2'!G20+'明细表 K5-2'!I20-'明细表 K5-2'!J20 -> 0 | H14: ='明细表 K5-2'!H20+'明细表 K5-2'!K20-'明细表 K5-2'!L20 -> 0 | I14: =F14+G14+H14 -> 0 | J14: =I14-E14 -> 0 | K14: =IF(AND(E14=0,J14=0),0,IF(AND(E14=0,J14>0),1,J14/E14)) -> 0
A15: 合计 | B15: =SUM(B7:B14) -> 0 | C15: =SUM(C7:C14) -> 0 | D15: =SUM(D7:D14) -> 0 | E15: =SUM(E7:E14) -> 0 | F15: =SUM(F7:F14) -> 0 | G15: =SUM(G7:G14) -> 0 | H15: =SUM(H7:H14) -> 0 | I15: =SUM(I7:I14) -> 0 | J15: =I15-E15 -> 0 | K15: =IF(AND(E15=0,J15=0),0,IF(AND(E15=0,J15>0),1,J15/E15)) -> 0
A16: TB数据：
A17: 差异： | B17: =B15-B16 -> 0 | C17: =C15-C16 -> 0 | D17: =D15-D16 -> 0 | E17: =E15-E16 -> 0 | F17: =F15-F16 -> 0 | G17: =G15-G16 -> 0 | H17: =H15-H16 -> 0 | I17: =I15-I16 -> 0 | ... K17: =K15-K16 -> 0
A18: 1.审计说明
A19: （1）预计负债本期较上期增加（负数为减少）：
A20: 主要原因（比例超过30%的）：
A22: （2）情况说明。
A24: 2.审计结论

Sheet 附注披露信息（上市公司)
A1: 致同会计师事务所
A2: 附注披露信息（上市公司）
A3: =底稿目录!A2 -> 被审计单位： | B3: =底稿目录!A4 -> 编制人： | C3: =底稿目录!A5 -> 编制日期： | D3: 索引： | E3: =底稿目录!D7 -> 0
A4: =底稿目录!A3 -> 截止日：202X年12月31日 | B4: =底稿目录!A6 -> 复核人： | C4: =底稿目录!A7 -> 复核日期： | D4: 页次： | E4: 1
A5: 预计负债
A6: 项 目 | B6: 期末数 | C6: 期初数 | D6: 形成原因
A7: ='审定表 K5-1'!A7 -> 弃置费用 | B7: ='明细表 K5-2'!P13 -> 0 | C7: ='明细表 K5-2'!M13 -> 0 | D7: ='明细表 K5-2'!B13 -> 0
A8: ='审定表 K5-1'!A8 -> 对外提供担保 | B8: ='明细表 K5-2'!P14 -> 0 | C8: ='明细表 K5-2'!M14 -> 0 | D8: ='明细表 K5-2'!B14 -> 0
A9: ='审定表 K5-1'!A9 -> 未决诉讼 | B9: ='明细表 K5-2'!P15 -> 0 | C9: ='明细表 K5-2'!M15 -> 0 | D9: ='明细表 K5-2'!B15 -> 0
A10: ='审定表 K5-1'!A10 -> 产品质量保证 | B10: ='明细表 K5-2'!P16 -> 0 | C10: ='明细表 K5-2'!M16 -> 0 | D10: ='明细表 K5-2'!B16 -> 0
A11: ='审定表 K5-1'!A11 -> 重组义务 | B11: ='明细表 K5-2'!P17 -> 0 | C11: ='明细表 K5-2'!M17 -> 0 | D11: ='明细表 K5-2'!B17 -> 0
A12: ='审定表 K5-1'!A12 -> 待执行的亏损合同 | B12: ='明细表 K5-2'!P18 -> 0 | C12: ='明细表 K5-2'!M18 -> 0 | D12: ='明细表 K5-2'!B18 -> 0
A13: ='审定表 K5-1'!A13 -> 应付退货款 | B13: ='明细表 K5-2'!P19 -> 0 | C13: ='明细表 K5-2'!M19 -> 0 | D13: ='明细表 K5-2'!B19 -> 0
A14: ='审定表 K5-1'!A14 -> 其他 | B14: ='明细表 K5-2'!P20 -> 0 | C14: ='明细表 K5-2'!M20 -> 0 | D14: ='明细表 K5-2'!B20 -> 0
A15: 合 计 | B15: =SUM(B7:B14) -> 0 | C15: =SUM(C7:C14) -> 0
A16: 说明：重要的预计负债，应披露相关重要假设、估计。

Sheet 附注披露信息（国企）
A1: 致同会计师事务所
A2: 附注披露信息（国企）
A3: =底稿目录!A2 -> 被审计单位： | B3: =底稿目录!A4 -> 编制人： | C3: =底稿目录!A5 -> 编制日期： | D3: 索引： | E3: =底稿目录!D8 -> 0
A4: =底稿目录!A3 -> 截止日：202X年12月31日 | B4: =底稿目录!A6 -> 复核人： | C4: =底稿目录!A7 -> 复核日期： | D4: 页次： | E4: 1
A5: 预计负债
A6: 项 目 | B6: 期末数 | C6: 期初数 | D6: 形成原因
A7: ='审定表 K5-1'!A7 -> 弃置费用 | B7: ='明细表 K5-2'!P13 -> 0 | C7: ='明细表 K5-2'!M13 -> 0 | D7: ='明细表 K5-2'!B13 -> 0
A8: ='审定表 K5-1'!A8 -> 对外提供担保 | B8: ='明细表 K5-2'!P14 -> 0 | C8: ='明细表 K5-2'!M14 -> 0 | D8: ='明细表 K5-2'!B14 -> 0
A9: ='审定表 K5-1'!A9 -> 未决诉讼 | B9: ='明细表 K5-2'!P15 -> 0 | C9: ='明细表 K5-2'!M15 -> 0 | D9: ='明细表 K5-2'!B15 -> 0
A10: ='审定表 K5-1'!A10 -> 产品质量保证 | B10: ='明细表 K5-2'!P16 -> 0 | C10: ='明细表 K5-2'!M16 -> 0 | D10: ='明细表 K5-2'!B16 -> 0
A11: ='审定表 K5-1'!A11 -> 重组义务 | B11: ='明细表 K5-2'!P17 -> 0 | C11: ='明细表 K5-2'!M17 -> 0 | D11: ='明细表 K5-2'!B17 -> 0
A12: ='审定表 K5-1'!A12 -> 待执行的亏损合同 | B12: ='明细表 K5-2'!P18 -> 0 | C12: ='明细表 K5-2'!M18 -> 0 | D12: ='明细表 K5-2'!B18 -> 0
A13: ='审定表 K5-1'!A13 -> 应付退货款 | B13: ='明细表 K5-2'!P19 -> 0 | C13: ='明细表 K5-2'!M19 -> 0 | D13: ='明细表 K5-2'!B19 -> 0
A14: ='审定表 K5-1'!A14 -> 其他 | B14: ='明细表 K5-2'!P20 -> 0 | C14: ='明细表 K5-2'!M20 -> 0 | D14: ='明细表 K5-2'!B20 -> 0
A15: 合 计 | B15: =SUM(B7:B14) -> 0 | C15: =SUM(C7:C14) -> 0

Sheet 明细表 K5-2
A1: 致同会计师事务所
A2: 预计负债明细表
A3: =底稿目录!A2 -> 被审计单位： | G3: =底稿目录!A4 -> 编制人： | L3: =底稿目录!A5 -> 编制日期： | P3: 索引号： | Q3: =底稿目录!D9 -> K5-2
A4: =底稿目录!A3 -> 截止日：202X年12月31日 | G4: =底稿目录!A6 -> 复核人： | L4: =底稿目录!A7 -> 复核日期： | P4: 页次：
A5: 一、审计目标:
A6: 1.资产负债表中记录的预计负债是存在的，且已记录于恰当的账户； | G6: 2.所有应记录的预计负债均已记录，所有应当包括在财务报表中的相关披露均已包括；
A7: 3.预计负债以恰当的金额包括在财务报表中，与之相关的计价或分摊调整已恰当记录，相关披露已得到恰当计量和描述。
A8: 二、审计过程：
A9: 1.了解形成预计负债的原因，并与管理层就预计负债的完整性和充分计提进行讨论，以确定金额估计是否合理，相关的会计处理是否正确
A10: 2.根据外部公开信息、会议纪要、公章使用登记簿等渠道，查找是否存在未入账的预计负债，例如未入账的对外担保、未决诉讼等事项的程序。
A11: 项目类别 | B11: 预计负债计提原因 | C11: 未审数 | G11: 期初调整 | I11: 账项调整 | K11: 重分类调整 | M11: 审定数 | Q11: 备注
C12: 期初数 | D12: 本期增加 | E12: 本期减少 | F12: 期末数 | G12: 账项调整 | H12: 重分类调整 | I12: 本期增加 | J12: 本期减少 | K12: 本期增加 | L12: 本期减少 | M12: 期初数 | N12: 本期增加 | O12: 本期减少 | P12: 期末数
A13: 弃置费用 | F13: =C13+D13-E13 -> 0 | M13: =C13+G13+H13 -> 0 | N13: =D13+I13+K13 -> 0 | O13: =E13+J13+L13 -> 0 | P13: =M13+N13-O13 -> 0
A14: 对外提供担保 | F14: =C14+D14-E14 -> 0 | M14: =C14+G14+H14 -> 0 | N14: =D14+I14+K14 -> 0 | O14: =E14+J14+L14 -> 0 | P14: =M14+N14-O14 -> 0
A15: 未决诉讼 | F15: =C15+D15-E15 -> 0 | M15: =C15+G15+H15 -> 0 | N15: =D15+I15+K15 -> 0 | O15: =E15+J15+L15 -> 0 | P15: =M15+N15-O15 -> 0
A16: 产品质量保证 | F16: =C16+D16-E16 -> 0 | M16: =C16+G16+H16 -> 0 | N16: =D16+I16+K16 -> 0 | O16: =E16+J16+L16 -> 0 | P16: =M16+N16-O16 -> 0
A17: 重组义务 | F17: =C17+D17-E17 -> 0 | M17: =C17+G17+H17 -> 0 | N17: =D17+I17+K17 -> 0 | O17: =E17+J17+L17 -> 0 | P17: =M17+N17-O17 -> 0
A18: 待执行的亏损合同 | F18: =C18+D18-E18 -> 0 | M18: =C18+G18+H18 -> 0 | N18: =D18+I18+K18 -> 0 | O18: =E18+J18+L18 -> 0 | P18: =M18+N18-O18 -> 0
A19: 应付退货款 | F19: =C19+D19-E19 -> 0 | M19: =C19+G19+H19 -> 0 | N19: =D19+I19+K19 -> 0 | O19: =E19+J19+L19 -> 0 | P19: =M19+N19-O19 -> 0
A20: 其他 | F20: =C20+D20-E20 -> 0 | M20: =C20+G20+H20 -> 0 | N20: =D20+I20+K20 -> 0 | O20: =E20+J20+L20 -> 0 | P20: =M20+N20-O20 -> 0
A21: 合计 | C21: =SUM(C13:C20) -> 0 | D21: =SUM(D13:D20) -> 0 | E21: =SUM(E13:E20) -> 0 | F21: =SUM(F13:F20) -> 0 | G21: =SUM(G13:G20) -> 0 | H21: =SUM(H13:H20) -> 0 | I21: =SUM(I13:I20) -> 0 | J21: =SUM(J13:J20) -> 0 | ... P21: =SUM(P13:P20) -> 0
A22: 三、审计说明：
A23: 1.关于应付退货款的检查，详见收入底稿D2XXXX
A26: 四、审计结论：
A29: 提示：
A30: 1、本科目核算企业确认的对外提供担保、未决诉讼、产品质量保证、重组义务、亏损性合同等预计负债。常见预计负债的项目：未决诉讼、未决仲裁、对外担保、票据贴现、亏损合同、环境污染整冶义务、附有销售退回条款的销售、重组义务、产品质量保证、承诺等。
A31: 2、对预计负债的计提方法应在“备注”栏中说明。满足预计负债的条件是：该义务是企业承担的现实义务；履行该义务很可能导致经济利益流出企业；该义务金额能够可靠计量。
A32: 3、企业由对外提供担保、未决诉讼、重组义务产生的预计负债，应按确定的金额，借记“营业外支出”等科目，贷记本科目。
A33: 4、因保证类质量保证产生的预计负债，应当按确定的金额，借记“主营业务成本”、“其他业务成本”等科目，贷记预计负债；。
A34: 5、由附有销售退回条款的销售产生的预计负债，按预期因销售退回将退还的金额，借记"银行存款"或"应收账款"，贷记本科目。
A35: 6、因亏损合同产生的预计负债，应当按照功能分类，借记“主营业务成本”、“其他业务成本”等科目，贷记预计负债。
A36: 7、由资产弃置义务产生的预计负债，应按确定的金额，借记“固定资产”或“油气资产”科目，贷记本科目。
A37: 在固定资产或油气资产的使用寿命内，按计算确定各期应负担的利息费用，借记“财务费用”科目，贷记本科目。
... A42: 12、审计结论可参考：A、未见异常。 B、除上述重大不符事项应当作为调整事项予以调整外，其余未见异常。 C、由于存在以下重大未调整事项（或审计范围受到限制无法获取充分、适当证据），不可确认。

Sheet 调整分录汇总 K5-3
A1: 致同会计师事务所
A2: 预计负债调整分录汇总表
A3: =底稿目录!A2 -> 被审计单位： | C3: =底稿目录!A4 -> 编制人： | F3: =底稿目录!A5 -> 编制日期： | I3: 索引号： | J3: =底稿目录!D10 -> K5-3
A4: =底稿目录!A3 -> 截止日：202X年12月31日 | C4: =底稿目录!A6 -> 复核人： | F4: =底稿目录!A7 -> 复核日期： | I4: 页次：
A5: 调整事项说明 | B5: 类别（报表调整/账项调整/其他） | C5: 报表项目 | D5: 科目名称 | E5: 附注项目 | F5: …… | G5: 借方调整金额 | H5: 贷方调整金额 | I5: 索引 | J5: 备注
A21: 提示：本底稿适用于调整分录较多、较复杂的项目，且仅列示与本报表项目相关的审计调整。项目组可根据项目实际情况选择是否使用该底稿。

Sheet 产品质量保修检查表 K5-4
A1: 致同会计师事务所
A2: 产品质量保修检查表
A3: =底稿目录!A2 -> 被审计单位： | C3: =底稿目录!A4 -> 编制人： | E3: =底稿目录!A5 -> 编制日期： | F3: 索引号： | G3: =底稿目录!D11 -> K5-4
A4: =底稿目录!A3 -> 截止日：202X年12月31日 | C4: =底稿目录!A6 -> 复核人： | E4: =底稿目录!A7 -> 复核日期： | F4: 页次：
A5: 一、审计目标:
A6: 1.资产负债表中记录的预计负债是存在的，且已经记录在恰当的账户中；
A7: 2. 所有应记录的预计负债均已记录，所有应当包括在财务报表中的相关披露均已包括；3.记录的预计负债是被审计单位应当履行的偿还义务；
A8: 4.预计负债以恰当的金额包括在财务报表中，与之相关的计价或分摊调整已恰当记录，相关披露已得到恰当计量和描述。
A9: 二、审计过程：
A10: （一）产品质量保修政策
A13: （二）检查历史质量保修情况，并评估产品质量保证金的计提比例是否合理
A14: 产品类别 | B14: 本期实际发生金额 | C14: 本期收入金额 | D14: 202X年实际发生金额 | E14: 202X年收入金额 | F14: 202X年实际发生金额 | G14: 202X年收入金额
A15: 产品1
A16: 产品2
A17: 产品3
A18: 产品4
A19: 合计 | B19: =SUM(B15:B18) -> 0 | C19: =SUM(C15:C18) -> 0 | D19: =SUM(D15:D18) -> 0 | E19: =SUM(E15:E18) -> 0 | F19: =SUM(F15:F18) -> 0 | G19: =SUM(G15:G18) -> 0
A22: （三）重新测算产品质量保证金
A23: 产品类别 | B23: 计提基数 | C23: 计提比例 | D23: 应计提金额 | E23: 账面已计提金额 | F23: 差异金额 | G23: 差异原因
A24: 产品1 | D24: =B24*C24 -> 0 | F24: =D24-E24 -> 0
A25: 产品2 | D25: =B25*C25 -> 0 | F25: =D25-E25 -> 0
A26: 产品3 | D26: =B26*C26 -> 0 | F26: =D26-E26 -> 0
A27: 产品4 | D27: =B27*C27 -> 0 | F27: =D27-E27 -> 0
A28: 合计 | B28: =SUM(B24:B27) -> 0 | D28: =SUM(D24:D27) -> 0 | E28: =SUM(E24:E27) -> 0 | F28: =SUM(F24:F27) -> 0
A31: （四）预计保修发生时间
A32: 序号 | B32: 产品 | C32: 期末数 | D32: 预计保修发生时间
D33: 1年以内 | E33: 1年以上
A34: 1 | B34: 产品1
A35: 2 | B35: 产品2
A36: 3 | B36: 产品3
A37: 4 | B37: 产品4
B38: 合计 | C38: =SUM(C33:C37) -> 0 | D38: =SUM(D33:D37) -> 0 | E38: =SUM(E33:E37) -> 0
A40: 三、审计说明：
A43: 四、审计结论：

Sheet 弃置费用检查表 K5-5
A1: 致同会计师事务所
A2: 弃置费用检查表
A3: =底稿目录!A2 -> 被审计单位： | C3: =底稿目录!A4 -> 编制人： | E3: =底稿目录!A5 -> 编制日期： | G3: 索引号： | H3: =底稿目录!D12 -> K5-5
A4: =底稿目录!A3 -> 截止日：202X年12月31日 | C4: =底稿目录!A6 -> 复核人： | E4: =底稿目录!A7 -> 复核日期： | G4: 页次：
A5: 一、审计目标:
A6: 1.资产负债表中记录的预计负债是存在的，且已经记录在恰当的账户中；
A7: 2. 所有应记录的预计负债均已记录，所有应当包括在财务报表中的相关披露均已包括；3.记录的预计负债是被审计单位应当履行的偿还义务；
A8: 4.预计负债以恰当的金额包括在财务报表中，与之相关的计价或分摊调整已恰当记录，相关披露已得到恰当计量和描述。
A9: 二、审计过程：
A10: （一）弃置费用的完整性检查
A11: 序号 | B11: 描述相关内部资料、外部评估报告等 | C11: 描述与第三方机构或监管机构的函件 | D11: 检查固定资产本期增加，是否有迹象表明计提的弃置费用不足 | E11: 实地观察固定资产，是否有迹象表明计提的弃置费用不足 | F11: 相关支持性资料索引
A12: 1
A13: （二）关键假设评估
A14: 序号 | B14: 关键假设 | E14: 是否与历史数据、行业数据一致 | F14: 期后事项是否会影响关键假设？ | G14: 关键假设是否合理？ | H14: 相关支持性资料索引
B15: 1、aa | C15: 2.bb | D15: 3.cc
A16: 1
A18: 借方发生额分析 | E18: 贷方发生数分析
A19: 序号 | B19: 对应科目 | C19: 对应金额 | D19: 备注 | E19: 对应科目 | G19: 对应金额 | H19: 备注
A20: 1
A21: 2
A22: 3
A23: 4
A24: 5
A25: 小计 | C25: =SUM(C20:C24) -> 0 | E25: 小计 | G25: =SUM(G20:G24) -> 0
A26: 三、审计说明：
A28: 四、审计结论：

Sheet 未决诉讼检查表 K5-6
A1: 致同会计师事务所
A2: 未决诉讼检查表
A3: =底稿目录!A2 -> 被审计单位： | D3: =底稿目录!A4 -> 编制人： | F3: =底稿目录!A5 -> 编制日期： | I3: 索引号： | J3: =底稿目录!D13 -> K5-6
A4: =底稿目录!A3 -> 截止日：202X年12月31日 | D4: =底稿目录!A6 -> 复核人： | F4: =底稿目录!A7 -> 复核日期： | I4: 页次：
A5: 一、审计目标:
A6: 1.资产负债表中记录的预计负债是存在的，且已经记录在恰当的账户中；
A7: 2. 所有应记录的预计负债均已记录，所有应当包括在财务报表中的相关披露均已包括；3.记录的预计负债是被审计单位应当履行的偿还义务；
A8: 4.预计负债以恰当的金额包括在财务报表中，与之相关的计价或分摊调整已恰当记录，相关披露已得到恰当计量和描述。
A9: 二、审计过程：
A10: 诉讼事项 | B10: 进展情况 | C10: 判决文件资料 | D10: 应承担的赔偿支出金额 | E10: 已计提的预计负债 | F10: 差异金额 | G10: 差异原因 | H10: 法律专家意见 | I10: 法律意见书/律师询证函索引号
F11: =E11-D11 -> 0
F12: =E12-D12 -> 0
F13: =E13-D13 -> 0
F14: =E14-D14 -> 0
F15: =E15-D15 -> 0
F16: =E16-D16 -> 0
F17: =E17-D17 -> 0
A18: 合计 | F18: =SUM(F11:F17) -> 0
A19: 一、审计说明：
A20: 1.诉讼事项描述：
A21: 2.截止审计报告日诉讼判决进展情况……
A22: 3.期后支付情况……
A23: 二、审计结论：
A26: 提示：
A27: 证监会发布的《2020年上市公司年报会计监管报告》指出： 1.未恰当确认因诉讼产生的支付义务 根据企业会计准则及相关规定，对于未决诉讼、未决仲裁等形成的或有负债，随着时间推移和事态的进展，相关未决诉讼在被证实很可能导致经济利益流出，且该义务金额也能够可靠计量时，企业应当确认预计负债。企业应当在资产负债表日对预计负债的账面价值进行复核。有确凿证据表明该账面价值不能真实反映当前最佳估计数的，应当按照当前最佳估计数对该账面价值进行调整。年报分析发现，个别上市公司因合同纠纷被起诉，在法院一审判决其败诉并要求对原告进行赔偿的情况下，上市公司仍以上诉为由未确认相关损失和预计负债，缺乏合理性。 2.不恰当抵销预计负债与或有资产 根据企业会计准则及相关规定，与或有事项相关的义务同时满足现时义务、很可能导致经济利益流出、金额能够可能计量的条件时，应当确认为预计负债。或有事项产生的经济利益只有在企业基本确定能够收到的情况下，才予以确认为资产。针对同一公司的预计负债与或有资产应在满足上述条件的前提下分别确认，二者之间不得随意抵销。年报分析发现，个别上市公司与不同公司间存在多个诉讼事项，相关公司同属一个集团。根据判决结果，个别诉讼判决公司需对外支付赔偿款，个别诉讼判决公司胜诉并基本确定能够获得赔偿款。公司认为相关诉讼案件中，其应付的赔偿义务与应收赔偿款金额大致持平，未根据实际情况合理确认预计负债及或有资产，错误地抵销预计负债与或有资产，未恰当确认预计赔偿损失及补偿收益。
A37: 提示：对于财务报表批准报出日已取得一审判决，在一审判决公司败诉并要求对原告进行赔偿的情况下，如果被审计单位未按照一审判决金额计提预计负债，建议项目组尽早履行业务咨询。

Sheet 预计负债检查表 K5-7
A1: 致同会计师事务所
A2: 预计负债检查表
A3: =底稿目录!A2 -> 被审计单位： | F3: =底稿目录!A4 -> 编制人： | J3: =底稿目录!A5 -> 编制日期： | P3: 索引号： | Q3: =底稿目录!D14 -> K5-7
A4: =底稿目录!A3 -> 截止日：202X年12月31日 | F4: =底稿目录!A6 -> 复核人： | J4: =底稿目录!A7 -> 复核日期： | P4: 页次：
A5: 一、审计目标：
A6: 1.资产负债表中记录的预计负债是存在的，且已经记录在恰当的账户中； | H6: 2.记录的预计负债是被审计单位应当履行的偿还义务；
A7: 3.预计负债以恰当的金额包括在财务报表中，与之相关的计价或分摊调整已恰当记录，相关披露已得到恰当计量和描述。
A8: 二、样本选取标准与规模：
A9: 测试总体： | B9: 如借方发生额所有凭证共XX笔金额XX、贷方发生额所有凭证共XX笔金额XX | G9: 特定样本： | H9: XX金额以上（大额）、关联方/关联交易形成的款项、XX异常款项全部测试，共XX笔；
A10: 抽样总体： | B10: 测试总体扣除特定样本以外的样本，共XX笔、金额XX | G10: 确定的抽样样本量： | H10: 抽取XX笔 | I10: （如果使用了样本计算器计算样本量，样本量计算过程见<XX>底稿）
A11: 抽样方法： | B11: 随机选样/系统选样/货币单元抽样/随意选样（非统计抽样适用） | G11: 抽样过程： | H11: 使用IDEA（XX抽样工具）选择XX数量、金额XX的样本进行测试，抽样工具中的样本选择过程和结果见<XX>底稿
A12: 三、测试：
A13: 测试内容说明：1.原始凭证是否齐全； 2.记账凭证与原始凭证是否相符；3.账务处理是否正确；4.是否记录于恰当的会计期间；5.……
A14: 1.本期发生额检查
A15: 明细项目 | B15: 记账凭证 | I15: 支持性文件 | J15: 核对内容 | O15: 索引号 | P15: 是否异常 | Q15: 备注说明
B16: 日期 | C16: 凭证编号 | D16: 业务内容 | E16: 对方科目 | F16: 对方明细科目 | G16: 借方金额 | H16: 贷方金额 | J16: 1 | K16: 2 | L16: 3 | M16: 4 | N16: 5
A27: 合计 | G27: =SUM(G17:G26) -> 0 | H27: =SUM(H17:H26) -> 0
A28: 2.期后检查
A29: 项目 | B29: 记账凭证 | I29: 支持性文件 | J29: 核对内容 | O29: 索引号 | P29: 是否异常 | Q29: 备注说明
B30: 日期 | C30: 凭证编号 | D30: 业务内容 | E30: 对方科目 | F30: 对方明细科目 | G30: 借方金额 | H30: 贷方金额 | J30: 1 | K30: 2 | L30: 3 | M30: 4 | N30: 5
A38: 合计 | G38: =SUM(G31:G37) -> 0 | H38: =SUM(H31:H37) -> 0
A39: 四、审计说明：
A40: 1.本期发生额、期末余额检查比例： | D40: 方向 | E40: 账面金额 | F40: 检查金额 | G40: 检查比例 | H40: 如果检查比例较低应扩大检查样本量或说明原因
D41: 本期借方 | E41: ='明细表 K5-2'!O21 -> 0 | F41: =G27 -> 0 | G41: =ROUND(F41/E41,4) -> #DIV/0!
D42: 本期贷方 | E42: ='明细表 K5-2'!N21 -> 0 | F42: =H27 -> 0 | G42: =ROUND(F42/E42,2) -> #DIV/0!
D43: 期末余额 | E43: ='明细表 K5-2'!P21 -> 0 | F43: =G38 -> 0 | G43: =ROUND(F43/E43,2) -> #DIV/0!
A44: 2.……
A45: 五、审计结论：
