Workbook

Sheet 底稿目录
A1: 底稿开列时，可先在以下单元格填写有关内容，以便其他底稿引用有关数据：
A2: 被审计单位：
A3: 截止日：202X年12月31日 | D3: 序号 | E3: 内容 | F3: 索引号 | G3: 备注
A4: 编制人： | D4: 1 | E4: 实质性程序表 | F4: K7A
A5: 编制日期： | D5: 2 | E5: 审定表 | F5: K7-1
A6: 复核人： | D6: 3 | E6: 附注披露信息（上市公司） | H6: 无需打印
A7: 复核日期： | D7: 4 | E7: 附注披露信息（国有企业） | H7: 无需打印
D8: 5 | E8: 明细表 | F8: K7-2
A9: 关于工作底稿与审计程序索引号对应的说明 | D9: 6 | E9: 调整分录汇总 | F9: K7-3
A10: 1.编制的审计工作底稿应与审计程序对应。审计项目组应根据被审计单位实际情况和风险评估情况在实质性程序表中裁剪、修改或增加审计程序，根据实际执行的审计程序完成相应审计工作底稿，编制的工作底稿中应按自然顺序依次编制索引号，并通过唯一的索引号将与实质性程序表中的程序对应关联（即将工作底稿的索引号填入实质性程序表中的底稿索引号列）。 | D10: 7 | E10: 测算表 | F10: K7-4
D11: 8 | E11: 递延收益检查表 | F11: K7-5
A14: 2.获取的支持性证据应与审计底稿或程序对应。审计项目组在完成底稿时获取的支持性证据应根据底稿索引号编制下一级按自然顺序排序的索引号（如D1-2-1、D1-2-2、……），并在底稿中说明引用的支持性证据、关联索引号。
A17: 3.工作底稿索引号的编码规则：实质性程序索引号按循环从“D”到“N”,循环内账户以顺序号排列，模板中底稿索引号按账户顺序+自然数顺序（即模板中索引号按二级自然顺序排列，如D1-1、D1-2、D1-3、……D1-N）。

Sheet 实质性程序表K7A
A1: 致同会计师事务所
A2: 递延收益实质性程序表
A3: =底稿目录!A2 -> 被审计单位： | C3: =底稿目录!A4 -> 编制人： | E3: =底稿目录!A5 -> 编制日期： | H3: 索引号： | I3: =底稿目录!F4 -> K7A
A4: =底稿目录!A3 -> 截止日：202X年12月31日 | C4: =底稿目录!A6 -> 复核人： | E4: =底稿目录!A7 -> 复核日期： | H4: 页 次：
A5: 一、本账户涉及的科目
A6: 递延收益
A7: 二、审计目标与认定的对应关系
A8: 审计目标 | G8: 财务报表的认定
A9: A. 资产负债表中记录的递延收益是存在的，且已记录于恰当的账户 | G9: 存在
A10: B. 所有应记录的递延收益均已记录，所有应当包括在财务报表中的相关披露均已包括 | G10: 完整性
A11: C. 记录的递延收益是被审计单位应当履行的偿还义务 | G11: 权利和义务
A12: D. 递延收益以恰当的金额包括在财务报表中，与之相关的计价或分摊调整已恰当记录，相关披露已得到恰当计量和描述 | G12: 准确性、计价和分摊
A13: E. 递延收益已被恰当地汇总或分解且表述清楚，相关披露在按照企业会计准则的编制基础下是相关的、可理解的 | G13: 列报
A14: 三、计划实施的实质性程序
A15: 序号 | B15: 审计程序 | C15: 程序分类 | D15: 财务报表的认定 | I15: 底稿索引号
D16: 存在 | E16: 完整性 | F16: 权利和 义务 | G16: 准确性、计价和分摊 | H16: 列报 | J16: 根据被审计单位实际情况和风险评估情况裁剪、修改或增加审计程序
A17: 1 | B17: 获取递延收益明细表，并执行下列程序，并编制审定表： 复核加计正确；将总金额与总账核对，期初余额与上期审定期末余额是否相符；了解递延收益核算的内容，判断其分类为递延收益是否恰当。 | C17: 常规★ | D17: √ | E17: √ | G17: √ | I17: K7-1 /K7-2
A18: 2 | B18: 在使用手工编制、自定义信息报告、系统生成的非固定格式报告等由被审计单位生成的信息时，测试有关信息准确性和完整性，并考虑针对编制和维护由被审计单位生成的信息的相关控制实施控制测试，以评价该信息是否能够为实现审计目的提供基础。 | C18: 常规★ | E18: √ | G18: √ | I18: T1 | J18: 可参见《审计手册》4.2.6，由被审计单位生成的信息可能是由系统生成的、或手工编制的、或二者兼而有之的方式生成的。例如，由被审计单位生成的信息可能包括： • 不涉及自定义的、由系统生成的报告（如，固定格式报告）； • 可能通过人工自定义的、由系统生成的报告，例如，（计算机）查询信息或特别定制的报告； • 手工编制的信息，例如，汇总信息的电子表格或用以支持分配、计算以及调节的电子表格； • 其他系统生成或手工编制的信息，例如，由被审计单位编制的客户发票； • 通过影印、拍摄、扫描或其他方式转换成电子形式的文件记录。
A19: 3 | B19: 对期初余额的审计，取得递延收益期初余额明细表复核加计是否正确，与总账、明细账合计数是否相符，检查上期递延收益在本期变动情况，将重大递延收益与其支持文件核对。（适用于首次承接） | C19: 备选 | D19: √ | E19: √ | F19: √ | G19: √ | J19: 由被审计单位生成的信息不包括： • 总分类账或明细分类账、试算平衡表、或经审计的财务报表； • 第三方（除了服务机构）的报表或报告，例如，原始银行对账单，或函证的回函； • 外部数据（例如，第三方发布的数据，如，定价来源）。
A20: 4 | B20: 关注会计政策、会计估计合理性、一贯性。关注其是否利用会计政策和会计估计及其变更操纵利润。 | C20: 常规★ | D20: √ | E20: √ | G20: √ | I20: K7-1 /K7-2
A21: 5 | B21: 对递延收益金额进行测算，确定摊销金额是否正确。 | C21: 常规★ | G21: √ | I21: K7-4
A22: 6 | B22: 检查政府补助相关原始凭证，结合其他收益的审计，确定业务的真实性、入账金额及会计处理是否正确： （1）获取并检查政府补助文件等支持性文件，判断政府补助是否与日常活动相关、款项是否收到、分类是否正确、会计处理是否适当，同类政府补助是否采用一样的处理方法，如都采用总额法或都采用净额法； （2）如存在验收条件的，获取验收报告等相关材料，检查审核资金使用范围是否符合相关文件规定，分析公司是否满足政府补助的确认条件。 | C22: 常规★ | D22: √ | F22: √ | G22: √ | I22: K7-5 /K11-4
A23: 7 | B23: 对重大、异常政府补助： （1）核对补助事项、查验资金来源，按照政府补助的定义认真核对公司认定的政府补助事项、并对补助资产的来源单位及其与政府文件规定的一致性进行查验； （2）关注政府补助的发放主体是否具备相应的权力和资质、补助文件中索引的政策依据是否适当，被审计单位申请政府补助的流程是否合法合规、是否已经履行完毕补助文件中的要求、实际收取资金前是否需要政府部门的实质性审核、历史上同类政府补助的实际发放情况； （3）政府补助文件规定不明确或存在明显不合理迹象时，与相关政府部门沟通或执行函证程序，或在必要时聘请律师或其他外部专家提供意见。 | C23: 备选 | D23: √ | F23: √ | G23: √
A24: 8 | B24: 对于在资产负债表日按照应收金额确认的政府补助，结合其他应收款、其他收益审计： （1）查验正式发布的财政资金管理办法中的（定额）测算公式，或检查政府补助批文是否标明确切金额，分析政府补助金额是否存在重大不确定性； （2）检查政府部门正式发布的财政扶持项目及其财政资金管理办法的适用范围，是否是普惠性的（任何符合规定条件的企业均可申请），而不是专门针对特定企业制定的； （3）检查补助款批文中承诺的拨付期限，以及款项拨付对应的财政预算，分析政府补助在规定期限内的可收回性； （4）必要时结合其他应收款函证政府补助金额。 | C24: 备选 | D24: √ | F24: √ | G24: √ | I24: K11-5
A25: 9 | B25: 根据评估的舞弊风险等因素增加的审计程序。 | C25: IPO/上市/新三板/重组/舞弊应对 | I25: K7-
A26: 10 | B26: 检查递延收益是否已按企业会计准则或其他适用的规定在财务报表中做出恰当列报和披露。 | C26: 常规★ | H26: √ | I26: K7-1

Sheet 审定表K7-1
A1: 致同会计师事务所
A2: 递延收益审定表
A3: =底稿目录!A2 -> 被审计单位： | E3: =底稿目录!A4 -> 编制人： | I3: =底稿目录!A5 -> 编制日期： | L3: 索引： | M3: =底稿目录!F5 -> K7-1
A4: =底稿目录!A3 -> 截止日：202X年12月31日 | E4: =底稿目录!A6 -> 复核人： | I4: =底稿目录!A7 -> 复核日期： | L4: 页次：
A5: 项目 | C5: 期初数 | G5: 期末数 | K5: 本期审定数与上期 审定数的比较 | M5: 原因分析
C6: 未审数 | D6: 账项调整 | E6: 重分类调整 | F6: 审定数 | G6: 未审数 | H6: 账项调整 | I6: 重分类调整 | J6: 审定数 | K6: 变动额 | L6: 变动率
A7: 与资产相关的政府补助 | C7: =SUMIF('明细表K7-2'!$B$11:$B$21,$A7,'明细表K7-2'!$C$11:$C$21) -> 0 | D7: =SUMIF('明细表K7-2'!$B$11:$B$21,$A7,'明细表K7-2'!$G$11:$G$21) -> 0 | E7: =SUMIF('明细表K7-2'!$B$11:$B$21,$A7,'明细表K7-2'!$H$11:$H$21) -> 0 | F7: =C7+D7+E7 -> 0 | G7: =SUMIF('明细表K7-2'!$B$11:$B$21,$A7,'明细表K7-2'!$F$11:$F$21) -> 0 | H7: =SUMIF('明细表K7-2'!$B$11:$B$21,$A7,'明细表K7-2'!$G$11:$G$21)+SUMIF('明细表K7-2'!$B$11:$B$21,$A7,'明细表K7-2'!$I$11:$I$21)-SUMIF('明细表K7-2'!$B$11:$B$21,$A7,'明细表K7-2'!$J$11:$J$21) -> 0 | I7: =SUMIF('明细表K7-2'!$B$11:$B$21,$A7,'明细表K7-2'!$H$11:$H$21)+SUMIF('明细表K7-2'!$B$11:$B$21,$A7,'明细表K7-2'!$K$11:$K$21)-SUMIF('明细表K7-2'!$B$11:$B$21,$A7,'明细表K7-2'!$L$11:$L$21) -> 0 | J7: =G7+H7+I7 -> 0 | K7: =J7-F7 -> 0 | L7: =IF(AND(F7=0,J7=0),0,IF(AND(F7=0,J7>0),1,K7/F7)) -> 0
A8: 与收益相关的政府补助 | C8: =SUMIF('明细表K7-2'!$B$11:$B$21,$A8,'明细表K7-2'!$C$11:$C$21) -> 0 | D8: =SUMIF('明细表K7-2'!$B$11:$B$21,$A8,'明细表K7-2'!$G$11:$G$21) -> 0 | E8: =SUMIF('明细表K7-2'!$B$11:$B$21,$A8,'明细表K7-2'!$H$11:$H$21) -> 0 | F8: =C8+D8+E8 -> 0 | G8: =SUMIF('明细表K7-2'!$B$11:$B$21,$A8,'明细表K7-2'!$F$11:$F$21) -> 0 | H8: =SUMIF('明细表K7-2'!$B$11:$B$21,$A8,'明细表K7-2'!$G$11:$G$21)+SUMIF('明细表K7-2'!$B$11:$B$21,$A8,'明细表K7-2'!$I$11:$I$21)-SUMIF('明细表K7-2'!$B$11:$B$21,$A8,'明细表K7-2'!$J$11:$J$21) -> 0 | I8: =SUMIF('明细表K7-2'!$B$11:$B$21,$A8,'明细表K7-2'!$H$11:$H$21)+SUMIF('明细表K7-2'!$B$11:$B$21,$A8,'明细表K7-2'!$K$11:$K$21)-SUMIF('明细表K7-2'!$B$11:$B$21,$A8,'明细表K7-2'!$L$11:$L$21) -> 0 | J8: =G8+H8+I8 -> 0 | K8: =J8-F8 -> 0 | L8: =IF(AND(F8=0,J8=0),0,IF(AND(F8=0,J8>0),1,K8/F8)) -> 0
A9: 其他 | C9: =SUMIF('明细表K7-2'!$B$11:$B$21,$A9,'明细表K7-2'!$C$11:$C$21) -> 0 | D9: =SUMIF('明细表K7-2'!$B$11:$B$21,$A9,'明细表K7-2'!$G$11:$G$21) -> 0 | E9: =SUMIF('明细表K7-2'!$B$11:$B$21,$A9,'明细表K7-2'!$H$11:$H$21) -> 0 | F9: =C9+D9+E9 -> 0 | G9: =SUMIF('明细表K7-2'!$B$11:$B$21,$A9,'明细表K7-2'!$F$11:$F$21) -> 0 | H9: =SUMIF('明细表K7-2'!$B$11:$B$21,$A9,'明细表K7-2'!$G$11:$G$21)+SUMIF('明细表K7-2'!$B$11:$B$21,$A9,'明细表K7-2'!$I$11:$I$21)-SUMIF('明细表K7-2'!$B$11:$B$21,$A9,'明细表K7-2'!$J$11:$J$21) -> 0 | I9: =SUMIF('明细表K7-2'!$B$11:$B$21,$A9,'明细表K7-2'!$H$11:$H$21)+SUMIF('明细表K7-2'!$B$11:$B$21,$A9,'明细表K7-2'!$K$11:$K$21)-SUMIF('明细表K7-2'!$B$11:$B$21,$A9,'明细表K7-2'!$L$11:$L$21) -> 0 | J9: =G9+H9+I9 -> 0 | K9: =J9-F9 -> 0 | L9: =IF(AND(F9=0,J9=0),0,IF(AND(F9=0,J9>0),1,K9/F9)) -> 0
A10: 合计 | C10: =SUM(C7:C9) -> 0 | D10: =SUM(D7:D9) -> 0 | E10: =SUM(E7:E9) -> 0 | F10: =C10+D10+E10 -> 0 | G10: =SUM(G7:G9) -> 0 | H10: =SUM(H7:H9) -> 0 | I10: =SUM(I7:I9) -> 0 | J10: =SUM(J7:J9) -> 0 | K10: =J10-F10 -> 0 | L10: =IF(AND(F10=0,J10=0),0,IF(AND(F10=0,J10>0),1,K10/F10)) -> 0
A11: 试算平衡表数
A12: 差异数 | F12: =F11-F10 -> 0 | J12: =J11-J10 -> 0
A13: 1.审计说明
A14: （1）期末余额较期初余额增加（负数为减少）： | D14: =L10 -> 0
A15: 主要原因（比例超过30%的）：
A17: （2）情况说明。
A19: 2.审计结论
A23: 编制说明：
A24: 1、本科目核算企业确认的应在以后期间计入当期损益的政府补助。
A25: 企业收到或应收的与资产相关的政府补助，借记“银行存款”、“其他应收款”等科目，贷记本科目。
A26: 在相关资产使用寿命内分配递延收益，借记本科目，贷记“营业外收入”科目。
A27: 与收益相关的政府补助，用于补偿企业以后期间相关费用或损失的，按收到或应收的金额，借记
A28: “银行存款”、“其他应收款”等科目，贷记本科目。
A29: 在发生相关费用或损失的未来期间，按应补偿的金额，借记本科目，贷记“营业外收入”科目。
A30: 用于补偿企业已发生的相关费用或损失的，按收到或应收的金额，借记“银行存款”、“其他应收款”等科目，
A31: 贷记“营业外收入”科目。
... A49: 参考结论：
A50: A、 | B50: 未见异常，可以确认。
A51: B、 | B51: 经审计调整后可确认。
A52: C、 | B52: 由于存在上述重大未调整事项（或审计范围受到限制无法获取充分、适当证据），不可确认。
A54: 4、注释：摊销期限只剩一年或不足一年的， 或预计在一年内（含一年）进行摊销的部分，不得归类为流动负债，仍在该项目中填列，不转入“一年内到期的非流动负债”项目。

Sheet 附注披露信息（上市公司）
A1: 致同会计师事务所
A2: 附注披露信息
A3: =底稿目录!A2 -> 被审计单位： | B3: =底稿目录!A4 -> 编制人： | D3: =底稿目录!A5 -> 编制日期： | F3: 索引号： | G3: =底稿目录!F6 -> 0
A4: =底稿目录!A3 -> 截止日：202X年12月31日 | B4: =底稿目录!A6 -> 复核人： | D4: =底稿目录!A7 -> 复核日期： | F4: 页次：
A5: 附注披露信息（上市公司）
A6: 递延收益
A7: 项 目 | B7: 期初余额 | C7: 本期增加 | D7: 本期减少 | E7: 期末余额 | F7: 形成原因
A8: 政府补助
A11: 合 计 | B11: =SUM(B8:B10) -> 0 | C11: =SUM(C8:C10) -> 0 | D11: =SUM(D8:D10) -> 0 | E11: =SUM(E8:E10) -> 0
A12: 说明：计入递延收益的政府补助详见附注附注八、政府补助。
A13: 【公司根据《企业会计准则》规定计入“递延收益”科目的金额，应按如下原则确定所属的报表项目：（1）受益期预计在一年以内（含一年）的，应在“其他流动负债”项目列报；（2）自资产负债表日起算的受益期限超过一年的，在“递延收益”目中列报。】【摊销期限只剩一年或不足一年的， 或预计在一年内（含一年）进行摊销的部分，不得归类为流动负债，仍在该项目中填列，不转入“一年内到期的非流动负债”项目。】

Sheet 附注披露信息（国有企业）
A1: 致同会计师事务所
A2: 附注披露信息
A3: =底稿目录!A2 -> 被审计单位： | C3: =底稿目录!A4 -> 编制人： | E3: =底稿目录!A5 -> 编制日期： | I3: 索引号： | J3: =底稿目录!F7 -> 0
A4: =底稿目录!A3 -> 截止日：202X年12月31日 | C4: =底稿目录!A6 -> 复核人： | E4: =底稿目录!A7 -> 复核日期： | I4: 页次：
A5: 附注披露信息（国企）
A6: 递延收益
A7: 项目/类别 | B7: 期初余额 | C7: 本期增加 | D7: 本期减少 | E7: 期末余额
A11: 合 计 | B11: =SUM(B8:B10) -> 0 | C11: =SUM(C8:C10) -> 0 | D11: =SUM(D8:D10) -> 0 | E11: =SUM(E8:E10) -> 0
A12: 注：企业还应当披露与政府补助有关的下列信息：1.政府补助的种类及金额；2.计入当期损益的政府补助金额；3.本期返还的政府补助金额及原因。
A13: 其中：递延收益-政府补助情况【参考披露格式如下】
A14: 补助项目 | B14: 期初余额 | C14: 本期新增补助金额 | D14: 本期计入损益金额 | E14: 本期计入损益的列报项目 | F14: 本期返还的金额 | G14: 其他变动 | H14: 期末余额 | I14: 与资产相关/与收益相关 | J14: 本期返还的原因
E15: 其他收益 | H15: =B15+C15-D15-F15-G15 -> 0
E16: 营业外收入 | H16: =B16+C16-D16-F16-G16 -> 0
H17: =B17+C17-D17-F17-G17 -> 0
A18: 合 计 | B18: =SUM(B15:B17) -> 0 | C18: =SUM(C15:C17) -> 0 | D18: =SUM(D15:D17) -> 0 | E18: =SUM(E15:E17) -> 0 | F18: =SUM(F15:F17) -> 0 | G18: =SUM(G15:G17) -> 0 | H18: =SUM(H15:H17) -> 0

Sheet 明细表K7-2
A1: 致同会计师事务所
A2: 递延收益明细表
A3: =底稿目录!A2 -> 被审计单位： | H3: =底稿目录!A4 -> 编制人： | O3: =底稿目录!A5 -> 编制日期： | V3: 索引号： | W3: =底稿目录!F8 -> K7-2
A4: =底稿目录!A3 -> 截止日：202X年12月31日 | H4: =底稿目录!A6 -> 复核人： | O4: =底稿目录!A7 -> 复核日期： | V4: 页 次：
A5: 一、审计目标：
A6: 1.资产负债表中记录的递延收益是存在的，且已记录于恰当的账户； | D6: 2.所有应记录的递延收益均已记录，所有应当包括在财务报表中的相关披露均已包括； | K6: 3.递延收益以恰当的金额包括在财务报表中，与之相关的计价或分摊调整已恰当记录，相关披露已得到恰当计量和描述 。
A7: 二、审计过程:
A8: 项目 | B8: 所属类别 | C8: 未审数 | G8: 期初调整 | I8: 账项调整 | K8: 重分类调整 | M8: 审定数 | U8: 形成原因 | V8: 文件索引号 | W8: 备注
C9: 期初数 | D9: 本期增加 | E9: 本期减少 | F9: 期末数 | G9: 账项调整 | H9: 重分类调整 | I9: 本期增加 | J9: 本期减少 | K9: 本期增加 | L9: 本期减少 | M9: 期初数 | N9: 本期增加 | O9: 本期增加其中项 | Q9: 本期减少 | R9: 本期减少其中项 | T9: 期末数
O10: 本期新增补助金额 | P10: 其他增加 | R10: 转入其他收益 | S10: 其他减少
F11: =C11+D11-E11 -> 0 | M11: =C11+G11+H11 -> 0 | N11: =D11+I11+K11 -> 0 | P11: =N11-O11 -> 0 | Q11: =E11+J11+L11 -> 0 | S11: =Q11-R11 -> 0 | T11: =M11+N11-Q11 -> 0
F12: =C12+D12-E12 -> 0 | M12: =C12+G12+H12 -> 0 | N12: =D12+I12+K12 -> 0 | P12: =N12-O12 -> 0 | Q12: =E12+J12+L12 -> 0 | S12: =Q12-R12 -> 0 | T12: =M12+N12-Q12 -> 0
F13: =C13+D13-E13 -> 0 | M13: =C13+G13+H13 -> 0 | N13: =D13+I13+K13 -> 0 | P13: =N13-O13 -> 0 | Q13: =E13+J13+L13 -> 0 | S13: =Q13-R13 -> 0 | T13: =M13+N13-Q13 -> 0
F14: =C14+D14-E14 -> 0 | M14: =C14+G14+H14 -> 0 | N14: =D14+I14+K14 -> 0 | P14: =N14-O14 -> 0 | Q14: =E14+J14+L14 -> 0 | S14: =Q14-R14 -> 0 | T14: =M14+N14-Q14 -> 0
F15: =C15+D15-E15 -> 0 | M15: =C15+G15+H15 -> 0 | N15: =D15+I15+K15 -> 0 | P15: =N15-O15 -> 0 | Q15: =E15+J15+L15 -> 0 | S15: =Q15-R15 -> 0 | T15: =M15+N15-Q15 -> 0
F16: =C16+D16-E16 -> 0 | M16: =C16+G16+H16 -> 0 | N16: =D16+I16+K16 -> 0 | P16: =N16-O16 -> 0 | Q16: =E16+J16+L16 -> 0 | S16: =Q16-R16 -> 0 | T16: =M16+N16-Q16 -> 0
F17: =C17+D17-E17 -> 0 | M17: =C17+G17+H17 -> 0 | N17: =D17+I17+K17 -> 0 | P17: =N17-O17 -> 0 | Q17: =E17+J17+L17 -> 0 | S17: =Q17-R17 -> 0 | T17: =M17+N17-Q17 -> 0
F18: =C18+D18-E18 -> 0 | M18: =C18+G18+H18 -> 0 | N18: =D18+I18+K18 -> 0 | P18: =N18-O18 -> 0 | Q18: =E18+J18+L18 -> 0 | S18: =Q18-R18 -> 0 | T18: =M18+N18-Q18 -> 0
F19: =C19+D19-E19 -> 0 | M19: =C19+G19+H19 -> 0 | N19: =D19+I19+K19 -> 0 | P19: =N19-O19 -> 0 | Q19: =E19+J19+L19 -> 0 | S19: =Q19-R19 -> 0 | T19: =M19+N19-Q19 -> 0
F20: =C20+D20-E20 -> 0 | M20: =C20+G20+H20 -> 0 | N20: =D20+I20+K20 -> 0 | P20: =N20-O20 -> 0 | Q20: =E20+J20+L20 -> 0 | S20: =Q20-R20 -> 0 | T20: =M20+N20-Q20 -> 0
F21: =C21+D21-E21 -> 0 | M21: =C21+G21+H21 -> 0 | N21: =D21+I21+K21 -> 0 | P21: =N21-O21 -> 0 | Q21: =E21+J21+L21 -> 0 | S21: =Q21-R21 -> 0 | T21: =M21+N21-Q21 -> 0
A22: 合计 | C22: =SUM(C11:C21) -> 0 | D22: =SUM(D11:D21) -> 0 | E22: =SUM(E11:E21) -> 0 | F22: =SUM(F11:F21) -> 0 | G22: =SUM(G11:G21) -> 0 | H22: =SUM(H11:H21) -> 0 | I22: =SUM(I11:I21) -> 0 | J22: =SUM(J11:J21) -> 0 | ... T22: =SUM(T11:T21) -> 0
A23: 三、审计说明：
A24: 1.相关文件检查见其他收益底稿K11-4、递延收益检查表K7-5。
A26: 四、审计结论：
A29: 编制说明：
A30: 1、本科目核算企业确认的应在以后期间计入当期损益的政府补助。应按政府补助每一明细账户分别列示。
A31: 2、外币政府补助应在“备注”栏中列明原币金额及折合汇率。
A32: 3、审计说明可以概述：（1）程序的测试情况、结果；（2）拟调整事项及其调整分录、未调整事项及其影响，审计范围受到限制情况及其影响。
A33: 4、审计结论可参考：A、未见异常。 B、除上述重大不符事项应当作为调整事项予以调整外，其余未见异常。 C、由于存在以下重大未调整事项（或审计范围受到限制无法获取充分、适当证据），不可确认。

Sheet 调整分录汇总K7-3
A1: 致同会计师事务所
A2: 递延收益调整分录汇总表
A3: =底稿目录!A2 -> 被审计单位： | C3: =底稿目录!A4 -> 编制人： | E3: =底稿目录!A5 -> 编制日期： | I3: 索引： | J3: =底稿目录!F9 -> K7-3
A4: =底稿目录!A3 -> 截止日：202X年12月31日 | C4: =底稿目录!A6 -> 复核人： | E4: =底稿目录!A7 -> 复核日期： | I4: 页次：
A5: 调整事项说明 | B5: 类别（报表调整/账项调整/其他） | C5: 报表项目 | D5: 科目名称 | E5: 附注项目 | F5: …… | G5: 借方调整金额 | H5: 贷方调整金额 | I5: 索引 | J5: 备注
A23: 提示：本底稿适用于调整分录较多、较复杂的项目，且仅列示与本报表项目相关的审计调整。项目组可根据项目实际情况选择是否使用该底稿。

Sheet 测算表K7-4
A1: 致同会计师事务所
A2: 递延收益测算表
A3: =底稿目录!A2 -> 被审计单位： | G3: =底稿目录!A4 -> 编制人： | N3: =底稿目录!A5 -> 编制日期： | Q3: 索引号： | R3: =底稿目录!F10 -> K7-4
A4: =底稿目录!A3 -> 截止日：202X年12月31日 | G4: =底稿目录!A6 -> 复核人： | N4: =底稿目录!A7 -> 复核日期： | Q4: 页 次：
A5: 一、审计目标：
A6: 递延收益以恰当的金额包括在财务报表中，与之相关的计价或分摊调整已恰当记录，相关披露已得到恰当计量和描述。
A7: 二、审计过程:
A8: 测试：
A9: 摊销期初 | B9: 45292 | C9: 摊销期末 | D9: 45657
A10: 项目 | B10: 期初原值 | C10: 期初金额 | D10: 开始摊销日 | E10: 本期增加 | F10: 本年新增入账时间 | G10: 期末原值 | H10: 202X年项目现状 | I10: 摊销期限（年） | J10: 摊销到期日 | K10: 期初金额摊销月份数 | L10: 本期新增摊销月份数 | M10: 期初余额应摊销金额 | N10: 本期新增应摊销金额 | O10: 账面本期摊销额 | P10: 补摊销金额 | Q10: 测算期末余额 | R10: 备注
G11: =B11+E11 -> 0 | J11: =DATE((YEAR(D11)+I11),MONTH(D11),DAY(D11)) -> 0 | K11: =IF(C11=0,0,IF(J11>$D$9,12,IF(YEAR($D$9)<>YEAR(J11),0,MONTH(J11)))) -> 0 | L11: =IF(C11=0,MONTH($D$9)-MONTH(F11),IF(J11>$D$9,MONTH($D$9)-MONTH(F11)+1,MONTH(J11)-MONTH(F11)+1)) -> 11 | M11: =IF(C11=0,0,C11/(I11*12-DATEDIF(D11,$B$9,"M"))*K11) -> 0 | N11: =IF(L11=0,0,E11/L11*L11) -> 0 | P11: =M11+N11-O11 -> 0 | Q11: =C11+E11-M11-N11 -> 0
G12: =B12+E12 -> 0 | J12: =DATE((YEAR(D12)+I12),MONTH(D12),DAY(D12)) -> 0 | K12: =IF(C12=0,0,IF(J12>$D$9,12,IF(YEAR($D$9)<>YEAR(J12),0,MONTH(J12)))) -> 0 | L12: =IF(C12=0,MONTH($D$9)-MONTH(F12),IF(J12>$D$9,MONTH($D$9)-MONTH(F12)+1,MONTH(J12)-MONTH(F12)+1)) -> 11 | M12: =IF(C12=0,0,C12/(I12*12-DATEDIF(D12,$B$9,"M"))*K12) -> 0 | N12: =IF(L12=0,0,E12/L12*L12) -> 0 | P12: =M12+N12-O12 -> 0 | Q12: =C12+E12-M12-N12 -> 0
G13: =B13+E13 -> 0 | J13: =DATE((YEAR(D13)+I13),MONTH(D13),DAY(D13)) -> 0 | K13: =IF(C13=0,0,IF(J13>$D$9,12,IF(YEAR($D$9)<>YEAR(J13),0,MONTH(J13)))) -> 0 | L13: =IF(C13=0,MONTH($D$9)-MONTH(F13),IF(J13>$D$9,MONTH($D$9)-MONTH(F13)+1,MONTH(J13)-MONTH(F13)+1)) -> 11 | M13: =IF(C13=0,0,C13/(I13*12-DATEDIF(D13,$B$9,"M"))*K13) -> 0 | N13: =IF(L13=0,0,E13/L13*L13) -> 0 | P13: =M13+N13-O13 -> 0 | Q13: =C13+E13-M13-N13 -> 0
G14: =B14+E14 -> 0 | J14: =DATE((YEAR(D14)+I14),MONTH(D14),DAY(D14)) -> 0 | K14: =IF(C14=0,0,IF(J14>$D$9,12,IF(YEAR($D$9)<>YEAR(J14),0,MONTH(J14)))) -> 0 | L14: =IF(C14=0,MONTH($D$9)-MONTH(F14),IF(J14>$D$9,MONTH($D$9)-MONTH(F14)+1,MONTH(J14)-MONTH(F14)+1)) -> 11 | M14: =IF(C14=0,0,C14/(I14*12-DATEDIF(D14,$B$9,"M"))*K14) -> 0 | N14: =IF(L14=0,0,E14/L14*L14) -> 0 | P14: =M14+N14-O14 -> 0 | Q14: =C14+E14-M14-N14 -> 0
G15: =B15+E15 -> 0 | J15: =DATE((YEAR(D15)+I15),MONTH(D15),DAY(D15)) -> 0 | K15: =IF(C15=0,0,IF(J15>$D$9,12,IF(YEAR($D$9)<>YEAR(J15),0,MONTH(J15)))) -> 0 | L15: =IF(C15=0,MONTH($D$9)-MONTH(F15),IF(J15>$D$9,MONTH($D$9)-MONTH(F15)+1,MONTH(J15)-MONTH(F15)+1)) -> 11 | M15: =IF(C15=0,0,C15/(I15*12-DATEDIF(D15,$B$9,"M"))*K15) -> 0 | N15: =IF(L15=0,0,E15/L15*L15) -> 0 | P15: =M15+N15-O15 -> 0 | Q15: =C15+E15-M15-N15 -> 0
G16: =B16+E16 -> 0 | J16: =DATE((YEAR(D16)+I16),MONTH(D16),DAY(D16)) -> 0 | K16: =IF(C16=0,0,IF(J16>$D$9,12,IF(YEAR($D$9)<>YEAR(J16),0,MONTH(J16)))) -> 0 | L16: =IF(C16=0,MONTH($D$9)-MONTH(F16),IF(J16>$D$9,MONTH($D$9)-MONTH(F16)+1,MONTH(J16)-MONTH(F16)+1)) -> 11 | M16: =IF(C16=0,0,C16/(I16*12-DATEDIF(D16,$B$9,"M"))*K16) -> 0 | N16: =IF(L16=0,0,E16/L16*L16) -> 0 | P16: =M16+N16-O16 -> 0 | Q16: =C16+E16-M16-N16 -> 0
G17: =B17+E17 -> 0 | J17: =DATE((YEAR(D17)+I17),MONTH(D17),DAY(D17)) -> 0 | K17: =IF(C17=0,0,IF(J17>$D$9,12,IF(YEAR($D$9)<>YEAR(J17),0,MONTH(J17)))) -> 0 | L17: =IF(C17=0,MONTH($D$9)-MONTH(F17),IF(J17>$D$9,MONTH($D$9)-MONTH(F17)+1,MONTH(J17)-MONTH(F17)+1)) -> 11 | M17: =IF(C17=0,0,C17/(I17*12-DATEDIF(D17,$B$9,"M"))*K17) -> 0 | N17: =IF(L17=0,0,E17/L17*L17) -> 0 | P17: =M17+N17-O17 -> 0 | Q17: =C17+E17-M17-N17 -> 0
G18: =B18+E18 -> 0 | J18: =DATE((YEAR(D18)+I18),MONTH(D18),DAY(D18)) -> 0 | K18: =IF(C18=0,0,IF(J18>$D$9,12,IF(YEAR($D$9)<>YEAR(J18),0,MONTH(J18)))) -> 0 | L18: =IF(C18=0,MONTH($D$9)-MONTH(F18),IF(J18>$D$9,MONTH($D$9)-MONTH(F18)+1,MONTH(J18)-MONTH(F18)+1)) -> 11 | M18: =IF(C18=0,0,C18/(I18*12-DATEDIF(D18,$B$9,"M"))*K18) -> 0 | N18: =IF(L18=0,0,E18/L18*L18) -> 0 | P18: =M18+N18-O18 -> 0 | Q18: =C18+E18-M18-N18 -> 0
G19: =B19+E19 -> 0 | J19: =DATE((YEAR(D19)+I19),MONTH(D19),DAY(D19)) -> 0 | K19: =IF(C19=0,0,IF(J19>$D$9,12,IF(YEAR($D$9)<>YEAR(J19),0,MONTH(J19)))) -> 0 | L19: =IF(C19=0,MONTH($D$9)-MONTH(F19),IF(J19>$D$9,MONTH($D$9)-MONTH(F19)+1,MONTH(J19)-MONTH(F19)+1)) -> 11 | M19: =IF(C19=0,0,C19/(I19*12-DATEDIF(D19,$B$9,"M"))*K19) -> 0 | N19: =IF(L19=0,0,E19/L19*L19) -> 0 | P19: =M19+N19-O19 -> 0 | Q19: =C19+E19-M19-N19 -> 0
A20: 合计 | B20: =SUM(B11:B19) -> 0 | C20: =SUM(C11:C19) -> 0 | E20: =SUM(E11:E19) -> 0 | G20: =SUM(G11:G19) -> 0 | N20: =SUM(N11:N19) -> 0 | O20: =SUM(O11:O19) -> 0 | P20: =SUM(P11:P19) -> 0 | Q20: =SUM(Q11:Q19) -> 0
A21: 三、审计说明：
A24: 四、审计结论：

Sheet 递延收益检查表K7-5
A1: 致同会计师事务所
A2: 递延收益检查表
A3: =底稿目录!A2 -> 被审计单位： | E3: =底稿目录!A4 -> 编制人： | I3: =底稿目录!A5 -> 编制日期： | P3: 索引号： | Q3: =底稿目录!F11 -> K7-5
A4: =底稿目录!A3 -> 截止日：202X年12月31日 | E4: =底稿目录!A6 -> 复核人： | I4: =底稿目录!A7 -> 复核日期： | P4: 页 次：
A5: 一、审计目标：
A6: 1.资产负债表中记录的递延收益是存在的，且已经记录在恰当的账户中； | F6: 2.记录的递延收益是被审计单位应当履行的偿还义务；
A7: 3.递延收益以恰当的金额包括在财务报表中，与之相关的计价或分摊调整已恰当记录，相关披露已得到恰当计量和描述。
A8: 二、测试： | C8: 测试原因：大额（）关联方（）大额交易频繁（）异常（）其他（）
A9: 测试内容说明：1.原始凭证是否齐全； 2.记账凭证与原始凭证是否相符；3.账务处理是否正确；4.是否记录于恰当的会计期间；5.……
A10: 政府补助项目 | B10: 记账凭证 | I10: 支持性文件 | J10: 核对内容 | O10: 索引号 | P10: 是否异常 | Q10: 备注说明
B11: 日期 | C11: 凭证编号 | D11: 业务内容 | E11: 对方科目 | F11: 对方明细科目 | G11: 借方金额 | H11: 贷方金额 | J11: 1 | K11: 2 | L11: 3 | M11: 4 | N11: 5
I12: 银行回单、XXX文件、验收报告……
A20: 合计 | H20: =SUM(H12:H19) -> 0
A21: 本期贷方发生额 | H21: ='明细表K7-2'!N22 -> 0
A22: 检查比例 | H22: =H20/H21 -> #DIV/0!
A23: 三、审计说明：
A27: 四、审计结论：

Sheet 会计提示
A1: 政府补助的确认、计量与列报
A2: （一）实务问题
A3: 1、如何区分财政资金与政府补助？收到的资金，如何在资产负债表列报分类（权益、负债或损益），如何现金流量分类？
A4: 2、政府补助确认时点？对定额的理解，收到还是应收？
A5: 3、是否为非经常性损益？是否确认有关递延所得税？
A7: （二）我们的理解
A8: 1、财政资金与政府补助的区分
A9: 我们认为，应当根据财政拨款的拨付依据、相关财政资金管理办法、企业财务通则等文件，判断政府拨入的财政资金的款项性质。
A10: 如果存在以下情形，拨款则不属于政府补助：
A11: （1）政府因拨款而享有所增加的股权或者独享资本公积，形成投资与被投资的关系,属于互惠交易。
A12: （2）款项属于“投资补助”的性质（由全体投资者按股权比例共同享有的）。
A13: （3）拨款需要返还（系负债）。
... A20: 财政资金拨款的会计处理如下：
A21: 序号 | B21: 财政资金类别 | C21: 性质 | D21: 会计处理 | E21: 报表列示 | F21: 现金流量分类
A22: 1 | B22: 属于国家直接投资、资本注入的财政资金，如基本建设投资、国债投资项目等 | C22: 政府资本性投入 | D22: 增加国有实收资本和国有资本公积 | E22: 资产负债表：权益 | F22: 筹资活动收到的现金
A23: 2 | B23: 属于投资补助的财政资金，如公益性和公共基础设施投资项目补助、推进科技进步和高新技术产业化的投资项目补助等。 | C23: 资本性投入 | D23: 增加资本公积或者实收资本，由全体投资者共同享有 | E23: 资产负债表：结转资本公积前，应在“专项应付款”列报 | F23: 筹资活动收到的现金
A24: 3 | B24: 属于政府转贷、偿还性资助的财政资金，如世界银行贷款项目等 | C24: 负债 | D24: 增加负债 | E24: 资产负债表：负债 | F24: 筹资活动收到的现金
A25: 4 | B25: 属于贷款贴息、专项经费补助的财政资金，如技术更新改造项目贷款贴息、中小企业发展专项资金、产业技术研究与开发资金、科技型中小企业技术创新基金、中小企业国际市场开拓资金等 | C25: 政府补助 | D25: 1.与资产相关的政府补助以及补偿企业以后期间相关费用或损失的与收益相关的政府补助，确认为递延收益 | E25: 资产负债表：“其他流动负债”或“其他非流动负债” | F25: 与资产相关的：投资活动；
A26: 5 | B26: 属于弥补亏损、救助损失或者其他用途的财政资金，如国有企业亏损补贴、“非典”期间补偿民航公司的损失、关闭小企业补助等。 | D26: 2.补偿企业已经发生的相关费用或损失的与收益相关的政府补助，计入当期损益 | E26: 利润表：营业外收入 | F26: 与收益相关的：经营活动
A27: 2、政府补助的确认时点
A28: 《企业会计准则第16号-政府补助》第五条规定，政府补助在企业能够满足政府补助所附条件并能够收到政府补助时予以确认。
A29: 《企业会计准则第16号-政府补助》应用指南规定，企业取得的各种政府补助为货币性资产的，如通过银行转账等方式拨付的补助，
A30: 通常按照实际收到的金额计量；存在确凿证据表明该项补助是按照固定的定额标准拨付的，如按照实际销量或储备量与单位
A31: 补贴定额计算的补助等，可以按照应收的金额计量。
A32: 实务中，与公司正常经营业务密切相关，符合国家政策规定、按照一定标准定额或定量持续享受的政府补助，
A33: 如粮棉企业的定额补助，可以按照“权责发生制”确认应收金额，并作为经常性损益。其他情形均应在实际收到时确认政府补助。
A34: 3、有关案例分析
A35: （1）收到税务机关退回公司购买国产设备退增值税款（货币资金），或政府返还的土地出让金，不能直接冲减固定资产
A36: 或无形资产的购置成本，应作为与资产有关的政府补助，按期摊入损益。现金流量表中应为投资活动（其他）的收到现金。
A37: （2）收到的所得税返还，不能直接冲减所得税费用，应作为政府补助，于实际收到时计入营业外收入。
A38: （3）不涉及资产直接转移的经济支持的税收优惠，如直接减征、直接免征、增加计税抵扣额、抵免部分税额等，
... A43: 职工费用的补贴、改制上市奖励等。

Sheet GT_Custom
A1: C1 | B1: Custom 1
A2: C2 | B2: Custom 2
A3: C3 | B3: Custom 3
A4: C4 | B4: Custom 4
A5: C5 | B5: Custom 5
A6: C6 | B6: Custom 6
A7: C7 | B7: Custom 7
A8: C8 | B8: Custom 8
