Workbook

Sheet Instructions
A1: IT general controls segregation of duties analysis template
A2: Period-end date
B4: This template is used to analyze segregation of duties related to information technology (IT) general controls. It may be modified to fit the circumstances of the engagement, such as by adding or deleting rows, or by deleting the new systems implementation analysis if it does not apply to the particular audit engagement.
B5: For each relevant IT general controls category, document the role that performs each of the duties identified. Place an "X" in the duty that the role performs. If a particular role performs more than one duty, there may be a segregation of duties issue. This includes situations in which an individual with IT related duties also has a role in the entity's business processes or the entity's financial reporting process (that is, the individual has the ability to initiate, record, process, or report entity transactions, events, or conditions or to maintain accountability for the related assets, liabilities, or equity). A lack of segregation of duties is identified as a control deficiency and evaluated as to severity.
B6: Depending on the configuration, segregation of duties related batch scheduling (technology infrastructure) may be addressed through the analysis of other IT general controls categories, particularly security management and technology (program) maintenance. If this is not the case, add a section related to batch scheduling (technology infrastructure) on the “ITGC SoD analysis” tab.
B7: Delete these instructions and do not include them in the audit file.
B8: Guidance
B9: Security management | C9: Security management includes sub-processes and control activities over who and what has access to technology, including who has the ability to execute transactions. Segregation of duties related to security management generally entails dividing responsibility for the authorization and approval of security access, processing security access rights, and monitoring security access to systems and programs.
B10: New system implementation (acquisition and development) | C10: New system implementation (acquisition and development) applies only when the entity acquired or internally developed and also implemented a new IT system related to financial reporting during the period. Segregation of duties related to new system implementation generally entails dividing responsibility for the following: - Authorization and approval of new systems or programs (for example, an IT governance board or manager) - Design and development of new systems or programs (for example, a developer or programmer) - Review and testing of new systems or programs (for example, another developer, programmer, or architect) - Implementation of new systems or programs (for example, a software change or system administrator).
B11: Technology (program) maintenance (including program change controls) | C11: Technology maintenance relates specifically to changes in technology, including program change controls. It ordinarily applies to all entities, regardless of whether IT systems are acquired or developed internally. Segregation of duties related to technology maintenance generally entails dividing responsibility for the following: - Authorization and approval of changes to existing systems or programs (for example, an IT governance board or manager) - Design and development of changes to existing systems or programs (for example, a developer or programmer) - Review and testing of changes to existing systems or programs (for example, another developer, programmer, or architect) - Implementation of changes to existing systems or programs (for example, a software change or system administrator).
B13: Illustrative example
B14: Individual (Role) | C14: Authorization/ approval | D14: Process access request | E14: Monitoring | F14: Business processes or financial reporting process | H14: Individual (role) performs more than one duty | I14: Control deficiency identified? | J14: Describe segregation of duties issue or significant judgments made (if any)
B16: Security management
B17: System Administrator | C17: - | D17: X | E17: - | F17: - | H17: =IF(COUNTIF(C17:F17,[1]Data!$A$3)>1,[1]Data!$B$2,[1]Data!$B$3) -> No
B18: Human Resources Manager | C18: X | D18: - | E18: - | F18: - | H18: =IF(COUNTIF(C18:F18,[1]Data!$A$3)>1,[1]Data!$B$2,[1]Data!$B$3) -> No
B19: Controller | C19: - | D19: - | E19: X | F19: X | H19: =IF(COUNTIF(C19:F19,[1]Data!$A$3)>1,[1]Data!$B$2,[1]Data!$B$3) -> Yes | I19: No | J19: In this circumstance, review of rights and financial reporting would likely not be seen as conflicting duties.
B20: Database Administrator | C20: X | D20: X | E20: - | F20: - | H20: =IF(COUNTIF(C20:F20,[1]Data!$A$3)>1,[1]Data!$B$2,[1]Data!$B$3) -> Yes | I20: Yes | J20: Role has ability to make changes at the database level but also can design system roles and grant application access.
B21: Controller | C21: - | D21: X | E21: - | F21: X | H21: =IF(COUNTIF(C21:F21,[1]Data!$A$3)>1,[1]Data!$B$2,[1]Data!$B$3) -> Yes | I21: Yes | J21: The controller has access to administer application security as well as perform financial reporting responsibilities.
B23: Illustrative example
B24: Individual (Role) | C24: Authorization/ approval | D24: Design/ development | E24: Review/ testing | F24: Implementation | G24: Business processes or financial reporting process | H24: Individual (role) performs more than one duty | I24: Control deficiency identified? | J24: Describe segregation of duties issue or significant judgments made (if any)
B26: Technology (program) maintenance (including program change controls)
B27: Program developer | C27: - | D27: X | E27: - | F27: X | G27: - | H27: =IF(COUNTIF(C27:G27,[1]Data!$A$3)>1,[1]Data!$B$2,[1]Data!$B$3) -> Yes | I27: Yes | J27: Ability to make changes to the system and push through to implementation would result in a segregation of duties issue.
B28: IT Director | C28: X | D28: X | E28: - | F28: - | G28: - | H28: =IF(COUNTIF(C28:G28,[1]Data!$A$3)>1,[1]Data!$B$2,[1]Data!$B$3) -> Yes | I28: Yes | J28: Ability to authorize changes and develop changes would result in a segregation of duties issue.
B29: Operations manager | C29: - | D29: - | E29: - | F29: - | G29: X | H29: =IF(COUNTIF(C29:G29,[1]Data!$A$3)>1,[1]Data!$B$2,[1]Data!$B$3) -> No
B31: New system implementation (acquisition and development)
B32: Project Manager | C32: - | D32: - | E32: X | F32: - | G32: - | H32: =IF(COUNTIF(C32:G32,[1]Data!$A$3)>1,[1]Data!$B$2,[1]Data!$B$3) -> No
B33: Controller | C33: X | D33: - | E33: - | F33: X | G33: - | H33: =IF(COUNTIF(C33:G33,[1]Data!$A$3)>1,[1]Data!$B$2,[1]Data!$B$3) -> Yes | I33: No | J33: In this circumstance, ability to authorize new systems and financial reporting would likely not result in conflicting duties.
B34: Implementation consultants (developers and programmers) | C34: - | D34: X | E34: - | F34: - | G34: - | H34: =IF(COUNTIF(C34:G34,[1]Data!$A$3)>1,[1]Data!$B$2,[1]Data!$B$3) -> No

Sheet 指引（填写示例）
A1: IT一般控制职责分离分析模板
A2: 截止日
A3: 此模板用于分析与信息技术 （IT） 一般控制的职责分离。可以按照实际情况进行修改，例如添加或删除行，或者当它不适用于特定的审计项目时删除新系统实施分析。
A4: 对于每个 IT 一般控制的类别，分别记录每个角色执行的职责，“√”代表执行该职责，“-”代表不执行该职责。如果某个角色履行多于一个职责，那么通常存在职责分离问题。这包括当具有IT相关职责的人员同时也在被审计单位业务流程或财务报告过程（即，有能力生成、记录、处理或报告被审计单位的交易、事项或情况以及维护相关资产、负债或权益的会计责任的人员）承担一定的角色，通常存在职责分离问题。 存在职责分离问题应该被确定为缺陷，并评价其严重程度。
A5: 根据配置，可以通过分析其他IT一般控制的类别，特别是安全管理和技术（程序）维护来解决与职责分离相关的批量调度（技术基础设施）问题。 如果不是这种情况，请在“ITGC SoD 分析”选项卡上添加与批量调度计划（技术基础设施）相关的部分。
A6: 删除这些说明，不要将它们包含在审计底稿中。
A7: 指引
A8: 安全管理 | B8: 安全管理包括针对谁有权限以及如何访问被审计单位的系统的子流程和控制活动，包括谁有能力执行该项交易。与安全管理相关的职责分离通常需要划分职责为安全访问的授权和批准、处理安全访问的权限、系统和程序安全访问的监控。
A9: 实施新系统（采购和开发） | B9: 实施新系统 (采购和开发)仅用于与企业采购或内部开发，并在该期间实施与财务报告相关的新IT系统。 与实施新系统相关的职责分离通常需要： - 新系统或软件的授权和批准 (例如，IT治理委员会或经理) - 设计和开发新系统或软件 (例如， 开发人员或程序员) - 复核和检查新系统或软件 (例如，其他开发人员、程序员。或工程师) - 实施新系统或软件 (例如， 软件变更或系统管理员)
A10: 技术维护 (包括程式变更控制) | B10: 技术维护与具体的技术变更相关，包括程式变更控制。这适用于所有实体，无论IT系统是外购的或自行开发的。与技术维护相关的职责分离通常需要划分职责为: - 变更现有系统或软件的授权和批准 (例如，IT治理委员会或经理) - 变更现有系统或软件的设计和开发 (例如， 开发人员或程序员) - 变更现有系统或软件的复核和检查 (例如，其他开发人员、程序员。或工程师) - 变更现有系统或软件的实施 (例如， 软件变更或系统管理员)
A11: 示例
A12: 人员（角色） | B12: 授权和批准 | C12: 进程访问请求 | D12: 监督 | E12: 业务流程或财务报告流程 | G12: 存在职责分离问题? | H12: 识别出缺陷 ? | I12: 描述职责分离问题或已作出的重大判断(如有)
A13: 安全管理
A14: 系统管理员 | B14: - | C14: √ | D14: - | E14: - | G14: =IF(COUNTIF(B14:E14,Data!$A$3)>1,Data!$B$2,Data!$B$3) -> 否 | H14: 否
A15: 人力资源经理 | B15: √ | C15: - | D15: - | E15: - | G15: =IF(COUNTIF(B15:E15,Data!$A$3)>1,Data!$B$2,Data!$B$3) -> 否 | H15: 否
A16: 财务总监 | B16: - | C16: - | D16: √ | E16: √ | G16: =IF(COUNTIF(B16:E16,Data!$A$3)>1,Data!$B$2,Data!$B$3) -> 否 | H16: 否 | I16: 在这种情况下，对权利和财务报告的复核不会被视为相互冲突的职责。
A17: 数据库管理员 | B17: √ | C17: √ | D17: - | E17: - | G17: =IF(COUNTIF(B17:E17,Data!$A$3)>1,Data!$B$2,Data!$B$3) -> 否 | H17: 是 | I17: 角色能够在数据库中进行更改，但也可以为各种人员设计角色
A18: 财务总监 | B18: - | C18: √ | D18: - | E18: √ | G18: =IF(COUNTIF(B18:E18,Data!$A$3)>1,Data!$B$2,Data!$B$3) -> 否 | H18: 是 | I18: 在这种情况下，设计和财务报告会产生职责分离问题
A19: 示例
A20: 人员（角色） | B20: 授权和批准 | C20: 设计/开发 | D20: 复核/测试 | E20: 实施 | F20: 业务流程或财务报告流程 | G20: 存在职责分离问题? | H20: 识别出缺陷 ? | I20: 描述职责分离问题或已作出的重大判断(如有)
A21: 技术维护 (包括程式变更控制)
A22: 程序开发员 | B22: - | C22: √ | D22: - | E22: √ | F22: - | G22: =IF(COUNTIF(B22:F22,Data!$A$3)>1,Data!$B$2,Data!$B$3) -> 否 | H22: 是 | I22: 能够对系统进行更改并推进实施将导致职责分离问题。
A23: IT总监 | B23: √ | C23: √ | D23: - | E23: - | F23: - | G23: =IF(COUNTIF(B23:F23,Data!$A$3)>1,Data!$B$2,Data!$B$3) -> 否 | H23: 是 | I23: 更改授权和更改开发的职责将导致职责分离问题。
A24: 运营经理 | B24: - | C24: - | D24: - | E24: - | F24: √ | G24: =IF(COUNTIF(B24:F24,Data!$A$3)>1,Data!$B$2,Data!$B$3) -> 否
A26: 新系统实施（引入和开发）
A27: 项目经理 | B27: - | C27: - | D27: √ | E27: - | F27: - | G27: =IF(COUNTIF(B27:F27,Data!$A$3)>1,Data!$B$2,Data!$B$3) -> 否
A28: 财务总监 | B28: √ | C28: - | D28: - | E28: √ | F28: - | G28: =IF(COUNTIF(B28:F28,Data!$A$3)>1,Data!$B$2,Data!$B$3) -> 否 | H28: 否 | I28: 在这种情况下，授权新系统和财务报告不会导致相互冲突的职责。
A29: 实施顾问（开发人员和程序员） | B29: - | C29: √ | D29: - | E29: - | F29: - | G29: =IF(COUNTIF(B29:F29,Data!$A$3)>1,Data!$B$2,Data!$B$3) -> 否

Sheet ITGC SoD analysis
A1: Entity Name
A2: IT general controls segregation of duties analysis
A3: Period-end date
B5: Understanding of entity's process
B7: Obtain and document an understanding of the entity's process related to segregation of duties with respect to each relevant IT general controls category, including how the entity implements and monitors such segregation of duties. Describe segregation of duties issues identified by management and include such issues within the analysis below.
B9: Individual (Role) | C9: Authorization/ approval | D9: Process access request | E9: Monitoring | F9: Business processes or financial reporting process | H9: Individual (role) performs more than one duty | I9: Control deficiency identified? | J9: Describe segregation of duties issue or significant judgments made (if any)
B11: Security management
B12: Individual 1 | C12: X | D12: X | E12: X | F12: X | H12: =IF(COUNTIF(C12:F12,[1]Data!$A$3)>1,[1]Data!$B$2,[1]Data!$B$3) -> Yes
B13: Individual 2 | H13: =IF(COUNTIF(C13:F13,[1]Data!$A$3)>1,[1]Data!$B$2,[1]Data!$B$3) -> No
B14: Individual 3 | H14: =IF(COUNTIF(C14:F14,[1]Data!$A$3)>1,[1]Data!$B$2,[1]Data!$B$3) -> No
B15: Individual 4 | H15: =IF(COUNTIF(C15:F15,[1]Data!$A$3)>1,[1]Data!$B$2,[1]Data!$B$3) -> No
B16: Individual 5 | H16: =IF(COUNTIF(C16:F16,[1]Data!$A$3)>1,[1]Data!$B$2,[1]Data!$B$3) -> No
B18: Individual (Role) | C18: Authorization/ approval | D18: Design/ development | E18: Review/ testing | F18: Implementation | G18: Business processes or financial reporting process | H18: Individual (role) performs more than one duty | I18: Control deficiency identified? | J18: Describe segregation of duties issue or significant judgments made (if any)
B20: Technology (program) maintenance (including program change controls)
B21: Individual 1 | H21: =IF(COUNTIF(C21:G21,[1]Data!$A$3)>1,[1]Data!$B$2,[1]Data!$B$3) -> No
B22: Individual 2 | H22: =IF(COUNTIF(C22:G22,[1]Data!$A$3)>1,[1]Data!$B$2,[1]Data!$B$3) -> No
B23: Individual 3 | H23: =IF(COUNTIF(C23:G23,[1]Data!$A$3)>1,[1]Data!$B$2,[1]Data!$B$3) -> No
B24: Individual 4 | H24: =IF(COUNTIF(C24:G24,[1]Data!$A$3)>1,[1]Data!$B$2,[1]Data!$B$3) -> No
B25: Individual 5 | H25: =IF(COUNTIF(C25:G25,[1]Data!$A$3)>1,[1]Data!$B$2,[1]Data!$B$3) -> No
B27: New system implementation (acquisition and development)
B28: Individual 1 | H28: =IF(COUNTIF(C28:G28,[1]Data!$A$3)>1,[1]Data!$B$2,[1]Data!$B$3) -> No
B29: Individual 2 | H29: =IF(COUNTIF(C29:G29,[1]Data!$A$3)>1,[1]Data!$B$2,[1]Data!$B$3) -> No
B30: Individual 3 | H30: =IF(COUNTIF(C30:G30,[1]Data!$A$3)>1,[1]Data!$B$2,[1]Data!$B$3) -> No
B31: Individual 4 | H31: =IF(COUNTIF(C31:G31,[1]Data!$A$3)>1,[1]Data!$B$2,[1]Data!$B$3) -> No
B32: Individual 5 | H32: =IF(COUNTIF(C32:G32,[1]Data!$A$3)>1,[1]Data!$B$2,[1]Data!$B$3) -> No

Sheet IT一般控制职责分离分析模板
A1: 致 同 会 计 师 事 务 所
A2: IT一般控制职责分离分析
A3: 被审计单位： | C3: 编制人（项目负责经理）： | E3: 编制日期： | G3: 索引号： | H3: B22A-4-4
A4: 截止日： | C4: 复核人（项目合伙人）： | E4: 复核日期： | G4: 页 次： | H4: 1
A5: 了解被审计单位流程
A6: 获取并记录与每个IT一般控制类别的职责分离相关的被审计单位流程的了解，包括被审计单位如何执行和监督职责分离。描述管理层识别出的职责分离问题，并将其列入下表进行分析。
A8: 人员（角色） | B8: 授权和批准 | C8: 进程访问请求 | D8: 监督 | E8: 业务流程或财务报告流程 | G8: 存在职责分离问题? | H8: 识别出缺陷 ? | I8: 描述职责分离问题或已作出的重大判断(如有)
A9: 安全管理
A10: 人员 1
A11: 人员 2
A12: 人员 3
A13: 人员 4
A14: 人员 5
A16: 个人（角色） | B16: 授权和批准 | C16: 设计 / 开发 | D16: 复核/测试 | E16: 实施 | F16: 业务流程或财务报告流程 | G16: 存在职责分离问题? | H16: 识别出缺陷 ? | I16: 描述职责分离问题或已作出的重大判断(如有)
A17: 技术维护 (包括程式变更控制)
A18: 人员 1
A19: 人员 2
A20: 人员 3
A21: 人员 4
A22: 人员 5
A24: 实施新系统 (采购和开发)
A25: 人员 1
A26: 人员 2
A27: 人员 3
A28: 人员 4
A29: 人员 5

Sheet Data
A1: 程序 | B1: 是或否
A2: - | B2: 是
A3: X | B3: 否

Sheet GT_Custom
A1: C1 | B1: Custom 1
A2: C2 | B2: Custom 2
A3: C3 | B3: Custom 3
A4: C4 | B4: Custom 4
A5: C5 | B5: Custom 5
A6: C6 | B6: Custom 6
A7: C7 | B7: Custom 7
A8: C8 | B8: Custom 8
