Workbook
Name AFV: #REF!
Name AS2DocOpenMode: "AS2DocumentEdit"
Name CCD: #REF!
Name CDE: #REF!
Name DEX: #REF!
Name EDC: #REF!
Name FAD: [1]Breakdown!#REF!
Name FASD: #REF!
Name FEDC: '[2]2004'!#REF!
Name RDES: #REF!
Name TextRefCopyRangeCount: 136
Name VFE: #REF!
Name XAP: #REF!
Name XAQ: #REF!
Name XCD: #REF!
Name XREF_COLUMN_1: #REF!
Name XREF_COLUMN_2: [1]Breakdown!#REF!
Name XREF_COLUMN_3: #REF!
Name XREF_COLUMN_5: '[2]2004'!#REF!
Name XRefActiveRow: #REF!
Name XRefColumnsCount: 2
Name XRefCopy1: #REF!
Name XRefCopy1Row: #REF!
Name XRefCopy2Row: #REF!
Name XRefCopyRangeCount: 2
Name XRefPaste1: #REF!
Name XRefPaste1Row: #REF!
Name XRefPaste2: #REF!
Name XRefPaste2Row: #REF!
Name XRefPaste3: #REF!
Name XRefPaste3Row: #REF!
Name XRefPasteRangeCount: 2
Name 本循环科目: [3]索引!$D$15:$D$76

Sheet 底稿目录
A1: 底稿开列时，可先在以下单元格填写有关内容，以便其他底稿引用有关数据：
A2: 被审计单位： | D2: 序号 | E2: 内容 | F2: 索引号
A3: 截止日：202X年12月31日 | D3: 1 | E3: 预收账款实质性程序表 | F3: D3A
A4: 编制人： | D4: 2 | E4: 审定表 | F4: D3-1
A5: 编制日期： | D5: 3 | E5: 附注披露信息(上市公司) | G5: 无需打印
A6: 复核人： | D6: 4 | E6: 附注披露信息(国企) | G6: 无需打印
A7: 复核日期： | D7: 5 | E7: 预收账款明细表 | F7: D3-2
D8: 6 | E8: 调整分录汇总表 | F8: D3-3
A9: 关于工作底稿与审计程序索引号对应的说明 | D9: 7 | E9: 预收账款分析表 | F9: D3-4
A10: 1.编制的审计工作底稿应与审计程序对应。审计项目组应根据被审计单位实际情况和风险评估情况在实质性程序表中裁剪、修改或增加审计程序，根据实际执行的审计程序完成相应审计工作底稿，编制的工作底稿中应按自然顺序依次编制索引号，并通过唯一的索引号将与实质性程序表中的程序对应关联（即将工作底稿的索引号填入实质性程序表中的底稿索引号列）。 | D10: 8 | E10: 函证结果汇总表 | F10: D0-1
D11: 9 | E11: 核实被函证单位信息 | F11: D0-2
D12: 10 | E12: 跟函函证过程控制 | F12: D0-3
D13: 11 | E13: 函证差异调节表 | F13: D0-4
A14: 2.获取的支持性证据应与审计底稿或程序对应。审计项目组在完成底稿时获取的支持性证据应根据底稿索引号编制下一级按自然顺序排序的索引号（如D1-2-1、D1-2-2、……），并在底稿中说明引用的支持性证据、关联索引号。 | D14: 12 | E14: 替代程序检查表 | F14: D0-6
D15: 13 | E15: 邮件传真回函可靠性验证 | F15: D0-7
D16: 14 | E16: 函证程序舞弊风险评价表 | F16: D0-8
A17: 3.工作底稿索引号的编码规则：实质性程序索引号按循环从“D”到“N”,循环内账户以顺序号排列，模板中底稿索引号按账户顺序+自然数顺序（即模板中索引号按二级自然顺序排列，如D1-1、D1-2、D1-3、……D1-N）。 | D17: 15 | E17: 长账龄预收账款检查表 | F17: D3-5
D18: 16 | E18: 关联关系及交易检查表 | F18: D3-6
D19: 17 | E19: 预收账款检查表 | F19: D3-7

Sheet 预收账款实质性程序表D3A
A1: 致同会计师事务所
A2: 预收账款实质性程序表
A3: =底稿目录!A2 -> 被审计单位： | C3: =底稿目录!A4 -> 编制人： | E3: =底稿目录!A5 -> 编制日期： | H3: 索引号： | I3: D3A
A4: =底稿目录!A3 -> 截止日：202X年12月31日 | C4: =底稿目录!A6 -> 复核人： | E4: =底稿目录!A7 -> 复核日期： | H4: 页 次：
A5: 一、本账户涉及的科目
A6: 预收账款
A7: 二、审计目标和财务报表的认定
A8: 审计目标 | G8: 财务报表的认定
A9: A.资产负债表中记录的预收账款是存在的，且已记录于恰当的账户 | G9: 存在
A10: B.所有应当记录的货币预收账款均已记录，所有应当包括在财务报表中的相关披露均已包括 | G10: 完整性
A11: C.记录的预收账款是被审计单位应当履行的现时义务 | G11: 权利和义务
A12: D.预收账款以恰当的金额包括在财务报表中，与之相关的计价或分摊调整已恰当记录，相关披露已得到恰当计量和描述 | G12: 准确性、计价和分摊
A13: E.预收账款已被恰当地汇总或分解且表述清楚，相关披露在按照企业会计准则的编制基础下是相关的、可理解的 | G13: 列报
A14: 三、计划实施的实质性程序
A15: 序号 | B15: 审计程序 | C15: 程序分类 | D15: 财务报表的认定 | I15: 底稿索引号
D16: 存在 | E16: 完整性 | F16: 权利和义务 | G16: 准确性、计价和分摊 | H16: 列报 | J16: 根据被审计单位实际情况和风险评估情况裁剪、修改或增加审计程序
A17: 1 | B17: 获取或编制预收账款明细表完成以下程序，并编制审定表： （1）复核加计是否正确，与总账、明细账合计数核对是否相符，期初余额与上期审定期末余额是否相符； （2）以非记账本位币结算的预收款项，检查其采用的折算汇率及折算是否正确； （3）检查是否存在借方余额，必要时进行重分类调整； （4）结合应收账款等往来项目的明细余额，检查是否同时挂账情况，必要时做出调整。 | C17: 常规★ | D17: √ | E17: √ | G17: √ | I17: D3-1 /D3-2
A18: 2 | B18: 在使用手工编制、自定义信息报告、系统生成的非固定格式报告等由被审计单位生成的信息时，测试有关信息准确性和完整性，并考虑针对编制和维护由被审计单位生成的信息的相关控制实施控制测试，以评价该信息是否能够为实现审计目的提供基础。 | C18: 常规★ | E18: √ | G18: √ | I18: T1 | J18: 可参见《审计手册》4.2.6，由被审计单位生成的信息可能是由系统生成的、或手工编制的、或二者兼而有之的方式生成的。例如，由被审计单位生成的信息可能包括： • 不涉及自定义的、由系统生成的报告（如，固定格式报告）； • 可能通过人工自定义的、由系统生成的报告，例如，（计算机）查询信息或特别定制的报告； • 手工编制的信息，例如，汇总信息的电子表格或用以支持分配、计算以及调节的电子表格； • 其他系统生成或手工编制的信息，例如，由被审计单位编制的客户发票； • 通过影印、拍摄、扫描或其他方式转换成电子形式的文件记录。
A19: 3 | B19: 对期初余额的审计，取得预收款项期初余额明细表复核加计是否正确，与总账、明细账合计数是否相符，检查上期预收款项在本期结转情况，函证期初余额以及其他必要追加的审计程序。（适用于首次承接） | C19: 备选 | D19: √ | E19: √ | F19: √ | G19: √ | J19: 由被审计单位生成的信息不包括： • 总分类账或明细分类账、试算平衡表、或经审计的财务报表； • 第三方（除了服务机构）的报表或报告，例如，原始银行对账单，或函证的回函； • 外部数据（例如，第三方发布的数据，如，定价来源）。
A20: 4 | B20: 实施分析性程序： （1）分析借贷方发生额，与对应科目比较是否存在异常； （1）比较主要债务人余额变动情况，分析合理性； | C20: 常规★ | D20: √ | G20: √ | I20: D3-4
A21: 5 | B21: 实施函证程序： （1）以积极方式对预收款项进行函证，设计询证函、发函前核实被函证单位信息； （2）注册会计师独立收发询证函； （3）编制函证结果汇总表，检查发函、回函物流信息和轨迹、比对回函印章和签字等以核实回函的真实性，检查回函是否相符，对不符事项查明原因确定是否存在错报； （4）如果未收到回函，应当考虑与被询证者联系，要求对方作出回应或再次寄发询证函，无法收到的回函实施替代程序； （5）如果管理层不允许寄发询证函的，询问管理层不允许寄发的原因，并就其原因的正当、合理性收集证据；考虑实施替代审计程序以获取相关、可靠的审计证据； （6）如果管理层不允许寄发询证函的原因不合理、或者认为回函不可靠，评价对评估的重大错报风险以及其他审计程序的性质、时间安排和范围的影响，并确定其对审计工作和审计意见的影响。 | C21: 常规★ | D21: √ | E21: √ | F21: √ | G21: √ | I21: D0
A22: 8 | B22: 检查预收账款长期挂账的原因，并作出记录，必要时提请被审计单位予以调整。 | C22: 常规★ | D22: √ | G22: √ | I22: D3-5
A23: 7 | B23: 检查预收关联方款项： （1）了解交易的商业理由、交易事项的目的、价格和条件，确定关联交易价格是否远高于或低于非关联方交易价格，考虑对关联方预收账款的合理性、合法性； （2）检查对关联方预收款项的真实性相关的支持性文件、检查会计处理是否正确； （3）考虑向关联方或其他注册会计师函证重大的关联交易和余额（包括担保和其他重要信息）； （4）必要时，向与交易相关的人员和机构（如银行、律师）函证或与其讨论有关信息； （5）考虑是否存在未识别的关联方，关联交易和余额披露是否正确。 | C23: 常规★ | D23: √ | E23: √ | F23: √ | G23: √ | I23: D3-6
A24: 6 | B24: 抽查预收款项有关的合同和收款凭证等，检查已实现销售是否及时转销预收账款，确定预收款项期末余额的准确性和合理性。 | C24: 常规★ | D24: √ | G24: √ | I24: D3-7
A25: 9 | B25: 通过货币资金的期后测试，以确定预收账款是否已计入恰当期间 | C25: 常规★ | D25: √ | E25: √
A26: 10 | B26: 考虑对重大、新增、异常等预收账款债务人执行背景调查、实地走访等延伸程序。 | C26: IPO/上市公司/新三板舞弊应对 | D26: √ | E26: √ | F26: √ | G26: √ | I26: D4-28 /D4-29 /D4-30 /D4-31 /D4-32
A27: 11 | B27: 根据评估的舞弊风险等因素增加的审计程序。 | C27: IPO/上市公司/新三板舞弊应对
A28: 12 | B28: 检查预收款项是否已按企业会计准则或其他适用的规定在财务报表中做出恰当列报和披露。 | C28: 常规★ | H28: √ | I28: A1-1/A1-15 /A1-16

Sheet 审定表D3-1
A1: 致同会计师事务所
A2: 预收账款审定表
A3: =底稿目录!A2 -> 被审计单位： | E3: =底稿目录!A4 -> 编制人： | H3: =底稿目录!A5 -> 编制日期： | K3: 索引号： | L3: D3-1
A4: =底稿目录!A3 -> 截止日：202X年12月31日 | E4: =底稿目录!A6 -> 复核人： | H4: =底稿目录!A7 -> 复核日期： | K4: 页次：
A5: 一、按照性质分类
A6: 项目 | B6: 期初数 | F6: 期末数 | J6: 期末与期初的比较 | L6: 原因分析
B7: 未审数 | C7: 账项调整 | D7: 重分类调整 | E7: 审定数 | F7: 未审数 | G7: 账项调整 | H7: 重分类调整 | I7: 审定数 | J7: 变动额 | K7: 变动率
A8: 预收销售固定资产款 | B8: =SUMIF('预收账款明细表D3-2'!$C$12:$C$22,'审定表D3-1'!A8,'预收账款明细表D3-2'!$E$12:$E$22) -> 0 | C8: =SUMIF('预收账款明细表D3-2'!$C$12:$C$22,'审定表D3-1'!A8,'预收账款明细表D3-2'!$F$12:$F$22) -> 0 | D8: =SUMIF('预收账款明细表D3-2'!$C$12:$C$22,'审定表D3-1'!A8,'预收账款明细表D3-2'!$G$12:$G$22) -> 0 | E8: =B8+C8+D8 -> 0 | F8: =SUMIF('预收账款明细表D3-2'!$C$12:$C$22,'审定表D3-1'!A8,'预收账款明细表D3-2'!$O$12:$O$22) -> 0 | G8: =SUMIF('预收账款明细表D3-2'!$C$12:$C$22,'审定表D3-1'!A8,'预收账款明细表D3-2'!$R$12:$R$22) -> 0 | H8: =SUMIF('预收账款明细表D3-2'!$C$12:$C$22,'审定表D3-1'!A8,'预收账款明细表D3-2'!$S$12:$S$22) -> 0 | I8: =F8+G8+H8 -> 0 | J8: =I8-E8 -> 0 | K8: =IF(AND(E8=0,I8=0),"",IF(AND(E8=0,I8>0),1,J8/E8))
A9: 预收销售土地使用权款 | B9: =SUMIF('预收账款明细表D3-2'!$C$12:$C$22,'审定表D3-1'!A9,'预收账款明细表D3-2'!$E$12:$E$22) -> 0 | C9: =SUMIF('预收账款明细表D3-2'!$C$12:$C$22,'审定表D3-1'!A9,'预收账款明细表D3-2'!$F$12:$F$22) -> 0 | D9: =SUMIF('预收账款明细表D3-2'!$C$12:$C$22,'审定表D3-1'!A9,'预收账款明细表D3-2'!$G$12:$G$22) -> 0 | E9: =B9+C9+D9 -> 0 | F9: =SUMIF('预收账款明细表D3-2'!$C$12:$C$22,'审定表D3-1'!A9,'预收账款明细表D3-2'!$O$12:$O$22) -> 0 | G9: =SUMIF('预收账款明细表D3-2'!$C$12:$C$22,'审定表D3-1'!A9,'预收账款明细表D3-2'!$R$12:$R$22) -> 0 | H9: =SUMIF('预收账款明细表D3-2'!$C$12:$C$22,'审定表D3-1'!A9,'预收账款明细表D3-2'!$S$12:$S$22) -> 0 | I9: =F9+G9+H9 -> 0 | J9: =I9-E9 -> 0 | K9: =IF(AND(E9=0,I9=0),"",IF(AND(E9=0,I9>0),1,J9/E9))
A10: 合同不成立时已收取的对价 | B10: =SUMIF('预收账款明细表D3-2'!$C$12:$C$22,'审定表D3-1'!A10,'预收账款明细表D3-2'!$E$12:$E$22) -> 0 | C10: =SUMIF('预收账款明细表D3-2'!$C$12:$C$22,'审定表D3-1'!A10,'预收账款明细表D3-2'!$F$12:$F$22) -> 0 | D10: =SUMIF('预收账款明细表D3-2'!$C$12:$C$22,'审定表D3-1'!A10,'预收账款明细表D3-2'!$G$12:$G$22) -> 0 | E10: =B10+C10+D10 -> 0 | F10: =SUMIF('预收账款明细表D3-2'!$C$12:$C$22,'审定表D3-1'!A10,'预收账款明细表D3-2'!$O$12:$O$22) -> 0 | G10: =SUMIF('预收账款明细表D3-2'!$C$12:$C$22,'审定表D3-1'!A10,'预收账款明细表D3-2'!$R$12:$R$22) -> 0 | H10: =SUMIF('预收账款明细表D3-2'!$C$12:$C$22,'审定表D3-1'!A10,'预收账款明细表D3-2'!$S$12:$S$22) -> 0 | I10: =F10+G10+H10 -> 0 | J10: =I10-E10 -> 0 | K10: =IF(AND(E10=0,I10=0),"",IF(AND(E10=0,I10>0),1,J10/E10))
A11: 其他 | B11: =SUMIF('预收账款明细表D3-2'!$C$12:$C$22,'审定表D3-1'!A11,'预收账款明细表D3-2'!$E$12:$E$22) -> 0 | C11: =SUMIF('预收账款明细表D3-2'!$C$12:$C$22,'审定表D3-1'!A11,'预收账款明细表D3-2'!$F$12:$F$22) -> 0 | D11: =SUMIF('预收账款明细表D3-2'!$C$12:$C$22,'审定表D3-1'!A11,'预收账款明细表D3-2'!$G$12:$G$22) -> 0 | E11: =B11+C11+D11 -> 0 | F11: =SUMIF('预收账款明细表D3-2'!$C$12:$C$22,'审定表D3-1'!A11,'预收账款明细表D3-2'!$O$12:$O$22) -> 0 | G11: =SUMIF('预收账款明细表D3-2'!$C$12:$C$22,'审定表D3-1'!A11,'预收账款明细表D3-2'!$R$12:$R$22) -> 0 | H11: =SUMIF('预收账款明细表D3-2'!$C$12:$C$22,'审定表D3-1'!A11,'预收账款明细表D3-2'!$S$12:$S$22) -> 0 | I11: =F11+G11+H11 -> 0 | J11: =I11-E11 -> 0 | K11: =IF(AND(E11=0,I11=0),"",IF(AND(E11=0,I11>0),1,J11/E11))
E12: =B12+C12+D12 -> 0 | I12: =F12+G12+H12 -> 0 | J12: =I12-E12 -> 0 | K12: =IF(AND(E12=0,I12=0),"",IF(AND(E12=0,I12>0),1,J12/E12))
A13: 合计 | B13: =SUM(B8:B12) -> 0 | C13: =SUM(C8:C12) -> 0 | D13: =SUM(D8:D12) -> 0 | E13: =SUM(E8:E12) -> 0 | F13: =SUM(F8:F12) -> 0 | G13: =SUM(G8:G12) -> 0 | H13: =SUM(H8:H12) -> 0 | I13: =SUM(I8:I12) -> 0 | J13: =I13-E13 -> 0 | K13: =IF(AND(E13=0,I13=0),"",IF(AND(E13=0,I13>0),1,J13/E13))
A14: 二、按照账龄分类
A15: 项目 | B15: 期初数 | F15: 期末数 | J15: 期末与期初的比较 | L15: 原因分析
B16: 未审数 | C16: 账项调整 | D16: 重分类调整 | E16: 审定数 | F16: 未审数 | G16: 账项调整 | H16: 重分类调整 | I16: 审定数 | J16: 变动额 | K16: 变动率
A17: 1年以内（含1年） | E17: =B17+C17+D17 -> 0 | I17: =F17+G17+H17 -> 0 | J17: =I17-E17 -> 0 | K17: =IF(AND(E17=0,I17=0),"",IF(AND(E17=0,I17>0),1,J17/E17))
A18: 1至2年（含2年） | E18: =B18+C18+D18 -> 0 | I18: =F18+G18+H18 -> 0 | J18: =I18-E18 -> 0 | K18: =IF(AND(E18=0,I18=0),"",IF(AND(E18=0,I18>0),1,J18/E18))
A19: 2至3年（含3年） | E19: =B19+C19+D19 -> 0 | I19: =F19+G19+H19 -> 0 | J19: =I19-E19 -> 0 | K19: =IF(AND(E19=0,I19=0),"",IF(AND(E19=0,I19>0),1,J19/E19))
A20: 3年以上 | E20: =B20+C20+D20 -> 0 | I20: =F20+G20+H20 -> 0 | J20: =I20-E20 -> 0 | K20: =IF(AND(E20=0,I20=0),"",IF(AND(E20=0,I20>0),1,J20/E20))
A21: 合计 | B21: =SUM(B17:B20) -> 0 | C21: =SUM(C17:C20) -> 0 | D21: =SUM(D17:D20) -> 0 | E21: =SUM(E17:E20) -> 0 | F21: =SUM(F17:F20) -> 0 | G21: =SUM(G17:G20) -> 0 | H21: =SUM(H17:H20) -> 0 | I21: =SUM(I17:I20) -> 0 | J21: =SUM(J17:J20) -> 0 | K21: =IF(AND(E21=0,I21=0),"",IF(AND(E21=0,I21>0),1,J21/E21))
A22: 试算平衡表数
A23: 差异数 | E23: =E21-E22 -> 0 | I23: =I21-I22 -> 0
A25: 1.审计说明： | I25: 2.审计结论：
A26: （1）账龄超过1年的大额预收账款，其性质及发生原因如下：
A30: 提示：企业因转让商品收到的预收款适用《企业会计准则第14号——收入》（2017年修订）进行会计处理时，不再使用“预收账款”科目及“递延收益”科目。

Sheet 附注披露信息(上市公司)
A1: 致同会计师事务所
A2: 预收账款附注披露信息（上市公司）
A3: =底稿目录!A2 -> 被审计单位： | B3: =底稿目录!A4 -> 编制人： | C3: =底稿目录!A5 -> 编制日期： | D3: 索引号：
A4: =底稿目录!A3 -> 截止日：202X年12月31日 | B4: =底稿目录!A6 -> 复核人： | C4: =底稿目录!A7 -> 复核日期： | D4: 页次：
A5: 预收款项
A6: 项 目 | B6: 期末余额 | C6: 上年年末余额
A7: ='审定表D3-1'!A8 -> 预收销售固定资产款 | B7: ='审定表D3-1'!I8 -> 0 | C7: ='审定表D3-1'!E8 -> 0
A8: ='审定表D3-1'!A9 -> 预收销售土地使用权款 | B8: ='审定表D3-1'!I9 -> 0 | C8: ='审定表D3-1'!E9 -> 0
A9: ='审定表D3-1'!A10 -> 合同不成立时已收取的对价 | B9: ='审定表D3-1'!I10 -> 0 | C9: ='审定表D3-1'!E10 -> 0
A10: ='审定表D3-1'!A11 -> 其他 | B10: ='审定表D3-1'!I11 -> 0 | C10: ='审定表D3-1'!E11 -> 0
A11: ='审定表D3-1'!A12 -> 0
A13: 合 计 | B13: =SUM(B7:B12) -> 0 | C13: =SUM(C7:C12) -> 0
A14: （1）账龄超过1年的重要预收款项
A15: 项目 | B15: 期末余额 | C15: 未偿还或未结转的原因
A16: ='账龄1年以上的预收账款检查表D3-5'!B12 -> 0 | B16: ='账龄1年以上的预收账款检查表D3-5'!C12 -> 0 | C16: ='账龄1年以上的预收账款检查表D3-5'!#REF! -> #REF!
A17: ='账龄1年以上的预收账款检查表D3-5'!B13 -> 0 | B17: ='账龄1年以上的预收账款检查表D3-5'!C13 -> 0 | C17: ='账龄1年以上的预收账款检查表D3-5'!#REF! -> #REF!
A18: ='账龄1年以上的预收账款检查表D3-5'!B14 -> 0 | B18: ='账龄1年以上的预收账款检查表D3-5'!C14 -> 0 | C18: ='账龄1年以上的预收账款检查表D3-5'!#REF! -> #REF!
A19: 合 计
A21: （2）本期预收账款账面价值的重大变动
A22: 项目 | B22: 变动金额 | C22: 变动原因
A23: ='账龄1年以上的预收账款检查表D3-5'!B19 -> 0
A24: ='账龄1年以上的预收账款检查表D3-5'!B21 -> 0
A25: ='账龄1年以上的预收账款检查表D3-5'!B22 -> 0
A26: 合 计

Sheet 附注披露信息(国企)
A1: 致同会计师事务所
A2: 预收账款附注披露信息（国企）
A3: =底稿目录!A2 -> 被审计单位： | B3: =底稿目录!A4 -> 编制人： | C3: =底稿目录!A5 -> 编制日期： | D3: 索引号：
A4: =底稿目录!A3 -> 截止日：202X年12月31日 | B4: =底稿目录!A6 -> 复核人： | C4: =底稿目录!A7 -> 复核日期： | D4: 页次：
A5: 预收账款附注披露信息：
A6: 账 龄 | B6: 期末余额 | C6: 期初余额
A7: 1年以内（含1年） | B7: ='审定表D3-1'!I17 -> 0 | C7: ='审定表D3-1'!E17 -> 0
A8: 1年以上 | B8: ='审定表D3-1'!I21-'审定表D3-1'!I17 -> 0 | C8: ='审定表D3-1'!E21-'审定表D3-1'!E17 -> 0
A9: 合 计 | B9: =B8+B7 -> 0 | C9: =C8+C7 -> 0
A10: 账龄超过1年的重要预收账款
A11: 债权单位名称 | B11: 期末余额 | C11: 未偿还原因
A12: ='账龄1年以上的预收账款检查表D3-5'!B12 -> 0 | B12: ='账龄1年以上的预收账款检查表D3-5'!C12 -> 0 | C12: ='账龄1年以上的预收账款检查表D3-5'!#REF! -> #REF!
A13: ='账龄1年以上的预收账款检查表D3-5'!B13 -> 0 | B13: ='账龄1年以上的预收账款检查表D3-5'!C13 -> 0 | C13: ='账龄1年以上的预收账款检查表D3-5'!#REF! -> #REF!
A14: ='账龄1年以上的预收账款检查表D3-5'!B14 -> 0 | B14: ='账龄1年以上的预收账款检查表D3-5'!C14 -> 0 | C14: ='账龄1年以上的预收账款检查表D3-5'!#REF! -> #REF!
A15: 合计 | B15: =SUM(B12:B14) -> 0

Sheet 预收账款明细表D3-2
A1: 致同会计师事务所
A2: 预收账款明细表
A3: =底稿目录!A2 -> 被审计单位： | J3: =底稿目录!A4 -> 编制人： | R3: =底稿目录!A5 -> 编制日期： | Z3: 索引号： | AA3: D3-2
A4: =底稿目录!A3 -> 截止日：202X年12月31日 | J4: =底稿目录!A6 -> 复核人： | R4: =底稿目录!A7 -> 复核日期： | Z4: 页次：
A5: 一、审计目标:
A6: 预收账款以恰当的金额包括在财务报表中，与之相关的计价或分摊调整已恰当记录，相关披露已得到恰当计量和描述
A7: 二、审计过程：
A8: 1.……
A10: 对方单位名称 | B10: 公司代码 | C10: 款项性质 | D10: 关联方类型 | E10: 期初未审余额 | F10: 期初账项调整 | G10: 期初重分类调整 | H10: 期初审定余额 | I10: 期初审定账龄 | M10: 借方发生 | N10: 贷方发生 | O10: 期末余额 | P10: 被审计单位重分类调整 | Q10: 期末未审余额 | R10: 期末账项调整 | S10: 期末重分类调整 | T10: 期末审定数 | U10: 审定账龄 | Y10: 是否发函 | Z10: 期后结转 | AA10: 备注
I11: 1年以下 | J11: 1～2年 | K11: ２～3年 | L11: 3年以上 | Q11: 期末余额 | U11: 1年以下 | V11: 1～2年 | W11: ２～3年 | X11: 3年以上
H12: =E12+F12+G12 -> 0 | O12: =E12+N12-M12 -> 0 | Q12: =O12+P12 -> 0 | T12: =Q12+R12+S12 -> 0
H13: =E13+F13+G13 -> 0 | O13: =E13+N13-M13 -> 0 | Q13: =O13+P13 -> 0 | T13: =Q13+R13+S13 -> 0
H14: =E14+F14+G14 -> 0 | O14: =E14+N14-M14 -> 0 | Q14: =O14+P14 -> 0 | T14: =Q14+R14+S14 -> 0
H15: =E15+F15+G15 -> 0 | O15: =E15+N15-M15 -> 0 | Q15: =O15+P15 -> 0 | T15: =Q15+R15+S15 -> 0
H16: =E16+F16+G16 -> 0 | O16: =E16+N16-M16 -> 0 | Q16: =O16+P16 -> 0 | T16: =Q16+R16+S16 -> 0
H17: =E17+F17+G17 -> 0 | O17: =E17+N17-M17 -> 0 | Q17: =O17+P17 -> 0 | T17: =Q17+R17+S17 -> 0
H18: =E18+F18+G18 -> 0 | O18: =E18+N18-M18 -> 0 | Q18: =O18+P18 -> 0 | T18: =Q18+R18+S18 -> 0
H19: =E19+F19+G19 -> 0 | O19: =E19+N19-M19 -> 0 | Q19: =O19+P19 -> 0 | T19: =Q19+R19+S19 -> 0
H20: =E20+F20+G20 -> 0 | O20: =E20+N20-M20 -> 0 | Q20: =O20+P20 -> 0 | T20: =Q20+R20+S20 -> 0
H21: =E21+F21+G21 -> 0 | O21: =E21+N21-M21 -> 0 | Q21: =O21+P21 -> 0 | T21: =Q21+R21+S21 -> 0
H22: =E22+F22+G22 -> 0 | O22: =E22+N22-M22 -> 0 | Q22: =O22+P22 -> 0 | T22: =Q22+R22+S22 -> 0
H23: =E23+F23+G23 -> 0 | O23: =E23+N23-M23 -> 0 | Q23: =O23+P23 -> 0 | T23: =Q23+R23+S23 -> 0
A24: 合计 | E24: =SUM(E12:E23) -> 0 | F24: =SUM(F12:F23) -> 0 | G24: =SUM(G12:G23) -> 0 | H24: =SUM(H12:H23) -> 0 | I24: =SUM(I12:I23) -> 0 | J24: =SUM(J12:J23) -> 0 | K24: =SUM(K12:K23) -> 0 | L24: =SUM(L12:L23) -> 0 | ... X24: =SUM(X12:X23) -> 0 | Z24: =SUM(Z12:Z23) -> 0
A25: 核对 | T25: =IF((T24-U24-V24-W24-X24)=0,"OK","账龄与审定不匹配") -> OK | V25: =IF(V24<=I24,TRUE,FALSE) -> TRUE | W25: =IF(W24<=J24,TRUE,FALSE) -> TRUE | X25: =IF(X24<=(K24+L24),TRUE,FALSE) -> TRUE
A26: 三、审计说明：
A27: 1.与期初相比，期末余额变动较大的原因：
A28: 2.预收账款的金额与预收政策和当期合同的执行情况是否匹配
A29: 3.账龄超过1年的大额预收账款，未偿还或未结转的原因: 。资产负债表日后偿还情况： 。
A30: 四、审计结论：

Sheet 调整分录汇总表D3-3
A1: 致同会计师事务所
A2: 预收账款调整分录汇总表
A3: =底稿目录!A2 -> 被审计单位： | D3: =底稿目录!A4 -> 编制人： | F3: =底稿目录!A5 -> 编制日期： | I3: 索引： | J3: D3-3
A4: =底稿目录!A3 -> 截止日：202X年12月31日 | D4: =底稿目录!A6 -> 复核人： | F4: =底稿目录!A7 -> 复核日期： | I4: 页次：
A5: 调整事项说明 | B5: 类别（报表调整/账项调整/其他） | C5: 报表项目 | D5: 科目名称 | E5: 附注项目 | F5: …… | G5: 借方调整金额 | H5: 贷方调整金额 | I5: 索引 | J5: 备注
A21: 提示：本底稿适用于调整分录较多、较复杂的项目，且仅列示与本报表项目相关的审计调整。项目组可根据项目实际情况选择是否使用该底稿。

Sheet 预收账款分析表D3-4
A1: 致同会计师事务所
A2: 预收账款分析表
A3: =底稿目录!A2 -> 被审计单位： | C3: =底稿目录!A4 -> 编制人： | E3: =底稿目录!A5 -> 编制日期： | G3: 索引号： | H3: D3-4
A4: =底稿目录!A3 -> 截止日：202X年12月31日 | C4: =底稿目录!A6 -> 复核人： | E4: =底稿目录!A7 -> 复核日期： | G4: 页 次：
A5: 一、审计目标
A6: 1.资产负债表中记录的预收账款是存在的，且已记录于恰当的账户。2.所有应当记录的预收账款均已记录，所有应当包括在财务报表中的相关披露均已包括。
A7: 3.预收账款以恰当的金额包括在财务报表中，与之相关的计价调整已恰当记录。
A8: 二、审计过程
A9: （一）预收账款借方发生额分析
A10: 项目 | B10: 金额 | C10: 数据来源 | D10: 备注
A11: 本期借方发生额合计
A12: 对方科目：
A13: 资产处置损益
A14: 固定资产
A15: 增值税
A16: ……
A17: 差异 | B17: =B11-B13-B14-B15-B16 -> 0
A18: 差异合理性分析
A19: （三）预收账款贷方发生额分析
B20: 金额 | C20: 数据来源 | D20: 与对方科目核对 | E20: 说明
A21: 本期贷方发生额合计 | C21: 预收账款总账 | D21: N/A | E21: N/A
A22: 其中：银行存款收款 | E22: 与银行存款借方发生额核对
A23: 应收票据 | E23: 与应收票据借方发生额核对
A24: ……
A25: 差异合理性分析
A26: （四）期末预收账款主要债务人分析 | I26: 提示：当预收款项业务较多时考虑编制（四）期末预收账款主要债务人分析
A27: 债务人名称 | B27: 期末账面余额 | C27: 期初账面余额 | D27: 变动金额 | E27: 变动比例 | F27: 发生时间及账龄 | G27: 发生原因 | H27: 期后结账
A28: 债务人1 | D28: =B28-C28 -> 0 | E28: =D28/C28 -> #DIV/0!
A29: 债务人2 | D29: =B29-C29 -> 0 | E29: =D29/C29 -> #DIV/0!
A30: 债务人3 | D30: =B30-C30 -> 0 | E30: =D30/C30 -> #DIV/0!
A31: 债务人4 | D31: =B31-C31 -> 0 | E31: =D31/C31 -> #DIV/0!
A32: 债务人5 | D32: =B32-C32 -> 0 | E32: =D32/C32 -> #DIV/0!
A33: 小计 | B33: =SUM(B28:B32) -> 0 | C33: =SUM(C28:C32) -> 0 | D33: =SUM(D28:D32) -> 0 | E33: =D33/C33 -> #DIV/0! | H33: =SUM(H28:H32) -> 0
A34: 三、审计说明
A38: 四、审计结论

Sheet 账龄1年以上的预收账款检查表D3-5
A1: 致同会计师事务所
A2: 账龄1年以上的预收账款检查表
A3: =底稿目录!A2 -> 被审计单位： | C3: =底稿目录!A4 -> 编制人： | E3: =底稿目录!A5 -> 编制日期： | G3: 索引号： | H3: =底稿目录!F17 -> D3-5
A4: =底稿目录!A3 -> 截止日：202X年12月31日 | C4: =底稿目录!A6 -> 复核人： | E4: =底稿目录!A7 -> 复核日期： | G4: 页次：
A5: 一、审计目标
A6: 资产负债表中记录的预收账款是存在的，且已经记录在恰当的账户中。
A7: 二、审计过程
A8: 1.……
A10: 对方单位名称 | B10: 期末余额 | C10: 账龄 | D10: 经济业务说明 | E10: 未结转或未偿还的原因 | F10: 至审计日结转或偿还金额 | G10: 处理计划 | H10: 备注
B14: =SUM(B11:B13) -> 0 | F14: =SUM(F11:F13) -> 0
A15: 三、审计说明
A19: 四、审计结论

Sheet 关联关系及交易检查表D3-6
A1: 致同会计师事务所
A2: 预收账款关联关系及交易检查表
A3: =底稿目录!A2 -> 被审计单位： | D3: =底稿目录!A4 -> 编制人： | G3: =底稿目录!A5 -> 编制日期： | I3: 索引号： | J3: =底稿目录!F18 -> D3-6
A4: =底稿目录!A3 -> 截止日：202X年12月31日 | D4: =底稿目录!A6 -> 复核人： | G4: =底稿目录!A7 -> 复核日期： | I4: 页次：
A5: 一、审计目标
A6: 1.资产负债表中记录的预收账款是存在的，且已记录于恰当的账户。2.所有应当记录的预收账款均已记录，所有应当包括在财务报表中的相关披露均已包括。
A7: 3.记录的预收账款是被审计单位应当履行的现时义务。4.预收账款以恰当的金额包括在财务报表中，与之相关的计价调整已恰当记录。
A8: 二、审计过程
A9: 1.……
A11: 关联方名称 | B11: 关联关系 | C11: 期初余额 | D11: 借方发生 | E11: 贷方发生 | F11: 期末余额 | G11: 发生时间及账龄 | H11: 发生原因（款项性质） | I11: 索引号 | J11: 备注
F12: =C12+E12-D12 -> 0
F13: =C13+E13-D13 -> 0
F14: =C14+E14-D14 -> 0
F15: =C15+E15-D15 -> 0
F16: =C16+E16-D16 -> 0
A17: 合计 | C17: =SUM(C12:C14) -> 0 | D17: =SUM(D12:D14) -> 0 | E17: =SUM(E12:E14) -> 0 | F17: =SUM(F12:F14) -> 0
A18: 三、审计说明：
A22: 四、审计结论：
B26: 勿改、勿删
B27: 实际控制人
B28: 控股股东
B29: 控股股东、实际控制人的附属企业
B30: 持有5%以上股份的法人或其他组织
B31: 联营企业
B32: 合营企业
B33: 董高监等关键管理人员
B34: 其他关联方

Sheet 预收账款检查表D3-7
A1: 致同会计师事务所
A2: 预收账款检查表
A3: =底稿目录!A2 -> 被审计单位： | F3: =底稿目录!A4 -> 编制人： | I3: =底稿目录!A5 -> 编制日期： | P3: 索引号： | Q3: =底稿目录!F19 -> D3-7
A4: =底稿目录!A3 -> 截止日：202X年12月31日 | F4: =底稿目录!A6 -> 复核人： | I4: =底稿目录!A7 -> 复核日期： | P4: 页次：
A5: 一、审计目标：
A6: 1.资产负债表中记录的预收账款是存在的，且已经记录在恰当的账户中；3.预收账款以恰当的金额包括在财务报表中，与之相关的计价或分摊调整已恰当记录，相关披露已得到恰当计量和描述
A7: 二、审计过程：
A8: 1.样本选取及标准
A9: 测试总体： | B9: 如预收账款借方发生额所有凭证共XX笔金额XX、贷方发生额所有凭证共XX笔金额XX | G9: 特定样本： | H9: XX金额以上（大额）、关联方/关联交易形成的款项、XX异常款项全部测试，共XX笔；
A10: 抽样总体： | B10: 测试总体扣除特定样本以外的样本，共XX笔、金额XX | G10: 确定的抽样样本量： | H10: 抽取XX笔 | I10: （如果使用了样本计算器计算样本量，样本量计算过程见<XX>底稿）
A11: 抽样方法： | B11: 随机选样/系统选样/货币单元抽样/随意选样（非统计抽样适用） | G11: 抽样过程： | H11: 使用IDEA（XX抽样工具）选择XX数量、金额XX的样本进行测试，抽样工具中的样本选择过程和结果见<XX>底稿
A12: 2.测试
A13: 测试内容说明：1.原始凭证是否齐全； 2.记账凭证与原始凭证是否相符；3.账务处理是否正确；4.是否记录于恰当的会计期间；5.……
A14: （1）本期增减变动检查
A15: 客户名称 | B15: 记账凭证 | I15: 支持性文件 | J15: 核对内容 | O15: 索引号 | P15: 是否异常 | Q15: 备注说明
B16: 日期 | C16: 凭证编号 | D16: 业务内容 | E16: 对方科目 | F16: 对方明细科目 | G16: 借方金额 | H16: 贷方金额 | J16: 1 | K16: 2 | L16: 3 | M16: 4 | N16: 5
A27: 合计 | G27: =SUM(G17:G26) -> 0 | H27: =SUM(H17:H26) -> 0
A28: （2）期后结转检查
A29: 客户名称 | B29: 记账凭证 | H29: 支持性文件 | J29: 核对内容 | O29: 索引号 | P29: 是否异常 | Q29: 备注说明
B30: 日期 | C30: 凭证编号 | D30: 业务内容 | E30: 对方科目 | F30: 对方明细科目 | G30: 贷方金额 | J30: 1 | K30: 2 | L30: 3 | M30: 4 | N30: 5
A39: 合计 | G39: =SUM(G31:G38) -> 0
A40: 三、审计说明：
A41: 1.本期发生额、期末余额检查比例： | D41: 方向 | E41: 账面金额 | F41: 检查金额 | G41: 检查比例 | H41: 如果检查比例较低应扩大检查样本量或说明原因
D42: 本期借方 | E42: ='预收账款明细表D3-2'!M24 -> 0 | F42: =G27 -> 0 | G42: =ROUND(F42/E42,4) -> #DIV/0!
D43: 本期贷方 | E43: ='预收账款明细表D3-2'!N24 -> 0 | F43: =H27 -> 0 | G43: =ROUND(F43/E43,2) -> #DIV/0!
D44: 期末余额 | E44: ='预收账款明细表D3-2'!T24 -> 0 | F44: =G39 -> 0 | G44: =ROUND(F44/E44,2) -> #DIV/0!
A45: 2.……
A46: 四、审计结论：

Sheet GT_Custom
A1: C1 | B1: Custom 1
A2: C2 | B2: Custom 2
A3: C3 | B3: Custom 3
A4: C4 | B4: Custom 4
A5: C5 | B5: Custom 5
A6: C6 | B6: Custom 6
A7: C7 | B7: Custom 7
A8: C8 | B8: Custom 8
