Workbook

Sheet 修订说明
A1: 修订前 | C1: 修订后 | D1: 备注 | E1: 主要修订内容
A2: G2 G2-1 G2-2 G2-3 存货及跌价准备-审定明细表类（Leap-常规程序）
A3: 存货实质性程序表 | B3: G2A | C3: 存货实质性程序表 | E3: 将原200条存货程序、75条计价测试程序整合为31条存货程序，存货盘点、舞弊程序单独体现
A4: 存货审定表 | B4: G2 | C4: 存货审定表
A5: 附注披露信息(上市公司） | B5: G2-1 | C5: 附注披露信息(上市公司）
A6: 附注披露信息(国企） | B6: G2-1 | C6: 附注披露信息(国企）
A7: 明细汇总表G2-2 | B7: G2-2 | C7: 明细汇总表G2-2
A8: 存货总体分析 | B8: G2-3 | D8: 移至分析性程序
A9: 一、原材料明细表 | B9: G2-2-1 | C9: 一、原材料明细表 | E9: 库龄改为1年以内、1-2年、2-3年、3年以上，增加库龄校验公式
A10: 二、材料采购、在途物资明细表 | B10: G2-2-2 | C10: 二、材料采购、在途物资明细表 | E10: 库龄改为1年以内、1-2年、2-3年、3年以上，增加库龄校验公式
A11: 三、周转材料、低值易耗品，包装物明细表 | B11: G2-2-3 | C11: 三、周转材料、低值易耗品，包装物明细表 | E11: 库龄改为1年以内、1-2年、2-3年、3年以上，增加库龄校验公式
A12: 四、自制半成品明细表 | B12: G2-2-4 | C12: 四、自制半成品明细表 | E12: 库龄改为1年以内、1-2年、2-3年、3年以上，增加库龄校验公式
A13: 五、委托加工物资明细表 | B13: G2-2-5 | C13: 五、委托加工物资明细表 | E13: 库龄改为1年以内、1-2年、2-3年、3年以上，增加库龄校验公式
A14: 六、库存商品明细表 | B14: G2-2-6 | C14: 六、库存商品明细表 | E14: 库龄改为1年以内、1-2年、2-3年、3年以上，增加库龄校验公式
A15: 七、发出商品 | B15: G2-2-7 | C15: 七、发出商品 | E15: 库龄改为1年以内、1-2年、2-3年、3年以上，增加库龄校验公式
A16: 八、开发产品 | B16: G2-2-8 | C16: 八、开发产品
A17: 九、开发成本 | B17: G2-2-9 | C17: 九、开发成本
A18: 十、工程施工 | B18: G2-2-10 | C18: 十、合同履约成本 | D18: 修改为合同履约成本 | E18: 增加项目编码，删除工程结算等列，删除合同名称、合同金额列（移至合同履约成本构成明细表中）
A19: 十一、消耗性生物资产 | B19: G2-2-11 | C19: 十一、消耗性生物资产 | E19: 库龄改为1年以内、1-2年、2-3年、3年以上，增加库龄校验公式
A20: 调整分录汇总 | B20: G2-2-12 | C20: 调整分录汇总
A21: G2-3 存货及跌价准备-分析类（Leap应对措施-分析程序）
C22: 存货总体分析 | E22: 删除毛利率分析、主要产品单位成本与同行业分析移至舞弊中、售后服务费占比移至成本分析中
A23: 存货单价分析表 | B23: G2-3-1 | D23: 移至舞弊应对中
A24: 存货产量变动分析表 | B24: G2-3-2 | C24: 存货产销量变动分析表
C25: 产品年度成本比较 | E25: 增加如果存在异常应进一步进行执行舞弊应对程序单耗分析的说明
A26: 存货产量与产能分析表 | B26: G2-3-3 | D26: 移至舞弊应对中
A27: 生产成本明细分析表 | B27: G2-3-4 | D27: 移至计价测试中
A28: 制造费用明细分析表 | B28: G2-3-5 | D28: 移至计价测试中
A29: 直接人工分析表 | B29: G2-3-6 | D29: 移至计价测试中
A30: 重要供应商结构分析 | B30: G2-3-7 | D30: 移至舞弊应对中
A31: 重要供应商采购成本情况分析 | B31: G2-3-8 | D31: 删除 | E31: 删除，与舞弊应对程序中原材料单价分析重复
A32: G2-4 存货及跌价准备-会计政策（Leap-常规程序）
A33: 会计政策、核算流程G2-4 | C33: 会计政策、核算流程G2-4 | E33: 修改审计过程，删除行业惯例，增加成本结转时点、方法与分配
A34: G2-5 G2-6 存货及跌价准备 - 盘点类（Leap应对措施- 存货监盘）
A35: 函证结果汇总表 | D35: 移至采购循环函证中
A36: 核实被函证客户信息 | D36: 移至采购循环函证中
A37: 函证过程控制 | D37: 移至采购循环函证中
A38: 函证差异调节表检查表 | D38: 移至采购循环函证中
A39: 回函核对记录 | D39: 移至采购循环函证中
A40: 存货监盘程序表 | C40: 存货监盘程序表 | E40: 将原118条程序、过程、关注点进行整理，整后为存货盘点6个步骤、26条程序
A41: 存货监盘小结 | C41: 存货盘点计划问卷 | E41: 删除下方编制人、复核人、编制日期等
A42: 存货监盘计划 | C42: 存货监盘计划
A43: 存货盘点计划问卷 | C43: 存货监盘小结 | E43: 将三、盘点参加人员的财务处改为财务部门，供销处改为仓储部门
C44: 存货账面余额与仓储台账（ERP业务数据)核对记录 | D44: 增加
A45: 盘点倒轧表 | C45: 存货抽盘表 | E45: 1、修改盘点时间、监盘人、盘点人格式；2、改为从盘点记录到实物、从实物到盘点记录两个方向；3、修改表头，删除盘点金额、抽盘金额、金额差异，将差异分为抽盘与账面差异、抽盘与企业盘点差异；4、将原双向核对表G2-6-7中财务账面与盘点数量核对整合至抽盘表中，5、修改审计目标
A46: 存货抽盘表 | C46: 盘点倒轧表G2-6-5 | E46: 增加存货编码、参加、仓库、数量差异、金额差异、是否调整列，删除审计目标、审计过程
A47: 双向核对表 | D47: 删除，整合至抽盘表中
A48: G2-7 G2-11 G2-12 G2-13 存货及跌价准备 -检查类（Leap应对措施-检查）
A49: 存货截止测试-入库 | B49: G2-7-1 | C49: 截止测试-入库（记账凭证至原始凭证）G2-7-1 | E49: 拆分为从记账凭证至原始凭证、从原始凭证至记账凭证两个方向
C50: 截止测试-入库（原始凭证至记账凭证）G2-7-1 | E50: 拆分为从记账凭证至原始凭证、从原始凭证至记账凭证两个方向
A51: 存货截止测试-出库 | B51: G2-7-2 | C51: 截止测试-出库（记账凭证至原始凭证）G2-7-2 | E51: 拆分为从记账凭证至原始凭证、从原始凭证至记账凭证两个方向
C52: 截止测试-出库（原始凭证至记账凭证）G2-7-2 | E52: 拆分为从记账凭证至原始凭证、从原始凭证至记账凭证两个方向
A53: 交易背景和商业目的调查（IPO、上市公司） | B53: G2-11 | D53: 移至舞弊应对中
C54: 存货采购检查表 | D54: 新增
C55: 材料领用检查表 | D55: 新增
A56: 委托加工物资核查表 | B56: G2-12 | C56: 委托加工物资核查表 | E56: 1、修改审计过程；2、增加加工费索引、函证编号列
A57: 合同履约成本测试表 | C57: 合同履约成本测试（示例） | D57: 移至合同履约成本 | E57: 将原摊销类型的测试表作为示例
A58: G2-8 存货及跌价准备 -计价测试（Leap-存货程序）
A59: 存货计价测试程序 | B59: G2-8 | D59: 删除，与存货程序表整合
A60: 计价方法测试表-月末一次加权平均法 | B60: G2-8-1 | C60: 计价方法测试表-月末一次加权平均法
A61: 存货发出计价测试（先进先出法） | B61: G2-8-2 | C61: 存货发出计价测试（先进先出法） | E61: 年度改为日期，需结合出入库日期、数量、单价计算，改为开放式底稿
A62: 计价方法测试表-成本差异 | B62: G2-8-3 | C62: 计价方法测试表-成本差异 | E62: 由于计划单价是不断调整的，将计划单价移至购入列中，修改购入、发出计划成本公式
C63: 生产成本明细表 | D63: 从分析类底稿移入
A64: 产品年度成本比较 | B64: G2-8-4 | C64: 产品年度成本比较 | D64: 转移至分析底稿中
C65: 直接人工分析表 | D65: 从分析类底稿移入 | E65: 单产人工成本（当月计入库存商品的直接人工/产量）移至舞弊应对单耗分析中
C66: 制造费用明细分析表 | D66: 从分析类底稿移入 | E66: 修改合计公式、修改占比格式
A67: 产品月度成本比较 | B67: G2-8-5 | D67: 移至舞弊应对中单耗分析中
A68: 生产成本分配 | B68: G2-8-6 | C68: 生产成本分配
A69: 产品同行业成本比较 | B69: G2-8-7 | D69: 移至舞弊应对中单耗分析中
A70: G2-9 存货及跌价准备 -跌价准备测试（Leap应对措施-会计估计）
A71: 存货跌价准备测试表 | B71: G2-9 | C71: 存货跌价准备测试表 | E71: 增加抽样过程、修改审计过程，表格增加存货名称，将质保期改为库龄，删除临期数量，删除农产品进项税、内部未实现损益列改为账面成本调整提示；销售单价、销售费用率、税率、售价依据纳入计算表；增加提示考虑亏损合同
A72: 跌价转回G2-9-1 | B72: G2-9-1 | C72: 长库龄/呆滞/超过保质期存货明细表 | E72: 修订底稿表页名称，改为只体现有减值迹象的存货（库龄明细表在存货明细表中已体现），删除重复的存货类别列，将是否单独计提存货跌价准备改为是否存在过时冷背呆滞等各种减值迹象，增加合计行
A73: 库龄表G2-9-2 | B73: G2-9-2 | C73: 跌价转回G2-9-1 | E73: 增加合计行，修改跌价转回金额公式
A74: 同行业存货跌价计提情况G2-9-3 | B74: G2-9-3 | D74: 删除 | E74: 在存货总体分析表G2-3中已提现存货跌价准备与同行业分析，总体分析表中增加提示：对存货跌价准备错报风险高的项目，可拆分为原材料、产成品等跌价准备分别占原材料、产成品等余额的比例与同行业对比分析
A75: G2-10 存货及跌价准备 -关联交易（Leap-常规程序）
A76: 关联采购分析表 | B76: G2-10 | C76: 关联采购分析表 | E76: 简化审计过程，对隐藏关联方的核查方式移至提示中，将采购统计占比与单价分析整合为一张表
A77: 采购定价公允性测算（询价函） | B77: G2-10-1 | D77: 移至舞弊应对中
A78: 采购定价公允性测算（市场价） | B78: G2-10-2 | D78: 移至舞弊应对中
A79: 识别未披露的关联方 | B79: G2-10-3 | D79: 移至舞弊应对中 | E79: 在未识别的关联方汇总审计说明中增加人员名单见<>，名单项目组自行附附件，不提供模板
A80: 姓名汇总 | B80: G2-10-4 | D80: 删除 | E80: 在未识别的关联方汇总审计说明中增加人员名单见<>，名单项目组自行附附件，不提供模板
A81: 公司高管亲属名单 | B81: G2-10-5 | D81: 删除 | E81: 在未识别的关联方汇总审计说明中增加人员名单见<>，名单项目组自行附附件，不提供模板
A82: 职工花名册 | B82: G2-10-6 | D82: 删除 | E82: 在未识别的关联方汇总审计说明中增加人员名单见<>，名单项目组自行附附件，不提供模板
A83: 经销商负责人名单 | B83: G2-10-7 | D83: 删除 | E83: 在未识别的关联方汇总审计说明中增加人员名单见<>，名单项目组自行附附件，不提供模板
A84: G2-合同履约成本
C85: 合同履约成本实质性程序表 | D85: 新增 | E85: 增加合同履约成本程序表和底稿
C86: 合同履约成本构成明细表 | D86: 新增 | E86: 增加合同履约成本程序表和底稿
C87: 合同履约成本检查表 | D87: 新增 | E87: 增加合同履约成本程序表和底稿
C88: 合同履约成本减值准备测算表 | D88: 新增 | E88: 增加合同履约成本程序表和底稿
C89: 亏损合同预计损失测算表 | D89: 新增 | E89: 增加合同履约成本程序表和底稿
C90: 合同履约成本测试（示例）
A91: G2-14 G-15 G-16 存货及跌价准备-舞弊应对审计程序
C92: 程序表 | D92: 新增 | E92: 梳理整合为12条存货舞弊应对审计程序
C93: 原材料采购价格分析表G2-3-1 | E93: 保留原材料采购单价，产成品入库单价在单耗分析中包含
C94: 原材料单价分析G2-14 | E94: 删除各项原材料采购数量及金额统计（包含在原材料入库单价分析中）；××原材料单价分析-供应商维度包含在供应商分析中
C95: 存货产量与产能分析表G2-3-3
C96: 主要产品生产成本及单耗分析表
C97: 关联方采购定价公允性核查（询价函）G2-10-1 | E97: 增加关联方名称、产品规格、采购价格、采购价格是否合理列，删除指标
C98: 关联方采购定价公允性核查（市场价）G2-10-2
C99: 识别未披露的关联方G2-10-3
C100: 重要供应商结构分析G2-3-7 | E100: 删除审计目标、审计过程、删除经营范围、规模等列，增加产品名称、交货方式列，增加采购金额是否与公司规模匹配等列，增加与供应商信息检查表的索引
...

Sheet 底稿目录
A1: 底稿开列时，可先在以下单元格填写有关内容，以便其他底稿引用有关数据：
A2: 被审计单位： | D2: 序号 | E2: 内容 | F2: 索引号
A3: 截止日：202X年12月21日 | D3: 1 | E3: 存货实质性程序表 | F3: F2A
A4: 编制人： | D4: 2 | E4: 存货审定表 | F4: F2-1
A5: 编制日期： | D5: 3 | E5: 附注披露信息(上市公司） | G5: 无需打印
A6: 复核人： | D6: 4 | E6: 附注披露信息(国企） | G6: 无需打印
A7: 复核日期： | D7: 5 | E7: 存货明细汇总表 | F7: F2-2
D8: 6 | E8: 一、原材料明细表 | F8: F2-3
A9: 关于工作底稿与审计程序索引号对应的说明 | D9: 7 | E9: 二、材料采购、在途物资明细表 | F9: F2-4
A10: 1.编制的审计工作底稿应与审计程序对应。审计项目组应根据被审计单位实际情况和风险评估情况在实质性程序表中裁剪、修改或增加审计程序，根据实际执行的审计程序完成相应审计工作底稿，编制的工作底稿中应按自然顺序依次编制索引号，并通过唯一的索引号将与实质性程序表中的程序对应关联（即将工作底稿的索引号填入实质性程序表中的底稿索引号列）。 | D10: 8 | E10: 三、周转材料、低值易耗品，包装物明细表 | F10: F2-5
D11: 9 | E11: 四、自制半成品明细表 | F11: F2-6
D12: 10 | E12: 五、委托加工物资明细表 | F12: F2-7
D13: 11 | E13: 六、库存商品明细表 | F13: F2-8
A14: 2.获取的支持性证据应与审计底稿或程序对应。审计项目组在完成底稿时获取的支持性证据应根据底稿索引号编制下一级按自然顺序排序的索引号（如D1-2-1、D1-2-2、……），并在底稿中说明引用的支持性证据、关联索引号。 | D14: 12 | E14: 七、发出商品明细表 | F14: F2-9
D15: 13 | E15: 八、开发产品明细表 | F15: F2-10
D16: 14 | E16: 九、开发成本明细表 | F16: F2-11
A17: 3.工作底稿索引号的编码规则：实质性程序索引号按循环从“D”到“N”,循环内账户以顺序号排列，模板中底稿索引号按账户顺序+自然数顺序（即模板中索引号按二级自然顺序排列，如D1-1、D1-2、D1-3、……D1-N）。 | D17: 15 | E17: 十、合同履约成本明细表 | F17: F2-12
D18: 16 | E18: 十一、消耗性生物资产明细表 | F18: F2-13
D19: 17 | E19: 调整分录汇总 | F19: F2-14

Sheet 存货实质性程序表F2A
A1: 致同会计师事务所
A2: 存货实质性程序
A3: =底稿目录!A2 -> 被审计单位： | D3: =底稿目录!A4 -> 编制人： | F3: =底稿目录!A5 -> 编制日期： | I3: 索引号： | J3: =底稿目录!F3 -> F2A
A4: =底稿目录!A3 -> 截止日：202X年12月21日 | D4: =底稿目录!A6 -> 复核人： | F4: =底稿目录!A7 -> 复核日期： | I4: 页 次：
A5: 一、本账户涉及的科目
A6: 存货及跌价准备
A7: 二、审计目标与认定的对应关系
A8: 审计目标 | H8: 财务报表的认定
A9: A. 资产负债表中记录的存货是存在的，且已经记录在恰当的账户中 | H9: 存在
A10: B. 所有应记录的存货均已记录，所有应当包括在财务报表中的相关披露均已包括 | H10: 完整性
A11: C. 记录的存货由被审计单位拥有或控制 | H11: 权利和义务
A12: D. 存货以恰当的金额包括在财务报表中，与之相关的计价或分摊调整已恰当记录，相关披露已得到恰当计量和描述 | H12: 准确性、计价和分摊
A13: E. 存货已被恰当地汇总或分解且表述清楚，相关披露在按照企业会计准则的编制基础下是相关的、可理解的 | H13: 列报
A14: 三、计划实施的实质性程序
A15: 序号 | B15: 与Leap对应 | C15: 审计程序 | D15: 程序分类 | E15: 财务报表的认定 | J15: 底稿索引号
E16: 存在 | F16: 完整性 | G16: 权利和 义务 | H16: 准确性、计价和分摊 | I16: 列报 | K16: 根据被审计单位实际情况和风险评估情况裁剪、修改或增加审计程序
A17: 1 | B17: 常规程序 | C17: 获取或编制存货的（收发存）明细表，完成以下工作，并编制审定表 （1）复核加计是否正确，与总账、明细账合计数核对是否相符，期初余额与上期审定期末余额是否相符； （2）获取管理层编制的存货库龄分析表，检查库龄划分是否正确； （3）检查存货明细表中是否有异常或负余额（包括数量为负或金额为负）的项目。 | D17: 常规★ | E17: √ | F17: √ | H17: √ | J17: F2-1/F2-2至F2-14
A18: 2 | B18: 常规程序 | C18: 抽查核对存货收发存明细账是否与仓储台账（ERP业务数据）、卡片记录相符（双向核对），存货是否及时入账，存货编号存在漏记、重复等。 | D18: 常规★ | E18: √ | F18: √ | H18: √ | J18: F2-24
A19: 3 | B19: IPE程序 | C19: 在使用手工编制、自定义信息报告、系统生成的非固定格式报告等由被审计单位生成的信息时，测试有关信息准确性和完整性，并考虑针对编制和维护由被审计单位生成的信息的相关控制实施控制测试，以评价该信息是否能够为实现审计目的提供基础。 | D19: 常规★ | F19: √ | H19: √ | J19: T1/ | K19: 可参见《审计手册》4.2.6，由被审计单位生成的信息可能是由系统生成的、或手工编制的、或二者兼而有之的方式生成的。例如，由被审计单位生成的信息可能包括： • 不涉及自定义的、由系统生成的报告（如，固定格式报告）； • 可能通过人工自定义的、由系统生成的报告，例如，（计算机）查询信息或特别定制的报告； • 手工编制的信息，例如，汇总信息的电子表格或用以支持分配、计算以及调节的电子表格； • 其他系统生成或手工编制的信息，例如，由被审计单位编制的客户发票； • 通过影印、拍摄、扫描或其他方式转换成电子形式的文件记录。
A20: 4 | B20: 期初余额程序 | C20: 对期初余额的审计，取得存货期初余额明细表复核加计是否正确，与总账、明细账合计数是否相符，检查期初存货在本期结转情况，取得上期存货盘点表核对差异，通过监盘当前的存货数量并调节至期初存货数量、对期初存货项目的计价实施审计程序、对毛利进行分析和存货截止实施审计程序。（适用于首次承接） | D20: 备选 | E20: √ | F20: √ | G20: √ | H20: √ | K20: 由被审计单位生成的信息不包括： • 总分类账或明细分类账、试算平衡表、或经审计的财务报表； • 第三方（除了服务机构）的报表或报告，例如，原始银行对账单，或函证的回函； • 外部数据（例如，第三方发布的数据，如，定价来源）。
A21: 5 | B21: 常规程序、应对措施-会计估计 | C21: 了解会计政策、会计估计合理性、一贯性，关注其是否利用会计政策和会计估计及其变更操纵利润。主要的会计政策和会计估计包括： （1）存货购入和发出的入账基础和计价方法、周转材料与固定资产的划分标准和摊销方法等； （2）生产工艺流程、辅助生产成本和制造费用摊销方法、自制半成品与完工产品的分配方法等； （3）存货跌价准备的计提方法、可变现净值的估计方法等； | D21: 常规★ | E21: √ | F21: √ | H21: √ | J21: F2-16
A22: 6 | B22: 应对措施-实质性/非实质性分析程序 | C22: 总体分析存货构成及重要指标： （1）分析本期及前期的构成，结构比变化情况； （2）分析整体存货周转率、存货跌价准备比率等存货关键指标的本期与前期变化、与同行业公司对比情况，主要产品的存货周转率本期与前期的变化情况； | D22: 常规★ | E22: √ | H22: √ | J22: F2-18
A23: 7 | B23: 应对措施-实质性/非实质性分析程序 | C23: 分析本期各月及前期主要产品的产量与销售量情况，分析前期及本期各月主要原材料本期采购与耗用情况，分析单位成本构成及变化情况，关注是否存在异常； | D23: 常规★ | E23: √ | H23: √ | J23: F2-19 /F2-20
A24: 8 | B24: 存货程序（选择“被审计单位执行定期盘点”“存货存放在多个地点”）、LEAP应对措施-检查（存货监盘） | C24: 实施存货监盘程序： （1）初步了解存货形态、存货存放地点等，初步确定监盘方式、时间和范围； （2）参与被审计单位存货盘点规划完成存货盘点问卷，获取盘点计划，评价被审计单位盘点内部控制、程序和指令是否恰当； （3）确定监盘时间、范围、人员、重点关注事项等，编制存货监盘计划； （4）观察被审计单位制定的盘点程序的执行情况，并检查存货的状况，是否存在过时、毁损或陈旧的存货； （5）执行抽盘，从存货盘点记录中选取项目追查至存货实物，以及从存货实物中选取项目追查至盘点记录，将抽盘结果与账面核对； （6）评价存货盘点结果，完成存货监盘小结。 | D24: 常规★ | E24: √ | F24: √ | G24: √ | H24: √ | J24: F2-21A
A25: 9 | B25: 存货程序（选择“被审计单位执行定期盘点”“存货存放在多个地点”）、LEAP应对措施-检查（存货监盘） | C25: 如果在存货盘点现场实施存货监盘不可行，实施替代审计程序。如果不能实施替代审计程序或实施替代审计程序无法获取有关存货的存在和状况的充分、适当的审计证据，考虑对审计意见的影响。替代程序主要包括： （1）检查进货交易凭证或生产记录以及其他相关资料； （2）检查资产负债表日后发生的销货交易凭证； （3）向顾客或供应商函证。 | D25: 常规★ | E25: √ | F25: √ | G25: √ | H25: √
A26: 10 | B26: 存货程序（选择“被审计单位存在由第三方保管或控制的存货”） | C26: 如果由第三方保管或控制的存货对财务报表是重要的，考虑： （1）现场盘点第三方保管或控制的存货； （2）向持有被审计单位存货的第三方函证存货的数量和状况； （3）实施检查或其他适合具体情况的审计程序。 | D26: 备选 | E26: √ | F26: √ | G26: √ | H26: √
A27: 11 | B27: 存货程序（选择“被审计单位存在寄售货物”） | C27: 如果存在他人委托被审计单位代售的商品（寄售商品），考虑： （1）该寄售商品未包含在被审计单位存货盘点范围内； （2）向寄售品所有者函证寄售商品； （3）检查受托代销的商品临近期末的重大销售，账务处理是否正确。 | D27: 备选 | E27: √ | F27: √ | G27: √ | H27: √
A28: 12 | B28: 应对措施-检查 | C28: 结合存货监盘程序，执行存货入库截止性测试： （1）从存货明细账借方发生额中抽取资产负债表日前后若干天、一定金额以上的凭证，与入库记录（如入库单，或购货发票，或运输单据）核对，以确定存货入库被记录在正确的会计期间； （2）从入库记录（如入库单或购货发票或运输单据）或其他表明所有权转移的单据中选取资产负债表日前后若干天、一定金额以上的凭据，与存货明细账的借方发生额进行核对，以确定存货人库被记录在正确的会计期间； （3）检查入库记录编号是否与执行存货监盘程序中获取的截止性资料编号存在冲突。 | D28: 常规★ | E28: √ | F28: √ | J28: F2-29 /F2-30
A29: 13 | B29: 应对措施-检查 | C29: 结合存货监盘、产成品结合营业收入截止程序，执行存货出库截止性测试： （1）从存货明细账贷方发生额中抽取资产负债表日前后若干张、一定金额以上的凭证，与出库记录（如出库单、原材料领用单）核对，以确定存货出库被记录在正确的会计期间； （2）从出库记录（如出库单、原材料领用单）中选取资产负债表日前后若干张、一定金额以上的凭据，与存货明细账的贷方发生额进行核对，以确定存货出库被记录在正确的会计期间； （3）检查出库记录编号是否与执行存货监盘程序中获取的截止性资料编号存在冲突。 | D29: 常规★ | E29: √ | F29: √ | J29: F2-31 /F2-32
A30: 14 | B30: 应对措施-检查 | C30: 采用恰当的抽样方法，从原材料、外购库存商品明细表中选择样本，检查入库单等支持性证据，确认会计处理是否正确。 | D30: 常规★ | E30: √ | G30: √ | H30: √ | J30: F2-33
A31: 15 | B31: 应对措施-检查 | C31: 采用恰当的抽样方法，从原材料发出明细账中选择样本，检查材料发出及领用的原始凭证，检查领料单的签发是否经过授权批准，手续是否齐全，会计处理是否正确。 | D31: 常规★ | E31: √ | F31: √ | H31: √ | J31: F2-34
A32: 16 | B32: 存货程序（存货成本） | C32: 采用恰当的抽样方法，从存货明细表中选择样本测试存货计价： （1）对原材料等外购存货，基于被审计单位原材料计价方法(如先进先出法，加权平均法等)，结合原材料的历史购买成本，测试其账面入库、出库、结存金额是否准确。 （2）对产成品，基于被审计单位产成品计价方法(如先进先出法，加权平均法等)，结合产成品入库成本，测试其账面入库、出库、结存金额是否准确。 | D32: 常规★ | H32: √ | J32: F2-38 /F2-39
A33: 17 | B33: 存货程序（存货成本） | C33: 在以标准成本计价时，应考虑标准成本的合理性并测试实际成本与标准成本差异的归集和分摊： （1）评价标准成本的合理性，检查标准成本在本期有无重大变动； （2）对直接材料结合采购等入库检查，测试材料成本差异的构成和分摊是否合理、正确；评估人工和间接费用分配方法和假设的合理性；评价标准制造费用中所包含的成本的适当性； （3）结合产成品成本计算单等，检查产成品实际价格与标准成本的差异分配是否正确； | D33: 备选 | H33: √ | J33: F2-40
A34: 18 | B34: 存货程序（存货成本） | C34: 检查生产成本/制造费用归集、分配是否合理、正确： （1）取得本期各月及前期的存货成本构成（料、工、费）明细情况，评价本期发生额和余额的总体合理性，将直接材料与材料耗用、直接人工与工资分配表等核对一致，检查生产成本分配方法，以及在完工产品与在产品间分配是否合理、一致、正确； （2）分析主要产品本期与上期的单位成本的变化，是否存在异常波动； （3）分析本期各月及前期产品计入生产成本的直接人工成本、单位人工成本情况，关注直接人工分摊是否合理，是否存在异常； （4）取得本期各月及前期制造费用明细情况，将资产折旧与折旧分配表、资产摊销与各项资产摊销分配表等核对一致，检查制造费用分配方法是否合理、适当，制造费用截止是否正确； （4）抽取成本计算单，检查直接材料、直接人工及制造费用的计算和分配是否正确。 | D34: 常规★ | H34: √ | J34: F2-41 /F2-20 /F2-42 /F2-43 /F2-44
A35: 19 | C35: 如果存在委托加工物资： （1）选取委托加工合同，检查有关发料凭证、加工费、运费结算凭证，关注所有权归属，核对其计费、计价是否正确，会计处理是否及时、正确； （2）检查加工完成物资的验收入库手续是否齐全，会计处理是否正确； （3）函证委托加工物资，必要时现场查看或利用其他注册会计师的工作。 | D35: 备选 | E35: √ | F35: √ | G35: √ | H35: √ | J35: F2-35 /F0
A36: 20 | B36: 存货程序（存货成本） | C36: 如果存在劳务成本： （1）选取劳务成本项目，检查有关劳务合同、劳务费结算等原始凭证，关注是否存在资本性支出，核对会计处理是否正确； （2）结合成本计算单等，检查劳务成本的分配是否合理、正确； （3）必要时对劳务成本实施截止测试，以确定被记录在正确的会计期间。 | D36: 备选 | H36: √
A37: 21 | B37: 存货程序（存货成本） | C37: 对于计入生产成本的借款费用，结合对长短期借款、应付债券或长期应付款等付息债务的审计，检查借款费用资本化的计算方法和资本化金额以及会计处理是否正确。 | D37: 备选 | H37: √
A38: 22 | B38: 存货程序（选择“期末存在在途货物”） | C38: 如果存在材料采购或在途物资： （1）选取期末物资采购或在途物资，检查有关原始单据； （2）抽取资产负债表日前后若干天物资采购或在途物资增减变动的有关账簿记录和收料报告单等资料，以确定被记录在正确的会计期间； （3）如采用标准成本计价，检查物资采购有关的材料成本差异归集和分配是否正确。 | D38: 备选 | E38: √ | F38: √ | G38: √ | H38: √
A39: 23 | C39: 如果存在周转材料（低值易耗品、包装物）： （1）检查周转材料的入库和领用的手续是否齐全，关注是否存在包装物押金，会计处理是否正确； （2）检查周转材料摊销方法是否正确，前后期是否一致； | D39: 备选 | E39: √ | F39: √ | G39: √ | H39: √
A40: 24 | B40: 应对措施-检查 | C40: 结合营业成本审计，检查发出库存商品的品种、数量和实际成本与“主营业务成本”是否相符。 | D40: 常规★ | E40: √ | F40: √ | H40: √ | J40: F5-6
A41: 25 | B41: 应对措施-会计估计 | C41: 存货跌价准备： （1）取得被审计单位存货跌价准备明细表、计算过程，评价存货跌价准备所依据的资料、假设及计提方法是否合理、是否符合会计准则的规定，会计处理是否正确； （2）分析存货的库龄、结合盘点结果识别滞销积压/停止经营/超出保质期或陈旧过时的存货； （3）选取样本重新计算期末存货跌价准备的金额； （4）检查存货跌价准备的转回是否合理，转回金额、会计处理是否正确。 | D41: 常规★ | H41: √ | J41: F2-47 /F2-48 /F2-49
A42: 26 | B42: 常规程序（选择“存在关联交易”） | C42: 检查关联方采购： （1）了解交易的商业理由、交易事项的目的、价格和条件，确定关联交易价格是否远高于或低于非关联方交易价格，考虑对关联方应付账款的合理性、合法性； （2）检查对关联方应付账款的真实性相关的支持性文件、检查会计处理是否正确； （3）考虑向关联方或其他注册会计师函证重大的关联采购交易和余额（包括担保和其他重要信息）； （4）必要时，向与交易相关的人员和机构（如银行、律师）函证或与其讨论有关信息； （5）考虑是否存在未识别的关联方，关联交易和余额披露是否正确。 | D42: 常规★ | E42: √ | F42: √ | G42: √ | H42: √ | I42: √ | J42: F2-52
A43: 27 | C43: 涉及异常或超出正常经营过程重大交易有关的存货项目（如债务重组、非货币性资产交换、企业合并等），询问管理层交易的性质和商业目的、期限和条件、交易对手，检查交易的支持性文件，考虑交易的商业理由是否合理，是否存在特别风险。 | D43: 备选 | E43: √ | F43: √ | H43: √
A44: 28 | C44: 针对涉及重大调整、销售退回、复杂交易、重大判断或估计、计量结果具有高度不确定性的存货项目考虑额外的审计程序 | D44: 备选 | E44: √ | F44: √ | H44: √
A45: 29 | C45: 如果存在合同履约成本，检查合同履约成本的构成是否合理、检查相关记账凭证和支持性证据、检查减值准备计提是否合理，考虑亏损合同等，检查合同履约成本的会计处理是否符合会计准则的规定等。 | D45: 备选 | J45: F2-55A
A46: 30 | C46: 关注或有、承诺事项： （1）询问管理层，检查有关合同协议、董事会会议记录等，确定存货是否存在用于抵押、担保的情况； （2）结合银行借款等科目的审计，了解是否有用于债务担保的存货，如有，则应取证并作相应的记录，同时核查被审计单位财务报表是否已作恰当披露。 | D46: 常规★ | G46: √ | H46: √ | I46: √
A47: 31 | C47: 根据评估的舞弊风险等因素增加的审计程序。 | D47: IPO/上市/新三板/重组/舞弊应对 | J47: F2-61A
A48: 32 | C48: 检查存货是否已按企业会计准则或其他适用的规定在财务报表中做出恰当列报和披露。 | D48: 常规★ | I48: √ | J48: A1-1/A1-15 /A1-16

Sheet 存货审定表F2-1
A1: 致同会计师事务所
A2: 存货及跌价准备审定表
A3: =底稿目录!A2 -> 被审计单位： | B3: =底稿目录!A4 -> 编制人： | C3: =底稿目录!A5 -> 编制日期： | E3: 索引号： | F3: =底稿目录!F4 -> F2-1
A4: =底稿目录!A3 -> 截止日：202X年12月21日 | B4: =底稿目录!A6 -> 复核人： | C4: =底稿目录!A7 -> 复核日期： | E4: 页 次：
A5: 项目 | B5: 期初数 | C5: 本期增加 | D5: 本期减少 | E5: 期末数 | F5: 索引
A6: 一、原值
A7: 未审数 | B7: =SUM(B8:B20) -> 0 | C7: =SUM(C8:C20) -> 0 | D7: =SUM(D8:D20) -> 0 | E7: =SUM(E8:E20) -> 0
A8: ='明细汇总表F2-2'!A17 -> 原材料 | B8: ='明细汇总表F2-2'!B17 -> 0 | C8: ='明细汇总表F2-2'!C17 -> 0 | D8: ='明细汇总表F2-2'!D17 -> 0 | E8: =B8+C8-D8 -> 0
A9: ='明细汇总表F2-2'!A18 -> 材料采购/在途物资 | B9: ='明细汇总表F2-2'!B18 -> 0 | C9: ='明细汇总表F2-2'!C18 -> 0 | D9: ='明细汇总表F2-2'!D18 -> 0 | E9: =B9+C9-D9 -> 0
A10: ='明细汇总表F2-2'!A19 -> 周转材料/低值易耗品/包装物 | B10: ='明细汇总表F2-2'!B19 -> 0 | C10: ='明细汇总表F2-2'!C19 -> 0 | D10: ='明细汇总表F2-2'!D19 -> 0 | E10: =B10+C10-D10 -> 0
A11: ='明细汇总表F2-2'!A20 -> 在产品 | B11: ='明细汇总表F2-2'!B20 -> 0 | C11: ='明细汇总表F2-2'!C20 -> 0 | D11: ='明细汇总表F2-2'!D20 -> 0 | E11: =B11+C11-D11 -> 0
A12: ='明细汇总表F2-2'!A21 -> 自制半成品 | B12: ='明细汇总表F2-2'!B21 -> 0 | C12: ='明细汇总表F2-2'!C21 -> 0 | D12: ='明细汇总表F2-2'!D21 -> 0 | E12: =B12+C12-D12 -> 0
A13: ='明细汇总表F2-2'!A22 -> 委托加工物资 | B13: ='明细汇总表F2-2'!B22 -> 0 | C13: ='明细汇总表F2-2'!C22 -> 0 | D13: ='明细汇总表F2-2'!D22 -> 0 | E13: =B13+C13-D13 -> 0
A14: ='明细汇总表F2-2'!A23 -> 库存商品 | B14: ='明细汇总表F2-2'!B23 -> 0 | C14: ='明细汇总表F2-2'!C23 -> 0 | D14: ='明细汇总表F2-2'!D23 -> 0 | E14: =B14+C14-D14 -> 0
A15: ='明细汇总表F2-2'!A24 -> 发出商品 | B15: ='明细汇总表F2-2'!B24 -> 0 | C15: ='明细汇总表F2-2'!C24 -> 0 | D15: ='明细汇总表F2-2'!D24 -> 0 | E15: =B15+C15-D15 -> 0
A16: ='明细汇总表F2-2'!A25 -> 开发产品 | B16: ='明细汇总表F2-2'!B25 -> 0 | C16: ='明细汇总表F2-2'!C25 -> 0 | D16: ='明细汇总表F2-2'!D25 -> 0 | E16: =B16+C16-D16 -> 0
A17: ='明细汇总表F2-2'!A26 -> 开发成本 | B17: ='明细汇总表F2-2'!B26 -> 0 | C17: ='明细汇总表F2-2'!C26 -> 0 | D17: ='明细汇总表F2-2'!D26 -> 0 | E17: =B17+C17-D17 -> 0
A18: 合同履约成本 | B18: ='明细汇总表F2-2'!B27 -> 0 | C18: ='明细汇总表F2-2'!C27 -> 0 | D18: ='明细汇总表F2-2'!D27 -> 0 | E18: =B18+C18-D18 -> 0
A19: ='明细汇总表F2-2'!A28 -> 消耗性生物资产 | B19: ='明细汇总表F2-2'!B28 -> 0 | C19: ='明细汇总表F2-2'!C28 -> 0 | D19: ='明细汇总表F2-2'!D28 -> 0 | E19: =B19+C19-D19 -> 0
A20: 数据资源 | B20: ='明细汇总表F2-2'!B29 -> 0 | C20: ='明细汇总表F2-2'!C29 -> 0 | D20: ='明细汇总表F2-2'!D29 -> 0 | E20: =B20+C20-D20 -> 0
A21: 账项调整 | B21: =SUM(B22:B34) -> 0 | C21: =SUM(C22:C34) -> 0 | D21: =SUM(D22:D34) -> 0 | E21: =SUM(E22:E34) -> 0
A22: =A8 -> 原材料 | B22: ='明细汇总表F2-2'!F17 -> 0 | C22: ='明细汇总表F2-2'!G17 -> 0 | D22: ='明细汇总表F2-2'!H17 -> 0 | E22: =B22+C22-D22 -> 0
A23: =A9 -> 材料采购/在途物资 | B23: ='明细汇总表F2-2'!F18 -> 0 | C23: ='明细汇总表F2-2'!G18 -> 0 | D23: ='明细汇总表F2-2'!H18 -> 0 | E23: =B23+C23-D23 -> 0
A24: =A10 -> 周转材料/低值易耗品/包装物 | B24: ='明细汇总表F2-2'!F19 -> 0 | C24: ='明细汇总表F2-2'!G19 -> 0 | D24: ='明细汇总表F2-2'!H19 -> 0 | E24: =B24+C24-D24 -> 0
A25: =A11 -> 在产品 | B25: ='明细汇总表F2-2'!F20 -> 0 | C25: ='明细汇总表F2-2'!G20 -> 0 | D25: ='明细汇总表F2-2'!H20 -> 0 | E25: =B25+C25-D25 -> 0
A26: =A12 -> 自制半成品 | B26: ='明细汇总表F2-2'!F21 -> 0 | C26: ='明细汇总表F2-2'!G21 -> 0 | D26: ='明细汇总表F2-2'!H21 -> 0 | E26: =B26+C26-D26 -> 0
A27: =A13 -> 委托加工物资 | B27: ='明细汇总表F2-2'!F22 -> 0 | C27: ='明细汇总表F2-2'!G22 -> 0 | D27: ='明细汇总表F2-2'!H22 -> 0 | E27: =B27+C27-D27 -> 0
A28: =A14 -> 库存商品 | B28: ='明细汇总表F2-2'!F23 -> 0 | C28: ='明细汇总表F2-2'!G23 -> 0 | D28: ='明细汇总表F2-2'!H23 -> 0 | E28: =B28+C28-D28 -> 0
A29: =A15 -> 发出商品 | B29: ='明细汇总表F2-2'!F24 -> 0 | C29: ='明细汇总表F2-2'!G24 -> 0 | D29: ='明细汇总表F2-2'!H24 -> 0 | E29: =B29+C29-D29 -> 0
A30: =A16 -> 开发产品 | B30: ='明细汇总表F2-2'!F25 -> 0 | C30: ='明细汇总表F2-2'!G25 -> 0 | D30: ='明细汇总表F2-2'!H25 -> 0 | E30: =B30+C30-D30 -> 0
A31: =A17 -> 开发成本 | B31: ='明细汇总表F2-2'!F26 -> 0 | C31: ='明细汇总表F2-2'!G26 -> 0 | D31: ='明细汇总表F2-2'!H26 -> 0 | E31: =B31+C31-D31 -> 0
A32: =A18 -> 合同履约成本 | B32: ='明细汇总表F2-2'!F27 -> 0 | C32: ='明细汇总表F2-2'!G27 -> 0 | D32: ='明细汇总表F2-2'!H27 -> 0 | E32: =B32+C32-D32 -> 0
A33: =A19 -> 消耗性生物资产 | B33: ='明细汇总表F2-2'!F28 -> 0 | C33: ='明细汇总表F2-2'!G28 -> 0 | D33: ='明细汇总表F2-2'!H28 -> 0 | E33: =B33+C33-D33 -> 0
A34: 数据资源 | B34: ='明细汇总表F2-2'!F29 -> 0 | C34: ='明细汇总表F2-2'!G29 -> 0 | D34: ='明细汇总表F2-2'!H29 -> 0 | E34: =B34+C34-D34 -> 0
A35: 审定数（原值） | B35: =SUM(B36:B48) -> 0 | C35: =SUM(C36:C48) -> 0 | D35: =SUM(D36:D48) -> 0 | E35: =SUM(E36:E48) -> 0
A36: =A8 -> 原材料 | B36: =B8+B22 -> 0 | C36: =C8+C22 -> 0 | D36: =D8+D22 -> 0 | E36: =E8+E22 -> 0
A37: =A9 -> 材料采购/在途物资 | B37: =B9+B23 -> 0 | C37: =C9+C23 -> 0 | D37: =D9+D23 -> 0 | E37: =E9+E23 -> 0
A38: =A10 -> 周转材料/低值易耗品/包装物 | B38: =B10+B24 -> 0 | C38: =C10+C24 -> 0 | D38: =D10+D24 -> 0 | E38: =E10+E24 -> 0
A39: =A11 -> 在产品 | B39: =B11+B25 -> 0 | C39: =C11+C25 -> 0 | D39: =D11+D25 -> 0 | E39: =E11+E25 -> 0
A40: =A12 -> 自制半成品 | B40: =B12+B26 -> 0 | C40: =C12+C26 -> 0 | D40: =D12+D26 -> 0 | E40: =E12+E26 -> 0
A41: =A13 -> 委托加工物资 | B41: =B13+B27 -> 0 | C41: =C13+C27 -> 0 | D41: =D13+D27 -> 0 | E41: =E13+E27 -> 0
A42: =A14 -> 库存商品 | B42: =B14+B28 -> 0 | C42: =C14+C28 -> 0 | D42: =D14+D28 -> 0 | E42: =E14+E28 -> 0
A43: =A15 -> 发出商品 | B43: =B15+B29 -> 0 | C43: =C15+C29 -> 0 | D43: =D15+D29 -> 0 | E43: =E15+E29 -> 0
A44: =A16 -> 开发产品 | B44: =B16+B30 -> 0 | C44: =C16+C30 -> 0 | D44: =D16+D30 -> 0 | E44: =E16+E30 -> 0
A45: =A17 -> 开发成本 | B45: =B17+B31 -> 0 | C45: =C17+C31 -> 0 | D45: =D17+D31 -> 0 | E45: =E17+E31 -> 0
A46: =A18 -> 合同履约成本 | B46: =B18+B32 -> 0 | C46: =C18+C32 -> 0 | D46: =D18+D32 -> 0 | E46: =E18+E32 -> 0
A47: =A19 -> 消耗性生物资产 | B47: =B19+B33 -> 0 | C47: =C19+C33 -> 0 | D47: =D19+D33 -> 0 | E47: =E19+E33 -> 0
A48: 数据资源 | B48: =B20+B34 -> 0 | C48: =C20+C34 -> 0 | D48: =D20+D34 -> 0 | E48: =E20+E34 -> 0
A49: 二、跌价准备
A50: 未审数 | B50: =SUM(B51:B63) -> 0 | C50: =SUM(C51:C63) -> 0 | D50: =SUM(D51:D63) -> 0 | E50: =SUM(E51:E63) -> 0
A51: =A8 -> 原材料 | B51: ='明细汇总表F2-2'!B35 -> 0 | C51: ='明细汇总表F2-2'!C35 -> 0 | D51: ='明细汇总表F2-2'!D35 -> 0 | E51: =B51+C51-D51 -> 0
A52: =A9 -> 材料采购/在途物资 | B52: ='明细汇总表F2-2'!B36 -> 0 | C52: ='明细汇总表F2-2'!C36 -> 0 | D52: ='明细汇总表F2-2'!D36 -> 0 | E52: =B52+C52-D52 -> 0
A53: =A10 -> 周转材料/低值易耗品/包装物 | B53: ='明细汇总表F2-2'!B37 -> 0 | C53: ='明细汇总表F2-2'!C37 -> 0 | D53: ='明细汇总表F2-2'!D37 -> 0 | E53: =B53+C53-D53 -> 0
A54: =A11 -> 在产品 | B54: ='明细汇总表F2-2'!B38 -> 0 | C54: ='明细汇总表F2-2'!C38 -> 0 | D54: ='明细汇总表F2-2'!D38 -> 0 | E54: =B54+C54-D54 -> 0
A55: =A12 -> 自制半成品 | B55: ='明细汇总表F2-2'!B39 -> 0 | C55: ='明细汇总表F2-2'!C39 -> 0 | D55: ='明细汇总表F2-2'!D39 -> 0 | E55: =B55+C55-D55 -> 0
A56: =A13 -> 委托加工物资 | B56: ='明细汇总表F2-2'!B40 -> 0 | C56: ='明细汇总表F2-2'!C40 -> 0 | D56: ='明细汇总表F2-2'!D40 -> 0 | E56: =B56+C56-D56 -> 0
A57: =A14 -> 库存商品 | B57: ='明细汇总表F2-2'!B41 -> 0 | C57: ='明细汇总表F2-2'!C41 -> 0 | D57: ='明细汇总表F2-2'!D41 -> 0 | E57: =B57+C57-D57 -> 0
A58: =A15 -> 发出商品 | B58: ='明细汇总表F2-2'!B42 -> 0 | C58: ='明细汇总表F2-2'!C42 -> 0 | D58: ='明细汇总表F2-2'!D42 -> 0 | E58: =B58+C58-D58 -> 0
A59: =A16 -> 开发产品 | B59: ='明细汇总表F2-2'!B43 -> 0 | C59: ='明细汇总表F2-2'!C43 -> 0 | D59: ='明细汇总表F2-2'!D43 -> 0 | E59: =B59+C59-D59 -> 0
A60: =A17 -> 开发成本 | B60: ='明细汇总表F2-2'!B44 -> 0 | C60: ='明细汇总表F2-2'!C44 -> 0 | D60: ='明细汇总表F2-2'!D44 -> 0 | E60: =B60+C60-D60 -> 0
A61: =A18 -> 合同履约成本 | B61: ='明细汇总表F2-2'!B45 -> 0 | C61: ='明细汇总表F2-2'!C45 -> 0 | D61: ='明细汇总表F2-2'!D45 -> 0 | E61: =B61+C61-D61 -> 0
A62: =A19 -> 消耗性生物资产 | B62: ='明细汇总表F2-2'!B46 -> 0 | C62: ='明细汇总表F2-2'!C46 -> 0 | D62: ='明细汇总表F2-2'!D46 -> 0 | E62: =B62+C62-D62 -> 0
A63: =A20 -> 数据资源 | B63: ='明细汇总表F2-2'!B47 -> 0 | C63: ='明细汇总表F2-2'!C47 -> 0 | D63: ='明细汇总表F2-2'!D47 -> 0
A64: 账项调整 | B64: =SUM(B65:B77) -> 0 | C64: =SUM(C65:C77) -> 0 | D64: =SUM(D65:D77) -> 0 | E64: =SUM(E65:E77) -> 0
A65: =A22 -> 原材料 | B65: ='明细汇总表F2-2'!F35 -> 0 | C65: ='明细汇总表F2-2'!G35 -> 0 | D65: ='明细汇总表F2-2'!H35 -> 0 | E65: =B65+C65-D65 -> 0
A66: =A23 -> 材料采购/在途物资 | B66: ='明细汇总表F2-2'!F36 -> 0 | C66: ='明细汇总表F2-2'!G36 -> 0 | D66: ='明细汇总表F2-2'!H36 -> 0 | E66: =B66+C66-D66 -> 0
A67: =A24 -> 周转材料/低值易耗品/包装物 | B67: ='明细汇总表F2-2'!F37 -> 0 | C67: ='明细汇总表F2-2'!G37 -> 0 | D67: ='明细汇总表F2-2'!H37 -> 0 | E67: =B67+C67-D67 -> 0
A68: =A25 -> 在产品 | B68: ='明细汇总表F2-2'!F38 -> 0 | C68: ='明细汇总表F2-2'!G38 -> 0 | D68: ='明细汇总表F2-2'!H38 -> 0 | E68: =B68+C68-D68 -> 0
A69: =A26 -> 自制半成品 | B69: ='明细汇总表F2-2'!F39 -> 0 | C69: ='明细汇总表F2-2'!G39 -> 0 | D69: ='明细汇总表F2-2'!H39 -> 0 | E69: =B69+C69-D69 -> 0
A70: =A27 -> 委托加工物资 | B70: ='明细汇总表F2-2'!F40 -> 0 | C70: ='明细汇总表F2-2'!G40 -> 0 | D70: ='明细汇总表F2-2'!H40 -> 0 | E70: =B70+C70-D70 -> 0
A71: =A28 -> 库存商品 | B71: ='明细汇总表F2-2'!F41 -> 0 | C71: ='明细汇总表F2-2'!G41 -> 0 | D71: ='明细汇总表F2-2'!H41 -> 0 | E71: =B71+C71-D71 -> 0
A72: =A29 -> 发出商品 | B72: ='明细汇总表F2-2'!F42 -> 0 | C72: ='明细汇总表F2-2'!G42 -> 0 | D72: ='明细汇总表F2-2'!H42 -> 0 | E72: =B72+C72-D72 -> 0
A73: =A30 -> 开发产品 | B73: ='明细汇总表F2-2'!F43 -> 0 | C73: ='明细汇总表F2-2'!G43 -> 0 | D73: ='明细汇总表F2-2'!H43 -> 0 | E73: =B73+C73-D73 -> 0
A74: =A31 -> 开发成本 | B74: ='明细汇总表F2-2'!F44 -> 0 | C74: ='明细汇总表F2-2'!G44 -> 0 | D74: ='明细汇总表F2-2'!H44 -> 0 | E74: =B74+C74-D74 -> 0
A75: =A32 -> 合同履约成本 | B75: ='明细汇总表F2-2'!F45 -> 0 | C75: ='明细汇总表F2-2'!G45 -> 0 | D75: ='明细汇总表F2-2'!H45 -> 0 | E75: =B75+C75-D75 -> 0
A76: =A33 -> 消耗性生物资产 | B76: ='明细汇总表F2-2'!F46 -> 0 | C76: ='明细汇总表F2-2'!G46 -> 0 | D76: ='明细汇总表F2-2'!H46 -> 0 | E76: =B76+C76-D76 -> 0
A77: =A34 -> 数据资源 | B77: ='明细汇总表F2-2'!F47 -> 0 | C77: ='明细汇总表F2-2'!G47 -> 0 | D77: ='明细汇总表F2-2'!H47 -> 0 | E77: =B77+C77-D77 -> 0
A78: 审定数（跌价准备） | B78: =SUM(B79:B91) -> 0 | C78: =SUM(C79:C91) -> 0 | D78: =SUM(D79:D91) -> 0 | E78: =SUM(E79:E91) -> 0
A79: =A36 -> 原材料 | B79: =B51+B65 -> 0 | C79: =C51+C65 -> 0 | D79: =D51+D65 -> 0 | E79: =E51+E65 -> 0
A80: =A37 -> 材料采购/在途物资 | B80: =B52+B66 -> 0 | C80: =C52+C66 -> 0 | D80: =D52+D66 -> 0 | E80: =E52+E66 -> 0
A81: =A38 -> 周转材料/低值易耗品/包装物 | B81: =B53+B67 -> 0 | C81: =C53+C67 -> 0 | D81: =D53+D67 -> 0 | E81: =E53+E67 -> 0
A82: =A39 -> 在产品 | B82: =B54+B68 -> 0 | C82: =C54+C68 -> 0 | D82: =D54+D68 -> 0 | E82: =E54+E68 -> 0
A83: =A40 -> 自制半成品 | B83: =B55+B69 -> 0 | C83: =C55+C69 -> 0 | D83: =D55+D69 -> 0 | E83: =E55+E69 -> 0
A84: =A41 -> 委托加工物资 | B84: =B56+B70 -> 0 | C84: =C56+C70 -> 0 | D84: =D56+D70 -> 0 | E84: =E56+E70 -> 0
A85: =A42 -> 库存商品 | B85: =B57+B71 -> 0 | C85: =C57+C71 -> 0 | D85: =D57+D71 -> 0 | E85: =E57+E71 -> 0
A86: =A43 -> 发出商品 | B86: =B58+B72 -> 0 | C86: =C58+C72 -> 0 | D86: =D58+D72 -> 0 | E86: =E58+E72 -> 0
A87: =A44 -> 开发产品 | B87: =B59+B73 -> 0 | C87: =C59+C73 -> 0 | D87: =D59+D73 -> 0 | E87: =E59+E73 -> 0
A88: =A45 -> 开发成本 | B88: =B60+B74 -> 0 | C88: =C60+C74 -> 0 | D88: =D60+D74 -> 0 | E88: =E60+E74 -> 0
A89: =A46 -> 合同履约成本 | B89: =B61+B75 -> 0 | C89: =C61+C75 -> 0 | D89: =D61+D75 -> 0 | E89: =E61+E75 -> 0
A90: =A47 -> 消耗性生物资产 | B90: =B62+B76 -> 0 | C90: =C62+C76 -> 0 | D90: =D62+D76 -> 0 | E90: =E62+E76 -> 0
A91: =A48 -> 数据资源 | B91: =B63+B77 -> 0 | C91: =C63+C77 -> 0 | D91: =D63+D77 -> 0 | E91: =E63+E77 -> 0
A92: 三、净值
A93: 审定数（净值） | B93: =SUM(B94:B106) -> 0 | C93: =SUM(C94:C106) -> 0 | D93: =SUM(D94:D106) -> 0 | E93: =SUM(E94:E106) -> 0
A94: =A8 -> 原材料 | B94: =B36-B79 -> 0 | C94: =C36-C79 -> 0 | D94: =D36-D79 -> 0 | E94: =E36-E79 -> 0
A95: =A9 -> 材料采购/在途物资 | B95: =B37-B80 -> 0 | C95: =C37-C80 -> 0 | D95: =D37-D80 -> 0 | E95: =E37-E80 -> 0
A96: =A10 -> 周转材料/低值易耗品/包装物 | B96: =B38-B81 -> 0 | C96: =C38-C81 -> 0 | D96: =D38-D81 -> 0 | E96: =E38-E81 -> 0
A97: =A11 -> 在产品 | B97: =B39-B82 -> 0 | C97: =C39-C82 -> 0 | D97: =D39-D82 -> 0 | E97: =E39-E82 -> 0
A98: =A12 -> 自制半成品 | B98: =B40-B83 -> 0 | C98: =C40-C83 -> 0 | D98: =D40-D83 -> 0 | E98: =E40-E83 -> 0
A99: =A13 -> 委托加工物资 | B99: =B41-B84 -> 0 | C99: =C41-C84 -> 0 | D99: =D41-D84 -> 0 | E99: =E41-E84 -> 0
A100: =A14 -> 库存商品 | B100: =B42-B85 -> 0 | C100: =C42-C85 -> 0 | D100: =D42-D85 -> 0 | E100: =E42-E85 -> 0
...

Sheet 附注披露信息（上市公司）
A1: 致同会计师事务所
A2: 存货附注披露信息（上市公司）
A3: =底稿目录!A2 -> 被审计单位： | C3: =底稿目录!A4 -> 编制人： | E3: =底稿目录!A5 -> 编制日期： | G3: 索引号：
A4: =底稿目录!A3 -> 截止日：202X年12月21日 | C4: =底稿目录!A6 -> 复核人： | E4: =底稿目录!A7 -> 复核日期： | G4: 页次：
A5: 存货附注披露信息：
A6: 存货
A7: （1）存货分类
A8: 存货种类 | B8: 期末数 | E8: 上年年末数
B9: 账面余额 | C9: 跌价准备/合同履约成本减值准备 | D9: 账面价值 | E9: 账面余额 | F9: 跌价准备/合同履约成本减值准备 | G9: 账面价值
A10: ='存货审定表F2-1'!A36 -> 原材料 | B10: ='存货审定表F2-1'!E36+'存货审定表F2-1'!E37 -> 0 | C10: ='存货审定表F2-1'!E79+'存货审定表F2-1'!E80 -> 0 | D10: =B10-C10 -> 0 | E10: ='存货审定表F2-1'!B36+'存货审定表F2-1'!B37 -> 0 | F10: ='存货审定表F2-1'!B79+'存货审定表F2-1'!B80 -> 0 | G10: =E10-F10 -> 0
A11: ='存货审定表F2-1'!A39 -> 在产品 | B11: ='存货审定表F2-1'!E39+'存货审定表F2-1'!E40 -> 0 | C11: ='存货审定表F2-1'!E82+'存货审定表F2-1'!E83 -> 0 | D11: =B11-C11 -> 0 | E11: ='存货审定表F2-1'!B39+'存货审定表F2-1'!B40 -> 0 | F11: ='存货审定表F2-1'!B82+'存货审定表F2-1'!B83 -> 0 | G11: =E11-F11 -> 0
A12: ='存货审定表F2-1'!A41 -> 委托加工物资 | B12: ='存货审定表F2-1'!E41 -> 0 | C12: ='存货审定表F2-1'!E84 -> 0 | D12: =B12-C12 -> 0 | E12: ='存货审定表F2-1'!B41 -> 0 | F12: ='存货审定表F2-1'!B84 -> 0 | G12: =E12-F12 -> 0
A13: ='存货审定表F2-1'!A42 -> 库存商品 | B13: ='存货审定表F2-1'!E42 -> 0 | C13: ='存货审定表F2-1'!E85 -> 0 | D13: =B13-C13 -> 0 | E13: ='存货审定表F2-1'!B42 -> 0 | F13: ='存货审定表F2-1'!B85 -> 0 | G13: =E13-F13 -> 0
A14: ='存货审定表F2-1'!A43 -> 发出商品 | B14: ='存货审定表F2-1'!E43 -> 0 | C14: ='存货审定表F2-1'!E86 -> 0 | D14: =B14-C14 -> 0 | E14: ='存货审定表F2-1'!B43 -> 0 | F14: ='存货审定表F2-1'!B86 -> 0 | G14: =E14-F14 -> 0
A15: 周转材料 | B15: ='存货审定表F2-1'!E38 -> 0 | C15: ='存货审定表F2-1'!E81 -> 0 | D15: =B15-C15 -> 0 | E15: ='存货审定表F2-1'!B38 -> 0 | F15: ='存货审定表F2-1'!B81 -> 0 | G15: =E15-F15 -> 0
A16: 合同履约成本 | B16: ='存货审定表F2-1'!E46 -> 0 | C16: ='存货审定表F2-1'!E89 -> 0 | D16: =B16-C16 -> 0 | E16: ='存货审定表F2-1'!B46 -> 0 | F16: ='存货审定表F2-1'!B89 -> 0 | G16: =E16-F16 -> 0
A17: ='存货审定表F2-1'!A47 -> 消耗性生物资产 | B17: ='存货审定表F2-1'!E47 -> 0 | C17: ='存货审定表F2-1'!E90 -> 0 | D17: =B17-C17 -> 0 | E17: ='存货审定表F2-1'!B47 -> 0 | F17: ='存货审定表F2-1'!B90 -> 0 | G17: =E17-F17 -> 0
A18: 数据资源 | B18: ='存货审定表F2-1'!E48 -> 0 | C18: ='存货审定表F2-1'!E91 -> 0 | D18: =B18-C18 -> 0 | E18: ='存货审定表F2-1'!B48 -> 0 | F18: ='存货审定表F2-1'!B91 -> 0 | G18: =E18-F18 -> 0
A19: 合 计 | B19: =SUM(B10:B18) -> 0 | C19: =SUM(C10:C18) -> 0 | D19: =SUM(D10:D18) -> 0 | E19: =SUM(E10:E18) -> 0 | F19: =SUM(F10:F18) -> 0 | G19: =SUM(G10:G18) -> 0
A20: （注：根据企业具体情况分类，房地产开发企业应增加“开发成本”、“开发产品”等种类）
A21: （2）存货跌价准备及合同履约成本减值准备
A22: 存货种类 | B22: 期初余额 | C22: 本期增加 | E22: 本期减少 | G22: 期末余额
C23: 计提 | D23: 其他 | E23: 转回或转销 | F23: 其他
A24: =A10 -> 原材料 | B24: ='存货审定表F2-1'!B79+'存货审定表F2-1'!B80 -> 0 | C24: ='明细汇总表F2-2'!K35+'明细汇总表F2-2'!K36 -> 0 | D24: ='明细汇总表F2-2'!L35+'明细汇总表F2-2'!L36 -> 0 | E24: ='明细汇总表F2-2'!N35+'明细汇总表F2-2'!O35+'明细汇总表F2-2'!N36+'明细汇总表F2-2'!O36 -> 0 | F24: ='明细汇总表F2-2'!P35+'明细汇总表F2-2'!P36 -> 0 | G24: =B24+C24+D24-E24-F24 -> 0
A25: =A11 -> 在产品 | B25: ='存货审定表F2-1'!B82+'存货审定表F2-1'!B83 -> 0 | C25: ='明细汇总表F2-2'!K38+'明细汇总表F2-2'!K39 -> 0 | D25: ='明细汇总表F2-2'!L38+'明细汇总表F2-2'!L39 -> 0 | E25: ='明细汇总表F2-2'!N38+'明细汇总表F2-2'!O38+'明细汇总表F2-2'!N39+'明细汇总表F2-2'!O39 -> 0 | F25: ='明细汇总表F2-2'!P38+'明细汇总表F2-2'!P39 -> 0 | G25: =B25+C25+D25-E25-F25 -> 0
A26: =A12 -> 委托加工物资 | B26: ='存货审定表F2-1'!B84 -> 0 | C26: ='明细汇总表F2-2'!K40 -> 0 | D26: ='明细汇总表F2-2'!L40 -> 0 | E26: ='明细汇总表F2-2'!N40+'明细汇总表F2-2'!O40 -> 0 | F26: ='明细汇总表F2-2'!P40 -> 0 | G26: =B26+C26+D26-E26-F26 -> 0
A27: =A13 -> 库存商品 | B27: ='存货审定表F2-1'!B85 -> 0 | C27: ='明细汇总表F2-2'!K41 -> 0 | D27: ='明细汇总表F2-2'!L41 -> 0 | E27: ='明细汇总表F2-2'!N41+'明细汇总表F2-2'!O41 -> 0 | F27: ='明细汇总表F2-2'!P41 -> 0 | G27: =B27+C27+D27-E27-F27 -> 0
A28: =A14 -> 发出商品 | B28: ='存货审定表F2-1'!B86 -> 0 | C28: ='明细汇总表F2-2'!K42 -> 0 | D28: ='明细汇总表F2-2'!L42 -> 0 | E28: ='明细汇总表F2-2'!N42+'明细汇总表F2-2'!O42 -> 0 | F28: ='明细汇总表F2-2'!P42 -> 0 | G28: =B28+C28+D28-E28-F28 -> 0
A29: =A15 -> 周转材料 | B29: ='存货审定表F2-1'!B81 -> 0 | C29: ='明细汇总表F2-2'!K37 -> 0 | D29: ='明细汇总表F2-2'!L37 -> 0 | E29: ='明细汇总表F2-2'!N37+'明细汇总表F2-2'!O37 -> 0 | F29: ='明细汇总表F2-2'!P37 -> 0 | G29: =B29+C29+D29-E29-F29 -> 0
A30: 合同履约成本 | B30: ='存货审定表F2-1'!B89 -> 0 | C30: ='明细汇总表F2-2'!K46 -> 0 | D30: ='明细汇总表F2-2'!L46 -> 0 | E30: ='明细汇总表F2-2'!N46+'明细汇总表F2-2'!O46 -> 0 | F30: ='明细汇总表F2-2'!P46 -> 0 | G30: =B30+C30+D30-E30-F30 -> 0
A31: =A17 -> 消耗性生物资产 | B31: ='存货审定表F2-1'!B90 -> 0 | C31: ='明细汇总表F2-2'!K46 -> 0 | D31: ='明细汇总表F2-2'!L46 -> 0 | E31: ='明细汇总表F2-2'!N46+'明细汇总表F2-2'!O46 -> 0 | F31: ='明细汇总表F2-2'!P46 -> 0 | G31: =B31+C31+D31-E31-F31 -> 0
A32: 数据资源 | B32: ='存货审定表F2-1'!B91 -> 0 | C32: ='明细汇总表F2-2'!K47 -> 0 | D32: ='明细汇总表F2-2'!L47 -> 0 | E32: ='明细汇总表F2-2'!N47+'明细汇总表F2-2'!O47 -> 0 | F32: ='明细汇总表F2-2'!P47 -> 0 | G32: =B32+C32+D32-E32-F32 -> 0
A33: 合 计 | B33: =SUM(B24:B32) -> 0 | C33: =SUM(C24:C32) -> 0 | D33: =SUM(D24:D32) -> 0 | E33: =SUM(E24:E32) -> 0 | F33: =SUM(F24:F32) -> 0 | G33: =SUM(G24:G32) -> 0
A34: 存货跌价准备及合同履约成本减值准备（续）
A35: 存货种类 | B35: 确定可变现净值/剩余对价与将要发生的成本的具体依据 | C35: 本期转回或转销存货跌价准备/合同履约成本减值准备的原因
A36: =A24 -> 原材料 | B36: ='明细汇总表F2-2'!I53+'明细汇总表F2-2'!I54 -> 0 | C36: ='明细汇总表F2-2'!J53+'明细汇总表F2-2'!J54 -> 0
A37: =A25 -> 在产品 | B37: ='明细汇总表F2-2'!I56+'明细汇总表F2-2'!I57 -> 0 | C37: ='明细汇总表F2-2'!J56+'明细汇总表F2-2'!J57 -> 0
A38: =A26 -> 委托加工物资 | B38: ='明细汇总表F2-2'!I58 -> 0 | C38: ='明细汇总表F2-2'!J58 -> 0
A39: =A27 -> 库存商品 | B39: ='明细汇总表F2-2'!I59 -> 0 | C39: ='明细汇总表F2-2'!J59 -> 0
A40: =A28 -> 发出商品 | B40: ='明细汇总表F2-2'!I60 -> 0 | C40: ='明细汇总表F2-2'!J60 -> 0
A41: =A29 -> 周转材料 | B41: ='明细汇总表F2-2'!I55 -> 0 | C41: ='明细汇总表F2-2'!J55 -> 0
A42: 合同履约成本 | B42: ='明细汇总表F2-2'!I64 -> 0 | C42: ='明细汇总表F2-2'!J64 -> 0
A43: =A31 -> 消耗性生物资产 | B43: ='明细汇总表F2-2'!I64 -> 0 | C43: ='明细汇总表F2-2'!J64 -> 0
A44: 数据资源 | B44: ='明细汇总表F2-2'!I65 -> 0 | C44: ='明细汇总表F2-2'!J65 -> 0
A45: 合 计 | B45: -- | C45: --
A46: 【披露确定可变现净值的具体依据及本期转回或转销存货跌价准备的原因。】
A47: （3）按组合计提存货跌价准备
A48: （15号文第十九条（六）按组合计提存货跌价准备的，应分类披露不同组合存货的期初余额、期末余额，对应的跌价准备的期初余额、期末余额、计提标准和比例。）
A49: 组 合 | B49: 期末余额
B50: 账面余额 | D50: 存货跌价准备 | G50: 账面价值
B51: 金额 | C51: 比例(%) | D51: 金额 | E51: 计提标准 | F51: 比例(%
C52: =B52/B54 -> #DIV/0! | F52: =D52/B52 -> #DIV/0! | G52: =B52-D52 -> 0
C53: =B53/B54 -> #DIV/0! | F53: =D53/B53 -> #DIV/0! | G53: =B53-D53 -> 0
A54: 合计 | B54: =SUM(B52:B53) -> 0 | C54: 1 | D54: =SUM(D52:D53) -> 0 | F54: =D54/B54 -> #DIV/0! | G54: =B54-D54 -> 0
A55: 续
A56: 组 合 | B56: 上年年末余额
B57: 账面余额 | D57: 存货跌价准备 | G57: 账面价值
B58: 金额 | C58: 比例(%) | D58: 金额 | E58: 计提标准 | F58: 比例(%
C59: =B59/B61 -> #DIV/0! | F59: =D59/B59 -> #DIV/0! | G59: =B59-D59 -> 0
C60: =B60/B61 -> #DIV/0! | F60: =D60/B60 -> #DIV/0! | G60: =B60-D60 -> 0
A61: 合计 | B61: =SUM(B59:B60) -> 0 | C61: 1 | D61: =SUM(D59:D60) -> 0 | F61: =D61/B61 -> #DIV/0! | G61: =B61-D61 -> 0
A63: （4）存货期末余额中含有借款费用资本化金额的说明：
A64: （15号文第十九条（六）披露存货期末余额中含有的借款费用资本化金额及其计算标准和依据。）
A65: （房地产开发企业，应按下列格式披露“开发成本”、“开发产品”等相关信息)
A66: （5）开发成本
A67: 项目名称 | B67: 开工时间 | C67: 预计竣工时间 | D67: 预计总投资 | E67: 期末数 | F67: 上年年末数 | G67: 期末跌价准备
A68: ='九、开发成本F2-11'!B9 -> 0 | B68: ='九、开发成本F2-11'!$D$9 -> 0 | C68: ='九、开发成本F2-11'!E9 -> 0 | D68: ='九、开发成本F2-11'!F9 -> 0 | E68: ='九、开发成本F2-11'!J37 -> 0 | F68: ='九、开发成本F2-11'!I37 -> 0 | G68: ='九、开发成本F2-11'!T23 -> 0
A69: ='九、开发成本F2-11'!B10 -> 0 | B69: ='九、开发成本F2-11'!$D$9 -> 0 | C69: ='九、开发成本F2-11'!E10 -> 0 | D69: ='九、开发成本F2-11'!F10 -> 0 | E69: ='九、开发成本F2-11'!J38 -> 0 | F69: ='九、开发成本F2-11'!I38 -> 0 | G69: ='九、开发成本F2-11'!T24 -> 0
A70: ='九、开发成本F2-11'!B11 -> 0 | B70: ='九、开发成本F2-11'!$D$9 -> 0 | C70: ='九、开发成本F2-11'!E11 -> 0 | D70: ='九、开发成本F2-11'!F11 -> 0 | E70: ='九、开发成本F2-11'!J39 -> 0 | F70: ='九、开发成本F2-11'!I39 -> 0 | G70: ='九、开发成本F2-11'!T25 -> 0
A71: ='九、开发成本F2-11'!B12 -> 0 | B71: ='九、开发成本F2-11'!$D$9 -> 0 | C71: ='九、开发成本F2-11'!E12 -> 0 | D71: ='九、开发成本F2-11'!F12 -> 0 | E71: ='九、开发成本F2-11'!J40 -> 0 | F71: ='九、开发成本F2-11'!I40 -> 0 | G71: ='九、开发成本F2-11'!T26 -> 0
A72: ='九、开发成本F2-11'!B13 -> 0 | B72: ='九、开发成本F2-11'!$D$9 -> 0 | C72: ='九、开发成本F2-11'!E13 -> 0 | D72: ='九、开发成本F2-11'!F13 -> 0 | E72: ='九、开发成本F2-11'!J41 -> 0 | F72: ='九、开发成本F2-11'!I41 -> 0 | G72: ='九、开发成本F2-11'!T27 -> 0
A73: 合 计 | E73: =SUM(E68:E72) -> 0 | F73: =SUM(F68:F72) -> 0 | G73: =SUM(G68:G72) -> 0
A74: （6）开发产品
A75: 项目名称 | B75: 竣工时间 | C75: 期初余额 | D75: 本期增加 | E75: 本期减少 | F75: 期末余额 | G75: 期末跌价准备
A76: ='八、开发产品F2-10'!$B$9 -> 0 | B76: ='八、开发产品F2-10'!$E$9 -> 0 | C76: ='八、开发产品F2-10'!H37 -> 0 | D76: ='八、开发产品F2-10'!O9+'八、开发产品F2-10'!V9+'八、开发产品F2-10'!W9-'八、开发产品F2-10'!I9-'八、开发产品F2-10'!J9 -> 0 | E76: =C76+D76-F76 -> 0 | F76: ='八、开发产品F2-10'!Q37 -> 0 | G76: ='八、开发产品F2-10'!S23 -> 0
A77: ='八、开发产品F2-10'!$B$9 -> 0 | B77: ='八、开发产品F2-10'!$E$9 -> 0 | C77: ='八、开发产品F2-10'!H45 -> 0 | D77: ='八、开发产品F2-10'!O17+'八、开发产品F2-10'!V17+'八、开发产品F2-10'!W17-'八、开发产品F2-10'!I17-'八、开发产品F2-10'!J17 -> 0 | E77: =C77+D77-F77 -> 0 | F77: ='八、开发产品F2-10'!Q45 -> 0 | G77: ='八、开发产品F2-10'!S31 -> 0
A78: ='八、开发产品F2-10'!$B$9 -> 0 | B78: ='八、开发产品F2-10'!$E$9 -> 0 | C78: ='八、开发产品F2-10'!H46 -> 0 | D78: ='八、开发产品F2-10'!O18+'八、开发产品F2-10'!V18+'八、开发产品F2-10'!W18-'八、开发产品F2-10'!I18-'八、开发产品F2-10'!J18 -> 0 | E78: =C78+D78-F78 -> 0 | F78: ='八、开发产品F2-10'!Q46 -> 0 | G78: ='八、开发产品F2-10'!S32 -> 0
A79: ='八、开发产品F2-10'!$B$9 -> 0 | B79: ='八、开发产品F2-10'!$E$9 -> 0 | C79: ='八、开发产品F2-10'!#REF! -> #REF! | D79: ='八、开发产品F2-10'!#REF!+'八、开发产品F2-10'!#REF!+'八、开发产品F2-10'!#REF!-'八、开发产品F2-10'!#REF!-'八、开发产品F2-10'!#REF! -> #REF! | E79: =C79+D79-F79 -> #REF! | F79: ='八、开发产品F2-10'!#REF! -> #REF! | G79: ='八、开发产品F2-10'!#REF! -> #REF!
A80: ='八、开发产品F2-10'!$B$9 -> 0 | B80: ='八、开发产品F2-10'!$E$9 -> 0 | C80: ='八、开发产品F2-10'!#REF! -> #REF! | D80: ='八、开发产品F2-10'!#REF!+'八、开发产品F2-10'!#REF!+'八、开发产品F2-10'!#REF!-'八、开发产品F2-10'!#REF!-'八、开发产品F2-10'!#REF! -> #REF! | E80: =C80+D80-F80 -> #REF! | F80: ='八、开发产品F2-10'!#REF! -> #REF! | G80: ='八、开发产品F2-10'!#REF! -> #REF!
A81: ='八、开发产品F2-10'!$B$9 -> 0 | B81: ='八、开发产品F2-10'!$E$9 -> 0 | C81: ='八、开发产品F2-10'!#REF! -> #REF! | D81: ='八、开发产品F2-10'!#REF!+'八、开发产品F2-10'!#REF!+'八、开发产品F2-10'!#REF!-'八、开发产品F2-10'!#REF!-'八、开发产品F2-10'!#REF! -> #REF! | E81: =C81+D81-F81 -> #REF! | F81: ='八、开发产品F2-10'!#REF! -> #REF! | G81: ='八、开发产品F2-10'!#REF! -> #REF!
A82: 合 计 | C82: =SUM(C76:C81) -> #REF! | D82: =SUM(D76:D81) -> #REF! | E82: =SUM(E76:E81) -> #REF! | F82: =SUM(F76:F81) -> #REF! | G82: =SUM(G76:G81) -> #REF!
A83: （7）周转房
A84: 项目名称 | B84: 期初余额 | C84: 本期增加 | D84: 本期减少 | E84: 期末余额
A87: 合 计
A88: （房地产开发企业列示存货跌价准备时，对于开发中项目，可以合并列示。对“停工”、“烂尾”“空置”项目，如果不计提或计提跌价比例较低，应详细说明理由。）

Sheet 附注披露信息（国企）
A1: 致同会计师事务所
A2: 存货附注披露信息（国企）
A3: =底稿目录!A2 -> 被审计单位： | B3: =底稿目录!A4 -> 编制人： | E3: =底稿目录!A5 -> 编制日期： | H3: 索引号：
A4: =底稿目录!A3 -> 截止日：202X年12月21日 | B4: =底稿目录!A6 -> 复核人： | E4: =底稿目录!A7 -> 复核日期： | H4: 页次：
A5: 存货附注披露信息：
A6: （1）存货分类
A7: 项 目 | B7: 期末数 | E7: 期初数
B8: 账面余额 | C8: 跌价准备/合同履约成本减值准备 | D8: 账面价值 | E8: 账面余额 | F8: 跌价准备/合同履约成本减值准备 | G8: 账面价值
A9: ='存货审定表F2-1'!A94 -> 原材料 | B9: ='存货审定表F2-1'!E36+'存货审定表F2-1'!E37 -> 0 | C9: ='存货审定表F2-1'!E79+'存货审定表F2-1'!E80 -> 0 | D9: =B9-C9 -> 0 | E9: ='存货审定表F2-1'!B36+'存货审定表F2-1'!B37 -> 0 | F9: ='存货审定表F2-1'!B79+'存货审定表F2-1'!B80 -> 0 | G9: =E9-F9 -> 0
A10: 自制半成品及在产品 | B10: ='存货审定表F2-1'!E39+'存货审定表F2-1'!E40+'存货审定表F2-1'!E45 -> 0 | C10: ='存货审定表F2-1'!E82+'存货审定表F2-1'!E83+'存货审定表F2-1'!E88 -> 0 | D10: =B10-C10 -> 0 | E10: ='存货审定表F2-1'!B39+'存货审定表F2-1'!B40+'存货审定表F2-1'!B45 -> 0 | F10: ='存货审定表F2-1'!B82+'存货审定表F2-1'!B83+'存货审定表F2-1'!B88 -> 0 | G10: =E10-F10 -> 0
A11: 其中：开发成本 | B11: ='存货审定表F2-1'!E45 -> 0 | C11: ='存货审定表F2-1'!E88 -> 0 | D11: =B11-C11 -> 0 | E11: ='存货审定表F2-1'!B45 -> 0 | F11: ='存货审定表F2-1'!B88 -> 0 | G11: =E11-F11 -> 0
A12: ='存货审定表F2-1'!A99 -> 委托加工物资 | B12: ='存货审定表F2-1'!E41 -> 0 | C12: ='存货审定表F2-1'!E84 -> 0 | D12: =B12-C12 -> 0 | E12: ='存货审定表F2-1'!B41 -> 0 | F12: ='存货审定表F2-1'!B84 -> 0 | G12: =E12-F12 -> 0
A13: 库存商品（产成品） | B13: ='存货审定表F2-1'!E42+'存货审定表F2-1'!E44 -> 0 | C13: ='存货审定表F2-1'!E85+'存货审定表F2-1'!E87 -> 0 | D13: =B13-C13 -> 0 | E13: ='存货审定表F2-1'!B42+'存货审定表F2-1'!B44 -> 0 | F13: ='存货审定表F2-1'!B85+'存货审定表F2-1'!B87 -> 0 | G13: =E13-F13 -> 0
A14: 其中：开发产品 | B14: ='存货审定表F2-1'!E44 -> 0 | C14: ='存货审定表F2-1'!E87 -> 0 | D14: =B14-C14 -> 0 | E14: ='存货审定表F2-1'!B44 -> 0 | F14: ='存货审定表F2-1'!B87 -> 0 | G14: =E14-F14 -> 0
A15: 周转材料（包装物、低值易耗品等） | B15: ='存货审定表F2-1'!E38 -> 0 | C15: ='存货审定表F2-1'!E81 -> 0 | D15: =B15-C15 -> 0 | E15: ='存货审定表F2-1'!B38 -> 0 | F15: ='存货审定表F2-1'!B81 -> 0 | G15: =E15-F15 -> 0
A16: ='存货审定表F2-1'!A101 -> 发出商品 | B16: ='存货审定表F2-1'!E43 -> 0 | C16: ='存货审定表F2-1'!E86 -> 0 | D16: =B16-C16 -> 0 | E16: ='存货审定表F2-1'!B43 -> 0 | F16: ='存货审定表F2-1'!B86 -> 0 | G16: =E16-F16 -> 0
A17: ='存货审定表F2-1'!A105 -> 消耗性生物资产 | B17: ='存货审定表F2-1'!E47 -> 0 | C17: ='存货审定表F2-1'!E90 -> 0 | D17: =B17-C17 -> 0 | E17: ='存货审定表F2-1'!B47 -> 0 | F17: ='存货审定表F2-1'!B90 -> 0 | G17: =E17-F17 -> 0
A18: 合同履约成本 | B18: ='存货审定表F2-1'!E46 -> 0 | C18: ='存货审定表F2-1'!E89 -> 0 | D18: =B18-C18 -> 0 | E18: ='存货审定表F2-1'!B46 -> 0 | F18: ='存货审定表F2-1'!B89 -> 0 | G18: =E18-F18 -> 0
A19: 数据资源 | B19: ='存货审定表F2-1'!E48 -> 0 | C19: ='存货审定表F2-1'!E91 -> 0 | D19: =B19-C19 -> 0 | E19: ='存货审定表F2-1'!B48 -> 0 | F19: ='存货审定表F2-1'!B91 -> 0 | G19: =E19-F19 -> 0
A20: 其他
A21: 其中：尚未开发的土地储备(由房地产开发企业填列）
A22: 合 计 | B22: =SUM(B9:B21)-B11-B14-B21 -> 0 | C22: =SUM(C9:C21)-C11-C14-C21 -> 0 | D22: =SUM(D9:D21)-D11-D14-D21 -> 0 | E22: =SUM(E9:E21)-E11-E14-E21 -> 0 | F22: =SUM(F9:F21)-F11-F14-F21 -> 0 | G22: =SUM(G9:G21)-G11-G14-G21 -> 0
A23: （注：其他项中应说明房地产企业土地储备的情况，包括土地储备的面积、本期增加及土地储备年末余额。）
A24: （2）存货跌价准备及合同履约成本减值准备
A25: 存货种类 | B25: 期初数 | C25: 本期增加 | E25: 本期减少 | H25: 期末数
C26: 计提 | D26: 其他 | E26: 转回 | F26: 转销 | G26: 其他
A27: =A9 -> 原材料 | B27: ='明细汇总表F2-2'!I35+'明细汇总表F2-2'!I36 -> 0 | C27: ='明细汇总表F2-2'!K35+'明细汇总表F2-2'!K36 -> 0 | D27: ='明细汇总表F2-2'!L35+'明细汇总表F2-2'!L36 -> 0 | E27: ='明细汇总表F2-2'!N35+'明细汇总表F2-2'!N36 -> 0 | F27: ='明细汇总表F2-2'!O35+'明细汇总表F2-2'!O36 -> 0 | G27: ='明细汇总表F2-2'!P35+'明细汇总表F2-2'!P36 -> 0 | H27: =B27+C27+D27-E27-F27-G27 -> 0
A28: =A10 -> 自制半成品及在产品 | B28: ='明细汇总表F2-2'!I38+'明细汇总表F2-2'!I39+'明细汇总表F2-2'!I44 -> 0 | C28: ='明细汇总表F2-2'!K38+'明细汇总表F2-2'!K39+'明细汇总表F2-2'!K44 -> 0 | D28: ='明细汇总表F2-2'!L38+'明细汇总表F2-2'!L39+'明细汇总表F2-2'!L44 -> 0 | E28: ='明细汇总表F2-2'!N38+'明细汇总表F2-2'!N39+'明细汇总表F2-2'!N44 -> 0 | F28: ='明细汇总表F2-2'!O38+'明细汇总表F2-2'!O39+'明细汇总表F2-2'!O44 -> 0 | G28: ='明细汇总表F2-2'!P38+'明细汇总表F2-2'!P39+'明细汇总表F2-2'!P44 -> 0 | H28: =B28+C28+D28-E28-F28-G28 -> 0
A29: =A11 -> 其中：开发成本 | B29: ='明细汇总表F2-2'!I44 -> 0 | C29: ='明细汇总表F2-2'!K44 -> 0 | D29: ='明细汇总表F2-2'!L44 -> 0 | E29: ='明细汇总表F2-2'!N44 -> 0 | F29: ='明细汇总表F2-2'!O44 -> 0 | G29: ='明细汇总表F2-2'!P44 -> 0 | H29: =B29+C29+D29-E29-F29-G29 -> 0
A30: =A12 -> 委托加工物资 | B30: ='明细汇总表F2-2'!I40 -> 0 | C30: ='明细汇总表F2-2'!K40 -> 0 | D30: ='明细汇总表F2-2'!L40 -> 0 | E30: ='明细汇总表F2-2'!N40 -> 0 | F30: ='明细汇总表F2-2'!O40 -> 0 | G30: ='明细汇总表F2-2'!P40 -> 0 | H30: =B30+C30+D30-E30-F30-G30 -> 0
A31: =A13 -> 库存商品（产成品） | B31: ='明细汇总表F2-2'!I41 -> 0 | C31: ='明细汇总表F2-2'!K41 -> 0 | D31: ='明细汇总表F2-2'!L41 -> 0 | E31: ='明细汇总表F2-2'!N41 -> 0 | F31: ='明细汇总表F2-2'!O41 -> 0 | G31: ='明细汇总表F2-2'!P41 -> 0 | H31: =B31+C31+D31-E31-F31-G31 -> 0
A32: =A14 -> 其中：开发产品 | B32: ='明细汇总表F2-2'!I43 -> 0 | C32: ='明细汇总表F2-2'!K43 -> 0 | D32: ='明细汇总表F2-2'!L43 -> 0 | E32: ='明细汇总表F2-2'!N43 -> 0 | F32: ='明细汇总表F2-2'!O43 -> 0 | G32: ='明细汇总表F2-2'!P43 -> 0 | H32: =B32+C32+D32-E32-F32-G32 -> 0
A33: =A15 -> 周转材料（包装物、低值易耗品等） | B33: ='明细汇总表F2-2'!I37 -> 0 | C33: ='明细汇总表F2-2'!K37 -> 0 | D33: ='明细汇总表F2-2'!L37 -> 0 | E33: ='明细汇总表F2-2'!N37 -> 0 | F33: ='明细汇总表F2-2'!O37 -> 0 | G33: ='明细汇总表F2-2'!P37 -> 0 | H33: =B33+C33+D33-E33-F33-G33 -> 0
A34: =A16 -> 发出商品 | B34: ='明细汇总表F2-2'!I42 -> 0 | C34: ='明细汇总表F2-2'!K42 -> 0 | D34: ='明细汇总表F2-2'!L42 -> 0 | E34: ='明细汇总表F2-2'!N42 -> 0 | F34: ='明细汇总表F2-2'!O42 -> 0 | G34: ='明细汇总表F2-2'!P42 -> 0 | H34: =B34+C34+D34-E34-F34-G34 -> 0
A35: =A17 -> 消耗性生物资产 | B35: ='明细汇总表F2-2'!I46 -> 0 | C35: ='明细汇总表F2-2'!K46 -> 0 | D35: ='明细汇总表F2-2'!L46 -> 0 | E35: ='明细汇总表F2-2'!N46 -> 0 | F35: ='明细汇总表F2-2'!O46 -> 0 | G35: ='明细汇总表F2-2'!P46 -> 0 | H35: =B35+C35+D35-E35-F35-G35 -> 0
A36: =A18 -> 合同履约成本 | B36: ='明细汇总表F2-2'!I45 -> 0 | C36: ='明细汇总表F2-2'!K45 -> 0 | D36: ='明细汇总表F2-2'!L45 -> 0 | E36: ='明细汇总表F2-2'!N45 -> 0 | F36: ='明细汇总表F2-2'!O45 -> 0 | G36: ='明细汇总表F2-2'!P45 -> 0 | H36: =B36+C36+D36-E36-F36-G36 -> 0
A37: 数据资源 | B37: ='明细汇总表F2-2'!I47 -> 0 | C37: ='明细汇总表F2-2'!K47 -> 0 | D37: ='明细汇总表F2-2'!L47 -> 0 | E37: ='明细汇总表F2-2'!N47 -> 0 | F37: ='明细汇总表F2-2'!O47 -> 0 | G37: ='明细汇总表F2-2'!P47 -> 0 | H37: =B37+C37+D37-E37-F37-G37 -> 0
A38: =A20 -> 其他
A39: 其中：尚未开发的土地储备(由房地产开发企业填列）
A40: 合 计 | B40: =SUM(B27:B39)-B29-B32-B39 -> 0 | C40: =SUM(C27:C39)-C29-C32-C39 -> 0 | D40: =SUM(D27:D39)-D29-D32-D39 -> 0 | E40: =SUM(E27:E39)-E29-E32-E39 -> 0 | F40: =SUM(F27:F39)-F29-F32-F39 -> 0 | G40: =SUM(G27:G39)-G29-G32-G39 -> 0 | H40: =SUM(H27:H39)-H29-H32-H39 -> 0
A41: （3）借款费用资本化
A42: 存货期末余额中含有借款费用资本化金额为XXX元。
A43: （4）合同履约成本本期摊销金额的说明

Sheet 明细汇总表F2-2
A1: 致同会计师事务所
A2: 存货明细汇总表
A3: =底稿目录!A2 -> 被审计单位： | F3: =底稿目录!A4 -> 编制人： | K3: =底稿目录!A5 -> 编制日期： | P3: 索引号： | Q3: =底稿目录!F7 -> F2-2
A4: =底稿目录!A3 -> 截止日：202X年12月21日 | F4: =底稿目录!A6 -> 复核人： | K4: =底稿目录!A7 -> 复核日期： | P4: 页 次：
A5: 一、审计目标：
A6: 1.资产负债表中记录的存货是存在的，且已经记录在恰当的账户中
A7: 2.所有应记录的存货均已记录，所有应当包括在财务报表中的相关披露均已包括
A8: 3.存货以恰当的金额包括在财务报表中，与之相关的计价或分摊调整已恰当记录，相关披露已得到恰当计量和描述
A9: 二、审计过程：
A10: 1.获取或编制存货（收发存）数量金额式明细表，复核加计正确，与总账、明细账合计数核对是否相符，期初余额与上期审定期末余额是否相符；
A11: 2.抽查核对存货收发存明细账是否与仓储台账（ERP业务数据）、卡片记录相符（双向核对），存货是否及时入账，存货编号存在漏记、重复等；
A12: 3.检查存货明细表中是否有异常或负余额（包括数量为负或金额为负）的项目；
A13: 4.获取管理层编制的存货库龄分析表，检查库龄划分是否正确；检查有无长期挂账的存货，如有，应查明原因，必要时作调整。
A14: （一）原值
A15: 项目 | B15: 未审数 | F15: 期初调整 | G15: 期末调整 | I15: 审定数 | M15: 备注 | N15: 索引号
B16: 期初余额 | C16: 本期增加 | D16: 本期减少 | E16: 期末数 | G16: 本期增加 | H16: 本期减少 | I16: 期初余额 | J16: 本期增加 | K16: 本期减少 | L16: 期末数
A17: 原材料 | B17: ='一、原材料明细表F2-3'!$G$25 -> 0 | C17: ='一、原材料明细表F2-3'!$J$25 -> 0 | D17: ='一、原材料明细表F2-3'!$M$25 -> 0 | E17: =B17+C17-D17 -> 0 | I17: =B17+F17 -> 0 | J17: =C17+G17 -> 0 | K17: =D17+H17 -> 0 | L17: =I17+J17-K17 -> 0
A18: 材料采购/在途物资 | B18: ='二、材料采购、在途物资明细表F2-4'!$F$25 -> 0 | C18: ='二、材料采购、在途物资明细表F2-4'!$I$25 -> 0 | D18: ='二、材料采购、在途物资明细表F2-4'!$L$25 -> 0 | E18: =B18+C18-D18 -> 0 | I18: =B18+F18 -> 0 | J18: =C18+G18 -> 0 | K18: =D18+H18 -> 0 | L18: =I18+J18-K18 -> 0
A19: 周转材料/低值易耗品/包装物 | B19: ='三、周转材料、低值易耗品，包装物明细表F2-5'!$G$27 -> 0 | C19: ='三、周转材料、低值易耗品，包装物明细表F2-5'!$J$27 -> 0 | D19: ='三、周转材料、低值易耗品，包装物明细表F2-5'!$M$27 -> 0 | E19: =B19+C19-D19 -> 0 | I19: =B19+F19 -> 0 | J19: =C19+G19 -> 0 | K19: =D19+H19 -> 0 | L19: =I19+J19-K19 -> 0
A20: 在产品 | E20: =B20+C20-D20 -> 0 | I20: =B20+F20 -> 0 | J20: =C20+G20 -> 0 | K20: =D20+H20 -> 0 | L20: =I20+J20-K20 -> 0
A21: 自制半成品 | B21: ='四、自制半成品明细表F2-6'!$G$25 -> 0 | C21: ='四、自制半成品明细表F2-6'!$J$25 -> 0 | D21: ='四、自制半成品明细表F2-6'!$M$25 -> 0 | E21: =B21+C21-D21 -> 0 | I21: =B21+F21 -> 0 | J21: =C21+G21 -> 0 | K21: =D21+H21 -> 0 | L21: =I21+J21-K21 -> 0
A22: 委托加工物资 | E22: =B22+C22-D22 -> 0 | I22: =B22+F22 -> 0 | J22: =C22+G22 -> 0 | K22: =D22+H22 -> 0 | L22: =I22+J22-K22 -> 0
A23: 库存商品 | B23: ='六、库存商品明细表F2-8'!$G$25 -> 0 | C23: ='六、库存商品明细表F2-8'!$J$25 -> 0 | D23: ='六、库存商品明细表F2-8'!$M$25 -> 0 | E23: =B23+C23-D23 -> 0 | I23: =B23+F23 -> 0 | J23: =C23+G23 -> 0 | K23: =D23+H23 -> 0 | L23: =I23+J23-K23 -> 0
A24: 发出商品 | B24: ='七、发出商品F2-9'!$F$25 -> 0 | C24: ='七、发出商品F2-9'!$I$25 -> 0 | D24: ='七、发出商品F2-9'!$L$25 -> 0 | E24: =B24+C24-D24 -> 0 | I24: =B24+F24 -> 0 | J24: =C24+G24 -> 0 | K24: =D24+H24 -> 0 | L24: =I24+J24-K24 -> 0
A25: 开发产品 | B25: ='八、开发产品F2-10'!$H$19 -> 0 | C25: ='八、开发产品F2-10'!$O$19 -> 0 | D25: ='八、开发产品F2-10'!$R$19 -> 0 | E25: =B25+C25-D25 -> 0 | F25: ='八、开发产品F2-10'!I19+'八、开发产品F2-10'!J19 -> 0 | G25: ='八、开发产品F2-10'!V19+'八、开发产品F2-10'!W19 -> 0 | I25: =B25+F25 -> 0 | J25: =C25+G25 -> 0 | K25: =D25+H25 -> 0 | L25: =I25+J25-K25 -> 0
A26: 开发成本 | B26: ='九、开发成本F2-11'!G19 -> 0 | C26: ='九、开发成本F2-11'!H19 -> 0 | D26: ='九、开发成本F2-11'!I19 -> 0 | E26: =B26+C26-D26 -> 0 | F26: ='九、开发成本F2-11'!K19+'九、开发成本F2-11'!L19 -> 0 | G26: ='九、开发成本F2-11'!M19+'九、开发成本F2-11'!O19 -> 0 | H26: ='九、开发成本F2-11'!N19+'九、开发成本F2-11'!P19 -> 0 | I26: =B26+F26 -> 0 | J26: =C26+G26 -> 0 | K26: =D26+H26 -> 0 | L26: =I26+J26-K26 -> 0
A27: 合同履约成本 | B27: ='十、合同履约成本F2-12'!F20 -> 0 | C27: ='十、合同履约成本F2-12'!G20 -> 0 | D27: ='十、合同履约成本F2-12'!H20 -> 0 | E27: =B27+C27-D27 -> 0 | I27: =B27+F27 -> 0 | J27: =C27+G27 -> 0 | K27: =D27+H27 -> 0 | L27: =I27+J27-K27 -> 0
A28: 消耗性生物资产 | B28: ='十一、消耗性生物资产F2-13'!$F$25 -> 0 | C28: ='十一、消耗性生物资产F2-13'!$I$25 -> 0 | D28: ='十一、消耗性生物资产F2-13'!$L$25 -> 0 | E28: =B28+C28-D28 -> 0 | I28: =B28+F28 -> 0 | J28: =C28+G28 -> 0 | K28: =D28+H28 -> 0 | L28: =I28+J28-K28 -> 0
A29: 数据资源 | E29: =B29+C29-D29 -> 0 | I29: =B29+F29 -> 0 | J29: =C29+G29 -> 0 | K29: =D29+H29 -> 0 | L29: =I29+J29-K29 -> 0
A30: …… | E30: =B30+C30-D30 -> 0 | I30: =B30+F30 -> 0 | J30: =C30+G30 -> 0 | K30: =D30+H30 -> 0 | L30: =I30+J30-K30 -> 0
A31: 合计 | B31: =SUM(B17:B30) -> 0 | C31: =SUM(C17:C30) -> 0 | D31: =SUM(D17:D30) -> 0 | E31: =SUM(E17:E30) -> 0 | F31: =SUM(F17:F30) -> 0 | G31: =SUM(G17:G30) -> 0 | H31: =SUM(H17:H30) -> 0 | I31: =SUM(I17:I30) -> 0 | ... L31: =SUM(L17:L30) -> 0
A32: （二）跌价准备
A33: 项目 | B33: 未审数 | F33: 期初调整 | G33: 期末调整 | I33: 审定数
B34: 期初余额 | C34: 本期增加 | D34: 本期减少 | E34: 期末数 | G34: 本期增加 | H34: 本期减少 | I34: 期初余额 | J34: 本期增加 | K34: 其中：(1)计提 | L34: (2)其他 | M34: 本期减少 | N34: 其中：(1)转回 | O34: (2)转销 | P34: (3)其他 | Q34: 期末数
A35: 原材料 | B35: ='一、原材料明细表F2-3'!G26 -> 0 | C35: ='一、原材料明细表F2-3'!J26 -> 0 | D35: ='一、原材料明细表F2-3'!M26 -> 0 | E35: =B35+C35-D35 -> 0 | I35: =B35+F35 -> 0 | J35: =C35+G35 -> 0 | L35: =J35-K35 -> 0 | M35: =D35+H35 -> 0 | P35: =M35-N35-O35 -> 0 | Q35: =I35+J35-M35 -> 0
A36: 材料采购/在途物资 | B36: ='二、材料采购、在途物资明细表F2-4'!F26 -> 0 | C36: ='二、材料采购、在途物资明细表F2-4'!I26 -> 0 | D36: ='二、材料采购、在途物资明细表F2-4'!L26 -> 0 | E36: =B36+C36-D36 -> 0 | I36: =B36+F36 -> 0 | J36: =C36+G36 -> 0 | L36: =J36-K36 -> 0 | M36: =D36+H36 -> 0 | P36: =M36-N36-O36 -> 0 | Q36: =I36+J36-M36 -> 0
A37: 周转材料/低值易耗品/包装物 | B37: ='三、周转材料、低值易耗品，包装物明细表F2-5'!G28 -> 0 | C37: ='三、周转材料、低值易耗品，包装物明细表F2-5'!J28 -> 0 | D37: ='三、周转材料、低值易耗品，包装物明细表F2-5'!M28 -> 0 | E37: =B37+C37-D37 -> 0 | I37: =B37+F37 -> 0 | J37: =C37+G37 -> 0 | L37: =J37-K37 -> 0 | M37: =D37+H37 -> 0 | P37: =M37-N37-O37 -> 0 | Q37: =I37+J37-M37 -> 0
A38: 在产品 | E38: =B38+C38-D38 -> 0 | I38: =B38+F38 -> 0 | J38: =C38+G38 -> 0 | L38: =J38-K38 -> 0 | M38: =D38+H38 -> 0 | P38: =M38-N38-O38 -> 0 | Q38: =I38+J38-M38 -> 0
A39: 自制半成品 | B39: ='四、自制半成品明细表F2-6'!G26 -> 0 | C39: ='四、自制半成品明细表F2-6'!J26 -> 0 | D39: ='四、自制半成品明细表F2-6'!M26 -> 0 | E39: =B39+C39-D39 -> 0 | I39: =B39+F39 -> 0 | J39: =C39+G39 -> 0 | L39: =J39-K39 -> 0 | M39: =D39+H39 -> 0 | P39: =M39-N39-O39 -> 0 | Q39: =I39+J39-M39 -> 0
A40: 委托加工物资 | E40: =B40+C40-D40 -> 0 | I40: =B40+F40 -> 0 | J40: =C40+G40 -> 0 | L40: =J40-K40 -> 0 | M40: =D40+H40 -> 0 | P40: =M40-N40-O40 -> 0 | Q40: =I40+J40-M40 -> 0
A41: 库存商品 | B41: ='六、库存商品明细表F2-8'!G26 -> 0 | C41: ='六、库存商品明细表F2-8'!J26 -> 0 | D41: ='六、库存商品明细表F2-8'!M26 -> 0 | E41: =B41+C41-D41 -> 0 | I41: =B41+F41 -> 0 | J41: =C41+G41 -> 0 | L41: =J41-K41 -> 0 | M41: =D41+H41 -> 0 | P41: =M41-N41-O41 -> 0 | Q41: =I41+J41-M41 -> 0
A42: 发出商品 | B42: ='七、发出商品F2-9'!F26 -> 0 | C42: ='七、发出商品F2-9'!I26 -> 0 | D42: ='七、发出商品F2-9'!L26 -> 0 | E42: =B42+C42-D42 -> 0 | I42: =B42+F42 -> 0 | J42: =C42+G42 -> 0 | L42: =J42-K42 -> 0 | M42: =D42+H42 -> 0 | P42: =M42-N42-O42 -> 0 | Q42: =I42+J42-M42 -> 0
A43: 开发产品 | B43: ='八、开发产品F2-10'!F33 -> 0 | C43: ='八、开发产品F2-10'!G33 -> 0 | D43: ='八、开发产品F2-10'!H33 -> 0 | E43: =B43+C43-D43 -> 0 | F43: ='八、开发产品F2-10'!J33+'八、开发产品F2-10'!K33 -> 0 | G43: ='八、开发产品F2-10'!L33+'八、开发产品F2-10'!N33 -> 0 | H43: ='八、开发产品F2-10'!M33+'八、开发产品F2-10'!O33 -> 0 | I43: =B43+F43 -> 0 | J43: =C43+G43 -> 0 | L43: =J43-K43 -> 0 | M43: =D43+H43 -> 0 | P43: =M43-N43-O43 -> 0 | Q43: =I43+J43-M43 -> 0
A44: 开发成本 | B44: ='九、开发成本F2-11'!G33 -> 0 | C44: ='九、开发成本F2-11'!H33 -> 0 | D44: ='九、开发成本F2-11'!I33 -> 0 | E44: =B44+C44-D44 -> 0 | F44: ='九、开发成本F2-11'!K33+'九、开发成本F2-11'!L33 -> 0 | G44: ='九、开发成本F2-11'!M33+'九、开发成本F2-11'!O33 -> 0 | H44: ='九、开发成本F2-11'!N33+'九、开发成本F2-11'!P33 -> 0 | I44: =B44+F44 -> 0 | J44: =C44+G44 -> 0 | L44: =J44-K44 -> 0 | M44: =D44+H44 -> 0 | P44: =M44-N44-O44 -> 0 | Q44: =I44+J44-M44 -> 0
A45: 合同履约成本 | B45: ='十、合同履约成本F2-12'!F21 -> 0 | C45: ='十、合同履约成本F2-12'!G21 -> 0 | D45: ='十、合同履约成本F2-12'!H21 -> 0 | E45: =B45+C45-D45 -> 0 | I45: =B45+F45 -> 0 | J45: =C45+G45 -> 0 | L45: =J45-K45 -> 0 | M45: =D45+H45 -> 0 | P45: =M45-N45-O45 -> 0 | Q45: =I45+J45-M45 -> 0
A46: 消耗性生物资产 | B46: ='十一、消耗性生物资产F2-13'!$C$40 -> 0 | C46: ='十一、消耗性生物资产F2-13'!$D$40 -> 0 | D46: ='十一、消耗性生物资产F2-13'!$E$40 -> 0 | E46: =B46+C46-D46 -> 0 | F46: ='十一、消耗性生物资产F2-13'!G40+'十一、消耗性生物资产F2-13'!H40 -> 0 | G46: ='十一、消耗性生物资产F2-13'!I40+'十一、消耗性生物资产F2-13'!K40 -> 0 | H46: ='十一、消耗性生物资产F2-13'!J40+'十一、消耗性生物资产F2-13'!L40 -> 0 | I46: =B46+F46 -> 0 | J46: =C46+G46 -> 0 | L46: =J46-K46 -> 0 | M46: =D46+H46 -> 0 | P46: =M46-N46-O46 -> 0 | Q46: =I46+J46-M46 -> 0
A47: 数据资源 | E47: =B47+C47-D47 -> 0 | I47: =B47+F47 -> 0 | J47: =C47+G47 -> 0 | L47: =J47-K47 -> 0 | M47: =D47+H47 -> 0 | P47: =M47-N47-O47 -> 0 | Q47: =I47+J47-M47 -> 0
A48: …… | E48: =B48+C48-D48 -> 0 | I48: =B48+F48 -> 0 | J48: =C48+G48 -> 0 | L48: =J48-K48 -> 0 | M48: =D48+H48 -> 0 | P48: =M48-N48-O48 -> 0 | Q48: =I48+J48-M48 -> 0
A49: 合计 | B49: =SUM(B35:B48) -> 0 | C49: =SUM(C35:C48) -> 0 | D49: =SUM(D35:D48) -> 0 | E49: =SUM(E35:E48) -> 0 | F49: =SUM(F35:F48) -> 0 | G49: =SUM(G35:G48) -> 0 | H49: =SUM(H35:H48) -> 0 | I49: =SUM(I35:I48) -> 0 | ... Q49: =SUM(Q35:Q48) -> 0
A50: （三）账面价值
A51: 项目 | B51: 未审数 | D51: 审定数 | F51: 变动率 | H51: 变动原因分析 | I51: 确定可变现净值的具体依据 | J51: 本期转回或转销存货跌价准备的原因 | K51: 索引号
B52: 期初数 | C52: 期末数 | D52: 期初数 | E52: 期末数 | F52: 未审变动率 | G52: 审定变动率
A53: 原材料 | B53: =B17-B35 -> 0 | C53: =E17-E35 -> 0 | D53: =I17-I35 -> 0 | E53: =L17-Q35 -> 0 | F53: =IF(B53=0,0,(C53-B53)/B53) -> 0 | G53: =IF(D53=0,0,(E53-D53)/D53) -> 0
A54: 材料采购/在途物资 | B54: =B18-B36 -> 0 | C54: =E18-E36 -> 0 | D54: =I18-I36 -> 0 | E54: =L18-Q36 -> 0 | F54: =IF(B54=0,0,(C54-B54)/B54) -> 0 | G54: =IF(D54=0,0,(E54-D54)/D54) -> 0
A55: 周转材料/低值易耗品/包装物 | B55: =B19-B37 -> 0 | C55: =E19-E37 -> 0 | D55: =I19-I37 -> 0 | E55: =L19-Q37 -> 0 | F55: =IF(B55=0,0,(C55-B55)/B55) -> 0 | G55: =IF(D55=0,0,(E55-D55)/D55) -> 0
A56: 在产品 | B56: =B20-B38 -> 0 | C56: =E20-E38 -> 0 | D56: =I20-I38 -> 0 | E56: =L20-Q38 -> 0 | F56: =IF(B56=0,0,(C56-B56)/B56) -> 0 | G56: =IF(D56=0,0,(E56-D56)/D56) -> 0
A57: 自制半成品 | B57: =B21-B39 -> 0 | C57: =E21-E39 -> 0 | D57: =I21-I39 -> 0 | E57: =L21-Q39 -> 0 | F57: =IF(B57=0,0,(C57-B57)/B57) -> 0 | G57: =IF(D57=0,0,(E57-D57)/D57) -> 0
A58: 委托加工物资 | B58: =B22-B40 -> 0 | C58: =E22-E40 -> 0 | D58: =I22-I40 -> 0 | E58: =L22-Q40 -> 0 | F58: =IF(B58=0,0,(C58-B58)/B58) -> 0 | G58: =IF(D58=0,0,(E58-D58)/D58) -> 0
A59: 库存商品 | B59: =B23-B41 -> 0 | C59: =E23-E41 -> 0 | D59: =I23-I41 -> 0 | E59: =L23-Q41 -> 0 | F59: =IF(B59=0,0,(C59-B59)/B59) -> 0 | G59: =IF(D59=0,0,(E59-D59)/D59) -> 0
A60: 发出商品 | B60: =B24-B42 -> 0 | C60: =E24-E42 -> 0 | D60: =I24-I42 -> 0 | E60: =L24-Q42 -> 0 | F60: =IF(B60=0,0,(C60-B60)/B60) -> 0 | G60: =IF(D60=0,0,(E60-D60)/D60) -> 0
A61: 开发产品 | B61: =B25-B43 -> 0 | C61: =E25-E43 -> 0 | D61: =I25-I43 -> 0 | E61: =L25-Q43 -> 0 | F61: =IF(B61=0,0,(C61-B61)/B61) -> 0 | G61: =IF(D61=0,0,(E61-D61)/D61) -> 0
A62: 开发成本 | B62: =B26-B44 -> 0 | C62: =E26-E44 -> 0 | D62: =I26-I44 -> 0 | E62: =L26-Q44 -> 0 | F62: =IF(B62=0,0,(C62-B62)/B62) -> 0 | G62: =IF(D62=0,0,(E62-D62)/D62) -> 0
A63: 合同履约成本 | B63: =B27-B45 -> 0 | C63: =E27-E45 -> 0 | D63: =I27-I45 -> 0 | E63: =L27-Q45 -> 0 | F63: =IF(B63=0,0,(C63-B63)/B63) -> 0 | G63: =IF(D63=0,0,(E63-D63)/D63) -> 0
A64: 消耗性生物资产 | B64: =B28-B46 -> 0 | C64: =E28-E46 -> 0 | D64: =I28-I46 -> 0 | E64: =L28-Q46 -> 0 | F64: =IF(B64=0,0,(C64-B64)/B64) -> 0 | G64: =IF(D64=0,0,(E64-D64)/D64) -> 0
... A66: …… | B66: =B30-B48 -> 0 | C66: =E30-E48 -> 0 | D66: =I30-I48 -> 0 | E66: =L30-Q48 -> 0 | F66: =IF(B66=0,0,(C66-B66)/B66) -> 0 | G66: =IF(D66=0,0,(E66-D66)/D66) -> 0
A67: 合计 | B67: =SUM(B53:B66) -> 0 | C67: =SUM(C53:C66) -> 0 | D67: =SUM(D53:D66) -> 0 | E67: =SUM(E53:E66) -> 0 | F67: =IF(B67=0,0,(C67-B67)/B67) -> 0 | G67: =IF(D67=0,0,(E67-D67)/D67) -> 0
A68: 三、审计说明：
A70: 四、审计结论：
A74: 提示：
A75: 1.审计说明可以概述：（1）程序的测试情况、结果；（2）拟调整事项及其调整分录、未调整事项及其影响，审计范围受到限制情况及其影响。
A76: 2.审计结论可参考：A、未见异常。 B、除上述重大不符事项应当作为调整事项予以调整外，其余未见异常。 C、由于存在以下重大未调整事项（或审计范围受到限制无法获取充分、适当证据），不可确认。

Sheet 一、原材料明细表F2-3
A1: 致同会计师事务所
A2: 存货明细表
A3: =底稿目录!A2 -> 被审计单位： | F3: =底稿目录!A4 -> 编制人： | M3: =底稿目录!A5 -> 编制日期： | T3: 索引号： | U3: =底稿目录!F8 -> F2-3
A4: =底稿目录!A3 -> 截止日：202X年12月21日 | F4: =底稿目录!A6 -> 复核人： | M4: =底稿目录!A7 -> 复核日期： | T4: 页次：
A5: 一、原材料明细表
A6: 存货编码 | B6: 存货名称 | C6: 规格 | D6: 单位 | E6: 期初库存 | H6: 本期购进 | K6: 本期发出 | N6: 期末结存 | Q6: 库龄 | U6: 品质状况（正常、残次、毁损、滞销等）
E7: 数量 | F7: 单价 | G7: 金额 | H7: 数量 | I7: 单价 | J7: 金额 | K7: 数量 | L7: 单价 | M7: 金额 | N7: 数量 | O7: 单价 | P7: 金额 | Q7: 1年以内 | R7: 1-2年 | S7: 2-3年 | T7: 3年以上
F9: =IF(E9=0,0,G9/E9) -> 0 | I9: =IF(H9=0,0,J9/H9) -> 0 | L9: =IF(K9=0,0,M9/K9) -> 0 | N9: =E9+H9-K9 -> 0 | O9: =IF(N9=0,0,P9/N9) -> 0 | P9: =G9+J9-M9 -> 0
F10: =IF(E10=0,0,G10/E10) -> 0 | I10: =IF(H10=0,0,J10/H10) -> 0 | L10: =IF(K10=0,0,M10/K10) -> 0 | N10: =E10+H10-K10 -> 0 | O10: =IF(N10=0,0,P10/N10) -> 0 | P10: =G10+J10-M10 -> 0
F11: =IF(E11=0,0,G11/E11) -> 0 | I11: =IF(H11=0,0,J11/H11) -> 0 | L11: =IF(K11=0,0,M11/K11) -> 0 | N11: =E11+H11-K11 -> 0 | O11: =IF(N11=0,0,P11/N11) -> 0 | P11: =G11+J11-M11 -> 0
F12: =IF(E12=0,0,G12/E12) -> 0 | I12: =IF(H12=0,0,J12/H12) -> 0 | L12: =IF(K12=0,0,M12/K12) -> 0 | N12: =E12+H12-K12 -> 0 | O12: =IF(N12=0,0,P12/N12) -> 0 | P12: =G12+J12-M12 -> 0
F13: =IF(E13=0,0,G13/E13) -> 0 | I13: =IF(H13=0,0,J13/H13) -> 0 | L13: =IF(K13=0,0,M13/K13) -> 0 | N13: =E13+H13-K13 -> 0 | O13: =IF(N13=0,0,P13/N13) -> 0 | P13: =G13+J13-M13 -> 0
F14: =IF(E14=0,0,G14/E14) -> 0 | I14: =IF(H14=0,0,J14/H14) -> 0 | L14: =IF(K14=0,0,M14/K14) -> 0 | N14: =E14+H14-K14 -> 0 | O14: =IF(N14=0,0,P14/N14) -> 0 | P14: =G14+J14-M14 -> 0
F15: =IF(E15=0,0,G15/E15) -> 0 | I15: =IF(H15=0,0,J15/H15) -> 0 | L15: =IF(K15=0,0,M15/K15) -> 0 | N15: =E15+H15-K15 -> 0 | O15: =IF(N15=0,0,P15/N15) -> 0 | P15: =G15+J15-M15 -> 0
F16: =IF(E16=0,0,G16/E16) -> 0 | I16: =IF(H16=0,0,J16/H16) -> 0 | L16: =IF(K16=0,0,M16/K16) -> 0 | N16: =E16+H16-K16 -> 0 | O16: =IF(N16=0,0,P16/N16) -> 0 | P16: =G16+J16-M16 -> 0
F17: =IF(E17=0,0,G17/E17) -> 0 | I17: =IF(H17=0,0,J17/H17) -> 0 | L17: =IF(K17=0,0,M17/K17) -> 0 | N17: =E17+H17-K17 -> 0 | O17: =IF(N17=0,0,P17/N17) -> 0 | P17: =G17+J17-M17 -> 0
F18: =IF(E18=0,0,G18/E18) -> 0 | I18: =IF(H18=0,0,J18/H18) -> 0 | L18: =IF(K18=0,0,M18/K18) -> 0 | N18: =E18+H18-K18 -> 0 | O18: =IF(N18=0,0,P18/N18) -> 0 | P18: =G18+J18-M18 -> 0
F19: =IF(E19=0,0,G19/E19) -> 0 | I19: =IF(H19=0,0,J19/H19) -> 0 | L19: =IF(K19=0,0,M19/K19) -> 0 | N19: =E19+H19-K19 -> 0 | O19: =IF(N19=0,0,P19/N19) -> 0 | P19: =G19+J19-M19 -> 0
F20: =IF(E20=0,0,G20/E20) -> 0 | I20: =IF(H20=0,0,J20/H20) -> 0 | L20: =IF(K20=0,0,M20/K20) -> 0 | N20: =E20+H20-K20 -> 0 | O20: =IF(N20=0,0,P20/N20) -> 0 | P20: =G20+J20-M20 -> 0
... F23: =IF(E23=0,0,G23/E23) -> 0 | I23: =IF(H23=0,0,J23/H23) -> 0 | L23: =IF(K23=0,0,M23/K23) -> 0 | N23: =E23+H23-K23 -> 0 | O23: =IF(N23=0,0,P23/N23) -> 0 | P23: =G23+J23-M23 -> 0
B24: …… | F24: =IF(E24=0,0,G24/E24) -> 0 | I24: =IF(H24=0,0,J24/H24) -> 0 | L24: =IF(K24=0,0,M24/K24) -> 0 | N24: =E24+H24-K24 -> 0 | O24: =IF(N24=0,0,P24/N24) -> 0 | P24: =G24+J24-M24 -> 0
B25: 合计 | E25: -- | F25: -- | G25: =SUM(G9:G24) -> 0 | H25: -- | I25: -- | J25: =SUM(J9:J24) -> 0 | K25: -- | L25: -- | M25: =SUM(M9:M24) -> 0 | N25: -- | O25: -- | P25: =SUM(P9:P24) -> 0 | Q25: =SUM(Q9:Q24) -> 0 | R25: =SUM(R9:R24) -> 0 | S25: =SUM(S9:S24) -> 0 | T25: =SUM(T9:T24) -> 0
B26: 减：存货跌价准备
B27: 原材料净额 | E27: -- | F27: -- | G27: =G25-G26 -> 0 | H27: -- | I27: -- | J27: =J25-J26 -> 0 | K27: -- | L27: -- | M27: =M25-M26 -> 0 | N27: -- | O27: -- | P27: =P25-P26 -> 0 | Q27: =Q25-Q26 -> 0 | R27: =R25-R26 -> 0 | S27: =S25-S26 -> 0 | T27: =T25-T26 -> 0
A28: 审计说明： | P28: =IF((P25-Q25-R25-S25-T25)=0,"OK","库龄与期末金额不匹配") -> OK
A29: 1.原材料计价方法： | J29: 3.原材料——**库龄较长的原因：
A30: 2.原材料本期发生重大变动的原因： | J30: 4.计提跌价准备的主要项目及原因：

Sheet 二、材料采购、在途物资明细表F2-4
A1: 致同会计师事务所
A2: 存货明细表
A3: =底稿目录!A2 -> 被审计单位： | F3: =底稿目录!A4 -> 编制人： | N3: =底稿目录!A5 -> 编制日期： | V3: 索引号： | W3: =底稿目录!F9 -> F2-4
A4: =底稿目录!A3 -> 截止日：202X年12月21日 | F4: =底稿目录!A6 -> 复核人： | N4: =底稿目录!A7 -> 复核日期： | V4: 页次：
A5: 二、材料采购/在途物资明细表
A6: 供货单位 | B6: 采购物资名称及规格 | C6: 单位 | D6: 期初库存 | G6: 本期购进 | J6: 本期转出 | M6: 期末结存 | P6: 期后结转 | S6: 库龄 | W6: 品质状况（正常、残次、毁损、滞销等）
D7: 数量 | E7: 单价 | F7: 金额 | G7: 数量 | H7: 单价 | I7: 金额 | J7: 数量 | K7: 单价 | L7: 金额 | M7: 数量 | N7: 单价 | O7: 金额 | P7: 数量 | Q7: 单价 | R7: 金额 | S7: 1年以内 | T7: 1-2年 | U7: 2-3年 | V7: 3年以上
E9: =IF(D9=0,0,F9/D9) -> 0 | H9: =IF(G9=0,0,I9/G9) -> 0 | K9: =IF(J9=0,0,L9/J9) -> 0 | M9: =D9+G9-J9 -> 0 | N9: =IF(M9=0,0,O9/M9) -> 0 | O9: =F9+I9-L9 -> 0 | Q9: =IF(P9=0,0,R9/P9) -> 0
E10: =IF(D10=0,0,F10/D10) -> 0 | H10: =IF(G10=0,0,I10/G10) -> 0 | K10: =IF(J10=0,0,L10/J10) -> 0 | M10: =D10+G10-J10 -> 0 | N10: =IF(M10=0,0,O10/M10) -> 0 | O10: =F10+I10-L10 -> 0 | Q10: =IF(P10=0,0,R10/P10) -> 0
E11: =IF(D11=0,0,F11/D11) -> 0 | H11: =IF(G11=0,0,I11/G11) -> 0 | K11: =IF(J11=0,0,L11/J11) -> 0 | M11: =D11+G11-J11 -> 0 | N11: =IF(M11=0,0,O11/M11) -> 0 | O11: =F11+I11-L11 -> 0 | Q11: =IF(P11=0,0,R11/P11) -> 0
E12: =IF(D12=0,0,F12/D12) -> 0 | H12: =IF(G12=0,0,I12/G12) -> 0 | K12: =IF(J12=0,0,L12/J12) -> 0 | M12: =D12+G12-J12 -> 0 | N12: =IF(M12=0,0,O12/M12) -> 0 | O12: =F12+I12-L12 -> 0 | Q12: =IF(P12=0,0,R12/P12) -> 0
E13: =IF(D13=0,0,F13/D13) -> 0 | H13: =IF(G13=0,0,I13/G13) -> 0 | K13: =IF(J13=0,0,L13/J13) -> 0 | M13: =D13+G13-J13 -> 0 | N13: =IF(M13=0,0,O13/M13) -> 0 | O13: =F13+I13-L13 -> 0 | Q13: =IF(P13=0,0,R13/P13) -> 0
E14: =IF(D14=0,0,F14/D14) -> 0 | H14: =IF(G14=0,0,I14/G14) -> 0 | K14: =IF(J14=0,0,L14/J14) -> 0 | M14: =D14+G14-J14 -> 0 | N14: =IF(M14=0,0,O14/M14) -> 0 | O14: =F14+I14-L14 -> 0 | Q14: =IF(P14=0,0,R14/P14) -> 0
E15: =IF(D15=0,0,F15/D15) -> 0 | H15: =IF(G15=0,0,I15/G15) -> 0 | K15: =IF(J15=0,0,L15/J15) -> 0 | M15: =D15+G15-J15 -> 0 | N15: =IF(M15=0,0,O15/M15) -> 0 | O15: =F15+I15-L15 -> 0 | Q15: =IF(P15=0,0,R15/P15) -> 0
E16: =IF(D16=0,0,F16/D16) -> 0 | H16: =IF(G16=0,0,I16/G16) -> 0 | K16: =IF(J16=0,0,L16/J16) -> 0 | M16: =D16+G16-J16 -> 0 | N16: =IF(M16=0,0,O16/M16) -> 0 | O16: =F16+I16-L16 -> 0 | Q16: =IF(P16=0,0,R16/P16) -> 0
E17: =IF(D17=0,0,F17/D17) -> 0 | H17: =IF(G17=0,0,I17/G17) -> 0 | K17: =IF(J17=0,0,L17/J17) -> 0 | M17: =D17+G17-J17 -> 0 | N17: =IF(M17=0,0,O17/M17) -> 0 | O17: =F17+I17-L17 -> 0 | Q17: =IF(P17=0,0,R17/P17) -> 0
E18: =IF(D18=0,0,F18/D18) -> 0 | H18: =IF(G18=0,0,I18/G18) -> 0 | K18: =IF(J18=0,0,L18/J18) -> 0 | M18: =D18+G18-J18 -> 0 | N18: =IF(M18=0,0,O18/M18) -> 0 | O18: =F18+I18-L18 -> 0 | Q18: =IF(P18=0,0,R18/P18) -> 0
E19: =IF(D19=0,0,F19/D19) -> 0 | H19: =IF(G19=0,0,I19/G19) -> 0 | K19: =IF(J19=0,0,L19/J19) -> 0 | M19: =D19+G19-J19 -> 0 | N19: =IF(M19=0,0,O19/M19) -> 0 | O19: =F19+I19-L19 -> 0 | Q19: =IF(P19=0,0,R19/P19) -> 0
E20: =IF(D20=0,0,F20/D20) -> 0 | H20: =IF(G20=0,0,I20/G20) -> 0 | K20: =IF(J20=0,0,L20/J20) -> 0 | M20: =D20+G20-J20 -> 0 | N20: =IF(M20=0,0,O20/M20) -> 0 | O20: =F20+I20-L20 -> 0 | Q20: =IF(P20=0,0,R20/P20) -> 0
... E23: =IF(D23=0,0,F23/D23) -> 0 | H23: =IF(G23=0,0,I23/G23) -> 0 | K23: =IF(J23=0,0,L23/J23) -> 0 | M23: =D23+G23-J23 -> 0 | N23: =IF(M23=0,0,O23/M23) -> 0 | O23: =F23+I23-L23 -> 0 | Q23: =IF(P23=0,0,R23/P23) -> 0
A24: …… | E24: =IF(D24=0,0,F24/D24) -> 0 | H24: =IF(G24=0,0,I24/G24) -> 0 | K24: =IF(J24=0,0,L24/J24) -> 0 | M24: =D24+G24-J24 -> 0 | N24: =IF(M24=0,0,O24/M24) -> 0 | O24: =F24+I24-L24 -> 0 | Q24: =IF(P24=0,0,R24/P24) -> 0
A25: 合计 | D25: -- | E25: -- | F25: =SUM(F9:F24) -> 0 | G25: -- | H25: -- | I25: =SUM(I9:I24) -> 0 | J25: -- | K25: -- | L25: =SUM(L9:L24) -> 0 | M25: -- | N25: -- | O25: =SUM(O9:O24) -> 0 | P25: -- | Q25: -- | R25: =SUM(R9:R24) -> 0 | S25: =SUM(S9:S24) -> 0 | T25: =SUM(T9:T24) -> 0 | U25: =SUM(U9:U24) -> 0 | V25: =SUM(V9:V24) -> 0
A26: 减：存货跌价准备
A27: 材料采购/在途物资净额 | D27: -- | E27: -- | F27: =F25-F26 -> 0 | G27: -- | H27: -- | I27: =I25-I26 -> 0 | J27: -- | K27: -- | L27: =L25-L26 -> 0 | M27: -- | N27: -- | O27: =O25-O26 -> 0 | P27: -- | Q27: -- | R27: =R25-R26 -> 0 | S27: =S25-S26 -> 0 | T27: =T25-T26 -> 0 | U27: =U25-U26 -> 0 | V27: =V25-V26 -> 0
A28: 审计说明： | O28: =IF((O25-S25-T25-U25-V25)=0,"OK","库龄与期末金额不匹配") -> OK
A29: 1.在途物资资产负债表日后入库情况： | J29: 3.物资采购/在途物资——**库龄较长的原因：
A30: 2.物资采购/在途物资本期发生重大变动的原因： | J30: 4.计提跌价准备的主要项目及原因：

Sheet 三、周转材料、低值易耗品，包装物明细表F2-5
A1: 致同会计师事务所
A2: 存货明细表
A3: =底稿目录!A2 -> 被审计单位： | G3: =底稿目录!A4 -> 编制人： | K3: =底稿目录!A5 -> 编制日期： | T3: 索引号： | U3: =底稿目录!F10 -> F2-5
A4: =底稿目录!A3 -> 截止日：202X年12月21日 | G4: =底稿目录!A6 -> 复核人： | K4: =底稿目录!A7 -> 复核日期： | T4: 页次：
A5: 三、周转材料/低值易耗品/包装物明细表
A6: 类别 | B6: 存货编码 | C6: 名称及规格 | D6: 单位 | E6: 期初库存 | H6: 本期购进 | K6: 本期发出 | N6: 期末结存 | Q6: 库龄 | U6: 品质状况（正常、残次、毁损、滞销等）
E7: 数量 | F7: 单价 | G7: 金额 | H7: 数量 | I7: 单价 | J7: 金额 | K7: 数量 | L7: 单价 | M7: 金额 | N7: 数量 | O7: 单价 | P7: 金额 | Q7: 1年以内 | R7: 1-2年 | S7: 2-3年 | T7: 3年以上
A9: （一）周转材料
F10: =IF(E10=0,0,G10/E10) -> 0 | I10: =IF(H10=0,0,J10/H10) -> 0 | L10: =IF(K10=0,0,M10/K10) -> 0 | N10: =E10+H10-K10 -> 0 | O10: =IF(N10=0,0,P10/N10) -> 0 | P10: =G10+J10-M10 -> 0
A11: … | F11: =IF(E11=0,0,G11/E11) -> 0 | I11: =IF(H11=0,0,J11/H11) -> 0 | L11: =IF(K11=0,0,M11/K11) -> 0 | N11: =E11+H11-K11 -> 0 | O11: =IF(N11=0,0,P11/N11) -> 0 | P11: =G11+J11-M11 -> 0
A12: 小计 | E12: -- | F12: -- | G12: =SUM(G10:G11) -> 0 | H12: -- | I12: -- | J12: =SUM(J10:J11) -> 0 | K12: -- | L12: -- | M12: =SUM(M10:M11) -> 0 | N12: -- | O12: -- | P12: =SUM(P10:P11) -> 0 | Q12: =SUM(Q10:Q11) -> 0 | R12: =SUM(R10:R11) -> 0 | S12: =SUM(S10:S11) -> 0 | T12: =SUM(T10:T11) -> 0
A13: （二）低值易耗品
F14: =IF(E14=0,0,G14/E14) -> 0 | I14: =IF(H14=0,0,J14/H14) -> 0 | L14: =IF(K14=0,0,M14/K14) -> 0 | N14: =E14+H14-K14 -> 0 | O14: =IF(N14=0,0,P14/N14) -> 0 | P14: =G14+J14-M14 -> 0
A15: … | F15: =IF(E15=0,0,G15/E15) -> 0 | I15: =IF(H15=0,0,J15/H15) -> 0 | L15: =IF(K15=0,0,M15/K15) -> 0 | N15: =E15+H15-K15 -> 0 | O15: =IF(N15=0,0,P15/N15) -> 0 | P15: =G15+J15-M15 -> 0
A16: 小计 | E16: -- | F16: -- | G16: =SUM(G14:G15) -> 0 | H16: -- | I16: -- | J16: =SUM(J14:J15) -> 0 | K16: -- | L16: -- | M16: =SUM(M14:M15) -> 0 | N16: -- | O16: -- | P16: =SUM(P14:P15) -> 0 | Q16: =SUM(Q14:Q15) -> 0 | R16: =SUM(R14:R15) -> 0 | S16: =SUM(S14:S15) -> 0 | T16: =SUM(T14:T15) -> 0
A17: （三）包装物
A18: 1.生产过程中用于包装产品作为产品组成部分的包装物 | F18: =IF(E18=0,0,G18/E18) -> 0 | I18: =IF(H18=0,0,J18/H18) -> 0 | L18: =IF(K18=0,0,M18/K18) -> 0 | N18: =E18+H18-K18 -> 0 | O18: =IF(N18=0,0,P18/N18) -> 0 | P18: =G18+J18-M18 -> 0
A19: … | F19: =IF(E19=0,0,G19/E19) -> 0 | I19: =IF(H19=0,0,J19/H19) -> 0 | L19: =IF(K19=0,0,M19/K19) -> 0 | N19: =E19+H19-K19 -> 0 | O19: =IF(N19=0,0,P19/N19) -> 0 | P19: =G19+J19-M19 -> 0
A20: 2.随同商品出售而不单独计价的包装物 | F20: =IF(E20=0,0,G20/E20) -> 0 | I20: =IF(H20=0,0,J20/H20) -> 0 | L20: =IF(K20=0,0,M20/K20) -> 0 | N20: =E20+H20-K20 -> 0 | O20: =IF(N20=0,0,P20/N20) -> 0 | P20: =G20+J20-M20 -> 0
A21: … | F21: =IF(E21=0,0,G21/E21) -> 0 | I21: =IF(H21=0,0,J21/H21) -> 0 | L21: =IF(K21=0,0,M21/K21) -> 0 | N21: =E21+H21-K21 -> 0 | O21: =IF(N21=0,0,P21/N21) -> 0 | P21: =G21+J21-M21 -> 0
A22: 3.随同商品出售而单独计价的包装物 | F22: =IF(E22=0,0,G22/E22) -> 0 | I22: =IF(H22=0,0,J22/H22) -> 0 | L22: =IF(K22=0,0,M22/K22) -> 0 | N22: =E22+H22-K22 -> 0 | O22: =IF(N22=0,0,P22/N22) -> 0 | P22: =G22+J22-M22 -> 0
A23: … | F23: =IF(E23=0,0,G23/E23) -> 0 | I23: =IF(H23=0,0,J23/H23) -> 0 | L23: =IF(K23=0,0,M23/K23) -> 0 | N23: =E23+H23-K23 -> 0 | O23: =IF(N23=0,0,P23/N23) -> 0 | P23: =G23+J23-M23 -> 0
A24: 4.出租或出借给购买单位使用的包装物 | F24: =IF(E24=0,0,G24/E24) -> 0 | I24: =IF(H24=0,0,J24/H24) -> 0 | L24: =IF(K24=0,0,M24/K24) -> 0 | N24: =E24+H24-K24 -> 0 | O24: =IF(N24=0,0,P24/N24) -> 0 | P24: =G24+J24-M24 -> 0
A25: … | F25: =IF(E25=0,0,G25/E25) -> 0 | I25: =IF(H25=0,0,J25/H25) -> 0 | L25: =IF(K25=0,0,M25/K25) -> 0 | N25: =E25+H25-K25 -> 0 | O25: =IF(N25=0,0,P25/N25) -> 0 | P25: =G25+J25-M25 -> 0
A26: 小计 | E26: -- | F26: -- | G26: =G18+G20+G22+G24 -> 0 | H26: -- | I26: -- | J26: =J18+J20+J22+J24 -> 0 | K26: -- | L26: -- | M26: =M18+M20+M22+M24 -> 0 | N26: -- | O26: -- | P26: =P18+P20+P22+P24 -> 0 | Q26: =Q18+Q20+Q22+Q24 -> 0 | R26: =R18+R20+R22+R24 -> 0 | S26: =S18+S20+S22+S24 -> 0 | T26: =T18+T20+T22+T24 -> 0
A27: 合计 | E27: -- | F27: -- | G27: =SUM(G12,G16,G26) -> 0 | H27: -- | I27: -- | J27: =SUM(J12,J16,J26) -> 0 | K27: -- | L27: -- | M27: =SUM(M12,M16,M26) -> 0 | N27: -- | O27: -- | P27: =SUM(P12,P16,P26) -> 0 | Q27: =SUM(Q12,Q16,Q26) -> 0 | R27: =SUM(R12,R16,R26) -> 0 | S27: =SUM(S12,S16,S26) -> 0 | T27: =SUM(T12,T16,T26) -> 0
A28: 减：存货跌价准备
A29: 周转材料/低值易耗品/包装物净额 | E29: -- | F29: -- | G29: =G27-G28 -> 0 | H29: -- | I29: -- | J29: =J27-J28 -> 0 | K29: -- | L29: -- | M29: =M27-M28 -> 0 | N29: -- | O29: -- | P29: =P27-P28 -> 0 | Q29: =Q27-Q28 -> 0 | R29: =R27-R28 -> 0 | S29: =S27-S28 -> 0 | T29: =T27-T28 -> 0
A30: 审计说明： | P30: =IF((P27-Q27-R27-S27-T27)=0,"OK","库龄与期末金额不匹配") -> OK
A31: 1.摊销方法说明： | K31: 3.周转材料/低值易耗品/包装物——**库龄较长的原因：
A32: 2.周转材料/低值易耗品/包装物本期发生重大变动的原因： | K32: 4.计提跌价准备的主要项目及原因：
A34: 提示：摊销方法采用五五、分次摊销法摊销时，金额按摊余价值列示，并作出说明。

Sheet 四、自制半成品明细表F2-6
A1: 致同会计师事务所
A2: 存货明细表
A3: =底稿目录!A2 -> 被审计单位： | G3: =底稿目录!A4 -> 编制人： | K3: =底稿目录!A5 -> 编制日期： | T3: 索引号： | U3: =底稿目录!F11 -> F2-6
A4: =底稿目录!A3 -> 截止日：202X年12月21日 | G4: =底稿目录!A6 -> 复核人： | K4: =底稿目录!A7 -> 复核日期： | T4: 页次：
A5: 四、自制半成品明细表
A6: 存货编码 | B6: 自制半成品名称 | C6: 规格 | D6: 单位 | E6: 期初库存 | H6: 本期购进 | K6: 本期发出 | N6: 期末结存 | Q6: 库龄 | U6: 品质状况（正常、残次、毁损、滞销等）
E7: 数量 | F7: 单价 | G7: 金额 | H7: 数量 | I7: 单价 | J7: 金额 | K7: 数量 | L7: 单价 | M7: 金额 | N7: 数量 | O7: 单价 | P7: 金额 | Q7: 1年以内 | R7: 1-2年 | S7: 2-3年 | T7: 3年以上
F9: =IF(E9=0,0,G9/E9) -> 0 | I9: =IF(H9=0,0,J9/H9) -> 0 | L9: =IF(K9=0,0,M9/K9) -> 0 | N9: =E9+H9-K9 -> 0 | O9: =IF(N9=0,0,P9/N9) -> 0 | P9: =G9+J9-M9 -> 0
F10: =IF(E10=0,0,G10/E10) -> 0 | I10: =IF(H10=0,0,J10/H10) -> 0 | L10: =IF(K10=0,0,M10/K10) -> 0 | N10: =E10+H10-K10 -> 0 | O10: =IF(N10=0,0,P10/N10) -> 0 | P10: =G10+J10-M10 -> 0
F11: =IF(E11=0,0,G11/E11) -> 0 | I11: =IF(H11=0,0,J11/H11) -> 0 | L11: =IF(K11=0,0,M11/K11) -> 0 | N11: =E11+H11-K11 -> 0 | O11: =IF(N11=0,0,P11/N11) -> 0 | P11: =G11+J11-M11 -> 0
F12: =IF(E12=0,0,G12/E12) -> 0 | I12: =IF(H12=0,0,J12/H12) -> 0 | L12: =IF(K12=0,0,M12/K12) -> 0 | N12: =E12+H12-K12 -> 0 | O12: =IF(N12=0,0,P12/N12) -> 0 | P12: =G12+J12-M12 -> 0
F13: =IF(E13=0,0,G13/E13) -> 0 | I13: =IF(H13=0,0,J13/H13) -> 0 | L13: =IF(K13=0,0,M13/K13) -> 0 | N13: =E13+H13-K13 -> 0 | O13: =IF(N13=0,0,P13/N13) -> 0 | P13: =G13+J13-M13 -> 0
F14: =IF(E14=0,0,G14/E14) -> 0 | I14: =IF(H14=0,0,J14/H14) -> 0 | L14: =IF(K14=0,0,M14/K14) -> 0 | N14: =E14+H14-K14 -> 0 | O14: =IF(N14=0,0,P14/N14) -> 0 | P14: =G14+J14-M14 -> 0
F15: =IF(E15=0,0,G15/E15) -> 0 | I15: =IF(H15=0,0,J15/H15) -> 0 | L15: =IF(K15=0,0,M15/K15) -> 0 | N15: =E15+H15-K15 -> 0 | O15: =IF(N15=0,0,P15/N15) -> 0 | P15: =G15+J15-M15 -> 0
F16: =IF(E16=0,0,G16/E16) -> 0 | I16: =IF(H16=0,0,J16/H16) -> 0 | L16: =IF(K16=0,0,M16/K16) -> 0 | N16: =E16+H16-K16 -> 0 | O16: =IF(N16=0,0,P16/N16) -> 0 | P16: =G16+J16-M16 -> 0
F17: =IF(E17=0,0,G17/E17) -> 0 | I17: =IF(H17=0,0,J17/H17) -> 0 | L17: =IF(K17=0,0,M17/K17) -> 0 | N17: =E17+H17-K17 -> 0 | O17: =IF(N17=0,0,P17/N17) -> 0 | P17: =G17+J17-M17 -> 0
F18: =IF(E18=0,0,G18/E18) -> 0 | I18: =IF(H18=0,0,J18/H18) -> 0 | L18: =IF(K18=0,0,M18/K18) -> 0 | N18: =E18+H18-K18 -> 0 | O18: =IF(N18=0,0,P18/N18) -> 0 | P18: =G18+J18-M18 -> 0
F19: =IF(E19=0,0,G19/E19) -> 0 | I19: =IF(H19=0,0,J19/H19) -> 0 | L19: =IF(K19=0,0,M19/K19) -> 0 | N19: =E19+H19-K19 -> 0 | O19: =IF(N19=0,0,P19/N19) -> 0 | P19: =G19+J19-M19 -> 0
F20: =IF(E20=0,0,G20/E20) -> 0 | I20: =IF(H20=0,0,J20/H20) -> 0 | L20: =IF(K20=0,0,M20/K20) -> 0 | N20: =E20+H20-K20 -> 0 | O20: =IF(N20=0,0,P20/N20) -> 0 | P20: =G20+J20-M20 -> 0
... F24: =IF(E24=0,0,G24/E24) -> 0 | I24: =IF(H24=0,0,J24/H24) -> 0 | L24: =IF(K24=0,0,M24/K24) -> 0 | N24: =E24+H24-K24 -> 0 | O24: =IF(N24=0,0,P24/N24) -> 0 | P24: =G24+J24-M24 -> 0
A25: 合计 | E25: -- | F25: -- | G25: =SUM(G9:G24) -> 0 | H25: -- | I25: -- | J25: =SUM(J9:J24) -> 0 | K25: -- | L25: -- | M25: =SUM(M9:M24) -> 0 | N25: -- | O25: -- | P25: =SUM(P9:P24) -> 0 | Q25: =SUM(Q9:Q24) -> 0 | R25: =SUM(R9:R24) -> 0 | S25: =SUM(S9:S24) -> 0 | T25: =SUM(T9:T24) -> 0
A26: 减：存货跌价准备
A27: 自制半成品净额 | E27: -- | F27: -- | G27: =G25-G26 -> 0 | H27: -- | I27: -- | J27: =J25-J26 -> 0 | K27: -- | L27: -- | M27: =M25-M26 -> 0 | N27: -- | O27: -- | P27: =P25-P26 -> 0 | Q27: =Q25-Q26 -> 0 | R27: =R25-R26 -> 0 | S27: =S25-S26 -> 0 | T27: =T25-T26 -> 0
A28: 审计说明： | P28: =IF((P25-Q25-R25-S25-T25)=0,"OK","库龄与期末金额不匹配") -> OK
A29: 1、自制半成品的计价方法： | K29: 3、自制半成品——**库龄较长的原因：
A30: 2、自制半成品本期发生重大变动的原因： | K30: 4、计提跌价准备的主要项目及原因：

Sheet 五、委托加工物资明细表F2-7
A1: 致同会计师事务所
A2: 存货明细表
A3: =底稿目录!A2 -> 被审计单位： | E3: =底稿目录!A4 -> 编制人： | J3: =底稿目录!A5 -> 编制日期： | N3: 索引号： | O3: =底稿目录!F12 -> F2-7
A4: =底稿目录!A3 -> 截止日：202X年12月21日 | E4: =底稿目录!A6 -> 复核人： | J4: =底稿目录!A7 -> 复核日期： | N4: 页次：
A5: 五、委托加工物资明细表
A6: 加工单位名称 | C6: 加工合同号 | D6: 发出加工物资名称 | E6: 数量 | F6: 单价 | G6: 金额 | H6: 加工费用 | I6: 运杂费 | J6: 计入加工物资成本的税金 | K6: 加工物资成本 | L6: 库龄
L7: 1年以内 | M7: 1-2年 | N7: 2-3年 | O7: 3年以上
G8: =E8*F8 -> 0
G9: =E9*F9 -> 0
G10: =E10*F10 -> 0
G11: =E11*F11 -> 0
G12: =E12*F12 -> 0
G13: =E13*F13 -> 0
G14: =E14*F14 -> 0
G15: =E15*F15 -> 0
G16: =E16*F16 -> 0
A17: 合计 | G17: =SUM(G8:G16) -> 0 | H17: =SUM(H8:H16) -> 0 | I17: =SUM(I8:I16) -> 0 | J17: =SUM(J8:J16) -> 0 | K17: =SUM(K8:K16) -> 0 | L17: =SUM(L8:L16) -> 0 | M17: =SUM(M8:M16) -> 0 | N17: =SUM(N8:N16) -> 0 | O17: =SUM(O8:O16) -> 0
A18: 减：存货减值准备
A19: 存货净额 | G19: =G17-G18 -> 0 | L19: =L17-L18 -> 0 | M19: =M17-M18 -> 0 | N19: =N17-N18 -> 0 | O19: =O17-O18 -> 0
A20: 审计说明： | G20: =IF((G17-L17-M17-N17-O17)=0,"OK","库龄与期末金额不匹配") -> OK
A21: 1.委托加工物资的成本核算方法： | G21: 3.委托加工物资——**库龄较长的原因：
A22: 2.委托加工物资本期发生重大变动的原因： | G22: 4.计提跌价准备的主要项目及原因：

Sheet 六、库存商品明细表F2-8
A1: 致同会计师事务所
A2: 存货明细表
A3: =底稿目录!A2 -> 被审计单位： | G3: =底稿目录!A4 -> 编制人： | M3: =底稿目录!A5 -> 编制日期： | W3: 索引号： | X3: =底稿目录!F13 -> F2-8
A4: =底稿目录!A3 -> 截止日：202X年12月21日 | G4: =底稿目录!A6 -> 复核人： | M4: =底稿目录!A7 -> 复核日期： | W4: 页次：
A5: 六、库存商品明细表
A6: 存货编码 | B6: 存货名称 | C6: 规格 | D6: 单位 | E6: 期初库存 | H6: 本期购进 | K6: 本期发出 | N6: 期末结存 | Q6: 库龄 | U6: 品质状况（正常、残次、毁损、滞销等） | V6: 是否有在手订单 | W6: 订单编号 | X6: 销售单价
E7: 数量 | F7: 单价 | G7: 金额 | H7: 数量 | I7: 单价 | J7: 金额 | K7: 数量 | L7: 单价 | M7: 金额 | N7: 数量 | O7: 单价 | P7: 金额 | Q7: 1年以内 | R7: 1-2年 | S7: 2-3年 | T7: 3年以上
F9: =IF(E9=0,0,G9/E9) -> 0 | I9: =IF(H9=0,0,J9/H9) -> 0 | L9: =IF(K9=0,0,M9/K9) -> 0 | N9: =E9+H9-K9 -> 0 | O9: =IF(N9=0,0,P9/N9) -> 0 | P9: =G9+J9-M9 -> 0
F10: =IF(E10=0,0,G10/E10) -> 0 | I10: =IF(H10=0,0,J10/H10) -> 0 | L10: =IF(K10=0,0,M10/K10) -> 0 | N10: =E10+H10-K10 -> 0 | O10: =IF(N10=0,0,P10/N10) -> 0 | P10: =G10+J10-M10 -> 0
F11: =IF(E11=0,0,G11/E11) -> 0 | I11: =IF(H11=0,0,J11/H11) -> 0 | L11: =IF(K11=0,0,M11/K11) -> 0 | N11: =E11+H11-K11 -> 0 | O11: =IF(N11=0,0,P11/N11) -> 0 | P11: =G11+J11-M11 -> 0
F12: =IF(E12=0,0,G12/E12) -> 0 | I12: =IF(H12=0,0,J12/H12) -> 0 | L12: =IF(K12=0,0,M12/K12) -> 0 | N12: =E12+H12-K12 -> 0 | O12: =IF(N12=0,0,P12/N12) -> 0 | P12: =G12+J12-M12 -> 0
F13: =IF(E13=0,0,G13/E13) -> 0 | I13: =IF(H13=0,0,J13/H13) -> 0 | L13: =IF(K13=0,0,M13/K13) -> 0 | N13: =E13+H13-K13 -> 0 | O13: =IF(N13=0,0,P13/N13) -> 0 | P13: =G13+J13-M13 -> 0
F14: =IF(E14=0,0,G14/E14) -> 0 | I14: =IF(H14=0,0,J14/H14) -> 0 | L14: =IF(K14=0,0,M14/K14) -> 0 | N14: =E14+H14-K14 -> 0 | O14: =IF(N14=0,0,P14/N14) -> 0 | P14: =G14+J14-M14 -> 0
F15: =IF(E15=0,0,G15/E15) -> 0 | I15: =IF(H15=0,0,J15/H15) -> 0 | L15: =IF(K15=0,0,M15/K15) -> 0 | N15: =E15+H15-K15 -> 0 | O15: =IF(N15=0,0,P15/N15) -> 0 | P15: =G15+J15-M15 -> 0
F16: =IF(E16=0,0,G16/E16) -> 0 | I16: =IF(H16=0,0,J16/H16) -> 0 | L16: =IF(K16=0,0,M16/K16) -> 0 | N16: =E16+H16-K16 -> 0 | O16: =IF(N16=0,0,P16/N16) -> 0 | P16: =G16+J16-M16 -> 0
F17: =IF(E17=0,0,G17/E17) -> 0 | I17: =IF(H17=0,0,J17/H17) -> 0 | L17: =IF(K17=0,0,M17/K17) -> 0 | N17: =E17+H17-K17 -> 0 | O17: =IF(N17=0,0,P17/N17) -> 0 | P17: =G17+J17-M17 -> 0
F18: =IF(E18=0,0,G18/E18) -> 0 | I18: =IF(H18=0,0,J18/H18) -> 0 | L18: =IF(K18=0,0,M18/K18) -> 0 | N18: =E18+H18-K18 -> 0 | O18: =IF(N18=0,0,P18/N18) -> 0 | P18: =G18+J18-M18 -> 0
F19: =IF(E19=0,0,G19/E19) -> 0 | I19: =IF(H19=0,0,J19/H19) -> 0 | L19: =IF(K19=0,0,M19/K19) -> 0 | N19: =E19+H19-K19 -> 0 | O19: =IF(N19=0,0,P19/N19) -> 0 | P19: =G19+J19-M19 -> 0
F20: =IF(E20=0,0,G20/E20) -> 0 | I20: =IF(H20=0,0,J20/H20) -> 0 | L20: =IF(K20=0,0,M20/K20) -> 0 | N20: =E20+H20-K20 -> 0 | O20: =IF(N20=0,0,P20/N20) -> 0 | P20: =G20+J20-M20 -> 0
... F23: =IF(E23=0,0,G23/E23) -> 0 | I23: =IF(H23=0,0,J23/H23) -> 0 | L23: =IF(K23=0,0,M23/K23) -> 0 | N23: =E23+H23-K23 -> 0 | O23: =IF(N23=0,0,P23/N23) -> 0 | P23: =G23+J23-M23 -> 0
A24: …… | F24: =IF(E24=0,0,G24/E24) -> 0 | I24: =IF(H24=0,0,J24/H24) -> 0 | L24: =IF(K24=0,0,M24/K24) -> 0 | N24: =E24+H24-K24 -> 0 | O24: =IF(N24=0,0,P24/N24) -> 0 | P24: =G24+J24-M24 -> 0
A25: 合计 | E25: -- | F25: -- | G25: =SUM(G9:G24) -> 0 | H25: -- | I25: -- | J25: =SUM(J9:J24) -> 0 | K25: =SUM(K9:K24) -> 0 | L25: -- | M25: =SUM(M9:M24) -> 0 | N25: -- | O25: -- | P25: =SUM(P9:P24) -> 0 | Q25: =SUM(Q9:Q24) -> 0 | R25: =SUM(R9:R24) -> 0 | S25: =SUM(S9:S24) -> 0 | T25: =SUM(T9:T24) -> 0
A26: 减：存货跌价准备
A27: 库存商品净额 | E27: -- | F27: -- | G27: =G25-G26 -> 0 | H27: -- | I27: -- | J27: =J25-J26 -> 0 | K27: -- | L27: -- | M27: =M25-M26 -> 0 | N27: -- | O27: -- | P27: =P25-P26 -> 0 | Q27: =Q25-Q26 -> 0 | R27: =R25-R26 -> 0 | S27: =S25-S26 -> 0 | T27: =T25-T26 -> 0
A28: 销售出库数量（销售台账） | P28: =IF((P25-Q25-R25-S25-T25)=0,"OK","库龄与期末金额不匹配") -> OK
A29: 差异 | K29: =K25-K28 -> 0
A30: 审计说明：
A31: 1.库存商品的计价方法： | K31: 3.库存商品——**库龄较长的原因：
A32: 2.库存商品本期发生重大变动的原因： | K32: 4.计提跌价准备的主要项目及原因：

Sheet 七、发出商品F2-9
A1: 致同会计师事务所
A2: 存货明细表
A3: =底稿目录!A2 -> 被审计单位： | F3: =底稿目录!A4 -> 编制人： | J3: =底稿目录!A5 -> 编制日期： | V3: 索引号： | W3: =底稿目录!F14 -> F2-9
A4: =底稿目录!A3 -> 截止日：202X年12月21日 | F4: =底稿目录!A6 -> 复核人： | J4: =底稿目录!A7 -> 复核日期： | V4: 页次：
A5: 七、发出商品明细表
A6: 购货单位 | B6: 发出商品名称及规格 | C6: 单位 | D6: 期初库存 | G6: 本期转入 | J6: 本期转出 | M6: 期末结存 | P6: 期后结转 | S6: 库龄 | W6: 品质状况（正常、残次、毁损、滞销等）
D7: 数量 | E7: 单价 | F7: 金额 | G7: 数量 | H7: 单价 | I7: 金额 | J7: 数量 | K7: 单价 | L7: 金额 | M7: 数量 | N7: 单价 | O7: 金额 | P7: 数量 | Q7: 单价 | R7: 金额 | S7: 1年以内 | T7: 1-2年 | U7: 2-3年 | V7: 3年以上
E9: =IF(D9=0,0,F9/D9) -> 0 | H9: =IF(G9=0,0,I9/G9) -> 0 | K9: =IF(J9=0,0,L9/J9) -> 0 | M9: =D9+G9-J9 -> 0 | N9: =IF(M9=0,0,O9/M9) -> 0 | O9: =F9+I9-L9 -> 0 | Q9: =IF(P9=0,0,R9/P9) -> 0
E10: =IF(D10=0,0,F10/D10) -> 0 | H10: =IF(G10=0,0,I10/G10) -> 0 | K10: =IF(J10=0,0,L10/J10) -> 0 | M10: =D10+G10-J10 -> 0 | N10: =IF(M10=0,0,O10/M10) -> 0 | O10: =F10+I10-L10 -> 0 | Q10: =IF(P10=0,0,R10/P10) -> 0
E11: =IF(D11=0,0,F11/D11) -> 0 | H11: =IF(G11=0,0,I11/G11) -> 0 | K11: =IF(J11=0,0,L11/J11) -> 0 | M11: =D11+G11-J11 -> 0 | N11: =IF(M11=0,0,O11/M11) -> 0 | O11: =F11+I11-L11 -> 0 | Q11: =IF(P11=0,0,R11/P11) -> 0
E12: =IF(D12=0,0,F12/D12) -> 0 | H12: =IF(G12=0,0,I12/G12) -> 0 | K12: =IF(J12=0,0,L12/J12) -> 0 | M12: =D12+G12-J12 -> 0 | N12: =IF(M12=0,0,O12/M12) -> 0 | O12: =F12+I12-L12 -> 0 | Q12: =IF(P12=0,0,R12/P12) -> 0
E13: =IF(D13=0,0,F13/D13) -> 0 | H13: =IF(G13=0,0,I13/G13) -> 0 | K13: =IF(J13=0,0,L13/J13) -> 0 | M13: =D13+G13-J13 -> 0 | N13: =IF(M13=0,0,O13/M13) -> 0 | O13: =F13+I13-L13 -> 0 | Q13: =IF(P13=0,0,R13/P13) -> 0
E14: =IF(D14=0,0,F14/D14) -> 0 | H14: =IF(G14=0,0,I14/G14) -> 0 | K14: =IF(J14=0,0,L14/J14) -> 0 | M14: =D14+G14-J14 -> 0 | N14: =IF(M14=0,0,O14/M14) -> 0 | O14: =F14+I14-L14 -> 0 | Q14: =IF(P14=0,0,R14/P14) -> 0
E15: =IF(D15=0,0,F15/D15) -> 0 | H15: =IF(G15=0,0,I15/G15) -> 0 | K15: =IF(J15=0,0,L15/J15) -> 0 | M15: =D15+G15-J15 -> 0 | N15: =IF(M15=0,0,O15/M15) -> 0 | O15: =F15+I15-L15 -> 0 | Q15: =IF(P15=0,0,R15/P15) -> 0
E16: =IF(D16=0,0,F16/D16) -> 0 | H16: =IF(G16=0,0,I16/G16) -> 0 | K16: =IF(J16=0,0,L16/J16) -> 0 | M16: =D16+G16-J16 -> 0 | N16: =IF(M16=0,0,O16/M16) -> 0 | O16: =F16+I16-L16 -> 0 | Q16: =IF(P16=0,0,R16/P16) -> 0
E17: =IF(D17=0,0,F17/D17) -> 0 | H17: =IF(G17=0,0,I17/G17) -> 0 | K17: =IF(J17=0,0,L17/J17) -> 0 | M17: =D17+G17-J17 -> 0 | N17: =IF(M17=0,0,O17/M17) -> 0 | O17: =F17+I17-L17 -> 0 | Q17: =IF(P17=0,0,R17/P17) -> 0
E18: =IF(D18=0,0,F18/D18) -> 0 | H18: =IF(G18=0,0,I18/G18) -> 0 | K18: =IF(J18=0,0,L18/J18) -> 0 | M18: =D18+G18-J18 -> 0 | N18: =IF(M18=0,0,O18/M18) -> 0 | O18: =F18+I18-L18 -> 0 | Q18: =IF(P18=0,0,R18/P18) -> 0
E19: =IF(D19=0,0,F19/D19) -> 0 | H19: =IF(G19=0,0,I19/G19) -> 0 | K19: =IF(J19=0,0,L19/J19) -> 0 | M19: =D19+G19-J19 -> 0 | N19: =IF(M19=0,0,O19/M19) -> 0 | O19: =F19+I19-L19 -> 0 | Q19: =IF(P19=0,0,R19/P19) -> 0
E20: =IF(D20=0,0,F20/D20) -> 0 | H20: =IF(G20=0,0,I20/G20) -> 0 | K20: =IF(J20=0,0,L20/J20) -> 0 | M20: =D20+G20-J20 -> 0 | N20: =IF(M20=0,0,O20/M20) -> 0 | O20: =F20+I20-L20 -> 0 | Q20: =IF(P20=0,0,R20/P20) -> 0
... E23: =IF(D23=0,0,F23/D23) -> 0 | H23: =IF(G23=0,0,I23/G23) -> 0 | K23: =IF(J23=0,0,L23/J23) -> 0 | M23: =D23+G23-J23 -> 0 | N23: =IF(M23=0,0,O23/M23) -> 0 | O23: =F23+I23-L23 -> 0 | Q23: =IF(P23=0,0,R23/P23) -> 0
A24: …… | E24: =IF(D24=0,0,F24/D24) -> 0 | H24: =IF(G24=0,0,I24/G24) -> 0 | K24: =IF(J24=0,0,L24/J24) -> 0 | M24: =D24+G24-J24 -> 0 | N24: =IF(M24=0,0,O24/M24) -> 0 | O24: =F24+I24-L24 -> 0 | Q24: =IF(P24=0,0,R24/P24) -> 0
A25: 合计 | D25: -- | E25: -- | F25: =SUM(F9:F24) -> 0 | G25: -- | H25: -- | I25: =SUM(I9:I24) -> 0 | J25: =SUM(J9:J24) -> 0 | K25: -- | L25: =SUM(L9:L24) -> 0 | M25: -- | N25: -- | O25: =SUM(O9:O24) -> 0 | P25: -- | Q25: -- | R25: =SUM(R9:R24) -> 0 | S25: =SUM(S9:S24) -> 0 | T25: =SUM(T9:T24) -> 0 | U25: =SUM(U9:U24) -> 0 | V25: =SUM(V9:V24) -> 0
A26: 减：存货跌价准备
A27: 发出商品净额 | D27: -- | E27: -- | F27: =F25-F26 -> 0 | G27: -- | H27: -- | I27: =I25-I26 -> 0 | J27: -- | K27: -- | L27: =L25-L26 -> 0 | M27: -- | N27: -- | O27: =O25-O26 -> 0 | P27: -- | Q27: -- | R27: =R25-R26 -> 0 | S27: =S25-S26 -> 0 | T27: =T25-T26 -> 0 | U27: =U25-U26 -> 0 | V27: =V25-V26 -> 0
A28: 销售出库数量（销售台账） | O28: =IF((O25-S25-T25-U25-V25)=0,"OK","库龄与期末金额不匹配") -> OK
A29: 差异 | J29: =J25-J28 -> 0
A31: 审计说明：
A32: 1.发出商品资产负债表日后销售情况： | I32: 3.发出商品——**库龄较长的原因：
A33: 2.发出商品本期发生重大变动的原因： | I33: 4.计提跌价准备的主要项目及原因：
A35: 审计提示：
A36: 关注产品退换货情况

Sheet 八、开发产品F2-10
A1: 致同会计师事务所
A2: 存货明细表
A3: =底稿目录!A2 -> 被审计单位： | H3: =底稿目录!A4 -> 编制人： | Q3: =底稿目录!A5 -> 编制日期： | Z3: 索引号： | AA3: =底稿目录!F15 -> F2-10
A4: =底稿目录!A3 -> 截止日：202X年12月21日 | H4: =底稿目录!A6 -> 复核人： | Q4: =底稿目录!A7 -> 复核日期： | Z4: 页次：
A5: 八、开发产品明细表
A6: （一）原值
A7: 序号 | B7: 项目名称 | C7: 总建筑面积/万平米 | D7: 开工时间 | E7: 竣工时间 | F7: 期初结存（未审） | I7: 期初调整 | K7: 期初审定 | M7: 本期转入 | P7: 本期转出 | S7: 期末结存（未审） | V7: 期末调整 | X7: 期末审定 | Z7: 库龄 | AA7: 品质状况（正常、停建、毁损、报废等）
F8: 面积 （平方米） | G8: 单位成本 | H8: 金额 | I8: 账项调整 | J8: 重分类调整 | K8: 单位成本 | L8: 金额 | M8: 面积 （平方米） | N8: 单位成本 | O8: 金额 | P8: 面积 （平方米） | Q8: 单位成本 | R8: 金额 | S8: 面积 （平方米） | T8: 单位成本 | U8: 金额 | V8: 账项调整 | W8: 重分类调整 | X8: 单位成本 | Y8: 金额
A9: 1 | G9: =IF(F9=0,0,H9/F9) -> 0 | K9: =IF(F9=0,0,L9/F9) -> 0 | L9: =H9+I9+J9 -> 0 | N9: =IF(M9=0,0,O9/M9) -> 0 | Q9: =IF(P9=0,0,R9/P9) -> 0 | S9: =F9+M9-P9 -> 0 | T9: =IF(S9=0,0,U9/S9) -> 0 | U9: =H9+O9-R9 -> 0 | X9: =IF(S9=0,0,Y9/S9) -> 0 | Y9: =U9+V9+W9 -> 0
A10: 2 | G10: =IF(F10=0,0,H10/F10) -> 0 | K10: =IF(F10=0,0,L10/F10) -> 0 | L10: =H10+I10+J10 -> 0 | N10: =IF(M10=0,0,O10/M10) -> 0 | Q10: =IF(P10=0,0,R10/P10) -> 0 | S10: =F10+M10-P10 -> 0 | T10: =IF(S10=0,0,U10/S10) -> 0 | U10: =H10+O10-R10 -> 0 | X10: =IF(S10=0,0,Y10/S10) -> 0 | Y10: =U10+V10+W10 -> 0
A11: 3 | G11: =IF(F11=0,0,H11/F11) -> 0 | K11: =IF(F11=0,0,L11/F11) -> 0 | L11: =H11+I11+J11 -> 0 | N11: =IF(M11=0,0,O11/M11) -> 0 | Q11: =IF(P11=0,0,R11/P11) -> 0 | S11: =F11+M11-P11 -> 0 | T11: =IF(S11=0,0,U11/S11) -> 0 | U11: =H11+O11-R11 -> 0 | X11: =IF(S11=0,0,Y11/S11) -> 0 | Y11: =U11+V11+W11 -> 0
A12: 4 | G12: =IF(F12=0,0,H12/F12) -> 0 | K12: =IF(F12=0,0,L12/F12) -> 0 | L12: =H12+I12+J12 -> 0 | N12: =IF(M12=0,0,O12/M12) -> 0 | Q12: =IF(P12=0,0,R12/P12) -> 0 | S12: =F12+M12-P12 -> 0 | T12: =IF(S12=0,0,U12/S12) -> 0 | U12: =H12+O12-R12 -> 0 | X12: =IF(S12=0,0,Y12/S12) -> 0 | Y12: =U12+V12+W12 -> 0
A13: 5 | G13: =IF(F13=0,0,H13/F13) -> 0 | K13: =IF(F13=0,0,L13/F13) -> 0 | L13: =H13+I13+J13 -> 0 | N13: =IF(M13=0,0,O13/M13) -> 0 | Q13: =IF(P13=0,0,R13/P13) -> 0 | S13: =F13+M13-P13 -> 0 | T13: =IF(S13=0,0,U13/S13) -> 0 | U13: =H13+O13-R13 -> 0 | X13: =IF(S13=0,0,Y13/S13) -> 0 | Y13: =U13+V13+W13 -> 0
A14: 6 | G14: =IF(F14=0,0,H14/F14) -> 0 | K14: =IF(F14=0,0,L14/F14) -> 0 | L14: =H14+I14+J14 -> 0 | N14: =IF(M14=0,0,O14/M14) -> 0 | Q14: =IF(P14=0,0,R14/P14) -> 0 | S14: =F14+M14-P14 -> 0 | T14: =IF(S14=0,0,U14/S14) -> 0 | U14: =H14+O14-R14 -> 0 | X14: =IF(S14=0,0,Y14/S14) -> 0 | Y14: =U14+V14+W14 -> 0
A15: 7 | G15: =IF(F15=0,0,H15/F15) -> 0 | K15: =IF(F15=0,0,L15/F15) -> 0 | L15: =H15+I15+J15 -> 0 | N15: =IF(M15=0,0,O15/M15) -> 0 | Q15: =IF(P15=0,0,R15/P15) -> 0 | S15: =F15+M15-P15 -> 0 | T15: =IF(S15=0,0,U15/S15) -> 0 | U15: =H15+O15-R15 -> 0 | X15: =IF(S15=0,0,Y15/S15) -> 0 | Y15: =U15+V15+W15 -> 0
A16: 8 | G16: =IF(F16=0,0,H16/F16) -> 0 | K16: =IF(F16=0,0,L16/F16) -> 0 | L16: =H16+I16+J16 -> 0 | N16: =IF(M16=0,0,O16/M16) -> 0 | Q16: =IF(P16=0,0,R16/P16) -> 0 | S16: =F16+M16-P16 -> 0 | T16: =IF(S16=0,0,U16/S16) -> 0 | U16: =H16+O16-R16 -> 0 | X16: =IF(S16=0,0,Y16/S16) -> 0 | Y16: =U16+V16+W16 -> 0
A17: 9 | G17: =IF(F17=0,0,H17/F17) -> 0 | K17: =IF(F17=0,0,L17/F17) -> 0 | L17: =H17+I17+J17 -> 0 | N17: =IF(M17=0,0,O17/M17) -> 0 | Q17: =IF(P17=0,0,R17/P17) -> 0 | S17: =F17+M17-P17 -> 0 | T17: =IF(S17=0,0,U17/S17) -> 0 | U17: =H17+O17-R17 -> 0 | X17: =IF(S17=0,0,Y17/S17) -> 0 | Y17: =U17+V17+W17 -> 0
A18: 10 | G18: =IF(F18=0,0,H18/F18) -> 0 | K18: =IF(F18=0,0,L18/F18) -> 0 | L18: =H18+I18+J18 -> 0 | N18: =IF(M18=0,0,O18/M18) -> 0 | Q18: =IF(P18=0,0,R18/P18) -> 0 | S18: =F18+M18-P18 -> 0 | T18: =IF(S18=0,0,U18/S18) -> 0 | U18: =H18+O18-R18 -> 0 | X18: =IF(S18=0,0,Y18/S18) -> 0 | Y18: =U18+V18+W18 -> 0
A19: 合计 | F19: =SUM(F9:F18) -> 0 | G19: =IF(F19=0,0,H19/F19) -> 0 | H19: =SUM(H9:H18) -> 0 | I19: =SUM(I9:I18) -> 0 | J19: =SUM(J9:J18) -> 0 | K19: =IF(F19=0,0,L19/F19) -> 0 | L19: =SUM(L9:L18) -> 0 | M19: =SUM(M9:M18) -> 0 | N19: =IF(M19=0,0,O19/M19) -> 0 | O19: =SUM(O9:O18) -> 0 | P19: =SUM(P9:P18) -> 0 | Q19: =IF(P19=0,0,R19/P19) -> 0 | R19: =SUM(R9:R18) -> 0 | S19: =SUM(S9:S18) -> 0 | T19: =IF(S19=0,0,U19/S19) -> 0 | U19: =SUM(U9:U18) -> 0 | V19: =SUM(V9:V18) -> 0 | W19: =SUM(W9:W18) -> 0 | X19: =IF(S19=0,0,Y19/S19) -> 0 | Y19: =SUM(Y9:Y18) -> 0
A20: （二）跌价准备
A21: 序号 | B21: 项目名称 | C21: 总建筑面积/万平米 | D21: 开工时间 | E21: 竣工时间 | F21: 未审数 | J21: 期初调整 | L21: 账项调整 | N21: 重分类调整 | P21: 审定数 | T21: 备注 | U21: 索引号
F22: 期初余额 | G22: 本期增加 | H22: 本期减少 | I22: 期末余额 | J22: 账项调整 | K22: 重分类调整 | L22: 本期增加 | M22: 本期减少 | N22: 本期增加 | O22: 本期减少 | P22: 期初余额 | Q22: 本期增加 | R22: 本期减少 | S22: 期末余额
A23: =A9 -> 1 | B23: =B9 -> 0 | C23: =C9 -> 0 | D23: =D9 -> 0 | E23: =E9 -> 0 | I23: =F23+G23-H23 -> 0 | P23: =F23+J23+K23 -> 0 | Q23: =G23+L23+N23 -> 0 | R23: =H23+M23+O23 -> 0 | S23: =P23+Q23-R23 -> 0
A24: =A10 -> 2 | B24: =B10 -> 0 | C24: =C10 -> 0 | D24: =D10 -> 0 | E24: =E10 -> 0 | I24: =F24+G24-H24 -> 0 | P24: =F24+J24+K24 -> 0 | Q24: =G24+L24+N24 -> 0 | R24: =H24+M24+O24 -> 0 | S24: =P24+Q24-R24 -> 0
A25: =A11 -> 3 | B25: =B11 -> 0 | C25: =C11 -> 0 | D25: =D11 -> 0 | E25: =E11 -> 0 | I25: =F25+G25-H25 -> 0 | P25: =F25+J25+K25 -> 0 | Q25: =G25+L25+N25 -> 0 | R25: =H25+M25+O25 -> 0 | S25: =P25+Q25-R25 -> 0
A26: =A12 -> 4 | B26: =B12 -> 0 | C26: =C12 -> 0 | D26: =D12 -> 0 | E26: =E12 -> 0 | I26: =F26+G26-H26 -> 0 | P26: =F26+J26+K26 -> 0 | Q26: =G26+L26+N26 -> 0 | R26: =H26+M26+O26 -> 0 | S26: =P26+Q26-R26 -> 0
A27: =A13 -> 5 | B27: =B13 -> 0 | C27: =C13 -> 0 | D27: =D13 -> 0 | E27: =E13 -> 0 | I27: =F27+G27-H27 -> 0 | P27: =F27+J27+K27 -> 0 | Q27: =G27+L27+N27 -> 0 | R27: =H27+M27+O27 -> 0 | S27: =P27+Q27-R27 -> 0
A28: =A14 -> 6 | B28: =B14 -> 0 | C28: =C14 -> 0 | D28: =D14 -> 0 | E28: =E14 -> 0 | I28: =F28+G28-H28 -> 0 | P28: =F28+J28+K28 -> 0 | Q28: =G28+L28+N28 -> 0 | R28: =H28+M28+O28 -> 0 | S28: =P28+Q28-R28 -> 0
A29: =A15 -> 7 | B29: =B15 -> 0 | C29: =C15 -> 0 | D29: =D15 -> 0 | E29: =E15 -> 0 | I29: =F29+G29-H29 -> 0 | P29: =F29+J29+K29 -> 0 | Q29: =G29+L29+N29 -> 0 | R29: =H29+M29+O29 -> 0 | S29: =P29+Q29-R29 -> 0
A30: =A16 -> 8 | B30: =B16 -> 0 | C30: =C16 -> 0 | D30: =D16 -> 0 | E30: =E16 -> 0 | I30: =F30+G30-H30 -> 0 | P30: =F30+J30+K30 -> 0 | Q30: =G30+L30+N30 -> 0 | R30: =H30+M30+O30 -> 0 | S30: =P30+Q30-R30 -> 0
A31: =A17 -> 9 | B31: =B17 -> 0 | C31: =C17 -> 0 | D31: =D17 -> 0 | E31: =E17 -> 0 | I31: =F31+G31-H31 -> 0 | P31: =F31+J31+K31 -> 0 | Q31: =G31+L31+N31 -> 0 | R31: =H31+M31+O31 -> 0 | S31: =P31+Q31-R31 -> 0
A32: =A18 -> 10 | B32: =B18 -> 0 | C32: =C18 -> 0 | D32: =D18 -> 0 | E32: =E18 -> 0 | I32: =F32+G32-H32 -> 0 | P32: =F32+J32+K32 -> 0 | Q32: =G32+L32+N32 -> 0 | R32: =H32+M32+O32 -> 0 | S32: =P32+Q32-R32 -> 0
A33: =A19 -> 合计 | F33: =SUM(F23:F32) -> 0 | G33: =SUM(G23:G32) -> 0 | H33: =SUM(H23:H32) -> 0 | I33: =SUM(I23:I32) -> 0 | J33: =SUM(J23:J32) -> 0 | K33: =SUM(K23:K32) -> 0 | L33: =SUM(L23:L32) -> 0 | M33: =SUM(M23:M32) -> 0 | ... S33: =SUM(S23:S32) -> 0
A34: （三）净值
A35: 序号 | B35: 项目名称 | C35: 总建筑面积/万平米 | D35: 开工时间 | E35: 竣工时间 | F35: 期初未审数 | I35: 期末未审数 | L35: 期初审定数 | O35: 期末审定数
F36: 面积 （平方米） | G36: 单位成本 | H36: 期初数 | I36: 面积 （平方米） | J36: 单位成本 | K36: 期末数 | L36: 面积 （平方米） | M36: 单位成本 | N36: 期初数 | O36: 面积 （平方米） | P36: 单位成本 | Q36: 期末数
A37: =A9 -> 1 | B37: =B9 -> 0 | C37: =C9 -> 0 | D37: =D9 -> 0 | E37: =E9 -> 0 | F37: =F9 -> 0 | G37: =IF(F37=0,0,H37/F37) -> 0 | H37: =H9-F23 -> 0 | I37: =S9 -> 0 | J37: =IF(I37=0,0,K37/I37) -> 0 | K37: =U9-I23 -> 0 | L37: =F37 -> 0 | M37: =IF(L37=0,0,N37/L37) -> 0 | N37: =L9-P23 -> 0 | O37: =I37 -> 0 | P37: =IF(O37=0,0,Q37/O37) -> 0 | Q37: =Y9-S23 -> 0
A38: =A10 -> 2 | B38: =B10 -> 0 | C38: =C10 -> 0 | D38: =D10 -> 0 | E38: =E10 -> 0 | F38: =F10 -> 0 | G38: =IF(F38=0,0,H38/F38) -> 0 | H38: =H10-F24 -> 0 | I38: =S10 -> 0 | J38: =IF(I38=0,0,K38/I38) -> 0 | K38: =U10-I24 -> 0 | L38: =F38 -> 0 | M38: =IF(L38=0,0,N38/L38) -> 0 | N38: =L10-P24 -> 0 | O38: =I38 -> 0 | P38: =IF(O38=0,0,Q38/O38) -> 0 | Q38: =Y10-S24 -> 0
A39: =A11 -> 3 | B39: =B11 -> 0 | C39: =C11 -> 0 | D39: =D11 -> 0 | E39: =E11 -> 0 | F39: =F11 -> 0 | G39: =IF(F39=0,0,H39/F39) -> 0 | H39: =H11-F25 -> 0 | I39: =S11 -> 0 | J39: =IF(I39=0,0,K39/I39) -> 0 | K39: =U11-I25 -> 0 | L39: =F39 -> 0 | M39: =IF(L39=0,0,N39/L39) -> 0 | N39: =L11-P25 -> 0 | O39: =I39 -> 0 | P39: =IF(O39=0,0,Q39/O39) -> 0 | Q39: =Y11-S25 -> 0
A40: =A12 -> 4 | B40: =B12 -> 0 | C40: =C12 -> 0 | D40: =D12 -> 0 | E40: =E12 -> 0 | F40: =F12 -> 0 | G40: =IF(F40=0,0,H40/F40) -> 0 | H40: =H12-F26 -> 0 | I40: =S12 -> 0 | J40: =IF(I40=0,0,K40/I40) -> 0 | K40: =U12-I26 -> 0 | L40: =F40 -> 0 | M40: =IF(L40=0,0,N40/L40) -> 0 | N40: =L12-P26 -> 0 | O40: =I40 -> 0 | P40: =IF(O40=0,0,Q40/O40) -> 0 | Q40: =Y12-S26 -> 0
A41: =A13 -> 5 | B41: =B13 -> 0 | C41: =C13 -> 0 | D41: =D13 -> 0 | E41: =E13 -> 0 | F41: =F13 -> 0 | G41: =IF(F41=0,0,H41/F41) -> 0 | H41: =H13-F27 -> 0 | I41: =S13 -> 0 | J41: =IF(I41=0,0,K41/I41) -> 0 | K41: =U13-I27 -> 0 | L41: =F41 -> 0 | M41: =IF(L41=0,0,N41/L41) -> 0 | N41: =L13-P27 -> 0 | O41: =I41 -> 0 | P41: =IF(O41=0,0,Q41/O41) -> 0 | Q41: =Y13-S27 -> 0
A42: =A14 -> 6 | B42: =B14 -> 0 | C42: =C14 -> 0 | D42: =D14 -> 0 | E42: =E14 -> 0 | F42: =F14 -> 0 | G42: =IF(F42=0,0,H42/F42) -> 0 | H42: =H14-F28 -> 0 | I42: =S14 -> 0 | J42: =IF(I42=0,0,K42/I42) -> 0 | K42: =U14-I28 -> 0 | L42: =F42 -> 0 | M42: =IF(L42=0,0,N42/L42) -> 0 | N42: =L14-P28 -> 0 | O42: =I42 -> 0 | P42: =IF(O42=0,0,Q42/O42) -> 0 | Q42: =Y14-S28 -> 0
A43: =A15 -> 7 | B43: =B15 -> 0 | C43: =C15 -> 0 | D43: =D15 -> 0 | E43: =E15 -> 0 | F43: =F15 -> 0 | G43: =IF(F43=0,0,H43/F43) -> 0 | H43: =H15-F29 -> 0 | I43: =S15 -> 0 | J43: =IF(I43=0,0,K43/I43) -> 0 | K43: =U15-I29 -> 0 | L43: =F43 -> 0 | M43: =IF(L43=0,0,N43/L43) -> 0 | N43: =L15-P29 -> 0 | O43: =I43 -> 0 | P43: =IF(O43=0,0,Q43/O43) -> 0 | Q43: =Y15-S29 -> 0
A44: =A16 -> 8 | B44: =B16 -> 0 | C44: =C16 -> 0 | D44: =D16 -> 0 | E44: =E16 -> 0 | F44: =F16 -> 0 | G44: =IF(F44=0,0,H44/F44) -> 0 | H44: =H16-F30 -> 0 | I44: =S16 -> 0 | J44: =IF(I44=0,0,K44/I44) -> 0 | K44: =U16-I30 -> 0 | L44: =F44 -> 0 | M44: =IF(L44=0,0,N44/L44) -> 0 | N44: =L16-P30 -> 0 | O44: =I44 -> 0 | P44: =IF(O44=0,0,Q44/O44) -> 0 | Q44: =Y16-S30 -> 0
A45: =A17 -> 9 | B45: =B17 -> 0 | C45: =C17 -> 0 | D45: =D17 -> 0 | E45: =E17 -> 0 | F45: =F17 -> 0 | G45: =IF(F45=0,0,H45/F45) -> 0 | H45: =H17-F31 -> 0 | I45: =S17 -> 0 | J45: =IF(I45=0,0,K45/I45) -> 0 | K45: =U17-I31 -> 0 | L45: =F45 -> 0 | M45: =IF(L45=0,0,N45/L45) -> 0 | N45: =L17-P31 -> 0 | O45: =I45 -> 0 | P45: =IF(O45=0,0,Q45/O45) -> 0 | Q45: =Y17-S31 -> 0
A46: =A18 -> 10 | B46: =B18 -> 0 | C46: =C18 -> 0 | D46: =D18 -> 0 | E46: =E18 -> 0 | F46: =F18 -> 0 | G46: =IF(F46=0,0,H46/F46) -> 0 | H46: =H18-F32 -> 0 | I46: =S18 -> 0 | J46: =IF(I46=0,0,K46/I46) -> 0 | K46: =U18-I32 -> 0 | L46: =F46 -> 0 | M46: =IF(L46=0,0,N46/L46) -> 0 | N46: =L18-P32 -> 0 | O46: =I46 -> 0 | P46: =IF(O46=0,0,Q46/O46) -> 0 | Q46: =Y18-S32 -> 0
A47: =A19 -> 合计 | F47: =SUM(F37:F46) -> 0 | G47: =IF(F47=0,0,H47/F47) -> 0 | H47: =SUM(H37:H46) -> 0 | I47: =SUM(I37:I46) -> 0 | J47: =IF(I47=0,0,K47/I47) -> 0 | K47: =SUM(K37:K46) -> 0 | L47: =SUM(L37:L46) -> 0 | M47: =IF(L47=0,0,N47/L47) -> 0 | N47: =SUM(N37:N46) -> 0 | O47: =SUM(O37:O46) -> 0 | P47: =IF(O47=0,0,Q47/O47) -> 0 | Q47: =SUM(Q37:Q46) -> 0
A48: 审计说明：
A49: 1.开发产品的计价方法： | N49: 3.开发产品——**库龄较长的原因：
A50: 2.开发产品本期发生重大变动的原因： | N50: 4.计提跌价准备的主要项目及原因：

Sheet 九、开发成本F2-11
A1: 致同会计师事务所
A2: 存货明细表
A3: =底稿目录!A2 -> 被审计单位： | H3: =底稿目录!A4 -> 编制人： | P3: =底稿目录!A5 -> 编制日期： | U3: 索引号： | V3: =底稿目录!F16 -> F2-11
A4: =底稿目录!A3 -> 截止日：202X年12月21日 | H4: =底稿目录!A6 -> 复核人： | P4: =底稿目录!A7 -> 复核日期： | U4: 页 次：
A5: 九、开发成本
A6: （一）原值
A7: 序号 | B7: 项目名称 | C7: 总建筑面积/万平米 | D7: 开工时间 | E7: 预计竣工时间 | F7: 预计总投资 | G7: 未审数 | K7: 期初调整 | M7: 账项调整 | O7: 重分类调整 | Q7: 审定数 | U7: 库龄 | V7: 品质状况（正常、停建、毁损、报废等）
G8: 期初余额 | H8: 本期转入 | I8: 本期转出 | J8: 期末余额 | K8: 账项调整 | L8: 重分类调整 | M8: 本期转入 | N8: 本期转出 | O8: 本期转入 | P8: 本期转出 | Q8: 期初余额 | R8: 本期转入 | S8: 本期转出 | T8: 期末余额
A9: 1 | J9: =G9+H9-I9 -> 0 | Q9: =G9+K9+L9 -> 0 | R9: =H9+M9+O9 -> 0 | S9: =I9+N9+P9 -> 0 | T9: =Q9+R9-S9 -> 0
A10: 2 | J10: =G10+H10-I10 -> 0 | Q10: =G10+K10+L10 -> 0 | R10: =H10+M10+O10 -> 0 | S10: =I10+N10+P10 -> 0 | T10: =Q10+R10-S10 -> 0
A11: 3 | J11: =G11+H11-I11 -> 0 | Q11: =G11+K11+L11 -> 0 | R11: =H11+M11+O11 -> 0 | S11: =I11+N11+P11 -> 0 | T11: =Q11+R11-S11 -> 0
A12: 4 | J12: =G12+H12-I12 -> 0 | Q12: =G12+K12+L12 -> 0 | R12: =H12+M12+O12 -> 0 | S12: =I12+N12+P12 -> 0 | T12: =Q12+R12-S12 -> 0
A13: 5 | J13: =G13+H13-I13 -> 0 | Q13: =G13+K13+L13 -> 0 | R13: =H13+M13+O13 -> 0 | S13: =I13+N13+P13 -> 0 | T13: =Q13+R13-S13 -> 0
A14: 6 | J14: =G14+H14-I14 -> 0 | Q14: =G14+K14+L14 -> 0 | R14: =H14+M14+O14 -> 0 | S14: =I14+N14+P14 -> 0 | T14: =Q14+R14-S14 -> 0
A15: 7 | J15: =G15+H15-I15 -> 0 | Q15: =G15+K15+L15 -> 0 | R15: =H15+M15+O15 -> 0 | S15: =I15+N15+P15 -> 0 | T15: =Q15+R15-S15 -> 0
A16: 8 | J16: =G16+H16-I16 -> 0 | Q16: =G16+K16+L16 -> 0 | R16: =H16+M16+O16 -> 0 | S16: =I16+N16+P16 -> 0 | T16: =Q16+R16-S16 -> 0
A17: 9 | J17: =G17+H17-I17 -> 0 | Q17: =G17+K17+L17 -> 0 | R17: =H17+M17+O17 -> 0 | S17: =I17+N17+P17 -> 0 | T17: =Q17+R17-S17 -> 0
A18: 10 | J18: =G18+H18-I18 -> 0 | Q18: =G18+K18+L18 -> 0 | R18: =H18+M18+O18 -> 0 | S18: =I18+N18+P18 -> 0 | T18: =Q18+R18-S18 -> 0
A19: 合计 | F19: =SUM(F9:F18) -> 0 | G19: =SUM(G9:G18) -> 0 | H19: =SUM(H9:H18) -> 0 | I19: =SUM(I9:I18) -> 0 | J19: =SUM(J9:J18) -> 0 | K19: =SUM(K9:K18) -> 0 | L19: =SUM(L9:L18) -> 0 | M19: =SUM(M9:M18) -> 0 | ... T19: =SUM(T9:T18) -> 0
A20: （二）跌价准备
A21: 序号 | B21: 项目名称 | C21: 总建筑面积/万平米 | D21: 预计开工时间 | E21: 预计竣工时间 | F21: 预计总投资 | G21: 未审数 | K21: 期初调整 | M21: 账项调整 | O21: 重分类调整 | Q21: 审定数 | U21: 备注 | V21: 索引号
G22: 期初余额 | H22: 本期增加 | I22: 本期减少 | J22: 期末余额 | K22: 账项调整 | L22: 重分类调整 | M22: 本期增加 | N22: 本期减少 | O22: 本期增加 | P22: 本期减少 | Q22: 期初余额 | R22: 本期增加 | S22: 本期减少 | T22: 期末余额
A23: =A9 -> 1 | B23: =B9 -> 0 | C23: =C9 -> 0 | D23: =D9 -> 0 | E23: =E9 -> 0 | F23: =F9 -> 0 | J23: =G23+H23-I23 -> 0 | Q23: =G23+K23+L23 -> 0 | R23: =H23+M23+O23 -> 0 | S23: =I23+N23+P23 -> 0 | T23: =Q23+R23-S23 -> 0
A24: =A10 -> 2 | B24: =B10 -> 0 | C24: =C10 -> 0 | D24: =D10 -> 0 | E24: =E10 -> 0 | F24: =F10 -> 0 | J24: =G24+H24-I24 -> 0 | Q24: =G24+K24+L24 -> 0 | R24: =H24+M24+O24 -> 0 | S24: =I24+N24+P24 -> 0 | T24: =Q24+R24-S24 -> 0
A25: =A11 -> 3 | B25: =B11 -> 0 | C25: =C11 -> 0 | D25: =D11 -> 0 | E25: =E11 -> 0 | F25: =F11 -> 0 | J25: =G25+H25-I25 -> 0 | Q25: =G25+K25+L25 -> 0 | R25: =H25+M25+O25 -> 0 | S25: =I25+N25+P25 -> 0 | T25: =Q25+R25-S25 -> 0
A26: =A12 -> 4 | B26: =B12 -> 0 | C26: =C12 -> 0 | D26: =D12 -> 0 | E26: =E12 -> 0 | F26: =F12 -> 0 | J26: =G26+H26-I26 -> 0 | Q26: =G26+K26+L26 -> 0 | R26: =H26+M26+O26 -> 0 | S26: =I26+N26+P26 -> 0 | T26: =Q26+R26-S26 -> 0
A27: =A13 -> 5 | B27: =B13 -> 0 | C27: =C13 -> 0 | D27: =D13 -> 0 | E27: =E13 -> 0 | F27: =F13 -> 0 | J27: =G27+H27-I27 -> 0 | Q27: =G27+K27+L27 -> 0 | R27: =H27+M27+O27 -> 0 | S27: =I27+N27+P27 -> 0 | T27: =Q27+R27-S27 -> 0
A28: =A14 -> 6 | B28: =B14 -> 0 | C28: =C14 -> 0 | D28: =D14 -> 0 | E28: =E14 -> 0 | F28: =F14 -> 0 | J28: =G28+H28-I28 -> 0 | Q28: =G28+K28+L28 -> 0 | R28: =H28+M28+O28 -> 0 | S28: =I28+N28+P28 -> 0 | T28: =Q28+R28-S28 -> 0
A29: =A15 -> 7 | B29: =B15 -> 0 | C29: =C15 -> 0 | D29: =D15 -> 0 | E29: =E15 -> 0 | F29: =F15 -> 0 | J29: =G29+H29-I29 -> 0 | Q29: =G29+K29+L29 -> 0 | R29: =H29+M29+O29 -> 0 | S29: =I29+N29+P29 -> 0 | T29: =Q29+R29-S29 -> 0
A30: =A16 -> 8 | B30: =B16 -> 0 | C30: =C16 -> 0 | D30: =D16 -> 0 | E30: =E16 -> 0 | F30: =F16 -> 0 | J30: =G30+H30-I30 -> 0 | Q30: =G30+K30+L30 -> 0 | R30: =H30+M30+O30 -> 0 | S30: =I30+N30+P30 -> 0 | T30: =Q30+R30-S30 -> 0
A31: =A17 -> 9 | B31: =B17 -> 0 | C31: =C17 -> 0 | D31: =D17 -> 0 | E31: =E17 -> 0 | F31: =F17 -> 0 | J31: =G31+H31-I31 -> 0 | Q31: =G31+K31+L31 -> 0 | R31: =H31+M31+O31 -> 0 | S31: =I31+N31+P31 -> 0 | T31: =Q31+R31-S31 -> 0
A32: =A18 -> 10 | B32: =B18 -> 0 | C32: =C18 -> 0 | D32: =D18 -> 0 | E32: =E18 -> 0 | F32: =F18 -> 0 | J32: =G32+H32-I32 -> 0 | Q32: =G32+K32+L32 -> 0 | R32: =H32+M32+O32 -> 0 | S32: =I32+N32+P32 -> 0 | T32: =Q32+R32-S32 -> 0
A33: 合计 | F33: =SUM(F23:F32) -> 0 | G33: =SUM(G23:G32) -> 0 | H33: =SUM(H23:H32) -> 0 | I33: =SUM(I23:I32) -> 0 | J33: =SUM(J23:J32) -> 0 | K33: =SUM(K23:K32) -> 0 | L33: =SUM(L23:L32) -> 0 | M33: =SUM(M23:M32) -> 0 | ... T33: =SUM(T23:T32) -> 0
A34: （三）净值
A35: 序号 | B35: 项目名称 | C35: 总建筑面积/万平米 | D35: 预计开工时间 | E35: 预计竣工时间 | F35: 预计总投资 | G35: 未审数 | I35: 审定数
G36: 期初数 | H36: 期末数 | I36: 期初数 | J36: 期末数
A37: =A9 -> 1 | B37: =B9 -> 0 | C37: =C9 -> 0 | D37: =D9 -> 0 | E37: =E9 -> 0 | F37: =F9 -> 0 | G37: =G9-G23 -> 0 | H37: =J9-J23 -> 0 | I37: =Q9-Q23 -> 0 | J37: =T9-T23 -> 0
A38: =A10 -> 2 | B38: =B10 -> 0 | C38: =C10 -> 0 | D38: =D10 -> 0 | E38: =E10 -> 0 | F38: =F10 -> 0 | G38: =G10-G24 -> 0 | H38: =J10-J24 -> 0 | I38: =Q10-Q24 -> 0 | J38: =T10-T24 -> 0
A39: =A11 -> 3 | B39: =B11 -> 0 | C39: =C11 -> 0 | D39: =D11 -> 0 | E39: =E11 -> 0 | F39: =F11 -> 0 | G39: =G11-G25 -> 0 | H39: =J11-J25 -> 0 | I39: =Q11-Q25 -> 0 | J39: =T11-T25 -> 0
A40: =A12 -> 4 | B40: =B12 -> 0 | C40: =C12 -> 0 | D40: =D12 -> 0 | E40: =E12 -> 0 | F40: =F12 -> 0 | G40: =G12-G26 -> 0 | H40: =J12-J26 -> 0 | I40: =Q12-Q26 -> 0 | J40: =T12-T26 -> 0
A41: =A13 -> 5 | B41: =B13 -> 0 | C41: =C13 -> 0 | D41: =D13 -> 0 | E41: =E13 -> 0 | F41: =F13 -> 0 | G41: =G13-G27 -> 0 | H41: =J13-J27 -> 0 | I41: =Q13-Q27 -> 0 | J41: =T13-T27 -> 0
A42: =A14 -> 6 | B42: =B14 -> 0 | C42: =C14 -> 0 | D42: =D14 -> 0 | E42: =E14 -> 0 | F42: =F14 -> 0 | G42: =G14-G28 -> 0 | H42: =J14-J28 -> 0 | I42: =Q14-Q28 -> 0 | J42: =T14-T28 -> 0
A43: =A15 -> 7 | B43: =B15 -> 0 | C43: =C15 -> 0 | D43: =D15 -> 0 | E43: =E15 -> 0 | F43: =F15 -> 0 | G43: =G15-G29 -> 0 | H43: =J15-J29 -> 0 | I43: =Q15-Q29 -> 0 | J43: =T15-T29 -> 0
A44: =A16 -> 8 | B44: =B16 -> 0 | C44: =C16 -> 0 | D44: =D16 -> 0 | E44: =E16 -> 0 | F44: =F16 -> 0 | G44: =G16-G30 -> 0 | H44: =J16-J30 -> 0 | I44: =Q16-Q30 -> 0 | J44: =T16-T30 -> 0
A45: =A17 -> 9 | B45: =B17 -> 0 | C45: =C17 -> 0 | D45: =D17 -> 0 | E45: =E17 -> 0 | F45: =F17 -> 0 | G45: =G17-G31 -> 0 | H45: =J17-J31 -> 0 | I45: =Q17-Q31 -> 0 | J45: =T17-T31 -> 0
A46: =A18 -> 10 | B46: =B18 -> 0 | C46: =C18 -> 0 | D46: =D18 -> 0 | E46: =E18 -> 0 | F46: =F18 -> 0 | G46: =G18-G32 -> 0 | H46: =J18-J32 -> 0 | I46: =Q18-Q32 -> 0 | J46: =T18-T32 -> 0
A47: =A19 -> 合计 | F47: =SUM(F37:F46) -> 0 | G47: =SUM(G37:G46) -> 0 | H47: =SUM(H37:H46) -> 0 | I47: =SUM(I37:I46) -> 0 | J47: =SUM(J37:J46) -> 0
A48: 审计说明：
A49: 1.开发成本核算方法： | H49: 3.开发成本——**库龄较长的原因：
A50: 2.开发成本本期发生的重大变动及原因： | H50: 4.计提跌价准备的主要项目及原因：

Sheet 十、合同履约成本F2-12
A1: 致同会计师事务所
A2: 存货明细表
A3: =底稿目录!A2 -> 被审计单位： | E3: =底稿目录!A4 -> 编制人： | H3: =底稿目录!A5 -> 编制日期： | M3: 索引号： | N3: =底稿目录!F17 -> F2-12
A4: =底稿目录!A3 -> 截止日：202X年12月21日 | E4: =底稿目录!A6 -> 复核人： | H4: =底稿目录!A7 -> 复核日期： | M4: 页 次：
A5: 十、合同履约成本
A6: 序号 | B6: 项目编码 | C6: 项目名称 | D6: 开工时间 | E6: 预计竣工时间 | F6: 期初金额 | G6: 本期转入 | H6: 本期转出 | I6: 期末余额 | J6: 库龄 | N6: 品质状况（正常、停建、毁损、报废等）
H7: 金额 | I7: 金额 | J7: 1年以内 | K7: 1-2年 | L7: 2-3年 | M7: 3年以上
A8: 1 | I8: =F8+G8-H8 -> 0
A9: 2 | I9: =F9+G9-H9 -> 0
A10: 3 | I10: =F10+G10-H10 -> 0
A11: 4 | I11: =F11+G11-H11 -> 0
A12: 5 | I12: =F12+G12-H12 -> 0
A13: 6 | I13: =F13+G13-H13 -> 0
I14: =F14+G14-H14 -> 0
I15: =F15+G15-H15 -> 0
I16: =F16+G16-H16 -> 0
I17: =F17+G17-H17 -> 0
I18: =F18+G18-H18 -> 0
I19: =F19+G19-H19 -> 0
A20: 合计 | F20: =SUM(F8:F19) -> 0 | G20: =SUM(G8:G19) -> 0 | H20: =SUM(H8:H19) -> 0 | I20: =SUM(I8:I19) -> 0 | J20: =SUM(J8:J19) -> 0 | K20: =SUM(K8:K19) -> 0 | L20: =SUM(L8:L19) -> 0 | M20: =SUM(M8:M19) -> 0
A21: 减：存货跌价准备
A22: 合同履约成本净额 | F22: =F20-F21 -> 0 | I22: =I20-I21 -> 0
A23: 审计说明： | I23: =IF((I20-J20-K20-L20-M20)=0,"OK","库龄与期末金额不匹配") -> OK
A24: 1.合同履约成本核算方法： | G24: 3.合同履约成本**停建的原因：
A25: 2.合同履约成本本期发生的重大变动及原因： | G25: 4.计提跌价准备的主要项目及原因：

Sheet 十一、消耗性生物资产F2-13
A1: 致同会计师事务所
A2: 消耗性生物资产明细表
A3: =底稿目录!A2 -> 被审计单位： | F3: =底稿目录!A4 -> 编制人： | L3: =底稿目录!A5 -> 编制日期： | S3: 索引号： | T3: =底稿目录!F18 -> F2-13
A4: =底稿目录!A3 -> 截止日：202X年12月21日 | F4: =底稿目录!A6 -> 复核人： | L4: =底稿目录!A7 -> 复核日期： | S4: 页次：
A5: 十一、消耗性生物资产明细表
A6: 存货名称 | B6: 品种 | C6: 单位 | D6: 期初库存 | G6: 本期购进 | J6: 本期发出 | M6: 期末结存 | P6: 库龄 | T6: 状况
D7: 存栏数 | E7: 单价 | F7: 金额 | G7: 存栏数 | H7: 单价 | I7: 金额 | J7: 存栏数 | K7: 单价 | L7: 金额 | M7: 存栏数 | N7: 单价 | O7: 金额 | P7: 1年以内 | Q7: 1-2年 | R7: 2-3年 | S7: 3年以上
E9: =IF(D9=0,0,F9/D9) -> 0 | H9: =IF(G9=0,0,I9/G9) -> 0 | K9: =IF(J9=0,0,L9/J9) -> 0 | M9: =D9+G9-J9 -> 0 | N9: =IF(M9=0,0,O9/M9) -> 0 | O9: =F9+I9-L9 -> 0
E10: =IF(D10=0,0,F10/D10) -> 0 | H10: =IF(G10=0,0,I10/G10) -> 0 | K10: =IF(J10=0,0,L10/J10) -> 0 | M10: =D10+G10-J10 -> 0 | N10: =IF(M10=0,0,O10/M10) -> 0 | O10: =F10+I10-L10 -> 0
E11: =IF(D11=0,0,F11/D11) -> 0 | H11: =IF(G11=0,0,I11/G11) -> 0 | K11: =IF(J11=0,0,L11/J11) -> 0 | M11: =D11+G11-J11 -> 0 | N11: =IF(M11=0,0,O11/M11) -> 0 | O11: =F11+I11-L11 -> 0
E12: =IF(D12=0,0,F12/D12) -> 0 | H12: =IF(G12=0,0,I12/G12) -> 0 | K12: =IF(J12=0,0,L12/J12) -> 0 | M12: =D12+G12-J12 -> 0 | N12: =IF(M12=0,0,O12/M12) -> 0 | O12: =F12+I12-L12 -> 0
E13: =IF(D13=0,0,F13/D13) -> 0 | H13: =IF(G13=0,0,I13/G13) -> 0 | K13: =IF(J13=0,0,L13/J13) -> 0 | M13: =D13+G13-J13 -> 0 | N13: =IF(M13=0,0,O13/M13) -> 0 | O13: =F13+I13-L13 -> 0
E14: =IF(D14=0,0,F14/D14) -> 0 | H14: =IF(G14=0,0,I14/G14) -> 0 | K14: =IF(J14=0,0,L14/J14) -> 0 | M14: =D14+G14-J14 -> 0 | N14: =IF(M14=0,0,O14/M14) -> 0 | O14: =F14+I14-L14 -> 0
E15: =IF(D15=0,0,F15/D15) -> 0 | H15: =IF(G15=0,0,I15/G15) -> 0 | K15: =IF(J15=0,0,L15/J15) -> 0 | M15: =D15+G15-J15 -> 0 | N15: =IF(M15=0,0,O15/M15) -> 0 | O15: =F15+I15-L15 -> 0
E16: =IF(D16=0,0,F16/D16) -> 0 | H16: =IF(G16=0,0,I16/G16) -> 0 | K16: =IF(J16=0,0,L16/J16) -> 0 | M16: =D16+G16-J16 -> 0 | N16: =IF(M16=0,0,O16/M16) -> 0 | O16: =F16+I16-L16 -> 0
E17: =IF(D17=0,0,F17/D17) -> 0 | H17: =IF(G17=0,0,I17/G17) -> 0 | K17: =IF(J17=0,0,L17/J17) -> 0 | M17: =D17+G17-J17 -> 0 | N17: =IF(M17=0,0,O17/M17) -> 0 | O17: =F17+I17-L17 -> 0
E18: =IF(D18=0,0,F18/D18) -> 0 | H18: =IF(G18=0,0,I18/G18) -> 0 | K18: =IF(J18=0,0,L18/J18) -> 0 | M18: =D18+G18-J18 -> 0 | N18: =IF(M18=0,0,O18/M18) -> 0 | O18: =F18+I18-L18 -> 0
E19: =IF(D19=0,0,F19/D19) -> 0 | H19: =IF(G19=0,0,I19/G19) -> 0 | K19: =IF(J19=0,0,L19/J19) -> 0 | M19: =D19+G19-J19 -> 0 | N19: =IF(M19=0,0,O19/M19) -> 0 | O19: =F19+I19-L19 -> 0
E20: =IF(D20=0,0,F20/D20) -> 0 | H20: =IF(G20=0,0,I20/G20) -> 0 | K20: =IF(J20=0,0,L20/J20) -> 0 | M20: =D20+G20-J20 -> 0 | N20: =IF(M20=0,0,O20/M20) -> 0 | O20: =F20+I20-L20 -> 0
... E24: =IF(D24=0,0,F24/D24) -> 0 | H24: =IF(G24=0,0,I24/G24) -> 0 | K24: =IF(J24=0,0,L24/J24) -> 0 | M24: =D24+G24-J24 -> 0 | N24: =IF(M24=0,0,O24/M24) -> 0 | O24: =F24+I24-L24 -> 0
A25: 合计 | D25: -- | E25: -- | F25: =SUM(F9:F24) -> 0 | G25: -- | H25: -- | I25: =SUM(I9:I24) -> 0 | J25: -- | K25: -- | L25: =SUM(L9:L24) -> 0 | M25: -- | N25: -- | O25: =SUM(O9:O24) -> 0 | P25: =SUM(P9:P24) -> 0 | Q25: =SUM(Q9:Q24) -> 0 | R25: =SUM(R9:R24) -> 0 | S25: =SUM(S9:S24) -> 0
A26: （二）跌价准备 | O26: =IF((O25-P25-Q25-R25-S25)=0,"OK","库龄与期末金额不匹配") -> OK
A27: 存货名称 | B27: 品种 | C27: 未审数 | G27: 期初调整 | I27: 账项调整 | K27: 重分类调整 | M27: 审定数
C28: 期初余额 | D28: 本期增加 | E28: 本期减少 | F28: 期末余额 | G28: 账项调整 | H28: 重分类调整 | I28: 本期增加 | J28: 本期减少 | K28: 本期增加 | L28: 本期减少 | M28: 期初余额 | N28: 本期增加 | O28: 本期减少 | P28: 期末余额
A29: =A9 -> 0 | B29: =B9 -> 0 | F29: =C29+D29-E29 -> 0 | M29: =C29+G29+H29 -> 0 | N29: =D29+I29+K29 -> 0 | O29: =E29+J29+L29 -> 0 | P29: =M29+N29-O29 -> 0
A30: =A10 -> 0 | B30: =B10 -> 0 | F30: =C30+D30-E30 -> 0 | M30: =C30+G30+H30 -> 0 | N30: =D30+I30+K30 -> 0 | O30: =E30+J30+L30 -> 0 | P30: =M30+N30-O30 -> 0
A31: =A11 -> 0 | B31: =B11 -> 0 | F31: =C31+D31-E31 -> 0 | M31: =C31+G31+H31 -> 0 | N31: =D31+I31+K31 -> 0 | O31: =E31+J31+L31 -> 0 | P31: =M31+N31-O31 -> 0
A32: =A12 -> 0 | B32: =B12 -> 0 | F32: =C32+D32-E32 -> 0 | M32: =C32+G32+H32 -> 0 | N32: =D32+I32+K32 -> 0 | O32: =E32+J32+L32 -> 0 | P32: =M32+N32-O32 -> 0
A33: =A13 -> 0 | B33: =B13 -> 0 | F33: =C33+D33-E33 -> 0 | M33: =C33+G33+H33 -> 0 | N33: =D33+I33+K33 -> 0 | O33: =E33+J33+L33 -> 0 | P33: =M33+N33-O33 -> 0
A34: =A14 -> 0 | B34: =B14 -> 0 | F34: =C34+D34-E34 -> 0 | M34: =C34+G34+H34 -> 0 | N34: =D34+I34+K34 -> 0 | O34: =E34+J34+L34 -> 0 | P34: =M34+N34-O34 -> 0
A35: =A15 -> 0 | B35: =B15 -> 0 | F35: =C35+D35-E35 -> 0 | M35: =C35+G35+H35 -> 0 | N35: =D35+I35+K35 -> 0 | O35: =E35+J35+L35 -> 0 | P35: =M35+N35-O35 -> 0
A36: =A16 -> 0 | B36: =B16 -> 0 | F36: =C36+D36-E36 -> 0 | M36: =C36+G36+H36 -> 0 | N36: =D36+I36+K36 -> 0 | O36: =E36+J36+L36 -> 0 | P36: =M36+N36-O36 -> 0
A37: =A17 -> 0 | B37: =B17 -> 0 | F37: =C37+D37-E37 -> 0 | M37: =C37+G37+H37 -> 0 | N37: =D37+I37+K37 -> 0 | O37: =E37+J37+L37 -> 0 | P37: =M37+N37-O37 -> 0
A38: =A18 -> 0 | B38: =B18 -> 0 | F38: =C38+D38-E38 -> 0 | M38: =C38+G38+H38 -> 0 | N38: =D38+I38+K38 -> 0 | O38: =E38+J38+L38 -> 0 | P38: =M38+N38-O38 -> 0
A39: =A24 -> 0 | B39: =B19 -> 0 | F39: =C39+D39-E39 -> 0 | M39: =C39+G39+H39 -> 0 | N39: =D39+I39+K39 -> 0 | O39: =E39+J39+L39 -> 0 | P39: =M39+N39-O39 -> 0
A40: =A25 -> 合计 | B40: -- | C40: =SUM(C29:C39) -> 0 | D40: =SUM(D29:D39) -> 0 | E40: =SUM(E29:E39) -> 0 | F40: =C40+D40-E40 -> 0 | G40: =SUM(G29:G39) -> 0 | H40: =SUM(H29:H39) -> 0 | I40: =SUM(I29:I39) -> 0 | J40: =SUM(J29:J39) -> 0 | K40: =SUM(K29:K39) -> 0 | L40: =SUM(L29:L39) -> 0 | M40: =C40+G40+H40 -> 0 | N40: =D40+I40+K40 -> 0 | O40: =E40+J40+L40 -> 0 | P40: =M40+N40-O40 -> 0
A41: （三）净值
A42: 存货名称 | B42: 品种 | C42: 期初未审数 | F42: 期末未审数
C43: 存栏数 | D43: 单位成本 | E43: 期初数 | F43: 存栏数 | G43: 单位成本 | H43: 期末数
A44: =A29 -> 0 | B44: =B29 -> 0 | C44: =D9 -> 0 | D44: =IF(C44=0,0,E44/C44) -> 0 | E44: =F9-F29 -> 0 | F44: =M9 -> 0 | G44: =IF(F44=0,0,H44/F44) -> 0 | H44: =O9-P29 -> 0
A45: =A30 -> 0 | B45: =B30 -> 0 | C45: =D10 -> 0 | D45: =IF(C45=0,0,E45/C45) -> 0 | E45: =F10-F30 -> 0 | F45: =M10 -> 0 | G45: =IF(F45=0,0,H45/F45) -> 0 | H45: =O10-P30 -> 0
A46: =A31 -> 0 | B46: =B31 -> 0 | C46: =D11 -> 0 | D46: =IF(C46=0,0,E46/C46) -> 0 | E46: =F11-F31 -> 0 | F46: =M11 -> 0 | G46: =IF(F46=0,0,H46/F46) -> 0 | H46: =O11-P31 -> 0
A47: =A32 -> 0 | B47: =B32 -> 0 | C47: =D12 -> 0 | D47: =IF(C47=0,0,E47/C47) -> 0 | E47: =F12-F32 -> 0 | F47: =M12 -> 0 | G47: =IF(F47=0,0,H47/F47) -> 0 | H47: =O12-P32 -> 0
A48: =A33 -> 0 | B48: =B33 -> 0 | C48: =D13 -> 0 | D48: =IF(C48=0,0,E48/C48) -> 0 | E48: =F13-F33 -> 0 | F48: =M13 -> 0 | G48: =IF(F48=0,0,H48/F48) -> 0 | H48: =O13-P33 -> 0
A49: =A34 -> 0 | B49: =B34 -> 0 | C49: =D14 -> 0 | D49: =IF(C49=0,0,E49/C49) -> 0 | E49: =F14-F34 -> 0 | F49: =M14 -> 0 | G49: =IF(F49=0,0,H49/F49) -> 0 | H49: =O14-P34 -> 0
A50: =A35 -> 0 | B50: =B35 -> 0 | C50: =D15 -> 0 | D50: =IF(C50=0,0,E50/C50) -> 0 | E50: =F15-F35 -> 0 | F50: =M15 -> 0 | G50: =IF(F50=0,0,H50/F50) -> 0 | H50: =O15-P35 -> 0
A51: =A36 -> 0 | B51: =B36 -> 0 | C51: =D16 -> 0 | D51: =IF(C51=0,0,E51/C51) -> 0 | E51: =F16-F36 -> 0 | F51: =M16 -> 0 | G51: =IF(F51=0,0,H51/F51) -> 0 | H51: =O16-P36 -> 0
A52: =A37 -> 0 | B52: =B37 -> 0 | C52: =D17 -> 0 | D52: =IF(C52=0,0,E52/C52) -> 0 | E52: =F17-F37 -> 0 | F52: =M17 -> 0 | G52: =IF(F52=0,0,H52/F52) -> 0 | H52: =O17-P37 -> 0
A53: =A38 -> 0 | B53: =B38 -> 0 | C53: =D18 -> 0 | D53: =IF(C53=0,0,E53/C53) -> 0 | E53: =F18-F38 -> 0 | F53: =M18 -> 0 | G53: =IF(F53=0,0,H53/F53) -> 0 | H53: =O18-P38 -> 0
A54: =A39 -> 0 | B54: =B39 -> 0 | C54: =D19 -> 0 | D54: =IF(C54=0,0,E54/C54) -> 0 | E54: =F19-F39 -> 0 | F54: =M19 -> 0 | G54: =IF(F54=0,0,H54/F54) -> 0 | H54: =O19-P39 -> 0
A55: =A25 -> 合计 | B55: -- | C55: =SUM(C44:C54) -> 0 | D55: =SUM(D44:D54) -> 0 | E55: =SUM(E44:E54) -> 0 | F55: =SUM(F44:F54) -> 0 | G55: =SUM(G44:G54) -> 0 | H55: =SUM(H44:H54) -> 0
A56: 审计说明：

Sheet 调整分录汇总F2-14
A1: 致同会计师事务所
A2: 存货及跌价准备调整分录汇总表
A3: =底稿目录!A2 -> 被审计单位： | D3: =底稿目录!A4 -> 编制人： | G3: =底稿目录!A5 -> 编制日期： | I3: 索引号： | J3: =底稿目录!F19 -> F2-14
A4: =底稿目录!A3 -> 截止日：202X年12月21日 | D4: =底稿目录!A6 -> 复核人： | G4: =底稿目录!A7 -> 复核日期： | I4: 页 次：
A5: 调整事项说明 | B5: 类别（报表调整/账项调整/其他） | C5: 报表项目 | D5: 科目名称 | E5: 附注项目 | F5: …… | G5: 借方调整金额 | H5: 贷方调整金额 | I5: 索引 | J5: 备注
A22: 提示：本底稿适用于调整分录较多、较复杂的项目，且仅列示与本报表项目相关的审计调整。项目组可根据项目实际情况选择是否使用该底稿。

Sheet GT_Custom
A1: C1 | B1: Custom 1
A2: C2 | B2: Custom 2
A3: C3 | B3: Custom 3
A4: C4 | B4: Custom 4
A5: C5 | B5: Custom 5
A6: C6 | B6: Custom 6
A7: C7 | B7: Custom 7
A8: C8 | B8: Custom 8
