Workbook
Name bs: {#N/A,#N/A,FALSE,"BBPREP"}
Name bs: {#N/A,#N/A,FALSE,"BBPREP"}
Name bs: {#N/A,#N/A,FALSE,"BBPREP"}
Name bs_1: {#N/A,#N/A,FALSE,"BBPREP"}
Name bs_1: {#N/A,#N/A,FALSE,"BBPREP"}

Sheet 底稿目录
A1: 底稿开列时，可先在以下单元格填写有关内容，以便其他底稿引用有关数据： | D1: 序号 | E1: 内容 | F1: 索引号
A2: 被审计单位： | D2: 1 | E2: 存货总体分析表 | F2: F2-18
A3: 截止日：202X年12月31日 | D3: =D2+1 -> 2 | E3: 存货产销量变动分析表 | F3: F2-19
A4: 编制人： | D4: =D3+1 -> 3 | E4: 产成品单位成本年度比较表 | F4: F2-20
A5: 编制日期：
A6: 复核人：
A7: 复核日期：

Sheet GT_Custom
A1: C1 | B1: Custom 1
A2: C2 | B2: Custom 2
A3: C3 | B3: Custom 3
A4: C4 | B4: Custom 4
A5: C5 | B5: Custom 5
A6: C6 | B6: Custom 6
A7: C7 | B7: Custom 7
A8: C8 | B8: Custom 8

Sheet 存货总体分析表F2-18
A1: 致同会计师事务所
A2: 存货总体分析表
A3: =底稿目录!A2 -> 被审计单位： | C3: =底稿目录!A4 -> 编制人： | E3: =底稿目录!A5 -> 编制日期： | H3: 索引号： | I3: =底稿目录!F2 -> F2-18
A4: =底稿目录!A3 -> 截止日：202X年12月31日 | C4: =底稿目录!A6 -> 复核人： | E4: =底稿目录!A7 -> 复核日期： | H4: 页 次：
A5: 一、审计目标：
A6: 1.资产负债表中记录的存货是存在的，且已经记录在恰当的账户中
A7: 2.存货以恰当的金额包括在财务报表中，与之相关的计价或分摊调整已恰当记录，相关披露已得到恰当计量和描述
A8: 二、审计过程：
A9: A、存货构成分析
A10: 存货项目 | C10: 20X5/12/31 | E10: 20X4/12/31 | G10: 20X3/12/31 | I10: 是否异常
C11: 金额 | D11: 结构比 | E11: 金额 | F11: 结构比 | G11: 金额 | H11: 结构比
A12: ='[1]明细汇总表F2-2'!A17 -> 原材料 | D12: =IF($C$25=0,0,C12/$C$25) -> 0 | F12: =IF($E$25=0,0,E12/$E$25) -> 0 | H12: =IF($G$25=0,0,G12/$G$25) -> 0
A13: ='[1]明细汇总表F2-2'!A18 -> 材料采购/在途物资 | D13: =IF($C$25=0,0,C13/$C$25) -> 0 | F13: =IF($E$25=0,0,E13/$E$25) -> 0 | H13: =IF($G$25=0,0,#REF!/$G$25) -> 0
A14: ='[1]明细汇总表F2-2'!A19 -> 周转材料/低值易耗品/包装物 | D14: =IF($C$25=0,0,C14/$C$25) -> 0 | F14: =IF($E$25=0,0,E14/$E$25) -> 0 | H14: =IF($G$25=0,0,G29/$G$25) -> 0
A15: ='[1]明细汇总表F2-2'!A20 -> 在产品 | D15: =IF($C$25=0,0,C15/$C$25) -> 0 | F15: =IF($E$25=0,0,E15/$E$25) -> 0 | H15: =IF($G$25=0,0,G30/$G$25) -> 0
A16: ='[1]明细汇总表F2-2'!A21 -> 自制半成品 | D16: =IF($C$25=0,0,C16/$C$25) -> 0 | F16: =IF($E$25=0,0,E16/$E$25) -> 0 | H16: =IF($G$25=0,0,G32/$G$25) -> 0
A17: ='[1]明细汇总表F2-2'!A22 -> 委托加工物资 | D17: =IF($C$25=0,0,C17/$C$25) -> 0 | F17: =IF($E$25=0,0,E17/$E$25) -> 0 | H17: =IF($G$25=0,0,#REF!/$G$25) -> 0
A18: ='[1]明细汇总表F2-2'!A23 -> 库存商品 | D18: =IF($C$25=0,0,C18/$C$25) -> 0 | F18: =IF($E$25=0,0,E18/$E$25) -> 0 | H18: =IF($G$25=0,0,#REF!/$G$25) -> 0
A19: ='[1]明细汇总表F2-2'!A24 -> 发出商品 | D19: =IF($C$25=0,0,C19/$C$25) -> 0 | F19: =IF($E$25=0,0,E19/$E$25) -> 0 | H19: =IF($G$25=0,0,#REF!/$G$25) -> 0
A20: ='[1]明细汇总表F2-2'!A25 -> 开发产品 | D20: =IF($C$25=0,0,C20/$C$25) -> 0 | F20: =IF($E$25=0,0,E20/$E$25) -> 0 | H20: =IF($G$25=0,0,#REF!/$G$25) -> 0
A21: ='[1]明细汇总表F2-2'!A26 -> 开发成本 | D21: =IF($C$25=0,0,C21/$C$25) -> 0 | F21: =IF($E$25=0,0,E21/$E$25) -> 0 | H21: =IF($G$25=0,0,#REF!/$G$25) -> 0
A22: ='[1]明细汇总表F2-2'!A27 -> 合同履约成本 | D22: =IF($C$25=0,0,C22/$C$25) -> 0 | F22: =IF($E$25=0,0,E22/$E$25) -> 0 | H22: =IF($G$25=0,0,#REF!/$G$25) -> 0
A23: ='[1]明细汇总表F2-2'!A28 -> 消耗性生物资产 | D23: =IF($C$25=0,0,C23/$C$25) -> 0 | F23: =IF($E$25=0,0,E23/$E$25) -> 0 | H23: =IF($G$25=0,0,#REF!/$G$25) -> 0
A24: ='[1]明细汇总表F2-2'!A29 -> 数据资源 | D24: =IF($C$25=0,0,C24/$C$25) -> 0 | F24: =IF($E$25=0,0,E24/$E$25) -> 0 | H24: =IF($G$25=0,0,#REF!/$G$25) -> 0
A25: 合计 | C25: =SUM(C12:C23) -> 0 | D25: =SUM(D12:D23) -> 0 | E25: =SUM(E12:E23) -> 0 | F25: =SUM(F12:F23) -> 0 | G25: =SUM(G12:G23) -> 0 | H25: =SUM(H12:H23) -> 0 | I25: ——
A26: 审计说明：
A27: 异常原因
A29: B、存货指标分析（三期数据对比）
A30: 指标 | C30: 20X5年 | E30: 20X4年 | G30: 20X3年 | I30: 是否异常
C31: 指标值 | D31: 变动率 | E31: 指标值 | F31: 变动率 | G31: 指标值 | H31: 变动率
A32: 存货周转率（销售成本÷平均存货） | D32: =IF(E32=0,0,(C32-E32)/E32) -> 0 | F32: =IF(G32=0,0,(E32-G32)/G32) -> 0 | H32: ——
A33: 存货平均天数（365天÷存货周转率） | D33: =IF(E33=0,0,(C33-E33)/E33) -> 0 | F33: =IF(G33=0,0,(E33-G33)/G33) -> 0 | H33: ——
A34: 存货跌价准备占存货余额比例 （存货跌价准备÷存货余额） | D34: =IF(E34=0,0,(C34-E34)/E34) -> 0 | F34: =IF(G34=0,0,(E34-G34)/G34) -> 0 | H34: ——
A35: 存货占流动资产比例 （平均存货÷平均流动资产） | D35: =IF(E35=0,0,(C35-E35)/E35) -> 0 | F35: =IF(G35=0,0,(E35-G35)/G35) -> 0 | H35: ——
A36: 废率（核销存货/平均存货余额） | D36: =IF(E36=0,0,(C36-E36)/E36) -> 0 | F36: =IF(G36=0,0,(E36-G36)/G36) -> 0 | H36: ——
A37: 审计说明：
A38: 异常原因
A40: C、存货指标分析（与同行业数据对比）
A41: 指标 | C41: 20X5年 | E41: 行业平均 | F41: 行业公司A | G41: 行业公司B | H41: 行业公司C | I41: 是否异常
C42: 指标值 | D42: 偏离
A43: 存货周转率（销售成本÷平均存货） | D43: =IF(E43=0,0,(C43-E43)/E43) -> 0
A44: 存货平均天数（365天÷存货周转率） | D44: =IF(E44=0,0,(C44-E44)/E44) -> 0
A45: 存货跌价准备占存货余额比例 （存货跌价准备÷存货余额） | D45: =IF(E45=0,0,(C45-E45)/E45) -> 0 | J45: 对存货跌价准备错报风险高的项目，可拆分为原材料、产成品等跌价准备分别占原材料、产成品等余额的比例与同行业对比分析
A46: 存货占流动资产比例 （平均存货÷平均流动资产） | D46: =IF(E46=0,0,(C46-E46)/E46) -> 0
A47: 审计说明：
A48: 异常原因
A50: D、存货周转率分析（主要产品大类三期数对比）
A51: 产品名称 | B51: 20X5年平均存货 | C51: 20X5年销售成本 | D51: 20X5年 | F51: 20X4年 | H51: 20X3年存货周转率 | I51: 是否异常
D52: 存货周转率 | E52: 变动率 | F52: 存货周转率 | G52: 变动率
D53: =IF(C53=0,0,C53/B53) -> 0 | E53: =IF(F53=0,0,(D53-F53)/F53) -> 0 | G53: =IF(H53=0,0,(F53-H53)/H53) -> 0
D54: =IF(C54=0,0,C54/B54) -> 0 | E54: =IF(F54=0,0,(D54-F54)/F54) -> 0 | G54: =IF(H54=0,0,(F54-H54)/H54) -> 0
D55: =IF(C55=0,0,C55/B55) -> 0 | E55: =IF(F55=0,0,(D55-F55)/F55) -> 0 | G55: =IF(H55=0,0,(F55-H55)/H55) -> 0
D56: =IF(C56=0,0,C56/B56) -> 0 | E56: =IF(F56=0,0,(D56-F56)/F56) -> 0 | G56: =IF(H56=0,0,(F56-H56)/H56) -> 0
D57: =IF(C57=0,0,C57/B57) -> 0 | E57: =IF(F57=0,0,(D57-F57)/F57) -> 0 | G57: =IF(H57=0,0,(F57-H57)/H57) -> 0
D58: =IF(C58=0,0,C58/B58) -> 0 | E58: =IF(F58=0,0,(D58-F58)/F58) -> 0 | G58: =IF(H58=0,0,(F58-H58)/H58) -> 0
D59: =IF(C59=0,0,C59/B59) -> 0 | E59: =IF(F59=0,0,(D59-F59)/F59) -> 0 | G59: =IF(H59=0,0,(F59-H59)/H59) -> 0
D60: =IF(C60=0,0,C60/B60) -> 0 | E60: =IF(F60=0,0,(D60-F60)/F60) -> 0 | G60: =IF(H60=0,0,(F60-H60)/H60) -> 0
A61: 审计说明：
A62: 异常原因
A65: 四、审计结论：
A69: 提示：
A70: 1.计算结果可与同行业或以前期间对比。
A71: 2.存货周转天数的含义，就是从原材料购入开始，经过仓储、生产、再仓储到产成品售出那一天，大概是多少天。
A72: 可分别计算不同类别存货的周转率（原材料、半成品、产成品etc）。

Sheet 存货产销量变动分析表F2-19
A1: 致同会计师事务所
A2: 存货产销量变动分析表
A3: =底稿目录!A2 -> 被审计单位： | E3: =底稿目录!A4 -> 编制人： | K3: =底稿目录!A5 -> 编制日期： | O3: 索引号： | P3: =底稿目录!F3 -> F2-19
A4: =底稿目录!A3 -> 截止日：202X年12月31日 | E4: =底稿目录!A6 -> 复核人： | K4: =底稿目录!A7 -> 复核日期： | O4: 页 次：
A5: 一、审计目标：
A6: 1.资产负债表中记录的存货是存在的，且已经记录在恰当的账户中
A7: 2.存货以恰当的金额包括在财务报表中，与之相关的计价或分摊调整已恰当记录，相关披露已得到恰当计量和描述
A8: 二、审计过程：
A9: 1.获取主要库存商品各月产量及原材料消耗量，测算报告期主要产品各月产耗比，与以前年度、可比公司、行业经验值进行比较，分析变动趋势及合理性；
A10: 2.结合存货监盘和对仓库实物账的核对，分析原材料实际投入量是否与财务账面记录一致。
A11: 库存商品各月产量统计
A12: 项目 | B12: 1月 | C12: 2月 | D12: 3月 | E12: 4月 | F12: 5月 | G12: 6月 | H12: 7月 | I12: 8月 | J12: 9月 | K12: 10月 | L12: 11月 | M12: 12月 | N12: 合计 | O12: 上年度 | P12: 变动率
N13: =SUM(B13:M13) -> 0 | P13: =IF(AND(O13=0,N13-O13=0),0,IF(AND(O13=0,N13-O13>0),1,(N13-O13)/O13)) -> 0
N14: =SUM(B14:M14) -> 0 | P14: =IF(AND(O14=0,N14-O14=0),0,IF(AND(O14=0,N14-O14>0),1,(N14-O14)/O14)) -> 0
N15: =SUM(B15:M15) -> 0 | P15: =IF(AND(O15=0,N15-O15=0),0,IF(AND(O15=0,N15-O15>0),1,(N15-O15)/O15)) -> 0
N16: =SUM(B16:M16) -> 0 | P16: =IF(AND(O16=0,N16-O16=0),0,IF(AND(O16=0,N16-O16>0),1,(N16-O16)/O16)) -> 0
N17: =SUM(B17:M17) -> 0 | P17: =IF(AND(O17=0,N17-O17=0),0,IF(AND(O17=0,N17-O17>0),1,(N17-O17)/O17)) -> 0
N18: =SUM(B18:M18) -> 0 | P18: =IF(AND(O18=0,N18-O18=0),0,IF(AND(O18=0,N18-O18>0),1,(N18-O18)/O18)) -> 0
A19: 合计 | B19: =SUM(B13:B18) -> 0 | C19: =SUM(C13:C18) -> 0 | D19: =SUM(D13:D18) -> 0 | E19: =SUM(E13:E18) -> 0 | F19: =SUM(F13:F18) -> 0 | G19: =SUM(G13:G18) -> 0 | H19: =SUM(H13:H18) -> 0 | I19: =SUM(I13:I18) -> 0 | ... M19: =SUM(M13:M18) -> 0 | N19: =SUM(B19:M19) -> 0 | O19: =SUM(C19:N19) -> 0 | P19: =IF(AND(O19=0,N19-O19=0),0,IF(AND(O19=0,N19-O19>0),1,(N19-O19)/O19)) -> 0
A20: 库存商品各月销售数量统计
A21: 项目 | B21: 1月 | C21: 2月 | D21: 3月 | E21: 4月 | F21: 5月 | G21: 6月 | H21: 7月 | I21: 8月 | J21: 9月 | K21: 10月 | L21: 11月 | M21: 12月 | N21: 合计 | O21: 上年度 | P21: 变动率
A22: =A13 -> 0 | N22: =SUM(B22:M22) -> 0 | P22: =IF(AND(O22=0,N22-O22=0),0,IF(AND(O22=0,N22-O22>0),1,(N22-O22)/O22)) -> 0
A23: =A14 -> 0 | N23: =SUM(B23:M23) -> 0 | P23: =IF(AND(O23=0,N23-O23=0),0,IF(AND(O23=0,N23-O23>0),1,(N23-O23)/O23)) -> 0
A24: =A15 -> 0 | N24: =SUM(B24:M24) -> 0 | P24: =IF(AND(O24=0,N24-O24=0),0,IF(AND(O24=0,N24-O24>0),1,(N24-O24)/O24)) -> 0
A25: =A16 -> 0 | N25: =SUM(B25:M25) -> 0 | P25: =IF(AND(O25=0,N25-O25=0),0,IF(AND(O25=0,N25-O25>0),1,(N25-O25)/O25)) -> 0
A26: =A17 -> 0 | N26: =SUM(B26:M26) -> 0 | P26: =IF(AND(O26=0,N26-O26=0),0,IF(AND(O26=0,N26-O26>0),1,(N26-O26)/O26)) -> 0
A27: =A18 -> 0 | N27: =SUM(B27:M27) -> 0 | P27: =IF(AND(O27=0,N27-O27=0),0,IF(AND(O27=0,N27-O27>0),1,(N27-O27)/O27)) -> 0
A28: 合计 | B28: =SUM(B22:B27) -> 0 | C28: =SUM(C22:C27) -> 0 | D28: =SUM(D22:D27) -> 0 | E28: =SUM(E22:E27) -> 0 | F28: =SUM(F22:F27) -> 0 | G28: =SUM(G22:G27) -> 0 | H28: =SUM(H22:H27) -> 0 | I28: =SUM(I22:I27) -> 0 | ... M28: =SUM(M22:M27) -> 0 | N28: =SUM(B28:M28) -> 0 | O28: =SUM(C28:N28) -> 0 | P28: =IF(AND(O28=0,N28-O28=0),0,IF(AND(O28=0,N28-O28>0),1,(N28-O28)/O28)) -> 0
A29: 库存商品各月销售量与产量占比分析
A30: 项目 | B30: 1月 | C30: 2月 | D30: 3月 | E30: 4月 | F30: 5月 | G30: 6月 | H30: 7月 | I30: 8月 | J30: 9月 | K30: 10月 | L30: 11月 | M30: 12月 | N30: 合计 | O30: 上年度 | P30: 变动率
A31: =A13 -> 0 | B31: =IF(B13=0,0,B22/B13) -> 0 | C31: =IF(C13=0,0,C22/C13) -> 0 | D31: =IF(D13=0,0,D22/D13) -> 0 | E31: =IF(E13=0,0,E22/E13) -> 0 | F31: =IF(F13=0,0,F22/F13) -> 0 | G31: =IF(G13=0,0,G22/G13) -> 0 | H31: =IF(H13=0,0,H22/H13) -> 0 | I31: =IF(I13=0,0,I22/I13) -> 0 | ... O31: =IF(O13=0,0,O22/O13) -> 0 | P31: =IF(AND(O31=0,N31-O31=0),0,IF(AND(O31=0,N31-O31>0),1,(N31-O31)/O31)) -> 0
A32: =A14 -> 0 | B32: =IF(B14=0,0,B23/B14) -> 0 | C32: =IF(C14=0,0,C23/C14) -> 0 | D32: =IF(D14=0,0,D23/D14) -> 0 | E32: =IF(E14=0,0,E23/E14) -> 0 | F32: =IF(F14=0,0,F23/F14) -> 0 | G32: =IF(G14=0,0,G23/G14) -> 0 | H32: =IF(H14=0,0,H23/H14) -> 0 | I32: =IF(I14=0,0,I23/I14) -> 0 | ... O32: =IF(O14=0,0,O23/O14) -> 0 | P32: =IF(AND(O32=0,N32-O32=0),0,IF(AND(O32=0,N32-O32>0),1,(N32-O32)/O32)) -> 0
A33: =A15 -> 0 | B33: =IF(B15=0,0,B24/B15) -> 0 | C33: =IF(C15=0,0,C24/C15) -> 0 | D33: =IF(D15=0,0,D24/D15) -> 0 | E33: =IF(E15=0,0,E24/E15) -> 0 | F33: =IF(F15=0,0,F24/F15) -> 0 | G33: =IF(G15=0,0,G24/G15) -> 0 | H33: =IF(H15=0,0,H24/H15) -> 0 | I33: =IF(I15=0,0,I24/I15) -> 0 | ... O33: =IF(O15=0,0,O24/O15) -> 0 | P33: =IF(AND(O33=0,N33-O33=0),0,IF(AND(O33=0,N33-O33>0),1,(N33-O33)/O33)) -> 0
A34: =A16 -> 0 | B34: =IF(B16=0,0,B25/B16) -> 0 | C34: =IF(C16=0,0,C25/C16) -> 0 | D34: =IF(D16=0,0,D25/D16) -> 0 | E34: =IF(E16=0,0,E25/E16) -> 0 | F34: =IF(F16=0,0,F25/F16) -> 0 | G34: =IF(G16=0,0,G25/G16) -> 0 | H34: =IF(H16=0,0,H25/H16) -> 0 | I34: =IF(I16=0,0,I25/I16) -> 0 | ... O34: =IF(O16=0,0,O25/O16) -> 0 | P34: =IF(AND(O34=0,N34-O34=0),0,IF(AND(O34=0,N34-O34>0),1,(N34-O34)/O34)) -> 0
A35: =A17 -> 0 | B35: =IF(B17=0,0,B26/B17) -> 0 | C35: =IF(C17=0,0,C26/C17) -> 0 | D35: =IF(D17=0,0,D26/D17) -> 0 | E35: =IF(E17=0,0,E26/E17) -> 0 | F35: =IF(F17=0,0,F26/F17) -> 0 | G35: =IF(G17=0,0,G26/G17) -> 0 | H35: =IF(H17=0,0,H26/H17) -> 0 | I35: =IF(I17=0,0,I26/I17) -> 0 | ... O35: =IF(O17=0,0,O26/O17) -> 0 | P35: =IF(AND(O35=0,N35-O35=0),0,IF(AND(O35=0,N35-O35>0),1,(N35-O35)/O35)) -> 0
A36: =A18 -> 0 | B36: =IF(B18=0,0,B27/B18) -> 0 | C36: =IF(C18=0,0,C27/C18) -> 0 | D36: =IF(D18=0,0,D27/D18) -> 0 | E36: =IF(E18=0,0,E27/E18) -> 0 | F36: =IF(F18=0,0,F27/F18) -> 0 | G36: =IF(G18=0,0,G27/G18) -> 0 | H36: =IF(H18=0,0,H27/H18) -> 0 | I36: =IF(I18=0,0,I27/I18) -> 0 | ... O36: =IF(O18=0,0,O27/O18) -> 0 | P36: =IF(AND(O36=0,N36-O36=0),0,IF(AND(O36=0,N36-O36>0),1,(N36-O36)/O36)) -> 0
A37: 合计 | B37: =IF(B19=0,0,B28/B19) -> 0 | C37: =IF(C19=0,0,C28/C19) -> 0 | D37: =IF(D19=0,0,D28/D19) -> 0 | E37: =IF(E19=0,0,E28/E19) -> 0 | F37: =IF(F19=0,0,F28/F19) -> 0 | G37: =IF(G19=0,0,G28/G19) -> 0 | H37: =IF(H19=0,0,H28/H19) -> 0 | I37: =IF(I19=0,0,I28/I19) -> 0 | ... O37: =IF(O19=0,0,O28/O19) -> 0 | P37: =IF(AND(O37=0,N37-O37=0),0,IF(AND(O37=0,N37-O37>0),1,(N37-O37)/O37)) -> 0
A38: 原材料各月采购统计
A39: 项目 | B39: 1月 | C39: 2月 | D39: 3月 | E39: 4月 | F39: 5月 | G39: 6月 | H39: 7月 | I39: 8月 | J39: 9月 | K39: 10月 | L39: 11月 | M39: 12月 | N39: 合计 | O39: 上年度 | P39: 变动率
A40: =A13 -> 0 | N40: =SUM(B40:M40) -> 0 | P40: =IF(AND(O40=0,N40-O40=0),0,IF(AND(O40=0,N40-O40>0),1,(N40-O40)/O40)) -> 0
A41: =A14 -> 0 | N41: =SUM(B41:M41) -> 0 | P41: =IF(AND(O41=0,N41-O41=0),0,IF(AND(O41=0,N41-O41>0),1,(N41-O41)/O41)) -> 0
A42: =A15 -> 0 | N42: =SUM(B42:M42) -> 0 | P42: =IF(AND(O42=0,N42-O42=0),0,IF(AND(O42=0,N42-O42>0),1,(N42-O42)/O42)) -> 0
A43: =A16 -> 0 | N43: =SUM(B43:M43) -> 0 | P43: =IF(AND(O43=0,N43-O43=0),0,IF(AND(O43=0,N43-O43>0),1,(N43-O43)/O43)) -> 0
A44: =A17 -> 0 | N44: =SUM(B44:M44) -> 0 | P44: =IF(AND(O44=0,N44-O44=0),0,IF(AND(O44=0,N44-O44>0),1,(N44-O44)/O44)) -> 0
A45: =A18 -> 0 | N45: =SUM(B45:M45) -> 0 | P45: =IF(AND(O45=0,N45-O45=0),0,IF(AND(O45=0,N45-O45>0),1,(N45-O45)/O45)) -> 0
A46: 合计 | B46: =SUM(B40:B45) -> 0 | C46: =SUM(C40:C45) -> 0 | D46: =SUM(D40:D45) -> 0 | E46: =SUM(E40:E45) -> 0 | F46: =SUM(F40:F45) -> 0 | G46: =SUM(G40:G45) -> 0 | H46: =SUM(H40:H45) -> 0 | I46: =SUM(I40:I45) -> 0 | ... M46: =SUM(M40:M45) -> 0 | N46: =SUM(B46:M46) -> 0 | O46: =SUM(C46:N46) -> 0 | P46: =IF(AND(O46=0,N46-O46=0),0,IF(AND(O46=0,N46-O46>0),1,(N46-O46)/O46)) -> 0
A47: 原材料各月耗用统计
A48: 项目 | B48: 1月 | C48: 2月 | D48: 3月 | E48: 4月 | F48: 5月 | G48: 6月 | H48: 7月 | I48: 8月 | J48: 9月 | K48: 10月 | L48: 11月 | M48: 12月 | N48: 合计 | O48: 上年度 | P48: 变动率
A49: =A13 -> 0 | N49: =SUM(B49:M49) -> 0 | P49: =IF(AND(O49=0,N49-O49=0),0,IF(AND(O49=0,N49-O49>0),1,(N49-O49)/O49)) -> 0
A50: =A14 -> 0 | N50: =SUM(B50:M50) -> 0 | P50: =IF(AND(O50=0,N50-O50=0),0,IF(AND(O50=0,N50-O50>0),1,(N50-O50)/O50)) -> 0
A51: =A15 -> 0 | N51: =SUM(B51:M51) -> 0 | P51: =IF(AND(O51=0,N51-O51=0),0,IF(AND(O51=0,N51-O51>0),1,(N51-O51)/O51)) -> 0
A52: =A16 -> 0 | N52: =SUM(B52:M52) -> 0 | P52: =IF(AND(O52=0,N52-O52=0),0,IF(AND(O52=0,N52-O52>0),1,(N52-O52)/O52)) -> 0
A53: =A17 -> 0 | N53: =SUM(B53:M53) -> 0 | P53: =IF(AND(O53=0,N53-O53=0),0,IF(AND(O53=0,N53-O53>0),1,(N53-O53)/O53)) -> 0
A54: =A18 -> 0 | N54: =SUM(B54:M54) -> 0 | P54: =IF(AND(O54=0,N54-O54=0),0,IF(AND(O54=0,N54-O54>0),1,(N54-O54)/O54)) -> 0
A55: 合计 | B55: =SUM(B49:B54) -> 0 | C55: =SUM(C49:C54) -> 0 | D55: =SUM(D49:D54) -> 0 | E55: =SUM(E49:E54) -> 0 | F55: =SUM(F49:F54) -> 0 | G55: =SUM(G49:G54) -> 0 | H55: =SUM(H49:H54) -> 0 | I55: =SUM(I49:I54) -> 0 | ... M55: =SUM(M49:M54) -> 0 | N55: =SUM(B55:M55) -> 0 | O55: =SUM(C55:N55) -> 0 | P55: =IF(AND(O55=0,N55-O55=0),0,IF(AND(O55=0,N55-O55>0),1,(N55-O55)/O55)) -> 0
A56: 原材料采购库存商品产量比
A57: 项目 | B57: 1月 | C57: 2月 | D57: 3月 | E57: 4月 | F57: 5月 | G57: 6月 | H57: 7月 | I57: 8月 | J57: 9月 | K57: 10月 | L57: 11月 | M57: 12月 | N57: 合计 | O57: 上年度 | P57: 变动率
A58: =A13 -> 0 | B58: =IF(B40=0,0,B40/B13) -> 0 | C58: =IF(C40=0,0,C40/C13) -> 0 | D58: =IF(D40=0,0,D40/D13) -> 0 | E58: =IF(E40=0,0,E40/E13) -> 0 | F58: =IF(F40=0,0,F40/F13) -> 0 | G58: =IF(G40=0,0,G40/G13) -> 0 | H58: =IF(H40=0,0,H40/H13) -> 0 | I58: =IF(I40=0,0,I40/I13) -> 0 | ... O58: =IF(O40=0,0,O40/O13) -> 0 | P58: =IF(AND(O58=0,N58-O58=0),0,IF(AND(O58=0,N58-O58>0),1,(N58-O58)/O58)) -> 0 | Q58: 对波动异常的产品应进一步执行舞弊应对程序中的产品生产成本及单耗分析<F2-64>
A59: =A14 -> 0 | B59: =IF(B41=0,0,B41/B14) -> 0 | C59: =IF(C41=0,0,C41/C14) -> 0 | D59: =IF(D41=0,0,D41/D14) -> 0 | E59: =IF(E41=0,0,E41/E14) -> 0 | F59: =IF(F41=0,0,F41/F14) -> 0 | G59: =IF(G41=0,0,G41/G14) -> 0 | H59: =IF(H41=0,0,H41/H14) -> 0 | I59: =IF(I41=0,0,I41/I14) -> 0 | ... O59: =IF(O41=0,0,O41/O14) -> 0 | P59: =IF(AND(O59=0,N59-O59=0),0,IF(AND(O59=0,N59-O59>0),1,(N59-O59)/O59)) -> 0
A60: =A15 -> 0 | B60: =IF(B42=0,0,B42/B15) -> 0 | C60: =IF(C42=0,0,C42/C15) -> 0 | D60: =IF(D42=0,0,D42/D15) -> 0 | E60: =IF(E42=0,0,E42/E15) -> 0 | F60: =IF(F42=0,0,F42/F15) -> 0 | G60: =IF(G42=0,0,G42/G15) -> 0 | H60: =IF(H42=0,0,H42/H15) -> 0 | I60: =IF(I42=0,0,I42/I15) -> 0 | ... O60: =IF(O42=0,0,O42/O15) -> 0 | P60: =IF(AND(O60=0,N60-O60=0),0,IF(AND(O60=0,N60-O60>0),1,(N60-O60)/O60)) -> 0
A61: =A16 -> 0 | B61: =IF(B43=0,0,B43/B16) -> 0 | D61: =IF(D43=0,0,D43/D16) -> 0 | E61: =IF(E43=0,0,E43/E16) -> 0 | F61: =IF(F43=0,0,F43/F16) -> 0 | G61: =IF(G43=0,0,G43/G16) -> 0 | H61: =IF(H43=0,0,H43/H16) -> 0 | I61: =IF(I43=0,0,I43/I16) -> 0 | J61: =IF(J43=0,0,J43/J16) -> 0 | K61: =IF(K43=0,0,K43/K16) -> 0 | ... O61: =IF(O43=0,0,O43/O16) -> 0 | P61: =IF(AND(O61=0,N61-O61=0),0,IF(AND(O61=0,N61-O61>0),1,(N61-O61)/O61)) -> 0
A62: =A17 -> 0 | B62: =IF(B44=0,0,B44/B17) -> 0 | C62: =IF(C44=0,0,C44/C17) -> 0 | D62: =IF(D44=0,0,D44/D17) -> 0 | E62: =IF(E44=0,0,E44/E17) -> 0 | F62: =IF(F44=0,0,F44/F17) -> 0 | G62: =IF(G44=0,0,G44/G17) -> 0 | H62: =IF(H44=0,0,H44/H17) -> 0 | I62: =IF(I44=0,0,I44/I17) -> 0 | ... O62: =IF(O44=0,0,O44/O17) -> 0 | P62: =IF(AND(O62=0,N62-O62=0),0,IF(AND(O62=0,N62-O62>0),1,(N62-O62)/O62)) -> 0
A63: =A18 -> 0 | B63: =IF(B45=0,0,B45/B18) -> 0 | C63: =IF(C45=0,0,C45/C18) -> 0 | D63: =IF(D45=0,0,D45/D18) -> 0 | E63: =IF(E45=0,0,E45/E18) -> 0 | F63: =IF(F45=0,0,F45/F18) -> 0 | G63: =IF(G45=0,0,G45/G18) -> 0 | H63: =IF(H45=0,0,H45/H18) -> 0 | I63: =IF(I45=0,0,I45/I18) -> 0 | ... O63: =IF(O45=0,0,O45/O18) -> 0 | P63: =IF(AND(O63=0,N63-O63=0),0,IF(AND(O63=0,N63-O63>0),1,(N63-O63)/O63)) -> 0
A64: 合计 | B64: =IF(B46=0,0,B46/B19) -> 0 | C64: =IF(C46=0,0,C46/C19) -> 0 | D64: =IF(D46=0,0,D46/D19) -> 0 | E64: =IF(E46=0,0,E46/E19) -> 0 | F64: =IF(F46=0,0,F46/F19) -> 0 | G64: =IF(G46=0,0,G46/G19) -> 0 | H64: =IF(H46=0,0,H46/H19) -> 0 | I64: =IF(I46=0,0,I46/I19) -> 0 | ... O64: =IF(O46=0,0,O46/O19) -> 0 | P64: =IF(AND(O64=0,N64-O64=0),0,IF(AND(O64=0,N64-O64>0),1,(N64-O64)/O64)) -> 0
A65: 产耗比
A66: 项目 | B66: 1月 | C66: 2月 | D66: 3月 | E66: 4月 | F66: 5月 | G66: 6月 | H66: 7月 | I66: 8月 | J66: 9月 | K66: 10月 | L66: 11月 | M66: 12月 | N66: 合计 | O66: 上年度 | P66: 变动率
A67: =A13 -> 0 | B67: =IF(B49=0,0,B13/B49) -> 0 | C67: =IF(C49=0,0,C13/C49) -> 0 | D67: =IF(D49=0,0,D13/D49) -> 0 | E67: =IF(E49=0,0,E13/E49) -> 0 | F67: =IF(F49=0,0,F13/F49) -> 0 | G67: =IF(G49=0,0,G13/G49) -> 0 | H67: =IF(H49=0,0,H13/H49) -> 0 | I67: =IF(I49=0,0,I13/I49) -> 0 | ... O67: =IF(O49=0,0,O13/O49) -> 0 | P67: =IF(AND(O67=0,N67-O67=0),0,IF(AND(O67=0,N67-O67>0),1,(N67-O67)/O67)) -> 0 | Q67: 对波动异常的产品应进一步执行舞弊应对程序中的产品生产成本及单耗分析<F2-64>
A68: =A14 -> 0 | B68: =IF(B50=0,0,B14/B50) -> 0 | C68: =IF(C50=0,0,C14/C50) -> 0 | D68: =IF(D50=0,0,D14/D50) -> 0 | E68: =IF(E50=0,0,E14/E50) -> 0 | F68: =IF(F50=0,0,F14/F50) -> 0 | G68: =IF(G50=0,0,G14/G50) -> 0 | H68: =IF(H50=0,0,H14/H50) -> 0 | I68: =IF(I50=0,0,I14/I50) -> 0 | ... O68: =IF(O50=0,0,O14/O50) -> 0 | P68: =IF(AND(O68=0,N68-O68=0),0,IF(AND(O68=0,N68-O68>0),1,(N68-O68)/O68)) -> 0
A69: =A15 -> 0 | B69: =IF(B51=0,0,B15/B51) -> 0 | C69: =IF(C51=0,0,C15/C51) -> 0 | D69: =IF(D51=0,0,D15/D51) -> 0 | E69: =IF(E51=0,0,E15/E51) -> 0 | F69: =IF(F51=0,0,F15/F51) -> 0 | G69: =IF(G51=0,0,G15/G51) -> 0 | H69: =IF(H51=0,0,H15/H51) -> 0 | I69: =IF(I51=0,0,I15/I51) -> 0 | ... O69: =IF(O51=0,0,O15/O51) -> 0 | P69: =IF(AND(O69=0,N69-O69=0),0,IF(AND(O69=0,N69-O69>0),1,(N69-O69)/O69)) -> 0
A70: =A16 -> 0 | B70: =IF(B52=0,0,B16/B52) -> 0 | C70: =IF(C52=0,0,C16/C52) -> 0 | D70: =IF(D52=0,0,D16/D52) -> 0 | E70: =IF(E52=0,0,E16/E52) -> 0 | F70: =IF(F52=0,0,F16/F52) -> 0 | G70: =IF(G52=0,0,G16/G52) -> 0 | H70: =IF(H52=0,0,H16/H52) -> 0 | I70: =IF(I52=0,0,I16/I52) -> 0 | ... O70: =IF(O52=0,0,O16/O52) -> 0 | P70: =IF(AND(O70=0,N70-O70=0),0,IF(AND(O70=0,N70-O70>0),1,(N70-O70)/O70)) -> 0
A71: =A17 -> 0 | B71: =IF(B53=0,0,B17/B53) -> 0 | C71: =IF(C53=0,0,C17/C53) -> 0 | D71: =IF(D53=0,0,D17/D53) -> 0 | E71: =IF(E53=0,0,E17/E53) -> 0 | F71: =IF(F53=0,0,F17/F53) -> 0 | G71: =IF(G53=0,0,G17/G53) -> 0 | H71: =IF(H53=0,0,H17/H53) -> 0 | I71: =IF(I53=0,0,I17/I53) -> 0 | ... O71: =IF(O53=0,0,O17/O53) -> 0 | P71: =IF(AND(O71=0,N71-O71=0),0,IF(AND(O71=0,N71-O71>0),1,(N71-O71)/O71)) -> 0
A72: =A18 -> 0 | B72: =IF(B54=0,0,B18/B54) -> 0 | C72: =IF(C54=0,0,C18/C54) -> 0 | D72: =IF(D54=0,0,D18/D54) -> 0 | E72: =IF(E54=0,0,E18/E54) -> 0 | F72: =IF(F54=0,0,F18/F54) -> 0 | G72: =IF(G54=0,0,G18/G54) -> 0 | H72: =IF(H54=0,0,H18/H54) -> 0 | I72: =IF(I54=0,0,I18/I54) -> 0 | ... O72: =IF(O54=0,0,O18/O54) -> 0 | P72: =IF(AND(O72=0,N72-O72=0),0,IF(AND(O72=0,N72-O72>0),1,(N72-O72)/O72)) -> 0
A73: 合计 | B73: =IF(B55=0,0,B19/B55) -> 0 | C73: =IF(C55=0,0,C19/C55) -> 0 | D73: =IF(D55=0,0,D19/D55) -> 0 | E73: =IF(E55=0,0,E19/E55) -> 0 | F73: =IF(F55=0,0,F19/F55) -> 0 | G73: =IF(G55=0,0,G19/G55) -> 0 | H73: =IF(H55=0,0,H19/H55) -> 0 | I73: =IF(I55=0,0,I19/I55) -> 0 | ... O73: =IF(O55=0,0,O19/O55) -> 0 | P73: =IF(AND(O73=0,N73-O73=0),0,IF(AND(O73=0,N73-O73>0),1,(N73-O73)/O73)) -> 0
A74: 三、审计说明
A75: 1.库存商品—***月产量变动异常的原因：
A76: 2.库存商品—**本年与上年相比变动较大的原因：
A77: 3.原材料—**本年与上年相比变动较大的原因：
A78: 4.库存商品—***采购与耗用比变动较大的原因：
A79: 5.产销量、产耗比异常变动的产品进一步进行生产成本及单耗分析见<F2-64>
A80: 四、审计结论
A84: 编制说明：
A85: 1、上述主要产品产耗比测算表假定一种库存商品仅耗用一种原料的情形；
A86: 2、如果耗用多种主要原料或耗用的主要原料计量单位不统一，请适当修改产耗比的测算过程。

Sheet 产品年度成本比较分析F2-20
A1: 致同会计师事务所
A2: 产成品单位成本年度比较分析表
A3: =底稿目录!A2 -> 被审计单位： | F3: =底稿目录!A4 -> 编制人： | L3: =底稿目录!A5 -> 编制日期： | Q3: 索引号： | R3: =底稿目录!F4 -> F2-20
A4: =底稿目录!A3 -> 截止日：202X年12月31日 | F4: =底稿目录!A6 -> 复核人： | L4: =底稿目录!A7 -> 复核日期： | Q4: 页次：
A5: 产成品名称 | B5: 本年单位成本 | G5: 上年单位成本 | L5: 波动比例 | Q5: 是否存在异常波动 | R5: 进一步审验底稿索引
B6: 直接材料 | C6: 直接人工 | D6: 制造费用 | F6: 合计 | G6: 直接材料 | H6: 直接人工 | I6: 制造费用 | K6: 合计 | L6: 直接材料 | M6: 直接人工 | N6: 制造费用 | P6: 合计
F7: =SUM(B7:E7) -> 0 | K7: =SUM(G7:J7) -> 0 | L7: =IF(G7=0,0,(B7-G7)/G7) -> 0 | M7: =IF(H7=0,0,(C7-H7)/H7) -> 0 | N7: =IF(I7=0,0,(D7-I7)/I7) -> 0 | O7: =IF(J7=0,0,(E7-J7)/J7) -> 0 | P7: =IF(K7=0,0,(F7-K7)/K7) -> 0 | S7: 对波动异常的产品应进一步执行舞弊应对程序中原材料采购价格分析<F2-61>、产品生产成本及单耗分析<F2-64>
F8: =SUM(B8:E8) -> 0 | K8: =SUM(G8:J8) -> 0 | L8: =IF(G8=0,0,(B8-G8)/G8) -> 0 | M8: =IF(H8=0,0,(C8-H8)/H8) -> 0 | N8: =IF(I8=0,0,(D8-I8)/I8) -> 0 | O8: =IF(J8=0,0,(E8-J8)/J8) -> 0 | P8: =IF(K8=0,0,(F8-K8)/K8) -> 0
F9: =SUM(B9:E9) -> 0 | K9: =SUM(G9:J9) -> 0 | L9: =IF(G9=0,0,(B9-G9)/G9) -> 0 | M9: =IF(H9=0,0,(C9-H9)/H9) -> 0 | N9: =IF(I9=0,0,(D9-I9)/I9) -> 0 | O9: =IF(J9=0,0,(E9-J9)/J9) -> 0 | P9: =IF(K9=0,0,(F9-K9)/K9) -> 0
F10: =SUM(B10:E10) -> 0 | K10: =SUM(G10:J10) -> 0 | L10: =IF(G10=0,0,(B10-G10)/G10) -> 0 | M10: =IF(H10=0,0,(C10-H10)/H10) -> 0 | N10: =IF(I10=0,0,(D10-I10)/I10) -> 0 | O10: =IF(J10=0,0,(E10-J10)/J10) -> 0 | P10: =IF(K10=0,0,(F10-K10)/K10) -> 0
F11: =SUM(B11:E11) -> 0 | K11: =SUM(G11:J11) -> 0 | L11: =IF(G11=0,0,(B11-G11)/G11) -> 0 | M11: =IF(H11=0,0,(C11-H11)/H11) -> 0 | N11: =IF(I11=0,0,(D11-I11)/I11) -> 0 | O11: =IF(J11=0,0,(E11-J11)/J11) -> 0 | P11: =IF(K11=0,0,(F11-K11)/K11) -> 0
F12: =SUM(B12:E12) -> 0 | K12: =SUM(G12:J12) -> 0 | L12: =IF(G12=0,0,(B12-G12)/G12) -> 0 | M12: =IF(H12=0,0,(C12-H12)/H12) -> 0 | N12: =IF(I12=0,0,(D12-I12)/I12) -> 0 | O12: =IF(J12=0,0,(E12-J12)/J12) -> 0 | P12: =IF(K12=0,0,(F12-K12)/K12) -> 0
F13: =SUM(B13:E13) -> 0 | K13: =SUM(G13:J13) -> 0 | L13: =IF(G13=0,0,(B13-G13)/G13) -> 0 | M13: =IF(H13=0,0,(C13-H13)/H13) -> 0 | N13: =IF(I13=0,0,(D13-I13)/I13) -> 0 | O13: =IF(J13=0,0,(E13-J13)/J13) -> 0 | P13: =IF(K13=0,0,(F13-K13)/K13) -> 0
F14: =SUM(B14:E14) -> 0 | K14: =SUM(G14:J14) -> 0 | L14: =IF(G14=0,0,(B14-G14)/G14) -> 0 | M14: =IF(H14=0,0,(C14-H14)/H14) -> 0 | N14: =IF(I14=0,0,(D14-I14)/I14) -> 0 | O14: =IF(J14=0,0,(E14-J14)/J14) -> 0 | P14: =IF(K14=0,0,(F14-K14)/K14) -> 0
F15: =SUM(B15:E15) -> 0 | K15: =SUM(G15:J15) -> 0 | L15: =IF(G15=0,0,(B15-G15)/G15) -> 0 | M15: =IF(H15=0,0,(C15-H15)/H15) -> 0 | N15: =IF(I15=0,0,(D15-I15)/I15) -> 0 | O15: =IF(J15=0,0,(E15-J15)/J15) -> 0 | P15: =IF(K15=0,0,(F15-K15)/K15) -> 0
F16: =SUM(B16:E16) -> 0 | K16: =SUM(G16:J16) -> 0 | L16: =IF(G16=0,0,(B16-G16)/G16) -> 0 | M16: =IF(H16=0,0,(C16-H16)/H16) -> 0 | N16: =IF(I16=0,0,(D16-I16)/I16) -> 0 | O16: =IF(J16=0,0,(E16-J16)/J16) -> 0 | P16: =IF(K16=0,0,(F16-K16)/K16) -> 0
A18: 审计说明：
A19: 1.XX产品单位成本异常波动原因： 对XX产品进一步进行生产成本及单耗分析见<F2-64>
A20: 2.原材料采购价格进一步分析见<F2-61>
A22: 审计结论：
