Workbook

Sheet 底稿目录
A1: 底稿开列时，可先在以下单元格填写有关内容，以便其他底稿引用有关数据：
A2: 被审计单位： | D2: 序号 | E2: 内容 | F2: 索引号
A3: 截止日：202X年12月31日 | D3: 1 | E3: 存货截止测试-入库（从记账凭证至原始凭证） | F3: F2-29
A4: 编制人： | D4: 2 | E4: 存货截止测试-入库（从原始凭证至记账凭证） | F4: F2-30
A5: 编制日期： | D5: 3 | E5: 存货截止测试-出库（记账凭证至原始凭证） | F5: F2-31
A6: 复核人： | D6: 4 | E6: 存货截止测试-出库（原始凭证至记账凭证） | F6: F2-32
A7: 复核日期： | D7: 5 | E7: 存货采购入库检查表 | F7: F2-33
D8: 6 | E8: 材料领用检查表 | F8: F2-34
D9: 7 | E9: 委托加工物资核查表 | F9: F2-35

Sheet GT_Custom
A1: C1 | B1: Custom 1
A2: C2 | B2: Custom 2
A3: C3 | B3: Custom 3
A4: C4 | B4: Custom 4
A5: C5 | B5: Custom 5
A6: C6 | B6: Custom 6
A7: C7 | B7: Custom 7
A8: C8 | B8: Custom 8

Sheet 截止测试-入库（记账凭证至原始凭证）F2-29
A1: 致同会计师事务所
A2: 存货（原材料/产成品）截止测试-入库（从记账凭证至原始凭证）
A3: =底稿目录!A2 -> 被审计单位： | E3: =底稿目录!A4 -> 编制人： | G3: =底稿目录!A5 -> 编制日期： | K3: 索引号： | L3: =底稿目录!F3 -> F2-29
A4: =底稿目录!A3 -> 截止日：202X年12月31日 | E4: =底稿目录!A6 -> 复核人： | G4: =底稿目录!A7 -> 复核日期： | K4: 页 次：
A5: 一、审计目标：
A6: 1.资产负债表中记录的存货是存在的，且已经记录在恰当的账户中
A7: 2.所有应记录的存货均已记录，所有应当包括在财务报表中的相关披露均已包括
A8: 二、审计过程：
A9: 1.从存货明细账借方发生额中抽取资产负债表日前（______）天、后（______）天，且金额大于______元的凭证，与入库记录（如入库单，或购货发票，或运输单据）核对；
A10: 2.结合存货监盘程序，检查入库记录编号是否与执行存货监盘程序中获取的截止性资料编号存在冲突。
A11: 提示：如果存在跨期舞弊风险或者所检查样本中发现有跨期的，应扩大测试期间和样本，甚至可以考虑将截止测试期间延长至审计报告日。同时考虑是否存在内控缺陷。
A12: 记账凭证 | F12: 入库单 | H12: 质检报告 | J12: …… | L12: 是否跨期√（×）
A13: 日期 | B13: 凭证编号 | C13: 业务内容 | D13: 存货名称 | E13: 金额 | F13: 编号 | G13: 日期 | H13: 编号 | I13: 日期 | J13: 编号 | K13: 日期
A27: ——————截止日期：202X年12月31日——————
A42: 三、审计说明：
A46: 四、审计结论：
A49: 提示：
A50: 1.应分别存货类别（如原材料、产成品）进行截止测试。
A51: 2.上述测试基于入库单作为存货入库的依据，如果存货入库的依据不是入库单，则相应调整。
A52: 3.审计说明可以概述：（1）程序的测试情况、结果；（2）拟调整事项及其调整分录、未调整事项及其影响，审计范围受到限制情况及其影响。
A53: 4.审计结论可参考：A、未见异常。 B、除上述重大不符事项应当作为调整事项予以调整外，其余未见异常。 C、由于存在以下重大未调整事项（或审计范围受到限制无法获取充分、适当证据），不可确认。

Sheet 截止测试-入库（原始凭证至记账凭证）F2-30
A1: 致同会计师事务所
A2: 存货（原材料/产成品）截止测试-入库（从原始凭证至记账凭证）
A3: =底稿目录!A2 -> 被审计单位： | D3: =底稿目录!A4 -> 编制人： | H3: =底稿目录!A5 -> 编制日期： | K3: 索引号： | L3: =底稿目录!F4 -> F2-30
A4: =底稿目录!A3 -> 截止日：202X年12月31日 | D4: =底稿目录!A6 -> 复核人： | H4: =底稿目录!A7 -> 复核日期： | K4: 页 次：
A5: 一、审计目标：
A6: 1.资产负债表中记录的存货是存在的，且已经记录在恰当的账户中
A7: 2.所有应记录的存货均已记录，所有应当包括在财务报表中的相关披露均已包括
A8: 二、审计过程：
A9: 1.从入库记录中抽取资产负债表日前（______）天、后（______）天，且金额大于______元的的凭据，与存货明细账的借方发生额进行核对；
A10: 2.结合存货监盘程序，检查入库记录编号是否与执行存货监盘程序中获取的截止性资料编号存在冲突。
A11: 提示：如果存在跨期舞弊风险或者所检查样本中发现有跨期的，应扩大测试期间和样本，甚至可以考虑将截止测试期间延长至审计报告日。同时考虑是否存在内控缺陷。
A12: 入库单 | C12: 质检报告 | E12: …… | G12: 记账凭证 | L12: 是否跨期√（×）
A13: 编号 | B13: 日期 | C13: 编号 | D13: 日期 | E13: 编号 | F13: 日期 | G13: 日期 | H13: 凭证编号 | I13: 业务内容 | J13: 存货名称 | K13: 金额
A27: ——————截止日期：202X年12月31日——————
A42: 三、审计说明：
A46: 四、审计结论：
A49: 提示：
A50: 1.应分别存货类别（如原材料、产成品）进行截止测试。
A51: 2.上述测试基于入库单作为存货入库的依据，如果存货入库的依据不是入库单，则相应调整。

Sheet 截止测试-出库（记账凭证至原始凭证）F2-31
A1: 致同会计师事务所
A2: 存货（原材料/产成品）截止测试-出库（从记账凭证至原始凭证）
A3: =底稿目录!A2 -> 被审计单位： | D3: =底稿目录!A4 -> 编制人： | F3: =底稿目录!A5 -> 编制日期： | I3: 索引号： | J3: =底稿目录!F5 -> F2-31
A4: =底稿目录!A3 -> 截止日：202X年12月31日 | D4: =底稿目录!A6 -> 复核人： | F4: =底稿目录!A7 -> 复核日期： | I4: 页 次：
A5: 一、审计目标：
A6: 1.资产负债表中记录的存货是存在的，且已经记录在恰当的账户中
A7: 2.所有应记录的存货均已记录，所有应当包括在财务报表中的相关披露均已包括
A8: 二、审计过程：
A9: 1.从存货明细账贷方发生额中抽取资产负债表日前（______）天、后（______）天，且金额大于______元的凭证，与出库记录（如出库单、原材料领用单、运输单据）核对；
A10: 2.结合存货监盘程序，检查出库记录编号是否与执行存货监盘程序中获取的截止性资料编号存在冲突。
A11: 3.产成品出库截止测试可与营业收入截止测试程序结合完成。
A12: 提示：如果存在跨期舞弊风险或者所检查样本中发现有跨期的，应扩大测试期间和样本，甚至可以考虑将截止测试期间延长至审计报告日。同时考虑是否存在内控缺陷。
A13: 记账凭证 | F13: 出库单/领料单 | H13: …… | J13: 是否跨期√（×）
A14: 日期 | B14: 凭证编号 | C14: 业务内容 | D14: 存货名称 | E14: 金额 | F14: 编号 | G14: 日期 | H14: 编号 | I14: 日期
A27: ='截止测试-入库（记账凭证至原始凭证）F2-29'!A27 -> ——————截止日期：202X年12月31日——————
A40: 四、审计说明：
A44: 五、审计结论：
A48: 提示：
A49: 1.应分别存货类别（如原材料、产成品等）进行截止测试。
A50: 2.上述测试基于出库单作为存货出库的依据，如果存货出库的依据不是出库单，则相应调整。
A51: 3.如果公司核算发出商品或存在不符合收入确认而已经发出产品或消耗产品等，产成品的出库截止性测试相应调整。

Sheet 截止测试-出库（原始凭证至记账凭证）F2-32
A1: 致同会计师事务所
A2: 存货（原材料/产成品）截止测试-出库（从原始凭证至记账凭证）
A3: =底稿目录!A2 -> 被审计单位： | D3: =底稿目录!A4 -> 编制人： | G3: =底稿目录!A5 -> 编制日期： | I3: 索引号： | J3: =底稿目录!F6 -> F2-32
A4: =底稿目录!A3 -> 截止日：202X年12月31日 | D4: =底稿目录!A6 -> 复核人： | G4: =底稿目录!A7 -> 复核日期： | I4: 页 次：
A5: 一、审计目标：
A6: 1.资产负债表中记录的存货是存在的，且已经记录在恰当的账户中
A7: 2.所有应记录的存货均已记录，所有应当包括在财务报表中的相关披露均已包括
A8: 二、审计过程：
A9: 1.从出库记录中抽取资产负债表日前（ ）天、后（ ）天，且金额大于 元的凭据，与存货明细账的贷方发生额进行核对；
A10: 2.结合存货监盘程序，检查出库记录编号是否与执行存货监盘程序中获取的截止性资料编号存在冲突。
A11: 3.产成品出库截止测试可与营业收入截止测试程序结合完成。
A12: 提示：如果存在跨期舞弊风险或者所检查样本中发现有跨期的，应扩大测试期间和样本，甚至可以考虑将截止测试期间延长至审计报告日。同时考虑是否存在内控缺陷。
A13: 出库单/领料单 | C13: …… | E13: 记账凭证 | J13: 是否跨期√（×）
A14: 编号 | B14: 日期 | C14: 编号 | D14: 日期 | E14: 日期 | F14: 凭证编号 | G14: 业务内容 | H14: 存货名称 | I14: 金额
A27: ='截止测试-入库（记账凭证至原始凭证）F2-29'!A27 -> ——————截止日期：202X年12月31日——————
A40: 四、审计说明：
A44: 五、审计结论：
A48: 提示：
A49: 1.应分别存货类别（如原材料、产成品等）进行截止测试。
A50: 2.上述测试基于出库单作为存货出库的依据，如果存货出库的依据不是出库单，则相应调整。
A51: 3.如果公司核算发出商品或存在不符合收入确认而已经发出产品或消耗产品等，产成品的出库截止性测试相应调整。

Sheet 存货采购入库检查表F2-33-新增
A1: 致同会计师事务所
A2: 存货采购入库检查表
A3: =底稿目录!A2 -> 被审计单位： | I3: =底稿目录!A4 -> 编制人： | O3: =底稿目录!A5 -> 编制日期： | U3: 索引号： | V3: =底稿目录!F7 -> F2-33
A4: =底稿目录!A3 -> 截止日：202X年12月31日 | I4: =底稿目录!A6 -> 复核人： | O4: =底稿目录!A7 -> 复核日期： | U4: 页 次：
A5: 一、审计目标：
A6: 1.资产负债表中记录的存货是存在的，且已经记录在恰当的账户中
A7: 2.记录的存货由被审计单位拥有或控制
A8: 3.存货以恰当的金额包括在财务报表中，与之相关的计价或分摊调整已恰当记录，相关披露已得到恰当计量和描述
A9: 二、样本选取标准与规模：
A10: 测试总体： | B10: 如存货借方发生额所有凭证共XX笔金额XX | J10: 特定样本： | K10: XX金额以上（大额）、关联方/关联交易形成的款项、XX异常款项全部测试，共XX笔
A11: 抽样总体： | B11: 测试总体扣除特定样本以外的样本，共XX笔、金额XX | J11: 确定的抽样样本量： | L11: 抽取XX笔 | M11: （如果使用了样本计算器计算样本量，样本量计算过程见<XX>底稿）
A12: 抽样方法： | B12: 随机选样/系统选样/货币单元抽样/随意选样（非统计抽样适用） | J12: 抽样过程： | K12: 使用IDEA（XX抽样工具）选择XX数量、金额XX的样本进行测试，抽样工具中的样本选择过程和结果见<XX>底稿
A13: 三、测试：
A14: 测试内容说明：1.原始凭证是否齐全； 2.记账凭证与原始凭证是否相符；3.账务处理是否正确；4.是否记录于恰当的会计期间；5.……
A15: 供应商名称 | B15: 存货类别 | C15: 记账凭证 | K15: 入库单/验收单 | M15: 质检报告 | N15: 物流单（运输单） | Q15: 采购发票 | T15: …… | U15: 索引号 | V15: 是否异常
C16: 凭证编号 | D16: 业务内容 | E16: 存货名称 | F16: 单位 | G16: 数量 | H16: 借方金额 | I16: 对方科目 | J16: 对方明细科目 | K16: 日期/编号 | L16: 数量 | M16: 日期/编号 | N16: 日期/编号 | O16: 物流单位 | P16: 数量 | Q16: 日期/编号 | R16: 对手方名称 | S16: 金额
A36: 合计 | H36: =SUM(H17:H35) -> 0 | S36: =SUM(S17:S35) -> 0
A37: 四、审计说明：
A38: 1.本期发生额、期末余额检查比例： | E38: 存货类别 | F38: 账面金额 | H38: 检查金额 | I38: 检查比例 | J38: 如果检查比例较低应扩大检查样本量或说明原因
I39: =ROUND(H39/F39,4) -> #DIV/0!
I40: =ROUND(H40/F40,2) -> #DIV/0!
I41: =ROUND(H41/F41,2) -> #DIV/0!
A42: 2.……
A43: 五、审计结论：

Sheet 材料领用检查表F2-34-新增
A1: 致同会计师事务所
A2: 材料领用检查表
A3: =底稿目录!A2 -> 被审计单位： | F3: =底稿目录!A4 -> 编制人： | I3: =底稿目录!A5 -> 编制日期： | M3: 索引号： | N3: =底稿目录!F8 -> F2-34
A4: =底稿目录!A3 -> 截止日：202X年12月31日 | F4: =底稿目录!A6 -> 复核人： | I4: =底稿目录!A7 -> 复核日期： | M4: 页 次：
A5: 一、审计目标：
A6: 1.资产负债表中记录的存货是存在的，且已经记录在恰当的账户中；2.所有应记录的存货均已记录，所有应当包括在财务报表中的相关披露均已包括
A7: 3.存货以恰当的金额包括在财务报表中，与之相关的计价或分摊调整已恰当记录，相关披露已得到恰当计量和描述
A8: 二、样本选取标准与规模：
A9: 测试总体： | B9: 如原材料贷方发生额所有凭证共XX笔金额XX | F9: 特定样本： | G9: XX金额以上（大额）、关联方/关联交易形成的款项、XX异常款项全部测试，共XX笔
A10: 抽样总体： | B10: 测试总体扣除特定样本以外的样本，共XX笔、金额XX | F10: 确定的抽样样本量： | H10: 抽取XX笔 | I10: （如果使用了样本计算器计算样本量，样本量计算过程见<XX>底稿）
A11: 抽样方法： | B11: 随机选样/系统选样/货币单元抽样/随意选样（非统计抽样适用） | F11: 抽样过程： | G11: 使用IDEA（XX抽样工具）选择XX数量、金额XX的样本进行测试，抽样工具中的样本选择过程和结果见<XX>底稿
A12: 三、测试：
A13: 测试内容说明：1.原始凭证是否齐全； 2.记账凭证与原始凭证是否相符；3.账务处理是否正确；4.是否记录于恰当的会计期间；5.……
A14: 记账凭证 | I14: 出库单/领料单 | L14: …… | M14: 索引号 | N14: 是否异常
A15: 凭证编号 | B15: 业务内容 | C15: 存货名称 | D15: 单位 | E15: 数量 | F15: 贷方金额 | G15: 对方科目 | H15: 对方明细科目 | I15: 日期/编号 | J15: 领用部门 | K15: 数量
A32: 合计 | F32: =SUM(F16:F31) -> 0
A33: 四、审计说明：
A34: 1.本期发生额、期末余额检查比例： | D34: 项目 | F34: 账面金额 | G34: 检查金额 | H34: 检查比例 | I34: 如果检查比例较低应扩大检查样本量或说明原因
D35: 原材料贷方 | G35: =F32 -> 0 | H35: =ROUND(G35/F35,4) -> #DIV/0!
A36: 2.……
A37: 五、审计结论：

Sheet 委托加工物资核查表F2-35
A1: 致同会计师事务所
A2: 委托加工物资核查表
A3: =底稿目录!A2 -> 被审计单位： | D3: =底稿目录!A4 -> 编制人： | F3: =底稿目录!A5 -> 编制日期： | H3: 索引号： | I3: =底稿目录!F9 -> F2-35
A4: =底稿目录!A3 -> 截止日：202X年12月31日 | D4: =底稿目录!A6 -> 复核人： | F4: =底稿目录!A7 -> 复核日期： | H4: 页次：
A5: 一、审计目标：
A6: 1.资产负债表中记录的存货是存在的，且已经记录在恰当的账户中
A7: 2.所有应记录的存货均已记录，所有应当包括在财务报表中的相关披露均已包括
A8: 3.记录的存货由被审计单位拥有或控制
A9: 4. 存货以恰当的金额包括在财务报表中，与之相关的计价或分摊调整已恰当记录，相关披露已得到恰当计量和描述
A10: 二、样本选取标准与规模：
A13: 三、审计过程：
A14: 1.获取或编制委托加工物资的明细表，抽查委托加工业务合同，检查有关发料凭证、加工费结算凭证。
A15: 2.针对当期加工工费及期末委托加工物资对被委托方进行函证。
A16: 3.……
A17: （一）委托加工物资基本情况
A18: 年度 | B18: 期初金额 | C18: 本期增加 | D18: 本期减少 | E18: 期末金额 | F18: 其中加工费发生额
A22: （二）主要委外供应商情况1
A23: 年度 | B23: 供应商名称 | C23: 主要加工工序 | D23: 委外加工入库数量 | E23: 委外加工入库金额 | F23: 加工费金额 | G23: 加工费结算单索引 | H23: 函证编号
A29: （三）主要委外供应商情况2
A30: 加工单位名称 | B30: 合同或协议号 | C30: 发出时间 | D30: 发出材料成本 | E30: 加工费 | F30: 收回材料成本 | G30: 未收回原因及是否需函证 | H30: 索引号 | I30: 备注
A36: 四、审计说明：
A39: 五、审计结论：
