Workbook

Sheet 底稿目录
A1: 底稿开列时，可先在以下单元格填写有关内容，以便其他底稿引用有关数据：
A2: 被审计单位： | D2: 序号 | E2: 内容 | F2: 索引号
A3: 截止日： | D3: 1 | E3: 合同履约成本实质性程序表 | F3: F2-55A
A4: 编制人： | D4: 2 | E4: 合同履约成本构成明细表 | F4: F2-55
A5: 编制日期： | D5: 3 | E5: 合同履约成本检查表 | F5: F2-56
A6: 复核人： | D6: 4 | E6: 合同履约成本减值准备测算表 | F6: F2-57
A7: 复核日期： | D7: 5 | E7: 亏损合同预计损失测算表 | F7: F2-58

Sheet 合同履约成本实质性程序表F2-55A
A1: 致同会计师事务所
A2: 合同履约成本实质性程序
A3: =底稿目录!A2 -> 被审计单位： | C3: =底稿目录!A4 -> 编制人： | E3: =底稿目录!A5 -> 编制日期： | H3: 索引号： | I3: =底稿目录!F3 -> F2-55A
A4: =底稿目录!A3 -> 截止日： | C4: =底稿目录!A6 -> 复核人： | E4: =底稿目录!A7 -> 复核日期： | H4: 页 次：
A5: 一、本账户涉及的科目
A6: 存货及跌价准备
A7: 二、审计目标与认定的对应关系
A8: 审计目标 | G8: 财务报表的认定
A9: A. 资产负债表中记录的合同履约成本是存在的，且已经记录在恰当的账户中 | G9: 存在
A10: B. 所有应记录的合同履约成本均已记录，所有应当包括在财务报表中的相关披露均已包括 | G10: 完整性
A11: C. 记录的合同履约成本由被审计单位拥有或控制 | G11: 权利和义务
A12: D. 合同履约成本以恰当的金额包括在财务报表中，与之相关的计价或分摊调整已恰当记录，相关披露已得到恰当计量和描述 | G12: 准确性、计价和分摊
A13: E. 合同履约成本已被恰当地汇总或分解且表述清楚，相关披露在按照企业会计准则的编制基础下是相关的、可理解的 | G13: 列报
A14: 三、计划实施的实质性程序
A15: 序号 | B15: 审计程序 | C15: 程序分类 | D15: 财务报表的认定 | I15: 底稿索引号
D16: 存在 | E16: 完整性 | F16: 权利和 义务 | G16: 准确性、计价和分摊 | H16: 列报 | J16: 根据被审计单位实际情况和风险评估情况裁剪、修改或增加审计程序
A17: 1 | B17: 取或编制合同履约成本明细表，复核加计是否正确，并与总账数、明细账合计数核对是否相符，关注是否存在异常或负数余额项目，关注项目进度，是否存在停工、停滞项目。 | C17: 常规★ | D17: √ | E17: √ | G17: √ | I17: F2-12
A18: 2 | B18: 取得项目合同履约成本构成明细，关注是否满足计入合同履约成本构成条件，是否预期能够收回，合同履约成本构成明细的合理性和一惯性，关注其是否利用会计政策和会计估计及其变更操纵利润。 | C18: 常规★ | D18: √ | E18: √ | I18: F2-55
A19: 3 | B19: 结合营业收入合同毛利分析等，选取项目检查相关记账凭证和支持性证据，会计处理是否正确。 | C19: 常规★ | D19: √ | F19: √ | G19: √ | I19: F2-56
A20: 4 | B20: 如果存在合同履约成本的摊销，检查摊销方法是否符合会计准则的规定，会计处理是否正确，选择样本重新计算摊销金额是否正确。 | C20: 备选 | G20: √
A21: 5 | B21: 如果存在实地实施周期较长的项目，选取合同履约成本进行实地勘察，关注项目现场是否正常进行，进度是否与账面进度一致，存放项目的存货是否与账面一致等。 | C21: 备选 | D21: √ | E21: √ | F21: √ | G21: √ | I21: F2-21A
A22: 6 | B22: 合同履约成本减值准备： （1）关注合同履约成本减值准备计提情形、依据、方法是否合理，前后各期是否一致，是否符合会计准则的规定，会计处理是否正确； （2）选取样本重新计算期末合同履约成本减值准备的金额； （3）检查合同履约成本减值准备的转回是否合理，转回金额、会计处理是否正确。 | C22: 常规★ | G22: √ | I22: F2-57
A23: 7 | B23: 关注是否存在亏损合同，检查亏损合同预计损失的计算和会计处理是否正确； | C23: 常规★ | E23: √ | F23: √ | I23: F2-58
A24: 8 | B24: 针对舞弊风险较大的供应商，考虑对采购额、合同条款、是否存在关联方关系及是否存在补充协议等实施函证程序。 | C24: IPO/上市/新三板/重组/舞弊应对 | D24: √ | E24: √ | F24: √ | G24: √ | I24: F0
A25: 9 | B25: 必要时对合同履约成本执行截止测试。 | C25: 备选 | D25: √ | E25: √
A26: 10 | B26: 根据评估的舞弊风险等因素增加的审计程序。 | C26: IPO/上市/新三板/重组/舞弊应对
A27: 11 | B27: 检查合同履约成本是否已按企业会计准则或其他适用的规定在财务报表中做出恰当列报和披露。 | C27: 常规★ | H27: √ | I27: A1-1/A1-15 /A1-16

Sheet 合同履约成本构成明细表F2-55
A1: 致同会计师事务所
A2: 合同履约成本构成明细表
A3: =底稿目录!A2 -> 被审计单位： | J3: =底稿目录!A4 -> 编制人： | W3: =底稿目录!A5 -> 编制日期： | AJ3: 索引号： | AK3: =底稿目录!F4 -> F2-55
A4: =底稿目录!A3 -> 截止日： | J4: =底稿目录!A6 -> 复核人： | W4: =底稿目录!A7 -> 复核日期： | AJ4: 页 次：
A5: 项目编码 | B5: 项目名称 | C5: 收入合同名称 | D5: 收入合同金额 | E5: 账面期初余额 | J5: 账面本期增加金额 | O5: 账面本期减少金额 | T5: 账面期末余额 | Y5: 是否与合同直接相关 | Z5: 是否预期能够收回 | AA5: 审计调整 | AF5: 期末审定金额 | AK5: 备注
E6: 设备/材料成本 | F6: 建安及分包成本 | G6: 人工费用 | H6: 其他费用 | I6: 小计 | J6: 设备/材料成本 | K6: 建安及分包成本 | L6: 人工费用 | M6: 其他费用 | N6: 小计 | O6: 设备/材料成本 | P6: 建安及分包成本 | Q6: 人工费用 | R6: 其他费用 | S6: 小计 | T6: 设备/材料成本 | U6: 建安及分包成本 | V6: 人工费用 | W6: 其他费用 | X6: 小计 | AA6: 设备/材料成本 | AB6: 建安及分包成本 | AC6: 人工费用 | AD6: 其他费用 | AE6: 小计 | AF6: 设备/材料成本 | AG6: 建安及分包成本 | AH6: 人工费用 | AI6: 其他费用 | AJ6: 小计
I7: =SUM(E7:H7) -> 0 | N7: =SUM(J7:M7) -> 0 | S7: =SUM(O7:R7) -> 0 | T7: =E7+J7-O7 -> 0 | U7: =F7+K7-P7 -> 0 | V7: =G7+L7-Q7 -> 0 | W7: =H7+M7-R7 -> 0 | X7: =SUM(T7:W7) -> 0 | AE7: =SUM(AA7:AD7) -> 0 | AF7: =T7+AA7 -> 0 | AG7: =U7+AB7 -> 0 | AH7: =V7+AC7 -> 0 | AI7: =W7+AD7 -> 0 | AJ7: =SUM(AF7:AI7) -> 0
I8: =SUM(E8:H8) -> 0 | N8: =SUM(J8:M8) -> 0 | S8: =SUM(O8:R8) -> 0 | T8: =E8+J8-O8 -> 0 | U8: =F8+K8-P8 -> 0 | V8: =G8+L8-Q8 -> 0 | W8: =H8+M8-R8 -> 0 | X8: =SUM(T8:W8) -> 0 | AE8: =SUM(AA8:AD8) -> 0 | AF8: =T8+AA8 -> 0 | AG8: =U8+AB8 -> 0 | AH8: =V8+AC8 -> 0 | AI8: =W8+AD8 -> 0 | AJ8: =SUM(AF8:AI8) -> 0
I9: =SUM(E9:H9) -> 0 | N9: =SUM(J9:M9) -> 0 | S9: =SUM(O9:R9) -> 0 | T9: =E9+J9-O9 -> 0 | U9: =F9+K9-P9 -> 0 | V9: =G9+L9-Q9 -> 0 | W9: =H9+M9-R9 -> 0 | X9: =SUM(T9:W9) -> 0 | AE9: =SUM(AA9:AD9) -> 0 | AF9: =T9+AA9 -> 0 | AG9: =U9+AB9 -> 0 | AH9: =V9+AC9 -> 0 | AI9: =W9+AD9 -> 0 | AJ9: =SUM(AF9:AI9) -> 0
I10: =SUM(E10:H10) -> 0 | N10: =SUM(J10:M10) -> 0 | S10: =SUM(O10:R10) -> 0 | T10: =E10+J10-O10 -> 0 | U10: =F10+K10-P10 -> 0 | V10: =G10+L10-Q10 -> 0 | W10: =H10+M10-R10 -> 0 | X10: =SUM(T10:W10) -> 0 | AE10: =SUM(AA10:AD10) -> 0 | AF10: =T10+AA10 -> 0 | AG10: =U10+AB10 -> 0 | AH10: =V10+AC10 -> 0 | AI10: =W10+AD10 -> 0 | AJ10: =SUM(AF10:AI10) -> 0
I11: =SUM(E11:H11) -> 0 | N11: =SUM(J11:M11) -> 0 | S11: =SUM(O11:R11) -> 0 | T11: =E11+J11-O11 -> 0 | U11: =F11+K11-P11 -> 0 | V11: =G11+L11-Q11 -> 0 | W11: =H11+M11-R11 -> 0 | X11: =SUM(T11:W11) -> 0 | AE11: =SUM(AA11:AD11) -> 0 | AF11: =T11+AA11 -> 0 | AG11: =U11+AB11 -> 0 | AH11: =V11+AC11 -> 0 | AI11: =W11+AD11 -> 0 | AJ11: =SUM(AF11:AI11) -> 0
I12: =SUM(E12:H12) -> 0 | N12: =SUM(J12:M12) -> 0 | S12: =SUM(O12:R12) -> 0 | T12: =E12+J12-O12 -> 0 | U12: =F12+K12-P12 -> 0 | V12: =G12+L12-Q12 -> 0 | W12: =H12+M12-R12 -> 0 | X12: =SUM(T12:W12) -> 0 | AE12: =SUM(AA12:AD12) -> 0 | AF12: =T12+AA12 -> 0 | AG12: =U12+AB12 -> 0 | AH12: =V12+AC12 -> 0 | AI12: =W12+AD12 -> 0 | AJ12: =SUM(AF12:AI12) -> 0
I13: =SUM(E13:H13) -> 0 | N13: =SUM(J13:M13) -> 0 | S13: =SUM(O13:R13) -> 0 | T13: =E13+J13-O13 -> 0 | U13: =F13+K13-P13 -> 0 | V13: =G13+L13-Q13 -> 0 | W13: =H13+M13-R13 -> 0 | X13: =SUM(T13:W13) -> 0 | AE13: =SUM(AA13:AD13) -> 0 | AF13: =T13+AA13 -> 0 | AG13: =U13+AB13 -> 0 | AH13: =V13+AC13 -> 0 | AI13: =W13+AD13 -> 0 | AJ13: =SUM(AF13:AI13) -> 0
I14: =SUM(E14:H14) -> 0 | N14: =SUM(J14:M14) -> 0 | S14: =SUM(O14:R14) -> 0 | T14: =E14+J14-O14 -> 0 | U14: =F14+K14-P14 -> 0 | V14: =G14+L14-Q14 -> 0 | W14: =H14+M14-R14 -> 0 | X14: =SUM(T14:W14) -> 0 | AE14: =SUM(AA14:AD14) -> 0 | AF14: =T14+AA14 -> 0 | AG14: =U14+AB14 -> 0 | AH14: =V14+AC14 -> 0 | AI14: =W14+AD14 -> 0 | AJ14: =SUM(AF14:AI14) -> 0
I15: =SUM(E15:H15) -> 0 | N15: =SUM(J15:M15) -> 0 | S15: =SUM(O15:R15) -> 0 | T15: =E15+J15-O15 -> 0 | U15: =F15+K15-P15 -> 0 | V15: =G15+L15-Q15 -> 0 | W15: =H15+M15-R15 -> 0 | X15: =SUM(T15:W15) -> 0 | AE15: =SUM(AA15:AD15) -> 0 | AF15: =T15+AA15 -> 0 | AG15: =U15+AB15 -> 0 | AH15: =V15+AC15 -> 0 | AI15: =W15+AD15 -> 0 | AJ15: =SUM(AF15:AI15) -> 0
I16: =SUM(E16:H16) -> 0 | N16: =SUM(J16:M16) -> 0 | S16: =SUM(O16:R16) -> 0 | T16: =E16+J16-O16 -> 0 | U16: =F16+K16-P16 -> 0 | V16: =G16+L16-Q16 -> 0 | W16: =H16+M16-R16 -> 0 | X16: =SUM(T16:W16) -> 0 | AE16: =SUM(AA16:AD16) -> 0 | AF16: =T16+AA16 -> 0 | AG16: =U16+AB16 -> 0 | AH16: =V16+AC16 -> 0 | AI16: =W16+AD16 -> 0 | AJ16: =SUM(AF16:AI16) -> 0
I17: =SUM(E17:H17) -> 0 | N17: =SUM(J17:M17) -> 0 | S17: =SUM(O17:R17) -> 0 | T17: =E17+J17-O17 -> 0 | U17: =F17+K17-P17 -> 0 | V17: =G17+L17-Q17 -> 0 | W17: =H17+M17-R17 -> 0 | X17: =SUM(T17:W17) -> 0 | AE17: =SUM(AA17:AD17) -> 0 | AF17: =T17+AA17 -> 0 | AG17: =U17+AB17 -> 0 | AH17: =V17+AC17 -> 0 | AI17: =W17+AD17 -> 0 | AJ17: =SUM(AF17:AI17) -> 0
I18: =SUM(E18:H18) -> 0 | N18: =SUM(J18:M18) -> 0 | S18: =SUM(O18:R18) -> 0 | T18: =E18+J18-O18 -> 0 | U18: =F18+K18-P18 -> 0 | V18: =G18+L18-Q18 -> 0 | W18: =H18+M18-R18 -> 0 | X18: =SUM(T18:W18) -> 0 | AE18: =SUM(AA18:AD18) -> 0 | AF18: =T18+AA18 -> 0 | AG18: =U18+AB18 -> 0 | AH18: =V18+AC18 -> 0 | AI18: =W18+AD18 -> 0 | AJ18: =SUM(AF18:AI18) -> 0
... I24: =SUM(E24:H24) -> 0 | N24: =SUM(J24:M24) -> 0 | S24: =SUM(O24:R24) -> 0 | T24: =E24+J24-O24 -> 0 | U24: =F24+K24-P24 -> 0 | V24: =G24+L24-Q24 -> 0 | W24: =H24+M24-R24 -> 0 | X24: =SUM(T24:W24) -> 0 | AE24: =SUM(AA24:AD24) -> 0 | AF24: =T24+AA24 -> 0 | AG24: =U24+AB24 -> 0 | AH24: =V24+AC24 -> 0 | AI24: =W24+AD24 -> 0 | AJ24: =SUM(AF24:AI24) -> 0
A25: 合计 | D25: =SUM(D6:D24) -> 0 | E25: =SUM(E6:E24) -> 0 | F25: =SUM(F6:F24) -> 0 | G25: =SUM(G6:G24) -> 0 | H25: =SUM(H6:H24) -> 0 | I25: =SUM(I6:I24) -> 0 | J25: =SUM(J6:J24) -> 0 | K25: =SUM(K6:K24) -> 0 | ... AJ25: =SUM(AJ6:AJ24) -> 0
A27: 1、审计说明： | O27: 2、审计结论：
A31: 提示1：计入合同履约成本须同时满足的条件：：
A32: （1）不属于其他企业会计准则规范范围，例如，《企业会计准则第1号——存货》《企业会计准则第4号——固定资产》以及《企业会计准则第6号——无形资产》等；
A33: （2）该成本与一份当前或预期取得的合同直接相关；包括直接人工、直接材料、制造费用（或类似费用）、明确由客户承担的成本以及仅因该合同而发生的其他成本；预期取得的合同应当是企业能够明确识别的合同，例如，现有合同续约后的合同、尚未获得批准的特定合同等。
A34: （3）该成本增加了企业未来用于履行履约义务的资源；（主体应当采用无形资产准则核算为履行与客户的合同而发生的培训费用，在为履行与客户的合同而发生的培训费用时确认为费用）
A35: （4）该成本预期能够收回。
A36: 提示2：
A37: （1）确认为资产的合同履约成本，初始确认时摊销期限不超过一年或一个正常营业周期的，在资产负债表中计入“存货”项目；
A38: （2）初始确认时摊销期限在一年或一个正常营业周期以上的，在资产负债表中计入“其他非流动资产”项目。
A39: 提示3：
A40: “与合同成本有关的资产”（合同履约成本）应当采用与该资产相关的商品收入确认相同的基础进行摊销，计入当期损益（营业成本）。

Sheet 合同履约成本检查表F2-56
A1: 致同会计师事务所
A2: 合同履约成本检查表
A3: =底稿目录!A2 -> 被审计单位： | I3: =底稿目录!A4 -> 编制人： | P3: =底稿目录!A5 -> 编制日期： | U3: 索引号： | V3: =底稿目录!F5 -> F2-56
A4: =底稿目录!A3 -> 截止日： | I4: =底稿目录!A6 -> 复核人： | P4: =底稿目录!A7 -> 复核日期： | U4: 页 次：
A5: 一、审计目标：
A6: 1.资产负债表中记录的合同履约成本是存在的，且已经记录在恰当的账户中
A7: 2.记录的合同履约成本由被审计单位拥有或控制
A8: 3.合同履约成本以恰当的金额包括在财务报表中，与之相关的计价或分摊调整已恰当记录，相关披露已得到恰当计量和描述
A9: 二、样本选取标准与规模：
A10: 测试总体： | B10: 所有合同履约成本项目共XX个，记账凭证共XX笔，金额XX | J10: 特定样本： | K10: XX金额以上（大额）、关联方/关联交易形成的项目、XX异常项目全部测试；
A11: 抽样总体： | B11: 测试范围扣除特定样本以外的样本，共XX个项目、XX笔记账凭证 | J11: 确定的抽样样本量： | L11: XX个项目、XX笔记账凭证 | N11: （如果使用了样本计算器计算样本量，样本量计算过程见<XX>底稿）
A12: 抽样方法： | B12: 随机选样/系统选样/货币单元抽样/随意选样（非统计抽样适用） | J12: 抽样过程： | K12: 使用IDEA（XX抽样工具）选择XX数量、金额XX的样本进行测试，抽样工具中的样本选择过程和结果见<XX>底稿
A13: 三、测试：
A14: 测试内容说明：1.原始凭证是否齐全； 2.记账凭证与原始凭证是否相符；3.账务处理是否正确；4.是否记录于恰当的会计期间；5.……
A15: 项目名称 | B15: 合同履约成本构成明细 | C15: 记账凭证 | H15: 合同/协议 | L15: 到货验收单 | O15: 物流单（运输单） | R15: 费用分配表/计算表 | U15: …… | V15: 索引号 | W15: 是否异常
C16: 凭证编号 | D16: 业务内容 | E16: 对方科目 | F16: 对方明细科目 | G16: 借方金额 | H16: 日期/编号 | I16: 供应商名称 | J16: 品名 | K16: 金额 | L16: 日期/编号 | M16: 品名 | N16: 数量 | O16: 日期/编号 | P16: 物流单位 | Q16: 数量 | R16: 月份 | S16: 金额 | T16: 分配依据
A32: 合计 | G32: =SUM(G17:G31) -> 0 | K32: =SUM(K17:K31) -> 0 | S32: =SUM(S17:S31) -> 0
A33: 四、审计说明：
A34: 1.本期借方金额检查比例： | C34: 项目 | D34: 账面金额 | E34: 检查金额 | F34: 检查比例 | G34: 如果检查比例较低请扩大检查样本量或说明原因
C35: 本期借方 | D35: ='合同履约成本构成明细表F2-55'!N25 -> 0 | E35: =G32 -> 0 | F35: =E35/D35 -> #DIV/0!
A37: 五、审计结论：

Sheet 合同履约成本减值准备测算表F2-57
A1: 致同会计师事务所
A2: 合同履约成本减值准备测算表
A3: =底稿目录!A2 -> 被审计单位： | F3: =底稿目录!A4 -> 编制人： | H3: =底稿目录!A5 -> 编制日期： | K3: 索引号： | L3: =底稿目录!F6 -> F2-57
A4: =底稿目录!A3 -> 截止日： | F4: =底稿目录!A6 -> 复核人： | H4: =底稿目录!A7 -> 复核日期： | K4: 页 次：
A5: 项目编码 | B5: 项目名称 | C5: 账面余额 | D5: 已计提减值准备 | E5: 账面价值 | F5: 转让与该资产相关的商品预期能够取得的剩余对价 | G5: 转让该相关商品估计将要发生的成本 | H5: 预期取得转让对价净额 | I5: 是否发生减值 | J5: 测算减值准备计提或转回金额 | K5: 企业账面记录的减值准备金额 | L5: 差异金额
E6: =C6-D6 -> 0 | H6: =F6-G6 -> 0 | I6: =IF(E6>H6,"是","否") -> 否 | J6: =IF(H6>E6,IF((H6-E6)>D6,-D6,-(H6-E6)),E6-H6) -> 0 | L6: =J6-K6 -> 0
E7: =C7-D7 -> 0 | H7: =F7-G7 -> 0 | I7: =IF(E7>H7,"是","否") -> 否 | J7: =IF(H7>E7,IF((H7-E7)>D7,-D7,-(H7-E7)),E7-H7) -> 0 | L7: =J7-K7 -> 0
E8: =C8-D8 -> 0 | H8: =F8-G8 -> 0 | I8: =IF(E8>H8,"是","否") -> 否 | J8: =IF(H8>E8,IF((H8-E8)>D8,-D8,-(H8-E8)),E8-H8) -> 0 | L8: =J8-K8 -> 0
E9: =C9-D9 -> 0 | H9: =F9-G9 -> 0 | I9: =IF(E9>H9,"是","否") -> 否 | J9: =IF(H9>E9,IF((H9-E9)>D9,-D9,-(H9-E9)),E9-H9) -> 0 | L9: =J9-K9 -> 0
E10: =C10-D10 -> 0 | H10: =F10-G10 -> 0 | I10: =IF(E10>H10,"是","否") -> 否 | J10: =IF(H10>E10,IF((H10-E10)>D10,-D10,-(H10-E10)),E10-H10) -> 0 | L10: =J10-K10 -> 0
E11: =C11-D11 -> 0 | H11: =F11-G11 -> 0 | I11: =IF(E11>H11,"是","否") -> 否 | J11: =IF(H11>E11,IF((H11-E11)>D11,-D11,-(H11-E11)),E11-H11) -> 0 | L11: =J11-K11 -> 0
E12: =C12-D12 -> 0 | H12: =F12-G12 -> 0 | I12: =IF(E12>H12,"是","否") -> 否 | J12: =IF(H12>E12,IF((H12-E12)>D12,-D12,-(H12-E12)),E12-H12) -> 0 | L12: =J12-K12 -> 0
E13: =C13-D13 -> 0 | H13: =F13-G13 -> 0 | I13: =IF(E13>H13,"是","否") -> 否 | J13: =IF(H13>E13,IF((H13-E13)>D13,-D13,-(H13-E13)),E13-H13) -> 0 | L13: =J13-K13 -> 0
E14: =C14-D14 -> 0 | H14: =F14-G14 -> 0 | I14: =IF(E14>H14,"是","否") -> 否 | J14: =IF(H14>E14,IF((H14-E14)>D14,-D14,-(H14-E14)),E14-H14) -> 0 | L14: =J14-K14 -> 0
E15: =C15-D15 -> 0 | H15: =F15-G15 -> 0 | I15: =IF(E15>H15,"是","否") -> 否 | J15: =IF(H15>E15,IF((H15-E15)>D15,-D15,-(H15-E15)),E15-H15) -> 0 | L15: =J15-K15 -> 0
E16: =C16-D16 -> 0 | H16: =F16-G16 -> 0 | I16: =IF(E16>H16,"是","否") -> 否 | J16: =IF(H16>E16,IF((H16-E16)>D16,-D16,-(H16-E16)),E16-H16) -> 0 | L16: =J16-K16 -> 0
E17: =C17-D17 -> 0 | H17: =F17-G17 -> 0 | I17: =IF(E17>H17,"是","否") -> 否 | J17: =IF(H17>E17,IF((H17-E17)>D17,-D17,-(H17-E17)),E17-H17) -> 0 | L17: =J17-K17 -> 0
A18: 合计 | C18: =SUM(C6:C17) -> 0 | D18: =SUM(D6:D17) -> 0 | E18: =C18-D18 -> 0 | F18: =SUM(F6:F17) -> 0 | G18: =SUM(G6:G17) -> 0 | H18: =SUM(H6:H17) -> 0 | J18: =SUM(J6:J17) -> 0 | K18: =SUM(K6:K17) -> 0 | L18: =SUM(L6:L17) -> 0
A19: 1、审计说明：
A22: 2、审计结论：
A25: 提示：
A26: 1.与合同成本有关的资产，其账面价值高于下列第一项减去第二项的差额的，超出部分应当计提减值准备，并确认为资产减值损失：一是企业因转让与该资产相关的商品预期能够取得的剩余对价；二是为转让该相关商品估计将要发生的成本。
A27: 2.企业应当按照确定交易价格的原则(关于可变对价估计的限制要求除外)预计其能够取得的剩余对价。估计将要发生的成本主要包括直接人工、直接材料、制造费用(或类似费用)、明确由客户承担的成本以及仅因该合同而发生的其他成本等。以前期间减值的因素之后发生变化，使得企业上述第一项减去第二项后的差额高于该资产账面价值的，应当转回原已计提的资产减值准备，并计入当期损益，但转回后的资产账面价值不应超过假定不计提减值准备情况下该资产在转回日的账面价值。

Sheet 亏损合同预计损失测算表F2-58
A1: 致同会计师事务所
A2: 亏损合同预计损失测算表
A3: =底稿目录!A2 -> 被审计单位： | E3: =底稿目录!A4 -> 编制人： | H3: =底稿目录!A5 -> 编制日期： | J3: 索引号： | K3: =底稿目录!F7 -> F2-58
A4: =底稿目录!A3 -> 截止日： | E4: =底稿目录!A6 -> 复核人： | H4: =底稿目录!A7 -> 复核日期： | J4: 页 次：
A5: 项目编码 | B5: 项目名称 | C5: 完工进度 | D5: 预计总收入 | E5: 预计总成本 | F5: 合同预计损失金额 | G5: 已在损益反映的亏损 | H5: 本期应确认合同亏损金额 | I5: 本期账面已确认合同亏损金额 | J5: 差异 | K5: 备注
C6: ① | D6: ② | E6: ③ | F6: ④=③-② | G6: ⑤=④*① | H6: ⑥=④-⑤ | I6: ⑦ | J6: ⑧=⑥-⑦
F7: =E7-D7 -> 0 | G7: =C7*F7 -> 0 | H7: =F7-G7 -> 0 | J7: =H7-I7 -> 0
F8: =E8-D8 -> 0 | G8: =C8*F8 -> 0 | H8: =F8-G8 -> 0 | J8: =H8-I8 -> 0
F9: =E9-D9 -> 0 | G9: =C9*F9 -> 0 | H9: =F9-G9 -> 0 | J9: =H9-I9 -> 0
F10: =E10-D10 -> 0 | G10: =C10*F10 -> 0 | H10: =F10-G10 -> 0 | J10: =H10-I10 -> 0
F11: =E11-D11 -> 0 | G11: =C11*F11 -> 0 | H11: =F11-G11 -> 0 | J11: =H11-I11 -> 0
F12: =E12-D12 -> 0 | G12: =C12*F12 -> 0 | H12: =F12-G12 -> 0 | J12: =H12-I12 -> 0
F13: =E13-D13 -> 0 | G13: =C13*F13 -> 0 | H13: =F13-G13 -> 0 | J13: =H13-I13 -> 0
F14: =E14-D14 -> 0 | G14: =C14*F14 -> 0 | H14: =F14-G14 -> 0 | J14: =H14-I14 -> 0
F15: =E15-D15 -> 0 | G15: =C15*F15 -> 0 | H15: =F15-G15 -> 0 | J15: =H15-I15 -> 0
F16: =E16-D16 -> 0 | G16: =C16*F16 -> 0 | H16: =F16-G16 -> 0 | J16: =H16-I16 -> 0
F17: =E17-D17 -> 0 | G17: =C17*F17 -> 0 | H17: =F17-G17 -> 0 | J17: =H17-I17 -> 0
F18: =E18-D18 -> 0 | G18: =C18*F18 -> 0 | H18: =F18-G18 -> 0 | J18: =H18-I18 -> 0
... F20: =E20-D20 -> 0 | G20: =C20*F20 -> 0 | H20: =F20-G20 -> 0 | J20: =H20-I20 -> 0
A21: 合计 | D21: =ROUND(SUM(D6:D20),2) -> 0 | E21: =ROUND(SUM(E6:E20),2) -> 0 | F21: =ROUND(SUM(F6:F20),2) -> 0 | G21: =SUM(G6:G20) -> 0 | H21: =D21+E21-G21 -> 0 | I21: =E21+F21-H21 -> 0 | J21: =F21+G21-I21 -> 0
A23: 1、审计说明：
A25: 2、审计结论：

Sheet 合同履约成本测试（示例）
A1: 致同会计师事务所
A2: 合同履约成本测试表
A3: =[4]底稿目录!A2 -> 被审计单位：ABC公司 | C3: =[4]底稿目录!A4 -> 编制人：张XX | F3: =[4]底稿目录!A5 -> 编制日期：2024-4-1 | I3: 索引号：
A4: =[4]底稿目录!A3 -> 截止日：202X年12月31日 | C4: =[4]底稿目录!A6 -> 复核人：李XX | F4: =[4]底稿目录!A7 -> 复核日期：2024-5-1 | I4: 页次：
A5: 一、审计目标：
B6: 判断履约成本是否符合资本化的要求及摊销的准确性。
A7: 二、审计过程：
A8: 甲公司与乙公司签订合同，为乙公司信息中心提供管理服务，合同期限为5 年。在向乙公司提供服务之前，甲公司设计并搭建了一个信息技术平台供其内部使用，该信息技术平台由相关的硬件和软件组成。甲公司需要提供设计方案，将该信息技术平台与乙公司现有的信息系统对接，并进行相关测试。该平台并不会转让给乙公司，但是，将用于向乙公司提供服务。甲公司为该平台的设计、购买硬件和软件以及信息中心的测试发生了成本。除此之外，甲公司专门指派两名员工负责向乙公司提供服务。
A9: （一）履约成本资本化判断
A10: 取得客户的合同，对合同中的成本构成进行列示、分析。
A11: 构建技术平台发生的初始成本如下：
A12: 合同初始成本构成 | B12: 合同初始成本金额 | C12: 是否按照履约成本资本化 | D12: 索引
A13: 设计服务 | B13: 40000 | C13: 是
A14: 硬件 | B14: 120000 | C14: 否
A15: 软件 | B15: 90000 | C15: 否
A16: 数据中心的测试 | B16: 100000 | C16: 是
A18: 合计 | B18: =SUM(B13:B17) -> 350000
A19: （二）摊销测算
A20: 将履约成本采用与该资产相关的商品收入确认相同的基础进行摊销
A21: 合同履约成本的构成 | B21: 合同履约初始成本金额 | C21: 本期履约进度或摊销月份 | D21: 累计履约进度或摊销月份 | E21: 摊销期限 | F21: 测算本期摊销额 | G21: 账面本期摊销金额 | H21: 本期摊销额差异 | I21: 累计应摊销额 | J21: 账面累计摊销额 | K21: 累计摊销额差异
A22: 数据中心的测试 | B22: 100000 | C22: 12 | D22: 24 | E22: =5*12 -> 60 | F22: =(B22/E22)*C22 -> 20000 | G22: 20000 | H22: =F22-G22 -> 0 | I22: =(B22/E22)*D22 -> 40000 | J22: 40000 | K22: =I22-J22 -> 0
A23: 设计服务 | B23: =B13 -> 40000 | C23: 12 | D23: 24 | E23: =5*12 -> 60 | F23: =(B23/E23)*C23 -> 8000 | G23: 8000 | H23: =F23-G23 -> 0 | I23: 11428.571 | J23: 11428.571 | K23: =I23-J23 -> 0
A27: 合计 | B27: =SUM(B22:B26) -> 140000 | F27: =SUM(F22:F26) -> 28000 | G27: =SUM(G22:G26) -> 28000 | H27: =SUM(H22:H26) -> 0 | I27: =SUM(I22:I26) -> 51428.571 | J27: =SUM(J22:J26) -> 51428.571 | K27: =SUM(K22:K26) -> 0
A28: 履约进度审核见<>
A29: 三、审计说明：
A31: 四、审计结论：
