Workbook

Sheet 底稿目录
A1: 底稿开列时，可先在以下单元格填写有关内容，以便其他底稿引用有关数据：
A2: 被审计单位：
A3: 截止日：202X年12月31日 | D3: 序号 | E3: 内容 | F3: 索引号
A4: 编制人： | D4: 1 | E4: 短期借款实质性程序表 | F4: L1A
A5: 编制日期： | D5: 2 | E5: 短期借款审定表 | F5: L1-1
A6: 复核人： | D6: 3 | E6: 短期借款附注披露（上市公司）信息核对表 | G6: 无需打印
A7: 复核日期： | D7: 4 | E7: 短期借款附注披露（国企）信息核对表 | G7: 无需打印
D8: 5 | E8: 短期借款明细表 | F8: L1-2
A9: 关于工作底稿与审计程序索引号对应的说明 | D9: 6 | E9: 调整分录汇总 | F9: L1-3
A10: 1.编制的审计工作底稿应与审计程序对应。审计项目组应根据被审计单位实际情况和风险评估情况在实质性程序表中裁剪、修改或增加审计程序，根据实际执行的审计程序完成相应审计工作底稿，编制的工作底稿中应按自然顺序依次编制索引号，并通过唯一的索引号将与实质性程序表中的程序对应关联（即将工作底稿的索引号填入实质性程序表中的底稿索引号列）。 | D10: 7 | E10: ='征信报告核对表L1-4'!A2 -> 征信报告核对表 | F10: L1-4
D11: 8 | E11: ='利息测算表L1-5'!A2 -> 短期借款利息测算表 | F11: L1-5
D12: 9 | E12: 贷款合同检查表 | F12: L1-6
D13: 10 | E13: ='逾期贷款检查表L1-7'!A2 -> 逾期贷款检查表 | F13: L1-7
A14: 2.获取的支持性证据应与审计底稿或程序对应。审计项目组在完成底稿时获取的支持性证据应根据底稿索引号编制下一级按自然顺序排序的索引号（如D1-2-1、D1-2-2、……），并在底稿中说明引用的支持性证据、关联索引号。 | D14: 11 | E14: ='抵质押资产检查表L1-8'!A2 -> 抵/质押资产检查表 | F14: L1-8
D15: 12 | E15: 函证结果汇总表 | F15: E0-1
D16: 13 | E16: 核实被函证单位信息 | F16: E0-2
A17: 3.工作底稿索引号的编码规则：实质性程序索引号按循环从“D”到“N”,循环内账户以顺序号排列，模板中底稿索引号按账户顺序+自然数顺序（即模板中索引号按二级自然顺序排列，如D1-1、D1-2、D1-3、……D1-N）。 | D17: 14 | E17: 货币资金发函记录表 | F17: E0-3
D18: 15 | E18: 借款发函记录表 | F18: E0-4
D19: 16 | E19: 跟函函证过程控制 | F19: E0-7
D20: 17 | E20: 函证程序舞弊风险评价表 | F20: E0-8
D21: 18 | E21: ='短期借款检查表L1-9'!A2 -> 短期借款检查底稿 | F21: L1-9

Sheet  短期借款实质性程序表L1A
A1: 致同会计师事务所
A2: 短期借款实质性程序
A3: =底稿目录!A2 -> 被审计单位： | C3: =底稿目录!A4 -> 编制人： | E3: =底稿目录!A5 -> 编制日期： | H3: 索引号： | I3: L1A
A4: =底稿目录!A3 -> 截止日：202X年12月31日 | C4: =底稿目录!A6 -> 复核人： | E4: =底稿目录!A7 -> 复核日期： | H4: 页 次：
A5: 一、本账户涉及的科目
A6: 短期借款
A7: 二、审计目标与认定对应关系
A8: 审计目标 | G8: 财务报表的认定
A9: A. 资产负债表中记录的短期借款是存在的，且已记录于恰当的账户 | G9: 存在
A10: B. 所有应记录的短期借款均已记录，所有应当包括在财务报表中的相关披露均已包括 | G10: 完整性
A11: C. 记录的短期借款是被审计单位应当履行的偿还义务 | G11: 权利和义务
A12: D. 短期借款以恰当的金额包括在财务报表中，与之相关的计价或分摊调整已恰当记录，相关披露已得到恰当计量和描述 | G12: 准确性、计价和分摊
A13: E. 短期借款已被恰当地汇总或分解且表述清楚，相关披露在按照企业会计准则的编制基础下是相关的、可理解的 | G13: 列报
A14: 三、计划实施的实质性程序
A15: 序号 | B15: 审计程序 | C15: 程序分类 | D15: 财务报表的认定 | I15: 底稿索引号
D16: 存在 | E16: 完整性 | F16: 权利和义务 | G16: 准确性、计价和分摊 | H16: 列报 | J16: 根据被审计单位实际情况和风险评估情况裁剪、修改或增加审计程序
A17: 1 | B17: 获取或编制短期借款的明细表，完成以下工作，并编制审定表 （1）复核加计是否正确，与总账、明细账合计数核对是否相符，期初余额与上期审定期末余额是否相符； （2）检查非记账本位币债务的折算汇率及折算金额是否正确，折算方法是否前后期一致。 | C17: 常规★ | D17: √ | E17: √ | G17: √ | I17: L1-1 /L1-2
A18: 2 | B18: 在使用手工编制、自定义信息报告、系统生成的非固定格式报告等由被审计单位生成的信息时，测试有关信息准确性和完整性，并针对编制和维护由被审计单位生成的信息的相关控制实施控制测试，以评价该信息是否能够为实现审计目的提供基础。 | C18: 常规★ | E18: √ | G18: √ | I18: T1 / | J18: 可参见《审计手册》4.2.6，由被审计单位生成的信息可能是由系统生成的、或手工编制的、或二者兼而有之的方式生成的。例如，由被审计单位生成的信息可能包括： • 不涉及自定义的、由系统生成的报告（如，固定格式报告）； • 可能通过人工自定义的、由系统生成的报告，例如，（计算机）查询信息或特别定制的报告； • 手工编制的信息，例如，汇总信息的电子表格或用以支持分配、计算以及调节的电子表格； • 其他系统生成或手工编制的信息，例如，由被审计单位编制的客户发票； • 通过影印、拍摄、扫描或其他方式转换成电子形式的文件记录。
A19: 3 | B19: 对期初余额的审计，取得短期借款期初余额明细表复核加计是否正确，与总账、明细账合计数是否相符。获得每项债务的信息，包括与债权人函证余额、抵押品、到期日、利率、担保等。检查上期短期借款在本期归还情况，函证期初余额以及其他必要追加的审计程序。（适用于首次承接） | C19: 备选 | D19: √ | E19: √ | F19: √ | G19: √ | J19: 由被审计单位生成的信息不包括： • 总分类账或明细分类账、试算平衡表、或经审计的财务报表； • 第三方（除了服务机构）的报表或报告，例如，原始银行对账单，或函证的回函； • 外部数据（例如，第三方发布的数据，如，定价来源）。
A20: 4 | B20: 获取被审计单位资产负债表日后最近一期的企业信用报告，核对关键信息，核实账面记录是否准确、完整。对被审计单位企业信用报告中列示的信息与账面记录核对的差异进行分析，关注企业信用报告中列示的被审计单位对外担保的信息。 | C20: 常规★ | D20: √ | E20: √ | F20: √ | I20: L1-4
A21: 5 | B21: 借款利息测算及资本化判断： （1）对短期借款的利息进行测算并与本期实计利息核对，检查会计处理是否正确； （2）结合存货、固定资产等循环审计，关注借款费用资本化是否恰当，资本化的处理是否符合规定，确认全部利息费用已正确区分为资本性支出和收益性支出，并已正确入账。 | C21: 常规★ | G21: √ | I21: L1-5
A22: 6 | B22: 针对性检查： （1）对本期新增债务，获取借款合同、担保合同、银行放款原始凭证等，关注金额、利率、期限等相关信息，检查会计处理是否正确。 （2）对本期减少的债务，获取归还借款的原始凭证，核实还款数据，检查会计处理是否正确。 （3）关注逾期借款的形成原因、还款计划调整、利息偿还情况及诉讼或其法律纠纷，若逾期金额较大，需评估对企业持续经营能力的影响，并检查是否已充分披露相关事项。 | C22: 常规★ | D22: √ | E22: √ | F22: √ | G22: √ | H22: √ | I22: L1-6 /L1-7 /L1-9
A23: 7 | B23: 检查被审计单位用于短期借款的抵押或质押等资产的所有权是否属于被审计单位，其价值和实际状况是否与契约中的规定相一致。 | C23: 常规★ | F23: √ | H23: √ | I23: L1-8
A24: 8 | B24: 实施函证程序： （1）以积极方式对短期借款进行函证，设计询证函、发函前核实被函证单位信息； （2）注册会计师独立收发询证函； （3）编制函证结果汇总表，检查发函、回函物流信息和轨迹、比对回函印章和签字等以核实回函的真实性，检查回函是否相符，对不符事项查明原因确定是否存在错报； （4）如果未收到回函，应当考虑与被询证者联系，要求对方作出回应或再次寄发询证函； （5）如果管理层不允许寄发询证函的，询问管理层不允许寄发的原因，并就其原因的正当、合理性收集证据；考虑实施替代审计程序以获取相关、可靠的审计证据； （6）如果管理层不允许寄发询证函的原因不合理、或者认为回函不可靠，评价对评估的重大错报风险以及其他审计程序的性质、时间安排和范围的影响，并确定其对审计工作和审计意见的影响。 | C24: 常规★ | D24: √ | E24: √ | F24: √ | G24: √ | I24: E0 | J24: 对短期借款进行函证。除非有充分证据表明某一借款对财务报表不重要且与之相关的重大错报风险很低。如果不对这些项目实施函证程序，在审计工作底稿中说明理由。
A25: 9 | B25: 根据评估的舞弊风险等因素增加的审计程序。 | C25: IPO/上市/新三板/重组/舞弊应对
A26: 10 | B26: 检查短期借款是否已按企业会计准则或其他适用的规定在财务报表中做出恰当列报和披露。 | C26: 常规★ | H26: √ | I26: A1-1/A1-15 /A1-16

Sheet 审定表L1-1
A1: 致同会计师事务所
A2: 短期借款审定表
A3: =底稿目录!A2 -> 被审计单位： | E3: =底稿目录!A4 -> 编制人： | I3: =底稿目录!A5 -> 编制日期： | M3: 索引号： | N3: =底稿目录!F5 -> L1-1
A4: =底稿目录!A3 -> 截止日：202X年12月31日 | E4: =底稿目录!A6 -> 复核人： | I4: =底稿目录!A7 -> 复核日期： | M4: 页 次：
A5: 项目 | B5: 期初数 | F5: 期末数 | J5: 本期未审数与上期 审定数的比较 | L5: 本期审定数与上期 审定数的比较 | N5: 原因分析
B6: 未审数 | C6: 账项调整 | D6: 重分类调整 | E6: 审定数 | F6: 未审数 | G6: 账项调整 | H6: 重分类调整 | I6: 审定数 | J6: 变动额 | K6: 变动率 | L6: 变动额 | M6: 变动率
A7: 信用借款 | B7: =SUMIF('明细表L1-2'!$B:$B,'审定表L1-1'!$A7,'明细表L1-2'!$H:$H) -> 0 | C7: =SUMIF('明细表L1-2'!$B:$B,'审定表L1-1'!$A7,'明细表L1-2'!L:L) -> 0 | D7: =SUMIF('明细表L1-2'!$B:$B,'审定表L1-1'!$A7,'明细表L1-2'!M:M) -> 0 | E7: =B7+C7+D7 -> 0 | F7: =SUMIF('明细表L1-2'!$B:$B,'审定表L1-1'!$A7,'明细表L1-2'!$K:$K) -> 0 | G7: =SUMIF('明细表L1-2'!$B:$B,'审定表L1-1'!$A7,'明细表L1-2'!$N:$N)-SUMIF('明细表L1-2'!$B:$B,'审定表L1-1'!$A7,'明细表L1-2'!$O:$O) -> 0 | H7: =SUMIF('明细表L1-2'!$B:$B,'审定表L1-1'!$A7,'明细表L1-2'!$P:$P)-SUMIF('明细表L1-2'!$B:$B,'审定表L1-1'!$A7,'明细表L1-2'!$Q:$Q) -> 0 | I7: =F7+G7+H7 -> 0 | J7: =F7-B7 -> 0 | K7: =IF(AND(B7=0,J7=0),0,IF(AND(B7=0,J7>0),1,J7/B7)) -> 0 | L7: =I7-E7 -> 0 | M7: =IF(AND(E7=0,L7=0),0,IF(AND(E7=0,L7>0),1,L7/E7)) -> 0
A8: 抵押借款 | B8: =SUMIF('明细表L1-2'!$B:$B,'审定表L1-1'!$A8,'明细表L1-2'!$H:$H) -> 0 | C8: =SUMIF('明细表L1-2'!$B:$B,'审定表L1-1'!$A8,'明细表L1-2'!L:L) -> 0 | D8: =SUMIF('明细表L1-2'!$B:$B,'审定表L1-1'!$A8,'明细表L1-2'!M:M) -> 0 | E8: =B8+C8+D8 -> 0 | F8: =SUMIF('明细表L1-2'!$B:$B,'审定表L1-1'!$A8,'明细表L1-2'!$K:$K) -> 0 | G8: =SUMIF('明细表L1-2'!$B:$B,'审定表L1-1'!$A8,'明细表L1-2'!$N:$N)-SUMIF('明细表L1-2'!$B:$B,'审定表L1-1'!$A8,'明细表L1-2'!$O:$O) -> 0 | H8: =SUMIF('明细表L1-2'!$B:$B,'审定表L1-1'!$A8,'明细表L1-2'!$P:$P)-SUMIF('明细表L1-2'!$B:$B,'审定表L1-1'!$A8,'明细表L1-2'!$Q:$Q) -> 0 | I8: =F8+G8+H8 -> 0 | J8: =F8-B8 -> 0 | K8: =IF(AND(B8=0,J8=0),0,IF(AND(B8=0,J8>0),1,J8/B8)) -> 0 | L8: =I8-E8 -> 0 | M8: =IF(AND(E8=0,L8=0),0,IF(AND(E8=0,L8>0),1,L8/E8)) -> 0
A9: 保证借款 | B9: =SUMIF('明细表L1-2'!$B:$B,'审定表L1-1'!$A9,'明细表L1-2'!$H:$H) -> 0 | C9: =SUMIF('明细表L1-2'!$B:$B,'审定表L1-1'!$A9,'明细表L1-2'!L:L) -> 0 | D9: =SUMIF('明细表L1-2'!$B:$B,'审定表L1-1'!$A9,'明细表L1-2'!M:M) -> 0 | E9: =B9+C9+D9 -> 0 | F9: =SUMIF('明细表L1-2'!$B:$B,'审定表L1-1'!$A9,'明细表L1-2'!$K:$K) -> 0 | G9: =SUMIF('明细表L1-2'!$B:$B,'审定表L1-1'!$A9,'明细表L1-2'!$N:$N)-SUMIF('明细表L1-2'!$B:$B,'审定表L1-1'!$A9,'明细表L1-2'!$O:$O) -> 0 | H9: =SUMIF('明细表L1-2'!$B:$B,'审定表L1-1'!$A9,'明细表L1-2'!$P:$P)-SUMIF('明细表L1-2'!$B:$B,'审定表L1-1'!$A9,'明细表L1-2'!$Q:$Q) -> 0 | I9: =F9+G9+H9 -> 0 | J9: =F9-B9 -> 0 | K9: =IF(AND(B9=0,J9=0),0,IF(AND(B9=0,J9>0),1,J9/B9)) -> 0 | L9: =I9-E9 -> 0 | M9: =IF(AND(E9=0,L9=0),0,IF(AND(E9=0,L9>0),1,L9/E9)) -> 0
A10: 质押借款 | B10: =SUMIF('明细表L1-2'!$B:$B,'审定表L1-1'!$A10,'明细表L1-2'!$H:$H) -> 0 | C10: =SUMIF('明细表L1-2'!$B:$B,'审定表L1-1'!$A10,'明细表L1-2'!L:L) -> 0 | D10: =SUMIF('明细表L1-2'!$B:$B,'审定表L1-1'!$A10,'明细表L1-2'!M:M) -> 0 | E10: =B10+C10+D10 -> 0 | F10: =SUMIF('明细表L1-2'!$B:$B,'审定表L1-1'!$A10,'明细表L1-2'!$K:$K) -> 0 | G10: =SUMIF('明细表L1-2'!$B:$B,'审定表L1-1'!$A10,'明细表L1-2'!$N:$N)-SUMIF('明细表L1-2'!$B:$B,'审定表L1-1'!$A10,'明细表L1-2'!$O:$O) -> 0 | H10: =SUMIF('明细表L1-2'!$B:$B,'审定表L1-1'!$A10,'明细表L1-2'!$P:$P)-SUMIF('明细表L1-2'!$B:$B,'审定表L1-1'!$A10,'明细表L1-2'!$Q:$Q) -> 0 | I10: =F10+G10+H10 -> 0 | J10: =F10-B10 -> 0 | K10: =IF(AND(B10=0,J10=0),0,IF(AND(B10=0,J10>0),1,J10/B10)) -> 0 | L10: =I10-E10 -> 0 | M10: =IF(AND(E10=0,L10=0),0,IF(AND(E10=0,L10>0),1,L10/E10)) -> 0
A11: 合计 | B11: =SUM(B7:B10) -> 0 | C11: =SUM(C7:C10) -> 0 | D11: =SUM(D7:D10) -> 0 | E11: =SUM(E7:E10) -> 0 | F11: =SUM(F7:F10) -> 0 | G11: =SUM(G7:G10) -> 0 | H11: =SUM(H7:H10) -> 0 | I11: =SUM(I7:I10) -> 0 | J11: =SUM(J7:J10) -> 0 | K11: =IF(AND(B11=0,J11=0),0,IF(AND(B11=0,J11>0),1,J11/B11)) -> 0 | L11: =SUM(L7:L10) -> 0 | M11: =IF(AND(E11=0,L11=0),0,IF(AND(E11=0,L11>0),1,L11/E11)) -> 0
A12: 1、审计说明
A13: （1）短期借款期末余额较期初余额增加（负数为减少）：
A14: 主要原因（比例超过30%的）：
A15: （2）已到期未偿还的短期借款情况说明。（贷款单位、贷款金额、贷款利率、贷款资金用途、未按期偿还的原因及预计还款期，
A16: 并在期后事项中反映报表日后是否已偿还。若已到期的短期借款获得展期，应说明展期条件、新的到期日。）
A17: （3）公司用于抵押、质押的财产情况说明。
A18: （4）关联方保证、抵押或质押情况说明。
A19: 2、审计结论

Sheet 附注披露信息核对（上市公司）
A1: 致同会计师事务所
A2: 短期借款附注披露信息
A3: =底稿目录!A2 -> 被审计单位： | B3: =底稿目录!A4 -> 编制人： | C3: =底稿目录!A5 -> 编制日期： | E3: 索引号：
A4: =底稿目录!A3 -> 截止日：202X年12月31日 | B4: =底稿目录!A6 -> 复核人： | C4: =底稿目录!A7 -> 复核日期： | E4: 页次：
A5: 附注披露信息（上市公司）：
A6: （1）短期借款分类
A7: 项 目 | B7: 期末余额 | C7: 上年年末余额
A8: 信用借款 | B8: =SUMIF('明细表L1-2'!B:B,'附注披露信息核对（上市公司）'!A8,'明细表L1-2'!U:U) -> 0 | C8: =SUMIF('明细表L1-2'!B:B,'附注披露信息核对（上市公司）'!A8,'明细表L1-2'!R:R) -> 0
A9: 质押借款 | B9: =SUMIF('明细表L1-2'!B:B,'附注披露信息核对（上市公司）'!A9,'明细表L1-2'!U:U) -> 0 | C9: =SUMIF('明细表L1-2'!B:B,'附注披露信息核对（上市公司）'!A9,'明细表L1-2'!R:R) -> 0
A10: 抵押借款 | B10: =SUMIF('明细表L1-2'!B:B,'附注披露信息核对（上市公司）'!A10,'明细表L1-2'!U:U) -> 0 | C10: =SUMIF('明细表L1-2'!B:B,'附注披露信息核对（上市公司）'!A10,'明细表L1-2'!R:R) -> 0
A11: 保证借款 | B11: =SUMIF('明细表L1-2'!B:B,'附注披露信息核对（上市公司）'!A11,'明细表L1-2'!U:U) -> 0 | C11: =SUMIF('明细表L1-2'!B:B,'附注披露信息核对（上市公司）'!A11,'明细表L1-2'!R:R) -> 0
A12: 合 计 | B12: =SUM(B9:B11) -> 0 | C12: =SUM(C9:C11) -> 0
A13: 说明：（用于抵押、质押的财产）
A14: （2）逾期借款情况（如无，删除）
A15: （汇总披露逾期借款（包括从长期借款转入的）的期末余额。对于重要的逾期借款，还应按借款单位列示借款期末余额、借款利率、逾期时间、逾期利率。）
A16: 本期末已逾期未偿还的短期借款余款合计XXX元，其中由长期借款转入金额为XXX元。
A17: 重要的逾期借款情况如下：
A18: 借款单位 | B18: 期末余额 | C18: 借款利率 | D18: 逾期时间 | E18: 逾期利率
A19: =IF('逾期贷款检查表L1-7'!J11,'逾期贷款检查表L1-7'!B11,"") | B19: =IF('逾期贷款检查表L1-7'!J11,'逾期贷款检查表L1-7'!E11,"") | C19: =IF('逾期贷款检查表L1-7'!J11>0,'逾期贷款检查表L1-7'!F11,"") | D19: =IF('逾期贷款检查表L1-7'!J11>0,'逾期贷款检查表L1-7'!J11,"") | E19: =IF('逾期贷款检查表L1-7'!J11,'逾期贷款检查表L1-7'!G11,"")
A20: =IF('逾期贷款检查表L1-7'!J12,'逾期贷款检查表L1-7'!B12,"") | B20: =IF('逾期贷款检查表L1-7'!J12,'逾期贷款检查表L1-7'!E12,"") | C20: =IF('逾期贷款检查表L1-7'!J12>0,'逾期贷款检查表L1-7'!F12,"") | D20: =IF('逾期贷款检查表L1-7'!J12>0,'逾期贷款检查表L1-7'!J12,"") | E20: =IF('逾期贷款检查表L1-7'!J12,'逾期贷款检查表L1-7'!G12,"")
A21: =IF('逾期贷款检查表L1-7'!J13,'逾期贷款检查表L1-7'!B13,"") | B21: =IF('逾期贷款检查表L1-7'!J13,'逾期贷款检查表L1-7'!E13,"") | C21: =IF('逾期贷款检查表L1-7'!J13>0,'逾期贷款检查表L1-7'!F13,"") | D21: =IF('逾期贷款检查表L1-7'!J13>0,'逾期贷款检查表L1-7'!J13,"") | E21: =IF('逾期贷款检查表L1-7'!J13,'逾期贷款检查表L1-7'!G13,"")
A22: =IF('逾期贷款检查表L1-7'!J14,'逾期贷款检查表L1-7'!B14,"") | B22: =IF('逾期贷款检查表L1-7'!J14,'逾期贷款检查表L1-7'!E14,"") | C22: =IF('逾期贷款检查表L1-7'!J14>0,'逾期贷款检查表L1-7'!F14,"") | D22: =IF('逾期贷款检查表L1-7'!J14>0,'逾期贷款检查表L1-7'!J14,"") | E22: =IF('逾期贷款检查表L1-7'!J14,'逾期贷款检查表L1-7'!G14,"")
A23: 合 计 | B23: =SUM(B19:B22) -> 0 | C23: -- | D23: -- | E23: --
A24: 说明：（用于抵押、质押的财产）

Sheet 附注披露信息核对（国企）
A1: 致同会计师事务所
A2: 短期借款附注披露信息
A3: =底稿目录!A2 -> 被审计单位： | B3: =底稿目录!A4 -> 编制人： | C3: =底稿目录!A5 -> 编制日期： | D3: 索引号：
A4: =底稿目录!A3 -> 截止日：202X年12月31日 | B4: =底稿目录!A6 -> 复核人： | C4: =底稿目录!A7 -> 复核日期： | D4: 页次：
A5: 附注披露信息（国企）：
A6: 短期借款
A7: （1）短期借款分类
A8: 借款类别 | B8: 期末余额 | C8: 年初余额
A9: 质押借款 | B9: =SUMIF('明细表L1-2'!B:B,A9,'明细表L1-2'!U:U) -> 0 | C9: =SUMIF('明细表L1-2'!B:B,A9,'明细表L1-2'!R:R) -> 0
A10: 抵押借款 | B10: =SUMIF('明细表L1-2'!B:B,A10,'明细表L1-2'!U:U) -> 0 | C10: =SUMIF('明细表L1-2'!B:B,A10,'明细表L1-2'!R:R) -> 0
A11: 保证借款 | B11: =SUMIF('明细表L1-2'!B:B,A11,'明细表L1-2'!U:U) -> 0 | C11: =SUMIF('明细表L1-2'!B:B,A11,'明细表L1-2'!R:R) -> 0
A12: 信用借款 | B12: =SUMIF('明细表L1-2'!B:B,A12,'明细表L1-2'!U:U) -> 0 | C12: =SUMIF('明细表L1-2'!B:B,A12,'明细表L1-2'!R:R) -> 0
A13: 合 计 | B13: =SUM(B9:B12) -> 0 | C13: =SUM(C9:C12) -> 0
A15: （2）已逾期未偿还的短期借款情况
A16: 债权单位 | B16: 期末余额 | C16: 借款利率
A17: =IF('逾期贷款检查表L1-7'!J11,'逾期贷款检查表L1-7'!B11,"") | B17: =IF('逾期贷款检查表L1-7'!J11,'逾期贷款检查表L1-7'!E11,"") | C17: =IF('逾期贷款检查表L1-7'!J11>0,'逾期贷款检查表L1-7'!F11,"")
A18: =IF('逾期贷款检查表L1-7'!J12,'逾期贷款检查表L1-7'!B12,"") | B18: =IF('逾期贷款检查表L1-7'!J12,'逾期贷款检查表L1-7'!E12,"") | C18: =IF('逾期贷款检查表L1-7'!J12>0,'逾期贷款检查表L1-7'!F12,"")
A19: =IF('逾期贷款检查表L1-7'!J13,'逾期贷款检查表L1-7'!B13,"") | B19: =IF('逾期贷款检查表L1-7'!J13,'逾期贷款检查表L1-7'!E13,"") | C19: =IF('逾期贷款检查表L1-7'!J13>0,'逾期贷款检查表L1-7'!F13,"")
A20: =IF('逾期贷款检查表L1-7'!J14,'逾期贷款检查表L1-7'!B14,"") | B20: =IF('逾期贷款检查表L1-7'!J14,'逾期贷款检查表L1-7'!E14,"") | C20: =IF('逾期贷款检查表L1-7'!J14>0,'逾期贷款检查表L1-7'!F14,"")
A21: 合 计 | B21: =SUM(B17:B20) -> 0 | C21: --
A22: 说明：
A23: ① 资产负债表日后已偿还金额XX元。
A24: ②（包括已到期短期借款或展期的，若已到期的短期借款获得展期，应说明展期条件、新的到期日。）

Sheet 明细表L1-2
A1: 致同会计师事务所 | P1: 致同会计师事务所
A2: 短期借款明细表 | P2: 短期借款明细表
A3: =底稿目录!A2 -> 被审计单位： | D3: =底稿目录!A4 -> 编制人： | K3: =底稿目录!A5 -> 编制日期： | N3: 索引号： | O3: =底稿目录!F8 -> L1-2 | Q3: =D3 -> 编制人： | V3: =K3 -> 编制日期： | AA3: 索引号： | AB3: =底稿目录!F8 -> L1-2
A4: =底稿目录!A3 -> 截止日：202X年12月31日 | D4: =底稿目录!A6 -> 复核人： | K4: =底稿目录!A7 -> 复核日期： | N4: 页次： | Q4: =D4 -> 复核人： | V4: =K4 -> 复核日期： | AA4: 页次：
A5: 一、审计目标:
D6: 1.资产负债表中记录的短期借款是存在的，且已经记录在恰当的账户中；2. 所有应记录的短期借款均已记录，所有应当包括在财务报表中的相关披露均已包括；3.应付利息以恰当的金额包括在财务报表中，与之相关的计价或分摊调整已恰当记录，相关披露已得到恰当计量和描述 | P6: 1.资产负债表中记录的短期借款是存在的，且已经记录在恰当的账户中；2. 所有应记录的短期借款均已记录，所有应当包括在财务报表中的相关披露均已包括；3.应付利息以恰当的金额包括在财务报表中，与之相关的计价或分摊调整已恰当记录，相关披露已得到恰当计量和描述
A7: 二、审计过程：
A8: 序号 | B8: 借款种类 | C8: 贷款单位 | D8: 起始日期 | E8: 讫止日期 | F8: 年利率 | G8: 固定/浮动利率 | H8: 未审数 | L8: 期初调整 | N8: 账项调整 | P8: 重分类调整 | R8: 审定数 | V8: 借款用途 | W8: 保证人/抵押物/质押物 | X8: 借款合同（索引） | Y8: 是否逾期 | Z8: 询证函（索引） | AA8: 与征信报告核对(√) | AB8: 备注
H9: 期初余额 | I9: 本期增加 | J9: 本期减少 | K9: 期末余额 | L9: 账项调整 | M9: 重分类调整 | N9: 本期增加 | O9: 本期减少 | P9: 本期增加 | Q9: 本期减少 | R9: 期初余额 | S9: 本期增加 | T9: 本期减少 | U9: 期末余额
A10: 1 | K10: =H10+I10-J10 -> 0 | R10: =H10+L10+M10 -> 0 | S10: =I10+N10+P10 -> 0 | T10: =J10+O10+Q10 -> 0 | U10: =R10+S10-T10 -> 0
A11: 2 | K11: =H11+I11-J11 -> 0 | R11: =H11+L11+M11 -> 0 | S11: =I11+N11+P11 -> 0 | T11: =J11+O11+Q11 -> 0 | U11: =R11+S11-T11 -> 0
A12: 3 | K12: =H12+I12-J12 -> 0 | R12: =H12+L12+M12 -> 0 | S12: =I12+N12+P12 -> 0 | T12: =J12+O12+Q12 -> 0 | U12: =R12+S12-T12 -> 0
A13: 4 | K13: =H13+I13-J13 -> 0 | R13: =H13+L13+M13 -> 0 | S13: =I13+N13+P13 -> 0 | T13: =J13+O13+Q13 -> 0 | U13: =R13+S13-T13 -> 0
A14: 5 | K14: =H14+I14-J14 -> 0 | R14: =H14+L14+M14 -> 0 | S14: =I14+N14+P14 -> 0 | T14: =J14+O14+Q14 -> 0 | U14: =R14+S14-T14 -> 0
A15: 6 | K15: =H15+I15-J15 -> 0 | R15: =H15+L15+M15 -> 0 | S15: =I15+N15+P15 -> 0 | T15: =J15+O15+Q15 -> 0 | U15: =R15+S15-T15 -> 0
A16: 7 | K16: =H16+I16-J16 -> 0 | R16: =H16+L16+M16 -> 0 | S16: =I16+N16+P16 -> 0 | T16: =J16+O16+Q16 -> 0 | U16: =R16+S16-T16 -> 0
A17: 8 | K17: =H17+I17-J17 -> 0 | R17: =H17+L17+M17 -> 0 | S17: =I17+N17+P17 -> 0 | T17: =J17+O17+Q17 -> 0 | U17: =R17+S17-T17 -> 0
A18: 9 | K18: =H18+I18-J18 -> 0 | R18: =H18+L18+M18 -> 0 | S18: =I18+N18+P18 -> 0 | T18: =J18+O18+Q18 -> 0 | U18: =R18+S18-T18 -> 0
A19: 10 | K19: =H19+I19-J19 -> 0 | R19: =H19+L19+M19 -> 0 | S19: =I19+N19+P19 -> 0 | T19: =J19+O19+Q19 -> 0 | U19: =R19+S19-T19 -> 0
A20: 11 | K20: =H20+I20-J20 -> 0 | R20: =H20+L20+M20 -> 0 | S20: =I20+N20+P20 -> 0 | T20: =J20+O20+Q20 -> 0 | U20: =R20+S20-T20 -> 0
A21: 12 | K21: =H21+I21-J21 -> 0 | R21: =H21+L21+M21 -> 0 | S21: =I21+N21+P21 -> 0 | T21: =J21+O21+Q21 -> 0 | U21: =R21+S21-T21 -> 0
... A25: 16 | K25: =H25+I25-J25 -> 0 | R25: =H25+L25+M25 -> 0 | S25: =I25+N25+P25 -> 0 | T25: =J25+O25+Q25 -> 0 | U25: =R25+S25-T25 -> 0
C26: 合计 | D26: —— | E26: —— | F26: —— | H26: =SUM(H10:H25) -> 0 | I26: =SUM(I10:I25) -> 0 | J26: =SUM(J10:J25) -> 0 | K26: =SUM(K10:K25) -> 0 | L26: =SUM(L10:L25) -> 0 | M26: =SUM(M10:M25) -> 0 | N26: =SUM(N10:N25) -> 0 | O26: =SUM(O10:O25) -> 0 | ... U26: =SUM(U10:U25) -> 0
A27: 1、如为外币借款，应在“备注”栏中说明原币金额及折合汇率。
A28: 2、如存在逾期借款，应在“备注”栏中说明。
A29: 三、审计说明：
A32: 四、审计结论：
A34: 提示：
A35: 1.对已到期未偿还的短期借款，应单独列示贷款单位.贷款金额.贷款利率.贷款资金用途.未按期偿还的原因及预计还款期，并在期后事项中反映报表日后是否已偿还。
A36: 2.应说明公司用于抵押.质押的财产情况；说明关联方保证.抵押或质押情况。。
A37: 3.取得年度内所有借款合同.相应担保合同（保证.抵押.质押）.借据.还款单。
A38: 4.与银行存款一起发函询证。
A39: 5.审计说明可以概述：（1）程序的测试情况.结果；（2）拟调整事项及其调整分录.未调整事项及其影响，审计范围受到限制情况及其影响。
A40: 6.审计结论可参考：A.未见异常。 B.除上述重大不符事项应当作为调整事项予以调整外，其余未见异常。 C.由于存在以下重大未调整事项（或审计范围受到限制无法获取充分.适当证据），不可确认。

Sheet 调整分录汇总L1-3
A1: 致同会计师事务所
A2: 短期借款调整分录汇总表
A3: 客户名称： | C3: 编制人： | G3: 编制日期： | I3: 索引： | J3: =底稿目录!F9 -> L1-3
A4: 截止日：202X年12月31日 | C4: 复核人： | G4: 复核日期： | I4: 页次：
A5: 调整事项说明 | B5: 类别（报表调整/账项调整/其他） | C5: 报表项目 | D5: 科目名称 | E5: 附注项目 | F5: …… | G5: 借方调整金额 | H5: 贷方调整金额 | I5: 索引 | J5: 备注
A23: 注：本底稿适用于调整分录较多、较复杂的项目，且仅列示与本报表项目相关的审计调整。项目组可根据项目实际情况选择是否使用该底稿。

Sheet 征信报告核对表L1-4
A1: 致同会计师事务所
A2: 征信报告核对表
A3: =底稿目录!A2 -> 被审计单位： | G3: =底稿目录!A4 -> 编制人： | N3: =底稿目录!A5 -> 编制日期： | S3: 索引号： | T3: =底稿目录!F10 -> L1-4
A4: =底稿目录!A3 -> 截止日：202X年12月31日 | G4: =底稿目录!A6 -> 复核人： | N4: =底稿目录!A7 -> 复核日期： | S4: 页次
A5: 一、审计目标:
A6: 1.资产负债表中记录的短期借款是存在的，且已经记录在恰当的账户中；2. 所有应记录的短期借款均已记录，所有应当包括在财务报表中的相关披露均已包括
A7: 二、审计过程：
A8: 获取企业征信报告并：1.考虑审查文件（如董事会/财务委员会会议纪要和信件）、定期存单原件，并在银行询证函中注明该定期存单是否已被质押或冻结；2.考虑检查房屋建筑物或土地使用权等权证的原件，如果被审计单位无法提供原件，则应追查原因，并向房产交易中心查询该权证是否已用于抵押或交易，以判断被审计单位是否存在未入账的银行借款。
A9: 1.测算过程
A10: 类别 | B10: 授信机构 | C10: 业务种类 | D10: 开立日期 | E10: 到期日 | F10: 币种 | G10: 借款金额 | H10: 发放形式 | I10: 担保方式 | J10: 企业信用查询记录信息余额 | K10: 逾期总额 | L10: 逾期本金 | M10: 逾期月数 | N10: 查询日到财务报表日减少金额 | O10: 查询日到财务报表日增加金额 | P10: 财务报表日的倒轧余额 | Q10: 账面借款金额 | R10: 征信报告信息与账面数据差异 | S10: 差异原因 | T10: 备注
P11: =J11+N11-O11 -> 0 | R11: =P11-Q11 -> 0
P12: =J12+N12-O12 -> 0 | R12: =P12-Q12 -> 0
P13: =J13+N13-O13 -> 0 | R13: =P13-Q13 -> 0
P14: =J14+N14-O14 -> 0 | R14: =P14-Q14 -> 0
P15: =J15+N15-O15 -> 0 | R15: =P15-Q15 -> 0
P16: =J16+N16-O16 -> 0 | R16: =P16-Q16 -> 0
A18: 2.借款人担保信息：
A19: 对外担保信息
A20: 被担保信息
A21: 3.其他信息
A22: 4.信用报告信息索引号：
A24: 三、审计说明：
A26: 四、审计结论：

Sheet 利息测算表L1-5
A1: 致同会计师事务所
A2: 短期借款利息测算表
A3: =底稿目录!A2 -> 被审计单位： | J3: =底稿目录!A4 -> 编制人： | N3: =底稿目录!A5 -> 编制日期： | S3: 索引号： | T3: =底稿目录!F11 -> L1-5
A4: =底稿目录!A3 -> 截止日：202X年12月31日 | J4: =底稿目录!A6 -> 复核人： | N4: =底稿目录!A7 -> 复核日期： | S4: 页 次：
A5: 一、审计目标:
A6: 短期借款以恰当的金额包括在财务报表中，与之相关的计价或分摊调整已恰当记录，相关披露已得到恰当计量和描述
A7: 二、审计过程：
A8: 对短期借款的利息进行测算，并检查会计处理是否正确
C9: 报告期间 | D9: 45658 | E9: 46022
A10: 序号 | B10: 借款种类 | C10: 贷款单位 | D10: 借款起始日期 | E10: 借款讫止日期 | F10: 结息日 | G10: 起算时点 | H10: 截止时点 | I10: 年利率 | J10: 借款本金 | K10: 本期实计利息① | L10: 本期应计息天数 | M10: 本期应计利息 | N10: 差异 | O10: 财务费用-利息支出② | P10: 资本化利息支出③ | Q10: 本期未付利息天数 | R10: 本期应付利息账面数 | S10: 本期应付利测算 | T10: 备注
A11: 1 | G11: =IF(D11<=$D$9,$D$9,D11) -> 45658 | H11: =IF(E11<=$E$9,E11,$E$9) -> 0 | L11: =IF(G11=0,0,IF((H11-G11)=365,H11-G11,H11-G11+1)) -> -45657 | M11: =J11*I11/365*L11 -> 0 | N11: =M11-K11 -> 0 | O11: =M11-P11 -> 0 | Q11: =IF(F11=0,0,IF((H11-F11)=365,H11-F11,H11-F11+1)) -> 0 | S11: =J11*I11/365*R11 -> 0
A12: 2 | L12: =IF(G12=0,0,IF((H12-G12)=365,H12-G12,H12-G12+1)) -> 0 | M12: =J12*I12/365*L12 -> 0 | N12: =M12-K12 -> 0 | O12: =M12-P12 -> 0 | Q12: =IF(F12=0,0,IF((H12-F12)=365,H12-F12,H12-F12+1)) -> 0 | S12: =J12*I12/365*R12 -> 0
A13: 3 | L13: =IF(G13=0,0,IF((H13-G13)=365,H13-G13,H13-G13+1)) -> 0 | M13: =J13*I13/365*L13 -> 0 | N13: =M13-K13 -> 0 | O13: =M13-P13 -> 0 | Q13: =IF(F13=0,0,IF((H13-F13)=365,H13-F13,H13-F13+1)) -> 0 | S13: =J13*I13/365*R13 -> 0
A14: 4 | L14: =IF(G14=0,0,IF((H14-G14)=365,H14-G14,H14-G14+1)) -> 0 | M14: =J14*I14/365*L14 -> 0 | N14: =M14-K14 -> 0 | O14: =M14-P14 -> 0 | Q14: =IF(F14=0,0,IF((H14-F14)=365,H14-F14,H14-F14+1)) -> 0 | S14: =J14*I14/365*R14 -> 0
A15: 5 | L15: =IF(G15=0,0,IF((H15-G15)=365,H15-G15,H15-G15+1)) -> 0 | M15: =J15*I15/365*L15 -> 0 | N15: =M15-K15 -> 0 | O15: =M15-P15 -> 0 | Q15: =IF(F15=0,0,IF((H15-F15)=365,H15-F15,H15-F15+1)) -> 0 | S15: =J15*I15/365*R15 -> 0
A16: 6 | L16: =IF(G16=0,0,IF((H16-G16)=365,H16-G16,H16-G16+1)) -> 0 | M16: =J16*I16/365*L16 -> 0 | N16: =M16-K16 -> 0 | O16: =M16-P16 -> 0 | Q16: =IF(F16=0,0,IF((H16-F16)=365,H16-F16,H16-F16+1)) -> 0 | S16: =J16*I16/365*R16 -> 0
A17: 7 | L17: =IF(G17=0,0,IF((H17-G17)=365,H17-G17,H17-G17+1)) -> 0 | M17: =J17*I17/365*L17 -> 0 | N17: =M17-K17 -> 0 | O17: =M17-P17 -> 0 | Q17: =IF(F17=0,0,IF((H17-F17)=365,H17-F17,H17-F17+1)) -> 0 | S17: =J17*I17/365*R17 -> 0
A18: 8 | L18: =IF(G18=0,0,IF((H18-G18)=365,H18-G18,H18-G18+1)) -> 0 | M18: =J18*I18/365*L18 -> 0 | N18: =M18-K18 -> 0 | O18: =M18-P18 -> 0 | Q18: =IF(F18=0,0,IF((H18-F18)=365,H18-F18,H18-F18+1)) -> 0 | S18: =J18*I18/365*R18 -> 0
L19: =IF(G19=0,0,IF((H19-G19)=365,H19-G19,H19-G19+1)) -> 0 | M19: =J19*I19/365*L19 -> 0 | N19: =M19-K19 -> 0 | O19: =M19-P19 -> 0 | Q19: =IF(F19=0,0,IF((H19-F19)=365,H19-F19,H19-F19+1)) -> 0 | S19: =J19*I19/365*R19 -> 0
L20: =IF(G20=0,0,IF((H20-G20)=365,H20-G20,H20-G20+1)) -> 0 | M20: =J20*I20/365*L20 -> 0 | N20: =M20-K20 -> 0 | O20: =M20-P20 -> 0 | Q20: =IF(F20=0,0,IF((H20-F20)=365,H20-F20,H20-F20+1)) -> 0 | S20: =J20*I20/365*R20 -> 0
A21: 合计 | J21: =SUM(J11:J20) -> 0 | K21: =SUM(K11:K20) -> 0 | L21: -- | M21: =SUM(M11:M20) -> 0 | N21: =SUM(N11:N20) -> 0 | O21: =SUM(O11:O20) -> 0 | P21: =SUM(P11:P20) -> 0 | Q21: -- | S21: =J21*I21/365*R21 -> 0
A22: 财务费用——利息支出：
A23: 资本化利息支出：
A24: 合计 | K24: =K22+K23 -> 0
A25: 与应计利息的差异 | K25: =K24-K21 -> 0
A27: 三、审计说明：
A29: 四、审计结论：

Sheet 贷款合同检查L1-6
A1: 致同会计师事务所 | R1: 致同会计师事务所
A2: 贷款合同检查表 | R2: 贷款合同检查表
B3: =底稿目录!A2 -> 被审计单位： | D3: =底稿目录!A4 -> 编制人： | G3: =底稿目录!A6 -> 复核人： | L3: 索引号： | M3: =底稿目录!F12 -> L1-6 | N3: =B3 -> 被审计单位： | R3: =D3 -> 编制人： | W3: =G3 -> 复核人： | Y3: 索引号： | Z3: =M3 -> L1-6
B4: =底稿目录!A3 -> 截止日：202X年12月31日 | D4: =底稿目录!A5 -> 编制日期： | G4: =底稿目录!A7 -> 复核日期： | L4: 页次： | N4: =B4 -> 截止日：202X年12月31日 | R4: =D4 -> 编制日期： | W4: =G4 -> 复核日期： | Y4: 页次：
B5: 一、审计目标:
B6: 1. 记录的短期借款是被审计单位应当履行的偿还义务;2.短期借款已被恰当地汇总或分解且表述清楚，相关披露在按照企业会计准则的编制基础下是相关的、可理解的
B7: 二、审计过程:
B8: 1.获取债务协议，复核关键或重要项，如本金、利息、到期日、抵押、规定的付息日及债务契约，汇总检查协议时注意到的重要信息； 2.检查被审计单位用于借款的抵押资产的所有权是否属于被审计单位，其价值和实际状况是否与协议中的规定一致。
B9: 3.如果存在有违反债务协议约定或者条款的情况：确定违反相关协议和其他协议（如：连带违约）的影响，确定和记录任何额外执行的程序（如，企业获得书面的豁免，如果需要，或签订合同，以保证违规在债务宽限期内修正违规），确定违约行为是否影响我们对持续经营评价。
B10: 借款/授信/保证/抵押/质押等合同信息
A11: 序号 | B11: 借款单位名称（公司全称） | C11: 贷款单位名称（银行全称） | D11: 合同索引 | E11: 合同类型 | F11: 借款合同编号 | G11: 合同名称 | H11: 借款类型 | I11: 借款用途 | J11: 起始日期 | K11: 讫止日期 | L11: 年利率 | M11: 合同约定利率 | N11: 借款期限 | O11: 是否到期 | P11: 币种 | Q11: 合同贷款总额/授信敞口(额度)/保证金额/抵、质押限额 | R11: 结息方式 | S11: 保证人/抵、质押人 | T11: 保证人/抵、质押人是否为关联方 | U11: 保证责任/抵押权顺位 | V11: 抵押物名称 | W11: 权属证书编号 | X11: 处所 | Y11: 面积 | Z11: 抵、质押物价值（万元）
A12: 1
A13: 2
A14: 3
A15: 4
A16: 5
A17: 6
A18: 7
A19: 8
A20: 9
B21: 三、审计说明：
B23: 四、审计结论：

Sheet 逾期贷款检查表L1-7
A1: 致同会计师事务所
A2: 逾期贷款检查表
A3: =底稿目录!A2 -> 被审计单位： | G3: =底稿目录!A4 -> 编制人： | J3: =底稿目录!A5 -> 编制日期： | P3: 索引号： | Q3: =底稿目录!F13 -> L1-7
A4: =底稿目录!A3 -> 截止日：202X年12月31日 | G4: =底稿目录!A6 -> 复核人： | J4: =底稿目录!A7 -> 复核日期： | P4: 页次：
A5: 一、审计目标:
A6: 1. 记录的短期借款是被审计单位应当履行的偿还义务;2.短期借款已被恰当地汇总或分解且表述清楚，相关披露在按照企业会计准则的编制基础下是相关的、可理解的
A7: 二、审计过程：
A8: 1.关注未能办理转期手续的是否引发了诉讼事项，如确引发了诉讼事项，取得贷款人的诉状；2.分析逾期借款占公司全部借款的比例，对公司持续经营的影响程度。
G9: 报告期间 | H9: 45658 | I9: 46022
A10: 序号 | B10: 贷款单位 | C10: 贷款类别 | D10: 贷款资金用途 | E10: 贷款金额 | F10: 借款利率 | G10: 逾期利率（日） | H10: 借款日期 | I10: 借款到期日期 | J10: 累计逾期时间（天） | K10: 本期计息天数 | L10: 本期应计利息 | M10: 累计应付利息 | N10: 是否涉诉 | O10: 未按期偿还的原因 | P10: 预计还款期 | Q10: 备注
A11: 1 | J11: =IF(I11=0,0,$I$9-I11) -> 0 | K11: =IF(#REF!=0,0,IF((#REF!-#REF!)=365,#REF!-#REF!,#REF!-#REF!+1)) -> #REF! | L11: =E11*G11*K11 -> #REF! | M11: =E11*G11*J11 -> 0
A12: 2 | J12: =IF(I12=0,0,$I$9-I12) -> 0 | K12: =IF(#REF!=0,0,IF((#REF!-#REF!)=365,#REF!-#REF!,#REF!-#REF!+1)) -> #REF! | L12: =K12*G12 -> #REF! | M12: =E12*G12*J12 -> 0
J13: =IF(I13=0,0,$I$9-I13) -> 0 | K13: =IF(#REF!=0,0,IF((#REF!-#REF!)=365,#REF!-#REF!,#REF!-#REF!+1)) -> #REF! | L13: =K13*G13 -> #REF! | M13: =E13*G13*J13 -> 0
J14: =IF(I14=0,0,$I$9-I14) -> 0 | K14: =IF(#REF!=0,0,IF((#REF!-#REF!)=365,#REF!-#REF!,#REF!-#REF!+1)) -> #REF! | L14: =K14*G14 -> #REF! | M14: =E14*G14*J14 -> 0
A15: 合计 | E15: =SUM(E11:E14) -> 0 | G15: —— | H15: —— | I15: —— | J15: —— | K15: —— | L15: =SUM(L11:L14) -> #REF! | M15: =SUM(M11:M14) -> 0 | N15: —— | O15: —— | P15: —— | Q15: ——
A16: 短期借款审定数 | E16: ='审定表L1-1'!I11 -> 0 | G16: 逾期比例 | J16: =E15/E16 -> #DIV/0!
A18: 三、审计说明：
A20: 四、审计结论：

Sheet 抵质押资产检查表L1-8
A1: 致同会计师事务所
A2: 抵/质押资产检查表
A3: =底稿目录!A2 -> 被审计单位： | F3: =底稿目录!A4 -> 编制人： | J3: =底稿目录!A5 -> 编制日期： | L3: 索引号： | M3: =底稿目录!F14 -> L1-8
A4: =底稿目录!A3 -> 截止日：202X年12月31日 | F4: =底稿目录!A6 -> 复核人： | J4: =底稿目录!A7 -> 复核日期： | L4: 页次：1
A5: 一、审计目标:
A6: 短期借款已被恰当地汇总或分解且表述清楚，相关披露在按照企业会计准则的编制基础下是相关的、可理解的。
A7: 二、审计过程：
A8: 抵/质押合同号 | B8: 资产状态 | C8: 抵/质押贷款额 | D8: 抵/质押资产评估价值 | E8: 抵/质押资产权证号 | F8: 资产明细索引号 | G8: 抵/质押资产所属报表科目 | H8: 抵/质押资产账面原值 | I8: 抵/质押资产折旧或摊销 | J8: 抵/质押资产账面净值 | K8: 抵/质押资产所有权是否归属于被审计单位 | L8: 抵/质押资产状况 | M8: 备注
J9: =H9-I9 -> 0
J10: =H10-I10 -> 0
J11: =H11-I11 -> 0
J12: =H12-I12 -> 0
J13: =H13-I13 -> 0
J14: =H14-I14 -> 0
J15: =H15-I15 -> 0
A16: 三、审计说明：
A19: 四、审计结论：

Sheet 短期借款检查表L1-9
A1: 致同会计师事务所
A2: 短期借款检查底稿
A3: =底稿目录!A2 -> 被审计单位： | D3: =底稿目录!A4 -> 编制人： | J3: =底稿目录!A5 -> 编制日期： | O3: 索引号 | P3: =底稿目录!F21 -> L1-9
A4: =底稿目录!A3 -> 截止日：202X年12月31日 | D4: =底稿目录!A6 -> 复核人： | J4: =底稿目录!A7 -> 复核日期： | O4: 页次：
A5: 一、审计目标：
A6: 1.资产负债表中记录的短期借款是存在的，且已经记录在恰当的账户中； 2.记录的短期借款由被审计单位拥有或控制；
A7: 3.短期借款以恰当的金额包括在财务报表中，与之相关的计价或分摊调整已恰当记录，相关披露已得到恰当计量和描述
A8: 二、测试： | C8: 测试原因：大额（）关联方（）大额交易频繁（）异常（）其他（）
A9: 测试内容说明：1.原始凭证是否齐全； 2.记账凭证与原始凭证是否相符；3.账务处理是否正确；4.是否记录于恰当的会计期间；5.……
A10: 记账凭证 | H10: 支持性文件 | I10: 核对内容 | N10: 索引号 | O10: 是否异常 | P10: 备注说明
A11: 日期 | B11: 凭证编号 | C11: 业务内容 | D11: 对方科目 | E11: 对方明细科目 | F11: 借方金额 | G11: 贷方金额 | I11: 1 | J11: 2 | K11: 3 | L11: 4 | M11: 5
A24: 合计 | F24: =SUM(F12:F23) -> 0 | G24: =SUM(G12:G23) -> 0
A25: 本期发生额 | F25: ='明细表L1-2'!T26 -> 0 | G25: ='明细表L1-2'!S26 -> 0
A26: 检查比例 | F26: =F24/F25 -> #DIV/0! | G26: =G24/G25 -> #DIV/0!
A27: 三、审计说明：
A28: 1.如果检查比例较低应扩大检查样本量或说明原因
A29: 2.……
A31: 四、审计结论：
