Workbook
Name bs: {#N/A,#N/A,FALSE,"BBPREP"}
Name bs_1: {#N/A,#N/A,FALSE,"BBPREP"}

Sheet 底稿目录
A1: 底稿开列时，可先在以下单元格填写有关内容，以便其他底稿引用有关数据：
A2: 被审计单位：
A3: 截止日：202X年12月31日 | D3: 序号 | E3: 内容 | F3: 索引号
A4: 编制人： | D4: 1 | E4: =应付利息实质性程序表L2A!A2 -> 应付利息实质性程序 | F4: L2A
A5: 编制日期： | D5: 4 | E5: ='审定表L2-1'!A2 -> 应付利息审定表 | F5: L2-1
A6: 复核人： | D6: 2 | E6: 应付利息附注披露（上市公司）信息核对表 | G6: 无需打印
A7: 复核日期： | D7: 3 | E7: 应付利息附注披露（国企）信息核对表 | G7: 无需打印
D8: 6 | E8: ='明细表L2-2'!A2 -> 应付利息明细表 | F8: L2-2
A9: 关于工作底稿与审计程序索引号对应的说明 | D9: 5 | E9: ='应付利息调整分录汇总L2-3'!A2 -> 应付利息调整分录汇总表 | F9: L2-3
A10: 1.编制的审计工作底稿应与审计程序对应。审计项目组应根据被审计单位实际情况和风险评估情况在实质性程序表中裁剪、修改或增加审计程序，根据实际执行的审计程序完成相应审计工作底稿，编制的工作底稿中应按自然顺序依次编制索引号，并通过唯一的索引号将与实质性程序表中的程序对应关联（即将工作底稿的索引号填入实质性程序表中的底稿索引号列）。 | D10: 9 | E10: ='应付利息检查表L2-4'!A2 -> 应付利息检查表 | F10: L2-4
A14: 2.获取的支持性证据应与审计底稿或程序对应。审计项目组在完成底稿时获取的支持性证据应根据底稿索引号编制下一级按自然顺序排序的索引号（如D1-2-1、D1-2-2、……），并在底稿中说明引用的支持性证据、关联索引号。
A17: 3.工作底稿索引号的编码规则：实质性程序索引号按循环从“D”到“N”,循环内账户以顺序号排列，模板中底稿索引号按账户顺序+自然数顺序（即模板中索引号按二级自然顺序排列，如D1-1、D1-2、D1-3、……D1-N）。

Sheet 应付利息实质性程序表L2A
A1: 致同会计师事务所
A2: 应付利息实质性程序
A3: =底稿目录!A2 -> 被审计单位： | C3: =底稿目录!A4 -> 编制人： | E3: =底稿目录!A5 -> 编制日期： | H3: 索引号： | I3: =底稿目录!F4 -> L2A
A4: =底稿目录!A3 -> 截止日：202X年12月31日 | C4: =底稿目录!A6 -> 复核人： | E4: =底稿目录!A7 -> 复核日期： | H4: 页 次：
A5: 一、本账户涉及的科目：应付利息
A6: 应付利息
A7: 二、审计目标与认定的对应关系
A8: 审计目标 | G8: 财务报表的认定
A9: A. 资产负债表中记录的应付利息是存在的，且已记录于恰当的账户 | G9: 存在
A10: B. 所有应记录的应付利息均已记录，所有应当包括在财务报表中的相关披露均已包括 | G10: 完整性
A11: C. 记录的应付利息是被审计单位应当履行的偿还义务 | G11: 权利和义务
A12: D. 应付利息以恰当的金额包括在财务报表中，与之相关的计价或分摊调整已恰当记录，相关披露已得到恰当计量和描述 | G12: 准确性、计价和分摊
A13: E. 应付利息已被恰当地汇总或分解且表述清楚，相关披露在按照企业会计准则的编制基础下是相关的、可理解的 | G13: 列报
A14: 三、计划实施的实质性程序
A15: 序号 | B15: 审计程序 | C15: 程序分类 | D15: 对应的认定/风险 | I15: 底稿索引号
D16: 存在 | E16: 完整性 | F16: 权利和 义务 | G16: 准确性、计价和分摊 | H16: 列报 | J16: 根据被审计单位实际情况和风险评估情况裁剪、修改或增加审计程序
A17: 1 | B17: 获取或编制应付利息的明细表，完成以下工作，并编制审定表。 （1）复核加计是否正确，与总账、明细账合计数核对是否相符，期初余额与上期审定期末余额是否相符； （2）确定流动负债和非流动负债的划分是否正确 。 | C17: 常规★ | D17: √ | E17: √ | G17: √ | I17: L2-1 /L2-2
A18: 2 | B18: 在使用手工编制、自定义信息报告、系统生成的非固定格式报告等由被审计单位生成的信息时，测试有关信息准确性和完整性，并针对编制和维护由被审计单位生成的信息的相关控制实施控制测试，以评价该信息是否能够为实现审计目的提供基础。 | C18: 常规★ | E18: √ | G18: √ | J18: 可参见《审计手册》4.2.6，由被审计单位生成的信息可能是由系统生成的、或手工编制的、或二者兼而有之的方式生成的。例如，由被审计单位生成的信息可能包括： • 不涉及自定义的、由系统生成的报告（如，固定格式报告）； • 可能通过人工自定义的、由系统生成的报告，例如，（计算机）查询信息或特别定制的报告； • 手工编制的信息，例如，汇总信息的电子表格或用以支持分配、计算以及调节的电子表格； • 其他系统生成或手工编制的信息，例如，由被审计单位编制的客户发票； • 通过影印、拍摄、扫描或其他方式转换成电子形式的文件记录。
A19: 3 | B19: 对期初余额的审计，取得应付利息期初余额明细表复核加计是否正确，与总账、明细账合计数是否相符，检查上期应付利息在本期偿还情况。（适用于首次承接） | C19: 备选 | D19: √ | E19: √ | F19: √ | G19: √ | J19: 由被审计单位生成的信息不包括： • 总分类账或明细分类账、试算平衡表、或经审计的财务报表； • 第三方（除了服务机构）的报表或报告，例如，原始银行对账单，或函证的回函； • 外部数据（例如，第三方发布的数据，如，定价来源）。
A20: 4 | B20: 与借款等相关科目核对应付利息金额是否正确。 | C20: 常规★ | G20: √
A21: 5 | B21: 检查与应付利息有关的的记账凭证和相应的支持性证据以确定交易的真实性，是否按规定进行相应的会计处理和披露。 | C21: 常规★ | D21: √ | E21: √ | G21: √ | I21: L2-4 /L1-5 /L3-5
A22: 6 | B22: 根据评估的舞弊风险等因素增加的审计程序。 | C22: IPO/上市/新三板/重组/舞弊应对
A23: 7 | B23: 检查应付利息是否已按企业会计准则或其他适用的规定在财务报表中做出恰当列报和披露。 | C23: 常规★ | H23: √ | I23: A1-1/A1-15 /A1-16

Sheet 审定表L2-1
A1: 致同会计师事务所
A2: 应付利息审定表
A3: =底稿目录!A2 -> 被审计单位： | E3: =底稿目录!A4 -> 编制人： | H3: =底稿目录!A5 -> 编制日期： | M3: 索引号： | N3: =底稿目录!F5 -> L2-1
A4: =底稿目录!A3 -> 截止日：202X年12月31日 | E4: =底稿目录!A6 -> 复核人： | H4: =底稿目录!A7 -> 复核日期： | M4: 页次：
A5: 项目 | B5: 期初数 | F5: 期末数 | J5: 本期未审数与上期 审定数的比较 | L5: 本期审定数与上期 审定数的比较 | N5: 原因分析
B6: 未审数 | C6: 账项调整 | D6: 重分类调整 | E6: 审定数 | F6: 未审数 | G6: 账项调整 | H6: 重分类调整 | I6: 审定数 | J6: 变动额 | K6: 变动率 | L6: 变动额 | M6: 变动率
A7: 分期付息到期还本的长期借款利息 | B7: =SUMIF('明细表L2-2'!A:A,A7,'明细表L2-2'!H:H) -> 0 | C7: =SUMIF('明细表L2-2'!A:A,A7,'明细表L2-2'!L:L) -> 0 | D7: =SUMIF('明细表L2-2'!A:A,A7,'明细表L2-2'!M:M) -> 0 | E7: =B7+C7+D7 -> 0 | F7: =SUMIF('明细表L2-2'!A:A,A7,'明细表L2-2'!K:K) -> 0 | G7: =SUMIF('明细表L2-2'!A:A,A7,'明细表L2-2'!L:L)+SUMIF('明细表L2-2'!A:A,A7,'明细表L2-2'!N:N)-SUMIF('明细表L2-2'!A:A,A7,'明细表L2-2'!O:O) -> 0 | H7: =SUMIF('明细表L2-2'!A:A,A7,'明细表L2-2'!M:M)+SUMIF('明细表L2-2'!A:A,A7,'明细表L2-2'!P:P)-SUMIF('明细表L2-2'!A:A,A7,'明细表L2-2'!Q:Q) -> 0 | I7: =F7+G7+H7 -> 0 | J7: =F7-B7 -> 0 | K7: =IF(AND(B7=0,J7=0),0,IF(AND(B7=0,J7>0),1,J7/B7)) -> 0 | L7: =I7-E7 -> 0 | M7: =IF(AND(E7=0,L7=0),0,IF(AND(E7=0,L7>0),1,L7/E7)) -> 0
A8: 企业债券利息 | B8: =SUMIF('明细表L2-2'!A:A,A8,'明细表L2-2'!H:H) -> 0 | C8: =SUMIF('明细表L2-2'!A:A,A8,'明细表L2-2'!L:L) -> 0 | D8: =SUMIF('明细表L2-2'!A:A,A8,'明细表L2-2'!M:M) -> 0 | E8: =B8+C8+D8 -> 0 | F8: =SUMIF('明细表L2-2'!A:A,A8,'明细表L2-2'!K:K) -> 0 | G8: =SUMIF('明细表L2-2'!A:A,A8,'明细表L2-2'!L:L)+SUMIF('明细表L2-2'!A:A,A8,'明细表L2-2'!N:N)-SUMIF('明细表L2-2'!A:A,A8,'明细表L2-2'!O:O) -> 0 | H8: =SUMIF('明细表L2-2'!A:A,A8,'明细表L2-2'!M:M)+SUMIF('明细表L2-2'!A:A,A8,'明细表L2-2'!P:P)-SUMIF('明细表L2-2'!A:A,A8,'明细表L2-2'!Q:Q) -> 0 | I8: =F8+G8+H8 -> 0 | J8: =F8-B8 -> 0 | K8: =IF(AND(B8=0,J8=0),0,IF(AND(B8=0,J8>0),1,J8/B8)) -> 0 | L8: =I8-E8 -> 0 | M8: =IF(AND(E8=0,L8=0),0,IF(AND(E8=0,L8>0),1,L8/E8)) -> 0
A9: 短期借款应付利息 | B9: =SUMIF('明细表L2-2'!A:A,A9,'明细表L2-2'!H:H) -> 0 | C9: =SUMIF('明细表L2-2'!A:A,A9,'明细表L2-2'!L:L) -> 0 | D9: =SUMIF('明细表L2-2'!A:A,A9,'明细表L2-2'!M:M) -> 0 | E9: =B9+C9+D9 -> 0 | F9: =SUMIF('明细表L2-2'!A:A,A9,'明细表L2-2'!K:K) -> 0 | G9: =SUMIF('明细表L2-2'!A:A,A9,'明细表L2-2'!L:L)+SUMIF('明细表L2-2'!A:A,A9,'明细表L2-2'!N:N)-SUMIF('明细表L2-2'!A:A,A9,'明细表L2-2'!O:O) -> 0 | H9: =SUMIF('明细表L2-2'!A:A,A9,'明细表L2-2'!M:M)+SUMIF('明细表L2-2'!A:A,A9,'明细表L2-2'!P:P)-SUMIF('明细表L2-2'!A:A,A9,'明细表L2-2'!Q:Q) -> 0 | I9: =F9+G9+H9 -> 0 | J9: =F9-B9 -> 0 | K9: =IF(AND(B9=0,J9=0),0,IF(AND(B9=0,J9>0),1,J9/B9)) -> 0 | L9: =I9-E9 -> 0 | M9: =IF(AND(E9=0,L9=0),0,IF(AND(E9=0,L9>0),1,L9/E9)) -> 0
A10: 划分为金融负债的优先股\永续债利息 | B10: =SUM(B11:B12) -> 0 | C10: =SUM(C11:C12) -> 0 | D10: =SUM(D11:D12) -> 0 | E10: =B10+C10+D10 -> 0 | F10: =SUM(F11:F12) -> 0 | G10: =SUM(G11:G12) -> 0 | H10: =SUM(H11:H12) -> 0 | I10: =F10+G10+H10 -> 0 | J10: =F10-B10 -> 0 | K10: =IF(AND(B10=0,J10=0),0,IF(AND(B10=0,J10>0),1,J10/B10)) -> 0 | L10: =I10-E10 -> 0 | M10: =IF(AND(E10=0,L10=0),0,IF(AND(E10=0,L10>0),1,L10/E10)) -> 0
A11: 其中：工具1 | B11: =SUMIF('明细表L2-2'!A:A,A11,'明细表L2-2'!H:H) -> 0 | C11: =SUMIF('明细表L2-2'!A:A,A11,'明细表L2-2'!L:L) -> 0 | D11: =SUMIF('明细表L2-2'!A:A,A11,'明细表L2-2'!M:M) -> 0 | E11: =B11+C11+D11 -> 0 | F11: =SUMIF('明细表L2-2'!A:A,A11,'明细表L2-2'!K:K) -> 0 | G11: =SUMIF('明细表L2-2'!A:A,A11,'明细表L2-2'!L:L)+SUMIF('明细表L2-2'!A:A,A11,'明细表L2-2'!N:N)-SUMIF('明细表L2-2'!A:A,A11,'明细表L2-2'!O:O) -> 0 | H11: =SUMIF('明细表L2-2'!A:A,A11,'明细表L2-2'!M:M)+SUMIF('明细表L2-2'!A:A,A11,'明细表L2-2'!P:P)-SUMIF('明细表L2-2'!A:A,A11,'明细表L2-2'!Q:Q) -> 0 | I11: =F11+G11+H11 -> 0 | J11: =F11-B11 -> 0 | K11: =IF(AND(B11=0,J11=0),0,IF(AND(B11=0,J11>0),1,J11/B11)) -> 0 | L11: =I11-E11 -> 0 | M11: =IF(AND(E11=0,L11=0),0,IF(AND(E11=0,L11>0),1,L11/E11)) -> 0
A12: 工具2 | B12: =SUMIF('明细表L2-2'!A:A,A12,'明细表L2-2'!H:H) -> 0 | C12: =SUMIF('明细表L2-2'!A:A,A12,'明细表L2-2'!L:L) -> 0 | D12: =SUMIF('明细表L2-2'!A:A,A12,'明细表L2-2'!M:M) -> 0 | E12: =B12+C12+D12 -> 0 | F12: =SUMIF('明细表L2-2'!A:A,A12,'明细表L2-2'!K:K) -> 0 | G12: =SUMIF('明细表L2-2'!A:A,A12,'明细表L2-2'!L:L)+SUMIF('明细表L2-2'!A:A,A12,'明细表L2-2'!N:N)-SUMIF('明细表L2-2'!A:A,A12,'明细表L2-2'!O:O) -> 0 | H12: =SUMIF('明细表L2-2'!A:A,A12,'明细表L2-2'!M:M)+SUMIF('明细表L2-2'!A:A,A12,'明细表L2-2'!P:P)-SUMIF('明细表L2-2'!A:A,A12,'明细表L2-2'!Q:Q) -> 0 | I12: =F12+G12+H12 -> 0 | J12: =F12-B12 -> 0 | K12: =IF(AND(B12=0,J12=0),0,IF(AND(B12=0,J12>0),1,J12/B12)) -> 0 | L12: =I12-E12 -> 0 | M12: =IF(AND(E12=0,L12=0),0,IF(AND(E12=0,L12>0),1,L12/E12)) -> 0
A13: 其他 | B13: =SUMIF('明细表L2-2'!A:A,A13,'明细表L2-2'!H:H) -> 0 | C13: =SUMIF('明细表L2-2'!A:A,A13,'明细表L2-2'!L:L) -> 0 | D13: =SUMIF('明细表L2-2'!A:A,A13,'明细表L2-2'!M:M) -> 0 | E13: =B13+C13+D13 -> 0 | F13: =SUMIF('明细表L2-2'!A:A,A13,'明细表L2-2'!K:K) -> 0 | G13: =SUMIF('明细表L2-2'!A:A,A13,'明细表L2-2'!L:L)+SUMIF('明细表L2-2'!A:A,A13,'明细表L2-2'!N:N)-SUMIF('明细表L2-2'!A:A,A13,'明细表L2-2'!O:O) -> 0 | H13: =SUMIF('明细表L2-2'!A:A,A13,'明细表L2-2'!M:M)+SUMIF('明细表L2-2'!A:A,A13,'明细表L2-2'!P:P)-SUMIF('明细表L2-2'!A:A,A13,'明细表L2-2'!Q:Q) -> 0 | I13: =F13+G13+H13 -> 0 | J13: =F13-B13 -> 0 | K13: =IF(AND(B13=0,J13=0),0,IF(AND(B13=0,J13>0),1,J13/B13)) -> 0 | L13: =I13-E13 -> 0 | M13: =IF(AND(E13=0,L13=0),0,IF(AND(E13=0,L13>0),1,L13/E13)) -> 0
A14: 合计 | B14: =SUM(B7:B10,B13) -> 0 | C14: =SUM(C7:C10,C13) -> 0 | D14: =SUM(D7:D10,D13) -> 0 | E14: =SUM(E7:E10,E13) -> 0 | F14: =SUM(F7:F10,F13) -> 0 | G14: =SUM(G7:G10,G13) -> 0 | H14: =SUM(H7:H10,H13) -> 0 | I14: =SUM(I7:I10,I13) -> 0 | J14: =SUM(J7:J13) -> 0 | K14: =IF(AND(B14=0,J14=0),0,IF(AND(B14=0,J14>0),1,J14/B14)) -> 0 | L14: =SUM(L7:L13) -> 0 | M14: =IF(AND(E14=0,L14=0),0,IF(AND(E14=0,L14>0),1,L14/E14)) -> 0
A15: 1、审计说明：
A16: （1）应付利息本期较上期增加（负数为减少）：
A17: 主要原因（比例超过30%的）：
A19: （2）欠付利息的原因说明：
A21: （3）与经审计的财务报表核对
B22: 期末数 | C22: 期初数
A23: 应付利息审定数 | B23: =I14 -> 0 | C23: =E14 -> 0
A24: 应付股利审定数
A25: 其他应付款审定数
A26: 其他应付款合计数 | B26: =SUM(B23:B25) -> 0 | C26: =SUM(C23:C25) -> 0
A27: 报表数
A28: 差异 | B28: =B26-B27 -> 0 | C28: =C26-C27 -> 0
A29: 2、审计结论：

Sheet 附注披露（国企）信息
A1: 致同会计师事务所
A2: 应付利息附注披露信息 | E2: 返回目录
A3: =底稿目录!A2 -> 被审计单位： | B3: ='审定表L2-1'!E3 -> 编制人： | C3: =底稿目录!A5 -> 编制日期： | D3: 索引号：
A4: =底稿目录!A3 -> 截止日：202X年12月31日 | B4: =底稿目录!A6 -> 复核人： | C4: =底稿目录!A7 -> 复核日期： | D4: 页次：
A5: 附注披露信息（国企）：
A6: 应付利息
A7: 项 目 | B7: 期末余额 | C7: 期初余额
A8: 分期付息到期还本的长期借款利息 | B8: =SUMIF('明细表L2-2'!A:A,'附注披露（上市公司）信息'!A8,'明细表L2-2'!U:U) -> 0 | C8: =SUMIF('明细表L2-2'!A:A,'附注披露（上市公司）信息'!A8,'明细表L2-2'!R:R) -> 0
A9: 企业债券利息 | B9: =SUMIF('明细表L2-2'!A:A,'附注披露（上市公司）信息'!A9,'明细表L2-2'!U:U) -> 0 | C9: =SUMIF('明细表L2-2'!A:A,'附注披露（上市公司）信息'!A9,'明细表L2-2'!R:R) -> 0
A10: 短期借款应付利息 | B10: =SUMIF('明细表L2-2'!A:A,'附注披露（上市公司）信息'!A10,'明细表L2-2'!U:U) -> 0 | C10: =SUMIF('明细表L2-2'!A:A,'附注披露（上市公司）信息'!A10,'明细表L2-2'!R:R) -> 0
A11: 划分为金融负债的优先股\永续债利息 | B11: =SUM(B12:B13) -> 0 | C11: =SUM(C12:C13) -> 0
A12: 其中：工具1 | B12: =SUMIF('明细表L2-2'!A:A,'附注披露（上市公司）信息'!A12,'明细表L2-2'!U:U) -> 0
A13: 工具2 | B13: =SUMIF('明细表L2-2'!A:A,'附注披露（上市公司）信息'!A13,'明细表L2-2'!U:U) -> 0 | C13: =SUMIF('明细表L2-2'!A:A,'附注披露（上市公司）信息'!A13,'明细表L2-2'!R:R) -> 0
A14: 其他 | B14: =SUMIF('明细表L2-2'!A:A,'附注披露（上市公司）信息'!A14,'明细表L2-2'!U:U) -> 0 | C14: =SUMIF('明细表L2-2'!A:A,'附注披露（上市公司）信息'!A14,'明细表L2-2'!R:R) -> 0
A15: 合 计 | B15: =SUM(B8:B11,B14) -> 0 | C15: =SUM(C8:C11,C14) -> 0
A16: 重要的逾期未付利息：
A17: 借款单位 | B17: 逾期金额 | C17: 逾期原因
A18: =IF('明细表L2-2'!V12>0,'明细表L2-2'!C12,"") | B18: =IF('明细表L2-2'!V12>0,'明细表L2-2'!V12,"") | C18: =IF('明细表L2-2'!V12>0,'明细表L2-2'!W12,"")
A19: =IF('明细表L2-2'!V13>0,'明细表L2-2'!C13,"") | B19: =IF('明细表L2-2'!V13>0,'明细表L2-2'!V13,"") | C19: =IF('明细表L2-2'!V13>0,'明细表L2-2'!W13,"")
A20: =IF('明细表L2-2'!V14>0,'明细表L2-2'!C14,"") | B20: =IF('明细表L2-2'!V14>0,'明细表L2-2'!V14,"") | C20: =IF('明细表L2-2'!V14>0,'明细表L2-2'!W14,"")
A21: =IF('明细表L2-2'!V15>0,'明细表L2-2'!C15,"") | B21: =IF('明细表L2-2'!V15>0,'明细表L2-2'!V15,"") | C21: =IF('明细表L2-2'!V15>0,'明细表L2-2'!W15,"")
A22: =IF('明细表L2-2'!V16>0,'明细表L2-2'!C16,"") | B22: =IF('明细表L2-2'!V16>0,'明细表L2-2'!V16,"") | C22: =IF('明细表L2-2'!V16>0,'明细表L2-2'!W16,"")
A23: =IF('明细表L2-2'!V17>0,'明细表L2-2'!C17,"") | B23: =IF('明细表L2-2'!V17>0,'明细表L2-2'!V17,"") | C23: =IF('明细表L2-2'!V17>0,'明细表L2-2'!W17,"")
A24: =IF('明细表L2-2'!V18>0,'明细表L2-2'!C18,"") | B24: =IF('明细表L2-2'!V18>0,'明细表L2-2'!V18,"") | C24: =IF('明细表L2-2'!V18>0,'明细表L2-2'!W18,"")
A25: =IF('明细表L2-2'!V19>0,'明细表L2-2'!C19,"") | B25: =IF('明细表L2-2'!V19>0,'明细表L2-2'!V19,"") | C25: =IF('明细表L2-2'!V19>0,'明细表L2-2'!W19,"")
A26: =IF('明细表L2-2'!V20>0,'明细表L2-2'!C20,"") | B26: =IF('明细表L2-2'!V20>0,'明细表L2-2'!V20,"") | C26: =IF('明细表L2-2'!V20>0,'明细表L2-2'!W20,"")
A27: =IF('明细表L2-2'!V21>0,'明细表L2-2'!C21,"") | B27: =IF('明细表L2-2'!V21>0,'明细表L2-2'!V21,"") | C27: =IF('明细表L2-2'!V21>0,'明细表L2-2'!W21,"")
A28: =IF('明细表L2-2'!V22>0,'明细表L2-2'!C22,"") | B28: =IF('明细表L2-2'!V22>0,'明细表L2-2'!V22,"") | C28: =IF('明细表L2-2'!V22>0,'明细表L2-2'!W22,"")
A29: =IF('明细表L2-2'!V23>0,'明细表L2-2'!C23,"") | B29: =IF('明细表L2-2'!V23>0,'明细表L2-2'!V23,"") | C29: =IF('明细表L2-2'!V23>0,'明细表L2-2'!W23,"")
... A33: =IF('明细表L2-2'!V27>0,'明细表L2-2'!C27,"") | B33: =IF('明细表L2-2'!V27>0,'明细表L2-2'!V27,"") | C33: =IF('明细表L2-2'!V27>0,'明细表L2-2'!W27,"")
A34: 合计 | B34: =SUM(B18:B33) -> 0 | C34: --

Sheet 附注披露（上市公司）信息
A1: 致同会计师事务所
A2: 应付利息附注披露信息 | F2: 返回目录
A3: =底稿目录!A2 -> 被审计单位： | B3: ='审定表L2-1'!E3 -> 编制人： | C3: =底稿目录!A5 -> 编制日期： | E3: 索引号：
A4: =底稿目录!A3 -> 截止日：202X年12月31日 | B4: =底稿目录!A6 -> 复核人： | C4: =底稿目录!A7 -> 复核日期： | E4: 页次：
A5: 附注披露信息（上市公司）：
A6: 应付利息
A7: 项 目 | B7: 期末余额 | C7: 上年年末余额
A8: 分期付息到期还本的长期借款利息 | B8: =SUMIF('明细表L2-2'!A:A,'附注披露（上市公司）信息'!A8,'明细表L2-2'!U:U) -> 0 | C8: =SUMIF('明细表L2-2'!A:A,'附注披露（上市公司）信息'!A8,'明细表L2-2'!R:R) -> 0
A9: 企业债券利息 | B9: =SUMIF('明细表L2-2'!A:A,'附注披露（上市公司）信息'!A9,'明细表L2-2'!U:U) -> 0 | C9: =SUMIF('明细表L2-2'!A:A,'附注披露（上市公司）信息'!A9,'明细表L2-2'!R:R) -> 0
A10: 短期借款应付利息 | B10: =SUMIF('明细表L2-2'!A:A,'附注披露（上市公司）信息'!A10,'明细表L2-2'!U:U) -> 0 | C10: =SUMIF('明细表L2-2'!A:A,'附注披露（上市公司）信息'!A10,'明细表L2-2'!R:R) -> 0
A11: 划分为金融负债的优先股\永续债利息 | B11: =SUM(B12:B13) -> 0 | C11: =SUM(C12:C13) -> 0
A12: 其中：工具1 | B12: =SUMIF('明细表L2-2'!A:A,'附注披露（上市公司）信息'!A12,'明细表L2-2'!U:U) -> 0
A13: 工具2 | B13: =SUMIF('明细表L2-2'!A:A,'附注披露（上市公司）信息'!A13,'明细表L2-2'!U:U) -> 0 | C13: =SUMIF('明细表L2-2'!A:A,'附注披露（上市公司）信息'!A13,'明细表L2-2'!R:R) -> 0
A14: 其他 | B14: =SUMIF('明细表L2-2'!A:A,'附注披露（上市公司）信息'!A14,'明细表L2-2'!U:U) -> 0 | C14: =SUMIF('明细表L2-2'!A:A,'附注披露（上市公司）信息'!A14,'明细表L2-2'!R:R) -> 0
A15: 合 计 | B15: =SUM(B8:B11,B14) -> 0 | C15: =SUM(C8:C11,C14) -> 0
A16: 重要的逾期未付利息：
A17: 借款单位 | B17: 逾期金额 | C17: 逾期原因
A18: =IF('明细表L2-2'!V12>0,'明细表L2-2'!C12,"") | B18: =IF('明细表L2-2'!V12>0,'明细表L2-2'!V12,"") | C18: =IF('明细表L2-2'!V12>0,'明细表L2-2'!W12,"")
A19: =IF('明细表L2-2'!V13>0,'明细表L2-2'!C13,"") | B19: =IF('明细表L2-2'!V13>0,'明细表L2-2'!V13,"") | C19: =IF('明细表L2-2'!V13>0,'明细表L2-2'!W13,"")
A20: =IF('明细表L2-2'!V14>0,'明细表L2-2'!C14,"") | B20: =IF('明细表L2-2'!V14>0,'明细表L2-2'!V14,"") | C20: =IF('明细表L2-2'!V14>0,'明细表L2-2'!W14,"")
A21: =IF('明细表L2-2'!V15>0,'明细表L2-2'!C15,"") | B21: =IF('明细表L2-2'!V15>0,'明细表L2-2'!V15,"") | C21: =IF('明细表L2-2'!V15>0,'明细表L2-2'!W15,"")
A22: =IF('明细表L2-2'!V16>0,'明细表L2-2'!C16,"") | B22: =IF('明细表L2-2'!V16>0,'明细表L2-2'!V16,"") | C22: =IF('明细表L2-2'!V16>0,'明细表L2-2'!W16,"")
A23: =IF('明细表L2-2'!V17>0,'明细表L2-2'!C17,"") | B23: =IF('明细表L2-2'!V17>0,'明细表L2-2'!V17,"") | C23: =IF('明细表L2-2'!V17>0,'明细表L2-2'!W17,"")
A24: =IF('明细表L2-2'!V18>0,'明细表L2-2'!C18,"") | B24: =IF('明细表L2-2'!V18>0,'明细表L2-2'!V18,"") | C24: =IF('明细表L2-2'!V18>0,'明细表L2-2'!W18,"")
A25: =IF('明细表L2-2'!V19>0,'明细表L2-2'!C19,"") | B25: =IF('明细表L2-2'!V19>0,'明细表L2-2'!V19,"") | C25: =IF('明细表L2-2'!V19>0,'明细表L2-2'!W19,"")
A26: =IF('明细表L2-2'!V20>0,'明细表L2-2'!C20,"") | B26: =IF('明细表L2-2'!V20>0,'明细表L2-2'!V20,"") | C26: =IF('明细表L2-2'!V20>0,'明细表L2-2'!W20,"")
A27: =IF('明细表L2-2'!V21>0,'明细表L2-2'!C21,"") | B27: =IF('明细表L2-2'!V21>0,'明细表L2-2'!V21,"") | C27: =IF('明细表L2-2'!V21>0,'明细表L2-2'!W21,"")
A28: =IF('明细表L2-2'!V22>0,'明细表L2-2'!C22,"") | B28: =IF('明细表L2-2'!V22>0,'明细表L2-2'!V22,"") | C28: =IF('明细表L2-2'!V22>0,'明细表L2-2'!W22,"")
A29: =IF('明细表L2-2'!V23>0,'明细表L2-2'!C23,"") | B29: =IF('明细表L2-2'!V23>0,'明细表L2-2'!V23,"") | C29: =IF('明细表L2-2'!V23>0,'明细表L2-2'!W23,"")
... A33: =IF('明细表L2-2'!V27>0,'明细表L2-2'!C27,"") | B33: =IF('明细表L2-2'!V27>0,'明细表L2-2'!V27,"") | C33: =IF('明细表L2-2'!V27>0,'明细表L2-2'!W27,"")
A34: 合计 | B34: =SUM(B18:B33) -> 0 | C34: --

Sheet 明细表L2-2
A1: 致同会计师事务所 | L1: 致同会计师事务所
A2: 应付利息明细表 | L2: 应付利息明细表
A3: =底稿目录!A2 -> 被审计单位： | C3: =底稿目录!A4 -> 编制人： | H3: =底稿目录!A5 -> 编制日期： | J3: 索引号： | K3: =底稿目录!F8 -> L2-2 | M3: =C3 -> 编制人： | Q3: =H3 -> 编制日期： | W3: 索引号： | X3: =底稿目录!F8 -> L2-2
A4: =底稿目录!A3 -> 截止日：202X年12月31日 | C4: =底稿目录!A6 -> 复核人： | H4: =底稿目录!A7 -> 复核日期： | J4: 页次： | M4: =C4 -> 复核人： | Q4: =H4 -> 复核日期： | W4: 页次：
A5: 一、审计目标:
A6: 1、资产负债表中记录的应付利息是存在的，且已经记录在恰当的账户中；2、 所有应记录的短期借款均已记录，所有应当包括在财务报表中的相关披露均已包括；
A7: 3、应付利息以恰当的金额包括在财务报表中，与之相关的计价或分摊调整已恰当记录，相关披露已得到恰当计量和描述
A8: 二、审计过程：
A9: 考虑发生在企业与关联方之间的交易是否得到适当的会计处理,了解关联交易事项的目的、价格和条件，检查交易的支持性文件，同时向关联方或其他注册会计师函证重大的交易（包括担保和其他重要信息），以确认交易的真实性；必要时，向与交易相关的人员和机构（如银行、律师）函证或与其讨论有关信息。
A10: 类别 | B10: 名称 | C10: 债权人名称 | D10: 计息基数 | E10: 起息日 | F10: 到期日 | G10: 利率 | H10: 未审数 | L10: 期初调整 | N10: 账项调整 | P10: 重分类调整 | R10: 审定数 | V10: 逾期未支付金额 | W10: 逾期原因 | X10: 备注
H11: 期初余额 | I11: 本期应付利息 | J11: 本期已付利息 | K11: 期末余额 | L11: 账项调整 | M11: 重分类调整 | N11: 本期增加 | O11: 本期偿还 | P11: 本期增加 | Q11: 本期偿还 | R11: 期初余额 | S11: 本期应付利息 | T11: 本期已付利息 | U11: 期末余额
A12: 分期付息到期还本的长期借款利息 | K12: =H12+I12-J12 -> 0 | R12: =H12+L12+M12 -> 0 | S12: =I12+N12+P12 -> 0 | T12: =J12+O12+Q12 -> 0 | U12: =R12+S12-T12 -> 0
A13: 分期付息到期还本的长期借款利息 | K13: =H13+I13-J13 -> 0 | R13: =H13+L13+M13 -> 0 | S13: =I13+N13+P13 -> 0 | T13: =J13+O13+Q13 -> 0 | U13: =R13+S13-T13 -> 0
A14: 分期付息到期还本的长期借款利息 | K14: =H14+I14-J14 -> 0 | R14: =H14+L14+M14 -> 0 | S14: =I14+N14+P14 -> 0 | T14: =J14+O14+Q14 -> 0 | U14: =R14+S14-T14 -> 0
A15: 分期付息到期还本的长期借款利息 | K15: =H15+I15-J15 -> 0 | R15: =H15+L15+M15 -> 0 | S15: =I15+N15+P15 -> 0 | T15: =J15+O15+Q15 -> 0 | U15: =R15+S15-T15 -> 0
A16: 分期付息到期还本的长期借款利息 | K16: =H16+I16-J16 -> 0 | R16: =H16+L16+M16 -> 0 | S16: =I16+N16+P16 -> 0 | T16: =J16+O16+Q16 -> 0 | U16: =R16+S16-T16 -> 0
A17: 企业债券利息 | K17: =H17+I17-J17 -> 0 | R17: =H17+L17+M17 -> 0 | S17: =I17+N17+P17 -> 0 | T17: =J17+O17+Q17 -> 0 | U17: =R17+S17-T17 -> 0
A18: 企业债券利息 | K18: =H18+I18-J18 -> 0 | R18: =H18+L18+M18 -> 0 | S18: =I18+N18+P18 -> 0 | T18: =J18+O18+Q18 -> 0 | U18: =R18+S18-T18 -> 0
A19: 企业债券利息 | K19: =H19+I19-J19 -> 0 | R19: =H19+L19+M19 -> 0 | S19: =I19+N19+P19 -> 0 | T19: =J19+O19+Q19 -> 0 | U19: =R19+S19-T19 -> 0
A20: 短期借款应付利息 | K20: =H20+I20-J20 -> 0 | R20: =H20+L20+M20 -> 0 | S20: =I20+N20+P20 -> 0 | T20: =J20+O20+Q20 -> 0 | U20: =R20+S20-T20 -> 0
A21: 短期借款应付利息 | K21: =H21+I21-J21 -> 0 | R21: =H21+L21+M21 -> 0 | S21: =I21+N21+P21 -> 0 | T21: =J21+O21+Q21 -> 0 | U21: =R21+S21-T21 -> 0
A22: 短期借款应付利息 | K22: =H22+I22-J22 -> 0 | R22: =H22+L22+M22 -> 0 | S22: =I22+N22+P22 -> 0 | T22: =J22+O22+Q22 -> 0 | U22: =R22+S22-T22 -> 0
A23: 划分为金融负债的优先股\永续债利息 | K23: =H23+I23-J23 -> 0 | R23: =H23+L23+M23 -> 0 | S23: =I23+N23+P23 -> 0 | T23: =J23+O23+Q23 -> 0 | U23: =R23+S23-T23 -> 0
... A27: 其他 | K27: =H27+I27-J27 -> 0 | R27: =H27+L27+M27 -> 0 | S27: =I27+N27+P27 -> 0 | T27: =J27+O27+Q27 -> 0 | U27: =R27+S27-T27 -> 0
A28: 合计 | H28: =SUM(H12:H27) -> 0 | I28: =SUM(I12:I27) -> 0 | J28: =SUM(J12:J27) -> 0 | K28: =SUM(K12:K27) -> 0 | L28: =SUM(L12:L27) -> 0 | M28: =SUM(M12:M27) -> 0 | N28: =SUM(N12:N27) -> 0 | O28: =SUM(O12:O27) -> 0 | ... V28: =SUM(V12:V27) -> 0
A29: 三、审计说明：
A30: 利息测算过程详见
A31: 注：“应付利息”仅反映相关金融工具已到期应支付但于资产负债表日尚未支付的利息。基于实际利率法计提的金融工具的利息应包含在相应金融工具的账面余额中。
A32: 四、审计结论：
A34: 提示：
A35: 1.“应付利息”仅反映相关金融工具已到期应支付但于资产负债表日尚未支付的利息。基于实际利率法计提的金融工具的利息应包含在相应金融工具的账面余额中。
A36: 2.审计说明可以概述：（1）程序的测试情况、结果；（2）拟调整事项及其调整分录、未调整事项及其影响，审计范围受到限制情况及其影响。
A37: 3.审计结论可参考：A、未见异常。 B、除上述重大不符事项应当作为调整事项予以调整外，其余未见异常。 C、由于存在以下重大未调整事项（或审计范围受到限制无法获取充分、适当证据），不可确认。

Sheet 应付利息调整分录汇总L2-3
A1: 致同会计师事务所
A2: 应付利息调整分录汇总表
A3: =底稿目录!A2 -> 被审计单位： | C3: =底稿目录!A4 -> 编制人： | G3: =底稿目录!A5 -> 编制日期： | I3: 索引： | J3: =底稿目录!F9 -> L2-3
A4: =底稿目录!A3 -> 截止日：202X年12月31日 | C4: =底稿目录!A6 -> 复核人： | G4: =底稿目录!A5 -> 编制日期： | I4: 页次：
A5: 调整事项说明 | B5: 类别（报表调整/账项调整/其他） | C5: 报表项目 | D5: 科目名称 | E5: 附注项目 | F5: …… | G5: 借方调整金额 | H5: 贷方调整金额 | I5: 索引 | J5: 备注
A6: 北京 | B6: 账项调整 | C6: 货币资金 | D6: 银行存款 | E6: 银行存款 | G6: 200 | H6: 200 | I6: 北京 | J6: 北京
A23: 1、审计说明
A27: 2、审计结论
A28: 注：本底稿适用于调整分录较多、较复杂的项目，且仅列示与本报表项目相关的审计调整。项目组可根据项目实际情况选择是否使用该底稿。

Sheet 应付利息检查表L2-4
A1: 致同会计师事务所
A2: 应付利息检查表
A3: =底稿目录!A2 -> 被审计单位： | E3: =底稿目录!A4 -> 编制人： | H3: =底稿目录!A5 -> 编制日期： | O3: 索引号： | P3: =底稿目录!F10 -> L2-4
A4: =底稿目录!A3 -> 截止日：202X年12月31日 | E4: =底稿目录!A6 -> 复核人： | H4: =底稿目录!A7 -> 复核日期： | O4: 页次：
A5: 一、审计目标:
A6: 1.资产负债表中记录的应付利息是存在的，且已经记录在恰当的账户中； 2.记录的应付利息由被审计单位拥有或控制；
A7: 3.应付利息以恰当的金额包括在财务报表中，与之相关的计价或分摊调整已恰当记录，相关披露已得到恰当计量和描述
A8: 二、测试： | C8: 测试原因：大额（）关联方（）大额交易频繁（）异常（）其他（）
A9: 测试内容说明：1.原始凭证齐全；2.经授权批准；3.会计处理正确；4.记账凭证与原始凭证金额核对相符；5…
A10: 记账凭证 | H10: 支持性文件 | I10: 核对内容 | N10: 索引号 | O10: 是否异常 | P10: 备注说明
A11: 日期 | B11: 凭证编号 | C11: 业务内容 | D11: 对方科目 | E11: 对方明细科目 | F11: 借方金额 | G11: 贷方金额 | I11: 1 | J11: 2 | K11: 3 | L11: 4 | M11: 5
A24: 合计 | F24: =SUM(F12:F23) -> 0 | G24: =SUM(G12:G23) -> 0
A25: 本期发生额 | F25: ='明细表L2-2'!T28 -> 0 | G25: ='明细表L2-2'!S28 -> 0
A26: 检查比例 | F26: =F24/F25 -> #DIV/0! | G26: =G24/G25 -> #DIV/0!
A27: 三、审计说明：
A29: 四、审计结论：
