Workbook

Sheet 底稿目录
A1: 底稿开列时，可先在以下单元格填写有关内容，以便其他底稿引用有关数据：
A2: 被审计单位：
A3: 截止日：202X年12月31日 | D3: 序号 | E3: 内容 | F3: 索引号
A4: 编制人： | D4: 1 | E4: 专项应付款循环实质性程序 | F4: L6A
A5: 编制日期： | D5: 2 | E5: 专项应付款审定表 | F5: L6-1
A6: 复核人： | D6: 3 | E6: 专项应付款附注披露（上市公司）信息核对表 | G6: 无需打印
A7: 复核日期： | D7: 4 | E7: 专项应付款附注披露（国企）信息核对表 | G7: 无需打印
D8: 5 | E8: 专项应付款明细表 | F8: L6-2
A9: 关于工作底稿与审计程序索引号对应的说明 | D9: 6 | E9: 专项应付款调整分录汇总表 | F9: L6-3
A10: 1.编制的审计工作底稿应与审计程序对应。审计项目组应根据被审计单位实际情况和风险评估情况在实质性程序表中裁剪、修改或增加审计程序，根据实际执行的审计程序完成相应审计工作底稿，编制的工作底稿中应按自然顺序依次编制索引号，并通过唯一的索引号将与实质性程序表中的程序对应关联（即将工作底稿的索引号填入实质性程序表中的底稿索引号列）。 | D10: 7 | E10: 专项应付款检查表 | F10: L6-4
A14: 2.获取的支持性证据应与审计底稿或程序对应。审计项目组在完成底稿时获取的支持性证据应根据底稿索引号编制下一级按自然顺序排序的索引号（如D1-2-1、D1-2-2、……），并在底稿中说明引用的支持性证据、关联索引号。
A17: 3.工作底稿索引号的编码规则：实质性程序索引号按循环从“D”到“N”,循环内账户以顺序号排列，模板中底稿索引号按账户顺序+自然数顺序（即模板中索引号按二级自然顺序排列，如D1-1、D1-2、D1-3、……D1-N）。

Sheet 专项应付款实质性程序表L6A
A1: 致同会计师事务所
A2: 专项应付款实质性程序
A3: =底稿目录!A2 -> 被审计单位： | C3: =底稿目录!A4 -> 编制人： | E3: =底稿目录!A5 -> 编制日期： | H3: 索引号： | I3: L6A
A4: =底稿目录!A3 -> 截止日：202X年12月31日 | C4: =底稿目录!A6 -> 复核人： | E4: =底稿目录!A7 -> 复核日期： | H4: 页 次：
A5: 一、本账户涉及的科目
A6: 专项应付款
A7: 二、审计目标与认定的对应关系
A8: 审计目标 | G8: 财务报表的认定
A9: A. 资产负债表中记录的专项应付款是存在的，且已记录于恰当的账户 | G9: 存在
A10: B. 所有应记录的专项应付款均已记录，所有应当包括在财务报表中的相关披露均已包括 | G10: 完整性
A11: C. 记录的专项应付款是被审计单位应当履行的偿还义务 | G11: 权利和义务
A12: D. 专项应付款以恰当的金额包括在财务报表中，与之相关的计价或分摊调整已恰当记录，相关披露已得到恰当计量和描述 | G12: 准确性、计价和分摊
A13: E. 专项应付款已被恰当地汇总或分解且表述清楚，相关披露在按照企业会计准则的编制基础下是相关的、可理解的 | G13: 列报
A14: 三、计划实施的实质性程序
A15: 序号 | B15: 审计程序 | C15: 程序分类 | D15: 财务报表的认定 | I15: 底稿索引号
D16: 存在 | E16: 完整性 | F16: 权利和义务 | G16: 准确性、计价和分摊 | H16: 列报 | J16: 根据被审计单位实际情况和风险评估情况裁剪、修改或增加审计程序
A17: 1 | B17: 获取或编制专项应付款明细表，完成以下工作，并编制审定表，复核加计是否正确，与总账、明细账合计数核对是否相符。 | C17: 常规★ | D17: √ | E17: √ | G17: √ | I17: L6-1 /L6-2
A18: 2 | B18: 在使用手工编制、自定义信息报告、系统生成的非固定格式报告等由被审计单位生成的信息时，测试有关信息准确性和完整性，并针对编制和维护由被审计单位生成的信息的相关控制实施控制测试，以评价该信息是否能够为实现审计目的提供基础。 | C18: 常规★ | E18: √ | G18: √ | I18: T1 | J18: 可参见《审计手册》4.2.6，由被审计单位生成的信息可能是由系统生成的、或手工编制的、或二者兼而有之的方式生成的。例如，由被审计单位生成的信息可能包括： • 不涉及自定义的、由系统生成的报告（如，固定格式报告）； • 可能通过人工自定义的、由系统生成的报告，例如，（计算机）查询信息或特别定制的报告； • 手工编制的信息，例如，汇总信息的电子表格或用以支持分配、计算以及调节的电子表格； • 其他系统生成或手工编制的信息，例如，由被审计单位编制的客户发票； • 通过影印、拍摄、扫描或其他方式转换成电子形式的文件记录。
A19: 3 | B19: 对期初余额的审计，取得专项应付款期初余额明细表复核加计是否正确，与总账、明细账合计数是否相符，检查上期专项应付款在本期转销情况。考虑获取前期拨款的批准文件、转销或返还依据，必要时可就拨款事项向拨款单位函证。（适用于首次承接） | C19: 备选 | D19: √ | E19: √ | F19: √ | G19: √ | J19: 由被审计单位生成的信息不包括： • 总分类账或明细分类账、试算平衡表、或经审计的财务报表； • 第三方（除了服务机构）的报表或报告，例如，原始银行对账单，或函证的回函； • 外部数据（例如，第三方发布的数据，如，定价来源）。
A20: 4 | B20: 针对专项应付款考虑执行以下程序： （1）检查专项应付款的内容是否系政府作为企业所有者投入的具有专项或特定用途的资本性投资项目拨款。检查各项拨款的批准文件，确定专项应付款发生的真实性。必要时可就拨款事项向拨款单位函证。 （2）检查拨款项目的完成情况，对专项应付款形成资产部分转销的手续是否健全；检查形成资产转销的和未形成长期资产需要核销及拨款结余返还的会计处理是否正确。 | C20: 常规★ | D20: √ | E20: √ | F20: √ | G20: √ | I20: L6-2 /L6-4
A21: 5 | B21: 检查专项应付款是否已按企业会计准则或其他适用的规定在财务报表中做出恰当列报和披露。 | C21: 常规★ | E21: √ | H21: √ | I21: A1-1/A1-15 /A1-16

Sheet 审定表L6-1
A1: 致同会计师事务所
A2: 专项应付款审定表
A3: =底稿目录!A2 -> 被审计单位： | E3: =底稿目录!A4 -> 编制人： | H3: =底稿目录!A5 -> 编制日期： | J3: 索引号： | K3: =底稿目录!F5 -> L6-1
A4: =底稿目录!A3 -> 截止日：202X年12月31日 | E4: =底稿目录!A6 -> 复核人： | H4: =底稿目录!A7 -> 复核日期： | J4: 页次：
A5: 项 目 | B5: 期初数 | F5: 期末数 | J5: 本期审定数与上期 审定数的比较
B6: 未审数 | C6: 账项调整 | D6: 重分类调整 | E6: 审定数 | F6: 未审数 | G6: 账项调整 | H6: 重分类调整 | I6: 审定数 | J6: 变动额 | K6: 变动率
A7: ='明细表L6-2'!B10 -> 0 | B7: ='明细表L6-2'!C10 -> 0 | C7: ='明细表L6-2'!H10 -> 0 | D7: ='明细表L6-2'!I10 -> 0 | E7: =B7+C7+D7 -> 0 | F7: ='明细表L6-2'!G10 -> 0 | G7: ='明细表L6-2'!H10+'明细表L6-2'!J10-'明细表L6-2'!K10-'明细表L6-2'!L10 -> 0 | H7: ='明细表L6-2'!I10+'明细表L6-2'!M10-'明细表L6-2'!N10-'明细表L6-2'!O10 -> 0 | I7: =F7+G7+H7 -> 0 | J7: =I7-E7 -> 0 | K7: =IF(AND(E7=0,J7=0),0,IF(AND(E7=0,J7>0),1,J7/E7)) -> 0
A8: ='明细表L6-2'!B11 -> 0 | B8: ='明细表L6-2'!C11 -> 0 | C8: ='明细表L6-2'!H11 -> 0 | D8: ='明细表L6-2'!I11 -> 0 | E8: =B8+C8+D8 -> 0 | F8: ='明细表L6-2'!G11 -> 0 | G8: ='明细表L6-2'!H11+'明细表L6-2'!J11-'明细表L6-2'!K11-'明细表L6-2'!L11 -> 0 | H8: ='明细表L6-2'!I11+'明细表L6-2'!M11-'明细表L6-2'!N11-'明细表L6-2'!O11 -> 0 | I8: =F8+G8+H8 -> 0 | J8: =I8-E8 -> 0 | K8: =IF(AND(E8=0,J8=0),0,IF(AND(E8=0,J8>0),1,J8/E8)) -> 0
A9: ='明细表L6-2'!B12 -> 0 | B9: ='明细表L6-2'!C12 -> 0 | C9: ='明细表L6-2'!H12 -> 0 | D9: ='明细表L6-2'!I12 -> 0 | E9: =B9+C9+D9 -> 0 | F9: ='明细表L6-2'!G12 -> 0 | G9: ='明细表L6-2'!H12+'明细表L6-2'!J12-'明细表L6-2'!K12-'明细表L6-2'!L12 -> 0 | H9: ='明细表L6-2'!I12+'明细表L6-2'!M12-'明细表L6-2'!N12-'明细表L6-2'!O12 -> 0 | I9: =F9+G9+H9 -> 0 | J9: =I9-E9 -> 0 | K9: =IF(AND(E9=0,J9=0),0,IF(AND(E9=0,J9>0),1,J9/E9)) -> 0
A10: ='明细表L6-2'!B13 -> 0 | B10: ='明细表L6-2'!C13 -> 0 | C10: ='明细表L6-2'!H13 -> 0 | D10: ='明细表L6-2'!I13 -> 0 | E10: =B10+C10+D10 -> 0 | F10: ='明细表L6-2'!G13 -> 0 | G10: ='明细表L6-2'!H13+'明细表L6-2'!J13-'明细表L6-2'!K13-'明细表L6-2'!L13 -> 0 | H10: ='明细表L6-2'!I13+'明细表L6-2'!M13-'明细表L6-2'!N13-'明细表L6-2'!O13 -> 0 | I10: =F10+G10+H10 -> 0 | J10: =I10-E10 -> 0 | K10: =IF(AND(E10=0,J10=0),0,IF(AND(E10=0,J10>0),1,J10/E10)) -> 0
A11: ='明细表L6-2'!B14 -> 0 | B11: ='明细表L6-2'!C14 -> 0 | C11: ='明细表L6-2'!H14 -> 0 | D11: ='明细表L6-2'!I14 -> 0 | E11: =B11+C11+D11 -> 0 | F11: ='明细表L6-2'!G14 -> 0 | G11: ='明细表L6-2'!H14+'明细表L6-2'!J14-'明细表L6-2'!K14-'明细表L6-2'!L14 -> 0 | H11: ='明细表L6-2'!I14+'明细表L6-2'!M14-'明细表L6-2'!N14-'明细表L6-2'!O14 -> 0 | I11: =F11+G11+H11 -> 0 | J11: =I11-E11 -> 0 | K11: =IF(AND(E11=0,J11=0),0,IF(AND(E11=0,J11>0),1,J11/E11)) -> 0
A12: ='明细表L6-2'!B15 -> 0 | B12: ='明细表L6-2'!C15 -> 0 | C12: ='明细表L6-2'!H15 -> 0 | D12: ='明细表L6-2'!I15 -> 0 | E12: =B12+C12+D12 -> 0 | F12: ='明细表L6-2'!G15 -> 0 | G12: ='明细表L6-2'!H15+'明细表L6-2'!J15-'明细表L6-2'!K15-'明细表L6-2'!L15 -> 0 | H12: ='明细表L6-2'!I15+'明细表L6-2'!M15-'明细表L6-2'!N15-'明细表L6-2'!O15 -> 0 | I12: =F12+G12+H12 -> 0 | J12: =I12-E12 -> 0 | K12: =IF(AND(E12=0,J12=0),0,IF(AND(E12=0,J12>0),1,J12/E12)) -> 0
A13: ='明细表L6-2'!B16 -> 0 | B13: ='明细表L6-2'!C16 -> 0 | C13: ='明细表L6-2'!H16 -> 0 | D13: ='明细表L6-2'!I16 -> 0 | E13: =B13+C13+D13 -> 0 | F13: ='明细表L6-2'!G16 -> 0 | G13: ='明细表L6-2'!H16+'明细表L6-2'!J16-'明细表L6-2'!K16-'明细表L6-2'!L16 -> 0 | H13: ='明细表L6-2'!I16+'明细表L6-2'!M16-'明细表L6-2'!N16-'明细表L6-2'!O16 -> 0 | I13: =F13+G13+H13 -> 0 | J13: =I13-E13 -> 0 | K13: =IF(AND(E13=0,J13=0),0,IF(AND(E13=0,J13>0),1,J13/E13)) -> 0
A14: ='明细表L6-2'!B17 -> 0 | B14: ='明细表L6-2'!C17 -> 0 | C14: ='明细表L6-2'!H17 -> 0 | D14: ='明细表L6-2'!I17 -> 0 | E14: =B14+C14+D14 -> 0 | F14: ='明细表L6-2'!G17 -> 0 | G14: ='明细表L6-2'!H17+'明细表L6-2'!J17-'明细表L6-2'!K17-'明细表L6-2'!L17 -> 0 | H14: ='明细表L6-2'!I17+'明细表L6-2'!M17-'明细表L6-2'!N17-'明细表L6-2'!O17 -> 0 | I14: =F14+G14+H14 -> 0 | J14: =I14-E14 -> 0 | K14: =IF(AND(E14=0,J14=0),0,IF(AND(E14=0,J14>0),1,J14/E14)) -> 0
A15: ='明细表L6-2'!B18 -> 0 | B15: ='明细表L6-2'!C18 -> 0 | C15: ='明细表L6-2'!H18 -> 0 | D15: ='明细表L6-2'!I18 -> 0 | E15: =B15+C15+D15 -> 0 | F15: ='明细表L6-2'!G18 -> 0 | G15: ='明细表L6-2'!H18+'明细表L6-2'!J18-'明细表L6-2'!K18-'明细表L6-2'!L18 -> 0 | H15: ='明细表L6-2'!I18+'明细表L6-2'!M18-'明细表L6-2'!N18-'明细表L6-2'!O18 -> 0 | I15: =F15+G15+H15 -> 0 | J15: =I15-E15 -> 0 | K15: =IF(AND(E15=0,J15=0),0,IF(AND(E15=0,J15>0),1,J15/E15)) -> 0
A16: ='明细表L6-2'!B19 -> 0 | B16: ='明细表L6-2'!C19 -> 0 | C16: ='明细表L6-2'!H19 -> 0 | D16: ='明细表L6-2'!I19 -> 0 | E16: =B16+C16+D16 -> 0 | F16: ='明细表L6-2'!G19 -> 0 | G16: ='明细表L6-2'!H19+'明细表L6-2'!J19-'明细表L6-2'!K19-'明细表L6-2'!L19 -> 0 | H16: ='明细表L6-2'!I19+'明细表L6-2'!M19-'明细表L6-2'!N19-'明细表L6-2'!O19 -> 0 | I16: =F16+G16+H16 -> 0 | J16: =I16-E16 -> 0 | K16: =IF(AND(E16=0,J16=0),0,IF(AND(E16=0,J16>0),1,J16/E16)) -> 0
A17: 合计 | B17: =SUM(B7:B16) -> 0 | C17: =SUM(C7:C16) -> 0 | D17: =SUM(D7:D16) -> 0 | E17: =SUM(E7:E16) -> 0 | F17: =SUM(F7:F16) -> 0 | G17: =SUM(G7:G16) -> 0 | H17: =SUM(H7:H16) -> 0 | I17: =SUM(I7:I16) -> 0 | J17: =SUM(J7:J16) -> 0 | K17: =IF(AND(E17=0,J17=0),0,IF(AND(E17=0,J17>0),1,J17/E17)) -> 0
A18: 1、审计说明：
A19: （1）专项应付款期末净值较期初净值增加（负数为减少）：
A20: 主要原因（比例超过30%的）：
A22: （2）与试算平衡表核对
B23: 期末数 | C23: 期初数
A24: 长期应付款审定数
A25: 专项应付款审定数 | B25: =I17 -> 0 | C25: =E17 -> 0
A26: 长期应付款与专项应付款合计数 | B26: =B24+B25 -> 0 | C26: =C24+C25 -> 0
A27: 试算平衡表数
A28: 差异 | B28: =B26-B27 -> 0 | C28: =C26-C27 -> 0
A30: 2、审计结论：

Sheet 附注披露（上市公司）信息
A1: 致同会计师事务所
A2: 专项应付款附注披露信息 | G2: 返回目录
A3: =底稿目录!A2 -> 被审计单位： | B3: ='审定表L6-1'!E3 -> 编制人： | D3: =底稿目录!A5 -> 编制日期： | F3: 索引号：
A4: =底稿目录!A3 -> 截止日：202X年12月31日 | B4: =底稿目录!A6 -> 复核人： | D4: =底稿目录!A7 -> 复核日期： | F4: 页次：
A5: 附注披露信息（上市公司）
A6: 【长期应付款与专项应付款的合计数披露详见P5-1】
A7: （2）专项应付款
A8: 项目 | B8: 期初数 | C8: 本期增加 | D8: 本期减少 | E8: 期末数 | F8: 形成原因
A9: ='明细表L6-2'!B10 -> 0 | B9: ='明细表L6-2'!P10 -> 0 | C9: ='明细表L6-2'!Q10 -> 0 | D9: ='明细表L6-2'!R10+'明细表L6-2'!S10 -> 0 | E9: ='明细表L6-2'!T10 -> 0
A10: ='明细表L6-2'!B11 -> 0 | B10: ='明细表L6-2'!P11 -> 0 | C10: ='明细表L6-2'!Q11 -> 0 | D10: ='明细表L6-2'!R11+'明细表L6-2'!S11 -> 0 | E10: ='明细表L6-2'!T11 -> 0
A11: ='明细表L6-2'!B12 -> 0 | B11: ='明细表L6-2'!P12 -> 0 | C11: ='明细表L6-2'!Q12 -> 0 | D11: ='明细表L6-2'!R12+'明细表L6-2'!S12 -> 0 | E11: ='明细表L6-2'!T12 -> 0
A12: ='明细表L6-2'!B13 -> 0 | B12: ='明细表L6-2'!P13 -> 0 | C12: ='明细表L6-2'!Q13 -> 0 | D12: ='明细表L6-2'!R13+'明细表L6-2'!S13 -> 0 | E12: ='明细表L6-2'!T13 -> 0
A13: ='明细表L6-2'!B14 -> 0 | B13: ='明细表L6-2'!P14 -> 0 | C13: ='明细表L6-2'!Q14 -> 0 | D13: ='明细表L6-2'!R14+'明细表L6-2'!S14 -> 0 | E13: ='明细表L6-2'!T14 -> 0
A14: ='明细表L6-2'!B15 -> 0 | B14: ='明细表L6-2'!P15 -> 0 | C14: ='明细表L6-2'!Q15 -> 0 | D14: ='明细表L6-2'!R15+'明细表L6-2'!S15 -> 0 | E14: ='明细表L6-2'!T15 -> 0
A15: ='明细表L6-2'!B16 -> 0 | B15: ='明细表L6-2'!P16 -> 0 | C15: ='明细表L6-2'!Q16 -> 0 | D15: ='明细表L6-2'!R16+'明细表L6-2'!S16 -> 0 | E15: ='明细表L6-2'!T16 -> 0
A16: ='明细表L6-2'!B17 -> 0 | B16: ='明细表L6-2'!P17 -> 0 | C16: ='明细表L6-2'!Q17 -> 0 | D16: ='明细表L6-2'!R17+'明细表L6-2'!S17 -> 0 | E16: ='明细表L6-2'!T17 -> 0
A17: ='明细表L6-2'!B18 -> 0 | B17: ='明细表L6-2'!P18 -> 0 | C17: ='明细表L6-2'!Q18 -> 0 | D17: ='明细表L6-2'!R18+'明细表L6-2'!S18 -> 0 | E17: ='明细表L6-2'!T18 -> 0
A18: ='明细表L6-2'!B19 -> 0 | B18: ='明细表L6-2'!P19 -> 0 | C18: ='明细表L6-2'!Q19 -> 0 | D18: ='明细表L6-2'!R19+'明细表L6-2'!S19 -> 0 | E18: ='明细表L6-2'!T19 -> 0
A19: 合计 | B19: =SUM(B9:B18) -> 0 | C19: =SUM(C9:C18) -> 0 | D19: =SUM(D9:D18) -> 0 | E19: =SUM(E9:E18) -> 0

Sheet 附注披露（国企）信息
A1: 致同会计师事务所
A2: 专项应付款附注披露信息 | F2: 返回目录
A3: =底稿目录!A2 -> 被审计单位： | B3: ='审定表L6-1'!E3 -> 编制人： | D3: =底稿目录!A5 -> 编制日期： | E3: 索引号：
A4: =底稿目录!A3 -> 截止日：202X年12月31日 | B4: =底稿目录!A6 -> 复核人： | D4: =底稿目录!A7 -> 复核日期： | E4: 页次：
A5: 附注披露信息（国企）
A6: 【长期应付款与专项应付款的合计数披露详见P5-1】
A7: （2）专项应付款
A8: （说明：分项披露专项应付款年末余额最大的前五项）
A9: 项目 | B9: 201X.01.01 | C9: 本期增加 | D9: 本期减少 | E9: 201X.12.31
A10: ='明细表L6-2'!B10 -> 0 | B10: ='明细表L6-2'!P10 -> 0 | C10: ='明细表L6-2'!Q10 -> 0 | D10: ='明细表L6-2'!R10+'明细表L6-2'!S10 -> 0 | E10: ='明细表L6-2'!T10 -> 0
A11: ='明细表L6-2'!B11 -> 0 | B11: ='明细表L6-2'!P11 -> 0 | C11: ='明细表L6-2'!Q11 -> 0 | D11: ='明细表L6-2'!R11+'明细表L6-2'!S11 -> 0 | E11: ='明细表L6-2'!T11 -> 0
A12: ='明细表L6-2'!B12 -> 0 | B12: ='明细表L6-2'!P12 -> 0 | C12: ='明细表L6-2'!Q12 -> 0 | D12: ='明细表L6-2'!R12+'明细表L6-2'!S12 -> 0 | E12: ='明细表L6-2'!T12 -> 0
A13: ='明细表L6-2'!B13 -> 0 | B13: ='明细表L6-2'!P13 -> 0 | C13: ='明细表L6-2'!Q13 -> 0 | D13: ='明细表L6-2'!R13+'明细表L6-2'!S13 -> 0 | E13: ='明细表L6-2'!T13 -> 0
A14: ='明细表L6-2'!B14 -> 0 | B14: ='明细表L6-2'!P14 -> 0 | C14: ='明细表L6-2'!Q14 -> 0 | D14: ='明细表L6-2'!R14+'明细表L6-2'!S14 -> 0 | E14: ='明细表L6-2'!T14 -> 0
A15: 其他 | B15: ='明细表L6-2'!P20-'明细表L6-2'!P10-'明细表L6-2'!P11-'明细表L6-2'!P12-'明细表L6-2'!P13-'明细表L6-2'!P14 -> 0 | C15: ='明细表L6-2'!Q20-'明细表L6-2'!Q10-'明细表L6-2'!Q11-'明细表L6-2'!Q12-'明细表L6-2'!Q13-'明细表L6-2'!Q14 -> 0 | D15: ='明细表L6-2'!R20-'明细表L6-2'!R10-'明细表L6-2'!R11-'明细表L6-2'!R12-'明细表L6-2'!R13-'明细表L6-2'!R14 -> 0 | E15: ='明细表L6-2'!S20-'明细表L6-2'!S10-'明细表L6-2'!S11-'明细表L6-2'!S12-'明细表L6-2'!S13-'明细表L6-2'!S14 -> 0
A16: 合计 | B16: =SUM(B10:B15) -> 0 | C16: =SUM(C10:C15) -> 0 | D16: =SUM(D10:D15) -> 0 | E16: =SUM(E10:E15) -> 0

Sheet 明细表L6-2
A1: 致同会计师事务所 | M1: 致同会计师事务所
A2: 专项应付款明细表 | M2: 专项应付款明细表
A3: =底稿目录!A2 -> 被审计单位： | E3: =底稿目录!A4 -> 编制人： | G3: =底稿目录!A5 -> 编制日期： | K3: 索引号： | L3: =底稿目录!F8 -> L6-2 | O3: =E3 -> 编制人： | S3: =G3 -> 编制日期： | W3: 索引号： | X3: =底稿目录!F8 -> L6-2
A4: =底稿目录!A3 -> 截止日：202X年12月31日 | E4: =底稿目录!A6 -> 复核人： | G4: =底稿目录!A7 -> 复核日期： | K4: 页次： | O4: =E4 -> 复核人： | S4: =G4 -> 复核日期： | W4: 页次：
A5: 一、审计目标: | C5: 1、资产负债表中记录的专项应付款是存在的，且已经记录在恰当的账户中；2、 所有应记录的短期借款均已记录，所有应当包括在财务报表中的相关披露均已包括； | M5: 1、资产负债表中记录的专项应付款是存在的，且已经记录在恰当的账户中；2、 所有应记录的短期借款均已记录，所有应当包括在财务报表中的相关披露均已包括；
C6: 3、专项应付款以恰当的金额包括在财务报表中，与之相关的计价或分摊调整已恰当记录，相关披露已得到恰当计量和描述 | M6: 3、专项应付款以恰当的金额包括在财务报表中，与之相关的计价或分摊调整已恰当记录，相关披露已得到恰当计量和描述
A7: 二、审计过程：
A8: 序号 | B8: 项目 | C8: 未审数 | H8: 期初调整 | J8: 账项调整 | M8: 重分类调整 | P8: 审定数 | U8: 文件依据 | V8: 索引号 | W8: 拨款项目的完成情况 | X8: 备注
C9: 期初余额 | D9: 本期拨入 | E9: 本期结转 | F9: 本期返还 | G9: 期末余额 | H9: 账项调整 | I9: 重分类调整 | J9: 本期拨入 | K9: 本期结转 | L9: 本期返还 | M9: 本期拨入 | N9: 本期结转 | O9: 本期返还 | P9: 期初余额 | Q9: 本期拨入 | R9: 本期结转 | S9: 本期返还 | T9: 期末余额
A10: 1 | G10: =C10+D10-E10-F10 -> 0 | P10: =C10+H10+I10 -> 0 | Q10: =D10+J10+M10 -> 0 | R10: =E10+K10+N10 -> 0 | S10: =F10+L10+O10 -> 0 | T10: =P10+Q10-R10-S10 -> 0
A11: 2 | G11: =C11+D11-E11-F11 -> 0 | P11: =C11+H11+I11 -> 0 | Q11: =D11+J11+M11 -> 0 | R11: =E11+K11+N11 -> 0 | S11: =F11+L11+O11 -> 0 | T11: =P11+Q11-R11-S11 -> 0
A12: 3 | G12: =C12+D12-E12-F12 -> 0 | P12: =C12+H12+I12 -> 0 | Q12: =D12+J12+M12 -> 0 | R12: =E12+K12+N12 -> 0 | S12: =F12+L12+O12 -> 0 | T12: =P12+Q12-R12-S12 -> 0
A13: 4 | G13: =C13+D13-E13-F13 -> 0 | P13: =C13+H13+I13 -> 0 | Q13: =D13+J13+M13 -> 0 | R13: =E13+K13+N13 -> 0 | S13: =F13+L13+O13 -> 0 | T13: =P13+Q13-R13-S13 -> 0
A14: 5 | G14: =C14+D14-E14-F14 -> 0 | P14: =C14+H14+I14 -> 0 | Q14: =D14+J14+M14 -> 0 | R14: =E14+K14+N14 -> 0 | S14: =F14+L14+O14 -> 0 | T14: =P14+Q14-R14-S14 -> 0
A15: 6 | G15: =C15+D15-E15-F15 -> 0 | P15: =C15+H15+I15 -> 0 | Q15: =D15+J15+M15 -> 0 | R15: =E15+K15+N15 -> 0 | S15: =F15+L15+O15 -> 0 | T15: =P15+Q15-R15-S15 -> 0
A16: 7 | G16: =C16+D16-E16-F16 -> 0 | P16: =C16+H16+I16 -> 0 | Q16: =D16+J16+M16 -> 0 | R16: =E16+K16+N16 -> 0 | S16: =F16+L16+O16 -> 0 | T16: =P16+Q16-R16-S16 -> 0
A17: 8 | G17: =C17+D17-E17-F17 -> 0 | P17: =C17+H17+I17 -> 0 | Q17: =D17+J17+M17 -> 0 | R17: =E17+K17+N17 -> 0 | S17: =F17+L17+O17 -> 0 | T17: =P17+Q17-R17-S17 -> 0
A18: 9 | G18: =C18+D18-E18-F18 -> 0 | P18: =C18+H18+I18 -> 0 | Q18: =D18+J18+M18 -> 0 | R18: =E18+K18+N18 -> 0 | S18: =F18+L18+O18 -> 0 | T18: =P18+Q18-R18-S18 -> 0
A19: 10 | G19: =C19+D19-E19-F19 -> 0 | P19: =C19+H19+I19 -> 0 | Q19: =D19+J19+M19 -> 0 | R19: =E19+K19+N19 -> 0 | S19: =F19+L19+O19 -> 0 | T19: =P19+Q19-R19-S19 -> 0
A20: 合计 | C20: =SUM(C10:C19) -> 0 | D20: =SUM(D10:D19) -> 0 | E20: =SUM(E10:E19) -> 0 | F20: =SUM(F10:F19) -> 0 | G20: =SUM(G10:G19) -> 0 | H20: =SUM(H10:H19) -> 0 | I20: =SUM(I10:I19) -> 0 | J20: =SUM(J10:J19) -> 0 | ... T20: =SUM(T10:T19) -> 0
A21: 三、审计说明：
A25: 四、审计结论：
A28: 提示：
A29: 1本科目核算企业取得政府作为企业所有者投入的具有专项或特定用途的款项。
A30: 2.专项应付款核算内容不包括与政府补助相关的项目。“政府补助”是指企业从政府无偿取得的货币性资产或非货币性资产，与收入的区别主要在于其“无偿性”；而收入用于计量与客户之间的合同形成的、与所有者投入资本无关的经济利益流入。 根据《企业会计准则应用指南——会计科目和主要账务处理》的规定，“专项应付款”科目核算的是企业取得政府作为企业所有者投入的具有专项或特定用途的款项，政府以投资者身份向企业投入资本，享有企业相应的所有者权益。实务中只有拨付文件中明确计入专项应付款的项目，或者符合准则相关规定要求应计入专项应付款的项目（例如符合要求的搬迁补偿等）才可以计入专项应付款。
A31: 3应按专项应付款每一明细账户分别列示。
A32: 4.外币专项应付款应在“备注”栏中列明原币金额及折合汇率。
A33: 5.应说明专项应付款的来源、指定的专门用途、使用限制等相关内容。如：该专项应付款为财政部按照XX文规定拨付的X项目专用设备购置款。
A34: 6.企业因城镇整体规划、库区建设、棚户区改造、沉陷区治理等公共利益进行搬迁，收到政府从财政预算直接拨付的搬迁补偿款，在专项应付款中核算。
A35: 7.根据《财政部关于印发〈工业企业结构调整专项奖补资金管理办法〉的通知》，中央财政将安排工业企业结构调整专项奖补资金，用于支持地方政府和中央企业推动钢铁、煤炭等行业化解过剩产能。中央企业在收到预拨的专项奖补资金时，应当暂通过“专项应付款”科目核算，借记“银行存款”等科目，贷记“专项应付款”科目。
A36: 8.审计说明可以概述：（1）程序的测试情况、结果；（2）拟调整事项及其调整分录、未调整事项及其影响，审计范围受到限制情况及其影响。
A37: 9.审计结论可参考：A、未见异常。 B、除上述重大不符事项应当作为调整事项予以调整外，其余未见异常。 C、由于存在以下重大未调整事项（或审计范围受到限制无法获取充分、适当证据），不可确认。

Sheet 调整分录汇总L6-3
A1: 致同会计师事务所
A2: 专项应付款调整分录汇总表
A3: =底稿目录!A2 -> 被审计单位： | D3: =底稿目录!A4 -> 编制人： | G3: =底稿目录!A5 -> 编制日期： | I3: 索引： | J3: =底稿目录!F9 -> L6-3
A4: =底稿目录!A3 -> 截止日：202X年12月31日 | D4: =底稿目录!A6 -> 复核人： | G4: =底稿目录!A7 -> 复核日期： | I4: 页次：
A5: 调整事项说明 | B5: 类别（报表调整/账项调整/其他） | C5: 报表项目 | D5: 科目名称 | E5: 附注项目 | F5: …… | G5: 借方调整金额 | H5: 贷方调整金额 | I5: 索引 | J5: 备注
A22: 注：本底稿适用于调整分录较多、较复杂的项目，且仅列示与本报表项目相关的审计调整。项目组可根据项目实际情况选择是否使用该底稿。

Sheet 检查表L6-4
A1: 致同会计师事务所
A2: 专项应付款检查表
A3: =底稿目录!A2 -> 被审计单位： | F3: =底稿目录!A4 -> 编制人： | K3: =底稿目录!A5 -> 编制日期： | P3: 索引号： | Q3: =底稿目录!F10 -> L6-4
A4: =底稿目录!A3 -> 截止日：202X年12月31日 | F4: =底稿目录!A6 -> 复核人： | K4: =底稿目录!A7 -> 复核日期： | P4: 页次：
A5: 一、审计目标:
A6: 1.资产负债表中记录的专项应付款是存在的，且已经记录在恰当的账户中； 2.记录的专项应付款由被审计单位拥有或控制；
A7: 3.专项应付款以恰当的金额包括在财务报表中，与之相关的计价或分摊调整已恰当记录，相关披露已得到恰当计量和描述
A8: 二、测试： | C8: 测试原因：大额（）关联方（）大额交易频繁（）异常（）其他（）
A9: 测试内容说明：1.原始凭证是否齐全； 2.记账凭证与原始凭证是否相符；3.账务处理是否正确；4.是否记录于恰当的会计期间；5.……
A10: 项目 | B10: 记账凭证 | I10: 支持性文件 | J10: 核对内容 | O10: 索引号 | P10: 是否异常 | Q10: 备注说明
B11: 日期 | C11: 凭证编号 | D11: 业务内容 | E11: 对方科目 | F11: 对方明细科目 | G11: 借方金额 | H11: 贷方金额 | J11: 1 | K11: 2 | L11: 3 | M11: 4 | N11: 5
A19: 合计 | G19: =SUM(G12:G18) -> 0 | H19: =SUM(H12:H18) -> 0
A20: 本期发生额 | G20: ='明细表L6-2'!R20+'明细表L6-2'!S20 -> 0 | H20: ='明细表L6-2'!Q20 -> 0
A21: 检查比例 | G21: =G19/G20 -> #DIV/0! | H21: =H19/H20 -> #DIV/0!
A22: 提示： | B22: 1、检查专项拨款是否按既定用途使用。 | F22: 2、未形成相应资产的专项应付款项是否经批准程序予以核销。
A23: 三、审计说明：
A25: 四、审计结论：

Sheet GT_Custom
A1: C1 | B1: Custom 1
A2: C2 | B2: Custom 2
A3: C3 | B3: Custom 3
A4: C4 | B4: Custom 4
A5: C5 | B5: Custom 5
A6: C6 | B6: Custom 6
A7: C7 | B7: Custom 7
A8: C8 | B8: Custom 8
