Workbook

Sheet 底稿目录
A1: 底稿开列时，可先在以下单元格填写有关内容，以便其他底稿引用有关数据：
A2: 被审计单位：
A3: 截止日：202X年12月31日 | D3: 序号 | E3: 内容 | F3: 索引号
A4: 编制人： | D4: 1 | E4: 其他非流动负债实质性程序表 | F4: L7A
A5: 编制日期： | D5: 2 | E5: 其他非流动负债审定表 | F5: L7-1
A6: 复核人： | D6: 3 | E6: 其他非流动负债附注披露（上市公司）信息核对表 | G6: 无需打印
A7: 复核日期： | D7: 4 | E7: 其他非流动负债附注披露（国企）信息核对表 | G7: 无需打印
D8: 5 | E8: 其他非流动负债明细表 | F8: L7-2
A9: 关于工作底稿与审计程序索引号对应的说明 | D9: 6 | E9: ='调整分录汇总L7-3'!A2 -> 其他非流动负债调整分录汇总表 | F9: L7-3
A10: 1.编制的审计工作底稿应与审计程序对应。审计项目组应根据被审计单位实际情况和风险评估情况在实质性程序表中裁剪、修改或增加审计程序，根据实际执行的审计程序完成相应审计工作底稿，编制的工作底稿中应按自然顺序依次编制索引号，并通过唯一的索引号将与实质性程序表中的程序对应关联（即将工作底稿的索引号填入实质性程序表中的底稿索引号列）。 | D10: 7 | E10: ='其他非流动负债检查表L7-4'!A2 -> 其他非流动负债检查表 | F10: L7-4
A14: 2.获取的支持性证据应与审计底稿或程序对应。审计项目组在完成底稿时获取的支持性证据应根据底稿索引号编制下一级按自然顺序排序的索引号（如D1-2-1、D1-2-2、……），并在底稿中说明引用的支持性证据、关联索引号。
A17: 3.工作底稿索引号的编码规则：实质性程序索引号按循环从“D”到“N”,循环内账户以顺序号排列，模板中底稿索引号按账户顺序+自然数顺序（即模板中索引号按二级自然顺序排列，如D1-1、D1-2、D1-3、……D1-N）。

Sheet 其他非流动负债实质性程序表L7A
A1: 致同会计师事务所
A2: 其他非流动负债实质性程序
A3: =底稿目录!A2 -> 被审计单位： | C3: =底稿目录!A4 -> 编制人： | E3: =底稿目录!A5 -> 编制日期： | H3: 索引号： | I3: =底稿目录!F4 -> L7A
A4: =底稿目录!A3 -> 截止日：202X年12月31日 | C4: =底稿目录!A6 -> 复核人： | E4: =底稿目录!A7 -> 复核日期： | H4: 页 次：
A5: 一、本账户涉及的科目
A6: 其他非流动负债
A7: 二、审计目标与认定的对应关系
A8: 审计目标 | G8: 财务报表的认定
A9: A. 资产负债表中记录的其他非流动负债是存在的，且已记录于恰当的账户 | G9: 存在
A10: B. 所有应记录的其他非流动负债均已记录，所有应当包括在财务报表中的相关披露均已包括 | G10: 完整性
A11: C. 记录的其他非流动负债是被审计单位应当履行的偿还义务 | G11: 权利和义务
A12: D. 其他非流动负债以恰当的金额包括在财务报表中，与之相关的计价或分摊调整已恰当记录，相关披露已得到恰当计量和描述 | G12: 准确性、计价和分摊
A13: E. 其他非流动负债已被恰当地汇总或分解且表述清楚，相关披露在按照企业会计准则的编制基础下是相关的、可理解的 | G13: 列报
A14: 三、计划实施的实质性程序
A15: 序号 | B15: 审计程序 | C15: 程序分类 | D15: 财务报表的认定 | I15: 底稿索引号
D16: 存在 | E16: 完整性 | F16: 权利和 义务 | G16: 准确性、计价和分摊 | H16: 列报 | J16: 根据被审计单位实际情况和风险评估情况裁剪、修改或增加审计程序
A17: 1 | B17: 获取其他非流动负债明细表，并编制审定表。 （1）复核加计是否正确，与总账、明细账合计数核对是否相符，期初余额与上期审定期末余额是否相符；； （2）确定流动负债和非流动负债的划分是否正确 。 | C17: 常规★ | D17: √ | E17: √ | G17: √ | I17: L7-1 /L7-2
A18: 2 | B18: 在使用手工编制、自定义信息报告`、系统生成的非固定格式报告等由被审计单位生成的信息时，测试有关信息准确性和完整性，并针对编制和维护由被审计单位生成的信息的相关控制实施控制测试，以评价该信息是否能够为实现审计目的提供基础。 | C18: 常规★ | E18: √ | G18: √ | I18: T1 / | J18: 可参见《审计手册》4.2.6，由被审计单位生成的信息可能是由系统生成的、或手工编制的、或二者兼而有之的方式生成的。例如，由被审计单位生成的信息可能包括： • 不涉及自定义的、由系统生成的报告（如，固定格式报告）； • 可能通过人工自定义的、由系统生成的报告，例如，（计算机）查询信息或特别定制的报告； • 手工编制的信息，例如，汇总信息的电子表格或用以支持分配、计算以及调节的电子表格； • 其他系统生成或手工编制的信息，例如，由被审计单位编制的客户发票； • 通过影印、拍摄、扫描或其他方式转换成电子形式的文件记录。
A19: 3 | B19: 对期初余额的审计，取得其他非流动负债期初余额明细表复核加计是否正确，与总账、明细账合计数是否相符，检查上期其他非流动负债在本期转销情况。（适用于首次承接） | C19: 备选 | D19: √ | E19: √ | F19: √ | G19: √ | J19: 由被审计单位生成的信息不包括： • 总分类账或明细分类账、试算平衡表、或经审计的财务报表； • 第三方（除了服务机构）的报表或报告，例如，原始银行对账单，或函证的回函； • 外部数据（例如，第三方发布的数据，如，定价来源）。
A20: 4 | B20: 检查与其他非流动负债有关的的记账凭证和相应的支持性证据以确定交易的真实性，是否按规定进行相应的会计处理和披露 | C20: 常规★ | D20: √ | F20: √ | G20: √ | I20: L7-4
A21: 5 | B21: 根据评估的舞弊风险等因素增加的审计程序。 | C21: IPO/上市/新三板/重组/舞弊应对
A22: 6 | B22: 确定需在财务报表中单独披露的信息已被记录。 | C22: 常规★ | H22: √ | I22: A1-1/A1-15 /A1-16

Sheet 审定表L7-1
A1: 致同会计师事务所
A2: 其他非流动负债审定表
A3: =底稿目录!A2 -> 被审计单位： | E3: =底稿目录!A4 -> 编制人： | H3: =底稿目录!A5 -> 编制日期： | J3: 索引号： | K3: =底稿目录!F5 -> L7-1
A4: =底稿目录!A3 -> 截止日：202X年12月31日 | E4: =底稿目录!A6 -> 复核人： | H4: =底稿目录!A7 -> 复核日期： | J4: 页次：
A5: 项 目 | B5: 期初数 | F5: 期末数 | J5: 本期审定数与上期 审定数的比较
B6: 未审数 | C6: 账项调整 | D6: 重分类调整 | E6: 审定数 | F6: 未审数 | G6: 账项调整 | H6: 重分类调整 | I6: 审定数 | J6: 变动额 | K6: 变动率
A7: ='明细表L7-2'!A12 -> 0 | B7: ='明细表L7-2'!B12 -> 0 | C7: ='明细表L7-2'!F12 -> 0 | D7: ='明细表L7-2'!G12 -> 0 | E7: =B7+C7+D7 -> 0 | F7: ='明细表L7-2'!E12 -> 0 | G7: ='明细表L7-2'!F12+'明细表L7-2'!H12-'明细表L7-2'!I12 -> 0 | H7: ='明细表L7-2'!G12+'明细表L7-2'!J12-'明细表L7-2'!K12 -> 0 | I7: =F7+G7+H7 -> 0 | J7: =I7-E7 -> 0 | K7: =IF(AND(E7=0,J7=0),0,IF(AND(E7=0,J7>0),1,J7/E7)) -> 0
A8: ='明细表L7-2'!A13 -> 0 | B8: ='明细表L7-2'!B13 -> 0 | C8: ='明细表L7-2'!F13 -> 0 | D8: ='明细表L7-2'!G13 -> 0 | E8: =B8+C8+D8 -> 0 | F8: ='明细表L7-2'!E13 -> 0 | G8: ='明细表L7-2'!F13+'明细表L7-2'!H13-'明细表L7-2'!I13 -> 0 | H8: ='明细表L7-2'!G13+'明细表L7-2'!J13-'明细表L7-2'!K13 -> 0 | I8: =F8+G8+H8 -> 0 | J8: =I8-E8 -> 0 | K8: =IF(AND(E8=0,J8=0),0,IF(AND(E8=0,J8>0),1,J8/E8)) -> 0
A9: ='明细表L7-2'!A14 -> 0 | B9: ='明细表L7-2'!B14 -> 0 | C9: ='明细表L7-2'!F14 -> 0 | D9: ='明细表L7-2'!G14 -> 0 | E9: =B9+C9+D9 -> 0 | F9: ='明细表L7-2'!E14 -> 0 | G9: ='明细表L7-2'!F14+'明细表L7-2'!H14-'明细表L7-2'!I14 -> 0 | H9: ='明细表L7-2'!G14+'明细表L7-2'!J14-'明细表L7-2'!K14 -> 0 | I9: =F9+G9+H9 -> 0 | J9: =I9-E9 -> 0 | K9: =IF(AND(E9=0,J9=0),0,IF(AND(E9=0,J9>0),1,J9/E9)) -> 0
A10: ='明细表L7-2'!A15 -> 0 | B10: ='明细表L7-2'!B15 -> 0 | C10: ='明细表L7-2'!F15 -> 0 | D10: ='明细表L7-2'!G15 -> 0 | E10: =B10+C10+D10 -> 0 | F10: ='明细表L7-2'!E15 -> 0 | G10: ='明细表L7-2'!F15+'明细表L7-2'!H15-'明细表L7-2'!I15 -> 0 | H10: ='明细表L7-2'!G15+'明细表L7-2'!J15-'明细表L7-2'!K15 -> 0 | I10: =F10+G10+H10 -> 0 | J10: =I10-E10 -> 0 | K10: =IF(AND(E10=0,J10=0),0,IF(AND(E10=0,J10>0),1,J10/E10)) -> 0
A11: ='明细表L7-2'!A16 -> 0 | B11: ='明细表L7-2'!B16 -> 0 | C11: ='明细表L7-2'!F16 -> 0 | D11: ='明细表L7-2'!G16 -> 0 | E11: =B11+C11+D11 -> 0 | F11: ='明细表L7-2'!E16 -> 0 | G11: ='明细表L7-2'!F16+'明细表L7-2'!H16-'明细表L7-2'!I16 -> 0 | H11: ='明细表L7-2'!G16+'明细表L7-2'!J16-'明细表L7-2'!K16 -> 0 | I11: =F11+G11+H11 -> 0 | J11: =I11-E11 -> 0 | K11: =IF(AND(E11=0,J11=0),0,IF(AND(E11=0,J11>0),1,J11/E11)) -> 0
A12: 合计 | B12: =SUM(B7:B11) -> 0 | C12: =SUM(C7:C11) -> 0 | D12: =SUM(D7:D11) -> 0 | E12: =SUM(E7:E11) -> 0 | F12: =SUM(F7:F11) -> 0 | G12: =SUM(G7:G11) -> 0 | H12: =SUM(H7:H11) -> 0 | I12: =SUM(I7:I11) -> 0 | J12: =SUM(J7:J11) -> 0 | K12: =IF(AND(E12=0,J12=0),0,IF(AND(E12=0,J12>0),1,J12/E12)) -> 0
A14: 试算平衡表数
A15: 差异数 | E15: =E12-E14 -> 0 | I15: =I12-I14 -> 0
A16: 一、审计说明：
A18: 二、审计结论：

Sheet 附注披露信息（上市公司）
A1: 致同会计师事务所
A2: 其他非流动负债附注披露信息 | E2: 返回目录
A3: =底稿目录!A2 -> 被审计单位： | B3: =底稿目录!A4 -> 编制人： | C3: =底稿目录!A5 -> 编制日期： | D3: 索引号：
A4: =底稿目录!A3 -> 截止日：202X年12月31日 | B4: =底稿目录!A6 -> 复核人： | C4: =底稿目录!A7 -> 复核日期： | D4: 页次：
A5: 其他非流动负债
A6: 项 目 | B6: 期末数 | C6: 上年年末数
A7: ='明细表L7-2'!A12 -> 0 | B7: ='明细表L7-2'!O12 -> 0 | C7: ='明细表L7-2'!L12 -> 0
A8: ='明细表L7-2'!A13 -> 0 | B8: ='明细表L7-2'!O13 -> 0 | C8: ='明细表L7-2'!L13 -> 0
A9: ='明细表L7-2'!A14 -> 0 | B9: ='明细表L7-2'!O14 -> 0 | C9: ='明细表L7-2'!L14 -> 0
A10: ='明细表L7-2'!A15 -> 0 | B10: ='明细表L7-2'!O15 -> 0 | C10: ='明细表L7-2'!L15 -> 0
A11: ='明细表L7-2'!A16 -> 0 | B11: ='明细表L7-2'!O16 -> 0 | C11: ='明细表L7-2'!L16 -> 0
A12: 合 计 | B12: =SUM(B7:B11) -> 0 | C12: =SUM(C7:C11) -> 0

Sheet 附注披露信息(国企)
A1: 致同会计师事务所
A2: 其他非流动负债附注披露信息 | E2: 返回目录
A3: =底稿目录!A2 -> 被审计单位： | B3: =底稿目录!A4 -> 编制人： | C3: =底稿目录!A5 -> 编制日期： | D3: 索引号：
A4: =底稿目录!A3 -> 截止日：202X年12月31日 | B4: =底稿目录!A6 -> 复核人： | C4: =底稿目录!A7 -> 复核日期： | D4: 页次：
A5: 其他非流动负债
A6: 项目 | B6: 年初余额 | C6: 期末余额
A7: ='明细表L7-2'!A12 -> 0 | B7: ='明细表L7-2'!L12 -> 0 | C7: ='明细表L7-2'!O12 -> 0
A8: ='明细表L7-2'!A13 -> 0 | B8: ='明细表L7-2'!L13 -> 0 | C8: ='明细表L7-2'!O13 -> 0
A9: ='明细表L7-2'!A14 -> 0 | B9: ='明细表L7-2'!L14 -> 0 | C9: ='明细表L7-2'!O14 -> 0
A10: ='明细表L7-2'!A15 -> 0 | B10: ='明细表L7-2'!L15 -> 0 | C10: ='明细表L7-2'!O15 -> 0
A11: ='明细表L7-2'!A16 -> 0 | B11: ='明细表L7-2'!L16 -> 0 | C11: ='明细表L7-2'!O16 -> 0
A12: 合 计 | B12: =SUM(B7:B11) -> 0 | C12: =SUM(C7:C11) -> 0

Sheet 明细表L7-2
A1: 致同会计师事务所
A2: 其他非流动负债明细表
A3: =底稿目录!A2 -> 被审计单位： | F3: =底稿目录!A4 -> 编制人： | M3: =底稿目录!A5 -> 编制日期： | Q3: 索引号： | R3: =底稿目录!F8 -> L7-2
A4: =底稿目录!A3 -> 截止日：202X年12月31日 | F4: =底稿目录!A6 -> 复核人： | M4: =底稿目录!A7 -> 复核日期： | Q4: 页次：
A5: 一、审计目标:
A6: 1.资产负债表中记录的其他非流动负债是存在的，且已记录于恰当的账户；2.所有应记录的其他非流动负债均已记录，所有应当包括在财务报表中的相关披露均已包括
A7: 3.其他非流动负债以恰当的金额包括在财务报表中，与之相关的计价或分摊调整已恰当记录，相关披露已得到恰当计量和描述 ；
A8: 4.其他非流动负债已被恰当地汇总或分解且表述清楚，相关披露在按照企业会计准则的编制基础下是相关的、可理解的
A9: 二、审计过程：
A10: 项目 | B10: 未审数 | F10: 期初调整 | H10: 账项调整 | J10: 重分类调整 | L10: 审定数 | P10: 文件依据 | Q10: 索引号 | R10: 备注
B11: 期初余额 | C11: 本期增加 | D11: 本期减少 | E11: 期末余额 | F11: 账项调整 | G11: 重分类调整 | H11: 本期增加 | I11: 本期减少 | J11: 本期增加 | K11: 本期减少 | L11: 期初余额 | M11: 本期增加 | N11: 本期减少 | O11: 期末余额
E12: =B12+C12-D12 -> 0 | L12: =B12+F12+G12 -> 0 | M12: =C12+H12+J12 -> 0 | N12: =D12+I12+K12 -> 0 | O12: =L12+M12-N12 -> 0
E13: =B13+C13-D13 -> 0 | L13: =B13+F13+G13 -> 0 | M13: =C13+H13+J13 -> 0 | N13: =D13+I13+K13 -> 0 | O13: =L13+M13-N13 -> 0
E14: =B14+C14-D14 -> 0 | L14: =B14+F14+G14 -> 0 | M14: =C14+H14+J14 -> 0 | N14: =D14+I14+K14 -> 0 | O14: =L14+M14-N14 -> 0
E15: =B15+C15-D15 -> 0 | L15: =B15+F15+G15 -> 0 | M15: =C15+H15+J15 -> 0 | N15: =D15+I15+K15 -> 0 | O15: =L15+M15-N15 -> 0
E16: =B16+C16-D16 -> 0 | L16: =B16+F16+G16 -> 0 | M16: =C16+H16+J16 -> 0 | N16: =D16+I16+K16 -> 0 | O16: =L16+M16-N16 -> 0
A17: 合计 | B17: =SUM(B12:B16) -> 0 | C17: =SUM(C12:C16) -> 0 | D17: =SUM(D12:D16) -> 0 | E17: =SUM(E12:E16) -> 0 | F17: =SUM(F12:F16) -> 0 | G17: =SUM(G12:G16) -> 0 | H17: =SUM(H12:H16) -> 0 | I17: =SUM(I12:I16) -> 0 | ... O17: =SUM(O12:O16) -> 0
A18: 三、审计说明：
A20: 四、审计结论：
A21: 提示：
A22: 1.审计说明可以概述：（1）程序的测试情况、结果；（2）拟调整事项及其调整分录、未调整事项及其影响，审计范围受到限制情况及其影响。
A23: 2.审计结论可参考：A、未见异常。 B、除上述重大不符事项应当作为调整事项予以调整外，其余未见异常。 C、由于存在以下重大未调整事项（或审计范围受到限制无法获取充分、适当证据），不可确认。

Sheet 调整分录汇总L7-3
A1: 致同会计师事务所
A2: 其他非流动负债调整分录汇总表
A3: =底稿目录!A2 -> 被审计单位： | D3: =底稿目录!A4 -> 编制人： | G3: =底稿目录!A5 -> 编制日期： | I3: 索引： | J3: =底稿目录!F9 -> L7-3
A4: =底稿目录!A3 -> 截止日：202X年12月31日 | D4: =底稿目录!A6 -> 复核人： | G4: =底稿目录!A7 -> 复核日期： | I4: 页次：
A5: 调整事项说明 | B5: 类别（报表调整/账项调整/其他） | C5: 报表项目 | D5: 科目名称 | E5: 附注项目 | F5: …… | G5: 借方调整金额 | H5: 贷方调整金额 | I5: 索引 | J5: 备注
A22: 注：本底稿适用于调整分录较多、较复杂的项目，且仅列示与本报表项目相关的审计调整。项目组可根据项目实际情况选择是否使用该底稿。

Sheet 其他非流动负债检查表L7-4
A1: 致同会计师事务所
A2: 其他非流动负债检查表
A3: =底稿目录!A2 -> 被审计单位： | D3: =底稿目录!A4 -> 编制人： | H3: =底稿目录!A5 -> 编制日期： | O3: 索引号： | P3: =底稿目录!F10 -> L7-4
A4: =底稿目录!A3 -> 截止日：202X年12月31日 | D4: =底稿目录!A6 -> 复核人： | H4: =底稿目录!A7 -> 复核日期： | O4: 页次：
A5: 一、审计目标:
A6: 1.资产负债表中记录的其他非流动负债是存在的，且已经记录在恰当的账户中； 2.记录的其他非流动负债由被审计单位拥有或控制；
A7: 3.其他非流动负债以恰当的金额包括在财务报表中，与之相关的计价或分摊调整已恰当记录，相关披露已得到恰当计量和描述
A8: 二、测试： | C8: 测试原因：大额（）关联方（）大额交易频繁（）异常（）其他（）
A9: 测试内容说明：1.原始凭证是否齐全； 2.记账凭证与原始凭证是否相符；3.账务处理是否正确；4.是否记录于恰当的会计期间；5.……
A10: 记账凭证 | H10: 支持性文件 | I10: 核对内容 | N10: 索引号 | O10: 是否异常 | P10: 备注说明
A11: 日期 | B11: 凭证编号 | C11: 业务内容 | D11: 对方科目 | E11: 对方明细科目 | F11: 借方金额 | G11: 贷方金额 | I11: 1 | J11: 2 | K11: 3 | L11: 4 | M11: 5
A22: 合计 | F22: =SUM(F12:F21) -> 0 | G22: =SUM(G12:G21) -> 0
A23: 本期发生额 | F23: ='明细表L7-2'!N17 -> 0 | G23: ='明细表L7-2'!M17 -> 0
A24: 检查比例 | F24: =F22/F23 -> #DIV/0! | G24: =G22/G23 -> #DIV/0!
A25: 三、审计说明：
A28: 四、审计结论：
