Workbook

Sheet 底稿目录
A1: 底稿开列时，可先在以下单元格填写有关内容，以便其他底稿引用有关数据：
A2: 被审计单位： | D2: 序号 | E2: 内容 | F2: 索引号
A3: 会计期间：202X年度 | D3: 1 | E3: 营业收入账面金额与ERP系统核对记录 | F3: D4-13
A4: 编制人： | D4: 2 | E4: 营业收入发生检查表 | F4: D4-14
A5: 编制日期： | D5: 3 | E5: 营业收入完整性检查表 | F5: D4-15
A6: 复核人： | D6: 4 | E6: 出口收入电子口岸系统核对 | F6: D4-16
A7: 复核日期： | D7: 5 | E7: 营业收入截止测试（账到单据） | F7: D4-17
D8: 6 | E8: 营业收入截止测试（单据到账） | F8: D4-18
A9: 关于工作底稿与审计程序索引号对应的说明 | D9: 7 | E9: 销售折扣与折让检查 | F9: D4-19
A10: 1.编制的审计工作底稿应与审计程序对应。审计项目组应根据被审计单位实际情况和风险评估情况在实质性程序表中裁剪、修改或增加审计程序，根据实际执行的审计程序完成相应审计工作底稿，编制的工作底稿中应按自然顺序依次编制索引号，并通过唯一的索引号将与实质性程序表中的程序对应关联（即将工作底稿的索引号填入实质性程序表中的底稿索引号列）。 | D10: 8 | E10: 销售退货检查 | F10: D4-20
A14: 2.获取的支持性证据应与审计底稿或程序对应。审计项目组在完成底稿时获取的支持性证据应根据底稿索引号编制下一级按自然顺序排序的索引号（如D1-2-1、D1-2-2、……），并在底稿中说明引用的支持性证据、关联索引号。
A17: 3.工作底稿索引号的编码规则：实质性程序索引号按循环从“D”到“N”,循环内账户以顺序号排列，模板中底稿索引号按账户顺序+自然数顺序（即模板中索引号按二级自然顺序排列，如D1-1、D1-2、D1-3、……D1-N）。

Sheet 营业收入账面金额与ERP系统核对记录D4-13
A1: 致同会计师事务所
A2: 营业收入账面金额与ERP系统核对记录
A3: =底稿目录!A2 -> 被审计单位： | B3: =底稿目录!A4 -> 编制人： | C3: =底稿目录!A5 -> 编制日期： | D3: 索引号： | E3: =底稿目录!F3 -> D4-13
A4: =底稿目录!A3 -> 会计期间：202X年度 | B4: =底稿目录!A6 -> 复核人： | C4: =底稿目录!A7 -> 复核日期： | D4: 页次：
A5: 一、核对过程
A15: 二、核对结论
A19: 提示：对于互联网等业务数据量大的被审计单位，应结合IT审计完成核对。

Sheet 营业收入发生检查表D4-14
A1: 致同会计师事务所 | U1: 致同会计师事务所
A2: 营业收入发生检查表 | U2: 营业收入发生检查表
A3: =底稿目录!A2 -> 被审计单位： | H3: =底稿目录!A4 -> 编制人： | M3: =底稿目录!A5 -> 编制日期： | S3: 索引号： | T3: =底稿目录!F4 -> D4-14 | U3: =底稿目录!A2 -> 被审计单位： | Y3: =底稿目录!A4 -> 编制人： | AC3: =底稿目录!A5 -> 编制日期： | AJ3: 索引号： | AK3: =底稿目录!F4 -> D4-14
A4: =底稿目录!A3 -> 会计期间：202X年度 | H4: =底稿目录!A6 -> 复核人： | M4: =底稿目录!A7 -> 复核日期： | S4: 页次： | U4: =底稿目录!A3 -> 会计期间：202X年度 | Y4: =底稿目录!A6 -> 复核人： | AC4: =底稿目录!A7 -> 复核日期： | AJ4: 页次：
A5: 一、审计目标：
A6: 1.利润表中记录的营业收入已发生，且与被审计单位有关；2.与营业收入有关的金额及其他数据已恰当记录，相关披露已得到恰当计量和描述；3.与营业收入有关的交易和事项已记录于正确的会计期间。
A7: 二、样本选取标准与规模：
A8: 测试总体： | C8: 如营业收入所有销售记账凭证共XX笔金额XX、贷方发生额所有凭证共XX笔金额XX | J8: 特定样本： | K8: XX金额以上（大额）、关联方/关联交易形成的款项、XX异常款项全部测试，共XX笔；
A9: 抽样总体： | C9: 测试总体扣除特定样本以外的样本，共XX笔、金额XX | J9: 确定的抽样样本量： | L9: 抽取XX笔 | M9: （如果使用了样本计算器计算样本量，样本量计算过程见<XX>底稿）
A10: 抽样方法： | C10: 随机选样/系统选样/货币单元抽样/随意选样（非统计抽样适用） | J10: 抽样过程： | K10: 使用IDEA（XX抽样工具）选择XX数量、金额XX的样本进行测试，抽样工具中的样本选择过程和结果见<XX>底稿
A11: 三、测试： | C11: 检查内容说明：1.核对合同、出库单、物流单、验收单等品名、规格一致、数量、单价、金额一致；2.核对验收单等控制权转移日期是否与记账相符，是否确认至恰当期间；
C12: 3.核对签收单签收人或盖章信息是否存在异常；4.核对运输地址是否与客户合同记录发货地址一致，是否存在异常；5.……
A13: 序号 | B13: 记账凭证 | H13: 销售合同/销售订单 | J13: 出库单 | N13: 仓库保管员 | O13: 发货审批人 | P13: 运输单 | U13: 签收单 | AB13: 发票 | AG13: …… | AI13: 其他支持性文件或说明 | AJ13: 索引号 | AK13: 是否异常
B14: 客户名称 | C14: 日期 | D14: 编号 | E14: 品名 | F14: 数量 | G14: 金额 | H14: 日期 | I14: 合同号/订单号 | J14: 日期 | K14: 编号 | L14: 品名 | M14: 数量 | P14: 日期 | Q14: 编号 | R14: 运输数量 | S14: 运输公司 | T14: 运输地址 | U14: 日期 | V14: 品名 | W14: 数量 | X14: 金额 | Y14: 签收人 | Z14: 盖章类型 | AA14: 盖章单位 | AB14: 日期 | AC14: 编号 | AD14: 品名 | AE14: 数量 | AF14: 金额 | AG14: …… | AH14: ……
A37: 合计 | G37: =SUM(G15:G36) -> 0 | X37: =SUM(X15:X36) -> 0 | AF37: =SUM(AF15:AF36) -> 0
A38: 本期发生额
A39: 检查比例 | G39: =G37/G38 -> #DIV/0!
A40: 四、审计说明：
A41: 1.如果检查比例较低应扩大检查样本量或说明原因
A44: 五、审计结论：
A48: 提示1：项目组应根据被审计单位业务特点确定应检查的收入确认依据以及检查要点，例如出口收入确认依据一般还包括报关单、提单等，工程施工收入确认依据一般包括进度审核单、竣工验收报告等。必要时，还应记录不同证据时间逻辑一致性检查。
A49: 提示2：根据《中国注册会计师审计准则问题解答第18号——识别和应对第三方配合实施财务舞弊》，项目组在检查收入发生时关注第三方配合虚假销售交易涉及的存货实物、交易单证票据和资金流转；例如，在虚假收入交易中的资金流转过程可能如下：
A50: （1）被审计单位通过虚假交易或虚增交易金额套取自有资金，或者为关联方违规提供担保、由该关联方取得金融机构借款，或者由关联方提供资金（参见《中国注册会计师审计准则问题解答第4号——收入确认》）。
A51: （2）虚假交易对手或关联方将资金支付给被审计单位“客户”；为增加隐蔽性，也可能先将资金支付给“过桥”方，再由“过桥”方支付给“客户”。
A52: （3）“客户”向被审计单位支付货款，形成虚假销售交易的资金闭环。

Sheet 营业收入完整性检查表D4-15
A1: 致同会计师事务所
A2: 营业收入完整性检查表
A3: =底稿目录!A2 -> 被审计单位： | G3: =底稿目录!A4 -> 编制人： | L3: =底稿目录!A5 -> 编制日期： | P3: 索引号： | Q3: =底稿目录!F5 -> D4-15
A4: =底稿目录!A3 -> 会计期间：202X年度 | G4: =底稿目录!A6 -> 复核人： | L4: =底稿目录!A7 -> 复核日期： | P4: 页次：
A5: 一、审计目标：
A6: 所有应当记录的营业收入均已记录，所有应当包括在财务报表中的相关披露均已包括。
A7: 二、审计过程
A8: 1.在报告期内选择一个重要时期，测试收入确认依据的资料文件（如发货单、验收单等）
A9: 2.选择大的或者异常的项目进行测试（如果收入完整性评估为高风险，则应当采用抽样的方式）。
A10: 3.检查每个所选项目的单证，并追查到交易记录（如，销售日记账）。
A11: 序号 | B11: 发货单 | G11: 发票 | L11: 记账凭证 | Q11: 所载信息是否一致√(X)
B12: 日期 | C12: 编号 | D12: 品名 | E12: 数量 | F12: 金额 | G12: 日期 | H12: 编号 | I12: 品名 | J12: 数量 | K12: 金额 | L12: 日期 | M12: 编号 | N12: 品名 | O12: 数量 | P12: 金额
A26: 三、审计说明：
A30: 四、审计结论：

Sheet 出口收入电子口岸系统核对D4-16
A1: 致同会计师事务所
A2: 出口收入电子口岸系统检查
A3: =底稿目录!A2 -> 被审计单位： | E3: =底稿目录!A4 -> 编制人： | H3: =底稿目录!A5 -> 编制日期： | J3: 索引号： | K3: =底稿目录!F6 -> D4-16
A4: =底稿目录!A3 -> 会计期间：202X年度 | E4: =底稿目录!A6 -> 复核人： | H4: =底稿目录!A7 -> 复核日期： | J4: 页 次：
A5: 一、审计目标：
A6: 1.利润表中记录的营业收入已发生，且与被审计单位有关；2.与营业收入有关的金额及其他数据已恰当记录，相关披露已得到恰当计量和描述；
A7: 3.与营业收入有关的交易和事项已记录于正确的会计期间。
A8: 二、审计过程：
A9: 1.……
A11: 账面出口收入金额 | B11: 电子口岸系统 | G11: 免抵退税申报数据
B12: 期间 | C12: 结关金额 | D12: 差异 | E12: 原因 | F12: 索引 | G12: 期间 | H12: 申报外销收入 | I12: 差异 | J12: 原因 | K12: 索引
D13: =C13-A13 -> 0 | I13: =H13-F13 -> 0
A16: 三、审计说明：
A20: 四、审计结论：

Sheet 营业收入截止测试（账到单据）D4-17
A1: 致同会计师事务所
A2: 营业收入截止测试（账到单据）
A3: =底稿目录!A2 -> 被审计单位： | D3: =底稿目录!A4 -> 编制人： | G3: =底稿目录!A5 -> 编制日期： | J3: 索引号： | K3: =底稿目录!F7 -> D4-17
A4: =底稿目录!A3 -> 会计期间：202X年度 | D4: =底稿目录!A6 -> 复核人： | G4: =底稿目录!A7 -> 复核日期： | J4: 页次：
A5: 一、审计目标
A6: 确认与营业收入有关事项已记录于正确的会计期间。
A7: 二、审计过程
A8: 1.获取报表日前（______）天、后（______）天，且金额大于______元收入记账凭证与发货单（或验收单、出库单等）核对确认收入是否记入了恰当的期间；
A9: 2.……
A10: 提示：如果存在跨期舞弊风险或者所检查样本中发现有跨期的，应扩大测试期间和样本，甚至可以考虑将截止测试期间延长至审计报告日。同时考虑是否存在内控缺陷。
A11: 记账凭证 | F11: 发货单 | K11: 是否跨期
A12: 日期 | B12: 编号 | C12: 品名 | D12: 数量 | E12: 金额 | F12: 日期 | G12: 编号 | H12: 品名 | I12: 数量 | J12: 金额 | K12: √（×）
A24: 截止日期：202X年12月31日
A36: 三、审计说明
A40: 四、审计结论
A42: 提示1：本表适用于对“以发货单为确认收入时点”的被审计单位的截止测试，项目组在使用模板时，请根据企业的收入确认政策修改或调整。
A43: 提示2：如果存在跨期舞弊风险或者所检查样本中发现有跨期的，应扩大测试期间和样本，考虑将截止测试期间延长至审计报告日。同时考虑是否存在内控缺陷。

Sheet 营业收入截止测试（单据到账）D4-18
A1: 致同会计师事务所
A2: 营业收入截止测试（单据到账）
A3: =底稿目录!A2 -> 被审计单位： | D3: =底稿目录!A4 -> 编制人： | G3: =底稿目录!A5 -> 编制日期： | J3: 索引号： | K3: =底稿目录!F8 -> D4-18
A4: =底稿目录!A3 -> 会计期间：202X年度 | D4: =底稿目录!A6 -> 复核人： | G4: =底稿目录!A7 -> 复核日期： | J4: 页次：
A5: 一、审计目标
A6: 确认与营业收入有关事项已记录于正确的会计期间。
A7: 二、审计过程
A8: 1.获取报表日前（______）天、后（______）天，且金额大于______元发货单（或验收单、出库单等）与收入记账凭证核对确认收入是否记入了恰当的期间；
A9: 2.……
A10: 提示：如果存在跨期舞弊风险或者所检查样本中发现有跨期的，应扩大测试期间和样本，甚至可以考虑将截止测试期间延长至审计报告日。同时考虑是否存在内控缺陷。
A11: 发货单 | F11: 记账凭证 | K11: 是否跨期
A12: 日期 | B12: 编号 | C12: 品名 | D12: 数量 | E12: 金额 | F12: 日期 | G12: 编号 | H12: 品名 | I12: 数量 | J12: 金额 | K12: √（×）
A24: 截止日期：202X年12月31日
A36: 三、审计说明
A40: 四、审计结论
A42: 提示1：本表适用于对“以发货单为确认收入时点”的被审计单位的截止测试，项目组在使用模板时，请根据企业的收入确认政策修改或调整。
A43: 提示2：如果存在跨期舞弊风险或者所检查样本中发现有跨期的，应扩大测试期间和样本，考虑将截止测试期间延长至审计报告日。同时考虑是否存在内控缺陷。

Sheet 销售折扣与折让检查D4-19
A1: 致同会计师事务所
A2: 销售折扣与折让检查
A3: =底稿目录!A2 -> 被审计单位： | E3: =底稿目录!A4 -> 编制人： | I3: =底稿目录!A5 -> 编制日期： | N3: 索引号： | O3: =底稿目录!F9 -> D4-19
A4: =底稿目录!A3 -> 会计期间：202X年度 | E4: =底稿目录!A6 -> 复核人： | I4: =底稿目录!A7 -> 复核日期： | N4: 页 次：
A5: 一、审计目标
A6: 与营业收入有关的金额及其他数据已恰当记录，相关披露已得到恰当计量和描述。
A7: 二、审计过程
A8: 1.取得被审计单位经授权批准的有关折扣与折让的规定和文件资料，检查发生的折扣或折让是否符合相关规定并经授权批准。
A9: 2.……
A11: 客户名称 | B11: 折扣或折让类型 | C11: 收入金额 | D11: 折扣或折让金额 | E11: 折扣或折让比例 | F11: 折扣或折让 原因 | G11: 记账凭证 | M11: 审批单 | O11: 备注
G12: 日期 | H12: 编号 | I12: 会计科目 | J12: 明细科目 | K12: 借方金额 | L12: 贷方金额 | M12: 日期 | N12: 审批人
P13: 价格折扣
P14: 现金折扣
P15: 实物返利
P16: 销售折让
A24: 三、审计说明
A28: 四、审计结论
A30: 提示：企业应当基于返利的形式和合同条款的约定，考虑相关条款安排是否会导致企业未来需要向客户提供可明确区分的商品或服务，在此基础上判断相关返利属于可变对价还是提供给客户的重大权利。一般而言，对基于客户采购情况等给予的现金返利，企业应当按照可变对价原则进行会计处理；对基于客户一定采购数量的实物返利或仅适用于未来采购的价格折扣，企业应当按照附有额外购买选择权的销售进行会计处理，评估该返利是否构成一项重大权利，以确定是否将其作为单项履约义务并分摊交易对价。《监管规则适用指引—会计类第2号》

Sheet 销售退货检查表 D4-20
A1: 致同会计师事务所
A2: 销售退货检查表
A3: =底稿目录!A2 -> 被审计单位： | F3: =底稿目录!A4 -> 编制人： | J3: =底稿目录!A5 -> 编制日期： | N3: 索引号： | O3: =底稿目录!F10 -> D4-20
A4: =底稿目录!A3 -> 会计期间：202X年度 | F4: =底稿目录!A6 -> 复核人： | J4: =底稿目录!A7 -> 复核日期： | N4: 页次：
A5: 一、审计目标:
A6: 确认与营业收入有关事项已记录于正确的会计期间。
A7: 二、审计过程：
A8: 1.产品退货政策
A11: 2.退货总体情况
A12: 本期退货金额 元，占本期销售收入的 %。按照客户类别/客户性质/产品类别分类统计如下：
A13: 分类 | B13: 本年度 | E13: 上年度
B14: 退货金额 | C14: 收入金额 | D14: 比例 | E14: 退货金额 | F14: 收入金额 | G14: 比例
A15: 贸易商 | D15: =B15/C15 -> #DIV/0! | G15: =E15/F15 -> #DIV/0!
A16: 终端用户 | D16: =B16/C16 -> #DIV/0! | G16: =E16/F16 -> #DIV/0!
A17: 合计 | B17: =B16+B15 -> 0 | C17: =C16+C15 -> 0 | D17: =B17/C17 -> #DIV/0! | E17: =E16+E15 -> 0 | F17: =F16+F15 -> 0 | G17: =E17/F17 -> #DIV/0!
A19: 3.评估产品退货计提比例是否合理
A20: （1)历史退货情况
A22: （2）……
A23: 4.重新测算产品退货金额
A24: 产品名称 | B24: 计提基数 | C24: 计提比例 | D24: 应计提金额 | E24: 账面已计提金额 | F24: 差异金额 | G24: 差异原因
D25: =B25*C25 -> 0
D26: =B26*C26 -> 0
D27: =B27*C27 -> 0
D28: =B28*C28 -> 0
D29: =B29*C29 -> 0
A31: 5.检查本期产品退货情况
A32: 记账凭证 | H32: 退货单 | M32: 是否涉及诉讼 | N32: 是否异常 | O32: 索引号
A33: 日期 | B33: 编号 | C33: 业务内容 | D33: 科目名称 | E33: 二级明细 | F33: 借方金额 | G33: 贷方金额 | H33: 客户名称 | I33: 产品名称 | J33: 退货数量 | K33: 退货金额 | L33: 退货原因
A37: 6.检查期后产品退货情况
A38: 记账凭证 | H38: 退货单 | M38: 是否涉及诉讼 | N38: 是否异常 | O38: 索引号
A39: 日期 | B39: 编号 | C39: 业务内容 | D39: 科目名称 | E39: 二级明细 | F39: 借方金额 | G39: 贷方金额 | H39: 客户名称 | I39: 产品名称 | J39: 退货数量 | K39: 退货金额 | L39: 退货原因
A43: 检查内容说明：
A44: （1）销售退回的原因及合理性判断：
A45: （2）销售退回审批手续是否完备；
A46: （3）相应的主营业务成本是否结转；
A47: （4）退货会计处理是否正确；
A48: （5）是否涉及跨期；
A49: 三、审计说明：
A53: 四、审计结论：
