Workbook

Sheet 关联方销售情况及价格分析D4-21
A1: 致同会计师事务所
A2: 关联方销售收入情况及价格公允性分析
A3: =[4]底稿目录!$A$2 -> 被审计单位： | E3: =[4]底稿目录!$A$4 -> 编制人： | H3: =[4]底稿目录!$A$5 -> 编制日期： | M3: 索引号： | N3: D4-21
A4: =[4]底稿目录!$A$3 -> 会计期间：202X年度 | E4: =[4]底稿目录!$A$6 -> 复核人： | H4: =[4]底稿目录!$A$7 -> 复核日期： | M4: 页 次：
A5: 一、审计目标：
A6: 1.利润表中记录的营业收入已发生，且与被审计单位有关，已记录于恰当的账户。2.所有应当记录的营业收入均已记录，所有应当包括在财务报表中的相关披露均已包括。
A7: 3.与营业收入有关的金额及其他数据已恰当记录，相关披露已得到恰当计量和描述。
A8: 二、审计过程：
A9: 1.调查及标明向关联方销售的情况及，记录其交易品种、价格、数量、金额和比例，并记录占总销售收入的比例。
A10: 2.确定已取得关联方交易披露数据及确定跟关联交易工作底稿相符。
A11: 3.获取关联方交易定价政策，检查定价公允性。
A12: 4.比较关联方交易主要产品价格与同类产品非关联方销售平均单价、可比公允价值的差异，分析合理性。
A13: 5.……
A14: 202X年：
A15: 关联方客户名称 | B15: 关联关系 | C15: 产品名称 | D15: 销售数量 | E15: 销售额 | F15: 销售额占同类产品销售额比例 | G15: 平均单价 | H15: 非关联方销售平均单价 | I15: 差异率 | J15: 可比公允价格 | K15: 差异率 | L15: 上年度销售额占同类产品销售额比例 | M15: 上年度销售平均单价 | N15: 备注
I16: =(G16-H16)/H16 -> #DIV/0! | K16: =(G16-J16)/J16 -> #DIV/0! | O16: 勿删、勿改
I17: =(G17-H17)/H17 -> #DIV/0! | K17: =(G17-J17)/J17 -> #DIV/0! | O17: 实际控制人
I18: =(G18-H18)/H18 -> #DIV/0! | K18: =(G18-J18)/J18 -> #DIV/0! | O18: 控股股东
I19: =(G19-H19)/H19 -> #DIV/0! | K19: =(G19-J19)/J19 -> #DIV/0! | O19: 控股股东、实际控制人的附属企业
I20: =(G20-H20)/H20 -> #DIV/0! | K20: =(G20-J20)/J20 -> #DIV/0! | O20: 持有5%以上股份的法人或其他组织
I21: =(G21-H21)/H21 -> #DIV/0! | K21: =(G21-J21)/J21 -> #DIV/0! | O21: 联营企业
I22: =(G22-H22)/H22 -> #DIV/0! | K22: =(G22-J22)/J22 -> #DIV/0! | O22: 合营企业
I23: =(G23-H23)/H23 -> #DIV/0! | K23: =(G23-J23)/J23 -> #DIV/0! | O23: 董高监等关键管理人员
I24: =(G24-H24)/H24 -> #DIV/0! | K24: =(G24-J24)/J24 -> #DIV/0! | O24: 其他关联方
I25: =(G25-H25)/H25 -> #DIV/0! | K25: =(G25-J25)/J25 -> #DIV/0!
I26: =(G26-H26)/H26 -> #DIV/0! | K26: =(G26-J26)/J26 -> #DIV/0!
I27: =(G27-H27)/H27 -> #DIV/0! | K27: =(G27-J27)/J27 -> #DIV/0!
I28: =(G28-H28)/H28 -> #DIV/0! | K28: =(G28-J28)/J28 -> #DIV/0!
I29: =(G29-H29)/H29 -> #DIV/0! | K29: =(G29-J29)/J29 -> #DIV/0!
I30: =(G30-H30)/H30 -> #DIV/0! | K30: =(G30-J30)/J30 -> #DIV/0!
A31: 三、审计说明：
A34: 四、审计结论：
