Workbook

Sheet 底稿目录
A1: 底稿开列时，可先在以下单元格填写有关内容，以便其他底稿引用有关数据：
A2: 被审计单位： | D2: 序号 | E2: 内容 | F2: 索引号
A3: 会计期间：202X年度 | D3: 1 | E3: 其他业务毛利率分析表 | F3: D4-33
A4: 编制人： | D4: 2 | E4: 其他业务收入合同测算表 | F4: D4-34
A5: 编制日期： | D5: 3 | E5: 其他业务收入检查表 | F5: D4-35
A6: 复核人： | D6: 4 | E6: 其他业务收入截止性测试 | F6: D4-36
A7: 复核日期：
A9: 关于工作底稿与审计程序索引号对应的说明
A10: 1.编制的审计工作底稿应与审计程序对应。审计项目组应根据被审计单位实际情况和风险评估情况在实质性程序表中裁剪、修改或增加审计程序，根据实际执行的审计程序完成相应审计工作底稿，编制的工作底稿中应按自然顺序依次编制索引号，并通过唯一的索引号将与实质性程序表中的程序对应关联（即将工作底稿的索引号填入实质性程序表中的底稿索引号列）。
A14: 2.获取的支持性证据应与审计底稿或程序对应。审计项目组在完成底稿时获取的支持性证据应根据底稿索引号编制下一级按自然顺序排序的索引号（如D1-2-1、D1-2-2、……），并在底稿中说明引用的支持性证据、关联索引号。
A17: 3.工作底稿索引号的编码规则：实质性程序索引号按循环从“D”到“N”,循环内账户以顺序号排列，模板中底稿索引号按账户顺序+自然数顺序（即模板中索引号按二级自然顺序排列，如D1-1、D1-2、D1-3、……D1-N）。

Sheet 其他业务毛利率分析表D4-33
A1: 致同会计师事务所
A2: 其他业务毛利率分析表
A3: =底稿目录!A2 -> 被审计单位： | F3: =底稿目录!A4 -> 编制人： | I3: =底稿目录!A5 -> 编制日期： | L3: 索引号： | M3: =底稿目录!F3 -> D4-33
A4: =底稿目录!A3 -> 会计期间：202X年度 | F4: =底稿目录!A6 -> 复核人： | I4: =底稿目录!A7 -> 复核日期： | L4: 页次：
A5: 一、审计目标：
A6: 1.利润表中记录的其他业务收入已发生，且与被审计单位有关，已记录于恰当的账户。
A7: 2.所有应当记录的其他业务收入均已记录，所有应当包括在财务报表中的相关披露均已包括。
A8: 3.与其他业务收入有关的金额及其他数据已恰当记录，相关披露已得到恰当计量和描述。
A9: 二、审计过程：
A10: 月份 | B10: 合计 | E10: 出租固定资产 | H10: 出租无形资产 | K10: 销售材料
B11: 收入 | C11: 成本 | D11: 毛利率 | E11: 收入 | F11: 成本 | G11: 毛利率 | H11: 收入 | I11: 成本 | J11: 毛利率 | K11: 收入 | L11: 成本 | M11: 毛利率
A12: 1 | B12: =E12+H12+K12 -> 0 | C12: =F12+I12+L12 -> 0 | D12: =(B12-C12)/B12 -> #DIV/0! | G12: =(E12-F12)/E12 -> #DIV/0! | J12: =(H12-I12)/H12 -> #DIV/0! | M12: =(K12-L12)/K12 -> #DIV/0!
A13: 2 | B13: =E13+H13+K13 -> 0 | C13: =F13+I13+L13 -> 0 | D13: =(B13-C13)/B13 -> #DIV/0! | G13: =(E13-F13)/E13 -> #DIV/0! | J13: =(H13-I13)/H13 -> #DIV/0! | M13: =(K13-L13)/K13 -> #DIV/0!
A14: 3 | B14: =E14+H14+K14 -> 0 | C14: =F14+I14+L14 -> 0 | D14: =(B14-C14)/B14 -> #DIV/0! | G14: =(E14-F14)/E14 -> #DIV/0! | J14: =(H14-I14)/H14 -> #DIV/0! | M14: =(K14-L14)/K14 -> #DIV/0!
A15: 4 | B15: =E15+H15+K15 -> 0 | C15: =F15+I15+L15 -> 0 | D15: =(B15-C15)/B15 -> #DIV/0! | G15: =(E15-F15)/E15 -> #DIV/0! | J15: =(H15-I15)/H15 -> #DIV/0! | M15: =(K15-L15)/K15 -> #DIV/0!
A16: 5 | B16: =E16+H16+K16 -> 0 | C16: =F16+I16+L16 -> 0 | D16: =(B16-C16)/B16 -> #DIV/0! | G16: =(E16-F16)/E16 -> #DIV/0! | J16: =(H16-I16)/H16 -> #DIV/0! | M16: =(K16-L16)/K16 -> #DIV/0!
A17: 6 | B17: =E17+H17+K17 -> 0 | C17: =F17+I17+L17 -> 0 | D17: =(B17-C17)/B17 -> #DIV/0! | G17: =(E17-F17)/E17 -> #DIV/0! | J17: =(H17-I17)/H17 -> #DIV/0! | M17: =(K17-L17)/K17 -> #DIV/0!
A18: 7 | B18: =E18+H18+K18 -> 0 | C18: =F18+I18+L18 -> 0 | D18: =(B18-C18)/B18 -> #DIV/0! | G18: =(E18-F18)/E18 -> #DIV/0! | J18: =(H18-I18)/H18 -> #DIV/0! | M18: =(K18-L18)/K18 -> #DIV/0!
A19: 8 | B19: =E19+H19+K19 -> 0 | C19: =F19+I19+L19 -> 0 | D19: =(B19-C19)/B19 -> #DIV/0! | G19: =(E19-F19)/E19 -> #DIV/0! | J19: =(H19-I19)/H19 -> #DIV/0! | M19: =(K19-L19)/K19 -> #DIV/0!
A20: 9 | B20: =E20+H20+K20 -> 0 | C20: =F20+I20+L20 -> 0 | D20: =(B20-C20)/B20 -> #DIV/0! | G20: =(E20-F20)/E20 -> #DIV/0! | J20: =(H20-I20)/H20 -> #DIV/0! | M20: =(K20-L20)/K20 -> #DIV/0!
A21: 10 | B21: =E21+H21+K21 -> 0 | C21: =F21+I21+L21 -> 0 | D21: =(B21-C21)/B21 -> #DIV/0! | G21: =(E21-F21)/E21 -> #DIV/0! | J21: =(H21-I21)/H21 -> #DIV/0! | M21: =(K21-L21)/K21 -> #DIV/0!
A22: 11 | B22: =E22+H22+K22 -> 0 | C22: =F22+I22+L22 -> 0 | D22: =(B22-C22)/B22 -> #DIV/0! | G22: =(E22-F22)/E22 -> #DIV/0! | J22: =(H22-I22)/H22 -> #DIV/0! | M22: =(K22-L22)/K22 -> #DIV/0!
A23: 12 | B23: =E23+H23+K23 -> 0 | C23: =F23+I23+L23 -> 0 | D23: =(B23-C23)/B23 -> #DIV/0! | G23: =(E23-F23)/E23 -> #DIV/0! | J23: =(H23-I23)/H23 -> #DIV/0! | M23: =(K23-L23)/K23 -> #DIV/0!
A24: 合 计 | B24: =SUM(B12:B23) -> 0 | C24: =SUM(C12:C23) -> 0 | D24: =(B24-C24)/B24 -> #DIV/0! | E24: =SUM(E12:E23) -> 0 | F24: =SUM(F12:F23) -> 0 | G24: =(E24-F24)/E24 -> #DIV/0! | H24: =SUM(H12:H23) -> 0 | I24: =SUM(I12:I23) -> 0 | J24: =(H24-I24)/H24 -> #DIV/0! | K24: =SUM(K12:K23) -> 0 | L24: =SUM(L12:L23) -> 0 | M24: =(K24-L24)/K24 -> #DIV/0!
A25: 上年数 | B25: =E25+H25+K25 -> 0 | C25: =F25+I25+L25 -> 0 | D25: =(B25-C25)/B25 -> #DIV/0! | G25: =(E25-F25)/E25 -> #DIV/0! | J25: =(H25-I25)/H25 -> #DIV/0! | M25: =(K25-L25)/K25 -> #DIV/0!
A26: 变动额 | B26: =B24-B25 -> 0 | C26: =C24-C25 -> 0 | D26: =D24-D25 -> #DIV/0! | E26: =E24-E25 -> 0 | F26: =F24-F25 -> 0 | G26: =G24-G25 -> #DIV/0! | H26: =H24-H25 -> 0 | I26: =I24-I25 -> 0 | ... M26: =M24-M25 -> #DIV/0!
A27: 变动比例 | B27: =IF(AND(B25=0,B24=0),0,IF(B25<=0,"不适用",B26/B25)) -> 0 | C27: =IF(AND(C25=0,C24=0),0,IF(C25<=0,"不适用",C26/C25)) -> 0 | D27: =IF(AND(D25=0,D24=0),0,IF(D25<=0,"不适用",D26/D25)) -> #DIV/0! | E27: =IF(AND(E25=0,E24=0),0,IF(E25<=0,"不适用",E26/E25)) -> 0 | F27: =IF(AND(F25=0,F24=0),0,IF(F25<=0,"不适用",F26/F25)) -> 0 | G27: =IF(AND(G25=0,G24=0),0,IF(G25<=0,"不适用",G26/G25)) -> #DIV/0! | H27: =IF(AND(H25=0,H24=0),0,IF(H25<=0,"不适用",H26/H25)) -> 0 | I27: =IF(AND(I25=0,I24=0),0,IF(I25<=0,"不适用",I26/I25)) -> 0 | ... M27: =IF(AND(M25=0,M24=0),0,IF(M25<=0,"不适用",M26/M25)) -> #DIV/0!
A28: 三、审计说明：
A30: 四、审计结论：

Sheet 其他业务收入合同测算表D4-34
A1: 致同会计师事务所
A2: 其他业务收入合同测算表
A3: =底稿目录!A2 -> 被审计单位： | E3: =底稿目录!A4 -> 编制人： | H3: =底稿目录!A5 -> 编制日期： | J3: 索引号： | K3: =底稿目录!F4 -> D4-34
A4: =底稿目录!A3 -> 会计期间：202X年度 | E4: =底稿目录!A6 -> 复核人： | H4: =底稿目录!A7 -> 复核日期： | J4: 页次：
A5: 一、审计目标：
A6: 1.利润表中记录的其他业务收入已发生，且与被审计单位有关，已记录于恰当的账户。
A7: 2.所有应当记录的其他业务收入均已记录，所有应当包括在财务报表中的相关披露均已包括
A8: 3.与其他业务收入有关的金额及其他数据已恰当记录，相关披露已得到恰当计量和描述
A9: 4.与其他业务收入有关的交易和事项已记录于正确的会计期间。
A10: 二、审计过程：
A11: 1.房屋租赁业务（其他租赁可参照）
A12: 序号 | B12: 承租方 | C12: 租赁期间 | D12: 租赁面积 | E12: 合同单价 | F12: 合同索引 | G12: 本期实际 租赁月数 | H12: 本期应计收入 | I12: 本期实计收入 | J12: 差异 | K12: 索引号
A13: 1 | J13: =H13-I13 -> 0
A14: 2 | J14: =H14-I14 -> 0
A15: 3 | J15: =H15-I15 -> 0
A16: 4 | J16: =H16-I16 -> 0
A17: 5 | J17: =H17-I17 -> 0
A18: 2.咨询业务
A19: 序号 | B19: 委托方 | D19: 咨询项目 | E19: 委托期限 | F19: 合同金额 | G19: 合同索引 | H19: 本期应计收入 | I19: 本期实计收入 | J19: 差异 | K19: 索引号
A20: 1 | J20: =H20-I20 -> 0
A21: 2 | J21: =H21-I21 -> 0
A22: 3 | J22: =H22-I22 -> 0
A23: 4 | J23: =H23-I23 -> 0
A24: 5 | J24: =H24-I24 -> 0
A25: 三、审计说明：
A28: 四、审计结论：

Sheet 其他业务收入检查表D4-35
A1: 致同会计师事务所
A2: 其他业务收入的检查表
A3: =底稿目录!A2 -> 被审计单位： | D3: =底稿目录!A4 -> 编制人： | G3: =底稿目录!A5 -> 编制日期： | P3: 索引号： | Q3: =底稿目录!F5 -> D4-35
A4: =底稿目录!A3 -> 会计期间：202X年度 | D4: =底稿目录!A6 -> 复核人： | G4: =底稿目录!A7 -> 复核日期： | P4: 页次：
A5: 一、审计目标：
A6: 1.利润表中记录的其他业务收入已发生，且与被审计单位有关，已记录于恰当的账户。2.与其他业务收入有关的金额及其他数据已恰当记录，相关披露已得到恰当计量和描述。
A7: 二、样本选取标准与规模：
A8: 测试总体： | B8: 如借方发生额所有凭证共XX笔金额XX、贷方发生额所有凭证共XX笔金额XX | F8: 特定样本： | G8: XX金额以上（大额）、关联方/关联交易形成的款项、XX异常款项全部测试，共XX笔；
A9: 抽样总体： | B9: 测试总体扣除特定样本以外的样本，共XX笔、金额XX | F9: 确定的抽样样本量： | G9: 抽取XX笔（如果使用了样本计算器计算样本量，样本量计算过程见<XX>底稿）
A10: 抽样方法： | B10: 随机选样/系统选样/货币单元抽样/随意选样（非统计抽样适用） | F10: 抽样过程： | G10: 使用IDEA（XX抽样工具）选择XX数量、金额XX的样本进行测试，抽样工具中的样本选择过程和结果见<XX>底稿
A11: 三、测试：
A12: 测试内容说明：1.原始凭证是否齐全；2.记账凭证与原始凭证是否相符；3.账务处理是否正确；4.是否记录于恰当的会计期间；5.……
A13: 日期 | B13: 凭证编号 | C13: 业务内容 | D13: 对方科目 | E13: 明细科目 | F13: 金额 | G13: 支持性文件 | H13: 核对内容 | O13: 索引号 | P13: 是否异常 | Q13: 备注说明
H14: 1 | I14: 2 | J14: 3 | K14: 4 | L14: 5 | M14: 6
A26: 合计 | F26: =SUM(F15:F25) -> 0
A27: 本期发生额 | F27: ='其他业务毛利率分析表D4-33'!B24 -> 0
A28: 检查比例 | F28: =F26/F27 -> #DIV/0!
A29: 四、审计说明：
A33: 五、审计结论：

Sheet 其他业务收入截止性测试D4-36
A1: 致同会计师事务所
A2: 其他业务收入截止性测试
A3: =底稿目录!A2 -> 被审计单位： | E3: =底稿目录!A4 -> 编制人： | H3: =底稿目录!A5 -> 编制日期： | J3: 索引号： | K3: =底稿目录!F6 -> D4-36
A4: =底稿目录!A3 -> 会计期间：202X年度 | E4: =底稿目录!A6 -> 复核人： | H4: =底稿目录!A7 -> 复核日期： | J4: 页次：
A5: 一、审计目标
A6: 确认与其他业务收入有关事项已记录于正确的会计期间。
A7: 二、审计过程
A8: 1.获取报表日前（______）天、后（______）天，且金额大于______元收入记账凭证与发货单（或验收单、出库单等）核对确认
A9: 收入是否记入了恰当的期间；
A10: 2.获取报表日前（______）天、后（______）天，且金额大于______元发货单（或验收单、出库单等）与收入记账凭证核对确认
A11: 收入是否记入了恰当的期间；
A12: 如果存在跨期舞弊风险或者所检查样本中发现有跨期的，应扩大测试期间和样本，甚至可以考虑将截止测试期间延长至审计报告日。同时考虑是否存在内控缺陷。
A13: （一）账到单据
A14: 记账凭证 | F14: 发货单（或验收单、出库单等） | K14: 是否跨期√(×)
A15: 日期 | B15: 编号 | C15: 品名 | D15: 数量 | E15: 金额 | F15: 日期 | G15: 编号 | H15: 品名 | I15: 数量 | J15: 金额
A24: 截止日期：202X年12月31日
A33: （二）单据到账
A34: 发货单（或验收单、出库单等） | F34: 记账凭证 | K34: 是否跨期
A35: 日期 | B35: 编号 | C35: 品名 | D35: 数量 | E35: 金额 | F35: 日期 | G35: 编号 | H35: 品名 | I35: 数量 | J35: 金额 | K35: √（×）
A44: 截止日期：202X年12月31日
A53: 三、审计说明：
A56: 四、审计结论：
A58: 提示1：本表适用于对“以发货单为确认收入时点”的被审计单位的截止测试，项目组在使用模板时，请根据企业的收入确认政策修改或调整。
A59: 提示2：如果存在跨期舞弊风险或者所检查样本中发现有跨期的，应扩大测试期间和样本，甚至可以考虑将截止测试期间延长至审计报告日。同时考虑是否存在内控缺陷。
