Workbook

Sheet 底稿目录
A1: 底稿开列时，可先在以下单元格填写有关内容，以便其他底稿引用有关数据：
A2: 被审计单位：
A3: 截止日：202X年12月31日 | D3: 序号 | E3: 内容 | F3: 索引号 | G3: 备注
A4: 编制人： | E4: 固定资产审计程序表 | F4: H1A
A5: 编制日期： | D5: 1 | E5: 审定表 | F5: H1-1
A6: 复核人： | D6: =D5+1 -> 2 | E6: 附注披露信息（上市公司） | G6: 无需打印
A7: 复核日期： | D7: =D6+1 -> 3 | E7: 附注披露信息（国有企业） | G7: 无需打印
A8: 固定资产类别设置（以下内容请根据实际情况修改）： | D8: =D7+1 -> 4 | E8: 明细表 | F8: H1-2
A9: 房屋及建筑物 | D9: =D8+1 -> 5 | E9: 调整分录汇总 | F9: H1-3
A10: 机器设备 | D10: =D9+1 -> 6 | E10: 闲置检查表 | F10: H1-4
A11: 运输设备 | D11: =D10+1 -> 7 | E11: 会计政策估计检查表 | F11: H1-5
A12: 办公设备 | D12: =D11+1 -> 8 | E12: 分析表 | F12: H1-6
A13: 其他设备 | D13: =D12+1 -> 9 | E13: 增加检查表 | F13: H1-7
A14: …… | D14: =D13+1 -> 10 | E14: 减少检查表 | F14: H1-8
D15: =D14+1 -> 11 | E15: 监盘计划 | F15: H1-9
A16: 关于工作底稿与审计程序索引号对应的说明 | D16: =D15+1 -> 12 | E16: 盘点检查表 | F16: H1-10
A17: 1.编制的审计工作底稿应与审计程序对应。审计项目组应根据被审计单位实际情况和风险评估情况在实质性程序表中裁剪、修改或增加审计程序，根据实际执行的审计程序完成相应审计工作底稿，编制的工作底稿中应按自然顺序依次编制索引号，并通过唯一的索引号将与实质性程序表中的程序对应关联（即将工作底稿的索引号填入实质性程序表中的底稿索引号列）。 | D17: =D16+1 -> 13 | E17: 监盘小结 | F17: H1-11
D18: =D17+1 -> 14 | E18: 折旧测算表（不含减值）-直线法 | F18: H1-12
D19: =D18+1 -> 15 | E19: 折旧测算表（含减值） | F19: H1-12
D20: =D19+1 -> 16 | E20: 折旧测算表（多次减值） | F20: H1-12
A21: 2.获取的支持性证据应与审计底稿或程序对应。审计项目组在完成底稿时获取的支持性证据应根据底稿索引号编制下一级按自然顺序排序的索引号（如D1-2-1、D1-2-2、……），并在底稿中说明引用的支持性证据、关联索引号。 | D21: =D20+1 -> 17 | E21: 折旧分配分析表 | F21: H1-13
D22: =D21+1 -> 18 | E22: 减值测算表 | F22: H1-14
D23: =D22+1 -> 19 | E23: 可收回金额测试表 | F23: H1-15
A24: 3.工作底稿索引号的编码规则：实质性程序索引号按循环从“D”到“N”,循环内账户以顺序号排列，模板中底稿索引号按账户顺序+自然数顺序（即模板中索引号按二级自然顺序排列，如D1-1、D1-2、D1-3、……D1-N）。 | D24: =D23+1 -> 20 | E24: 房屋建筑物权属检查表 | F24: H1-16
D25: =D24+1 -> 21 | E25: 运输设备权属检查表 | F25: H1-17
D26: =D25+1 -> 22 | E26: 关联交易检查表 | F26: H1-18
D27: =D26+1 -> 23 | E27: 经营租出固定资产检查表 | F27: H1-19
D28: =D27+1 -> 24 | E28: 融资租出固定资产检查表 | F28: H1-20

Sheet 固定资产审计程序表H1A
A1: 致同会计师事务所
A2: 固定资产实质性程序表
A3: =底稿目录!A2 -> 被审计单位： | C3: =底稿目录!A4 -> 编制人： | E3: =底稿目录!A5 -> 编制日期： | I3: 索引号： | J3: H1A
A4: =底稿目录!A3 -> 截止日：202X年12月31日 | C4: =底稿目录!A6 -> 复核人： | E4: =底稿目录!A7 -> 复核日期： | I4: 页 次：
A5: 一、本账户涉及的科目
A6: 固定资产、累计折旧、减值准备
A7: 二、审计目标与认定的对应关系
A8: 审计目标 | G8: 财务报表的认定
A9: A. 资产负债表中记录的固定资产是存在的，且已记录于恰当的账户 | G9: 存在
A10: B. 所有应记录的固定资产均已记录，所有应当包括在财务报表中的相关披露均已包括 | G10: 完整性
A11: C. 记录的固定资产由被审计单位拥有或控制； | G11: 权利和义务
A12: D. 固定资产以恰当的金额包括在财务报表中，与之相关的计价或分摊调整已恰当记录，相关披露已得到恰当计量和描述 | G12: 准确性、计价和分摊
A13: E. 固定资产已被恰当地汇总或分解且表述清楚，相关披露在按照企业会计准则的编制基础下是相关的、可理解的 | G13: 列报
A14: 三、计划实施的实质性程序
A15: 序号 | B15: 审计程序 | C15: 程序分类 | D15: 财务报表的认定 | I15: 底稿索引号
D16: 存在 | E16: 完整性 | F16: 权利和 义务 | G16: 准确性、计价和分摊 | H16: 列报 | K16: 根据被审计单位实际情况和风险评估情况裁剪、修改或增加审计程序
A17: 1 | B17: 获取或编制固定资产的明细表，完成以下工作，并编制审定表 （1）复核加计是否正确，并与总账数和明细账合计数核对是否相符，期初余额与上期审定期末余额是否相符； （2）结合固定资产减值准备科目和报表数核对是否相符 （3）询问闲置资产或未入账资产处置情况（如有）。 | C17: 常规★ | D17: √ | E17: √ | G17: √ | I17: H1-1 /H1-2 /H1-4
A18: 2 | B18: 取得固定资产维修和保养的明细（如有），考虑执行以下程序：详细检查单个重大的固定资产，并复核相关支持性的文件，确定计入费用的项目是否合理。 | C18: 备选 | D18: √ | E18: √ | G18: √
A19: 3 | B19: 在使用手工编制、自定义信息报告、系统生成的非固定格式报告等由被审计单位生成的信息时，测试有关信息准确性和完整性，并考虑针对编制和维护由被审计单位生成的信息的相关控制实施控制测试，以评价该信息是否能够为实现审计目的提供基础。 | C19: 常规★ | E19: √ | G19: √ | I19: T1 / | K19: 可参见《审计手册》4.2.6，由被审计单位生成的信息可能是由系统生成的、或手工编制的、或二者兼而有之的方式生成的。例如，由被审计单位生成的信息可能包括： • 不涉及自定义的、由系统生成的报告（如，固定格式报告）； • 可能通过人工自定义的、由系统生成的报告，例如，（计算机）查询信息或特别定制的报告； • 手工编制的信息，例如，汇总信息的电子表格或用以支持分配、计算以及调节的电子表格； • 其他系统生成或手工编制的信息，例如，由被审计单位编制的客户发票； • 通过影印、拍摄、扫描或其他方式转换成电子形式的文件记录。
A20: 4 | B20: 对期初余额的审计，取得上期固定资产明细表、长期租赁资产（经营租出、融资租出）的明细表复核加计是否正确，与总账、明细账合计数是否相符； 重新测算期初累计折旧余额准确性；对单项金额重大资产，进行实地查看资产或检查支持性文件，其他必要追加的审计程序。（适用于首次承接） | C20: 备选 | D20: √ | E20: √ | F20: √ | G20: √ | K20: 由被审计单位生成的信息不包括： • 总分类账或明细分类账、试算平衡表、或经审计的财务报表； • 第三方（除了服务机构）的报表或报告，例如，原始银行对账单，或函证的回函； • 外部数据（例如，第三方发布的数据，如，定价来源）。
A21: 5 | B21: 关注会计政策、会计估计合理性、一贯性，关注其是否利用会计政策和会计估计及其变更操纵利润。必要时与同行业其他公司会计政策、会计估计进行对比，主要会计政策和估计包括： （1）固定资产的初始计量； （2）固定资产折旧/减值的政策和方法； （3）固定资产的后续支出（包括支出费用化和资本化）及终止确认。 | C21: 常规★ | D21: √ | E21: √ | G21: √ | I21: H1-5
A22: 6 | B22: 执行分析性程序，考虑识别需要执行额外程序的领域： （1）分析本期和上期固定资产净值占资产总额比例、当期计提折旧额、累计折旧及减值准备余额分别占固定资产原值比例是否异常； （2）分析固定资产原值与本期产品产量的比率（固定资产的规模及其变化是否与产能匹配）、并与以前年度对比； （3）分析租赁资产占相应资产的比例及本期与以前年度租赁收入情况（判断被审计单位对资产租赁收益的依赖程度及盈利能力的稳定性）； （4）分析维修费用与固定资产原值的比例等，并与以前年度对比。 | C22: 常规★ | D22: √ | E22: √ | G22: √ | I22: H1-6
A23: 7 | B23: 了解被审计单位的主要生产设备的名称、位置、建设及投产情况，与所生产产品种类的对应关系。将主要生产设备的产能与当期产量对比，判断是否存在异常迹象。 | C23: IPO/上市/新三板/重组/舞弊应对 | D23: √ | E23: √ | G23: √
A24: 8 | B24: 实地观察固定资产投入及运行情况、厂区员工人数以及车间生产情况，分析资产规模与产能的匹配性，开工情况与产量的匹配性；结合产能、产量、销量数据计算产能利用率（开工率），与同行业企业进行对比，分析变化原因及合理性。 | C24: IPO/上市/新三板/重组/舞弊应对 | D24: √ | E24: √ | G24: √
A25: 9 | B25: 检查本期新增的固定资产： （1）对于外购的固定资产，检查购置合同、发票、保险单、发运凭证等文件，检查其金额及会计处理是否正确；如果购买固定资产的价款超过正常信用条件延期支付，检查实质上是否具有融资性质，固定资产的成本是否以购买价款的现值为基础确定； （2）对于在建工程转入的固定资产，结合固定资产盘点程序，检查竣工决算、验收和移交报告是否正确，与在建工程相关的记录是否核对相符，借款费用资本化金额是否恰当；对已经在用或已经达到预定可使用状态但尚未办理竣工决算的固定资产，检查其是否已经暂估入账，并按规定计提折旧；检查资本性支出与收益性支出的划分是否恰当；竣工决算完成后，是否及时调整； （3）对于更新改造增加的固定资产，检查增加的固定资产原值是否真实，是否符合资本化条件，增计金额是否超过了该项固定资产的可收回金额；重新确定的剩余折旧年限是否恰当； （4）对于盘盈的固定资产，检查固定资产计价及确认的损益是否符合会计准则及相关规定； （5）关注固定资产是否存在弃置费用，如果存在弃置费用，检查弃置费用的估计方法和弃置费用现值的计算是否合理，会计处理是否正确。 | C25: 常规★ | D25: √ | E25: √ | F25: √ | G25: √ | I25: H1-7
A26: 10 | B26: 检查本期固定资产的处置： （1）结合固定资产清理科目，抽查固定资产账面转销额是否正确； （2）检查出售、盘亏、转让、报废或毁损的固定资产是否经授权批准、检查相关合同等，相关收益或损失已正确计算，并进行正确的会计处理； （3）检查因修理、更新改造而停止使用的固定资产的会计处理是否正确； | C26: 常规★ | D26: √ | E26: √ | G26: √ | I26: H1-8
A27: 11 | B27: 其他方式增加或减少的固定资产，考虑执行以下程序： （1）对于非货币性资产交换、债务重组、投资、投资者投入等交易方式取得或减少的有关长期资产，检查相关合同/协议，关注计价是否正确、移交手续是否办理以及会计处理是否正确。 （2）对于因清产核资、资产评估调增或调减有关长期资产价值的，检查有关清产核资报告、资产评估报告、国有资产管理等部门的确认文件、验资报告等，检查会计处理是否正确。 | C27: 备选 | D27: √ | E27: √ | F27: √ | G27: √ | I27: H1-7 /H1-8
A28: 12 | B28: 监盘固定资产： （1）取得公司固定资产清单，盘点范围考虑包括本期新增、容易侵占、重要、数量巨大、已损坏项目、存放在第三方及其他异常等。关注是否存在已报废但仍未核销的固定资产 （2）获取被审计单位对于固定资产的盘点计划，制定和实施监盘计划（如有）及盘点控制文件的复印件（如：盘点清单，标签控制清单）； （3）取得固定资产存放地点清单，初步确定监盘方式、时间、监盘计划； （4）观察被审计单位制定的盘点程序的执行情况 （5）检查固定资产的状态（在用、闲置、毁损或陈旧等）； （6）执行抽盘，注册会计师从固定资产盘点记录追查至固定资产实物，以及从固定资产实物中选取项目追查至固定资产清单，将抽盘结果与账面核对； （7）评价固定资产盘点结果，完成监盘小结。 | C28: 常规★ | D28: √ | F28: √ | G28: √ | I28: H1-9 /H1-10 /H1-11
A29: 13 | B29: 存放其他地方的资产（如有），考虑实地观察或函证由其他人保管或保管在盘点地之外的资产。 | C29: 备选 | D29: √ | F29: √ | G29: √
A30: 14 | B30: 检查累计折旧，考虑执行以下程序： （1）获取或编制累计折旧分类汇总表，复核加计正确，并与总账数和明细账合计数核对。 （2）重新计算折旧，当存在减值时，是否按照扣除减值损失之后的使用权资产账面价值进行后续折旧。 （3）获取暂时闲置、已提足折旧仍继续使用和前期已计提减值准备的固定资产的相关证明文件，并观察其实际状况，检查是否已按规定计提折旧； （4）检查折旧分配到成本、费用的情况，关注分配是否合理，与上期分配方法是否一致。 | C30: 常规★ | G30: √ | I30: H1-12 /H1-13
A31: 15 | B31: 结合固定资产清单和盘点程序，了解固定资产的状态。针对存在减值迹象的固定资产，考虑执行下列程序： 获取被审计单位在资产负债表日就固定资产是否可能发生减值迹象的判断的说明，判断其合理性。对于已计提减值准备的固定资产，检查减值测试相关参数是否合理，减值准备计提是否正确。对于管理层聘请评估专家出具的评估报告，复核评估报告。 | C31: 常规★ | G31: √ | I31: H1-14 /H1-15
A32: 16 | B32: 检查固定资产的所有权或控制权 （1）检查房屋及建筑物、运输设备等固定资产，并同时查看资产权属证明原件，结合银行借款等项目的检查，了解是否存在重大的抵押、担保情况，并取得复印件作为工作底稿； （2）对于正在办理权属证明的大额资产，了解权属证明办理情况，确认是否存在权属纠纷或实质性障碍。 | C32: 常规★ | F32: √ | I32: H1-16 /H1-17
A33: 17 | B33: 检查关联交易情况，检查关联交易的真实性、合理性及合规性；检查关联交易会计处理是否正确，考虑是否存在未识别的关联方，检查关联交易和余额披露是否正确。 | C33: 常规★ | D33: √ | E33: √ | F33: √ | G33: √ | H33: √ | I33: H1-18
A34: 18 | B34: 针对长期资产租赁（经营租出固定资产），考虑执行下列程序： （1）获取或编制资产租赁明细表，获取租赁合同/协议，核对重要条款，检查租赁分类是否正确。 （2）根据租赁合同/协议等文件，检查初始直接费用、或有租金确认是否合理，会计处理是否正确，重新计算租金收入并与利润表其他业务收入进行核对。 | C34: 备选 | D34: √ | E34: √ | F34: √ | G34: √ | I34: H1-19
A35: 19 | B35: 针对长期资产租赁（融资租出固定资产），考虑执行下列程序： （1）获取或编制资产租赁明细表，获取租赁合同/协议，核对重要条款，检查租赁分类是否正确，与固定资产增减变动明细表核对一致； （2）检查长期应收款、未确认融资收益的计算是否正确，实际利率、初始直接费用及或有租金的确认是否合理； （3）未担保余值发生变动的，分析变动原因，检查会计处理是否正确。 （4）本期租赁期届满的，分析处理方式（收回、优惠续租和出售），检查会计处理是否正确。 | C35: 备选 | D35: √ | E35: √ | F35: √ | G35: √ | I35: H1-20
A36: 20 | B36: 存在弃置义务的固定资产结合预计负债底稿检查会计处理是否正确。 | C36: 备选 | E36: √
A37: 21 | B37: 根据评估的舞弊风险等因素增加的审计程序。 | C37: IPO/上市/新三板/重组/舞弊应对
A38: 22 | B38: 检查固定资产、抵押和担保情况等是否已按企业会计准则或其他适用的规定在财务报表中做出恰当列报和披露 | C38: 常规★ | H38: √ | I38: A 1-1/A1-15 /A1-16

Sheet 审定表H1-1
A1: 致同会计师事务所
A2: 固定资产、累计折旧、减值准备审定表
A3: =底稿目录!A2 -> 被审计单位： | D3: =底稿目录!A4 -> 编制人： | G3: =底稿目录!A5 -> 编制日期： | H3: 索引号： | I3: H1-1
A4: =底稿目录!A3 -> 截止日：202X年12月31日 | D4: =底稿目录!A6 -> 复核人： | G4: =底稿目录!A7 -> 复核日期： | H4: 页 次：
A5: 项目 | B5: 期初数 | E5: 期末数 | H5: 本期审定数与上期 审定数的比较
B6: 未审数 | C6: 账项调整 | D6: 审定数 | E6: 未审数 | F6: 账项调整 | G6: 审定数 | H6: 变动额 | I6: 变动率
A7: 一、固定资产原值
A8: =底稿目录!A9 -> 房屋及建筑物 | B8: ='明细表H1-2'!D35 -> 0 | C8: ='明细表H1-2'!J35 -> 0 | D8: =B8+C8 -> 0 | E8: ='明细表H1-2'!I35 -> 0 | F8: ='明细表H1-2'!J35+'明细表H1-2'!K35-'明细表H1-2'!L35 -> 0 | G8: =E8+F8 -> 0 | H8: =G8-D8 -> 0 | I8: =IF(AND(D8=0,H8=0),0,IF(AND(D8=0,H8>0),1,H8/D8)) -> 0
A9: =底稿目录!A10 -> 机器设备 | B9: ='明细表H1-2'!D36 -> 0 | C9: ='明细表H1-2'!J36 -> 0 | D9: =B9+C9 -> 0 | E9: ='明细表H1-2'!I36 -> 0 | F9: ='明细表H1-2'!J36+'明细表H1-2'!K36-'明细表H1-2'!L36 -> 0 | G9: =E9+F9 -> 0 | H9: =G9-D9 -> 0 | I9: =IF(AND(D9=0,H9=0),0,IF(AND(D9=0,H9>0),1,H9/D9)) -> 0
A10: =底稿目录!A11 -> 运输设备 | B10: ='明细表H1-2'!D37 -> 0 | C10: ='明细表H1-2'!J37 -> 0 | D10: =B10+C10 -> 0 | E10: ='明细表H1-2'!I37 -> 0 | F10: ='明细表H1-2'!J37+'明细表H1-2'!K37-'明细表H1-2'!L37 -> 0 | G10: =E10+F10 -> 0 | H10: =G10-D10 -> 0 | I10: =IF(AND(D10=0,H10=0),0,IF(AND(D10=0,H10>0),1,H10/D10)) -> 0
A11: =底稿目录!A12 -> 办公设备 | B11: ='明细表H1-2'!D38 -> 0 | C11: ='明细表H1-2'!J38 -> 0 | D11: =B11+C11 -> 0 | E11: ='明细表H1-2'!I38 -> 0 | F11: ='明细表H1-2'!J38+'明细表H1-2'!K38-'明细表H1-2'!L38 -> 0 | G11: =E11+F11 -> 0 | H11: =G11-D11 -> 0 | I11: =IF(AND(D11=0,H11=0),0,IF(AND(D11=0,H11>0),1,H11/D11)) -> 0
A12: =底稿目录!A13 -> 其他设备 | B12: ='明细表H1-2'!D39 -> 0 | C12: ='明细表H1-2'!J39 -> 0 | D12: =B12+C12 -> 0 | E12: ='明细表H1-2'!I39 -> 0 | F12: ='明细表H1-2'!J39+'明细表H1-2'!K39-'明细表H1-2'!L39 -> 0 | G12: =E12+F12 -> 0 | H12: =G12-D12 -> 0 | I12: =IF(AND(D12=0,H12=0),0,IF(AND(D12=0,H12>0),1,H12/D12)) -> 0
A13: 合计 | B13: =SUM(B8:B12) -> 0 | C13: =SUM(C8:C12) -> 0 | D13: =SUM(D8:D12) -> 0 | E13: =SUM(E8:E12) -> 0 | F13: =SUM(F8:F12) -> 0 | G13: =SUM(G8:G12) -> 0 | H13: =G13-D13 -> 0 | I13: =IF(AND(D13=0,H13=0),0,IF(AND(D13=0,H13>0),1,H13/D13)) -> 0
A14: 二、累计折旧
A15: =底稿目录!A9 -> 房屋及建筑物 | B15: ='明细表H1-2'!Q35 -> 0 | C15: ='明细表H1-2'!W35 -> 0 | D15: =B15+C15 -> 0 | E15: ='明细表H1-2'!V35 -> 0 | F15: ='明细表H1-2'!W35+'明细表H1-2'!X35-'明细表H1-2'!Z35+'明细表H1-2'!Y35-'明细表H1-2'!AA35 -> 0 | G15: =E15+F15 -> 0 | H15: =G15-D15 -> 0 | I15: =IF(AND(D15=0,H15=0),0,IF(AND(D15=0,H15>0),1,H15/D15)) -> 0
A16: =底稿目录!A10 -> 机器设备 | B16: ='明细表H1-2'!Q36 -> 0 | C16: ='明细表H1-2'!W36 -> 0 | D16: =B16+C16 -> 0 | E16: ='明细表H1-2'!V36 -> 0 | F16: ='明细表H1-2'!W36+'明细表H1-2'!X36-'明细表H1-2'!Z36+'明细表H1-2'!Y36-'明细表H1-2'!AA36 -> 0 | G16: =E16+F16 -> 0 | H16: =G16-D16 -> 0 | I16: =IF(AND(D16=0,H16=0),0,IF(AND(D16=0,H16>0),1,H16/D16)) -> 0
A17: =底稿目录!A11 -> 运输设备 | B17: ='明细表H1-2'!Q37 -> 0 | C17: ='明细表H1-2'!W37 -> 0 | D17: =B17+C17 -> 0 | E17: ='明细表H1-2'!V37 -> 0 | F17: ='明细表H1-2'!W37+'明细表H1-2'!X37-'明细表H1-2'!Z37+'明细表H1-2'!Y37-'明细表H1-2'!AA37 -> 0 | G17: =E17+F17 -> 0 | H17: =G17-D17 -> 0 | I17: =IF(AND(D17=0,H17=0),0,IF(AND(D17=0,H17>0),1,H17/D17)) -> 0
A18: =底稿目录!A12 -> 办公设备 | B18: ='明细表H1-2'!Q38 -> 0 | C18: ='明细表H1-2'!W38 -> 0 | D18: =B18+C18 -> 0 | E18: ='明细表H1-2'!V38 -> 0 | F18: ='明细表H1-2'!W38+'明细表H1-2'!X38-'明细表H1-2'!Z38+'明细表H1-2'!Y38-'明细表H1-2'!AA38 -> 0 | G18: =E18+F18 -> 0 | H18: =G18-D18 -> 0 | I18: =IF(AND(D18=0,H18=0),0,IF(AND(D18=0,H18>0),1,H18/D18)) -> 0
A19: =底稿目录!A13 -> 其他设备 | B19: ='明细表H1-2'!Q39 -> 0 | C19: ='明细表H1-2'!W39 -> 0 | D19: =B19+C19 -> 0 | E19: ='明细表H1-2'!V39 -> 0 | F19: ='明细表H1-2'!W39+'明细表H1-2'!X39-'明细表H1-2'!Z39+'明细表H1-2'!Y39-'明细表H1-2'!AA39 -> 0 | G19: =E19+F19 -> 0 | H19: =G19-D19 -> 0 | I19: =IF(AND(D19=0,H19=0),0,IF(AND(D19=0,H19>0),1,H19/D19)) -> 0
A20: 合计 | B20: =SUM(B15:B19) -> 0 | C20: =SUM(C15:C19) -> 0 | D20: =SUM(D15:D19) -> 0 | E20: =SUM(E15:E19) -> 0 | F20: =SUM(F15:F19) -> 0 | G20: =SUM(G15:G19) -> 0 | H20: =G20-D20 -> 0 | I20: =IF(AND(D20=0,H20=0),0,IF(AND(D20=0,H20>0),1,H20/D20)) -> 0
A21: 三、减值准备
A22: =底稿目录!A9 -> 房屋及建筑物 | B22: ='明细表H1-2'!AF35 -> 0 | C22: ='明细表H1-2'!AL35 -> 0 | D22: =B22+C22 -> 0 | E22: ='明细表H1-2'!AK35 -> 0 | F22: ='明细表H1-2'!AL35+'明细表H1-2'!AM35-'明细表H1-2'!AO35+'明细表H1-2'!AN35-'明细表H1-2'!AP35 -> 0 | G22: =E22+F22 -> 0 | H22: =G22-D22 -> 0 | I22: =IF(AND(D22=0,H22=0),0,IF(AND(D22=0,H22>0),1,H22/D22)) -> 0
A23: =底稿目录!A10 -> 机器设备 | B23: ='明细表H1-2'!AF36 -> 0 | C23: ='明细表H1-2'!AL36 -> 0 | D23: =B23+C23 -> 0 | E23: ='明细表H1-2'!AK36 -> 0 | F23: ='明细表H1-2'!AL36+'明细表H1-2'!AM36-'明细表H1-2'!AO36+'明细表H1-2'!AN36-'明细表H1-2'!AP36 -> 0 | G23: =E23+F23 -> 0 | H23: =G23-D23 -> 0 | I23: =IF(AND(D23=0,H23=0),0,IF(AND(D23=0,H23>0),1,H23/D23)) -> 0
A24: =底稿目录!A11 -> 运输设备 | B24: ='明细表H1-2'!AF37 -> 0 | C24: ='明细表H1-2'!AL37 -> 0 | D24: =B24+C24 -> 0 | E24: ='明细表H1-2'!AK37 -> 0 | F24: ='明细表H1-2'!AL37+'明细表H1-2'!AM37-'明细表H1-2'!AO37+'明细表H1-2'!AN37-'明细表H1-2'!AP37 -> 0 | G24: =E24+F24 -> 0 | H24: =G24-D24 -> 0 | I24: =IF(AND(D24=0,H24=0),0,IF(AND(D24=0,H24>0),1,H24/D24)) -> 0
A25: =底稿目录!A12 -> 办公设备 | B25: ='明细表H1-2'!AF38 -> 0 | C25: ='明细表H1-2'!AL38 -> 0 | D25: =B25+C25 -> 0 | E25: ='明细表H1-2'!AK38 -> 0 | F25: ='明细表H1-2'!AL38+'明细表H1-2'!AM38-'明细表H1-2'!AO38+'明细表H1-2'!AN38-'明细表H1-2'!AP38 -> 0 | G25: =E25+F25 -> 0 | H25: =G25-D25 -> 0 | I25: =IF(AND(D25=0,H25=0),0,IF(AND(D25=0,H25>0),1,H25/D25)) -> 0
A26: =底稿目录!A13 -> 其他设备 | B26: ='明细表H1-2'!AF39 -> 0 | C26: ='明细表H1-2'!AL39 -> 0 | D26: =B26+C26 -> 0 | E26: ='明细表H1-2'!AK39 -> 0 | F26: ='明细表H1-2'!AL39+'明细表H1-2'!AM39-'明细表H1-2'!AO39+'明细表H1-2'!AN39-'明细表H1-2'!AP39 -> 0 | G26: =E26+F26 -> 0 | H26: =G26-D26 -> 0 | I26: =IF(AND(D26=0,H26=0),0,IF(AND(D26=0,H26>0),1,H26/D26)) -> 0
A27: 合计 | B27: =SUM(B22:B26) -> 0 | C27: =SUM(C22:C26) -> 0 | D27: =SUM(D22:D26) -> 0 | E27: =SUM(E22:E26) -> 0 | F27: =SUM(F22:F26) -> 0 | G27: =SUM(G22:G26) -> 0 | H27: =G27-D27 -> 0 | I27: =IF(AND(D27=0,H27=0),0,IF(AND(D27=0,H27>0),1,H27/D27)) -> 0
A28: 四、净值
A29: =底稿目录!A9 -> 房屋及建筑物 | B29: =B8-B15-B22 -> 0 | C29: =C8-C15-C22 -> 0 | D29: =D8-D15-D22 -> 0 | E29: =E8-E15-E22 -> 0 | F29: =F8-F15-F22 -> 0 | G29: =E29+F29 -> 0 | H29: =G29-D29 -> 0 | I29: =IF(AND(D29=0,H29=0),0,IF(AND(D29=0,H29>0),1,H29/D29)) -> 0
A30: =底稿目录!A10 -> 机器设备 | B30: =B9-B16-B23 -> 0 | C30: =C9-C16-C23 -> 0 | D30: =D9-D16-D23 -> 0 | E30: =E9-E16-E23 -> 0 | F30: =F9-F16-F23 -> 0 | G30: =E30+F30 -> 0 | H30: =G30-D30 -> 0 | I30: =IF(AND(D30=0,H30=0),0,IF(AND(D30=0,H30>0),1,H30/D30)) -> 0
A31: =底稿目录!A11 -> 运输设备 | B31: =B10-B17-B24 -> 0 | C31: =C10-C17-C24 -> 0 | D31: =D10-D17-D24 -> 0 | E31: =E10-E17-E24 -> 0 | F31: =F10-F17-F24 -> 0 | G31: =E31+F31 -> 0 | H31: =G31-D31 -> 0 | I31: =IF(AND(D31=0,H31=0),0,IF(AND(D31=0,H31>0),1,H31/D31)) -> 0
A32: =底稿目录!A12 -> 办公设备 | B32: =B11-B18-B25 -> 0 | C32: =C11-C18-C25 -> 0 | D32: =D11-D18-D25 -> 0 | E32: =E11-E18-E25 -> 0 | F32: =F11-F18-F25 -> 0 | G32: =E32+F32 -> 0 | H32: =G32-D32 -> 0 | I32: =IF(AND(D32=0,H32=0),0,IF(AND(D32=0,H32>0),1,H32/D32)) -> 0
A33: =底稿目录!A13 -> 其他设备 | B33: =B12-B19-B26 -> 0 | C33: =C12-C19-C26 -> 0 | D33: =D12-D19-D26 -> 0 | E33: =E12-E19-E26 -> 0 | F33: =F12-F19-F26 -> 0 | G33: =E33+F33 -> 0 | H33: =G33-D33 -> 0 | I33: =IF(AND(D33=0,H33=0),0,IF(AND(D33=0,H33>0),1,H33/D33)) -> 0
A34: 合计 | B34: =SUM(B29:B33) -> 0 | C34: =SUM(C29:C33) -> 0 | D34: =SUM(D29:D33) -> 0 | E34: =SUM(E29:E33) -> 0 | F34: =SUM(F29:F33) -> 0 | G34: =SUM(G29:G33) -> 0 | H34: =G34-D34 -> 0 | I34: =IF(AND(D34=0,H34=0),0,IF(AND(D34=0,H34>0),1,H34/D34)) -> 0
A35: 1、审计说明：
A36: （1）固定资产期末净值较期初净值增加（负数为减少）：
A37: 主要原因（比例超过30%的）：
A39: （2）本期由在建工程转入：
A41: （3）抵押、担保情况说明：
A43: （4）出售、置换情况说明：
A46: （5）租赁情况说明：（通过融资租赁租入的固定资产应披露每类租入资产的账面原值、累计折旧、账面净值；
A47: 通过经营租赁租出的固定资产应披露每类租出资产的账面价值。）
A49: （6）与试算平衡表的核对
B50: 期末数 | C50: 期初数
A51: 固定资产净值审定数 | B51: =G34 -> 0 | C51: =D34 -> 0
A52: 固定资产清理审定数
A53: 固定资产与固定资产清理合计数 | B53: =B51+B52 -> 0 | C53: =C51+C52 -> 0
A54: 试算平衡表
A55: 差异 | B55: =B53-B54 -> 0 | C55: =C53-C54 -> 0
A57: 2、审计结论：

Sheet 附注披露信息（上市公司）
A1: 致同会计师事务所
A2: 附注披露信息（上市公司）
A3: =底稿目录!A2 -> 被审计单位： | C3: =底稿目录!A4 -> 编制人： | F3: =底稿目录!A6 -> 复核人： | G3: 索引号： | H3: 返回目录
A4: =底稿目录!A3 -> 截止日：202X年12月31日 | C4: =底稿目录!A5 -> 编制日期： | F4: =底稿目录!A7 -> 复核日期： | G4: 页 次：
A6: 15、固定资产
A7: 项 目 | B7: 期末余额 | C7: 上年年末余额
A8: 固定资产
A9: 固定资产清理
A10: 合 计 | B10: X.XX | C10: X.XX
A11: （1）固定资产
A12: ①固定资产情况
A13: 项 目 | B13: 房屋及建筑物 | C13: 机器设备 | D13: 运输设备 | E13: …… | F13: 合 计
A14: 一、账面原值：
A15: 1.期初余额
A16: 2.本期增加金额
A17: （1）购置
A18: （2）在建工程转入
A19: （3）企业合并增加
A20: ……
A21: 3.本期减少金额
A22: （1）处置或报废
A23: （2）其他减少
A24: ……
A25: 4.期末余额
... A59: ②暂时闲置的固定资产情况
A60: 项 目 | B60: 账面原值 | C60: 累计折旧 | D60: 减值准备 | E60: 账面价值 | F60: 备注
A61: 房屋及建筑物
A62: 机器设备
A63: 电子设备
A64: 运输设备
A65: 可无限量添加行
A66: 合 计 | B66: X.XX | C66: X.XX | D66: X.XX | E66: X.XX
A68: ③通过经营租赁租出的固定资产
A69: 项 目 | B69: 账面价值
A70: 房屋及建筑物
A71: 机器设备
A72: 电子设备
A73: 运输设备
A74: 可无限量添加行
A75: 合 计 | B75: X.XX
A77: ④未办妥产权证书的固定资产情况
A78: （披露期末未办妥产权证书的固定资产账面价值及原因。）
A79: 项 目 | B79: 账面价值 | C79: 未办妥产权证书原因
A84: ⑤本期冲减固定资产账面价值的政府补助金额为XXX元，具体情况见附注八、政府补助。
A85: （提示：对于冲减无形资产或其他资产账面价值的政府补助，在无形资产或其他资产的科目附注中比照上述要求进行披露。）
A86: （2）固定资产清理
A87: 项 目 | B87: 期末余额 | C87: 上年年末余额 | D87: 转入清理的原因
A91: 合 计 | B91: X.XX | C91: X.XX
A93: （说明转入固定资产清理起始时间已超过1年的固定资产清理进展情况）

Sheet 附注披露信息（国有企业）
A1: 致同会计师事务所
A2: 附注披露信息（国有企业）
A3: =底稿目录!A2 -> 被审计单位： | B3: =底稿目录!A4 -> 编制人： | D3: =底稿目录!A6 -> 复核人： | F3: 索引号： | G3: 返回目录
A4: =底稿目录!A3 -> 截止日：202X年12月31日 | B4: =底稿目录!A5 -> 编制日期： | D4: =底稿目录!A7 -> 复核日期： | F4: 页 次：
A6: 15、固定资产
A7: 项 目 | B7: 期末账面价值 | C7: 期初账面价值
A8: 固定资产
A9: 固定资产清理
A10: 合 计 | B10: X.XX | C10: X.XX
A11: （1）固定资产情况
A12: ① 固定资产情况
A13: 项 目 | B13: 期初余额 | C13: 本期增加 | D13: 本期减少 | E13: 期末余额
A14: 一、账面原值合计 | B14: XX | C14: XX | D14: XX | E14: XX
A15: 其中：土地资产
A16: 房屋、建筑物
A17: 机器设备
A18: 运输工具
A19: 电子设备
A20: 办公设备
A21: 酒店业家具
A22: 其他 | B22: XX | C22: XX | D22: XX | E22: XX
A23: 二、累计折旧合计 | B23: XX | C23: XX | D23: XX | E23: XX
A24: 其中：土地资产 | B24: — | C24: — | D24: — | E24: —
A25: 房屋、建筑物
A26: 机器设备
A27: 运输工具
A28: 电子设备
A29: 办公设备
A30: 酒店业家具
A31: 其他 | B31: XX | C31: XX | D31: XX | E31: XX
A32: 三、固定资产账面净值合计 | B32: XX | C32: XX | D32: XX | E32: XX
A33: 其中：土地资产 | C33: -- | D33: --
A34: 房屋、建筑物 | C34: -- | D34: --
A35: 机器设备 | C35: -- | D35: --
A36: 运输工具 | C36: -- | D36: --
A37: 电子设备 | C37: -- | D37: --
A38: 办公设备 | C38: -- | D38: --
A39: 酒店业家具 | C39: -- | D39: --
A40: 其他 | B40: XX | C40: -- | D40: -- | E40: XX
A41: 四、固定资产减值准备合计 | B41: XX | C41: XX | D41: XX | E41: XX
A42: 其中：土地资产 | B42: -- | C42: -- | D42: -- | E42: --
A43: 房屋、建筑物
A44: 机器设备
A45: 运输工具
A46: 电子设备
A47: 办公设备
A48: 酒店业家具
A49: 其他 | B49: XX | C49: XX | D49: XX | E49: XX
A50: 五、固定资产账面价值合计 | B50: XX | C50: XX | D50: XX | E50: XX
A51: 其中：土地资产 | C51: -- | D51: --
A52: 房屋、建筑物 | C52: -- | D52: --
A53: 机器设备 | C53: -- | D53: --
A54: 运输工具 | C54: -- | D54: --
A55: 电子设备 | C55: -- | D55: --
A56: 办公设备 | C56: -- | D56: --
A57: 酒店业家具 | C57: -- | D57: --
A58: 其他 | B58: XX | C58: -- | D58: -- | E58: XX
A59: ② 暂时闲置的固定资产情况
A60: 项 目 | B60: 账面原值 | C60: 累计折旧 | D60: 减值准备 | E60: 账面价值 | F60: 备注
A64: 合 计
A65: ③ 未办妥产权证书的固定资产情况
A66: 项 目 | B66: 账面价值 | C66: 未办妥产权证书原因
A70: 合 计
A71: （2）固定资产清理
A72: 项 目 | B72: 期末账面价值 | C72: 期初账面价值 | D72: 转入清理的原因
A76: 合 计 | D76: --
A78: 注：说明转入固定资产清理起始时间已超过1年的固定资产清理进展情况。

Sheet 明细表H1-2
D1: 致同会计师事务所 | Q1: 致同会计师事务所 | AF1: 致同会计师事务所
D2: 固定资产、累计折旧及减值准备明细表 | Q2: 固定资产、累计折旧及减值准备明细表 | AF2: 固定资产、累计折旧及减值准备明细表
A3: =底稿目录!A2 -> 被审计单位： | H3: =底稿目录!A4 -> 编制人： | L3: =底稿目录!A5 -> 编制日期： | O3: 索引号： | P3: H1-2 | Q3: =底稿目录!A2 -> 被审计单位： | V3: =底稿目录!A4 -> 编制人： | Z3: =底稿目录!A5 -> 编制日期： | AD3: 索引号： | AE3: H1-2 | AF3: =底稿目录!A2 -> 被审计单位： | AN3: =底稿目录!A4 -> 编制人： | AT3: =底稿目录!A5 -> 编制日期： | BA3: 索引号： | BB3: H1-2
A4: =底稿目录!A3 -> 截止日：202X年12月31日 | H4: =底稿目录!A6 -> 复核人： | L4: =底稿目录!A7 -> 复核日期： | O4: 页 次： | Q4: =底稿目录!A3 -> 截止日：202X年12月31日 | V4: =底稿目录!A6 -> 复核人： | Z4: =底稿目录!A7 -> 复核日期： | AD4: 页 次： | AF4: =底稿目录!A3 -> 截止日：202X年12月31日 | AN4: =底稿目录!A6 -> 复核人： | AT4: =底稿目录!A7 -> 复核日期： | BA4: 页 次：
A5: 一、审计目标:
A6: 1.资产负债表中记录的固定资产是存在的，且已记录于恰当的账户；2.所有应记录的固定资产均已记录，所有应当包括在财务报表中的相关披露均已包括；
A7: 3.固定资产以恰当的金额包括在财务报表中，与之相关的计价或分摊调整已恰当记录，相关披露已得到恰当计量和描述
A8: 二、审计过程：
A9: 固定资产类别 | B9: 固定资产编号 | C9: 固定资产名称 | D9: 固定资产原值 | Q9: 累计折旧 | AF9: 减值准备 | AU9: 期初净值 | AW9: 期末净值 | AY9: 是否提足折旧 | AZ9: 是否闲置 | BA9: 是否有权属证明 | BB9: 是否抵押受限
D10: 未审数 | J10: 期初调整 | K10: 账项调整 | M10: 审定数 | Q10: 未审数 | W10: 期初调整 | X10: 账项调整 | AB10: 审定数 | AF10: 未审数 | AL10: 期初调整 | AM10: 账项调整 | AQ10: 审定数
D11: 期初数 | E11: 本期增加 | G11: 本期减少 | I11: 期末数 | K11: 本期增加 | L11: 本期减少 | M11: 期初数 | N11: 本期增加 | O11: 本期减少 | P11: 期末数 | Q11: 期初数 | R11: 本期增加 | T11: 本期减少 | V11: 期末数 | X11: 本期增加 | Z11: 本期减少 | AB11: 期初数 | AC11: 本期增加 | AD11: 本期减少 | AE11: 期末数 | AF11: 期初数 | AG11: 本期增加 | AI11: 本期减少 | AK11: 期末数 | AM11: 本期增加 | AO11: 本期减少 | AQ11: 期初数 | AR11: 本期增加 | AS11: 本期减少 | AT11: 期末数 | AU11: 未审净值 | AV11: 审定净值 | AW11: 未审净值 | AX11: 审定净值
E12: 金额 | F12: 增加方式 | G12: 金额 | H12: 减少方式 | R12: 本期计提 | S12: 其他增加 | T12: 处置 | U12: 其他减少 | X12: 本期计提 | Y12: 其他增加 | Z12: 处置 | AA12: 其他减少 | AG12: 本期计提 | AH12: 其他增加 | AI12: 处置 | AJ12: 其他减少 | AM12: 本期计提 | AN12: 其他增加 | AO12: 处置 | AP12: 其他减少
I13: =SUM(D13:E13)-G13 -> 0 | M13: =D13+J13 -> 0 | N13: =E13+K13 -> 0 | O13: =G13+L13 -> 0 | P13: =M13+N13-O13 -> 0 | V13: =SUM(Q13:S13)-SUM(T13:U13) -> 0 | AB13: =Q13+W13 -> 0 | AC13: =R13+X13+S13+Y13 -> 0 | AD13: =T13+Z13+U13+AA13 -> 0 | AE13: =AB13+AC13-AD13 -> 0 | AK13: =SUM(AF13:AH13)-SUM(AI13:AJ13) -> 0 | AQ13: =AF13+AL13 -> 0 | AR13: =AG13+AM13+AH13+AN13 -> 0 | AS13: =AI13+AO13+AJ13+AP13 -> 0 | AT13: =AQ13+AR13-AS13 -> 0 | AU13: =D13-Q13-AF13 -> 0 | AV13: =M13-AB13-AQ13 -> 0 | AW13: =I13-V13-AK13 -> 0 | AX13: =P13-AE13-AT13 -> 0
I14: =SUM(D14:E14)-G14 -> 0 | M14: =D14+J14 -> 0 | N14: =E14+K14 -> 0 | O14: =G14+L14 -> 0 | P14: =M14+N14-O14 -> 0 | V14: =SUM(Q14:S14)-SUM(T14:U14) -> 0 | AB14: =Q14+W14 -> 0 | AC14: =R14+X14+S14+Y14 -> 0 | AD14: =T14+Z14+U14+AA14 -> 0 | AE14: =AB14+AC14-AD14 -> 0 | AK14: =SUM(AF14:AH14)-SUM(AI14:AJ14) -> 0 | AQ14: =AF14+AL14 -> 0 | AR14: =AG14+AM14+AH14+AN14 -> 0 | AS14: =AI14+AO14+AJ14+AP14 -> 0 | AT14: =AQ14+AR14-AS14 -> 0 | AU14: =D14-Q14-AF14 -> 0 | AV14: =M14-AB14-AQ14 -> 0 | AW14: =I14-V14-AK14 -> 0 | AX14: =P14-AE14-AT14 -> 0
I15: =SUM(D15:E15)-G15 -> 0 | M15: =D15+J15 -> 0 | N15: =E15+K15 -> 0 | O15: =G15+L15 -> 0 | P15: =M15+N15-O15 -> 0 | V15: =SUM(Q15:S15)-SUM(T15:U15) -> 0 | AB15: =Q15+W15 -> 0 | AC15: =R15+X15+S15+Y15 -> 0 | AD15: =T15+Z15+U15+AA15 -> 0 | AE15: =AB15+AC15-AD15 -> 0 | AK15: =SUM(AF15:AH15)-SUM(AI15:AJ15) -> 0 | AQ15: =AF15+AL15 -> 0 | AR15: =AG15+AM15+AH15+AN15 -> 0 | AS15: =AI15+AO15+AJ15+AP15 -> 0 | AT15: =AQ15+AR15-AS15 -> 0 | AU15: =D15-Q15-AF15 -> 0 | AV15: =M15-AB15-AQ15 -> 0 | AW15: =I15-V15-AK15 -> 0 | AX15: =P15-AE15-AT15 -> 0
I16: =SUM(D16:E16)-G16 -> 0 | M16: =D16+J16 -> 0 | N16: =E16+K16 -> 0 | O16: =G16+L16 -> 0 | P16: =M16+N16-O16 -> 0 | V16: =SUM(Q16:S16)-SUM(T16:U16) -> 0 | AB16: =Q16+W16 -> 0 | AC16: =R16+X16+S16+Y16 -> 0 | AD16: =T16+Z16+U16+AA16 -> 0 | AE16: =AB16+AC16-AD16 -> 0 | AK16: =SUM(AF16:AH16)-SUM(AI16:AJ16) -> 0 | AQ16: =AF16+AL16 -> 0 | AR16: =AG16+AM16+AH16+AN16 -> 0 | AS16: =AI16+AO16+AJ16+AP16 -> 0 | AT16: =AQ16+AR16-AS16 -> 0 | AU16: =D16-Q16-AF16 -> 0 | AV16: =M16-AB16-AQ16 -> 0 | AW16: =I16-V16-AK16 -> 0 | AX16: =P16-AE16-AT16 -> 0
I17: =SUM(D17:E17)-G17 -> 0 | M17: =D17+J17 -> 0 | N17: =E17+K17 -> 0 | O17: =G17+L17 -> 0 | P17: =M17+N17-O17 -> 0 | V17: =SUM(Q17:S17)-SUM(T17:U17) -> 0 | AB17: =Q17+W17 -> 0 | AC17: =R17+X17+S17+Y17 -> 0 | AD17: =T17+Z17+U17+AA17 -> 0 | AE17: =AB17+AC17-AD17 -> 0 | AK17: =SUM(AF17:AH17)-SUM(AI17:AJ17) -> 0 | AQ17: =AF17+AL17 -> 0 | AR17: =AG17+AM17+AH17+AN17 -> 0 | AS17: =AI17+AO17+AJ17+AP17 -> 0 | AT17: =AQ17+AR17-AS17 -> 0 | AU17: =D17-Q17-AF17 -> 0 | AV17: =M17-AB17-AQ17 -> 0 | AW17: =I17-V17-AK17 -> 0 | AX17: =P17-AE17-AT17 -> 0
I18: =SUM(D18:E18)-G18 -> 0 | M18: =D18+J18 -> 0 | N18: =E18+K18 -> 0 | O18: =G18+L18 -> 0 | P18: =M18+N18-O18 -> 0 | V18: =SUM(Q18:S18)-SUM(T18:U18) -> 0 | AB18: =Q18+W18 -> 0 | AC18: =R18+X18+S18+Y18 -> 0 | AD18: =T18+Z18+U18+AA18 -> 0 | AE18: =AB18+AC18-AD18 -> 0 | AK18: =SUM(AF18:AH18)-SUM(AI18:AJ18) -> 0 | AQ18: =AF18+AL18 -> 0 | AR18: =AG18+AM18+AH18+AN18 -> 0 | AS18: =AI18+AO18+AJ18+AP18 -> 0 | AT18: =AQ18+AR18-AS18 -> 0 | AU18: =D18-Q18-AF18 -> 0 | AV18: =M18-AB18-AQ18 -> 0 | AW18: =I18-V18-AK18 -> 0 | AX18: =P18-AE18-AT18 -> 0
I19: =SUM(D19:E19)-G19 -> 0 | M19: =D19+J19 -> 0 | N19: =E19+K19 -> 0 | O19: =G19+L19 -> 0 | P19: =M19+N19-O19 -> 0 | V19: =SUM(Q19:S19)-SUM(T19:U19) -> 0 | AB19: =Q19+W19 -> 0 | AC19: =R19+X19+S19+Y19 -> 0 | AD19: =T19+Z19+U19+AA19 -> 0 | AE19: =AB19+AC19-AD19 -> 0 | AK19: =SUM(AF19:AH19)-SUM(AI19:AJ19) -> 0 | AQ19: =AF19+AL19 -> 0 | AR19: =AG19+AM19+AH19+AN19 -> 0 | AS19: =AI19+AO19+AJ19+AP19 -> 0 | AT19: =AQ19+AR19-AS19 -> 0 | AU19: =D19-Q19-AF19 -> 0 | AV19: =M19-AB19-AQ19 -> 0 | AW19: =I19-V19-AK19 -> 0 | AX19: =P19-AE19-AT19 -> 0
I20: =SUM(D20:E20)-G20 -> 0 | M20: =D20+J20 -> 0 | N20: =E20+K20 -> 0 | O20: =G20+L20 -> 0 | P20: =M20+N20-O20 -> 0 | V20: =SUM(Q20:S20)-SUM(T20:U20) -> 0 | AB20: =Q20+W20 -> 0 | AC20: =R20+X20+S20+Y20 -> 0 | AD20: =T20+Z20+U20+AA20 -> 0 | AE20: =AB20+AC20-AD20 -> 0 | AK20: =SUM(AF20:AH20)-SUM(AI20:AJ20) -> 0 | AQ20: =AF20+AL20 -> 0 | AR20: =AG20+AM20+AH20+AN20 -> 0 | AS20: =AI20+AO20+AJ20+AP20 -> 0 | AT20: =AQ20+AR20-AS20 -> 0 | AU20: =D20-Q20-AF20 -> 0 | AV20: =M20-AB20-AQ20 -> 0 | AW20: =I20-V20-AK20 -> 0 | AX20: =P20-AE20-AT20 -> 0
I21: =SUM(D21:E21)-G21 -> 0 | M21: =D21+J21 -> 0 | N21: =E21+K21 -> 0 | O21: =G21+L21 -> 0 | P21: =M21+N21-O21 -> 0 | V21: =SUM(Q21:S21)-SUM(T21:U21) -> 0 | AB21: =Q21+W21 -> 0 | AC21: =R21+X21+S21+Y21 -> 0 | AD21: =T21+Z21+U21+AA21 -> 0 | AE21: =AB21+AC21-AD21 -> 0 | AK21: =SUM(AF21:AH21)-SUM(AI21:AJ21) -> 0 | AQ21: =AF21+AL21 -> 0 | AR21: =AG21+AM21+AH21+AN21 -> 0 | AS21: =AI21+AO21+AJ21+AP21 -> 0 | AT21: =AQ21+AR21-AS21 -> 0 | AU21: =D21-Q21-AF21 -> 0 | AV21: =M21-AB21-AQ21 -> 0 | AW21: =I21-V21-AK21 -> 0 | AX21: =P21-AE21-AT21 -> 0
I22: =SUM(D22:E22)-G22 -> 0 | M22: =D22+J22 -> 0 | N22: =E22+K22 -> 0 | O22: =G22+L22 -> 0 | P22: =M22+N22-O22 -> 0 | V22: =SUM(Q22:S22)-SUM(T22:U22) -> 0 | AB22: =Q22+W22 -> 0 | AC22: =R22+X22+S22+Y22 -> 0 | AD22: =T22+Z22+U22+AA22 -> 0 | AE22: =AB22+AC22-AD22 -> 0 | AK22: =SUM(AF22:AH22)-SUM(AI22:AJ22) -> 0 | AQ22: =AF22+AL22 -> 0 | AR22: =AG22+AM22+AH22+AN22 -> 0 | AS22: =AI22+AO22+AJ22+AP22 -> 0 | AT22: =AQ22+AR22-AS22 -> 0 | AU22: =D22-Q22-AF22 -> 0 | AV22: =M22-AB22-AQ22 -> 0 | AW22: =I22-V22-AK22 -> 0 | AX22: =P22-AE22-AT22 -> 0
I23: =SUM(D23:E23)-G23 -> 0 | M23: =D23+J23 -> 0 | N23: =E23+K23 -> 0 | O23: =G23+L23 -> 0 | P23: =M23+N23-O23 -> 0 | V23: =SUM(Q23:S23)-SUM(T23:U23) -> 0 | AB23: =Q23+W23 -> 0 | AC23: =R23+X23+S23+Y23 -> 0 | AD23: =T23+Z23+U23+AA23 -> 0 | AE23: =AB23+AC23-AD23 -> 0 | AK23: =SUM(AF23:AH23)-SUM(AI23:AJ23) -> 0 | AQ23: =AF23+AL23 -> 0 | AR23: =AG23+AM23+AH23+AN23 -> 0 | AS23: =AI23+AO23+AJ23+AP23 -> 0 | AT23: =AQ23+AR23-AS23 -> 0 | AU23: =D23-Q23-AF23 -> 0 | AV23: =M23-AB23-AQ23 -> 0 | AW23: =I23-V23-AK23 -> 0 | AX23: =P23-AE23-AT23 -> 0
I24: =SUM(D24:E24)-G24 -> 0 | M24: =D24+J24 -> 0 | N24: =E24+K24 -> 0 | O24: =G24+L24 -> 0 | P24: =M24+N24-O24 -> 0 | V24: =SUM(Q24:S24)-SUM(T24:U24) -> 0 | AB24: =Q24+W24 -> 0 | AC24: =R24+X24+S24+Y24 -> 0 | AD24: =T24+Z24+U24+AA24 -> 0 | AE24: =AB24+AC24-AD24 -> 0 | AK24: =SUM(AF24:AH24)-SUM(AI24:AJ24) -> 0 | AQ24: =AF24+AL24 -> 0 | AR24: =AG24+AM24+AH24+AN24 -> 0 | AS24: =AI24+AO24+AJ24+AP24 -> 0 | AT24: =AQ24+AR24-AS24 -> 0 | AU24: =D24-Q24-AF24 -> 0 | AV24: =M24-AB24-AQ24 -> 0 | AW24: =I24-V24-AK24 -> 0 | AX24: =P24-AE24-AT24 -> 0
... I32: =SUM(D32:E32)-G32 -> 0 | M32: =D32+J32 -> 0 | N32: =E32+K32 -> 0 | O32: =G32+L32 -> 0 | P32: =M32+N32-O32 -> 0 | V32: =SUM(Q32:S32)-SUM(T32:U32) -> 0 | AB32: =Q32+W32 -> 0 | AC32: =R32+X32+S32+Y32 -> 0 | AD32: =T32+Z32+U32+AA32 -> 0 | AE32: =AB32+AC32-AD32 -> 0 | AK32: =SUM(AF32:AH32)-SUM(AI32:AJ32) -> 0 | AQ32: =AF32+AL32 -> 0 | AR32: =AG32+AM32+AH32+AN32 -> 0 | AS32: =AI32+AO32+AJ32+AP32 -> 0 | AT32: =AQ32+AR32-AS32 -> 0 | AU32: =D32-Q32-AF32 -> 0 | AV32: =M32-AB32-AQ32 -> 0 | AW32: =I32-V32-AK32 -> 0 | AX32: =P32-AE32-AT32 -> 0
A33: 合计 | D33: =SUM(D13:D32) -> 0 | E33: =SUM(E13:E32) -> 0 | G33: =SUM(G13:G32) -> 0 | I33: =SUM(I13:I32) -> 0 | J33: =SUM(J13:J32) -> 0 | K33: =SUM(K13:K32) -> 0 | L33: =SUM(L13:L32) -> 0 | M33: =SUM(M13:M32) -> 0 | N33: =SUM(N13:N32) -> 0 | O33: =SUM(O13:O32) -> 0 | P33: =SUM(P13:P32) -> 0 | ... AX33: =SUM(AX13:AX32) -> 0
A34: 其中：
A35: =底稿目录!A9 -> 房屋及建筑物 | D35: =SUMPRODUCT(($A$13:$A$32=$A35)*(D$13:D$32)) -> 0 | E35: =SUMPRODUCT(($A$13:$A$32=$A35)*(E$13:E$32)) -> 0 | G35: =SUMPRODUCT(($A$13:$A$32=$A35)*(G$13:G$32)) -> 0 | I35: =SUMPRODUCT(($A$13:$A$32=$A35)*(I$13:I$32)) -> 0 | J35: =SUMPRODUCT(($A$13:$A$32=$A35)*(J$13:J$32)) -> 0 | K35: =SUMPRODUCT(($A$13:$A$32=$A35)*(K$13:K$32)) -> 0 | L35: =SUMPRODUCT(($A$13:$A$32=$A35)*(L$13:L$32)) -> 0 | M35: =SUMPRODUCT(($A$13:$A$32=$A35)*(M$13:M$32)) -> 0 | N35: =SUMPRODUCT(($A$13:$A$32=$A35)*(N$13:N$32)) -> 0 | O35: =SUMPRODUCT(($A$13:$A$32=$A35)*(O$13:O$32)) -> 0 | P35: =SUMPRODUCT(($A$13:$A$32=$A35)*(P$13:P$32)) -> 0 | ... AX35: =SUMPRODUCT(($A$13:$A$32=$A35)*(AX$13:AX$32)) -> 0
A36: =底稿目录!A10 -> 机器设备 | D36: =SUMPRODUCT(($A$13:$A$32=$A36)*(D$13:D$32)) -> 0 | E36: =SUMPRODUCT(($A$13:$A$32=$A36)*(E$13:E$32)) -> 0 | G36: =SUMPRODUCT(($A$13:$A$32=$A36)*(G$13:G$32)) -> 0 | I36: =SUMPRODUCT(($A$13:$A$32=$A36)*(I$13:I$32)) -> 0 | J36: =SUMPRODUCT(($A$13:$A$32=$A36)*(J$13:J$32)) -> 0 | K36: =SUMPRODUCT(($A$13:$A$32=$A36)*(K$13:K$32)) -> 0 | L36: =SUMPRODUCT(($A$13:$A$32=$A36)*(L$13:L$32)) -> 0 | M36: =SUMPRODUCT(($A$13:$A$32=$A36)*(M$13:M$32)) -> 0 | N36: =SUMPRODUCT(($A$13:$A$32=$A36)*(N$13:N$32)) -> 0 | O36: =SUMPRODUCT(($A$13:$A$32=$A36)*(O$13:O$32)) -> 0 | P36: =SUMPRODUCT(($A$13:$A$32=$A36)*(P$13:P$32)) -> 0 | ... AX36: =SUMPRODUCT(($A$13:$A$32=$A36)*(AX$13:AX$32)) -> 0
A37: =底稿目录!A11 -> 运输设备 | D37: =SUMPRODUCT(($A$13:$A$32=$A37)*(D$13:D$32)) -> 0 | E37: =SUMPRODUCT(($A$13:$A$32=$A37)*(E$13:E$32)) -> 0 | G37: =SUMPRODUCT(($A$13:$A$32=$A37)*(G$13:G$32)) -> 0 | I37: =SUMPRODUCT(($A$13:$A$32=$A37)*(I$13:I$32)) -> 0 | J37: =SUMPRODUCT(($A$13:$A$32=$A37)*(J$13:J$32)) -> 0 | K37: =SUMPRODUCT(($A$13:$A$32=$A37)*(K$13:K$32)) -> 0 | L37: =SUMPRODUCT(($A$13:$A$32=$A37)*(L$13:L$32)) -> 0 | M37: =SUMPRODUCT(($A$13:$A$32=$A37)*(M$13:M$32)) -> 0 | N37: =SUMPRODUCT(($A$13:$A$32=$A37)*(N$13:N$32)) -> 0 | O37: =SUMPRODUCT(($A$13:$A$32=$A37)*(O$13:O$32)) -> 0 | P37: =SUMPRODUCT(($A$13:$A$32=$A37)*(P$13:P$32)) -> 0 | ... AX37: =SUMPRODUCT(($A$13:$A$32=$A37)*(AX$13:AX$32)) -> 0
A38: =底稿目录!A12 -> 办公设备 | D38: =SUMPRODUCT(($A$13:$A$32=$A38)*(D$13:D$32)) -> 0 | E38: =SUMPRODUCT(($A$13:$A$32=$A38)*(E$13:E$32)) -> 0 | G38: =SUMPRODUCT(($A$13:$A$32=$A38)*(G$13:G$32)) -> 0 | I38: =SUMPRODUCT(($A$13:$A$32=$A38)*(I$13:I$32)) -> 0 | J38: =SUMPRODUCT(($A$13:$A$32=$A38)*(J$13:J$32)) -> 0 | K38: =SUMPRODUCT(($A$13:$A$32=$A38)*(K$13:K$32)) -> 0 | L38: =SUMPRODUCT(($A$13:$A$32=$A38)*(L$13:L$32)) -> 0 | M38: =SUMPRODUCT(($A$13:$A$32=$A38)*(M$13:M$32)) -> 0 | N38: =SUMPRODUCT(($A$13:$A$32=$A38)*(N$13:N$32)) -> 0 | O38: =SUMPRODUCT(($A$13:$A$32=$A38)*(O$13:O$32)) -> 0 | P38: =SUMPRODUCT(($A$13:$A$32=$A38)*(P$13:P$32)) -> 0 | ... AX38: =SUMPRODUCT(($A$13:$A$32=$A38)*(AX$13:AX$32)) -> 0
A39: =底稿目录!A13 -> 其他设备 | D39: =SUMPRODUCT(($A$13:$A$32=$A39)*(D$13:D$32)) -> 0 | E39: =SUMPRODUCT(($A$13:$A$32=$A39)*(E$13:E$32)) -> 0 | G39: =SUMPRODUCT(($A$13:$A$32=$A39)*(G$13:G$32)) -> 0 | I39: =SUMPRODUCT(($A$13:$A$32=$A39)*(I$13:I$32)) -> 0 | J39: =SUMPRODUCT(($A$13:$A$32=$A39)*(J$13:J$32)) -> 0 | K39: =SUMPRODUCT(($A$13:$A$32=$A39)*(K$13:K$32)) -> 0 | L39: =SUMPRODUCT(($A$13:$A$32=$A39)*(L$13:L$32)) -> 0 | M39: =SUMPRODUCT(($A$13:$A$32=$A39)*(M$13:M$32)) -> 0 | N39: =SUMPRODUCT(($A$13:$A$32=$A39)*(N$13:N$32)) -> 0 | O39: =SUMPRODUCT(($A$13:$A$32=$A39)*(O$13:O$32)) -> 0 | P39: =SUMPRODUCT(($A$13:$A$32=$A39)*(P$13:P$32)) -> 0 | ... AX39: =SUMPRODUCT(($A$13:$A$32=$A39)*(AX$13:AX$32)) -> 0
A40: 三、审计说明：
A43: 四、审计结论
A46: 提示：
A47: 1.本科目核算企业持有的固定资产原价。建造承包商的临时设施，以及企业购置计算机硬件所附带的、未单独计价的软件，也通过本科目核算。
A48: 2.审计说明可以概述：（1）程序的测试情况、结果；（2）拟调整事项及其调整分录、未调整事项及其影响，审计范围受到限制情况及其影响。
A49: 3.审计结论可参考：A、未见异常。 B、除上述重大不符事项应当作为调整事项予以调整外，其余未见异常。 C、由于存在以下重大未调整事项（或审计范围受到限制无法获取充分、适当证据），不可确认。

Sheet 调整分录汇总H1-3
A1: 致同会计师事务所
A2: 固定资产调整分录汇总表
A3: =底稿目录!A2 -> 被审计单位： | D3: =底稿目录!A4 -> 编制人： | G3: =底稿目录!A5 -> 编制日期： | I3: 索引号： | J3: H1-3
A4: =底稿目录!A3 -> 截止日：202X年12月31日 | D4: =底稿目录!A6 -> 复核人： | G4: =底稿目录!A7 -> 复核日期： | I4: 页 次：
A5: 调整事项说明 | B5: 类别（报表调整/账项调整/其他） | C5: 报表项目 | D5: 科目名称 | E5: 附注项目 | F5: …… | G5: 借方调整金额 | H5: 贷方调整金额 | I5: 索引 | J5: 备注
A24: 提示：本底稿适用于调整分录较多、较复杂的项目，且仅列示与本报表项目相关的审计调整。项目组可根据项目实际情况选择是否使用该底稿。

Sheet 闲置检查表H1-4
A1: 致同会计师事务所
A2: 闲置固定资产检查表
A3: =底稿目录!A2 -> 被审计单位： | E3: =底稿目录!A4 -> 编制人： | G3: =底稿目录!A5 -> 编制日期： | I3: 索引号： | J3: H1-4
A4: =底稿目录!A3 -> 截止日：202X年12月31日 | E4: =底稿目录!A6 -> 复核人： | G4: =底稿目录!A7 -> 复核日期： | I4: 页 次：
A5: 一、审计目标：
A6: 1.资产负债表中记录的固定资产是存在的，且已记录于恰当的账户；
A7: 2.固定资产以恰当的金额包括在财务报表中，与之相关的计价或分摊调整已恰当记录，相关披露已得到恰当计量和描述。
A8: 二、审计过程：
A9: 1.获取暂时闲置固定资产的相关证明文件，并观察其实际状况，是否已按规定计提折旧，相关的会计处理是否正确。
A10: 2.考虑暂时闲置固定资产是否存在减值迹象，……
A11: ①未使用固定资产：
A12: 序号 | B12: 固定资产类别 | C12: 固定资产名称 | D12: 固定资产原值 | E12: 累计折旧 | F12: 减值准备 | G12: 固定资产净值 | H12: 起止时间 | I12: 状况 | J12: 备注
A13: 1 | G13: =D13-E13-F13 -> 0
A14: 2 | G14: =D14-E14-F14 -> 0
A15: 3 | G15: =D15-E15-F15 -> 0
A16: … | G16: =D16-E16-F16 -> 0
A17: 合计 | D17: =SUM(D13:D16) -> 0 | E17: =SUM(E13:E16) -> 0 | F17: =SUM(F13:F16) -> 0 | G17: =SUM(G13:G16) -> 0
A18: ②不需用固定资产：
A19: 序号 | B19: 固定资产类别 | C19: 固定资产名称 | D19: 固定资产原值 | E19: 累计折旧 | F19: 减值准备 | G19: 固定资产净值 | H19: 起止时间 | I19: 状况 | J19: 备注
A20: 1 | G20: =D20-E20-F20 -> 0
A21: 2 | G21: =D21-E21-F21 -> 0
A22: 3 | G22: =D22-E22-F22 -> 0
A23: … | G23: =D23-E23-F23 -> 0
A24: 合计 | D24: =SUM(D20:D23) -> 0 | E24: =SUM(E20:E23) -> 0 | F24: =SUM(F20:F23) -> 0 | G24: =SUM(G20:G23) -> 0
A25: 三、审计说明：
A27: 四、审计结论：
A31: 提示：在停工停产期间应继续计提固定资产折旧和无形资产摊销，并根据用途计入相关资产的成本或当期损益。例如，企业因需求不足而停产或因事故而停工检修等，相关生产设备应当继续计提折旧，并计入营业成本。

Sheet 会计政策估计检查表H1-5
A1: 致同会计师事务所
A2: 固定资产相关会计政策/估计检查表
A3: =底稿目录!A2 -> 被审计单位： | E3: =底稿目录!A4 -> 编制人： | H3: =底稿目录!A5 -> 编制日期： | J3: 索引号： | K3: H1-5
A4: =底稿目录!A3 -> 截止日：202X年12月31日 | E4: =底稿目录!A6 -> 复核人： | H4: =底稿目录!A7 -> 复核日期： | J4: 页 次：
A5: 一、审计目标：
A6: 1.资产负债表中记录的固定资产是存在的，且已记录于恰当的账户；2.所有应记录的固定资产均已记录，所有应当包括在财务报表中的相关披露均已包括；
A7: 3.固定资产以恰当的金额包括在财务报表中，与之相关的计价或分摊调整已恰当记录，相关披露已得到恰当计量和描述
A8: 二、审计过程：
A9: 被审计单位的固定资产折旧政策：
A10: 序号 | B10: 类别 | C10: 折旧年限 | D10: 折旧方法 | E10: 残值率 | F10: 是否符合实际经营情况和会计准则的要求 | G10: 是否与相关资产所包含的经济利益预期实现方式相一致 | H10: 与同行业公司相比，会计政策是否合理 | I10: 是否存在会计政策/会计估计变更 | J10: 会计政策/会计估计变更是否合理 | K10: 备注
A11: 1 | B11: 房屋及建筑物
A12: 2 | B12: 机器设备
A13: 3 | B13: 运输设备
A14: 4 | B14: 办公设备
A15: 5 | B15: 其他设备
A16: 同行业其他公司的固定资产折旧政策
A17: 序号 | B17: 类别 | C17: 同行业公司1 | F17: 同行业公司2 | I17: 同行业公司3
C18: 折旧年限 | D18: 折旧方法 | E18: 残值率 | F18: 折旧年限 | G18: 折旧方法 | H18: 残值率 | I18: 折旧年限 | J18: 折旧方法 | K18: 残值率
A19: 1 | B19: 房屋及建筑物
A20: 2 | B20: 机器设备
A21: 3 | B21: 运输设备
A22: 4 | B22: 办公设备
A23: 5 | B23: 其他设备
B24: 如本期存在会计估计变更，原会计估计如下：
A25: 序号 | B25: 类别 | C25: 使用寿命 | D25: 摊销方法 | E25: 残值率
A26: 1 | B26: 房屋及建筑物
A27: 2 | B27: 机器设备
A28: 3 | B28: 运输设备
A29: 4 | B29: 办公设备
A30: 5 | B30: 其他设备
A31: 三、审计说明：
A34: 四、审计结论：

Sheet 分析表H1-6
A1: 致同会计师事务所
A2: 固定资产分析表
A3: =底稿目录!A2 -> 被审计单位： | C3: =底稿目录!A4 -> 编制人： | D3: =底稿目录!A5 -> 编制日期： | E3: 索引号： | F3: H1-6
A4: =底稿目录!A3 -> 截止日：202X年12月31日 | C4: =底稿目录!A6 -> 复核人： | D4: =底稿目录!A7 -> 复核日期： | E4: 页 次：
A5: 一、审计目标：
A6: 1.资产负债表中记录的固定资产是存在的，且已记录于恰当的账户；
A7: 2.所有应记录的固定资产均已记录，所有应当包括在财务报表中的相关披露均已包括；
A8: 3.固定资产以恰当的金额包括在财务报表中，与之相关的计价或分摊调整已恰当记录，相关披露已得到恰当计量和描述 。
A9: 二、审计过程：
A10: 序号 | B10: 比例 | C10: 2025年 | D10: 2024年 | E10: 变动 | F10: 变动原因及合理性解释
A11: 1 | B11: 固定资产净值÷资产总额 | E11: =C11-D11 -> 0
A12: 2 | B12: 本期计提折旧额÷固定资产原值 | E12: =C12-D12 -> 0
A13: 3 | B13: 累计计提折旧额÷固定资产原值 | E13: =C13-D13 -> 0
A14: 4 | B14: 固定资产减值准备余额÷固定资产原值 | E14: =C14-D14 -> 0
A15: 5 | B15: 固定资产原值÷本期产品产量 | E15: =C15-D15 -> 0
A16: 6 | B16: 租赁资产原值÷固定资产原值 | E16: =C16-D16 -> 0
A17: 7 | B17: 出租租金收入÷固定资产原值 | E17: =C17-D17 -> 0
A18: 8 | B18: 维修费用÷固定资产原值 | E18: =C18-D18 -> 0
A19: 9 | B19: …… | E19: =C19-D19 -> 0
A20: 三、审计说明：
A24: 四、审计结论：
A27: 提示：
A28: 1、分析固定资产的构成及其增减变动情况、增减变动原因，与在建工程、现金流量表、生产能力等相关信息交叉复核，检查固定资产相关金额的合理性和准确性；
A29: 2、分析本期末固定资产减值准备数额占期末固定资产原价的比率，并与期初数比较。

Sheet 增加检查表H1-7
A1: 致同会计师事务所
A2: 固定资产增加检查表
A3: =底稿目录!A2 -> 被审计单位： | F3: =底稿目录!A4 -> 编制人： | N3: =底稿目录!A5 -> 编制日期： | V3: 索引号： | W3: H1-7
A4: =底稿目录!A3 -> 截止日：202X年12月31日 | F4: =底稿目录!A6 -> 复核人： | N4: =底稿目录!A7 -> 复核日期： | V4: 页 次：
A5: 一、审计目标：
A6: 1.资产负债表中记录的固定资产是存在的，且已记录于恰当的账户；2.所有应记录的固定资产均已记录，所有应当包括在财务报表中的相关披露均已包括；
A7: 3.记录的固定资产由被审计单位拥有或控制；4.固定资产以恰当的金额包括在财务报表中，与之相关的计价或分摊调整已恰当记录，相关披露已得到恰当计量和描述。
A8: 二、样本选取标准与规模：
A9: 测试总体： | C9: 如固定资产借方发生额所有凭证共XX笔金额XX | I9: 特定样本： | J9: XX金额以上（大额）、关联方/关联交易形成的款项、XX异常款项全部测试，共XX笔；
A10: 抽样总体： | C10: 测试总体扣除特定样本以外的样本，共XX笔、金额XX | I10: 确定的抽样样本量： | K10: 抽取XX笔 | L10: （如果使用了样本计算器计算样本量，样本量计算过程见<XX>底稿）
A11: 抽样方法： | C11: 随机选样/系统选样/货币单元抽样/随意选样（非统计抽样适用） | I11: 抽样过程： | J11: 使用IDEA（XX抽样工具）选择XX数量、金额XX的样本进行测试，抽样工具中的样本选择过程和结果见<XX>底稿
A12: 三、测试过程：
A13: 测试内容说明：1.原始凭证是否齐全； 2.记账凭证与原始凭证是否相符；3.账务处理是否正确；4.是否记录于恰当的会计期间；5.……
A14: 序号 | B14: 固定资产类别 | C14: 固定资产编号 | D14: 固定资产名称 | E14: 增加日期 | F14: 增加方式 | G14: 入账凭证号 | H14: 对方科目 | I14: 增加情况 | M14: 验收单 | O14: 合同/协议/订单 | R14: 采购发票 | U14: …… | V14: 索引号 | W14: 是否异常 | X14: 检查的关键证据和要素根据被审计单位具体情况修改
I15: 原值 | J15: 累计折旧 | K15: 减值准备 | L15: 净值 | M15: 单据编号 | N15: 验收日期 | O15: 日期/编号 | P15: 对手方名称 | Q15: 金额 | R15: 日期/编号 | S15: 对手方名称 | T15: 金额
A16: 1 | L16: =I16-J16-K16 -> 0
A17: 2 | L17: =I17-J17-K17 -> 0
A18: 3 | L18: =I18-J18-K18 -> 0
A19: 4 | L19: =I19-J19-K19 -> 0
A20: 5 | L20: =I20-J20-K20 -> 0
A21: 6 | L21: =I21-J21-K21 -> 0
A22: 7 | L22: =I22-J22-K22 -> 0
A23: 8 | L23: =I23-J23-K23 -> 0
A24: 9 | L24: =I24-J24-K24 -> 0
A25: 10 | L25: =I25-J25-K25 -> 0
A26: 11 | L26: =I26-J26-K26 -> 0
A27: 12 | L27: =I27-J27-K27 -> 0
... A30: 15 | L30: =I30-J30-K30 -> 0
A31: …… | L31: =I31-J31-K31 -> 0
A32: 合计 | I32: =SUM(I16:I31) -> 0 | J32: =SUM(J16:J31) -> 0 | K32: =SUM(K16:K31) -> 0 | L32: =SUM(L16:L31) -> 0 | Q32: =SUM(Q16:Q31) -> 0 | T32: =SUM(T16:T31) -> 0
A33: 本期新增固定资产合计 | I33: ='明细表H1-2'!N33 -> 0
A34: 检查比例 | I34: =IF(I32=0,0,I32/$I$33) -> 0
A35: 四、审计说明：
A36: 1.如果检查比例较低应扩大检查样本量或说明原因
A37: 2.……
A39: 五、审计结论：
A42: 提示：
A43: 1、本表用于汇总本年度增加固定资产的测试情况。
A44: 2、对于外购固定资产，检查购货合同、发票、保险单、发运凭证等文件，抽查测试其计价是否正确，会计处理是否正确；如果购买固定资产的价款超过正常信用条件延期支付，
A45: 检查实质上是否具有融资性质，固定资产的成本是否以购买价款的现值为基础确定。
A46: 3、对于在建工程转入的固定资产，应检查竣工决算、验收和移交报告是否正确，与在建工程相关的记录是否核对相符，借款费用资本化金额是否恰当；对已经在用或已经
A47: 达到预定可使用状态但尚未办理竣工决算的固定资产，检查其是否已经暂估入账，并按规定计提折旧；检查资本性支出与收益性支出的划分是否恰当；竣工决算完成后，
A48: 是否及时调整。
A49: 4、对于更新改造增加的固定资产，检查增加的固定资产原值是否真实，是否符合资本化条件，增计金额是否超过了该项固定资产的可收回金额；重新确定的剩余折旧年限是否恰当。
... A56: 如果还识别出被审计单位存在可能导致关联方资金占用以及其他套取资金行为的舞弊风险因素，则很可能表面存在第三方配合舞弊，应采取恰当的措施应对。

Sheet 减少检查表H1-8
A1: 致同会计师事务所
A2: 固定资产减少检查表
A3: =底稿目录!A2 -> 被审计单位： | F3: =底稿目录!A4 -> 编制人： | O3: =底稿目录!A5 -> 编制日期： | Y3: 索引号： | Z3: H1-8
A4: =底稿目录!A3 -> 截止日：202X年12月31日 | F4: =底稿目录!A6 -> 复核人： | O4: =底稿目录!A7 -> 复核日期： | Y4: 页 次：
A5: 一、审计目标：
A6: 1.资产负债表中记录的固定资产是存在的，且已记录于恰当的账户；2.所有应记录的固定资产均已记录，所有应当包括在财务报表中的相关披露均已包括；
A7: 3.固定资产以恰当的金额包括在财务报表中，与之相关的计价或分摊调整已恰当记录，相关披露已得到恰当计量和描述。
A8: 二、测试： | C8: 测试原因：大额（）关联方（）大额交易频繁（）异常（）其他（）
A9: 测试内容说明：1.原始凭证是否齐全； 2.记账凭证与原始凭证是否相符；3.账务处理是否正确；4.是否记录于恰当的会计期间；5.……
A10: 序号 | B10: 固定资产类别 | C10: 固定资产编号 | D10: 固定资产名称 | E10: 减少方式 | F10: 减少日期 | G10: 凭证号 | H10: 对方科目 | I10: 减少情况 | P10: 审批单 | R10: 合同/协议/订单 | U10: 发票 | X10: …… | Y10: 索引号 | Z10: 是否异常
I11: 转入清理的固定资产 | M11: 清理净收入 | O11: 清理净损益 | P11: 日期/编号 | Q11: 是否经过恰当审批 | R11: 日期/编号 | S11: 对手方名称 | T11: 金额 | U11: 日期/编号 | V11: 对手方名称 | W11: 金额 | AA11: 检查的关键证据和要素根据被审计单位具体情况修改
I12: 原值 | J12: 累计折旧 | K12: 减值准备 | L12: 净值 | M12: 清理费用 | N12: 清理收入
A13: 1 | L13: =I13-J13-K13 -> 0 | O13: =N13-M13-L13 -> 0
A14: 2 | L14: =I14-J14-K14 -> 0 | O14: =N14-M14-L14 -> 0
A15: 3 | L15: =I15-J15-K15 -> 0 | O15: =N15-M15-L15 -> 0
A16: 4 | L16: =I16-J16-K16 -> 0 | O16: =N16-M16-L16 -> 0
A17: 5 | L17: =I17-J17-K17 -> 0 | O17: =N17-M17-L17 -> 0
A18: 6 | L18: =I18-J18-K18 -> 0 | O18: =N18-M18-L18 -> 0
A19: 7 | L19: =I19-J19-K19 -> 0 | O19: =N19-M19-L19 -> 0
A20: 8 | L20: =I20-J20-K20 -> 0 | O20: =N20-M20-L20 -> 0
A21: 9 | L21: =I21-J21-K21 -> 0 | O21: =N21-M21-L21 -> 0
A22: 10 | L22: =I22-J22-K22 -> 0 | O22: =N22-M22-L22 -> 0
A23: 11 | L23: =I23-J23-K23 -> 0 | O23: =N23-M23-L23 -> 0
A24: 12 | L24: =I24-J24-K24 -> 0 | O24: =N24-M24-L24 -> 0
... A26: 14 | L26: =I26-J26-K26 -> 0 | O26: =N26-M26-L26 -> 0
A27: …… | L27: =I27-J27-K27 -> 0 | O27: =N27-M27-L27 -> 0
A28: 合计 | I28: =SUM(I13:I27) -> 0 | J28: =SUM(J13:J27) -> 0 | K28: =SUM(K13:K27) -> 0 | L28: =SUM(L13:L27) -> 0 | M28: =SUM(M13:M27) -> 0 | N28: =SUM(N13:N27) -> 0 | O28: =SUM(O13:O27) -> 0
A29: 本期减少固定资产合计 | I29: ='明细表H1-2'!O33 -> 0
A30: 检查比例 | I30: =IF(I28=0,0,I28/$I$29) -> 0
A31: 三、审计说明：
A32: 1.如果检查比例较低应扩大检查样本量或说明原因
A33: 2.……
A36: 四、审计结论：
A40: 提示：
A41: 1、本表用于汇总本年度减少固定资产的测试情况。
A42: 2、检查当年减少的固定资产的销账情况，减少的固定资产产生的损益是否及时记入营业外收支科目，账务处理是否与减少固定资产的授权批准文件一致。

Sheet 监盘计划H1-9
A1: 致同会计师事务所
A2: 固定资产监盘计划
A3: =底稿目录!A2 -> 被审计单位： | D3: =底稿目录!A4 -> 编制人： | F3: =底稿目录!A5 -> 编制日期： | H3: 索引号： | I3: H1-9
A4: =底稿目录!A3 -> 截止日：202X年12月31日 | D4: =底稿目录!A6 -> 复核人： | F4: =底稿目录!A7 -> 复核日期： | H4: 页 次：
A5: 一、确定的固定资产存在性认定可能存在重大错报的风险程度：
A7: 二、了解被审计单位固定资产期末状况与管理规定：
A8: （一）固定资产的期末状况：
A9: 1．期末资产状况：截至期末，闲置的资产包括……………，对应的金额 …………
A10: 2．资产存放地点：
B11: 类 别 | C11: 仓库（或场所） | D11: 地点 | E11: 说明
A15: （二）企业定期盘点内部控制制度与执行情况：
A16: 1．制度名称：（提示：按企业内部控制制度名称填写） 索引号：（ ）
A17: （1）规定盘点的时间与次数：
A18: （2）负责盘点的部门： | F18: 负责人：
A19: （提示：如制度规定与实际执行不一致的，应按制度规定与实际负责的部门分别填写）
A20: 2．企业实际盘点情况：
A21: （1）盘点计划安排：
A22: （2）盘点会议情况：
A23: （3）预计安排的盘点人员数量： | F23: 负责人：
A24: （4）对企业盘点计划的评价：
A25: （三）查阅以前年度工作底稿记录：
A26: 1．上一年度监盘时间： | F26: 实施监盘的人员：
A27: 2．抽盘的固定资产范围： | F27: 抽盘比例：
A28: 3．实施监盘中发现的问题与存在的不足：
A29: （提示：上年度如是本所实施监盘的，应当查阅上一年度工作底稿；如不是本所实施审计的，应当在与前任会计师实施沟通程序中安排本项沟通内容。）
A30: 三、评估审计人员的专业胜任能力：
A32: 提示：针对特殊类型的存货，应当评估审计人员是否具备专业胜任能力
A33: 四、盘点计划安排：
A34: （一）预计监盘时间：
A35: （二）预计安排监盘人员数量： | F35: 监盘程序负责人：
A36: （三）预计监盘的固定资产范围：
A37: 1.类别范围
A38: 类别 | B38: 期末余额 | C38: 减值准备 | D38: 账面净值 | E38: 计量单位 | F38: 数量 | G38: 计划监盘数量 | H38: 计划监盘金额 | I38: 监盘比例
A42: 合计： | B42: =SUM(B39:B41) -> 0 | C42: =SUM(C39:C41) -> 0 | D42: =SUM(D39:D41) -> 0 | E42: =SUM(E39:E41) -> 0 | F42: =SUM(F39:F41) -> 0 | G42: =SUM(G39:G41) -> 0 | H42: =SUM(H39:H41) -> 0 | I42: =SUM(I39:I41) -> 0
A43: 2．地点范围：
A44: （四）拟实施的盘点方法：
A45: （五）就监盘计划与管理层沟通事项
A46: 1．时间： | E46: 2.管理层人员：
A47: 3．审计小组参与人员：
A48: （六）针对被审计单位具体情况，需要向管理层提出的监盘的特殊要求：
A49: （七）预计监盘中抽取样本的方法与数量
A50: 1．从会计明细账簿中选取样本的方法： | G50: 预计选取数量： | I50: =F42 -> 0
A51: 2．从实际固定资产中选取样本的方法： | G51: 预计选取数量： | I51: 1
A52: （八）实际监盘时点至资产负债表日的推算方法：
A53: 1．推断方法说明：
A55: 2．预计拟要求的盘点复盘比例： | D55: 235

Sheet 盘点检查表H1-10
A1: 致同会计师事务所
A2: 固定资产盘点检查表
A3: =底稿目录!A2 -> 被审计单位： | E3: =底稿目录!A4 -> 编制人： | I3: =底稿目录!A5 -> 编制日期： | L3: 索引号： | M3: H1-10
A4: =底稿目录!A3 -> 截止日：202X年12月31日 | E4: =底稿目录!A6 -> 复核人： | I4: =底稿目录!A7 -> 复核日期： | L4: 页 次：
A5: 一、审计目标：
A6: 1.资产负债表中记录的固定资产是存在的，且已记录于恰当的账户；2.记录的固定资产由被审计单位拥有或控制；
A7: 3.固定资产以恰当的金额包括在财务报表中，与之相关的计价或分摊调整已恰当记录，相关披露已得到恰当计量和描述 。
A8: 二、样本选取标准与规模：
A9: 测试总体： | B9: 如期末固定资产数量XX、金额XX | G9: 特定样本： | H9: XX金额以上（大额）、关联方/关联交易形成的款项、XX异常款项全部测试，共XX笔；
A10: 抽样总体： | B10: 测试总体扣除特定样本以外的样本，数量XX、金额XX | G10: 确定的抽样样本量： | H10: 抽取XX笔 | I10: （如果使用了样本计算器计算样本量，样本量计算过程见<XX>底稿）
A11: 抽样方法： | B11: 随机选样/系统选样/货币单元抽样/随意选样（非统计抽样适用） | G11: 抽样过程： | H11: 使用IDEA（XX抽样工具）选择XX数量、金额XX的样本进行测试，抽样工具中的样本选择过程和结果见<XX>底稿
A12: 三、审计过程：
A13: 抽盘地点：______________ | C13: 盘点人员： | D13: 被审计单位仓库盘点人和财务监盘人签字 | I13: 监盘人员： | J13: （审计人员签字） | L13: 盘点时间：__________________
A14: （一）从固定资产盘点记录中选取项目追查至固定资产实物
A15: 固定资产名称/类别 | B15: 资产编号 | C15: 规格 | D15: 单位 | E15: 单价 | F15: 盘点前财务账面记录 | H15: 企业盘点记录数量 | I15: 抽盘数量 | J15: 抽盘与账面差异（+盈-亏） | K15: 抽盘与企业盘点差异 | L15: 企业盘点与账面差异 | M15: 品质状况（正常/闲置/毁损等）
F16: 数量 | G16: 金额
J17: =I17-F17 -> 0 | K17: =I17-H17 -> 0 | L17: =H17-F17 -> 0
J18: =I18-F18 -> 0 | K18: =I18-H18 -> 0 | L18: =H18-F18 -> 0
J19: =I19-F19 -> 0 | K19: =I19-H19 -> 0 | L19: =H19-F19 -> 0
J20: =I20-F20 -> 0 | K20: =I20-H20 -> 0 | L20: =H20-F20 -> 0
J21: =I21-F21 -> 0 | K21: =I21-H21 -> 0 | L21: =H21-F21 -> 0
J22: =I22-F22 -> 0 | K22: =I22-H22 -> 0 | L22: =H22-F22 -> 0
J23: =I23-F23 -> 0 | K23: =I23-H23 -> 0 | L23: =H23-F23 -> 0
J24: =I24-F24 -> 0 | K24: =I24-H24 -> 0 | L24: =H24-F24 -> 0
J25: =I25-F25 -> 0 | K25: =I25-H25 -> 0 | L25: =H25-F25 -> 0
J26: =I26-F26 -> 0 | K26: =I26-H26 -> 0 | L26: =H26-F26 -> 0
A27: 合计 | F27: =SUM(F17:F26) -> 0 | G27: =SUM(G17:G26) -> 0 | H27: =SUM(H17:H26) -> 0 | I27: =SUM(I17:I26) -> 0 | J27: =SUM(J17:J26) -> 0 | K27: =SUM(K17:K26) -> 0 | L27: =SUM(L17:L26) -> 0
A28: 期末固定资产原值合计：
A29: 抽取样本占期末原值合计的比例：（%） | G29: =G27/G28 -> #DIV/0!
A31: （二）从固定资产实物中选取项目追查至固定资产盘点记录
A32: 固定资产名称/类别 | B32: 资产编号 | C32: 规格 | D32: 单位 | E32: 单价 | F32: 盘点前财务账面记录 | H32: 企业盘点记录数量 | I32: 抽盘数量 | J32: 抽盘与账面差异（+盈-亏） | K32: 抽盘与企业盘点差异 | L32: 企业盘点与账面差异 | M32: 品质状况（正常/闲着/毁损等）
F33: 数量 | G33: 金额
J34: =I34-F34 -> 0 | K34: =I34-H34 -> 0 | L34: =H34-F34 -> 0
J35: =I35-F35 -> 0 | K35: =I35-H35 -> 0 | L35: =H35-F35 -> 0
J36: =I36-F36 -> 0 | K36: =I36-H36 -> 0 | L36: =H36-F36 -> 0
J37: =I37-F37 -> 0 | K37: =I37-H37 -> 0 | L37: =H37-F37 -> 0
J38: =I38-F38 -> 0 | K38: =I38-H38 -> 0 | L38: =H38-F38 -> 0
J39: =I39-F39 -> 0 | K39: =I39-H39 -> 0 | L39: =H39-F39 -> 0
J40: =I40-F40 -> 0 | K40: =I40-H40 -> 0 | L40: =H40-F40 -> 0
J41: =I41-F41 -> 0 | K41: =I41-H41 -> 0 | L41: =H41-F41 -> 0
J42: =I42-F42 -> 0 | K42: =I42-H42 -> 0 | L42: =H42-F42 -> 0
J43: =I43-F43 -> 0 | K43: =I43-H43 -> 0 | L43: =H43-F43 -> 0
J44: =I44-F44 -> 0 | K44: =I44-H44 -> 0 | L44: =H44-F44 -> 0
A45: 合计 | F45: =SUM(F34:F44) -> 0 | G45: =SUM(G34:G44) -> 0 | H45: =SUM(H34:H44) -> 0 | I45: =SUM(I34:I44) -> 0 | J45: =SUM(J34:J44) -> 0 | K45: =SUM(K34:K44) -> 0 | L45: =SUM(L34:L44) -> 0
A46: 期末固定资产原值合计：
A47: 抽取样本占期末原值合计的比例：（%） | G47: =G45/G46 -> #DIV/0!
A49: 四、审计说明：
A52: 五、审计结论：
A55: 提示：
A56: 1、本表可作为固定资产盘点汇总表或盘点明细表或固定资产抽盘表。
A57: 2、财务账面记录与资产管理管理部门账面记录应一致，若存在差异应调整一致。
A58: 3、财务账面记录与实际盘点记录的差异构成盘盈/盘亏，应根据具体原因分析处理。应说明企业的处理结果。
A59: 4、盘点时，应关注易移动的“存量资产”及可能发生减值的“存量资产”；
A60: 5、盘点时应关注资产的品质状况（影响减值准备的计提）。

Sheet 监盘小结H1-11
A1: 致同会计师事务所
A2: 固定资产监盘小结
A3: =底稿目录!A2 -> 被审计单位： | D3: =底稿目录!A4 -> 编制人： | F3: =底稿目录!A5 -> 编制日期： | H3: 索引号： | I3: H1-11
A4: =底稿目录!A3 -> 截止日：202X年12月31日 | D4: =底稿目录!A6 -> 复核人： | F4: =底稿目录!A7 -> 复核日期： | H4: 页 次：
A5: 一、资产负债表日：
A7: 二、主要资产存放情况（房屋建筑物及主要机器设备）：
A8: 提示：房屋建筑物地点请核对房产证记载的地点，有多处房产的，请逐一说明
A9: 序号 | B9: 资产类别 | C9: 资产名称 | D9: 存放地点
A10: 1
A11: 2
A12: 3
A13: 三、了解资产管理情况
A14: 序号 | B14: 项目
A15: 1 | B15: 资产管理部门：
A16: 2 | B16: 管理人员：
A17: 3 | B17: 资产是否具有管理标识：
A18: 4 | B18: 资产是否具有定期保养制度：
A19: 5 | B19: 大修理周期时间：
A20: 6 | B20: 资产明细账（卡）是否完整：
A21: 7 | B21: 资产明细账（卡）的各项记录是否完整：
A22: 三、参与盘点人员：
A23: 1． 被审计单位的人员：
A24: 序号 | B24: 盘点人员所属部门 | C24: 人员数量 | D24: 人员名称 | E24: 所负责的部分
A25: 1
A26: 2
A27: 3
A28: 2． 审计人员：
A29: 序号 | B29: 人员名称 | C29: 负责的部分
A30: 1
A31: 2
A32: 3
A33: 四、实际盘点前的检查程序：
A34: 1．资产现场观察说明：
A35: 2．盘点前检查程序：
A36: （1）资产明细账（卡） 是否获取： | G36: 索引：
A37: （2）固定资产管理制度 是否获取： | G37: 索引：
A38: （3）固定资产维修制度是否获取： | G38: 索引：
A39: （4）获取或编制资产位置简图： | G39: 索引：
A40: 五、实际盘点时间：
A41: 实际监盘（盘点）日： | E41: 开始时间： | H41: 结束时间：
A42: 六、企业实际盘点情况说明
A43: （一）企业实际盘点人员
A44: 部门： | E44: 姓名： | H44: 岗位：
A45: 部门： | E45: 姓名： | H45: 岗位：
A46: 部门： | E46: 姓名： | H46: 岗位：
A47: 盘点人员共分 | D47: 组，其中：
A48: 第一组： | D48: 点数并报出型号、规格， | H48: 记录
A49: 第二组： | D49: 点数并报出型号、规格， | H49: 记录
A50: 第三组： | D50: 点数并报出型号、规格， | H50: 记录
A51: （二）特殊情况说明：
A52: 七、审计人员复盘记录：
A53: （一）抽盘样本确定方法
A54: 1．从会计明细账中抽取的方法
A55: 2．从实物资产中抽取样本的方法
A56: （二）盘点方法：
A57: 1．盘点人员共分 | D57: 组，其中：
A58: 2．第一组： | E58: 负责监盘的固定资产类别：
C59: 点数并报出型号、规格， | H59: 记录
A60: 第二组： | E60: 负责监盘的固定资产类别：
C61: 点数并报出型号、规格， | H61: 记录
A62: 第三组： | E62: 负责监盘的固定资产类别：
C63: 点数并报出型号、规格， | H63: 记录
A64: 3. 固定资产是否停止流动
A65: 4．监盘中特殊情况说明：
A66: 上述人员在盘点过程中，除 | F66: 外，自始至终未离开现场 是（ ） 否（ ）。
A67: （三）审计人员实际抽盘情况 | G67: 底稿索引：
A68: 1．房屋建筑物盘点说明：
A69: （1）房产证上记载的房屋栋号与会计账簿记载的资产名称是否能对应：
A70: 房屋土地使用权审核工作底稿检查记录索引：
A71: （2）房产证上记载的房屋数量与会计账簿记载的数量是否一致：
A72: 检查记录索引：（ ）（提示：如无法核对的，应当说明情况）
A73: （3）抽查房产证上记载的房屋面积与会计账簿记载的面积是否一致：
A74: 检查记录索引：（ ）（提示：如无法核对的，应当说明情况）
A75: （4）是否存在有证无房或有房无证的情况：
A76: （5）其他情况：
A77: 2．机器设备盘点说明：
A78: （1）相同类型的设备是否具有可供识别的管理标识，并能清晰区分：
A79: 管理标识编号规则： | G79: 检查记录索引：
A80: （2）各型号设备数量是否与会计账簿记载的数量一致： | G80: 检查记录索引：
A81: （3）是否存在不需用的设备：
A82: （4）是否存在实际已报废、毁损而会计账簿仍记载的设备：
A83: （5）是否存在实际已使用而会计账簿未记载的设备：
A84: （6）对主要设备是否获取或编制设备位置简图并能按图核对：
A85: （7）对设备管道是否获取或编制走向图并能按图核对：
A86: （8）对电力设备（如大型变电设备）是否检查其权属状况：
A87: 3．运输设备盘点说明：
A88: （1） 是否在现场核对设备所有权证与设备情况：检查记录索引：
A89: （2） 是否按检查设备所有权证予以证实资产的存在性：检查记录索引：
A90: （3） 对处于工作途中的设备确认其存在性的方法说明：检查记录索引：
A91: （4） 是否存在不需用的设备：
A92: （5） 是否存在实际已报废、毁损而会计账簿仍记载的设备：
... A103: 九、复盘记录：（提示：应按照审计准则规定确定复盘的样本）
A104: 1、复盘人员： | F104: 复盘底稿记录索引：
A105: 2、复盘统计：
A106: 设备共有 | C106: 台（套），实施复盘共： | G106: 台（套），占
A107: 固定资产账面余额： | E107: 元，实施复盘： | H107: 元，占
A108: 倒退至资产负债表日是否存在尚未购入且未入账的资产：
A109: 倒退至资产负债表日分析是否存在已报废与处置的资产：
A110: 本次复盘的资产余额合计占资产负债表日的固定资产余额 | G110: %
A111: 3、计算复盘正确率：
...

Sheet 折旧测算表（不含减值）-直线法H1-12
A1: 致同会计师事务所
A2: 固定资产折旧测算表
A3: =底稿目录!A2 -> 被审计单位： | G3: =底稿目录!A4 -> 编制人： | M3: =底稿目录!A5 -> 编制日期： | R3: 索引号： | S3: H1-12
A4: =底稿目录!A3 -> 截止日：202X年12月31日 | G4: =底稿目录!A6 -> 复核人： | M4: =底稿目录!A7 -> 复核日期： | R4: 页 次：
A5: 一、审计目标：固定资产以恰当的金额包括在财务报表中，与之相关的计价或分摊调整已恰当记录，相关披露已得到恰当计量和描述。
A6: 二、审计过程：
A7: 折旧期初： | C7: 折旧期末： | E7: 各列顺序请根据需要进行调整，行数请根据需要增加。非公式列输入数据时请使用“选择性粘贴-数值”。
A8: 固定资产类别 | B8: 固定资产编号 | C8: 固定资产名称 | D8: 管理部门 | E8: 原值 （期末） | F8: 累计折旧（期末） | G8: 开始使用日期 | H8: 使用年限 | I8: 残值率 | J8: 账面月折旧额 | K8: 使用月限 | L8: 测算到期日 | M8: 已提折旧月份 | N8: 本期折旧月份 | O8: 测算月折旧 | P8: 当期折旧费用 | Q8: 月折旧额差异 | R8: 累计折旧费用 | S8: 累计折旧额差异
A9: ='明细表H1-2'!A13 -> 0 | B9: ='明细表H1-2'!B13 -> 0 | C9: ='明细表H1-2'!C13 -> 0 | E9: ='明细表H1-2'!P13 -> 0 | F9: ='明细表H1-2'!AE13 -> 0 | K9: =IF(H9=0,0,IF(RIGHT(H9,1)<>"年",H9*12,IF(LEN(H9)=3,VALUE(LEFT(H9,2))*12,IF(LEN(H9)=2,VALUE(LEFT(H9,1))*12,"??")))) -> 0 | L9: =DATE((YEAR(G9)+H9),MONTH(G9),DAY(G9)) -> 0 | M9: =MIN((YEAR(L9)-YEAR(G9))*12+(MONTH(L9)-MONTH(G9)),(YEAR($D$7)-YEAR(G9))*12+MONTH($D$7)-MONTH(G9),H9*12) -> 0 | N9: =IF(YEAR(L9)=YEAR($D$7),12-(MONTH($D$7)-MONTH(L9)),(IF(L9<$B$7,0,IF($D$7>L9,MIN(MONTH($D$7),DATEDIF(DATE(YEAR(G9),MONTH(G9),"1"),$D$7,"M")-DATEDIF(DATE(YEAR(G9),MONTH(G9),"1"),DATEDIF(YEAR(L9),MONTH(L9),"1"),"M")),MIN(DATEDIF(DATE(YEAR(G9),MONTH(G9),"1"),$D$7,"m"),MONTH($D$7)))))) -> 12 | O9: =IF(K9=0,0,ROUND(((1-I9)/K9)*E9,4)) -> 0 | P9: =ROUND(O9*N9,2) -> 0 | Q9: =ROUND(J9-O9,2) -> 0 | R9: =ROUND(O9*M9,2) -> 0 | S9: =ROUND(F9-R9,2) -> 0
A10: ='明细表H1-2'!A14 -> 0 | B10: ='明细表H1-2'!B14 -> 0 | C10: ='明细表H1-2'!C14 -> 0 | E10: ='明细表H1-2'!P14 -> 0 | F10: ='明细表H1-2'!AE14 -> 0 | K10: =IF(H10=0,0,IF(RIGHT(H10,1)<>"年",H10*12,IF(LEN(H10)=3,VALUE(LEFT(H10,2))*12,IF(LEN(H10)=2,VALUE(LEFT(H10,1))*12,"??")))) -> 0 | L10: =DATE((YEAR(G10)+H10),MONTH(G10),DAY(G10)) -> 0 | M10: =MIN((YEAR(L10)-YEAR(G10))*12+(MONTH(L10)-MONTH(G10)),(YEAR($D$7)-YEAR(G10))*12+MONTH($D$7)-MONTH(G10),H10*12) -> 0 | N10: =IF(YEAR(L10)=YEAR($D$7),12-(MONTH($D$7)-MONTH(L10)),(IF(L10<$B$7,0,IF($D$7>L10,MIN(MONTH($D$7),DATEDIF(DATE(YEAR(G10),MONTH(G10),"1"),$D$7,"M")-DATEDIF(DATE(YEAR(G10),MONTH(G10),"1"),DATEDIF(YEAR(L10),MONTH(L10),"1"),"M")),MIN(DATEDIF(DATE(YEAR(G10),MONTH(G10),"1"),$D$7,"m"),MONTH($D$7)))))) -> 12 | O10: =IF(K10=0,0,ROUND(((1-I10)/K10)*E10,4)) -> 0 | P10: =ROUND(O10*N10,2) -> 0 | Q10: =ROUND(J10-O10,2) -> 0 | R10: =ROUND(O10*M10,2) -> 0 | S10: =ROUND(F10-R10,2) -> 0
A11: ='明细表H1-2'!A15 -> 0 | B11: ='明细表H1-2'!B15 -> 0 | C11: ='明细表H1-2'!C15 -> 0 | E11: ='明细表H1-2'!P15 -> 0 | F11: ='明细表H1-2'!AE15 -> 0 | K11: =IF(H11=0,0,IF(RIGHT(H11,1)<>"年",H11*12,IF(LEN(H11)=3,VALUE(LEFT(H11,2))*12,IF(LEN(H11)=2,VALUE(LEFT(H11,1))*12,"??")))) -> 0 | L11: =DATE((YEAR(G11)+H11),MONTH(G11),DAY(G11)) -> 0 | M11: =MIN((YEAR(L11)-YEAR(G11))*12+(MONTH(L11)-MONTH(G11)),(YEAR($D$7)-YEAR(G11))*12+MONTH($D$7)-MONTH(G11),H11*12) -> 0 | N11: =IF(YEAR(L11)=YEAR($D$7),12-(MONTH($D$7)-MONTH(L11)),(IF(L11<$B$7,0,IF($D$7>L11,MIN(MONTH($D$7),DATEDIF(DATE(YEAR(G11),MONTH(G11),"1"),$D$7,"M")-DATEDIF(DATE(YEAR(G11),MONTH(G11),"1"),DATEDIF(YEAR(L11),MONTH(L11),"1"),"M")),MIN(DATEDIF(DATE(YEAR(G11),MONTH(G11),"1"),$D$7,"m"),MONTH($D$7)))))) -> 12 | O11: =IF(K11=0,0,ROUND(((1-I11)/K11)*E11,4)) -> 0 | P11: =ROUND(O11*N11,2) -> 0 | Q11: =ROUND(J11-O11,2) -> 0 | R11: =ROUND(O11*M11,2) -> 0 | S11: =ROUND(F11-R11,2) -> 0
A12: ='明细表H1-2'!A16 -> 0 | B12: ='明细表H1-2'!B16 -> 0 | C12: ='明细表H1-2'!C16 -> 0 | E12: ='明细表H1-2'!P16 -> 0 | F12: ='明细表H1-2'!AE16 -> 0 | K12: =IF(H12=0,0,IF(RIGHT(H12,1)<>"年",H12*12,IF(LEN(H12)=3,VALUE(LEFT(H12,2))*12,IF(LEN(H12)=2,VALUE(LEFT(H12,1))*12,"??")))) -> 0 | L12: =DATE((YEAR(G12)+H12),MONTH(G12),DAY(G12)) -> 0 | M12: =MIN((YEAR(L12)-YEAR(G12))*12+(MONTH(L12)-MONTH(G12)),(YEAR($D$7)-YEAR(G12))*12+MONTH($D$7)-MONTH(G12),H12*12) -> 0 | N12: =IF(YEAR(L12)=YEAR($D$7),12-(MONTH($D$7)-MONTH(L12)),(IF(L12<$B$7,0,IF($D$7>L12,MIN(MONTH($D$7),DATEDIF(DATE(YEAR(G12),MONTH(G12),"1"),$D$7,"M")-DATEDIF(DATE(YEAR(G12),MONTH(G12),"1"),DATEDIF(YEAR(L12),MONTH(L12),"1"),"M")),MIN(DATEDIF(DATE(YEAR(G12),MONTH(G12),"1"),$D$7,"m"),MONTH($D$7)))))) -> 12 | O12: =IF(K12=0,0,ROUND(((1-I12)/K12)*E12,4)) -> 0 | P12: =ROUND(O12*N12,2) -> 0 | Q12: =ROUND(J12-O12,2) -> 0 | R12: =ROUND(O12*M12,2) -> 0 | S12: =ROUND(F12-R12,2) -> 0
A13: ='明细表H1-2'!A17 -> 0 | B13: ='明细表H1-2'!B17 -> 0 | C13: ='明细表H1-2'!C17 -> 0 | E13: ='明细表H1-2'!P17 -> 0 | F13: ='明细表H1-2'!AE17 -> 0 | K13: =IF(H13=0,0,IF(RIGHT(H13,1)<>"年",H13*12,IF(LEN(H13)=3,VALUE(LEFT(H13,2))*12,IF(LEN(H13)=2,VALUE(LEFT(H13,1))*12,"??")))) -> 0 | L13: =DATE((YEAR(G13)+H13),MONTH(G13),DAY(G13)) -> 0 | M13: =MIN((YEAR(L13)-YEAR(G13))*12+(MONTH(L13)-MONTH(G13)),(YEAR($D$7)-YEAR(G13))*12+MONTH($D$7)-MONTH(G13),H13*12) -> 0 | N13: =IF(YEAR(L13)=YEAR($D$7),12-(MONTH($D$7)-MONTH(L13)),(IF(L13<$B$7,0,IF($D$7>L13,MIN(MONTH($D$7),DATEDIF(DATE(YEAR(G13),MONTH(G13),"1"),$D$7,"M")-DATEDIF(DATE(YEAR(G13),MONTH(G13),"1"),DATEDIF(YEAR(L13),MONTH(L13),"1"),"M")),MIN(DATEDIF(DATE(YEAR(G13),MONTH(G13),"1"),$D$7,"m"),MONTH($D$7)))))) -> 12 | O13: =IF(K13=0,0,ROUND(((1-I13)/K13)*E13,4)) -> 0 | P13: =ROUND(O13*N13,2) -> 0 | Q13: =ROUND(J13-O13,2) -> 0 | R13: =ROUND(O13*M13,2) -> 0 | S13: =ROUND(F13-R13,2) -> 0
A14: ='明细表H1-2'!A18 -> 0 | B14: ='明细表H1-2'!B18 -> 0 | C14: ='明细表H1-2'!C18 -> 0 | E14: ='明细表H1-2'!P18 -> 0 | F14: ='明细表H1-2'!AE18 -> 0 | K14: =IF(H14=0,0,IF(RIGHT(H14,1)<>"年",H14*12,IF(LEN(H14)=3,VALUE(LEFT(H14,2))*12,IF(LEN(H14)=2,VALUE(LEFT(H14,1))*12,"??")))) -> 0 | L14: =DATE((YEAR(G14)+H14),MONTH(G14),DAY(G14)) -> 0 | M14: =MIN((YEAR(L14)-YEAR(G14))*12+(MONTH(L14)-MONTH(G14)),(YEAR($D$7)-YEAR(G14))*12+MONTH($D$7)-MONTH(G14),H14*12) -> 0 | N14: =IF(YEAR(L14)=YEAR($D$7),12-(MONTH($D$7)-MONTH(L14)),(IF(L14<$B$7,0,IF($D$7>L14,MIN(MONTH($D$7),DATEDIF(DATE(YEAR(G14),MONTH(G14),"1"),$D$7,"M")-DATEDIF(DATE(YEAR(G14),MONTH(G14),"1"),DATEDIF(YEAR(L14),MONTH(L14),"1"),"M")),MIN(DATEDIF(DATE(YEAR(G14),MONTH(G14),"1"),$D$7,"m"),MONTH($D$7)))))) -> 12 | O14: =IF(K14=0,0,ROUND(((1-I14)/K14)*E14,4)) -> 0 | P14: =ROUND(O14*N14,2) -> 0 | Q14: =ROUND(J14-O14,2) -> 0 | R14: =ROUND(O14*M14,2) -> 0 | S14: =ROUND(F14-R14,2) -> 0
A15: ='明细表H1-2'!A19 -> 0 | B15: ='明细表H1-2'!B19 -> 0 | C15: ='明细表H1-2'!C19 -> 0 | E15: ='明细表H1-2'!P19 -> 0 | F15: ='明细表H1-2'!AE19 -> 0 | K15: =IF(H15=0,0,IF(RIGHT(H15,1)<>"年",H15*12,IF(LEN(H15)=3,VALUE(LEFT(H15,2))*12,IF(LEN(H15)=2,VALUE(LEFT(H15,1))*12,"??")))) -> 0 | L15: =DATE((YEAR(G15)+H15),MONTH(G15),DAY(G15)) -> 0 | M15: =MIN((YEAR(L15)-YEAR(G15))*12+(MONTH(L15)-MONTH(G15)),(YEAR($D$7)-YEAR(G15))*12+MONTH($D$7)-MONTH(G15),H15*12) -> 0 | N15: =IF(YEAR(L15)=YEAR($D$7),12-(MONTH($D$7)-MONTH(L15)),(IF(L15<$B$7,0,IF($D$7>L15,MIN(MONTH($D$7),DATEDIF(DATE(YEAR(G15),MONTH(G15),"1"),$D$7,"M")-DATEDIF(DATE(YEAR(G15),MONTH(G15),"1"),DATEDIF(YEAR(L15),MONTH(L15),"1"),"M")),MIN(DATEDIF(DATE(YEAR(G15),MONTH(G15),"1"),$D$7,"m"),MONTH($D$7)))))) -> 12 | O15: =IF(K15=0,0,ROUND(((1-I15)/K15)*E15,4)) -> 0 | P15: =ROUND(O15*N15,2) -> 0 | Q15: =ROUND(J15-O15,2) -> 0 | R15: =ROUND(O15*M15,2) -> 0 | S15: =ROUND(F15-R15,2) -> 0
A16: ='明细表H1-2'!A20 -> 0 | B16: ='明细表H1-2'!B20 -> 0 | C16: ='明细表H1-2'!C20 -> 0 | E16: ='明细表H1-2'!P20 -> 0 | F16: ='明细表H1-2'!AE20 -> 0 | K16: =IF(H16=0,0,IF(RIGHT(H16,1)<>"年",H16*12,IF(LEN(H16)=3,VALUE(LEFT(H16,2))*12,IF(LEN(H16)=2,VALUE(LEFT(H16,1))*12,"??")))) -> 0 | L16: =DATE((YEAR(G16)+H16),MONTH(G16),DAY(G16)) -> 0 | M16: =MIN((YEAR(L16)-YEAR(G16))*12+(MONTH(L16)-MONTH(G16)),(YEAR($D$7)-YEAR(G16))*12+MONTH($D$7)-MONTH(G16),H16*12) -> 0 | N16: =IF(YEAR(L16)=YEAR($D$7),12-(MONTH($D$7)-MONTH(L16)),(IF(L16<$B$7,0,IF($D$7>L16,MIN(MONTH($D$7),DATEDIF(DATE(YEAR(G16),MONTH(G16),"1"),$D$7,"M")-DATEDIF(DATE(YEAR(G16),MONTH(G16),"1"),DATEDIF(YEAR(L16),MONTH(L16),"1"),"M")),MIN(DATEDIF(DATE(YEAR(G16),MONTH(G16),"1"),$D$7,"m"),MONTH($D$7)))))) -> 12 | O16: =IF(K16=0,0,ROUND(((1-I16)/K16)*E16,4)) -> 0 | P16: =ROUND(O16*N16,2) -> 0 | Q16: =ROUND(J16-O16,2) -> 0 | R16: =ROUND(O16*M16,2) -> 0 | S16: =ROUND(F16-R16,2) -> 0
A17: ='明细表H1-2'!A21 -> 0 | B17: ='明细表H1-2'!B21 -> 0 | C17: ='明细表H1-2'!C21 -> 0 | E17: ='明细表H1-2'!P21 -> 0 | F17: ='明细表H1-2'!AE21 -> 0 | K17: =IF(H17=0,0,IF(RIGHT(H17,1)<>"年",H17*12,IF(LEN(H17)=3,VALUE(LEFT(H17,2))*12,IF(LEN(H17)=2,VALUE(LEFT(H17,1))*12,"??")))) -> 0 | L17: =DATE((YEAR(G17)+H17),MONTH(G17),DAY(G17)) -> 0 | M17: =MIN((YEAR(L17)-YEAR(G17))*12+(MONTH(L17)-MONTH(G17)),(YEAR($D$7)-YEAR(G17))*12+MONTH($D$7)-MONTH(G17),H17*12) -> 0 | N17: =IF(YEAR(L17)=YEAR($D$7),12-(MONTH($D$7)-MONTH(L17)),(IF(L17<$B$7,0,IF($D$7>L17,MIN(MONTH($D$7),DATEDIF(DATE(YEAR(G17),MONTH(G17),"1"),$D$7,"M")-DATEDIF(DATE(YEAR(G17),MONTH(G17),"1"),DATEDIF(YEAR(L17),MONTH(L17),"1"),"M")),MIN(DATEDIF(DATE(YEAR(G17),MONTH(G17),"1"),$D$7,"m"),MONTH($D$7)))))) -> 12 | O17: =IF(K17=0,0,ROUND(((1-I17)/K17)*E17,4)) -> 0 | P17: =ROUND(O17*N17,2) -> 0 | Q17: =ROUND(J17-O17,2) -> 0 | R17: =ROUND(O17*M17,2) -> 0 | S17: =ROUND(F17-R17,2) -> 0
A18: ='明细表H1-2'!A22 -> 0 | B18: ='明细表H1-2'!B22 -> 0 | C18: ='明细表H1-2'!C22 -> 0 | E18: ='明细表H1-2'!P22 -> 0 | F18: ='明细表H1-2'!AE22 -> 0 | K18: =IF(H18=0,0,IF(RIGHT(H18,1)<>"年",H18*12,IF(LEN(H18)=3,VALUE(LEFT(H18,2))*12,IF(LEN(H18)=2,VALUE(LEFT(H18,1))*12,"??")))) -> 0 | L18: =DATE((YEAR(G18)+H18),MONTH(G18),DAY(G18)) -> 0 | M18: =MIN((YEAR(L18)-YEAR(G18))*12+(MONTH(L18)-MONTH(G18)),(YEAR($D$7)-YEAR(G18))*12+MONTH($D$7)-MONTH(G18),H18*12) -> 0 | N18: =IF(YEAR(L18)=YEAR($D$7),12-(MONTH($D$7)-MONTH(L18)),(IF(L18<$B$7,0,IF($D$7>L18,MIN(MONTH($D$7),DATEDIF(DATE(YEAR(G18),MONTH(G18),"1"),$D$7,"M")-DATEDIF(DATE(YEAR(G18),MONTH(G18),"1"),DATEDIF(YEAR(L18),MONTH(L18),"1"),"M")),MIN(DATEDIF(DATE(YEAR(G18),MONTH(G18),"1"),$D$7,"m"),MONTH($D$7)))))) -> 12 | O18: =IF(K18=0,0,ROUND(((1-I18)/K18)*E18,4)) -> 0 | P18: =ROUND(O18*N18,2) -> 0 | Q18: =ROUND(J18-O18,2) -> 0 | R18: =ROUND(O18*M18,2) -> 0 | S18: =ROUND(F18-R18,2) -> 0
A19: ='明细表H1-2'!A23 -> 0 | B19: ='明细表H1-2'!B23 -> 0 | C19: ='明细表H1-2'!C23 -> 0 | E19: ='明细表H1-2'!P23 -> 0 | F19: ='明细表H1-2'!AE23 -> 0 | K19: =IF(H19=0,0,IF(RIGHT(H19,1)<>"年",H19*12,IF(LEN(H19)=3,VALUE(LEFT(H19,2))*12,IF(LEN(H19)=2,VALUE(LEFT(H19,1))*12,"??")))) -> 0 | L19: =DATE((YEAR(G19)+H19),MONTH(G19),DAY(G19)) -> 0 | M19: =MIN((YEAR(L19)-YEAR(G19))*12+(MONTH(L19)-MONTH(G19)),(YEAR($D$7)-YEAR(G19))*12+MONTH($D$7)-MONTH(G19),H19*12) -> 0 | N19: =IF(YEAR(L19)=YEAR($D$7),12-(MONTH($D$7)-MONTH(L19)),(IF(L19<$B$7,0,IF($D$7>L19,MIN(MONTH($D$7),DATEDIF(DATE(YEAR(G19),MONTH(G19),"1"),$D$7,"M")-DATEDIF(DATE(YEAR(G19),MONTH(G19),"1"),DATEDIF(YEAR(L19),MONTH(L19),"1"),"M")),MIN(DATEDIF(DATE(YEAR(G19),MONTH(G19),"1"),$D$7,"m"),MONTH($D$7)))))) -> 12 | O19: =IF(K19=0,0,ROUND(((1-I19)/K19)*E19,4)) -> 0 | P19: =ROUND(O19*N19,2) -> 0 | Q19: =ROUND(J19-O19,2) -> 0 | R19: =ROUND(O19*M19,2) -> 0 | S19: =ROUND(F19-R19,2) -> 0
A20: ='明细表H1-2'!A24 -> 0 | B20: ='明细表H1-2'!B24 -> 0 | C20: ='明细表H1-2'!C24 -> 0 | E20: ='明细表H1-2'!P24 -> 0 | F20: ='明细表H1-2'!AE24 -> 0 | K20: =IF(H20=0,0,IF(RIGHT(H20,1)<>"年",H20*12,IF(LEN(H20)=3,VALUE(LEFT(H20,2))*12,IF(LEN(H20)=2,VALUE(LEFT(H20,1))*12,"??")))) -> 0 | L20: =DATE((YEAR(G20)+H20),MONTH(G20),DAY(G20)) -> 0 | M20: =MIN((YEAR(L20)-YEAR(G20))*12+(MONTH(L20)-MONTH(G20)),(YEAR($D$7)-YEAR(G20))*12+MONTH($D$7)-MONTH(G20),H20*12) -> 0 | N20: =IF(YEAR(L20)=YEAR($D$7),12-(MONTH($D$7)-MONTH(L20)),(IF(L20<$B$7,0,IF($D$7>L20,MIN(MONTH($D$7),DATEDIF(DATE(YEAR(G20),MONTH(G20),"1"),$D$7,"M")-DATEDIF(DATE(YEAR(G20),MONTH(G20),"1"),DATEDIF(YEAR(L20),MONTH(L20),"1"),"M")),MIN(DATEDIF(DATE(YEAR(G20),MONTH(G20),"1"),$D$7,"m"),MONTH($D$7)))))) -> 12 | O20: =IF(K20=0,0,ROUND(((1-I20)/K20)*E20,4)) -> 0 | P20: =ROUND(O20*N20,2) -> 0 | Q20: =ROUND(J20-O20,2) -> 0 | R20: =ROUND(O20*M20,2) -> 0 | S20: =ROUND(F20-R20,2) -> 0
... A28: ='明细表H1-2'!A32 -> 0 | B28: ='明细表H1-2'!B32 -> 0 | C28: ='明细表H1-2'!C32 -> 0 | E28: ='明细表H1-2'!P32 -> 0 | F28: ='明细表H1-2'!AE32 -> 0 | K28: =IF(H28=0,0,IF(RIGHT(H28,1)<>"年",H28*12,IF(LEN(H28)=3,VALUE(LEFT(H28,2))*12,IF(LEN(H28)=2,VALUE(LEFT(H28,1))*12,"??")))) -> 0 | L28: =DATE((YEAR(G28)+H28),MONTH(G28),DAY(G28)) -> 0 | M28: =MIN((YEAR(L28)-YEAR(G28))*12+(MONTH(L28)-MONTH(G28)),(YEAR($D$7)-YEAR(G28))*12+MONTH($D$7)-MONTH(G28),H28*12) -> 0 | N28: =IF(YEAR(L28)=YEAR($D$7),12-(MONTH($D$7)-MONTH(L28)),(IF(L28<$B$7,0,IF($D$7>L28,MIN(MONTH($D$7),DATEDIF(DATE(YEAR(G28),MONTH(G28),"1"),$D$7,"M")-DATEDIF(DATE(YEAR(G28),MONTH(G28),"1"),DATEDIF(YEAR(L28),MONTH(L28),"1"),"M")),MIN(DATEDIF(DATE(YEAR(G28),MONTH(G28),"1"),$D$7,"m"),MONTH($D$7)))))) -> 12 | O28: =IF(K28=0,0,ROUND(((1-I28)/K28)*E28,4)) -> 0 | P28: =ROUND(O28*N28,2) -> 0 | Q28: =ROUND(J28-O28,2) -> 0 | R28: =ROUND(O28*M28,2) -> 0 | S28: =ROUND(F28-R28,2) -> 0
A29: ='明细表H1-2'!A33 -> 合计 | E29: =SUM(E9:E28) -> 0 | F29: =SUM(F9:F28) -> 0 | O29: =SUM(O9:O28) -> 0 | P29: =SUM(P9:P28) -> 0 | Q29: =SUM(Q9:Q28) -> 0 | R29: =SUM(R9:R28) -> 0 | S29: =SUM(S9:S28) -> 0
A30: ='明细表H1-2'!A34 -> 其中：
A31: ='明细表H1-2'!A35 -> 房屋及建筑物 | E31: =SUMPRODUCT(($A$9:$A$28=$A31)*(E$9:E$28)) -> 0 | F31: =SUMPRODUCT(($A$9:$A$28=$A31)*(F$9:F$28)) -> 0 | S31: =SUMPRODUCT(($A$9:$A$28=$A31)*(S$9:S$28)) -> 0
A32: ='明细表H1-2'!A36 -> 机器设备 | E32: =SUMPRODUCT(($A$9:$A$28=$A32)*(E$9:E$28)) -> 0 | F32: =SUMPRODUCT(($A$9:$A$28=$A32)*(F$9:F$28)) -> 0 | S32: =SUMPRODUCT(($A$9:$A$28=$A32)*(S$9:S$28)) -> 0
A33: ='明细表H1-2'!A37 -> 运输设备 | E33: =SUMPRODUCT(($A$9:$A$28=$A33)*(E$9:E$28)) -> 0 | F33: =SUMPRODUCT(($A$9:$A$28=$A33)*(F$9:F$28)) -> 0 | S33: =SUMPRODUCT(($A$9:$A$28=$A33)*(S$9:S$28)) -> 0
A34: ='明细表H1-2'!A38 -> 办公设备 | E34: =SUMPRODUCT(($A$9:$A$28=$A34)*(E$9:E$28)) -> 0 | F34: =SUMPRODUCT(($A$9:$A$28=$A34)*(F$9:F$28)) -> 0 | S34: =SUMPRODUCT(($A$9:$A$28=$A34)*(S$9:S$28)) -> 0
A35: ='明细表H1-2'!A39 -> 其他设备 | E35: =SUMPRODUCT(($A$9:$A$28=$A35)*(E$9:E$28)) -> 0 | F35: =SUMPRODUCT(($A$9:$A$28=$A35)*(F$9:F$28)) -> 0 | S35: =SUMPRODUCT(($A$9:$A$28=$A35)*(S$9:S$28)) -> 0
A36: 三、审计说明：
A37: 需单独考虑本期固定资产减少对累计折旧的影响
A39: 四、审计结论
A44: 提示：
A45: 《企业所得税法实施条例》
A46: 第五十九条 固定资产按照直线法计算的折旧，准予扣除。
A47: 企业应当自固定资产投入使用月份的次月起计算折旧；停止使用的固定资产，应当自停止使用月份的次月起停止计算折旧。
A48: 企业应当根据固定资产的性质和使用情况，合理确定固定资产的预计净残值。固定资产的预计净残值一经确定，不得变更。
A49: 第六十条 除国务院财政、税务主管部门另有规定外，固定资产计算折旧的最低年限如下：
A50: （一）房屋、建筑物，为20年；
A51: （二）飞机、火车、轮船、机器、机械和其他生产设备，为10年；
A52: （三）与生产经营活动有关的器具、工具、家具等，为5年；
... A68: 4.考虑对方回复的可信度，并验证相关解释及回复的恰当性。确定是否需要额外的程序，如是，实施适当的应对程序。

Sheet 折旧测算表（含减值）H1-12
A1: 致同会计师事务所
A2: 固定资产折旧测算表
A3: =底稿目录!A2 -> 被审计单位： | G3: =底稿目录!A4 -> 编制人： | R3: =底稿目录!A5 -> 编制日期： | X3: 索引号： | Y3: H1-12
A4: =底稿目录!A3 -> 截止日：202X年12月31日 | G4: =底稿目录!A6 -> 复核人： | R4: =底稿目录!A7 -> 复核日期： | X4: 页 次：
A5: 一、审计目标：固定资产以恰当的金额包括在财务报表中，与之相关的计价或分摊调整已恰当记录，相关披露已得到恰当计量和描述。
A6: 二、审计过程：
A7: 折旧期初： | C7: 折旧期末： | E7: 计提减值准备日期： | G7: 各列顺序请根据需要进行调整，行数请根据需要增加。非公式列输入数据时请使用“选择性粘贴-数值”。
A8: 固定资产类别 | B8: 固定资产编号 | C8: 固定资产名称 | D8: 管理部门 | E8: 原值 （期末） | F8: 累计折旧（期末） | G8: 减值准备（期末） | H8: 开始使用日期 | I8: 使用年限 | J8: 残值率 | K8: 账面月折旧额 | L8: 使用月限 | M8: 测算到期日 | N8: 已提折旧月份 | O8: 截止计提减值准备日计提月份 | P8: 本期折旧月份 | Q8: 本期折旧月份（减值前） | R8: 本期折旧月份（减值后） | S8: 计提减值准备前月折旧 | T8: 计提减值准备前累计折旧 | U8: 计提减值准备后月折旧 | V8: 当期折旧费用 | W8: 月折旧额差异 | X8: 累计折旧费用 | Y8: 累计折旧额差异
A9: ='明细表H1-2'!A13 -> 0 | B9: ='明细表H1-2'!B13 -> 0 | C9: ='明细表H1-2'!C13 -> 0 | E9: ='明细表H1-2'!P13 -> 0 | F9: ='明细表H1-2'!AE13 -> 0 | G9: ='明细表H1-2'!AT13 -> 0 | L9: =IF(I9=0,0,IF(RIGHT(I9,1)<>"年",I9*12,IF(LEN(I9)=3,VALUE(LEFT(I9,2))*12,IF(LEN(I9)=2,VALUE(LEFT(I9,1))*12,"??")))) -> 0 | M9: =IF(DAY(H9)=1,IF(H9=0,0,DATE(YEAR(H9),MONTH(H9)+L9,DAY(H9))),IF(H9=0,0,DATE(YEAR(H9),MONTH(H9)+L9,DAY(H9)-1))) -> 0 | N9: =MIN(IF(AND(DAY(H9)=31,DAY($D$7)=30),IF(H9=0,0,IF(M9>$D$7,VALUE(DATEDIF(H9,MIN($D$7,M9),"m"))+1,VALUE(DATEDIF(H9,MIN($D$7,M9),"m")+2))),IF(H9=0,0,IF(M9>$D$7,DATEDIF(H9,MIN($D$7,M9),"m"),VALUE(DATEDIF(H9,MIN($D$7,M9),"m")+1)))),L9) -> 0 | O9: =IF(AND(DAY(H9)=31,DAY($F$7)=30),MIN(IF(H9=0,0,IF($F$7>H9,VALUE(DATEDIF(H9,$F$7,"m"))+1,0)),N9+1),MIN(IF(H9=0,0,IF($F$7>H9,DATEDIF(H9,$F$7,"m"),0)),N9)) -> 0 | P9: =IF(OR(H9=0,M9<$B$7),0,IF(AND(H9<$B$7,M9>$D$7),VALUE(DATEDIF($B$7,$D$7,"m")+1),IF(AND(H9<$B$7,M9<=$D$7),VALUE(DATEDIF($B$7,M9,"m")+1),IF(AND(H9>=$B$7,M9>$D$7),VALUE(DATEDIF(H9,$D$7,"m")),IF(AND(H9>=$B$7,M9<=$D$7),VALUE(DATEDIF(H9,M9,"m")+1),))))) -> 0 | Q9: =IF(AND(YEAR(H9)=YEAR($D$7),DAY(H9)=31,DAY($D$7)=30),IF(H9>$F$7,0,P9-R9+1),IF(H9>$F$7,0,P9-R9)) -> 0 | R9: =IF(AND(DAY($F$7)=31,DAY($D$7)=30),IF(H9=0,0,IF($F$7<$B$7,P9,VALUE(DATEDIF(MAX(H9,$F$7),MIN(M9,$D$7),"m")))+1),IF(H9=0,0,IF($F$7<$B$7,P9,DATEDIF(MAX(H9,$F$7),MIN(M9,$D$7),"m")))) -> 0 | S9: =IF(L9=0,0,ROUND(((1-J9)/L9)*E9,4)) -> 0 | T9: =ROUND(S9*O9,2) -> 0 | U9: =IF((E9*(1-J9)-T9-G9)>0,(E9*(1-J9)-T9-G9)/(L9-O9),0) -> 0 | V9: =ROUND(S9*Q9,2)+ROUND(U9*R9,2) -> 0 | W9: =ROUND(K9-U9,2) -> 0 | X9: =ROUND(S9*O9,2)+ROUND(U9*(N9-O9),2) -> 0 | Y9: =ROUND(F9-X9,2) -> 0
A10: ='明细表H1-2'!A14 -> 0 | B10: ='明细表H1-2'!B14 -> 0 | C10: ='明细表H1-2'!C14 -> 0 | E10: ='明细表H1-2'!P14 -> 0 | F10: ='明细表H1-2'!AE14 -> 0 | G10: ='明细表H1-2'!AT14 -> 0 | L10: =IF(I10=0,0,IF(RIGHT(I10,1)<>"年",I10*12,IF(LEN(I10)=3,VALUE(LEFT(I10,2))*12,IF(LEN(I10)=2,VALUE(LEFT(I10,1))*12,"??")))) -> 0 | M10: =IF(DAY(H10)=1,IF(H10=0,0,DATE(YEAR(H10),MONTH(H10)+L10,DAY(H10))),IF(H10=0,0,DATE(YEAR(H10),MONTH(H10)+L10,DAY(H10)-1))) -> 0 | N10: =MIN(IF(AND(DAY(H10)=31,DAY($D$7)=30),IF(H10=0,0,IF(M10>$D$7,VALUE(DATEDIF(H10,MIN($D$7,M10),"m"))+1,VALUE(DATEDIF(H10,MIN($D$7,M10),"m")+2))),IF(H10=0,0,IF(M10>$D$7,DATEDIF(H10,MIN($D$7,M10),"m"),VALUE(DATEDIF(H10,MIN($D$7,M10),"m")+1)))),L10) -> 0 | O10: =IF(AND(DAY(H10)=31,DAY($F$7)=30),MIN(IF(H10=0,0,IF($F$7>H10,VALUE(DATEDIF(H10,$F$7,"m"))+1,0)),N10+1),MIN(IF(H10=0,0,IF($F$7>H10,DATEDIF(H10,$F$7,"m"),0)),N10)) -> 0 | P10: =IF(OR(H10=0,M10<$B$7),0,IF(AND(H10<$B$7,M10>$D$7),VALUE(DATEDIF($B$7,$D$7,"m")+1),IF(AND(H10<$B$7,M10<=$D$7),VALUE(DATEDIF($B$7,M10,"m")+1),IF(AND(H10>=$B$7,M10>$D$7),VALUE(DATEDIF(H10,$D$7,"m")),IF(AND(H10>=$B$7,M10<=$D$7),VALUE(DATEDIF(H10,M10,"m")+1),))))) -> 0 | Q10: =IF(AND(YEAR(H10)=YEAR($D$7),DAY(H10)=31,DAY($D$7)=30),IF(H10>$F$7,0,P10-R10+1),IF(H10>$F$7,0,P10-R10)) -> 0 | R10: =IF(AND(DAY($F$7)=31,DAY($D$7)=30),IF(H10=0,0,IF($F$7<$B$7,P10,VALUE(DATEDIF(MAX(H10,$F$7),MIN(M10,$D$7),"m")))+1),IF(H10=0,0,IF($F$7<$B$7,P10,DATEDIF(MAX(H10,$F$7),MIN(M10,$D$7),"m")))) -> 0 | S10: =IF(L10=0,0,ROUND(((1-J10)/L10)*E10,4)) -> 0 | T10: =ROUND(S10*O10,2) -> 0 | U10: =IF((E10*(1-J10)-T10-G10)>0,(E10*(1-J10)-T10-G10)/(L10-O10),0) -> 0 | V10: =ROUND(S10*Q10,2)+ROUND(U10*R10,2) -> 0 | W10: =ROUND(K10-U10,2) -> 0 | X10: =ROUND(S10*O10,2)+ROUND(U10*(N10-O10),2) -> 0 | Y10: =ROUND(F10-X10,2) -> 0
A11: ='明细表H1-2'!A15 -> 0 | B11: ='明细表H1-2'!B15 -> 0 | C11: ='明细表H1-2'!C15 -> 0 | E11: ='明细表H1-2'!P15 -> 0 | F11: ='明细表H1-2'!AE15 -> 0 | G11: ='明细表H1-2'!AT15 -> 0 | L11: =IF(I11=0,0,IF(RIGHT(I11,1)<>"年",I11*12,IF(LEN(I11)=3,VALUE(LEFT(I11,2))*12,IF(LEN(I11)=2,VALUE(LEFT(I11,1))*12,"??")))) -> 0 | M11: =IF(DAY(H11)=1,IF(H11=0,0,DATE(YEAR(H11),MONTH(H11)+L11,DAY(H11))),IF(H11=0,0,DATE(YEAR(H11),MONTH(H11)+L11,DAY(H11)-1))) -> 0 | N11: =MIN(IF(AND(DAY(H11)=31,DAY($D$7)=30),IF(H11=0,0,IF(M11>$D$7,VALUE(DATEDIF(H11,MIN($D$7,M11),"m"))+1,VALUE(DATEDIF(H11,MIN($D$7,M11),"m")+2))),IF(H11=0,0,IF(M11>$D$7,DATEDIF(H11,MIN($D$7,M11),"m"),VALUE(DATEDIF(H11,MIN($D$7,M11),"m")+1)))),L11) -> 0 | O11: =IF(AND(DAY(H11)=31,DAY($F$7)=30),MIN(IF(H11=0,0,IF($F$7>H11,VALUE(DATEDIF(H11,$F$7,"m"))+1,0)),N11+1),MIN(IF(H11=0,0,IF($F$7>H11,DATEDIF(H11,$F$7,"m"),0)),N11)) -> 0 | P11: =IF(OR(H11=0,M11<$B$7),0,IF(AND(H11<$B$7,M11>$D$7),VALUE(DATEDIF($B$7,$D$7,"m")+1),IF(AND(H11<$B$7,M11<=$D$7),VALUE(DATEDIF($B$7,M11,"m")+1),IF(AND(H11>=$B$7,M11>$D$7),VALUE(DATEDIF(H11,$D$7,"m")),IF(AND(H11>=$B$7,M11<=$D$7),VALUE(DATEDIF(H11,M11,"m")+1),))))) -> 0 | Q11: =IF(AND(YEAR(H11)=YEAR($D$7),DAY(H11)=31,DAY($D$7)=30),IF(H11>$F$7,0,P11-R11+1),IF(H11>$F$7,0,P11-R11)) -> 0 | R11: =IF(AND(DAY($F$7)=31,DAY($D$7)=30),IF(H11=0,0,IF($F$7<$B$7,P11,VALUE(DATEDIF(MAX(H11,$F$7),MIN(M11,$D$7),"m")))+1),IF(H11=0,0,IF($F$7<$B$7,P11,DATEDIF(MAX(H11,$F$7),MIN(M11,$D$7),"m")))) -> 0 | S11: =IF(L11=0,0,ROUND(((1-J11)/L11)*E11,4)) -> 0 | T11: =ROUND(S11*O11,2) -> 0 | U11: =IF((E11*(1-J11)-T11-G11)>0,(E11*(1-J11)-T11-G11)/(L11-O11),0) -> 0 | V11: =ROUND(S11*Q11,2)+ROUND(U11*R11,2) -> 0 | W11: =ROUND(K11-U11,2) -> 0 | X11: =ROUND(S11*O11,2)+ROUND(U11*(N11-O11),2) -> 0 | Y11: =ROUND(F11-X11,2) -> 0
A12: ='明细表H1-2'!A16 -> 0 | B12: ='明细表H1-2'!B16 -> 0 | C12: ='明细表H1-2'!C16 -> 0 | E12: ='明细表H1-2'!P16 -> 0 | F12: ='明细表H1-2'!AE16 -> 0 | G12: ='明细表H1-2'!AT16 -> 0 | L12: =IF(I12=0,0,IF(RIGHT(I12,1)<>"年",I12*12,IF(LEN(I12)=3,VALUE(LEFT(I12,2))*12,IF(LEN(I12)=2,VALUE(LEFT(I12,1))*12,"??")))) -> 0 | M12: =IF(DAY(H12)=1,IF(H12=0,0,DATE(YEAR(H12),MONTH(H12)+L12,DAY(H12))),IF(H12=0,0,DATE(YEAR(H12),MONTH(H12)+L12,DAY(H12)-1))) -> 0 | N12: =MIN(IF(AND(DAY(H12)=31,DAY($D$7)=30),IF(H12=0,0,IF(M12>$D$7,VALUE(DATEDIF(H12,MIN($D$7,M12),"m"))+1,VALUE(DATEDIF(H12,MIN($D$7,M12),"m")+2))),IF(H12=0,0,IF(M12>$D$7,DATEDIF(H12,MIN($D$7,M12),"m"),VALUE(DATEDIF(H12,MIN($D$7,M12),"m")+1)))),L12) -> 0 | O12: =IF(AND(DAY(H12)=31,DAY($F$7)=30),MIN(IF(H12=0,0,IF($F$7>H12,VALUE(DATEDIF(H12,$F$7,"m"))+1,0)),N12+1),MIN(IF(H12=0,0,IF($F$7>H12,DATEDIF(H12,$F$7,"m"),0)),N12)) -> 0 | P12: =IF(OR(H12=0,M12<$B$7),0,IF(AND(H12<$B$7,M12>$D$7),VALUE(DATEDIF($B$7,$D$7,"m")+1),IF(AND(H12<$B$7,M12<=$D$7),VALUE(DATEDIF($B$7,M12,"m")+1),IF(AND(H12>=$B$7,M12>$D$7),VALUE(DATEDIF(H12,$D$7,"m")),IF(AND(H12>=$B$7,M12<=$D$7),VALUE(DATEDIF(H12,M12,"m")+1),))))) -> 0 | Q12: =IF(AND(YEAR(H12)=YEAR($D$7),DAY(H12)=31,DAY($D$7)=30),IF(H12>$F$7,0,P12-R12+1),IF(H12>$F$7,0,P12-R12)) -> 0 | R12: =IF(AND(DAY($F$7)=31,DAY($D$7)=30),IF(H12=0,0,IF($F$7<$B$7,P12,VALUE(DATEDIF(MAX(H12,$F$7),MIN(M12,$D$7),"m")))+1),IF(H12=0,0,IF($F$7<$B$7,P12,DATEDIF(MAX(H12,$F$7),MIN(M12,$D$7),"m")))) -> 0 | S12: =IF(L12=0,0,ROUND(((1-J12)/L12)*E12,4)) -> 0 | T12: =ROUND(S12*O12,2) -> 0 | U12: =IF((E12*(1-J12)-T12-G12)>0,(E12*(1-J12)-T12-G12)/(L12-O12),0) -> 0 | V12: =ROUND(S12*Q12,2)+ROUND(U12*R12,2) -> 0 | W12: =ROUND(K12-U12,2) -> 0 | X12: =ROUND(S12*O12,2)+ROUND(U12*(N12-O12),2) -> 0 | Y12: =ROUND(F12-X12,2) -> 0
A13: ='明细表H1-2'!A17 -> 0 | B13: ='明细表H1-2'!B17 -> 0 | C13: ='明细表H1-2'!C17 -> 0 | E13: ='明细表H1-2'!P17 -> 0 | F13: ='明细表H1-2'!AE17 -> 0 | G13: ='明细表H1-2'!AT17 -> 0 | L13: =IF(I13=0,0,IF(RIGHT(I13,1)<>"年",I13*12,IF(LEN(I13)=3,VALUE(LEFT(I13,2))*12,IF(LEN(I13)=2,VALUE(LEFT(I13,1))*12,"??")))) -> 0 | M13: =IF(DAY(H13)=1,IF(H13=0,0,DATE(YEAR(H13),MONTH(H13)+L13,DAY(H13))),IF(H13=0,0,DATE(YEAR(H13),MONTH(H13)+L13,DAY(H13)-1))) -> 0 | N13: =MIN(IF(AND(DAY(H13)=31,DAY($D$7)=30),IF(H13=0,0,IF(M13>$D$7,VALUE(DATEDIF(H13,MIN($D$7,M13),"m"))+1,VALUE(DATEDIF(H13,MIN($D$7,M13),"m")+2))),IF(H13=0,0,IF(M13>$D$7,DATEDIF(H13,MIN($D$7,M13),"m"),VALUE(DATEDIF(H13,MIN($D$7,M13),"m")+1)))),L13) -> 0 | O13: =IF(AND(DAY(H13)=31,DAY($F$7)=30),MIN(IF(H13=0,0,IF($F$7>H13,VALUE(DATEDIF(H13,$F$7,"m"))+1,0)),N13+1),MIN(IF(H13=0,0,IF($F$7>H13,DATEDIF(H13,$F$7,"m"),0)),N13)) -> 0 | P13: =IF(OR(H13=0,M13<$B$7),0,IF(AND(H13<$B$7,M13>$D$7),VALUE(DATEDIF($B$7,$D$7,"m")+1),IF(AND(H13<$B$7,M13<=$D$7),VALUE(DATEDIF($B$7,M13,"m")+1),IF(AND(H13>=$B$7,M13>$D$7),VALUE(DATEDIF(H13,$D$7,"m")),IF(AND(H13>=$B$7,M13<=$D$7),VALUE(DATEDIF(H13,M13,"m")+1),))))) -> 0 | Q13: =IF(AND(YEAR(H13)=YEAR($D$7),DAY(H13)=31,DAY($D$7)=30),IF(H13>$F$7,0,P13-R13+1),IF(H13>$F$7,0,P13-R13)) -> 0 | R13: =IF(AND(DAY($F$7)=31,DAY($D$7)=30),IF(H13=0,0,IF($F$7<$B$7,P13,VALUE(DATEDIF(MAX(H13,$F$7),MIN(M13,$D$7),"m")))+1),IF(H13=0,0,IF($F$7<$B$7,P13,DATEDIF(MAX(H13,$F$7),MIN(M13,$D$7),"m")))) -> 0 | S13: =IF(L13=0,0,ROUND(((1-J13)/L13)*E13,4)) -> 0 | T13: =ROUND(S13*O13,2) -> 0 | U13: =IF((E13*(1-J13)-T13-G13)>0,(E13*(1-J13)-T13-G13)/(L13-O13),0) -> 0 | V13: =ROUND(S13*Q13,2)+ROUND(U13*R13,2) -> 0 | W13: =ROUND(K13-U13,2) -> 0 | X13: =ROUND(S13*O13,2)+ROUND(U13*(N13-O13),2) -> 0 | Y13: =ROUND(F13-X13,2) -> 0
A14: ='明细表H1-2'!A18 -> 0 | B14: ='明细表H1-2'!B18 -> 0 | C14: ='明细表H1-2'!C18 -> 0 | E14: ='明细表H1-2'!P18 -> 0 | F14: ='明细表H1-2'!AE18 -> 0 | G14: ='明细表H1-2'!AT18 -> 0 | L14: =IF(I14=0,0,IF(RIGHT(I14,1)<>"年",I14*12,IF(LEN(I14)=3,VALUE(LEFT(I14,2))*12,IF(LEN(I14)=2,VALUE(LEFT(I14,1))*12,"??")))) -> 0 | M14: =IF(DAY(H14)=1,IF(H14=0,0,DATE(YEAR(H14),MONTH(H14)+L14,DAY(H14))),IF(H14=0,0,DATE(YEAR(H14),MONTH(H14)+L14,DAY(H14)-1))) -> 0 | N14: =MIN(IF(AND(DAY(H14)=31,DAY($D$7)=30),IF(H14=0,0,IF(M14>$D$7,VALUE(DATEDIF(H14,MIN($D$7,M14),"m"))+1,VALUE(DATEDIF(H14,MIN($D$7,M14),"m")+2))),IF(H14=0,0,IF(M14>$D$7,DATEDIF(H14,MIN($D$7,M14),"m"),VALUE(DATEDIF(H14,MIN($D$7,M14),"m")+1)))),L14) -> 0 | O14: =IF(AND(DAY(H14)=31,DAY($F$7)=30),MIN(IF(H14=0,0,IF($F$7>H14,VALUE(DATEDIF(H14,$F$7,"m"))+1,0)),N14+1),MIN(IF(H14=0,0,IF($F$7>H14,DATEDIF(H14,$F$7,"m"),0)),N14)) -> 0 | P14: =IF(OR(H14=0,M14<$B$7),0,IF(AND(H14<$B$7,M14>$D$7),VALUE(DATEDIF($B$7,$D$7,"m")+1),IF(AND(H14<$B$7,M14<=$D$7),VALUE(DATEDIF($B$7,M14,"m")+1),IF(AND(H14>=$B$7,M14>$D$7),VALUE(DATEDIF(H14,$D$7,"m")),IF(AND(H14>=$B$7,M14<=$D$7),VALUE(DATEDIF(H14,M14,"m")+1),))))) -> 0 | Q14: =IF(AND(YEAR(H14)=YEAR($D$7),DAY(H14)=31,DAY($D$7)=30),IF(H14>$F$7,0,P14-R14+1),IF(H14>$F$7,0,P14-R14)) -> 0 | R14: =IF(AND(DAY($F$7)=31,DAY($D$7)=30),IF(H14=0,0,IF($F$7<$B$7,P14,VALUE(DATEDIF(MAX(H14,$F$7),MIN(M14,$D$7),"m")))+1),IF(H14=0,0,IF($F$7<$B$7,P14,DATEDIF(MAX(H14,$F$7),MIN(M14,$D$7),"m")))) -> 0 | S14: =IF(L14=0,0,ROUND(((1-J14)/L14)*E14,4)) -> 0 | T14: =ROUND(S14*O14,2) -> 0 | U14: =IF((E14*(1-J14)-T14-G14)>0,(E14*(1-J14)-T14-G14)/(L14-O14),0) -> 0 | V14: =ROUND(S14*Q14,2)+ROUND(U14*R14,2) -> 0 | W14: =ROUND(K14-U14,2) -> 0 | X14: =ROUND(S14*O14,2)+ROUND(U14*(N14-O14),2) -> 0 | Y14: =ROUND(F14-X14,2) -> 0
A15: ='明细表H1-2'!A19 -> 0 | B15: ='明细表H1-2'!B19 -> 0 | C15: ='明细表H1-2'!C19 -> 0 | E15: ='明细表H1-2'!P19 -> 0 | F15: ='明细表H1-2'!AE19 -> 0 | G15: ='明细表H1-2'!AT19 -> 0 | L15: =IF(I15=0,0,IF(RIGHT(I15,1)<>"年",I15*12,IF(LEN(I15)=3,VALUE(LEFT(I15,2))*12,IF(LEN(I15)=2,VALUE(LEFT(I15,1))*12,"??")))) -> 0 | M15: =IF(DAY(H15)=1,IF(H15=0,0,DATE(YEAR(H15),MONTH(H15)+L15,DAY(H15))),IF(H15=0,0,DATE(YEAR(H15),MONTH(H15)+L15,DAY(H15)-1))) -> 0 | N15: =MIN(IF(AND(DAY(H15)=31,DAY($D$7)=30),IF(H15=0,0,IF(M15>$D$7,VALUE(DATEDIF(H15,MIN($D$7,M15),"m"))+1,VALUE(DATEDIF(H15,MIN($D$7,M15),"m")+2))),IF(H15=0,0,IF(M15>$D$7,DATEDIF(H15,MIN($D$7,M15),"m"),VALUE(DATEDIF(H15,MIN($D$7,M15),"m")+1)))),L15) -> 0 | O15: =IF(AND(DAY(H15)=31,DAY($F$7)=30),MIN(IF(H15=0,0,IF($F$7>H15,VALUE(DATEDIF(H15,$F$7,"m"))+1,0)),N15+1),MIN(IF(H15=0,0,IF($F$7>H15,DATEDIF(H15,$F$7,"m"),0)),N15)) -> 0 | P15: =IF(OR(H15=0,M15<$B$7),0,IF(AND(H15<$B$7,M15>$D$7),VALUE(DATEDIF($B$7,$D$7,"m")+1),IF(AND(H15<$B$7,M15<=$D$7),VALUE(DATEDIF($B$7,M15,"m")+1),IF(AND(H15>=$B$7,M15>$D$7),VALUE(DATEDIF(H15,$D$7,"m")),IF(AND(H15>=$B$7,M15<=$D$7),VALUE(DATEDIF(H15,M15,"m")+1),))))) -> 0 | Q15: =IF(AND(YEAR(H15)=YEAR($D$7),DAY(H15)=31,DAY($D$7)=30),IF(H15>$F$7,0,P15-R15+1),IF(H15>$F$7,0,P15-R15)) -> 0 | R15: =IF(AND(DAY($F$7)=31,DAY($D$7)=30),IF(H15=0,0,IF($F$7<$B$7,P15,VALUE(DATEDIF(MAX(H15,$F$7),MIN(M15,$D$7),"m")))+1),IF(H15=0,0,IF($F$7<$B$7,P15,DATEDIF(MAX(H15,$F$7),MIN(M15,$D$7),"m")))) -> 0 | S15: =IF(L15=0,0,ROUND(((1-J15)/L15)*E15,4)) -> 0 | T15: =ROUND(S15*O15,2) -> 0 | U15: =IF((E15*(1-J15)-T15-G15)>0,(E15*(1-J15)-T15-G15)/(L15-O15),0) -> 0 | V15: =ROUND(S15*Q15,2)+ROUND(U15*R15,2) -> 0 | W15: =ROUND(K15-U15,2) -> 0 | X15: =ROUND(S15*O15,2)+ROUND(U15*(N15-O15),2) -> 0 | Y15: =ROUND(F15-X15,2) -> 0
A16: ='明细表H1-2'!A20 -> 0 | B16: ='明细表H1-2'!B20 -> 0 | C16: ='明细表H1-2'!C20 -> 0 | E16: ='明细表H1-2'!P20 -> 0 | F16: ='明细表H1-2'!AE20 -> 0 | G16: ='明细表H1-2'!AT20 -> 0 | L16: =IF(I16=0,0,IF(RIGHT(I16,1)<>"年",I16*12,IF(LEN(I16)=3,VALUE(LEFT(I16,2))*12,IF(LEN(I16)=2,VALUE(LEFT(I16,1))*12,"??")))) -> 0 | M16: =IF(DAY(H16)=1,IF(H16=0,0,DATE(YEAR(H16),MONTH(H16)+L16,DAY(H16))),IF(H16=0,0,DATE(YEAR(H16),MONTH(H16)+L16,DAY(H16)-1))) -> 0 | N16: =MIN(IF(AND(DAY(H16)=31,DAY($D$7)=30),IF(H16=0,0,IF(M16>$D$7,VALUE(DATEDIF(H16,MIN($D$7,M16),"m"))+1,VALUE(DATEDIF(H16,MIN($D$7,M16),"m")+2))),IF(H16=0,0,IF(M16>$D$7,DATEDIF(H16,MIN($D$7,M16),"m"),VALUE(DATEDIF(H16,MIN($D$7,M16),"m")+1)))),L16) -> 0 | O16: =IF(AND(DAY(H16)=31,DAY($F$7)=30),MIN(IF(H16=0,0,IF($F$7>H16,VALUE(DATEDIF(H16,$F$7,"m"))+1,0)),N16+1),MIN(IF(H16=0,0,IF($F$7>H16,DATEDIF(H16,$F$7,"m"),0)),N16)) -> 0 | P16: =IF(OR(H16=0,M16<$B$7),0,IF(AND(H16<$B$7,M16>$D$7),VALUE(DATEDIF($B$7,$D$7,"m")+1),IF(AND(H16<$B$7,M16<=$D$7),VALUE(DATEDIF($B$7,M16,"m")+1),IF(AND(H16>=$B$7,M16>$D$7),VALUE(DATEDIF(H16,$D$7,"m")),IF(AND(H16>=$B$7,M16<=$D$7),VALUE(DATEDIF(H16,M16,"m")+1),))))) -> 0 | Q16: =IF(AND(YEAR(H16)=YEAR($D$7),DAY(H16)=31,DAY($D$7)=30),IF(H16>$F$7,0,P16-R16+1),IF(H16>$F$7,0,P16-R16)) -> 0 | R16: =IF(AND(DAY($F$7)=31,DAY($D$7)=30),IF(H16=0,0,IF($F$7<$B$7,P16,VALUE(DATEDIF(MAX(H16,$F$7),MIN(M16,$D$7),"m")))+1),IF(H16=0,0,IF($F$7<$B$7,P16,DATEDIF(MAX(H16,$F$7),MIN(M16,$D$7),"m")))) -> 0 | S16: =IF(L16=0,0,ROUND(((1-J16)/L16)*E16,4)) -> 0 | T16: =ROUND(S16*O16,2) -> 0 | U16: =IF((E16*(1-J16)-T16-G16)>0,(E16*(1-J16)-T16-G16)/(L16-O16),0) -> 0 | V16: =ROUND(S16*Q16,2)+ROUND(U16*R16,2) -> 0 | W16: =ROUND(K16-U16,2) -> 0 | X16: =ROUND(S16*O16,2)+ROUND(U16*(N16-O16),2) -> 0 | Y16: =ROUND(F16-X16,2) -> 0
A17: ='明细表H1-2'!A21 -> 0 | B17: ='明细表H1-2'!B21 -> 0 | C17: ='明细表H1-2'!C21 -> 0 | E17: ='明细表H1-2'!P21 -> 0 | F17: ='明细表H1-2'!AE21 -> 0 | G17: ='明细表H1-2'!AT21 -> 0 | L17: =IF(I17=0,0,IF(RIGHT(I17,1)<>"年",I17*12,IF(LEN(I17)=3,VALUE(LEFT(I17,2))*12,IF(LEN(I17)=2,VALUE(LEFT(I17,1))*12,"??")))) -> 0 | M17: =IF(DAY(H17)=1,IF(H17=0,0,DATE(YEAR(H17),MONTH(H17)+L17,DAY(H17))),IF(H17=0,0,DATE(YEAR(H17),MONTH(H17)+L17,DAY(H17)-1))) -> 0 | N17: =MIN(IF(AND(DAY(H17)=31,DAY($D$7)=30),IF(H17=0,0,IF(M17>$D$7,VALUE(DATEDIF(H17,MIN($D$7,M17),"m"))+1,VALUE(DATEDIF(H17,MIN($D$7,M17),"m")+2))),IF(H17=0,0,IF(M17>$D$7,DATEDIF(H17,MIN($D$7,M17),"m"),VALUE(DATEDIF(H17,MIN($D$7,M17),"m")+1)))),L17) -> 0 | O17: =IF(AND(DAY(H17)=31,DAY($F$7)=30),MIN(IF(H17=0,0,IF($F$7>H17,VALUE(DATEDIF(H17,$F$7,"m"))+1,0)),N17+1),MIN(IF(H17=0,0,IF($F$7>H17,DATEDIF(H17,$F$7,"m"),0)),N17)) -> 0 | P17: =IF(OR(H17=0,M17<$B$7),0,IF(AND(H17<$B$7,M17>$D$7),VALUE(DATEDIF($B$7,$D$7,"m")+1),IF(AND(H17<$B$7,M17<=$D$7),VALUE(DATEDIF($B$7,M17,"m")+1),IF(AND(H17>=$B$7,M17>$D$7),VALUE(DATEDIF(H17,$D$7,"m")),IF(AND(H17>=$B$7,M17<=$D$7),VALUE(DATEDIF(H17,M17,"m")+1),))))) -> 0 | Q17: =IF(AND(YEAR(H17)=YEAR($D$7),DAY(H17)=31,DAY($D$7)=30),IF(H17>$F$7,0,P17-R17+1),IF(H17>$F$7,0,P17-R17)) -> 0 | R17: =IF(AND(DAY($F$7)=31,DAY($D$7)=30),IF(H17=0,0,IF($F$7<$B$7,P17,VALUE(DATEDIF(MAX(H17,$F$7),MIN(M17,$D$7),"m")))+1),IF(H17=0,0,IF($F$7<$B$7,P17,DATEDIF(MAX(H17,$F$7),MIN(M17,$D$7),"m")))) -> 0 | S17: =IF(L17=0,0,ROUND(((1-J17)/L17)*E17,4)) -> 0 | T17: =ROUND(S17*O17,2) -> 0 | U17: =IF((E17*(1-J17)-T17-G17)>0,(E17*(1-J17)-T17-G17)/(L17-O17),0) -> 0 | V17: =ROUND(S17*Q17,2)+ROUND(U17*R17,2) -> 0 | W17: =ROUND(K17-U17,2) -> 0 | X17: =ROUND(S17*O17,2)+ROUND(U17*(N17-O17),2) -> 0 | Y17: =ROUND(F17-X17,2) -> 0
A18: ='明细表H1-2'!A22 -> 0 | B18: ='明细表H1-2'!B22 -> 0 | C18: ='明细表H1-2'!C22 -> 0 | E18: ='明细表H1-2'!P22 -> 0 | F18: ='明细表H1-2'!AE22 -> 0 | G18: ='明细表H1-2'!AT22 -> 0 | L18: =IF(I18=0,0,IF(RIGHT(I18,1)<>"年",I18*12,IF(LEN(I18)=3,VALUE(LEFT(I18,2))*12,IF(LEN(I18)=2,VALUE(LEFT(I18,1))*12,"??")))) -> 0 | M18: =IF(DAY(H18)=1,IF(H18=0,0,DATE(YEAR(H18),MONTH(H18)+L18,DAY(H18))),IF(H18=0,0,DATE(YEAR(H18),MONTH(H18)+L18,DAY(H18)-1))) -> 0 | N18: =MIN(IF(AND(DAY(H18)=31,DAY($D$7)=30),IF(H18=0,0,IF(M18>$D$7,VALUE(DATEDIF(H18,MIN($D$7,M18),"m"))+1,VALUE(DATEDIF(H18,MIN($D$7,M18),"m")+2))),IF(H18=0,0,IF(M18>$D$7,DATEDIF(H18,MIN($D$7,M18),"m"),VALUE(DATEDIF(H18,MIN($D$7,M18),"m")+1)))),L18) -> 0 | O18: =IF(AND(DAY(H18)=31,DAY($F$7)=30),MIN(IF(H18=0,0,IF($F$7>H18,VALUE(DATEDIF(H18,$F$7,"m"))+1,0)),N18+1),MIN(IF(H18=0,0,IF($F$7>H18,DATEDIF(H18,$F$7,"m"),0)),N18)) -> 0 | P18: =IF(OR(H18=0,M18<$B$7),0,IF(AND(H18<$B$7,M18>$D$7),VALUE(DATEDIF($B$7,$D$7,"m")+1),IF(AND(H18<$B$7,M18<=$D$7),VALUE(DATEDIF($B$7,M18,"m")+1),IF(AND(H18>=$B$7,M18>$D$7),VALUE(DATEDIF(H18,$D$7,"m")),IF(AND(H18>=$B$7,M18<=$D$7),VALUE(DATEDIF(H18,M18,"m")+1),))))) -> 0 | Q18: =IF(AND(YEAR(H18)=YEAR($D$7),DAY(H18)=31,DAY($D$7)=30),IF(H18>$F$7,0,P18-R18+1),IF(H18>$F$7,0,P18-R18)) -> 0 | R18: =IF(AND(DAY($F$7)=31,DAY($D$7)=30),IF(H18=0,0,IF($F$7<$B$7,P18,VALUE(DATEDIF(MAX(H18,$F$7),MIN(M18,$D$7),"m")))+1),IF(H18=0,0,IF($F$7<$B$7,P18,DATEDIF(MAX(H18,$F$7),MIN(M18,$D$7),"m")))) -> 0 | S18: =IF(L18=0,0,ROUND(((1-J18)/L18)*E18,4)) -> 0 | T18: =ROUND(S18*O18,2) -> 0 | U18: =IF((E18*(1-J18)-T18-G18)>0,(E18*(1-J18)-T18-G18)/(L18-O18),0) -> 0 | V18: =ROUND(S18*Q18,2)+ROUND(U18*R18,2) -> 0 | W18: =ROUND(K18-U18,2) -> 0 | X18: =ROUND(S18*O18,2)+ROUND(U18*(N18-O18),2) -> 0 | Y18: =ROUND(F18-X18,2) -> 0
A19: ='明细表H1-2'!A23 -> 0 | B19: ='明细表H1-2'!B23 -> 0 | C19: ='明细表H1-2'!C23 -> 0 | E19: ='明细表H1-2'!P23 -> 0 | F19: ='明细表H1-2'!AE23 -> 0 | G19: ='明细表H1-2'!AT23 -> 0 | L19: =IF(I19=0,0,IF(RIGHT(I19,1)<>"年",I19*12,IF(LEN(I19)=3,VALUE(LEFT(I19,2))*12,IF(LEN(I19)=2,VALUE(LEFT(I19,1))*12,"??")))) -> 0 | M19: =IF(DAY(H19)=1,IF(H19=0,0,DATE(YEAR(H19),MONTH(H19)+L19,DAY(H19))),IF(H19=0,0,DATE(YEAR(H19),MONTH(H19)+L19,DAY(H19)-1))) -> 0 | N19: =MIN(IF(AND(DAY(H19)=31,DAY($D$7)=30),IF(H19=0,0,IF(M19>$D$7,VALUE(DATEDIF(H19,MIN($D$7,M19),"m"))+1,VALUE(DATEDIF(H19,MIN($D$7,M19),"m")+2))),IF(H19=0,0,IF(M19>$D$7,DATEDIF(H19,MIN($D$7,M19),"m"),VALUE(DATEDIF(H19,MIN($D$7,M19),"m")+1)))),L19) -> 0 | O19: =IF(AND(DAY(H19)=31,DAY($F$7)=30),MIN(IF(H19=0,0,IF($F$7>H19,VALUE(DATEDIF(H19,$F$7,"m"))+1,0)),N19+1),MIN(IF(H19=0,0,IF($F$7>H19,DATEDIF(H19,$F$7,"m"),0)),N19)) -> 0 | P19: =IF(OR(H19=0,M19<$B$7),0,IF(AND(H19<$B$7,M19>$D$7),VALUE(DATEDIF($B$7,$D$7,"m")+1),IF(AND(H19<$B$7,M19<=$D$7),VALUE(DATEDIF($B$7,M19,"m")+1),IF(AND(H19>=$B$7,M19>$D$7),VALUE(DATEDIF(H19,$D$7,"m")),IF(AND(H19>=$B$7,M19<=$D$7),VALUE(DATEDIF(H19,M19,"m")+1),))))) -> 0 | Q19: =IF(AND(YEAR(H19)=YEAR($D$7),DAY(H19)=31,DAY($D$7)=30),IF(H19>$F$7,0,P19-R19+1),IF(H19>$F$7,0,P19-R19)) -> 0 | R19: =IF(AND(DAY($F$7)=31,DAY($D$7)=30),IF(H19=0,0,IF($F$7<$B$7,P19,VALUE(DATEDIF(MAX(H19,$F$7),MIN(M19,$D$7),"m")))+1),IF(H19=0,0,IF($F$7<$B$7,P19,DATEDIF(MAX(H19,$F$7),MIN(M19,$D$7),"m")))) -> 0 | S19: =IF(L19=0,0,ROUND(((1-J19)/L19)*E19,4)) -> 0 | T19: =ROUND(S19*O19,2) -> 0 | U19: =IF((E19*(1-J19)-T19-G19)>0,(E19*(1-J19)-T19-G19)/(L19-O19),0) -> 0 | V19: =ROUND(S19*Q19,2)+ROUND(U19*R19,2) -> 0 | W19: =ROUND(K19-U19,2) -> 0 | X19: =ROUND(S19*O19,2)+ROUND(U19*(N19-O19),2) -> 0 | Y19: =ROUND(F19-X19,2) -> 0
A20: ='明细表H1-2'!A24 -> 0 | B20: ='明细表H1-2'!B24 -> 0 | C20: ='明细表H1-2'!C24 -> 0 | E20: ='明细表H1-2'!P24 -> 0 | F20: ='明细表H1-2'!AE24 -> 0 | G20: ='明细表H1-2'!AT24 -> 0 | L20: =IF(I20=0,0,IF(RIGHT(I20,1)<>"年",I20*12,IF(LEN(I20)=3,VALUE(LEFT(I20,2))*12,IF(LEN(I20)=2,VALUE(LEFT(I20,1))*12,"??")))) -> 0 | M20: =IF(DAY(H20)=1,IF(H20=0,0,DATE(YEAR(H20),MONTH(H20)+L20,DAY(H20))),IF(H20=0,0,DATE(YEAR(H20),MONTH(H20)+L20,DAY(H20)-1))) -> 0 | N20: =MIN(IF(AND(DAY(H20)=31,DAY($D$7)=30),IF(H20=0,0,IF(M20>$D$7,VALUE(DATEDIF(H20,MIN($D$7,M20),"m"))+1,VALUE(DATEDIF(H20,MIN($D$7,M20),"m")+2))),IF(H20=0,0,IF(M20>$D$7,DATEDIF(H20,MIN($D$7,M20),"m"),VALUE(DATEDIF(H20,MIN($D$7,M20),"m")+1)))),L20) -> 0 | O20: =IF(AND(DAY(H20)=31,DAY($F$7)=30),MIN(IF(H20=0,0,IF($F$7>H20,VALUE(DATEDIF(H20,$F$7,"m"))+1,0)),N20+1),MIN(IF(H20=0,0,IF($F$7>H20,DATEDIF(H20,$F$7,"m"),0)),N20)) -> 0 | P20: =IF(OR(H20=0,M20<$B$7),0,IF(AND(H20<$B$7,M20>$D$7),VALUE(DATEDIF($B$7,$D$7,"m")+1),IF(AND(H20<$B$7,M20<=$D$7),VALUE(DATEDIF($B$7,M20,"m")+1),IF(AND(H20>=$B$7,M20>$D$7),VALUE(DATEDIF(H20,$D$7,"m")),IF(AND(H20>=$B$7,M20<=$D$7),VALUE(DATEDIF(H20,M20,"m")+1),))))) -> 0 | Q20: =IF(AND(YEAR(H20)=YEAR($D$7),DAY(H20)=31,DAY($D$7)=30),IF(H20>$F$7,0,P20-R20+1),IF(H20>$F$7,0,P20-R20)) -> 0 | R20: =IF(AND(DAY($F$7)=31,DAY($D$7)=30),IF(H20=0,0,IF($F$7<$B$7,P20,VALUE(DATEDIF(MAX(H20,$F$7),MIN(M20,$D$7),"m")))+1),IF(H20=0,0,IF($F$7<$B$7,P20,DATEDIF(MAX(H20,$F$7),MIN(M20,$D$7),"m")))) -> 0 | S20: =IF(L20=0,0,ROUND(((1-J20)/L20)*E20,4)) -> 0 | T20: =ROUND(S20*O20,2) -> 0 | U20: =IF((E20*(1-J20)-T20-G20)>0,(E20*(1-J20)-T20-G20)/(L20-O20),0) -> 0 | V20: =ROUND(S20*Q20,2)+ROUND(U20*R20,2) -> 0 | W20: =ROUND(K20-U20,2) -> 0 | X20: =ROUND(S20*O20,2)+ROUND(U20*(N20-O20),2) -> 0 | Y20: =ROUND(F20-X20,2) -> 0
... A28: ='明细表H1-2'!A32 -> 0 | B28: ='明细表H1-2'!B32 -> 0 | C28: ='明细表H1-2'!C32 -> 0 | E28: ='明细表H1-2'!P32 -> 0 | F28: ='明细表H1-2'!AE32 -> 0 | G28: ='明细表H1-2'!AT32 -> 0 | L28: =IF(I28=0,0,IF(RIGHT(I28,1)<>"年",I28*12,IF(LEN(I28)=3,VALUE(LEFT(I28,2))*12,IF(LEN(I28)=2,VALUE(LEFT(I28,1))*12,"??")))) -> 0 | M28: =IF(DAY(H28)=1,IF(H28=0,0,DATE(YEAR(H28),MONTH(H28)+L28,DAY(H28))),IF(H28=0,0,DATE(YEAR(H28),MONTH(H28)+L28,DAY(H28)-1))) -> 0 | N28: =MIN(IF(AND(DAY(H28)=31,DAY($D$7)=30),IF(H28=0,0,IF(M28>$D$7,VALUE(DATEDIF(H28,MIN($D$7,M28),"m"))+1,VALUE(DATEDIF(H28,MIN($D$7,M28),"m")+2))),IF(H28=0,0,IF(M28>$D$7,DATEDIF(H28,MIN($D$7,M28),"m"),VALUE(DATEDIF(H28,MIN($D$7,M28),"m")+1)))),L28) -> 0 | O28: =IF(AND(DAY(H28)=31,DAY($F$7)=30),MIN(IF(H28=0,0,IF($F$7>H28,VALUE(DATEDIF(H28,$F$7,"m"))+1,0)),N28+1),MIN(IF(H28=0,0,IF($F$7>H28,DATEDIF(H28,$F$7,"m"),0)),N28)) -> 0 | P28: =IF(OR(H28=0,M28<$B$7),0,IF(AND(H28<$B$7,M28>$D$7),VALUE(DATEDIF($B$7,$D$7,"m")+1),IF(AND(H28<$B$7,M28<=$D$7),VALUE(DATEDIF($B$7,M28,"m")+1),IF(AND(H28>=$B$7,M28>$D$7),VALUE(DATEDIF(H28,$D$7,"m")),IF(AND(H28>=$B$7,M28<=$D$7),VALUE(DATEDIF(H28,M28,"m")+1),))))) -> 0 | Q28: =IF(AND(YEAR(H28)=YEAR($D$7),DAY(H28)=31,DAY($D$7)=30),IF(H28>$F$7,0,P28-R28+1),IF(H28>$F$7,0,P28-R28)) -> 0 | R28: =IF(AND(DAY($F$7)=31,DAY($D$7)=30),IF(H28=0,0,IF($F$7<$B$7,P28,VALUE(DATEDIF(MAX(H28,$F$7),MIN(M28,$D$7),"m")))+1),IF(H28=0,0,IF($F$7<$B$7,P28,DATEDIF(MAX(H28,$F$7),MIN(M28,$D$7),"m")))) -> 0 | S28: =IF(L28=0,0,ROUND(((1-J28)/L28)*E28,4)) -> 0 | T28: =ROUND(S28*O28,2) -> 0 | U28: =IF((E28*(1-J28)-T28-G28)>0,(E28*(1-J28)-T28-G28)/(L28-O28),0) -> 0 | V28: =ROUND(S28*Q28,2)+ROUND(U28*R28,2) -> 0 | W28: =ROUND(K28-U28,2) -> 0 | X28: =ROUND(S28*O28,2)+ROUND(U28*(N28-O28),2) -> 0 | Y28: =ROUND(F28-X28,2) -> 0
A29: ='明细表H1-2'!A33 -> 合计 | E29: =SUM(E9:E28) -> 0 | F29: =SUM(F9:F28) -> 0 | G29: =SUM(G9:G28) -> 0 | S29: =SUM(S9:S28) -> 0 | T29: =SUM(T9:T28) -> 0 | U29: =SUM(U9:U28) -> 0 | V29: =SUM(V9:V28) -> 0 | W29: =SUM(W9:W28) -> 0 | X29: =SUM(X9:X28) -> 0 | Y29: =SUM(Y9:Y28) -> 0
A30: ='明细表H1-2'!A34 -> 其中：
A31: ='明细表H1-2'!A35 -> 房屋及建筑物 | E31: =SUMPRODUCT(($A$9:$A$28=$A31)*(E$9:E$28)) -> 0 | F31: =SUMPRODUCT(($A$9:$A$28=$A31)*(F$9:F$28)) -> 0 | G31: =SUMPRODUCT(($A$9:$A$28=$A31)*(G$9:G$28)) -> 0 | Y31: =SUMPRODUCT(($A$9:$A$28=$A31)*(Y$9:Y$28)) -> 0
A32: ='明细表H1-2'!A36 -> 机器设备 | E32: =SUMPRODUCT(($A$9:$A$28=$A32)*(E$9:E$28)) -> 0 | F32: =SUMPRODUCT(($A$9:$A$28=$A32)*(F$9:F$28)) -> 0 | G32: =SUMPRODUCT(($A$9:$A$28=$A32)*(G$9:G$28)) -> 0 | Y32: =SUMPRODUCT(($A$9:$A$28=$A32)*(Y$9:Y$28)) -> 0
A33: ='明细表H1-2'!A37 -> 运输设备 | E33: =SUMPRODUCT(($A$9:$A$28=$A33)*(E$9:E$28)) -> 0 | F33: =SUMPRODUCT(($A$9:$A$28=$A33)*(F$9:F$28)) -> 0 | G33: =SUMPRODUCT(($A$9:$A$28=$A33)*(G$9:G$28)) -> 0 | Y33: =SUMPRODUCT(($A$9:$A$28=$A33)*(Y$9:Y$28)) -> 0
A34: ='明细表H1-2'!A38 -> 办公设备 | E34: =SUMPRODUCT(($A$9:$A$28=$A34)*(E$9:E$28)) -> 0 | F34: =SUMPRODUCT(($A$9:$A$28=$A34)*(F$9:F$28)) -> 0 | G34: =SUMPRODUCT(($A$9:$A$28=$A34)*(G$9:G$28)) -> 0 | Y34: =SUMPRODUCT(($A$9:$A$28=$A34)*(Y$9:Y$28)) -> 0
A35: ='明细表H1-2'!A39 -> 其他设备 | E35: =SUMPRODUCT(($A$9:$A$28=$A35)*(E$9:E$28)) -> 0 | F35: =SUMPRODUCT(($A$9:$A$28=$A35)*(F$9:F$28)) -> 0 | G35: =SUMPRODUCT(($A$9:$A$28=$A35)*(G$9:G$28)) -> 0 | Y35: =SUMPRODUCT(($A$9:$A$28=$A35)*(Y$9:Y$28)) -> 0
A36: 三、审计说明：
A37: 需单独考虑本期固定资产减少对累计折旧的影响
A40: 四、审计结论

Sheet 折旧测算表（多次减值）H1-12
A1: 致同会计师事务所
A2: 固定资产折旧测算表
A3: =底稿目录!A2 -> 被审计单位： | G3: =底稿目录!A4 -> 编制人： | T3: =底稿目录!A5 -> 编制日期： | Z3: 索引号： | AA3: H1-12
A4: =底稿目录!A3 -> 截止日：202X年12月31日 | G4: =底稿目录!A6 -> 复核人： | T4: =底稿目录!A7 -> 复核日期： | Z4: 页 次：
A5: 一、审计目标：固定资产以恰当的金额包括在财务报表中，与之相关的计价或分摊调整已恰当记录，相关披露已得到恰当计量和描述。
A6: 二、审计过程：
A7: 折旧期初： | C7: 折旧期末： | E7: 计提减值准备日期： | G7: 各列顺序请根据需要进行调整，行数请根据需要增加。非公式列输入数据时请使用“选择性粘贴-数值”。 | U7: 【使用本测算表时请注意：应已对期初累计折旧进行了测试且无差异】
A8: 固定资产类别 | B8: 固定资产编号 | C8: 固定资产名称 | D8: 管理部门 | E8: 原值 （期末） | F8: 期初累计折旧 | G8: 期末累计折旧 | H8: 期初减值准备余额 | I8: 期末减值准备余额 | J8: 开始使用日期 | K8: 使用年限 | L8: 残值率 | M8: 账面月折旧额 | N8: 使用月限 | O8: 测算到期日 | P8: 期初已提折旧月份 | Q8: 期末已提折旧月份 | R8: 本期折旧月份 | S8: 本期折旧月份（减值前） | T8: 本期折旧月份（减值后） | U8: 本期计提减值准备前月折旧 | V8: 计提减值准备前累计折旧 | W8: 本期计提减值准备后月折旧 | X8: 当期折旧费用 | Y8: 月折旧额差异 | Z8: 累计折旧费用 | AA8: 累计折旧额差异
A9: ='明细表H1-2'!A13 -> 0 | B9: ='明细表H1-2'!B13 -> 0 | C9: ='明细表H1-2'!C13 -> 0 | E9: ='明细表H1-2'!P13 -> 0 | F9: ='明细表H1-2'!AB13 -> 0 | G9: ='明细表H1-2'!AE13 -> 0 | H9: ='明细表H1-2'!AQ13 -> 0 | I9: ='明细表H1-2'!AT13 -> 0 | N9: =IF(K9=0,0,IF(RIGHT(K9,1)<>"年",K9*12,IF(LEN(K9)=3,VALUE(LEFT(K9,2))*12,IF(LEN(K9)=2,VALUE(LEFT(K9,1))*12,"??")))) -> 0 | O9: =IF(DAY(J9)=1,IF(J9=0,0,DATE(YEAR(J9),MONTH(J9)+N9,DAY(J9))),IF(J9=0,0,DATE(YEAR(J9),MONTH(J9)+N9,DAY(J9)-1))) -> 0 | P9: =MIN(IF(AND(DAY(J9)=31,DAY($B$7-1)=30),IF(J9=0,0,IF(O9>($B$7-1),VALUE(DATEDIF(J9,MIN(($B$7-1),O9),"m"))+1,VALUE(DATEDIF(J9,MIN(($B$7-1),O9),"m")+2))),IF(J9=0,0,IF(O9>($B$7-1),DATEDIF(J9,MIN(($B$7-1),O9),"m"),VALUE(DATEDIF(J9,MIN(($B$7-1),O9),"m")+1)))),N9) -> #NUM! | Q9: =MIN(IF(AND(DAY(J9)=31,DAY($D$7)=30),IF(J9=0,0,IF(O9>$D$7,VALUE(DATEDIF(J9,MIN($D$7,O9),"m"))+1,VALUE(DATEDIF(J9,MIN($D$7,O9),"m")+2))),IF(J9=0,0,IF(O9>$D$7,DATEDIF(J9,MIN($D$7,O9),"m"),VALUE(DATEDIF(J9,MIN($D$7,O9),"m")+1)))),N9) -> 0 | R9: =IF(OR(J9=0,O9<$B$7),0,IF(AND(J9<$B$7,O9>$D$7),VALUE(DATEDIF($B$7,$D$7,"m")+1),IF(AND(J9<$B$7,O9<=$D$7),VALUE(DATEDIF($B$7,O9,"m")+1),IF(AND(J9>=$B$7,O9>$D$7),VALUE(DATEDIF(J9,$D$7,"m")),IF(AND(J9>=$B$7,O9<=$D$7),VALUE(DATEDIF(J9,O9,"m")+1),))))) -> 0 | S9: =IF(AND(YEAR(J9)=YEAR($D$7),DAY(J9)=31,DAY($D$7)=30),IF(J9>$F$7,0,R9-T9+1),IF(J9>$F$7,0,R9-T9)) -> 0 | T9: =IF(AND(DAY($F$7)=31,DAY($D$7)=30),IF(J9=0,0,IF($F$7<$B$7,R9,VALUE(DATEDIF(MAX(J9,$F$7),MIN(O9,$D$7),"m")))+1),IF(J9=0,0,IF($F$7<$B$7,R9,DATEDIF(MAX(J9,$F$7),MIN(O9,$D$7),"m")))) -> 0 | U9: =IF(N9=0,0,ROUND((E9*(1-L9)-F9-H9)/(N9-P9),2)) -> 0 | V9: =ROUND(U9*S9,2)+F9 -> 0 | W9: =IF((E9*(1-L9)-V9-I9)>0,(E9*(1-L9)-V9-I9)/(N9-P9-S9),0) -> 0 | X9: =ROUND(U9*S9,2)+ROUND(W9*T9,2) -> 0 | Y9: =ROUND(M9-W9,2) -> 0 | Z9: =F9+X9 -> 0 | AA9: =ROUND(G9-Z9,2) -> 0
A10: ='明细表H1-2'!A14 -> 0 | B10: ='明细表H1-2'!B14 -> 0 | C10: ='明细表H1-2'!C14 -> 0 | E10: ='明细表H1-2'!P14 -> 0 | F10: ='明细表H1-2'!AB14 -> 0 | G10: ='明细表H1-2'!AE14 -> 0 | H10: ='明细表H1-2'!AQ14 -> 0 | I10: ='明细表H1-2'!AT14 -> 0 | N10: =IF(K10=0,0,IF(RIGHT(K10,1)<>"年",K10*12,IF(LEN(K10)=3,VALUE(LEFT(K10,2))*12,IF(LEN(K10)=2,VALUE(LEFT(K10,1))*12,"??")))) -> 0 | O10: =IF(DAY(J10)=1,IF(J10=0,0,DATE(YEAR(J10),MONTH(J10)+N10,DAY(J10))),IF(J10=0,0,DATE(YEAR(J10),MONTH(J10)+N10,DAY(J10)-1))) -> 0 | P10: =MIN(IF(AND(DAY(J10)=31,DAY($B$7-1)=30),IF(J10=0,0,IF(O10>($B$7-1),VALUE(DATEDIF(J10,MIN(($B$7-1),O10),"m"))+1,VALUE(DATEDIF(J10,MIN(($B$7-1),O10),"m")+2))),IF(J10=0,0,IF(O10>($B$7-1),DATEDIF(J10,MIN(($B$7-1),O10),"m"),VALUE(DATEDIF(J10,MIN(($B$7-1),O10),"m")+1)))),N10) -> #NUM! | Q10: =MIN(IF(AND(DAY(J10)=31,DAY($D$7)=30),IF(J10=0,0,IF(O10>$D$7,VALUE(DATEDIF(J10,MIN($D$7,O10),"m"))+1,VALUE(DATEDIF(J10,MIN($D$7,O10),"m")+2))),IF(J10=0,0,IF(O10>$D$7,DATEDIF(J10,MIN($D$7,O10),"m"),VALUE(DATEDIF(J10,MIN($D$7,O10),"m")+1)))),N10) -> 0 | R10: =IF(OR(J10=0,O10<$B$7),0,IF(AND(J10<$B$7,O10>$D$7),VALUE(DATEDIF($B$7,$D$7,"m")+1),IF(AND(J10<$B$7,O10<=$D$7),VALUE(DATEDIF($B$7,O10,"m")+1),IF(AND(J10>=$B$7,O10>$D$7),VALUE(DATEDIF(J10,$D$7,"m")),IF(AND(J10>=$B$7,O10<=$D$7),VALUE(DATEDIF(J10,O10,"m")+1),))))) -> 0 | S10: =IF(AND(YEAR(J10)=YEAR($D$7),DAY(J10)=31,DAY($D$7)=30),IF(J10>$F$7,0,R10-T10+1),IF(J10>$F$7,0,R10-T10)) -> 0 | T10: =IF(AND(DAY($F$7)=31,DAY($D$7)=30),IF(J10=0,0,IF($F$7<$B$7,R10,VALUE(DATEDIF(MAX(J10,$F$7),MIN(O10,$D$7),"m")))+1),IF(J10=0,0,IF($F$7<$B$7,R10,DATEDIF(MAX(J10,$F$7),MIN(O10,$D$7),"m")))) -> 0 | U10: =IF(N10=0,0,ROUND((E10*(1-L10)-F10-H10)/(N10-P10),2)) -> 0 | V10: =ROUND(U10*S10,2)+F10 -> 0 | W10: =IF((E10*(1-L10)-V10-I10)>0,(E10*(1-L10)-V10-I10)/(N10-P10-S10),0) -> 0 | X10: =ROUND(U10*S10,2)+ROUND(W10*T10,2) -> 0 | Y10: =ROUND(M10-W10,2) -> 0 | Z10: =F10+X10 -> 0 | AA10: =ROUND(G10-Z10,2) -> 0
A11: ='明细表H1-2'!A15 -> 0 | B11: ='明细表H1-2'!B15 -> 0 | C11: ='明细表H1-2'!C15 -> 0 | E11: ='明细表H1-2'!P15 -> 0 | F11: ='明细表H1-2'!AB15 -> 0 | G11: ='明细表H1-2'!AE15 -> 0 | H11: ='明细表H1-2'!AQ15 -> 0 | I11: ='明细表H1-2'!AT15 -> 0 | N11: =IF(K11=0,0,IF(RIGHT(K11,1)<>"年",K11*12,IF(LEN(K11)=3,VALUE(LEFT(K11,2))*12,IF(LEN(K11)=2,VALUE(LEFT(K11,1))*12,"??")))) -> 0 | O11: =IF(DAY(J11)=1,IF(J11=0,0,DATE(YEAR(J11),MONTH(J11)+N11,DAY(J11))),IF(J11=0,0,DATE(YEAR(J11),MONTH(J11)+N11,DAY(J11)-1))) -> 0 | P11: =MIN(IF(AND(DAY(J11)=31,DAY($B$7-1)=30),IF(J11=0,0,IF(O11>($B$7-1),VALUE(DATEDIF(J11,MIN(($B$7-1),O11),"m"))+1,VALUE(DATEDIF(J11,MIN(($B$7-1),O11),"m")+2))),IF(J11=0,0,IF(O11>($B$7-1),DATEDIF(J11,MIN(($B$7-1),O11),"m"),VALUE(DATEDIF(J11,MIN(($B$7-1),O11),"m")+1)))),N11) -> #NUM! | Q11: =MIN(IF(AND(DAY(J11)=31,DAY($D$7)=30),IF(J11=0,0,IF(O11>$D$7,VALUE(DATEDIF(J11,MIN($D$7,O11),"m"))+1,VALUE(DATEDIF(J11,MIN($D$7,O11),"m")+2))),IF(J11=0,0,IF(O11>$D$7,DATEDIF(J11,MIN($D$7,O11),"m"),VALUE(DATEDIF(J11,MIN($D$7,O11),"m")+1)))),N11) -> 0 | R11: =IF(OR(J11=0,O11<$B$7),0,IF(AND(J11<$B$7,O11>$D$7),VALUE(DATEDIF($B$7,$D$7,"m")+1),IF(AND(J11<$B$7,O11<=$D$7),VALUE(DATEDIF($B$7,O11,"m")+1),IF(AND(J11>=$B$7,O11>$D$7),VALUE(DATEDIF(J11,$D$7,"m")),IF(AND(J11>=$B$7,O11<=$D$7),VALUE(DATEDIF(J11,O11,"m")+1),))))) -> 0 | S11: =IF(AND(YEAR(J11)=YEAR($D$7),DAY(J11)=31,DAY($D$7)=30),IF(J11>$F$7,0,R11-T11+1),IF(J11>$F$7,0,R11-T11)) -> 0 | T11: =IF(AND(DAY($F$7)=31,DAY($D$7)=30),IF(J11=0,0,IF($F$7<$B$7,R11,VALUE(DATEDIF(MAX(J11,$F$7),MIN(O11,$D$7),"m")))+1),IF(J11=0,0,IF($F$7<$B$7,R11,DATEDIF(MAX(J11,$F$7),MIN(O11,$D$7),"m")))) -> 0 | U11: =IF(N11=0,0,ROUND((E11*(1-L11)-F11-H11)/(N11-P11),2)) -> 0 | V11: =ROUND(U11*S11,2)+F11 -> 0 | W11: =IF((E11*(1-L11)-V11-I11)>0,(E11*(1-L11)-V11-I11)/(N11-P11-S11),0) -> 0 | X11: =ROUND(U11*S11,2)+ROUND(W11*T11,2) -> 0 | Y11: =ROUND(M11-W11,2) -> 0 | Z11: =F11+X11 -> 0 | AA11: =ROUND(G11-Z11,2) -> 0
A12: ='明细表H1-2'!A16 -> 0 | B12: ='明细表H1-2'!B16 -> 0 | C12: ='明细表H1-2'!C16 -> 0 | E12: ='明细表H1-2'!P16 -> 0 | F12: ='明细表H1-2'!AB16 -> 0 | G12: ='明细表H1-2'!AE16 -> 0 | H12: ='明细表H1-2'!AQ16 -> 0 | I12: ='明细表H1-2'!AT16 -> 0 | N12: =IF(K12=0,0,IF(RIGHT(K12,1)<>"年",K12*12,IF(LEN(K12)=3,VALUE(LEFT(K12,2))*12,IF(LEN(K12)=2,VALUE(LEFT(K12,1))*12,"??")))) -> 0 | O12: =IF(DAY(J12)=1,IF(J12=0,0,DATE(YEAR(J12),MONTH(J12)+N12,DAY(J12))),IF(J12=0,0,DATE(YEAR(J12),MONTH(J12)+N12,DAY(J12)-1))) -> 0 | P12: =MIN(IF(AND(DAY(J12)=31,DAY($B$7-1)=30),IF(J12=0,0,IF(O12>($B$7-1),VALUE(DATEDIF(J12,MIN(($B$7-1),O12),"m"))+1,VALUE(DATEDIF(J12,MIN(($B$7-1),O12),"m")+2))),IF(J12=0,0,IF(O12>($B$7-1),DATEDIF(J12,MIN(($B$7-1),O12),"m"),VALUE(DATEDIF(J12,MIN(($B$7-1),O12),"m")+1)))),N12) -> #NUM! | Q12: =MIN(IF(AND(DAY(J12)=31,DAY($D$7)=30),IF(J12=0,0,IF(O12>$D$7,VALUE(DATEDIF(J12,MIN($D$7,O12),"m"))+1,VALUE(DATEDIF(J12,MIN($D$7,O12),"m")+2))),IF(J12=0,0,IF(O12>$D$7,DATEDIF(J12,MIN($D$7,O12),"m"),VALUE(DATEDIF(J12,MIN($D$7,O12),"m")+1)))),N12) -> 0 | R12: =IF(OR(J12=0,O12<$B$7),0,IF(AND(J12<$B$7,O12>$D$7),VALUE(DATEDIF($B$7,$D$7,"m")+1),IF(AND(J12<$B$7,O12<=$D$7),VALUE(DATEDIF($B$7,O12,"m")+1),IF(AND(J12>=$B$7,O12>$D$7),VALUE(DATEDIF(J12,$D$7,"m")),IF(AND(J12>=$B$7,O12<=$D$7),VALUE(DATEDIF(J12,O12,"m")+1),))))) -> 0 | S12: =IF(AND(YEAR(J12)=YEAR($D$7),DAY(J12)=31,DAY($D$7)=30),IF(J12>$F$7,0,R12-T12+1),IF(J12>$F$7,0,R12-T12)) -> 0 | T12: =IF(AND(DAY($F$7)=31,DAY($D$7)=30),IF(J12=0,0,IF($F$7<$B$7,R12,VALUE(DATEDIF(MAX(J12,$F$7),MIN(O12,$D$7),"m")))+1),IF(J12=0,0,IF($F$7<$B$7,R12,DATEDIF(MAX(J12,$F$7),MIN(O12,$D$7),"m")))) -> 0 | U12: =IF(N12=0,0,ROUND((E12*(1-L12)-F12-H12)/(N12-P12),2)) -> 0 | V12: =ROUND(U12*S12,2)+F12 -> 0 | W12: =IF((E12*(1-L12)-V12-I12)>0,(E12*(1-L12)-V12-I12)/(N12-P12-S12),0) -> 0 | X12: =ROUND(U12*S12,2)+ROUND(W12*T12,2) -> 0 | Y12: =ROUND(M12-W12,2) -> 0 | Z12: =F12+X12 -> 0 | AA12: =ROUND(G12-Z12,2) -> 0
A13: ='明细表H1-2'!A17 -> 0 | B13: ='明细表H1-2'!B17 -> 0 | C13: ='明细表H1-2'!C17 -> 0 | E13: ='明细表H1-2'!P17 -> 0 | F13: ='明细表H1-2'!AB17 -> 0 | G13: ='明细表H1-2'!AE17 -> 0 | H13: ='明细表H1-2'!AQ17 -> 0 | I13: ='明细表H1-2'!AT17 -> 0 | N13: =IF(K13=0,0,IF(RIGHT(K13,1)<>"年",K13*12,IF(LEN(K13)=3,VALUE(LEFT(K13,2))*12,IF(LEN(K13)=2,VALUE(LEFT(K13,1))*12,"??")))) -> 0 | O13: =IF(DAY(J13)=1,IF(J13=0,0,DATE(YEAR(J13),MONTH(J13)+N13,DAY(J13))),IF(J13=0,0,DATE(YEAR(J13),MONTH(J13)+N13,DAY(J13)-1))) -> 0 | P13: =MIN(IF(AND(DAY(J13)=31,DAY($B$7-1)=30),IF(J13=0,0,IF(O13>($B$7-1),VALUE(DATEDIF(J13,MIN(($B$7-1),O13),"m"))+1,VALUE(DATEDIF(J13,MIN(($B$7-1),O13),"m")+2))),IF(J13=0,0,IF(O13>($B$7-1),DATEDIF(J13,MIN(($B$7-1),O13),"m"),VALUE(DATEDIF(J13,MIN(($B$7-1),O13),"m")+1)))),N13) -> #NUM! | Q13: =MIN(IF(AND(DAY(J13)=31,DAY($D$7)=30),IF(J13=0,0,IF(O13>$D$7,VALUE(DATEDIF(J13,MIN($D$7,O13),"m"))+1,VALUE(DATEDIF(J13,MIN($D$7,O13),"m")+2))),IF(J13=0,0,IF(O13>$D$7,DATEDIF(J13,MIN($D$7,O13),"m"),VALUE(DATEDIF(J13,MIN($D$7,O13),"m")+1)))),N13) -> 0 | R13: =IF(OR(J13=0,O13<$B$7),0,IF(AND(J13<$B$7,O13>$D$7),VALUE(DATEDIF($B$7,$D$7,"m")+1),IF(AND(J13<$B$7,O13<=$D$7),VALUE(DATEDIF($B$7,O13,"m")+1),IF(AND(J13>=$B$7,O13>$D$7),VALUE(DATEDIF(J13,$D$7,"m")),IF(AND(J13>=$B$7,O13<=$D$7),VALUE(DATEDIF(J13,O13,"m")+1),))))) -> 0 | S13: =IF(AND(YEAR(J13)=YEAR($D$7),DAY(J13)=31,DAY($D$7)=30),IF(J13>$F$7,0,R13-T13+1),IF(J13>$F$7,0,R13-T13)) -> 0 | T13: =IF(AND(DAY($F$7)=31,DAY($D$7)=30),IF(J13=0,0,IF($F$7<$B$7,R13,VALUE(DATEDIF(MAX(J13,$F$7),MIN(O13,$D$7),"m")))+1),IF(J13=0,0,IF($F$7<$B$7,R13,DATEDIF(MAX(J13,$F$7),MIN(O13,$D$7),"m")))) -> 0 | U13: =IF(N13=0,0,ROUND((E13*(1-L13)-F13-H13)/(N13-P13),2)) -> 0 | V13: =ROUND(U13*S13,2)+F13 -> 0 | W13: =IF((E13*(1-L13)-V13-I13)>0,(E13*(1-L13)-V13-I13)/(N13-P13-S13),0) -> 0 | X13: =ROUND(U13*S13,2)+ROUND(W13*T13,2) -> 0 | Y13: =ROUND(M13-W13,2) -> 0 | Z13: =F13+X13 -> 0 | AA13: =ROUND(G13-Z13,2) -> 0
A14: ='明细表H1-2'!A18 -> 0 | B14: ='明细表H1-2'!B18 -> 0 | C14: ='明细表H1-2'!C18 -> 0 | E14: ='明细表H1-2'!P18 -> 0 | F14: ='明细表H1-2'!AB18 -> 0 | G14: ='明细表H1-2'!AE18 -> 0 | H14: ='明细表H1-2'!AQ18 -> 0 | I14: ='明细表H1-2'!AT18 -> 0 | N14: =IF(K14=0,0,IF(RIGHT(K14,1)<>"年",K14*12,IF(LEN(K14)=3,VALUE(LEFT(K14,2))*12,IF(LEN(K14)=2,VALUE(LEFT(K14,1))*12,"??")))) -> 0 | O14: =IF(DAY(J14)=1,IF(J14=0,0,DATE(YEAR(J14),MONTH(J14)+N14,DAY(J14))),IF(J14=0,0,DATE(YEAR(J14),MONTH(J14)+N14,DAY(J14)-1))) -> 0 | P14: =MIN(IF(AND(DAY(J14)=31,DAY($B$7-1)=30),IF(J14=0,0,IF(O14>($B$7-1),VALUE(DATEDIF(J14,MIN(($B$7-1),O14),"m"))+1,VALUE(DATEDIF(J14,MIN(($B$7-1),O14),"m")+2))),IF(J14=0,0,IF(O14>($B$7-1),DATEDIF(J14,MIN(($B$7-1),O14),"m"),VALUE(DATEDIF(J14,MIN(($B$7-1),O14),"m")+1)))),N14) -> #NUM! | Q14: =MIN(IF(AND(DAY(J14)=31,DAY($D$7)=30),IF(J14=0,0,IF(O14>$D$7,VALUE(DATEDIF(J14,MIN($D$7,O14),"m"))+1,VALUE(DATEDIF(J14,MIN($D$7,O14),"m")+2))),IF(J14=0,0,IF(O14>$D$7,DATEDIF(J14,MIN($D$7,O14),"m"),VALUE(DATEDIF(J14,MIN($D$7,O14),"m")+1)))),N14) -> 0 | R14: =IF(OR(J14=0,O14<$B$7),0,IF(AND(J14<$B$7,O14>$D$7),VALUE(DATEDIF($B$7,$D$7,"m")+1),IF(AND(J14<$B$7,O14<=$D$7),VALUE(DATEDIF($B$7,O14,"m")+1),IF(AND(J14>=$B$7,O14>$D$7),VALUE(DATEDIF(J14,$D$7,"m")),IF(AND(J14>=$B$7,O14<=$D$7),VALUE(DATEDIF(J14,O14,"m")+1),))))) -> 0 | S14: =IF(AND(YEAR(J14)=YEAR($D$7),DAY(J14)=31,DAY($D$7)=30),IF(J14>$F$7,0,R14-T14+1),IF(J14>$F$7,0,R14-T14)) -> 0 | T14: =IF(AND(DAY($F$7)=31,DAY($D$7)=30),IF(J14=0,0,IF($F$7<$B$7,R14,VALUE(DATEDIF(MAX(J14,$F$7),MIN(O14,$D$7),"m")))+1),IF(J14=0,0,IF($F$7<$B$7,R14,DATEDIF(MAX(J14,$F$7),MIN(O14,$D$7),"m")))) -> 0 | U14: =IF(N14=0,0,ROUND((E14*(1-L14)-F14-H14)/(N14-P14),2)) -> 0 | V14: =ROUND(U14*S14,2)+F14 -> 0 | W14: =IF((E14*(1-L14)-V14-I14)>0,(E14*(1-L14)-V14-I14)/(N14-P14-S14),0) -> 0 | X14: =ROUND(U14*S14,2)+ROUND(W14*T14,2) -> 0 | Y14: =ROUND(M14-W14,2) -> 0 | Z14: =F14+X14 -> 0 | AA14: =ROUND(G14-Z14,2) -> 0
A15: ='明细表H1-2'!A19 -> 0 | B15: ='明细表H1-2'!B19 -> 0 | C15: ='明细表H1-2'!C19 -> 0 | E15: ='明细表H1-2'!P19 -> 0 | F15: ='明细表H1-2'!AB19 -> 0 | G15: ='明细表H1-2'!AE19 -> 0 | H15: ='明细表H1-2'!AQ19 -> 0 | I15: ='明细表H1-2'!AT19 -> 0 | N15: =IF(K15=0,0,IF(RIGHT(K15,1)<>"年",K15*12,IF(LEN(K15)=3,VALUE(LEFT(K15,2))*12,IF(LEN(K15)=2,VALUE(LEFT(K15,1))*12,"??")))) -> 0 | O15: =IF(DAY(J15)=1,IF(J15=0,0,DATE(YEAR(J15),MONTH(J15)+N15,DAY(J15))),IF(J15=0,0,DATE(YEAR(J15),MONTH(J15)+N15,DAY(J15)-1))) -> 0 | P15: =MIN(IF(AND(DAY(J15)=31,DAY($B$7-1)=30),IF(J15=0,0,IF(O15>($B$7-1),VALUE(DATEDIF(J15,MIN(($B$7-1),O15),"m"))+1,VALUE(DATEDIF(J15,MIN(($B$7-1),O15),"m")+2))),IF(J15=0,0,IF(O15>($B$7-1),DATEDIF(J15,MIN(($B$7-1),O15),"m"),VALUE(DATEDIF(J15,MIN(($B$7-1),O15),"m")+1)))),N15) -> #NUM! | Q15: =MIN(IF(AND(DAY(J15)=31,DAY($D$7)=30),IF(J15=0,0,IF(O15>$D$7,VALUE(DATEDIF(J15,MIN($D$7,O15),"m"))+1,VALUE(DATEDIF(J15,MIN($D$7,O15),"m")+2))),IF(J15=0,0,IF(O15>$D$7,DATEDIF(J15,MIN($D$7,O15),"m"),VALUE(DATEDIF(J15,MIN($D$7,O15),"m")+1)))),N15) -> 0 | R15: =IF(OR(J15=0,O15<$B$7),0,IF(AND(J15<$B$7,O15>$D$7),VALUE(DATEDIF($B$7,$D$7,"m")+1),IF(AND(J15<$B$7,O15<=$D$7),VALUE(DATEDIF($B$7,O15,"m")+1),IF(AND(J15>=$B$7,O15>$D$7),VALUE(DATEDIF(J15,$D$7,"m")),IF(AND(J15>=$B$7,O15<=$D$7),VALUE(DATEDIF(J15,O15,"m")+1),))))) -> 0 | S15: =IF(AND(YEAR(J15)=YEAR($D$7),DAY(J15)=31,DAY($D$7)=30),IF(J15>$F$7,0,R15-T15+1),IF(J15>$F$7,0,R15-T15)) -> 0 | T15: =IF(AND(DAY($F$7)=31,DAY($D$7)=30),IF(J15=0,0,IF($F$7<$B$7,R15,VALUE(DATEDIF(MAX(J15,$F$7),MIN(O15,$D$7),"m")))+1),IF(J15=0,0,IF($F$7<$B$7,R15,DATEDIF(MAX(J15,$F$7),MIN(O15,$D$7),"m")))) -> 0 | U15: =IF(N15=0,0,ROUND((E15*(1-L15)-F15-H15)/(N15-P15),2)) -> 0 | V15: =ROUND(U15*S15,2)+F15 -> 0 | W15: =IF((E15*(1-L15)-V15-I15)>0,(E15*(1-L15)-V15-I15)/(N15-P15-S15),0) -> 0 | X15: =ROUND(U15*S15,2)+ROUND(W15*T15,2) -> 0 | Y15: =ROUND(M15-W15,2) -> 0 | Z15: =F15+X15 -> 0 | AA15: =ROUND(G15-Z15,2) -> 0
A16: ='明细表H1-2'!A20 -> 0 | B16: ='明细表H1-2'!B20 -> 0 | C16: ='明细表H1-2'!C20 -> 0 | E16: ='明细表H1-2'!P20 -> 0 | F16: ='明细表H1-2'!AB20 -> 0 | G16: ='明细表H1-2'!AE20 -> 0 | H16: ='明细表H1-2'!AQ20 -> 0 | I16: ='明细表H1-2'!AT20 -> 0 | N16: =IF(K16=0,0,IF(RIGHT(K16,1)<>"年",K16*12,IF(LEN(K16)=3,VALUE(LEFT(K16,2))*12,IF(LEN(K16)=2,VALUE(LEFT(K16,1))*12,"??")))) -> 0 | O16: =IF(DAY(J16)=1,IF(J16=0,0,DATE(YEAR(J16),MONTH(J16)+N16,DAY(J16))),IF(J16=0,0,DATE(YEAR(J16),MONTH(J16)+N16,DAY(J16)-1))) -> 0 | P16: =MIN(IF(AND(DAY(J16)=31,DAY($B$7-1)=30),IF(J16=0,0,IF(O16>($B$7-1),VALUE(DATEDIF(J16,MIN(($B$7-1),O16),"m"))+1,VALUE(DATEDIF(J16,MIN(($B$7-1),O16),"m")+2))),IF(J16=0,0,IF(O16>($B$7-1),DATEDIF(J16,MIN(($B$7-1),O16),"m"),VALUE(DATEDIF(J16,MIN(($B$7-1),O16),"m")+1)))),N16) -> #NUM! | Q16: =MIN(IF(AND(DAY(J16)=31,DAY($D$7)=30),IF(J16=0,0,IF(O16>$D$7,VALUE(DATEDIF(J16,MIN($D$7,O16),"m"))+1,VALUE(DATEDIF(J16,MIN($D$7,O16),"m")+2))),IF(J16=0,0,IF(O16>$D$7,DATEDIF(J16,MIN($D$7,O16),"m"),VALUE(DATEDIF(J16,MIN($D$7,O16),"m")+1)))),N16) -> 0 | R16: =IF(OR(J16=0,O16<$B$7),0,IF(AND(J16<$B$7,O16>$D$7),VALUE(DATEDIF($B$7,$D$7,"m")+1),IF(AND(J16<$B$7,O16<=$D$7),VALUE(DATEDIF($B$7,O16,"m")+1),IF(AND(J16>=$B$7,O16>$D$7),VALUE(DATEDIF(J16,$D$7,"m")),IF(AND(J16>=$B$7,O16<=$D$7),VALUE(DATEDIF(J16,O16,"m")+1),))))) -> 0 | S16: =IF(AND(YEAR(J16)=YEAR($D$7),DAY(J16)=31,DAY($D$7)=30),IF(J16>$F$7,0,R16-T16+1),IF(J16>$F$7,0,R16-T16)) -> 0 | T16: =IF(AND(DAY($F$7)=31,DAY($D$7)=30),IF(J16=0,0,IF($F$7<$B$7,R16,VALUE(DATEDIF(MAX(J16,$F$7),MIN(O16,$D$7),"m")))+1),IF(J16=0,0,IF($F$7<$B$7,R16,DATEDIF(MAX(J16,$F$7),MIN(O16,$D$7),"m")))) -> 0 | U16: =IF(N16=0,0,ROUND((E16*(1-L16)-F16-H16)/(N16-P16),2)) -> 0 | V16: =ROUND(U16*S16,2)+F16 -> 0 | W16: =IF((E16*(1-L16)-V16-I16)>0,(E16*(1-L16)-V16-I16)/(N16-P16-S16),0) -> 0 | X16: =ROUND(U16*S16,2)+ROUND(W16*T16,2) -> 0 | Y16: =ROUND(M16-W16,2) -> 0 | Z16: =F16+X16 -> 0 | AA16: =ROUND(G16-Z16,2) -> 0
A17: ='明细表H1-2'!A21 -> 0 | B17: ='明细表H1-2'!B21 -> 0 | C17: ='明细表H1-2'!C21 -> 0 | E17: ='明细表H1-2'!P21 -> 0 | F17: ='明细表H1-2'!AB21 -> 0 | G17: ='明细表H1-2'!AE21 -> 0 | H17: ='明细表H1-2'!AQ21 -> 0 | I17: ='明细表H1-2'!AT21 -> 0 | N17: =IF(K17=0,0,IF(RIGHT(K17,1)<>"年",K17*12,IF(LEN(K17)=3,VALUE(LEFT(K17,2))*12,IF(LEN(K17)=2,VALUE(LEFT(K17,1))*12,"??")))) -> 0 | O17: =IF(DAY(J17)=1,IF(J17=0,0,DATE(YEAR(J17),MONTH(J17)+N17,DAY(J17))),IF(J17=0,0,DATE(YEAR(J17),MONTH(J17)+N17,DAY(J17)-1))) -> 0 | P17: =MIN(IF(AND(DAY(J17)=31,DAY($B$7-1)=30),IF(J17=0,0,IF(O17>($B$7-1),VALUE(DATEDIF(J17,MIN(($B$7-1),O17),"m"))+1,VALUE(DATEDIF(J17,MIN(($B$7-1),O17),"m")+2))),IF(J17=0,0,IF(O17>($B$7-1),DATEDIF(J17,MIN(($B$7-1),O17),"m"),VALUE(DATEDIF(J17,MIN(($B$7-1),O17),"m")+1)))),N17) -> #NUM! | Q17: =MIN(IF(AND(DAY(J17)=31,DAY($D$7)=30),IF(J17=0,0,IF(O17>$D$7,VALUE(DATEDIF(J17,MIN($D$7,O17),"m"))+1,VALUE(DATEDIF(J17,MIN($D$7,O17),"m")+2))),IF(J17=0,0,IF(O17>$D$7,DATEDIF(J17,MIN($D$7,O17),"m"),VALUE(DATEDIF(J17,MIN($D$7,O17),"m")+1)))),N17) -> 0 | R17: =IF(OR(J17=0,O17<$B$7),0,IF(AND(J17<$B$7,O17>$D$7),VALUE(DATEDIF($B$7,$D$7,"m")+1),IF(AND(J17<$B$7,O17<=$D$7),VALUE(DATEDIF($B$7,O17,"m")+1),IF(AND(J17>=$B$7,O17>$D$7),VALUE(DATEDIF(J17,$D$7,"m")),IF(AND(J17>=$B$7,O17<=$D$7),VALUE(DATEDIF(J17,O17,"m")+1),))))) -> 0 | S17: =IF(AND(YEAR(J17)=YEAR($D$7),DAY(J17)=31,DAY($D$7)=30),IF(J17>$F$7,0,R17-T17+1),IF(J17>$F$7,0,R17-T17)) -> 0 | T17: =IF(AND(DAY($F$7)=31,DAY($D$7)=30),IF(J17=0,0,IF($F$7<$B$7,R17,VALUE(DATEDIF(MAX(J17,$F$7),MIN(O17,$D$7),"m")))+1),IF(J17=0,0,IF($F$7<$B$7,R17,DATEDIF(MAX(J17,$F$7),MIN(O17,$D$7),"m")))) -> 0 | U17: =IF(N17=0,0,ROUND((E17*(1-L17)-F17-H17)/(N17-P17),2)) -> 0 | V17: =ROUND(U17*S17,2)+F17 -> 0 | W17: =IF((E17*(1-L17)-V17-I17)>0,(E17*(1-L17)-V17-I17)/(N17-P17-S17),0) -> 0 | X17: =ROUND(U17*S17,2)+ROUND(W17*T17,2) -> 0 | Y17: =ROUND(M17-W17,2) -> 0 | Z17: =F17+X17 -> 0 | AA17: =ROUND(G17-Z17,2) -> 0
A18: ='明细表H1-2'!A22 -> 0 | B18: ='明细表H1-2'!B22 -> 0 | C18: ='明细表H1-2'!C22 -> 0 | E18: ='明细表H1-2'!P22 -> 0 | F18: ='明细表H1-2'!AB22 -> 0 | G18: ='明细表H1-2'!AE22 -> 0 | H18: ='明细表H1-2'!AQ22 -> 0 | I18: ='明细表H1-2'!AT22 -> 0 | N18: =IF(K18=0,0,IF(RIGHT(K18,1)<>"年",K18*12,IF(LEN(K18)=3,VALUE(LEFT(K18,2))*12,IF(LEN(K18)=2,VALUE(LEFT(K18,1))*12,"??")))) -> 0 | O18: =IF(DAY(J18)=1,IF(J18=0,0,DATE(YEAR(J18),MONTH(J18)+N18,DAY(J18))),IF(J18=0,0,DATE(YEAR(J18),MONTH(J18)+N18,DAY(J18)-1))) -> 0 | P18: =MIN(IF(AND(DAY(J18)=31,DAY($B$7-1)=30),IF(J18=0,0,IF(O18>($B$7-1),VALUE(DATEDIF(J18,MIN(($B$7-1),O18),"m"))+1,VALUE(DATEDIF(J18,MIN(($B$7-1),O18),"m")+2))),IF(J18=0,0,IF(O18>($B$7-1),DATEDIF(J18,MIN(($B$7-1),O18),"m"),VALUE(DATEDIF(J18,MIN(($B$7-1),O18),"m")+1)))),N18) -> #NUM! | Q18: =MIN(IF(AND(DAY(J18)=31,DAY($D$7)=30),IF(J18=0,0,IF(O18>$D$7,VALUE(DATEDIF(J18,MIN($D$7,O18),"m"))+1,VALUE(DATEDIF(J18,MIN($D$7,O18),"m")+2))),IF(J18=0,0,IF(O18>$D$7,DATEDIF(J18,MIN($D$7,O18),"m"),VALUE(DATEDIF(J18,MIN($D$7,O18),"m")+1)))),N18) -> 0 | R18: =IF(OR(J18=0,O18<$B$7),0,IF(AND(J18<$B$7,O18>$D$7),VALUE(DATEDIF($B$7,$D$7,"m")+1),IF(AND(J18<$B$7,O18<=$D$7),VALUE(DATEDIF($B$7,O18,"m")+1),IF(AND(J18>=$B$7,O18>$D$7),VALUE(DATEDIF(J18,$D$7,"m")),IF(AND(J18>=$B$7,O18<=$D$7),VALUE(DATEDIF(J18,O18,"m")+1),))))) -> 0 | S18: =IF(AND(YEAR(J18)=YEAR($D$7),DAY(J18)=31,DAY($D$7)=30),IF(J18>$F$7,0,R18-T18+1),IF(J18>$F$7,0,R18-T18)) -> 0 | T18: =IF(AND(DAY($F$7)=31,DAY($D$7)=30),IF(J18=0,0,IF($F$7<$B$7,R18,VALUE(DATEDIF(MAX(J18,$F$7),MIN(O18,$D$7),"m")))+1),IF(J18=0,0,IF($F$7<$B$7,R18,DATEDIF(MAX(J18,$F$7),MIN(O18,$D$7),"m")))) -> 0 | U18: =IF(N18=0,0,ROUND((E18*(1-L18)-F18-H18)/(N18-P18),2)) -> 0 | V18: =ROUND(U18*S18,2)+F18 -> 0 | W18: =IF((E18*(1-L18)-V18-I18)>0,(E18*(1-L18)-V18-I18)/(N18-P18-S18),0) -> 0 | X18: =ROUND(U18*S18,2)+ROUND(W18*T18,2) -> 0 | Y18: =ROUND(M18-W18,2) -> 0 | Z18: =F18+X18 -> 0 | AA18: =ROUND(G18-Z18,2) -> 0
A19: ='明细表H1-2'!A23 -> 0 | B19: ='明细表H1-2'!B23 -> 0 | C19: ='明细表H1-2'!C23 -> 0 | E19: ='明细表H1-2'!P23 -> 0 | F19: ='明细表H1-2'!AB23 -> 0 | G19: ='明细表H1-2'!AE23 -> 0 | H19: ='明细表H1-2'!AQ23 -> 0 | I19: ='明细表H1-2'!AT23 -> 0 | N19: =IF(K19=0,0,IF(RIGHT(K19,1)<>"年",K19*12,IF(LEN(K19)=3,VALUE(LEFT(K19,2))*12,IF(LEN(K19)=2,VALUE(LEFT(K19,1))*12,"??")))) -> 0 | O19: =IF(DAY(J19)=1,IF(J19=0,0,DATE(YEAR(J19),MONTH(J19)+N19,DAY(J19))),IF(J19=0,0,DATE(YEAR(J19),MONTH(J19)+N19,DAY(J19)-1))) -> 0 | P19: =MIN(IF(AND(DAY(J19)=31,DAY($B$7-1)=30),IF(J19=0,0,IF(O19>($B$7-1),VALUE(DATEDIF(J19,MIN(($B$7-1),O19),"m"))+1,VALUE(DATEDIF(J19,MIN(($B$7-1),O19),"m")+2))),IF(J19=0,0,IF(O19>($B$7-1),DATEDIF(J19,MIN(($B$7-1),O19),"m"),VALUE(DATEDIF(J19,MIN(($B$7-1),O19),"m")+1)))),N19) -> #NUM! | Q19: =MIN(IF(AND(DAY(J19)=31,DAY($D$7)=30),IF(J19=0,0,IF(O19>$D$7,VALUE(DATEDIF(J19,MIN($D$7,O19),"m"))+1,VALUE(DATEDIF(J19,MIN($D$7,O19),"m")+2))),IF(J19=0,0,IF(O19>$D$7,DATEDIF(J19,MIN($D$7,O19),"m"),VALUE(DATEDIF(J19,MIN($D$7,O19),"m")+1)))),N19) -> 0 | R19: =IF(OR(J19=0,O19<$B$7),0,IF(AND(J19<$B$7,O19>$D$7),VALUE(DATEDIF($B$7,$D$7,"m")+1),IF(AND(J19<$B$7,O19<=$D$7),VALUE(DATEDIF($B$7,O19,"m")+1),IF(AND(J19>=$B$7,O19>$D$7),VALUE(DATEDIF(J19,$D$7,"m")),IF(AND(J19>=$B$7,O19<=$D$7),VALUE(DATEDIF(J19,O19,"m")+1),))))) -> 0 | S19: =IF(AND(YEAR(J19)=YEAR($D$7),DAY(J19)=31,DAY($D$7)=30),IF(J19>$F$7,0,R19-T19+1),IF(J19>$F$7,0,R19-T19)) -> 0 | T19: =IF(AND(DAY($F$7)=31,DAY($D$7)=30),IF(J19=0,0,IF($F$7<$B$7,R19,VALUE(DATEDIF(MAX(J19,$F$7),MIN(O19,$D$7),"m")))+1),IF(J19=0,0,IF($F$7<$B$7,R19,DATEDIF(MAX(J19,$F$7),MIN(O19,$D$7),"m")))) -> 0 | U19: =IF(N19=0,0,ROUND((E19*(1-L19)-F19-H19)/(N19-P19),2)) -> 0 | V19: =ROUND(U19*S19,2)+F19 -> 0 | W19: =IF((E19*(1-L19)-V19-I19)>0,(E19*(1-L19)-V19-I19)/(N19-P19-S19),0) -> 0 | X19: =ROUND(U19*S19,2)+ROUND(W19*T19,2) -> 0 | Y19: =ROUND(M19-W19,2) -> 0 | Z19: =F19+X19 -> 0 | AA19: =ROUND(G19-Z19,2) -> 0
A20: ='明细表H1-2'!A24 -> 0 | B20: ='明细表H1-2'!B24 -> 0 | C20: ='明细表H1-2'!C24 -> 0 | E20: ='明细表H1-2'!P24 -> 0 | F20: ='明细表H1-2'!AB24 -> 0 | G20: ='明细表H1-2'!AE24 -> 0 | H20: ='明细表H1-2'!AQ24 -> 0 | I20: ='明细表H1-2'!AT24 -> 0 | N20: =IF(K20=0,0,IF(RIGHT(K20,1)<>"年",K20*12,IF(LEN(K20)=3,VALUE(LEFT(K20,2))*12,IF(LEN(K20)=2,VALUE(LEFT(K20,1))*12,"??")))) -> 0 | O20: =IF(DAY(J20)=1,IF(J20=0,0,DATE(YEAR(J20),MONTH(J20)+N20,DAY(J20))),IF(J20=0,0,DATE(YEAR(J20),MONTH(J20)+N20,DAY(J20)-1))) -> 0 | P20: =MIN(IF(AND(DAY(J20)=31,DAY($B$7-1)=30),IF(J20=0,0,IF(O20>($B$7-1),VALUE(DATEDIF(J20,MIN(($B$7-1),O20),"m"))+1,VALUE(DATEDIF(J20,MIN(($B$7-1),O20),"m")+2))),IF(J20=0,0,IF(O20>($B$7-1),DATEDIF(J20,MIN(($B$7-1),O20),"m"),VALUE(DATEDIF(J20,MIN(($B$7-1),O20),"m")+1)))),N20) -> #NUM! | Q20: =MIN(IF(AND(DAY(J20)=31,DAY($D$7)=30),IF(J20=0,0,IF(O20>$D$7,VALUE(DATEDIF(J20,MIN($D$7,O20),"m"))+1,VALUE(DATEDIF(J20,MIN($D$7,O20),"m")+2))),IF(J20=0,0,IF(O20>$D$7,DATEDIF(J20,MIN($D$7,O20),"m"),VALUE(DATEDIF(J20,MIN($D$7,O20),"m")+1)))),N20) -> 0 | R20: =IF(OR(J20=0,O20<$B$7),0,IF(AND(J20<$B$7,O20>$D$7),VALUE(DATEDIF($B$7,$D$7,"m")+1),IF(AND(J20<$B$7,O20<=$D$7),VALUE(DATEDIF($B$7,O20,"m")+1),IF(AND(J20>=$B$7,O20>$D$7),VALUE(DATEDIF(J20,$D$7,"m")),IF(AND(J20>=$B$7,O20<=$D$7),VALUE(DATEDIF(J20,O20,"m")+1),))))) -> 0 | S20: =IF(AND(YEAR(J20)=YEAR($D$7),DAY(J20)=31,DAY($D$7)=30),IF(J20>$F$7,0,R20-T20+1),IF(J20>$F$7,0,R20-T20)) -> 0 | T20: =IF(AND(DAY($F$7)=31,DAY($D$7)=30),IF(J20=0,0,IF($F$7<$B$7,R20,VALUE(DATEDIF(MAX(J20,$F$7),MIN(O20,$D$7),"m")))+1),IF(J20=0,0,IF($F$7<$B$7,R20,DATEDIF(MAX(J20,$F$7),MIN(O20,$D$7),"m")))) -> 0 | U20: =IF(N20=0,0,ROUND((E20*(1-L20)-F20-H20)/(N20-P20),2)) -> 0 | V20: =ROUND(U20*S20,2)+F20 -> 0 | W20: =IF((E20*(1-L20)-V20-I20)>0,(E20*(1-L20)-V20-I20)/(N20-P20-S20),0) -> 0 | X20: =ROUND(U20*S20,2)+ROUND(W20*T20,2) -> 0 | Y20: =ROUND(M20-W20,2) -> 0 | Z20: =F20+X20 -> 0 | AA20: =ROUND(G20-Z20,2) -> 0
... A28: ='明细表H1-2'!A32 -> 0 | B28: ='明细表H1-2'!B32 -> 0 | C28: ='明细表H1-2'!C32 -> 0 | E28: ='明细表H1-2'!P32 -> 0 | F28: ='明细表H1-2'!AB32 -> 0 | G28: ='明细表H1-2'!AE32 -> 0 | H28: ='明细表H1-2'!AQ32 -> 0 | I28: ='明细表H1-2'!AT32 -> 0 | N28: =IF(K28=0,0,IF(RIGHT(K28,1)<>"年",K28*12,IF(LEN(K28)=3,VALUE(LEFT(K28,2))*12,IF(LEN(K28)=2,VALUE(LEFT(K28,1))*12,"??")))) -> 0 | O28: =IF(DAY(J28)=1,IF(J28=0,0,DATE(YEAR(J28),MONTH(J28)+N28,DAY(J28))),IF(J28=0,0,DATE(YEAR(J28),MONTH(J28)+N28,DAY(J28)-1))) -> 0 | P28: =MIN(IF(AND(DAY(J28)=31,DAY($B$7-1)=30),IF(J28=0,0,IF(O28>($B$7-1),VALUE(DATEDIF(J28,MIN(($B$7-1),O28),"m"))+1,VALUE(DATEDIF(J28,MIN(($B$7-1),O28),"m")+2))),IF(J28=0,0,IF(O28>($B$7-1),DATEDIF(J28,MIN(($B$7-1),O28),"m"),VALUE(DATEDIF(J28,MIN(($B$7-1),O28),"m")+1)))),N28) -> #NUM! | Q28: =MIN(IF(AND(DAY(J28)=31,DAY($D$7)=30),IF(J28=0,0,IF(O28>$D$7,VALUE(DATEDIF(J28,MIN($D$7,O28),"m"))+1,VALUE(DATEDIF(J28,MIN($D$7,O28),"m")+2))),IF(J28=0,0,IF(O28>$D$7,DATEDIF(J28,MIN($D$7,O28),"m"),VALUE(DATEDIF(J28,MIN($D$7,O28),"m")+1)))),N28) -> 0 | R28: =IF(OR(J28=0,O28<$B$7),0,IF(AND(J28<$B$7,O28>$D$7),VALUE(DATEDIF($B$7,$D$7,"m")+1),IF(AND(J28<$B$7,O28<=$D$7),VALUE(DATEDIF($B$7,O28,"m")+1),IF(AND(J28>=$B$7,O28>$D$7),VALUE(DATEDIF(J28,$D$7,"m")),IF(AND(J28>=$B$7,O28<=$D$7),VALUE(DATEDIF(J28,O28,"m")+1),))))) -> 0 | S28: =IF(AND(YEAR(J28)=YEAR($D$7),DAY(J28)=31,DAY($D$7)=30),IF(J28>$F$7,0,R28-T28+1),IF(J28>$F$7,0,R28-T28)) -> 0 | T28: =IF(AND(DAY($F$7)=31,DAY($D$7)=30),IF(J28=0,0,IF($F$7<$B$7,R28,VALUE(DATEDIF(MAX(J28,$F$7),MIN(O28,$D$7),"m")))+1),IF(J28=0,0,IF($F$7<$B$7,R28,DATEDIF(MAX(J28,$F$7),MIN(O28,$D$7),"m")))) -> 0 | U28: =IF(N28=0,0,ROUND((E28*(1-L28)-F28-H28)/(N28-P28),2)) -> 0 | V28: =ROUND(U28*S28,2)+F28 -> 0 | W28: =IF((E28*(1-L28)-V28-I28)>0,(E28*(1-L28)-V28-I28)/(N28-P28-S28),0) -> 0 | X28: =ROUND(U28*S28,2)+ROUND(W28*T28,2) -> 0 | Y28: =ROUND(M28-W28,2) -> 0 | Z28: =F28+X28 -> 0 | AA28: =ROUND(G28-Z28,2) -> 0
A29: 合计 | E29: =SUM(E9:E28) -> 0 | F29: =SUM(F9:F28) -> 0 | G29: =SUM(G9:G28) -> 0 | H29: =SUM(H9:H28) -> 0 | I29: =SUM(I9:I28) -> 0 | O29: =IF(J29=0,0,DATE(YEAR(J29),MONTH(J29)+N29,DAY(J29)-1)) -> 0 | U29: =SUM(U9:U28) -> 0 | V29: =SUM(V9:V28) -> 0 | W29: =SUM(W9:W28) -> 0 | X29: =SUM(X9:X28) -> 0 | Y29: =SUM(Y9:Y28) -> 0 | Z29: =SUM(Z9:Z28) -> 0 | AA29: =SUM(AA9:AA28) -> 0
A30: ='明细表H1-2'!A34 -> 其中：
A31: ='明细表H1-2'!A35 -> 房屋及建筑物 | E31: =SUMPRODUCT(($A$9:$A$28=$A31)*(E$9:E$28)) -> 0 | F31: =SUMPRODUCT(($A$9:$A$28=$A31)*(F$9:F$28)) -> 0 | G31: =SUMPRODUCT(($A$9:$A$28=$A31)*(G$9:G$28)) -> 0 | H31: =SUMPRODUCT(($A$9:$A$28=$A31)*(H$9:H$28)) -> 0 | I31: =SUMPRODUCT(($A$9:$A$28=$A31)*(I$9:I$28)) -> 0 | U31: =SUMPRODUCT(($A$9:$A$28=$A31)*(U$9:U$28)) -> 0 | V31: =SUMPRODUCT(($A$9:$A$28=$A31)*(V$9:V$28)) -> 0 | W31: =SUMPRODUCT(($A$9:$A$28=$A31)*(W$9:W$28)) -> 0 | X31: =SUMPRODUCT(($A$9:$A$28=$A31)*(X$9:X$28)) -> 0 | Y31: =SUMPRODUCT(($A$9:$A$28=$A31)*(Y$9:Y$28)) -> 0 | Z31: =SUMPRODUCT(($A$9:$A$28=$A31)*(Z$9:Z$28)) -> 0 | AA31: =SUMPRODUCT(($A$9:$A$28=$A31)*(AA$9:AA$28)) -> 0
A32: ='明细表H1-2'!A36 -> 机器设备 | E32: =SUMPRODUCT(($A$9:$A$28=$A32)*(E$9:E$28)) -> 0 | F32: =SUMPRODUCT(($A$9:$A$28=$A32)*(F$9:F$28)) -> 0 | G32: =SUMPRODUCT(($A$9:$A$28=$A32)*(G$9:G$28)) -> 0 | H32: =SUMPRODUCT(($A$9:$A$28=$A32)*(H$9:H$28)) -> 0 | I32: =SUMPRODUCT(($A$9:$A$28=$A32)*(I$9:I$28)) -> 0 | U32: =SUMPRODUCT(($A$9:$A$28=$A32)*(U$9:U$28)) -> 0 | V32: =SUMPRODUCT(($A$9:$A$28=$A32)*(V$9:V$28)) -> 0 | W32: =SUMPRODUCT(($A$9:$A$28=$A32)*(W$9:W$28)) -> 0 | X32: =SUMPRODUCT(($A$9:$A$28=$A32)*(X$9:X$28)) -> 0 | Y32: =SUMPRODUCT(($A$9:$A$28=$A32)*(Y$9:Y$28)) -> 0 | Z32: =SUMPRODUCT(($A$9:$A$28=$A32)*(Z$9:Z$28)) -> 0 | AA32: =SUMPRODUCT(($A$9:$A$28=$A32)*(AA$9:AA$28)) -> 0
A33: ='明细表H1-2'!A37 -> 运输设备 | E33: =SUMPRODUCT(($A$9:$A$28=$A33)*(E$9:E$28)) -> 0 | F33: =SUMPRODUCT(($A$9:$A$28=$A33)*(F$9:F$28)) -> 0 | G33: =SUMPRODUCT(($A$9:$A$28=$A33)*(G$9:G$28)) -> 0 | H33: =SUMPRODUCT(($A$9:$A$28=$A33)*(H$9:H$28)) -> 0 | I33: =SUMPRODUCT(($A$9:$A$28=$A33)*(I$9:I$28)) -> 0 | U33: =SUMPRODUCT(($A$9:$A$28=$A33)*(U$9:U$28)) -> 0 | V33: =SUMPRODUCT(($A$9:$A$28=$A33)*(V$9:V$28)) -> 0 | W33: =SUMPRODUCT(($A$9:$A$28=$A33)*(W$9:W$28)) -> 0 | X33: =SUMPRODUCT(($A$9:$A$28=$A33)*(X$9:X$28)) -> 0 | Y33: =SUMPRODUCT(($A$9:$A$28=$A33)*(Y$9:Y$28)) -> 0 | Z33: =SUMPRODUCT(($A$9:$A$28=$A33)*(Z$9:Z$28)) -> 0 | AA33: =SUMPRODUCT(($A$9:$A$28=$A33)*(AA$9:AA$28)) -> 0
A34: ='明细表H1-2'!A38 -> 办公设备 | E34: =SUMPRODUCT(($A$9:$A$28=$A34)*(E$9:E$28)) -> 0 | F34: =SUMPRODUCT(($A$9:$A$28=$A34)*(F$9:F$28)) -> 0 | G34: =SUMPRODUCT(($A$9:$A$28=$A34)*(G$9:G$28)) -> 0 | H34: =SUMPRODUCT(($A$9:$A$28=$A34)*(H$9:H$28)) -> 0 | I34: =SUMPRODUCT(($A$9:$A$28=$A34)*(I$9:I$28)) -> 0 | U34: =SUMPRODUCT(($A$9:$A$28=$A34)*(U$9:U$28)) -> 0 | V34: =SUMPRODUCT(($A$9:$A$28=$A34)*(V$9:V$28)) -> 0 | W34: =SUMPRODUCT(($A$9:$A$28=$A34)*(W$9:W$28)) -> 0 | X34: =SUMPRODUCT(($A$9:$A$28=$A34)*(X$9:X$28)) -> 0 | Y34: =SUMPRODUCT(($A$9:$A$28=$A34)*(Y$9:Y$28)) -> 0 | Z34: =SUMPRODUCT(($A$9:$A$28=$A34)*(Z$9:Z$28)) -> 0 | AA34: =SUMPRODUCT(($A$9:$A$28=$A34)*(AA$9:AA$28)) -> 0
A35: ='明细表H1-2'!A39 -> 其他设备 | E35: =SUMPRODUCT(($A$9:$A$28=$A35)*(E$9:E$28)) -> 0 | F35: =SUMPRODUCT(($A$9:$A$28=$A35)*(F$9:F$28)) -> 0 | G35: =SUMPRODUCT(($A$9:$A$28=$A35)*(G$9:G$28)) -> 0 | H35: =SUMPRODUCT(($A$9:$A$28=$A35)*(H$9:H$28)) -> 0 | I35: =SUMPRODUCT(($A$9:$A$28=$A35)*(I$9:I$28)) -> 0 | U35: =SUMPRODUCT(($A$9:$A$28=$A35)*(U$9:U$28)) -> 0 | V35: =SUMPRODUCT(($A$9:$A$28=$A35)*(V$9:V$28)) -> 0 | W35: =SUMPRODUCT(($A$9:$A$28=$A35)*(W$9:W$28)) -> 0 | X35: =SUMPRODUCT(($A$9:$A$28=$A35)*(X$9:X$28)) -> 0 | Y35: =SUMPRODUCT(($A$9:$A$28=$A35)*(Y$9:Y$28)) -> 0 | Z35: =SUMPRODUCT(($A$9:$A$28=$A35)*(Z$9:Z$28)) -> 0 | AA35: =SUMPRODUCT(($A$9:$A$28=$A35)*(AA$9:AA$28)) -> 0
A36: 三、审计说明：
A37: 需单独考虑本期固定资产减少对累计折旧的影响
A39: 四、审计结论

Sheet 折旧分配分析表H1-13
A1: 致同会计师事务所
A2: 固定资产折旧分配分析表
A3: =底稿目录!A2 -> 被审计单位： | D3: =底稿目录!A4 -> 编制人： | G3: =底稿目录!A5 -> 编制日期： | I3: 索引号： | J3: H1-13
A4: =底稿目录!A3 -> 截止日：202X年12月31日 | D4: =底稿目录!A6 -> 复核人： | G4: =底稿目录!A7 -> 复核日期： | I4: 页 次：
A5: 一、审计目标：固定资产以恰当的金额包括在财务报表中，与之相关的计价或分摊调整已恰当记录，相关披露已得到恰当计量和描述。
A6: 二、审计过程：
A7: 序号 | B7: 固定资产类别 | C7: 生产成本 | D7: 制造费用 | E7: 销售费用 | F7: 管理费用 | G7: 研发费用 | H7: … | I7: 合计 | J7: 备注
A8: 1 | B8: 房屋及建筑物 | I8: =SUM(C8:H8) -> 0
A9: 2 | B9: 机器设备 | I9: =SUM(C9:H9) -> 0
A10: 3 | B10: 运输设备 | I10: =SUM(C10:H10) -> 0
A11: 4 | B11: 办公设备 | I11: =SUM(C11:H11) -> 0
A12: 5 | B12: 其他设备 | I12: =SUM(C12:H12) -> 0
A13: 合计 | C13: =SUM(C8:C12) -> 0 | D13: =SUM(D8:D12) -> 0 | E13: =SUM(E8:E12) -> 0 | F13: =SUM(F8:F12) -> 0 | G13: =SUM(G8:G12) -> 0 | H13: =SUM(H8:H12) -> 0 | I13: =SUM(I8:I12) -> 0
B14: 勾稽关系情况 | C14: 勾稽一致，详见xx-XX | D14: 勾稽一致，详见xx-XX | E14: 勾稽一致，详见xx-XX | F14: 勾稽一致，详见xx-XX | G14: 勾稽一致，详见xx-XX | H14: 勾稽一致，详见xx-XX
A15: 三、审计说明：
A17: 四、审计结论：

Sheet 减值测算表H1-14
A1: 致同会计师事务所
A2: 固定资产减值测算表
A3: =底稿目录!A2 -> 被审计单位： | F3: =底稿目录!A4 -> 编制人： | I3: =底稿目录!A5 -> 编制日期： | L3: 索引号： | M3: H1-14
A4: =底稿目录!A3 -> 截止日：202X年12月31日 | F4: =底稿目录!A6 -> 复核人： | I4: =底稿目录!A7 -> 复核日期： | L4: 页 次：
A5: 一、审计目标：固定资产以恰当的金额包括在财务报表中，与之相关的计价或分摊调整已恰当记录，相关披露已得到恰当计量和描述。
A6: 二、审计过程：
A7: 固定资产类别 | B7: 项目名称 | C7: 是否存在减值迹象 | D7: 减值迹象描述 | E7: 账面价值 | F7: 可收回金额 | I7: 期末应计提的减值金额（当⑤＜②） | J7: 期末账面已计提的减值准备 | K7: 本期应补提 或冲回的减值准备 | L7: 工作底稿索引号 | M7: 备注
F8: 公允价值减处置费用的净额 | G8: 预计未来现金流量现值 | H8: 可收回金额（③、④较高者） | J8: 期末已计提 减值准备
D9: ① | E9: ② | F9: ③ | G9: ④ | H9: ⑤ | I9: ⑥＝②-⑤ | J9: ⑦ | K9: ⑧=⑥-⑦
H10: =MAX(F10,G10) -> 0 | I10: =IF(E10>H10,E10-H10,0) -> 0 | K10: =I10-J10 -> 0
H11: =MAX(F11,G11) -> 0 | I11: =IF(E11>H11,E11-H11,0) -> 0 | K11: =I11-J11 -> 0
H12: =MAX(F12,G12) -> 0 | I12: =IF(E12>H12,E12-H12,0) -> 0 | K12: =I12-J12 -> 0
H13: =MAX(F13,G13) -> 0 | I13: =IF(E13>H13,E13-H13,0) -> 0 | K13: =I13-J13 -> 0
H14: =MAX(F14,G14) -> 0 | I14: =IF(E14>H14,E14-H14,0) -> 0 | K14: =I14-J14 -> 0
H15: =MAX(F15,G15) -> 0 | I15: =IF(E15>H15,E15-H15,0) -> 0 | K15: =I15-J15 -> 0
H16: =MAX(F16,G16) -> 0 | I16: =IF(E16>H16,E16-H16,0) -> 0 | K16: =I16-J16 -> 0
H17: =MAX(F17,G17) -> 0 | I17: =IF(E17>H17,E17-H17,0) -> 0 | K17: =I17-J17 -> 0
H18: =MAX(F18,G18) -> 0 | I18: =IF(E18>H18,E18-H18,0) -> 0 | K18: =I18-J18 -> 0
H19: =MAX(F19,G19) -> 0 | I19: =IF(E19>H19,E19-H19,0) -> 0 | K19: =I19-J19 -> 0
H20: =MAX(F20,G20) -> 0 | I20: =IF(E20>H20,E20-H20,0) -> 0 | K20: =I20-J20 -> 0
H21: =MAX(F21,G21) -> 0 | I21: =IF(E21>H21,E21-H21,0) -> 0 | K21: =I21-J21 -> 0
A22: 合计 | E22: =SUM(E10:E21) -> 0 | F22: =SUM(F10:F21) -> 0 | G22: =SUM(G10:G21) -> 0 | H22: =SUM(H10:H21) -> 0 | I22: =SUM(I10:I21) -> 0 | J22: =SUM(J10:J21) -> 0 | K22: =SUM(K10:K21) -> 0
A23: 其中：
A24: =底稿目录!A9 -> 房屋及建筑物 | E24: =SUMPRODUCT(($A$10:$A$21=$A24)*(E$10:E$21)) -> 0 | F24: =SUMPRODUCT(($A$10:$A$21=$A24)*(F$10:F$21)) -> 0 | G24: =SUMPRODUCT(($A$10:$A$21=$A24)*(G$10:G$21)) -> 0 | H24: =SUMPRODUCT(($A$10:$A$21=$A24)*(H$10:H$21)) -> 0 | I24: =SUMPRODUCT(($A$10:$A$21=$A24)*(I$10:I$21)) -> 0 | J24: =SUMPRODUCT(($A$10:$A$21=$A24)*(J$10:J$21)) -> 0 | K24: =SUMPRODUCT(($A$10:$A$21=$A24)*(K$10:K$21)) -> 0
A25: =底稿目录!A10 -> 机器设备 | E25: =SUMPRODUCT(($A$10:$A$21=$A25)*(E$10:E$21)) -> 0 | F25: =SUMPRODUCT(($A$10:$A$21=$A25)*(F$10:F$21)) -> 0 | G25: =SUMPRODUCT(($A$10:$A$21=$A25)*(G$10:G$21)) -> 0 | H25: =SUMPRODUCT(($A$10:$A$21=$A25)*(H$10:H$21)) -> 0 | I25: =SUMPRODUCT(($A$10:$A$21=$A25)*(I$10:I$21)) -> 0 | J25: =SUMPRODUCT(($A$10:$A$21=$A25)*(J$10:J$21)) -> 0 | K25: =SUMPRODUCT(($A$10:$A$21=$A25)*(K$10:K$21)) -> 0
A26: =底稿目录!A11 -> 运输设备 | E26: =SUMPRODUCT(($A$10:$A$21=$A26)*(E$10:E$21)) -> 0 | F26: =SUMPRODUCT(($A$10:$A$21=$A26)*(F$10:F$21)) -> 0 | G26: =SUMPRODUCT(($A$10:$A$21=$A26)*(G$10:G$21)) -> 0 | H26: =SUMPRODUCT(($A$10:$A$21=$A26)*(H$10:H$21)) -> 0 | I26: =SUMPRODUCT(($A$10:$A$21=$A26)*(I$10:I$21)) -> 0 | J26: =SUMPRODUCT(($A$10:$A$21=$A26)*(J$10:J$21)) -> 0 | K26: =SUMPRODUCT(($A$10:$A$21=$A26)*(K$10:K$21)) -> 0
A27: =底稿目录!A12 -> 办公设备 | E27: =SUMPRODUCT(($A$10:$A$21=$A27)*(E$10:E$21)) -> 0 | F27: =SUMPRODUCT(($A$10:$A$21=$A27)*(F$10:F$21)) -> 0 | G27: =SUMPRODUCT(($A$10:$A$21=$A27)*(G$10:G$21)) -> 0 | H27: =SUMPRODUCT(($A$10:$A$21=$A27)*(H$10:H$21)) -> 0 | I27: =SUMPRODUCT(($A$10:$A$21=$A27)*(I$10:I$21)) -> 0 | J27: =SUMPRODUCT(($A$10:$A$21=$A27)*(J$10:J$21)) -> 0 | K27: =SUMPRODUCT(($A$10:$A$21=$A27)*(K$10:K$21)) -> 0
A28: =底稿目录!A13 -> 其他设备 | E28: =SUMPRODUCT(($A$10:$A$21=$A28)*(E$10:E$21)) -> 0 | F28: =SUMPRODUCT(($A$10:$A$21=$A28)*(F$10:F$21)) -> 0 | G28: =SUMPRODUCT(($A$10:$A$21=$A28)*(G$10:G$21)) -> 0 | H28: =SUMPRODUCT(($A$10:$A$21=$A28)*(H$10:H$21)) -> 0 | I28: =SUMPRODUCT(($A$10:$A$21=$A28)*(I$10:I$21)) -> 0 | J28: =SUMPRODUCT(($A$10:$A$21=$A28)*(J$10:J$21)) -> 0 | K28: =SUMPRODUCT(($A$10:$A$21=$A28)*(K$10:K$21)) -> 0
A29: 三、审计说明：
A32: 四、审计结论：
A36: 提示
A37: 2.检查固定资产减值准备计提和转销的批准程序，取得书面报告等证明文件；检查被审计单位计提固定资产减值准备的依据是否充分，会计处理是否正确；
A38: 3.检查固定资产转让时，相应的减值准备是否一并结转，会计处理是否正确；
A39: 4.重新测试被审计单位计提的减值准备是否合理；比较我们预期所估计减值准备和已记录的金额，调查所有重大差异；
A40: 5.上期确认的固定资产减值准备在本期的变动是否适当。

Sheet 可收回金额测试表H1-15
A1: 致同会计师事务所
A2: 固定资产减值准备测试表-可收回金额
A3: =底稿目录!A2 -> 被审计单位： | E3: =底稿目录!A4 -> 编制人： | I3: =底稿目录!A5 -> 编制日期： | N3: 索引号： | O3: H1-15
A4: =底稿目录!A3 -> 截止日：202X年12月31日 | E4: =底稿目录!A6 -> 复核人： | I4: =底稿目录!A7 -> 复核日期： | N4: 页 次：
A5: 一、审计目标：固定资产以恰当的金额包括在财务报表中，与之相关的计价或分摊调整已恰当记录，相关披露已得到恰当计量和描述。
A6: 二、审计过程：
A7: （一）资产的公允价值减去处置费用后的净额
A8: 项目名称 | B8: 公允价值 | H8: 处置费用（资产处置的直接归属费用） | N8: 公允价值-处置费用 | O8: 备注
B9: 销售协议价格 | C9: 说明 | D9: 资产活跃市场价格 | E9: 说明 | F9: 估计价格 | G9: 说明 | H9: 法律费用 | I9: 相关税费 | J9: 搬运费 | K9: 直接费用 | L9: 其他费用 | M9: 处置费用合计
M10: =SUM(H10:L10) -> 0 | N10: =IF(B10>0,B10,IF(D10>0,D10,F10))-M10 -> 0
M11: =SUM(H11:L11) -> 0 | N11: =IF(B11>0,B11,IF(D11>0,D11,F11))-M11 -> 0
M12: =SUM(H12:L12) -> 0 | N12: =IF(B12>0,B12,IF(D12>0,D12,F12))-M12 -> 0
A13: 合 计 | B13: =SUM(B10:B12) -> 0 | D13: =SUM(D10:D12) -> 0 | F13: =SUM(F10:F12) -> 0 | H13: =SUM(H10:H12) -> 0 | I13: =SUM(I10:I12) -> 0 | J13: =SUM(J10:J12) -> 0 | K13: =SUM(K10:K12) -> 0 | L13: =SUM(L10:L12) -> 0 | M13: =SUM(M10:M12) -> 0 | N13: =SUM(N10:N12) -> 0
A14: 审计说明：
A16: （二）资产预计未来现金流量的现值
A17: 预计未来现金流量 | B17: 预算或者预测期 | G17: 以后年度 | I17: 行业的长期平均增长率 | J17: 市场长期平均增长率 | K17: 所在国家或地区的长期平均增长率 | L17: 增长率确定依据 | N17: 预计未来现金流量的现值 | O17: 备注
B18: 第一年 | C18: 第二年 | D18: 第三年 | E18: 第四年 | F18: 第五年 | G18: 基数 | H18: 增长率
A19: 现金净流量（税前） | G19: =F19 -> 0
A20: 折现系数 | B20: =1/(1+$K$24)^1 -> #DIV/0! | C20: =1/(1+$K$24)^2 -> #DIV/0! | D20: =1/(1+$K$24)^3 -> #DIV/0! | E20: =1/(1+$K$24)^4 -> #DIV/0! | F20: =1/(1+$K$24)^5 -> #DIV/0! | G20: =(1+H19)/((J24-H19)*(1+K24)^5) -> #DIV/0! | H20: （企业管理层如能证明递增的增长率是合理的，可以以递增的增长率为基础。）
A21: 现值 | B21: =B19*B20 -> #DIV/0! | C21: =C19*C20 -> #DIV/0! | D21: =D19*D20 -> #DIV/0! | E21: =E19*E20 -> #DIV/0! | F21: =F19*F20 -> #DIV/0! | G21: =G19*G20 -> #DIV/0! | H21: （建立在预算或者预测基础上的预计现金流量最多涵盖5年，更长期间需证明合理性。） | N21: =SUM(B21:G21) -> #DIV/0!
A22: 折现率 | B22: 所得税率 | C22: 债务总额 D | D22: 资本总额 E | E22: 债务成本Kd | F22: 无风险报酬率Rf | G22: β系数 | H22: 市场平均收益率Rm | I22: 资本成本Ke | J22: WACC (税后) | K22: 折现率 (税前) | L22: 税后折税前调整说明 | N22: 可收回金额 | O22: 备注
B23: 适用税率 | L23: 税率调整 | M23: 调整说明
A24: 加权平均资金成本 | I24: =F24+G24*(H24-F24) -> 0 | J24: =((C24*E24*(1-B24)+D24*I24))/(C24+D24) -> #DIV/0! | K24: =J24/(1-(B24+L24)) -> #DIV/0! | N24: =MAX(N13,N21) -> #DIV/0!
A25: 审计说明：
A27: （三）可收回金额
B28: =N24 -> #DIV/0! | C28: 资产的公允价值减去处置费用后的净额与资产预计未来现金流量的现值两者之间较高者
A29: 三、审计说明：
A32: 四、审计结论
A36: 提示
A37: 1、可收回金额应当根据资产的公允价值减去处置费用后的净额与资产预计未来现金流量的现值两者之间较高者确定。
A39: 2、资产的公允价值减去处置费用后的净额，应当根据公平交易中销售协议价格减去可直接归属于该资产处置费用的金额确定。不存在销售协议但存在资产活跃市场的，
A40: 应当按照该资产的市场价格减去处置费用后的金额确定。资产的市场价格通常应当根据资产的买方出价确定。在不存在销售协议和资产活跃市场的情况下，应当
A41: 以可获取的最佳信息为基础，估计资产的公允价值减去处置费用后的净额，该净额可以参考同行业类似资产的最近交易价格或者结果进行估计。企业按照上述规定
A42: 仍然无法可靠估计资产的公允价值减去处置费用后的净额的，应当以该资产预计未来现金流量的现值作为其可收回金额。
A43: 3、处置费用包括与资产处置有关的法律费用、相关税费、搬运费以及为使资产达到可销售状态所发生的直接费用等。
A45: 4、资产预计未来现金流量的现值，应当按照资产在持续使用过程中和最终处置时所产生的预计未来现金流量，选择恰当的折现率对其进行折现后的金额加以确定。
A50: 5、预计资产的未来现金流量，应当以经企业管理层批准的最近财务预算或者预测数据，以及该预算或者预测期之后年份稳定的或者递减的增长率为基础。
A51: 预计的资产未来现金流量应当包括下列各项：
... A88: 资产组，是指企业可以认定的最小资产组合，其产生的现金流入应当基本上独立于其他资产或者资产组产生的现金流入。

Sheet 房屋建筑物权属检查表H1-16
A1: 致同会计师事务所
A2: 房屋建筑物权属检查表
A3: =底稿目录!A2 -> 被审计单位： | J3: =底稿目录!A4 -> 编制人： | O3: =底稿目录!A5 -> 编制日期： | U3: 索引号： | V3: H1-16
A4: =底稿目录!A3 -> 截止日：202X年12月31日 | J4: =底稿目录!A6 -> 复核人： | O4: =底稿目录!A7 -> 复核日期： | U4: 页 次：
A5: 一、审计目标：记录的固定资产由被审计单位拥有或控制。
A6: 二、审计过程：
A7: 资产编号 | B7: 资产名称 | C7: 财务账面记载 | G7: 权证记载 | S7: 抵押情况
C8: 原值 | D8: 累计折旧 | E8: 减值准备 | F8: 净值 | G8: 权证编号 | H8: 房屋所有权人/权利人 | I8: 共有情况 | J8: 房屋坐落/坐落 | K8: 登记时间 | L8: 房屋性质/权利类型 | M8: 规划用途 | N8: 建筑面积 | O8: 使用年限/使用期限 | P8: 填发单位 | Q8: 他项权利 | R8: 权证复印件索引 | S8: 是否抵押受限 | T8: 抵押面积 | U8: 抵押价值 | V8: 抵押性质
F9: =C9-D9-E9 -> 0
F10: =C10-D10-E10 -> 0
F11: =C11-D11-E11 -> 0
F12: =C12-D12-E12 -> 0
F13: =C13-D13-E13 -> 0
F14: =C14-D14-E14 -> 0
F15: =C15-D15-E15 -> 0
F16: =C16-D16-E16 -> 0
A17: 合计 | C17: =SUM(C9:C16) -> 0 | D17: =SUM(D9:D16) -> 0 | E17: =SUM(E9:E16) -> 0 | F17: =SUM(F9:F16) -> 0
A18: 三、审计说明：
A19: 1.权证是否齐全；是否归属公司所有
A20: 2.房屋抵押情况描述
A24: 四、审计结论：
A30: （提示：每次审计需要重新取得原件，进行原件和复印件的核对并记录）检查资产的权属证明，验证其属于被审计单位所有。

Sheet 运输设备权属检查表H1-17
A1: 致同会计师事务所
A2: 运输设备权属检查表
A3: =底稿目录!A2 -> 被审计单位： | G3: =底稿目录!A4 -> 编制人： | M3: =底稿目录!A5 -> 编制日期： | Q3: 索引号： | R3: H1-17
A4: =底稿目录!A3 -> 截止日：202X年12月31日 | G4: =底稿目录!A6 -> 复核人： | M4: =底稿目录!A7 -> 复核日期： | Q4: 页 次：
A5: 一、审计目标：记录的固定资产由被审计单位拥有或控制；
A6: 一、审计过程： | D6: （提示：每次审计需要重新取得原件，进行原件和复印件的核对并记录）检查资产的权属证明，验证其属于被审计单位所有。
A7: 资产编号 | B7: 资产名称 | C7: 财务账面记载 | G7: 机动车登记证书 | N7: 抵押情况 | Q7: 机动车行驶证
C8: 原值 | D8: 累计折旧 | E8: 减值准备 | F8: 净值 | G8: 机动车所有人 | H8: 机动车登记编号 | I8: 车辆品牌 | J8: 发动机号 | K8: 发证日期 | L8: 登记栏 | M8: 机动车登记证书索引 | N8: 是否抵押受限 | O8: 抵押价值 | P8: 抵押性质 | Q8: 年检截止日 （最后） | R8: 行驶证复印件索引
F9: =C9-D9-E9 -> 0
F10: =C10-D10-E10 -> 0
F11: =C11-D11-E11 -> 0
F12: =C12-D12-E12 -> 0
F13: =C13-D13-E13 -> 0
F14: =C14-D14-E14 -> 0
F15: =C15-D15-E15 -> 0
F16: =C16-D16-E16 -> 0
A17: 合计 | C17: =SUM(C9:C16) -> 0 | D17: =SUM(D9:D16) -> 0 | E17: =SUM(E9:E16) -> 0 | F17: =C17-D17-E17 -> 0
A18: 三、审计说明：
A19: 1 | B19: 权证是否齐全；是否归属公司所有
A21: 2 | B21: 抵押情况描述
A23: 四、审计结论：
A26: 提示：
A27: 机动车行驶证：是准予机动车在中华人民共和国境内道路上行驶的法定证件，需随车携带
A28: 机动车登记证书：是车辆的法定所有权证明,具有法律上的约束力,能够明确车辆的所有权归属。该证书由车主负责妥善保存,无需随车携带。“登记栏“中查看车辆变更、抵押情况等
A29: 机动车行驶证与机动车登记证书不同，后者为车辆权属的核心证明，但机动车行驶证在多数日常场景中具备法律效力。‌‌

Sheet 关联交易检查表H1-18
A1: 致同会计师事务所
A2: 关联交易检查表
A3: =底稿目录!A2 -> 被审计单位： | F3: =底稿目录!A4 -> 编制人： | J3: =底稿目录!A5 -> 编制日期： | N3: 索引号： | O3: H1-18
A4: =底稿目录!A3 -> 截止日：202X年12月31日 | F4: =底稿目录!A6 -> 复核人： | J4: =底稿目录!A7 -> 复核日期： | N4: 页 次：
A5: 一、审计目标:
A6: 1.资产负债表中记录的固定资产是存在的，且已记录于恰当的账户；2.所有应记录的固定资产均已记录，所有应当包括在财务报表中的相关披露均已包括；3.记录的固定资产由被审计单位拥有或控制。
A7: 4.固定资产以恰当的金额包括在财务报表中，与之相关的计价或分摊调整已恰当记录，相关披露已得到恰当计量和描述；5.固定资产已被恰当地汇总或分解且表述清楚，相关披露在按照企业会计准则的编制基础下是相关的、可理解的。
A8: 二、审计过程：
A9: 1.对于合并范围外关联方的往来，核对合同、发票等有关文件，了解交易事项目的、价格和条件，确认关联方交易是否真实、公允。
A10: （1）向合并范围外关联方采购固定资产
A11: 关联单位名称 | B11: 关联方关系 | C11: 资产类别 | D11: 购买固定资产名称 | E11: 购买价款 | F11: 固定资产入账价值 | G11: 占同类交易金额的比例％ | H11: 购入时间 | I11: 折旧年限 | J11: 定价政策 | K11: 关联交易是否存在异常 | L11: 备注 | M11: 索引号
A19: （2）向合并范围外关联方出售固定资产
A20: 关联单位名称 | B20: 关联方关系 | C20: 资产类别 | D20: 出售固定资产名称 | E20: 出售时固定资产原值 | F20: 出售时累计折旧 | G20: 出售时减值准备 | H20: 出售时净值 | I20: 销售价格 （不含税） | J20: 占同类交易金额的比例％ | K20: 出售时间 | L20: 定价政策 | M20: 关联交易是否存在异常 | N20: 备注 | O20: 索引号
H21: =E21-F21-G21 -> 0
H22: =E22-F22-G22 -> 0
H23: =E23-F23-G23 -> 0
H24: =E24-F24-G24 -> 0
H25: =E25-F25-G25 -> 0
H26: =E26-F26-G26 -> 0
A28: 三、审计说明：
A33: 四、审计结论：
A37: 勿删
A38: 关联关系
A39: 实际控制人
A40: 控股股东
A41: 控股股东、实际控制人的附属企业
A42: 持有5%以上股份的法人或其他组织
A43: 联营企业
A44: 合营企业
A45: 董高监等关键管理人员
A46: 其他关联方

Sheet 经营租出固定资产检查表H1-19
A1: 致同会计师事务所
A2: 经营租出固定资产检查表
A3: =底稿目录!A2 -> 被审计单位： | G3: =底稿目录!A4 -> 编制人： | N3: =底稿目录!A5 -> 编制日期： | U3: 索引号： | V3: H1-19
A4: =底稿目录!A3 -> 截止日：202X年12月31日 | G4: =底稿目录!A6 -> 复核人： | N4: =底稿目录!A7 -> 复核日期： | U4: 页 次：
A5: 一、审计目标：1.资产负债表中记录的固定资产是存在的，且已记录于恰当的账户；2.记录的固定资产由被审计单位拥有或控制；3.固定资产以恰当的金额包括在财务报表中，与之相关的计价或分摊调整已恰当记录，相关披露已得到恰当计量和描述
A6: 二、审计过程：
A7: 序号 | B7: 固定资产名称 | C7: 资产类别 | D7: 规格型号 | E7: 承租单位名称 | F7: 租赁开始日 | G7: 租赁到期日 | H7: 租赁合同总金额 | I7: 本年应计租金月份数 | J7: 经营租出固定资产应计提的折旧费用核对 | R7: 经营租出固定资产应计提的租金收入核对 | V7: 租赁合同索引号
J8: 固定资产原价 | K8: 固定资产累计折旧 | L8: 折旧年限 | M8: 残值率 | N8: 月折旧额 | O8: 本期应计入其他业务支出的折旧额 | P8: 账面计入其他业务支出的折旧额 | Q8: 差异 | R8: 月租金收入 | S8: 本期应计租金收入 | T8: 账面计入其他业务收入的租金额 | U8: 差异
A9: 1 | N9: =J9*(1-M9)/L9/12 -> #DIV/0! | O9: =I9*N9 -> #DIV/0! | Q9: =O9-P9 -> #DIV/0! | S9: =I9*R9 -> 0 | U9: =S9-T9 -> 0
A10: 2 | O10: =I10*N10 -> 0 | Q10: =O10-P10 -> 0 | S10: =I10*R10 -> 0 | U10: =S10-T10 -> 0
A11: 3 | O11: =I11*N11 -> 0 | Q11: =O11-P11 -> 0 | S11: =I11*R11 -> 0 | U11: =S11-T11 -> 0
A12: 4 | O12: =I12*N12 -> 0 | Q12: =O12-P12 -> 0 | S12: =I12*R12 -> 0 | U12: =S12-T12 -> 0
A13: 5 | O13: =I13*N13 -> 0 | Q13: =O13-P13 -> 0 | S13: =I13*R13 -> 0 | U13: =S13-T13 -> 0
A14: 6 | O14: =I14*N14 -> 0 | Q14: =O14-P14 -> 0 | S14: =I14*R14 -> 0 | U14: =S14-T14 -> 0
A15: 7 | O15: =I15*N15 -> 0 | Q15: =O15-P15 -> 0 | S15: =I15*R15 -> 0 | U15: =S15-T15 -> 0
A16: 8 | O16: =I16*N16 -> 0 | Q16: =O16-P16 -> 0 | S16: =I16*R16 -> 0 | U16: =S16-T16 -> 0
A17: 三、审计说明：
A22: 四、审计结论：

Sheet 融资租出固定资产检查表H1-20
A1: 致同会计师事务所
A2: 融资租出固定资产检查表
A3: =底稿目录!A2 -> 被审计单位： | E3: =底稿目录!A4 -> 编制人： | J3: =底稿目录!A5 -> 编制日期： | K3: 索引号： | L3: H1-20
A4: =底稿目录!A3 -> 截止日：202X年12月31日 | E4: =底稿目录!A6 -> 复核人： | J4: =底稿目录!A7 -> 复核日期： | K4: 页 次：
A5: 一、审计目标：1.资产负债表中记录的固定资产是存在的，且已记录于恰当的账户；2.记录的固定资产由被审计单位拥有或控制；3.固定资产以恰当的金额包括在财务报表中，与之相关的计价或分摊调整已恰当记录，相关披露已得到恰当计量和描述。
A6: 二、审计过程：
A7: 序号 | B7: 融资租出固定资产编号 | C7: 融资租出固定资产名称 | D7: 承租单位名称 | E7: 租赁开始日 | F7: 租赁合同索引号 | G7: 是否满足融资租赁的定义
G8: 在租赁期届满时，租赁资产的所有权转移给承租人； | H8: 租赁期占租赁资产使用寿命的大部分（>=75%）； | I8: 承租人有购买租赁资产的选择权，在租赁开始日可合理确定承租人将行使该权利 | J8: 承租人租赁开始日的最低租赁付款额的现值，几乎相当于租赁开始日租赁资产公允价值（>=90%） | K8: 出租人租赁开始日的最低租赁收款额的现值，几乎相当于租赁开始日租赁资产公允价值（>=90%） | L8: 租赁资产性质特殊，如不作较大改造，只有承租人才能使用
A9: 1
A10: 2
A11: 3
A12: 4
A13: 5
A14: 6
A15: 7
A16: 8
A17: 1.确定租赁内含利率
A18: 项目 | B18: 各期租金之和 | I18: 行使优惠购买选择权支付的金额
B19: 2014年 | C19: 2015年 | D19: 2016年 | E19: 2017年 | F19: 2018年 | G19: 2019年 | H19: …
A20: 最低租赁收款额
A21: 折现率1
A22: 折现值1 | B22: =B20*B21 -> 0 | C22: =C20*C21 -> 0 | D22: =D20*D21 -> 0 | E22: =E20*E21 -> 0 | F22: =F20*F21 -> 0 | G22: =G20*G21 -> 0 | H22: =H20*H21 -> 0 | I22: =I20*I21 -> 0
A23: 最低租赁收款额现值1 | B23: =SUM(B22:I22) -> 0
A24: 折现率2
A25: 折现值2 | B25: =B20*B24 -> 0 | C25: =C20*C24 -> 0 | D25: =D20*D24 -> 0 | E25: =E20*E24 -> 0 | F25: =F20*F24 -> 0 | G25: =G20*G24 -> 0 | H25: =H20*H24 -> 0 | I25: =I20*I24 -> 0
A26: 最低租赁收款额现值2 | B26: =SUM(B25:I25) -> 0
A27: 租赁开始日，租赁资产的公允价值
A28: 初始直接费用
A29: 两者的合计 | B29: =B27+B28 -> 0
A30: 租赁内含利率
A31: 2.确定应收融资租赁款和未实现融资收益
A32: 序号 | B32: 金额
A33: 最低租赁收款额 | B33: =SUM(B20:I20) -> 0
A34: 初始直接费用 | B34: =B28 -> 0
A35: 应收融资租赁款 | B35: =B33+B34 -> 0
A36: 未实现融资收益 | B36: =B35-B29 -> 0
A37: 3.未确认融资收益分配表（如适用）
A38: 日期 | B38: 租金 | C38: 确认的融资收入 | D38: 租赁投资净额减少额 | E38: 租赁投资净额余额
A39: ① | B39: ② | C39: ③=期初⑤X租赁内含利率 | D39: ④=②-③ | E39: 期末⑤=期初⑤-④
A40: 2014年12月31日 | E40: =B27 -> 0
A41: 2015年12月31日 | B41: =C20 -> 0 | C41: =E40*$C$31 -> 0 | D41: =B41-C41 -> 0 | E41: =E40-D41 -> 0
A42: 2016年12月31日 | B42: =D20 -> 0 | C42: =E41*$C$31 -> 0 | D42: =B42-C42 -> 0 | E42: =E41-D42 -> 0
A43: 2017年12月31日 | B43: =E20 -> 0 | C43: =E42*$C$31 -> 0 | D43: =B43-C43 -> 0 | E43: =E42-D43 -> 0
A44: 2018年12月31日 | B44: =F20 -> 0 | C44: =E43*$C$31 -> 0 | D44: =B44-C44 -> 0 | E44: =E43-D44 -> 0
A45: 2019年12月31日 | B45: =G20 -> 0 | C45: =E44*$C$31 -> 0 | D45: =B45-C45 -> 0 | E45: =E44-D45 -> 0
A46: … | C46: =B46-D46 -> 0 | D46: =E45 -> 0 | E46: =E45-D46 -> 0
A47: 合计 | B47: =SUM(B41:B46) -> 0
A48: 三、审计说明：
A49: 1 | B49: 融资租出固定资产的条件是否满足
A50: 2 | B50: 长期应收款、融资租赁资产、未确认融资收益的入账价值是否正确
A51: 3 | B51: 所采用的租赁内含利率是否正确
A52: 4 | B52: 未确认融资收益的分配是否恰当
A53: 四、审计结论：
