Workbook

Sheet 底稿目录
A1: 底稿开列时，可先在以下单元格填写有关内容，以便其他底稿引用有关数据：
A2: 被审计单位：
A3: 截止日：202X年12月31日 | D3: 序号 | E3: 内容 | F3: 索引号 | G3: 备注
A4: 编制人： | E4: 固定资产清理实质性程序表 | F4: H6A
A5: 复核人： | D5: 1 | E5: 审定表 | F5: H6-1
A6: 编制日期： | D6: =D5+1 -> 2 | E6: 附注披露信息（上市公司） | G6: 无需打印
A7: 复核日期： | D7: =D6+1 -> 3 | E7: 附注披露信息（国有企业） | G7: 无需打印
D8: =D7+1 -> 4 | E8: 明细表 | F8: H6-2
A9: 关于工作底稿与审计程序索引号对应的说明 | D9: =D8+1 -> 5 | E9: 调整分录汇总 | F9: H6-3
A10: 1.编制的审计工作底稿应与审计程序对应。审计项目组应根据被审计单位实际情况和风险评估情况在实质性程序表中裁剪、修改或增加审计程序，根据实际执行的审计程序完成相应审计工作底稿，编制的工作底稿中应按自然顺序依次编制索引号，并通过唯一的索引号将与实质性程序表中的程序对应关联（即将工作底稿的索引号填入实质性程序表中的底稿索引号列）。 | D10: =D9+1 -> 6 | E10: 检查表 | F10: H6-4
A14: 2.获取的支持性证据应与审计底稿或程序对应。审计项目组在完成底稿时获取的支持性证据应根据底稿索引号编制下一级按自然顺序排序的索引号（如D1-2-1、D1-2-2、……），并在底稿中说明引用的支持性证据、关联索引号。
A17: 3.工作底稿索引号的编码规则：实质性程序索引号按循环从“D”到“N”,循环内账户以顺序号排列，模板中底稿索引号按账户顺序+自然数顺序（即模板中索引号按二级自然顺序排列，如D1-1、D1-2、D1-3、……D1-N）。

Sheet 固定资产清理实质性程序表H6A
A1: 致同会计师事务所
A2: 固定资产清理实质性程序表
A3: =底稿目录!A2 -> 被审计单位： | C3: =底稿目录!A4 -> 编制人： | E3: =底稿目录!A6 -> 编制日期： | H3: 索引号： | I3: H6A
A4: =底稿目录!A3 -> 截止日：202X年12月31日 | C4: =底稿目录!A5 -> 复核人： | E4: =底稿目录!A7 -> 复核日期： | H4: 页 次：
A5: 一、本账户涉及的科目
A6: 固定资产清理
A7: 二、审计目标与认定的对应关系
A8: 审计目标 | G8: 财务报表的认定
A9: A. 资产负债表中记录的固定资产清理是存在的，且已记录于恰当的账户 | G9: 存在
A10: B. 所有应记录的固定资产清理均已记录，所有应当包括在财务报表中的相关披露均已包括 | G10: 完整性
A11: C. 记录的固定资产清理由被审计单位拥有或控制； | G11: 权利和义务
A12: D. 固定资产清理以恰当的金额包括在财务报表中，与之相关的计价或分摊调整已恰当记录，相关披露已得到恰当计量和描述 | G12: 准确性、计价和分摊
A13: E. 固定资产清理已被恰当地汇总或分解且表述清楚，相关披露在按照企业会计准则的编制基础下是相关的、可理解的 | G13: 列报
A14: 三、计划实施的实质性程序
A15: 序号 | B15: 审计程序 | C15: 程序分类 | D15: 财务报表的认定 | I15: 底稿索引号
D16: 存在 | E16: 完整性 | F16: 权利和 义务 | G16: 准确性、计价和分摊 | H16: 列报 | J16: 根据被审计单位实际情况和风险评估情况裁剪、修改或增加审计程序
A17: 1 | B17: 获取或编制固定资产清理的明细表，完成以下工作，并编制审定表： （1）复核加计是否正确，并与总账数和明细账合计数核对是否相符，期初余额与上期审定期末余额是否相符； （2）分析固定资产清理与上期变动情况； （3）关注固定资产清理是否长期挂账。 | C17: 常规★ | D17: √ | E17: √ | G17: √ | I17: H6-1 /H6-2
A18: 2 | B18: 在使用手工编制、自定义信息报告、系统生成的非固定格式报告等由被审计单位生成的信息时，测试有关信息准确性和完整性，并考虑针对编制和维护由被审计单位生成的信息的相关控制实施控制测试，以评价该信息是否能够为实现审计目的提供基础。 | C18: 常规★ | E18: √ | G18: √ | I18: T1 / | J18: 可参见《审计手册》4.2.6，由被审计单位生成的信息可能是由系统生成的、或手工编制的、或二者兼而有之的方式生成的。例如，由被审计单位生成的信息可能包括： • 不涉及自定义的、由系统生成的报告（如，固定格式报告）； • 可能通过人工自定义的、由系统生成的报告，例如，（计算机）查询信息或特别定制的报告； • 手工编制的信息，例如，汇总信息的电子表格或用以支持分配、计算以及调节的电子表格； • 其他系统生成或手工编制的信息，例如，由被审计单位编制的客户发票； • 通过影印、拍摄、扫描或其他方式转换成电子形式的文件记录。
A19: 3 | B19: 对期初余额的审计，取得上期固定资产清理明细表复核加计是否正确，与总账、明细账合计数是否相符；检查期初固定资产清理在本期处置情况；对单项金额重大资产检查支持性文件，其他必要追加的审计程序。（适用于首次承接） | C19: 备选 | D19: √ | E19: √ | F19: √ | G19: √ | J19: 由被审计单位生成的信息不包括： • 总分类账或明细分类账、试算平衡表、或经审计的财务报表； • 第三方（除了服务机构）的报表或报告，例如，原始银行对账单，或函证的回函； • 外部数据（例如，第三方发布的数据，如，定价来源）。
A20: 4 | B20: 检查本期固定资产清理： （1）检查固定资产清理发生的原因（出售、报废、毁损、对外投资、非货币性资产交换、债务重组等），是否经有关授权批准； （2）结合固定资产等科目的审计，检查原值、累计折旧和减值准备等账面转入额是否正确，清理收人和清理费用的发生是否真实，清理净损益的计算是否正确，会计处理是否正确。 | C20: 常规★ | D20: √ | E20: √ | F20: √ | G20: √ | I20: H6-4
A21: 5 | B21: 检查关联交易情况，检查关联交易的真实性、合理性及合规性；检查关联交易会计处理是否正确，考虑是否存在未识别的关联方，检查关联交易和余额披露是否正确。 | C21: 常规★ | D21: √ | E21: √ | F21: √ | G21: √ | H21: √
A22: 6 | B22: 根据评估的舞弊风险等因素增加的审计程序。 | C22: IPO/上市/新三板/重组/舞弊应对 | D22: √ | E22: √ | F22: √ | G22: √
A23: 7 | B23: 检查固定资产清理是否已按企业会计准则或其他适用的规定在财务报表中做出恰当列报和披露 | C23: 常规★ | H23: √ | I23: A 1-1/A1-15 /A1-16

Sheet 审定表H6-1
A1: 致同会计师事务所
A2: 固定资产清理审定表
A3: =底稿目录!A2 -> 被审计单位： | D3: =底稿目录!A4 -> 编制人： | F3: =底稿目录!A6 -> 编制日期： | H3: 索引号： | I3: H6-1
A4: =底稿目录!A3 -> 截止日：202X年12月31日 | D4: =底稿目录!A5 -> 复核人： | F4: =底稿目录!A7 -> 复核日期： | H4: 页 次：
A5: 项目 | B5: 期初数 | E5: 期末数 | H5: 本期审定数与上期 审定数的比较
B6: 未审数 | C6: 账项调整 | D6: 审定数 | E6: 未审数 | F6: 账项调整 | G6: 审定数 | H6: 变动额 | I6: 变动率
A7: ='明细表H6-2'!A11 -> 0 | B7: ='明细表H6-2'!B11 -> 0 | C7: ='明细表H6-2'!F11 -> 0 | D7: =B7+C7 -> 0 | E7: ='明细表H6-2'!E11 -> 0 | F7: ='明细表H6-2'!F11+'明细表H6-2'!G11-'明细表H6-2'!H11 -> 0 | G7: =E7+F7 -> 0 | H7: =G7-D7 -> 0 | I7: =IF(AND(D7=0,H7=0),0,IF(AND(D7=0,H7>0),1,H7/D7)) -> 0
A8: ='明细表H6-2'!A12 -> 0 | B8: ='明细表H6-2'!B12 -> 0 | C8: ='明细表H6-2'!F12 -> 0 | D8: =B8+C8 -> 0 | E8: ='明细表H6-2'!E12 -> 0 | F8: ='明细表H6-2'!F12+'明细表H6-2'!G12-'明细表H6-2'!H12 -> 0 | G8: =E8+F8 -> 0 | H8: =G8-D8 -> 0 | I8: =IF(AND(D8=0,H8=0),0,IF(AND(D8=0,H8>0),1,H8/D8)) -> 0
A9: ='明细表H6-2'!A13 -> 0 | B9: ='明细表H6-2'!B13 -> 0 | C9: ='明细表H6-2'!F13 -> 0 | D9: =B9+C9 -> 0 | E9: ='明细表H6-2'!E13 -> 0 | F9: ='明细表H6-2'!F13+'明细表H6-2'!G13-'明细表H6-2'!H13 -> 0 | G9: =E9+F9 -> 0 | H9: =G9-D9 -> 0 | I9: =IF(AND(D9=0,H9=0),0,IF(AND(D9=0,H9>0),1,H9/D9)) -> 0
A10: ='明细表H6-2'!A14 -> 0 | B10: ='明细表H6-2'!B14 -> 0 | C10: ='明细表H6-2'!F14 -> 0 | D10: =B10+C10 -> 0 | E10: ='明细表H6-2'!E14 -> 0 | F10: ='明细表H6-2'!F14+'明细表H6-2'!G14-'明细表H6-2'!H14 -> 0 | G10: =E10+F10 -> 0 | H10: =G10-D10 -> 0 | I10: =IF(AND(D10=0,H10=0),0,IF(AND(D10=0,H10>0),1,H10/D10)) -> 0
A11: ='明细表H6-2'!A15 -> 0 | B11: ='明细表H6-2'!B15 -> 0 | C11: ='明细表H6-2'!F15 -> 0 | D11: =B11+C11 -> 0 | E11: ='明细表H6-2'!E15 -> 0 | F11: ='明细表H6-2'!F15+'明细表H6-2'!G15-'明细表H6-2'!H15 -> 0 | G11: =E11+F11 -> 0 | H11: =G11-D11 -> 0 | I11: =IF(AND(D11=0,H11=0),0,IF(AND(D11=0,H11>0),1,H11/D11)) -> 0
A12: 合计 | B12: =SUM(B7:B11) -> 0 | C12: =SUM(C7:C11) -> 0 | D12: =SUM(D7:D11) -> 0 | E12: =SUM(E7:E11) -> 0 | F12: =SUM(F7:F11) -> 0 | G12: =SUM(G7:G11) -> 0 | H12: =G12-D12 -> 0 | I12: =IF(AND(D12=0,H12=0),0,IF(AND(D12=0,H12>0),1,H12/D12)) -> 0
A13: 1、审计说明
A14: （1）固定资产清理期末余额较期初余额增加（负数为减少）：
A15: 主要原因（比例超过30%的）：
A17: （2）情况说明：
A19: （3）与经审计的财务报表核对
B20: 期末数 | C20: 期初数
A21: 固定资产净值审定数
A22: 固定资产清理审定数 | B22: =G12 -> 0 | C22: =D12 -> 0
A23: 固定资产与固定资产清理合计数 | B23: =B21+B22 -> 0 | C23: =C21+C22 -> 0
A24: 报表数
A25: 差异 | B25: =B23-B24 -> 0 | C25: =C23-C24 -> 0
A27: 2、审计结论

Sheet 附注披露信息（上市公司）
A1: 致同会计师事务所
A2: 附注披露表（上市公司）
A3: =底稿目录!A2 -> 被审计单位： | B3: =底稿目录!A4 -> 编制人： | C3: =底稿目录!A6 -> 编制日期： | D3: 索引号：
A4: =底稿目录!A3 -> 截止日：202X年12月31日 | B4: =底稿目录!A5 -> 复核人： | C4: =底稿目录!A7 -> 复核日期： | D4: 页 次： | E4: 返回目录
A5: 【固定资产与固定资产清理的合计数披露详见H1-1】
A6: 22、固定资产
A7: 项 目 | B7: 期末余额 | C7: 上年年末余额
A8: 固定资产
A9: 固定资产清理
A10: 合 计 | B10: X.XX | C10: X.XX
A12: （2）固定资产清理
A13: 项 目 | B13: 期末余额 | C13: 上年年末余额 | D13: 转入清理的原因
A17: 合 计 | B17: X.XX | C17: X.XX
A18: （说明转入固定资产清理起始时间已超过1年的固定资产清理进展情况）

Sheet 附注披露信息（国有企业）
A1: 致同会计师事务所
A2: 附注披露表（国有企业）
A3: =底稿目录!A2 -> 被审计单位： | B3: =底稿目录!A4 -> 编制人： | C3: =底稿目录!A6 -> 编制日期： | D3: 索引号：
A4: =底稿目录!A3 -> 截止日：202X年12月31日 | B4: =底稿目录!A5 -> 复核人： | C4: =底稿目录!A7 -> 复核日期： | D4: 页 次： | E4: 返回目录
A5: 【固定资产与固定资产清理的合计数披露详见H1-1】
A6: 22、固定资产
A7: 项 目 | B7: 期末账面价值 | C7: 期初账面价值
A8: 固定资产
A9: 固定资产清理
A10: 合 计 | B10: X.XX | C10: X.XX
A12: （2）固定资产清理
A13: 项 目 | B13: 期末账面价值 | C13: 期初账面价值 | D13: 转入清理的原因
A17: 合 计 | D17: --
A18: 注：说明转入固定资产清理起始时间已超过1年的固定资产清理进展情况。

Sheet 明细表H6-2
A1: 致同会计师事务所
A2: 固定资产清理明细表
A3: =底稿目录!A2 -> 被审计单位： | E3: =底稿目录!A4 -> 编制人： | I3: =底稿目录!A6 -> 编制日期： | O3: 索引号： | P3: H6-2
A4: =底稿目录!A3 -> 截止日：202X年12月31日 | E4: =底稿目录!A5 -> 复核人： | I4: =底稿目录!A7 -> 复核日期： | O4: 页 次：
A5: 一、审计目标：
A6: 1. 资产负债表中记录的固定资产清理是存在的，且已记录于恰当的账户；2. 所有应记录的固定资产清理均已记录，所有应当包括在财务报表中的相关披露均已包括；
A7: 3. 固定资产清理以恰当的金额包括在财务报表中，与之相关的计价或分摊调整已恰当记录，相关披露已得到恰当计量和描述。
A8: 二、审计过程：
A9: 项目 | B9: 未审数 | F9: 期初调整 | G9: 账项调整 | I9: 审定数 | M9: 转入清理的原因 | N9: 转入清理的时间 | O9: 转入固定资产清理起始时间已超过1年的固定资产清理进展情况 | P9: 备注
B10: 期初数 | C10: 本期增加 | D10: 本期减少 | E10: 期末数 | G10: 本期增加 | H10: 本期减少 | I10: 期初数 | J10: 本期增加 | K10: 本期减少 | L10: 期末数
E11: =SUM(B11:C11)-D11 -> 0 | I11: =B11+F11 -> 0 | J11: =C11+G11 -> 0 | K11: =D11+H11 -> 0 | L11: =I11+J11-K11 -> 0
E12: =SUM(B12:C12)-D12 -> 0 | I12: =B12+F12 -> 0 | J12: =C12+G12 -> 0 | K12: =D12+H12 -> 0 | L12: =I12+J12-K12 -> 0
E13: =SUM(B13:C13)-D13 -> 0 | I13: =B13+F13 -> 0 | J13: =C13+G13 -> 0 | K13: =D13+H13 -> 0 | L13: =I13+J13-K13 -> 0
E14: =SUM(B14:C14)-D14 -> 0 | I14: =B14+F14 -> 0 | J14: =C14+G14 -> 0 | K14: =D14+H14 -> 0 | L14: =I14+J14-K14 -> 0
E15: =SUM(B15:C15)-D15 -> 0 | I15: =B15+F15 -> 0 | J15: =C15+G15 -> 0 | K15: =D15+H15 -> 0 | L15: =I15+J15-K15 -> 0
A16: 合计 | B16: =SUM(B11:B15) -> 0 | C16: =SUM(C11:C15) -> 0 | D16: =SUM(D11:D15) -> 0 | E16: =SUM(E11:E15) -> 0 | F16: =SUM(F11:F15) -> 0 | G16: =SUM(G11:G15) -> 0 | H16: =SUM(H11:H15) -> 0 | I16: =SUM(I11:I15) -> 0 | ... L16: =SUM(L11:L15) -> 0
A17: 三、审计说明：
A21: 四、审计结论：
A27: 提示：
A28: 1、本科目核算企业因出售、报废、毁损、对外投资、非货币性资产交换、债务重组等原因转出的固定资产价值以及在清理过程中发生的费用等。
A29: 2、固定资产清理完成后，属于生产经营期间正常的处理损失，借记“营业外支出——处置非流动资产损失”科目，贷记本科目；
A30: 属于自然灾害等非正常原因造成的损失，借记“营业外支出——非常损失”科目，贷记本科目。如为贷方余额，借记本科目，贷记“营业外收入”科目。
A31: 3.审计说明可以概述:(1)程序的测试情况、结果;(2)拟调整事项及其调整分录、未调整事项及其影响，审计范围受到限制情况及其影响。
A32: 4.审计结论可参考：A、未见异常。 B、除上述重大不符事项应当作为调整事项予以调整外，其余未见异常。 C、由于存在以下重大未调整事项(或审计范围受到限制无法获取充分、适当证据)，不可确认。

Sheet 调整分录汇总H6-3
A1: 致同会计师事务所
A2: 固定资产清理调整分录汇总表
A3: =底稿目录!A2 -> 被审计单位： | D3: =底稿目录!A4 -> 编制人： | G3: =底稿目录!A6 -> 编制日期： | I3: 索引号： | J3: H6-3
A4: =底稿目录!A3 -> 截止日：202X年12月31日 | D4: =底稿目录!A5 -> 复核人： | G4: =底稿目录!A7 -> 复核日期： | I4: 页 次：
A5: 调整事项说明 | B5: 类别（报表调整/账项调整/其他） | C5: 报表项目 | D5: 科目名称 | E5: 附注项目 | F5: …… | G5: 借方调整金额 | H5: 贷方调整金额 | I5: 索引 | J5: 备注
A21: 提示：本底稿适用于调整分录较多、较复杂的项目，且仅列示与本报表项目相关的审计调整。项目组可根据项目实际情况选择是否使用该底稿。

Sheet 检查表H6-4
A1: 致同会计师事务所
A2: 固定资产清理检查表
A3: =底稿目录!A2 -> 被审计单位： | F3: =底稿目录!A4 -> 编制人： | L3: =底稿目录!A6 -> 编制日期： | P3: 索引号： | Q3: H6-4
A4: =底稿目录!A3 -> 截止日：202X年12月31日 | F4: =底稿目录!A5 -> 复核人： | L4: =底稿目录!A7 -> 复核日期： | P4: 页 次：
A5: 一、审计目标：
A6: 1. 资产负债表中记录的固定资产清理是存在的，且已记录于恰当的账户；2. 所有应记录的固定资产清理均已记录，所有应当包括在财务报表中的相关披露均已包括；
A7: 3. 记录的固定资产清理由被审计单位拥有或控制；4. 固定资产清理以恰当的金额包括在财务报表中，与之相关的计价或分摊调整已恰当记录，相关披露已得到恰当计量和描述。
A8: 二、测试过程： | C8: 测试原因：大额（）关联方（）大额交易频繁（）异常（）其他（）
A9: 测试内容说明：1.原始凭证是否齐全； 2.记账凭证与原始凭证是否相符；3.账务处理是否正确；4.是否记录于恰当的会计期间；5.……
A10: 日期 | B10: 凭证编号 | C10: 固定资产类别 | D10: 固定资产名称 | E10: 被清理固定资产情况 | I10: 清理费用 | J10: 清理收入 | K10: 清理净损益 | L10: 转营业外收入（支出） | M10: 转资产处置收益 | N10: 期末余额 | O10: 清理原因 | P10: 批准人 | Q10: 相关文件和附件索引
E11: 原值 | F11: 累计折旧 | G11: 减值准备 | H11: 净值
H12: =E12-F12-G12 -> 0 | K12: =J12-I12-H12 -> 0
H13: =E13-F13-G13 -> 0 | K13: =J13-I13-H13 -> 0
H14: =E14-F14-G14 -> 0
H15: =E15-F15-G15 -> 0
H16: =E16-F16-G16 -> 0
H17: =E17-F17-G17 -> 0
H18: =E18-F18-G18 -> 0
H19: =E19-F19-G19 -> 0
H20: =E20-F20-G20 -> 0 | K20: =J20-I20-H20 -> 0
H21: =E21-F21-G21 -> 0 | K21: =J21-I21-H21 -> 0
H22: =E22-F22-G22 -> 0 | K22: =J22-I22-H22 -> 0
A23: 合计 | E23: =SUM(E12:E22) -> 0 | F23: =SUM(F12:F22) -> 0 | G23: =SUM(G12:G22) -> 0 | H23: =SUM(H12:H22) -> 0 | I23: =SUM(I12:I22) -> 0 | J23: =SUM(J12:J22) -> 0 | K23: =SUM(K12:K22) -> 0 | L23: =SUM(L12:L22) -> 0 | M23: =SUM(M12:M22) -> 0
A24: 本期固定资产清理减少合计 | H24: ='明细表H6-2'!K16 -> 0
A25: 检查比例 | H25: =H23/H24 -> #DIV/0!
A26: 三、审计说明：
A27: 1.如果检查比例较低应扩大检查样本量或说明原因
A28: 2.……
A29: 四、审计结论：
