Workbook

Sheet 底稿目录
A1: 底稿开列时，可先在以下单元格填写有关内容，以便其他底稿引用有关数据：
A2: 被审计单位：
A3: 截止日： | D3: 序号 | E3: 内容 | F3: 索引号 | G3: 备注
A4: 编制人： | D4: 1 | E4: 生物资产实质性程序表 | F4: H7A
A5: 复核人： | D5: =D4+1 -> 2 | E5: 审定表（成本模式） | F5: H7-1
A6: 编制日期： | D6: =D5+1 -> 3 | E6: 审定表（公允价值模式） | F6: H7-1
A7: 复核日期： | D7: =D6+1 -> 4 | E7: 附注披露信息（上市公司） | G7: 无需打印
A8: 生物性生物资产类别设置（以下内容请根据实际情况修改）： | D8: =D7+1 -> 5 | E8: 附注披露信息（国有企业） | G8: 无需打印
A9: 种植业 | D9: =D8+1 -> 6 | E9: 明细表（成本模式） | F9: H7-2
A10: 畜牧养殖业 | D10: =D9+1 -> 7 | E10: 明细表（公允价值模式） | F10: H7-2
A11: 林业 | D11: =D10+1 -> 8 | E11: 调整分录汇总 | F11: H7-3
A12: 水产业 | D12: =D11+1 -> 9 | E12: 会计政策估计检查表 | F12: H7-4
A13: …… | D13: =D12+1 -> 10 | E13: 分析表 | F13: H7-5
D14: =D13+1 -> 11 | E14: 增加检查表（成本模式） | F14: H7-6
A15: 关于工作底稿与审计程序索引号对应的说明 | D15: =D14+1 -> 12 | E15: 增加检查表（公允价值模式） | F15: H7-6
A16: 1.编制的审计工作底稿应与审计程序对应。审计项目组应根据被审计单位实际情况和风险评估情况在实质性程序表中裁剪、修改或增加审计程序，根据实际执行的审计程序完成相应审计工作底稿，编制的工作底稿中应按自然顺序依次编制索引号，并通过唯一的索引号将与实质性程序表中的程序对应关联（即将工作底稿的索引号填入实质性程序表中的底稿索引号列）。 | D16: =D15+1 -> 13 | E16: 减少检查表（成本模式） | F16: H7-7
D17: =D16+1 -> 14 | E17: 减少检查表（公允价值模式） | F17: H7-7
D18: =D17+1 -> 15 | E18: 监盘计划 | F18: H7-8
D19: =D18+1 -> 16 | E19: 盘点检查表 | F19: H7-9
A20: 2.获取的支持性证据应与审计底稿或程序对应。审计项目组在完成底稿时获取的支持性证据应根据底稿索引号编制下一级按自然顺序排序的索引号（如D1-2-1、D1-2-2、……），并在底稿中说明引用的支持性证据、关联索引号。 | D20: =D19+1 -> 17 | E20: 监盘小结 | F20: H7-10
D21: =D20+1 -> 18 | E21: 折旧测算表（不含减值）-直线法 | F21: H7-11
D22: =D21+1 -> 19 | E22: 折旧测算表（含减值） | F22: H7-11
A23: 3.工作底稿索引号的编码规则：实质性程序索引号按循环从“D”到“N”,循环内账户以顺序号排列，模板中底稿索引号按账户顺序+自然数顺序（即模板中索引号按二级自然顺序排列，如D1-1、D1-2、D1-3、……D1-N）。 | D23: =D22+1 -> 20 | E23: 折旧分配分析表 | F23: H7-12
D24: =D23+1 -> 21 | E24: 公允价值复核表 | F24: H7-13
D25: =D24+1 -> 22 | E25: 互转审核表 | F25: H7-14
D26: =D25+1 -> 23 | E26: 减值测算表 | F26: H7-15
D27: =D26+1 -> 24 | E27: 可收回金额测试表 | F27: H7-16
D28: =D27+1 -> 25 | E28: 关联交易检查表 | F28: H7-17

Sheet 生物资产实质性程序表H7A
A1: 致同会计师事务所
A2: 生物资产实质性程序表
A3: =底稿目录!A2 -> 被审计单位： | C3: =底稿目录!A4 -> 编制人： | E3: =底稿目录!A6 -> 编制日期： | H3: 索引号： | I3: H7A
A4: =底稿目录!A3 -> 截止日： | C4: =底稿目录!A5 -> 复核人： | E4: =底稿目录!A7 -> 复核日期： | H4: 页 次：
A5: 一、本账户涉及的科目
A6: 生物资产、累计折旧、减值准备
A7: 二、审计目标与认定的对应关系
A8: 审计目标 | G8: 财务报表的认定
A9: A. 资产负债表中记录的生产性生物资产是存在的，且已记录于恰当的账户 | G9: 存在
A10: B. 所有应记录的生产性生物资产均已记录，所有应当包括在财务报表中的相关披露均已包括 | G10: 完整性
A11: C. 记录的生产性生物资产由被审计单位拥有或控制； | G11: 权利和义务
A12: D. 生产性生物资产以恰当的金额包括在财务报表中，与之相关的计价或分摊调整已恰当记录，相关披露已得到恰当计量和描述 | G12: 准确性、计价和分摊
A13: E. 生产性生物资产已被恰当地汇总或分解且表述清楚，相关披露在按照企业会计准则的编制基础下是相关的、可理解的 | G13: 列报
A14: 三、计划实施的实质性程序
A15: 序号 | B15: 审计程序 | C15: 程序分类 | D15: 财务报表的认定 | I15: 底稿索引号
D16: 存在 | E16: 完整性 | F16: 权利和 义务 | G16: 准确性、计价和分摊 | H16: 列报 | J16: 根据被审计单位实际情况和风险评估情况裁剪、修改或增加审计程序
A17: 1 | B17: 获取或编制生产性生物资产的明细表，完成以下工作，并编制审定表 （1）复核加计是否正确，并与总账数和明细账合计数核对是否相符，期初余额与上期审定期末余额是否相符； （2）结合生产性生物资产减值准备科目和报表数核对是否相符 （3）询问闲置资产或未入账资产处置情况（如有）。 | C17: 常规★ | D17: √ | E17: √ | G17: √ | I17: H7-1 /H7-2
A18: 2 | B18: 在使用手工编制、自定义信息报告、系统生成的非固定格式报告等由被审计单位生成的信息时，测试有关信息准确性和完整性，并考虑针对编制和维护由被审计单位生成的信息的相关控制实施控制测试，以评价该信息是否能够为实现审计目的提供基础。 | C18: 常规★ | E18: √ | G18: √ | I18: T1 / | J18: 可参见《审计手册》4.2.6，由被审计单位生成的信息可能是由系统生成的、或手工编制的、或二者兼而有之的方式生成的。例如，由被审计单位生成的信息可能包括： • 不涉及自定义的、由系统生成的报告（如，固定格式报告）； • 可能通过人工自定义的、由系统生成的报告，例如，（计算机）查询信息或特别定制的报告； • 手工编制的信息，例如，汇总信息的电子表格或用以支持分配、计算以及调节的电子表格； • 其他系统生成或手工编制的信息，例如，由被审计单位编制的客户发票； • 通过影印、拍摄、扫描或其他方式转换成电子形式的文件记录。
A19: 3 | B19: 对期初余额的审计，取得上期固定资产明细表复核加计是否正确，与总账、明细账合计数是否相符； 重新测算期初累计折旧余额准确性；对单项金额重大资产，进行实地查看资产或检查支持性文件，其他必要追加的审计程序。（适用于首次承接） | C19: 备选 | D19: √ | E19: √ | F19: √ | G19: √ | J19: 由被审计单位生成的信息不包括： • 总分类账或明细分类账、试算平衡表、或经审计的财务报表； • 第三方（除了服务机构）的报表或报告，例如，原始银行对账单，或函证的回函； • 外部数据（例如，第三方发布的数据，如，定价来源）。
A20: 4 | B20: 关注会计政策、会计估计合理性、一贯性，关注其是否利用会计政策和会计估计及其变更操纵利润。必要时与同行业其他公司会计政策、会计估计进行对比，主要会计政策和估计包括： （1）生产性生物资产资产的初始计量； （2）生产性生物资产折旧/减值的政策和方法； （3）生产性生物资产的后续支出（包括支出费用化和资本化）及终止确认。 | C20: 常规★ | D20: √ | E20: √ | G20: √ | I20: H7-4
A21: 5 | B21: 执行分析性程序，考虑识别需要执行额外程序的领域： （1）分析本期和上期生产性生物资产净值占资产总额比例、当期计提折旧额、累计折旧及减值准备余额分别占生产性生物资产原值比例是否异常； （2）分析生产性生物资产周转率、原值与本期产品产量的比率等指标，并与以前年度对比； （3）分析管护费、管护费占生产性生物资产、管护费占营业收入等的比例，并与以前年度对比； | C21: 常规★ | D21: √ | E21: √ | G21: √ | I21: H7-5
A22: 6 | B22: 计算生产性生物资产养殖成本占生产性生物资产原值的比例，并进行本期各月、本期与以前各期的比较。 | C22: IPO/上市/新三板/重组/舞弊应对 | D22: √ | E22: √ | G22: √
A23: 7 | B23: 检查本期新增的生产性生物资产： （1）对于外购的生产性生物资产，检查购置合同、发票、保险单、发运凭证等文件，抽查测试其计价是否正确，会计处理是否正确；如果购买生物资产的价款超过正常信用条件延期支付，检查实质上是否具有融资性质，生物资产的成本是否以购买价款的现值为基础确定。 （2）对于盘盈的生产性生物资产，检查生物资产计价及确认的损益是否符合会计准则及相关规定。 | C23: 常规★ | D23: √ | E23: √ | F23: √ | G23: √ | I23: H7-6
A24: 8 | B24: 检查本期生产性生物资产的处置： （1）检查处置、报废等相关的合同、发票及其他文件，确认已经办理审批手续，相关收益或损失已正确计算，并进行正确的会计处理。 （2）检查死亡或毁损的生产性生物资产是否经授权批准，会计处理是否正确； | C24: 常规★ | D24: √ | E24: √ | G24: √ | I24: H7-7
A25: 9 | B25: 其他方式增加或减少生产性生物资产，考虑执行下列程序 （1）对于非货币性资产交换、债务重组、企业合并、投资者投入等交易方式取得或减少的有关长期资产，检查相关合同/协议，关注计价是否正确、移交手续是否办理以及会计处理是否正确。 （2）对于因清产核资、资产评估调增或调减有关长期资产价值的，检查有关清产核资报告、资产评估报告、国有资产管理等部门的确认文件、验资报告等，检查会计处理是否正确。 | C25: 备选 | D25: √ | F25: √ | G25: √ | I25: H7-6 /H7-7
A26: 10 | B26: 监盘生产性生物资产： （1）取得公司生产性生物资产清单，盘点范围考虑包括本期新增、容易侵占、重要、数量巨大、已损坏项目、存放在第三方及其他异常等。 （2）获取被审计单位对于生产性生物资产的盘点计划，制定和实施监盘计划（如有）及盘点控制文件的复印件（如：盘点清单，标签控制清单）； （3）取得生产性生物资产存放地点清单，初步确定监盘方式、时间、监盘计划； （4）观察被审计单位制定的盘点程序的执行情况 （5）检查生产性生物资产的状态（未成材、成材等）； （6）执行抽盘，注册会计师从生产性生物资产盘点记录追查至生产性生物资产实物，以及从生产性生物资产实物中选取项目追查至生产性生物资产清单，将抽盘结果与账面核对； （7）评价生产性生物资产盘点结果，完成监盘小结。 | C26: 常规★ | D26: √ | F26: √ | G26: √ | I26: H7-8 /H7-9 /H7-10
A27: 11 | B27: 存放其他地方的资产（如有），考虑实地观察或函证由其他人保管或保管在盘点地之外的资产。 | C27: 备选 | D27: √ | F27: √ | G27: √ | I27: H0
A28: 12 | B28: 检查累计折旧，考虑执行以下程序： （1）获取或编制累计折旧分类汇总表，复核加计正确，并与总账数和明细账合计数核对。 （2）重新计算折旧。 （3）获取暂时闲置、已提足折旧仍继续使用和前期已计提减值准备的生产性生物资产的相关证明文件，并观察其实际状况，检查是否已按规定计提折旧； （4）检查折旧分配到成本、费用的情况，关注分配是否合理，与上期分配方法是否一致。 | C28: 常规★ | G28: √ | I28: H7-11 /H7-12
A29: 13 | B29: 对采用公允价值计量的生产性生物资产：取得公允价值计算过程，关注公允价值来源和依据是否合理，与上期计价方法是否一致，复核公允价值计算是否正确。 | C29: 备选 | G29: √ | I29: H7-13
A30: 14 | B30: 结合生产性生物资产清单和盘点程序，了解生产性生物资产的状态。针对存在减值迹象的生产性生物资产，考虑执行下列程序： 获取被审计单位在资产负债表日就生产性生物资产是否可能发生减值迹象的判断的说明，判断其合理性。对于已计提减值准备的生产性生物资产，检查减值测试相关参数是否合理，减值准备计提是否正确。对于管理层聘请评估专家出具的评估报告，复核评估报告。 | C30: 常规★ | G30: √ | I30: H7-15 /H7-16
A31: 15 | B31: 检查关联交易情况，检查关联交易的真实性、合理性及合规性；检查关联交易会计处理是否正确，考虑是否存在未识别的关联方，检查关联交易和余额披露是否正确。 | C31: 常规★ | D31: √ | E31: √ | F31: √ | G31: √ | H31: √ | I31: H7-17
A32: 16 | B32: 针对长期资产租赁，考虑执行下列程序： （1）获取或编制资产租赁明细表，获取租赁合同/协议，核对重要条款，检查租赁分类是否正确。对于重大的租约，核对租赁协议重要条款。 （2）检查租入资产是否确属企业必需，出租资产是否确属企业多余、闲置不用。必要时，实施函证。 | C32: 备选 | D32: √ | E32: √ | F32: √ | G32: √
A33: 17 | B33: 检查生产性生物资产保险情况，复核保险范围是否足够。 | C33: IPO/上市/新三板/重组/舞弊应对
A34: 18 | B34: 根据评估的舞弊风险等因素增加的审计程序。 | C34: IPO/上市/新三板/重组/舞弊应对 | D34: √ | E34: √ | F34: √ | G34: √
A35: 19 | B35: 检查生产性生物资产、抵押和担保情况等是否已按企业会计准则或其他适用的规定在财务报表中做出恰当列报和披露 | C35: 常规★ | H35: √ | I35: A 1-1/A1-15 /A1-16

Sheet 审定表（成本模式）H7-1
A1: 致同会计师事务所
A2: 生产性生物资产、累计折旧、减值准备审定表（成本模式）
A3: =底稿目录!A2 -> 被审计单位： | D3: =底稿目录!A4 -> 编制人： | F3: =底稿目录!A6 -> 编制日期： | H3: 索引号： | I3: H7-1
A4: =底稿目录!A3 -> 截止日： | D4: =底稿目录!A5 -> 复核人： | F4: =底稿目录!A7 -> 复核日期： | H4: 页 次：
A5: 项目 | B5: 期初数 | E5: 期末数 | H5: 本期审定数与上期 审定数的比较
B6: 未审数 | C6: 账项调整 | D6: 审定数 | E6: 未审数 | F6: 账项调整 | G6: 审定数 | H6: 变动额 | I6: 变动率
A7: 一、生产性生物资产原值
A8: =底稿目录!A9 -> 种植业 | B8: ='明细表（成本模式）H7-2'!D39 -> 0 | C8: ='明细表（成本模式）H7-2'!J39 -> 0 | D8: ='明细表（成本模式）H7-2'!M39 -> 0 | E8: ='明细表（成本模式）H7-2'!I39 -> 0 | F8: ='明细表（成本模式）H7-2'!J39+'明细表（成本模式）H7-2'!K39-'明细表（成本模式）H7-2'!L39 -> 0 | G8: ='明细表（成本模式）H7-2'!P39 -> 0 | H8: =G8-D8 -> 0 | I8: =IF(AND(D8=0,H8=0),0,IF(AND(D8=0,H8>0),1,H8/D8)) -> 0
A9: =底稿目录!A10 -> 畜牧养殖业 | B9: ='明细表（成本模式）H7-2'!D40 -> 0 | C9: ='明细表（成本模式）H7-2'!J40 -> 0 | D9: ='明细表（成本模式）H7-2'!M40 -> 0 | E9: ='明细表（成本模式）H7-2'!I40 -> 0 | F9: ='明细表（成本模式）H7-2'!J40+'明细表（成本模式）H7-2'!K40-'明细表（成本模式）H7-2'!L40 -> 0 | G9: ='明细表（成本模式）H7-2'!P40 -> 0 | H9: =G9-D9 -> 0 | I9: =IF(AND(D9=0,H9=0),0,IF(AND(D9=0,H9>0),1,H9/D9)) -> 0
A10: =底稿目录!A11 -> 林业 | B10: ='明细表（成本模式）H7-2'!D41 -> 0 | C10: ='明细表（成本模式）H7-2'!J41 -> 0 | D10: ='明细表（成本模式）H7-2'!M41 -> 0 | E10: ='明细表（成本模式）H7-2'!I41 -> 0 | F10: ='明细表（成本模式）H7-2'!J41+'明细表（成本模式）H7-2'!K41-'明细表（成本模式）H7-2'!L41 -> 0 | G10: ='明细表（成本模式）H7-2'!P41 -> 0 | H10: =G10-D10 -> 0 | I10: =IF(AND(D10=0,H10=0),0,IF(AND(D10=0,H10>0),1,H10/D10)) -> 0
A11: =底稿目录!A12 -> 水产业 | B11: ='明细表（成本模式）H7-2'!D42 -> 0 | C11: ='明细表（成本模式）H7-2'!J42 -> 0 | D11: ='明细表（成本模式）H7-2'!M42 -> 0 | E11: ='明细表（成本模式）H7-2'!I42 -> 0 | F11: ='明细表（成本模式）H7-2'!J42+'明细表（成本模式）H7-2'!K42-'明细表（成本模式）H7-2'!L42 -> 0 | G11: ='明细表（成本模式）H7-2'!P42 -> 0 | H11: =G11-D11 -> 0 | I11: =IF(AND(D11=0,H11=0),0,IF(AND(D11=0,H11>0),1,H11/D11)) -> 0
A12: =底稿目录!A13 -> …… | B12: ='明细表（成本模式）H7-2'!D43 -> 0 | C12: ='明细表（成本模式）H7-2'!J43 -> 0 | D12: ='明细表（成本模式）H7-2'!M43 -> 0 | E12: ='明细表（成本模式）H7-2'!I43 -> 0 | F12: ='明细表（成本模式）H7-2'!J43+'明细表（成本模式）H7-2'!K43-'明细表（成本模式）H7-2'!L43 -> 0 | G12: ='明细表（成本模式）H7-2'!P43 -> 0 | H12: =G12-D12 -> 0 | I12: =IF(AND(D12=0,H12=0),0,IF(AND(D12=0,H12>0),1,H12/D12)) -> 0
A13: 合计 | B13: =SUM(B8:B12) -> 0 | C13: =SUM(C8:C12) -> 0 | D13: =SUM(D8:D12) -> 0 | E13: =SUM(E8:E12) -> 0 | F13: =SUM(F8:F12) -> 0 | G13: =SUM(G8:G12) -> 0 | H13: =G13-D13 -> 0 | I13: =IF(AND(D13=0,H13=0),0,IF(AND(D13=0,H13>0),1,H13/D13)) -> 0
A14: 二、累计折旧
A15: =A8 -> 种植业 | B15: ='明细表（成本模式）H7-2'!Q39 -> 0 | C15: ='明细表（成本模式）H7-2'!W39 -> 0 | D15: ='明细表（成本模式）H7-2'!AB39 -> 0 | E15: ='明细表（成本模式）H7-2'!V39 -> 0 | F15: ='明细表（成本模式）H7-2'!W39+'明细表（成本模式）H7-2'!X39-'明细表（成本模式）H7-2'!Z39+'明细表（成本模式）H7-2'!Y39-'明细表（成本模式）H7-2'!AA39 -> 0 | G15: ='明细表（成本模式）H7-2'!AE39 -> 0 | H15: =G15-D15 -> 0 | I15: =IF(AND(D15=0,H15=0),0,IF(AND(D15=0,H15>0),1,H15/D15)) -> 0
A16: =A9 -> 畜牧养殖业 | B16: ='明细表（成本模式）H7-2'!Q40 -> 0 | C16: ='明细表（成本模式）H7-2'!W40 -> 0 | D16: ='明细表（成本模式）H7-2'!AB40 -> 0 | E16: ='明细表（成本模式）H7-2'!V40 -> 0 | F16: ='明细表（成本模式）H7-2'!W40+'明细表（成本模式）H7-2'!X40-'明细表（成本模式）H7-2'!Z40+'明细表（成本模式）H7-2'!Y40-'明细表（成本模式）H7-2'!AA40 -> 0 | G16: ='明细表（成本模式）H7-2'!AE40 -> 0 | H16: =G16-D16 -> 0 | I16: =IF(AND(D16=0,H16=0),0,IF(AND(D16=0,H16>0),1,H16/D16)) -> 0
A17: =A10 -> 林业 | B17: ='明细表（成本模式）H7-2'!Q41 -> 0 | C17: ='明细表（成本模式）H7-2'!W41 -> 0 | D17: ='明细表（成本模式）H7-2'!AB41 -> 0 | E17: ='明细表（成本模式）H7-2'!V41 -> 0 | F17: ='明细表（成本模式）H7-2'!W41+'明细表（成本模式）H7-2'!X41-'明细表（成本模式）H7-2'!Z41+'明细表（成本模式）H7-2'!Y41-'明细表（成本模式）H7-2'!AA41 -> 0 | G17: ='明细表（成本模式）H7-2'!AE41 -> 0 | H17: =G17-D17 -> 0 | I17: =IF(AND(D17=0,H17=0),0,IF(AND(D17=0,H17>0),1,H17/D17)) -> 0
A18: =A11 -> 水产业 | B18: ='明细表（成本模式）H7-2'!Q42 -> 0 | C18: ='明细表（成本模式）H7-2'!W42 -> 0 | D18: ='明细表（成本模式）H7-2'!AB42 -> 0 | E18: ='明细表（成本模式）H7-2'!V42 -> 0 | F18: ='明细表（成本模式）H7-2'!W42+'明细表（成本模式）H7-2'!X42-'明细表（成本模式）H7-2'!Z42+'明细表（成本模式）H7-2'!Y42-'明细表（成本模式）H7-2'!AA42 -> 0 | G18: ='明细表（成本模式）H7-2'!AE42 -> 0 | H18: =G18-D18 -> 0 | I18: =IF(AND(D18=0,H18=0),0,IF(AND(D18=0,H18>0),1,H18/D18)) -> 0
A19: =A12 -> …… | B19: ='明细表（成本模式）H7-2'!Q43 -> 0 | C19: ='明细表（成本模式）H7-2'!W43 -> 0 | D19: ='明细表（成本模式）H7-2'!AB43 -> 0 | E19: ='明细表（成本模式）H7-2'!V43 -> 0 | F19: ='明细表（成本模式）H7-2'!W43+'明细表（成本模式）H7-2'!X43-'明细表（成本模式）H7-2'!Z43+'明细表（成本模式）H7-2'!Y43-'明细表（成本模式）H7-2'!AA43 -> 0 | G19: ='明细表（成本模式）H7-2'!AE43 -> 0 | H19: =G19-D19 -> 0 | I19: =IF(AND(D19=0,H19=0),0,IF(AND(D19=0,H19>0),1,H19/D19)) -> 0
A20: 合计 | B20: =SUM(B15:B19) -> 0 | C20: =SUM(C15:C19) -> 0 | D20: =SUM(D15:D19) -> 0 | E20: =SUM(E15:E19) -> 0 | F20: =SUM(F15:F19) -> 0 | G20: =SUM(G15:G19) -> 0 | H20: =G20-D20 -> 0 | I20: =IF(AND(D20=0,H20=0),0,IF(AND(D20=0,H20>0),1,H20/D20)) -> 0
A21: 三、减值准备
A22: =A15 -> 种植业 | B22: ='明细表（成本模式）H7-2'!AF39 -> 0 | C22: ='明细表（成本模式）H7-2'!AL39 -> 0 | D22: ='明细表（成本模式）H7-2'!AQ39 -> 0 | E22: ='明细表（成本模式）H7-2'!AK39 -> 0 | F22: ='明细表（成本模式）H7-2'!AL39+'明细表（成本模式）H7-2'!AM39-'明细表（成本模式）H7-2'!AP39+'明细表（成本模式）H7-2'!AN39-'明细表（成本模式）H7-2'!AO39 -> 0 | G22: ='明细表（成本模式）H7-2'!AT39 -> 0 | H22: =G22-D22 -> 0 | I22: =IF(AND(D22=0,H22=0),0,IF(AND(D22=0,H22>0),1,H22/D22)) -> 0
A23: =A16 -> 畜牧养殖业 | B23: ='明细表（成本模式）H7-2'!AF40 -> 0 | C23: ='明细表（成本模式）H7-2'!AL40 -> 0 | D23: ='明细表（成本模式）H7-2'!AQ40 -> 0 | E23: ='明细表（成本模式）H7-2'!AK40 -> 0 | F23: ='明细表（成本模式）H7-2'!AL40+'明细表（成本模式）H7-2'!AM40-'明细表（成本模式）H7-2'!AP40+'明细表（成本模式）H7-2'!AN40-'明细表（成本模式）H7-2'!AO40 -> 0 | G23: ='明细表（成本模式）H7-2'!AT40 -> 0 | H23: =G23-D23 -> 0 | I23: =IF(AND(D23=0,H23=0),0,IF(AND(D23=0,H23>0),1,H23/D23)) -> 0
A24: =A17 -> 林业 | B24: ='明细表（成本模式）H7-2'!AF41 -> 0 | C24: ='明细表（成本模式）H7-2'!AL41 -> 0 | D24: ='明细表（成本模式）H7-2'!AQ41 -> 0 | E24: ='明细表（成本模式）H7-2'!AK41 -> 0 | F24: ='明细表（成本模式）H7-2'!AL41+'明细表（成本模式）H7-2'!AM41-'明细表（成本模式）H7-2'!AP41+'明细表（成本模式）H7-2'!AN41-'明细表（成本模式）H7-2'!AO41 -> 0 | G24: ='明细表（成本模式）H7-2'!AT41 -> 0 | H24: =G24-D24 -> 0 | I24: =IF(AND(D24=0,H24=0),0,IF(AND(D24=0,H24>0),1,H24/D24)) -> 0
A25: =A18 -> 水产业 | B25: ='明细表（成本模式）H7-2'!AF42 -> 0 | C25: ='明细表（成本模式）H7-2'!AL42 -> 0 | D25: ='明细表（成本模式）H7-2'!AQ42 -> 0 | E25: ='明细表（成本模式）H7-2'!AK42 -> 0 | F25: ='明细表（成本模式）H7-2'!AL42+'明细表（成本模式）H7-2'!AM42-'明细表（成本模式）H7-2'!AP42+'明细表（成本模式）H7-2'!AN42-'明细表（成本模式）H7-2'!AO42 -> 0 | G25: ='明细表（成本模式）H7-2'!AT42 -> 0 | H25: =G25-D25 -> 0 | I25: =IF(AND(D25=0,H25=0),0,IF(AND(D25=0,H25>0),1,H25/D25)) -> 0
A26: =A19 -> …… | B26: ='明细表（成本模式）H7-2'!AF43 -> 0 | C26: ='明细表（成本模式）H7-2'!AL43 -> 0 | D26: ='明细表（成本模式）H7-2'!AQ43 -> 0 | E26: ='明细表（成本模式）H7-2'!AK43 -> 0 | F26: ='明细表（成本模式）H7-2'!AL43+'明细表（成本模式）H7-2'!AM43-'明细表（成本模式）H7-2'!AP43+'明细表（成本模式）H7-2'!AN43-'明细表（成本模式）H7-2'!AO43 -> 0 | G26: ='明细表（成本模式）H7-2'!AT43 -> 0 | H26: =G26-D26 -> 0 | I26: =IF(AND(D26=0,H26=0),0,IF(AND(D26=0,H26>0),1,H26/D26)) -> 0
A27: 合计 | B27: =SUM(B22:B26) -> 0 | C27: =SUM(C22:C26) -> 0 | D27: =SUM(D22:D26) -> 0 | E27: =SUM(E22:E26) -> 0 | F27: =SUM(F22:F26) -> 0 | G27: =SUM(G22:G26) -> 0 | H27: =G27-D27 -> 0 | I27: =IF(AND(D27=0,H27=0),0,IF(AND(D27=0,H27>0),1,H27/D27)) -> 0
A28: 四、净值
A29: =A22 -> 种植业 | B29: =B8-B15-B22 -> 0 | C29: =C8-C15-C22 -> 0 | D29: =D8-D15-D22 -> 0 | E29: =E8-E15-E22 -> 0 | F29: =F8-F15-F22 -> 0 | G29: =G8-G15-G22 -> 0 | H29: =G29-D29 -> 0 | I29: =IF(AND(D29=0,H29=0),0,IF(AND(D29=0,H29>0),1,H29/D29)) -> 0
A30: =A23 -> 畜牧养殖业 | B30: =B9-B16-B23 -> 0 | C30: =C9-C16-C23 -> 0 | D30: =D9-D16-D23 -> 0 | E30: =E9-E16-E23 -> 0 | F30: =F9-F16-F23 -> 0 | G30: =G9-G16-G23 -> 0 | H30: =G30-D30 -> 0 | I30: =IF(AND(D30=0,H30=0),0,IF(AND(D30=0,H30>0),1,H30/D30)) -> 0
A31: =A24 -> 林业 | B31: =B10-B17-B24 -> 0 | C31: =C10-C17-C24 -> 0 | D31: =D10-D17-D24 -> 0 | E31: =E10-E17-E24 -> 0 | F31: =F10-F17-F24 -> 0 | G31: =G10-G17-G24 -> 0 | H31: =G31-D31 -> 0 | I31: =IF(AND(D31=0,H31=0),0,IF(AND(D31=0,H31>0),1,H31/D31)) -> 0
A32: =A25 -> 水产业 | B32: =B11-B18-B25 -> 0 | C32: =C11-C18-C25 -> 0 | D32: =D11-D18-D25 -> 0 | E32: =E11-E18-E25 -> 0 | F32: =F11-F18-F25 -> 0 | G32: =G11-G18-G25 -> 0 | H32: =G32-D32 -> 0 | I32: =IF(AND(D32=0,H32=0),0,IF(AND(D32=0,H32>0),1,H32/D32)) -> 0
A33: =A26 -> …… | B33: =B12-B19-B26 -> 0 | C33: =C12-C19-C26 -> 0 | D33: =D12-D19-D26 -> 0 | E33: =E12-E19-E26 -> 0 | F33: =F12-F19-F26 -> 0 | G33: =G12-G19-G26 -> 0 | H33: =G33-D33 -> 0 | I33: =IF(AND(D33=0,H33=0),0,IF(AND(D33=0,H33>0),1,H33/D33)) -> 0
A34: 合计 | B34: =SUM(B29:B33) -> 0 | C34: =SUM(C29:C33) -> 0 | D34: =SUM(D29:D33) -> 0 | E34: =SUM(E29:E33) -> 0 | F34: =SUM(F29:F33) -> 0 | G34: =SUM(G29:G33) -> 0 | H34: =G34-D34 -> 0 | I34: =IF(AND(D34=0,H34=0),0,IF(AND(D34=0,H34>0),1,H34/D34)) -> 0
A35: 1、审计说明：
A36: （1）生产性生物资产期末净值较期初净值增加（负数为减少）：
A37: 主要原因（比例超过30%的）：
A39: （2）本期外购情况说明：
A41: （3）自行营造或繁殖的生产性生物资产的成本情况说明：
A43: （4）处置或其他情况说明：
A46: （5）与试算平衡表核对
B47: 期末数 | C47: 期初数
A48: 生产性生物资产净值审定数 | B48: =G34 -> 0 | C48: =D34 -> 0
A49: 试算平衡表数
A50: 差异 | B50: =B48-B49 -> 0 | C50: =C48-C49 -> 0
A52: 2、审计结论：

Sheet 审定表（公允价值模式）H7-1
A1: 致同会计师事务所
A2: 生产性生物资产审定表（公允价值模式）
A3: =底稿目录!A2 -> 被审计单位： | D3: =底稿目录!A4 -> 编制人： | F3: =底稿目录!A6 -> 编制日期： | H3: 索引号： | I3: H7-1
A4: =底稿目录!A3 -> 截止日： | D4: =底稿目录!A5 -> 复核人： | F4: =底稿目录!A7 -> 复核日期： | H4: 页 次：
A5: 项目 | B5: 期初数 | E5: 期末数 | H5: 本期审定数与上期 审定数的比较
B6: 未审数 | C6: 账项调整 | D6: 审定数 | E6: 未审数 | F6: 账项调整 | G6: 审定数 | H6: 变动额 | I6: 变动率
A7: 一、生产性生物资产原值
A8: =底稿目录!A9 -> 种植业 | B8: ='明细表（公允价值模式）H7-2'!D39 -> 0 | C8: ='明细表（公允价值模式）H7-2'!J39 -> 0 | D8: ='明细表（公允价值模式）H7-2'!M39 -> 0 | E8: ='明细表（公允价值模式）H7-2'!I39 -> 0 | F8: ='明细表（公允价值模式）H7-2'!J39+'明细表（公允价值模式）H7-2'!K39-'明细表（公允价值模式）H7-2'!L39 -> 0 | G8: ='明细表（公允价值模式）H7-2'!P39 -> 0 | H8: =G8-D8 -> 0 | I8: =IF(AND(D8=0,H8=0),0,IF(AND(D8=0,H8>0),1,H8/D8)) -> 0
A9: =底稿目录!A10 -> 畜牧养殖业 | B9: ='明细表（公允价值模式）H7-2'!D40 -> 0 | C9: ='明细表（公允价值模式）H7-2'!J40 -> 0 | D9: ='明细表（公允价值模式）H7-2'!M40 -> 0 | E9: ='明细表（公允价值模式）H7-2'!I40 -> 0 | F9: ='明细表（公允价值模式）H7-2'!J40+'明细表（公允价值模式）H7-2'!K40-'明细表（公允价值模式）H7-2'!L40 -> 0 | G9: ='明细表（公允价值模式）H7-2'!P40 -> 0 | H9: =G9-D9 -> 0 | I9: =IF(AND(D9=0,H9=0),0,IF(AND(D9=0,H9>0),1,H9/D9)) -> 0
A10: =底稿目录!A11 -> 林业 | B10: ='明细表（公允价值模式）H7-2'!D41 -> 0 | C10: ='明细表（公允价值模式）H7-2'!J41 -> 0 | D10: ='明细表（公允价值模式）H7-2'!M41 -> 0 | E10: ='明细表（公允价值模式）H7-2'!I41 -> 0 | F10: ='明细表（公允价值模式）H7-2'!J41+'明细表（公允价值模式）H7-2'!K41-'明细表（公允价值模式）H7-2'!L41 -> 0 | G10: ='明细表（公允价值模式）H7-2'!P41 -> 0 | H10: =G10-D10 -> 0 | I10: =IF(AND(D10=0,H10=0),0,IF(AND(D10=0,H10>0),1,H10/D10)) -> 0
A11: =底稿目录!A12 -> 水产业 | B11: ='明细表（公允价值模式）H7-2'!D42 -> 0 | C11: ='明细表（公允价值模式）H7-2'!J42 -> 0 | D11: ='明细表（公允价值模式）H7-2'!M42 -> 0 | E11: ='明细表（公允价值模式）H7-2'!I42 -> 0 | F11: ='明细表（公允价值模式）H7-2'!J42+'明细表（公允价值模式）H7-2'!K42-'明细表（公允价值模式）H7-2'!L42 -> 0 | G11: ='明细表（公允价值模式）H7-2'!P42 -> 0 | H11: =G11-D11 -> 0 | I11: =IF(AND(D11=0,H11=0),0,IF(AND(D11=0,H11>0),1,H11/D11)) -> 0
A12: =底稿目录!A13 -> …… | B12: ='明细表（公允价值模式）H7-2'!D43 -> 0 | C12: ='明细表（公允价值模式）H7-2'!J43 -> 0 | D12: ='明细表（公允价值模式）H7-2'!M43 -> 0 | E12: ='明细表（公允价值模式）H7-2'!I43 -> 0 | F12: ='明细表（公允价值模式）H7-2'!J43+'明细表（公允价值模式）H7-2'!K43-'明细表（公允价值模式）H7-2'!L43 -> 0 | G12: ='明细表（公允价值模式）H7-2'!P43 -> 0 | H12: =G12-D12 -> 0 | I12: =IF(AND(D12=0,H12=0),0,IF(AND(D12=0,H12>0),1,H12/D12)) -> 0
A13: 合计 | B13: =SUM(B8:B12) -> 0 | C13: =SUM(C8:C12) -> 0 | D13: =SUM(D8:D12) -> 0 | E13: =SUM(E8:E12) -> 0 | F13: =SUM(F8:F12) -> 0 | G13: =SUM(G8:G12) -> 0 | H13: =G13-D13 -> 0 | I13: =IF(AND(D13=0,H13=0),0,IF(AND(D13=0,H13>0),1,H13/D13)) -> 0
A14: 二、公允价值变动
A15: =A8 -> 种植业 | B15: ='明细表（公允价值模式）H7-2'!Q39 -> 0 | C15: ='明细表（公允价值模式）H7-2'!T39 -> 0 | D15: ='明细表（公允价值模式）H7-2'!V39 -> 0 | E15: ='明细表（公允价值模式）H7-2'!S39 -> 0 | F15: ='明细表（公允价值模式）H7-2'!T39+'明细表（公允价值模式）H7-2'!U39 -> 0 | G15: ='明细表（公允价值模式）H7-2'!X39 -> 0 | H15: =G15-D15 -> 0 | I15: =IF(AND(D15=0,H15=0),0,IF(AND(D15=0,H15>0),1,H15/D15)) -> 0
A16: =A9 -> 畜牧养殖业 | B16: ='明细表（公允价值模式）H7-2'!Q40 -> 0 | C16: ='明细表（公允价值模式）H7-2'!T40 -> 0 | D16: ='明细表（公允价值模式）H7-2'!V40 -> 0 | E16: ='明细表（公允价值模式）H7-2'!S40 -> 0 | F16: ='明细表（公允价值模式）H7-2'!T40+'明细表（公允价值模式）H7-2'!U40 -> 0 | G16: ='明细表（公允价值模式）H7-2'!X40 -> 0 | H16: =G16-D16 -> 0 | I16: =IF(AND(D16=0,H16=0),0,IF(AND(D16=0,H16>0),1,H16/D16)) -> 0
A17: =A10 -> 林业 | B17: ='明细表（公允价值模式）H7-2'!Q41 -> 0 | C17: ='明细表（公允价值模式）H7-2'!T41 -> 0 | D17: ='明细表（公允价值模式）H7-2'!V41 -> 0 | E17: ='明细表（公允价值模式）H7-2'!S41 -> 0 | F17: ='明细表（公允价值模式）H7-2'!T41+'明细表（公允价值模式）H7-2'!U41 -> 0 | G17: ='明细表（公允价值模式）H7-2'!X41 -> 0 | H17: =G17-D17 -> 0 | I17: =IF(AND(D17=0,H17=0),0,IF(AND(D17=0,H17>0),1,H17/D17)) -> 0
A18: =A11 -> 水产业 | B18: ='明细表（公允价值模式）H7-2'!Q42 -> 0 | C18: ='明细表（公允价值模式）H7-2'!T42 -> 0 | D18: ='明细表（公允价值模式）H7-2'!V42 -> 0 | E18: ='明细表（公允价值模式）H7-2'!S42 -> 0 | F18: ='明细表（公允价值模式）H7-2'!T42+'明细表（公允价值模式）H7-2'!U42 -> 0 | G18: ='明细表（公允价值模式）H7-2'!X42 -> 0 | H18: =G18-D18 -> 0 | I18: =IF(AND(D18=0,H18=0),0,IF(AND(D18=0,H18>0),1,H18/D18)) -> 0
A19: =A12 -> …… | B19: ='明细表（公允价值模式）H7-2'!Q43 -> 0 | C19: ='明细表（公允价值模式）H7-2'!T43 -> 0 | D19: ='明细表（公允价值模式）H7-2'!V43 -> 0 | E19: ='明细表（公允价值模式）H7-2'!S43 -> 0 | F19: ='明细表（公允价值模式）H7-2'!T43+'明细表（公允价值模式）H7-2'!U43 -> 0 | G19: ='明细表（公允价值模式）H7-2'!X43 -> 0 | H19: =G19-D19 -> 0 | I19: =IF(AND(D19=0,H19=0),0,IF(AND(D19=0,H19>0),1,H19/D19)) -> 0
A20: 合计 | B20: =SUM(B15:B19) -> 0 | C20: =SUM(C15:C19) -> 0 | D20: =SUM(D15:D19) -> 0 | E20: =SUM(E15:E19) -> 0 | F20: =SUM(F15:F19) -> 0 | G20: =SUM(G15:G19) -> 0 | H20: =G20-D20 -> 0 | I20: =IF(AND(D20=0,H20=0),0,IF(AND(D20=0,H20>0),1,H20/D20)) -> 0
A21: 三、净值
A22: =A8 -> 种植业 | B22: =B8+B15 -> 0 | C22: =C8+C15 -> 0 | D22: =D8+D15 -> 0 | E22: =E8+E15 -> 0 | F22: =F8+F15 -> 0 | G22: =G8+G15 -> 0 | H22: =G22-D22 -> 0 | I22: =IF(AND(D22=0,H22=0),0,IF(AND(D22=0,H22>0),1,H22/D22)) -> 0
A23: =A9 -> 畜牧养殖业 | B23: =B9+B16 -> 0 | C23: =C9+C16 -> 0 | D23: =D9+D16 -> 0 | E23: =E9+E16 -> 0 | F23: =F9+F16 -> 0 | G23: =G9+G16 -> 0 | H23: =G23-D23 -> 0 | I23: =IF(AND(D23=0,H23=0),0,IF(AND(D23=0,H23>0),1,H23/D23)) -> 0
A24: =A10 -> 林业 | B24: =B10+B17 -> 0 | C24: =C10+C17 -> 0 | D24: =D10+D17 -> 0 | E24: =E10+E17 -> 0 | F24: =F10+F17 -> 0 | G24: =G10+G17 -> 0 | H24: =G24-D24 -> 0 | I24: =IF(AND(D24=0,H24=0),0,IF(AND(D24=0,H24>0),1,H24/D24)) -> 0
A25: =A11 -> 水产业 | B25: =B11+B18 -> 0 | C25: =C11+C18 -> 0 | D25: =D11+D18 -> 0 | E25: =E11+E18 -> 0 | F25: =F11+F18 -> 0 | G25: =G11+G18 -> 0 | H25: =G25-D25 -> 0 | I25: =IF(AND(D25=0,H25=0),0,IF(AND(D25=0,H25>0),1,H25/D25)) -> 0
A26: =A12 -> …… | B26: =B12+B19 -> 0 | C26: =C12+C19 -> 0 | D26: =D12+D19 -> 0 | E26: =E12+E19 -> 0 | F26: =F12+F19 -> 0 | G26: =G12+G19 -> 0 | H26: =G26-D26 -> 0 | I26: =IF(AND(D26=0,H26=0),0,IF(AND(D26=0,H26>0),1,H26/D26)) -> 0
A27: 合计 | B27: =SUM(B22:B26) -> 0 | C27: =SUM(C22:C26) -> 0 | D27: =SUM(D22:D26) -> 0 | E27: =SUM(E22:E26) -> 0 | F27: =SUM(F22:F26) -> 0 | G27: =SUM(G22:G26) -> 0 | H27: =G27-D27 -> 0 | I27: =IF(AND(D27=0,H27=0),0,IF(AND(D27=0,H27>0),1,H27/D27)) -> 0
A28: 1、审计说明：
A29: （1）生产性生物资产期末账面价值较期初账面价值增加（负数为减少）：
A30: 主要原因（比例超过30%的）：
A33: （2）生产性生物资产公允价值的确定依据及公允价值金额的增减变动情况说明：
A37: （3）其他说明：
A40: （4）与试算平衡表核对
B41: 期末数 | C41: 期初数
A42: 生产性生物资产净值审定数 | B42: =G27 -> 0 | C42: =D27 -> 0
A43: 试算平衡表数
A44: 差异 | B44: =B42-B43 -> 0 | C44: =C42-C43 -> 0
A47: 2、审计结论：
A54: 提示：
A55: 1、如适用，根据1131号等审计准则和指南的要求编制，说明涉及事项内容、应对措施、审计结论或解决方法，
A56: 以及可能对审计报告的影响。
A57: A、风险评估结果和内控了解、测试情况（不适用则说明：不存在重大错报风险。)
A58: (识别和实际评估的重大错报风险、尤其识特别风险，以及对内控了解和控制测试情况〔采用综合方案时〕）；
A59: 提示：a、收入科目应当假定存在舞弊的特别风险，如不存在，应说明理由；
A60: b、涉及特别风险时，应当重点说明有关事项、应当措施、结果〔可索引有关底稿〕。
A61: 特别风险涉及的事项包括但不限于：
A62: （1）舞弊风险（如1141准则的示例）；（2）重大非常规交易（如企业购并、债务重组、非货币性资产交换、
A63: 重大或有事项、持续经营、违反法律法规等）；(3)重大关联交易；(4)重大判断事项（如重大会计估计、
A64: 会计政策及其变更）；(5)重大复杂交易；(6)仅通过实质性程序无法应对的重大错报风险（如日常交易采用
... A78: 二是能够从交易市场上取得同类或类似生物资产的市场价格及其他相关信息，从而对生物资产的公允价值作出合理估计。同类或类似，是指生物资产的品种相同或类似、质量等级相同或类似、生长时间相同或类似、所处气候和地理环境相同或类似。

Sheet 附注披露信息（上市公司）
A1: 致同会计师事务所
A2: 附注披露信息（上市公司）
A3: =底稿目录!A2 -> 被审计单位： | C3: =底稿目录!A4 -> 编制人： | F3: =底稿目录!A6 -> 编制日期： | I3: 索引号：
A4: =底稿目录!A3 -> 截止日： | C4: =底稿目录!A5 -> 复核人： | F4: =底稿目录!A7 -> 复核日期： | I4: 页 次：
K5: 返回目录
A6: 24、生产性生物资产（不适用的删除）
A7: （有公益性生物资产的企业，应增设“公益性生物资产”项目，列在“生产性生物资产”项目之后）
A8: （1）以成本计量
A9: 项 目 | B9: 种植业 | D9: 畜牧养殖业 | F9: 林业 | H9: 水产业 | J9: 合计
B10: 类别 | C10: …… | D10: 类别 | E10: …… | F10: 类别 | G10: …… | H10: 类别 | I10: ……
A11: 一、账面原值
A12: 1.期初余额
A13: 2.本期增加金额
A14: （1）外购
A15: （2）自行培育
A16: （3）其他增加
A17: 3.本期减少金额
A18: （1）处置
A19: （2）其他
A20: ……
A21: 4.期末余额
A22: 二、累计折旧
... A50: （2）以公允价值计量
A51: 项 目 | B51: 种植业 | D51: 畜牧养殖业 | F51: 林业 | H51: 水产业 | J51: 合计
B52: 类别 | C52: …… | D52: 类别 | E52: …… | F52: 类别 | G52: …… | H52: 类别 | I52: ……
A53: 一、期初余额
A54: 二、本期变动
A55: 加：外购
A56: 自行培育
A57: 企业合并增加
A58: ……
A59: 减：处置
A60: 其他转出
A62: 公允价值变动
A63: ……
A64: 三、期末余额

Sheet 附注披露信息（国有企业）
A1: 致同会计师事务所
A2: 附注披露信息（国有企业）
A3: =底稿目录!A2 -> 被审计单位： | B3: =底稿目录!A4 -> 编制人： | D3: =底稿目录!A6 -> 编制日期： | E3: 索引号：
A4: =底稿目录!A3 -> 截止日： | B4: =底稿目录!A5 -> 复核人： | D4: =底稿目录!A7 -> 复核日期： | E4: 页 次： | F4: 返回目录
A6: 24、生产性生物资产
A7: （1）以成本计量
A8: 项 目 | B8: 期初账面价值 | C8: 本期增加额 | D8: 本期减少额 | E8: 期末账面价值
A9: 一、种植业
A10: 其中：1．
A11: ……
A12: 二、畜牧养殖业
A13: 其中：1．
A14: ……
A15: 三、林业
A16: 其中：1．
A17: ……
A18: 四、水产业
A19: 其中：1．
A20: ……
... A24: （2）以公允价值计量
A25: 项 目 | B25: 期初账面价值 | C25: 本期增加额 | D25: 本期减少额 | E25: 期末账面价值
A26: 一、种植业
A27: 其中：1．
A28: ……
A29: 二、畜牧养殖业
A30: 其中：1．
A31: ……
A32: 三、林业
A33: 其中：1．
A34: ……
A35: 四、水产业
A36: 其中：1．
A37: ……
... A40: （3）说明生产性生物资产相关的风险情况与管理措施。

Sheet 明细表（成本模式）H7-2
A1: 致同会计师事务所 | Q1: 致同会计师事务所 | AF1: 致同会计师事务所
A2: 生产性生物资产、累计折旧及减值准备明细表 | Q2: 生产性生物资产、累计折旧及减值准备明细表 | AF2: 生产性生物资产、累计折旧及减值准备明细表
A3: =底稿目录!A2 -> 被审计单位： | G3: =底稿目录!A4 -> 编制人： | K3: =底稿目录!A6 -> 编制日期： | O3: 索引号： | P3: H7-2 | U3: =底稿目录!A4 -> 编制人： | Y3: =底稿目录!A6 -> 编制日期： | AD3: 索引号： | AE3: H7-2 | AJ3: =底稿目录!A4 -> 编制人： | AQ3: =底稿目录!A6 -> 编制日期： | AX3: 索引号： | AY3: H7-2
A4: =底稿目录!A3 -> 截止日： | G4: =底稿目录!A5 -> 复核人： | K4: =底稿目录!A7 -> 复核日期： | O4: 页 次： | U4: =底稿目录!A5 -> 复核人： | Y4: =底稿目录!A7 -> 复核日期： | AD4: 页 次： | AJ4: =底稿目录!A5 -> 复核人： | AQ4: =底稿目录!A7 -> 复核日期： | AX4: 页 次：
A5: 一、审计目标:
A6: 1. 资产负债表中记录的生产性生物资产是存在的，且已记录于恰当的账户；2. 所有应记录的生产性生物资产均已记录，所有应当包括在财务报表中的相关披露均已包括；
A7: 3. 生产性生物资产以恰当的金额包括在财务报表中，与之相关的计价或分摊调整已恰当记录，相关披露已得到恰当计量和描述.
A8: 二、审计过程：
A9: 生产性生物资产类别 | B9: 生产性生物资产编号 | C9: 生产性生物资产名称 | D9: 生产性生物资产原值 | Q9: 累计折旧 | AF9: 减值准备 | AU9: 期初净值 | AW9: 期末净值 | AY9: 是否提足折旧
D10: 未审数 | J10: 期初调整 | K10: 账项调整 | M10: 审定数 | Q10: 未审数 | W10: 期初调整 | X10: 账项调整 | AB10: 审定数 | AF10: 未审数 | AL10: 期初调整 | AM10: 账项调整 | AQ10: 审定数
D11: 期初数 | E11: 本期增加 | G11: 本期减少 | I11: 期末数 | K11: 本期增加 | L11: 本期减少 | M11: 期初数 | N11: 本期增加 | O11: 本期减少 | P11: 期末数 | Q11: 期初数 | R11: 本期增加 | T11: 本期减少 | V11: 期末数 | X11: 本期增加 | Z11: 本期减少 | AB11: 期初数 | AC11: 本期增加 | AD11: 本期减少 | AE11: 期末数 | AF11: 期初数 | AG11: 本期增加 | AI11: 本期减少 | AK11: 期末数 | AM11: 本期增加 | AO11: 本期减少 | AQ11: 期初数 | AR11: 本期增加 | AS11: 本期减少 | AT11: 期末数 | AU11: 未审净值 | AV11: 审定净值 | AW11: 未审净值 | AX11: 审定净值
E12: 金额 | F12: 增加方式 | G12: 金额 | H12: 减少方式 | R12: 本期计提 | S12: 其他增加 | T12: 处置 | U12: 其他减少 | X12: 本期计提 | Y12: 其他增加 | Z12: 处置 | AA12: 其他减少 | AG12: 本期计提 | AH12: 其他增加 | AI12: 处置 | AJ12: 其他减少 | AM12: 本期计提 | AN12: 其他增加 | AO12: 处置 | AP12: 其他减少
I13: =SUM(D13:E13)-G13 -> 0 | M13: =D13+J13 -> 0 | N13: =E13+K13 -> 0 | O13: =G13+L13 -> 0 | P13: =M13+N13-O13 -> 0 | V13: =SUM(Q13:S13)-SUM(T13:U13) -> 0 | AB13: =Q13+W13 -> 0 | AC13: =R13+X13+S13+Y13 -> 0 | AD13: =T13+Z13+U13+AA13 -> 0 | AE13: =AB13+AC13-AD13 -> 0 | AK13: =SUM(AF13:AH13)-SUM(AI13:AJ13) -> 0 | AQ13: =AF13+AL13 -> 0 | AR13: =AG13+AM13+AH13+AN13 -> 0 | AS13: =AI13+AP13+AJ13+AO13 -> 0 | AT13: =AQ13+AR13-AS13 -> 0 | AU13: =D13-Q13-AF13 -> 0 | AV13: =M13-AB13-AQ13 -> 0 | AW13: =I13-V13-AK13 -> 0 | AX13: =P13-AE13-AT13 -> 0
I14: =SUM(D14:E14)-G14 -> 0 | M14: =D14+J14 -> 0 | N14: =E14+K14 -> 0 | O14: =G14+L14 -> 0 | P14: =M14+N14-O14 -> 0 | V14: =SUM(Q14:S14)-SUM(T14:U14) -> 0 | AB14: =Q14+W14 -> 0 | AC14: =R14+X14+S14+Y14 -> 0 | AD14: =T14+Z14+U14+AA14 -> 0 | AE14: =AB14+AC14-AD14 -> 0 | AK14: =SUM(AF14:AH14)-SUM(AI14:AJ14) -> 0 | AQ14: =AF14+AL14 -> 0 | AR14: =AG14+AM14+AH14+AN14 -> 0 | AS14: =AI14+AP14+AJ14+AO14 -> 0 | AT14: =AQ14+AR14-AS14 -> 0 | AU14: =D14-Q14-AF14 -> 0 | AV14: =M14-AB14-AQ14 -> 0 | AW14: =I14-V14-AK14 -> 0 | AX14: =P14-AE14-AT14 -> 0
I15: =SUM(D15:E15)-G15 -> 0 | M15: =D15+J15 -> 0 | N15: =E15+K15 -> 0 | O15: =G15+L15 -> 0 | P15: =M15+N15-O15 -> 0 | V15: =SUM(Q15:S15)-SUM(T15:U15) -> 0 | AB15: =Q15+W15 -> 0 | AC15: =R15+X15+S15+Y15 -> 0 | AD15: =T15+Z15+U15+AA15 -> 0 | AE15: =AB15+AC15-AD15 -> 0 | AK15: =SUM(AF15:AH15)-SUM(AI15:AJ15) -> 0 | AQ15: =AF15+AL15 -> 0 | AR15: =AG15+AM15+AH15+AN15 -> 0 | AS15: =AI15+AP15+AJ15+AO15 -> 0 | AT15: =AQ15+AR15-AS15 -> 0 | AU15: =D15-Q15-AF15 -> 0 | AV15: =M15-AB15-AQ15 -> 0 | AW15: =I15-V15-AK15 -> 0 | AX15: =P15-AE15-AT15 -> 0
I16: =SUM(D16:E16)-G16 -> 0 | M16: =D16+J16 -> 0 | N16: =E16+K16 -> 0 | O16: =G16+L16 -> 0 | P16: =M16+N16-O16 -> 0 | V16: =SUM(Q16:S16)-SUM(T16:U16) -> 0 | AB16: =Q16+W16 -> 0 | AC16: =R16+X16+S16+Y16 -> 0 | AD16: =T16+Z16+U16+AA16 -> 0 | AE16: =AB16+AC16-AD16 -> 0 | AK16: =SUM(AF16:AH16)-SUM(AI16:AJ16) -> 0 | AQ16: =AF16+AL16 -> 0 | AR16: =AG16+AM16+AH16+AN16 -> 0 | AS16: =AI16+AP16+AJ16+AO16 -> 0 | AT16: =AQ16+AR16-AS16 -> 0 | AU16: =D16-Q16-AF16 -> 0 | AV16: =M16-AB16-AQ16 -> 0 | AW16: =I16-V16-AK16 -> 0 | AX16: =P16-AE16-AT16 -> 0
I17: =SUM(D17:E17)-G17 -> 0 | M17: =D17+J17 -> 0 | N17: =E17+K17 -> 0 | O17: =G17+L17 -> 0 | P17: =M17+N17-O17 -> 0 | V17: =SUM(Q17:S17)-SUM(T17:U17) -> 0 | AB17: =Q17+W17 -> 0 | AC17: =R17+X17+S17+Y17 -> 0 | AD17: =T17+Z17+U17+AA17 -> 0 | AE17: =AB17+AC17-AD17 -> 0 | AK17: =SUM(AF17:AH17)-SUM(AI17:AJ17) -> 0 | AQ17: =AF17+AL17 -> 0 | AR17: =AG17+AM17+AH17+AN17 -> 0 | AS17: =AI17+AP17+AJ17+AO17 -> 0 | AT17: =AQ17+AR17-AS17 -> 0 | AU17: =D17-Q17-AF17 -> 0 | AV17: =M17-AB17-AQ17 -> 0 | AW17: =I17-V17-AK17 -> 0 | AX17: =P17-AE17-AT17 -> 0
I18: =SUM(D18:E18)-G18 -> 0 | M18: =D18+J18 -> 0 | N18: =E18+K18 -> 0 | O18: =G18+L18 -> 0 | P18: =M18+N18-O18 -> 0 | V18: =SUM(Q18:S18)-SUM(T18:U18) -> 0 | AB18: =Q18+W18 -> 0 | AC18: =R18+X18+S18+Y18 -> 0 | AD18: =T18+Z18+U18+AA18 -> 0 | AE18: =AB18+AC18-AD18 -> 0 | AK18: =SUM(AF18:AH18)-SUM(AI18:AJ18) -> 0 | AQ18: =AF18+AL18 -> 0 | AR18: =AG18+AM18+AH18+AN18 -> 0 | AS18: =AI18+AP18+AJ18+AO18 -> 0 | AT18: =AQ18+AR18-AS18 -> 0 | AU18: =D18-Q18-AF18 -> 0 | AV18: =M18-AB18-AQ18 -> 0 | AW18: =I18-V18-AK18 -> 0 | AX18: =P18-AE18-AT18 -> 0
I19: =SUM(D19:E19)-G19 -> 0 | M19: =D19+J19 -> 0 | N19: =E19+K19 -> 0 | O19: =G19+L19 -> 0 | P19: =M19+N19-O19 -> 0 | V19: =SUM(Q19:S19)-SUM(T19:U19) -> 0 | AB19: =Q19+W19 -> 0 | AC19: =R19+X19+S19+Y19 -> 0 | AD19: =T19+Z19+U19+AA19 -> 0 | AE19: =AB19+AC19-AD19 -> 0 | AK19: =SUM(AF19:AH19)-SUM(AI19:AJ19) -> 0 | AQ19: =AF19+AL19 -> 0 | AR19: =AG19+AM19+AH19+AN19 -> 0 | AS19: =AI19+AP19+AJ19+AO19 -> 0 | AT19: =AQ19+AR19-AS19 -> 0 | AU19: =D19-Q19-AF19 -> 0 | AV19: =M19-AB19-AQ19 -> 0 | AW19: =I19-V19-AK19 -> 0 | AX19: =P19-AE19-AT19 -> 0
I20: =SUM(D20:E20)-G20 -> 0 | M20: =D20+J20 -> 0 | N20: =E20+K20 -> 0 | O20: =G20+L20 -> 0 | P20: =M20+N20-O20 -> 0 | V20: =SUM(Q20:S20)-SUM(T20:U20) -> 0 | AB20: =Q20+W20 -> 0 | AC20: =R20+X20+S20+Y20 -> 0 | AD20: =T20+Z20+U20+AA20 -> 0 | AE20: =AB20+AC20-AD20 -> 0 | AK20: =SUM(AF20:AH20)-SUM(AI20:AJ20) -> 0 | AQ20: =AF20+AL20 -> 0 | AR20: =AG20+AM20+AH20+AN20 -> 0 | AS20: =AI20+AP20+AJ20+AO20 -> 0 | AT20: =AQ20+AR20-AS20 -> 0 | AU20: =D20-Q20-AF20 -> 0 | AV20: =M20-AB20-AQ20 -> 0 | AW20: =I20-V20-AK20 -> 0 | AX20: =P20-AE20-AT20 -> 0
I21: =SUM(D21:E21)-G21 -> 0 | M21: =D21+J21 -> 0 | N21: =E21+K21 -> 0 | O21: =G21+L21 -> 0 | P21: =M21+N21-O21 -> 0 | V21: =SUM(Q21:S21)-SUM(T21:U21) -> 0 | AB21: =Q21+W21 -> 0 | AC21: =R21+X21+S21+Y21 -> 0 | AD21: =T21+Z21+U21+AA21 -> 0 | AE21: =AB21+AC21-AD21 -> 0 | AK21: =SUM(AF21:AH21)-SUM(AI21:AJ21) -> 0 | AQ21: =AF21+AL21 -> 0 | AR21: =AG21+AM21+AH21+AN21 -> 0 | AS21: =AI21+AP21+AJ21+AO21 -> 0 | AT21: =AQ21+AR21-AS21 -> 0 | AU21: =D21-Q21-AF21 -> 0 | AV21: =M21-AB21-AQ21 -> 0 | AW21: =I21-V21-AK21 -> 0 | AX21: =P21-AE21-AT21 -> 0
I22: =SUM(D22:E22)-G22 -> 0 | M22: =D22+J22 -> 0 | N22: =E22+K22 -> 0 | O22: =G22+L22 -> 0 | P22: =M22+N22-O22 -> 0 | V22: =SUM(Q22:S22)-SUM(T22:U22) -> 0 | AB22: =Q22+W22 -> 0 | AC22: =R22+X22+S22+Y22 -> 0 | AD22: =T22+Z22+U22+AA22 -> 0 | AE22: =AB22+AC22-AD22 -> 0 | AK22: =SUM(AF22:AH22)-SUM(AI22:AJ22) -> 0 | AQ22: =AF22+AL22 -> 0 | AR22: =AG22+AM22+AH22+AN22 -> 0 | AS22: =AI22+AP22+AJ22+AO22 -> 0 | AT22: =AQ22+AR22-AS22 -> 0 | AU22: =D22-Q22-AF22 -> 0 | AV22: =M22-AB22-AQ22 -> 0 | AW22: =I22-V22-AK22 -> 0 | AX22: =P22-AE22-AT22 -> 0
I23: =SUM(D23:E23)-G23 -> 0 | M23: =D23+J23 -> 0 | N23: =E23+K23 -> 0 | O23: =G23+L23 -> 0 | P23: =M23+N23-O23 -> 0 | V23: =SUM(Q23:S23)-SUM(T23:U23) -> 0 | AB23: =Q23+W23 -> 0 | AC23: =R23+X23+S23+Y23 -> 0 | AD23: =T23+Z23+U23+AA23 -> 0 | AE23: =AB23+AC23-AD23 -> 0 | AK23: =SUM(AF23:AH23)-SUM(AI23:AJ23) -> 0 | AQ23: =AF23+AL23 -> 0 | AR23: =AG23+AM23+AH23+AN23 -> 0 | AS23: =AI23+AP23+AJ23+AO23 -> 0 | AT23: =AQ23+AR23-AS23 -> 0 | AU23: =D23-Q23-AF23 -> 0 | AV23: =M23-AB23-AQ23 -> 0 | AW23: =I23-V23-AK23 -> 0 | AX23: =P23-AE23-AT23 -> 0
I24: =SUM(D24:E24)-G24 -> 0 | M24: =D24+J24 -> 0 | N24: =E24+K24 -> 0 | O24: =G24+L24 -> 0 | P24: =M24+N24-O24 -> 0 | V24: =SUM(Q24:S24)-SUM(T24:U24) -> 0 | AB24: =Q24+W24 -> 0 | AC24: =R24+X24+S24+Y24 -> 0 | AD24: =T24+Z24+U24+AA24 -> 0 | AE24: =AB24+AC24-AD24 -> 0 | AK24: =SUM(AF24:AH24)-SUM(AI24:AJ24) -> 0 | AQ24: =AF24+AL24 -> 0 | AR24: =AG24+AM24+AH24+AN24 -> 0 | AS24: =AI24+AP24+AJ24+AO24 -> 0 | AT24: =AQ24+AR24-AS24 -> 0 | AU24: =D24-Q24-AF24 -> 0 | AV24: =M24-AB24-AQ24 -> 0 | AW24: =I24-V24-AK24 -> 0 | AX24: =P24-AE24-AT24 -> 0
... I36: =SUM(D36:E36)-G36 -> 0 | M36: =D36+J36 -> 0 | N36: =E36+K36 -> 0 | O36: =G36+L36 -> 0 | P36: =M36+N36-O36 -> 0 | V36: =SUM(Q36:S36)-SUM(T36:U36) -> 0 | AB36: =Q36+W36 -> 0 | AC36: =R36+X36+S36+Y36 -> 0 | AD36: =T36+Z36+U36+AA36 -> 0 | AE36: =AB36+AC36-AD36 -> 0 | AK36: =SUM(AF36:AH36)-SUM(AI36:AJ36) -> 0 | AQ36: =AF36+AL36 -> 0 | AR36: =AG36+AM36+AH36+AN36 -> 0 | AS36: =AI36+AP36+AJ36+AO36 -> 0 | AT36: =AQ36+AR36-AS36 -> 0 | AU36: =D36-Q36-AF36 -> 0 | AV36: =M36-AB36-AQ36 -> 0 | AW36: =I36-V36-AK36 -> 0 | AX36: =P36-AE36-AT36 -> 0
A37: 合计 | D37: =SUM(D13:D36) -> 0 | E37: =SUM(E13:E36) -> 0 | G37: =SUM(G13:G36) -> 0 | I37: =SUM(I13:I36) -> 0 | J37: =SUM(J13:J36) -> 0 | K37: =SUM(K13:K36) -> 0 | L37: =SUM(L13:L36) -> 0 | M37: =SUM(M13:M36) -> 0 | N37: =SUM(N13:N36) -> 0 | O37: =SUM(O13:O36) -> 0 | P37: =SUM(P13:P36) -> 0 | ... AX37: =SUM(AX13:AX36) -> 0
A38: 其中：
A39: =底稿目录!A9 -> 种植业 | D39: =SUMPRODUCT(($A$13:$A$36=$A39)*(D$13:D$36)) -> 0 | E39: =SUMPRODUCT(($A$13:$A$36=$A39)*(E$13:E$36)) -> 0 | G39: =SUMPRODUCT(($A$13:$A$36=$A39)*(G$13:G$36)) -> 0 | I39: =SUMPRODUCT(($A$13:$A$36=$A39)*(I$13:I$36)) -> 0 | J39: =SUMPRODUCT(($A$13:$A$36=$A39)*(J$13:J$36)) -> 0 | K39: =SUMPRODUCT(($A$13:$A$36=$A39)*(K$13:K$36)) -> 0 | L39: =SUMPRODUCT(($A$13:$A$36=$A39)*(L$13:L$36)) -> 0 | M39: =SUMPRODUCT(($A$13:$A$36=$A39)*(M$13:M$36)) -> 0 | N39: =SUMPRODUCT(($A$13:$A$36=$A39)*(N$13:N$36)) -> 0 | O39: =SUMPRODUCT(($A$13:$A$36=$A39)*(O$13:O$36)) -> 0 | P39: =SUMPRODUCT(($A$13:$A$36=$A39)*(P$13:P$36)) -> 0 | ... AX39: =SUMPRODUCT(($A$13:$A$36=$A39)*(AX$13:AX$36)) -> 0
A40: =底稿目录!A10 -> 畜牧养殖业 | D40: =SUMPRODUCT(($A$13:$A$36=$A40)*(D$13:D$36)) -> 0 | E40: =SUMPRODUCT(($A$13:$A$36=$A40)*(E$13:E$36)) -> 0 | G40: =SUMPRODUCT(($A$13:$A$36=$A40)*(G$13:G$36)) -> 0 | I40: =SUMPRODUCT(($A$13:$A$36=$A40)*(I$13:I$36)) -> 0 | J40: =SUMPRODUCT(($A$13:$A$36=$A40)*(J$13:J$36)) -> 0 | K40: =SUMPRODUCT(($A$13:$A$36=$A40)*(K$13:K$36)) -> 0 | L40: =SUMPRODUCT(($A$13:$A$36=$A40)*(L$13:L$36)) -> 0 | M40: =SUMPRODUCT(($A$13:$A$36=$A40)*(M$13:M$36)) -> 0 | N40: =SUMPRODUCT(($A$13:$A$36=$A40)*(N$13:N$36)) -> 0 | O40: =SUMPRODUCT(($A$13:$A$36=$A40)*(O$13:O$36)) -> 0 | P40: =SUMPRODUCT(($A$13:$A$36=$A40)*(P$13:P$36)) -> 0 | ... AX40: =SUMPRODUCT(($A$13:$A$36=$A40)*(AX$13:AX$36)) -> 0
A41: =底稿目录!A11 -> 林业 | D41: =SUMPRODUCT(($A$13:$A$36=$A41)*(D$13:D$36)) -> 0 | E41: =SUMPRODUCT(($A$13:$A$36=$A41)*(E$13:E$36)) -> 0 | G41: =SUMPRODUCT(($A$13:$A$36=$A41)*(G$13:G$36)) -> 0 | I41: =SUMPRODUCT(($A$13:$A$36=$A41)*(I$13:I$36)) -> 0 | J41: =SUMPRODUCT(($A$13:$A$36=$A41)*(J$13:J$36)) -> 0 | K41: =SUMPRODUCT(($A$13:$A$36=$A41)*(K$13:K$36)) -> 0 | L41: =SUMPRODUCT(($A$13:$A$36=$A41)*(L$13:L$36)) -> 0 | M41: =SUMPRODUCT(($A$13:$A$36=$A41)*(M$13:M$36)) -> 0 | N41: =SUMPRODUCT(($A$13:$A$36=$A41)*(N$13:N$36)) -> 0 | O41: =SUMPRODUCT(($A$13:$A$36=$A41)*(O$13:O$36)) -> 0 | P41: =SUMPRODUCT(($A$13:$A$36=$A41)*(P$13:P$36)) -> 0 | ... AX41: =SUMPRODUCT(($A$13:$A$36=$A41)*(AX$13:AX$36)) -> 0
A42: =底稿目录!A12 -> 水产业 | D42: =SUMPRODUCT(($A$13:$A$36=$A42)*(D$13:D$36)) -> 0 | E42: =SUMPRODUCT(($A$13:$A$36=$A42)*(E$13:E$36)) -> 0 | G42: =SUMPRODUCT(($A$13:$A$36=$A42)*(G$13:G$36)) -> 0 | I42: =SUMPRODUCT(($A$13:$A$36=$A42)*(I$13:I$36)) -> 0 | J42: =SUMPRODUCT(($A$13:$A$36=$A42)*(J$13:J$36)) -> 0 | K42: =SUMPRODUCT(($A$13:$A$36=$A42)*(K$13:K$36)) -> 0 | L42: =SUMPRODUCT(($A$13:$A$36=$A42)*(L$13:L$36)) -> 0 | M42: =SUMPRODUCT(($A$13:$A$36=$A42)*(M$13:M$36)) -> 0 | N42: =SUMPRODUCT(($A$13:$A$36=$A42)*(N$13:N$36)) -> 0 | O42: =SUMPRODUCT(($A$13:$A$36=$A42)*(O$13:O$36)) -> 0 | P42: =SUMPRODUCT(($A$13:$A$36=$A42)*(P$13:P$36)) -> 0 | ... AX42: =SUMPRODUCT(($A$13:$A$36=$A42)*(AX$13:AX$36)) -> 0
A43: =底稿目录!A13 -> …… | D43: =SUMPRODUCT(($A$13:$A$36=$A43)*(D$13:D$36)) -> 0 | E43: =SUMPRODUCT(($A$13:$A$36=$A43)*(E$13:E$36)) -> 0 | G43: =SUMPRODUCT(($A$13:$A$36=$A43)*(G$13:G$36)) -> 0 | I43: =SUMPRODUCT(($A$13:$A$36=$A43)*(I$13:I$36)) -> 0 | J43: =SUMPRODUCT(($A$13:$A$36=$A43)*(J$13:J$36)) -> 0 | K43: =SUMPRODUCT(($A$13:$A$36=$A43)*(K$13:K$36)) -> 0 | L43: =SUMPRODUCT(($A$13:$A$36=$A43)*(L$13:L$36)) -> 0 | M43: =SUMPRODUCT(($A$13:$A$36=$A43)*(M$13:M$36)) -> 0 | N43: =SUMPRODUCT(($A$13:$A$36=$A43)*(N$13:N$36)) -> 0 | O43: =SUMPRODUCT(($A$13:$A$36=$A43)*(O$13:O$36)) -> 0 | P43: =SUMPRODUCT(($A$13:$A$36=$A43)*(P$13:P$36)) -> 0 | ... AX43: =SUMPRODUCT(($A$13:$A$36=$A43)*(AX$13:AX$36)) -> 0
A44: 三、审计说明：
A47: 四、审计结论
A53: 提示：
A54: 1、本科目核算为产出农产品、提供劳务或出租等目的而持有的生物资产，包括经济林、薪炭林、产畜和役畜等
A55: 2.审计说明可以概述:(1)程序的测试情况、结果;(2)拟调整事项及其调整分录、未调整事项及其影响，审计范围受到限制情况及其影响。
A56: 3.审计结论可参考：A、未见异常。 B、除上述重大不符事项应当作为调整事项予以调整外，其余未见异常。 C、由于存在以下重大未调整事项(或审计范围受到限制无法获取充分、适当证据)，不可确认。

Sheet 明细表（公允价值模式）H7-2
A1: 致同会计师事务所 | Q1: 致同会计师事务所
A2: 生产性生物资产明细表（公允价值模式） | Q2: 生产性生物资产明细表（公允价值模式）
A3: =底稿目录!A2 -> 被审计单位： | H3: =底稿目录!A4 -> 编制人： | L3: =底稿目录!A6 -> 编制日期： | O3: 索引号： | P3: H7-2 | U3: =底稿目录!A4 -> 编制人： | X3: =底稿目录!A6 -> 编制日期： | AA3: 索引号： | AB3: H7-2
A4: =底稿目录!A3 -> 截止日： | H4: =底稿目录!A5 -> 复核人： | L4: =底稿目录!A7 -> 复核日期： | O4: 页 次： | U4: =底稿目录!A5 -> 复核人： | X4: =底稿目录!A7 -> 复核日期： | AA4: 页 次：
A5: 一、审计目标:
A6: 1. 资产负债表中记录的生产性生物资产是存在的，且已记录于恰当的账户；2. 所有应记录的生产性生物资产均已记录，所有应当包括在财务报表中的相关披露均已包括；
A7: 3. 生产性生物资产以恰当的金额包括在财务报表中，与之相关的计价或分摊调整已恰当记录，相关披露已得到恰当计量和描述.
A8: 二、审计过程：
A9: 生产性生物资产类别 | B9: 生产性生物资产编号 | C9: 生产性生物资产名称 | D9: 生产性生物资产原值 | Q9: 公允价值变动 | Y9: 期初净值 | Z9: 期末净值 | AA9: 是否有权属证明 | AB9: 是否抵押受限
D10: 未审数 | J10: 期初调整 | K10: 账项调整 | M10: 审定数 | Q10: 未审数 | T10: 期初调整 | U10: 本期变动调整 | V10: 审定数
D11: 期初余额 | E11: 本年增加 | F11: 增加方式 | G11: 本年减少 | H11: 减少方式 | I11: 期末余额 | K11: 本期增加 | L11: 本期减少 | M11: 期初余额 | N11: 本年增加 | O11: 本年减少 | P11: 期末余额 | Q11: 期初余额 | R11: 本年变动 | S11: 期末余额 | V11: 期初余额 | W11: 本年变动 | X11: 期末余额
I12: =D12+E12-G12 -> 0 | M12: =D12+J12 -> 0 | N12: =E12+K12 -> 0 | O12: =G12+L12 -> 0 | P12: =M12+N12-O12 -> 0 | S12: =Q12+R12 -> 0 | V12: =Q12+T12 -> 0 | W12: =R12+U12 -> 0 | X12: =V12+W12 -> 0 | Y12: =M12+V12 -> 0 | Z12: =P12+X12 -> 0
I13: =D13+E13-G13 -> 0 | M13: =D13+J13 -> 0 | N13: =E13+K13 -> 0 | O13: =G13+L13 -> 0 | P13: =M13+N13-O13 -> 0 | S13: =Q13+R13 -> 0 | V13: =Q13+T13 -> 0 | W13: =R13+U13 -> 0 | X13: =V13+W13 -> 0 | Y13: =M13+V13 -> 0 | Z13: =P13+X13 -> 0
I14: =D14+E14-G14 -> 0 | M14: =D14+J14 -> 0 | N14: =E14+K14 -> 0 | O14: =G14+L14 -> 0 | P14: =M14+N14-O14 -> 0 | S14: =Q14+R14 -> 0 | V14: =Q14+T14 -> 0 | W14: =R14+U14 -> 0 | X14: =V14+W14 -> 0 | Y14: =M14+V14 -> 0 | Z14: =P14+X14 -> 0
I15: =D15+E15-G15 -> 0 | M15: =D15+J15 -> 0 | N15: =E15+K15 -> 0 | O15: =G15+L15 -> 0 | P15: =M15+N15-O15 -> 0 | S15: =Q15+R15 -> 0 | V15: =Q15+T15 -> 0 | W15: =R15+U15 -> 0 | X15: =V15+W15 -> 0 | Y15: =M15+V15 -> 0 | Z15: =P15+X15 -> 0
I16: =D16+E16-G16 -> 0 | M16: =D16+J16 -> 0 | N16: =E16+K16 -> 0 | O16: =G16+L16 -> 0 | P16: =M16+N16-O16 -> 0 | S16: =Q16+R16 -> 0 | V16: =Q16+T16 -> 0 | W16: =R16+U16 -> 0 | X16: =V16+W16 -> 0 | Y16: =M16+V16 -> 0 | Z16: =P16+X16 -> 0
I17: =D17+E17-G17 -> 0 | M17: =D17+J17 -> 0 | N17: =E17+K17 -> 0 | O17: =G17+L17 -> 0 | P17: =M17+N17-O17 -> 0 | S17: =Q17+R17 -> 0 | V17: =Q17+T17 -> 0 | W17: =R17+U17 -> 0 | X17: =V17+W17 -> 0 | Y17: =M17+V17 -> 0 | Z17: =P17+X17 -> 0
I18: =D18+E18-G18 -> 0 | M18: =D18+J18 -> 0 | N18: =E18+K18 -> 0 | O18: =G18+L18 -> 0 | P18: =M18+N18-O18 -> 0 | S18: =Q18+R18 -> 0 | V18: =Q18+T18 -> 0 | W18: =R18+U18 -> 0 | X18: =V18+W18 -> 0 | Y18: =M18+V18 -> 0 | Z18: =P18+X18 -> 0
I19: =D19+E19-G19 -> 0 | M19: =D19+J19 -> 0 | N19: =E19+K19 -> 0 | O19: =G19+L19 -> 0 | P19: =M19+N19-O19 -> 0 | S19: =Q19+R19 -> 0 | V19: =Q19+T19 -> 0 | W19: =R19+U19 -> 0 | X19: =V19+W19 -> 0 | Y19: =M19+V19 -> 0 | Z19: =P19+X19 -> 0
I20: =D20+E20-G20 -> 0 | M20: =D20+J20 -> 0 | N20: =E20+K20 -> 0 | O20: =G20+L20 -> 0 | P20: =M20+N20-O20 -> 0 | S20: =Q20+R20 -> 0 | V20: =Q20+T20 -> 0 | W20: =R20+U20 -> 0 | X20: =V20+W20 -> 0 | Y20: =M20+V20 -> 0 | Z20: =P20+X20 -> 0
I21: =D21+E21-G21 -> 0 | M21: =D21+J21 -> 0 | N21: =E21+K21 -> 0 | O21: =G21+L21 -> 0 | P21: =M21+N21-O21 -> 0 | S21: =Q21+R21 -> 0 | V21: =Q21+T21 -> 0 | W21: =R21+U21 -> 0 | X21: =V21+W21 -> 0 | Y21: =M21+V21 -> 0 | Z21: =P21+X21 -> 0
I22: =D22+E22-G22 -> 0 | M22: =D22+J22 -> 0 | N22: =E22+K22 -> 0 | O22: =G22+L22 -> 0 | P22: =M22+N22-O22 -> 0 | S22: =Q22+R22 -> 0 | V22: =Q22+T22 -> 0 | W22: =R22+U22 -> 0 | X22: =V22+W22 -> 0 | Y22: =M22+V22 -> 0 | Z22: =P22+X22 -> 0
I23: =D23+E23-G23 -> 0 | M23: =D23+J23 -> 0 | N23: =E23+K23 -> 0 | O23: =G23+L23 -> 0 | P23: =M23+N23-O23 -> 0 | S23: =Q23+R23 -> 0 | V23: =Q23+T23 -> 0 | W23: =R23+U23 -> 0 | X23: =V23+W23 -> 0 | Y23: =M23+V23 -> 0 | Z23: =P23+X23 -> 0
... I36: =D36+E36-G36 -> 0 | M36: =D36+J36 -> 0 | N36: =E36+K36 -> 0 | O36: =G36+L36 -> 0 | P36: =M36+N36-O36 -> 0 | S36: =Q36+R36 -> 0 | V36: =Q36+T36 -> 0 | W36: =R36+U36 -> 0 | X36: =V36+W36 -> 0 | Y36: =M36+V36 -> 0 | Z36: =P36+X36 -> 0
A37: 合计 | D37: =SUM(D12:D36) -> 0 | E37: =SUM(E12:E36) -> 0 | G37: =SUM(G12:G36) -> 0 | I37: =SUM(I12:I36) -> 0 | J37: =SUM(J12:J36) -> 0 | K37: =SUM(K12:K36) -> 0 | L37: =SUM(L12:L36) -> 0 | M37: =SUM(M12:M36) -> 0 | N37: =SUM(N12:N36) -> 0 | O37: =SUM(O12:O36) -> 0 | P37: =SUM(P12:P36) -> 0 | ... Z37: =SUM(Z12:Z36) -> 0
A38: 其中：
A39: =底稿目录!A9 -> 种植业 | D39: =SUMPRODUCT(($A$12:$A$36=$A39)*(D$12:D$36)) -> 0 | E39: =SUMPRODUCT(($A$12:$A$36=$A39)*(E$12:E$36)) -> 0 | G39: =SUMPRODUCT(($A$12:$A$36=$A39)*(G$12:G$36)) -> 0 | I39: =SUMPRODUCT(($A$12:$A$36=$A39)*(I$12:I$36)) -> 0 | J39: =SUMPRODUCT(($A$12:$A$36=$A39)*(J$12:J$36)) -> 0 | K39: =SUMPRODUCT(($A$12:$A$36=$A39)*(K$12:K$36)) -> 0 | L39: =SUMPRODUCT(($A$12:$A$36=$A39)*(L$12:L$36)) -> 0 | M39: =SUMPRODUCT(($A$12:$A$36=$A39)*(M$12:M$36)) -> 0 | N39: =SUMPRODUCT(($A$12:$A$36=$A39)*(N$12:N$36)) -> 0 | O39: =SUMPRODUCT(($A$12:$A$36=$A39)*(O$12:O$36)) -> 0 | P39: =SUMPRODUCT(($A$12:$A$36=$A39)*(P$12:P$36)) -> 0 | ... Z39: =SUMPRODUCT(($A$12:$A$36=$A39)*(Z$12:Z$36)) -> 0
A40: =底稿目录!A10 -> 畜牧养殖业 | D40: =SUMPRODUCT(($A$12:$A$36=$A40)*(D$12:D$36)) -> 0 | E40: =SUMPRODUCT(($A$12:$A$36=$A40)*(E$12:E$36)) -> 0 | G40: =SUMPRODUCT(($A$12:$A$36=$A40)*(G$12:G$36)) -> 0 | I40: =SUMPRODUCT(($A$12:$A$36=$A40)*(I$12:I$36)) -> 0 | J40: =SUMPRODUCT(($A$12:$A$36=$A40)*(J$12:J$36)) -> 0 | K40: =SUMPRODUCT(($A$12:$A$36=$A40)*(K$12:K$36)) -> 0 | L40: =SUMPRODUCT(($A$12:$A$36=$A40)*(L$12:L$36)) -> 0 | M40: =SUMPRODUCT(($A$12:$A$36=$A40)*(M$12:M$36)) -> 0 | N40: =SUMPRODUCT(($A$12:$A$36=$A40)*(N$12:N$36)) -> 0 | O40: =SUMPRODUCT(($A$12:$A$36=$A40)*(O$12:O$36)) -> 0 | P40: =SUMPRODUCT(($A$12:$A$36=$A40)*(P$12:P$36)) -> 0 | ... Z40: =SUMPRODUCT(($A$12:$A$36=$A40)*(Z$12:Z$36)) -> 0
A41: =底稿目录!A11 -> 林业 | D41: =SUMPRODUCT(($A$12:$A$36=$A41)*(D$12:D$36)) -> 0 | E41: =SUMPRODUCT(($A$12:$A$36=$A41)*(E$12:E$36)) -> 0 | G41: =SUMPRODUCT(($A$12:$A$36=$A41)*(G$12:G$36)) -> 0 | I41: =SUMPRODUCT(($A$12:$A$36=$A41)*(I$12:I$36)) -> 0 | J41: =SUMPRODUCT(($A$12:$A$36=$A41)*(J$12:J$36)) -> 0 | K41: =SUMPRODUCT(($A$12:$A$36=$A41)*(K$12:K$36)) -> 0 | L41: =SUMPRODUCT(($A$12:$A$36=$A41)*(L$12:L$36)) -> 0 | M41: =SUMPRODUCT(($A$12:$A$36=$A41)*(M$12:M$36)) -> 0 | N41: =SUMPRODUCT(($A$12:$A$36=$A41)*(N$12:N$36)) -> 0 | O41: =SUMPRODUCT(($A$12:$A$36=$A41)*(O$12:O$36)) -> 0 | P41: =SUMPRODUCT(($A$12:$A$36=$A41)*(P$12:P$36)) -> 0 | ... Z41: =SUMPRODUCT(($A$12:$A$36=$A41)*(Z$12:Z$36)) -> 0
A42: =底稿目录!A12 -> 水产业 | D42: =SUMPRODUCT(($A$12:$A$36=$A42)*(D$12:D$36)) -> 0 | E42: =SUMPRODUCT(($A$12:$A$36=$A42)*(E$12:E$36)) -> 0 | G42: =SUMPRODUCT(($A$12:$A$36=$A42)*(G$12:G$36)) -> 0 | I42: =SUMPRODUCT(($A$12:$A$36=$A42)*(I$12:I$36)) -> 0 | J42: =SUMPRODUCT(($A$12:$A$36=$A42)*(J$12:J$36)) -> 0 | K42: =SUMPRODUCT(($A$12:$A$36=$A42)*(K$12:K$36)) -> 0 | L42: =SUMPRODUCT(($A$12:$A$36=$A42)*(L$12:L$36)) -> 0 | M42: =SUMPRODUCT(($A$12:$A$36=$A42)*(M$12:M$36)) -> 0 | N42: =SUMPRODUCT(($A$12:$A$36=$A42)*(N$12:N$36)) -> 0 | O42: =SUMPRODUCT(($A$12:$A$36=$A42)*(O$12:O$36)) -> 0 | P42: =SUMPRODUCT(($A$12:$A$36=$A42)*(P$12:P$36)) -> 0 | ... Z42: =SUMPRODUCT(($A$12:$A$36=$A42)*(Z$12:Z$36)) -> 0
A43: =底稿目录!A13 -> …… | D43: =SUMPRODUCT(($A$12:$A$36=$A43)*(D$12:D$36)) -> 0 | E43: =SUMPRODUCT(($A$12:$A$36=$A43)*(E$12:E$36)) -> 0 | G43: =SUMPRODUCT(($A$12:$A$36=$A43)*(G$12:G$36)) -> 0 | I43: =SUMPRODUCT(($A$12:$A$36=$A43)*(I$12:I$36)) -> 0 | J43: =SUMPRODUCT(($A$12:$A$36=$A43)*(J$12:J$36)) -> 0 | K43: =SUMPRODUCT(($A$12:$A$36=$A43)*(K$12:K$36)) -> 0 | L43: =SUMPRODUCT(($A$12:$A$36=$A43)*(L$12:L$36)) -> 0 | M43: =SUMPRODUCT(($A$12:$A$36=$A43)*(M$12:M$36)) -> 0 | N43: =SUMPRODUCT(($A$12:$A$36=$A43)*(N$12:N$36)) -> 0 | O43: =SUMPRODUCT(($A$12:$A$36=$A43)*(O$12:O$36)) -> 0 | P43: =SUMPRODUCT(($A$12:$A$36=$A43)*(P$12:P$36)) -> 0 | ... Z43: =SUMPRODUCT(($A$12:$A$36=$A43)*(Z$12:Z$36)) -> 0
A45: 三、审计说明
A47: 四、审计结论
A49: 提示：
A50: 1、本科目核算为产出农产品、提供劳务或出租等目的而持有的生物资产，包括经济林、薪炭林、产畜和役畜等
A51: 2.审计说明可以概述:(1)程序的测试情况、结果;(2)拟调整事项及其调整分录、未调整事项及其影响，审计范围受到限制情况及其影响。
A52: 3.审计结论可参考：A、未见异常。 B、除上述重大不符事项应当作为调整事项予以调整外，其余未见异常。 C、由于存在以下重大未调整事项(或审计范围受到限制无法获取充分、适当证据)，不可确认。

Sheet 调整分录汇总H7-3
A1: 致同会计师事务所
A2: 生物性生物资产调整分录汇总表
A3: =底稿目录!A2 -> 被审计单位： | D3: =底稿目录!A4 -> 编制人： | G3: =底稿目录!A6 -> 编制日期： | I3: 索引号： | J3: H7-3
A4: =底稿目录!A3 -> 截止日： | D4: =底稿目录!A5 -> 复核人： | G4: =底稿目录!A7 -> 复核日期： | I4: 页 次：
A5: 调整事项说明 | B5: 类别（报表调整/账项调整/其他） | C5: 报表项目 | D5: 科目名称 | E5: 附注项目 | F5: …… | G5: 借方调整金额 | H5: 贷方调整金额 | I5: 索引 | J5: 备注
A24: 提示：本底稿适用于调整分录较多、较复杂的项目，且仅列示与本报表项目相关的审计调整。项目组可根据项目实际情况选择是否使用该底稿。

Sheet 会计政策估计检查表H7-4
A1: 致同会计师事务所
A2: 生产性生物资产相关会计政策/估计检查表
A3: =底稿目录!A2 -> 被审计单位： | E3: =底稿目录!A4 -> 编制人： | H3: =底稿目录!A6 -> 编制日期： | J3: 索引号： | K3: H7-4
A4: =底稿目录!A3 -> 截止日： | E4: =底稿目录!A5 -> 复核人： | H4: =底稿目录!A7 -> 复核日期： | J4: 页 次：
A5: 一、审计目标：
A6: 1.所有应记录的生产性生物资产均已记录，所有应当包括在财务报表中的相关披露均已包括；
A7: 2.生产性生物资产以恰当的金额包括在财务报表中，与之相关的计价或分摊调整已恰当记录，相关披露已得到恰当计量和描述 。
A8: 二、审计过程：
B10: （一）被审计单位对生产性生物资产的计量属性的选择及其原因：
B12: （二）成本模式下被审计单位的生产性生物资产折旧政策：
A13: 序号 | B13: 类别 | C13: 折旧年限 | D13: 折旧方法 | E13: 残值率 | F13: 是否符合实际经营情况和会计准则的要求 | G13: 是否与相关资产所包含的经济利益预期实现方式相一致 | H13: 与同行业公司相比，会计政策是否合理 | I13: 是否存在会计政策/会计估计变更 | J13: 会计政策/会计估计变更是否合理 | K13: 备注
A14: 1 | B14: 种植业
A15: 2 | B15: 畜牧养殖业
A16: 3 | B16: 林业
A17: 4 | B17: 水产业
A18: 5 | B18: ……
B19: （三）成本模式下同行业其他公司的生产性生物资产折旧政策
A20: 序号 | B20: 类别 | C20: 同行业公司1 | F20: 同行业公司2 | I20: 同行业公司3
C21: 折旧年限 | D21: 折旧方法 | E21: 残值率 | F21: 折旧年限 | G21: 折旧方法 | H21: 残值率 | I21: 折旧年限 | J21: 折旧方法 | K21: 残值率
A22: 1 | B22: 种植业
A23: 2 | B23: 畜牧养殖业
A24: 3 | B24: 林业
A25: 4 | B25: 水产业
A26: 5 | B26: ……
B28: （四）公允价值模式下，期末生产性生物资产公允价值的取得：
B31: （五）如本期存在会计估计变更，原会计估计如下：
A32: 序号 | B32: 类别 | C32: 使用寿命 | D32: 摊销方法 | E32: 残值率
A33: 1 | B33: 种植业
A34: 2 | B34: 畜牧养殖业
A35: 3 | B35: 林业
A36: 4 | B36: 水产业
A37: 5 | B37: ……
A39: 三、审计说明：
A42: 四、审计结论：

Sheet 分析表H7-5
A1: 致同会计师事务所
A2: 生产性生物资产分析表
A3: =底稿目录!A2 -> 被审计单位： | C3: =底稿目录!A4 -> 编制人： | D3: =底稿目录!A6 -> 编制日期： | E3: 索引号： | F3: H7-5
A4: =底稿目录!A3 -> 截止日： | C4: =底稿目录!A5 -> 复核人： | D4: =底稿目录!A7 -> 复核日期： | E4: 页 次：
A5: 一、审计目标:
A6: 1. 资产负债表中记录的生产性生物资产是存在的，且已记录于恰当的账户；2. 所有应记录的生产性生物资产均已记录，所有应当包括在财务报表中的相关披露均已包括。
A7: 3. 生产性生物资产以恰当的金额包括在财务报表中，与之相关的计价或分摊调整已恰当记录，相关披露已得到恰当计量和描述
A8: 二、审计过程：
A9: 序号 | B9: 比例 | C9: 2025年 | D9: 2024年 | E9: 变动 | F9: 变动原因及合理性解释
A10: 1 | B10: 生产性生物资产原值 | E10: =(C10-D10)/D10 -> #DIV/0!
A11: 2 | B11: 累计折旧 | E11: =(C11-D11)/D11 -> #DIV/0!
A12: 3 | B12: 本期计提折旧/生产性生物资产原值 | E12: =(C12-D12)/D12 -> #DIV/0!
A13: 4 | B13: 累计折旧/生产性生物资产原值 | E13: =(C13-D13)/D13 -> #DIV/0!
A14: 5 | B14: 生产性生物资产减值准备/生产性生物资产原值 | E14: =(C14-D14)/D14 -> #DIV/0!
A15: 6 | B15: 主要类别生产性生物资产原值/生产性生物资产原值 | E15: =(C15-D15)/D15 -> #DIV/0!
A16: 7 | B16: 生产性生物资产净值/总资产 | E16: =(C16-D16)/D16 -> #DIV/0!
A17: 8 | B17: 生产性生物资产周转率 | E17: =(C17-D17)/D17 -> #DIV/0!
A18: 9 | B18: 生产性生物资产原值/本期产量 | E18: =(C18-D18)/D18 -> #DIV/0!
A19: 10 | B19: 生产性生物资产养殖成本÷生产性生物资产原值 | E19: =(C19-D19)/D19 -> #DIV/0!
A20: 11 | B20: 主营业务收入/生产性生物资产原值 | E20: =(C20-D20)/D20 -> #DIV/0!
A21: 12 | B21: 生产性生物资产管护费 | E21: =(C21-D21)/D21 -> #DIV/0!
... A24: 15 | B24: 生产性生物资产管护费/费用总额 | E24: =(C24-D24)/D24 -> #DIV/0!
A25: 三、审计说明：
A29: 四、审计结论：
A32: 提示：
A33: 1、分析生产性生物资产的构成及其增减变动情况、增减变动原因，与现金流量表等相关信息交叉复核，检查生产性生物资产相关金额的合理性和准确性；
A34: 2、分析本期末生产性生物资产减值准备数额占期末生产性生物资产原价的比率，并与期初数比较。

Sheet 增加检查表（成本模式）H7-6
A1: 致同会计师事务所
A2: 增加检查表（成本模式）
A3: =底稿目录!A2 -> 被审计单位： | F3: =底稿目录!A4 -> 编制人： | J3: =底稿目录!A6 -> 编制日期： | T3: 索引号： | U3: H7-6
A4: =底稿目录!A3 -> 截止日： | F4: =底稿目录!A5 -> 复核人： | J4: =底稿目录!A7 -> 复核日期： | T4: 页 次：
A5: 一、审计目标：1.资产负债表中记录的生产性生物资产是存在的，且已记录于恰当的账户；2.所有应记录的生产性生物资产均已记录，所有应当包括在财务报表中的相关披露均已包括；3.记录的生产性生物资产由被审计单位拥有或控制；4.生产性生物资产以恰当的金额包括在财务报表中，与之相关的计价或分摊调整已恰当记录，相关披露已得到恰当计量和描述。
A6: 二、样本选取标准与规模：
A7: 测试总体： | B7: 如生产性生物资产借方发生额所有凭证共XX笔金额XX | I7: 特定样本： | J7: XX金额以上（大额）、关联方/关联交易形成的款项、XX异常款项全部测试，共XX笔；
A8: 抽样总体： | B8: 测试总体扣除特定样本以外的样本，共XX笔、金额XX | I8: 确定的抽样样本量： | K8: 抽取XX笔 | L8: （如果使用了样本计算器计算样本量，样本量计算过程见<XX>底稿）
A9: 抽样方法： | B9: 随机选样/系统选样/货币单元抽样/随意选样（非统计抽样适用） | I9: 抽样过程： | J9: 使用IDEA（XX抽样工具）选择XX数量、金额XX的样本进行测试，抽样工具中的样本选择过程和结果见<XX>底稿
A10: 三、测试过程：
A11: 测试内容说明：1.原始凭证是否齐全； 2.记账凭证与原始凭证是否相符；3.账务处理是否正确；4.是否记录于恰当的会计期间；5.……
A12: 序号 | B12: 生产性生物资产类别 | C12: 生产性生物资产编号 | D12: 生产性生物资产名称 | E12: 增加日期 | F12: 增加方式 | G12: 入账凭证号 | H12: 对方科目 | I12: 增加情况 | M12: 合同/协议/订单 | P12: 采购发票 | S12: …… | T12: 索引号 | U12: 是否异常
I13: 原值 | J13: 累计折旧 | K13: 减值准备 | L13: 净值 | M13: 日期/编号 | N13: 对手方名称 | O13: 金额 | P13: 日期/编号 | Q13: 对手方名称 | R13: 金额 | V13: 检查的关键证据和要素根据被审计单位具体情况修改
A14: 1 | L14: =I14-J14-K14 -> 0
A15: 2 | L15: =I15-J15-K15 -> 0
A16: 3 | L16: =I16-J16-K16 -> 0
A17: 4 | L17: =I17-J17-K17 -> 0
A18: 5 | L18: =I18-J18-K18 -> 0
A19: 6 | L19: =I19-J19-K19 -> 0
A20: 7 | L20: =I20-J20-K20 -> 0
A21: 8 | L21: =I21-J21-K21 -> 0
A22: 9 | L22: =I22-J22-K22 -> 0
A23: 10 | L23: =I23-J23-K23 -> 0
A24: 合计 | I24: =SUM(I14:I23) -> 0 | J24: =SUM(J14:J23) -> 0 | K24: =SUM(K14:K23) -> 0 | L24: =SUM(L14:L23) -> 0
A25: 本期新增生产性生物资产合计 | I25: ='明细表（成本模式）H7-2'!N37 -> 0
A26: 检查比例 | I26: =IF(I24=0,0,I24/$I$25) -> 0
A27: 四、审计说明：
A28: 1.如果检查比例较低应扩大检查样本量或说明原因
A29: 2.……
A32: 五、审计结论：
A36: 提示：
A37: 1、本表用于汇总本年度增加生产性生物资产的测试情况。
A38: 2、对于外购生产性生物资产，检查购货合同、发票、保险单、发运凭证等文件，抽查测试其计价是否正确，会计处理是否正确；如果购买生产性生物资产的价款超过正常信用条件延期支付，
A39: 检查实质上是否具有融资性质，生产性生物资产的成本是否以购买价款的现值为基础确定。
A40: 3、对于自行培育的生产性生物资产，检查增加的生产性生物资产原值是否真实。
A41: 4、对于非货币性资产交换、债务重组、企业合并、投资者投入等交易方式取得的有关长期资产，检查相关合同/协议，关注计价是否正确、移交手续是否办理以及会计处理是否正确。
A42: 5、对于因清产核资、资产评估调增有关长期资产价值的，检查有关清产核资报告、资产评估报告、国有资产管理等部门的确认文件、验资报告等，检查会计处理是否正确。
A43: 6、概述：（1）程序的测试情况、结果；
A44: （2）拟调整事项及其调整分录、未调整事项及其影响，审计范围受到限制情况及其影响。

Sheet 增加检查表（公允价值模式）H7-6
A1: 致同会计师事务所
A2: 增加检查表（公允价值模式）
A3: =底稿目录!A2 -> 被审计单位： | F3: =底稿目录!A4 -> 编制人： | J3: =底稿目录!A6 -> 编制日期： | S3: 索引号： | T3: H7-6
A4: =底稿目录!A3 -> 截止日： | F4: =底稿目录!A5 -> 复核人： | J4: =底稿目录!A7 -> 复核日期： | S4: 页 次：
A5: 一、审计目标：1.资产负债表中记录的生产性生物资产是存在的，且已记录于恰当的账户；2.所有应记录的生产性生物资产均已记录，所有应当包括在财务报表中的相关披露均已包括；3.记录的生产性生物资产由被审计单位拥有或控制；4.生产性生物资产以恰当的金额包括在财务报表中，与之相关的计价或分摊调整已恰当记录，相关披露已得到恰当计量和描述。
A6: 二、样本选取标准与规模：
A7: 测试总体： | B7: 如生产性生物资产借方发生额所有凭证共XX笔金额XX | J7: 特定样本： | K7: XX金额以上（大额）、关联方/关联交易形成的款项、XX异常款项全部测试，共XX笔；
A8: 抽样总体： | B8: 测试总体扣除特定样本以外的样本，共XX笔、金额XX | J8: 确定的抽样样本量： | L8: 抽取XX笔 | M8: （如果使用了样本计算器计算样本量，样本量计算过程见<XX>底稿）
A9: 抽样方法： | B9: 随机选样/系统选样/货币单元抽样/随意选样（非统计抽样适用） | J9: 抽样过程： | K9: 使用IDEA（XX抽样工具）选择XX数量、金额XX的样本进行测试，抽样工具中的样本选择过程和结果见<XX>底稿
A10: 三、测试：
A11: 测试内容说明：1.原始凭证是否齐全； 2.记账凭证与原始凭证是否相符；3.账务处理是否正确；4.是否记录于恰当的会计期间；5.……
A12: 序号 | B12: 生产性生物资产类别类别 | C12: 生产性生物资产编号 | D12: 生产性生物资产名称 | E12: 增加日期 | F12: 增加方式 | G12: 入账凭证号 | H12: 对方科目 | I12: 增加情况 | L12: 合同/协议/订单 | O12: 采购发票 | R12: …… | S12: 索引号 | T12: 是否异常
I13: 原值 | J13: 公允价值变动 | K13: 期末余额 | L13: 日期/编号 | M13: 对手方名称 | N13: 金额 | O13: 日期/编号 | P13: 对手方名称 | Q13: 金额 | U13: 检查的关键证据和要素根据被审计单位具体情况修改
A14: 1 | K14: =I14+J14 -> 0
A15: 2 | K15: =I15+J15 -> 0
A16: 3 | K16: =I16+J16 -> 0
A17: 4 | K17: =I17+J17 -> 0
A18: 5 | K18: =I18+J18 -> 0
A19: 6 | K19: =I19+J19 -> 0
A20: 7 | K20: =I20+J20 -> 0
A21: 8 | K21: =I21+J21 -> 0
A22: 9 | K22: =I22+J22 -> 0
A23: 10 | K23: =I23+J23 -> 0
A24: 合计 | I24: =SUM(I14:I23) -> 0 | J24: =SUM(J14:J23) -> 0 | K24: =SUM(K14:K23) -> 0
A25: 本期新增生产性生物资产合计 | K25: ='明细表（公允价值模式）H7-2'!N37+IF('明细表（公允价值模式）H7-2'!R37>0,'明细表（公允价值模式）H7-2'!R37,0) -> 0
A26: 检查比例 | K26: =IF(K24=0,0,K24/$K$25) -> 0
A27: 四、审计说明：
A28: 1.如果检查比例较低应扩大检查样本量或说明原因
A29: 2.……
A32: 五、审计结论：
A35: 提示：
A36: 1、本表用于汇总本年度增加、减少生产性生物资产的测试情况。
A37: 2、概述：（1）程序的测试情况、结果；
A38: （2）拟调整事项及其调整分录、未调整事项及其影响，审计范围受到限制情况及其影响。

Sheet 减少检查表（成本模式）H7-7
A1: 致同会计师事务所
A2: 减少检查表（成本模式）
A3: =底稿目录!A2 -> 被审计单位： | F3: =底稿目录!A4 -> 编制人： | O3: =底稿目录!A6 -> 编制日期： | V3: 索引号： | W3: H7-7
A4: =底稿目录!A3 -> 截止日： | F4: =底稿目录!A5 -> 复核人： | O4: =底稿目录!A7 -> 复核日期： | V4: 页 次：
A5: 一、审计目标：1. 资产负债表中记录的生产性生物资产是存在的，且已记录于恰当的账户；2. 所有应记录的生产性生物资产均已记录，所有应当包括在财务报表中的相关披露均已包括；3. 生产性生物资产以恰当的金额包括在财务报表中，与之相关的计价或分摊调整已恰当记录，相关披露已得到恰当计量和描述。
A6: 二、样本选取标准与规模：
A7: 测试总体： | B7: 如生产性生物资产贷方发生额所有凭证共XX笔金额XX | I7: 特定样本： | J7: XX金额以上（大额）、关联方/关联交易形成的款项、XX异常款项全部测试，共XX笔；
A8: 抽样总体： | B8: 测试总体扣除特定样本以外的样本，共XX笔、金额XX | I8: 确定的抽样样本量： | K8: 抽取XX笔 | L8: （如果使用了样本计算器计算样本量，样本量计算过程见<XX>底稿）
A9: 抽样方法： | B9: 随机选样/系统选样/货币单元抽样/随意选样（非统计抽样适用） | I9: 抽样过程： | J9: 使用IDEA（XX抽样工具）选择XX数量、金额XX的样本进行测试，抽样工具中的样本选择过程和结果见<XX>底稿
A10: 三、测试过程：
A11: 测试内容说明：1.原始凭证是否齐全； 2.记账凭证与原始凭证是否相符；3.账务处理是否正确；4.是否记录于恰当的会计期间；5.……
A12: 序号 | B12: 生产性生物资产类别 | C12: 生产性生物资产编号 | D12: 生产性生物资产名称 | E12: 减少方式 | F12: 减少日期 | G12: 凭证号 | H12: 对方科目 | I12: 减少情况 | P12: 审批单 | R12: 合同/协议/订单 | U12: …… | V12: 索引号 | W12: 是否异常
I13: 转入清理的生产性生物资产 | M13: 清理净收入 | O13: 清理净损益 | P13: 日期/编号 | Q13: 是否经过恰当审批 | R13: 日期/编号 | S13: 对手方名称 | T13: 金额
I14: 原值 | J14: 累计折旧 | K14: 减值准备 | L14: 净值 | M14: 清理费用 | N14: 清理收入 | R14: 3 | S14: 4 | T14: 5 | X14: 检查的关键证据和要素根据被审计单位具体情况修改
A15: 1 | L15: =I15-J15-K15 -> 0 | O15: =N15-M15-L15 -> 0
A16: 2 | L16: =I16-J16-K16 -> 0 | O16: =N16-M16-L16 -> 0
A17: 3 | L17: =I17-J17-K17 -> 0 | O17: =N17-M17-L17 -> 0
A18: 4 | L18: =I18-J18-K18 -> 0 | O18: =N18-M18-L18 -> 0
A19: 5 | L19: =I19-J19-K19 -> 0 | O19: =N19-M19-L19 -> 0
A20: 6 | L20: =I20-J20-K20 -> 0 | O20: =N20-M20-L20 -> 0
A21: 7 | L21: =I21-J21-K21 -> 0 | O21: =N21-M21-L21 -> 0
A22: 8 | L22: =I22-J22-K22 -> 0 | O22: =N22-M22-L22 -> 0
A23: 9 | L23: =I23-J23-K23 -> 0 | O23: =N23-M23-L23 -> 0
A24: 10 | L24: =I24-J24-K24 -> 0 | O24: =N24-M24-L24 -> 0
A25: 合计 | I25: =SUM(I15:I24) -> 0 | J25: =SUM(J15:J24) -> 0 | K25: =SUM(K15:K24) -> 0 | L25: =SUM(L15:L24) -> 0 | M25: =SUM(M15:M24) -> 0 | N25: =SUM(N15:N24) -> 0 | O25: =SUM(O15:O24) -> 0
A26: 本期减少生产性生物资产合计 | I26: ='明细表（成本模式）H7-2'!O37 -> 0
A27: 检查比例 | I27: =IF(I25=0,0,I25/$I$26) -> 0
A28: 四、审计说明：
A29: 1.如果检查比例较低应扩大检查样本量或说明原因
A30: 2.……
A33: 五、审计结论：
A36: 提示：
A37: 1、本表用于汇总本年度减少生产性生物资产的测试情况。
A38: 2、检查当年减少的生产性生物资产的销账情况，减少的生产性生物资产产生的损益是否及时记入营业外收支科目，账务处理是否与减少生产性生物资产的授权批准文件一致。
A40: 3、概述：（1）程序的测试情况、结果；
A41: （2）拟调整事项及其调整分录、未调整事项及其影响，审计范围受到限制情况及其影响。

Sheet 减少检查表（公允价值模式）H7-7
A1: 致同会计师事务所
A2: 减少检查表（公允价值模式）
A3: =底稿目录!A2 -> 被审计单位： | I3: =底稿目录!A4 -> 编制人： | L3: =底稿目录!A6 -> 编制日期： | R3: 索引号： | S3: H7-7
A4: =底稿目录!A3 -> 截止日： | I4: =底稿目录!A5 -> 复核人： | L4: =底稿目录!A7 -> 复核日期： | R4: 页 次：
A5: 一、审计目标：1. 资产负债表中记录的生产性生物资产是存在的，且已记录于恰当的账户；2. 所有应记录的生产性生物资产均已记录，所有应当包括在财务报表中的相关披露均已包括；3. 生产性生物资产以恰当的金额包括在财务报表中，与之相关的计价或分摊调整已恰当记录，相关披露已得到恰当计量和描述。
A6: 二、样本选取标准与规模：
A7: 测试总体： | B7: 如生产性生物资产贷方发生额所有凭证共XX笔金额XX | H7: 特定样本： | I7: XX金额以上（大额）、关联方/关联交易形成的款项、XX异常款项全部测试，共XX笔；
A8: 抽样总体： | B8: 测试总体扣除特定样本以外的样本，共XX笔、金额XX | H8: 确定的抽样样本量： | J8: 抽取XX笔
A9: 抽样方法： | B9: 随机选样/系统选样/货币单元抽样/随意选样（非统计抽样适用） | H9: 抽样过程： | I9: 使用IDEA（XX抽样工具）选择XX数量、金额XX的样本进行测试，抽样工具中的样本选择过程和结果见<XX>底稿
A10: 三、测试：
A11: 测试内容说明：1.原始凭证是否齐全； 2.记账凭证与原始凭证是否相符；3.账务处理是否正确；4.是否记录于恰当的会计期间；5.……
A12: 序号 | B12: 生产性生物资产类别 | C12: 生产性生物资产编号 | D12: 生产性生物资产名称 | E12: 减少方式 | F12: 减少日期 | G12: 凭证号 | H12: 对方科目 | I12: 减少情况 | L12: 付款审批单 | N12: 合同/协议/订单 | Q12: …… | R12: 索引号 | S12: 是否异常
I13: 原值 | J13: 公允价值变动 | K13: 期末余额 | L13: 日期/编号 | M13: 是否经过恰当审批 | N13: 日期/编号 | O13: 对手方名称 | P13: 金额 | T13: 检查的关键证据和要素根据被审计单位具体情况修改
A14: 1 | K14: =I14+J14 -> 0
A15: 2 | K15: =I15+J15 -> 0
A16: 3 | K16: =I16+J16 -> 0
A17: 4 | K17: =I17+J17 -> 0
A18: 5 | K18: =I18+J18 -> 0
A19: 6 | K19: =I19+J19 -> 0
A20: 7 | K20: =I20+J20 -> 0
A21: 合计 | I21: =SUM(I14:I20) -> 0 | J21: =SUM(J14:J20) -> 0 | K21: =SUM(K14:K20) -> 0
A22: 本期减少生产性生物资产合计
A23: 检查比例 | K23: =K21/K22 -> #DIV/0!
A24: 四、审计说明：
A25: 1.如果检查比例较低应扩大检查样本量或说明原因
A26: 2.……
A27: 五、审计结论：
A29: 提示：
A30: 1、本表用于汇总本年度增加、减少生产性生物资产的测试情况。
A31: 2、概述：（1）程序的测试情况、结果；
A32: （2）拟调整事项及其调整分录、未调整事项及其影响，审计范围受到限制情况及其影响。

Sheet 监盘计划H7-8
A1: 致同会计师事务所
A2: 生产性生物资产监盘计划
A3: =底稿目录!A2 -> 被审计单位： | D3: =底稿目录!A4 -> 编制人： | F3: =底稿目录!A6 -> 编制日期： | H3: 索引号： | I3: H7-8
A4: =底稿目录!A3 -> 截止日： | D4: =底稿目录!A5 -> 复核人： | F4: =底稿目录!A7 -> 复核日期： | H4: 页 次：
A5: 被审计单位名称： | F5: 审计目标：
A6: 一、确定的生产性生物资产存在性认定可能存在重大错报的风险程度：
A8: 二、了解被审计单位生产性生物资产期末状况与管理规定：
A9: （一）生产性生物资产的期末状况：
A10: 1．期末余额： | E10: 提取的减值准备金额：
A11: 2．大类生产性生物资产金额情况：
B12: 类别 | C12: 期末余额 | D12: 减值准备 | E12: 账面净值
A16: 3．期末资产数量：
B17: 类 别 | C17: 计量单位 | D17: 数量 | E17: 说明
A21: 4．资产存放地点：
B22: 类 别 | C22: 仓库（或场所） | D22: 地点 | E22: 说明
A26: （二）企业定期盘点内部控制制度与执行情况：
A27: 1．制度名称：（提示：按企业内部控制制度名称填写） 索引号：（ ）
A28: （1）规定盘点的时间与次数：
A29: （2）负责盘点的部门： | F29: 负责人：
A30: （提示：如制度规定与实际执行不一致的，应按制度规定与实际负责的部门分别填写）
A31: 2．企业实际盘点情况：
A32: （1）盘点计划安排：
A33: （2）盘点会议情况：
A34: （3）预计安排的盘点人员数量： | F34: 负责人：
A35: （4）对企业盘点计划的评价：
A36: （三）查阅以前年度工作底稿记录：
A37: 1．上一年度监盘时间： | F37: 实施监盘的人员：
A38: 2．抽盘的生产性生物资产范围： | F38: 抽盘比例：
A39: 3．实施监盘中发现的问题与存在的不足：
A40: （提示：上年度如是本所实施监盘的，应当查阅上一年度工作底稿；如不是本所实施审计的，应当在与前任会计师实施沟通程序中安排本项沟通内容。）
A41: 三、评估审计人员的专业胜任能力：
A43: 提示：针对特殊类型的存货，应当评估审计人员是否具备专业胜任能力
A44: 四、盘点计划安排：
A45: （一）预计监盘时间：
A46: （二）预计安排监盘人员数量： | F46: 监盘程序负责人：
A47: （三）预计监盘的生产性生物资产范围：
A48: 1．类别范围：
A49: 2．地点范围：
A50: （四）拟实施的盘点方法：
A51: （五）就监盘计划与管理层沟通事项
A52: 1．时间： | E52: 2.管理层人员：
A53: 3．审计小组参与人员：
A54: （六）针对被审计单位具体情况，需要向管理层提出的监盘的特殊要求：
A55: （七）预计监盘中抽取样本的方法与数量
A56: 1．从会计明细账簿中选取样本的方法： | G56: 预计选取数量：
A57: 2．从实际生产性生物资产中选取样本的方法： | G57: 预计选取数量：
A58: （八）实际监盘时点至资产负债表日的推算方法：
A59: 1．推断方法说明：
A61: 2．预计拟要求的盘点复盘比例：

Sheet 盘点检查表H7-9
A1: 致同会计师事务所
A2: 生产性生物资产盘点检查表
A3: =底稿目录!A2 -> 被审计单位： | E3: =底稿目录!A4 -> 编制人： | J3: =底稿目录!A6 -> 编制日期： | L3: 索引号： | M3: H7-9
A4: =底稿目录!A3 -> 截止日： | E4: =底稿目录!A5 -> 复核人： | J4: =底稿目录!A7 -> 复核日期： | L4: 页 次：
A5: 一、审计目标：
A6: 1.资产负债表中记录的生产性生物资产是存在的，且已记录于恰当的账户；2.所有应记录的生产性生物资产均已记录，所有应当包括在财务报表中的相关披露均已包括；
A7: 3.生产性生物资产产以恰当的金额包括在财务报表中，与之相关的计价或分摊调整已恰当记录，相关披露已得到恰当计量和描述 。
A8: 二、样本选取标准与规模：
A9: 测试总体： | B9: 如期末生产性生物资产数量XX、金额XX | G9: 特定样本： | H9: XX金额以上（大额）、关联方/关联交易形成的款项、XX异常款项全部测试，共XX笔；
A10: 抽样总体： | B10: 测试总体扣除特定样本以外的样本，共XX笔、金额XX | G10: 确定的抽样样本量： | H10: 抽取XX笔 | I10: （如果使用了样本计算器计算样本量，样本量计算过程见<XX>底稿）
A11: 抽样方法： | B11: 随机选样/系统选样/货币单元抽样/随意选样（非统计抽样适用） | G11: 抽样过程： | H11: 使用IDEA（XX抽样工具）选择XX数量、金额XX的样本进行测试，抽样工具中的样本选择过程和结果见<XX>底稿
A12: 三、审计过程：
A13: 抽盘地点：______________ | C13: 盘点人员： | D13: 被审计单位仓库盘点人和财务监盘人签字 | I13: 监盘人员： | J13: （审计人员签字） | L13: 盘点时间：__________________
A14: （一）从生产性生物资产盘点记录中选取项目追查至生产性生物资产实物
A15: 生产性生物资产名称/类别 | B15: 资产编号 | C15: 规格 | D15: 单位 | E15: 单价 | F15: 盘点前财务账面记录 | H15: 企业盘点记录数量 | I15: 抽盘数量 | J15: 抽盘与账面差异（+盈-亏） | K15: 抽盘与企业盘点差异 | L15: 企业盘点与账面差异 | M15: 品质状况（正常/闲置/毁损等）
F16: 数量 | G16: 金额
J17: =I17-F17 -> 0 | K17: =I17-H17 -> 0 | L17: =H17-F17 -> 0
J18: =I18-F18 -> 0 | K18: =I18-H18 -> 0 | L18: =H18-F18 -> 0
J19: =I19-F19 -> 0 | K19: =I19-H19 -> 0 | L19: =H19-F19 -> 0
J20: =I20-F20 -> 0 | K20: =I20-H20 -> 0 | L20: =H20-F20 -> 0
J21: =I21-F21 -> 0 | K21: =I21-H21 -> 0 | L21: =H21-F21 -> 0
J22: =I22-F22 -> 0 | K22: =I22-H22 -> 0 | L22: =H22-F22 -> 0
J23: =I23-F23 -> 0 | K23: =I23-H23 -> 0 | L23: =H23-F23 -> 0
J24: =I24-F24 -> 0 | K24: =I24-H24 -> 0 | L24: =H24-F24 -> 0
J25: =I25-F25 -> 0 | K25: =I25-H25 -> 0 | L25: =H25-F25 -> 0
J26: =I26-F26 -> 0 | K26: =I26-H26 -> 0 | L26: =H26-F26 -> 0
J27: =I27-F27 -> 0 | K27: =I27-H27 -> 0 | L27: =H27-F27 -> 0
A28: 合计 | F28: =SUM(F17:F27) -> 0 | G28: =SUM(G17:G27) -> 0 | H28: =SUM(H17:H27) -> 0 | I28: =SUM(I17:I27) -> 0 | J28: =SUM(J17:J27) -> 0 | K28: =SUM(K17:K27) -> 0 | L28: =SUM(L17:L27) -> 0 | M28: =SUM(M17:M27) -> 0
A29: 期末生产性生物资产原值合计：
A30: 抽取样本占期末原值合计的比例：（%） | G30: =G28/G29 -> #DIV/0!
A32: （二）从生产性生物资产实物中选取项目追查至生产性生物资产盘点记录
A33: 生产性生物资产名称/类别 | B33: 资产编号 | C33: 规格 | D33: 单位 | E33: 单价 | F33: 盘点前财务账面记录 | H33: 企业盘点记录数量 | I33: 抽盘数量 | J33: 抽盘与账面差异（+盈-亏） | K33: 抽盘与企业盘点差异 | L33: 企业盘点与账面差异 | M33: 品质状况（正常/残次/毁损/滞销等）
F34: 数量 | G34: 金额
J35: =I35-F35 -> 0 | K35: =I35-H35 -> 0 | L35: =H35-F35 -> 0
J36: =I36-F36 -> 0 | K36: =I36-H36 -> 0 | L36: =H36-F36 -> 0
J37: =I37-F37 -> 0 | K37: =I37-H37 -> 0 | L37: =H37-F37 -> 0
J38: =I38-F38 -> 0 | K38: =I38-H38 -> 0 | L38: =H38-F38 -> 0
J39: =I39-F39 -> 0 | K39: =I39-H39 -> 0 | L39: =H39-F39 -> 0
J40: =I40-F40 -> 0 | K40: =I40-H40 -> 0 | L40: =H40-F40 -> 0
J41: =I41-F41 -> 0 | K41: =I41-H41 -> 0 | L41: =H41-F41 -> 0
J42: =I42-F42 -> 0 | K42: =I42-H42 -> 0 | L42: =H42-F42 -> 0
J43: =I43-F43 -> 0 | K43: =I43-H43 -> 0 | L43: =H43-F43 -> 0
J44: =I44-F44 -> 0 | K44: =I44-H44 -> 0 | L44: =H44-F44 -> 0
J45: =I45-F45 -> 0 | K45: =I45-H45 -> 0 | L45: =H45-F45 -> 0
A46: 合计 | F46: =SUM(F35:F45) -> 0 | G46: =SUM(G35:G45) -> 0 | H46: =SUM(H35:H45) -> 0 | I46: =SUM(I35:I45) -> 0 | J46: =SUM(J35:J45) -> 0 | K46: =SUM(K35:K45) -> 0 | L46: =SUM(L35:L45) -> 0 | M46: =SUM(M35:M45) -> 0
A47: 期末生产性生物资产原值合计：
A48: 抽取样本占期末原值合计的比例：（%） | G48: =G46/G47 -> #DIV/0!
A50: 四、审计说明：
A51: （1）备忘录详见“生产性生物资产盘点实地监盘备忘录”。
A53: 五、审计结论：
A57: 提示：
A58: 1、本表可作为生产性生物资产盘点汇总表或盘点明细表或生产性生物资产抽盘表。
A59: 2、财务账面记录与资产管理部门账面记录应一致，若存在差异应调整一致。
A60: 3、财务账面记录与实际盘点记录的差异构成盘盈/盘亏，应根据具体原因分析处理。应说明企业的处理结果。
A61: 4、盘点时应关注资产的品质状况（影响减值准备的计提）。

Sheet 监盘小结H7-10
A1: 致同会计师事务所
A2: 生产性生物资产监盘小结
A3: =底稿目录!A2 -> 被审计单位： | D3: =底稿目录!A4 -> 编制人： | F3: =底稿目录!A6 -> 编制日期： | H3: 索引号： | I3: H7-10
A4: =底稿目录!A3 -> 截止日： | D4: =底稿目录!A5 -> 复核人： | F4: =底稿目录!A7 -> 复核日期： | H4: 页 次：
A5: 一、资产负债表日：
A7: 二、主要资产存放情况：
A9: 序号 | B9: 资产类别 | C9: 资产名称 | D9: 存放地点
A10: 1
A11: 2
A12: 3
A13: 三、了解资产管理情况
A14: 序号 | B14: 项目
A15: 1 | B15: 资产管理部门：
A16: 2 | B16: 管理人员：
A17: 3 | B17: 资产是否具有管理标识：
A18: 4 | B18: 资产是否具有定期保养制度：
A19: 5 | B19: 资产明细账（卡）是否完整：
A20: 6 | B20: 资产明细账（卡）的各项记录是否完整：
A21: 三、参与盘点人员：
A22: 1． 被审计单位的人员：
A23: 序号 | B23: 盘点人员所属部门 | C23: 人员数量 | D23: 人员名称 | E23: 所负责的部分
A24: 1
A25: 2
A26: 3
A27: 2． 审计人员：
A28: 序号 | B28: 人员名称 | C28: 负责的部分
A29: 1
A30: 2
A31: 3
A32: 四、实际盘点前的检查程序：
A33: 1．资产现场观察说明：
A34: 2．盘点前检查程序：
A35: （1）资产明细账（卡） 是否获取： | G35: 索引：
A36: （2）生产性生物资产管理制度 是否获取： | G36: 索引：
A37: （3）获取或编制资产位置简图： | G37: 索引：
A38: 五、实际盘点时间：
A39: 实际监盘（盘点）日： | E39: 开始时间： | H39: 结束时间：
A40: 六、企业实际盘点情况说明
A41: （一）企业实际盘点人员
A42: 部门： | E42: 姓名： | H42: 岗位：
A43: 部门： | E43: 姓名： | H43: 岗位：
A44: 部门： | E44: 姓名： | H44: 岗位：
A45: 盘点人员共分 | D45: 组，其中：
A46: 第一组： | D46: 点数并报出类别、标识， | H46: 记录
A47: 第二组： | D47: 点数并报出类别、标识， | H47: 记录
A48: 第三组： | D48: 点数并报出类别、标识， | H48: 记录
A49: （二）特殊情况说明：
A50: 七、审计人员复盘记录：
A51: （一）抽盘样本确定方法
A52: 1．从会计明细账中抽取的方法
A53: 2．从实物资产中抽取样本的方法
A54: （二）盘点方法：
A55: 1．盘点人员共分 | D55: 组，其中：
A56: 2．第一组： | E56: 负责监盘的生产性生物资产类别：
C57: 点数并报出类别、标识， | H57: 记录
A58: 第二组： | E58: 负责监盘的生产性生物资产类别：
C59: 点数并报出类别、标识， | H59: 记录
A60: 第三组： | E60: 负责监盘的生产性生物资产类别：
C61: 点数并报出类别、标识， | H61: 记录
A62: 3. 生产性生物资产是否停止流动
A63: 4．监盘中特殊情况说明：
A64: 上述人员在盘点过程中，除 | F64: 外，自始至终未离开现场 是（ ） 否（ ）。
A65: （三）审计人员实际抽盘情况 | G65: 底稿索引：
A67: 1．生产性生物资产盘点说明：
A68: （1）相同生产性生物资产是否具有可供识别的管理标识，并能清晰区分：
A69: 管理标识编号规则： | G69: 检查记录索引：
A70: （2）各类型生产性生物资产数量是否与会计账簿记载的数量一致： | G70: 检查记录索引：
A71: （3）是否存在实际已死亡或毁损而会计账簿仍记载的生产性生物资产：
A72: （4）是否有实际已使用而会计账簿未记载的生产性生物资产：
A73: （5）关注资产的品质状况：
A76: 八、盘点中异常情况说明：
A78: 九、复盘记录：（提示：应按照审计准则规定确定复盘的样本）
A79: 1、复盘人员： | F79: 复盘底稿记录索引：
A80: 2、复盘统计：
A81: 生产性生物资产共有 | C81: （头）只等，实施复盘共： | G81: （头）只等，占
A82: 生产性生物资产账面余额： | E82: 元，实施复盘： | H82: 元，占
A83: 倒退至资产负债表日是否存在尚未购入且未入账的资产：
A84: 倒退至资产负债表日分析是否存在已报废与处置的资产：
A85: 本次复盘的资产余额合计占资产负债表日的生产性生物资产余额 | G85: %
A86: 3、计算复盘正确率：
A87: 复盘 | C87: （头）只等， 其中复盘正确的共 | G87: 种，占
A88: 复盘金额 | D88: 元， 其中复盘正确的共 | G88: 元，占
A89: 十、盘点结束工作说明：
A90: 盘点结束后的工作记录
A91: 1、对盘点工作的评价：
A92: 生产性生物资产管理人员对生产性生物资产管理业务的熟悉程度：
A93: 生产性生物资产管理人员对盘点工作与复盘工作的负责态度：
A94: 对审计人员索取的资料配合程度：
A95: 2、索取由生产性生物资产人员编制的〈盘点差异说明〉，并请其加盖公章：
A96: 3、请被审计单位的人员在〈生产性生物资产复盘抽查情况表〉上签字：
G97: 监盘人员签字：
G98: 复核人员签字：

Sheet 折旧测算表（不含减值）-直线法H7-11
A1: 致同会计师事务所
A2: 生产性生物资产折旧测算表
A3: =底稿目录!A2 -> 被审计单位： | G3: =底稿目录!A4 -> 编制人： | M3: =底稿目录!A6 -> 编制日期： | R3: 索引号： | S3: H7-11
A4: =底稿目录!A3 -> 截止日： | G4: =底稿目录!A5 -> 复核人： | M4: =底稿目录!A7 -> 复核日期： | R4: 页 次：
A5: 一、审计目标：生产性生物资产以恰当的金额包括在财务报表中，与之相关的计价或分摊调整已恰当记录，相关披露已得到恰当计量和描述。
A6: 二、审计过程：
A7: 折旧期初： | B7: 45658 | C7: 折旧期末： | D7: 46022 | E7: 各列顺序请根据需要进行调整，行数请根据需要增加。非公式列输入数据时请使用“选择性粘贴-数值”。
A8: 生产性生物资产类别 | B8: 生产性生物资产编号 | C8: 生产性生物资产名称 | D8: 管理部门 | E8: 原值 | F8: 累计折旧 | G8: 开始使用日期 | H8: 使用年限 | I8: 残值率 | J8: 账面月折旧额 | K8: 使用月限 | L8: 测算到期日 | M8: 已提折旧月份 | N8: 本期折旧月份 | O8: 测算月折旧 | P8: 当期折旧费用 | Q8: 月折旧额差异 | R8: 累计折旧费用 | S8: 累计折旧额差异
K9: =IF(H9=0,0,IF(RIGHT(H9,1)<>"年",H9*12,IF(LEN(H9)=3,VALUE(LEFT(H9,2))*12,IF(LEN(H9)=2,VALUE(LEFT(H9,1))*12,"??")))) -> 0 | L9: =DATE((YEAR(G9)+H9),MONTH(G9),DAY(G9)) -> 0 | M9: =MIN((YEAR(L9)-YEAR(G9))*12+(MONTH(L9)-MONTH(G9)),(YEAR($D$7)-YEAR(G9))*12+MONTH($D$7)-MONTH(G9),H9*12) -> 0 | N9: =IF(L9<$B$7,0,IF($D$7>L9,MIN(MONTH($D$7),DATEDIF(DATE(YEAR(G9),MONTH(G9),"1"),$D$7,"M")-DATEDIF(DATE(YEAR(G9),MONTH(G9),"1"),DATEDIF(YEAR(L9),MONTH(L9),"1"),"M")),MIN(DATEDIF(DATE(YEAR(G9),MONTH(G9),"1"),$D$7,"m"),MONTH($D$7)))) -> 0 | O9: =IF(K9=0,0,ROUND(((1-I9)/K9)*E9,4)) -> 0 | P9: =ROUND(O9*N9,2) -> 0 | Q9: =ROUND(J9-O9,2) -> 0 | R9: =ROUND(O9*M9,2) -> 0 | S9: =ROUND(F9-R9,2) -> 0
K10: =IF(H10=0,0,IF(RIGHT(H10,1)<>"年",H10*12,IF(LEN(H10)=3,VALUE(LEFT(H10,2))*12,IF(LEN(H10)=2,VALUE(LEFT(H10,1))*12,"??")))) -> 0 | L10: =DATE((YEAR(G10)+H10),MONTH(G10),DAY(G10)) -> 0 | M10: =MIN((YEAR(L10)-YEAR(G10))*12+(MONTH(L10)-MONTH(G10)),(YEAR($D$7)-YEAR(G10))*12+MONTH($D$7)-MONTH(G10),H10*12) -> 0 | N10: =IF(L10<$B$7,0,IF($D$7>L10,MIN(MONTH($D$7),DATEDIF(DATE(YEAR(G10),MONTH(G10),"1"),$D$7,"M")-DATEDIF(DATE(YEAR(G10),MONTH(G10),"1"),DATEDIF(YEAR(L10),MONTH(L10),"1"),"M")),MIN(DATEDIF(DATE(YEAR(G10),MONTH(G10),"1"),$D$7,"m"),MONTH($D$7)))) -> 0 | O10: =IF(K10=0,0,ROUND(((1-I10)/K10)*E10,4)) -> 0 | P10: =ROUND(O10*N10,2) -> 0 | Q10: =ROUND(J10-O10,2) -> 0 | R10: =ROUND(O10*M10,2) -> 0 | S10: =ROUND(F10-R10,2) -> 0
K11: =IF(H11=0,0,IF(RIGHT(H11,1)<>"年",H11*12,IF(LEN(H11)=3,VALUE(LEFT(H11,2))*12,IF(LEN(H11)=2,VALUE(LEFT(H11,1))*12,"??")))) -> 0 | L11: =DATE((YEAR(G11)+H11),MONTH(G11),DAY(G11)) -> 0 | M11: =MIN((YEAR(L11)-YEAR(G11))*12+(MONTH(L11)-MONTH(G11)),(YEAR($D$7)-YEAR(G11))*12+MONTH($D$7)-MONTH(G11),H11*12) -> 0 | N11: =IF(L11<$B$7,0,IF($D$7>L11,MIN(MONTH($D$7),DATEDIF(DATE(YEAR(G11),MONTH(G11),"1"),$D$7,"M")-DATEDIF(DATE(YEAR(G11),MONTH(G11),"1"),DATEDIF(YEAR(L11),MONTH(L11),"1"),"M")),MIN(DATEDIF(DATE(YEAR(G11),MONTH(G11),"1"),$D$7,"m"),MONTH($D$7)))) -> 0 | O11: =IF(K11=0,0,ROUND(((1-I11)/K11)*E11,4)) -> 0 | P11: =ROUND(O11*N11,2) -> 0 | Q11: =ROUND(J11-O11,2) -> 0 | R11: =ROUND(O11*M11,2) -> 0 | S11: =ROUND(F11-R11,2) -> 0
K12: =IF(H12=0,0,IF(RIGHT(H12,1)<>"年",H12*12,IF(LEN(H12)=3,VALUE(LEFT(H12,2))*12,IF(LEN(H12)=2,VALUE(LEFT(H12,1))*12,"??")))) -> 0 | L12: =DATE((YEAR(G12)+H12),MONTH(G12),DAY(G12)) -> 0 | M12: =MIN((YEAR(L12)-YEAR(G12))*12+(MONTH(L12)-MONTH(G12)),(YEAR($D$7)-YEAR(G12))*12+MONTH($D$7)-MONTH(G12),H12*12) -> 0 | N12: =IF(L12<$B$7,0,IF($D$7>L12,MIN(MONTH($D$7),DATEDIF(DATE(YEAR(G12),MONTH(G12),"1"),$D$7,"M")-DATEDIF(DATE(YEAR(G12),MONTH(G12),"1"),DATEDIF(YEAR(L12),MONTH(L12),"1"),"M")),MIN(DATEDIF(DATE(YEAR(G12),MONTH(G12),"1"),$D$7,"m"),MONTH($D$7)))) -> 0 | O12: =IF(K12=0,0,ROUND(((1-I12)/K12)*E12,4)) -> 0 | P12: =ROUND(O12*N12,2) -> 0 | Q12: =ROUND(J12-O12,2) -> 0 | R12: =ROUND(O12*M12,2) -> 0 | S12: =ROUND(F12-R12,2) -> 0
K13: =IF(H13=0,0,IF(RIGHT(H13,1)<>"年",H13*12,IF(LEN(H13)=3,VALUE(LEFT(H13,2))*12,IF(LEN(H13)=2,VALUE(LEFT(H13,1))*12,"??")))) -> 0 | L13: =DATE((YEAR(G13)+H13),MONTH(G13),DAY(G13)) -> 0 | M13: =MIN((YEAR(L13)-YEAR(G13))*12+(MONTH(L13)-MONTH(G13)),(YEAR($D$7)-YEAR(G13))*12+MONTH($D$7)-MONTH(G13),H13*12) -> 0 | N13: =IF(L13<$B$7,0,IF($D$7>L13,MIN(MONTH($D$7),DATEDIF(DATE(YEAR(G13),MONTH(G13),"1"),$D$7,"M")-DATEDIF(DATE(YEAR(G13),MONTH(G13),"1"),DATEDIF(YEAR(L13),MONTH(L13),"1"),"M")),MIN(DATEDIF(DATE(YEAR(G13),MONTH(G13),"1"),$D$7,"m"),MONTH($D$7)))) -> 0 | O13: =IF(K13=0,0,ROUND(((1-I13)/K13)*E13,4)) -> 0 | P13: =ROUND(O13*N13,2) -> 0 | Q13: =ROUND(J13-O13,2) -> 0 | R13: =ROUND(O13*M13,2) -> 0 | S13: =ROUND(F13-R13,2) -> 0
K14: =IF(H14=0,0,IF(RIGHT(H14,1)<>"年",H14*12,IF(LEN(H14)=3,VALUE(LEFT(H14,2))*12,IF(LEN(H14)=2,VALUE(LEFT(H14,1))*12,"??")))) -> 0 | L14: =DATE((YEAR(G14)+H14),MONTH(G14),DAY(G14)) -> 0 | M14: =MIN((YEAR(L14)-YEAR(G14))*12+(MONTH(L14)-MONTH(G14)),(YEAR($D$7)-YEAR(G14))*12+MONTH($D$7)-MONTH(G14),H14*12) -> 0 | N14: =IF(L14<$B$7,0,IF($D$7>L14,MIN(MONTH($D$7),DATEDIF(DATE(YEAR(G14),MONTH(G14),"1"),$D$7,"M")-DATEDIF(DATE(YEAR(G14),MONTH(G14),"1"),DATEDIF(YEAR(L14),MONTH(L14),"1"),"M")),MIN(DATEDIF(DATE(YEAR(G14),MONTH(G14),"1"),$D$7,"m"),MONTH($D$7)))) -> 0 | O14: =IF(K14=0,0,ROUND(((1-I14)/K14)*E14,4)) -> 0 | P14: =ROUND(O14*N14,2) -> 0 | Q14: =ROUND(J14-O14,2) -> 0 | R14: =ROUND(O14*M14,2) -> 0 | S14: =ROUND(F14-R14,2) -> 0
K15: =IF(H15=0,0,IF(RIGHT(H15,1)<>"年",H15*12,IF(LEN(H15)=3,VALUE(LEFT(H15,2))*12,IF(LEN(H15)=2,VALUE(LEFT(H15,1))*12,"??")))) -> 0 | L15: =DATE((YEAR(G15)+H15),MONTH(G15),DAY(G15)) -> 0 | M15: =MIN((YEAR(L15)-YEAR(G15))*12+(MONTH(L15)-MONTH(G15)),(YEAR($D$7)-YEAR(G15))*12+MONTH($D$7)-MONTH(G15),H15*12) -> 0 | N15: =IF(L15<$B$7,0,IF($D$7>L15,MIN(MONTH($D$7),DATEDIF(DATE(YEAR(G15),MONTH(G15),"1"),$D$7,"M")-DATEDIF(DATE(YEAR(G15),MONTH(G15),"1"),DATEDIF(YEAR(L15),MONTH(L15),"1"),"M")),MIN(DATEDIF(DATE(YEAR(G15),MONTH(G15),"1"),$D$7,"m"),MONTH($D$7)))) -> 0 | O15: =IF(K15=0,0,ROUND(((1-I15)/K15)*E15,4)) -> 0 | P15: =ROUND(O15*N15,2) -> 0 | Q15: =ROUND(J15-O15,2) -> 0 | R15: =ROUND(O15*M15,2) -> 0 | S15: =ROUND(F15-R15,2) -> 0
K16: =IF(H16=0,0,IF(RIGHT(H16,1)<>"年",H16*12,IF(LEN(H16)=3,VALUE(LEFT(H16,2))*12,IF(LEN(H16)=2,VALUE(LEFT(H16,1))*12,"??")))) -> 0 | L16: =DATE((YEAR(G16)+H16),MONTH(G16),DAY(G16)) -> 0 | M16: =MIN((YEAR(L16)-YEAR(G16))*12+(MONTH(L16)-MONTH(G16)),(YEAR($D$7)-YEAR(G16))*12+MONTH($D$7)-MONTH(G16),H16*12) -> 0 | N16: =IF(L16<$B$7,0,IF($D$7>L16,MIN(MONTH($D$7),DATEDIF(DATE(YEAR(G16),MONTH(G16),"1"),$D$7,"M")-DATEDIF(DATE(YEAR(G16),MONTH(G16),"1"),DATEDIF(YEAR(L16),MONTH(L16),"1"),"M")),MIN(DATEDIF(DATE(YEAR(G16),MONTH(G16),"1"),$D$7,"m"),MONTH($D$7)))) -> 0 | O16: =IF(K16=0,0,ROUND(((1-I16)/K16)*E16,4)) -> 0 | P16: =ROUND(O16*N16,2) -> 0 | Q16: =ROUND(J16-O16,2) -> 0 | R16: =ROUND(O16*M16,2) -> 0 | S16: =ROUND(F16-R16,2) -> 0
K17: =IF(H17=0,0,IF(RIGHT(H17,1)<>"年",H17*12,IF(LEN(H17)=3,VALUE(LEFT(H17,2))*12,IF(LEN(H17)=2,VALUE(LEFT(H17,1))*12,"??")))) -> 0 | L17: =DATE((YEAR(G17)+H17),MONTH(G17),DAY(G17)) -> 0 | M17: =MIN((YEAR(L17)-YEAR(G17))*12+(MONTH(L17)-MONTH(G17)),(YEAR($D$7)-YEAR(G17))*12+MONTH($D$7)-MONTH(G17),H17*12) -> 0 | N17: =IF(L17<$B$7,0,IF($D$7>L17,MIN(MONTH($D$7),DATEDIF(DATE(YEAR(G17),MONTH(G17),"1"),$D$7,"M")-DATEDIF(DATE(YEAR(G17),MONTH(G17),"1"),DATEDIF(YEAR(L17),MONTH(L17),"1"),"M")),MIN(DATEDIF(DATE(YEAR(G17),MONTH(G17),"1"),$D$7,"m"),MONTH($D$7)))) -> 0 | O17: =IF(K17=0,0,ROUND(((1-I17)/K17)*E17,4)) -> 0 | P17: =ROUND(O17*N17,2) -> 0 | Q17: =ROUND(J17-O17,2) -> 0 | R17: =ROUND(O17*M17,2) -> 0 | S17: =ROUND(F17-R17,2) -> 0
K18: =IF(H18=0,0,IF(RIGHT(H18,1)<>"年",H18*12,IF(LEN(H18)=3,VALUE(LEFT(H18,2))*12,IF(LEN(H18)=2,VALUE(LEFT(H18,1))*12,"??")))) -> 0 | L18: =DATE((YEAR(G18)+H18),MONTH(G18),DAY(G18)) -> 0 | M18: =MIN((YEAR(L18)-YEAR(G18))*12+(MONTH(L18)-MONTH(G18)),(YEAR($D$7)-YEAR(G18))*12+MONTH($D$7)-MONTH(G18),H18*12) -> 0 | N18: =IF(L18<$B$7,0,IF($D$7>L18,MIN(MONTH($D$7),DATEDIF(DATE(YEAR(G18),MONTH(G18),"1"),$D$7,"M")-DATEDIF(DATE(YEAR(G18),MONTH(G18),"1"),DATEDIF(YEAR(L18),MONTH(L18),"1"),"M")),MIN(DATEDIF(DATE(YEAR(G18),MONTH(G18),"1"),$D$7,"m"),MONTH($D$7)))) -> 0 | O18: =IF(K18=0,0,ROUND(((1-I18)/K18)*E18,4)) -> 0 | P18: =ROUND(O18*N18,2) -> 0 | Q18: =ROUND(J18-O18,2) -> 0 | R18: =ROUND(O18*M18,2) -> 0 | S18: =ROUND(F18-R18,2) -> 0
K19: =IF(H19=0,0,IF(RIGHT(H19,1)<>"年",H19*12,IF(LEN(H19)=3,VALUE(LEFT(H19,2))*12,IF(LEN(H19)=2,VALUE(LEFT(H19,1))*12,"??")))) -> 0 | L19: =DATE((YEAR(G19)+H19),MONTH(G19),DAY(G19)) -> 0 | M19: =MIN((YEAR(L19)-YEAR(G19))*12+(MONTH(L19)-MONTH(G19)),(YEAR($D$7)-YEAR(G19))*12+MONTH($D$7)-MONTH(G19),H19*12) -> 0 | N19: =IF(L19<$B$7,0,IF($D$7>L19,MIN(MONTH($D$7),DATEDIF(DATE(YEAR(G19),MONTH(G19),"1"),$D$7,"M")-DATEDIF(DATE(YEAR(G19),MONTH(G19),"1"),DATEDIF(YEAR(L19),MONTH(L19),"1"),"M")),MIN(DATEDIF(DATE(YEAR(G19),MONTH(G19),"1"),$D$7,"m"),MONTH($D$7)))) -> 0 | O19: =IF(K19=0,0,ROUND(((1-I19)/K19)*E19,4)) -> 0 | P19: =ROUND(O19*N19,2) -> 0 | Q19: =ROUND(J19-O19,2) -> 0 | R19: =ROUND(O19*M19,2) -> 0 | S19: =ROUND(F19-R19,2) -> 0
K20: =IF(H20=0,0,IF(RIGHT(H20,1)<>"年",H20*12,IF(LEN(H20)=3,VALUE(LEFT(H20,2))*12,IF(LEN(H20)=2,VALUE(LEFT(H20,1))*12,"??")))) -> 0 | L20: =DATE((YEAR(G20)+H20),MONTH(G20),DAY(G20)) -> 0 | M20: =MIN((YEAR(L20)-YEAR(G20))*12+(MONTH(L20)-MONTH(G20)),(YEAR($D$7)-YEAR(G20))*12+MONTH($D$7)-MONTH(G20),H20*12) -> 0 | N20: =IF(L20<$B$7,0,IF($D$7>L20,MIN(MONTH($D$7),DATEDIF(DATE(YEAR(G20),MONTH(G20),"1"),$D$7,"M")-DATEDIF(DATE(YEAR(G20),MONTH(G20),"1"),DATEDIF(YEAR(L20),MONTH(L20),"1"),"M")),MIN(DATEDIF(DATE(YEAR(G20),MONTH(G20),"1"),$D$7,"m"),MONTH($D$7)))) -> 0 | O20: =IF(K20=0,0,ROUND(((1-I20)/K20)*E20,4)) -> 0 | P20: =ROUND(O20*N20,2) -> 0 | Q20: =ROUND(J20-O20,2) -> 0 | R20: =ROUND(O20*M20,2) -> 0 | S20: =ROUND(F20-R20,2) -> 0
... K25: =IF(H25=0,0,IF(RIGHT(H25,1)<>"年",H25*12,IF(LEN(H25)=3,VALUE(LEFT(H25,2))*12,IF(LEN(H25)=2,VALUE(LEFT(H25,1))*12,"??")))) -> 0 | L25: =DATE((YEAR(G25)+H25),MONTH(G25),DAY(G25)) -> 0 | M25: =MIN((YEAR(L25)-YEAR(G25))*12+(MONTH(L25)-MONTH(G25)),(YEAR($D$7)-YEAR(G25))*12+MONTH($D$7)-MONTH(G25),H25*12) -> 0 | N25: =IF(L25<$B$7,0,IF($D$7>L25,MIN(MONTH($D$7),DATEDIF(DATE(YEAR(G25),MONTH(G25),"1"),$D$7,"M")-DATEDIF(DATE(YEAR(G25),MONTH(G25),"1"),DATEDIF(YEAR(L25),MONTH(L25),"1"),"M")),MIN(DATEDIF(DATE(YEAR(G25),MONTH(G25),"1"),$D$7,"m"),MONTH($D$7)))) -> 0 | O25: =IF(K25=0,0,ROUND(((1-I25)/K25)*E25,4)) -> 0 | P25: =ROUND(O25*N25,2) -> 0 | Q25: =ROUND(J25-O25,2) -> 0 | R25: =ROUND(O25*M25,2) -> 0 | S25: =ROUND(F25-R25,2) -> 0
A26: 合计 | E26: =SUM(E9:E25) -> 0 | F26: =SUM(F9:F25) -> 0 | O26: =SUM(O9:O25) -> 0 | P26: =SUM(P9:P25) -> 0 | Q26: =SUM(Q9:Q25) -> 0 | R26: =SUM(R9:R25) -> 0 | S26: =SUM(S9:S25) -> 0
A27: 其中：
A28: =底稿目录!A9 -> 种植业 | E28: =SUMPRODUCT(($A$9:$A$25=$A28)*(E$9:E$25)) -> 0 | F28: =SUMPRODUCT(($A$9:$A$25=$A28)*(F$9:F$25)) -> 0 | O28: =SUMPRODUCT(($A$9:$A$25=$A28)*(O$9:O$25)) -> 0 | P28: =SUMPRODUCT(($A$9:$A$25=$A28)*(P$9:P$25)) -> 0 | Q28: =SUMPRODUCT(($A$9:$A$25=$A28)*(Q$9:Q$25)) -> 0 | R28: =SUMPRODUCT(($A$9:$A$25=$A28)*(R$9:R$25)) -> 0 | S28: =SUMPRODUCT(($A$9:$A$25=$A28)*(S$9:S$25)) -> 0
A29: =底稿目录!A10 -> 畜牧养殖业 | E29: =SUMPRODUCT(($A$9:$A$25=$A29)*(E$9:E$25)) -> 0 | F29: =SUMPRODUCT(($A$9:$A$25=$A29)*(F$9:F$25)) -> 0 | O29: =SUMPRODUCT(($A$9:$A$25=$A29)*(O$9:O$25)) -> 0 | P29: =SUMPRODUCT(($A$9:$A$25=$A29)*(P$9:P$25)) -> 0 | Q29: =SUMPRODUCT(($A$9:$A$25=$A29)*(Q$9:Q$25)) -> 0 | R29: =SUMPRODUCT(($A$9:$A$25=$A29)*(R$9:R$25)) -> 0 | S29: =SUMPRODUCT(($A$9:$A$25=$A29)*(S$9:S$25)) -> 0
A30: =底稿目录!A11 -> 林业 | E30: =SUMPRODUCT(($A$9:$A$25=$A30)*(E$9:E$25)) -> 0 | F30: =SUMPRODUCT(($A$9:$A$25=$A30)*(F$9:F$25)) -> 0 | O30: =SUMPRODUCT(($A$9:$A$25=$A30)*(O$9:O$25)) -> 0 | P30: =SUMPRODUCT(($A$9:$A$25=$A30)*(P$9:P$25)) -> 0 | Q30: =SUMPRODUCT(($A$9:$A$25=$A30)*(Q$9:Q$25)) -> 0 | R30: =SUMPRODUCT(($A$9:$A$25=$A30)*(R$9:R$25)) -> 0 | S30: =SUMPRODUCT(($A$9:$A$25=$A30)*(S$9:S$25)) -> 0
A31: =底稿目录!A12 -> 水产业 | E31: =SUMPRODUCT(($A$9:$A$25=$A31)*(E$9:E$25)) -> 0 | F31: =SUMPRODUCT(($A$9:$A$25=$A31)*(F$9:F$25)) -> 0 | O31: =SUMPRODUCT(($A$9:$A$25=$A31)*(O$9:O$25)) -> 0 | P31: =SUMPRODUCT(($A$9:$A$25=$A31)*(P$9:P$25)) -> 0 | Q31: =SUMPRODUCT(($A$9:$A$25=$A31)*(Q$9:Q$25)) -> 0 | R31: =SUMPRODUCT(($A$9:$A$25=$A31)*(R$9:R$25)) -> 0 | S31: =SUMPRODUCT(($A$9:$A$25=$A31)*(S$9:S$25)) -> 0
A32: =底稿目录!A13 -> …… | E32: =SUMPRODUCT(($A$9:$A$25=$A32)*(E$9:E$25)) -> 0 | F32: =SUMPRODUCT(($A$9:$A$25=$A32)*(F$9:F$25)) -> 0 | O32: =SUMPRODUCT(($A$9:$A$25=$A32)*(O$9:O$25)) -> 0 | P32: =SUMPRODUCT(($A$9:$A$25=$A32)*(P$9:P$25)) -> 0 | Q32: =SUMPRODUCT(($A$9:$A$25=$A32)*(Q$9:Q$25)) -> 0 | R32: =SUMPRODUCT(($A$9:$A$25=$A32)*(R$9:R$25)) -> 0 | S32: =SUMPRODUCT(($A$9:$A$25=$A32)*(S$9:S$25)) -> 0
A33: 三、审计说明：
A36: 四、审计结论
A40: 提示：
A41: 《企业所得税法实施条例》
A42: 第六十二条生产性生物资产按照以下方法确定计税基础：
A43: （一）外购的生产性生物资产，以购买价款和支付的相关税费为计税基础；
A44: （二）通过捐赠、投资、非货币性资产交换、债务重组等方式取得的生产性生物资产，以该资产的公允价值和支付的相关税费为计税基础。
A45: 前款所称生产性生物资产，是指企业为生产农产品、提供劳务或者出租等而持有的生物资产，包括经济林、薪炭林、产畜和役畜等。
A47: 第六十三条生产性生物资产按照直线法计算的折旧，准予扣除。
A48: 企业应当自生产性生物资产投入使用月份的次月起计算折旧；停止使用的生产性生物资产，应当自停止使用月份的次月起停止计算折旧。
A49: 企业应当根据生产性生物资产的性质和使用情况，合理确定生产性生物资产的预计净残值。生产性生物资产的预计净残值一经确定，不得变更。
A51: 第六十四条生产性生物资产计算折旧的最低年限如下：
... A58: 第二十条 企业至少应当于每年年度终了对生产性生物资产的使用寿命、预计净残值和折旧方法进行复核。使用寿命或预计净残值的预期数与原先估计数有差异的，或者有关经济利益预期实现方式有重大改变的，应当作为会计估计变更，按照《企业会计准则第28 号--会计政策、会计估计变更和差错更正》处理，调整生产性生物资产的使用寿命或预计净残值或者改变折旧方法。

Sheet 折旧测算表（含减值）H7-11
A1: 致同会计师事务所
A2: 生产性生物资产折旧测算表
A3: =底稿目录!A2 -> 被审计单位： | G3: =底稿目录!A4 -> 编制人： | S3: =底稿目录!A6 -> 编制日期： | X3: 索引号： | Y3: H7-11
A4: =底稿目录!A3 -> 截止日： | G4: =底稿目录!A5 -> 复核人： | S4: =底稿目录!A7 -> 复核日期： | X4: 页 次：
A5: 一、审计目标：生产性生物资产以恰当的金额包括在财务报表中，与之相关的计价或分摊调整已恰当记录，相关披露已得到恰当计量和描述。
A6: 二、审计过程：
A7: 折旧期初： | B7: 45658 | C7: 折旧期末： | D7: 46022 | E7: 计提减值准备日期： | F7: 45782 | G7: 各列顺序请根据需要进行调整，行数请根据需要增加。非公式列输入数据时请使用“选择性粘贴-数值”。
A8: 生产性生物资产类别 | B8: 生产性生物资产编号 | C8: 生产性生物资产名称 | D8: 管理部门 | E8: 原值 | F8: 累计折旧 | G8: 减值准备 | H8: 开始使用日期 | I8: 使用年限 | J8: 残值率 | K8: 账面月折旧额 | L8: 使用月限 | M8: 测算到期日 | N8: 已提折旧月份 | O8: 截止计提减值准备日计提月份 | P8: 本期折旧月份 | Q8: 本期折旧月份（减值前） | R8: 本期折旧月份（减值后） | S8: 计提减值准备前月折旧 | T8: 计提减值准备前累计折旧 | U8: 计提减值准备后月折旧 | V8: 当期折旧费用 | W8: 月折旧额差异 | X8: 累计折旧费用 | Y8: 累计折旧额差异
L9: =IF(I9=0,0,IF(RIGHT(I9,1)<>"年",I9*12,IF(LEN(I9)=3,VALUE(LEFT(I9,2))*12,IF(LEN(I9)=2,VALUE(LEFT(I9,1))*12,"??")))) -> 0 | M9: =IF(DAY(H9)=1,IF(H9=0,0,DATE(YEAR(H9),MONTH(H9)+L9,DAY(H9))),IF(H9=0,0,DATE(YEAR(H9),MONTH(H9)+L9,DAY(H9)-1))) -> 0 | N9: =MIN(IF(AND(DAY(H9)=31,DAY($D$7)=30),IF(H9=0,0,IF(M9>$D$7,VALUE(DATEDIF(H9,MIN($D$7,M9),"m"))+1,VALUE(DATEDIF(H9,MIN($D$7,M9),"m")+2))),IF(H9=0,0,IF(M9>$D$7,DATEDIF(H9,MIN($D$7,M9),"m"),VALUE(DATEDIF(H9,MIN($D$7,M9),"m")+1)))),L9) -> 0 | O9: =IF(AND(DAY(H9)=31,DAY($F$7)=30),MIN(IF(H9=0,0,IF($F$7>H9,VALUE(DATEDIF(H9,$F$7,"m"))+1,0)),N9+1),MIN(IF(H9=0,0,IF($F$7>H9,DATEDIF(H9,$F$7,"m"),0)),N9)) -> 0 | P9: =IF(OR(H9=0,M9<$B$7),0,IF(AND(H9<$B$7,M9>$D$7),VALUE(DATEDIF($B$7,$D$7,"m")+1),IF(AND(H9<$B$7,M9<=$D$7),VALUE(DATEDIF($B$7,M9,"m")+1),IF(AND(H9>=$B$7,M9>$D$7),VALUE(DATEDIF(H9,$D$7,"m")),IF(AND(H9>=$B$7,M9<=$D$7),VALUE(DATEDIF(H9,M9,"m")+1),))))) -> 0 | Q9: =IF(AND(YEAR(H9)=YEAR($D$7),DAY(H9)=31,DAY($D$7)=30),IF(H9>$F$7,0,P9-R9+1),IF(H9>$F$7,0,P9-R9)) -> 0 | R9: =IF(AND(DAY($F$7)=31,DAY($D$7)=30),IF(H9=0,0,IF($F$7<$B$7,P9,VALUE(DATEDIF(MAX(H9,$F$7),MIN(M9,$D$7),"m")))+1),IF(H9=0,0,IF($F$7<$B$7,P9,DATEDIF(MAX(H9,$F$7),MIN(M9,$D$7),"m")))) -> 0 | S9: =IF(L9=0,0,ROUND(((1-J9)/L9)*E9,4)) -> 0 | T9: =ROUND(S9*O9,2) -> 0 | U9: =IF((E9*(1-J9)-T9-G9)>0,(E9*(1-J9)-T9-G9)/(L9-O9),0) -> 0 | V9: =ROUND(S9*Q9,2)+ROUND(U9*R9,2) -> 0 | W9: =ROUND(K9-U9,2) -> 0 | X9: =ROUND(S9*O9,2)+ROUND(U9*(N9-O9),2) -> 0 | Y9: =ROUND(F9-X9,2) -> 0
L10: =IF(I10=0,0,IF(RIGHT(I10,1)<>"年",I10*12,IF(LEN(I10)=3,VALUE(LEFT(I10,2))*12,IF(LEN(I10)=2,VALUE(LEFT(I10,1))*12,"??")))) -> 0 | M10: =IF(DAY(H10)=1,IF(H10=0,0,DATE(YEAR(H10),MONTH(H10)+L10,DAY(H10))),IF(H10=0,0,DATE(YEAR(H10),MONTH(H10)+L10,DAY(H10)-1))) -> 0 | N10: =MIN(IF(AND(DAY(H10)=31,DAY($D$7)=30),IF(H10=0,0,IF(M10>$D$7,VALUE(DATEDIF(H10,MIN($D$7,M10),"m"))+1,VALUE(DATEDIF(H10,MIN($D$7,M10),"m")+2))),IF(H10=0,0,IF(M10>$D$7,DATEDIF(H10,MIN($D$7,M10),"m"),VALUE(DATEDIF(H10,MIN($D$7,M10),"m")+1)))),L10) -> 0 | O10: =IF(AND(DAY(H10)=31,DAY($F$7)=30),MIN(IF(H10=0,0,IF($F$7>H10,VALUE(DATEDIF(H10,$F$7,"m"))+1,0)),N10+1),MIN(IF(H10=0,0,IF($F$7>H10,DATEDIF(H10,$F$7,"m"),0)),N10)) -> 0 | P10: =IF(OR(H10=0,M10<$B$7),0,IF(AND(H10<$B$7,M10>$D$7),VALUE(DATEDIF($B$7,$D$7,"m")+1),IF(AND(H10<$B$7,M10<=$D$7),VALUE(DATEDIF($B$7,M10,"m")+1),IF(AND(H10>=$B$7,M10>$D$7),VALUE(DATEDIF(H10,$D$7,"m")),IF(AND(H10>=$B$7,M10<=$D$7),VALUE(DATEDIF(H10,M10,"m")+1),))))) -> 0 | Q10: =IF(AND(YEAR(H10)=YEAR($D$7),DAY(H10)=31,DAY($D$7)=30),IF(H10>$F$7,0,P10-R10+1),IF(H10>$F$7,0,P10-R10)) -> 0 | R10: =IF(AND(DAY($F$7)=31,DAY($D$7)=30),IF(H10=0,0,IF($F$7<$B$7,P10,VALUE(DATEDIF(MAX(H10,$F$7),MIN(M10,$D$7),"m")))+1),IF(H10=0,0,IF($F$7<$B$7,P10,DATEDIF(MAX(H10,$F$7),MIN(M10,$D$7),"m")))) -> 0 | S10: =IF(L10=0,0,ROUND(((1-J10)/L10)*E10,4)) -> 0 | T10: =ROUND(S10*O10,2) -> 0 | U10: =IF((E10*(1-J10)-T10-G10)>0,(E10*(1-J10)-T10-G10)/(L10-O10),0) -> 0 | V10: =ROUND(S10*Q10,2)+ROUND(U10*R10,2) -> 0 | W10: =ROUND(K10-U10,2) -> 0 | X10: =ROUND(S10*O10,2)+ROUND(U10*(N10-O10),2) -> 0 | Y10: =ROUND(F10-X10,2) -> 0
L11: =IF(I11=0,0,IF(RIGHT(I11,1)<>"年",I11*12,IF(LEN(I11)=3,VALUE(LEFT(I11,2))*12,IF(LEN(I11)=2,VALUE(LEFT(I11,1))*12,"??")))) -> 0 | M11: =IF(DAY(H11)=1,IF(H11=0,0,DATE(YEAR(H11),MONTH(H11)+L11,DAY(H11))),IF(H11=0,0,DATE(YEAR(H11),MONTH(H11)+L11,DAY(H11)-1))) -> 0 | N11: =MIN(IF(AND(DAY(H11)=31,DAY($D$7)=30),IF(H11=0,0,IF(M11>$D$7,VALUE(DATEDIF(H11,MIN($D$7,M11),"m"))+1,VALUE(DATEDIF(H11,MIN($D$7,M11),"m")+2))),IF(H11=0,0,IF(M11>$D$7,DATEDIF(H11,MIN($D$7,M11),"m"),VALUE(DATEDIF(H11,MIN($D$7,M11),"m")+1)))),L11) -> 0 | O11: =IF(AND(DAY(H11)=31,DAY($F$7)=30),MIN(IF(H11=0,0,IF($F$7>H11,VALUE(DATEDIF(H11,$F$7,"m"))+1,0)),N11+1),MIN(IF(H11=0,0,IF($F$7>H11,DATEDIF(H11,$F$7,"m"),0)),N11)) -> 0 | P11: =IF(OR(H11=0,M11<$B$7),0,IF(AND(H11<$B$7,M11>$D$7),VALUE(DATEDIF($B$7,$D$7,"m")+1),IF(AND(H11<$B$7,M11<=$D$7),VALUE(DATEDIF($B$7,M11,"m")+1),IF(AND(H11>=$B$7,M11>$D$7),VALUE(DATEDIF(H11,$D$7,"m")),IF(AND(H11>=$B$7,M11<=$D$7),VALUE(DATEDIF(H11,M11,"m")+1),))))) -> 0 | Q11: =IF(AND(YEAR(H11)=YEAR($D$7),DAY(H11)=31,DAY($D$7)=30),IF(H11>$F$7,0,P11-R11+1),IF(H11>$F$7,0,P11-R11)) -> 0 | R11: =IF(AND(DAY($F$7)=31,DAY($D$7)=30),IF(H11=0,0,IF($F$7<$B$7,P11,VALUE(DATEDIF(MAX(H11,$F$7),MIN(M11,$D$7),"m")))+1),IF(H11=0,0,IF($F$7<$B$7,P11,DATEDIF(MAX(H11,$F$7),MIN(M11,$D$7),"m")))) -> 0 | S11: =IF(L11=0,0,ROUND(((1-J11)/L11)*E11,4)) -> 0 | T11: =ROUND(S11*O11,2) -> 0 | U11: =IF((E11*(1-J11)-T11-G11)>0,(E11*(1-J11)-T11-G11)/(L11-O11),0) -> 0 | V11: =ROUND(S11*Q11,2)+ROUND(U11*R11,2) -> 0 | W11: =ROUND(K11-U11,2) -> 0 | X11: =ROUND(S11*O11,2)+ROUND(U11*(N11-O11),2) -> 0 | Y11: =ROUND(F11-X11,2) -> 0
L12: =IF(I12=0,0,IF(RIGHT(I12,1)<>"年",I12*12,IF(LEN(I12)=3,VALUE(LEFT(I12,2))*12,IF(LEN(I12)=2,VALUE(LEFT(I12,1))*12,"??")))) -> 0 | M12: =IF(DAY(H12)=1,IF(H12=0,0,DATE(YEAR(H12),MONTH(H12)+L12,DAY(H12))),IF(H12=0,0,DATE(YEAR(H12),MONTH(H12)+L12,DAY(H12)-1))) -> 0 | N12: =MIN(IF(AND(DAY(H12)=31,DAY($D$7)=30),IF(H12=0,0,IF(M12>$D$7,VALUE(DATEDIF(H12,MIN($D$7,M12),"m"))+1,VALUE(DATEDIF(H12,MIN($D$7,M12),"m")+2))),IF(H12=0,0,IF(M12>$D$7,DATEDIF(H12,MIN($D$7,M12),"m"),VALUE(DATEDIF(H12,MIN($D$7,M12),"m")+1)))),L12) -> 0 | O12: =IF(AND(DAY(H12)=31,DAY($F$7)=30),MIN(IF(H12=0,0,IF($F$7>H12,VALUE(DATEDIF(H12,$F$7,"m"))+1,0)),N12+1),MIN(IF(H12=0,0,IF($F$7>H12,DATEDIF(H12,$F$7,"m"),0)),N12)) -> 0 | P12: =IF(OR(H12=0,M12<$B$7),0,IF(AND(H12<$B$7,M12>$D$7),VALUE(DATEDIF($B$7,$D$7,"m")+1),IF(AND(H12<$B$7,M12<=$D$7),VALUE(DATEDIF($B$7,M12,"m")+1),IF(AND(H12>=$B$7,M12>$D$7),VALUE(DATEDIF(H12,$D$7,"m")),IF(AND(H12>=$B$7,M12<=$D$7),VALUE(DATEDIF(H12,M12,"m")+1),))))) -> 0 | Q12: =IF(AND(YEAR(H12)=YEAR($D$7),DAY(H12)=31,DAY($D$7)=30),IF(H12>$F$7,0,P12-R12+1),IF(H12>$F$7,0,P12-R12)) -> 0 | R12: =IF(AND(DAY($F$7)=31,DAY($D$7)=30),IF(H12=0,0,IF($F$7<$B$7,P12,VALUE(DATEDIF(MAX(H12,$F$7),MIN(M12,$D$7),"m")))+1),IF(H12=0,0,IF($F$7<$B$7,P12,DATEDIF(MAX(H12,$F$7),MIN(M12,$D$7),"m")))) -> 0 | S12: =IF(L12=0,0,ROUND(((1-J12)/L12)*E12,4)) -> 0 | T12: =ROUND(S12*O12,2) -> 0 | U12: =IF((E12*(1-J12)-T12-G12)>0,(E12*(1-J12)-T12-G12)/(L12-O12),0) -> 0 | V12: =ROUND(S12*Q12,2)+ROUND(U12*R12,2) -> 0 | W12: =ROUND(K12-U12,2) -> 0 | X12: =ROUND(S12*O12,2)+ROUND(U12*(N12-O12),2) -> 0 | Y12: =ROUND(F12-X12,2) -> 0
L13: =IF(I13=0,0,IF(RIGHT(I13,1)<>"年",I13*12,IF(LEN(I13)=3,VALUE(LEFT(I13,2))*12,IF(LEN(I13)=2,VALUE(LEFT(I13,1))*12,"??")))) -> 0 | M13: =IF(DAY(H13)=1,IF(H13=0,0,DATE(YEAR(H13),MONTH(H13)+L13,DAY(H13))),IF(H13=0,0,DATE(YEAR(H13),MONTH(H13)+L13,DAY(H13)-1))) -> 0 | N13: =MIN(IF(AND(DAY(H13)=31,DAY($D$7)=30),IF(H13=0,0,IF(M13>$D$7,VALUE(DATEDIF(H13,MIN($D$7,M13),"m"))+1,VALUE(DATEDIF(H13,MIN($D$7,M13),"m")+2))),IF(H13=0,0,IF(M13>$D$7,DATEDIF(H13,MIN($D$7,M13),"m"),VALUE(DATEDIF(H13,MIN($D$7,M13),"m")+1)))),L13) -> 0 | O13: =IF(AND(DAY(H13)=31,DAY($F$7)=30),MIN(IF(H13=0,0,IF($F$7>H13,VALUE(DATEDIF(H13,$F$7,"m"))+1,0)),N13+1),MIN(IF(H13=0,0,IF($F$7>H13,DATEDIF(H13,$F$7,"m"),0)),N13)) -> 0 | P13: =IF(OR(H13=0,M13<$B$7),0,IF(AND(H13<$B$7,M13>$D$7),VALUE(DATEDIF($B$7,$D$7,"m")+1),IF(AND(H13<$B$7,M13<=$D$7),VALUE(DATEDIF($B$7,M13,"m")+1),IF(AND(H13>=$B$7,M13>$D$7),VALUE(DATEDIF(H13,$D$7,"m")),IF(AND(H13>=$B$7,M13<=$D$7),VALUE(DATEDIF(H13,M13,"m")+1),))))) -> 0 | Q13: =IF(AND(YEAR(H13)=YEAR($D$7),DAY(H13)=31,DAY($D$7)=30),IF(H13>$F$7,0,P13-R13+1),IF(H13>$F$7,0,P13-R13)) -> 0 | R13: =IF(AND(DAY($F$7)=31,DAY($D$7)=30),IF(H13=0,0,IF($F$7<$B$7,P13,VALUE(DATEDIF(MAX(H13,$F$7),MIN(M13,$D$7),"m")))+1),IF(H13=0,0,IF($F$7<$B$7,P13,DATEDIF(MAX(H13,$F$7),MIN(M13,$D$7),"m")))) -> 0 | S13: =IF(L13=0,0,ROUND(((1-J13)/L13)*E13,4)) -> 0 | T13: =ROUND(S13*O13,2) -> 0 | U13: =IF((E13*(1-J13)-T13-G13)>0,(E13*(1-J13)-T13-G13)/(L13-O13),0) -> 0 | V13: =ROUND(S13*Q13,2)+ROUND(U13*R13,2) -> 0 | W13: =ROUND(K13-U13,2) -> 0 | X13: =ROUND(S13*O13,2)+ROUND(U13*(N13-O13),2) -> 0 | Y13: =ROUND(F13-X13,2) -> 0
L14: =IF(I14=0,0,IF(RIGHT(I14,1)<>"年",I14*12,IF(LEN(I14)=3,VALUE(LEFT(I14,2))*12,IF(LEN(I14)=2,VALUE(LEFT(I14,1))*12,"??")))) -> 0 | M14: =IF(DAY(H14)=1,IF(H14=0,0,DATE(YEAR(H14),MONTH(H14)+L14,DAY(H14))),IF(H14=0,0,DATE(YEAR(H14),MONTH(H14)+L14,DAY(H14)-1))) -> 0 | N14: =MIN(IF(AND(DAY(H14)=31,DAY($D$7)=30),IF(H14=0,0,IF(M14>$D$7,VALUE(DATEDIF(H14,MIN($D$7,M14),"m"))+1,VALUE(DATEDIF(H14,MIN($D$7,M14),"m")+2))),IF(H14=0,0,IF(M14>$D$7,DATEDIF(H14,MIN($D$7,M14),"m"),VALUE(DATEDIF(H14,MIN($D$7,M14),"m")+1)))),L14) -> 0 | O14: =IF(AND(DAY(H14)=31,DAY($F$7)=30),MIN(IF(H14=0,0,IF($F$7>H14,VALUE(DATEDIF(H14,$F$7,"m"))+1,0)),N14+1),MIN(IF(H14=0,0,IF($F$7>H14,DATEDIF(H14,$F$7,"m"),0)),N14)) -> 0 | P14: =IF(OR(H14=0,M14<$B$7),0,IF(AND(H14<$B$7,M14>$D$7),VALUE(DATEDIF($B$7,$D$7,"m")+1),IF(AND(H14<$B$7,M14<=$D$7),VALUE(DATEDIF($B$7,M14,"m")+1),IF(AND(H14>=$B$7,M14>$D$7),VALUE(DATEDIF(H14,$D$7,"m")),IF(AND(H14>=$B$7,M14<=$D$7),VALUE(DATEDIF(H14,M14,"m")+1),))))) -> 0 | Q14: =IF(AND(YEAR(H14)=YEAR($D$7),DAY(H14)=31,DAY($D$7)=30),IF(H14>$F$7,0,P14-R14+1),IF(H14>$F$7,0,P14-R14)) -> 0 | R14: =IF(AND(DAY($F$7)=31,DAY($D$7)=30),IF(H14=0,0,IF($F$7<$B$7,P14,VALUE(DATEDIF(MAX(H14,$F$7),MIN(M14,$D$7),"m")))+1),IF(H14=0,0,IF($F$7<$B$7,P14,DATEDIF(MAX(H14,$F$7),MIN(M14,$D$7),"m")))) -> 0 | S14: =IF(L14=0,0,ROUND(((1-J14)/L14)*E14,4)) -> 0 | T14: =ROUND(S14*O14,2) -> 0 | U14: =IF((E14*(1-J14)-T14-G14)>0,(E14*(1-J14)-T14-G14)/(L14-O14),0) -> 0 | V14: =ROUND(S14*Q14,2)+ROUND(U14*R14,2) -> 0 | W14: =ROUND(K14-U14,2) -> 0 | X14: =ROUND(S14*O14,2)+ROUND(U14*(N14-O14),2) -> 0 | Y14: =ROUND(F14-X14,2) -> 0
L15: =IF(I15=0,0,IF(RIGHT(I15,1)<>"年",I15*12,IF(LEN(I15)=3,VALUE(LEFT(I15,2))*12,IF(LEN(I15)=2,VALUE(LEFT(I15,1))*12,"??")))) -> 0 | M15: =IF(DAY(H15)=1,IF(H15=0,0,DATE(YEAR(H15),MONTH(H15)+L15,DAY(H15))),IF(H15=0,0,DATE(YEAR(H15),MONTH(H15)+L15,DAY(H15)-1))) -> 0 | N15: =MIN(IF(AND(DAY(H15)=31,DAY($D$7)=30),IF(H15=0,0,IF(M15>$D$7,VALUE(DATEDIF(H15,MIN($D$7,M15),"m"))+1,VALUE(DATEDIF(H15,MIN($D$7,M15),"m")+2))),IF(H15=0,0,IF(M15>$D$7,DATEDIF(H15,MIN($D$7,M15),"m"),VALUE(DATEDIF(H15,MIN($D$7,M15),"m")+1)))),L15) -> 0 | O15: =IF(AND(DAY(H15)=31,DAY($F$7)=30),MIN(IF(H15=0,0,IF($F$7>H15,VALUE(DATEDIF(H15,$F$7,"m"))+1,0)),N15+1),MIN(IF(H15=0,0,IF($F$7>H15,DATEDIF(H15,$F$7,"m"),0)),N15)) -> 0 | P15: =IF(OR(H15=0,M15<$B$7),0,IF(AND(H15<$B$7,M15>$D$7),VALUE(DATEDIF($B$7,$D$7,"m")+1),IF(AND(H15<$B$7,M15<=$D$7),VALUE(DATEDIF($B$7,M15,"m")+1),IF(AND(H15>=$B$7,M15>$D$7),VALUE(DATEDIF(H15,$D$7,"m")),IF(AND(H15>=$B$7,M15<=$D$7),VALUE(DATEDIF(H15,M15,"m")+1),))))) -> 0 | Q15: =IF(AND(YEAR(H15)=YEAR($D$7),DAY(H15)=31,DAY($D$7)=30),IF(H15>$F$7,0,P15-R15+1),IF(H15>$F$7,0,P15-R15)) -> 0 | R15: =IF(AND(DAY($F$7)=31,DAY($D$7)=30),IF(H15=0,0,IF($F$7<$B$7,P15,VALUE(DATEDIF(MAX(H15,$F$7),MIN(M15,$D$7),"m")))+1),IF(H15=0,0,IF($F$7<$B$7,P15,DATEDIF(MAX(H15,$F$7),MIN(M15,$D$7),"m")))) -> 0 | S15: =IF(L15=0,0,ROUND(((1-J15)/L15)*E15,4)) -> 0 | T15: =ROUND(S15*O15,2) -> 0 | U15: =IF((E15*(1-J15)-T15-G15)>0,(E15*(1-J15)-T15-G15)/(L15-O15),0) -> 0 | V15: =ROUND(S15*Q15,2)+ROUND(U15*R15,2) -> 0 | W15: =ROUND(K15-U15,2) -> 0 | X15: =ROUND(S15*O15,2)+ROUND(U15*(N15-O15),2) -> 0 | Y15: =ROUND(F15-X15,2) -> 0
L16: =IF(I16=0,0,IF(RIGHT(I16,1)<>"年",I16*12,IF(LEN(I16)=3,VALUE(LEFT(I16,2))*12,IF(LEN(I16)=2,VALUE(LEFT(I16,1))*12,"??")))) -> 0 | M16: =IF(DAY(H16)=1,IF(H16=0,0,DATE(YEAR(H16),MONTH(H16)+L16,DAY(H16))),IF(H16=0,0,DATE(YEAR(H16),MONTH(H16)+L16,DAY(H16)-1))) -> 0 | N16: =MIN(IF(AND(DAY(H16)=31,DAY($D$7)=30),IF(H16=0,0,IF(M16>$D$7,VALUE(DATEDIF(H16,MIN($D$7,M16),"m"))+1,VALUE(DATEDIF(H16,MIN($D$7,M16),"m")+2))),IF(H16=0,0,IF(M16>$D$7,DATEDIF(H16,MIN($D$7,M16),"m"),VALUE(DATEDIF(H16,MIN($D$7,M16),"m")+1)))),L16) -> 0 | O16: =IF(AND(DAY(H16)=31,DAY($F$7)=30),MIN(IF(H16=0,0,IF($F$7>H16,VALUE(DATEDIF(H16,$F$7,"m"))+1,0)),N16+1),MIN(IF(H16=0,0,IF($F$7>H16,DATEDIF(H16,$F$7,"m"),0)),N16)) -> 0 | P16: =IF(OR(H16=0,M16<$B$7),0,IF(AND(H16<$B$7,M16>$D$7),VALUE(DATEDIF($B$7,$D$7,"m")+1),IF(AND(H16<$B$7,M16<=$D$7),VALUE(DATEDIF($B$7,M16,"m")+1),IF(AND(H16>=$B$7,M16>$D$7),VALUE(DATEDIF(H16,$D$7,"m")),IF(AND(H16>=$B$7,M16<=$D$7),VALUE(DATEDIF(H16,M16,"m")+1),))))) -> 0 | Q16: =IF(AND(YEAR(H16)=YEAR($D$7),DAY(H16)=31,DAY($D$7)=30),IF(H16>$F$7,0,P16-R16+1),IF(H16>$F$7,0,P16-R16)) -> 0 | R16: =IF(AND(DAY($F$7)=31,DAY($D$7)=30),IF(H16=0,0,IF($F$7<$B$7,P16,VALUE(DATEDIF(MAX(H16,$F$7),MIN(M16,$D$7),"m")))+1),IF(H16=0,0,IF($F$7<$B$7,P16,DATEDIF(MAX(H16,$F$7),MIN(M16,$D$7),"m")))) -> 0 | S16: =IF(L16=0,0,ROUND(((1-J16)/L16)*E16,4)) -> 0 | T16: =ROUND(S16*O16,2) -> 0 | U16: =IF((E16*(1-J16)-T16-G16)>0,(E16*(1-J16)-T16-G16)/(L16-O16),0) -> 0 | V16: =ROUND(S16*Q16,2)+ROUND(U16*R16,2) -> 0 | W16: =ROUND(K16-U16,2) -> 0 | X16: =ROUND(S16*O16,2)+ROUND(U16*(N16-O16),2) -> 0 | Y16: =ROUND(F16-X16,2) -> 0
L17: =IF(I17=0,0,IF(RIGHT(I17,1)<>"年",I17*12,IF(LEN(I17)=3,VALUE(LEFT(I17,2))*12,IF(LEN(I17)=2,VALUE(LEFT(I17,1))*12,"??")))) -> 0 | M17: =IF(DAY(H17)=1,IF(H17=0,0,DATE(YEAR(H17),MONTH(H17)+L17,DAY(H17))),IF(H17=0,0,DATE(YEAR(H17),MONTH(H17)+L17,DAY(H17)-1))) -> 0 | N17: =MIN(IF(AND(DAY(H17)=31,DAY($D$7)=30),IF(H17=0,0,IF(M17>$D$7,VALUE(DATEDIF(H17,MIN($D$7,M17),"m"))+1,VALUE(DATEDIF(H17,MIN($D$7,M17),"m")+2))),IF(H17=0,0,IF(M17>$D$7,DATEDIF(H17,MIN($D$7,M17),"m"),VALUE(DATEDIF(H17,MIN($D$7,M17),"m")+1)))),L17) -> 0 | O17: =IF(AND(DAY(H17)=31,DAY($F$7)=30),MIN(IF(H17=0,0,IF($F$7>H17,VALUE(DATEDIF(H17,$F$7,"m"))+1,0)),N17+1),MIN(IF(H17=0,0,IF($F$7>H17,DATEDIF(H17,$F$7,"m"),0)),N17)) -> 0 | P17: =IF(OR(H17=0,M17<$B$7),0,IF(AND(H17<$B$7,M17>$D$7),VALUE(DATEDIF($B$7,$D$7,"m")+1),IF(AND(H17<$B$7,M17<=$D$7),VALUE(DATEDIF($B$7,M17,"m")+1),IF(AND(H17>=$B$7,M17>$D$7),VALUE(DATEDIF(H17,$D$7,"m")),IF(AND(H17>=$B$7,M17<=$D$7),VALUE(DATEDIF(H17,M17,"m")+1),))))) -> 0 | Q17: =IF(AND(YEAR(H17)=YEAR($D$7),DAY(H17)=31,DAY($D$7)=30),IF(H17>$F$7,0,P17-R17+1),IF(H17>$F$7,0,P17-R17)) -> 0 | R17: =IF(AND(DAY($F$7)=31,DAY($D$7)=30),IF(H17=0,0,IF($F$7<$B$7,P17,VALUE(DATEDIF(MAX(H17,$F$7),MIN(M17,$D$7),"m")))+1),IF(H17=0,0,IF($F$7<$B$7,P17,DATEDIF(MAX(H17,$F$7),MIN(M17,$D$7),"m")))) -> 0 | S17: =IF(L17=0,0,ROUND(((1-J17)/L17)*E17,4)) -> 0 | T17: =ROUND(S17*O17,2) -> 0 | U17: =IF((E17*(1-J17)-T17-G17)>0,(E17*(1-J17)-T17-G17)/(L17-O17),0) -> 0 | V17: =ROUND(S17*Q17,2)+ROUND(U17*R17,2) -> 0 | W17: =ROUND(K17-U17,2) -> 0 | X17: =ROUND(S17*O17,2)+ROUND(U17*(N17-O17),2) -> 0 | Y17: =ROUND(F17-X17,2) -> 0
L18: =IF(I18=0,0,IF(RIGHT(I18,1)<>"年",I18*12,IF(LEN(I18)=3,VALUE(LEFT(I18,2))*12,IF(LEN(I18)=2,VALUE(LEFT(I18,1))*12,"??")))) -> 0 | M18: =IF(DAY(H18)=1,IF(H18=0,0,DATE(YEAR(H18),MONTH(H18)+L18,DAY(H18))),IF(H18=0,0,DATE(YEAR(H18),MONTH(H18)+L18,DAY(H18)-1))) -> 0 | N18: =MIN(IF(AND(DAY(H18)=31,DAY($D$7)=30),IF(H18=0,0,IF(M18>$D$7,VALUE(DATEDIF(H18,MIN($D$7,M18),"m"))+1,VALUE(DATEDIF(H18,MIN($D$7,M18),"m")+2))),IF(H18=0,0,IF(M18>$D$7,DATEDIF(H18,MIN($D$7,M18),"m"),VALUE(DATEDIF(H18,MIN($D$7,M18),"m")+1)))),L18) -> 0 | O18: =IF(AND(DAY(H18)=31,DAY($F$7)=30),MIN(IF(H18=0,0,IF($F$7>H18,VALUE(DATEDIF(H18,$F$7,"m"))+1,0)),N18+1),MIN(IF(H18=0,0,IF($F$7>H18,DATEDIF(H18,$F$7,"m"),0)),N18)) -> 0 | P18: =IF(OR(H18=0,M18<$B$7),0,IF(AND(H18<$B$7,M18>$D$7),VALUE(DATEDIF($B$7,$D$7,"m")+1),IF(AND(H18<$B$7,M18<=$D$7),VALUE(DATEDIF($B$7,M18,"m")+1),IF(AND(H18>=$B$7,M18>$D$7),VALUE(DATEDIF(H18,$D$7,"m")),IF(AND(H18>=$B$7,M18<=$D$7),VALUE(DATEDIF(H18,M18,"m")+1),))))) -> 0 | Q18: =IF(AND(YEAR(H18)=YEAR($D$7),DAY(H18)=31,DAY($D$7)=30),IF(H18>$F$7,0,P18-R18+1),IF(H18>$F$7,0,P18-R18)) -> 0 | R18: =IF(AND(DAY($F$7)=31,DAY($D$7)=30),IF(H18=0,0,IF($F$7<$B$7,P18,VALUE(DATEDIF(MAX(H18,$F$7),MIN(M18,$D$7),"m")))+1),IF(H18=0,0,IF($F$7<$B$7,P18,DATEDIF(MAX(H18,$F$7),MIN(M18,$D$7),"m")))) -> 0 | S18: =IF(L18=0,0,ROUND(((1-J18)/L18)*E18,4)) -> 0 | T18: =ROUND(S18*O18,2) -> 0 | U18: =IF((E18*(1-J18)-T18-G18)>0,(E18*(1-J18)-T18-G18)/(L18-O18),0) -> 0 | V18: =ROUND(S18*Q18,2)+ROUND(U18*R18,2) -> 0 | W18: =ROUND(K18-U18,2) -> 0 | X18: =ROUND(S18*O18,2)+ROUND(U18*(N18-O18),2) -> 0 | Y18: =ROUND(F18-X18,2) -> 0
L19: =IF(I19=0,0,IF(RIGHT(I19,1)<>"年",I19*12,IF(LEN(I19)=3,VALUE(LEFT(I19,2))*12,IF(LEN(I19)=2,VALUE(LEFT(I19,1))*12,"??")))) -> 0 | M19: =IF(DAY(H19)=1,IF(H19=0,0,DATE(YEAR(H19),MONTH(H19)+L19,DAY(H19))),IF(H19=0,0,DATE(YEAR(H19),MONTH(H19)+L19,DAY(H19)-1))) -> 0 | N19: =MIN(IF(AND(DAY(H19)=31,DAY($D$7)=30),IF(H19=0,0,IF(M19>$D$7,VALUE(DATEDIF(H19,MIN($D$7,M19),"m"))+1,VALUE(DATEDIF(H19,MIN($D$7,M19),"m")+2))),IF(H19=0,0,IF(M19>$D$7,DATEDIF(H19,MIN($D$7,M19),"m"),VALUE(DATEDIF(H19,MIN($D$7,M19),"m")+1)))),L19) -> 0 | O19: =IF(AND(DAY(H19)=31,DAY($F$7)=30),MIN(IF(H19=0,0,IF($F$7>H19,VALUE(DATEDIF(H19,$F$7,"m"))+1,0)),N19+1),MIN(IF(H19=0,0,IF($F$7>H19,DATEDIF(H19,$F$7,"m"),0)),N19)) -> 0 | P19: =IF(OR(H19=0,M19<$B$7),0,IF(AND(H19<$B$7,M19>$D$7),VALUE(DATEDIF($B$7,$D$7,"m")+1),IF(AND(H19<$B$7,M19<=$D$7),VALUE(DATEDIF($B$7,M19,"m")+1),IF(AND(H19>=$B$7,M19>$D$7),VALUE(DATEDIF(H19,$D$7,"m")),IF(AND(H19>=$B$7,M19<=$D$7),VALUE(DATEDIF(H19,M19,"m")+1),))))) -> 0 | Q19: =IF(AND(YEAR(H19)=YEAR($D$7),DAY(H19)=31,DAY($D$7)=30),IF(H19>$F$7,0,P19-R19+1),IF(H19>$F$7,0,P19-R19)) -> 0 | R19: =IF(AND(DAY($F$7)=31,DAY($D$7)=30),IF(H19=0,0,IF($F$7<$B$7,P19,VALUE(DATEDIF(MAX(H19,$F$7),MIN(M19,$D$7),"m")))+1),IF(H19=0,0,IF($F$7<$B$7,P19,DATEDIF(MAX(H19,$F$7),MIN(M19,$D$7),"m")))) -> 0 | S19: =IF(L19=0,0,ROUND(((1-J19)/L19)*E19,4)) -> 0 | T19: =ROUND(S19*O19,2) -> 0 | U19: =IF((E19*(1-J19)-T19-G19)>0,(E19*(1-J19)-T19-G19)/(L19-O19),0) -> 0 | V19: =ROUND(S19*Q19,2)+ROUND(U19*R19,2) -> 0 | W19: =ROUND(K19-U19,2) -> 0 | X19: =ROUND(S19*O19,2)+ROUND(U19*(N19-O19),2) -> 0 | Y19: =ROUND(F19-X19,2) -> 0
L20: =IF(I20=0,0,IF(RIGHT(I20,1)<>"年",I20*12,IF(LEN(I20)=3,VALUE(LEFT(I20,2))*12,IF(LEN(I20)=2,VALUE(LEFT(I20,1))*12,"??")))) -> 0 | M20: =IF(DAY(H20)=1,IF(H20=0,0,DATE(YEAR(H20),MONTH(H20)+L20,DAY(H20))),IF(H20=0,0,DATE(YEAR(H20),MONTH(H20)+L20,DAY(H20)-1))) -> 0 | N20: =MIN(IF(AND(DAY(H20)=31,DAY($D$7)=30),IF(H20=0,0,IF(M20>$D$7,VALUE(DATEDIF(H20,MIN($D$7,M20),"m"))+1,VALUE(DATEDIF(H20,MIN($D$7,M20),"m")+2))),IF(H20=0,0,IF(M20>$D$7,DATEDIF(H20,MIN($D$7,M20),"m"),VALUE(DATEDIF(H20,MIN($D$7,M20),"m")+1)))),L20) -> 0 | O20: =IF(AND(DAY(H20)=31,DAY($F$7)=30),MIN(IF(H20=0,0,IF($F$7>H20,VALUE(DATEDIF(H20,$F$7,"m"))+1,0)),N20+1),MIN(IF(H20=0,0,IF($F$7>H20,DATEDIF(H20,$F$7,"m"),0)),N20)) -> 0 | P20: =IF(OR(H20=0,M20<$B$7),0,IF(AND(H20<$B$7,M20>$D$7),VALUE(DATEDIF($B$7,$D$7,"m")+1),IF(AND(H20<$B$7,M20<=$D$7),VALUE(DATEDIF($B$7,M20,"m")+1),IF(AND(H20>=$B$7,M20>$D$7),VALUE(DATEDIF(H20,$D$7,"m")),IF(AND(H20>=$B$7,M20<=$D$7),VALUE(DATEDIF(H20,M20,"m")+1),))))) -> 0 | Q20: =IF(AND(YEAR(H20)=YEAR($D$7),DAY(H20)=31,DAY($D$7)=30),IF(H20>$F$7,0,P20-R20+1),IF(H20>$F$7,0,P20-R20)) -> 0 | R20: =IF(AND(DAY($F$7)=31,DAY($D$7)=30),IF(H20=0,0,IF($F$7<$B$7,P20,VALUE(DATEDIF(MAX(H20,$F$7),MIN(M20,$D$7),"m")))+1),IF(H20=0,0,IF($F$7<$B$7,P20,DATEDIF(MAX(H20,$F$7),MIN(M20,$D$7),"m")))) -> 0 | S20: =IF(L20=0,0,ROUND(((1-J20)/L20)*E20,4)) -> 0 | T20: =ROUND(S20*O20,2) -> 0 | U20: =IF((E20*(1-J20)-T20-G20)>0,(E20*(1-J20)-T20-G20)/(L20-O20),0) -> 0 | V20: =ROUND(S20*Q20,2)+ROUND(U20*R20,2) -> 0 | W20: =ROUND(K20-U20,2) -> 0 | X20: =ROUND(S20*O20,2)+ROUND(U20*(N20-O20),2) -> 0 | Y20: =ROUND(F20-X20,2) -> 0
... L32: =IF(I32=0,0,IF(RIGHT(I32,1)<>"年",I32*12,IF(LEN(I32)=3,VALUE(LEFT(I32,2))*12,IF(LEN(I32)=2,VALUE(LEFT(I32,1))*12,"??")))) -> 0 | M32: =IF(DAY(H32)=1,IF(H32=0,0,DATE(YEAR(H32),MONTH(H32)+L32,DAY(H32))),IF(H32=0,0,DATE(YEAR(H32),MONTH(H32)+L32,DAY(H32)-1))) -> 0 | N32: =MIN(IF(AND(DAY(H32)=31,DAY($D$7)=30),IF(H32=0,0,IF(M32>$D$7,VALUE(DATEDIF(H32,MIN($D$7,M32),"m"))+1,VALUE(DATEDIF(H32,MIN($D$7,M32),"m")+2))),IF(H32=0,0,IF(M32>$D$7,DATEDIF(H32,MIN($D$7,M32),"m"),VALUE(DATEDIF(H32,MIN($D$7,M32),"m")+1)))),L32) -> 0 | O32: =IF(AND(DAY(H32)=31,DAY($F$7)=30),MIN(IF(H32=0,0,IF($F$7>H32,VALUE(DATEDIF(H32,$F$7,"m"))+1,0)),N32+1),MIN(IF(H32=0,0,IF($F$7>H32,DATEDIF(H32,$F$7,"m"),0)),N32)) -> 0 | P32: =IF(OR(H32=0,M32<$B$7),0,IF(AND(H32<$B$7,M32>$D$7),VALUE(DATEDIF($B$7,$D$7,"m")+1),IF(AND(H32<$B$7,M32<=$D$7),VALUE(DATEDIF($B$7,M32,"m")+1),IF(AND(H32>=$B$7,M32>$D$7),VALUE(DATEDIF(H32,$D$7,"m")),IF(AND(H32>=$B$7,M32<=$D$7),VALUE(DATEDIF(H32,M32,"m")+1),))))) -> 0 | Q32: =IF(AND(YEAR(H32)=YEAR($D$7),DAY(H32)=31,DAY($D$7)=30),IF(H32>$F$7,0,P32-R32+1),IF(H32>$F$7,0,P32-R32)) -> 0 | R32: =IF(AND(DAY($F$7)=31,DAY($D$7)=30),IF(H32=0,0,IF($F$7<$B$7,P32,VALUE(DATEDIF(MAX(H32,$F$7),MIN(M32,$D$7),"m")))+1),IF(H32=0,0,IF($F$7<$B$7,P32,DATEDIF(MAX(H32,$F$7),MIN(M32,$D$7),"m")))) -> 0 | S32: =IF(L32=0,0,ROUND(((1-J32)/L32)*E32,4)) -> 0 | T32: =ROUND(S32*O32,2) -> 0 | U32: =IF((E32*(1-J32)-T32-G32)>0,(E32*(1-J32)-T32-G32)/(L32-O32),0) -> 0 | V32: =ROUND(S32*Q32,2)+ROUND(U32*R32,2) -> 0 | W32: =ROUND(K32-U32,2) -> 0 | X32: =ROUND(S32*O32,2)+ROUND(U32*(N32-O32),2) -> 0 | Y32: =ROUND(F32-X32,2) -> 0
A33: 合计 | E33: =SUM(E9:E32) -> 0 | F33: =SUM(F9:F32) -> 0 | G33: =SUM(G9:G32) -> 0 | S33: =SUM(S9:S32) -> 0 | T33: =SUM(T9:T32) -> 0 | U33: =SUM(U9:U32) -> 0 | V33: =SUM(V9:V32) -> 0 | W33: =SUM(W9:W32) -> 0 | X33: =SUM(X9:X32) -> 0 | Y33: =SUM(Y9:Y32) -> 0
A34: 其中：
A35: =底稿目录!A9 -> 种植业 | E35: =SUMPRODUCT(($A$9:$A$32=$A35)*(E$9:E$32)) -> 0 | F35: =SUMPRODUCT(($A$9:$A$32=$A35)*(F$9:F$32)) -> 0 | G35: =SUMPRODUCT(($A$9:$A$32=$A35)*(G$9:G$32)) -> 0 | O35: =SUMPRODUCT(($A$9:$A$32=$A35)*(O$9:O$32)) -> 0 | P35: =SUMPRODUCT(($A$9:$A$32=$A35)*(P$9:P$32)) -> 0 | S35: =SUMPRODUCT(($A$9:$A$32=$A35)*(S$9:S$32)) -> 0 | T35: =SUMPRODUCT(($A$9:$A$32=$A35)*(T$9:T$32)) -> 0 | U35: =SUMPRODUCT(($A$9:$A$32=$A35)*(U$9:U$32)) -> 0 | V35: =SUMPRODUCT(($A$9:$A$32=$A35)*(V$9:V$32)) -> 0 | W35: =SUMPRODUCT(($A$9:$A$32=$A35)*(W$9:W$32)) -> 0 | X35: =SUMPRODUCT(($A$9:$A$32=$A35)*(X$9:X$32)) -> 0 | Y35: =SUMPRODUCT(($A$9:$A$32=$A35)*(Y$9:Y$32)) -> 0
A36: =底稿目录!A10 -> 畜牧养殖业 | E36: =SUMPRODUCT(($A$9:$A$32=$A36)*(E$9:E$32)) -> 0 | F36: =SUMPRODUCT(($A$9:$A$32=$A36)*(F$9:F$32)) -> 0 | G36: =SUMPRODUCT(($A$9:$A$32=$A36)*(G$9:G$32)) -> 0 | O36: =SUMPRODUCT(($A$9:$A$32=$A36)*(O$9:O$32)) -> 0 | P36: =SUMPRODUCT(($A$9:$A$32=$A36)*(P$9:P$32)) -> 0 | S36: =SUMPRODUCT(($A$9:$A$32=$A36)*(S$9:S$32)) -> 0 | T36: =SUMPRODUCT(($A$9:$A$32=$A36)*(T$9:T$32)) -> 0 | U36: =SUMPRODUCT(($A$9:$A$32=$A36)*(U$9:U$32)) -> 0 | V36: =SUMPRODUCT(($A$9:$A$32=$A36)*(V$9:V$32)) -> 0 | W36: =SUMPRODUCT(($A$9:$A$32=$A36)*(W$9:W$32)) -> 0 | X36: =SUMPRODUCT(($A$9:$A$32=$A36)*(X$9:X$32)) -> 0 | Y36: =SUMPRODUCT(($A$9:$A$32=$A36)*(Y$9:Y$32)) -> 0
A37: =底稿目录!A11 -> 林业 | E37: =SUMPRODUCT(($A$9:$A$32=$A37)*(E$9:E$32)) -> 0 | F37: =SUMPRODUCT(($A$9:$A$32=$A37)*(F$9:F$32)) -> 0 | G37: =SUMPRODUCT(($A$9:$A$32=$A37)*(G$9:G$32)) -> 0 | O37: =SUMPRODUCT(($A$9:$A$32=$A37)*(O$9:O$32)) -> 0 | P37: =SUMPRODUCT(($A$9:$A$32=$A37)*(P$9:P$32)) -> 0 | S37: =SUMPRODUCT(($A$9:$A$32=$A37)*(S$9:S$32)) -> 0 | T37: =SUMPRODUCT(($A$9:$A$32=$A37)*(T$9:T$32)) -> 0 | U37: =SUMPRODUCT(($A$9:$A$32=$A37)*(U$9:U$32)) -> 0 | V37: =SUMPRODUCT(($A$9:$A$32=$A37)*(V$9:V$32)) -> 0 | W37: =SUMPRODUCT(($A$9:$A$32=$A37)*(W$9:W$32)) -> 0 | X37: =SUMPRODUCT(($A$9:$A$32=$A37)*(X$9:X$32)) -> 0 | Y37: =SUMPRODUCT(($A$9:$A$32=$A37)*(Y$9:Y$32)) -> 0
A38: =底稿目录!A12 -> 水产业 | E38: =SUMPRODUCT(($A$9:$A$32=$A38)*(E$9:E$32)) -> 0 | F38: =SUMPRODUCT(($A$9:$A$32=$A38)*(F$9:F$32)) -> 0 | G38: =SUMPRODUCT(($A$9:$A$32=$A38)*(G$9:G$32)) -> 0 | O38: =SUMPRODUCT(($A$9:$A$32=$A38)*(O$9:O$32)) -> 0 | P38: =SUMPRODUCT(($A$9:$A$32=$A38)*(P$9:P$32)) -> 0 | S38: =SUMPRODUCT(($A$9:$A$32=$A38)*(S$9:S$32)) -> 0 | T38: =SUMPRODUCT(($A$9:$A$32=$A38)*(T$9:T$32)) -> 0 | U38: =SUMPRODUCT(($A$9:$A$32=$A38)*(U$9:U$32)) -> 0 | V38: =SUMPRODUCT(($A$9:$A$32=$A38)*(V$9:V$32)) -> 0 | W38: =SUMPRODUCT(($A$9:$A$32=$A38)*(W$9:W$32)) -> 0 | X38: =SUMPRODUCT(($A$9:$A$32=$A38)*(X$9:X$32)) -> 0 | Y38: =SUMPRODUCT(($A$9:$A$32=$A38)*(Y$9:Y$32)) -> 0
A39: =底稿目录!A13 -> …… | E39: =SUMPRODUCT(($A$9:$A$32=$A39)*(E$9:E$32)) -> 0 | F39: =SUMPRODUCT(($A$9:$A$32=$A39)*(F$9:F$32)) -> 0 | G39: =SUMPRODUCT(($A$9:$A$32=$A39)*(G$9:G$32)) -> 0 | O39: =SUMPRODUCT(($A$9:$A$32=$A39)*(O$9:O$32)) -> 0 | P39: =SUMPRODUCT(($A$9:$A$32=$A39)*(P$9:P$32)) -> 0 | S39: =SUMPRODUCT(($A$9:$A$32=$A39)*(S$9:S$32)) -> 0 | T39: =SUMPRODUCT(($A$9:$A$32=$A39)*(T$9:T$32)) -> 0 | U39: =SUMPRODUCT(($A$9:$A$32=$A39)*(U$9:U$32)) -> 0 | V39: =SUMPRODUCT(($A$9:$A$32=$A39)*(V$9:V$32)) -> 0 | W39: =SUMPRODUCT(($A$9:$A$32=$A39)*(W$9:W$32)) -> 0 | X39: =SUMPRODUCT(($A$9:$A$32=$A39)*(X$9:X$32)) -> 0 | Y39: =SUMPRODUCT(($A$9:$A$32=$A39)*(Y$9:Y$32)) -> 0
A40: 三、审计说明：
A42: 四、审计结论

Sheet 折旧分配分析表H7-12
A1: 致同会计师事务所
A2: 生产性生物资产折旧分配分析表
A3: =底稿目录!A2 -> 被审计单位： | D3: =底稿目录!A4 -> 编制人： | G3: =底稿目录!A6 -> 编制日期： | I3: 索引号： | J3: H7-12
A4: =底稿目录!A3 -> 截止日： | D4: =底稿目录!A5 -> 复核人： | G4: =底稿目录!A7 -> 复核日期： | I4: 页 次：
A5: 一、审计目标：生产性生物资产以恰当的金额包括在财务报表中，与之相关的计价或分摊调整已恰当记录，相关披露已得到恰当计量和描述。
A6: 二、审计过程：
A7: 序号 | B7: 生产性生物资产类别 | C7: 生产成本 | D7: 管理费用 | E7: … | I7: 合计 | J7: 备注
A8: 1 | I8: =SUM(C8:H8) -> 0
A9: 2 | I9: =SUM(C9:H9) -> 0
A10: 3 | I10: =SUM(C10:H10) -> 0
A11: 4 | I11: =SUM(C11:H11) -> 0
A12: 5 | I12: =SUM(C12:H12) -> 0
A13: 合计 | C13: =SUM(C8:C12) -> 0 | D13: =SUM(D8:D12) -> 0 | E13: =SUM(E8:E12) -> 0 | F13: =SUM(F8:F12) -> 0 | G13: =SUM(G8:G12) -> 0 | H13: =SUM(H8:H12) -> 0 | I13: =SUM(I8:I12) -> 0
B14: 勾稽关系情况 | C14: 勾稽一致，详见xx-XX | D14: 勾稽一致，详见xx-XX | E14: 勾稽一致，详见xx-XX | F14: 勾稽一致，详见xx-XX | G14: 勾稽一致，详见xx-XX | H14: 勾稽一致，详见xx-XX
A15: 三、审计说明：
A17: 四、审计结论：

Sheet 公允价值复核表H7-13
A1: 致同会计师事务所
A2: 生产性生物资产公允价值复核表
A3: =底稿目录!A2 -> 被审计单位： | D3: =底稿目录!A4 -> 编制人： | H3: =底稿目录!A6 -> 编制日期： | L3: 索引号： | M3: H7-13
A4: =底稿目录!A3 -> 截止日： | D4: =底稿目录!A5 -> 复核人： | H4: =底稿目录!A7 -> 复核日期： | L4: 页 次：
A5: 一、审计目标：生产性生物资产以恰当的金额包括在财务报表中，与之相关的计价或分摊调整已恰当记录，相关披露已得到恰当计量和描述。
A6: 二、审计过程：
A7: 生产性生物资产类别 | B7: 生产性生物资产名称 | C7: 账面数 | F7: 复核 | L7: 索引号 | M7: 备注
C8: 期初公允价值 | D8: 面积 | E8: 期末余额 | F8: 参考单价 | G8: 参考单价来源 | H8: 公允价值 | I8: 差异 | J8: 差异原因 | K8: 与上期计价方法是否一致
C9: ① | D9: ② | E9: ③ | F9: ④ | G9: ⑤ | H9: ⑥=②×④ | I9: ⑦=③-⑥ | J9: ⑧ | K9: ⑨
H10: =D10*F10 -> 0 | I10: =E10-H10 -> 0
H11: =D11*F11 -> 0 | I11: =E11-H11 -> 0
H12: =D12*F12 -> 0 | I12: =E12-H12 -> 0
H13: =D13*F13 -> 0 | I13: =E13-H13 -> 0
H14: =D14*F14 -> 0 | I14: =E14-H14 -> 0
H15: =D15*F15 -> 0 | I15: =E15-H15 -> 0
H16: =D16*F16 -> 0 | I16: =E16-H16 -> 0
H17: =D17*F17 -> 0 | I17: =E17-H17 -> 0
H18: =D18*F18 -> 0 | I18: =E18-H18 -> 0
H19: =D19*F19 -> 0 | I19: =E19-H19 -> 0
H20: =D20*F20 -> 0 | I20: =E20-H20 -> 0
H21: =D21*F21 -> 0 | I21: =E21-H21 -> 0
... H28: =D28*F28 -> 0 | I28: =E28-H28 -> 0
A29: 合计 | C29: =SUM(C10:C28) -> 0 | D29: =SUM(D10:D28) -> 0 | E29: =SUM(E10:E28) -> 0 | F29: =SUM(F10:F28) -> 0 | G29: =SUM(G10:G28) -> 0 | H29: =SUM(H10:H28) -> 0 | I29: =SUM(I10:I28) -> 0
A30: 其中：
A31: =底稿目录!A9 -> 种植业 | C31: =SUMPRODUCT(($A$10:$A$28=$A31)*(C$10:C$28)) -> 0 | D31: =SUMPRODUCT(($A$10:$A$28=$A31)*(D$10:D$28)) -> 0 | E31: =SUMPRODUCT(($A$10:$A$28=$A31)*(E$10:E$28)) -> 0 | F31: =SUMPRODUCT(($A$10:$A$28=$A31)*(F$10:F$28)) -> 0 | H31: =SUMPRODUCT(($A$10:$A$28=$A31)*(H$10:H$28)) -> 0 | I31: =SUMPRODUCT(($A$10:$A$28=$A31)*(I$10:I$28)) -> 0
A32: =底稿目录!A10 -> 畜牧养殖业 | C32: =SUMPRODUCT(($A$10:$A$28=$A32)*(C$10:C$28)) -> 0 | D32: =SUMPRODUCT(($A$10:$A$28=$A32)*(D$10:D$28)) -> 0 | E32: =SUMPRODUCT(($A$10:$A$28=$A32)*(E$10:E$28)) -> 0 | F32: =SUMPRODUCT(($A$10:$A$28=$A32)*(F$10:F$28)) -> 0 | H32: =SUMPRODUCT(($A$10:$A$28=$A32)*(H$10:H$28)) -> 0 | I32: =SUMPRODUCT(($A$10:$A$28=$A32)*(I$10:I$28)) -> 0
A33: =底稿目录!A11 -> 林业 | C33: =SUMPRODUCT(($A$10:$A$28=$A33)*(C$10:C$28)) -> 0 | D33: =SUMPRODUCT(($A$10:$A$28=$A33)*(D$10:D$28)) -> 0 | E33: =SUMPRODUCT(($A$10:$A$28=$A33)*(E$10:E$28)) -> 0 | F33: =SUMPRODUCT(($A$10:$A$28=$A33)*(F$10:F$28)) -> 0 | H33: =SUMPRODUCT(($A$10:$A$28=$A33)*(H$10:H$28)) -> 0 | I33: =SUMPRODUCT(($A$10:$A$28=$A33)*(I$10:I$28)) -> 0
A34: =底稿目录!A12 -> 水产业 | C34: =SUMPRODUCT(($A$10:$A$28=$A34)*(C$10:C$28)) -> 0 | D34: =SUMPRODUCT(($A$10:$A$28=$A34)*(D$10:D$28)) -> 0 | E34: =SUMPRODUCT(($A$10:$A$28=$A34)*(E$10:E$28)) -> 0 | F34: =SUMPRODUCT(($A$10:$A$28=$A34)*(F$10:F$28)) -> 0 | H34: =SUMPRODUCT(($A$10:$A$28=$A34)*(H$10:H$28)) -> 0 | I34: =SUMPRODUCT(($A$10:$A$28=$A34)*(I$10:I$28)) -> 0
A35: =底稿目录!A13 -> …… | C35: =SUMPRODUCT(($A$10:$A$28=$A35)*(C$10:C$28)) -> 0 | D35: =SUMPRODUCT(($A$10:$A$28=$A35)*(D$10:D$28)) -> 0 | E35: =SUMPRODUCT(($A$10:$A$28=$A35)*(E$10:E$28)) -> 0 | F35: =SUMPRODUCT(($A$10:$A$28=$A35)*(F$10:F$28)) -> 0 | H35: =SUMPRODUCT(($A$10:$A$28=$A35)*(H$10:H$28)) -> 0 | I35: =SUMPRODUCT(($A$10:$A$28=$A35)*(I$10:I$28)) -> 0
A37: 三、审计说明：
A41: 四、审计结论：
A48: 提示：
A49: 根据《企业会计准则-生物资产》规定，生物资产通常按照成本计量，但有确凿证据表明其公允价值能够持续可靠取得的除外。采用公允价值计量的生物资产，应当同时满足下列两个条件：
A50: 一是生物资产有活跃的交易市场。活跃的交易市场，是指同时具有下列特征的市场：
A51: （1）市场内交易的对象具有同质性；
A52: （2）可以随时找到自愿交易的买方和卖方；
A53: （3）市场价格的信息是公开的。
A54: 二是能够从交易市场上取得同类或类似生物资产的市场价格及其他相关信息，从而对生物资产的公允价值作出合理估计。同类或类似，是指生物资产的品种相同或类似、质量等级相同或类似、生长时间相同或类似、所处气候和地理环境相同或类似。
A57: 审计过程提示
A58: 1.确定生产性生物资产后续计量选用公允价值模式政策恰当，计算复核期末计价正确：
A59: 2.逐项检查公允价值的确定依据是否充分，公允价值变动损益计算是否正确，会计处理是否正确；与利润表公允价值变动损益中的相应数字核对无误。
... A61: 4.如果需利用专家等工作，应对专家的执业资格和胜任能力、工作结果等进行评价。

Sheet 互转审核表H7-14
A1: 致同会计师事务所
A2: 生产性生物资产与消耗性生物资产互转审核表
A3: =底稿目录!A2 -> 被审计单位： | D3: =底稿目录!A4 -> 编制人： | J3: =底稿目录!A6 -> 编制日期： | T3: 索引号： | U3: H7-14
A4: =底稿目录!A3 -> 截止日： | D4: =底稿目录!A5 -> 复核人： | J4: =底稿目录!A7 -> 复核日期： | T4: 页 次：
A5: 一、审计目标：
A6: 1. 生产性生物资产以恰当的金额包括在财务报表中，与之相关的计价或分摊调整已恰当记录，相关披露已得到恰当计量和描述；
A7: 2. 生产性生物资产已被恰当地汇总或分解且表述清楚，相关披露在按照企业会计准则的编制基础下是相关的、可理解的
A8: 二、审计过程：
A9: 生产性生物资产类别 | B9: 生产性生物资产名称 | C9: 转换日期 | D9: 消耗性生物资产转换日价值 | H9: 生产性生物资产转换日价值 | Q9: 转换影响 | S9: 转换原因 | T9: 批准文件 | U9: 备注
H10: 成本模式 | L10: 公允价值模式
D11: 资产原值 | E11: 累计折旧 | F11: 减值准备 | G11: 净额 | H11: 资产原值 | I11: 累计折旧 | J11: 减值准备 | K11: 净额 | L11: 账面价值 | M11: 公允价值 | N11: 面积 | O11: 参考单价 | P11: 参考单价来源 | Q11: 当期损益 | R11: 其他综合收益
D12: ① | E12: ② | F12: ③ | G12: ④=①-②-③ | H12: ⑤ | I12: ⑥ | J12: ⑦ | K12: ⑧=⑤-⑥-⑦ | L12: ⑨ | M12: ⑩ | Q12: ⑾=⑨-⑩ | R12: ⑿=⑩-⑨
G13: =D13-E13-F13 -> 0 | K13: =H13-I13-J13 -> 0 | L13: =G13 -> 0 | M13: =N13*O13 -> 0 | Q13: =IF(L13>M13,L13-M13,0) -> 0 | R13: =IF(M13>L13,M13-L13,0) -> 0
G14: =D14-E14-F14 -> 0 | K14: =H14-I14-J14 -> 0 | L14: =G14 -> 0 | M14: =N14*O14 -> 0 | Q14: =IF(L14>M14,L14-M14,0) -> 0 | R14: =IF(M14>L14,M14-L14,0) -> 0
G15: =D15-E15-F15 -> 0 | K15: =H15-I15-J15 -> 0 | L15: =G15 -> 0 | M15: =N15*O15 -> 0 | Q15: =IF(L15>M15,L15-M15,0) -> 0 | R15: =IF(M15>L15,M15-L15,0) -> 0
G16: =D16-E16-F16 -> 0 | K16: =H16-I16-J16 -> 0 | L16: =G16 -> 0 | M16: =N16*O16 -> 0 | Q16: =IF(L16>M16,L16-M16,0) -> 0 | R16: =IF(M16>L16,M16-L16,0) -> 0
G17: =D17-E17-F17 -> 0 | K17: =H17-I17-J17 -> 0 | L17: =G17 -> 0 | M17: =N17*O17 -> 0 | Q17: =IF(L17>M17,L17-M17,0) -> 0 | R17: =IF(M17>L17,M17-L17,0) -> 0
G18: =D18-E18-F18 -> 0 | K18: =H18-I18-J18 -> 0 | L18: =G18 -> 0 | M18: =N18*O18 -> 0 | Q18: =IF(L18>M18,L18-M18,0) -> 0 | R18: =IF(M18>L18,M18-L18,0) -> 0
G19: =D19-E19-F19 -> 0 | K19: =H19-I19-J19 -> 0 | L19: =G19 -> 0 | M19: =N19*O19 -> 0 | Q19: =IF(L19>M19,L19-M19,0) -> 0 | R19: =IF(M19>L19,M19-L19,0) -> 0
G20: =D20-E20-F20 -> 0 | K20: =H20-I20-J20 -> 0 | L20: =G20 -> 0 | M20: =N20*O20 -> 0 | Q20: =IF(L20>M20,L20-M20,0) -> 0 | R20: =IF(M20>L20,M20-L20,0) -> 0
G21: =D21-E21-F21 -> 0 | K21: =H21-I21-J21 -> 0 | L21: =G21 -> 0 | M21: =N21*O21 -> 0 | Q21: =IF(L21>M21,L21-M21,0) -> 0 | R21: =IF(M21>L21,M21-L21,0) -> 0
G22: =D22-E22-F22 -> 0 | K22: =H22-I22-J22 -> 0 | L22: =G22 -> 0 | M22: =N22*O22 -> 0 | Q22: =IF(L22>M22,L22-M22,0) -> 0 | R22: =IF(M22>L22,M22-L22,0) -> 0
G23: =D23-E23-F23 -> 0 | K23: =H23-I23-J23 -> 0 | L23: =G23 -> 0 | M23: =N23*O23 -> 0 | Q23: =IF(L23>M23,L23-M23,0) -> 0 | R23: =IF(M23>L23,M23-L23,0) -> 0
G24: =D24-E24-F24 -> 0 | K24: =H24-I24-J24 -> 0 | L24: =G24 -> 0 | M24: =N24*O24 -> 0 | Q24: =IF(L24>M24,L24-M24,0) -> 0 | R24: =IF(M24>L24,M24-L24,0) -> 0
... G28: =D28-E28-F28 -> 0 | K28: =H28-I28-J28 -> 0 | L28: =G28 -> 0 | M28: =N28*O28 -> 0 | Q28: =IF(L28>M28,L28-M28,0) -> 0 | R28: =IF(M28>L28,M28-L28,0) -> 0
A29: 合计 | D29: =SUM(D13:D28) -> 0 | E29: =SUM(E13:E28) -> 0 | F29: =SUM(F13:F28) -> 0 | G29: =SUM(G13:G28) -> 0 | H29: =SUM(H13:H28) -> 0 | I29: =SUM(I13:I28) -> 0 | J29: =SUM(J13:J28) -> 0 | K29: =SUM(K13:K28) -> 0 | ... M29: =SUM(M13:M28) -> 0 | Q29: =SUM(Q13:Q28) -> 0 | R29: =SUM(R13:R28) -> 0
A30: 其中：
A31: =底稿目录!A9 -> 种植业 | D31: =SUMPRODUCT(($A$13:$A$28=$A31)*(D$13:D$28)) -> 0 | E31: =SUMPRODUCT(($A$13:$A$28=$A31)*(E$13:E$28)) -> 0 | F31: =SUMPRODUCT(($A$13:$A$28=$A31)*(F$13:F$28)) -> 0 | G31: =SUMPRODUCT(($A$13:$A$28=$A31)*(G$13:G$28)) -> 0 | H31: =SUMPRODUCT(($A$13:$A$28=$A31)*(H$13:H$28)) -> 0 | I31: =SUMPRODUCT(($A$13:$A$28=$A31)*(I$13:I$28)) -> 0 | J31: =SUMPRODUCT(($A$13:$A$28=$A31)*(J$13:J$28)) -> 0 | K31: =SUMPRODUCT(($A$13:$A$28=$A31)*(K$13:K$28)) -> 0 | ... M31: =SUMPRODUCT(($A$13:$A$28=$A31)*(M$13:M$28)) -> 0 | Q31: =SUMPRODUCT(($A$13:$A$28=$A31)*(Q$13:Q$28)) -> 0 | R31: =SUMPRODUCT(($A$13:$A$28=$A31)*(R$13:R$28)) -> 0
A32: =底稿目录!A10 -> 畜牧养殖业 | D32: =SUMPRODUCT(($A$13:$A$28=$A32)*(D$13:D$28)) -> 0 | E32: =SUMPRODUCT(($A$13:$A$28=$A32)*(E$13:E$28)) -> 0 | F32: =SUMPRODUCT(($A$13:$A$28=$A32)*(F$13:F$28)) -> 0 | G32: =SUMPRODUCT(($A$13:$A$28=$A32)*(G$13:G$28)) -> 0 | H32: =SUMPRODUCT(($A$13:$A$28=$A32)*(H$13:H$28)) -> 0 | I32: =SUMPRODUCT(($A$13:$A$28=$A32)*(I$13:I$28)) -> 0 | J32: =SUMPRODUCT(($A$13:$A$28=$A32)*(J$13:J$28)) -> 0 | K32: =SUMPRODUCT(($A$13:$A$28=$A32)*(K$13:K$28)) -> 0 | ... M32: =SUMPRODUCT(($A$13:$A$28=$A32)*(M$13:M$28)) -> 0 | Q32: =SUMPRODUCT(($A$13:$A$28=$A32)*(Q$13:Q$28)) -> 0 | R32: =SUMPRODUCT(($A$13:$A$28=$A32)*(R$13:R$28)) -> 0
A33: =底稿目录!A11 -> 林业 | D33: =SUMPRODUCT(($A$13:$A$28=$A33)*(D$13:D$28)) -> 0 | E33: =SUMPRODUCT(($A$13:$A$28=$A33)*(E$13:E$28)) -> 0 | F33: =SUMPRODUCT(($A$13:$A$28=$A33)*(F$13:F$28)) -> 0 | G33: =SUMPRODUCT(($A$13:$A$28=$A33)*(G$13:G$28)) -> 0 | H33: =SUMPRODUCT(($A$13:$A$28=$A33)*(H$13:H$28)) -> 0 | I33: =SUMPRODUCT(($A$13:$A$28=$A33)*(I$13:I$28)) -> 0 | J33: =SUMPRODUCT(($A$13:$A$28=$A33)*(J$13:J$28)) -> 0 | K33: =SUMPRODUCT(($A$13:$A$28=$A33)*(K$13:K$28)) -> 0 | ... M33: =SUMPRODUCT(($A$13:$A$28=$A33)*(M$13:M$28)) -> 0 | Q33: =SUMPRODUCT(($A$13:$A$28=$A33)*(Q$13:Q$28)) -> 0 | R33: =SUMPRODUCT(($A$13:$A$28=$A33)*(R$13:R$28)) -> 0
A34: =底稿目录!A12 -> 水产业 | D34: =SUMPRODUCT(($A$13:$A$28=$A34)*(D$13:D$28)) -> 0 | E34: =SUMPRODUCT(($A$13:$A$28=$A34)*(E$13:E$28)) -> 0 | F34: =SUMPRODUCT(($A$13:$A$28=$A34)*(F$13:F$28)) -> 0 | G34: =SUMPRODUCT(($A$13:$A$28=$A34)*(G$13:G$28)) -> 0 | H34: =SUMPRODUCT(($A$13:$A$28=$A34)*(H$13:H$28)) -> 0 | I34: =SUMPRODUCT(($A$13:$A$28=$A34)*(I$13:I$28)) -> 0 | J34: =SUMPRODUCT(($A$13:$A$28=$A34)*(J$13:J$28)) -> 0 | K34: =SUMPRODUCT(($A$13:$A$28=$A34)*(K$13:K$28)) -> 0 | ... M34: =SUMPRODUCT(($A$13:$A$28=$A34)*(M$13:M$28)) -> 0 | Q34: =SUMPRODUCT(($A$13:$A$28=$A34)*(Q$13:Q$28)) -> 0 | R34: =SUMPRODUCT(($A$13:$A$28=$A34)*(R$13:R$28)) -> 0
A35: =底稿目录!A13 -> …… | D35: =SUMPRODUCT(($A$13:$A$28=$A35)*(D$13:D$28)) -> 0 | E35: =SUMPRODUCT(($A$13:$A$28=$A35)*(E$13:E$28)) -> 0 | F35: =SUMPRODUCT(($A$13:$A$28=$A35)*(F$13:F$28)) -> 0 | G35: =SUMPRODUCT(($A$13:$A$28=$A35)*(G$13:G$28)) -> 0 | H35: =SUMPRODUCT(($A$13:$A$28=$A35)*(H$13:H$28)) -> 0 | I35: =SUMPRODUCT(($A$13:$A$28=$A35)*(I$13:I$28)) -> 0 | J35: =SUMPRODUCT(($A$13:$A$28=$A35)*(J$13:J$28)) -> 0 | K35: =SUMPRODUCT(($A$13:$A$28=$A35)*(K$13:K$28)) -> 0 | ... M35: =SUMPRODUCT(($A$13:$A$28=$A35)*(M$13:M$28)) -> 0 | Q35: =SUMPRODUCT(($A$13:$A$28=$A35)*(Q$13:Q$28)) -> 0 | R35: =SUMPRODUCT(($A$13:$A$28=$A35)*(R$13:R$28)) -> 0
A36: 三、审计说明：
A39: 四、审计结论：
A42: 编制说明：
A43: 根据《企业会计准则-生物资产》规定，生物资产通常按照成本计量，但有确凿证据表明其公允价值能够持续可靠取得的除外。采用公允价值计量的生物资产，应当同时满足下列两个条件：
A44: 一是生物资产有活跃的交易市场。活跃的交易市场，是指同时具有下列特征的市场：
A45: （1）市场内交易的对象具有同质性；
A46: （2）可以随时找到自愿交易的买方和卖方；
A47: （3）市场价格的信息是公开的。
A48: 二是能够从交易市场上取得同类或类似生物资产的市场价格及其他相关信息，从而对生物资产的公允价值作出合理估计。同类或类似，是指生物资产的品种相同或类似、质量等级相同或类似、生长时间相同或类似、所处气候和地理环境相同或类似。
A52: 审计过程提示
A53: 1.检查董事会等决议文件，确定后续计量模式改变的适当性、会计处理的正确性，并提请被审计单位进行充分披露。
A54: 2.审查生产性生物资产计量模式转为公允价值计量模式是否作为会计政策变更进行追溯调整期初留存收益处理；测算转换日的转换价值及相关损益是否计量正确

Sheet 减值测算表H7-15
A1: 致同会计师事务所
A2: 生产性生物资产减值测算表
A3: =底稿目录!A2 -> 被审计单位： | G3: =底稿目录!A4 -> 编制人： | J3: =底稿目录!A6 -> 编制日期： | M3: 索引号： | N3: H7-15
A4: =底稿目录!A3 -> 截止日： | G4: =底稿目录!A5 -> 复核人： | J4: =底稿目录!A7 -> 复核日期： | M4: 页 次：
A5: 一、审计目标：生产性生物资产以恰当的金额包括在财务报表中，与之相关的计价或分摊调整已恰当记录，相关披露已得到恰当计量和描述。
A6: 二、审计过程：
A7: 生产性生物资产类别 | B7: 生产性生物资产编号 | C7: 生产性生物资产名称 | D7: 是否存在减值迹象 | E7: 减值迹象描述 | F7: 账面价值 | G7: 可收回金额 | J7: 期末应计提的减值金额（当⑤＜②） | K7: 期末账面已计提的减值准备 | L7: 本期应补提 或冲回的减值准备 | M7: 工作底稿索引号 | N7: 备注
G8: 公允价值减处置费用的净额 | H8: 预计未来现金流量现值 | I8: 可收回金额（③、④较高者） | K8: 期末已计提 减值准备
E9: ① | F9: ② | G9: ③ | H9: ④ | I9: ⑤ | J9: ⑥＝②-⑤ | K9: ⑦ | L9: ⑧=⑥-⑦
I10: =MAX(G10,H10) -> 0 | J10: =IF(F10>I10,F10-I10,0) -> 0 | L10: =J10-K10 -> 0
I11: =MAX(G11,H11) -> 0 | J11: =IF(F11>I11,F11-I11,0) -> 0 | L11: =J11-K11 -> 0
I12: =MAX(G12,H12) -> 0 | J12: =IF(F12>I12,F12-I12,0) -> 0 | L12: =J12-K12 -> 0
I13: =MAX(G13,H13) -> 0 | J13: =IF(F13>I13,F13-I13,0) -> 0 | L13: =J13-K13 -> 0
I14: =MAX(G14,H14) -> 0 | J14: =IF(F14>I14,F14-I14,0) -> 0 | L14: =J14-K14 -> 0
I15: =MAX(G15,H15) -> 0 | J15: =IF(F15>I15,F15-I15,0) -> 0 | L15: =J15-K15 -> 0
I16: =MAX(G16,H16) -> 0 | J16: =IF(F16>I16,F16-I16,0) -> 0 | L16: =J16-K16 -> 0
I17: =MAX(G17,H17) -> 0 | J17: =IF(F17>I17,F17-I17,0) -> 0 | L17: =J17-K17 -> 0
I18: =MAX(G18,H18) -> 0 | J18: =IF(F18>I18,F18-I18,0) -> 0 | L18: =J18-K18 -> 0
I19: =MAX(G19,H19) -> 0 | J19: =IF(F19>I19,F19-I19,0) -> 0 | L19: =J19-K19 -> 0
I20: =MAX(G20,H20) -> 0 | J20: =IF(F20>I20,F20-I20,0) -> 0 | L20: =J20-K20 -> 0
I21: =MAX(G21,H21) -> 0 | J21: =IF(F21>I21,F21-I21,0) -> 0 | L21: =J21-K21 -> 0
A22: 合计 | F22: =SUM(F10:F21) -> 0 | G22: =SUM(G10:G21) -> 0 | H22: =SUM(H10:H21) -> 0 | I22: =SUM(I10:I21) -> 0 | J22: =SUM(J10:J21) -> 0 | K22: =SUM(K10:K21) -> 0 | L22: =SUM(L10:L21) -> 0
A23: 其中：
A24: =底稿目录!A9 -> 种植业 | F24: =SUMPRODUCT(($A$10:$A$21=$A24)*(F$10:F$21)) -> 0 | G24: =SUMPRODUCT(($A$10:$A$21=$A24)*(G$10:G$21)) -> 0 | H24: =SUMPRODUCT(($A$10:$A$21=$A24)*(H$10:H$21)) -> 0 | I24: =SUMPRODUCT(($A$10:$A$21=$A24)*(I$10:I$21)) -> 0 | J24: =SUMPRODUCT(($A$10:$A$21=$A24)*(J$10:J$21)) -> 0 | K24: =SUMPRODUCT(($A$10:$A$21=$A24)*(K$10:K$21)) -> 0 | L24: =SUMPRODUCT(($A$10:$A$21=$A24)*(L$10:L$21)) -> 0
A25: =底稿目录!A10 -> 畜牧养殖业 | F25: =SUMPRODUCT(($A$10:$A$21=$A25)*(F$10:F$21)) -> 0 | G25: =SUMPRODUCT(($A$10:$A$21=$A25)*(G$10:G$21)) -> 0 | H25: =SUMPRODUCT(($A$10:$A$21=$A25)*(H$10:H$21)) -> 0 | I25: =SUMPRODUCT(($A$10:$A$21=$A25)*(I$10:I$21)) -> 0 | J25: =SUMPRODUCT(($A$10:$A$21=$A25)*(J$10:J$21)) -> 0 | K25: =SUMPRODUCT(($A$10:$A$21=$A25)*(K$10:K$21)) -> 0 | L25: =SUMPRODUCT(($A$10:$A$21=$A25)*(L$10:L$21)) -> 0
A26: =底稿目录!A11 -> 林业 | F26: =SUMPRODUCT(($A$10:$A$21=$A26)*(F$10:F$21)) -> 0 | G26: =SUMPRODUCT(($A$10:$A$21=$A26)*(G$10:G$21)) -> 0 | H26: =SUMPRODUCT(($A$10:$A$21=$A26)*(H$10:H$21)) -> 0 | I26: =SUMPRODUCT(($A$10:$A$21=$A26)*(I$10:I$21)) -> 0 | J26: =SUMPRODUCT(($A$10:$A$21=$A26)*(J$10:J$21)) -> 0 | K26: =SUMPRODUCT(($A$10:$A$21=$A26)*(K$10:K$21)) -> 0 | L26: =SUMPRODUCT(($A$10:$A$21=$A26)*(L$10:L$21)) -> 0
A27: =底稿目录!A12 -> 水产业 | F27: =SUMPRODUCT(($A$10:$A$21=$A27)*(F$10:F$21)) -> 0 | G27: =SUMPRODUCT(($A$10:$A$21=$A27)*(G$10:G$21)) -> 0 | H27: =SUMPRODUCT(($A$10:$A$21=$A27)*(H$10:H$21)) -> 0 | I27: =SUMPRODUCT(($A$10:$A$21=$A27)*(I$10:I$21)) -> 0 | J27: =SUMPRODUCT(($A$10:$A$21=$A27)*(J$10:J$21)) -> 0 | K27: =SUMPRODUCT(($A$10:$A$21=$A27)*(K$10:K$21)) -> 0 | L27: =SUMPRODUCT(($A$10:$A$21=$A27)*(L$10:L$21)) -> 0
A28: =底稿目录!A13 -> …… | F28: =SUMPRODUCT(($A$10:$A$21=$A28)*(F$10:F$21)) -> 0 | G28: =SUMPRODUCT(($A$10:$A$21=$A28)*(G$10:G$21)) -> 0 | H28: =SUMPRODUCT(($A$10:$A$21=$A28)*(H$10:H$21)) -> 0 | I28: =SUMPRODUCT(($A$10:$A$21=$A28)*(I$10:I$21)) -> 0 | J28: =SUMPRODUCT(($A$10:$A$21=$A28)*(J$10:J$21)) -> 0 | K28: =SUMPRODUCT(($A$10:$A$21=$A28)*(K$10:K$21)) -> 0 | L28: =SUMPRODUCT(($A$10:$A$21=$A28)*(L$10:L$21)) -> 0
A29: 三、审计说明：
A32: 四、审计结论：
A37: 提示：
A38: 根据本准则第二十一条规定，企业至少应当于每年年度终了对消耗性和生产性生物资产进行检查，有确凿证据表明生物资产发生减值的，应当计提消耗性生物资产跌价准备或生产性生物资产减值准备。
A39: 生物资产存在下列情形之一的，通常表明该生物资产发生了减值：
A40: （一）因遭受火灾、旱灾、水灾、冻灾、台风、冰雹等自然灾害，造成消耗性或生产性生物资产发生实体损坏，影响该资产的进一步生长或生产，从而降低其产生经济利益的能力。
A41: （二）因遭受病虫害或动物疫病侵袭，造成消耗性或生产性生物资产的市场价格大幅度持续下跌，并且在可预见的未来无回升的希望。
A42: （三）因消费者偏好改变而使企业消耗性或生产性生物资产收获的农产品的市场需求发生变化，导致市场价格逐渐下跌。
A43: （四）因企业所处经营环境，如动植物检验检疫标准等发生重大变化，从而对企业产生不利影响，导致消耗性或生产性生物资产的市场价格逐渐下跌。
A44: （五）其他足以证明消耗性或生产性生物资产实质上已经发生减值的情形。
A49: 审计过程提示
A50: 1.获取或编制生产性生物资产减值准备明细表，复核加计正确，并与总账数和明细账合计数核对相符；
... A54: 5.上期确认的固定资产减值准备在本期的变动是否适当。

Sheet 可收回金额测试表H7-16
A1: 致同会计师事务所
A2: 生产性生物资产减值准备测试表-可收回金额
A3: =底稿目录!A2 -> 被审计单位： | E3: =底稿目录!A4 -> 编制人： | I3: =底稿目录!A6 -> 编制日期： | N3: 索引号： | O3: H7-16
A4: =底稿目录!A3 -> 截止日： | E4: =底稿目录!A5 -> 复核人： | I4: =底稿目录!A7 -> 复核日期： | N4: 页 次：
A5: 一、审计目标：生产性生物资产以恰当的金额包括在财务报表中，与之相关的计价或分摊调整已恰当记录，相关披露已得到恰当计量和描述。
A6: 二、审计过程：
A7: （一）资产的公允价值减去处置费用后的净额
A8: 项目名称 | B8: 公允价值 | H8: 处置费用（资产处置的直接归属费用） | N8: 公允价值-处置费用 | O8: 备注
B9: 销售协议价格 | C9: 说明 | D9: 资产活跃市场价格 | E9: 说明 | F9: 估计价格 | G9: 说明 | H9: 法律费用 | I9: 相关税费 | J9: 搬运费 | K9: 直接费用 | L9: 其他费用 | M9: 处置费用合计
M10: =SUM(H10:L10) -> 0 | N10: =IF(B10>0,B10,IF(D10>0,D10,F10))-M10 -> 0
M11: =SUM(H11:L11) -> 0 | N11: =IF(B11>0,B11,IF(D11>0,D11,F11))-M11 -> 0
M12: =SUM(H12:L12) -> 0 | N12: =IF(B12>0,B12,IF(D12>0,D12,F12))-M12 -> 0
A13: 合 计 | B13: =SUM(B10:B12) -> 0 | D13: =SUM(D10:D12) -> 0 | F13: =SUM(F10:F12) -> 0 | H13: =SUM(H10:H12) -> 0 | I13: =SUM(I10:I12) -> 0 | J13: =SUM(J10:J12) -> 0 | K13: =SUM(K10:K12) -> 0 | L13: =SUM(L10:L12) -> 0 | M13: =SUM(M10:M12) -> 0 | N13: =SUM(N10:N12) -> 0
A14: 审计说明：
A16: （二）资产预计未来现金流量的现值
A17: 预计未来现金流量 | B17: 预算或者预测期 | G17: 以后年度 | I17: 行业的长期平均增长率 | J17: 市场长期平均增长率 | K17: 所在国家或地区的长期平均增长率 | L17: 增长率确定依据 | N17: 预计未来现金流量的现值 | O17: 备注
B18: 第一年 | C18: 第二年 | D18: 第三年 | E18: 第四年 | F18: 第五年 | G18: 基数 | H18: 增长率
A19: 现金净流量（税前） | G19: =F19 -> 0
A20: 折现系数 | B20: =1/(1+$K$24)^1 -> #DIV/0! | C20: =1/(1+$K$24)^2 -> #DIV/0! | D20: =1/(1+$K$24)^3 -> #DIV/0! | E20: =1/(1+$K$24)^4 -> #DIV/0! | F20: =1/(1+$K$24)^5 -> #DIV/0! | G20: =(1+H19)/((J24-H19)*(1+K24)^5) -> #DIV/0! | H20: （企业管理层如能证明递增的增长率是合理的，可以以递增的增长率为基础。）
A21: 现值 | B21: =B19*B20 -> #DIV/0! | C21: =C19*C20 -> #DIV/0! | D21: =D19*D20 -> #DIV/0! | E21: =E19*E20 -> #DIV/0! | F21: =F19*F20 -> #DIV/0! | G21: =G19*G20 -> #DIV/0! | H21: （建立在预算或者预测基础上的预计现金流量最多涵盖5年，更长期间需证明合理性。） | N21: =SUM(B21:G21) -> #DIV/0!
A22: 折现率 | B22: 所得税率 | C22: 债务总额 D | D22: 资本总额 E | E22: 债务成本Kd | F22: 无风险报酬率Rf | G22: β系数 | H22: 市场平均收益率Rm | I22: 资本成本Ke | J22: WACC (税后) | K22: 折现率 (税前) | L22: 税后折税前调整说明 | N22: 可收回金额 | O22: 备注
B23: 适用税率 | L23: 税率调整 | M23: 调整说明
A24: 加权平均资金成本 | I24: =F24+G24*(H24-F24) -> 0 | J24: =((C24*E24*(1-B24)+D24*I24))/(C24+D24) -> #DIV/0! | K24: =J24/(1-(B24+L24)) -> #DIV/0! | N24: =MAX(N13,N21) -> #DIV/0!
A25: 审计说明：
A27: （三）可收回金额
B28: =N24 -> #DIV/0! | C28: 资产的公允价值减去处置费用后的净额与资产预计未来现金流量的现值两者之间较高者
A29: 三、审计说明：
A32: 四、审计结论
A38: 提示：
A39: 1、可收回金额应当根据资产的公允价值减去处置费用后的净额与资产预计未来现金流量的现值两者之间较高者确定。
A41: 2、资产的公允价值减去处置费用后的净额，应当根据公平交易中销售协议价格减去可直接归属于该资产处置费用的金额确定。不存在销售协议但存在资产活跃市场的，
A42: 应当按照该资产的市场价格减去处置费用后的金额确定。资产的市场价格通常应当根据资产的买方出价确定。在不存在销售协议和资产活跃市场的情况下，应当
A43: 以可获取的最佳信息为基础，估计资产的公允价值减去处置费用后的净额，该净额可以参考同行业类似资产的最近交易价格或者结果进行估计。企业按照上述规定
A44: 仍然无法可靠估计资产的公允价值减去处置费用后的净额的，应当以该资产预计未来现金流量的现值作为其可收回金额。
A45: 3、处置费用包括与资产处置有关的法律费用、相关税费、搬运费以及为使资产达到可销售状态所发生的直接费用等。
A47: 4、资产预计未来现金流量的现值，应当按照资产在持续使用过程中和最终处置时所产生的预计未来现金流量，选择恰当的折现率对其进行折现后的金额加以确定。
A52: 5、预计资产的未来现金流量，应当以经企业管理层批准的最近财务预算或者预测数据，以及该预算或者预测期之后年份稳定的或者递减的增长率为基础。
A53: 预计的资产未来现金流量应当包括下列各项：
... A99: 5.上期确认的固定资产减值准备在本期的变动是否适当。

Sheet 关联交易检查表H7-17
A1: 致同会计师事务所
A2: 关联交易检查表
A3: =底稿目录!A2 -> 被审计单位： | F3: =底稿目录!A4 -> 编制人： | I3: =底稿目录!A6 -> 编制日期： | N3: 索引号： | O3: H7-17
A4: =底稿目录!A3 -> 截止日： | F4: =底稿目录!A5 -> 复核人： | I4: =底稿目录!A7 -> 复核日期： | N4: 页 次：
A5: 一、审计目标:
A6: 1.资产负债表中记录的生产性生物资产是存在的，且已记录于恰当的账户；2.所有应记录的生产性生物资产均已记录，所有应当包括在财务报表中的相关披露均已包括；3.记录的生产性生物资产由被审计单位拥有或控制；
A7: 4.生产性生物资产以恰当的金额包括在财务报表中，与之相关的计价或分摊调整已恰当记录，相关披露已得到恰当计量和描述；5.生产性生物资产已被恰当地汇总或分解且表述清楚，相关披露在按照企业会计准则的编制基础下是相关的、可理解的.
A8: 二、审计过程：
A9: （1）向合并范围外关联方采购生产性生物资产
A10: 关联单位名称 | B10: 关联方关系 | C10: 资产类别 | D10: 购买生产性生物资产名称 | E10: 购买价款 | F10: 生产性生物资产入账价值 | G10: 占同类交易金额的比例％ | H10: 购入时间 | I10: 折旧年限 | J10: 定价政策 | K10: 关联交易是否存在异常 | L10: 备注 | M10: 索引号
A17: （2）向合并范围外关联方出售生产性生物资产
A18: 关联单位名称 | B18: 关联方关系 | C18: 资产类别 | D18: 出售固定资产名称 | E18: 出售时生产性生物资产原值 | F18: 出售时累计折旧 | G18: 出售时减值准备 | H18: 出售时净值 | I18: 销售价格 （不含税） | J18: 占同类交易金额的比例％ | K18: 出售时间 | L18: 定价政策 | M18: 关联交易是否存在异常 | N18: 备注 | O18: 索引号
H19: =E19-F19-G19 -> 0
A28: 三、审计说明：
A33: 四、审计结论：
A41: 勿删
A42: 关联关系
A43: 实际控制人
A44: 控股股东
A45: 控股股东、实际控制人的附属企业
A46: 持有5%以上股份的法人或其他组织
A47: 联营企业
A48: 合营企业
A49: 董高监等关键管理人员
A50: 其他关联方
