Workbook

Sheet 底稿目录
A1: 底稿开列时，可先在以下单元格填写有关内容，以便其他底稿引用有关数据：
A2: 被审计单位： | D2: 序号 | E2: 内容 | F2: 索引号 | G2: 备注
A3: 截止日：202X年12月31日 | D3: 1 | E3: 租赁负债实质性程序表 | F3: H9A
A4: 编制人： | D4: =D3+1 -> 2 | E4: 审定表 | F4: H9-1
A5: 复核人： | D5: =D4+1 -> 3 | E5: 附注披露信息（上市公司） | G5: 无需打印
A6: 编制日期： | D6: =D5+1 -> 4 | E6: 附注披露信息（国企） | G6: 无需打印
A7: 复核日期： | D7: =D6+1 -> 5 | E7: 租赁负债明细表 | F7: H9-2
D8: =D7+1 -> 6 | E8: 未确认融资费用明细表 | F8: H9-3
A9: 关于工作底稿与审计程序索引号对应的说明 | D9: =D8+1 -> 7 | E9: 调整分录汇总 | F9: H9-4
A10: 1.编制的审计工作底稿应与审计程序对应。审计项目组应根据被审计单位实际情况和风险评估情况在实质性程序表中裁剪、修改或增加审计程序，根据实际执行的审计程序完成相应审计工作底稿，编制的工作底稿中应按自然顺序依次编制索引号，并通过唯一的索引号将与实质性程序表中的程序对应关联（即将工作底稿的索引号填入实质性程序表中的底稿索引号列）。
A14: 2.获取的支持性证据应与审计底稿或程序对应。审计项目组在完成底稿时获取的支持性证据应根据底稿索引号编制下一级按自然顺序排序的索引号（如D1-2-1、D1-2-2、……），并在底稿中说明引用的支持性证据、关联索引号。
A17: 3.工作底稿索引号的编码规则：实质性程序索引号按循环从“D”到“N”,循环内账户以顺序号排列，模板中底稿索引号按账户顺序+自然数顺序（即模板中索引号按二级自然顺序排列，如D1-1、D1-2、D1-3、……D1-N）。

Sheet 租赁负债实质性程序表H9A
A1: 致同会计师事务所
A2: 租赁负债实质性程序表
A3: =底稿目录!A2 -> 被审计单位： | C3: =底稿目录!A4 -> 编制人： | E3: =底稿目录!A6 -> 编制日期： | H3: 索引号： | I3: H9A
A4: =底稿目录!A3 -> 截止日：202X年12月31日 | C4: =底稿目录!A5 -> 复核人： | E4: =底稿目录!A7 -> 复核日期： | H4: 页 次：
A5: 一、本账户涉及的科目
A6: 租赁负债、未确认融资费用
A7: 二、审计目标与认定的对应关系
A8: 审计目标 | G8: 财务报表的认定
A9: A. 资产负债表中记录的租赁负债是存在的，且已记录于恰当的账户 | G9: 存在
A10: B. 所有应记录的租赁负债均已记录，所有应当包括在财务报表中的相关披露均已包括 | G10: 完整性
A11: C. 记录的租赁负债由被审计单位拥有或控制； | G11: 权利和义务
A12: D. 租赁负债以恰当的金额包括在财务报表中，与之相关的计价或分摊调整已恰当记录，相关披露已得到恰当计量和描述 | G12: 准确性、计价和分摊
A13: E. 租赁负债已被恰当地汇总或分解且表述清楚，相关披露在按照企业会计准则的编制基础下是相关的、可理解的 | G13: 列报
A14: 三、计划实施的实质性程序
A15: 序号 | B15: 审计程序 | C15: 程序分类 | D15: 财务报表的认定 | I15: 底稿索引号
D16: 存在 | E16: 完整性 | F16: 权利和 义务 | G16: 准确性、计价和分摊 | H16: 列报 | J16: 根据被审计单位实际情况和风险评估情况裁剪、修改或增加审计程序
A17: 1 | B17: 获取或编制租赁负债的明细表，复核加计是否正确，并与总账数和明细账合计数核对是否相符,分析租赁负债与上期变动情况；并编制审定表。 | C17: 常规★ | D17: √ | E17: √ | G17: √ | I17: H9-1 /H9-2
A18: 2 | B18: 在使用手工编制、自定义信息报告、系统生成的非固定格式报告等由被审计单位生成的信息时，测试有关信息准确性和完整性，并考虑针对编制和维护由被审计单位生成的信息的相关控制实施控制测试，以评价该信息是否能够为实现审计目的提供基础。 | C18: 常规★ | E18: √ | G18: √ | I18: T1 / | J18: 可参见《审计手册》4.2.6，由被审计单位生成的信息可能是由系统生成的、或手工编制的、或二者兼而有之的方式生成的。例如，由被审计单位生成的信息可能包括： • 不涉及自定义的、由系统生成的报告（如，固定格式报告）； • 可能通过人工自定义的、由系统生成的报告，例如，（计算机）查询信息或特别定制的报告； • 手工编制的信息，例如，汇总信息的电子表格或用以支持分配、计算以及调节的电子表格； • 其他系统生成或手工编制的信息，例如，由被审计单位编制的客户发票； • 通过影印、拍摄、扫描或其他方式转换成电子形式的文件记录。
A19: 3 | B19: 对期初余额的审计，取得上期租赁负债明细表复核加计是否正确，与总账、明细账合计数是否相符； 结合使用权资产重新测算期初租赁负债余额准确性；对单项金额重大租赁负债结合使用权资产检查支持性文件，其他必要追加的审计程序。（适用于首次承接） | C19: 备选 | D19: √ | E19: √ | F19: √ | G19: √ | J19: 由被审计单位生成的信息不包括： • 总分类账或明细分类账、试算平衡表、或经审计的财务报表； • 第三方（除了服务机构）的报表或报告，例如，原始银行对账单，或函证的回函； • 外部数据（例如，第三方发布的数据，如，定价来源）。
A20: 4 | B20: 关注会计政策、会计估计合理性、一贯性，关注其是否利用会计政策和会计估计及其变更操纵利润。 | C20: 常规★ | D20: √ | E20: √ | G20: √ | I20: H8-4 /H8-5
A21: 5 | B21: 结合使用权资产的审计，检查租赁负债的初始计量和后续计量： （1）获取相关租赁合同/协议，检查初始直接费用、或有租金确认、折现率是否合理，使用权资产和租赁负债的入账价值是否正确和会计处理是否正确。 （2）当存在续租选择权、购买选择权和终止租赁选择权时，了解被审计单位对是否行使相关权利做出的判断，检查其判断依据是否充分，并评估对使用权资产、租赁负债入账价值的影响； （3）按实际利率法重新计算未确认融资费用摊销、租赁负债余额，计算使用权资产余额，与被审计单位账面记录核对是否一致； （4）重估或租赁变更等原因导致租赁付款额发生变动时，重新计量租赁负债账面价值会计处理是否正确。 | C21: 常规★ | D21: √ | E21: √ | F21: √ | G21: √ | I21: H8-6 /H8-7
A22: 6 | B22: 检查关联交易情况，检查关联交易的真实性、合理性及合规性；检查关联交易会计处理是否正确，考虑是否存在未识别的关联方，检查关联交易和余额披露是否正确。 | C22: 常规★ | D22: √ | E22: √ | F22: √ | G22: √ | H22: √ | I22: H8-14
A23: 7 | B23: 必要时函证租赁资产、租赁期、应付和已付租金、租赁条款等信息。 | C23: IPO/上市/新三板/重组/舞弊应对 | D23: √ | E23: √ | F23: √ | G23: √ | I23: H0
A24: 8 | B24: 根据评估的舞弊风险等因素增加的审计程序。 | C24: IPO/上市/新三板/重组/舞弊应对
A25: 9 | B25: 检查租赁负债是否已按企业会计准则或其他适用的规定在财务报表中做出恰当列报和披露 | C25: 常规★ | H25: √ | I25: A 1-1/A1-15 /A1-16

Sheet 审定表H9-1
A1: 致同会计师事务所
A2: 租赁负债审定表
A3: =底稿目录!A2 -> 被审计单位： | D3: =底稿目录!A4 -> 编制人： | H3: =底稿目录!A6 -> 编制日期： | L3: 索引号： | M3: H9-1
A4: =底稿目录!A3 -> 截止日：202X年12月31日 | D4: =底稿目录!A5 -> 复核人： | H4: =底稿目录!A7 -> 复核日期： | L4: 页 次：
A5: 项目 | B5: 期初数 | G5: 期末数 | L5: 本期审定数与上期 审定数的比较
B6: 未审数 | C6: 账项调整 | D6: 审定数 | E6: 重分类：减一年内到期的租赁负债 | F6: 报表数 | G6: 未审数 | H6: 账项调整 | I6: 审定数 | J6: 重分类：减一年内到期的租赁负债 | K6: 报表数 | L6: 变动额 | M6: 变动率
A7: 一、租赁负债原值
A8: 项目A | D8: =B8+C8 -> 0 | F8: =D8-E8 -> 0 | I8: =G8+H8 -> 0 | K8: =I8-J8 -> 0 | L8: =K8-F8 -> 0 | M8: =IF(AND(F8=0,L8=0),0,IF(AND(F8=0,L8>0),1,L8/F8)) -> 0
A9: 项目B | D9: =B9+C9 -> 0 | F9: =D9-E9 -> 0 | I9: =G9+H9 -> 0 | K9: =I9-J9 -> 0 | L9: =K9-F9 -> 0 | M9: =IF(AND(F9=0,L9=0),0,IF(AND(F9=0,L9>0),1,L9/F9)) -> 0
A10: … | D10: =B10+C10 -> 0 | F10: =D10-E10 -> 0 | I10: =G10+H10 -> 0 | K10: =I10-J10 -> 0 | L10: =K10-F10 -> 0 | M10: =IF(AND(F10=0,L10=0),0,IF(AND(F10=0,L10>0),1,L10/F10)) -> 0
A11: 合计 | B11: =SUM(B8:B10) -> 0 | C11: =SUM(C8:C10) -> 0 | D11: =SUM(D8:D10) -> 0 | E11: =SUM(E8:E10) -> 0 | F11: =SUM(F8:F10) -> 0 | G11: =SUM(G8:G10) -> 0 | H11: =SUM(H8:H10) -> 0 | I11: =SUM(I8:I10) -> 0 | ... K11: =SUM(K8:K10) -> 0 | L11: =K11-F11 -> 0 | M11: =IF(AND(F11=0,L11=0),0,IF(AND(F11=0,L11>0),1,L11/F11)) -> 0
A12: 二、未确认融资费用
A13: 项目A | D13: =B13+C13 -> 0 | F13: =D13-E13 -> 0 | I13: =G13+H13 -> 0 | K13: =I13-J13 -> 0 | L13: =K13-F13 -> 0 | M13: =IF(AND(F13=0,L13=0),0,IF(AND(F13=0,L13>0),1,L13/F13)) -> 0
A14: 项目B | D14: =B14+C14 -> 0 | F14: =D14-E14 -> 0 | I14: =G14+H14 -> 0 | K14: =I14-J14 -> 0 | L14: =K14-F14 -> 0 | M14: =IF(AND(F14=0,L14=0),0,IF(AND(F14=0,L14>0),1,L14/F14)) -> 0
A15: … | D15: =B15+C15 -> 0 | F15: =D15-E15 -> 0 | I15: =G15+H15 -> 0 | K15: =I15-J15 -> 0 | L15: =K15-F15 -> 0 | M15: =IF(AND(F15=0,L15=0),0,IF(AND(F15=0,L15>0),1,L15/F15)) -> 0
A16: 合计 | B16: =SUM(B13:B15) -> 0 | C16: =SUM(C13:C15) -> 0 | D16: =SUM(D13:D15) -> 0 | E16: =SUM(E13:E15) -> 0 | F16: =SUM(F13:F15) -> 0 | G16: =SUM(G13:G15) -> 0 | H16: =SUM(H13:H15) -> 0 | I16: =SUM(I13:I15) -> 0 | ... K16: =SUM(K13:K15) -> 0 | L16: =K16-F16 -> 0 | M16: =IF(AND(F16=0,L16=0),0,IF(AND(F16=0,L16>0),1,L16/F16)) -> 0
A17: 三、租赁负债净值
A18: 项目A | B18: =B8-B13 -> 0 | C18: =C8-C13 -> 0 | D18: =D8-D13 -> 0 | E18: =E8-E13 -> 0 | F18: =F8-F13 -> 0 | G18: =G8-G13 -> 0 | H18: =H8-H13 -> 0 | I18: =I8-I13 -> 0 | ... K18: =K8-K13 -> 0 | L18: =K18-F18 -> 0 | M18: =IF(AND(F18=0,L18=0),0,IF(AND(F18=0,L18>0),1,L18/F18)) -> 0
A19: 项目B | B19: =B9-B14 -> 0 | C19: =C9-C14 -> 0 | D19: =D9-D14 -> 0 | E19: =E9-E14 -> 0 | F19: =F9-F14 -> 0 | G19: =G9-G14 -> 0 | H19: =H9-H14 -> 0 | I19: =I9-I14 -> 0 | ... K19: =K9-K14 -> 0 | L19: =K19-F19 -> 0 | M19: =IF(AND(F19=0,L19=0),0,IF(AND(F19=0,L19>0),1,L19/F19)) -> 0
A20: … | B20: =B10-B15 -> 0 | C20: =C10-C15 -> 0 | D20: =D10-D15 -> 0 | E20: =E10-E15 -> 0 | F20: =F10-F15 -> 0 | G20: =G10-G15 -> 0 | H20: =H10-H15 -> 0 | I20: =I10-I15 -> 0 | ... K20: =K10-K15 -> 0 | L20: =K20-F20 -> 0 | M20: =IF(AND(F20=0,L20=0),0,IF(AND(F20=0,L20>0),1,L20/F20)) -> 0
A21: 合计 | B21: =SUM(B18:B20) -> 0 | C21: =SUM(C18:C20) -> 0 | D21: =SUM(D18:D20) -> 0 | E21: =SUM(E18:E20) -> 0 | F21: =SUM(F18:F20) -> 0 | G21: =SUM(G18:G20) -> 0 | H21: =SUM(H18:H20) -> 0 | I21: =SUM(I18:I20) -> 0 | ... K21: =SUM(K18:K20) -> 0 | L21: =K21-F21 -> 0 | M21: =IF(AND(F21=0,L21=0),0,IF(AND(F21=0,L21>0),1,L21/F21)) -> 0
A22: 试算平衡表数
A23: 差异 | F23: =F21-F22 -> 0 | K23: =K21-K22 -> 0
A24: 1、审计说明： | I24: 2、审计结论：
A25: （1）租赁负债期末净值较期初净值增加（负数为减少）：
A26: 主要原因（比例超过30%的）：

Sheet 附注披露信息（上市公司）
A1: 致同会计师事务所
A2: 附注披露表（上市公司）
A3: =底稿目录!A2 -> 被审计单位： | B3: =底稿目录!A4 -> 编制人： | C3: =底稿目录!A6 -> 编制日期： | D3: 索引号：
A4: =底稿目录!A3 -> 截止日：202X年12月31日 | B4: =底稿目录!A5 -> 复核人： | C4: =底稿目录!A7 -> 复核日期： | D4: 页 次：
F5: 返回目录
A6: 47、租赁负债
A7: 项 目 | B7: 期末余额 | C7: 上年年末余额
A11: 小 计 | B11: X.XX
A12: 减：一年内到期的租赁负债
A13: 合 计 | B13: X.XX
A14: 2024年计提的租赁负债利息费用金额为XX万元，计入财务费用-利息支出金额为XX万元，计入固定资产金额为XX万元。
A15: 【提示：
A16: （1）承租人根据《企业会计准则第21号——租赁》所确认的租赁负债发生的利息费用适用借款费用准则。使用权资产于租赁期开始日便达到预定可使用状态，租赁负债相关利息费用不应资本化计入使用权资产。租赁期开始日后，租赁负债可视同企业的一般借款。
A17: （2）承租人向出租人支付的租金等款项中包含应缴纳的增值税的，相关增值税税额不属于租赁付款额的范畴，不应纳入租赁负债和使用权资产的计量。
A18: （3）出租人为确保承租人履行合同相关义务收取租赁保证金的，该租赁保证金不属于出租人的租赁收款额和承租人的租赁付款额，出租人和承租人应当分别将其作为单独的负债和资产进行会计处理。】

Sheet 附注披露信息（国企）
A1: 致同会计师事务所
A2: 附注披露表（上市公司）
A3: =底稿目录!A2 -> 被审计单位： | B3: =底稿目录!A4 -> 编制人： | C3: =底稿目录!A6 -> 编制日期： | D3: 索引号：
A4: =底稿目录!A3 -> 截止日：202X年12月31日 | B4: =底稿目录!A5 -> 复核人： | C4: =底稿目录!A7 -> 复核日期： | D4: 页 次：
F5: 返回目录
A6: 49、租赁负债
A7: 项 目 | B7: 期末余额 | C7: 期初余额
A8: 租赁付款额
A9: 减：未确认的融资费用
A10: 重分类至一年内到期的非流动负债
A11: ……
A12: 租赁负债净额
A13: 【提示：
A14: 1、承租人根据《企业会计准则第21号——租赁》所确认的租赁负债发生的利息费用适用借款费用准则。使用权资产于租赁期开始日便达到预定可使用状态，租赁负债相关利息费用不应资本化计入使用权资产。租赁期开始日后，租赁负债可视同企业的一般借款。
A15: 2、承租人向出租人支付的租金等款项中包含应缴纳的增值税的，相关增值税税额不属于租赁付款额的范畴，不应纳入租赁负债和使用权资产的计量。
A16: 3、出租人为确保承租人履行合同相关义务收取租赁保证金的，该租赁保证金不属于出租人的租赁收款额和承租人的租赁付款额，出租人和承租人应当分别将其作为单独的负债和资产进行会计处理。】

Sheet 租赁负债明细表H9-2
A1: 致同会计师事务所
A2: 租赁负债明细表
A3: =底稿目录!A2 -> 被审计单位： | F3: =底稿目录!A4 -> 编制人： | M3: =底稿目录!A6 -> 编制日期： | U3: 索引号： | V3: H9-2
A4: =底稿目录!A3 -> 截止日：202X年12月31日 | F4: =底稿目录!A5 -> 复核人： | M4: =底稿目录!A7 -> 复核日期： | U4: 页 次：
A5: 一、审计目标：1. 资产负债表中记录的租赁负债是存在的，且已记录于恰当的账户；2. 所有应记录的租赁负债均已记录，所有应当包括在财务报表中的相关披露均已包括；3. 租赁负债以恰当的金额包括在财务报表中，与之相关的计价或分摊调整已恰当记录，相关披露已得到恰当计量和描述。
A6: 二、审计过程：
A7: 出租方名称 | B7: 期初余额 | C7: 未审数 | F7: 期初调整 | G7: 本期调整 | I7: 审定数 | M7: 重分类：减一年内到期的租赁负债 | N7: 期末报表数 | O7: 期末到期日分析 | S7: 是否关联方 | T7: 发函或替代情况 | U7: 期后付款 | V7: 备注
C8: 借方发生 | D8: 贷方发生 | E8: 期末余额 | G8: 借方发生 | H8: 贷方发生 | I8: 期初余额 | J8: 借方发生 | K8: 贷方发生 | L8: 期末余额 | O8: 1年以下 | P8: 1～2年 | Q8: ２～3年 | R8: 3年以上
E9: =B9-C9+D9 -> 0 | I9: =B9+F9 -> 0 | J9: =C9+G9 -> 0 | K9: =D9+H9 -> 0 | L9: =I9-J9+K9 -> 0 | N9: =L9-M9 -> 0
E10: =B10-C10+D10 -> 0 | I10: =B10+F10 -> 0 | J10: =C10+G10 -> 0 | K10: =D10+H10 -> 0 | L10: =I10-J10+K10 -> 0 | N10: =L10-M10 -> 0
E11: =B11-C11+D11 -> 0 | I11: =B11+F11 -> 0 | J11: =C11+G11 -> 0 | K11: =D11+H11 -> 0 | L11: =I11-J11+K11 -> 0 | N11: =L11-M11 -> 0
E12: =B12-C12+D12 -> 0 | I12: =B12+F12 -> 0 | J12: =C12+G12 -> 0 | K12: =D12+H12 -> 0 | L12: =I12-J12+K12 -> 0 | N12: =L12-M12 -> 0
E13: =B13-C13+D13 -> 0 | I13: =B13+F13 -> 0 | J13: =C13+G13 -> 0 | K13: =D13+H13 -> 0 | L13: =I13-J13+K13 -> 0 | N13: =L13-M13 -> 0
A14: 合计 | B14: =SUM(B9:B13) -> 0 | C14: =SUM(C9:C13) -> 0 | D14: =SUM(D9:D13) -> 0 | E14: =SUM(E9:E13) -> 0 | F14: =SUM(F9:F13) -> 0 | G14: =SUM(G9:G13) -> 0 | H14: =SUM(H9:H13) -> 0 | I14: =SUM(I9:I13) -> 0 | ... R14: =SUM(R9:R13) -> 0 | S14: -- | T14: -- | U14: =SUM(U9:U13) -> 0 | V14: --
A15: 1、审计说明： | I15: 2、审计结论：
A16: 租赁负债的初始确认及未确认融资费用的摊销计算过程，详见使用权资产底稿<H8-4/H8-5/H8-6/H8-7>
A19: 提示：
A20: 审计说明可以概述:(1)程序的测试情况、结果;(2)拟调整事项及其调整分录、未调整事项及其影响，审计范围受到限制情况及其影响。
A21: 审计结论可参考：A、未见异常。 B、除上述重大不符事项应当作为调整事项予以调整外，其余未见异常。 C、由于存在以下重大未调整事项(或审计范围受到限制无法获取充分、适当证据)，不可确认。

Sheet 未确认融资费用明细表H9-3
A1: 致同会计师事务所
A2: 未确认融资费用明细表
A3: =底稿目录!A2 -> 被审计单位： | G3: =底稿目录!A4 -> 编制人： | M3: =底稿目录!A6 -> 编制日期： | T3: 索引号： | U3: H9-3
A4: =底稿目录!A3 -> 截止日：202X年12月31日 | G4: =底稿目录!A5 -> 复核人： | M4: =底稿目录!A7 -> 复核日期： | T4: 页 次：
A5: 一、审计目标：1. 资产负债表中记录的租赁负债是存在的，且已记录于恰当的账户；2. 所有应记录的租赁负债均已记录，所有应当包括在财务报表中的相关披露均已包括；3. 租赁负债以恰当的金额包括在财务报表中，与之相关的计价或分摊调整已恰当记录，相关披露已得到恰当计量和描述。
A6: 二、审计过程：获取或编制未确认融资费用明细表，将总金额与报表、总账、明细账合计数核对相符。
A7: 出租方名称 | B7: 期初余额 | C7: 未审数 | F7: 账项调整 | H7: 重分类调整 | J7: 审定数 | N7: 减：期末一年内到期未确认融资费用 | O7: 期末最终审定数 | P7: 到期日 | T7: 是否是关联方 | U7: 备注
C8: 借方发生 | D8: 贷方发生 | E8: 期末余额 | F8: 借方发生 | G8: 贷方发生 | H8: 借方发生 | I8: 贷方发生 | J8: 期初余额 | K8: 借方发生 | L8: 贷方发生 | M8: 期末余额 | P8: 1年以下 | Q8: 1～2年 | R8: ２～3年 | S8: 3年以上
A9: ='租赁负债明细表H9-2'!A9 -> 0 | E9: =B9+C9-D9 -> 0 | J9: =B9 -> 0 | K9: =C9+F9+H9 -> 0 | L9: =D9+G9+I9 -> 0 | M9: =J9+K9-L9 -> 0 | O9: =M9-N9 -> 0
A10: ='租赁负债明细表H9-2'!A10 -> 0 | J10: =B10 -> 0 | K10: =C10+F10+H10 -> 0 | L10: =D10+G10+I10 -> 0 | M10: =J10+K10-L10 -> 0 | O10: =M10-N10 -> 0
A11: ='租赁负债明细表H9-2'!A11 -> 0 | J11: =B11 -> 0 | K11: =C11+F11+H11 -> 0 | L11: =D11+G11+I11 -> 0 | M11: =J11+K11-L11 -> 0 | O11: =M11-N11 -> 0
A12: ='租赁负债明细表H9-2'!A12 -> 0 | J12: =B12 -> 0 | K12: =C12+F12+H12 -> 0 | L12: =D12+G12+I12 -> 0 | M12: =J12+K12-L12 -> 0 | O12: =M12-N12 -> 0
A13: ='租赁负债明细表H9-2'!A13 -> 0 | J13: =B13 -> 0 | K13: =C13+F13+H13 -> 0 | L13: =D13+G13+I13 -> 0 | M13: =J13+K13-L13 -> 0 | O13: =M13-N13 -> 0
A14: 合计 | B14: =SUM(B9:B13) -> 0 | C14: =SUM(C9:C13) -> 0 | D14: =SUM(D9:D13) -> 0 | E14: =SUM(E9:E13) -> 0 | F14: =SUM(F9:F13) -> 0 | G14: =SUM(G9:G13) -> 0 | H14: =SUM(H9:H13) -> 0 | I14: =SUM(I9:I13) -> 0 | ... S14: =SUM(S9:S13) -> 0
A15: 三、审计说明：
A16: 租赁负债的初始确认及未确认融资费用的摊销计算过程，详见使用权资产底稿<H8-4/H8-5/H8-6/H8-7>
A19: 四、审计结论：
A23: 提示：
A24: 审计说明可以概述:(1)程序的测试情况、结果;(2)拟调整事项及其调整分录、未调整事项及其影响，审计范围受到限制情况及其影响。
A25: 审计结论可参考：A、未见异常。 B、除上述重大不符事项应当作为调整事项予以调整外，其余未见异常。 C、由于存在以下重大未调整事项(或审计范围受到限制无法获取充分、适当证据)，不可确认。
A26: 本科目核算企业应当分期计入利息费用的未确认融资费用。

Sheet 调整分录汇总H9-4
A1: 致同会计师事务所
A2: 租赁负债调整分录汇总表
A3: =底稿目录!A2 -> 被审计单位： | D3: =底稿目录!A4 -> 编制人： | G3: =底稿目录!A6 -> 编制日期： | I3: 索引号： | J3: H9-4
A4: =底稿目录!A3 -> 截止日：202X年12月31日 | D4: =底稿目录!A5 -> 复核人： | G4: =底稿目录!A7 -> 复核日期： | I4: 页 次：
A5: 调整事项说明 | B5: 类别（报表调整/账项调整/其他） | C5: 报表项目 | D5: 科目名称 | E5: 附注项目 | F5: …… | G5: 借方调整金额 | H5: 贷方调整金额 | I5: 索引 | J5: 备注
A23: 提示：本底稿适用于调整分录较多、较复杂的项目，且仅列示与本报表项目相关的审计调整。项目组可根据项目实际情况选择是否使用该底稿。

Sheet GT_Custom
A1: C1 | B1: Custom 1
A2: C2 | B2: Custom 2
A3: C3 | B3: Custom 3
A4: C4 | B4: Custom 4
A5: C5 | B5: Custom 5
A6: C6 | B6: Custom 6
A7: C7 | B7: Custom 7
A8: C8 | B8: Custom 8
