Workbook

Sheet 底稿目录
A1: 底稿开列时，可先在以下单元格填写有关内容，以便其他底稿引用有关数据：
A2: 被审计单位：
A3: 截止日：202X年12月31日 | D3: 序号 | E3: 内容 | F3: 索引号
A4: 编制人： | E4: 交易性金融资产实质性程序表 | F4: G1A
A5: 编制日期： | D5: 1 | E5: 审定表 | F5: G1-1
A6: 复核人： | D6: 2 | E6: 附注披露信息（上市公司） | G6: 无需打印
A7: 复核日期： | D7: 3 | E7: 附注披露信息（国企） | G7: 无需打印
D8: 4 | E8: 明细表 | F8: G1-2
A9: 关于工作底稿与审计程序索引号对应的说明 | D9: 5 | E9: 调整分录汇总 | F9: G1-3
A10: 1.编制的审计工作底稿应与审计程序对应。审计项目组应根据被审计单位实际情况和风险评估情况在实质性程序表中裁剪、修改或增加审计程序，根据实际执行的审计程序完成相应审计工作底稿，编制的工作底稿中应按自然顺序依次编制索引号，并通过唯一的索引号将与实质性程序表中的程序对应关联（即将工作底稿的索引号填入实质性程序表中的底稿索引号列）。 | D10: 6 | E10: 期末结存表 | F10: G1-4
D11: 7 | E11: 收益测算表 | F11: G1-5
D12: 8 | E12: 公允价值测试表 | F12: G1-6
D13: 9 | E13: 第三层次公允价值计量的调节表 | F13: G1-7
A14: 2.获取的支持性证据应与审计底稿或程序对应。审计项目组在完成底稿时获取的支持性证据应根据底稿索引号编制下一级按自然顺序排序的索引号（如D1-2-1、D1-2-2、……），并在底稿中说明引用的支持性证据、关联索引号。 | D14: 10 | E14: 业务模式分析 | F14: G1-8
D15: 11 | E15: 分类的适当性检查表 | F15: G1-9
D16: 12 | E16: 合同现金流量特征分析 | F16: G1-10
A17: 3.工作底稿索引号的编码规则：实质性程序索引号按循环从“D”到“N”,循环内账户以顺序号排列，模板中底稿索引号按账户顺序+自然数顺序（即模板中索引号按二级自然顺序排列，如D1-1、D1-2、D1-3、……D1-N）。 | D17: 13 | E17: 有价证券监盘表 | F17: G1-11
D18: 14 | E18: 有价证券盘点倒轧表 | F18: G1-12
D19: 15 | E19: 函证结果汇总表 | F19: G0-1
D20: 16 | E20: 核实被函证单位信息 | F20: G0-2
D21: 17 | E21: 跟函函证过程控制 | F21: G0-3
D22: 18 | E22: 函证差异核对表（证券投资） | F22: G0-4
D23: 19 | E23: 函证差异核对表(非证券投资) | F23: G0-5
D24: 20 | E24: 替代程序检查表 | F24: G0-6
D25: 21 | E25: 邮件传真回函可靠性验证 | F25: G0-7
D26: 22 | E26: 函证程序舞弊风险评价表 | F26: G0-8
D27: 23 | E27: 检查表 | F27: G1-13
D28: 24 | E28: 衍生金融工具核对表 | F28: G1-14

Sheet 交易性金融资产实质性程序表G1A 
A1: 致同会计师事务所
A2: 交易性金融资产实质性程序表
A3: =底稿目录!A2 -> 被审计单位： | C3: =底稿目录!A4 -> 编制人： | E3: =底稿目录!A5 -> 编制日期： | H3: 索引号： | I3: =底稿目录!F4 -> G1A
A4: =底稿目录!A3 -> 截止日：202X年12月31日 | C4: =底稿目录!A6 -> 复核人： | E4: =底稿目录!A7 -> 复核日期： | H4: 页 次：
A5: 一、本账户涉及的科目
A6: 交易性金融资产
A7: 二、审计目标与认定的对应关系
A8: 审计目标 | G8: 财务报表的认定
A9: A.资产负债表中记录的交易性金融资产是存在的，且已记录于恰当的账户 | G9: 存在
A10: B.所有应记录的交易性金融资产均已记录，所有应当包括在财务报表中的相关披露均已包括 | G10: 完整性
A11: C.记录的交易性金融资产由被审计单位拥有或控制 | G11: 权利和义务
A12: D.交易性金融资产以恰当的金额包括在财务报表中，与之相关的计价或分摊调整已恰当记录，相关披露已得到恰当计量和描述 | G12: 准确性、计价和分摊
A13: E.交易性金融资产已被恰当地汇总或分解且表述清楚，相关披露在按照企业会计准则的编制基础下是相关的、可理解的 | G13: 列报
A14: 三、审计目标与审计程序的对应关系
A15: 序号 | B15: 审计程序 | C15: 程序分类 | D15: 财务报表的认定 | I15: 底稿索引号
D16: 存在 | E16: 完整性 | F16: 权利和 义务 | G16: 准确性、计价和分摊 | H16: 列报 | J16: 根据被审计单位实际情况和风险评估情况裁剪、修改或增加审计程序
A17: 1 | B17: 获取或编制交易性金融资产的明细表，完成以下工作，并编制审定表 （1）复核加计是否正确，与总账、明细账合计数核对是否相符，将期初余额与上期期末余额核对； （2）与上年明细项目进行比较，确定与上年分类相同； （3）与应收利息、投资收益、公允价值变动损益等项目的变动进行核对，复核其勾稽关系； （4）调查重大或者异常的调节项目，并与客户的适当人员讨论差异，考虑回复的可信度并确认相关解释，以及采取适当的措施； （5）检查非记账本位币计量的交易性金融资产的折算汇率及折算是否正确。 | C17: 常规★ | D17: √ | E17: √ | G17: √ | I17: G1-1 /G1-2
A18: 2 | B18: 在使用手工编制、自定义信息报告、系统生成的非固定格式报告等由被审计单位生成的信息时，测试有关信息准确性和完整性，并考虑针对编制和维护由被审计单位生成的信息的相关控制实施控制测试，以评价该信息是否能够为实现审计目的提供基础。 | C18: 常规★ | E18: √ | G18: √ | I18: T1 /G0-2 /
A19: 3 | B19: 对期初余额的审计，取得交易性金融资产期初余额明细表复核加计是否正确，与总账、明细账合计数是否相符，确定会计政策及程序是否适当，确定计算的准确性；检查期初投资在本期处置情况，确定证券投资是否在第一个季度亏损出售；将重大投资与其支持性文件核对一致；确定是否需要补充必要的程序，如果是，执行适当的应对程序。（适用于首次承接） | C19: 备选 | D19: √ | E19: √ | F19: √ | G19: √
A20: 4 | B20: 根据实际情况，实施以下分析程序： （1）获取增、减分析表，确定增加内容及减少方式、对损益的影响； （2）复核年度交易性金融资产的总体合理性；对变化较大的项目或没有变动的项目进行复核，与被审计单位适当人员讨论原因，判断其存在的合理性，是否存在减值； （3）结合交易性金融资产循环中投资收益的审计，计算年度金融资产循环收益占利润总额的比例，分析公司对金融资产循环收益的依赖程度，判断其盈利能力和稳定性。 | C20: 常规★ | D20: √ | G20: √ | I20: G1-1 /G1-2
A21: 5 | B21: 确认交易性金融资产会计政策、会计处理是否合理并与前期一致，会计估计是否合理，实施以下程序： （1）关注被审计单位管理金融工具的业务模式，并结合合同现金流量特征，分析管理层对债权投资的金融资产分类是否合理； （2）与管理层讨论交易性金融资产分类是否符合企业会计准则，是否根据确定的分类选用了正确的核算方法； （3）是否发现管理层在以前年度运用的重大判断和估计存在不合理的情形。如果存在，记录下管理层是否在当年进行了恰当的会计处理和披露，并选用了更为准确的判断和假设。 | C21: 常规★ | D21: √ | E21: √ | G21: √ | I21: G1-1 /G1-2 /G1-7 /G1-8
A22: 6 | B22: 获取股票、债券、期货、基金、衍生金融资产等账户对账单，与明细账余额核对，如有差异，应调查原因并考虑作出适当调整。 | C22: 常规★ | D22: √ | E22: √ | F22: √ | G22: √ | I22: G1-4
A23: 7 | B23: 询问各项投资是否存在任何限制、抵押或留置权,检查有无变现存在重大限制的资产，如有，则查明情况，作出记录。 | C23: 常规★ | F23: √ | I23: G1-2 /G1-4
A24: 8 | B24: 对于本期新增的金融资产投资，执行以下程序： （1）获取本期增加的金融资产投资的合约、协议、中介机构报告等（若适用），查验金融资产的分类及计价是否正确；追查至相应的原始凭证及支持文件，检查其是否经过授权审批，确认是否符合合同协议条款的规定；必要时进行穿透核查，明确相关金融产品的资金投向，是否存在定向投资要求、投资对象是否与控股股东存在关联关系等； （2）对本期增加中的特定项目（如金额重大或性质特殊的）进行以下测试：检查非货币性资产交换、债务重组、企业合并、投资等发生取得金融资产的会计处理是否正确； | C24: 常规★ | D24: √ | F24: √ | G24: √ | I24: G1-2 /G1-12
A25: 9 | B25: 关注单独的重大金融资产转移或处置，考虑实施以下程序： （1）获取本期减少的金融资产投资的合约、协议、中介机构报告等（若适用），查验金融资产转移的处理及计价是否正确；追查至相应的原始凭证及支持文件，检查其是否经过授权审批，确认是否符合合同协议条款的规定； （2）对本期减少中的特定项目进行以下测试：检查非货币性资产交换、债务重组、企业合并、投资等发生金融资产转移的会计处理是否正确； （3）重新计算相关的利得或损失； （4）关注处置日期是否记录恰当，会计处理是否恰当。 | C25: 常规★ | D25: √ | E25: √ | F25: √ | G25: √ | I25: G1-2 /G1-11
A26: 10 | B26: 对于本期发生的金融资产重新分类，询问管理层，了解报告期是否存在业务模式变更.金融工具准则指出，金融资产业务模式变更属于极其少见的情形，只有当企业开始或终止某项对其经营影响重大的活动时（例如当企业收购、处置或终止某一业务线时），其管理金融资产的业务模式才会发生变更。如存在，需要获取相关重大交易的会议纪要、批准文件、合同等作为审计证据。 | C26: 常规★ | G26: √ | I26: G1-7 /G1-8
A27: 11 | B27: 针对公允价值计量的投资，复核交易性金融资产计价方法，检查其是否按公允价值计量，前后期是否一致；复核公允价值取得依据是否充分；复核计算持有期间的投资收益；检查会计处理是否正确。若选择利用专家工作的审计程序，参考“S12利用专家的工作”相关程序执行 | C27: 常规★ | G27: √ | H27: √ | I27: G1-5/G1-6
A28: 12 | B28: 对库存证券，执行监盘程序： （1）观察证券，将观察的证券与与投资明细核对一致，如有差异，查明原因，并作出恰当处理； （2）对抽样确定的监盘样本，观察证券并与各存放地点汇总明细核对一致； （3）盘点日在资产负债表日后的，实施盘点到轧，并对资产负债表日至盘点日的增减变动取得审计证据；并且调查重大的调节项目； （4）与客户的适当人员讨论差异，考虑回复的可信度并确认相关解释,以及采取适当的措施。 | C28: 备选 | D28: √ | F28: √ | I28: G1-10 /G1-11
A29: 13 | B29: 对于衍生金融工具，执行以下程序： （1）复核衍生金融工具交易对手的信用状况，确定衍生金融资产的交易对手能够履行他们的合同义务； （2）检查贷款或权益、投资协议、销售合同等，了解其中是否包含嵌入衍生金融工具； （3）阅读治理层的会议纪要，以及治理层收到的与衍生活动相关的文件和报告等其他信息； （4）确定金融工具的会计处理是合理的，估值结果是恰当的； （5）确定是否应引入估值专家，以协助评价该企业估值专家对该金融工具的估值工作。若选择利用专家工作的审计程序，参考“S12利用专家的工作”相关程序执行。 | C29: 常规★ | D29: √ | F29: √ | G29: √ | I29: G1-13
A30: 14 | B30: 关注资产负债表日后事项，新增、售出、兑换、处置、收回或偿付的大额出售或购买交易，确认是否被记录在恰当时期内；检查报表日后的证券处置是否出现亏损，如果确认亏损，确定这些亏损是否应该记录在报表期。 | C30: 常规★ | D30: √ | E30: √ | G30: √ | I30: G1-12
A31: 15 | B31: 向相关机构发函，并确定是否存在变现限制，同时记录函证过程： （1）以积极方式进行函证，设计询证函、发函前核实被函证单位信息； （2）注册会计师独立收发询证函； （3）编制函证结果汇总表，检查发函、回函物流信息和轨迹、比对回函印章和签字等以核实回函的真实性，检查回函是否相符，对不符事项查明原因确定是否存在错报； （4）如果未收到回函，应当考虑与被询证者联系，要求对方作出回应或再次寄发询证函，无法收到的回函实施替代程序； （5）如果管理层不允许寄发询证函的，询问管理层不允许寄发的原因，并就其原因的正当、合理性收集证据；考虑实施替代审计程序以获取相关、可靠的审计证据； （6）如果管理层不允许寄发询证函的原因不合理、或者认为回函不可靠，评价对评估的重大错报风险以及其他审计程序的性质、时间安排和范围的影响，并确定其对审计工作和审计意见的影响。 | C31: 备选 | D31: √ | E31: √ | F31: √ | G31: √ | I31: G0
A32: 16 | B32: 检查关联方交易： （1）了解关联交易的商业理由、交易事项的目的、价格和条件，考虑对关联方交易性金融资产的合理性、合法性； （2）检查对关联方交易性金融资产的真实性相关的支持性文件、检查会计处理是否正确； （3）考虑向关联方或其他注册会计师函证重大的关联交易和余额（包括担保和其他重要信息）； （4）必要时，向与交易相关的人员和机构函证或与其讨论有关信息； （5）考虑是否存在未识别的关联方，关联交易和余额披露是否正确。 | C32: 常规★ | D32: √ | E32: √ | F32: √ | G32: √ | H32: √ | I32: G1-12
A33: 17 | B33: 根据评估的舞弊风险等因素增加的审计程序。 | C33: IPO/上市/新三板/重组/舞弊应对
A34: 18 | B34: 检查交易性金融资产是否已按企业会计准则或其他适用的规定在财务报表中做出恰当列报和披露。 | C34: 常规★ | H34: √ | I34: A1-1

Sheet 审定表G1-1
A1: 致同会计师事务所
A2: 交易性金融资产审定表
A3: =底稿目录!A2 -> 被审计单位： | D3: =底稿目录!A4 -> 编制人： | G3: =底稿目录!A5 -> 编制日期： | I3: 索引号： | J3: =底稿目录!F5 -> G1-1
A4: =底稿目录!A3 -> 截止日：202X年12月31日 | D4: =底稿目录!A6 -> 复核人： | G4: =底稿目录!A7 -> 复核日期： | I4: 页 次：
A5: 项目 | B5: 期初数 | E5: 期末数 | H5: 本期与上期审定数比较 | J5: 原因分析
B6: 未审数 | C6: 账项调整 | D6: 审定数 | E6: 未审数 | F6: 账项调整 | G6: 审定数 | H6: 变动额 | I6: 变动率
A7: （一）投资成本
A8: 交易性金融资产 | B8: =SUM(B9:B15) -> 0 | C8: =SUM(C9:C15) -> 0 | D8: =SUM(D9:D15) -> 0 | E8: =SUM(E9:E15) -> 0 | F8: =SUM(F9:F15) -> 0 | G8: =SUM(G9:G15) -> 0 | H8: =SUM(H9:H15) -> 0 | I8: =IF(AND(D8=0,G8=0),"",IF(AND(D8=0,G8>0),1,H8/D8))
A9: 其中：债务工具投资 | B9: =SUMIF('明细表G1-2'!A12:A16,"债务工具投资",'明细表G1-2'!C12:C16) -> 0 | C9: =SUMIF('明细表G1-2'!A12:A16,"债务工具投资",'明细表G1-2'!F12:F16) -> 0 | D9: =B9+C9 -> 0 | E9: =SUMIF('明细表G1-2'!A12:A16,"债务工具投资",'明细表G1-2'!P12:P16) -> 0 | F9: =SUMIF('明细表G1-2'!A12:A16,"债务工具投资",'明细表G1-2'!S12:S16) -> 0 | G9: =E9+F9 -> 0 | H9: =G9-D9 -> 0 | I9: =IF(AND(D9=0,G9=0),"",IF(AND(D9=0,G9>0),1,H9/D9))
A10: 权益工具投资 | B10: =SUMIF('明细表G1-2'!A12:A16,"权益工具投资",'明细表G1-2'!C12:C16) -> 0 | C10: =SUMIF('明细表G1-2'!A12:A16,"权益工具投资",'明细表G1-2'!F12:F16) -> 0 | D10: =B10+C10 -> 0 | E10: =SUMIF('明细表G1-2'!A12:A16,"权益工具投资",'明细表G1-2'!P12:P16) -> 0 | F10: =SUMIF('明细表G1-2'!A12:A16,"权益工具投资",'明细表G1-2'!S12:S16) -> 0 | G10: =E10+F10 -> 0 | H10: =G10-D10 -> 0 | I10: =IF(AND(D10=0,G10=0),"",IF(AND(D10=0,G10>0),1,H10/D10))
A11: 衍生金融资产 | B11: =SUMIF('明细表G1-2'!A12:A16,"衍生金融资产",'明细表G1-2'!C12:C16) -> 0 | C11: =SUMIF('明细表G1-2'!A12:A16,"衍生金融资产",'明细表G1-2'!A12:A16) -> 0 | D11: =B11+C11 -> 0 | E11: =SUMIF('明细表G1-2'!A12:A16,"衍生金融资产",'明细表G1-2'!P12:P16) -> 0 | F11: =SUMIF('明细表G1-2'!A12:A16,"衍生金融资产",'明细表G1-2'!S12:S16) -> 0 | G11: =E11+F11 -> 0 | H11: =G11-D11 -> 0 | I11: =IF(AND(D11=0,G11=0),"",IF(AND(D11=0,G11>0),1,H11/D11))
A12: 理财产品 | B12: =SUMIF('明细表G1-2'!A12:A16,"理财产品",'明细表G1-2'!C12:C16) -> 0 | C12: =SUMIF('明细表G1-2'!A12:A16,"理财产品",'明细表G1-2'!A12:A16) -> 0 | D12: =B12+C12 -> 0 | E12: =SUMIF('明细表G1-2'!A12:A16,"理财产品",'明细表G1-2'!P12:P16) -> 0 | F12: =SUMIF('明细表G1-2'!A12:A16,"理财产品",'明细表G1-2'!S12:S16) -> 0 | G12: =E12+F12 -> 0 | H12: =G12-D12 -> 0 | I12: =IF(AND(D12=0,G12=0),"",IF(AND(D12=0,G12>0),1,H12/D12))
A13: 结构性存款 | B13: =SUMIF('明细表G1-2'!A12:A16,"结构性存款",'明细表G1-2'!C12:C16) -> 0 | C13: =SUMIF('明细表G1-2'!A12:A16,"结构性存款",'明细表G1-2'!A12:A16) -> 0 | D13: =B13+C13 -> 0 | E13: =SUMIF('明细表G1-2'!A12:A16,"结构性存款",'明细表G1-2'!P12:P16) -> 0 | F13: =SUMIF('明细表G1-2'!A12:A16,"结构性存款",'明细表G1-2'!S12:S16) -> 0 | G13: =E13+F13 -> 0 | H13: =G13-D13 -> 0 | I13: =IF(AND(D13=0,G13=0),"",IF(AND(D13=0,G13>0),1,H13/D13))
A14: 基金 | B14: =SUMIF('明细表G1-2'!A12:A16,"基金",'明细表G1-2'!C12:C16) -> 0 | C14: =SUMIF('明细表G1-2'!A12:A16,"基金",'明细表G1-2'!A12:A16) -> 0 | D14: =B14+C14 -> 0 | E14: =SUMIF('明细表G1-2'!A12:A16,"基金",'明细表G1-2'!P12:P16) -> 0 | F14: =SUMIF('明细表G1-2'!A12:A16,"基金",'明细表G1-2'!S12:S16) -> 0 | G14: =E14+F14 -> 0 | H14: =G14-D14 -> 0 | I14: =IF(AND(D14=0,G14=0),"",IF(AND(D14=0,G14>0),1,H14/D14))
A15: 其他 | B15: =SUMIF('明细表G1-2'!A12:A16,"其他",'明细表G1-2'!C12:C16) -> 0 | C15: =SUMIF('明细表G1-2'!A12:A16,"其他",'明细表G1-2'!A12:A16) -> 0 | D15: =B15+C15 -> 0 | E15: =SUMIF('明细表G1-2'!A12:A16,"其他",'明细表G1-2'!P12:P16) -> 0 | F15: =SUMIF('明细表G1-2'!A12:A16,"其他",'明细表G1-2'!S12:S16) -> 0 | G15: =E15+F15 -> 0 | H15: =G15-D15 -> 0 | I15: =IF(AND(D15=0,G15=0),"",IF(AND(D15=0,G15>0),1,H15/D15))
A16: 划分为以公允价值计量且其变动计入当期损益的金融资产 | B16: =SUM(B17:B23) -> 0 | C16: =SUM(C17:C23) -> 0 | D16: =SUM(D17:D23) -> 0 | E16: =SUM(E17:E23) -> 0 | F16: =SUM(F17:F23) -> 0 | G16: =SUM(G17:G23) -> 0 | H16: =SUM(H17:H23) -> 0 | I16: =IF(AND(D16=0,G16=0),"",IF(AND(D16=0,G16>0),1,H16/D16))
A17: 其中：债务工具投资 | B17: =SUMIF('明细表G1-2'!A19:A23,"债务工具投资",'明细表G1-2'!C19:C23) -> 0 | C17: =SUMIF('明细表G1-2'!A19:A23,"债务工具投资",'明细表G1-2'!F19:F23) -> 0 | D17: =B17+C17 -> 0 | E17: =SUMIF('明细表G1-2'!A19:A23,"债务工具投资",'明细表G1-2'!P19:P23) -> 0 | F17: =SUMIF('明细表G1-2'!A19:A23,"债务工具投资",'明细表G1-2'!S19:S23) -> 0 | G17: =E17+F17 -> 0 | H17: =G17-D17 -> 0 | I17: =IF(AND(D17=0,G17=0),"",IF(AND(D17=0,G17>0),1,H17/D17))
A18: 权益工具投资 | B18: =SUMIF('明细表G1-2'!A19:A23,"权益工具投资",'明细表G1-2'!C19:C23) -> 0 | C18: =SUMIF('明细表G1-2'!A19:A23,"权益工具投资",'明细表G1-2'!F19:F23) -> 0 | D18: =B18+C18 -> 0 | E18: =SUMIF('明细表G1-2'!A19:A23,"权益工具投资",'明细表G1-2'!P19:P23) -> 0 | F18: =SUMIF('明细表G1-2'!A19:A23,"权益工具投资",'明细表G1-2'!S19:S23) -> 0 | G18: =E18+F18 -> 0 | H18: =G18-D18 -> 0 | I18: =IF(AND(D18=0,G18=0),"",IF(AND(D18=0,G18>0),1,H18/D18))
A19: 衍生金融资产 | B19: =SUMIF('明细表G1-2'!A19:A23,"衍生金融资产",'明细表G1-2'!C19:C23) -> 0 | C19: =SUMIF('明细表G1-2'!A19:A23,"衍生金融资产",'明细表G1-2'!F19:F23) -> 0 | D19: =B19+C19 -> 0 | E19: =SUMIF('明细表G1-2'!A19:A23,"衍生金融资产",'明细表G1-2'!P19:P23) -> 0 | F19: =SUMIF('明细表G1-2'!A19:A23,"衍生金融资产",'明细表G1-2'!S19:S23) -> 0 | G19: =E19+F19 -> 0 | H19: =G19-D19 -> 0 | I19: =IF(AND(D19=0,G19=0),"",IF(AND(D19=0,G19>0),1,H19/D19))
A20: 理财产品 | B20: =SUMIF('明细表G1-2'!A19:A23,"理财产品",'明细表G1-2'!C19:C23) -> 0 | C20: =SUMIF('明细表G1-2'!A19:A23,"理财产品",'明细表G1-2'!F19:F23) -> 0 | D20: =B20+C20 -> 0 | E20: =SUMIF('明细表G1-2'!A19:A23,"理财产品",'明细表G1-2'!P19:P23) -> 0 | F20: =SUMIF('明细表G1-2'!A20:A24,"理财产品",'明细表G1-2'!S20:S24) -> 0 | G20: =E20+F20 -> 0 | H20: =G20-D20 -> 0 | I20: =IF(AND(D20=0,G20=0),"",IF(AND(D20=0,G20>0),1,H20/D20))
A21: 结构性存款 | B21: =SUMIF('明细表G1-2'!A19:A23,"结构性存款",'明细表G1-2'!C19:C23) -> 0 | C21: =SUMIF('明细表G1-2'!A19:A23,"结构性存款",'明细表G1-2'!F19:F23) -> 0 | D21: =B21+C21 -> 0 | E21: =SUMIF('明细表G1-2'!A19:A23,"结构性存款",'明细表G1-2'!P19:P23) -> 0 | F21: =SUMIF('明细表G1-2'!A20:A24,"结构性存款",'明细表G1-2'!S20:S24) -> 0 | G21: =E21+F21 -> 0 | H21: =G21-D21 -> 0 | I21: =IF(AND(D21=0,G21=0),"",IF(AND(D21=0,G21>0),1,H21/D21))
A22: 基金 | B22: =SUMIF('明细表G1-2'!A19:A23,"基金",'明细表G1-2'!C19:C23) -> 0 | C22: =SUMIF('明细表G1-2'!A19:A23,"基金",'明细表G1-2'!F19:F23) -> 0 | D22: =B22+C22 -> 0 | E22: =SUMIF('明细表G1-2'!A19:A23,"基金",'明细表G1-2'!P19:P23) -> 0 | F22: =SUMIF('明细表G1-2'!A20:A24,"基金",'明细表G1-2'!S20:S24) -> 0 | G22: =E22+F22 -> 0 | H22: =G22-D22 -> 0 | I22: =IF(AND(D22=0,G22=0),"",IF(AND(D22=0,G22>0),1,H22/D22))
A23: 其他 | B23: =SUMIF('明细表G1-2'!A19:A23,"其他",'明细表G1-2'!C19:C23) -> 0 | C23: =SUMIF('明细表G1-2'!A19:A23,"其他",'明细表G1-2'!F19:F23) -> 0 | D23: =B23+C23 -> 0 | E23: =SUMIF('明细表G1-2'!A19:A23,"其他",'明细表G1-2'!P19:P23) -> 0 | F23: =SUMIF('明细表G1-2'!A19:A23,"其他",'明细表G1-2'!S19:S23) -> 0 | G23: =E23+F23 -> 0 | H23: =G23-D23 -> 0 | I23: =IF(AND(D23=0,G23=0),"",IF(AND(D23=0,G23>0),1,H23/D23))
A24: 指定为以公允价值计量且其变动计入当期损益的金融资产 | B24: =SUM(B25:B26) -> 0 | C24: =SUM(C25:C26) -> 0 | D24: =SUM(D25:D26) -> 0 | E24: =SUM(E25:E26) -> 0 | F24: =SUM(F25:F26) -> 0 | G24: =SUM(G25:G26) -> 0 | H24: =SUM(H25:H26) -> 0 | I24: =IF(AND(D24=0,G24=0),"",IF(AND(D24=0,G24>0),1,H24/D24))
A25: 其中：债务工具投资 | B25: =SUMIF('明细表G1-2'!A26:A28,"债务工具投资",'明细表G1-2'!C26:C28) -> 0 | C25: =SUMIF('明细表G1-2'!A26:A28,"债务工具投资",'明细表G1-2'!F26:F28) -> 0 | D25: =B25+C25 -> 0 | E25: =SUMIF('明细表G1-2'!A26:A28,"债务工具投资",'明细表G1-2'!P26:P28) -> 0 | F25: =SUMIF('明细表G1-2'!A26:A28,"债务工具投资",'明细表G1-2'!S26:S28) -> 0 | G25: =E25+F25 -> 0 | H25: =G25-D25 -> 0 | I25: =IF(AND(D25=0,G25=0),"",IF(AND(D25=0,G25>0),1,H25/D25))
A26: 其他 | B26: =SUMIF('明细表G1-2'!A26:A28,"其他",'明细表G1-2'!C26:C28) -> 0 | C26: =SUMIF('明细表G1-2'!A26:A28,"其他",'明细表G1-2'!F26:F28) -> 0 | D26: =B26+C26 -> 0 | E26: =SUMIF('明细表G1-2'!A26:A28,"其他",'明细表G1-2'!P26:P28) -> 0 | F26: =SUMIF('明细表G1-2'!A26:A28,"其他",'明细表G1-2'!S26:S28) -> 0 | G26: =E26+F26 -> 0 | H26: =G26-D26 -> 0 | I26: =IF(AND(D26=0,G26=0),"",IF(AND(D26=0,G26>0),1,H26/D26))
A27: 投资成本小计 | B27: =SUM(B8,B16,B24) -> 0 | C27: =SUM(C8,C16,C24) -> 0 | D27: =SUM(D8,D16,D24) -> 0 | E27: =SUM(E8,E16,E24) -> 0 | F27: =SUM(F8,F16,F24) -> 0 | G27: =SUM(G8,G16,G24) -> 0 | H27: =SUM(H8,H24) -> 0 | I27: =IF(AND(D27=0,G27=0),"",IF(AND(D27=0,G27>0),1,H27/D27))
A28: （二）累计公允价值变动
A29: 交易性金融资产 | B29: =SUM(B30:B36) -> 0 | C29: =SUM(C30:C36) -> 0 | D29: =SUM(D30:D36) -> 0 | E29: =SUM(E30:E36) -> 0 | F29: =SUM(F30:F36) -> 0 | G29: =SUM(G30:G36) -> 0 | H29: =SUM(H30:H36) -> 0 | I29: =IF(AND(D29=0,G29=0),"",IF(AND(D29=0,G29>0),1,H29/D29))
A30: 其中：债务工具投资 | B30: =SUMIF('明细表G1-2'!A12:A16,"债务工具投资",'明细表G1-2'!D12:D16) -> 0 | C30: =SUMIF('明细表G1-2'!A12:A16,"债务工具投资",'明细表G1-2'!G12:G16) -> 0 | D30: =B30+C30 -> 0 | E30: =SUMIF('明细表G1-2'!A12:A16,"债务工具投资",'明细表G1-2'!Q12:Q16) -> 0 | F30: =SUMIF('明细表G1-2'!A12:A16,"债务工具投资",'明细表G1-2'!T12:T16) -> 0 | G30: =E30+F30 -> 0 | H30: =G30-D30 -> 0 | I30: =IF(AND(D30=0,G30=0),"",IF(AND(D30=0,G30>0),1,H30/D30))
A31: 权益工具投资 | B31: =SUMIF('明细表G1-2'!A12:A16,"权益工具投资",'明细表G1-2'!D12:D16) -> 0 | C31: =SUMIF('明细表G1-2'!A12:A16,"权益工具投资",'明细表G1-2'!G12:G16) -> 0 | D31: =B31+C31 -> 0 | E31: =SUMIF('明细表G1-2'!A12:A16,"权益工具投资",'明细表G1-2'!Q12:Q16) -> 0 | F31: =SUMIF('明细表G1-2'!A12:A16,"权益工具投资",'明细表G1-2'!T12:T16) -> 0 | G31: =E31+F31 -> 0 | H31: =G31-D31 -> 0 | I31: =IF(AND(D31=0,G31=0),"",IF(AND(D31=0,G31>0),1,H31/D31))
A32: 衍生金融资产 | B32: =SUMIF('明细表G1-2'!A12:A16,"衍生金融资产",'明细表G1-2'!D12:D16) -> 0 | C32: =SUMIF('明细表G1-2'!A12:A16,"衍生金融资产",'明细表G1-2'!G12:G16) -> 0 | D32: =B32+C32 -> 0 | E32: =SUMIF('明细表G1-2'!A12:A16,"衍生金融资产",'明细表G1-2'!Q12:Q16) -> 0 | F32: =SUMIF('明细表G1-2'!A12:A16,"衍生金融资产",'明细表G1-2'!T12:T16) -> 0 | G32: =E32+F32 -> 0 | H32: =G32-D32 -> 0 | I32: =IF(AND(D32=0,G32=0),"",IF(AND(D32=0,G32>0),1,H32/D32))
A33: 理财产品 | B33: =SUMIF('明细表G1-2'!A12:A16,"理财产品",'明细表G1-2'!D12:D16) -> 0 | C33: =SUMIF('明细表G1-2'!A31:A34,"理财产品",'明细表G1-2'!A31:A34) -> 0 | D33: =B33+C33 -> 0 | E33: =SUMIF('明细表G1-2'!A12:A16,"理财产品",'明细表G1-2'!Q12:Q16) -> 0 | F33: =SUMIF('明细表G1-2'!A31:A34,"理财产品",'明细表G1-2'!S31:S34) -> 0 | G33: =E33+F33 -> 0 | H33: =G33-D33 -> 0 | I33: =IF(AND(D33=0,G33=0),"",IF(AND(D33=0,G33>0),1,H33/D33))
A34: 结构性存款 | B34: =SUMIF('明细表G1-2'!A12:A16,"结构性存款",'明细表G1-2'!D12:D16) -> 0 | C34: =SUMIF('明细表G1-2'!A31:A34,"结构性存款",'明细表G1-2'!A31:A34) -> 0 | D34: =B34+C34 -> 0 | E34: =SUMIF('明细表G1-2'!A12:A16,"结构性存款",'明细表G1-2'!Q12:Q16) -> 0 | F34: =SUMIF('明细表G1-2'!A31:A34,"结构性存款",'明细表G1-2'!S31:S34) -> 0 | G34: =E34+F34 -> 0 | H34: =G34-D34 -> 0 | I34: =IF(AND(D34=0,G34=0),"",IF(AND(D34=0,G34>0),1,H34/D34))
A35: 基金 | B35: =SUMIF('明细表G1-2'!A12:A16,"基金",'明细表G1-2'!D12:D16) -> 0 | C35: =SUMIF('明细表G1-2'!A31:A34,"基金",'明细表G1-2'!A31:A34) -> 0 | D35: =B35+C35 -> 0 | E35: =SUMIF('明细表G1-2'!A12:A16,"基金",'明细表G1-2'!Q12:Q16) -> 0 | F35: =SUMIF('明细表G1-2'!A31:A34,"基金",'明细表G1-2'!S31:S34) -> 0 | G35: =E35+F35 -> 0 | H35: =G35-D35 -> 0 | I35: =IF(AND(D35=0,G35=0),"",IF(AND(D35=0,G35>0),1,H35/D35))
A36: 其他 | B36: =SUMIF('明细表G1-2'!A12:A16,"其他",'明细表G1-2'!D12:D16) -> 0 | C36: =SUMIF('明细表G1-2'!A12:A16,"其他",'明细表G1-2'!G12:G16) -> 0 | D36: =B36+C36 -> 0 | E36: =SUMIF('明细表G1-2'!A12:A16,"其他",'明细表G1-2'!Q12:Q16) -> 0 | F36: =SUMIF('明细表G1-2'!A12:A16,"其他",'明细表G1-2'!T12:T16) -> 0 | G36: =E36+F36 -> 0 | H36: =G36-D36 -> 0 | I36: =IF(AND(D36=0,G36=0),"",IF(AND(D36=0,G36>0),1,H36/D36))
A37: 划分为以公允价值计量且其变动计入当期损益的金融资产 | B37: =SUM(B38:B44) -> 0 | C37: =SUM(C38:C44) -> 0 | D37: =SUM(D38:D44) -> 0 | E37: =SUM(E38:E44) -> 0 | F37: =SUM(F38:F44) -> 0 | G37: =SUM(G38:G44) -> 0 | H37: =SUM(H38:H44) -> 0 | I37: =IF(AND(D37=0,G37=0),"",IF(AND(D37=0,G37>0),1,H37/D37))
A38: 其中：债务工具投资 | B38: =SUMIF('明细表G1-2'!A19:A23,"债务工具投资",'明细表G1-2'!D19:D23) -> 0 | C38: =SUMIF('明细表G1-2'!A19:A23,"债务工具投资",'明细表G1-2'!G19:G23) -> 0 | D38: =B38+C38 -> 0 | E38: =SUMIF('明细表G1-2'!A19:A23,"债务工具投资",'明细表G1-2'!Q19:Q23) -> 0 | F38: =SUMIF('明细表G1-2'!A19:A23,"债务工具投资",'明细表G1-2'!T19:T23) -> 0 | G38: =E38+F38 -> 0 | H38: =G38-D38 -> 0 | I38: =IF(AND(D38=0,G38=0),"",IF(AND(D38=0,G38>0),1,H38/D38))
A39: 权益工具投资 | B39: =SUMIF('明细表G1-2'!A19:A23,"权益工具投资",'明细表G1-2'!D19:D23) -> 0 | C39: =SUMIF('明细表G1-2'!A19:A23,"权益工具投资",'明细表G1-2'!G19:G23) -> 0 | D39: =B39+C39 -> 0 | E39: =SUMIF('明细表G1-2'!A19:A23,"权益工具投资",'明细表G1-2'!Q19:Q23) -> 0 | F39: =SUMIF('明细表G1-2'!A19:A23,"权益工具投资",'明细表G1-2'!T19:T23) -> 0 | G39: =E39+F39 -> 0 | H39: =G39-D39 -> 0 | I39: =IF(AND(D39=0,G39=0),"",IF(AND(D39=0,G39>0),1,H39/D39))
A40: 衍生金融资产 | B40: =SUMIF('明细表G1-2'!A19:A23,"衍生金融资产",'明细表G1-2'!D19:D23) -> 0 | C40: =SUMIF('明细表G1-2'!A19:A23,"衍生金融资产",'明细表G1-2'!G19:G23) -> 0 | D40: =B40+C40 -> 0 | E40: =SUMIF('明细表G1-2'!A19:A23,"衍生金融资产",'明细表G1-2'!Q19:Q23) -> 0 | F40: =SUMIF('明细表G1-2'!A19:A23,"衍生金融资产",'明细表G1-2'!T19:T23) -> 0 | G40: =E40+F40 -> 0 | H40: =G40-D40 -> 0 | I40: =IF(AND(D40=0,G40=0),"",IF(AND(D40=0,G40>0),1,H40/D40))
A41: 理财产品 | B41: =SUMIF('明细表G1-2'!A19:A23,"理财产品",'明细表G1-2'!D19:D23) -> 0 | C41: =SUMIF('明细表G1-2'!A19:A23,"理财产品",'明细表G1-2'!G19:G23) -> 0 | D41: =B41+C41 -> 0 | E41: =SUMIF('明细表G1-2'!A19:A23,"理财产品",'明细表G1-2'!Q19:Q23) -> 0 | F41: =SUMIF('明细表G1-2'!A19:A23,"理财产品",'明细表G1-2'!T19:T23) -> 0 | G41: =E41+F41 -> 0 | H41: =G41-D41 -> 0 | I41: =IF(AND(D41=0,G41=0),"",IF(AND(D41=0,G41>0),1,H41/D41))
A42: 结构性存款 | B42: =SUMIF('明细表G1-2'!A19:A23,"结构性存款",'明细表G1-2'!D19:D23) -> 0 | C42: =SUMIF('明细表G1-2'!A19:A23,"结构性存款",'明细表G1-2'!G19:G23) -> 0 | D42: =B42+C42 -> 0 | E42: =SUMIF('明细表G1-2'!A19:A23,"结构性存款",'明细表G1-2'!Q19:Q23) -> 0 | F42: =SUMIF('明细表G1-2'!A19:A23,"结构性存款",'明细表G1-2'!T19:T23) -> 0 | G42: =E42+F42 -> 0 | H42: =G42-D42 -> 0 | I42: =IF(AND(D42=0,G42=0),"",IF(AND(D42=0,G42>0),1,H42/D42))
A43: 基金 | B43: =SUMIF('明细表G1-2'!A19:A23,"基金",'明细表G1-2'!D19:D23) -> 0 | C43: =SUMIF('明细表G1-2'!A19:A23,"基金",'明细表G1-2'!G19:G23) -> 0 | D43: =B43+C43 -> 0 | E43: =SUMIF('明细表G1-2'!A19:A23,"基金",'明细表G1-2'!Q19:Q23) -> 0 | F43: =SUMIF('明细表G1-2'!A19:A23,"基金",'明细表G1-2'!T19:T23) -> 0 | G43: =E43+F43 -> 0 | H43: =G43-D43 -> 0 | I43: =IF(AND(D43=0,G43=0),"",IF(AND(D43=0,G43>0),1,H43/D43))
A44: 其他 | B44: =SUMIF('明细表G1-2'!A19:A23,"其他",'明细表G1-2'!D19:D23) -> 0 | C44: =SUMIF('明细表G1-2'!A19:A23,"其他",'明细表G1-2'!G19:G23) -> 0 | D44: =B44+C44 -> 0 | E44: =SUMIF('明细表G1-2'!A19:A23,"其他",'明细表G1-2'!Q19:Q23) -> 0 | F44: =SUMIF('明细表G1-2'!A19:A23,"其他",'明细表G1-2'!T19:T23) -> 0 | G44: =E44+F44 -> 0 | H44: =G44-D44 -> 0 | I44: =IF(AND(D44=0,G44=0),"",IF(AND(D44=0,G44>0),1,H44/D44))
A45: 指定为以公允价值计量且其变动计入当期损益的金融资产 | B45: =SUM(B46:B47) -> 0 | C45: =SUM(C46:C47) -> 0 | D45: =SUM(D46:D47) -> 0 | E45: =SUM(E46:E47) -> 0 | F45: =SUM(F46:F47) -> 0 | G45: =SUM(G46:G47) -> 0 | H45: =SUM(H46:H47) -> 0 | I45: =IF(AND(D45=0,G45=0),"",IF(AND(D45=0,G45>0),1,H45/D45))
A46: 其中：债务工具投资 | B46: =SUMIF('明细表G1-2'!A26:A28,"债务工具投资",'明细表G1-2'!D26:D28) -> 0 | C46: =SUMIF('明细表G1-2'!A26:A28,"债务工具投资",'明细表G1-2'!G26:G28) -> 0 | D46: =B46+C46 -> 0 | E46: =SUMIF('明细表G1-2'!A26:A28,"债务工具投资",'明细表G1-2'!Q26:Q28) -> 0 | F46: =SUMIF('明细表G1-2'!A26:A28,"债务工具投资",'明细表G1-2'!T26:T28) -> 0 | G46: =E46+F46 -> 0 | H46: =G46-D46 -> 0 | I46: =IF(AND(D46=0,G46=0),"",IF(AND(D46=0,G46>0),1,H46/D46))
A47: 其他 | B47: =SUMIF('明细表G1-2'!A26:A28,"其他",'明细表G1-2'!D26:D28) -> 0 | C47: =SUMIF('明细表G1-2'!A26:A28,"其他",'明细表G1-2'!G26:G28) -> 0 | D47: =B47+C47 -> 0 | E47: =SUMIF('明细表G1-2'!A26:A28,"其他",'明细表G1-2'!Q26:Q28) -> 0 | F47: =SUMIF('明细表G1-2'!A26:A28,"其他",'明细表G1-2'!T26:T28) -> 0 | G47: =E47+F47 -> 0 | H47: =G47-D47 -> 0 | I47: =IF(AND(D47=0,G47=0),"",IF(AND(D47=0,G47>0),1,H47/D47))
A48: 公允价值变动小计 | B48: =SUM(B29,B37,B45) -> 0 | C48: =SUM(C29,C37,C45) -> 0 | D48: =SUM(D29,D37,D45) -> 0 | E48: =SUM(E29,E37,E45) -> 0 | F48: =SUM(F29,F37,F45) -> 0 | G48: =SUM(G29,G37,G45) -> 0 | H48: =SUM(H29,H45) -> 0 | I48: =IF(AND(D48=0,G48=0),"",IF(AND(D48=0,G48>0),1,H48/D48))
A49: （三）账面余额（公允价值）
A50: 交易性金融资产 | B50: =B8+B29 -> 0 | C50: =C8+C29 -> 0 | D50: =D8+D29 -> 0 | E50: =E8+E29 -> 0 | F50: =F8+F29 -> 0 | G50: =G8+G29 -> 0 | H50: =H8+H29 -> 0 | I50: =IF(AND(D50=0,G50=0),"",IF(AND(D50=0,G50>0),1,H50/D50))
A51: 其中：债务工具投资 | B51: =B9+B30 -> 0 | C51: =C9+C30 -> 0 | D51: =D9+D30 -> 0 | E51: =E9+E30 -> 0 | F51: =F9+F30 -> 0 | G51: =G9+G30 -> 0 | H51: =H9+H30 -> 0 | I51: =IF(AND(D51=0,G51=0),"",IF(AND(D51=0,G51>0),1,H51/D51))
A52: 权益工具投资 | B52: =B10+B31 -> 0 | C52: =C10+C31 -> 0 | D52: =D10+D31 -> 0 | E52: =E10+E31 -> 0 | F52: =F10+F31 -> 0 | G52: =G10+G31 -> 0 | H52: =H10+H31 -> 0 | I52: =IF(AND(D52=0,G52=0),"",IF(AND(D52=0,G52>0),1,H52/D52))
A53: 衍生金融资产 | B53: =B11+B32 -> 0 | C53: =C11+C32 -> 0 | D53: =D11+D32 -> 0 | E53: =E11+E32 -> 0 | F53: =F11+F32 -> 0 | G53: =G11+G32 -> 0 | H53: =H11+H32 -> 0 | I53: =IF(AND(D53=0,G53=0),"",IF(AND(D53=0,G53>0),1,H53/D53))
A54: 理财产品 | B54: =B12+B33 -> 0 | C54: =C12+C33 -> 0 | D54: =D12+D33 -> 0 | E54: =E12+E33 -> 0 | F54: =F12+F33 -> 0 | G54: =G12+G33 -> 0 | H54: =H12+H33 -> 0 | I54: =IF(AND(D54=0,G54=0),"",IF(AND(D54=0,G54>0),1,H54/D54))
A55: 结构性存款 | B55: =B13+B34 -> 0 | C55: =C13+C34 -> 0 | D55: =D13+D34 -> 0 | E55: =E13+E34 -> 0 | F55: =F13+F34 -> 0 | G55: =G13+G34 -> 0 | H55: =H13+H34 -> 0 | I55: =IF(AND(D55=0,G55=0),"",IF(AND(D55=0,G55>0),1,H55/D55))
A56: 基金 | B56: =B14+B35 -> 0 | C56: =C14+C35 -> 0 | D56: =D14+D35 -> 0 | E56: =E14+E35 -> 0 | F56: =F14+F35 -> 0 | G56: =G14+G35 -> 0 | H56: =H14+H35 -> 0 | I56: =IF(AND(D56=0,G56=0),"",IF(AND(D56=0,G56>0),1,H56/D56))
A57: 其他 | B57: =B15+B36 -> 0 | C57: =C15+C36 -> 0 | D57: =D15+D36 -> 0 | E57: =E15+E36 -> 0 | F57: =F15+F36 -> 0 | G57: =G15+G36 -> 0 | H57: =H15+H36 -> 0 | I57: =IF(AND(D57=0,G57=0),"",IF(AND(D57=0,G57>0),1,H57/D57))
A58: 划分为以公允价值计量且其变动计入当期损益的金融资产 | B58: =SUM(B59:B65) -> 0 | C58: =SUM(C59:C65) -> 0 | D58: =SUM(D59:D65) -> 0 | E58: =SUM(E59:E65) -> 0 | F58: =SUM(F59:F65) -> 0 | G58: =SUM(G59:G65) -> 0 | H58: =SUM(H59:H65) -> 0 | I58: =IF(AND(D58=0,G58=0),"",IF(AND(D58=0,G58>0),1,H58/D58))
A59: 其中：债务工具投资 | B59: =B17+B38 -> 0 | C59: =C17+C38 -> 0 | D59: =B59+C59 -> 0 | E59: =E17+E38 -> 0 | F59: =F17+F38 -> 0 | G59: =E59+F59 -> 0 | H59: =G59-D59 -> 0 | I59: =IF(AND(D59=0,G59=0),"",IF(AND(D59=0,G59>0),1,H59/D59))
A60: 权益工具投资 | B60: =B18+B39 -> 0 | C60: =C18+C39 -> 0 | D60: =B60+C60 -> 0 | E60: =E18+E39 -> 0 | F60: =F18+F39 -> 0 | G60: =E60+F60 -> 0 | H60: =G60-D60 -> 0 | I60: =IF(AND(D60=0,G60=0),"",IF(AND(D60=0,G60>0),1,H60/D60))
A61: 衍生金融资产 | B61: =B19+B40 -> 0 | C61: =C19+C40 -> 0 | D61: =B61+C61 -> 0 | E61: =E19+E40 -> 0 | F61: =F19+F40 -> 0 | G61: =E61+F61 -> 0 | H61: =G61-D61 -> 0 | I61: =IF(AND(D61=0,G61=0),"",IF(AND(D61=0,G61>0),1,H61/D61))
A62: 理财产品 | B62: =B20+B41 -> 0 | C62: =C20+C41 -> 0 | D62: =B62+C62 -> 0 | E62: =E20+E41 -> 0 | F62: =F20+F41 -> 0 | G62: =E62+F62 -> 0 | H62: =G62-D62 -> 0 | I62: =IF(AND(D62=0,G62=0),"",IF(AND(D62=0,G62>0),1,H62/D62))
A63: 结构性存款 | B63: =B21+B42 -> 0 | C63: =C21+C42 -> 0 | D63: =B63+C63 -> 0 | E63: =E21+E42 -> 0 | F63: =F21+F42 -> 0 | G63: =E63+F63 -> 0 | H63: =G63-D63 -> 0 | I63: =IF(AND(D63=0,G63=0),"",IF(AND(D63=0,G63>0),1,H63/D63))
A64: 基金 | B64: =B22+B43 -> 0 | C64: =C22+C43 -> 0 | D64: =B64+C64 -> 0 | E64: =E22+E43 -> 0 | F64: =F22+F43 -> 0 | G64: =E64+F64 -> 0 | H64: =G64-D64 -> 0 | I64: =IF(AND(D64=0,G64=0),"",IF(AND(D64=0,G64>0),1,H64/D64))
A65: 其他 | B65: =B23+B44 -> 0 | C65: =C23+C44 -> 0 | D65: =B65+C65 -> 0 | E65: =E23+E44 -> 0 | F65: =F23+F44 -> 0 | G65: =E65+F65 -> 0 | H65: =G65-D65 -> 0 | I65: =IF(AND(D65=0,G65=0),"",IF(AND(D65=0,G65>0),1,H65/D65))
A66: 指定为以公允价值计量且其变动计入当期损益的金融资产 | B66: =B24+B45 -> 0 | C66: =C24+C45 -> 0 | D66: =D24+D45 -> 0 | E66: =E24+E45 -> 0 | F66: =F24+F45 -> 0 | G66: =G24+G45 -> 0 | H66: =H24+H45 -> 0 | I66: =IF(AND(D66=0,G66=0),"",IF(AND(D66=0,G66>0),1,H66/D66))
A67: 其中：债务工具投资 | B67: =B25+B46 -> 0 | C67: =C25+C46 -> 0 | D67: =D25+D46 -> 0 | E67: =E25+E46 -> 0 | F67: =F25+F46 -> 0 | G67: =G25+G46 -> 0 | H67: =H25+H46 -> 0 | I67: =IF(AND(D67=0,G67=0),"",IF(AND(D67=0,G67>0),1,H67/D67))
A68: 其他 | B68: =B26+B47 -> 0 | C68: =C26+C47 -> 0 | D68: =D26+D47 -> 0 | E68: =E26+E47 -> 0 | F68: =F26+F47 -> 0 | G68: =G26+G47 -> 0 | H68: =H26+H47 -> 0 | I68: =IF(AND(D68=0,G68=0),"",IF(AND(D68=0,G68>0),1,H68/D68))
A69: 小计 | B69: =SUM(B50,B58,B66) -> 0 | C69: =SUM(C50,C58,C66) -> 0 | D69: =SUM(D50,D58,D66) -> 0 | E69: =SUM(E50,E58,E66) -> 0 | F69: =SUM(F50,F58,F66) -> 0 | G69: =SUM(G50,G58,G66) -> 0 | H69: =SUM(H50,H58,H66) -> 0 | I69: =IF(AND(D69=0,G69=0),"",IF(AND(D69=0,G69>0),1,H69/D69))
A70: 减：超过一年到期的部分 | C70: ='明细表G1-2'!X30 -> 0 | D70: =B70+C70 -> 0 | F70: ='明细表G1-2'!X30 -> 0 | G70: =E70+F70 -> 0 | H70: =G70-D70 -> 0 | I70: =IF(AND(D70=0,G70=0),"",IF(AND(D70=0,G70>0),1,H70/D70))
A71: 账面余额（公允价值）合计 | B71: =B69-B70 -> 0 | C71: =C69-C70 -> 0 | D71: =D69-D70 -> 0 | E71: =E69-E70 -> 0 | F71: =F69-F70 -> 0 | G71: =G69-G70 -> 0 | H71: =H69-H70 -> 0 | I71: =IF(AND(D71=0,G71=0),"",IF(AND(D71=0,G71>0),1,H71/D71))
A72: 试算平衡表数
A73: 差异数 | D73: =D71-D72 -> 0 | G73: =G71-G72 -> 0
A75: 1、审计说明
A76: （1）交易性金融资产本期较上期增加（负数为减少）： | D76: =IF(AND(D71=0,G71=0),0,IF(AND(D71=0,G71>0),1,(G71-D71)/D71)) -> 0
A77: 主要原因（比例超过30%的）：
A79: （2）情况说明：
A81: 2、审计结论
A83: 提示：第一项“交易性金融资产”和第二项“划分为以公允价值计量且其变动计入当期损益的金融资产”，在财务报表附注披露中，合并披露为“划分为以公允价值计量且其变动计入当期损益的金融资产”
A84: 编制说明【非打印内容】
A85: 金融资产或金融负债满足下列条件之一的，表明企业持有该金融资产或承担该金融负债的目的是交易性的：
A86: （一）取得相关金融资产或承担相关金融负债的目的，主要是为了近期出售或回购。
A87: （二）相关金融资产或金融负债在初始确认时属于集中管理的可辨认金融工具组合的一部分，且有客观证据表明近期实际存在短期获利模式。
A88: （三）相关金融资产或金融负债属于衍生工具。但符合财务担保合同定义的衍生工具以及被指定为有效套期工具的衍生工具除外。
A90: 债务工具投资/权益工具投资
A91: 持有方在判断持有的金融资产是否属于权益工具投资时，应当遵循第22号准则和第37号准则的相关规定。

Sheet 附注披露信息（上市公司）
A1: 致同会计师事务所
A2: 附注披露信息（上市公司）
A3: =底稿目录!A2 -> 被审计单位： | C3: =底稿目录!A4 -> 编制人： | D3: =底稿目录!A5 -> 编制日期： | E3: 索引号： | F3: =底稿目录!F6 -> 0
A4: =底稿目录!A3 -> 截止日：202X年12月31日 | C4: =底稿目录!A6 -> 复核人： | D4: =底稿目录!A7 -> 复核日期： | E4: 页次：
A5: 附注披露信息
A6: 交易性金融资产
A7: 项 目 | C7: 期末余额 | D7: 上年年末余额
A8: 以公允价值计量且其变动计入当期损益的金融资产 | C8: =SUM(C9:C15) -> 0 | D8: =SUM(D9:D15) -> 0
A9: 其中：债务工具投资 | C9: ='审定表G1-1'!G51+'审定表G1-1'!G59 -> 0 | D9: ='审定表G1-1'!D51+'审定表G1-1'!D59 -> 0
A10: 权益工具投资 | C10: ='审定表G1-1'!G52+'审定表G1-1'!G60 -> 0 | D10: ='审定表G1-1'!D52+'审定表G1-1'!D60 -> 0
A11: 衍生金融资产 | C11: ='审定表G1-1'!G53+'审定表G1-1'!G61 -> 0 | D11: ='审定表G1-1'!D53+'审定表G1-1'!D61 -> 0
A12: 理财产品
A13: 结构性存款
A14: 基金
A15: 其他（如或有对价） | C15: ='审定表G1-1'!G57+'审定表G1-1'!G65 -> 0 | D15: ='审定表G1-1'!D57+'审定表G1-1'!D65 -> 0
A16: 指定为以公允价值计量且其变动计入当期损益的金融资产 | C16: =SUM(C17:C18) -> 0 | D16: =SUM(D17:D18) -> 0
A17: 其中：债务工具投资 | C17: ='审定表G1-1'!G67 -> 0 | D17: ='审定表G1-1'!D67 -> 0
A18: 其他 | C18: ='审定表G1-1'!G68 -> 0 | D18: ='审定表G1-1'!D68 -> 0
A19: 合 计 | C19: =C8+C16 -> 0 | D19: =D8+D16 -> 0
A20: 【对于指定为以公允价值计量且其变动计入当期损益的金融资产，披露指定的理由和依据。（15号文第十九条（二）】
A21: 【提示：结构性存款的收益若与利率、汇率等指数或者与某实体的信用等级挂钩，不满足合同现金流量测试，企业应当将其分类为以公允价值计量且其变动计入当期损益的金融资产，记入“交易性金融资产”科目。。】
A22: 说明：
A23: X、衍生金融资产
A24: （提示：企业衍生金融工具业务具有重要性的，单独披露衍生金融资产。）
A25: （15号文第十九条（三），分类列示衍生金融资产期初余额、期末余额，披露其产生的原因以及相关会计处理。）
A26: 项 目 | B26: 期末余额 | C26: 上年年末余额
A33: 合 计 | B33: =SUM(B27:B32) -> 0 | C33: =SUM(C27:C32) -> 0
A34: 说明：（【披露衍生金融资产产生的原因以及相关会计处理。15号文第十九条（三）】。）
A35: 公允价值
A36: 按照在公允价值计量中对计量整体具有重大意义的最低层次的输入值，公允价值层次可分为：
A37: 第一层次：相同资产或负债在活跃市场中的报价（未经调整的）。
A38: 第二层次：直接（即价格）或间接（即从价格推导出）地使用除第一层次中的资产或负债的市场报价之外的可观察输入值。
A39: 第三层次：资产或负债使用了任何非基于可观察市场数据的输入值（不可观察输入值）。
A40: （1）以公允价值计量的项目和金额
A41: 期末，以公允价值计量的资产及负债按上述三个层次列示如下：（不适用的项目请删除）
A42: 项 目 | B42: 第一层次公允价值计量 | C42: 第二层次公允价值计量 | D42: 第三层次公允价值计量 | E42: 合计
A43: 一、持续的公允价值计量
A44: （一）交易性金融资产
A45: 1. 债务工具投资
A46: 2. 权益工具投资
A47: 3. 指定为以公允价值计量且其变动计入当期损益的金融资产
A48: 4.其他
A49: （二）衍生金融资产
A50: （三）应收款项融资 | B50: --
A51: （四）一年内到期的非流动资产
A52: （五）其他债权投资
A53: （六）其他权益工具投资
A54: （七）其他非流动金融资产
A55: （八）投资性房地产
A56: 1. 出租的土地使用权
A57: 2. 出租的建筑物
A58: 3. 持有并准备增值后转让的土地使用权
A59: （九）生物资产
A60: 1. 消耗性生物资产
A61: 2. 生产性生物资产
A62: 持续以公允价值计量的资产总额
... A79: （2）第二层次公允价值计量的相关信息（不适用的项目请删除）
A80: 内 容 | B80: 期末公允价值 | C80: 估值技术 | D80: 输入值
A81: 衍生工具：
A82: 衍生金融资产 | B82: -- | C82: 现金流量折现法 | D82: 预期利率
D83: 合同利率
D84: 反映发行人信用风险的折现率
A85: 衍生金融负债 | B85: -- | C85: 现金流量折现法 | D85: 预期利率
D86: 合同利率
D87: 反映发行人信用风险的折现率
A88: （3）第三层次公允价值计量中使用的重要的不可观察输入值的量化信息（不适用的项目请删除）
A89: 内 容 | B89: 期末公允价值 | C89: 估值技术 | D89: 不可观察输入值 | E89: 范围（加权平均值）
A90: 权益工具投资：
A91: 非上市股权投资 | C91: 市场法（企业价值倍数） | D91: EBITDA乘数 | E91: 10-15 (11.3)
D92: 收入乘数 | E92: 1.5-2.0 (1.7)
D93: 流动性折价 | E93: 5%-20% (17%)
D94: 控制权溢价 | E94: 10%-30% (20%)
C95: 收益法（现金流量折现法） | D95: 加权平均资本成本 | E95: 8%-16% (12.1%)
D96: 长期收入增长率 | E96: 2%-6% (4.2%)
D97: 长期税前营业利润率 | E97: 3%-20% (10.3%)
D98: 流动性折价 | E98: 5%-20% (17%)
D99: 控制权溢价 | E99: 10%-30% (20%)
A100: 私募股权基金投资 | C100: 净资产价值 | D100: 不适用 | E100: N/A
A101: 债务工具投资：
A102: 住房抵押担保证券 | C102: 收益法（现金流量折现法） | D102: 提前偿付率 | E102: 3.5%-5.5% (4.5%)
D103: 违约概率 | E103: 5%-50% (10%)
D104: 违约损失率 | E104: 40%-100% (60%)
A105: 担保债务凭证 | C105: 协商定价法 | D105: 所提供的报价 | E105: 20-50
D106: 可比性调整（%） | E106: -10% 至 +15% (+5%)
A107: 衍生工具：
A108: 信用合同 | C108: 收益法（期权定价模型） | D108: 波动率 | E108: 10%-25%
D109: 交易对手信用风险 | E109: 0.5%-3.5%
D110: 自身信用风险 | E110: 0.3%-2.0%
A111: 投资性房地产：
A112: 商业房地产 | C112: 收益法（现金流量折现法） | D112: 长期净营业收入利润率 | E112: 18%-32% (20%)
D113: 计算资产余值所使用的利率 | E113: 8%-12%(10%)
C114: 市场法（上市公司比较法） | D114: 每平方米单价 | E114: 60000
A117: （4）归入公允价值层级第三层次的公允价值计量的调节表（不适用的项目请删除）
A118: 项 目（本期金额） | B118: 期初余额 | C118: 转入第三层次 | D118: 转出第三层次 | E118: 当期利得或损失总额 | G118: 购买、发行、出售和结算 | K118: 期末余额 | L118: 对于在报告期末持有的资产，计入损益的当期未实现利得或损失的变动
E119: 计入损益 | F119: 计入其他综合收益 | G119: 购入 | H119: 发行 | I119: 出售 | J119: 结算
A120: 交易性金融资产：
A121: 债务工具投资
A122: 权益工具投资
A123: 指定为以公允价值计量且其变动计入当期损益的金融资产
A124: 其他
...

Sheet 附注披露信息（国企）
A1: 致同会计师事务所
A2: 附注披露信息（国企）
A3: =底稿目录!A2 -> 被审计单位： | B3: =底稿目录!A4 -> 编制人： | C3: =底稿目录!A5 -> 编制日期： | D3: 索引号： | E3: =底稿目录!F7 -> 0
A4: =底稿目录!A3 -> 截止日：202X年12月31日 | B4: =底稿目录!A6 -> 复核人： | C4: =底稿目录!A7 -> 复核日期： | D4: 页次：
A5: 附注披露信息
A6: 交易性金融资产
A7: 项 目 | C7: 期末公允价值 | D7: 期初公允价值
A8: 分类以公允价值计量且其变动计入当期损益的金融资产 | C8: =SUM(C9:C11) -> 0 | D8: =SUM(D9:D11) -> 0
A9: 其中：债务工具投资 | C9: ='审定表G1-1'!G51+'审定表G1-1'!G59 -> 0 | D9: ='审定表G1-1'!D51+'审定表G1-1'!D59 -> 0
A10: 权益工具投资 | C10: ='审定表G1-1'!G52+'审定表G1-1'!G60 -> 0 | D10: ='审定表G1-1'!D52+'审定表G1-1'!D60 -> 0
A11: 其他 | C11: ='审定表G1-1'!G53+'审定表G1-1'!G57+'审定表G1-1'!G61+'审定表G1-1'!G65 -> 0 | D11: ='审定表G1-1'!D53+'审定表G1-1'!D57+'审定表G1-1'!D61+'审定表G1-1'!D65 -> 0
A12: 指定为以公允价值计量且其变动计入当期损益的金融资产 | C12: =SUM(C13:C14) -> 0 | D12: =SUM(D13:D14) -> 0
A13: 其中：债务工具投资 | C13: ='审定表G1-1'!G67 -> 0 | D13: ='审定表G1-1'!D67 -> 0
A14: 其他 | C14: ='审定表G1-1'!G68 -> 0 | D14: ='审定表G1-1'!D68 -> 0
A15: 合 计 | C15: =C8+C12 -> 0 | D15: =D8+D12 -> 0
A16: （注：应披露公允价值确认依据。）
A17: 衍生金融资产
A18: 项 目 | C18: 期末余额 | D18: 期初余额
A30: 合 计 | C30: =SUM(C19:C29) -> 0 | D30: =SUM(D19:D29) -> 0
A31: 【提示：披露金额较大的前十项及其产生的原因，其余汇总填列。】

Sheet 明细表G1-2
A1: 致同会计师事务所 | S1: 致同会计师事务所
A2: 交易性金融资产明细表 | S2: 交易性金融资产明细表
A3: =底稿目录!A2 -> 被审计单位： | F3: =底稿目录!A4 -> 编制人： | K3: =底稿目录!A5 -> 编制日期： | Q3: 索引号： | R3: =底稿目录!F8 -> G1-2 | S3: =底稿目录!A2 -> 被审计单位： | V3: =底稿目录!A4 -> 编制人： | X3: =底稿目录!A5 -> 编制日期： | Z3: 索引号： | AA3: =R3 -> G1-2
A4: =底稿目录!A3 -> 截止日：202X年12月31日 | F4: =底稿目录!A6 -> 复核人： | K4: =底稿目录!A7 -> 复核日期： | Q4: 页次： | S4: =底稿目录!A3 -> 截止日：202X年12月31日 | V4: =底稿目录!A6 -> 复核人： | X4: =底稿目录!A7 -> 复核日期： | Z4: 页次：
A5: 一、审计目标
A6: 1.资产负债表中记录的交易性金融资产是存在的，且已经记录在恰当的账户中；2.所有应记录的交易性金融资产均已记录，所有应当包括在财务报表中的相关披露均已包括；
A7: 3.交易性金融资产以恰当的金额包括在财务报表中，与之相关的计价或分摊调整已恰当记录，相关披露已得到恰当计量和描述
A8: 二、审计过程
A9: 类别 | B9: 投资项目【按明细项目列示，如证券名称或被投资单位名称】 | C9: 期初余额 | F9: 期初账项调整 | H9: 期初审定数 | K9: 减：期初超过一年到期的部分 | L9: 期初报表数 | M9: 本期变动（增加为正数） | P9: 期末余额 | S9: 账项调整 | U9: 期末审定数 | X9: 减：超过一年到期的部分 | Y9: 期末报表数 | Z9: 变现是否存在限制 | AA9: 是否函证
C10: 成本 | D10: 累计公允价值变动 | E10: 公允价值 | F10: 成本 | G10: 公允价值变动 | H10: 成本 | I10: 累计公允价值变动 | J10: 公允价值 | M10: 成本 | N10: 本期公允价值变动 | O10: 计入投资收益的股息 | P10: 成本 | Q10: 累计公允价值变动 | R10: 公允价值 | S10: 成本 | T10: 公允价值变动 | U10: 成本 | V10: 累计公允价值变动 | W10: 公允价值
A11: 交易性金融资产
A12: 债务工具投资 | E12: =C12+D12 -> 0 | H12: =C12+F12 -> 0 | I12: =D12+G12 -> 0 | J12: =H12+I12 -> 0 | L12: =J12+K12 -> 0 | P12: =C12+M12 -> 0 | Q12: =D12+N12 -> 0 | R12: =P12+Q12 -> 0 | T12: ='公允价值测试表G1-6'!H10-'明细表G1-2'!R12 -> 0 | U12: =P12+S12 -> 0 | V12: =Q12+T12 -> 0 | W12: =U12+V12 -> 0 | Y12: =W12+X12 -> 0
E13: =C13+D13 -> 0 | H13: =C13+F13 -> 0 | I13: =D13+G13 -> 0 | J13: =H13+I13 -> 0 | L13: =J13+K13 -> 0 | P13: =C13+M13 -> 0 | Q13: =D13+N13 -> 0 | R13: =P13+Q13 -> 0 | T13: ='公允价值测试表G1-6'!H11-'明细表G1-2'!R13 -> 0 | U13: =P13+S13 -> 0 | V13: =Q13+T13 -> 0 | W13: =U13+V13 -> 0 | Y13: =W13+X13 -> 0
E14: =C14+D14 -> 0 | H14: =C14+F14 -> 0 | I14: =D14+G14 -> 0 | J14: =H14+I14 -> 0 | L14: =J14+K14 -> 0 | P14: =C14+M14 -> 0 | Q14: =D14+N14 -> 0 | R14: =P14+Q14 -> 0 | T14: ='公允价值测试表G1-6'!H12-'明细表G1-2'!R14 -> 0 | U14: =P14+S14 -> 0 | V14: =Q14+T14 -> 0 | W14: =U14+V14 -> 0 | Y14: =W14+X14 -> 0
E15: =C15+D15 -> 0 | H15: =C15+F15 -> 0 | I15: =D15+G15 -> 0 | J15: =H15+I15 -> 0 | L15: =J15+K15 -> 0 | P15: =C15+M15 -> 0 | Q15: =D15+N15 -> 0 | R15: =P15+Q15 -> 0 | T15: ='公允价值测试表G1-6'!H13-'明细表G1-2'!R15 -> 0 | U15: =P15+S15 -> 0 | V15: =Q15+T15 -> 0 | W15: =U15+V15 -> 0 | Y15: =W15+X15 -> 0
E16: =C16+D16 -> 0 | H16: =C16+F16 -> 0 | I16: =D16+G16 -> 0 | J16: =H16+I16 -> 0 | L16: =J16+K16 -> 0 | P16: =C16+M16 -> 0 | Q16: =D16+N16 -> 0 | R16: =P16+Q16 -> 0 | T16: ='公允价值测试表G1-6'!H14-'明细表G1-2'!R16 -> 0 | U16: =P16+S16 -> 0 | V16: =Q16+T16 -> 0 | W16: =U16+V16 -> 0 | Y16: =W16+X16 -> 0
A17: 小计 | C17: =SUM(C12:C16) -> 0 | D17: =SUM(D12:D16) -> 0 | E17: =SUM(E12:E16) -> 0 | F17: =SUM(F12:F16) -> 0 | G17: =SUM(G12:G16) -> 0 | H17: =SUM(H12:H16) -> 0 | I17: =SUM(I12:I16) -> 0 | J17: =SUM(J12:J16) -> 0 | ... Y17: =SUM(Y12:Y16) -> 0
A18: 划分为以公允价值计量且其变动计入当期损益的金融资产
A19: 债务工具投资 | B19: 结构性存款 | E19: =C19+D19 -> 0 | H19: =C19+F19 -> 0 | I19: =D19+G19 -> 0 | J19: =H19+I19 -> 0 | L19: =J19+K19 -> 0 | P19: =C19+M19 -> 0 | Q19: =D19+N19 -> 0 | R19: =P19+Q19 -> 0 | U19: =P19+S19 -> 0 | V19: =Q19+T19 -> 0 | W19: =U19+V19 -> 0 | Y19: =W19+X19 -> 0
E20: =C20+D20 -> 0 | H20: =C20+F20 -> 0 | I20: =D20+G20 -> 0 | J20: =H20+I20 -> 0 | L20: =J20+K20 -> 0 | P20: =C20+M20 -> 0 | Q20: =D20+N20 -> 0 | R20: =P20+Q20 -> 0 | U20: =P20+S20 -> 0 | V20: =Q20+T20 -> 0 | W20: =U20+V20 -> 0 | Y20: =W20+X20 -> 0
E21: =C21+D21 -> 0 | H21: =C21+F21 -> 0 | I21: =D21+G21 -> 0 | J21: =H21+I21 -> 0 | L21: =J21+K21 -> 0 | P21: =C21+M21 -> 0 | Q21: =D21+N21 -> 0 | R21: =P21+Q21 -> 0 | U21: =P21+S21 -> 0 | V21: =Q21+T21 -> 0 | W21: =U21+V21 -> 0 | Y21: =W21+X21 -> 0
E22: =C22+D22 -> 0 | H22: =C22+F22 -> 0 | I22: =D22+G22 -> 0 | J22: =H22+I22 -> 0 | L22: =J22+K22 -> 0 | P22: =C22+M22 -> 0 | Q22: =D22+N22 -> 0 | R22: =P22+Q22 -> 0 | U22: =P22+S22 -> 0 | V22: =Q22+T22 -> 0 | W22: =U22+V22 -> 0 | Y22: =W22+X22 -> 0
E23: =C23+D23 -> 0 | H23: =C23+F23 -> 0 | I23: =D23+G23 -> 0 | J23: =H23+I23 -> 0 | L23: =J23+K23 -> 0 | P23: =C23+M23 -> 0 | Q23: =D23+N23 -> 0 | R23: =P23+Q23 -> 0 | U23: =P23+S23 -> 0 | V23: =Q23+T23 -> 0 | W23: =U23+V23 -> 0 | Y23: =W23+X23 -> 0
A24: 小计 | C24: =SUM(C19:C23) -> 0 | D24: =SUM(D19:D23) -> 0 | E24: =SUM(E19:E23) -> 0 | F24: =SUM(F19:F23) -> 0 | G24: =SUM(G19:G23) -> 0 | H24: =SUM(H19:H23) -> 0 | I24: =SUM(I19:I23) -> 0 | J24: =SUM(J19:J23) -> 0 | ... Y24: =SUM(Y19:Y23) -> 0
A25: 指定为以公允价值计量且其变动计入当期损益的金融资产
E26: =C26+D26 -> 0 | H26: =C26+F26 -> 0 | I26: =D26+G26 -> 0 | J26: =H26+I26 -> 0 | L26: =J26+K26 -> 0 | P26: =C26+M26 -> 0 | Q26: =D26+N26 -> 0 | R26: =P26+Q26 -> 0 | U26: =P26+S26 -> 0 | V26: =Q26+T26 -> 0 | W26: =U26+V26 -> 0 | Y26: =W26+X26 -> 0
E27: =C27+D27 -> 0 | H27: =C27+F27 -> 0 | I27: =D27+G27 -> 0 | J27: =H27+I27 -> 0 | L27: =J27+K27 -> 0 | P27: =C27+M27 -> 0 | Q27: =D27+N27 -> 0 | R27: =P27+Q27 -> 0 | U27: =P27+S27 -> 0 | V27: =Q27+T27 -> 0 | W27: =U27+V27 -> 0 | Y27: =W27+X27 -> 0
E28: =C28+D28 -> 0 | H28: =C28+F28 -> 0 | I28: =D28+G28 -> 0 | J28: =H28+I28 -> 0 | L28: =J28+K28 -> 0 | P28: =C28+M28 -> 0 | Q28: =D28+N28 -> 0 | R28: =P28+Q28 -> 0 | U28: =P28+S28 -> 0 | V28: =Q28+T28 -> 0 | W28: =U28+V28 -> 0 | Y28: =W28+X28 -> 0
A29: 小计 | C29: =SUM(C26:C28) -> 0 | D29: =SUM(D26:D28) -> 0 | E29: =SUM(E26:E28) -> 0 | F29: =SUM(F26:F28) -> 0 | G29: =SUM(G26:G28) -> 0 | H29: =SUM(H26:H28) -> 0 | I29: =SUM(I26:I28) -> 0 | J29: =SUM(J26:J28) -> 0 | ... Y29: =SUM(Y26:Y28) -> 0
A30: 合计 | C30: =SUM(C17,C24,C29) -> 0 | D30: =SUM(D17,D24,D29) -> 0 | E30: =SUM(E17,E24,E29) -> 0 | F30: =SUM(F17,F24,F29) -> 0 | G30: =SUM(G17,G24,G29) -> 0 | H30: =SUM(H17,H24,H29) -> 0 | I30: =SUM(I17,I24,I29) -> 0 | J30: =SUM(J17,J24,J29) -> 0 | ... Y30: =SUM(Y17,Y24,Y29) -> 0
A31: 注1：相关金融工具已到期可收取但于资产负债表日尚未收到的利息在“应收利息”反映。
A32: 三、审计说明：
B33: 本期计入“投资收益”的利息金额为：
B34: 本期计入“投资收益”的股利金额为：
A38: 四、审计结论：
A40: 提示：第一项“交易性金融资产”和第二项“划分为以公允价值计量且其变动计入当期损益的金融资产”，在财务报表附注披露中，合并披露为“划分为以公允价值计量且其变动计入当期损益的金融资产”
A41: 编制说明【非打印内容】：
A42: 1．编制时应列入交易性金融资产的每一明细账户。2．外币交易性金融资产应列明原币金额及折合汇率（自行添加项目）。
A43: 2、本项目可能包括：
A44: （1）未能通过SPPI测试的、到期日不超过一年或预期持有不超过一年的债务工具投资（含嵌入衍生工具），例如非保本理财产品、保本浮动收益理财产品（结构性存款）等；
A45: （2）以其他业务模式持有的债务工具投资（含嵌入衍生工具）；
A46: （3）未指定为有效套期工具的衍生工具；
A47: （4）到期日不超过一年或预期持有不超过一年的权益工具投资（不包括指定为FVOCI的）；
A48: （5）到期日不超过一年或预期持有不超过一年的、直接指定为FVTPL的债务工具投资（含嵌入衍生工具）。
A49: 3、根据《中国注册会计师审计准则问题解答第18号——识别和应对第三方配合实施财务舞弊》：当期存在大额对外投资时，需考虑是否存在通过被审计单位将资金投入被投资单位，
A50: 再从被投资单位套取资金（如投资私募基金后，在私募基金配合下将投资款从私募基金转出），如果还识别出被审计单位存在可能导致关联方资金占用以及其他套取资金行为的舞弊风险因素，则很可能表面存在第三方配合舞弊，应采取恰当的措施应对。
... A52: 5.审计结论可参考：A、未见异常。 B、除上述重大不符事项应当作为调整事项予以调整外，其余未见异常。 C、由于存在以下重大未调整事项（或审计范围受到限制无法获取充分、适当证据），不可确认。

Sheet 调整分录汇总G1-3
A1: 致同会计师事务所
A2: 交易性金融资产调整分录汇总表
A3: =底稿目录!A2 -> 被审计单位： | C3: =底稿目录!A4 -> 编制人： | F3: =底稿目录!A5 -> 编制日期： | I3: 索引号： | J3: =底稿目录!F9 -> G1-3
A4: =底稿目录!A3 -> 截止日：202X年12月31日 | C4: =底稿目录!A6 -> 复核人： | F4: =底稿目录!A7 -> 复核日期： | I4: 页次：
A5: 调整事项说明 | B5: 类别（报表调整/账项调整/其他） | C5: 报表项目 | D5: 科目名称 | E5: 附注项目 | F5: …… | G5: 借方调整金额 | H5: 贷方调整金额 | I5: 索引 | J5: 备注
A21: 【注：本底稿适用于调整分录较多、较复杂的项目，且仅列示与本报表项目相关的审计调整。项目组可根据项目实际情况选择是否使用该底稿。】

Sheet 结存表G1-4
A1: 致同会计师事务所
A2: 交易性金融资产期末结存表
A3: =底稿目录!A2 -> 被审计单位： | I3: =底稿目录!A4 -> 编制人： | N3: =底稿目录!A5 -> 编制日期： | T3: 索引号： | U3: =底稿目录!F10 -> G1-4
A4: =底稿目录!A3 -> 截止日：202X年12月31日 | I4: =底稿目录!A6 -> 复核人： | N4: =底稿目录!A7 -> 复核日期： | T4: 页 次： | U4: 1
A5: 一、审计目标
A6: 1.资产负债表中记录的交易性金融资产是存在的，且已记录于恰当的账户 | G6: 2.所有应记录的交易性金融资产均已记录，所有应当包括在财务报表中的相关披露均已包括
A7: 3.记录的交易性金融资产由被审计单位拥有或控制 | G7: 4.交易性金融资产以恰当的金额包括在财务报表中，与之相关的计价或分摊调整已恰当记录，相关披露已得到恰当计量和描述
A8: 二、审计过程
A9: 获取股票、债券、期货、基金等账户的开户资料，获取被审计单位内部证券各账户电子文档清单及余额调节表，取得证券服务机构提供的所有投资账户的电子文件，对账单（在可能的情况下自行进入交易系统获得对账单），并执行以下工作： | B9: 获取股票、债券、期货、基金等账户的开户资料，获取被审计单位内部证券各账户电子文档清单及余额调节表，取得证券服务机构提供的所有投资账户的电子文件，对账单（在可能的情况下自行进入交易系统获得对账单），并执行以下工作：
A10: 1.将证券账户开户资料、投资账户电子文档清单、对账单、余额调节表等资料进行核对,调查重大或者异常的调节项目。
A11: 2.检查相关资产的会计记录是否完整、是否归被审计单位所有，关注相关资产的变现是否存在重大限制：
A12: 3.取得有关账户流水单，对照检查账面记录是否完整。检查购入资产是否为被审计单位拥有；
A13: 4.向相关机构发函，并确定是否存在变现限制，同时记录函证过程。如相关资产的变现存在限制，则查明情况，并提请被审计单位做适当调整。
A14: 账面结存证券投资① | I14: 资产负债表日库存有价证券② | L14: 对账单③ | O14: 函证证券投资④ | R14: 差异⑤=①-②-（③或④） | U14: 备注
A15: 证券名称 | B15: 资金账号 | C15: 开户名称 | D15: 数量 | E15: 面值（单价） | F15: 票面利率 | G15: 到期日(如适用) | H15: 总计 | I15: 数量 | J15: 面值（单价） | K15: 总计 | L15: 数量 | M15: 面值（单价） | N15: 总计 | O15: 数量 | P15: 面值（单价） | Q15: 总计 | R15: 数量 | S15: 面值（单价） | T15: 总计
H16: =D16*E16 -> 0 | K16: =I16*J16 -> 0 | N16: =L16*M16 -> 0 | Q16: =O16*P16 -> 0
H17: =D17*E17 -> 0 | K17: =I17*J17 -> 0 | N17: =L17*M17 -> 0 | Q17: =O17*P17 -> 0
H18: =D18*E18 -> 0 | K18: =I18*J18 -> 0 | N18: =L18*M18 -> 0 | Q18: =O18*P18 -> 0
H19: =D19*E19 -> 0 | K19: =I19*J19 -> 0 | N19: =L19*M19 -> 0 | Q19: =O19*P19 -> 0
H20: =D20*E20 -> 0 | K20: =I20*J20 -> 0 | N20: =L20*M20 -> 0 | Q20: =O20*P20 -> 0
H21: =D21*E21 -> 0 | K21: =I21*J21 -> 0 | N21: =L21*M21 -> 0 | Q21: =O21*P21 -> 0
H22: =D22*E22 -> 0 | K22: =I22*J22 -> 0 | N22: =L22*M22 -> 0 | Q22: =O22*P22 -> 0
H23: =D23*E23 -> 0 | K23: =I23*J23 -> 0 | N23: =L23*M23 -> 0 | Q23: =O23*P23 -> 0
H24: =D24*E24 -> 0 | K24: =I24*J24 -> 0 | N24: =L24*M24 -> 0 | Q24: =O24*P24 -> 0
H25: =D25*E25 -> 0 | K25: =I25*J25 -> 0 | N25: =L25*M25 -> 0 | Q25: =O25*P25 -> 0
H26: =D26*E26 -> 0 | K26: =I26*J26 -> 0 | N26: =L26*M26 -> 0 | Q26: =O26*P26 -> 0
H27: =D27*E27 -> 0 | K27: =I27*J27 -> 0 | N27: =L27*M27 -> 0 | Q27: =O27*P27 -> 0
A28: 合计 | H28: =SUM(H16:H27) -> 0 | K28: =SUM(K16:K27) -> 0 | N28: =SUM(N16:N27) -> 0 | Q28: =SUM(Q16:Q27) -> 0 | T28: =SUM(T16:T27) -> 0
A29: 三、审计说明：
A32: 四、审计结论：

Sheet 收益测算表G1-5
A1: 致同会计师事务所
A2: 收益测算表
A3: =底稿目录!A2 -> 被审计单位： | E3: =底稿目录!A4 -> 编制人： | G3: =底稿目录!A5 -> 编制日期： | J3: 索引号： | K3: =底稿目录!F11 -> G1-5
A4: =底稿目录!A3 -> 截止日：202X年12月31日 | E4: =底稿目录!A6 -> 复核人： | G4: =底稿目录!A7 -> 复核日期： | J4: 页 次：
A5: 一、审计目标
A6: 测试账面中确认的收益是否准确。
A7: 二、审计过程
A8: 1. 获取持有的债券和其他固收类产品。
A9: 2. 根据合同金额、票面利率和投资日期等要素，计算应计利息金额，并与账面计提利息比对。
A10: 3.与管理人讨论，了解并分析差异的原因。
A11: 金融投资名称 | B11: 合同金额 | C11: 年化利率 | D11: 起始日 | E11: 结息日 | F11: 到期日 | G11: 计息天数 | I11: 应计利息
G12: 结息前 | H12: 结息后 | I12: 结息前 | J12: 结息后 | K12: 小计
I13: =B13*C13*G13/365 -> 0 | J13: =B13*C13*H13/365 -> 0 | K13: =I13+J13 -> 0
I14: =B14*C14*G14/365 -> 0 | J14: =B14*C14*H14/365 -> 0 | K14: =I14+J14 -> 0
I15: =B15*C15*G15/365 -> 0 | J15: =B15*C15*H15/365 -> 0 | K15: =I15+J15 -> 0
I16: =B16*C16*G16/365 -> 0 | J16: =B16*C16*H16/365 -> 0 | K16: =I16+J16 -> 0
I17: =B17*C17*G17/365 -> 0 | J17: =B17*C17*H17/365 -> 0 | K17: =I17+J17 -> 0
I18: =B18*C18*G18/365 -> 0 | J18: =B18*C18*H18/365 -> 0 | K18: =I18+J18 -> 0
A19: 合 计 | B19: =SUM(B13:B18) -> 0 | C19: ---- | D19: ---- | E19: ---- | F19: ---- | G19: ---- | H19: ---- | I19: =SUM(I13:I18) -> 0 | J19: =SUM(J13:J18) -> 0 | K19: =SUM(K13:K18) -> 0
A20: 续上表
A21: 账计利息 | F21: 差异
A22: 投资收益 | D22: … | E22: 小计
E23: =SUM(A23:D23) -> 0 | F23: =E23-K19 -> 0
A25: 三、审计说明：
A29: 四、审计结论：
A32: 《企业会计准则应用指南汇编2024》第二十二章 金融工具确认和计量
A33: 交易性金融资产持有期间，被投资单位宣告发放现金股利，应借记“应收股利”科目，贷记“投资收益”科目。交易性金融资产为债权投资的，可以将按票面或合同利率计算的利息计入投资收益，借记本科目(应计利息),贷记“投资收益”科目；也可以不单独确认前述利息，而通过本科目(公允价值变动)汇总反映包含利息的债权投资的公允价值变化。

Sheet 公允价值测试表G1-6
A1: 致同会计师事务所
A2: 交易性金融资产公允价值测试表
A3: =底稿目录!A2 -> 被审计单位： | G3: =底稿目录!A4 -> 编制人： | L3: =底稿目录!A5 -> 编制日期： | Q3: 索引号： | R3: =底稿目录!F12 -> G1-6
A4: =底稿目录!A3 -> 截止日：202X年12月31日 | G4: =底稿目录!A6 -> 复核人： | L4: =底稿目录!A7 -> 复核日期： | Q4: 页 次：
A5: 一、审计目标 | B5: 交易性金融资产以恰当的金额包括在财务报表中，与之相关的计价或分摊调整已恰当记录，相关披露已得到恰当计量和描述
A6: 二、审计过程 | B6: 1. 检查公允价值计量，前后期方法是否保持一致。 | H6: 2. 了解公允价值来源和计算模型，判断管理层对公允价值层次的划分是否合理。
B7: 3. 对于公允价值为第二层次、第三层次的投资，考虑利用专家工作，确定公允价值计量是否恰当。 | H7: 4. 复核公允价值取得依据是否充分。公允价值与账面价值的差额是否计入公允价值变动损益科目。
A8: 投资项目【按明细项目列示，如证券名称或被投资单位名称】 | B8: 期末未审数 | F8: 期末审定数 | J8: 差异 | K8: 估值方法 | L8: 估值方法与上期是否一致 | M8: 第一层次 | N8: 第二层次 | O8: 第三层次 | R8: 估值文件索引号
B9: 数量（张/股） | C9: 单位公允价值 | D9: 公允价值 | E9: 公允价值层次 | F9: 数量（张/股） | G9: 单位公允价值 | H9: 公允价值 | I9: 公允价值层次 | M9: 公允价值来源机构 | N9: 输入值来源及调整考虑因素 | O9: 估值技术 | P9: 不可观察输入值 | Q9: 数值
A10: 公司债券 | D10: =B10*C10 -> 0 | H10: =F10*G10 -> 0 | I10: 第二层次 | J10: =H10-D10 -> 0 | N10: 以合同规定的未来现金流量按照市场上具有可比信用等级并在相同条件下提供几乎相同现金流量的利率进行折现后的现值确定
D11: =B11*C11 -> 0 | H11: =F11*G11 -> 0 | I11: 第三层次 | J11: =H11-D11 -> 0 | O11: 收益法（折现现金流量法） | P11: 加权平均资本成本 长期收入增长率 长期税前营业利润率 非流通折价 | Q11: 16% 2% 10.3% 20%
H12: =F12*G12 -> 0 | J12: =H12-D12 -> 0
H13: =F13*G13 -> 0 | J13: =H13-D13 -> 0
H14: =F14*G14 -> 0 | J14: =H14-D14 -> 0
H15: =F15*G15 -> 0 | J15: =H15-D15 -> 0
H16: =F16*G16 -> 0 | J16: =H16-D16 -> 0
H17: =F17*G17 -> 0 | J17: =H17-D17 -> 0
H18: =F18*G18 -> 0 | J18: =H18-D18 -> 0
H19: =F19*G19 -> 0 | J19: =H19-D19 -> 0
A20: 合计 | D20: =SUM(D10:D19) -> 0 | H20: =SUM(H10:H19) -> 0 | J20: =SUM(J10:J19) -> 0
A21: 三、审计说明：
A22: 了解专家资质及利用估值专家的工作详见：B21、C25、S12、S13
A25: 四、审计结论：
A27: 编制说明：
A28: 1、公允价值的层次
A29: （1）第一层次——相同资产或负债在活跃市场中的报价（未经调整的）。只有在交易所或活跃指数/市场上进行交易的工具才能归入第一层次。
A30: 这一层次包括上市的权益证券和债权工具以及交易所交易的衍生产品如股指期货（基于Nasdaq、S&P500等指数）等。
A31: （2）第二层次——直接（即价格）或间接（即从价格推导出）地使用除第一层次中的资产或负债的市场报价之外的可观察输入值。
A32: 这一层次包括大部分场外交易的衍生工具和债券，交易性贷款和发行的结构型债务工具。
A33: （3）第三层次——资产或负债使用了任何非基于可观察市场数据的输入值（不可观察输入值）。
A34: 这一层次包括一项或多项重大输入为不可观察变量的股权和债券工具。所采用的估值模型通常为现金流折现模型。

Sheet 第三层次公允价值计量的调节表G1-7
A1: 致同会计师事务所
A2: 第三层次公允价值计量的调节表
A3: =底稿目录!A2 -> 被审计单位： | F3: =底稿目录!A4 -> 编制人： | I3: =底稿目录!A5 -> 编制日期： | L3: 索引号： | M3: =底稿目录!F13 -> G1-7
A4: =底稿目录!A3 -> 截止日：202X年12月31日 | F4: =底稿目录!A6 -> 复核人： | I4: =底稿目录!A7 -> 复核日期： | L4: 页次：
A5: 一、审计目标 | C5: 交易性金融资产以恰当的金额包括在财务报表中，与之相关的计价或分摊调整已恰当记录，相关披露已得到恰当计量和描述
A6: 二、审计过程 | C6: 1、取得第三层次公允价值计量金融资产明细清单，复核加计是否正确； | I6: 2、确定第三层次公允价值计量调节过程披露是否适当
A7: 投资项目【按明细项目列示，如证券名称或被投资单位名称】 | C7: 期初余额 | D7: 转入第三层次 | E7: 转出第三层次 | F7: 当期利得或损失总额 | H7: 购买、发行、出售和结算 | L7: 期末余额 | M7: 对于在报告期末持有的资产，计入损益的当期未实现利得或损失的变动
F8: 公允价值变动损益 | G8: 投资收益 | H8: 购入 | I8: 发行 | J8: 出售 | K8: 结算
L9: =C9+D9-E9+F9+H9+I9-J9-K9 -> 0
L10: =C10+D10-E10+F10+H10+I10-J10-K10 -> 0
L11: =C11+D11-E11+F11+H11+I11-J11-K11 -> 0
L12: =C12+D12-E12+F12+H12+I12-J12-K12 -> 0
L13: =C13+D13-E13+F13+H13+I13-J13-K13 -> 0
L14: =C14+D14-E14+F14+H14+I14-J14-K14 -> 0
L15: =C15+D15-E15+F15+H15+I15-J15-K15 -> 0
L16: =C16+D16-E16+F16+H16+I16-J16-K16 -> 0
L17: =C17+D17-E17+F17+H17+I17-J17-K17 -> 0
A18: 合 计 | C18: =SUM(C9:C17) -> 0 | D18: =SUM(D9:D17) -> 0 | E18: =SUM(E9:E17) -> 0 | F18: =SUM(F9:F17) -> 0 | G18: =SUM(G9:G17) -> 0 | H18: =SUM(H9:H17) -> 0 | I18: =SUM(I9:I17) -> 0 | J18: =SUM(J9:J17) -> 0 | ... L18: =SUM(L9:L17) -> 0
A19: 三、审计说明：
A21: 四、审计结论：

Sheet 业务模式分析G1-8
A1: 致同会计师事务所
A2: 业务模式分析
A3: =底稿目录!A2 -> 被审计单位： | D3: =底稿目录!A4 -> 编制人： | E3: =底稿目录!A5 -> 编制日期： | F3: 索引号： | G3: =底稿目录!F14 -> G1-8
A4: =底稿目录!A3 -> 截止日：202X年12月31日 | D4: =底稿目录!A6 -> 复核人： | E4: =底稿目录!A7 -> 复核日期： | F4: 页 次：
A5: 一、审计目标： | B5: 确定被审计单位管理交易性金融资产的业务模式，并结合合同现金流量特征，确定债权投资的金融资产分类。
A6: 二、审计过程：
A7: 1.了解并观察被审计单位如何管理其金融资产以产生现金流量…… | H7: 业务模式决定企业所管理金融资产现金流量的来源是收取合同现金流量、出售金融资产还是两者兼有。
A8: 2. 了解被审计单位确定业务模式的层次。若被审计单位将应收账款划分为不同的组合从而确定多个业务模式，分析划分组合的依据是否明确，各组合是否可明确区分…… | H8: 业务目标：获取现金流量、最大化投资回报、满足流动性需求等。
A9: 3. 对于以收取合同现金流量为目标的业务模式…… | H9: 业务模式是一项事实而非仅仅是认定，也不是一项选择，不依赖于管理层对单项工具的意图。
A10: 4. 对于以收取合同现金流量和出售金融资产为目标的业务模式…… | H10: 业务模式应当在反映如何对多组金融资产一起进行管理以实现特定业务目标的层次上确定。
A11: 5. 对于其他业务模式…… | C11: 具体可参见蓝色文字提示 | H11: 出售本身并不能决定业务模式。 但频繁且重大的出售说明业务模式不是以收取合同现金流量为目标。
A13: （一）以单一业务模式管理所有交易性金融资产
A14: 了解并观察被审计单位管理交易性金融资产的实际情况及未来预期 | E14: 是或否 | F14: 说明
A15: 1. 被审计单位是否涉及大额且频繁的交易性金融资产出售？ | E15: 是
A16: 2. 被审计单位持有交易性金融资产的目的是交易性的？ | E16: =IF(AND(E17="否",E18="否",E19="否"),"否","是") -> 是
A17: 2.1 取得相关金融资产的目的，主要是为了近期出售或回购？ | E17: 是
A18: 2.2 相关金融资产在初始确认时属于集中管理的可辨认金融工具组合的一部分，且有客观证据表明近期实际存在短期获利模式？ | E18: 否
A19: 2.3 相关金融资产属于衍生工具（但符合财务担保合同定义的衍生工具以及被指定为有效套期工具的衍生工具除外）？ | E19: 否
A20: 3. 被审计单位基于交易性金融资产的公允价值作出决策并对其进行管理？ | E20: 否
A21: 4. 未来是否预期会进行大额且频繁的债权投资出售？ | E21: 否
A22: 5. 未来是否预期持有交易性金融资产的目的是交易性的或基于交易性金融资产的公允价值作出决策并对其进行管理？ | E22: 否
A23: =IF(AND(E15="是",E16="否",E20="否"),"属于以收取合同现金流量和出售金融资产为目标的业务模式",IF(OR(AND(E15="是",E16="是"),AND(E15="是",E20="是")),"属于其他业务模式",IF(AND(E21="是",E22<>"是"),"属于以收取合同现金流量和出售金融资产为目标的业务模式",IF(E22="是","属于其他业务模式","属于以收取合同现金流量为目标的业务模式")))) -> 属于其他业务模式 | F23: =IF(AND(E15="否",E16="是"),"逻辑有误","") | H23: 注意：合并报表层面的业务模式可能与个别报表层面不同
A25: （二）将交易性金融资产分拆为次级组合分别确定业务模式 | E25: 是否适用： | F25: 否
A26: 确定组合的依据及对应业务模式如下：
A27: 组合 | B27: 组合依据 | D27: 业务模式 | G27: 列报项目
A28: 交易性金融资产组合1： | H28: 单个主体可能具有一个以上管理其金融资产的业务模式。在某些情况下，将金融资产组合分拆为次级组合以反映主体据以管理该等金融资产的层次可能是恰当的。
A29: 交易性金融资产组合2：
A31: 三、审计说明：
A33: 四、审计结论：
A35: 提示：
A36: 分类判断依据： | B36: “交易性”[需属于下列任一情形之一] | C36: 取得相关金融资产的目的，主要是为了近期出售或回购
C37: 相关金融资产在初始确认时属于集中管理的可辨认金融工具组合的一部分，且有客观证据表明近期实际存在短期获利模式
C38: 相关金融资产属于衍生工具（但符合财务担保合同定义的衍生工具以及被指定为有效套期工具的衍生工具除外）
B39: 交易性金融资产 | C39: 合同现金流量并非仅为对本金和以未偿付本金金额为基础的利息的支付
B40: 在初始确认时，如果能够消除或显著减少会计错配，企业可以将金融资产指定为以公允价值计量且其变动计入当期损益的金融资产
A41: 1.了解并观察被审计单位如何管理其金融资产以产生现金流量……
A42: 1.1 了解被审计单位关键管理人员决定的对金融资产进行管理的特定业务目标；
A43: 1.2 考虑被审计单位评价和向关键管理人员报告金融资产业绩的方式、影响金融资产业绩的风险及其管理方式以及相关业务管理人员获得报酬的方式（例如报酬是基于所管理资产的公允价值还是所收取的合同现金流量）等。
A44: 2. 了解被审计单位确定业务模式的层次。若被审计单位将应收账款划分为不同的组合从而确定多个业务模式，分析划分组合的依据是否明确，各组合是否可明确区分……
A45: 3. 对于以收取合同现金流量为目标的业务模式……
A46: 3.1 了解以前的出售是否频繁，但金额不重大；或金额虽重大（如在压力情景下出售），但不频繁；
A47: 3.2 了解以前的出售是否在接近到期日发生；
A48: 3.3 了解被审计单位对未来出售活动的预期。
A49: 4. 对于以收取合同现金流量和出售金融资产为目标的业务模式……
A50: 4.1 了解收取合同现金流量和出售金融资产对于实现其管理目标而言是否都是不可或缺的；
A51: 4.2 了解被审计单位是否涉及更高频率和更大价值的出售，即经常进行大额贴现或背书。
A52: 5. 对于其他业务模式……
... A54: 5.2 了解被审计单位是否基于债权投资的公允价值作出决策并对其进行管理。

Sheet 分类的适当性检查表G1-9
A1: 致同会计师事务所
A2: 分类的适当性检查表
A3: =底稿目录!A2 -> 被审计单位： | D3: =底稿目录!A4 -> 编制人： | F3: =底稿目录!A5 -> 编制日期： | I3: 索引号： | J3: =底稿目录!F15 -> G1-9
A4: =底稿目录!A3 -> 截止日：202X年12月31日 | D4: =底稿目录!A6 -> 复核人： | F4: =底稿目录!A7 -> 复核日期： | I4: 页 次：
A5: 一、审计目标 | B5: 确定以公允价值计量且其变动计入当期损益的金融资产投资分类是否正确。
A6: 二、审计过程 | B6: 1. 以公允价值计量且其变动计入当期损益的金融资产投资的指定是否符合准则要求、会计处理是否合理并与前期一致。
B7: 2. 就管理层将投资确定为非交易性的目的获取书面声明，询问管理层持有相关资产的目的，实施以下程序印证管理层的答复，确定相关资产的分类是否正确：
B8: 2.1 考虑管理层以前所述的对于投资持有目的的实际实施情况；
B9: 2.2 复核包括预算、管理层会议纪要等在内的文件和报告记录，检查管理层是否对投资的持有目的进行了明确的书面指定。
B10: 3. 与管理层讨论金融资产分类是否符合企业会计准则，是否根据确定的分类选用了正确的核算方法。
B11: 4. 是否发现管理层在以前年度运用的重大判断和估计存在不合理的情形。如果存在，记录管理层是否在当年进行了恰当的会计处理和披露，并选用了更为准确的判断和假设。
A12: 投资项目 | B12: 期末账面价值 | C12: “交易性”[需属于下列任一情形之一] | F12: 债务工具投资 | G12: 权益工具投资 | H12: “初始确认时指定” | I12: 其他 | J12: 书面文件索引号
C13: 取得相关金融资产的目的，主要是为了近期出售或回购 | D13: 相关金融资产在初始确认时属于集中管理的可辨认金融工具组合的一部分，且有客观证据表明近期实际存在短期获利模式 | E13: 相关金融资产属于衍生工具（但符合财务担保合同定义的衍生工具以及被指定为有效套期工具的衍生工具除外） | F13: 合同现金流量并非仅为对本金和以未偿付本金金额为基础的利息的支付 | G13: 权益工具投资 | H13: 能够消除或显著减少会计错配
A14: ='明细表G1-2'!B12 -> 0 | B14: ='明细表G1-2'!W12 -> 0 | F14: 满足
B15: ='明细表G1-2'!W13 -> 0
B16: ='明细表G1-2'!W14 -> 0
B17: ='明细表G1-2'!W15 -> 0
B18: ='明细表G1-2'!W16 -> 0
A24: 合计 | B24: =SUM(B14:B23) -> 0
A26: 三、审计说明：
A29: 四、审计结论

Sheet 合同现金流量特征分析G1-10
A1: 致同会计师事务所
A2: 合同现金流量特征分析
A3: =底稿目录!A2 -> 被审计单位： | D3: =底稿目录!A4 -> 编制人： | F3: =底稿目录!A5 -> 编制日期： | G3: 索引号： | H3: =底稿目录!F16 -> G1-10
A4: =底稿目录!A3 -> 截止日：202X年12月31日 | D4: =底稿目录!A6 -> 复核人： | F4: =底稿目录!A7 -> 复核日期： | G4: 页 次：
A5: 一、审计目标：
A6: 确定被审计单位管理债务工具投资的合同现金流量特征是否仅为对本金和以未偿付本金金额为基础的利息的支付（能否通过SPPI测试），并结合业务模式，确定债务工具投资的金融资产分类。
A7: 二、审计过程： | B7: 1.分析金融资产的利息构成…… | E7: 4. 考虑无追索权规定……
B8: 2. 修正的货币时间价值…… | E8: 5. 分析合同挂钩工具…… | G8: 具体可参见蓝色文字提示
B9: 3. 分析导致合同现金流量的时间或金额变更的合同条款…… | E9: 6. 考虑极其微小的影响或不现实的现金流量特征…… | I9: 货币时间价值要素有时可能存在修正（即，不完善）。例如，如果金融资产的利率定期予以重设，但重设的频率与利率的期限错配（例如，利率每月被重设为一年期利率），或者如果金融资产的利率定期重设为特定短期和长期利率的平均值，则属于这种情况。 也就是说，按合同计算的利息是对实际货币时间价值的修正。 评估经修正的货币时间价值要素的目标在于，确定合同（未折现的）现金流量与若货币时间价值要素未作出修正时（未折现的）现金流量（即，基准现金流量）之间有何差异。
A10: （一）债券投资（国债、公司债、企业债）
A11: 投资项目 | B11: 票面价值总额 | C11: 票面利率 | D11: 提前回售选择权 | E11: 展期选择权 | F11: 权益转换特征 | G11: 杠杆因素 | H11: 结论
H12: 通过SPPI测试 | I12: 一般债券通常能通过SPPI测试（合同现金流量仅为对本金和以未偿付本金金额为基础的利息的支付）
H13: 通过SPPI测试
H14: 通过SPPI测试
A16: （二）银行理财产品
A17: 1.是否保本保收益
A18: 投资项目 | B18: 投资总额 | C18: 保证本金 | D18: 固定收益 | F18: 浮动收益 | H18: 结论
D19: 保证固定收益 | E19: 固定收益率 | F19: 约定浮动收益 | G19: 浮动收益率
A20: 保证收益型 | C20: 是 | D20: 是 | E20: 0.035 | F20: 否 | H20: =IF(AND(C20="是",D20="是",F20="否"),"通过SPPI测试",IF(AND(C20="是",F20="是"),"分析浮动收益是否是不现实的","穿透分析底层资产")) -> 通过SPPI测试
A21: X银行结构性存款 | C21: 是 | D21: 是 | E21: 0.0181 | F21: 是 | G21: 0.0179 | H21: =IF(AND(C21="是",D21="是",F21="否"),"通过SPPI测试",IF(AND(C21="是",F21="是"),"分析浮动收益是否是不现实的","穿透分析底层资产")) -> 分析浮动收益是否是不现实的
A22: G银行结构性存款 | C22: 是 | D22: 否 | F22: 是 | H22: =IF(AND(C22="是",D22="是",F22="否"),"通过SPPI测试",IF(AND(C22="是",F22="是"),"分析浮动收益是否是不现实的","穿透分析底层资产")) -> 分析浮动收益是否是不现实的
A23: 非保本型理财产品 | C23: 否 | D23: 否 | F23: 是 | H23: =IF(AND(C23="是",D23="是",F23="否"),"通过SPPI测试",IF(AND(C23="是",F23="是"),"分析浮动收益是否是不现实的","穿透分析底层资产")) -> 穿透分析底层资产 | I23: 债权人的索偿要求仅限于债务人的特定资产或基于特定资产的现金流量并不一定会导致金融资产不符合本金加利息的合同现金流量特征。企业需要对特定的基础资产或其现金流量进行评估（即穿透），以确定待分类的金融资产是否符合本金加利息的合同现金流量特征。
A24: 2.浮动收益是否是不现实的 | I24: 若无法了解基础资产的具体情况，因而无法对特定的基础资产或其现金流量进行评估（穿透），则通不过SPPI测试
A25: 投资项目 | B25: 固定收益率 | C25: 浮动收益确定方式 | F25: 基础变量历史变动情况 | G25: 浮动收益是否是不现实的 | H25: 结论
A26: G银行结构性存款 | B26: 0.033 | C26: 如在观察期内，欧元/美元汇率始终位于参考区间（1.0600,1.1442）内，则到期时预期可实现的投资年化收益率为3.35%。如在观察期内，欧元/美元汇率突破了参考区间，则到期时预期可实现的投资年化收益率为3.30%/年。 | F26: 2007年以来，欧元/美元汇率最低1.0511（2016年）、最高1.4588（2007年）；近三年的波动幅度也达到[1.09,1.19]。因此突破了参考区间，浮动并非是“不现实的”。 | G26: 现实的 | H26: =IF(G26="不现实的","通过SPPI测试","通不过SPPI测试") -> 通不过SPPI测试 | I26: 基于历史波动情况分析时，需考虑过去跨周期时的波动区间（例如过去12年的波动，包含2008年金融危机），而不能仅考虑挂钩期间（观察期）的变动情况。
A28: （三）优先股、永续债
A29: 投资项目 | B29: 票面价值总额 | C29: 期限 | D29: 首个计息期利率 | E29: 重置票面利率 | F29: 递延利息是否计息 | G29: 可转换为发行方固定数量的权益工具 | H29: 结论 | I29: 永续工具可视为具有连续性的多项展期选择权。如果利息支付具有强制性且必须永久性支付，则可能导致其符合本金加利息的合同现金流量特征。如含有或有结算条款的、递延利息计息的永续债。
A30: XX公司2019年度第二期中期票据 | C30: 3+N | D30: 0.045 | E30: 当期基准利率+初始利差+300BP | F30: 计息 | G30: 否 | H30: 通过SPPI测试 | I30: 如果递延利息不产生额外孳息，则不符合本金加利息的合同现金流量特征。
I31: 如果可转换为发行方固定数量的权益工具，则不符合本金加利息的合同现金流量特征。
A34: （四）可转换债券
A35: 投资项目 | B35: 投资总额 | C35: 期限 | D35: 票面利率 | E35: 初始转股价格 | F35: 说明 | H35: 结论
A36: YY转债“190009” | C36: 5年 | D36: 第一年0.50%，第二年0.70%，第三年1.30%，第四年1.70%，第五年2.00% | E36: 17.72元/股 | F36: 可转换债券可转换成固定数量的发行人权益工具，其回报与发行人的权益工具价值挂钩，不符合本金加利息的合同现金流量特征 | H36: 通不过SPPI测试 | I36: 可转换债券若可转换为可变数量的股份，且其价值等于本金及未偿付本金金额之利息的未支付金额，则能通过SPPI测试。
A40: （五）项目收益债、信托计划份额
A41: 投资项目 | B41: 投资总额 | C41: 期限 | D41: 票面利率 | E41: 基础资产现金流 | F41: 差额补偿机制 | G41: 担保 | H41: 结论
A42: “17延安01”项目收益专项公司债 | C42: 10年 | D42: 0.07 | E42: 延安圣地河谷·金延安板块一期综合开发建设项目门票收入、商业配套收入 | F42: 集团公司作为差额补偿人，当募投项目收入无法覆盖本息，发行人用自身其他收入进行不足后，保证金专用账户余额仍不能覆盖应付本息时，由集团公司承担差额补足义务。 | G42: 由集团公司提供全额无条件不可撤销的连带责任保证担保 | H42: 项目收益债收入并不仅限于项目收入，发行人自身其他收入应进行补足足，且存在差额补足义务人，因此不属于真正的“无追索权”，可以通过SPPI测试 | I42: 债权人的索偿要求仅限于债务人的特定资产或基于特定资产的现金流量（无追索权）并不一定会导致金融资产不符合本金加利息的合同现金流量特征。企业需要对特定的基础资产或其现金流量进行评估（即穿透），以确定待分类的金融资产是否符合本金加利息的合同现金流量特征。
A43: 00号集合信托计划 | C43: 18个月 | D43: A类受益人预期年收益率：7.3% | E43: 权益投资 | F43: 不涉及 | G43: 不涉及 | H43: 基础资产为权益投资，不符合本金加利息的合同现金流量特征 | I43: 如果合同现金流量特征仅对金融资产的合同现金流量构成极其微小的影响，则不会影响金融资产的分类。
A46: （六）资产支持证券
A47: 投资项目 | B47: 投资总额 | C47: 期限 | D47: 票面利率 | E47: 级次 | F47: 基础资产现金流 | G47: 信用风险比较 | H47: 结论
A48: "19XX06”优先A | D48: 0.0485 | E48: 优先级 | F48: 贷款 | G48: 分级的信用评级高于假设发行单一工具（不分级），该工具所得到的信用评级 | H48: 分级的合同条款产生的现金流量仅为对本金和以未偿付本金金额为基础的利息的支付；基础资产包含一个或多个符合本金加利息的合同现金流量特征的工具；该分级所承担的基础资产的信用风险，等于或小于基础资产本身的信用风险。可以通过SPPI测试 | I48: 当同时符合下列条件时，企业持有的某一分级的金融资产才符合本金加利息的合同现金流量特征： （1）分级的合同条款（在未穿透基础资产的情况下），产生的现金流量仅为对本金和以未偿付本金金额为基础的利息的支付（例如该分级的利率未与商品价格指数挂钩）。 （2）基础资产包含一个或多个符合本金加利息的合同现金流量特征的工具（以下称基础工具）。这里的基础资产，是指穿透到最底层的、源生现金流量而非过手现金流量的资产。 （3）该分级所承担的基础资产的信用风险，等于或小于基础资产本身的信用风险。例如，分级的信用评级等于或高于假设发行单一工具（不分级），该工具所得到的信用评级。
A49: "19XX09”次级 | D49: 无 | E49: 次级 | F49: 贷款 | G49: 分级的信用评级低于假设发行单一工具（不分级），该工具所得到的信用评级 | H49: 分级的合同条款产生的现金流量并非仅为对本金和以未偿付本金金额为基础的利息的支付；该分级所承担的基础资产的信用风险，并非等于或小于基础资产本身的信用风险。通不过SPPI测试
A53: 三、审计说明：
A55: 四、审计结论：
A57: 提示：
A58: 1.分析金融资产的利息构成……
A59: 1.1 使用金融资产的计价货币来评估金融资产的合同现金流量特征；
A60: 1.2 分析利息是否包括对货币时间价值、与特定时期未偿付本金金额相关的信用风险、以及其他基本借贷风险（如流动性风险）、成本（如管理费用）和利润的对价； | I60: 在基本借贷安排中，利息的构成要素中最重要的通常是货币时间价值和信用风险的对价。 货币时间价值是利息要素中仅因为时间流逝而提供对价的部分，不包括为所持有金融资产的其他风险或成本提供的对价。
A61: 1.3 分析金融资产合同中是否包含与基本借贷安排无关的合同现金流量风险敞口或波动性敞口（例如权益价格或商品价格变动敞口）的条款。
A62: 2. 修正的货币时间价值…… | G62: 具体可参见蓝色文字提示
A63: 2.1 在货币时间价值要素存在修正的情况下，对相关修正进行评估；
A64: 2.2 考虑修正的货币时间价值在每一报告期间的影响以及在金融工具整个存续期内的累积影响；
A65: 2.3 确定未折现合同现金流量与假如未对货币时间价值要素进行修正的情形下未折现的合同现金流量（基准现金流量）之间的差异。
A66: 3. 分析导致合同现金流量的时间或金额变更的合同条款…… | I66: 货币时间价值要素有时可能存在修正（即，不完善）。例如，如果金融资产的利率定期予以重设，但重设的频率与利率的期限错配（例如，利率每月被重设为一年期利率），或者如果金融资产的利率定期重设为特定短期和长期利率的平均值，则属于这种情况。 也就是说，按合同计算的利息是对实际货币时间价值的修正。 评估经修正的货币时间价值要素的目标在于，确定合同（未折现的）现金流量与若货币时间价值要素未作出修正时（未折现的）现金流量（即，基准现金流量）之间有何差异。
A67: 3.1 分析浮动利率、提前回售选择权、展期选择权是否影响合同现金流量特征；
A68: 3.2 分析金融资产的合同现金流量特征中是否包含杠杆因素，或者金融资产代表对特定资产或现金流量的投资；
A69: 3.3 分析以溢价或折价购入或源生的、且具有提前偿付特征的债务工具是否符合本金加利息的合同现金流量特征。
A70: 4. 考虑无追索权规定……
A71: 4.1 如果存在无追索权规定（债权人的索偿要求仅限于债务人的特定资产或产生于特定资产的现金流量），债权人必须评估（看穿）特定标的资产或现金流量以确定金融资产的合同现金流量是否符合“本金加利息的合同现金流量特征”；
A72: 4.2 如果金融资产的合同条款产生了其他现金流量，或者以一种与代表本金和利息的支付不一致的方式限制了现金流量，则该金融资产不符合本金加利息的合同现金流量特征；
A73: 4.3 如果企业无法了解基础资产的具体情况（如投资的具体组成、期限、条款等），因而无法对特定的基础资产或其现金流量进行评估，则企业无法确定待分类的金融资产是否符合本金加利息的合同现金流量特征。
A74: 5. 分析合同挂钩工具……
A75: 5.1 分级的合同条款（在未穿透基础资产的情况下），产生的现金流量是否仅为对本金和以未偿付本金金额为基础的利息的支付（例如该分级的利率未与商品价格指数挂钩）；
A76: 5.2 基础资产是否包含一个或多个符合本金加利息的合同现金流量特征的工具（以下称基础工具）； | I76: 这里的基础资产，是指穿透到最底层的、源生现金流量而非过手现金流量的资产。
A77: 5.3 该分级所承担的基础资产的信用风险，是否等于或小于基础资产本身的信用风险。 | I77: 例如，分级的信用评级等于或高于假设发行单一工具（不分级），该工具所得到的信用评级。
A78: 6. 考虑极其微小的影响或不现实的现金流量特征……
A79: 6.1 考虑合同现金流量特征在每一会计期间的潜在影响以及在金融工具整个存续期内的累积影响； | I79: 如果合同现金流量特征仅对金融资产的合同现金流量构成极其微小的影响，则不会影响金融资产的分类。
A80: 6.2 如果合同现金流量特征（无论某一会计期间还是整个存续期）对合同现金流量的影响超过了极其微小的程度，进一步判断该现金流量特征是否是不现实的。 | I80: 如果现金流量特征仅在极端罕见、显著异常且几乎不可能的事件发生时才影响该工具的合同现金流量，那么该现金流量特征是不现实的。如果该现金流量特征不现实，则不影响金融资产的分类。

Sheet 有价证券监盘表G1-11
A1: 致同会计师事务所
A2: 有价证券监盘表
A3: =底稿目录!A2 -> 被审计单位： | D3: =底稿目录!A4 -> 编制人： | E3: =底稿目录!A5 -> 编制日期： | F3: 索引： | G3: =底稿目录!F17 -> G1-11
A4: =底稿目录!A3 -> 截止日：202X年12月31日 | D4: =底稿目录!A6 -> 复核人： | E4: =底稿目录!A7 -> 复核日期： | F4: 页次：
A5: 一、审计目标 | C5: 资产负债表中记录的交易性金融资产是存在的，且已记录于恰当的账户
A6: 二、审计过程
A7: 1、盘点情况
B8: 盘点单位： | F8: 盘点日期：
B9: 会计主管： | F9: 监盘人：
B10: 出纳人员： | F10: 复核人：
B11: 盘点人员：
B12: XX（人）于xx年xx月xx日，在xx（地点）对有价证券进行盘点，现将现场盘点出的有价证券列示如下：
B13: 证券名称 | C13: 面值 | D13: 数量 | E13: 总计 | F13: 票面利率 | G13: 到期日
A31: 2、有价证券盘点倒扎表
B32: 见“有价证券盘点倒轧表I9-9-2”。
A33: 三、审计说明：
A36: 四、审计结论：
A39: 说明：1、盘点时，需要与现金盘点同时进行，审计人员不要单独接触有价证券。
A40: 2、对放置在不同位置的有价证券要同时进行检查，以免有价证券被移置影响检查的正确性。
A41: 3、如果盘点日不是资产负债表日，应将盘点日实存有价证券，推算至资产负债表日实存有价证券。

Sheet 有价证券盘点倒轧表G1-12
A1: 致同会计师事务所
A2: 有价证券盘点倒轧表
A3: =底稿目录!A2 -> 被审计单位： | E3: =底稿目录!A4 -> 编制人： | K3: =底稿目录!A5 -> 编制日期： | Q3: 索引号： | R3: =底稿目录!F18 -> G1-12
A4: =底稿目录!A3 -> 截止日：202X年12月31日 | E4: =底稿目录!A6 -> 复核人： | K4: =底稿目录!A7 -> 复核日期： | Q4: 页次： | R4: 1
A5: 证券名称 | B5: 盘点日实存有价证券 | G5: 资产负债表日到盘点日的增加（减少）有价证券 | I5: 资产负债表日实存有价证券 | N5: 账面结存交易性金融资产 | Q5: 差异 | R5: 备注
B6: 数量 | C6: 面值 | D6: 总计 | E6: 票面利率 | F6: 到期日 | G6: 数量 | H6: 面值总额 | I6: 数量 | J6: 面值 | K6: 总计 | L6: 票面利率 | M6: 到期日 | N6: 数量 | O6: 面值 | P6: 总计
A7: 债务工具投资 | D7: =SUM(D8:D10) -> 0 | K7: =SUM(K8:K10) -> 0 | P7: =SUM(P8:P10) -> 0 | Q7: =SUM(Q8:Q10) -> 0
A8: 1.**** | D8: =B8*C8 -> 0 | K8: =I8*J8 -> 0 | P8: =N8*O8 -> 0 | Q8: =P8-K8 -> 0
A9: 2.**** | D9: =B9*C9 -> 0 | K9: =I9*J9 -> 0 | P9: =N9*O9 -> 0 | Q9: =P9-K9 -> 0
A10: …… | D10: =B10*C10 -> 0 | K10: =I10*J10 -> 0 | P10: =N10*O10 -> 0 | Q10: =P10-K10 -> 0
A11: 权益工具投资 | D11: =SUM(D12:D14) -> 0 | K11: =SUM(K12:K14) -> 0 | P11: =SUM(P12:P14) -> 0 | Q11: =SUM(Q12:Q14) -> 0
A12: 1.**** | D12: =B12*C12 -> 0 | K12: =I12*J12 -> 0 | P12: =N12*O12 -> 0 | Q12: =P12-K12 -> 0
A13: 2.**** | D13: =B13*C13 -> 0 | K13: =I13*J13 -> 0 | P13: =N13*O13 -> 0 | Q13: =P13-K13 -> 0
A14: …… | D14: =B14*C14 -> 0 | K14: =I14*J14 -> 0 | P14: =N14*O14 -> 0 | Q14: =P14-K14 -> 0
A15: 衍生金融资产 | D15: =SUM(D16:D18) -> 0 | K15: =SUM(K16:K18) -> 0 | P15: =SUM(P16:P18) -> 0 | Q15: =SUM(Q16:Q18) -> 0
A16: 1.**** | D16: =B16*C16 -> 0 | K16: =I16*J16 -> 0 | P16: =N16*O16 -> 0 | Q16: =P16-K16 -> 0
A17: 2.**** | D17: =B17*C17 -> 0 | K17: =I17*J17 -> 0 | P17: =N17*O17 -> 0 | Q17: =P17-K17 -> 0
A18: …… | D18: =B18*C18 -> 0 | K18: =I18*J18 -> 0 | P18: =N18*O18 -> 0 | Q18: =P18-K18 -> 0
A19: 其他 | D19: =SUM(D20:D22) -> 0 | K19: =SUM(K20:K22) -> 0 | P19: =SUM(P20:P22) -> 0 | Q19: =SUM(Q20:Q22) -> 0
A20: 1.**** | D20: =B20*C20 -> 0 | K20: =I20*J20 -> 0 | P20: =N20*O20 -> 0 | Q20: =P20-K20 -> 0
A21: 2.**** | D21: =B21*C21 -> 0 | K21: =I21*J21 -> 0 | P21: =N21*O21 -> 0 | Q21: =P21-K21 -> 0
A22: …… | D22: =B22*C22 -> 0 | K22: =I22*J22 -> 0 | P22: =N22*O22 -> 0 | Q22: =P22-K22 -> 0
A23: 合计 | D23: =D19+D15+D11+D7 -> 0 | K23: =K19+K15+K11+K7 -> 0 | P23: =P19+P15+P11+P7 -> 0 | Q23: =P23-K23 -> 0

Sheet 检查表G1-13
A1: 致同会计师事务所
A2: 交易性金融资产检查表
A3: =底稿目录!A2 -> 被审计单位： | F3: =底稿目录!A4 -> 编制人： | K3: =底稿目录!A5 -> 编制日期： | O3: 索引号： | P3: =底稿目录!F27 -> G1-13
A4: =底稿目录!A3 -> 截止日：202X年12月31日 | F4: =底稿目录!A6 -> 复核人： | K4: =底稿目录!A7 -> 复核日期： | O4: 页次：
A5: 一、审计目标：
A6: 1.资产负债表中记录的交易性金融资产是存在的，且已经记录在恰当的账户中； | F6: 2.记录的交易性金融资产由被审计单位拥有或控制；
A7: 3.交易性金融资产以恰当的金额包括在财务报表中，与之相关的计价或分摊调整已恰当记录，相关披露已得到恰当计量和描述。
A8: 二、样本选取标准与规模：
A9: 测试总体： | B9: 如借方发生额所有凭证共XX笔金额XX、贷方发生额所有凭证共XX笔金额XX | F9: 特定样本： | G9: XX金额以上（大额）、关联方/关联交易形成的款项、XX异常款项全部测试，共XX笔；
A10: 抽样总体： | B10: 测试总体扣除特定样本以外的样本，共XX笔、金额XX | F10: 确定的抽样样本量： | G10: 抽取XX笔 | H10: （如果使用了样本计算器计算样本量，样本量计算过程见<XX>底稿）
A11: 抽样方法： | B11: 随机选样/系统选样/货币单元抽样/随意选样（非统计抽样适用） | F11: 抽样过程： | G11: 使用IDEA（XX抽样工具）选择XX数量、金额XX的样本进行测试，抽样工具中的样本选择过程和结果见<XX>底稿
A12: 三、测试：
A13: 测试内容说明：1.原始凭证是否齐全； 2.记账凭证与原始凭证是否相符；3.账务处理是否正确；4.是否记录于恰当的会计期间；5.……
A14: 1.本期发生额检查
A15: 记账凭证 | H15: 支持性文件 | I15: 核对内容 | N15: 索引号 | O15: 是否异常 | P15: 备注说明
A16: 日期 | B16: 凭证编号 | C16: 业务内容 | D16: 对方科目 | E16: 对方明细科目 | F16: 借方金额 | G16: 贷方金额 | I16: 1 | J16: 2 | K16: 3 | L16: 4 | M16: 5
H17: 付款审批单、银行回单、投资协议、交易确认单、……
A25: 合计 | F25: =SUM(F17:F24) -> 0 | G25: =SUM(G17:G24) -> 0
A26: 本期发生额
A27: 检查比例 | F27: =F25/F26 -> #DIV/0! | G27: =G25/G26 -> #DIV/0!
A28: 2.期后处置、新增检查表
A29: 记账凭证 | H29: 支持性文件 | I29: 核对内容 | N29: 索引号 | O29: 是否异常 | P29: 备注说明
A30: 日期 | B30: 凭证编号 | C30: 业务内容 | D30: 对方科目 | E30: 对方明细科目 | F30: 借方金额 | G30: 贷方金额 | I30: 1 | J30: 2 | K30: 3 | L30: 4 | M30: 5
A35: 合计 | F35: =SUM(F31:F34) -> 0 | G35: =SUM(G31:G34) -> 0
A36: 四、审计说明：
A39: 五、审计结论：

Sheet 衍生金融工具核查表G1-14
A1: 致同会计师事务所
A2: 衍生金融工具核查表
A3: =底稿目录!A2 -> 被审计单位： | D3: =底稿目录!A4 -> 编制人： | E3: =底稿目录!A5 -> 编制日期： | G3: 索引号： | H3: =底稿目录!F28 -> G1-14
A4: =底稿目录!A3 -> 截止日：202X年12月31日 | D4: =底稿目录!A6 -> 复核人： | E4: =底稿目录!A7 -> 复核日期： | G4: 页次：
A5: 一、审计目标 | C5: 确定衍生工具投资的确认、计量是否准确。
A6: 二、审计过程
A7: 1 | B7: 确定衍生工具
C8: 工具名称：___________________________________________
A9: A | B9: 复核与(主合同的)交易对方所签订贷款、投资、存款或其它工具的协议（如适用）
A10: B | B10: 在协议中有无提及任何有下列影响的项目(即是否存在任何衍生工具或附于主合同的衍生工具？) | F10: 回答
B11: 合同所要求的部分/全部现金流量将依据以下各特定项目予以修正：
C12: (1)利率 | G12: (是或否)
C13: (2)金融工具价格 | G13: (是或否)
C14: (3)商品价格 | G14: (是或否)
C15: (4)汇率 | G15: (是或否)
C16: (5)价格或利率指数 | G16: (是或否)
C17: (6)信用等级/信用指数 | G17: (是或否)
C18: (7)其它非金融变量(请注明：______________) | G18: (是或否)
C19: (8)其它非金融变量非合同某一方特有的(请注明：________) | G19: (是或否)
C20: (如果对于上述B项的任何答案为否，即表示不存在任何衍生工具，则无需回答下列问题)
A21: C | B21: 所包含的衍生工具是否属于嵌入衍生工具？
C22: 如果上述B项的任何答案为是，即表明存在附于主合同的衍生工具，请回答下列问题：
C23: (1)有关衍生工具不可以独立于该金融工具进行合约转让 | G23: (是或否)
C24: (2)有关衍生工具具有与主金融工具(主合同)相同的交易对方 | G24: (是或否)
C25: 如果上述C项的任何答案为否，即表明不存在任何嵌入衍生工具，则无需回答下列问题。有关衍生工具应单独进行核算。
C26: 对衍生工具(不是嵌入衍生工具)执行的额外工作：
C27: (a)说明有关性质 | G27: (描述性)
C28: (b)增设新的科目描述及编码以确认所包含的衍生工具 | G28: (描述性)
C29: (c)说明适用于有关衍生工具的会计政策 | G29: (描述性)
A30: 结论：
A31: 1 | B31: 衍生工具名称：(如不适用无需填写)
A32: 2 | B32: 衍生工具的特征：(嵌入/非嵌入)(删除不适用的部分)
A33: 3 | B33: 混合合同包含的主合同属于CAS 22规范的金融资产的，企业不应从该混合合同中分拆嵌入衍生工具，而应当将该混合合同作为一个整体
B34: 适用金融资产分类的相关规定。
A35: 2 | B35: 抽查衍生工具的会计处理
A36: 日 期 | B36: 凭证编号 | C36: 业务内容 | D36: 明细科目 | E36: 对方科目 | F36: 金 额 | H36: 结论
F37: 借方 | G37: 贷方
A42: 3 | B42: 专家资质及利用估值专家的工作
B43: 序号 | C43: 项目 | D43: 索引号
B44: 1 | C44: 了解专家的资质
B45: 2 | C45: 利用专家的工作
