Workbook

Sheet 底稿目录
A1: 底稿开列时，可先在以下单元格填写有关内容，以便其他底稿引用有关数据：
A2: 被审计单位：
A3: 会计期间：202X年度 | D3: 序号 | E3: 内容 | F3: 索引号
A4: 编制人： | E4: 投资收益实质性程序表 | F4: G11A
A5: 编制日期： | D5: 1 | E5: 审定表 | F5: G11-1
A6: 复核人： | D6: 2 | E6: 附注披露信息（上市公司）
A7: 复核日期： | D7: 3 | E7: 附注披露信息（国企）
D8: 4 | E8: 明细分析表 | F8: G11-2
A9: 关于工作底稿与审计程序索引号对应的说明 | D9: 5 | E9: 调整分录汇总 | F9: G11-3
A10: 1.编制的审计工作底稿应与审计程序对应。审计项目组应根据被审计单位实际情况和风险评估情况在实质性程序表中裁剪、修改或增加审计程序，根据实际执行的审计程序完成相应审计工作底稿，编制的工作底稿中应按自然顺序依次编制索引号，并通过唯一的索引号将与实质性程序表中的程序对应关联（即将工作底稿的索引号填入实质性程序表中的底稿索引号列）。 | D10: 6 | E10: 收益率分析表 | F10: G11-4
D11: 7 | E11: 凭证检查表 | F11: G11-5
A14: 2.获取的支持性证据应与审计底稿或程序对应。审计项目组在完成底稿时获取的支持性证据应根据底稿索引号编制下一级按自然顺序排序的索引号（如D1-2-1、D1-2-2、……），并在底稿中说明引用的支持性证据、关联索引号。
A17: 3.工作底稿索引号的编码规则：实质性程序索引号按循环从“D”到“N”,循环内账户以顺序号排列，模板中底稿索引号按账户顺序+自然数顺序（即模板中索引号按二级自然顺序排列，如D1-1、D1-2、D1-3、……D1-N）。

Sheet 投资收益实质性程序表G11A
A1: 致同会计师事务所
A2: 投资收益实质性程序表
A3: =底稿目录!A2 -> 被审计单位： | C3: =底稿目录!A4 -> 编制人： | F3: =底稿目录!A5 -> 编制日期： | H3: 索引号： | I3: =底稿目录!F4 -> G11A
A4: =底稿目录!A3 -> 会计期间：202X年度 | C4: =底稿目录!A6 -> 复核人： | F4: =底稿目录!A7 -> 复核日期： | H4: 页 次：
A5: 一、本账户涉及的科目
A6: 投资收益
A7: 二、审计目标与认定的对应关系
A8: 审计目标 | G8: 财务报表的认定
A9: A. 利润表中记录的投资收益已发生，且与被审计单位有关，已记录于恰当的账户 | G9: 发生
A10: B. 所有应记录的投资收益均已记录，所有应当包括在财务报表中的相关披露均已包括 | G10: 完整性
A11: C. 与投资收益有关的金额及其他数据已恰当记录，相关披露已得到恰当计量和描述 | G11: 准确性
A12: D. 投资收益已记录于正确的会计期间 | G12: 截止
A13: E. 投资收益已被恰当地汇总或分解且表述清楚，相关披露在按照企业会计准则的编制基础下是相关的、可理解的 | G13: 列报
A14: 三、计划实施的实质性程序
A15: 序号 | B15: 审计程序 | C15: 程序分类 | D15: 财务报表的认定 | I15: 底稿索引号
D16: 发生 | E16: 完整性 | F16: 准确性 | G16: 截止 | H16: 列报 | J16: 根据被审计单位实际情况和风险评估情况裁剪、修改或增加审计程序
A17: 1 | B17: 获取或编制投资收益的明细表，完成以下工作，并编制审定表 （1）复核加计是否正确，与总账、明细账合计数核对是否相符； （2）将上期发生额与上期经审计的财务报表核对 （3）与上年明细项目进行比较，确定与上年分类相同。 | C17: 常规★ | D17: √ | E17: √ | F17: √ | I17: G11-1 /G11-2
A18: 2 | B18: 在使用手工编制、自定义信息报告、系统生成的非固定格式报告等由被审计单位生成的信息时，测试有关信息准确性和完整性，并考虑针对编制和维护由被审计单位生成的信息的相关控制实施控制测试，以评价该信息是否能够为实现审计目的提供基础。 | C18: 常规★ | E18: √ | F18: √ | I18: T1
A19: 3 | B19: 结合相关金融资产、负债的审计审计，关注本期重大投资收益： （1）检查与股权投资处置相关的合同、发票及其他文件； （2）重新计算相关的利得或损失； （3）确定会计处理是否恰当； （4）识别期后发生的长期股权投资的减少，检查至支持性文件，确定是否是被记录在恰当的期间内。 | C19: 常规★ | D19: √ | E19: √ | F19: √ | G19: √ | I19: G11-2 /G11-4 /G11-5
A20: 4 | B20: 结合金融资产循环中投资收益的审计，分析对投资收益的依赖程度，分析盈利能力的稳定性；比较投资收益率及其变动是否异常。 | C20: IPO/上市/新三板/重组/舞弊应对 | D20: √ | E20: √ | F20: √ | G20: √ | I20: G11-4
A21: 6 | B21: 根据评估的舞弊风险等因素增加的审计程序。 | C21: IPO/上市/新三板/重组/舞弊应对
A22: 7 | B22: 检查投资收益是否已按企业会计准则或其他适用的规定在财务报表中做出恰当列报和披露。 | C22: 常规★ | H22: √ | I22: A1-1/A1-15 /A1-16

Sheet 投资收益实质性程序表G11A-修订前
A1: 致同会计师事务所
A2: 投资收益实质性程序表
A3: =底稿目录!A2 -> 被审计单位： | C3: =底稿目录!A4 -> 编制人： | F3: =底稿目录!A5 -> 编制日期： | H3: 索引号： | I3: =底稿目录!F4 -> G11A
A4: =底稿目录!A3 -> 会计期间：202X年度 | C4: =底稿目录!A6 -> 复核人： | F4: =底稿目录!A7 -> 复核日期： | H4: 页 次：
A5: 一、本账户涉及的科目
A6: 投资收益
A7: 二、重大错报风险需从实质性程序获取的保证程度
A8: 审计目标与认定对应关系 | C8: 财务报表的认定 | H8: 信赖/不信赖/不适用 | I8: 索引号
C9: 发生 | D9: 完整性 | E9: 准确性 | F9: 分类 | G9: 列报与披露
A10: A. 利润表中记录的投资收益已发生，且与被审计单位有关。 | C10: √
A11: B. 所有应当记录的投资收益均已记录。 | D11: √
A12: C. 与投资收益有关的金额及其他数据已恰当记录于正确的会计期间。 | E12: √
A13: D. 投资收益已记录于恰当的账户。 | F13: √
A14: E. 投资收益已按照企业会计准则的规定在财务报表中作出恰当的列报和披露。 | G14: √
A15: 三、计划实施的实质性程序
A16: 序号 | B16: 审计程序 | C16: 程序分类 | D16: 审计目标 | H16: 执行情况说明 （含底稿索引）
A17: 一 | B17: 编制审定表 | C17: 常规★ | D17: ABCD | H17: H3 | J17: 整合为1 | K17: 获取或编制投资收益的明细表，完成以下工作，并编制审定表 （1）复核加计是否正确，与总账、明细账合计数核对是否相符； （2）将期初余额与上期期末余额核对； （3）与上年明细项目进行比较，确定与上年分类相同。
A18: 二 | B18: 获取或编制投资收益明细表，并执行下列程序： | C18: 常规★ | D18: ABCD | H18: H3-2 | J18: 整合为1
A19: 1 | B19: 复核加计正确。 | C19: 常规 | J19: 整合为1
A20: 2 | B20: 与总账核对一致。 | C20: 常规 | J20: 整合为1
A21: 3 | B21: 将期初余额与上期期末余额核对。 | C21: 常规 | J21: 整合为1
A22: 4 | B22: 与上年明细项目进行比较，确定与上年分类相同。 | C22: 常规 | J22: 整合为1
A23: 三 | B23: 在使用被审计单位生成的信息（IPE）时，应当评价该信息对实现审计目的是否足够可靠，包括根据具体情况在必要时实施下列程序： | C23: 常规★ | D23: B | H23: T1 | J23: 保留修改为2 | K23: 在使用手工编制、自定义信息报告、系统生成的非固定格式报告等由被审计单位生成的信息时，测试有关信息准确性和完整性，并考虑针对编制和维护由被审计单位生成的信息的相关控制实施控制测试，以评价该信息是否能够为实现审计目的提供基础。
A24: 1 | B24: 获取有关信息准确性和完整性的审计证据。 | J24: 保留修改为2
A25: 2 | B25: 评价信息对实现审计目的是否足够准确和详细。 | J25: 保留修改为2
A26: 四 | B26: 确定本期处置的重大股权投资，并执行下列程序： | C26: 常规★ | D26: D | H26: H3-5 | J26: 保留为3
A27: 1 | B27: 检查与股权投资处置相关的合同、发票及其他文件。 | C27: 常规★ | J27: 保留为3
A28: 2 | B28: 重新计算相关的利得或损失。 | C28: 常规★ | J28: 保留为3
A29: 3 | B29: 确定会计处理是否恰当。 | C29: 常规★ | J29: 保留为3
A30: 4 | B30: 识别期后发生的长期股权投资的减少，检查至支持性文件，确定是否是被记录在恰当的期间内。 | C30: 常规★ | J30: 保留为3
A31: 五 | B31: 结合金融资产循环中投资收益的审计，分析对投资收益的依赖程度，分析盈利能力的稳定性；比较投资收益率及其变动是否异常。 | C31: IPO/上市公司 | D31: D | H31: H3-3 | J31: 保留为4
A32: 六 | B32: 对于重大的投资收益项目，检查相关文件，并结合长期股权投资等项目的审计程序，确定会计处理是否正确。 | C32: 常规 | D32: D | H32: H3-5 | J32: 保留为5
A33: 七 | B33: 根据评估的舞弊风险等因素增加的审计程序。 | C33: 常规 | D33: ABCD | J33: 保留为6
A34: 八 | B34: 确定需在财务报表中单独披露的信息已被记录。 | C34: 常规★ | D34: E | H34: H3-1 | J34: 保留为7

Sheet 审定表G11-1
A1: 致同会计师事务所
A2: 投资收益审定表
A3: =底稿目录!A2 -> 被审计单位： | C3: =底稿目录!A4 -> 编制人： | G3: =底稿目录!A5 -> 编制日期： | J3: 索引号： | K3: =底稿目录!F5 -> G11-1
A4: =底稿目录!A3 -> 会计期间：202X年度 | C4: =底稿目录!A6 -> 复核人： | G4: =底稿目录!A7 -> 复核日期： | J4: 页 次：1
A5: 项目 | B5: 本期数 | E5: 上期数 | H5: 本期审定数与上期 审定数的比较 | J5: 原因分析 | K5: 索引
B6: 本期未审数 | C6: 账项调整 | D6: 本期审定数 | E6: 上期未审数 | F6: 账项调整 | G6: 上期审定数 | H6: 变动额 | I6: 变动率
A7: 权益法核算的长期股权投资收益 | B7: =SUMIF('明细分析表G11-2'!$B:$B,$A7,'明细分析表G11-2'!D:D) -> 0 | C7: =SUMIF('明细分析表G11-2'!$B:$B,$A7,'明细分析表G11-2'!E:E) -> 0 | D7: =B7+C7 -> 0 | E7: =SUMIF('明细分析表G11-2'!$B:$B,$A7,'明细分析表G11-2'!H:H) -> 0 | F7: =SUMIF('明细分析表G11-2'!$B:$B,$A7,'明细分析表G11-2'!I:I) -> 0 | G7: =E7+F7 -> 0 | H7: =D7-G7 -> 0 | I7: =IF(AND(D7=0,G7=0),0,IF(AND(D7=0,G7>0),1,H7/G7)) -> 0
A8: 处置长期股权投资产生的投资收益 | B8: =SUMIF('明细分析表G11-2'!$B:$B,$A8,'明细分析表G11-2'!D:D) -> 0 | C8: =SUMIF('明细分析表G11-2'!$B:$B,$A8,'明细分析表G11-2'!E:E) -> 0 | D8: =B8+C8 -> 0 | E8: =SUMIF('明细分析表G11-2'!$B:$B,$A8,'明细分析表G11-2'!H:H) -> 0 | F8: =SUMIF('明细分析表G11-2'!$B:$B,$A8,'明细分析表G11-2'!I:I) -> 0 | G8: =E8+F8 -> 0 | H8: =D8-G8 -> 0 | I8: =IF(AND(D8=0,G8=0),0,IF(AND(D8=0,G8>0),1,H8/G8)) -> 0
A9: 处置划分为持有待售资产的长期股权投资产生的投资收益 | B9: =SUMIF('明细分析表G11-2'!$B:$B,$A9,'明细分析表G11-2'!D:D) -> 0 | C9: =SUMIF('明细分析表G11-2'!$B:$B,$A9,'明细分析表G11-2'!E:E) -> 0 | D9: =B9+C9 -> 0 | E9: =SUMIF('明细分析表G11-2'!$B:$B,$A9,'明细分析表G11-2'!H:H) -> 0 | F9: =SUMIF('明细分析表G11-2'!$B:$B,$A9,'明细分析表G11-2'!I:I) -> 0 | G9: =E9+F9 -> 0 | H9: =D9-G9 -> 0 | I9: =IF(AND(D9=0,G9=0),0,IF(AND(D9=0,G9>0),1,H9/G9)) -> 0
A10: 交易性金融资产持有期间的投资收益 | B10: =SUMIF('明细分析表G11-2'!$B:$B,$A10,'明细分析表G11-2'!D:D) -> 0 | C10: =SUMIF('明细分析表G11-2'!$B:$B,$A10,'明细分析表G11-2'!E:E) -> 0 | D10: =B10+C10 -> 0 | E10: =SUMIF('明细分析表G11-2'!$B:$B,$A10,'明细分析表G11-2'!H:H) -> 0 | F10: =SUMIF('明细分析表G11-2'!$B:$B,$A10,'明细分析表G11-2'!I:I) -> 0 | G10: =E10+F10 -> 0 | H10: =D10-G10 -> 0 | I10: =IF(AND(D10=0,G10=0),0,IF(AND(D10=0,G10>0),1,H10/G10)) -> 0
A11: 处置交易性金融资产取得的投资收益 | B11: =SUMIF('明细分析表G11-2'!$B:$B,$A11,'明细分析表G11-2'!D:D) -> 0 | C11: =SUMIF('明细分析表G11-2'!$B:$B,$A11,'明细分析表G11-2'!E:E) -> 0 | D11: =B11+C11 -> 0 | E11: =SUMIF('明细分析表G11-2'!$B:$B,$A11,'明细分析表G11-2'!H:H) -> 0 | F11: =SUMIF('明细分析表G11-2'!$B:$B,$A11,'明细分析表G11-2'!I:I) -> 0 | G11: =E11+F11 -> 0 | H11: =D11-G11 -> 0 | I11: =IF(AND(D11=0,G11=0),0,IF(AND(D11=0,G11>0),1,H11/G11)) -> 0
A12: 债权投资持有期间的利息收益 | B12: =SUMIF('明细分析表G11-2'!$B:$B,$A12,'明细分析表G11-2'!D:D) -> 0 | C12: =SUMIF('明细分析表G11-2'!$B:$B,$A12,'明细分析表G11-2'!E:E) -> 0 | D12: =B12+C12 -> 0 | E12: =SUMIF('明细分析表G11-2'!$B:$B,$A12,'明细分析表G11-2'!H:H) -> 0 | F12: =SUMIF('明细分析表G11-2'!$B:$B,$A12,'明细分析表G11-2'!I:I) -> 0 | G12: =E12+F12 -> 0 | H12: =D12-G12 -> 0 | I12: =IF(AND(D12=0,G12=0),0,IF(AND(D12=0,G12>0),1,H12/G12)) -> 0
A13: 其他债权投资持有期间的利息收益 | B13: =SUMIF('明细分析表G11-2'!$B:$B,$A13,'明细分析表G11-2'!D:D) -> 0 | C13: =SUMIF('明细分析表G11-2'!$B:$B,$A13,'明细分析表G11-2'!E:E) -> 0 | D13: =B13+C13 -> 0 | E13: =SUMIF('明细分析表G11-2'!$B:$B,$A13,'明细分析表G11-2'!H:H) -> 0 | F13: =SUMIF('明细分析表G11-2'!$B:$B,$A13,'明细分析表G11-2'!I:I) -> 0 | G13: =E13+F13 -> 0 | H13: =D13-G13 -> 0 | I13: =IF(AND(D13=0,G13=0),0,IF(AND(D13=0,G13>0),1,H13/G13)) -> 0
A14: 债权投资处置收益 | B14: =SUMIF('明细分析表G11-2'!$B:$B,$A14,'明细分析表G11-2'!D:D) -> 0 | C14: =SUMIF('明细分析表G11-2'!$B:$B,$A14,'明细分析表G11-2'!E:E) -> 0 | D14: =B14+C14 -> 0 | E14: =SUMIF('明细分析表G11-2'!$B:$B,$A14,'明细分析表G11-2'!H:H) -> 0 | F14: =SUMIF('明细分析表G11-2'!$B:$B,$A14,'明细分析表G11-2'!I:I) -> 0 | G14: =E14+F14 -> 0 | H14: =D14-G14 -> 0 | I14: =IF(AND(D14=0,G14=0),0,IF(AND(D14=0,G14>0),1,H14/G14)) -> 0
A15: 其他债权投资处置收益 | B15: =SUMIF('明细分析表G11-2'!$B:$B,$A15,'明细分析表G11-2'!D:D) -> 0 | C15: =SUMIF('明细分析表G11-2'!$B:$B,$A15,'明细分析表G11-2'!E:E) -> 0 | D15: =B15+C15 -> 0 | E15: =SUMIF('明细分析表G11-2'!$B:$B,$A15,'明细分析表G11-2'!H:H) -> 0 | F15: =SUMIF('明细分析表G11-2'!$B:$B,$A15,'明细分析表G11-2'!I:I) -> 0 | G15: =E15+F15 -> 0 | H15: =D15-G15 -> 0 | I15: =IF(AND(D15=0,G15=0),0,IF(AND(D15=0,G15>0),1,H15/G15)) -> 0
A16: 持有其他非流动金融资产期间取得的投资收益 | B16: =SUMIF('明细分析表G11-2'!$B:$B,$A16,'明细分析表G11-2'!D:D) -> 0 | C16: =SUMIF('明细分析表G11-2'!$B:$B,$A16,'明细分析表G11-2'!E:E) -> 0 | D16: =B16+C16 -> 0 | E16: =SUMIF('明细分析表G11-2'!$B:$B,$A16,'明细分析表G11-2'!H:H) -> 0 | F16: =SUMIF('明细分析表G11-2'!$B:$B,$A16,'明细分析表G11-2'!I:I) -> 0 | G16: =E16+F16 -> 0 | H16: =D16-G16 -> 0 | I16: =IF(AND(D16=0,G16=0),0,IF(AND(D16=0,G16>0),1,H16/G16)) -> 0
A17: 处置其他非流动金融资产取得的投资收益 | B17: =SUMIF('明细分析表G11-2'!$B:$B,$A17,'明细分析表G11-2'!D:D) -> 0 | C17: =SUMIF('明细分析表G11-2'!$B:$B,$A17,'明细分析表G11-2'!E:E) -> 0 | D17: =B17+C17 -> 0 | E17: =SUMIF('明细分析表G11-2'!$B:$B,$A17,'明细分析表G11-2'!H:H) -> 0 | F17: =SUMIF('明细分析表G11-2'!$B:$B,$A17,'明细分析表G11-2'!I:I) -> 0 | G17: =E17+F17 -> 0 | H17: =D17-G17 -> 0 | I17: =IF(AND(D17=0,G17=0),0,IF(AND(D17=0,G17>0),1,H17/G17)) -> 0
A18: 取得控制权时，股权按公允价值重新计量产生的利得 | B18: =SUMIF('明细分析表G11-2'!$B:$B,$A18,'明细分析表G11-2'!D:D) -> 0 | C18: =SUMIF('明细分析表G11-2'!$B:$B,$A18,'明细分析表G11-2'!E:E) -> 0 | D18: =B18+C18 -> 0 | E18: =SUMIF('明细分析表G11-2'!$B:$B,$A18,'明细分析表G11-2'!H:H) -> 0 | F18: =SUMIF('明细分析表G11-2'!$B:$B,$A18,'明细分析表G11-2'!I:I) -> 0 | G18: =E18+F18 -> 0 | H18: =D18-G18 -> 0 | I18: =IF(AND(D18=0,G18=0),0,IF(AND(D18=0,G18>0),1,H18/G18)) -> 0
... A24: 其他 | B24: =SUMIF('明细分析表G11-2'!$B:$B,$A24,'明细分析表G11-2'!D:D) -> 0 | C24: =SUMIF('明细分析表G11-2'!$B:$B,$A24,'明细分析表G11-2'!E:E) -> 0 | D24: =B24+C24 -> 0 | E24: =SUMIF('明细分析表G11-2'!$B:$B,$A24,'明细分析表G11-2'!H:H) -> 0 | F24: =SUMIF('明细分析表G11-2'!$B:$B,$A24,'明细分析表G11-2'!I:I) -> 0 | G24: =E24+F24 -> 0 | H24: =D24-G24 -> 0 | I24: =IF(AND(D24=0,G24=0),0,IF(AND(D24=0,G24>0),1,H24/G24)) -> 0
A25: 合 计 | B25: =SUM(B7:B24) -> 0 | C25: =SUM(C7:C24) -> 0 | D25: =SUM(D7:D24) -> 0 | E25: =SUM(E7:E24) -> 0 | F25: =SUM(F7:F24) -> 0 | G25: =SUM(G7:G24) -> 0 | H25: =D25-G25 -> 0 | I25: =IF(AND(D25=0,G25=0),0,IF(AND(D25=0,G25>0),1,H25/G25)) -> 0
A26: 试算平衡表数
A27: 差异数 | D27: =D24-D26 -> 0 | G27: =G24-G26 -> 0
A29: 1、审计说明
A31: 2、审计结论
A33: 编制说明：
A34: 1、本科目核算企业确认的投资收益或投资损失。
A35: 2、企业（金融）债券投资持有期间取得的利息收入，也可在“利息收入”科目核算。
A36: 3.对于指定为以公允价值计量且其变动计入其他综合收益的非交易性权益工具投资，
A37: 除了获得的股利（属于投资成本收回部分的除外）计入当期损益外，
A38: 其他相关的利得和损失（包括汇兑损益）均应计入其他综合收益，且后续不得转入当期损益。
A39: 企业只有在同时符合下列条件时，才能确认股利收入并计入当期损益：
A40: ①企业收取股利的权利已经确立；
A41: ②股利相关的经济利益很可能流入企业；
A42: ③股利的金额能够可靠计量。
... A76: 参考结论：
A77: A、 | B77: 未见异常，可以确认。
A78: B、 | B78: 经审计调整后可确认。
A79: C、 | B79: 由于存在上述重大未调整事项（或审计范围受到限制无法获取充分、适当证据），不可确认。

Sheet 附注披露信息（上市公司）
A1: 致同会计师事务所
A2: 附注披露信息（上市公司）
A3: =底稿目录!A2 -> 被审计单位： | B3: =底稿目录!A4 -> 编制人： | C3: =底稿目录!A5 -> 编制日期： | D3: 索引： | E3: =底稿目录!F6 -> 0
A4: =底稿目录!A3 -> 会计期间：202X年度 | B4: =底稿目录!A6 -> 复核人： | C4: =底稿目录!A7 -> 复核日期： | D4: 页次：
A5: 附注披露信息
A6: 投资收益（注：以下不存在的项目可以删除）
A7: 项 目 | C7: 本期发生额 | D7: 上期发生额
A8: 权益法核算的长期股权投资收益 | C8: =SUMIF('审定表G11-1'!$A:$A,A8,'审定表G11-1'!$D:$D) -> 0 | D8: =SUMIF('审定表G11-1'!$A:$A,A8,'审定表G11-1'!$G:$G) -> 0
A9: 处置长期股权投资产生的投资收益 | C9: =SUMIF('审定表G11-1'!$A:$A,A9,'审定表G11-1'!$D:$D) -> 0 | D9: =SUMIF('审定表G11-1'!$A:$A,A9,'审定表G11-1'!$G:$G) -> 0
A10: 处置划分为持有待售资产的长期股权投资产生的投资收益 | C10: =SUMIF('审定表G11-1'!$A:$A,A10,'审定表G11-1'!$D:$D) -> 0 | D10: =SUMIF('审定表G11-1'!$A:$A,A10,'审定表G11-1'!$G:$G) -> 0
A11: 交易性金融资产持有期间的投资收益 | C11: =SUMIF('审定表G11-1'!$A:$A,A11,'审定表G11-1'!$D:$D) -> 0 | D11: =SUMIF('审定表G11-1'!$A:$A,A11,'审定表G11-1'!$G:$G) -> 0
A12: 债权投资持有期间的利息收入 | C12: =SUMIF('审定表G11-1'!$A:$A,A12,'审定表G11-1'!$D:$D) -> 0 | D12: =SUMIF('审定表G11-1'!$A:$A,A12,'审定表G11-1'!$G:$G) -> 0
A13: 其他债权投资持有期间的利息收入 | C13: =SUMIF('审定表G11-1'!$A:$A,A13,'审定表G11-1'!$D:$D) -> 0 | D13: =SUMIF('审定表G11-1'!$A:$A,A13,'审定表G11-1'!$G:$G) -> 0
A14: 其他权益工具投资的股利收入 | C14: =SUMIF('审定表G11-1'!$A:$A,A14,'审定表G11-1'!$D:$D) -> 0 | D14: =SUMIF('审定表G11-1'!$A:$A,A14,'审定表G11-1'!$G:$G) -> 0
A15: 处置交易性金融资产取得的投资收益 | C15: =SUMIF('审定表G11-1'!$A:$A,A15,'审定表G11-1'!$D:$D) -> 0 | D15: =SUMIF('审定表G11-1'!$A:$A,A15,'审定表G11-1'!$G:$G) -> 0
A16: 处置衍生金融资产取得的投资收益 | C16: =SUMIF('审定表G11-1'!$A:$A,A16,'审定表G11-1'!$D:$D) -> 0 | D16: =SUMIF('审定表G11-1'!$A:$A,A16,'审定表G11-1'!$G:$G) -> 0
A17: 处置债权投资取得的投资收益 | C17: =SUMIF('审定表G11-1'!$A:$A,A17,'审定表G11-1'!$D:$D) -> 0 | D17: =SUMIF('审定表G11-1'!$A:$A,A17,'审定表G11-1'!$G:$G) -> 0
A18: 取得控制权时，股权按公允价值重新计量产生的利得 | C18: =SUMIF('审定表G11-1'!$A:$A,A18,'审定表G11-1'!$D:$D) -> 0 | D18: =SUMIF('审定表G11-1'!$A:$A,A18,'审定表G11-1'!$G:$G) -> 0
A19: 丧失控制权后，剩余股权按公允价值重新计量产生的利得 | C19: =SUMIF('审定表G11-1'!$A:$A,A19,'审定表G11-1'!$D:$D) -> 0 | D19: =SUMIF('审定表G11-1'!$A:$A,A19,'审定表G11-1'!$G:$G) -> 0
A20: 其他 | C20: =SUMIF('审定表G11-1'!$A:$A,A20,'审定表G11-1'!$D:$D) -> 0 | D20: =SUMIF('审定表G11-1'!$A:$A,A20,'审定表G11-1'!$G:$G) -> 0
A21: 合 计 | C21: =SUM(C8:C20) -> 0 | D21: =SUM(D8:D20) -> 0
A22: 【提示：对于业务（包括子公司和分公司）处置的收益，无论直接出售还是先持有待售再出售，均整体计入投资收益，与业务相关的其他综合收益同时转入投资收益。】
A23: 注1：处置交易性金融资产取得的投资收益明细如下：【存在套期业务的，增加本注释内容，注意与附注九、3保持一致】
A24: 项 目 | B24: 本期发生额 | C24: 上期发生额
A25: 交易性权益工具投资-股票投资
A26: 交易性债务工具投资-债券投资
A27: 未指定为套期关系的衍生工具
A28: 其中：商品期货合约
A29: 远期外汇合约
A30: 有效套期保值的衍生工具
A31: 其中：公允价值套期
A33: 其他
A34: 合 计

Sheet 附注披露信息（国企）
A1: 致同会计师事务所
A2: 附注披露信息（国企）
A3: =底稿目录!A2 -> 被审计单位： | B3: =底稿目录!A4 -> 编制人： | C3: =底稿目录!A5 -> 编制日期： | D3: 索引：
A4: =底稿目录!A3 -> 会计期间：202X年度 | B4: =底稿目录!A6 -> 复核人： | C4: =底稿目录!A7 -> 复核日期： | D4: 页次：
A5: 附注披露信息
A6: （1）投资收益明细情况
A7: 项 目 | C7: 本期发生额 | D7: 上期发生额
A8: 权益法核算的长期股权投资收益 | C8: =SUMIF('审定表G11-1'!$A:$A,$F8,'审定表G11-1'!$D:$D) -> 0 | D8: =SUMIF('审定表G11-1'!$A:$A,$F8,'审定表G11-1'!$G:$G) -> 0
A9: 处置长期股权投资产生的投资收益 | C9: =SUMIF('审定表G11-1'!$A:$A,$F9,'审定表G11-1'!$D:$D) -> 0 | D9: =SUMIF('审定表G11-1'!$A:$A,$F9,'审定表G11-1'!$G:$G) -> 0
A10: 处置划分为持有待售资产的长期股权投资产生的投资收益 | C10: =SUMIF('审定表G11-1'!$A:$A,$F10,'审定表G11-1'!$D:$D) -> 0 | D10: =SUMIF('审定表G11-1'!$A:$A,$F10,'审定表G11-1'!$G:$G) -> 0
A11: 交易性金融资产持有期间取得的投资收益 | C11: =SUMIF('审定表G11-1'!$A:$A,$F11,'审定表G11-1'!$D:$D) -> 0 | D11: =SUMIF('审定表G11-1'!$A:$A,$F11,'审定表G11-1'!$G:$G) -> 0
A12: 处置交易性金融资产取得的投资收益 | C12: =SUMIF('审定表G11-1'!$A:$A,$F12,'审定表G11-1'!$D:$D) -> 0 | D12: =SUMIF('审定表G11-1'!$A:$A,$F12,'审定表G11-1'!$G:$G) -> 0
A13: 债权投资持有期间的利息收益 | C13: =SUMIF('审定表G11-1'!$A:$A,$F13,'审定表G11-1'!$D:$D) -> 0 | D13: =SUMIF('审定表G11-1'!$A:$A,$F13,'审定表G11-1'!$G:$G) -> 0
A14: 其他债权投资持有期间的利息收益 | C14: =SUMIF('审定表G11-1'!$A:$A,$F14,'审定表G11-1'!$D:$D) -> 0 | D14: =SUMIF('审定表G11-1'!$A:$A,$F14,'审定表G11-1'!$G:$G) -> 0
A15: 债权投资处置收益 | C15: =SUMIF('审定表G11-1'!$A:$A,$F15,'审定表G11-1'!$D:$D) -> 0 | D15: =SUMIF('审定表G11-1'!$A:$A,$F15,'审定表G11-1'!$G:$G) -> 0
A16: 其他债权投资处置收益 | C16: =SUMIF('审定表G11-1'!$A:$A,$F16,'审定表G11-1'!$D:$D) -> 0 | D16: =SUMIF('审定表G11-1'!$A:$A,$F16,'审定表G11-1'!$G:$G) -> 0
A17: 持有其他非流动金融资产期间取得的投资收益 | C17: =SUMIF('审定表G11-1'!$A:$A,$F17,'审定表G11-1'!$D:$D) -> 0 | D17: =SUMIF('审定表G11-1'!$A:$A,$F17,'审定表G11-1'!$G:$G) -> 0
A18: 处置其他非流动金融资产取得的投资收益 | C18: =SUMIF('审定表G11-1'!$A:$A,$F18,'审定表G11-1'!$D:$D) -> 0 | D18: =SUMIF('审定表G11-1'!$A:$A,$F18,'审定表G11-1'!$G:$G) -> 0
A19: 取得控制权时，股权按公允价值重新计量产生的利得 | C19: =SUMIF('审定表G11-1'!$A:$A,$F19,'审定表G11-1'!$D:$D) -> 0 | D19: =SUMIF('审定表G11-1'!$A:$A,$F19,'审定表G11-1'!$G:$G) -> 0
... A24: 其他 | C24: =SUMIF('审定表G11-1'!$A:$A,$F24,'审定表G11-1'!$D:$D) -> 0 | D24: =SUMIF('审定表G11-1'!$A:$A,$F24,'审定表G11-1'!$G:$G) -> 0
A25: 合 计 | C25: =C8+C9+C10+SUM(C13:C24) -> 0 | D25: =SUM(D8:D12)+D19+D20+D24 -> 0
A26: 注：若投资收益汇回有重大限制的，应予以说明。若不存在此类重大限制，也应做出说明。

Sheet 明细分析表G11-2
A1: 致同会计师事务所
A2: 投资收益明细分析表
A3: =底稿目录!A2 -> 被审计单位： | E3: =底稿目录!A4 -> 编制人： | H3: =底稿目录!A5 -> 编制日期： | L3: 索引号： | M3: =底稿目录!F8 -> G11-2
A4: =底稿目录!A3 -> 会计期间：202X年度 | E4: =底稿目录!A6 -> 复核人： | H4: =底稿目录!A7 -> 复核日期： | L4: 页 次：
A5: 一、审计目标
A6: 1.利润表中记录的投资收益已发生，且与被审计单位有关，已记录于恰当的账户；2.所有应记录的投资收益均已记录，所有应当包括在财务报表中的相关披露均已包括；
A7: 3.与投资收益有关的金额及其他数据已恰当记录，相关披露已得到恰当计量和描述
A8: 二、审计过程
A9: 序号 | B9: 项目 | C9: 被投资单位 | D9: 本期未审数 | E9: 本期调整 | F9: 本期审定数 | G9: 各项目占比 | H9: 上年未审数 | I9: 上期调整 | J9: 上年审定数 | K9: 各项目占比 | L9: 变动额 | M9: 变动原因/索引号
A10: 1 | B10: 权益法核算的长期股权投资收益 | F10: =D10+E10 -> 0 | G10: =IF(F10=0,0,F10/$F$31) -> 0 | J10: =H10+I10 -> 0 | K10: =IF(J10=0,0,J10/$J$31) -> 0 | L10: =F10-J10 -> 0
A11: 2 | B11: 权益法核算的长期股权投资收益 | F11: =D11+E11 -> 0 | G11: =IF(F11=0,0,F11/$F$31) -> 0 | J11: =H11+I11 -> 0 | K11: =IF(J11=0,0,J11/$J$31) -> 0 | L11: =F11-J11 -> 0
A12: 3 | B12: 处置长期股权投资产生的投资收益 | F12: =D12+E12 -> 0 | G12: =IF(F12=0,0,F12/$F$31) -> 0 | J12: =H12+I12 -> 0 | K12: =IF(J12=0,0,J12/$J$31) -> 0 | L12: =F12-J12 -> 0
A13: 4 | B13: 交易性金融资产持有期间的投资收益 | F13: =D13+E13 -> 0 | G13: =IF(F13=0,0,F13/$F$31) -> 0 | J13: =H13+I13 -> 0 | K13: =IF(J13=0,0,J13/$J$31) -> 0 | L13: =F13-J13 -> 0
A14: 5 | B14: 交易性金融资产持有期间的投资收益 | F14: =D14+E14 -> 0 | G14: =IF(F14=0,0,F14/$F$31) -> 0 | J14: =H14+I14 -> 0 | K14: =IF(J14=0,0,J14/$J$31) -> 0 | L14: =F14-J14 -> 0
A15: 6 | B15: 处置交易性金融资产取得的投资收益 | F15: =D15+E15 -> 0 | G15: =IF(F15=0,0,F15/$F$31) -> 0 | J15: =H15+I15 -> 0 | K15: =IF(J15=0,0,J15/$J$31) -> 0 | L15: =F15-J15 -> 0
A16: 7 | B16: 处置交易性金融资产取得的投资收益 | F16: =D16+E16 -> 0 | G16: =IF(F16=0,0,F16/$F$31) -> 0 | J16: =H16+I16 -> 0 | K16: =IF(J16=0,0,J16/$J$31) -> 0 | L16: =F16-J16 -> 0
A17: 8 | B17: 债权投资持有期间的利息收益 | F17: =D17+E17 -> 0 | G17: =IF(F17=0,0,F17/$F$31) -> 0 | J17: =H17+I17 -> 0 | K17: =IF(J17=0,0,J17/$J$31) -> 0 | L17: =F17-J17 -> 0
A18: 9 | B18: 其他债权投资持有期间的利息收益 | F18: =D18+E18 -> 0 | G18: =IF(F18=0,0,F18/$F$31) -> 0 | J18: =H18+I18 -> 0 | K18: =IF(J18=0,0,J18/$J$31) -> 0 | L18: =F18-J18 -> 0
A19: 10 | B19: 债权投资处置收益 | F19: =D19+E19 -> 0 | G19: =IF(F19=0,0,F19/$F$31) -> 0 | J19: =H19+I19 -> 0 | K19: =IF(J19=0,0,J19/$J$31) -> 0 | L19: =F19-J19 -> 0
A20: 11 | B20: 其他债权投资持有期间的利息收益 | F20: =D20+E20 -> 0 | G20: =IF(F20=0,0,F20/$F$31) -> 0 | J20: =H20+I20 -> 0 | K20: =IF(J20=0,0,J20/$J$31) -> 0 | L20: =F20-J20 -> 0
A21: 12 | B21: 持有其他非流动金融资产期间取得的投资收益 | F21: =D21+E21 -> 0 | G21: =IF(F21=0,0,F21/$F$31) -> 0 | J21: =H21+I21 -> 0 | K21: =IF(J21=0,0,J21/$J$31) -> 0 | L21: =F21-J21 -> 0
... A30: 21 | B30: 其他 | F30: =D30+E30 -> 0 | G30: =IF(F30=0,0,F30/$F$31) -> 0 | J30: =H30+I30 -> 0 | K30: =IF(J30=0,0,J30/$J$31) -> 0 | L30: =F30-J30 -> 0
A31: 合计 | D31: =SUM(D10:D30) -> 0 | E31: =SUM(E10:E30) -> 0 | F31: =SUM(F10:F30) -> 0 | G31: =IF(F31=0,0,F31/$F$31) -> 0 | H31: =SUM(H10:H30) -> 0 | I31: =SUM(I10:I30) -> 0 | J31: =SUM(J10:J30) -> 0 | K31: =IF(J31=0,0,J31/$J$31) -> 0 | L31: =SUM(L10:L30) -> 0
A32: 本年利润总额 | E32: -- | G32: -- | I32: -- | K32: -- | L32: --
A33: 三、审计说明：
A34: 1、 | B34: 对变动比率在20%以上的项目实施的审计程序（记录变动内容、原因，分析其合理性，如不合理，需进一步核实确认）
A35: 四、审计结论：
A37: 编制说明：
A38: 1.审计说明可以概述:(1)程序的测试情况、结果;(2)拟调整事项及其调整分录、未调整事项及其影响，审计范围受到限制情况及其影响。
A39: 2.审计结论可参考:A、未见异常。 B、除上述重大不符事项应当作为调整事项予以调整外，其余未见异常。由于存在以下重大未调整事项(或审计范围受到限制无法获取充分、适当证据)，不可确认。

Sheet 调整分录汇总G11-3
A1: 致同会计师事务所
A2: 投资收益调整分录汇总表
A3: =底稿目录!A2 -> 被审计单位： | D3: =底稿目录!A4 -> 编制人： | G3: =底稿目录!A5 -> 编制日期： | I3: 索引号： | J3: =底稿目录!F9 -> G11-3
A4: =底稿目录!A3 -> 会计期间：202X年度 | D4: =底稿目录!A6 -> 复核人： | G4: =底稿目录!A7 -> 复核日期： | I4: 页 次：1
A5: 调整事项说明 | B5: 类别（报表调整/账项调整/其他） | C5: 报表项目 | D5: 科目名称 | E5: 附注项目 | F5: …… | G5: 借方调整金额 | H5: 贷方调整金额 | I5: 索引 | J5: 备注

Sheet 收益率分析表G11-4
A1: 致同会计师事务所
A2: 投资收益分析-投资收益率
A3: =底稿目录!A2 -> 被审计单位： | C3: =底稿目录!A4 -> 编制人： | F3: =底稿目录!A5 -> 编制日期： | H3: 索引号： | I3: =底稿目录!F10 -> G11-4
A4: =底稿目录!A3 -> 会计期间：202X年度 | C4: =底稿目录!A6 -> 复核人： | F4: =底稿目录!A7 -> 复核日期： | H4: 页 次：
A5: 一、审计目标： | C5: 与投资收益有关的金额及其他数据已恰当记录，相关披露已得到恰当计量和描述
A6: 二、审计过程
A7: （一）计算变动比率
A8: 项目名称 | C8: 本期数 | F8: 上期数 | I8: 变动⑦=③-⑥
C9: 发生额① | D9: 平均投资② | E9: 比率③=①/② | F9: 审定数④ | G9: 平均投资⑤ | H9: 比率⑥=④/⑤
A10: 权益法核算的长期股权投资收益 | C10: ='审定表G11-1'!D7 -> 0 | E10: =IF(D10=0,0,C10/D10) -> 0 | F10: ='审定表G11-1'!G7 -> 0 | H10: =IF(G10=0,0,F10/G10) -> 0 | I10: =E10-H10 -> 0
A11: 处置长期股权投资产生的投资收益 | C11: ='审定表G11-1'!D8 -> 0 | E11: =IF(D11=0,0,C11/D11) -> 0 | F11: ='审定表G11-1'!G8 -> 0 | H11: =IF(G11=0,0,F11/G11) -> 0 | I11: =E11-H11 -> 0
A12: 处置划分为持有待售资产的长期股权投资产生的投资收益 | C12: ='审定表G11-1'!D9 -> 0 | E12: =IF(D12=0,0,C12/D12) -> 0 | F12: ='审定表G11-1'!G9 -> 0 | H12: =IF(G12=0,0,F12/G12) -> 0 | I12: =E12-H12 -> 0
A13: 以公允价值计量且其变动计入当期损益的金融资产持有期间取得的投资收益 | C13: ='审定表G11-1'!D10 -> 0 | E13: =IF(D13=0,0,C13/D13) -> 0 | F13: ='审定表G11-1'!G10 -> 0 | H13: =IF(G13=0,0,F13/G13) -> 0 | I13: =E13-H13 -> 0
A14: 处置以公允价值计量且其变动计入当期损益的金融资产取得的投资收益 | C14: ='审定表G11-1'!D11 -> 0 | E14: =IF(D14=0,0,C14/D14) -> 0 | F14: ='审定表G11-1'!G11 -> 0 | H14: =IF(G14=0,0,F14/G14) -> 0 | I14: =E14-H14 -> 0
A15: 债权投资持有期间的利息收益 | C15: ='审定表G11-1'!D12 -> 0 | E15: =IF(D15=0,0,C15/D15) -> 0 | F15: ='审定表G11-1'!G12 -> 0 | H15: =IF(G15=0,0,F15/G15) -> 0 | I15: =E15-H15 -> 0
A16: 其他债权投资持有期间的利息收益 | C16: ='审定表G11-1'!D13 -> 0 | E16: =IF(D16=0,0,C16/D16) -> 0 | F16: ='审定表G11-1'!G13 -> 0 | H16: =IF(G16=0,0,F16/G16) -> 0 | I16: =E16-H16 -> 0
A17: 债权投资处置收益 | C17: ='审定表G11-1'!D14 -> 0 | E17: =IF(D17=0,0,C17/D17) -> 0 | F17: ='审定表G11-1'!G14 -> 0 | H17: =IF(G17=0,0,F17/G17) -> 0 | I17: =E17-H17 -> 0
A18: 其他债权投资处置收益 | C18: ='审定表G11-1'!D15 -> 0 | E18: =IF(D18=0,0,C18/D18) -> 0 | F18: ='审定表G11-1'!G15 -> 0 | H18: =IF(G18=0,0,F18/G18) -> 0 | I18: =E18-H18 -> 0
A19: 持有其他非流动金融资产期间取得的投资收益 | C19: ='审定表G11-1'!D16 -> 0 | E19: =IF(D19=0,0,C19/D19) -> 0 | F19: ='审定表G11-1'!G16 -> 0 | H19: =IF(G19=0,0,F19/G19) -> 0 | I19: =E19-H19 -> 0
A20: 处置其他非流动金融资产取得的投资收益 | C20: ='审定表G11-1'!D17 -> 0 | E20: =IF(D20=0,0,C20/D20) -> 0 | F20: ='审定表G11-1'!G17 -> 0 | H20: =IF(G20=0,0,F20/G20) -> 0 | I20: =E20-H20 -> 0
A21: 取得控制权时，股权按公允价值重新计量产生的利得 | C21: ='审定表G11-1'!D18 -> 0 | E21: =IF(D21=0,0,C21/D21) -> 0 | F21: ='审定表G11-1'!G18 -> 0 | H21: =IF(G21=0,0,F21/G21) -> 0 | I21: =E21-H21 -> 0
... A23: 持有其他权益工具投资期间取得的股利收入 | C23: ='审定表G11-1'!D20 -> 0 | E23: =IF(D23=0,0,C23/D23) -> 0 | F23: ='审定表G11-1'!G20 -> 0 | H23: =IF(G23=0,0,F23/G23) -> 0 | I23: =E23-H23 -> 0
A24: 其他 | C24: ='审定表G11-1'!D24 -> 0 | E24: =IF(D24=0,0,C24/D24) -> 0 | F24: ='审定表G11-1'!G24 -> 0 | H24: =IF(G24=0,0,F24/G24) -> 0 | I24: =E24-H24 -> 0
A25: 合计 | C25: =SUM(C10:C24) -> 0 | D25: =SUM(D10:D24) -> 0 | E25: =IF(D25=0,0,C25/D25) -> 0 | F25: =SUM(F10:F24) -> 0 | G25: =SUM(G10:G24) -> 0 | H25: =IF(G25=0,0,F25/G25) -> 0 | I25: =E25-H25 -> 0
A26: （二）投资收益率分析实施的审计程序（比较两年度的投资收益率，分析投资获利能力。如果被审计单位投资所占比重较大，可取得市场的平均投资收益率，并进行比较分析）
A28: 三、审计说明：
A30: 四、审计结论：

Sheet 凭证检查表G11-5
A1: 致同会计师事务所
A2: 投资收益凭证检查表
A3: =底稿目录!A2 -> 被审计单位： | D3: =底稿目录!A4 -> 编制人： | F3: =底稿目录!A5 -> 编制日期： | O3: 索引号： | P3: =底稿目录!F11 -> G11-5
A4: =底稿目录!A3 -> 会计期间：202X年度 | D4: =底稿目录!A6 -> 复核人： | F4: =底稿目录!A7 -> 复核日期： | O4: 页 次：
A5: 一、审计目标：
A6: 1.利润表中记录的投资收益已发生，且与被审计单位有关，已记录于恰当的账户；2.所有应记录的投资收益均已记录，所有应当包括在财务报表中的相关披露均已包括；
A7: 3.与投资收益有关的金额及其他数据已恰当记录，相关披露已得到恰当计量和描述
A8: 二、样本选取方法与规模：
A9: 测试总体： | B9: 如投资收益本期发生额所有凭证共XX笔金额XX | D9: 特定样本： | E9: XX金额以上（大额）、关联方/关联交易形成的款项、XX异常款项全部测试，共XX笔；
A10: 抽样总体： | B10: 测试总体扣除特定样本以外的样本，共XX笔、金额XX | D10: 确定的抽样样本量： | E10: 抽取XX笔 | F10: （如果使用了样本计算器计算样本量，样本量计算过程见<XX>底稿）
A11: 抽样方法： | B11: 随机选样/系统选样/货币单元抽样/随意选样 | D11: 抽样过程： | E11: 使用IDEA（XX抽样工具）选择XX数量、金额XX的样本进行测试，抽样工具中的样本选择过程和结果见<XX>底稿
A12: 三、测试：
A13: 测试内容说明：1.原始凭证是否齐全； 2.有适当的授权批准；3.投资收益金额计算正确；4.会计期间划分恰当；5、会计处理正确；6.……
A14: 记账凭证 | G14: 支持性文件 | I14: 核对内容 | N14: 索引号 | O14: 是否异常 | P14: 备注说明
A15: 日期 | B15: 凭证编号 | C15: 业务内容 | D15: 对方科目 | E15: 对方明细科目 | F15: 贷方金额 | I15: 1 | J15: 2 | K15: 3 | L15: 4 | M15: 5
A27: 合计 | F27: =SUM(F16:F26) -> 0
A28: 本期发生额 | F28: ='审定表G11-1'!D25 -> 0
A29: 检查比例 | F29: =F27/F28 -> #DIV/0!
A30: 四、审计说明：
A33: 五、审计结论：
A39: 编制说明：
A40: 1、概述：（1）程序的测试情况、结果；
A41: （2）拟调整事项及其调整分录、未调整事项及其影响，审计范围受到限制情况及其影响。
A42: 参考结论：
A43: A、 | B43: 未见异常。
A44: B、 | B44: 除以下重大不符事项应当作为调整事项予以调整外，其余未见异常。
A45: C、 | B45: 由于存在以下重大未调整事项（或审计范围受到限制无法获取充分、适当证据），不可确认。
