Workbook
Name _.dbf: #REF!
Name _00510: #REF!
Name _1、: #REF!
Name _1、受本循环影响的相关交易和账户余额: #REF!
Name _13: #REF!
Name _1w6_: #REF!
Name _1固定资产数据库_筛选打印: #REF!
Name _2、主要业务活动: #REF!
Name _2、注册会计师通常应在本循环中了解与上述业务活动相关的内部控制_如果计划在其他业务循环中对上述: #REF!
Name _2其他资产_开办费除外_明细表: #REF!
Name _3余额表_一级_.dbf: #REF!
Name _DAT1: #REF!
Name _DAT10: #REF!
Name _DAT11: #REF!
Name _DAT2: #REF!
Name _DAT3: #REF!
Name _DAT4: #REF!
Name _DAT5: #REF!
Name _DAT6: #REF!
Name _DAT7: #REF!
Name _DAT8: #REF!
Name _DAT9: #REF!
Name _YE1: #REF!
Name _YS1: #REF!
Name _YS2: '[1]YS02-02'!#REF!
Name a: #REF!
Name a1c1: #REF!,#REF!
Name aa: #REF!
Name aaa: #REF!
Name agmmt: #REF!
Name agmt: #REF!
Name agmt1: #REF!
Name al: #REF!
Name avg_days: [2]Sheet3!$A$2
Name a暗暗: [3]企业表一!$F$20
Name b: #REF!
Name BD: #REF!
Name beg_day: #REF!
Name beg_day1: #REF!
Name CarryKnown: #REF!
Name CarryKnownTable: #REF!
Name CarryLikely: #REF!
Name CarryLikelyTable: #REF!
Name Carryover_Effect_of_Prior_Year: #REF!
Name CarryoverTitle: #REF!
Name CC_Instruction: #REF!
Name CE_CarryKnownProtection: #REF!
Name CE_CarryKnownTable: #REF!
Name CE_CarryLikely1Protection: #REF!
Name CE_CarryLikely1Table: #REF!
Name CE_CarryLikely2Protection: #REF!
Name CE_CarryLikely2Table: #REF!
Name CE_CarryTaxable: #REF!
Name CE_Desc: #REF!
Name CE_Income: #REF!
Name CE_KeepFormat: #REF!
Name CE_KnownChange: #REF!
Name CE_KnownFormulaProtection: #REF!
Name CE_KnownImpact: #REF!
Name CE_Likely1Change: #REF!

Sheet 底稿目录
A1: 底稿开列时，可先在以下单元格填写有关内容，以便其他底稿引用有关数据：
A2: 被审计单位：
A3: 截止日：202X年12月31日 | D3: 序号 | E3: 内容 | F3: 索引号
A4: 编制人： | E4: 应收股利实质性程序表 | F4: G3A
A5: 编制日期： | D5: 1 | E5: 审定表 | F5: G3-1
A6: 复核人： | D6: 2 | E6: 附注披露信息（上市公司）
A7: 复核日期： | D7: 3 | E7: 附注披露信息（国企）
D8: 4 | E8: 明细表 | F8: G3-2
A9: 关于工作底稿与审计程序索引号对应的说明 | D9: 5 | E9: 调整分录汇总 | F9: G3-3
A10: 1.编制的审计工作底稿应与审计程序对应。审计项目组应根据被审计单位实际情况和风险评估情况在实质性程序表中裁剪、修改或增加审计程序，根据实际执行的审计程序完成相应审计工作底稿，编制的工作底稿中应按自然顺序依次编制索引号，并通过唯一的索引号将与实质性程序表中的程序对应关联（即将工作底稿的索引号填入实质性程序表中的底稿索引号列）。 | D10: 6 | E10: 测算及检查表 | F10: G3-4
D11: 7 | E11: 长期未收回款项检查表 | F11: G3-5
A14: 2.获取的支持性证据应与审计底稿或程序对应。审计项目组在完成底稿时获取的支持性证据应根据底稿索引号编制下一级按自然顺序排序的索引号（如D1-2-1、D1-2-2、……），并在底稿中说明引用的支持性证据、关联索引号。
A17: 3.工作底稿索引号的编码规则：实质性程序索引号按循环从“D”到“N”,循环内账户以顺序号排列，模板中底稿索引号按账户顺序+自然数顺序（即模板中索引号按二级自然顺序排列，如D1-1、D1-2、D1-3、……D1-N）。

Sheet 应收股利实质性程序表G3A
A1: 致同会计师事务所
A2: 应收股利实质性程序表
A3: =底稿目录!A2 -> 被审计单位： | C3: =底稿目录!A4 -> 编制人： | F3: =底稿目录!A5 -> 编制日期： | H3: 索引号： | I3: =底稿目录!F4 -> G3A
A4: =底稿目录!A3 -> 截止日：202X年12月31日 | C4: =底稿目录!A6 -> 复核人： | F4: =底稿目录!A7 -> 复核日期： | H4: 页 次：
A5: 一、本账户涉及的科目
A6: 应收股利
A7: 二、审计目标与认定的对应关系
A8: 审计目标 | G8: 财务报表的认定
A9: A. 资产负债表中记录的应收股利是存在的，且已记录于恰当的账户 | G9: 存在
A10: B. 所有应记录的应收股利均已记录，所有应当包括在财务报表中的相关披露均已包括 | G10: 完整性
A11: C. 记录的应收股利由被审计单位拥有或控制 | G11: 权利和义务
A12: D. 应收股利以恰当的金额包括在财务报表中，与之相关的计价或分摊调整已恰当记录，相关披露已得到恰当计量和描述 | G12: 准确性、计价和分摊
A13: E. 应收股利已被恰当地汇总或分解且表述清楚，相关披露在按照企业会计准则的编制基础下是相关的、可理解的 | G13: 列报
A14: 三、计划实施的实质性程序
A15: 序号 | B15: 审计程序 | C15: 程序分类 | D15: 财务报表的认定 | I15: 底稿索引号
D16: 存在 | E16: 完整性 | F16: 权利和 义务 | G16: 准确性、计价和分摊 | H16: 列报 | J16: 根据被审计单位实际情况和风险评估情况裁剪、修改或增加审计程序
A17: 1 | B17: 获取或编制应收股利的明细表，完成以下工作，并编制审定表 （1）复核加计是否正确，与总账、明细账合计数核对是否相符，期初余额与上期审定期末余额是否相符； （2）与上年明细项目进行比较，确定与上年分类相同； （3）检查非记账本位币计量的应收股利的折算汇率及折算是否正确。 | C17: 常规★ | D17: √ | E17: √ | G17: √ | I17: G3-1 /G3-2
A18: 2 | B18: 在使用手工编制、自定义信息报告、系统生成的非固定格式报告等由被审计单位生成的信息时，测试有关信息准确性和完整性，并考虑针对编制和维护由被审计单位生成的信息的相关控制实施控制测试，以评价该信息是否能够为实现审计目的提供基础。 | C18: 常规★ | E18: √ | G18: √ | I18: T1 /G0-2 /
A19: 3 | B19: 对期初余额的审计，取得应收股利期初余额明细表复核加计是否正确，与总账、明细账合计数是否相符，检查上期应收股利在本期收回情况，函证期初余额以及其他必要追加的审计程序。（适用于首次承接） | C19: 备选 | D19: √ | E19: √ | F19: √ | G19: √
A20: 4 | B20: 关注会计政策、会计估计合理性、一贯性。关注其是否利用会计政策和会计估计及其变更操纵利润。 | C20: 常规★ | D20: √ | E20: √ | G20: √ | I20: G3-1 /G3-2
A21: 5 | B21: 对本期应收股利的增减变动，追查至相应的原始凭证及支持文件，检查其是否经过授权审批，确认是否符合合同协议条款的规定。 | C21: 常规★ | D21: √ | F21: √ | G21: √ | I21: G3-1 /G3-2
A22: 6 | B22: 检查期后收款情况： （1）检查至审计时已收回金额较大的款项，如核对收款凭证、银行对账单、股利分配方案等； （2）对长期未收回且金额较大的应收股利，询问被审计单位管理人员及相关职员或者查询被投资单位的情况，确定应收股利的可收回性。必要时，向被投资单位函证股利支付情况，复核并记录函证结果。 | C22: 常规★ | D22: √ | E22: √ | G22: √ | I22: G3-2
A23: 7 | B23: 针对坏账准备，执行下列核对程序： （1）对于坏账准备的账面金额、本期审计调整金额、审定金额分别与坏账准备账面、本期审计调整、审定金额勾稽一致； （2）确定应收股利是否已计提充足的坏账准备； （3）取得上述经账龄复核后的账龄明细表，并取得被审计单位的坏账准备计算表，复核加计正确，与总账数、明细账合计数核对相符； （4）重新计算应计提的坏账准备，与客户已记录的坏账准备进行比较，调整差异。特别关注大额坏账准备转回是否合理； （5）根据账龄分析表中，选取金额大于的账户，逾期超过（）天账户，以及其他认为必要的账户。针对所选取的账户，与授信部门经理或其他负责人员讨论其可收回性，并复核往来函件或其他相关信息，以支持被审计单位就此作出的声明； （6）实际发生坏账损失的，检查核销依据是否符合有关规定，会计处理是否正确。已经确认并转销的坏账重新收回的，检查其会计处理是否正确。 | C23: 常规★ | G23: √
A24: 8 | B24: 必要时，向相关机构发函，并确定是否存在变现限制，同时记录函证过程： （1）以积极方式进行函证，设计询证函、发函前核实被函证单位信息； （2）注册会计师独立收发询证函； （3）编制函证结果汇总表，检查发函、回函物流信息和轨迹、比对回函印章和签字等以核实回函的真实性，检查回函是否相符，对不符事项查明原因确定是否存在错报； （4）如果未收到回函，应当考虑与被询证者联系，要求对方作出回应或再次寄发询证函，无法收到的回函实施替代程序； （5）如果管理层不允许寄发询证函的，询问管理层不允许寄发的原因，并就其原因的正当、合理性收集证据；考虑实施替代审计程序以获取相关、可靠的审计证据； （6）如果管理层不允许寄发询证函的原因不合理、或者认为回函不可靠，评价对评估的重大错报风险以及其他审计程序的性质、时间安排和范围的影响，并确定其对审计工作和审计意见的影响。 | C24: 备选 | D24: √ | E24: √ | F24: √ | G24: √ | I24: G0
A25: 10 | B25: 根据评估的舞弊风险等因素增加的审计程序。 | C25: IPO/上市/新三板/重组/舞弊应对
A26: 11 | B26: 检查应收股利是否已按企业会计准则或其他适用的规定在财务报表中做出恰当列报和披露。 | C26: 常规★ | H26: √ | I26: A1-1/A1-15 /A1-16

Sheet 审定表G3-1
A1: 致同会计师事务所
A2: 应收股利审定表
A3: =底稿目录!A2 -> 被审计单位： | D3: =底稿目录!A4 -> 编制人： | H3: =底稿目录!A5 -> 编制日期： | M3: 索引号： | N3: =底稿目录!F5 -> G3-1
A4: =底稿目录!A3 -> 截止日：202X年12月31日 | D4: =底稿目录!A6 -> 复核人： | H4: =底稿目录!A7 -> 复核日期： | M4: 页 次：
A5: 项目 | B5: 期初数 | F5: 期末数 | J5: 本期未审数与上期 未审数的比较 | L5: 本期审定数与上期 审定数的比较 | N5: 索引
B6: 未审数 | C6: 账项调整 | D6: 重分类调整 | E6: 审定数 | F6: 未审数 | G6: 账项调整 | H6: 重分类调整 | I6: 审定数 | J6: 变动额 | K6: 变动率 | L6: 变动额 | M6: 变动率
A7: 一、账面余额
A8: 账龄一年以内的应收股利 | B8: ='明细表G3-2'!C21 -> 0 | C8: ='明细表G3-2'!G21 -> 0 | D8: ='明细表G3-2'!H21 -> 0 | E8: =B8+C8+D8 -> 0 | F8: ='明细表G3-2'!F21 -> 0 | G8: ='明细表G3-2'!G21+'明细表G3-2'!I21-'明细表G3-2'!J21 -> 0 | H8: ='明细表G3-2'!H21+'明细表G3-2'!K21-'明细表G3-2'!L21 -> 0 | I8: =F8+G8+H8 -> 0 | J8: =F8-B8 -> 0 | K8: =IF(AND(B8=0,J8=0),0,IF(AND(B8=0,J8>0),1,J8/B8)) -> 0 | L8: =I8-E8 -> 0 | M8: =IF(AND(E8=0,L8=0),0,IF(AND(E8=0,L8>0),1,L8/E8)) -> 0
A9: 账龄一年以上的应收股利 | B9: ='明细表G3-2'!C29 -> 0 | C9: ='明细表G3-2'!G29 -> 0 | D9: ='明细表G3-2'!H29 -> 0 | E9: =B9+C9+D9 -> 0 | F9: ='明细表G3-2'!F29 -> 0 | G9: ='明细表G3-2'!G29+'明细表G3-2'!I29-'明细表G3-2'!J29 -> 0 | H9: ='明细表G3-2'!H29+'明细表G3-2'!K29-'明细表G3-2'!L29 -> 0 | I9: =F9+G9+H9 -> 0 | J9: =F9-B9 -> 0 | K9: =IF(AND(B9=0,J9=0),0,IF(AND(B9=0,J9>0),1,J9/B9)) -> 0 | L9: =I9-E9 -> 0 | M9: =IF(AND(E9=0,L9=0),0,IF(AND(E9=0,L9>0),1,L9/E9)) -> 0
A10: 合计 | B10: =SUM(B8:B9) -> 0 | C10: =SUM(C8:C9) -> 0 | D10: =SUM(D8:D9) -> 0 | E10: =SUM(E8:E9) -> 0 | F10: =SUM(F8:F9) -> 0 | G10: =SUM(G8:G9) -> 0 | H10: =SUM(H8:H9) -> 0 | I10: =SUM(I8:I9) -> 0 | J10: =F10-B10 -> 0 | K10: =IF(AND(B10=0,J10=0),0,IF(AND(B10=0,J10>0),1,J10/B10)) -> 0 | L10: =I10-E10 -> 0 | M10: =IF(AND(E10=0,L10=0),0,IF(AND(E10=0,L10>0),1,L10/E10)) -> 0
A11: 二、减值准备
A12: =A8 -> 账龄一年以内的应收股利 | B12: ='明细表G3-2'!Q21 -> 0 | C12: ='明细表G3-2'!U21 -> 0 | D12: ='明细表G3-2'!V21 -> 0 | E12: =B12+C12+D12 -> 0 | F12: ='明细表G3-2'!T21 -> 0 | G12: ='明细表G3-2'!U21+'明细表G3-2'!W21-'明细表G3-2'!X21 -> 0 | H12: ='明细表G3-2'!V21+'明细表G3-2'!Y21-'明细表G3-2'!Z21 -> 0 | I12: =F12+G12+H12 -> 0 | J12: =F12-B12 -> 0 | K12: =IF(AND(B12=0,J12=0),0,IF(AND(B12=0,J12>0),1,J12/B12)) -> 0 | L12: =I12-E12 -> 0 | M12: =IF(AND(E12=0,L12=0),0,IF(AND(E12=0,L12>0),1,L12/E12)) -> 0
A13: =A9 -> 账龄一年以上的应收股利 | B13: ='明细表G3-2'!Q29 -> 0 | C13: ='明细表G3-2'!U29 -> 0 | D13: ='明细表G3-2'!V29 -> 0 | E13: =B13+C13+D13 -> 0 | F13: ='明细表G3-2'!T29 -> 0 | G13: ='明细表G3-2'!U29+'明细表G3-2'!W29-'明细表G3-2'!X29 -> 0 | H13: ='明细表G3-2'!V29+'明细表G3-2'!Y29-'明细表G3-2'!Z29 -> 0 | I13: =F13+G13+H13 -> 0 | J13: =F13-B13 -> 0 | K13: =IF(AND(B13=0,J13=0),0,IF(AND(B13=0,J13>0),1,J13/B13)) -> 0 | L13: =I13-E13 -> 0 | M13: =IF(AND(E13=0,L13=0),0,IF(AND(E13=0,L13>0),1,L13/E13)) -> 0
A14: 合计 | B14: =SUM(B12:B13) -> 0 | C14: =SUM(C12:C13) -> 0 | D14: =SUM(D12:D13) -> 0 | E14: =SUM(E12:E13) -> 0 | F14: =SUM(F12:F13) -> 0 | G14: =SUM(G12:G13) -> 0 | H14: =SUM(H12:H13) -> 0 | I14: =SUM(I12:I13) -> 0 | J14: =F14-B14 -> 0 | K14: =IF(AND(B14=0,J14=0),0,IF(AND(B14=0,J14>0),1,J14/B14)) -> 0 | L14: =I14-E14 -> 0 | M14: =IF(AND(E14=0,L14=0),0,IF(AND(E14=0,L14>0),1,L14/E14)) -> 0
A15: 三、账面价值
A16: =A12 -> 账龄一年以内的应收股利 | B16: =B8-B12 -> 0 | C16: =C8-C12 -> 0 | D16: =D8-D12 -> 0 | E16: =B16+C16+D16 -> 0 | F16: =F8-F12 -> 0 | G16: =G8-G12 -> 0 | H16: =H8-H12 -> 0 | I16: =F16+G16+H16 -> 0 | J16: =F16-B16 -> 0 | K16: =IF(AND(B16=0,J16=0),0,IF(AND(B16=0,J16>0),1,J16/B16)) -> 0 | L16: =I16-E16 -> 0 | M16: =IF(AND(E16=0,L16=0),0,IF(AND(E16=0,L16>0),1,L16/E16)) -> 0
A17: =A13 -> 账龄一年以上的应收股利 | B17: =B9-B13 -> 0 | C17: =C9-C13 -> 0 | D17: =D9-D13 -> 0 | E17: =B17+C17+D17 -> 0 | F17: =F9-F13 -> 0 | G17: =G9-G13 -> 0 | H17: =H9-H13 -> 0 | I17: =F17+G17+H17 -> 0 | J17: =F17-B17 -> 0 | K17: =IF(AND(B17=0,J17=0),0,IF(AND(B17=0,J17>0),1,J17/B17)) -> 0 | L17: =I17-E17 -> 0 | M17: =IF(AND(E17=0,L17=0),0,IF(AND(E17=0,L17>0),1,L17/E17)) -> 0
A18: 合计 | B18: =SUM(B16:B17) -> 0 | C18: =SUM(C16:C17) -> 0 | D18: =SUM(D16:D17) -> 0 | E18: =SUM(E16:E17) -> 0 | F18: =SUM(F16:F17) -> 0 | G18: =SUM(G16:G17) -> 0 | H18: =SUM(H16:H17) -> 0 | I18: =SUM(I16:I17) -> 0 | J18: =F18-B18 -> 0 | K18: =IF(AND(B18=0,J18=0),0,IF(AND(B18=0,J18>0),1,J18/B18)) -> 0 | L18: =I18-E18 -> 0 | M18: =IF(AND(E18=0,L18=0),0,IF(AND(E18=0,L18>0),1,L18/E18)) -> 0
A19: 1、审计说明
A20: （1）公司应收股利期末余额较期初余额增加（负数为减少）： | C20: =M18 -> 0
A21: 主要原因（比例超过30%的）：
A22: （2）金额较大的1年以上应收未收的应收股利金额，分别贷款单位说明未收回的原因和对相关款项是否发生减值
A23: 所作的判断。
A25: 2、审计结论
A28: 编制说明：
A29: 1、如适用，根据1131号等审计准则和指南的要求编制，说明涉及事项内容、应对措施、审计结论或解决方法，
A30: 以及可能对审计报告的影响。
A31: A、风险评估结果和内控了解、测试情况（不适用则说明：不存在重大错报风险。)
A32: (识别和实际评估的重大错报风险、尤其识特别风险，以及对内控了解和控制测试情况〔采用综合方案时〕）；
A33: 提示：a、收入科目应当假定存在舞弊的特别风险，如不存在，应说明理由；
A34: b、涉及特别风险时，应当重点说明有关事项、应当措施、结果〔可索引有关底稿〕。
A35: 特别风险涉及的事项包括但不限于：
... A48: C、

Sheet 附注披露信息（上市公司）
A1: 致同会计师事务所
A2: 附注披露信息（上市公司）
A3: =底稿目录!A2 -> 被审计单位： | B3: =底稿目录!A4 -> 编制人： | C3: =底稿目录!A5 -> 编制日期： | D3: 索引： | E3: =底稿目录!F6 -> 0
A4: =底稿目录!A3 -> 截止日：202X年12月31日 | B4: =底稿目录!A6 -> 复核人： | C4: =底稿目录!A7 -> 复核日期： | D4: 页次：1
A5: 附注披露信息
A6: 【其他应收款、应收股利与应收利息的合计数披露详见M1-1】
A7: 应收股利
A8: 项 目（或被投资单位） | B8: 期末余额 | C8: 上年年末余额
A21: 小 计
A22: 减：坏账准备
A23: 合 计 | B23: =SUM(B9:B22) -> 0 | C23: =SUM(C9:C22) -> 0
A24: ①重要的账龄超过1年的应收股利：
A25: 项目（或被投资单位） | B25: 期末余额 | C25: 账龄 | D25: 未收回的原因 | E25: 是否发生减值及其原因
A26: ='明细表G3-2'!B23 -> 0 | B26: ='明细表G3-2'!AF23 -> 0 | C26: =#REF! -> #REF! | D26: =#REF! -> #REF! | E26: =#REF! -> #REF!
A27: ='明细表G3-2'!B24 -> 0 | B27: ='明细表G3-2'!AF24 -> 0 | C27: =#REF! -> #REF! | D27: =#REF! -> #REF! | E27: =#REF! -> #REF!
A28: ='明细表G3-2'!B25 -> 0 | B28: ='明细表G3-2'!AF25 -> 0 | C28: =#REF! -> #REF! | D28: =#REF! -> #REF! | E28: =#REF! -> #REF!
A29: ='明细表G3-2'!B26 -> 0 | B29: ='明细表G3-2'!AF26 -> 0 | C29: =#REF! -> #REF! | D29: =#REF! -> #REF! | E29: =#REF! -> #REF!
A30: ='明细表G3-2'!B27 -> 0 | B30: ='明细表G3-2'!AF27 -> 0 | C30: =#REF! -> #REF! | D30: =#REF! -> #REF! | E30: =#REF! -> #REF!
A31: ='明细表G3-2'!B28 -> 0 | B31: ='明细表G3-2'!AF28 -> 0 | C31: =#REF! -> #REF! | D31: =#REF! -> #REF! | E31: =#REF! -> #REF!
A32: 合 计 | B32: =SUM(B26:B31) -> 0 | C32: -- | D32: -- | E32: --
A33: （对于重要的账龄超过1 年的应收股利，应披露未收回的原因和对相关款项是否发生减值的判断。）
A34: ② 坏账准备计提情况
A35: 说明期末处于第一阶段、第二阶段和第三阶段的应收股利的坏账准备计提情况，披露格式可参考其他应收款的披露格式（见附注五、8、（3）③）。 说明坏账准备本期计提、转回、转销、核销情况，披露格式可参考其他应收款的披露格式。 说明本期发生损失准备的应收股利账面余额显著变动的情况。 【也可以在其他应收款项下合并披露应收股利的坏账准备计提情况，则索引至附注五、8、（3）③】

Sheet 附注披露信息（国企）
A1: 致同会计师事务所
A2: 附注披露信息（上市公司）
A3: =底稿目录!A2 -> 被审计单位： | B3: =底稿目录!A4 -> 编制人： | C3: =底稿目录!A5 -> 编制日期： | D3: 索引： | E3: =底稿目录!F7 -> 0
A4: =底稿目录!A3 -> 截止日：202X年12月31日 | B4: =底稿目录!A6 -> 复核人： | C4: =底稿目录!A7 -> 复核日期： | D4: 页次：1
A5: 附注披露信息
A6: 【其他应收款、应收股利与应收利息的合计数披露详见M1-1】
A7: 应收股利
A8: 项 目 | B8: 期末余额 | C8: 年初余额 | D8: 未收回的原因 | E8: 相关款项是否发生减值
A9: 账龄一年以内的应收股利 | B9: =SUM(B10:B17) -> 0 | C9: =SUM(C10:C17) -> 0 | D9: —— | E9: ——
A10: ='明细表G3-2'!B13 -> 0 | B10: ='明细表G3-2'!M13 -> 0 | C10: ='明细表G3-2'!M13 -> 0
A11: ='明细表G3-2'!B14 -> 0 | B11: ='明细表G3-2'!M14 -> 0 | C11: ='明细表G3-2'!M14 -> 0
A12: ='明细表G3-2'!B15 -> 0 | B12: ='明细表G3-2'!M15 -> 0 | C12: ='明细表G3-2'!M15 -> 0
A13: ='明细表G3-2'!B16 -> 0 | B13: ='明细表G3-2'!M16 -> 0 | C13: ='明细表G3-2'!M16 -> 0
A14: ='明细表G3-2'!B17 -> 0 | B14: ='明细表G3-2'!M17 -> 0 | C14: ='明细表G3-2'!M17 -> 0
A15: ='明细表G3-2'!B18 -> 0 | B15: ='明细表G3-2'!M18 -> 0 | C15: ='明细表G3-2'!M18 -> 0
A16: ='明细表G3-2'!B19 -> 0 | B16: ='明细表G3-2'!M19 -> 0 | C16: ='明细表G3-2'!M19 -> 0
A17: ='明细表G3-2'!B20 -> 0 | B17: ='明细表G3-2'!M20 -> 0 | C17: ='明细表G3-2'!M20 -> 0
A18: 账龄一年以上的应收股利 | B18: =SUM(B19:B24) -> 0 | C18: =SUM(C19:C24) -> 0 | D18: —— | E18: ——
A19: ='明细表G3-2'!B23 -> 0 | B19: ='明细表G3-2'!P23 -> 0 | C19: ='明细表G3-2'!M23 -> 0 | D19: =#REF! -> #REF! | E19: =#REF! -> #REF!
A20: ='明细表G3-2'!B24 -> 0 | B20: ='明细表G3-2'!P24 -> 0 | C20: ='明细表G3-2'!M24 -> 0 | D20: =#REF! -> #REF! | E20: =#REF! -> #REF!
A21: ='明细表G3-2'!B25 -> 0 | B21: ='明细表G3-2'!P25 -> 0 | C21: ='明细表G3-2'!M25 -> 0 | D21: =#REF! -> #REF! | E21: =#REF! -> #REF!
A22: ='明细表G3-2'!B26 -> 0 | B22: ='明细表G3-2'!P26 -> 0 | C22: ='明细表G3-2'!M26 -> 0 | D22: =#REF! -> #REF! | E22: =#REF! -> #REF!
A23: ='明细表G3-2'!B27 -> 0 | B23: ='明细表G3-2'!P27 -> 0 | C23: ='明细表G3-2'!M27 -> 0 | D23: =#REF! -> #REF! | E23: =#REF! -> #REF!
A24: ='明细表G3-2'!B28 -> 0 | B24: ='明细表G3-2'!P28 -> 0 | C24: ='明细表G3-2'!M28 -> 0 | D24: =#REF! -> #REF! | E24: =#REF! -> #REF!
A25: 小计 | B25: =B18+B9 -> 0 | C25: =C18+C9 -> 0
A26: 减：坏账准备 | B26: ='明细表G3-2'!AD30 -> 0 | C26: ='明细表G3-2'!AA30 -> 0
A27: 合 计 | B27: =B25-B26 -> 0 | C27: =C25-C26 -> 0 | D27: —— | E27: ——

Sheet 明细表G3-2
A1: 致同会计师事务所 | Q1: 致同会计师事务所
A2: 应收股利明细表 | Q2: 应收股利明细表（减值准备）
A3: =底稿目录!A2 -> 被审计单位： | G3: =底稿目录!A4 -> 编制人： | K3: =底稿目录!A5 -> 编制日期： | O3: 索引号： | P3: =底稿目录!F8 -> G3-2 | V3: =底稿目录!A4 -> 编制人： | AA3: =底稿目录!A5 -> 编制日期： | AF3: 索引号： | AG3: =底稿目录!F8 -> G3-2
A4: =底稿目录!A3 -> 截止日：202X年12月31日 | G4: =底稿目录!A6 -> 复核人： | K4: =底稿目录!A7 -> 复核日期： | O4: 页 次： | V4: =底稿目录!A6 -> 复核人： | AA4: =底稿目录!A7 -> 复核日期： | AF4: 页 次：
C5: 一、审计目标 | Q5: 一、审计目标
C6: 1.资产负债表中记录的应收股利是存在的，且已经记录在恰当的账户中；2.所有应记录的应收股利均已记录，所有应当包括在财务报表中的相关披露均已包括； | Q6: 1.资产负债表中记录的应收股利是存在的，且已经记录在恰当的账户中；2.所有应记录的应收股利均已记录，所有应当包括在财务报表中的相关披露均已包括；
C7: 3.应收股利以恰当的金额包括在财务报表中，与之相关的计价或分摊调整已恰当记录，相关披露已得到恰当计量和描述 | Q7: 3.应收股利以恰当的金额包括在财务报表中，与之相关的计价或分摊调整已恰当记录，相关披露已得到恰当计量和描述
C8: 二、审计过程： | Q8: 二、审计过程：
A9: 项目 | C9: 账面余额 | Q9: 减值准备 | AE9: 账面价值 | AG9: 备注
C10: 未审数 | G10: 期初调整 | I10: 账项调整 | K10: 重分类调整 | M10: 审定数 | Q10: 未审数 | U10: 期初调整 | W10: 账项调整 | Y10: 重分类调整 | AA10: 审定数 | AE10: 审定数
C11: 期初数 | D11: 本期增加 | E11: 本期减少 | F11: 期末数 | G11: 账项调整 | H11: 重分类调整 | I11: 本期增加 | J11: 本期减少 | K11: 本期增加 | L11: 本期减少 | M11: 期初数 | N11: 本期增加 | O11: 本期减少 | P11: 期末数 | Q11: 期初数 | R11: 本期增加 | S11: 本期减少 | T11: 期末数 | U11: 账项调整 | V11: 重分类调整 | W11: 本期增加 | X11: 本期减少 | Y11: 本期增加 | Z11: 本期减少 | AA11: 期初数 | AB11: 本期增加 | AC11: 本期减少 | AD11: 期末数 | AE11: 期初数 | AF11: 期末数
A12: 1、账龄一年以内的应收股利
F13: =SUM(C13:D13)-E13 -> 0 | M13: =C13+G13+H13 -> 0 | N13: =D13+I13+K13 -> 0 | O13: =E13+J13+L13 -> 0 | P13: =M13+N13-O13 -> 0 | T13: =SUM(Q13:R13)-S13 -> 0 | AA13: =Q13+U13+V13 -> 0 | AB13: =R13+W13+Y13 -> 0 | AC13: =S13+X13+Z13 -> 0 | AD13: =AA13+AB13-AC13 -> 0 | AE13: =M13-AA13 -> 0 | AF13: =P13-AD13 -> 0
F14: =SUM(C14:D14)-E14 -> 0 | M14: =C14+G14+H14 -> 0 | N14: =D14+I14+K14 -> 0 | O14: =E14+J14+L14 -> 0 | P14: =M14+N14-O14 -> 0 | T14: =SUM(Q14:R14)-S14 -> 0 | AA14: =Q14+U14+V14 -> 0 | AB14: =R14+W14+Y14 -> 0 | AC14: =S14+X14+Z14 -> 0 | AD14: =AA14+AB14-AC14 -> 0 | AE14: =M14-AA14 -> 0 | AF14: =P14-AD14 -> 0
F15: =SUM(C15:D15)-E15 -> 0 | M15: =C15+G15+H15 -> 0 | N15: =D15+I15+K15 -> 0 | O15: =E15+J15+L15 -> 0 | P15: =M15+N15-O15 -> 0 | T15: =SUM(Q15:R15)-S15 -> 0 | AA15: =Q15+U15+V15 -> 0 | AB15: =R15+W15+Y15 -> 0 | AC15: =S15+X15+Z15 -> 0 | AD15: =AA15+AB15-AC15 -> 0 | AE15: =M15-AA15 -> 0 | AF15: =P15-AD15 -> 0
F16: =SUM(C16:D16)-E16 -> 0 | M16: =C16+G16+H16 -> 0 | N16: =D16+I16+K16 -> 0 | O16: =E16+J16+L16 -> 0 | P16: =M16+N16-O16 -> 0 | T16: =SUM(Q16:R16)-S16 -> 0 | AA16: =Q16+U16+V16 -> 0 | AB16: =R16+W16+Y16 -> 0 | AC16: =S16+X16+Z16 -> 0 | AD16: =AA16+AB16-AC16 -> 0 | AE16: =M16-AA16 -> 0 | AF16: =P16-AD16 -> 0
F17: =SUM(C17:D17)-E17 -> 0 | M17: =C17+G17+H17 -> 0 | N17: =D17+I17+K17 -> 0 | O17: =E17+J17+L17 -> 0 | P17: =M17+N17-O17 -> 0 | T17: =SUM(Q17:R17)-S17 -> 0 | AA17: =Q17+U17+V17 -> 0 | AB17: =R17+W17+Y17 -> 0 | AC17: =S17+X17+Z17 -> 0 | AD17: =AA17+AB17-AC17 -> 0 | AE17: =M17-AA17 -> 0 | AF17: =P17-AD17 -> 0
F18: =SUM(C18:D18)-E18 -> 0 | M18: =C18+G18+H18 -> 0 | N18: =D18+I18+K18 -> 0 | O18: =E18+J18+L18 -> 0 | P18: =M18+N18-O18 -> 0 | T18: =SUM(Q18:R18)-S18 -> 0 | AA18: =Q18+U18+V18 -> 0 | AB18: =R18+W18+Y18 -> 0 | AC18: =S18+X18+Z18 -> 0 | AD18: =AA18+AB18-AC18 -> 0 | AE18: =M18-AA18 -> 0 | AF18: =P18-AD18 -> 0
F19: =SUM(C19:D19)-E19 -> 0 | M19: =C19+G19+H19 -> 0 | N19: =D19+I19+K19 -> 0 | O19: =E19+J19+L19 -> 0 | P19: =M19+N19-O19 -> 0 | T19: =SUM(Q19:R19)-S19 -> 0 | AA19: =Q19+U19+V19 -> 0 | AB19: =R19+W19+Y19 -> 0 | AC19: =S19+X19+Z19 -> 0 | AD19: =AA19+AB19-AC19 -> 0 | AE19: =M19-AA19 -> 0 | AF19: =P19-AD19 -> 0
F20: =SUM(C20:D20)-E20 -> 0 | M20: =C20+G20+H20 -> 0 | N20: =D20+I20+K20 -> 0 | O20: =E20+J20+L20 -> 0 | P20: =M20+N20-O20 -> 0 | T20: =SUM(Q20:R20)-S20 -> 0 | AA20: =Q20+U20+V20 -> 0 | AB20: =R20+W20+Y20 -> 0 | AC20: =S20+X20+Z20 -> 0 | AD20: =AA20+AB20-AC20 -> 0 | AE20: =M20-AA20 -> 0 | AF20: =P20-AD20 -> 0
A21: 小计 | C21: =SUM(C13:C20) -> 0 | D21: =SUM(D13:D20) -> 0 | E21: =SUM(E13:E20) -> 0 | F21: =SUM(F13:F20) -> 0 | G21: =SUM(G13:G20) -> 0 | H21: =SUM(H13:H20) -> 0 | I21: =SUM(I13:I20) -> 0 | J21: =SUM(J13:J20) -> 0 | ... AF21: =SUM(AF13:AF20) -> 0
A22: 2、账龄一年以上的应收股利
F23: =SUM(C23:D23)-E23 -> 0 | M23: =C23+G23+H23 -> 0 | N23: =D23+I23+K23 -> 0 | O23: =E23+J23+L23 -> 0 | P23: =M23+N23-O23 -> 0 | T23: =SUM(Q23:R23)-S23 -> 0 | AA23: =Q23+U23+V23 -> 0 | AB23: =R23+W23+Y23 -> 0 | AC23: =S23+X23+Z23 -> 0 | AD23: =AA23+AB23-AC23 -> 0 | AE23: =M23-AA23 -> 0 | AF23: =P23-AD23 -> 0
F24: =SUM(C24:D24)-E24 -> 0 | M24: =C24+G24+H24 -> 0 | N24: =D24+I24+K24 -> 0 | O24: =E24+J24+L24 -> 0 | P24: =M24+N24-O24 -> 0 | T24: =SUM(Q24:R24)-S24 -> 0 | AA24: =Q24+U24+V24 -> 0 | AB24: =R24+W24+Y24 -> 0 | AC24: =S24+X24+Z24 -> 0 | AD24: =AA24+AB24-AC24 -> 0 | AE24: =M24-AA24 -> 0 | AF24: =P24-AD24 -> 0
F25: =SUM(C25:D25)-E25 -> 0 | M25: =C25+G25+H25 -> 0 | N25: =D25+I25+K25 -> 0 | O25: =E25+J25+L25 -> 0 | P25: =M25+N25-O25 -> 0 | T25: =SUM(Q25:R25)-S25 -> 0 | AA25: =Q25+U25+V25 -> 0 | AB25: =R25+W25+Y25 -> 0 | AC25: =S25+X25+Z25 -> 0 | AD25: =AA25+AB25-AC25 -> 0 | AE25: =M25-AA25 -> 0 | AF25: =P25-AD25 -> 0
F26: =SUM(C26:D26)-E26 -> 0 | M26: =C26+G26+H26 -> 0 | N26: =D26+I26+K26 -> 0 | O26: =E26+J26+L26 -> 0 | P26: =M26+N26-O26 -> 0 | T26: =SUM(Q26:R26)-S26 -> 0 | AA26: =Q26+U26+V26 -> 0 | AB26: =R26+W26+Y26 -> 0 | AC26: =S26+X26+Z26 -> 0 | AD26: =AA26+AB26-AC26 -> 0 | AE26: =M26-AA26 -> 0 | AF26: =P26-AD26 -> 0
F27: =SUM(C27:D27)-E27 -> 0 | M27: =C27+G27+H27 -> 0 | N27: =D27+I27+K27 -> 0 | O27: =E27+J27+L27 -> 0 | P27: =M27+N27-O27 -> 0 | T27: =SUM(Q27:R27)-S27 -> 0 | AA27: =Q27+U27+V27 -> 0 | AB27: =R27+W27+Y27 -> 0 | AC27: =S27+X27+Z27 -> 0 | AD27: =AA27+AB27-AC27 -> 0 | AE27: =M27-AA27 -> 0 | AF27: =P27-AD27 -> 0
F28: =SUM(C28:D28)-E28 -> 0 | M28: =C28+G28+H28 -> 0 | N28: =D28+I28+K28 -> 0 | O28: =E28+J28+L28 -> 0 | P28: =M28+N28-O28 -> 0 | T28: =SUM(Q28:R28)-S28 -> 0 | AA28: =Q28+U28+V28 -> 0 | AB28: =R28+W28+Y28 -> 0 | AC28: =S28+X28+Z28 -> 0 | AD28: =AA28+AB28-AC28 -> 0 | AE28: =M28-AA28 -> 0 | AF28: =P28-AD28 -> 0
A29: 小计 | C29: =SUM(C23:C28) -> 0 | D29: =SUM(D23:D28) -> 0 | E29: =SUM(E23:E28) -> 0 | F29: =SUM(F23:F28) -> 0 | G29: =SUM(G23:G28) -> 0 | H29: =SUM(H23:H28) -> 0 | I29: =SUM(I23:I28) -> 0 | J29: =SUM(J23:J28) -> 0 | ... AF29: =SUM(AF23:AF28) -> 0
A30: 合计 | C30: =C29+C21 -> 0 | D30: =D29+D21 -> 0 | E30: =E29+E21 -> 0 | F30: =F29+F21 -> 0 | G30: =G29+G21 -> 0 | H30: =H29+H21 -> 0 | I30: =I29+I21 -> 0 | J30: =J29+J21 -> 0 | ... AF30: =AF29+AF21 -> 0
A31: 三、审计说明：
A33: 四、审计结论：
A35: 提示：1、减值准备测算可参考其他应收款底稿
A36: 编制说明：
A37: 1.审计说明可以概述:(1)程序的测试情况、结果;(2)拟调整事项及其调整分录、未调整事项及其影响，审计范围受到限制情况及其影响。
A38: 2.审计结论可参考:A、未见异常。 B、除上述重大不符事项应当作为调整事项予以调整外，其余未见异常。由于存在以下重大未调整事项(或审计范围受到限制无法获取充分、适当证据)，不可确认。

Sheet 调整分录汇总G3-3
A1: 致同会计师事务所
A2: 应收股利调整分录汇总表
A3: =底稿目录!A2 -> 被审计单位： | D3: =底稿目录!A4 -> 编制人： | G3: =底稿目录!A5 -> 编制日期： | I3: 索引号： | J3: =底稿目录!F9 -> G3-3
A4: =底稿目录!A3 -> 截止日：202X年12月31日 | D4: =底稿目录!A6 -> 复核人： | G4: =底稿目录!A7 -> 复核日期： | I4: 页 次：1
A5: 调整事项说明 | B5: 类别（报表调整/账项调整/其他） | C5: 报表项目 | D5: 科目名称 | E5: 附注项目 | F5: …… | G5: 借方调整金额 | H5: 贷方调整金额 | I5: 索引 | J5: 备注

Sheet 测算及检查表G3-4
A1: 致同会计师事务所
A2: 应收股利测算及检查表
A3: =底稿目录!A2 -> 被审计单位： | E3: =底稿目录!A4 -> 编制人： | G3: =底稿目录!A5 -> 编制日期： | I3: 索引号： | J3: =底稿目录!F10 -> G3-4
A4: =底稿目录!A3 -> 截止日：202X年12月31日 | E4: =底稿目录!A6 -> 复核人： | G4: =底稿目录!A7 -> 复核日期： | I4: 页 次：
A5: 一、审计目标: | C5: 确定应收股利计量是否恰当。
A6: 二、审计过程：
A7: 测试内容说明：1.原始凭证是否齐全； 2.记账凭证与原始凭证是否相符；3.账务处理是否正确；4.是否记录于恰当的会计期间；5.……
A8: 1.增加项目检查 | C8: 如果在投资项目中已对应收股利进行测算，索引至投资项目即可。
A9: 项目名称 | C9: 持股比例 ① | D9: 宣告分派股利日 | E9: 主要股利分配政策 | F9: 被投资项目股利分配总额 ② | G9: 按持股比例计算应计股利 ③＝①*② | H9: 账面已计股利 ④ | I9: 差异 ⑤=④-③ | J9: 股利分配文件索引号
G10: =C10*F10 -> 0 | I10: =G10-H10 -> 0
G11: =C11*F11 -> 0 | I11: =G11-H11 -> 0
G12: =C12*F12 -> 0 | I12: =G12-H12 -> 0
G13: =C13*F13 -> 0 | I13: =G13-H13 -> 0
G14: =C14*F14 -> 0 | I14: =G14-H14 -> 0
A15: 合 计 | B15: 合计 | G15: =SUM(G10:G14) -> 0 | H15: =SUM(H10:H14) -> 0 | I15: =SUM(I10:I14) -> 0
A16: 2.减少项目检查
A17: 项目名称 | C17: 持股比例 | D17: 本期减少① | E17: 收回金额② | F17: 其他原因减少 | I17: 差异 | J17: 原因/文件索引号
F18: 会计科目 | G18: 金额 | H18: 原因
I19: =D19-E19-G19 -> 0
I20: =D20-E20-G20 -> 0
I21: =D21-E21-G21 -> 0
I22: =D22-E22-G22 -> 0
I23: =D23-E23-G23 -> 0
I24: =D24-E24-G24 -> 0
A25: 合计 | D25: =SUM(D19:D24) -> 0 | E25: =SUM(E19:E24) -> 0 | F25: =SUM(F19:F24) -> 0 | I25: =SUM(I19:I24) -> 0
A26: 3.期后收款检查表
A27: 日 期 | B27: 凭证编号 | C27: 业务内容 | D27: 对方科目 | E27: 对方明细科目 | F27: 金 额 | H27: 支持性文件 | I27: 核对内容 | N27: 索引号 | O27: 是否异常
F28: 借方 | G28: 贷方 | I28: 1 | J28: 2 | K28: 3 | L28: 4 | M28: 5
A34: 合计 | F34: =SUM(F29:F33) -> 0 | G34: =SUM(G29:G33) -> 0
A35: 三、审计说明：
A38: 四、审计结论：
B42: 编制说明：
B43: 1、概述：（1）程序的测试情况、结果；
B44: （2）拟调整事项及其调整分录、未调整事项及其影响，审计范围受到限制情况及其影响。
B45: 参考结论：
B46: A、 | C46: 未见异常。
B47: B、 | C47: 除以下重大不符事项应当作为调整事项予以调整外，其余未见异常。
B48: C、 | C48: 由于存在以下重大未调整事项（或审计范围受到限制无法获取充分、适当证据），不可确认。

Sheet 长期未收回款项检查表G3-5
A1: 致同会计师事务所
A2: 长期未收回款项检查表
A3: =底稿目录!A2 -> 被审计单位： | D3: =底稿目录!A4 -> 编制人： | H3: =底稿目录!A5 -> 编制日期： | L3: 索引号： | M3: =底稿目录!F11 -> G3-5
A4: =底稿目录!A3 -> 截止日：202X年12月31日 | D4: =底稿目录!A6 -> 复核人： | H4: =底稿目录!A7 -> 复核日期： | L4: 页 次：
A5: 一、审计目标:
A6: 1.资产负债表中记录的应收股利、坏账准备是存在的，且已记录于恰当的账户；
A7: 2.应收股利、坏账准备以恰当的金额包括在财务报表中，与之相关的计价或分摊调整已恰当记录，相关披露已得到恰当计量和描述
A8: 二、审计过程：
A9: 债务人名称 | B9: 期初余额 | C9: 本期借方发生额 | D9: 本期贷方发生额 | E9: 期末余额 | F9: 账龄 | G9: 经济业务说明 | H9: 未收回或未结转的原因 | I9: 是否无法收回 | J9: 处理计划 | K9: 审定余额 | L9: 期后收款金额 | M9: 备注
E10: =B10+C10-D10 -> 0
A13: 合计 | B13: =SUM(B10:B12) -> 0 | C13: =SUM(C10:C12) -> 0 | D13: =SUM(D10:D12) -> 0 | E13: =SUM(E10:E12) -> 0 | F13: =SUM(F10:F12) -> 0 | K13: =SUM(K10:K12) -> 0 | L13: =SUM(L10:L12) -> 0
A15: 三、审计说明
A16: 1.针对期后收款的凭证检查，详见测算及检查表G3-4
A18: 四、审计结论
A22: 编制说明：
A23: 1、概述：（1）程序的测试情况、结果；
A24: （2）拟调整事项及其调整分录、未调整事项及其影响，审计范围受到限制情况及其影响。
A25: 参考结论：
A26: A、 | C26: 未见异常。
A27: B、 | C27: 除以下重大不符事项应当作为调整事项予以调整外，其余未见异常。
A28: C、 | C28: 由于存在以下重大未调整事项（或审计范围受到限制无法获取充分、适当证据），不可确认。
