Workbook

Sheet 底稿目录
A1: 底稿开列时，可先在以下单元格填写有关内容，以便其他底稿引用有关数据：
A2: 被审计单位：
A3: 截止日：202X年12月31日 | D3: 序号 | E3: 内容 | F3: 索引号
A4: 编制人： | E4: 长期股权投资实质性程序表 | F4: G7A
A5: 编制日期： | D5: 1 | E5: 长期股权投资审定表 | F5: G7-1
A6: 复核人： | D6: 2 | E6: 附注披露信息（上市公司） | G6: 无需打印
A7: 复核日期： | D7: 3 | E7: 附注披露信息（国企） | G7: 无需打印
D8: 4 | E8: 明细表 | F8: G7-2
A9: 关于工作底稿与审计程序索引号对应的说明 | D9: 5 | E9: 调整分录汇总 | F9: G7-3
A10: 1.编制的审计工作底稿应与审计程序对应。审计项目组应根据被审计单位实际情况和风险评估情况在实质性程序表中裁剪、修改或增加审计程序，根据实际执行的审计程序完成相应审计工作底稿，编制的工作底稿中应按自然顺序依次编制索引号，并通过唯一的索引号将与实质性程序表中的程序对应关联（即将工作底稿的索引号填入实质性程序表中的底稿索引号列）。 | D10: 6 | E10: 被投资单位基本信息 | F10: G7-4
D11: 7 | E11: 被投资单位财务信息（合营、联营） | F11: G7-5
D12: 8 | E12: 被投资公司会计政策 | F12: G7-6
D13: 9 | E13: 长期股权投资初始判断 | F13: G7-7
A14: 2.获取的支持性证据应与审计底稿或程序对应。审计项目组在完成底稿时获取的支持性证据应根据底稿索引号编制下一级按自然顺序排序的索引号（如D1-2-1、D1-2-2、……），并在底稿中说明引用的支持性证据、关联索引号。 | D14: 10 | E14: 子公司初始计量测试（同控） | F14: G7-8
D15: 11 | E15: 子公司初始计量测试（非同控） | F15: G7-9
D16: 12 | E16: 子公司后续计量测试表 | F16: G7-10
A17: 3.工作底稿索引号的编码规则：实质性程序索引号按循环从“D”到“N”,循环内账户以顺序号排列，模板中底稿索引号按账户顺序+自然数顺序（即模板中索引号按二级自然顺序排列，如D1-1、D1-2、D1-3、……D1-N）。 | D17: 13 | E17: 处置子公司测试表（不包含一揽子交易） | F17: G7-11
D18: 14 | E18: 处置子公司测试表（一揽子交易） | F18: G7-12
D19: 15 | E19: 合营、联营企业投资成本测试表 | F19: G7-13
D20: 16 | E20: 权益法测算表 | F20: G7-14
D21: 17 | E21: 权益法未实现内部交易抵销测算表 | F21: G7-15
D22: 18 | E22: 未确认投资损失测试表 | F22: G7-16
D23: 19 | E23: 减值测试表 | F23: G7-17
D24: 20 | E24: 凭证检查表 | F24: G7-18

Sheet 长期股权投资实质性程序表G7A
A1: 致同会计师事务所
A2: 长期股权投资实质性程序表
A3: =底稿目录!A2 -> 被审计单位： | C3: =底稿目录!A4 -> 编制人： | F3: =底稿目录!A5 -> 编制日期： | H3: 索引号： | I3: =底稿目录!F4 -> G7A
A4: =底稿目录!A3 -> 截止日：202X年12月31日 | C4: =底稿目录!A6 -> 复核人： | F4: =底稿目录!A7 -> 复核日期： | H4: 页 次：
A5: 一、本账户涉及的科目
A6: 长期股权投资、长期股权投资减值准备
A7: 二、审计目标与认定的对应关系
A8: 审计目标 | G8: 财务报表的认定
A9: A. 资产负债表中记录的长期股权投资是存在的，且已记录于恰当的账户 | G9: 存在
A10: B. 所有应记录的长期股权投资均已记录，所有应当包括在财务报表中的相关披露均已包括 | G10: 完整性
A11: C. 记录的长期股权投资由被审计单位拥有或控制 | G11: 权利和义务
A12: D. 长期股权投资以恰当的金额包括在财务报表中，与之相关的计价或分摊调整已恰当记录，相关披露已得到恰当计量和描述 | G12: 准确性、计价和分摊
A13: E. 长期股权投资已被恰当地汇总或分解且表述清楚，相关披露在按照企业会计准则的编制基础下是相关的、可理解的 | G13: 列报
A14: 三、计划实施的实质性程序
A15: 序号 | B15: 审计程序 | C15: 程序分类 | D15: 财务报表的认定 | I15: 底稿索引号
D16: 存在 | E16: 完整性 | F16: 权利和 义务 | G16: 准确性、计价和分摊 | H16: 列报 | J16: 根据被审计单位实际情况和风险评估情况裁剪、修改或增加审计程序
A17: 1 | B17: 获取或编制长期股权投资的明细表，完成以下工作，并编制审定表 （1）复核加计是否正确，与总账、明细账合计数核对是否相符； （2）将期初余额与上期期末余额核对； （3）与上年明细项目进行比较，确定与上年分类相同； （4）检查非记账本位币计量的长期股权投资的折算汇率及折算是否正确。 | C17: 常规★ | D17: √ | E17: √ | G17: √ | I17: G7-1 /G7-2
A18: 2 | B18: 在使用手工编制、自定义信息报告、系统生成的非固定格式报告等由被审计单位生成的信息时，测试有关信息准确性和完整性，并考虑针对编制和维护由被审计单位生成的信息的相关控制实施控制测试，以评价该信息是否能够为实现审计目的提供基础。 | C18: 常规★ | E18: √ | G18: √ | I18: T1 /G0-2 /
A19: 3 | B19: 对期初余额的审计，获取前期期末对被投资单位股权投资的明细，以及相关支持文件并分析，判断公司对投资的分类及其影响程度的认定是否正确，关注计算的准确性，会计处理是否恰当；确定是否需要补充必要的程序。（适用于首次承接） | C19: 备选 | D19: √ | E19: √ | F19: √ | G19: √
A20: 4 | B20: 确认长期股权投资会计政策、会计处理是否合理并与前期一致；核对相关资产减值准备本期与以前年度计提方法是否一致，如有差异，查明政策调整的原因，并确定政策改变对本期损益的影响，提请被审计单位做适当披露。 | C20: 常规★ | D20: √ | E20: √ | G20: √ | I20: G7-6
A21: 5 | B21: 取得被投资单位的章程、营业执照、组织机构代码证等资料，根据有关合同和文件，确认长期股权投资的股权比例、表决权等，检查长期股权投资的分类和核算方法是否正确。 | C21: 常规★ | D21: √ | E21: √ | F21: √ | G21: √ | I21: G7-7 /G7-8 /G7-9 /G7-13 /G7-18
A22: 6 | B22: 对本期发生的长期股权投资的增减变动，检查至支持性文件，综合判断长期股权投资的购买日（或交易日）的认定是否正确，确定其会计处理是否正确，是否被记录在恰当的期间内。 | C22: 常规★ | D22: √ | F22: √ | G22: √ | I22: G7-10 /G7-14 /G7-15 /G7-16 /G7-18
A23: 7 | B23: 必要时对被投资单位进行函证确认主要条款（或查询工商存档文件），核实投资是否存在。 | C23: 备选 | D23: √ | E23: √ | F23: √ | G23: √ | I23: G0
A24: 8 | B24: 确定本期处置的重大股权投资，并执行下列程序： （1）检查与股权投资处置相关的合同、发票及其他文件； （2）重新计算相关的利得或损失； （3）确定会计处理是否恰当。 对于成本法和权益法相互转换的，检查会计处理是否正确。 | C24: 常规★ | D24: √ | E24: √ | F24: √ | G24: √ | I24: G7-11 /G7-12 /G7-18
A25: 9 | B25: 确定本期按权益法核算的长期股权投资进行正确的核算，考虑以下因素：（1）被投资单位的经营成果、财务状况和资本交易； （2）被投资单位为符合投资单位的会计政策而作出的任何必要的会计政策调整； （3）针对被投资单位账面价值、股利分配、收益影响、其他综合收益及其他权益变动的持续调整。 | C25: 常规★ | G25: √ | I25: G7-14 /G7-15 /G7-16
A26: 10 | B26: 对于按成本法核算的长期股权投资，检查股利分配的原始凭证及分配决议等资料，确定会计处理是否正确。 | C26: 常规★ | G26: √ | I26: G7-10
A27: 11 | B27: 针对存在减值迹象的长期股权投资，考虑执行下列程序： （1）获取长期股权投资的减值明细表，考虑对该投资可能造成减值的事件或环境变化； （2）获取被审计单位管理层在资产负债表日就长期股权投资是否存在可能发生减值迹象的判断说明及减值测试过程，关注计提减值准备的依据是否充分，减值测试过程是否合理，会计处理是否正确。 （3）考虑是否需要利用估值专家的工作，如需要完成利用专家工作底稿。 | C27: 常规★ | G27: √ | I27: G7-17
A28: 12 | B28: 了解长期股权投资是否存在所有权限制，承诺或留置。 | C28: 常规★ | F28: √ | I28: G7-2
A29: 13 | B29: 与被审计单位人员讨论确定是否存在被投资单位由于所在国家和地区及其他方面的影响，其向被审计单位转移资金的能力受到限制的情况，如存在，应详细记录受限情况，并提请被审计单位充分披露。 | C29: 常规★ | H29: √ | I29: G7-2
A30: 14 | B30: 检查关联方交易： （1）了解关联交易的商业理由、交易事项的目的、价格和条件，考虑对关联方交易性金融资产的合理性、合法性； （2）检查对关联方交易性金融资产的真实性相关的支持性文件、检查会计处理是否正确； （3）考虑向关联方或其他注册会计师函证重大的关联交易和余额（包括担保和其他重要信息）； （4）必要时，向与交易相关的人员和机构函证或与其讨论有关信息； （5）考虑是否存在未识别的关联方，关联交易和余额披露是否正确。 | C30: 常规★ | D30: √ | E30: √ | F30: √ | G30: √ | H30: √
A31: 15 | B31: 根据评估的舞弊风险等因素增加的审计程序。 | C31: IPO/上市/新三板/重组/舞弊应对
A32: 16 | B32: 检查长期股权投资是否已按照企业会计准则的规定在财务报表中作出恰当列报和披露。 | C32: 常规★ | H32: √ | I32: A1-1/A1-15 /A1-16

Sheet 长期股权投资审定表G7-1
A1: 致同会计师事务所
A2: 长期股权投资审定表
A3: =底稿目录!A2 -> 被审计单位： | D3: =底稿目录!A4 -> 编制人： | E3: =底稿目录!A5 -> 编制日期： | F3: 索引号： | G3: =底稿目录!F5 -> G7-1
A4: =底稿目录!A3 -> 截止日：202X年12月31日 | D4: =底稿目录!A6 -> 复核人： | E4: =底稿目录!A7 -> 复核日期： | F4: 页 次：
A5: 项目 | C5: 期初数 | D5: 本期增加 | E5: 本期减少 | F5: 期末数 | G5: 索引
A6: 一、原值
A7: 未审数 | C7: =SUM(C8:C11) -> 0 | D7: =SUM(D8:D11) -> 0 | E7: =SUM(E8:E11) -> 0 | F7: =SUM(F8:F11) -> 0
A8: 一、对子公司投资 | C8: ='明细表G7-2'!M26 -> 0 | D8: ='明细表G7-2'!O26 -> 0 | E8: ='明细表G7-2'!R26 -> 0 | F8: =C8+D8-E8 -> 0
A9: 二、对合营企业投资 | C9: ='明细表G7-2'!H38 -> 0 | D9: ='明细表G7-2'!J38+'明细表G7-2'!N38 -> 0 | E9: ='明细表G7-2'!Q38+'明细表G7-2'!R38 -> 0 | F9: =C9+D9-E9 -> 0
A10: 三、对联营企业投资 | C10: ='明细表G7-2'!H45 -> 0 | D10: ='明细表G7-2'!J45+'明细表G7-2'!N45 -> 0 | E10: ='明细表G7-2'!Q45+'明细表G7-2'!R45 -> 0 | F10: =C10+D10-E10 -> 0
F11: =C11+D11-E11 -> 0
A12: 账项调整 | C12: =SUM(C13:C16) -> 0 | D12: =SUM(D13:D16) -> 0 | E12: =SUM(E13:E16) -> 0 | F12: =SUM(F13:F16) -> 0
A13: =A8 -> 一、对子公司投资 | C13: ='明细表G7-2'!V26 -> 0 | D13: ='明细表G7-2'!X26 -> 0 | E13: ='明细表G7-2'!Y26 -> 0 | F13: =C13+D13-E13 -> 0
A14: =A9 -> 二、对合营企业投资 | C14: ='明细表G7-2'!V38 -> 0 | D14: ='明细表G7-2'!X38+'明细表G7-2'!Y38+'明细表G7-2'!Z38+'明细表G7-2'!AA38 -> 0 | E14: ='明细表G7-2'!AC38+'明细表G7-2'!AD38 -> 0 | F14: =C14+D14-E14 -> 0
A15: =A10 -> 三、对联营企业投资 | C15: ='明细表G7-2'!V45 -> 0 | D15: ='明细表G7-2'!X45+'明细表G7-2'!Y45+'明细表G7-2'!Z45+'明细表G7-2'!AA45 -> 0 | E15: ='明细表G7-2'!AC45+'明细表G7-2'!AD45 -> 0 | F15: =C15+D15-E15 -> 0
A16: =A11 -> 0 | F16: =C16+D16-E16 -> 0
A17: 重分类调整 | C17: =SUM(C18:C21) -> 0 | D17: =SUM(D18:D21) -> 0 | E17: =SUM(E18:E21) -> 0 | F17: =SUM(F18:F21) -> 0
A18: =A13 -> 一、对子公司投资 | C18: ='明细表G7-2'!W26 -> 0 | D18: ='明细表G7-2'!Z26 -> 0 | E18: ='明细表G7-2'!AA26 -> 0 | F18: =C18+D18-E18 -> 0
A19: =A14 -> 二、对合营企业投资 | C19: ='明细表G7-2'!W38 -> 0 | D19: ='明细表G7-2'!AF38+'明细表G7-2'!AG38+'明细表G7-2'!AH38+'明细表G7-2'!AI38 -> 0 | E19: ='明细表G7-2'!AK38+'明细表G7-2'!AL38 -> 0 | F19: =C19+D19-E19 -> 0
A20: =A15 -> 三、对联营企业投资 | C20: ='明细表G7-2'!W45 -> 0 | D20: ='明细表G7-2'!AF45+'明细表G7-2'!AG45+'明细表G7-2'!AH45+'明细表G7-2'!AI45 -> 0 | E20: ='明细表G7-2'!AK45+'明细表G7-2'!AL45 -> 0 | F20: =C20+D20-E20 -> 0
A21: =A16 -> 0 | F21: =C21+D21-E21 -> 0
A22: 审定数1 | C22: =SUM(C23:C26) -> 0 | D22: =SUM(D23:D26) -> 0 | E22: =SUM(E23:E26) -> 0 | F22: =SUM(F23:F26) -> 0
A23: =A18 -> 一、对子公司投资 | C23: =C8+C13+C18 -> 0 | D23: =D8+D13+D18 -> 0 | E23: =E8+E13+E18 -> 0 | F23: =C23+D23-E23 -> 0
A24: =A19 -> 二、对合营企业投资 | C24: =C9+C14+C19 -> 0 | D24: =D9+D14+D19 -> 0 | E24: =E9+E14+E19 -> 0 | F24: =C24+D24-E24 -> 0
A25: =A20 -> 三、对联营企业投资 | C25: =C10+C15+C20 -> 0 | D25: =D10+D15+D20 -> 0 | E25: =E10+E15+E20 -> 0 | F25: =C25+D25-E25 -> 0
A26: =A21 -> 0 | C26: =C11+C16+C21 -> 0 | D26: =D11+D16+D21 -> 0 | E26: =E11+E16+E21 -> 0 | F26: =C26+D26-E26 -> 0
A27: 二、减值准备
A28: 未审数 | C28: =SUM(C29:C32) -> 0 | D28: =SUM(D29:D32) -> 0 | E28: =SUM(E29:E32) -> 0 | F28: =SUM(F29:F32) -> 0
A29: =A8 -> 一、对子公司投资 | C29: ='明细表G7-2'!G63 -> 0 | D29: ='明细表G7-2'!H63 -> 0 | E29: ='明细表G7-2'!I63 -> 0 | F29: =C29+D29-E29 -> 0
A30: =A9 -> 二、对合营企业投资 | C30: ='明细表G7-2'!G71 -> 0 | D30: ='明细表G7-2'!H71 -> 0 | E30: ='明细表G7-2'!I71 -> 0 | F30: =C30+D30-E30 -> 0
A31: =A10 -> 三、对联营企业投资 | C31: ='明细表G7-2'!G78 -> 0 | D31: ='明细表G7-2'!H78 -> 0 | E31: ='明细表G7-2'!I78 -> 0 | F31: =C31+D31-E31 -> 0
A32: =A11 -> 0 | F32: =C32+D32-E32 -> 0
A33: 账项调整 | C33: =SUM(C34:C37) -> 0 | D33: =SUM(D34:D37) -> 0 | E33: =SUM(E34:E37) -> 0 | F33: =SUM(F34:F37) -> 0
A34: =A13 -> 一、对子公司投资 | C34: ='明细表G7-2'!L63 -> 0 | D34: ='明细表G7-2'!N63 -> 0 | E34: ='明细表G7-2'!O63 -> 0 | F34: =C34+D34-E34 -> 0
A35: =A14 -> 二、对合营企业投资 | C35: ='明细表G7-2'!L71 -> 0 | D35: ='明细表G7-2'!N71 -> 0 | E35: ='明细表G7-2'!O71 -> 0 | F35: =C35+D35-E35 -> 0
A36: =A15 -> 三、对联营企业投资 | C36: ='明细表G7-2'!L78 -> 0 | D36: ='明细表G7-2'!N78 -> 0 | E36: ='明细表G7-2'!O78 -> 0 | F36: =C36+D36-E36 -> 0
A37: =A16 -> 0 | F37: =C37+D37-E37 -> 0
A38: 重分类调整 | C38: =SUM(C39:C42) -> 0 | D38: =SUM(D39:D42) -> 0 | E38: =SUM(E39:E42) -> 0 | F38: =SUM(F39:F42) -> 0
A39: =A18 -> 一、对子公司投资 | C39: ='明细表G7-2'!M62 -> 0 | D39: ='明细表G7-2'!N63 -> 0 | E39: ='明细表G7-2'!O63 -> 0 | F39: =C39+D39-E39 -> 0
A40: =A19 -> 二、对合营企业投资 | C40: ='明细表G7-2'!M71 -> 0 | D40: ='明细表G7-2'!P71 -> 0 | E40: ='明细表G7-2'!Q71 -> 0 | F40: =C40+D40-E40 -> 0
A41: =A20 -> 三、对联营企业投资 | C41: ='明细表G7-2'!M78 -> 0 | D41: ='明细表G7-2'!P78 -> 0 | E41: ='明细表G7-2'!Q78 -> 0 | F41: =C41+D41-E41 -> 0
A42: =A21 -> 0 | F42: =C42+D42-E42 -> 0
A43: 审定数2 | C43: =SUM(C44:C47) -> 0 | D43: =SUM(D44:D47) -> 0 | E43: =SUM(E44:E47) -> 0 | F43: =SUM(F44:F47) -> 0
A44: =A23 -> 一、对子公司投资 | C44: =C29+C34+C39 -> 0 | D44: =D29+D34+D39 -> 0 | E44: =E29+E34+E39 -> 0 | F44: =C44+D44-E44 -> 0
A45: =A24 -> 二、对合营企业投资 | C45: =C30+C35+C40 -> 0 | D45: =D30+D35+D40 -> 0 | E45: =E30+E35+E40 -> 0 | F45: =C45+D45-E45 -> 0
A46: =A25 -> 三、对联营企业投资 | C46: =C31+C36+C41 -> 0 | D46: =D31+D36+D41 -> 0 | E46: =E31+E36+E41 -> 0 | F46: =C46+D46-E46 -> 0
A47: =A26 -> 0 | C47: =C32+C37+C42 -> 0 | D47: =D32+D37+D42 -> 0 | E47: =E32+E37+E42 -> 0 | F47: =C47+D47-E47 -> 0
A48: 三、净值
A49: 审定数3 | C49: =SUM(C50:C53) -> 0 | D49: =SUM(D50:D53) -> 0 | E49: =SUM(E50:E53) -> 0 | F49: =SUM(F50:F53) -> 0
A50: =A8 -> 一、对子公司投资 | C50: =C23-C44 -> 0 | D50: =D23-D44 -> 0 | E50: =E23-E44 -> 0 | F50: =C50+D50-E50 -> 0
A51: =A9 -> 二、对合营企业投资 | C51: =C24-C45 -> 0 | D51: =D24-D45 -> 0 | E51: =E24-E45 -> 0 | F51: =C51+D51-E51 -> 0
A52: =A10 -> 三、对联营企业投资 | C52: =C25-C46 -> 0 | D52: =D25-D46 -> 0 | E52: =E25-E46 -> 0 | F52: =C52+D52-E52 -> 0
A53: =A11 -> 0 | C53: =C26-C47 -> 0 | D53: =D26-D47 -> 0 | E53: =E26-E47 -> 0 | F53: =C53+D53-E53 -> 0
A54: 试算平衡表数
A55: 差异数 | C55: =C49-C54 -> 0 | F55: =F49-F54 -> 0
A56: 1、审计说明：
A57: （1）期末净值较期初净值增加（负数为减少）： | E57: =IF(AND(C49=0,F49>0),1,(F49-C49)/C49) -> #DIV/0!
A58: 主要原因（比例超过30%的）：
A63: （2）情况说明：
A68: 2、审计结论：
A75: 编制说明：
A76: 1、原持有的对被投资单位不具有控制、共同控制或重大影响，并且在活跃市场中没有报价、公允价值不能可靠计量的
A77: 权益性投资（“三无投资”）按照《企业会计准则第22号——金融工具确认和计量》（CAS 22）进行处理。
A78: 2、如适用，根据1131号等审计准则和指南的要求编制，说明涉及事项内容、应对措施、审计结论或解决方法，
A79: 以及可能对审计报告的影响。
A80: A、风险评估结果和内控了解、测试情况（不适用则说明：不存在重大错报风险。)
A81: (识别和实际评估的重大错报风险、尤其识特别风险，以及对内控了解和控制测试情况〔采用综合方案时〕）；
A82: 提示：a、收入科目应当假定存在舞弊的特别风险，如不存在，应说明理由；
A83: b、涉及特别风险时，应当重点说明有关事项、应当措施、结果〔可索引有关底稿〕。
... A94: 参考结论：
A95: A、 | B95: 未见异常，可以确认。
A96: B、 | B96: 经审计调整后可确认。
A97: C、 | B97: 由于存在上述重大未调整事项（或审计范围受到限制无法获取充分、适当证据），不可确认。

Sheet 附注披露信息（上市公司）
A1: 致同会计师事务所
A2: 附注披露信息（上市公司）
A3: =底稿目录!A2 -> 被审计单位： | C3: =底稿目录!A4 -> 编制人： | F3: =底稿目录!A5 -> 编制日期： | K3: 索引号： | L3: =底稿目录!F6 -> 0
A4: =底稿目录!A3 -> 截止日：202X年12月31日 | C4: =底稿目录!A6 -> 复核人： | F4: =底稿目录!A7 -> 复核日期： | K4: 页次：
A5: 附注披露信息
A6: 长期股权投资
A8: 被投资单位 | B8: 期初余额（账面价值） | D8: 本期增减变动 | L8: 期末余额（账面价值） | M8: 减值准备期末余额
C9: 减值准备期初余额 | D9: 追加/新增投资 | E9: 减少投资 | F9: 权益法下 | G9: 其他综合 | H9: 其他权益变动 | I9: 宣告发放现金股利或利润 | J9: 计提减值准备 | K9: 其他
F10: 确认的 | G10: 收益调整
F11: 投资损益
A12: ①合营企业
A13: …
A15: 小 计
A16: ②联营企业
A17: …
A22: 小 计
A23: 合 计
A24: （长期资产本期进行减值测试的，应披露可收回金额的具体确定方法。可收回金额按公允价值减去处置费用后的净额确定的，应披露公允价值和处置费用的确定方式、关键参数及其确定依据。可收回金额按预计未来现金流量的现值确定的，应披露预测期的年限、预测期及稳定期的关键参数及其确定依据。前述信息与以前年度减值测试采用的信息或外部信息明显不一致的，或公司以前年度减值测试采用信息与当年实际情况明显不一致的，应披露差异原因。（15号文第十九条（十九）））
A26: 1、在子公司中的权益
A27: （1）企业集团的构成
A28: 子公司名称 | B28: 主要经营地 | C28: 注册地 | D28: 业务性质 | E28: 持股比例% | G28: 取得方式
E29: 直接 | F29: 间接
A30: ='被投资单位基本信息G7-4'!B12 -> 0 | B30: ='被投资单位基本信息G7-4'!F12 -> 0 | C30: ='被投资单位基本信息G7-4'!G12 -> 0 | D30: ='被投资单位基本信息G7-4'!H12 -> 0 | E30: ='被投资单位基本信息G7-4'!M12 -> 0 | F30: ='被投资单位基本信息G7-4'!N12 -> 0 | G30: ='被投资单位基本信息G7-4'!S12 -> 0
A31: ='被投资单位基本信息G7-4'!B13 -> 0 | B31: ='被投资单位基本信息G7-4'!F13 -> 0 | C31: ='被投资单位基本信息G7-4'!G13 -> 0 | D31: ='被投资单位基本信息G7-4'!H13 -> 0 | E31: ='被投资单位基本信息G7-4'!M13 -> 0 | F31: ='被投资单位基本信息G7-4'!N13 -> 0 | G31: ='被投资单位基本信息G7-4'!S13 -> 0
A32: ='被投资单位基本信息G7-4'!B14 -> 0 | B32: ='被投资单位基本信息G7-4'!F14 -> 0 | C32: ='被投资单位基本信息G7-4'!G14 -> 0 | D32: ='被投资单位基本信息G7-4'!H14 -> 0 | E32: ='被投资单位基本信息G7-4'!M14 -> 0 | F32: ='被投资单位基本信息G7-4'!N14 -> 0 | G32: ='被投资单位基本信息G7-4'!S14 -> 0
A33: ='被投资单位基本信息G7-4'!B15 -> 0 | B33: ='被投资单位基本信息G7-4'!F15 -> 0 | C33: ='被投资单位基本信息G7-4'!G15 -> 0 | D33: ='被投资单位基本信息G7-4'!H15 -> 0 | E33: ='被投资单位基本信息G7-4'!M15 -> 0 | F33: ='被投资单位基本信息G7-4'!N15 -> 0 | G33: ='被投资单位基本信息G7-4'!S15 -> 0
A34: ='被投资单位基本信息G7-4'!B16 -> 0 | B34: ='被投资单位基本信息G7-4'!F16 -> 0 | C34: ='被投资单位基本信息G7-4'!G16 -> 0 | D34: ='被投资单位基本信息G7-4'!H16 -> 0 | E34: ='被投资单位基本信息G7-4'!M16 -> 0 | F34: ='被投资单位基本信息G7-4'!N16 -> 0 | G34: ='被投资单位基本信息G7-4'!S16 -> 0
A35: ='被投资单位基本信息G7-4'!B17 -> 0 | B35: ='被投资单位基本信息G7-4'!F17 -> 0 | C35: ='被投资单位基本信息G7-4'!G17 -> 0 | D35: ='被投资单位基本信息G7-4'!H17 -> 0 | E35: ='被投资单位基本信息G7-4'!M17 -> 0 | F35: ='被投资单位基本信息G7-4'!N17 -> 0 | G35: ='被投资单位基本信息G7-4'!S17 -> 0
A36: ='被投资单位基本信息G7-4'!B18 -> 0 | B36: ='被投资单位基本信息G7-4'!F18 -> 0 | C36: ='被投资单位基本信息G7-4'!G18 -> 0 | D36: ='被投资单位基本信息G7-4'!H18 -> 0 | E36: ='被投资单位基本信息G7-4'!M18 -> 0 | F36: ='被投资单位基本信息G7-4'!N18 -> 0 | G36: ='被投资单位基本信息G7-4'!S18 -> 0
A37: ='被投资单位基本信息G7-4'!B19 -> 0 | B37: ='被投资单位基本信息G7-4'!F19 -> 0 | C37: ='被投资单位基本信息G7-4'!G19 -> 0 | D37: ='被投资单位基本信息G7-4'!H19 -> 0 | E37: ='被投资单位基本信息G7-4'!M19 -> 0 | F37: ='被投资单位基本信息G7-4'!N19 -> 0 | G37: ='被投资单位基本信息G7-4'!S19 -> 0
A38: ='被投资单位基本信息G7-4'!B20 -> 0 | B38: ='被投资单位基本信息G7-4'!F20 -> 0 | C38: ='被投资单位基本信息G7-4'!G20 -> 0 | D38: ='被投资单位基本信息G7-4'!H20 -> 0 | E38: ='被投资单位基本信息G7-4'!M20 -> 0 | F38: ='被投资单位基本信息G7-4'!N20 -> 0 | G38: ='被投资单位基本信息G7-4'!S20 -> 0
A39: ='被投资单位基本信息G7-4'!B21 -> …… | B39: ='被投资单位基本信息G7-4'!F21 -> 0 | C39: ='被投资单位基本信息G7-4'!G21 -> 0 | D39: ='被投资单位基本信息G7-4'!H21 -> 0 | E39: ='被投资单位基本信息G7-4'!M21 -> 0 | F39: ='被投资单位基本信息G7-4'!N21 -> 0 | G39: ='被投资单位基本信息G7-4'!S21 -> 0
A40: 说明：
A41: （1）子公司的持股比例不同于表决权比例的，应说明表决权比例及差异原因。
A42: （2）持有其他主体半数或以下表决权但仍控制该主体、以及公司持有其他主体半数以上表决权但不控制该主体的，公司应披露相关判断和依据。
A43: （3）披露确定公司是代理人还是委托人的判断和依据。
A44: （4）对于纳入合并范围的重要的结构化主体，应披露控制的相关判断和依据。
A45: 【例如资产证券化，公司应根据《信贷资产证券化试点管理办法》和《企业会计准则第23号-金融资产转移》，披露金融资产证券化业务的主要交易安排及其会计处理。涉及非金融资产的资产证券化业务，参照《信贷资产证券化试点管理办法》和《企业会计准则第23号-金融资产转移》的有关规定，披露资产证券化业务的主要交易安排及其会计处理。同时，应详细说明资产证券化业务的破产隔离条款。
A46: （本集团于本年度内将一笔金额为人民币[X]元（200Y年：人民币[X]元）的应收账款证券化转让给由XX银行设立的XX信托计划。作为转让的一部分，本集团就该笔应收账款的预期损失向信托计划提供信用担保。因此，本集团继续全额确认应收账款的账面金额并将因转让而收取的现金确认为抵押借款。在200X年12月31日，被转让的应收账款账面金额为人民币[X]元（200Y年：人民币[X]元），而相关负债的账面金额为人民币[X]元。）】
A47: （2）重要的非全资子公司
A48: 【提示：如果单个非全资子公司的少数股东权益对企业集团而言并不重要，则不需要披露下述信息。】
A49: 子公司名称 | B49: 少数股东持股比例% | C49: 本期归属于少数股东的损益 | D49: 本期向少数股东宣告分派的股利 | E49: 期末少数股东权益余额
A55: 说明：持股比例不同于表决权比例的，应说明表决权比例及差异原因
A56: （3）重要非全资子公司的主要财务信息：（划分为持有待售的除外）
A57: 【提示：如果单个非全资子公司的少数股东权益对企业集团而言并不重要，则不需要披露下述信息。】
A58: 子公司名称 | B58: 期末数
B59: 流动资产 | C59: 非流动资产 | D59: 资产合计 | E59: 流动负债 | F59: 非流动负债 | G59: 负债合计
A65: 续（1）：
A66: 子公司名称 | B66: 期初数
B67: 流动资产 | C67: 非流动资产 | D67: 资产合计 | E67: 流动负债 | F67: 非流动负债 | G67: 负债合计
A73: 续（2）：
A74: 子公司名称 | B74: 本期发生额 | F74: 上期发生额
B75: 营业收入 | C75: 净利润 | D75: 综合收益总额 | E75: 经营活动现金流量 | F75: 营业收入 | G75: 净利润 | H75: 综合收益总额 | I75: 经营活动现金流量
A81: 【提示：上述财务数据以合并日子公司可辨认资产和负债的公允价值为基础进行调整；被划分为持有待售资产的，不需要披露该子公司的上述财务信息。】
A82: （4）使用资产和清偿负债存在的重大限制（不适用的删除）
A83: 说明：（1）限制内容，包括对母公司或子公司与集团内其他主体相互转移现金或其他资产的限制，以及对集团内主体之间发放股利或进行利润分配、发放或收回贷款或垫款等的限制；
A84: （2）子公司少数股东享有保护性权利，并且该保护性权利对使用集团资产或清偿集团负债的能力存在重大限制的，披露限制的性质和程度；
A85: （3）限制涉及的资产和负债在合并财务报表中的金额。
A86: （5）向纳入合并财务报表范围的结构化主体提供的财务支持或其他支持
A87: 说明：应披露与结构化主体相关的风险信息，向结构化主体提供财务支持或其他支持，包括帮助结构化主体取得财务支持：
A88: （1）有合同约定的，披露财务支持的合同条款包括可能导致企业承担损失的事项或情况；
A89: （2）在没有合同约定的情况下，披露所提供支持的类型、金额及原因，包括帮助该结构化主体获得财务支持的情况。其中，本期对以前未纳入合并财务报表范围的结构化主体提供了财务支持或其他支持并且该支持导致控制了该结构化主体的，披露决定提供支持的相关因素；
A90: （3）存在提供支持意图的，披露该意图，包括帮助该结构化主体获得财务支持的意图。
A91: （6）在子公司的所有者权益份额发生变化且仍控制子公司的交易
A92: （15号文第三十五条，公司在子公司的所有者权益份额发生变化且该变化未影响公司对子公司的控制权的，应披露在子公司所有者权益份额的变化情况、对归属于母公司所有者权益和少数股东权益的影响金额，以及上述金额的计算依据。）
... A95: ②交易对于少数股东权益及归属于母公司所有者权益的影响：
A96: 项 目 | B96: 公司1 | C96: 公司2 | D96: 公司3 | E96: 公司4 | F96: 公司5 | G96: 公司6
A97: 购买成本/处置对价：
A98: 现金
A99: 非现金资产的公允价值
A100: 发行或承担的债务的账面价值
A101: 发行的权益性证券的面值
A102: 或有对价
A103: 购买成本/处置对价合计
A104: 减：按取得/处置的股权比例计算的子公司净资产份额
A105: 差额
A106: 其中：调整资本公积
A107: 调整盈余公积
A108: 调整未分配利润 | B108: ='子公司后续计量测试表G7-10'!G21 -> 0 | C108: ='子公司后续计量测试表G7-10'!H21 -> 0 | D108: ='子公司后续计量测试表G7-10'!I21 -> 0 | E108: ='子公司后续计量测试表G7-10'!G34 -> 0 | F108: ='子公司后续计量测试表G7-10'!H34 -> 0 | G108: ='子公司后续计量测试表G7-10'!I34 -> 0
A109: 2、在合营安排或联营企业中的权益
A110: （1）重要的合营企业或联营企业
A111: 合营企业或联营企业名称 | B111: 主要经营地 | C111: 注册地 | D111: 业务性质 | E111: 持股比例(%) | G111: 对合营企业或联营企业投资的会计处理方法
E112: 直接 | F112: 间接
A113: ①合营企业
A114: ='被投资单位基本信息G7-4'!B23 -> 0 | B114: ='被投资单位基本信息G7-4'!F23 -> 0 | C114: ='被投资单位基本信息G7-4'!G23 -> 0 | D114: ='被投资单位基本信息G7-4'!H23 -> 0 | E114: ='被投资单位基本信息G7-4'!M23 -> 0 | F114: ='被投资单位基本信息G7-4'!N23 -> 0 | G114: ='被投资单位基本信息G7-4'!T23 -> 权益法
A115: ='被投资单位基本信息G7-4'!B24 -> 0 | B115: ='被投资单位基本信息G7-4'!F24 -> 0 | C115: ='被投资单位基本信息G7-4'!G24 -> 0 | D115: ='被投资单位基本信息G7-4'!H24 -> 0 | E115: ='被投资单位基本信息G7-4'!M24 -> 0 | F115: ='被投资单位基本信息G7-4'!N24 -> 0 | G115: ='被投资单位基本信息G7-4'!T24 -> 0
A116: ='被投资单位基本信息G7-4'!B25 -> 0 | B116: ='被投资单位基本信息G7-4'!F25 -> 0 | C116: ='被投资单位基本信息G7-4'!G25 -> 0 | D116: ='被投资单位基本信息G7-4'!H25 -> 0 | E116: ='被投资单位基本信息G7-4'!M25 -> 0 | F116: ='被投资单位基本信息G7-4'!N25 -> 0 | G116: ='被投资单位基本信息G7-4'!T25 -> 0
A117: ='被投资单位基本信息G7-4'!B26 -> 0 | B117: ='被投资单位基本信息G7-4'!F26 -> 0 | C117: ='被投资单位基本信息G7-4'!G26 -> 0 | D117: ='被投资单位基本信息G7-4'!H26 -> 0 | E117: ='被投资单位基本信息G7-4'!M26 -> 0 | F117: ='被投资单位基本信息G7-4'!N26 -> 0 | G117: ='被投资单位基本信息G7-4'!T26 -> 0
A118: ='被投资单位基本信息G7-4'!B27 -> …… | B118: ='被投资单位基本信息G7-4'!F27 -> 0 | C118: ='被投资单位基本信息G7-4'!G27 -> 0 | D118: ='被投资单位基本信息G7-4'!H27 -> 0 | E118: ='被投资单位基本信息G7-4'!M27 -> 0 | F118: ='被投资单位基本信息G7-4'!N27 -> 0 | G118: ='被投资单位基本信息G7-4'!T27 -> 0
A119: ②联营企业
A120: ='被投资单位基本信息G7-4'!B29 -> 0 | B120: ='被投资单位基本信息G7-4'!F29 -> 0 | C120: ='被投资单位基本信息G7-4'!G29 -> 0 | D120: ='被投资单位基本信息G7-4'!H29 -> 0 | E120: ='被投资单位基本信息G7-4'!M29 -> 0 | F120: ='被投资单位基本信息G7-4'!N29 -> 0 | G120: ='被投资单位基本信息G7-4'!T29 -> 权益法
A121: ='被投资单位基本信息G7-4'!B30 -> 0 | B121: ='被投资单位基本信息G7-4'!F30 -> 0 | C121: ='被投资单位基本信息G7-4'!G30 -> 0 | D121: ='被投资单位基本信息G7-4'!H30 -> 0 | E121: ='被投资单位基本信息G7-4'!M30 -> 0 | F121: ='被投资单位基本信息G7-4'!N30 -> 0 | G121: ='被投资单位基本信息G7-4'!T30 -> 0
A122: ='被投资单位基本信息G7-4'!B31 -> 0 | B122: ='被投资单位基本信息G7-4'!F31 -> 0 | C122: ='被投资单位基本信息G7-4'!G31 -> 0 | D122: ='被投资单位基本信息G7-4'!H31 -> 0 | E122: ='被投资单位基本信息G7-4'!M31 -> 0 | F122: ='被投资单位基本信息G7-4'!N31 -> 0 | G122: ='被投资单位基本信息G7-4'!T31 -> 0
A123: ='被投资单位基本信息G7-4'!B32 -> 0 | B123: ='被投资单位基本信息G7-4'!F32 -> 0 | C123: ='被投资单位基本信息G7-4'!G32 -> 0 | D123: ='被投资单位基本信息G7-4'!H32 -> 0 | E123: ='被投资单位基本信息G7-4'!M32 -> 0 | F123: ='被投资单位基本信息G7-4'!N32 -> 0 | G123: ='被投资单位基本信息G7-4'!T32 -> 0
A124: ='被投资单位基本信息G7-4'!B33 -> …… | B124: ='被投资单位基本信息G7-4'!F33 -> 0 | C124: ='被投资单位基本信息G7-4'!G33 -> 0 | D124: ='被投资单位基本信息G7-4'!H33 -> 0 | E124: ='被投资单位基本信息G7-4'!M33 -> 0 | F124: ='被投资单位基本信息G7-4'!N33 -> 0 | G124: ='被投资单位基本信息G7-4'!T33 -> 0
A125: 说明：
A126: （1）持股比例不同于表决权比例的，应说明表决权比例及差异原因。
A127: （2）持有其他主体20%以下表决权但具有重大影响，或者持有其他主体20%或以上表决权但不具有重大影响的，应披露相关判断和依据。
A128: （2）重要合营企业的主要财务信息：（划分为持有待售的除外）
A129: （主要财务信息按照权益法调整后的金额披露；）
...

Sheet 附注披露信息（国企）
A1: 致同会计师事务所
A2: 附注披露信息（国企）
A3: =底稿目录!A2 -> 被审计单位： | D3: =底稿目录!A4 -> 编制人： | H3: =底稿目录!A5 -> 编制日期： | K3: 索引号： | L3: =底稿目录!F7 -> 0
A4: =底稿目录!A3 -> 截止日：202X年12月31日 | D4: =底稿目录!A6 -> 复核人： | H4: =底稿目录!A7 -> 复核日期： | K4: 页次：
A5: 附注披露信息
A6: 七、企业合并及合并财务报表
A7: （一）本期纳入合并报表范围的子公司基本情况
A8: （企业应当按下列格式披露纳入报表合并范围的全部子公司主要情况；大型企业集团合并报表范围可以披露到二级子公司，集团所属重要子公司不分级次全部披露）
A9: 序号 | B9: 企业名称 | C9: 级次 | D9: 企业类型 | E9: 注册地 | F9: 主要经营地 | G9: 业务性质 | H9: 实收资本 | I9: 认缴持股比例 （%） | J9: 实缴持股比例（%） | K9: 享有的表决权（%） | L9: 投资额 | M9: 取得方式
A10: 1 | B10: ='被投资单位基本信息G7-4'!B12 -> 0 | C10: ='被投资单位基本信息G7-4'!C12 -> 0 | D10: ='被投资单位基本信息G7-4'!D12 -> 0 | E10: ='被投资单位基本信息G7-4'!G12 -> 0 | F10: ='被投资单位基本信息G7-4'!F12 -> 0 | G10: ='被投资单位基本信息G7-4'!H12 -> 0 | H10: ='被投资单位基本信息G7-4'!I12 -> 0 | J10: ='被投资单位基本信息G7-4'!M12+'被投资单位基本信息G7-4'!N12 -> 0 | K10: ='被投资单位基本信息G7-4'!O12 -> 0 | L10: ='明细表G7-2'!AI16 -> 0 | M10: ='被投资单位基本信息G7-4'!S12 -> 0
A11: 2 | B11: ='被投资单位基本信息G7-4'!B13 -> 0 | C11: ='被投资单位基本信息G7-4'!C13 -> 0 | D11: ='被投资单位基本信息G7-4'!D13 -> 0 | E11: ='被投资单位基本信息G7-4'!G13 -> 0 | F11: ='被投资单位基本信息G7-4'!F13 -> 0 | G11: ='被投资单位基本信息G7-4'!H13 -> 0 | H11: ='被投资单位基本信息G7-4'!I13 -> 0 | J11: ='被投资单位基本信息G7-4'!M13+'被投资单位基本信息G7-4'!N13 -> 0 | K11: ='被投资单位基本信息G7-4'!O13 -> 0 | L11: ='明细表G7-2'!AI17 -> 0 | M11: ='被投资单位基本信息G7-4'!S13 -> 0
A12: 3 | B12: ='被投资单位基本信息G7-4'!B14 -> 0 | C12: ='被投资单位基本信息G7-4'!C14 -> 0 | D12: ='被投资单位基本信息G7-4'!D14 -> 0 | E12: ='被投资单位基本信息G7-4'!G14 -> 0 | F12: ='被投资单位基本信息G7-4'!F14 -> 0 | G12: ='被投资单位基本信息G7-4'!H14 -> 0 | H12: ='被投资单位基本信息G7-4'!I14 -> 0 | J12: ='被投资单位基本信息G7-4'!M14+'被投资单位基本信息G7-4'!N14 -> 0 | K12: ='被投资单位基本信息G7-4'!O14 -> 0 | L12: ='明细表G7-2'!AI18 -> 0 | M12: ='被投资单位基本信息G7-4'!S14 -> 0
A13: 4 | B13: ='被投资单位基本信息G7-4'!B15 -> 0 | C13: ='被投资单位基本信息G7-4'!C15 -> 0 | D13: ='被投资单位基本信息G7-4'!D15 -> 0 | E13: ='被投资单位基本信息G7-4'!G15 -> 0 | F13: ='被投资单位基本信息G7-4'!F15 -> 0 | G13: ='被投资单位基本信息G7-4'!H15 -> 0 | H13: ='被投资单位基本信息G7-4'!I15 -> 0 | J13: ='被投资单位基本信息G7-4'!M15+'被投资单位基本信息G7-4'!N15 -> 0 | K13: ='被投资单位基本信息G7-4'!O15 -> 0 | L13: ='明细表G7-2'!AI19 -> 0 | M13: ='被投资单位基本信息G7-4'!S15 -> 0
A14: 5 | B14: ='被投资单位基本信息G7-4'!B16 -> 0 | C14: ='被投资单位基本信息G7-4'!C16 -> 0 | D14: ='被投资单位基本信息G7-4'!D16 -> 0 | E14: ='被投资单位基本信息G7-4'!G16 -> 0 | F14: ='被投资单位基本信息G7-4'!F16 -> 0 | G14: ='被投资单位基本信息G7-4'!H16 -> 0 | H14: ='被投资单位基本信息G7-4'!I16 -> 0 | J14: ='被投资单位基本信息G7-4'!M16+'被投资单位基本信息G7-4'!N16 -> 0 | K14: ='被投资单位基本信息G7-4'!O16 -> 0 | L14: ='明细表G7-2'!AI20 -> 0 | M14: ='被投资单位基本信息G7-4'!S16 -> 0
A15: 6 | B15: ='被投资单位基本信息G7-4'!B17 -> 0 | C15: ='被投资单位基本信息G7-4'!C17 -> 0 | D15: ='被投资单位基本信息G7-4'!D17 -> 0 | E15: ='被投资单位基本信息G7-4'!G17 -> 0 | F15: ='被投资单位基本信息G7-4'!F17 -> 0 | G15: ='被投资单位基本信息G7-4'!H17 -> 0 | H15: ='被投资单位基本信息G7-4'!I17 -> 0 | J15: ='被投资单位基本信息G7-4'!M17+'被投资单位基本信息G7-4'!N17 -> 0 | K15: ='被投资单位基本信息G7-4'!O17 -> 0 | L15: ='明细表G7-2'!AI21 -> 0 | M15: ='被投资单位基本信息G7-4'!S17 -> 0
A16: 7 | B16: ='被投资单位基本信息G7-4'!B18 -> 0 | C16: ='被投资单位基本信息G7-4'!C18 -> 0 | D16: ='被投资单位基本信息G7-4'!D18 -> 0 | E16: ='被投资单位基本信息G7-4'!G18 -> 0 | F16: ='被投资单位基本信息G7-4'!F18 -> 0 | G16: ='被投资单位基本信息G7-4'!H18 -> 0 | H16: ='被投资单位基本信息G7-4'!I18 -> 0 | J16: ='被投资单位基本信息G7-4'!M18+'被投资单位基本信息G7-4'!N18 -> 0 | K16: ='被投资单位基本信息G7-4'!O18 -> 0 | L16: ='明细表G7-2'!AI22 -> 0 | M16: ='被投资单位基本信息G7-4'!S18 -> 0
A17: 8 | B17: ='被投资单位基本信息G7-4'!B19 -> 0 | C17: ='被投资单位基本信息G7-4'!C19 -> 0 | D17: ='被投资单位基本信息G7-4'!D19 -> 0 | E17: ='被投资单位基本信息G7-4'!G19 -> 0 | F17: ='被投资单位基本信息G7-4'!F19 -> 0 | G17: ='被投资单位基本信息G7-4'!H19 -> 0 | H17: ='被投资单位基本信息G7-4'!I19 -> 0 | J17: ='被投资单位基本信息G7-4'!M19+'被投资单位基本信息G7-4'!N19 -> 0 | K17: ='被投资单位基本信息G7-4'!O19 -> 0 | L17: ='明细表G7-2'!AI23 -> 0 | M17: ='被投资单位基本信息G7-4'!S19 -> 0
A18: 9 | B18: ='被投资单位基本信息G7-4'!B20 -> 0 | C18: ='被投资单位基本信息G7-4'!C20 -> 0 | D18: ='被投资单位基本信息G7-4'!D20 -> 0 | E18: ='被投资单位基本信息G7-4'!G20 -> 0 | F18: ='被投资单位基本信息G7-4'!F20 -> 0 | G18: ='被投资单位基本信息G7-4'!H20 -> 0 | H18: ='被投资单位基本信息G7-4'!I20 -> 0 | J18: ='被投资单位基本信息G7-4'!M20+'被投资单位基本信息G7-4'!N20 -> 0 | K18: ='被投资单位基本信息G7-4'!O20 -> 0 | L18: ='明细表G7-2'!AI24 -> 0 | M18: ='被投资单位基本信息G7-4'!S20 -> 0
A19: 10 | B19: ='被投资单位基本信息G7-4'!B21 -> …… | C19: ='被投资单位基本信息G7-4'!C21 -> 0 | D19: ='被投资单位基本信息G7-4'!D21 -> 0 | E19: ='被投资单位基本信息G7-4'!G21 -> 0 | F19: ='被投资单位基本信息G7-4'!F21 -> 0 | G19: ='被投资单位基本信息G7-4'!H21 -> 0 | H19: ='被投资单位基本信息G7-4'!I21 -> 0 | J19: ='被投资单位基本信息G7-4'!M21+'被投资单位基本信息G7-4'!N21 -> 0 | K19: ='被投资单位基本信息G7-4'!O21 -> 0 | L19: ='明细表G7-2'!AI25 -> 0 | M19: ='被投资单位基本信息G7-4'!S21 -> 0
A20: （注：企业类型：1.境内非金融子企业，2.境内金融子企业，3.境外子企业，4.事业单位，5.基建单位；
A21: 取得方式：1.投资设立，2.同一控制下的企业合并，3.非同一控制下的企业合并，4.其他）
A22: （注：子公司的持股比例不同于表决权比例的，应说明表决权比例及差异原因。）
A23: （注：级次为在整个中央企业集团内的法人级次）
A24: （二）母公司拥有被投资单位表决权不足半数但能对被投资单位形成控制的原因
A25: 序号 | B25: 企业名称 | C25: 认缴持股 比例（%） | D25: 享有的表决权 | E25: 注册资本 | F25: 投资额 | G25: 级次 | H25: 纳入合并范围原因
B26: =IF('被投资单位基本信息G7-4'!O12<=0.5,'被投资单位基本信息G7-4'!B12,0) -> 0 | C26: =IF('被投资单位基本信息G7-4'!O12<=0.5,'被投资单位基本信息G7-4'!M12+'被投资单位基本信息G7-4'!N12,0) -> 0 | D26: =IF('被投资单位基本信息G7-4'!O12<=0.5,'被投资单位基本信息G7-4'!O12,0) -> 0 | E26: =IF('被投资单位基本信息G7-4'!O12<=0.5,'被投资单位基本信息G7-4'!I12,0) -> 0 | F26: =IF('被投资单位基本信息G7-4'!O12<=0.5,'被投资单位基本信息G7-4'!J12,0) -> 0 | G26: =IF('被投资单位基本信息G7-4'!O12<=0.5,'被投资单位基本信息G7-4'!C12,0) -> 0 | H26: =IF('被投资单位基本信息G7-4'!O12<=0.5,'被投资单位基本信息G7-4'!Q12,0) -> 0
B27: =IF('被投资单位基本信息G7-4'!O13<=0.5,'被投资单位基本信息G7-4'!B13,0) -> 0 | C27: =IF('被投资单位基本信息G7-4'!O13<=0.5,'被投资单位基本信息G7-4'!M13+'被投资单位基本信息G7-4'!N13,0) -> 0 | D27: =IF('被投资单位基本信息G7-4'!O13<=0.5,'被投资单位基本信息G7-4'!O13,0) -> 0 | E27: =IF('被投资单位基本信息G7-4'!O13<=0.5,'被投资单位基本信息G7-4'!I13,0) -> 0 | F27: =IF('被投资单位基本信息G7-4'!O13<=0.5,'被投资单位基本信息G7-4'!J13,0) -> 0 | G27: =IF('被投资单位基本信息G7-4'!O13<=0.5,'被投资单位基本信息G7-4'!C13,0) -> 0 | H27: =IF('被投资单位基本信息G7-4'!O13<=0.5,'被投资单位基本信息G7-4'!Q13,0) -> 0
B28: =IF('被投资单位基本信息G7-4'!O14<=0.5,'被投资单位基本信息G7-4'!B14,0) -> 0 | C28: =IF('被投资单位基本信息G7-4'!O14<=0.5,'被投资单位基本信息G7-4'!M14+'被投资单位基本信息G7-4'!N14,0) -> 0 | D28: =IF('被投资单位基本信息G7-4'!O14<=0.5,'被投资单位基本信息G7-4'!O14,0) -> 0 | E28: =IF('被投资单位基本信息G7-4'!O14<=0.5,'被投资单位基本信息G7-4'!I14,0) -> 0 | F28: =IF('被投资单位基本信息G7-4'!O14<=0.5,'被投资单位基本信息G7-4'!J14,0) -> 0 | G28: =IF('被投资单位基本信息G7-4'!O14<=0.5,'被投资单位基本信息G7-4'!C14,0) -> 0 | H28: =IF('被投资单位基本信息G7-4'!O14<=0.5,'被投资单位基本信息G7-4'!Q14,0) -> 0
B29: =IF('被投资单位基本信息G7-4'!O15<=0.5,'被投资单位基本信息G7-4'!B15,0) -> 0 | C29: =IF('被投资单位基本信息G7-4'!O15<=0.5,'被投资单位基本信息G7-4'!M15+'被投资单位基本信息G7-4'!N15,0) -> 0 | D29: =IF('被投资单位基本信息G7-4'!O15<=0.5,'被投资单位基本信息G7-4'!O15,0) -> 0 | E29: =IF('被投资单位基本信息G7-4'!O15<=0.5,'被投资单位基本信息G7-4'!I15,0) -> 0 | F29: =IF('被投资单位基本信息G7-4'!O15<=0.5,'被投资单位基本信息G7-4'!J15,0) -> 0 | G29: =IF('被投资单位基本信息G7-4'!O15<=0.5,'被投资单位基本信息G7-4'!C15,0) -> 0 | H29: =IF('被投资单位基本信息G7-4'!O15<=0.5,'被投资单位基本信息G7-4'!Q15,0) -> 0
B30: =IF('被投资单位基本信息G7-4'!O16<=0.5,'被投资单位基本信息G7-4'!B16,0) -> 0 | C30: =IF('被投资单位基本信息G7-4'!O16<=0.5,'被投资单位基本信息G7-4'!M16+'被投资单位基本信息G7-4'!N16,0) -> 0 | D30: =IF('被投资单位基本信息G7-4'!O16<=0.5,'被投资单位基本信息G7-4'!O16,0) -> 0 | E30: =IF('被投资单位基本信息G7-4'!O16<=0.5,'被投资单位基本信息G7-4'!I16,0) -> 0 | F30: =IF('被投资单位基本信息G7-4'!O16<=0.5,'被投资单位基本信息G7-4'!J16,0) -> 0 | G30: =IF('被投资单位基本信息G7-4'!O16<=0.5,'被投资单位基本信息G7-4'!C16,0) -> 0 | H30: =IF('被投资单位基本信息G7-4'!O16<=0.5,'被投资单位基本信息G7-4'!Q16,0) -> 0
B31: =IF('被投资单位基本信息G7-4'!O17<=0.5,'被投资单位基本信息G7-4'!B17,0) -> 0 | C31: =IF('被投资单位基本信息G7-4'!O17<=0.5,'被投资单位基本信息G7-4'!M17+'被投资单位基本信息G7-4'!N17,0) -> 0 | D31: =IF('被投资单位基本信息G7-4'!O17<=0.5,'被投资单位基本信息G7-4'!O17,0) -> 0 | E31: =IF('被投资单位基本信息G7-4'!O17<=0.5,'被投资单位基本信息G7-4'!I17,0) -> 0 | F31: =IF('被投资单位基本信息G7-4'!O17<=0.5,'被投资单位基本信息G7-4'!J17,0) -> 0 | G31: =IF('被投资单位基本信息G7-4'!O17<=0.5,'被投资单位基本信息G7-4'!C17,0) -> 0 | H31: =IF('被投资单位基本信息G7-4'!O17<=0.5,'被投资单位基本信息G7-4'!Q17,0) -> 0
B32: =IF('被投资单位基本信息G7-4'!O18<=0.5,'被投资单位基本信息G7-4'!B18,0) -> 0 | C32: =IF('被投资单位基本信息G7-4'!O18<=0.5,'被投资单位基本信息G7-4'!M18+'被投资单位基本信息G7-4'!N18,0) -> 0 | D32: =IF('被投资单位基本信息G7-4'!O18<=0.5,'被投资单位基本信息G7-4'!O18,0) -> 0 | E32: =IF('被投资单位基本信息G7-4'!O18<=0.5,'被投资单位基本信息G7-4'!I18,0) -> 0 | F32: =IF('被投资单位基本信息G7-4'!O18<=0.5,'被投资单位基本信息G7-4'!J18,0) -> 0 | G32: =IF('被投资单位基本信息G7-4'!O18<=0.5,'被投资单位基本信息G7-4'!C18,0) -> 0 | H32: =IF('被投资单位基本信息G7-4'!O18<=0.5,'被投资单位基本信息G7-4'!Q18,0) -> 0
B33: =IF('被投资单位基本信息G7-4'!O19<=0.5,'被投资单位基本信息G7-4'!B19,0) -> 0 | C33: =IF('被投资单位基本信息G7-4'!O19<=0.5,'被投资单位基本信息G7-4'!M19+'被投资单位基本信息G7-4'!N19,0) -> 0 | D33: =IF('被投资单位基本信息G7-4'!O19<=0.5,'被投资单位基本信息G7-4'!O19,0) -> 0 | E33: =IF('被投资单位基本信息G7-4'!O19<=0.5,'被投资单位基本信息G7-4'!I19,0) -> 0 | F33: =IF('被投资单位基本信息G7-4'!O19<=0.5,'被投资单位基本信息G7-4'!J19,0) -> 0 | G33: =IF('被投资单位基本信息G7-4'!O19<=0.5,'被投资单位基本信息G7-4'!C19,0) -> 0 | H33: =IF('被投资单位基本信息G7-4'!O19<=0.5,'被投资单位基本信息G7-4'!Q19,0) -> 0
B34: =IF('被投资单位基本信息G7-4'!O20<=0.5,'被投资单位基本信息G7-4'!B20,0) -> 0 | C34: =IF('被投资单位基本信息G7-4'!O20<=0.5,'被投资单位基本信息G7-4'!M20+'被投资单位基本信息G7-4'!N20,0) -> 0 | D34: =IF('被投资单位基本信息G7-4'!O20<=0.5,'被投资单位基本信息G7-4'!O20,0) -> 0 | E34: =IF('被投资单位基本信息G7-4'!O20<=0.5,'被投资单位基本信息G7-4'!I20,0) -> 0 | F34: =IF('被投资单位基本信息G7-4'!O20<=0.5,'被投资单位基本信息G7-4'!J20,0) -> 0 | G34: =IF('被投资单位基本信息G7-4'!O20<=0.5,'被投资单位基本信息G7-4'!C20,0) -> 0 | H34: =IF('被投资单位基本信息G7-4'!O20<=0.5,'被投资单位基本信息G7-4'!Q20,0) -> 0
B35: =IF('被投资单位基本信息G7-4'!O21<=0.5,'被投资单位基本信息G7-4'!B21,0) -> …… | C35: =IF('被投资单位基本信息G7-4'!O21<=0.5,'被投资单位基本信息G7-4'!M21+'被投资单位基本信息G7-4'!N21,0) -> 0 | D35: =IF('被投资单位基本信息G7-4'!O21<=0.5,'被投资单位基本信息G7-4'!O21,0) -> 0 | E35: =IF('被投资单位基本信息G7-4'!O21<=0.5,'被投资单位基本信息G7-4'!I21,0) -> 0 | F35: =IF('被投资单位基本信息G7-4'!O21<=0.5,'被投资单位基本信息G7-4'!J21,0) -> 0 | G35: =IF('被投资单位基本信息G7-4'!O21<=0.5,'被投资单位基本信息G7-4'!C21,0) -> 0 | H35: =IF('被投资单位基本信息G7-4'!O21<=0.5,'被投资单位基本信息G7-4'!Q21,0) -> 0
A36: （三）母公司直接或通过其他子公司间接拥有被投资单位半数以上的表决权但未能对其形成控制的原因
A37: 序号 | B37: 企业名称 | C37: 认缴持股 比例（%） | D37: 享有的表决权 | E37: 注册资本 | F37: 投资额 | G37: 级次 | H37: 未纳入合并范围原因
B38: 合营企业
B39: =IF('被投资单位基本信息G7-4'!M23+'被投资单位基本信息G7-4'!N23>0.5,'被投资单位基本信息G7-4'!B23,0) -> 0 | C39: =IF('被投资单位基本信息G7-4'!M23+'被投资单位基本信息G7-4'!N23>0.5,'被投资单位基本信息G7-4'!M23+'被投资单位基本信息G7-4'!N23,0) -> 0 | D39: =IF('被投资单位基本信息G7-4'!M23+'被投资单位基本信息G7-4'!N23>0.5,'被投资单位基本信息G7-4'!O23,0) -> 0 | E39: =IF('被投资单位基本信息G7-4'!M23+'被投资单位基本信息G7-4'!N23>0.5,'被投资单位基本信息G7-4'!I23,0) -> 0 | F39: =IF('被投资单位基本信息G7-4'!M23+'被投资单位基本信息G7-4'!N23>0.5,'被投资单位基本信息G7-4'!J23,0) -> 0 | G39: =IF('被投资单位基本信息G7-4'!M23+'被投资单位基本信息G7-4'!N23>0.5,'被投资单位基本信息G7-4'!C23,0) -> 0 | H39: =IF('被投资单位基本信息G7-4'!M23+'被投资单位基本信息G7-4'!N23>0.5,'被投资单位基本信息G7-4'!R23,0) -> 0
B40: =IF('被投资单位基本信息G7-4'!M24+'被投资单位基本信息G7-4'!N24>0.5,'被投资单位基本信息G7-4'!B24,0) -> 0 | C40: =IF('被投资单位基本信息G7-4'!M24+'被投资单位基本信息G7-4'!N24>0.5,'被投资单位基本信息G7-4'!M24+'被投资单位基本信息G7-4'!N24,0) -> 0 | D40: =IF('被投资单位基本信息G7-4'!M24+'被投资单位基本信息G7-4'!N24>0.5,'被投资单位基本信息G7-4'!O24,0) -> 0 | E40: =IF('被投资单位基本信息G7-4'!M24+'被投资单位基本信息G7-4'!N24>0.5,'被投资单位基本信息G7-4'!I24,0) -> 0 | F40: =IF('被投资单位基本信息G7-4'!M24+'被投资单位基本信息G7-4'!N24>0.5,'被投资单位基本信息G7-4'!J24,0) -> 0 | G40: =IF('被投资单位基本信息G7-4'!M24+'被投资单位基本信息G7-4'!N24>0.5,'被投资单位基本信息G7-4'!C24,0) -> 0 | H40: =IF('被投资单位基本信息G7-4'!M24+'被投资单位基本信息G7-4'!N24>0.5,'被投资单位基本信息G7-4'!R24,0) -> 0
B41: =IF('被投资单位基本信息G7-4'!M25+'被投资单位基本信息G7-4'!N25>0.5,'被投资单位基本信息G7-4'!B25,0) -> 0 | C41: =IF('被投资单位基本信息G7-4'!M25+'被投资单位基本信息G7-4'!N25>0.5,'被投资单位基本信息G7-4'!M25+'被投资单位基本信息G7-4'!N25,0) -> 0 | D41: =IF('被投资单位基本信息G7-4'!M25+'被投资单位基本信息G7-4'!N25>0.5,'被投资单位基本信息G7-4'!O25,0) -> 0 | E41: =IF('被投资单位基本信息G7-4'!M25+'被投资单位基本信息G7-4'!N25>0.5,'被投资单位基本信息G7-4'!I25,0) -> 0 | F41: =IF('被投资单位基本信息G7-4'!M25+'被投资单位基本信息G7-4'!N25>0.5,'被投资单位基本信息G7-4'!J25,0) -> 0 | G41: =IF('被投资单位基本信息G7-4'!M25+'被投资单位基本信息G7-4'!N25>0.5,'被投资单位基本信息G7-4'!C25,0) -> 0 | H41: =IF('被投资单位基本信息G7-4'!M25+'被投资单位基本信息G7-4'!N25>0.5,'被投资单位基本信息G7-4'!R25,0) -> 0
B42: =IF('被投资单位基本信息G7-4'!M26+'被投资单位基本信息G7-4'!N26>0.5,'被投资单位基本信息G7-4'!B26,0) -> 0 | C42: =IF('被投资单位基本信息G7-4'!M26+'被投资单位基本信息G7-4'!N26>0.5,'被投资单位基本信息G7-4'!M26+'被投资单位基本信息G7-4'!N26,0) -> 0 | D42: =IF('被投资单位基本信息G7-4'!M26+'被投资单位基本信息G7-4'!N26>0.5,'被投资单位基本信息G7-4'!O26,0) -> 0 | E42: =IF('被投资单位基本信息G7-4'!M26+'被投资单位基本信息G7-4'!N26>0.5,'被投资单位基本信息G7-4'!I26,0) -> 0 | F42: =IF('被投资单位基本信息G7-4'!M26+'被投资单位基本信息G7-4'!N26>0.5,'被投资单位基本信息G7-4'!J26,0) -> 0 | G42: =IF('被投资单位基本信息G7-4'!M26+'被投资单位基本信息G7-4'!N26>0.5,'被投资单位基本信息G7-4'!C26,0) -> 0 | H42: =IF('被投资单位基本信息G7-4'!M26+'被投资单位基本信息G7-4'!N26>0.5,'被投资单位基本信息G7-4'!R26,0) -> 0
B43: =IF('被投资单位基本信息G7-4'!M27+'被投资单位基本信息G7-4'!N27>0.5,'被投资单位基本信息G7-4'!B27,0) -> 0 | C43: =IF('被投资单位基本信息G7-4'!M27+'被投资单位基本信息G7-4'!N27>0.5,'被投资单位基本信息G7-4'!M27+'被投资单位基本信息G7-4'!N27,0) -> 0 | D43: =IF('被投资单位基本信息G7-4'!M27+'被投资单位基本信息G7-4'!N27>0.5,'被投资单位基本信息G7-4'!O27,0) -> 0 | E43: =IF('被投资单位基本信息G7-4'!M27+'被投资单位基本信息G7-4'!N27>0.5,'被投资单位基本信息G7-4'!I27,0) -> 0 | F43: =IF('被投资单位基本信息G7-4'!M27+'被投资单位基本信息G7-4'!N27>0.5,'被投资单位基本信息G7-4'!J27,0) -> 0 | G43: =IF('被投资单位基本信息G7-4'!M27+'被投资单位基本信息G7-4'!N27>0.5,'被投资单位基本信息G7-4'!C27,0) -> 0 | H43: =IF('被投资单位基本信息G7-4'!M27+'被投资单位基本信息G7-4'!N27>0.5,'被投资单位基本信息G7-4'!R27,0) -> 0
B44: 联营企业
B45: =IF('被投资单位基本信息G7-4'!M29+'被投资单位基本信息G7-4'!N29>0.5,'被投资单位基本信息G7-4'!B29,0) -> 0 | C45: =IF('被投资单位基本信息G7-4'!M29+'被投资单位基本信息G7-4'!N29>0.5,'被投资单位基本信息G7-4'!M29+'被投资单位基本信息G7-4'!N29,0) -> 0 | D45: =IF('被投资单位基本信息G7-4'!M29+'被投资单位基本信息G7-4'!N29>0.5,'被投资单位基本信息G7-4'!O29+'被投资单位基本信息G7-4'!N29,0) -> 0 | E45: =IF('被投资单位基本信息G7-4'!M29+'被投资单位基本信息G7-4'!N29>0.5,'被投资单位基本信息G7-4'!I29,0) -> 0 | F45: =IF('被投资单位基本信息G7-4'!M29+'被投资单位基本信息G7-4'!N29>0.5,'被投资单位基本信息G7-4'!J29,0) -> 0 | G45: =IF('被投资单位基本信息G7-4'!M29+'被投资单位基本信息G7-4'!N29>0.5,'被投资单位基本信息G7-4'!C29,0) -> 0 | H45: =IF('被投资单位基本信息G7-4'!M29+'被投资单位基本信息G7-4'!N29>0.5,'被投资单位基本信息G7-4'!R29,0) -> 0
B46: =IF('被投资单位基本信息G7-4'!M30+'被投资单位基本信息G7-4'!N30>0.5,'被投资单位基本信息G7-4'!B30,0) -> 0 | C46: =IF('被投资单位基本信息G7-4'!M30+'被投资单位基本信息G7-4'!N30>0.5,'被投资单位基本信息G7-4'!M30+'被投资单位基本信息G7-4'!N30,0) -> 0 | D46: =IF('被投资单位基本信息G7-4'!M30+'被投资单位基本信息G7-4'!N30>0.5,'被投资单位基本信息G7-4'!O30+'被投资单位基本信息G7-4'!N30,0) -> 0 | E46: =IF('被投资单位基本信息G7-4'!M30+'被投资单位基本信息G7-4'!N30>0.5,'被投资单位基本信息G7-4'!I30,0) -> 0 | F46: =IF('被投资单位基本信息G7-4'!M30+'被投资单位基本信息G7-4'!N30>0.5,'被投资单位基本信息G7-4'!J30,0) -> 0 | G46: =IF('被投资单位基本信息G7-4'!M30+'被投资单位基本信息G7-4'!N30>0.5,'被投资单位基本信息G7-4'!C30,0) -> 0 | H46: =IF('被投资单位基本信息G7-4'!M30+'被投资单位基本信息G7-4'!N30>0.5,'被投资单位基本信息G7-4'!R30,0) -> 0
B47: =IF('被投资单位基本信息G7-4'!M31+'被投资单位基本信息G7-4'!N31>0.5,'被投资单位基本信息G7-4'!B31,0) -> 0 | C47: =IF('被投资单位基本信息G7-4'!M31+'被投资单位基本信息G7-4'!N31>0.5,'被投资单位基本信息G7-4'!M31+'被投资单位基本信息G7-4'!N31,0) -> 0 | D47: =IF('被投资单位基本信息G7-4'!M31+'被投资单位基本信息G7-4'!N31>0.5,'被投资单位基本信息G7-4'!O31+'被投资单位基本信息G7-4'!N31,0) -> 0 | E47: =IF('被投资单位基本信息G7-4'!M31+'被投资单位基本信息G7-4'!N31>0.5,'被投资单位基本信息G7-4'!I31,0) -> 0 | F47: =IF('被投资单位基本信息G7-4'!M31+'被投资单位基本信息G7-4'!N31>0.5,'被投资单位基本信息G7-4'!J31,0) -> 0 | G47: =IF('被投资单位基本信息G7-4'!M31+'被投资单位基本信息G7-4'!N31>0.5,'被投资单位基本信息G7-4'!C31,0) -> 0 | H47: =IF('被投资单位基本信息G7-4'!M31+'被投资单位基本信息G7-4'!N31>0.5,'被投资单位基本信息G7-4'!R31,0) -> 0
B48: =IF('被投资单位基本信息G7-4'!M32+'被投资单位基本信息G7-4'!N32>0.5,'被投资单位基本信息G7-4'!B32,0) -> 0 | C48: =IF('被投资单位基本信息G7-4'!M32+'被投资单位基本信息G7-4'!N32>0.5,'被投资单位基本信息G7-4'!M32+'被投资单位基本信息G7-4'!N32,0) -> 0 | D48: =IF('被投资单位基本信息G7-4'!M32+'被投资单位基本信息G7-4'!N32>0.5,'被投资单位基本信息G7-4'!O32+'被投资单位基本信息G7-4'!N32,0) -> 0 | E48: =IF('被投资单位基本信息G7-4'!M32+'被投资单位基本信息G7-4'!N32>0.5,'被投资单位基本信息G7-4'!I32,0) -> 0 | F48: =IF('被投资单位基本信息G7-4'!M32+'被投资单位基本信息G7-4'!N32>0.5,'被投资单位基本信息G7-4'!J32,0) -> 0 | G48: =IF('被投资单位基本信息G7-4'!M32+'被投资单位基本信息G7-4'!N32>0.5,'被投资单位基本信息G7-4'!C32,0) -> 0 | H48: =IF('被投资单位基本信息G7-4'!M32+'被投资单位基本信息G7-4'!N32>0.5,'被投资单位基本信息G7-4'!R32,0) -> 0
B49: =IF('被投资单位基本信息G7-4'!M33+'被投资单位基本信息G7-4'!N33>0.5,'被投资单位基本信息G7-4'!B33,0) -> 0 | C49: =IF('被投资单位基本信息G7-4'!M33+'被投资单位基本信息G7-4'!N33>0.5,'被投资单位基本信息G7-4'!M33+'被投资单位基本信息G7-4'!N33,0) -> 0 | D49: =IF('被投资单位基本信息G7-4'!M33+'被投资单位基本信息G7-4'!N33>0.5,'被投资单位基本信息G7-4'!O33+'被投资单位基本信息G7-4'!N33,0) -> 0 | E49: =IF('被投资单位基本信息G7-4'!M33+'被投资单位基本信息G7-4'!N33>0.5,'被投资单位基本信息G7-4'!I33,0) -> 0 | F49: =IF('被投资单位基本信息G7-4'!M33+'被投资单位基本信息G7-4'!N33>0.5,'被投资单位基本信息G7-4'!J33,0) -> 0 | G49: =IF('被投资单位基本信息G7-4'!M33+'被投资单位基本信息G7-4'!N33>0.5,'被投资单位基本信息G7-4'!C33,0) -> 0 | H49: =IF('被投资单位基本信息G7-4'!M33+'被投资单位基本信息G7-4'!N33>0.5,'被投资单位基本信息G7-4'!R33,0) -> 0
B50: 其他
B51: ='被投资单位基本信息G7-4'!#REF! -> #REF!
B52: ='被投资单位基本信息G7-4'!#REF! -> #REF!
A53: （四）重要非全资子公司情况
A54: 1、少数股东
A55: 序号 | B55: 企业名称 | C55: 少数股东持股比例 | D55: 当期归属于少数股东的损益 | E55: 当期向少数股东支付的股利 | F55: 期末累计少数股东权益
A61: 2、主要财务信息：
A62: 项 目
C63: 期末数/本期发生额 | D63: 期初数/上期发生额 | E63: 期末数/本期发生额 | F63: 期初数/上期发生额 | G63: 期末数/本期发生额 | H63: 期初数/上期发生额 | I63: 期末数/本期发生额 | J63: 期初数/上期发生额 | K63: 期末数/本期发生额 | L63: 期初数/上期发生额
A64: 流动资产
A65: 非流动资产
A66: 资产合计
A67: 流动负债
A68: 非流动负债
A69: 负债合计
A70: 营业收入
A71: 净利润
A72: 综合收益总额
A73: 经营活动现金流量
A74: 【提示：上述财务数据以合并日子公司可辨认资产和负债的公允价值为基础进行调整；被划分为持有待售资产的，不需要披露该子公司的上述财务信息。】
A75: （五）子公司与母公司会计期间不一致的，母公司编制合并财务报表的处理方法
... A77: （1）原子公司的基本情况
A78: 序号 | B78: 企业名称 | C78: 注册地 | D78: 业务性质 | E78: 持股比例（%） | F78: 表决权比例（%） | G78: 本期不再成为子公司的原因
A79: 1 | B79: ='处置子公司测试表（不包含一揽子交易）G7-11'!B9 -> 0 | C79: ='处置子公司测试表（不包含一揽子交易）G7-11'!C9 -> 0 | D79: ='处置子公司测试表（不包含一揽子交易）G7-11'!D9 -> 0 | E79: ='处置子公司测试表（不包含一揽子交易）G7-11'!E9 -> 0 | F79: ='处置子公司测试表（不包含一揽子交易）G7-11'!F9 -> 0 | G79: ='处置子公司测试表（不包含一揽子交易）G7-11'!G9 -> 0
A80: 2 | B80: ='处置子公司测试表（不包含一揽子交易）G7-11'!B10 -> 0 | C80: ='处置子公司测试表（不包含一揽子交易）G7-11'!C10 -> 0 | D80: ='处置子公司测试表（不包含一揽子交易）G7-11'!D10 -> 0 | E80: ='处置子公司测试表（不包含一揽子交易）G7-11'!E10 -> 0 | F80: ='处置子公司测试表（不包含一揽子交易）G7-11'!F10 -> 0 | G80: ='处置子公司测试表（不包含一揽子交易）G7-11'!G10 -> 0
A81: 3 | B81: ='处置子公司测试表（不包含一揽子交易）G7-11'!B11 -> 0 | C81: ='处置子公司测试表（不包含一揽子交易）G7-11'!C11 -> 0 | D81: ='处置子公司测试表（不包含一揽子交易）G7-11'!D11 -> 0 | E81: ='处置子公司测试表（不包含一揽子交易）G7-11'!E11 -> 0 | F81: ='处置子公司测试表（不包含一揽子交易）G7-11'!F11 -> 0 | G81: ='处置子公司测试表（不包含一揽子交易）G7-11'!G11 -> 0
A82: 4 | B82: ='处置子公司测试表（不包含一揽子交易）G7-11'!B12 -> 0 | C82: ='处置子公司测试表（不包含一揽子交易）G7-11'!C12 -> 0 | D82: ='处置子公司测试表（不包含一揽子交易）G7-11'!D12 -> 0 | E82: ='处置子公司测试表（不包含一揽子交易）G7-11'!E12 -> 0 | F82: ='处置子公司测试表（不包含一揽子交易）G7-11'!F12 -> 0 | G82: ='处置子公司测试表（不包含一揽子交易）G7-11'!G12 -> 0
A83: 5 | B83: ='处置子公司测试表（不包含一揽子交易）G7-11'!B13 -> 0 | C83: ='处置子公司测试表（不包含一揽子交易）G7-11'!C13 -> 0 | D83: ='处置子公司测试表（不包含一揽子交易）G7-11'!D13 -> 0 | E83: ='处置子公司测试表（不包含一揽子交易）G7-11'!E13 -> 0 | F83: ='处置子公司测试表（不包含一揽子交易）G7-11'!F13 -> 0 | G83: ='处置子公司测试表（不包含一揽子交易）G7-11'!G13 -> 0
A85: （2）本期出售的子公司出售日的财务状况
A86: （说明出售日的确定方法）
A87: 公司名称 | C87: 公司1 | E87: 公司2
A88: 截止日期 | C88: 出售日 | D88: 期初余额 | E88: 出售日 | F88: 期初余额
A89: 流动资产
A90: 长期股权投资
A91: 固定资产
A92: 无形资产
A93: 其他非流动资产
A94: 流动负债
A95: 非流动负债
A96: 所有者权益
A97: （3）本期出售的子公司出售日的经营成果
A98: 公司名称 | C98: A公司 | E98: B公司 | G98: C公司 | I98: D公司 | K98: E公司
A99: 期间 | C99: 本年年初-出售日 | D99: 上年发生额 | E99: 本年年初-出售日 | F99: 上年发生额 | G99: 本年年初-出售日 | H99: 上年发生额 | I99: 本年年初-出售日 | J99: 上年发生额 | K99: 本年年初-出售日 | L99: 上年发生额
A100: 营业收入
A101: 营业成本
A102: 期间费用
A103: 营业利润
A104: 利润总额
A105: 所得税费用
A106: 净利润
A107: 【提示：本期因处置部分股权投资或其他原因丧失了对原有子公司控制权的，对于处置后的剩余股权，还应按照《企业会计准则解释第4号》的规定，在附注中披露处置后的剩余股权在丧失控制权日的公允价值、按照公允价值重新计量产生的相关利得或损失的金额，具体披露格式请参考本所“股份公司年审报告模板”】
...

Sheet 明细表G7-2
A1: 致同会计师事务所 | V1: 致同会计师事务所 | AN1: 致同会计师事务所
A2: 长期股权投资明细表 | V2: 长期股权投资明细表 | AN2: 长期股权投资明细表
A3: =底稿目录!A2 -> 被审计单位： | C3: =底稿目录!A4 -> 编制人： | E3: =底稿目录!A5 -> 编制日期： | I3: 索引号： | J3: =底稿目录!F8 -> G7-2 | L3: =A3 -> 被审计单位： | P3: =C3 -> 编制人： | R3: =E3 -> 编制日期： | T3: =I3 -> 索引号： | U3: =J3 -> G7-2 | V3: =底稿目录!A2 -> 被审计单位： | AA3: =底稿目录!A4 -> 编制人： | AE3: =底稿目录!A5 -> 编制日期： | AL3: 索引号： | AM3: =底稿目录!F8 -> G7-2 | AN3: =底稿目录!A2 -> 被审计单位： | AS3: =底稿目录!A4 -> 编制人： | AX3: =底稿目录!A5 -> 编制日期： | BA3: 索引号： | BB3: =底稿目录!F8 -> G7-2
A4: =底稿目录!A3 -> 截止日：202X年12月31日 | C4: =底稿目录!A6 -> 复核人： | E4: =底稿目录!A7 -> 复核日期： | I4: 页 次： | L4: =A4 -> 截止日：202X年12月31日 | P4: =C4 -> 复核人： | R4: =E4 -> 复核日期： | T4: =I4 -> 页 次： | U4: =J4 -> 0 | V4: =底稿目录!A3 -> 截止日：202X年12月31日 | AA4: =底稿目录!A6 -> 复核人： | AE4: =底稿目录!A7 -> 复核日期： | AL4: 页次： | AN4: =底稿目录!A3 -> 截止日：202X年12月31日 | AS4: =底稿目录!A6 -> 复核人： | AX4: =底稿目录!A7 -> 复核日期： | BA4: 页次：
A5: 一、审计目标： | L5: =A5 -> 一、审计目标： | V5: =L5 -> 一、审计目标： | AN5: =V5 -> 一、审计目标：
A6: 1.资产负债表中记录的长期股权投资是存在的，且已经记录在恰当的账户中； | L6: 1.资产负债表中记录的长期股权投资是存在的，且已经记录在恰当的账户中； | V6: =L6 -> 1.资产负债表中记录的长期股权投资是存在的，且已经记录在恰当的账户中； | AN6: =V6 -> 1.资产负债表中记录的长期股权投资是存在的，且已经记录在恰当的账户中；
A7: 2.所有应记录的长期股权投资均已记录，所有应当包括在财务报表中的相关披露均已包括； | L7: 2.所有应记录的长期股权投资均已记录，所有应当包括在财务报表中的相关披露均已包括； | V7: =L7 -> 2.所有应记录的长期股权投资均已记录，所有应当包括在财务报表中的相关披露均已包括； | AN7: =V7 -> 2.所有应记录的长期股权投资均已记录，所有应当包括在财务报表中的相关披露均已包括；
A8: 3.长期股权投资以恰当的金额包括在财务报表中，与之相关的计价或分摊调整已恰当记录，相关披露已得到恰当计量和描述； | L8: 3.长期股权投资以恰当的金额包括在财务报表中，与之相关的计价或分摊调整已恰当记录，相关披露已得到恰当计量和描述； | V8: =L8 -> 3.长期股权投资以恰当的金额包括在财务报表中，与之相关的计价或分摊调整已恰当记录，相关披露已得到恰当计量和描述； | AN8: =V8 -> 3.长期股权投资以恰当的金额包括在财务报表中，与之相关的计价或分摊调整已恰当记录，相关披露已得到恰当计量和描述；
A9: 4.记录的长期股权投资由被审计单位拥有或控制 | L9: 4.记录的长期股权投资由被审计单位拥有或控制 | V9: =L9 -> 4.记录的长期股权投资由被审计单位拥有或控制 | AN9: =V9 -> 4.记录的长期股权投资由被审计单位拥有或控制
A10: 二、审计过程 | L10: =A10 -> 二、审计过程 | V10: =L10 -> 二、审计过程 | AN10: =V10 -> 二、审计过程
A11: 提示：与被审计单位人员讨论确定是否存在被投资单位由于所在国家和地区及其他方面的影响，其向被审计单位转移资金的能力受到限制的情况，如存在，应详细记录受限情况，并提请被审计单位充分披露 | L11: =A11 -> 提示：与被审计单位人员讨论确定是否存在被投资单位由于所在国家和地区及其他方面的影响，其向被审计单位转移资金的能力受到限制的情况，如存在，应详细记录受限情况，并提请被审计单位充分披露 | V11: =L11 -> 提示：与被审计单位人员讨论确定是否存在被投资单位由于所在国家和地区及其他方面的影响，其向被审计单位转移资金的能力受到限制的情况，如存在，应详细记录受限情况，并提请被审计单位充分披露 | AN11: =V11 -> 提示：与被审计单位人员讨论确定是否存在被投资单位由于所在国家和地区及其他方面的影响，其向被审计单位转移资金的能力受到限制的情况，如存在，应详细记录受限情况，并提请被审计单位充分披露
A12: （一）按成本法核算的长期股权投资 | L12: （一）按成本法核算的长期股权投资 | V12: （一）按成本法核算的长期股权投资
A13: 序号 | B13: 被投资单位名称 | F13: 初始投资成本 | H13: 投资比例 | I13: 投资时间 | J13: 投资方式 | K13: 本期现金红利 | L13: 未审数 | V13: 期初调整 | X13: 账项调整 | Z13: 重分类调整 | AB13: 审定数
L14: 期初余额 | N14: 本期增加 | Q14: 本期减少 | T14: 期末余额 | V14: 账项调整 | W14: 重分类调整 | X14: 本期增加 | Y14: 本期减少 | Z14: 本期增加 | AA14: 本期减少 | AB14: 期初余额 | AD14: 本期增加 | AF14: 本期减少 | AH14: 期末余额
L15: 投资比例 | M15: 金额 | N15: 投资比例 | O15: 金额 | P15: 索引号 | Q15: 投资比例 | R15: 金额 | S15: 索引号 | T15: 投资比例 | U15: 金额 | X15: 本期增加 | Y15: 本期减少 | Z15: 本期增加 | AA15: 本期减少 | AB15: 投资比例 | AC15: 金额 | AD15: 投资比例 | AE15: 金额 | AF15: 投资比例 | AG15: 金额 | AH15: 投资比例 | AI15: 金额
A16: 1 | T16: =L16+N16-Q16 -> 0 | U16: =M16+O16-R16 -> 0 | AB16: =L16 -> 0 | AC16: =M16+V16+W16 -> 0 | AD16: =N16 -> 0 | AE16: =O16+X16+Z16 -> 0 | AF16: =Q16 -> 0 | AG16: =R16+Y16+AA16 -> 0 | AH16: =AB16+AD16-AF16 -> 0 | AI16: =AC16+AE16-AG16 -> 0
A17: 2 | T17: =L17+N17-Q17 -> 0 | U17: =M17+O17-R17 -> 0 | AB17: =L17 -> 0 | AC17: =M17+V17+W17 -> 0 | AD17: =N17 -> 0 | AE17: =O17+X17+Z17 -> 0 | AF17: =Q17 -> 0 | AG17: =R17+Y17+AA17 -> 0 | AH17: =AB17+AD17-AF17 -> 0 | AI17: =AC17+AE17-AG17 -> 0
A18: 3 | T18: =L18+N18-Q18 -> 0 | U18: =M18+O18-R18 -> 0 | AB18: =L18 -> 0 | AC18: =M18+V18+W18 -> 0 | AD18: =N18 -> 0 | AE18: =O18+X18+Z18 -> 0 | AF18: =Q18 -> 0 | AG18: =R18+Y18+AA18 -> 0 | AH18: =AB18+AD18-AF18 -> 0 | AI18: =AC18+AE18-AG18 -> 0
A19: 4 | T19: =L19+N19-Q19 -> 0 | U19: =M19+O19-R19 -> 0 | AB19: =L19 -> 0 | AC19: =M19+V19+W19 -> 0 | AD19: =N19 -> 0 | AE19: =O19+X19+Z19 -> 0 | AF19: =Q19 -> 0 | AG19: =R19+Y19+AA19 -> 0 | AH19: =AB19+AD19-AF19 -> 0 | AI19: =AC19+AE19-AG19 -> 0
A20: 5 | T20: =L20+N20-Q20 -> 0 | U20: =M20+O20-R20 -> 0 | AB20: =L20 -> 0 | AC20: =M20+V20+W20 -> 0 | AD20: =N20 -> 0 | AE20: =O20+X20+Z20 -> 0 | AF20: =Q20 -> 0 | AG20: =R20+Y20+AA20 -> 0 | AH20: =AB20+AD20-AF20 -> 0 | AI20: =AC20+AE20-AG20 -> 0
A21: 6 | T21: =L21+N21-Q21 -> 0 | U21: =M21+O21-R21 -> 0 | AB21: =L21 -> 0 | AC21: =M21+V21+W21 -> 0 | AD21: =N21 -> 0 | AE21: =O21+X21+Z21 -> 0 | AF21: =Q21 -> 0 | AG21: =R21+Y21+AA21 -> 0 | AH21: =AB21+AD21-AF21 -> 0 | AI21: =AC21+AE21-AG21 -> 0
A22: 7 | T22: =L22+N22-Q22 -> 0 | U22: =M22+O22-R22 -> 0 | AB22: =L22 -> 0 | AC22: =M22+V22+W22 -> 0 | AD22: =N22 -> 0 | AE22: =O22+X22+Z22 -> 0 | AF22: =Q22 -> 0 | AG22: =R22+Y22+AA22 -> 0 | AH22: =AB22+AD22-AF22 -> 0 | AI22: =AC22+AE22-AG22 -> 0
A23: 8 | T23: =L23+N23-Q23 -> 0 | U23: =M23+O23-R23 -> 0 | AB23: =L23 -> 0 | AC23: =M23+V23+W23 -> 0 | AD23: =N23 -> 0 | AE23: =O23+X23+Z23 -> 0 | AF23: =Q23 -> 0 | AG23: =R23+Y23+AA23 -> 0 | AH23: =AB23+AD23-AF23 -> 0 | AI23: =AC23+AE23-AG23 -> 0
A24: 9 | T24: =L24+N24-Q24 -> 0 | U24: =M24+O24-R24 -> 0 | AB24: =L24 -> 0 | AC24: =M24+V24+W24 -> 0 | AD24: =N24 -> 0 | AE24: =O24+X24+Z24 -> 0 | AF24: =Q24 -> 0 | AG24: =R24+Y24+AA24 -> 0 | AH24: =AB24+AD24-AF24 -> 0 | AI24: =AC24+AE24-AG24 -> 0
A25: 10 | B25: …… | T25: =L25+N25-Q25 -> 0 | U25: =M25+O25-R25 -> 0 | AB25: =L25 -> 0 | AC25: =M25+V25+W25 -> 0 | AD25: =N25 -> 0 | AE25: =O25+X25+Z25 -> 0 | AF25: =Q25 -> 0 | AG25: =R25+Y25+AA25 -> 0 | AH25: =AB25+AD25-AF25 -> 0 | AI25: =AC25+AE25-AG25 -> 0
A26: 成本法小计 | G26: =SUM(G16:G25) -> 0 | H26: -- | I26: -- | J26: -- | K26: =SUM(K16:K25) -> 0 | L26: -- | M26: =SUM(M16:M25) -> 0 | N26: -- | O26: =SUM(O16:O25) -> 0 | P26: -- | Q26: -- | R26: =SUM(R16:R25) -> 0 | S26: -- | T26: -- | U26: =SUM(U16:U25) -> 0 | V26: =SUM(V16:V25) -> 0 | W26: =SUM(W16:W25) -> 0 | X26: =SUM(X16:X25) -> 0 | Y26: =SUM(Y16:Y25) -> 0 | Z26: =SUM(Z16:Z25) -> 0 | AA26: =SUM(AA16:AA25) -> 0 | AB26: -- | AC26: =SUM(AC16:AC25) -> 0 | AD26: -- | AE26: =SUM(AE16:AE25) -> 0 | AF26: -- | AG26: =SUM(AG16:AG25) -> 0 | AH26: -- | AI26: =SUM(AI16:AI25) -> 0
A27: （二）按权益法核算的长期股权投资 | V27: （二）按权益法核算的长期股权投资 | AN27: （二）按权益法核算的长期股权投资
A28: 序号 | B28: 被投资单位名称 | C28: 初始投资成本 | D28: 投资比例 | E28: 投资时间 | F28: 投资方式 | G28: 未审数 | V28: 期初调整 | X28: 账项调整 | AF28: 重分类调整 | AN28: 审定数
G29: 期初余额 | I29: 本期增加 | P29: 本期减少 | T29: 期末余额 | V29: 账项调整 | W29: 重分类调整 | X29: 本期增加 | AC29: 本期减少 | AF29: 本期增加 | AK29: 本期减少 | AN29: 期初余额 | AP29: 本期增加 | AW29: 本期减少 | BA29: 期末余额
G30: 投资比例 | H30: 金额 | I30: 投资比例 | J30: 投资成本增加 | K30: 权益增加 | O30: 其他 | P30: 投资比例 | Q30: 投资成本减少 | R30: 本期分回利润 | S30: 其他 | T30: 投资比例 | U30: 金额 | X30: 投资成本增加 | Y30: 权益增加 | AB30: 其他 | AC30: 投资成本减少 | AD30: 本期分回利润 | AE30: 其他 | AF30: 投资成本增加 | AG30: 权益增加 | AJ30: 其他 | AK30: 投资成本减少 | AL30: 本期分回利润 | AM30: 其他 | AN30: 投资比例 | AO30: 金额 | AP30: 投资比例 | AQ30: 投资成本增加 | AR30: 权益增加 | AV30: 其他 | AW30: 投资比例 | AX30: 投资成本减少 | AY30: 本期分回利润 | AZ30: 其他 | BA30: 投资比例 | BB30: 金额
K31: 损益调整 | L31: 其他综合收益 | M31: 其他权益变动 | N31: 权益增加小计 | Y31: 损益调整 | Z31: 其他综合收益 | AA31: 其他权益变动 | AG31: 损益调整 | AH31: 其他综合收益 | AI31: 其他权益变动 | AR31: 损益调整 | AS31: 其他综合收益 | AT31: 其他权益变动 | AU31: 权益增加小计
A32: 合营企业：
A33: 1 | N33: =SUM(K33:M33) -> 0 | T33: =G33+I33-P33 -> 0 | U33: =H33+J33+N33-Q33-R33+O33-S33 -> 0 | AN33: =G33 -> 0 | AO33: =H33+V33+W33 -> 0 | AP33: =I33 -> 0 | AQ33: =J33+X33+AF33 -> 0 | AR33: =K33+Y33+AG33 -> 0 | AS33: =L33+Z33+AH33 -> 0 | AT33: =M33+AA33+AI33 -> 0 | AU33: =SUM(AR33:AT33) -> 0 | AV33: =O33+AB33+AJ33 -> 0 | AW33: =P33 -> 0 | AX33: =Q33+AC33+AK33 -> 0 | AY33: =R33+AD33+AL33 -> 0 | AZ33: =S33+AE33+AM33 -> 0 | BA33: =AN33+AP33-AW33 -> 0 | BB33: =AO33+AQ33+AU33-AX33-AY33 -> 0
A34: 2 | N34: =SUM(K34:M34) -> 0 | T34: =G34+I34-P34 -> 0 | U34: =H34+J34+N34-Q34-R34+O34-S34 -> 0 | AN34: =G34 -> 0 | AO34: =H34+V34+W34 -> 0 | AP34: =I34 -> 0 | AQ34: =J34+X34+AF34 -> 0 | AR34: =K34+Y34+AG34 -> 0 | AS34: =L34+Z34+AH34 -> 0 | AT34: =M34+AA34+AI34 -> 0 | AU34: =SUM(AR34:AT34) -> 0 | AV34: =O34+AB34+AJ34 -> 0 | AW34: =P34 -> 0 | AX34: =Q34+AC34+AK34 -> 0 | AY34: =R34+AD34+AL34 -> 0 | AZ34: =S34+AE34+AM34 -> 0 | BA34: =AN34+AP34-AW34 -> 0 | BB34: =AO34+AQ34+AU34-AX34-AY34 -> 0
A35: 3 | N35: =SUM(K35:M35) -> 0 | T35: =G35+I35-P35 -> 0 | U35: =H35+J35+N35-Q35-R35+O35-S35 -> 0 | AN35: =G35 -> 0 | AO35: =H35+V35+W35 -> 0 | AP35: =I35 -> 0 | AQ35: =J35+X35+AF35 -> 0 | AR35: =K35+Y35+AG35 -> 0 | AS35: =L35+Z35+AH35 -> 0 | AT35: =M35+AA35+AI35 -> 0 | AU35: =SUM(AR35:AT35) -> 0 | AV35: =O35+AB35+AJ35 -> 0 | AW35: =P35 -> 0 | AX35: =Q35+AC35+AK35 -> 0 | AY35: =R35+AD35+AL35 -> 0 | AZ35: =S35+AE35+AM35 -> 0 | BA35: =AN35+AP35-AW35 -> 0 | BB35: =AO35+AQ35+AU35-AX35-AY35 -> 0
A36: 4 | N36: =SUM(K36:M36) -> 0 | T36: =G36+I36-P36 -> 0 | U36: =H36+J36+N36-Q36-R36+O36-S36 -> 0 | AN36: =G36 -> 0 | AO36: =H36+V36+W36 -> 0 | AP36: =I36 -> 0 | AQ36: =J36+X36+AF36 -> 0 | AR36: =K36+Y36+AG36 -> 0 | AS36: =L36+Z36+AH36 -> 0 | AT36: =M36+AA36+AI36 -> 0 | AU36: =SUM(AR36:AT36) -> 0 | AV36: =O36+AB36+AJ36 -> 0 | AW36: =P36 -> 0 | AX36: =Q36+AC36+AK36 -> 0 | AY36: =R36+AD36+AL36 -> 0 | AZ36: =S36+AE36+AM36 -> 0 | BA36: =AN36+AP36-AW36 -> 0 | BB36: =AO36+AQ36+AU36-AX36-AY36 -> 0
A37: 5 | B37: …… | N37: =SUM(K37:M37) -> 0 | T37: =G37+I37-P37 -> 0 | U37: =H37+J37+N37-Q37-R37+O37-S37 -> 0 | AN37: =G37 -> 0 | AO37: =H37+V37+W37 -> 0 | AP37: =I37 -> 0 | AQ37: =J37+X37+AF37 -> 0 | AR37: =K37+Y37+AG37 -> 0 | AS37: =L37+Z37+AH37 -> 0 | AT37: =M37+AA37+AI37 -> 0 | AU37: =SUM(AR37:AT37) -> 0 | AV37: =O37+AB37+AJ37 -> 0 | AW37: =P37 -> 0 | AX37: =Q37+AC37+AK37 -> 0 | AY37: =R37+AD37+AL37 -> 0 | AZ37: =S37+AE37+AM37 -> 0 | BA37: =AN37+AP37-AW37 -> 0 | BB37: =AO37+AQ37+AU37-AX37-AY37 -> 0
A38: 小计 | G38: -- | H38: =SUM(H33:H37) -> 0 | I38: -- | J38: =SUM(J33:J37) -> 0 | K38: =SUM(K33:K37) -> 0 | L38: =SUM(L33:L37) -> 0 | M38: =SUM(M33:M37) -> 0 | N38: =SUM(K38:M38) -> 0 | O38: =SUM(O33:O37) -> 0 | P38: =SUM(P33:P37) -> 0 | Q38: =SUM(Q33:Q37) -> 0 | R38: =SUM(R33:R37) -> 0 | T38: -- | U38: =SUM(U33:U37) -> 0 | V38: =SUM(V33:V37) -> 0 | W38: =SUM(W33:W37) -> 0 | X38: =SUM(X33:X37) -> 0 | Y38: =SUM(Y33:Y37) -> 0 | Z38: =SUM(Z33:Z37) -> 0 | AA38: =SUM(AA33:AA37) -> 0 | AB38: =SUM(AB33:AB37) -> 0 | ... AM38: =SUM(AM33:AM37) -> 0 | AN38: -- | AO38: =SUM(AO33:AO37) -> 0 | AP38: -- | AQ38: =SUM(AQ33:AQ37) -> 0 | AR38: =SUM(AR33:AR37) -> 0 | AS38: =SUM(AS33:AS37) -> 0 | AT38: =SUM(AT33:AT37) -> 0 | AU38: =SUM(AU33:AU37) -> 0 | AV38: =SUM(AV33:AV37) -> 0 | AW38: -- | AX38: =SUM(AX33:AX37) -> 0 | AY38: =SUM(AY33:AY37) -> 0 | AZ38: =SUM(AZ33:AZ37) -> 0 | BA38: -- | BB38: =SUM(BB33:BB37) -> 0
A39: 联营企业：
A40: 1 | N40: =SUM(K40:M40) -> 0 | T40: =G40+I40-P40 -> 0 | U40: =H40+J40+N40-Q40-R40+O40-S40 -> 0 | AN40: =G40 -> 0 | AO40: =H40+V40+W40 -> 0 | AP40: =I40 -> 0 | AQ40: =J40+X40+AF40 -> 0 | AR40: =K40+Y40+AG40 -> 0 | AS40: =L40+Z40+AH40 -> 0 | AT40: =M40+AA40+AI40 -> 0 | AU40: =SUM(AR40:AT40) -> 0 | AV40: =O40+AB40+AJ40 -> 0 | AW40: =P40 -> 0 | AX40: =Q40+AC40+AK40 -> 0 | AY40: =R40+AD40+AL40 -> 0 | AZ40: =S40+AE40+AM40 -> 0 | BA40: =AN40+AP40-AW40 -> 0 | BB40: =AO40+AQ40+AU40-AX40-AY40 -> 0
A41: 2 | N41: =SUM(K41:M41) -> 0 | T41: =G41+I41-P41 -> 0 | U41: =H41+J41+N41-Q41-R41 -> 0 | AN41: =G41 -> 0 | AO41: =H41+V41+W41 -> 0 | AP41: =I41 -> 0 | AQ41: =J41+X41+AF41 -> 0 | AR41: =K41+Y41+AG41 -> 0 | AS41: =L41+Z41+AH41 -> 0 | AT41: =M41+AA41+AI41 -> 0 | AU41: =SUM(AR41:AT41) -> 0 | AV41: =O41+AB41+AJ41 -> 0 | AW41: =P41 -> 0 | AX41: =Q41+AC41+AK41 -> 0 | AY41: =R41+AD41+AL41 -> 0 | AZ41: =S41+AE41+AM41 -> 0 | BA41: =AN41+AP41-AW41 -> 0 | BB41: =AO41+AQ41+AU41-AX41-AY41 -> 0
A42: 3 | N42: =SUM(K42:M42) -> 0 | T42: =G42+I42-P42 -> 0 | U42: =H42+J42+N42-Q42-R42 -> 0 | AN42: =G42 -> 0 | AO42: =H42+V42+W42 -> 0 | AP42: =I42 -> 0 | AQ42: =J42+X42+AF42 -> 0 | AR42: =K42+Y42+AG42 -> 0 | AS42: =L42+Z42+AH42 -> 0 | AT42: =M42+AA42+AI42 -> 0 | AU42: =SUM(AR42:AT42) -> 0 | AV42: =O42+AB42+AJ42 -> 0 | AW42: =P42 -> 0 | AX42: =Q42+AC42+AK42 -> 0 | AY42: =R42+AD42+AL42 -> 0 | AZ42: =S42+AE42+AM42 -> 0 | BA42: =AN42+AP42-AW42 -> 0 | BB42: =AO42+AQ42+AU42-AX42-AY42 -> 0
A43: 4 | N43: =SUM(K43:M43) -> 0 | T43: =G43+I43-P43 -> 0 | U43: =H43+J43+N43-Q43-R43 -> 0 | AN43: =G43 -> 0 | AO43: =H43+V43+W43 -> 0 | AP43: =I43 -> 0 | AQ43: =J43+X43+AF43 -> 0 | AR43: =K43+Y43+AG43 -> 0 | AS43: =L43+Z43+AH43 -> 0 | AT43: =M43+AA43+AI43 -> 0 | AU43: =SUM(AR43:AT43) -> 0 | AV43: =O43+AB43+AJ43 -> 0 | AW43: =P43 -> 0 | AX43: =Q43+AC43+AK43 -> 0 | AY43: =R43+AD43+AL43 -> 0 | AZ43: =S43+AE43+AM43 -> 0 | BA43: =AN43+AP43-AW43 -> 0 | BB43: =AO43+AQ43+AU43-AX43-AY43 -> 0
A44: 5 | B44: …… | N44: =SUM(K44:M44) -> 0 | T44: =G44+I44-P44 -> 0 | U44: =H44+J44+N44-Q44-R44 -> 0 | AN44: =G44 -> 0 | AO44: =H44+V44+W44 -> 0 | AP44: =I44 -> 0 | AQ44: =J44+X44+AF44 -> 0 | AR44: =K44+Y44+AG44 -> 0 | AS44: =L44+Z44+AH44 -> 0 | AT44: =M44+AA44+AI44 -> 0 | AU44: =SUM(AR44:AT44) -> 0 | AV44: =O44+AB44+AJ44 -> 0 | AW44: =P44 -> 0 | AX44: =Q44+AC44+AK44 -> 0 | AY44: =R44+AD44+AL44 -> 0 | AZ44: =S44+AE44+AM44 -> 0 | BA44: =AN44+AP44-AW44 -> 0 | BB44: =AO44+AQ44+AU44-AX44-AY44 -> 0
A45: 小计 | G45: -- | H45: =SUM(H40:H44) -> 0 | I45: -- | J45: =SUM(J40:J44) -> 0 | K45: =SUM(K40:K44) -> 0 | L45: =SUM(L40:L44) -> 0 | M45: =SUM(M40:M44) -> 0 | N45: =SUM(K45:M45) -> 0 | O45: =SUM(O40:O44) -> 0 | P45: =SUM(P40:P44) -> 0 | Q45: =SUM(Q40:Q44) -> 0 | R45: =SUM(R40:R44) -> 0 | S45: =SUM(S40:S44) -> 0 | T45: -- | U45: =H45+J45+N45-Q45-R45+O45-S45 -> 0 | V45: =SUM(V40:V44) -> 0 | W45: =SUM(W40:W44) -> 0 | X45: =SUM(X40:X44) -> 0 | Y45: =SUM(Y40:Y44) -> 0 | Z45: =SUM(Z40:Z44) -> 0 | AA45: =SUM(AA40:AA44) -> 0 | AB45: =SUM(AB40:AB44) -> 0 | AC45: =SUM(AC40:AC44) -> 0 | ... AM45: =SUM(AM40:AM44) -> 0 | AN45: -- | AO45: =SUM(AO40:AO44) -> 0 | AP45: -- | AQ45: =SUM(AQ40:AQ44) -> 0 | AR45: =SUM(AR40:AR44) -> 0 | AS45: =SUM(AS40:AS44) -> 0 | AT45: =SUM(AT40:AT44) -> 0 | AU45: =SUM(AU40:AU44) -> 0 | AV45: =SUM(AV40:AV44) -> 0 | AW45: -- | AX45: =SUM(AX40:AX44) -> 0 | AY45: =SUM(AY40:AY44) -> 0 | AZ45: =S45+AE45+AM45 -> 0 | BA45: -- | BB45: =SUM(BB40:BB44) -> 0
A46: 权益法小计 | C46: =SUM(C33:C44) -> 0 | D46: -- | E46: -- | F46: -- | G46: -- | H46: =H45+H38 -> 0 | I46: -- | J46: =J38+J45 -> 0 | K46: =K38+K45 -> 0 | L46: =L38+L45 -> 0 | M46: =M38+M45 -> 0 | N46: =N38+N45 -> 0 | O46: =O38+O45 -> 0 | P46: -- | Q46: =Q38+Q45 -> 0 | R46: =R38+R45 -> 0 | S46: =S38+S45 -> 0 | T46: -- | U46: =U38+U45 -> 0 | V46: =SUM(V33:V44) -> 0 | W46: =SUM(W33:W44) -> 0 | X46: =SUM(X33:X44) -> 0 | Y46: =SUM(Y33:Y44) -> 0 | AA46: =SUM(AA33:AA44) -> 0 | AB46: =SUM(AB33:AB44) -> 0 | AC46: =SUM(AC33:AC44) -> 0 | AD46: =SUM(AD33:AD44) -> 0 | AE46: =SUM(AE33:AE44) -> 0 | AF46: =SUM(AF33:AF44) -> 0 | AG46: =SUM(AG33:AG44) -> 0 | AH46: =SUM(AH33:AH44) -> 0 | ... AM46: =SUM(AM33:AM44) -> 0 | AN46: -- | AO46: =SUM(AO33:AO44) -> 0 | AP46: =SUM(AP33:AP44) -> 0 | AQ46: =SUM(AQ33:AQ44) -> 0 | AR46: =SUM(AR33:AR44) -> 0 | AS46: =SUM(AS33:AS44) -> 0 | AT46: =SUM(AT33:AT44) -> 0 | AU46: =SUM(AU33:AU44) -> 0 | AV46: =SUM(AV33:AV44) -> 0 | AW46: -- | AX46: =SUM(AX33:AX44) -> 0 | AY46: =SUM(AY33:AY44) -> 0 | AZ46: =SUM(AZ33:AZ44) -> 0 | BB46: =SUM(BB33:BB44) -> 0
A47: 长期股权投资合计 | C47: -- | D47: -- | E47: -- | F47: -- | G47: -- | H47: =M26+H46 -> 0 | I47: -- | J47: =J46+O26 -> 0 | K47: =K46 -> 0 | L47: =L46 -> 0 | M47: =M46 -> 0 | N47: =N46 -> 0 | O47: =O46 -> 0 | P47: -- | U47: =SUM(U26,U46) -> 0 | V47: =V26+V46 -> 0 | W47: =W26+W46 -> 0 | X47: =X26+X46 -> 0 | Y47: =Y46 -> 0 | Z47: =Z46 -> 0 | AA47: =AA46 -> 0 | AC47: =AC46+Y26 -> 0 | AD47: =AD46 -> 0 | AE47: =AE46 -> 0 | AF47: =Z26+AF46 -> 0 | AG47: =AG46 -> 0 | AH47: =AH46 -> 0 | AI47: =AI46 -> 0 | AJ47: =AJ46 -> 0 | AK47: =AK46+AA26 -> 0 | AL47: =AL46 -> 0 | AM47: =AM46 -> 0 | AN47: -- | AO47: =AO46+AC26 -> 0 | AP47: -- | AQ47: =AQ46+AE26 -> 0 | AR47: =AR46 -> 0 | AS47: =AS46 -> 0 | AT47: =AT46 -> 0 | AU47: =AU46 -> 0 | AV47: =AV46 -> 0 | AW47: -- | AX47: =AX46+AG26 -> 0 | AY47: =AY46 -> 0 | AZ47: =AZ46 -> 0 | BA47: -- | BB47: =BB46+AI26 -> 0
A48: （三）长期股权投资减值准备 | T48: （三）长期股权投资减值准备
A49: 序号 | B49: 被投资单位名称 | C49: 初始投资成本 | D49: 投资比例 | E49: 投资时间 | F49: 投资方式 | G49: 未审数 | L49: 期初调整 | N49: 账项调整 | P49: 重分类调整 | R49: 审定数
G50: 期初余额 | H50: 本期增加 | I50: 本期减少 | J50: 期末余额 | K50: 备注 | L50: 账项调整 | M50: 重分类调整 | N50: 本期增加 | O50: 本期减少 | P50: 本期增加 | Q50: 本期减少 | R50: 期初余额 | S50: 本期增加 | T50: 本期减少 | U50: 期末余额
M51: 重分类调整 | N51: 本期增加 | O51: 本期减少 | P51: 本期增加 | Q51: 本期减少 | S51: 本期增加 | T51: 本期减少 | U51: 期末余额
A52: 按成本法核算的长期股权投资
A53: 1 | B53: =B16 -> 0 | J53: =G53+H53-I53 -> 0 | R53: =G53+L53+M53 -> 0 | S53: =H53+N53+P53 -> 0 | T53: =I53+O53+Q53 -> 0 | U53: =R53+S53-T53 -> 0
A54: 2 | B54: =B17 -> 0 | J54: =G54+H54-I54 -> 0 | R54: =G54+L54+M54 -> 0 | S54: =H54+N54+P54 -> 0 | T54: =I54+O54+Q54 -> 0 | U54: =R54+S54-T54 -> 0
A55: 3 | B55: =B18 -> 0 | J55: =G55+H55-I55 -> 0 | R55: =G55+L55+M55 -> 0 | S55: =H55+N55+P55 -> 0 | T55: =I55+O55+Q55 -> 0 | U55: =R55+S55-T55 -> 0
A56: 4 | B56: =B19 -> 0 | J56: =G56+H56-I56 -> 0 | R56: =G56+L56+M56 -> 0 | S56: =H56+N56+P56 -> 0 | T56: =I56+O56+Q56 -> 0 | U56: =R56+S56-T56 -> 0
A57: 5 | B57: =B20 -> 0 | J57: =G57+H57-I57 -> 0 | R57: =G57+L57+M57 -> 0 | S57: =H57+N57+P57 -> 0 | T57: =I57+O57+Q57 -> 0 | U57: =R57+S57-T57 -> 0
A58: 6 | B58: =B21 -> 0 | J58: =G58+H58-I58 -> 0 | R58: =G58+L58+M58 -> 0 | S58: =H58+N58+P58 -> 0 | T58: =I58+O58+Q58 -> 0 | U58: =R58+S58-T58 -> 0
A59: 7 | B59: =B22 -> 0 | J59: =G59+H59-I59 -> 0 | R59: =G59+L59+M59 -> 0 | S59: =H59+N59+P59 -> 0 | T59: =I59+O59+Q59 -> 0 | U59: =R59+S59-T59 -> 0
A60: 8 | B60: =B23 -> 0 | J60: =G60+H60-I60 -> 0 | R60: =G60+L60+M60 -> 0 | S60: =H60+N60+P60 -> 0 | T60: =I60+O60+Q60 -> 0 | U60: =R60+S60-T60 -> 0
A61: 9 | B61: =B24 -> 0 | J61: =G61+H61-I61 -> 0 | R61: =G61+L61+M61 -> 0 | S61: =H61+N61+P61 -> 0 | T61: =I61+O61+Q61 -> 0 | U61: =R61+S61-T61 -> 0
A62: 10 | B62: =B25 -> …… | J62: =G62+H62-I62 -> 0 | R62: =G62+L62+M62 -> 0 | S62: =H62+N62+P62 -> 0 | T62: =I62+O62+Q62 -> 0 | U62: =R62+S62-T62 -> 0
A63: 按成本法核算的长期股权投资小计 | C63: -- | D63: -- | E63: -- | F63: -- | G63: =SUM(G53:G62) -> 0 | H63: =SUM(H53:H62) -> 0 | I63: =SUM(I53:I62) -> 0 | J63: =SUM(J53:J62) -> 0 | K63: -- | L63: =SUM(L53:L62) -> 0 | M63: =SUM(M53:M62) -> 0 | N63: =SUM(N53:N62) -> 0 | O63: =SUM(O53:O62) -> 0 | P63: =SUM(P53:P62) -> 0 | Q63: =SUM(Q53:Q62) -> 0 | R63: =SUM(R53:R62) -> 0 | S63: =SUM(S53:S62) -> 0 | ... U63: =SUM(U53:U62) -> 0
A64: 按权益法核算的长期股权投资 | J64: -- | R64: =G64+L64+M64 -> 0 | S64: =H64+N64+P64 -> 0 | T64: =I64+O64+Q64 -> 0 | U64: =R64+S64-T64 -> 0
A65: ——合营企业： | J65: --
A66: 1 | B66: =B33 -> 0 | J66: =G66+H66-I66 -> 0 | R66: =G66+L66+M66 -> 0 | S66: =H66+N66+P66 -> 0 | T66: =I66+O66+Q66 -> 0 | U66: =R66+S66-T66 -> 0
A67: 2 | B67: =B34 -> 0 | J67: =G67+H67-I67 -> 0 | R67: =G67+L67+M67 -> 0 | S67: =H67+N67+P67 -> 0 | T67: =I67+O67+Q67 -> 0 | U67: =R67+S67-T67 -> 0
A68: 3 | B68: =B35 -> 0 | J68: =G68+H68-I68 -> 0 | R68: =G68+L68+M68 -> 0 | S68: =H68+N68+P68 -> 0 | T68: =I68+O68+Q68 -> 0 | U68: =R68+S68-T68 -> 0
A69: 4 | B69: =B36 -> 0 | J69: =G69+H69-I69 -> 0 | R69: =G69+L69+M69 -> 0 | S69: =H69+N69+P69 -> 0 | T69: =I69+O69+Q69 -> 0 | U69: =R69+S69-T69 -> 0
A70: 5 | B70: =B37 -> …… | J70: =G70+H70-I70 -> 0 | R70: =G70+L70+M70 -> 0 | S70: =H70+N70+P70 -> 0 | T70: =I70+O70+Q70 -> 0 | U70: =R70+S70-T70 -> 0
A71: 合营企业小计 | C71: -- | D71: -- | E71: -- | F71: -- | G71: =SUM(G66:G70) -> 0 | H71: =SUM(H66:H70) -> 0 | I71: =SUM(I66:I70) -> 0 | J71: =SUM(J66:J70) -> 0 | K71: -- | L71: =SUM(L66:L70) -> 0 | M71: =SUM(M66:M70) -> 0 | N71: =SUM(N66:N70) -> 0 | O71: =SUM(O66:O70) -> 0 | P71: =SUM(P66:P70) -> 0 | Q71: =SUM(Q66:Q70) -> 0 | R71: =SUM(R66:R70) -> 0 | S71: =SUM(S66:S70) -> 0 | ... U71: =SUM(U66:U70) -> 0
A72: ——联营企业 | J72: --
A73: 1 | B73: =B40 -> 0 | J73: =G73+H73-I73 -> 0 | R73: =G73+L73+M73 -> 0 | S73: =H73+N73+P73 -> 0 | T73: =I73+O73+Q73 -> 0 | U73: =R73+S73-T73 -> 0
A74: 2 | B74: =B41 -> 0 | J74: =G74+H74-I74 -> 0 | R74: =G74+L74+M74 -> 0 | S74: =H74+N74+P74 -> 0 | T74: =I74+O74+Q74 -> 0 | U74: =R74+S74-T74 -> 0
A75: 3 | B75: =B42 -> 0 | J75: =G75+H75-I75 -> 0 | R75: =G75+L75+M75 -> 0 | S75: =H75+N75+P75 -> 0 | T75: =I75+O75+Q75 -> 0 | U75: =R75+S75-T75 -> 0
A76: 4 | B76: =B43 -> 0 | J76: =G76+H76-I76 -> 0 | R76: =G76+L76+M76 -> 0 | S76: =H76+N76+P76 -> 0 | T76: =I76+O76+Q76 -> 0 | U76: =R76+S76-T76 -> 0
A77: 5 | B77: =B44 -> …… | J77: =G77+H77-I77 -> 0 | R77: =G77+L77+M77 -> 0 | S77: =H77+N77+P77 -> 0 | T77: =I77+O77+Q77 -> 0 | U77: =R77+S77-T77 -> 0
A78: 联营企业小计 | C78: -- | D78: -- | E78: -- | F78: -- | G78: =SUM(G73:G77) -> 0 | H78: =SUM(H73:H77) -> 0 | I78: =SUM(I73:I77) -> 0 | J78: =SUM(J73:J77) -> 0 | K78: -- | L78: =SUM(L73:L77) -> 0 | M78: =SUM(M73:M77) -> 0 | N78: =SUM(N73:N77) -> 0 | O78: =SUM(O73:O77) -> 0 | P78: =SUM(P73:P77) -> 0 | Q78: =SUM(Q73:Q77) -> 0 | R78: =SUM(R73:R77) -> 0 | S78: =SUM(S73:S77) -> 0 | ... U78: =SUM(U73:U77) -> 0
A79: 按权益法核算的长期股权投资小计 | C79: -- | D79: -- | E79: -- | F79: -- | G79: =G71+G78 -> 0 | H79: =H71+H78 -> 0 | I79: =I71+I78 -> 0 | J79: =J71+J78 -> 0 | K79: -- | L79: =L71+L78 -> 0 | M79: =M71+M78 -> 0 | N79: =N71+N78 -> 0 | O79: =O71+O78 -> 0 | P79: =P71+P78 -> 0 | Q79: =Q71+Q78 -> 0 | R79: =G79+L79+M79 -> 0 | S79: =H79+N79+P79 -> 0 | T79: =I79+O79+Q79 -> 0 | U79: =R79+S79-T79 -> 0
A80: 减值准备合计 | C80: -- | D80: -- | E80: -- | F80: -- | G80: =G63+G79 -> 0 | H80: =H63+H79 -> 0 | I80: =I63+I79 -> 0 | J80: =SUM(J53:J79) -> 0 | K80: -- | L80: =L63+L79 -> 0 | M80: =M63+M79 -> 0 | N80: =N63+N79 -> 0 | O80: =O63+O79 -> 0 | P80: =P63+P79 -> 0 | Q80: =Q63+Q79 -> 0 | R80: =G80+L80+M80 -> 0 | S80: =H80+N80+P80 -> 0 | T80: =I80+O80+Q80 -> 0 | U80: =R80+S80-T80 -> 0
A81: 长期股权投资净值合计 | C81: -- | D81: -- | E81: -- | F81: -- | G81: =H47-G80 -> 0 | H81: -- | I81: -- | J81: =U47-J80 -> 0 | K81: -- | L81: -- | M81: -- | N81: -- | O81: -- | P81: -- | Q81: -- | R81: =AO47-R80 -> 0 | S81: -- | T81: -- | U81: =BB47-U80 -> 0
A82: 三、审计说明：
A83: 1、 | B83: 长期股权投资存在所有权限制、承诺或留置的情况如下：
A86: 四、审计结论：
A91: 编制说明：
B92: 1、投资方式指现金出资、发行权益性证券、投资者投入、非货币性资产交换、债务重组、企业合并等。
B93: 2、投资文件指产权登记表、投资协议、出资证明、验资报告等。
B94: 3、备注可填写本年新增加、处置投资是否有授权批准、投资文件索引号或其他说明事项。
B95: 4、根据《中国注册会计师审计准则问题解答第18号——识别和应对第三方配合实施财务舞弊》：当期存在大额对外投资时，需考虑是否存在通过被审计单位将资金投入被投资单位，
B96: 再从被投资单位套取资金（如投资私募基金后，在私募基金配合下将投资款从私募基金转出），如果还识别出被审计单位存在可能导致关联方资金占用以及其他套取资金行为的舞弊风险因素，则很可能表面存在第三方配合舞弊，应采取恰当的措施应对。
B97: 5、审计说明可以概述:(1)程序的测试情况、结果;(2)拟调整事项及其调整分录、未调整事项及其影响，审计范围受到限制情况及其影响。
B98: 6、审计结论可参考:A、未见异常。 B、除上述重大不符事项应当作为调整事项予以调整外，其余未见异常。由于存在以下重大未调整事项(或审计范围受到限制无法获取充分、适当证据)，不可确认。

Sheet 调整分录汇总G7-3
A1: 致同会计师事务所
A2: 长期股权投资调整分录汇总表
A3: =底稿目录!A2 -> 被审计单位： | D3: =底稿目录!A4 -> 编制人： | G3: =底稿目录!A5 -> 编制日期： | I3: 索引号： | J3: =底稿目录!F9 -> G7-3
A4: =底稿目录!A3 -> 截止日：202X年12月31日 | D4: =底稿目录!A6 -> 复核人： | G4: =底稿目录!A7 -> 复核日期： | I4: 页 次：
A5: 调整事项说明 | B5: 类别（报表调整/账项调整/其他） | C5: 报表项目 | D5: 科目名称 | E5: 附注项目 | F5: …… | G5: 借方调整金额 | H5: 贷方调整金额 | I5: 索引 | J5: 备注

Sheet 被投资单位基本信息G7-4
A1: 致同会计师事务所
A2: 被投资单位基本信息
A3: =底稿目录!A2 -> 被审计单位： | F3: =底稿目录!A4 -> 编制人： | M3: =底稿目录!A5 -> 编制日期： | S3: 索引号： | T3: =底稿目录!F10 -> G7-4
A4: =底稿目录!A3 -> 截止日：202X年12月31日 | F4: =底稿目录!A6 -> 复核人： | M4: =底稿目录!A7 -> 复核日期： | S4: 页 次：
A5: 一、审计目标： | C5: 了解被审计单位投资公司的基本情况
A6: 二、审计过程 | C6: 1、取得被审计单位投资单位备查明细簿，了解投资单位的基本情况；
C7: 2、结合以前年度审计情况，了解被审计单位对各投资单位的核算方法。
C8: 3、结合“子公司初始计量测试”底稿，了解表决权比例不足半数但能对被投资单位形成控制的原因及直接或通过其他子公司间接拥有被投资单位半数以上的表决权但未能对其形成控制的原因
A9: 公司名称 | C9: 级次（国企适用） | D9: 企业类型（国企适用） | E9: 是否为本期新纳入合并范围的子公司（国企适用） | F9: 主要经营地 | G9: 注册地 | H9: 业务性质 | I9: 注册资本 | J9: 投资额 | K9: 期末净资产 | L9: 本期净利润 | M9: 持股比例/享有的份额% | O9: 表决权比例 | P9: 持股比例与表决权比例不一致的原因 | Q9: 表决权比例不足半数但能对被投资单位形成控制的原因 | R9: 直接或通过其他子公司间接拥有被投资单位半数以上的表决权但未能对其形成控制的原因 | S9: 取得方式 | T9: 会计处理方法
M10: 直接 | N10: 间接
A11: （一）子公司
B12: ='明细表G7-2'!B16 -> 0 | T12: 成本法
B13: ='明细表G7-2'!B17 -> 0
B14: ='明细表G7-2'!B18 -> 0
B15: ='明细表G7-2'!B19 -> 0
B16: ='明细表G7-2'!B20 -> 0
B17: ='明细表G7-2'!B21 -> 0
B18: ='明细表G7-2'!B22 -> 0
B19: ='明细表G7-2'!B23 -> 0
B20: ='明细表G7-2'!B24 -> 0
B21: ='明细表G7-2'!B25 -> ……
A22: （二）合营企业（共同控制）
B23: ='明细表G7-2'!B33 -> 0 | C23: -- | D23: -- | Q23: -- | T23: 权益法
B24: ='明细表G7-2'!B34 -> 0 | C24: -- | D24: -- | Q24: --
B25: ='明细表G7-2'!B35 -> 0 | C25: -- | D25: -- | Q25: --
B26: ='明细表G7-2'!B36 -> 0 | C26: -- | D26: -- | Q26: --
B27: ='明细表G7-2'!B37 -> …… | C27: -- | D27: -- | Q27: --
A28: （三）联营企业（重大影响）
B29: ='明细表G7-2'!B40 -> 0 | C29: -- | D29: -- | Q29: -- | T29: 权益法
B30: ='明细表G7-2'!B41 -> 0 | C30: -- | D30: -- | Q30: --
B31: ='明细表G7-2'!B42 -> 0 | C31: -- | D31: -- | Q31: --
B32: ='明细表G7-2'!B43 -> 0 | C32: -- | D32: -- | Q32: --
B33: ='明细表G7-2'!B44 -> …… | C33: -- | D33: -- | Q33: --
A34: （四）共同经营（共同控制）
C35: -- | D35: -- | O35: -- | P35: -- | T35: 各项单独确认
C36: -- | D36: -- | O36: -- | P36: --
C37: -- | D37: -- | O37: -- | P37: --
C38: -- | D38: -- | O38: -- | P38: --
A39: （注：企业类型：1.境内非金融子企业，2.境内金融子企业，3.境外子企业，4.事业单位，5.基建单位；
A40: 三、审计说明：
A42: 四、审计结论：

Sheet 被投资单位财务信息（合营、联营）G7-5
B1: 致同会计师事务所
B2: 被投资单位主要财务信息（合营、联营）
A3: =底稿目录!A2 -> 被审计单位： | D3: =底稿目录!A4 -> 编制人： | F3: =底稿目录!A5 -> 编制日期： | I3: 索引号： | J3: =底稿目录!F11 -> G7-5
A4: =底稿目录!A3 -> 截止日：202X年12月31日 | D4: =底稿目录!A6 -> 复核人： | F4: =底稿目录!A7 -> 复核日期： | I4: 页 次：
A5: 一、审计目标： | C5: 了解被审计单位合营、联营企业主要财务信息
A6: 二、审计过程 | C6: 取得被审计单位联营、合营企业已审计/审阅的财务报表；确定被投资单位联营、合营企业的主要财务信息
A7: 1.1重要合营、联营企业
B8: 项目 | C8: 合营企业1 | E8: 合营企业2 | G8: 联营企业1 | I8: 联营企业2
C9: 本期数 | D9: 上期数 | E9: 本期数 | F9: 上期数 | G9: 本期数 | H9: 上期数 | I9: 本期数 | J9: 上期数
B10: 流动资产
B11: 其中：现金和现金等价物
B12: 非流动资产
B13: 资产合计 | C13: =C10+C12 -> 0 | D13: =D10+D12 -> 0 | E13: =E10+E12 -> 0 | F13: =F10+F12 -> 0 | G13: =G10+G12 -> 0 | H13: =H10+H12 -> 0 | I13: =I10+I12 -> 0 | J13: =J10+J12 -> 0
B14: 流动负债
B15: 非流动负债
B16: 负债合计 | C16: =C14+C15 -> 0 | D16: =D14+D15 -> 0 | E16: =E14+E15 -> 0 | F16: =F14+F15 -> 0 | G16: =G14+G15 -> 0 | H16: =H14+H15 -> 0 | I16: =I14+I15 -> 0 | J16: =J14+J15 -> 0
B17: 净资产
B18: 其中：少数股东权益
B19: 归属于母公司的所有者权益
B20: 持股比例%
B21: 按持股比例计算的净资产份额 | C21: =C17*C20 -> 0 | D21: =D17*D20 -> 0 | E21: =E17*E20 -> 0 | F21: =F17*F20 -> 0 | G21: =G17*G20 -> 0 | H21: =H17*H20 -> 0 | I21: =I17*I20 -> 0 | J21: =J17*J20 -> 0
B22: 调整事项 | C22: =SUM(C23:C26) -> 0 | D22: =SUM(D23:D26) -> 0 | E22: =SUM(E23:E26) -> 0 | F22: =SUM(F23:F26) -> 0 | G22: =SUM(G23:G26) -> 0 | H22: =SUM(H23:H26) -> 0 | I22: =SUM(I23:I26) -> 0 | J22: =SUM(J23:J26) -> 0
B23: 其中：商誉
B24: 未实现内部交易损益
B25: 减值准备
B26: 其他
B27: 对合营/联营企业权益投资的账面价值 | C27: =C21-C22 -> 0 | D27: =D21-D22 -> 0 | E27: =E21-E22 -> 0 | F27: =F21-F22 -> 0 | G27: =G21-G22 -> 0 | H27: =H21-H22 -> 0 | I27: =I21-I22 -> 0 | J27: =J21-J22 -> 0
B28: 存在公开报价的权益投资的公允价值
B29: 营业收入
B30: 财务费用
B31: 所得税费用
B32: 净利润
B33: 终止经营的净利润
B34: 其他综合收益
B35: 综合收益总额 | C35: =C32+C34 -> 0 | D35: =D32+D34 -> 0 | E35: =E32+E34 -> 0 | F35: =F32+F34 -> 0 | G35: =G32+G34 -> 0 | H35: =H32+H34 -> 0 | I35: =I32+I34 -> 0 | J35: =J32+J34 -> 0
B36: 企业本期收到的来自合营/联营企业的股利
B37: 前期累积未确认的损失份额
B38: 本期未确认的损失份额（或本期实现净利润的分享额）
B39: 本期末累积未确认的损失份额 | C39: =C37+C38 -> 0 | D39: =D37+D38 -> 0 | E39: =E37+E38 -> 0 | F39: =F37+F38 -> 0 | G39: =G37+G38 -> 0 | H39: =H37+H38 -> 0 | I39: =I37+I38 -> 0 | J39: =J37+J38 -> 0
A40: 1.2其他合营企业
B41: 项 目 | C41: 公司1 | D41: 公司2 | E41: 公司3 | F41: 公司4 | G41: 期末数/本期发生数 | H41: 上期数/上期发生数
B42: 投资账面价值合计 | G42: =SUM(C42:F42) -> 0
B43: 下列各项按持股比例计算的合计数 | G43: =SUM(C43:F43) -> 0
B44: 净利润 | G44: =SUM(C44:F44) -> 0
B45: 其他综合收益 | G45: =SUM(C45:F45) -> 0
B46: 综合收益总额 | G46: =SUM(C46:F46) -> 0
A47: 1.3其他联营企业
B48: 项 目 | C48: 公司1 | D48: 公司2 | E48: 公司3 | F48: 公司4 | G48: 期末数/本期发生数 | H48: 上期数/上期发生数
B49: 投资账面价值合计 | G49: =SUM(C49:F49) -> 0
B50: 下列各项按持股比例计算的合计数 | G50: =SUM(C50:F50) -> 0
B51: 净利润 | G51: =SUM(C51:F51) -> 0
B52: 其他综合收益 | G52: =SUM(C52:F52) -> 0
B53: 综合收益总额 | G53: =SUM(C53:F53) -> 0
A54: 三、审计说明：
A56: 四、审计结论：

Sheet 被投资公司会计政策G7-6
A1: 致同会计师事务所
A2: 被投资单位会计政策
A3: =底稿目录!A2 -> 被审计单位： | C3: =底稿目录!A4 -> 编制人： | D3: =底稿目录!A5 -> 编制日期： | E3: 索引号： | F3: =底稿目录!F12 -> G7-6
A4: =底稿目录!A3 -> 截止日：202X年12月31日 | C4: =底稿目录!A6 -> 复核人： | D4: =底稿目录!A7 -> 复核日期： | E4: 页 次：
A5: 一、审计目标： | C5: 被投资公司会计政策与母公司主要会计政策比较，对主要会计政策差异在合并时进行调整
A6: 二、审计过程 | C6: 1、取得被投资单位会计政策，与被审计单位会计政策进行比对；
C7: 2、确定被投资单位是否需要为符合投资单位的会计政策而作出的任何必要的会计政策调整。
B8: 政策项目 | C8: AAA公司 | F8: 与本公司政策是否一致
B9: 会计年度 | C9: 1月1日-12月31日 | F9: 是
B10: 计量属性 | C10: 除公允价值套期工具外，按照历史价格计价 | F10: 是
B11: 记账本位币 | C11: 人民币 | F11: 是
B12: 外币折算 | C12: 交易发生日即期汇率折算 | F12: 是
B13: 现金及现金等价物 | C13: 随时可用于支付的流动性强、价值变动很小的投资
B14: 存货 | C14: 取得时实际成本入账、月末一次加权平均和移动加权平均法、成本与可变现净值孰低，永续盘存。 | F14: 是
B15: 长期股权投资 | F15: 是
B16: 固定资产 | C16: 使用周期超过一个会计年度的有形资产。 | F16: 是
B17: 累计折旧 | C17: 平均年限法 | F17: 是
B18: 在建工程 | C18: 达到预定可使用状态时转入固定资产，在建工程不计提折旧 | F18: 是
B19: 无形资产 | C19: 以成本减累计折旧于报表列示，直线法在预计可使用期限内摊销，土地使用权摊销按照土地证上年限摊销，无使用期限不固定的无形资产。 | F19: 是
B20: 职工薪酬 | C20: 除辞退福利外，其他计入当期负债及成本费用 | F20: 是
B21: 收入 | C21: 权责发生制 | F21: 是
B22: ……
A23: 三、审计说明
A24: 1 | B24: 主要会计政策基本相同。
B25: AAA公司为07年11月成立，其成立时被审计单位即持股30%。其主要资产为自行购建，且主要为自用，公允价值与其账面价值一致。
A29: 四、审计结论
B30: 经审计，未发现重大异常。

Sheet 长期股权投资初始判断G7-7
A1: 致同会计师事务所
A2: 长期股权投资初始判断
A3: =底稿目录!A2 -> 被审计单位： | D3: =底稿目录!A4 -> 编制人： | E3: =底稿目录!A5 -> 编制日期： | G3: 索引号： | H3: =底稿目录!F13 -> G7-7
A4: =底稿目录!A3 -> 截止日：202X年12月31日 | D4: =底稿目录!A6 -> 复核人： | E4: =底稿目录!A7 -> 复核日期： | G4: 页 次：
A5: 一、审计目标： | C5: 确定被审计单位对子公司长期股权投资初始计量是否恰当
A6: 二、审计过程：
A7: 1、是否控制的判断及结论
A8: 判断的事项 | D8: 公司1 | F8: 公司2
D9: 对应情形 | E9: 结论 | F9: 对应情形 | G9: 结论
A10: 被投资者的目标及设计
A11: 是否控制
A12: （1）权力
A13: （2）面临可变回报的风险
A14: （3）使用权力影响可变回报的能力
A15: 结 论
A16: 2、联营企业与合营企业的判断
A17: 合营判断（共同控制）： | D17: 说明 | E17: 联营判断（重大影响）： | H17: 说明 | I17: 审计证据
A18: （l）任何一个合营方均不能单独控制合营企业的相关活动 | E18: （1）在被投资单位的董事会或类似权力机构中派有代表
A19: （2）涉及合营企业的相关活动的决策需要各合营方一致同意 | E19: （2）参与被投资单位的政策制定过程,包括股利分配政策等的制定
A20: （3）各合营方可能通过合同或协议的形式任命其中的一个合营方对合营企业的日常活动进行管理,但其必须在各合营方已经一致同意的相关活动范围内行使管理权。 | E20: （3）与被投资单位之间发生重要交易
E21: （4）向被投资单位派出管理人员
A22: （4）其他 | E22: （5）向被投资单位提供关键技术资料
E23: （6）其他
A24: 3、确认合并（购买）日：
A25: 确认依据： | D25: 公司1 | E25: 公司2 | F25: 公司3
A26: （1）企业合并合同或协议已获股东大会等内部权力机构通过。
A27: （2）合并事项需要经过国家有关主管部门审批的，已获得相关部门的批准
A28: （3）参与合并各方已办理了必要的财产权交接手续。
A29: （4）购买方已支付了购买价款的大部分（一般应超过50％），并且有能力、有计划支付剩余款项。
A30: （5）购买方实际上已经控制了被购买方的财务和经营政策，享有相应的收益并承担相应的风险。
A31: 最终确定的合并（购买）日 | D31: 年 月 日 | E31: 年 月 日 | F31: 年 月 日
A32: 审计证据索引号
A33: 三、审计说明
A37: 四、审计结论
A40: 提示：
A41: 3、合并方式取得的长期股权投资初始投资成本：
A42: A、上述计算前提是合并前合并方与被合并方采用的会计政策应当一致。如企业合并前合并方与被合并方采用的会计政策不同的，应基于重要性原则，统一合并方与被合并方的会计政策。在按照合并方的会计政策对被合并方资产、负债的账面价值进行调整的基础上，计算确定形成长期股权投资的初始投资成本。
A43: B、在编制合并资产负债表时，对于被合并方在企业合并前实现的留存收益（盈余公积和未分配利润之和）中归属于合并方的部分，应按以下原则，自合并方的资本公积转入留存收益和未分配利润：
A44: ①确认企业合并形成的长期股权投资后，合并方账面资本公积（资本溢价或股本溢价）贷方余额大于被合并方在合并前实现的留存收益中归属于合并方的部分，在合并资产负债表中，应将被合并方在合并前实现的留存收益中归属于合并方的部分自“资本公积”转入“盈余公积”和“未分配利润”。在合并工作底稿中，借记“资本公积”项目，贷记“盈余公积”和“未分配利润”项目。 ②确认企业合并形成的长期股权投资后，合并方面资本公积（资本溢价或股本溢价）贷方余额小于被合并方在合并前实现的留存收益中归属于合并方的部分的，在合并资产负债表中，应以合并方资本公积(资本溢价或股本溢价)的贷方余额为限，将被合并方在企业合并前实现的留存收益中归属于合并方的部分自“资本公积”转入“盈余公积”和“未分配利润”。在合并工作底稿中，借记“资本公积”项目，贷记“盈余公积”和“未分配利润”项目。 因合并方的资本公积（资本溢价或股本溢价）余额不足，被合并方在合并前实现的留存收益中归属于合并方的部分在合并资产负债表中未予全额恢复的，合并方应当在会计报表附注中对这一情况进行说明。
A45: C、如果分步取得对子公司股权投资直至取得控制权的各项交易属于“一揽子交易”，应当将各项交易作为一项取得子公司控制权的交易。
A46: 4、通过多次交易分步实现的同一控制下企业合并（不构成一揽子交易）：
A47: 通过多次交易分步实现同一控制下的企业合并，在个别财务报表中，以合并日持股比例计算的合并日应享有被合并方净资产在最终控制方合并财务报表中的账面价值的份额作为该项投资的初始投资成本；初始投资成本与原持有投资的账面价值加上合并日新增投资成本之和的差额，调整资本公积（股本溢价/资本溢价），资本公积不足冲减的，调整留存收益。

Sheet 子公司初始计量测试（同控）G7-8
A1: 致同会计师事务所
A2: 子公司初始计量测试表
A3: =底稿目录!A2 -> 被审计单位： | D3: =底稿目录!A4 -> 编制人： | F3: =底稿目录!A5 -> 编制日期： | H3: 索引号： | I3: =底稿目录!F14 -> G7-8
A4: =底稿目录!A3 -> 截止日：202X年12月31日 | D4: =底稿目录!A6 -> 复核人： | F4: =底稿目录!A7 -> 复核日期： | H4: 页 次：
A5: 一、审计目标： | C5: 确定被审计单位对子公司长期股权投资初始计量是否恰当
A6: 二、审计过程：
A7: 1、合并方式取得的长期股权投资初始投资成本：
A8: 审核项目 | D8: 公司1 | E8: 索引 | F8: 公司2 | G8: 索引 | H8: 公司3 | I8: 索引
A9: 最终控制方
A10: 被合并方所有者权益账面价值（如果被合并方存在合并财务报表，则取合并报表数据）① | D10: 100
A11: 合并方合并后占被投资单位的出资比例② | D11: 0.32
A12: 长期股权投资初始投资成本：③=①*② | D12: =D10*D11 -> 32 | F12: =F10*F11 -> 0 | H12: =H10*H11 -> 0
A13: 购买方付出的资产，发生或承担的负债、发行的权益性证券的账面价值之和④ | D13: =SUM(D14:D18) -> 10 | F13: =SUM(F14:F18) -> 0 | H13: =SUM(H14:H18) -> 0
A14: 其中：现金 | D14: 2
A15: 非现金资产的账面价值 | D15: 2
A16: 发行或承担的债务的账面价值 | D16: 3
A17: 发行的权益性证券的面值
A18: 或有对价 | D18: 3
A19: 母公司报表中调整资本公积、留存收益⑤=③-④ | D19: =D12-D13 -> 22 | F19: =F12-F13 -> 0 | H19: =H12-H13 -> 0
A21: 2、通过多次交易分步实现的同一控制下企业合并（不构成一揽子交易）：
A22: 项目 | D22: P公司 | G22: Q公司
A23: 次别 | D23: 1 | E23: 2 | F23: 小计 | G23: 4 | H23: 5 | I23: 小计
A24: 交易日期 | D24: 1 | E24: 1 | F24: -- | I24: --
A25: 购买比例① | D25: 0.01 | E25: 0.02 | F25: =SUM(D25:E25) -> 0.03 | I25: =SUM(G25:H25) -> 0
A26: 支付对价② | D26: 1 | E26: 3 | F26: =SUM(D26:E26) -> 4 | I26: =SUM(G26:H26) -> 0
A27: 每笔交易发生时被投资方可辨认净资产的账面价值 | D27: 22 | E27: 44 | F27: -- | I27: --
A28: 因权益法核算确认的长期股权投资其他综合收益、损益调整和其他变动或其他投资确认的计入其他综合收益的公允价值调整③ | D28: 22 | E28: 4 | F28: =SUM(D28:E28) -> 26 | I28: =SUM(G28:H28) -> 0
A29: 公司名称 | C29: 合并日被投资方可辨认净资产的账面价值④ | D29: 合并日长期股权投资投资成本：⑤=④*① | E29: 母公司报表中调整资本公积、留存收益⑥=②+③-⑤ | F29: 索引/备注
A30: P公司 | C30: =E27 -> 44 | D30: =C30*F25 -> 1.32 | E30: =F26+F28-D30 -> 28.68
A31: Q公司 | C31: =H27 -> 0 | D31: =C31*I25 -> 0 | E31: =I26+I28-D31 -> 0
A33: 3、反向购买
A34: 交易内容 | C34: 会计上的购买方 | D34: 会计上的购买方的股东 | E34: 会计上的被购买方（上市公司） | F34: 会计上的被购买方的原股东（上市公司原股东） | G34: 判断构成反向购买的依据 | H34: 是否构成业务及其判断依据 | I34: 索引号
A38: 三、审计说明
A42: 四、审计结论
A45: 提示：
A46: 3、合并方式取得的长期股权投资初始投资成本：
A47: A、上述计算前提是合并前合并方与被合并方采用的会计政策应当一致。如企业合并前合并方与被合并方采用的会计政策不同的，应基于重要性原则，统一合并方与被合并方的会计政策。在按照合并方的会计政策对被合并方资产、负债的账面价值进行调整的基础上，计算确定形成长期股权投资的初始投资成本。
A48: B、在编制合并资产负债表时，对于被合并方在企业合并前实现的留存收益（盈余公积和未分配利润之和）中归属于合并方的部分，应按以下原则，自合并方的资本公积转入留存收益和未分配利润：
A49: ①确认企业合并形成的长期股权投资后，合并方账面资本公积（资本溢价或股本溢价）贷方余额大于被合并方在合并前实现的留存收益中归属于合并方的部分，在合并资产负债表中，应将被合并方在合并前实现的留存收益中归属于合并方的部分自“资本公积”转入“盈余公积”和“未分配利润”。在合并工作底稿中，借记“资本公积”项目，贷记“盈余公积”和“未分配利润”项目。 ②确认企业合并形成的长期股权投资后，合并方面资本公积（资本溢价或股本溢价）贷方余额小于被合并方在合并前实现的留存收益中归属于合并方的部分的，在合并资产负债表中，应以合并方资本公积(资本溢价或股本溢价)的贷方余额为限，将被合并方在企业合并前实现的留存收益中归属于合并方的部分自“资本公积”转入“盈余公积”和“未分配利润”。在合并工作底稿中，借记“资本公积”项目，贷记“盈余公积”和“未分配利润”项目。 因合并方的资本公积（资本溢价或股本溢价）余额不足，被合并方在合并前实现的留存收益中归属于合并方的部分在合并资产负债表中未予全额恢复的，合并方应当在会计报表附注中对这一情况进行说明。
A50: C、如果分步取得对子公司股权投资直至取得控制权的各项交易属于“一揽子交易”，应当将各项交易作为一项取得子公司控制权的交易。
A51: 4、通过多次交易分步实现的同一控制下企业合并（不构成一揽子交易）：
A52: 通过多次交易分步实现同一控制下的企业合并，在个别财务报表中，以合并日持股比例计算的合并日应享有被合并方净资产在最终控制方合并财务报表中的账面价值的份额作为该项投资的初始投资成本；初始投资成本与原持有投资的账面价值加上合并日新增投资成本之和的差额，调整资本公积（股本溢价/资本溢价），资本公积不足冲减的，调整留存收益。

Sheet 子公司初始计量测试（非同控）G7-9
A1: 致同会计师事务所
A2: 子公司初始计量测试表
A3: =底稿目录!A2 -> 被审计单位： | D3: =底稿目录!A4 -> 编制人： | F3: =底稿目录!A5 -> 编制日期： | H3: 索引号： | I3: =底稿目录!F15 -> G7-9
A4: =底稿目录!A3 -> 截止日：202X年12月31日 | D4: =底稿目录!A6 -> 复核人： | F4: =底稿目录!A7 -> 复核日期： | H4: 页 次：
A5: 一、审计目标： | C5: 确定被审计单位对子公司长期股权投资初始计量是否恰当
A6: 二、审计过程：
A7: 1、合并方式取得的长期股权投资初始投资成本：
A8: 审核项目 | D8: A公司 | E8: 索引 | F8: B公司 | G8: 索引 | H8: C公司 | I8: 索引
A9: 被合并方所有者权益账面价值
A10: 被购买方可辨认净资产的公允价值①
A11: 合并后占被投资单位的出资比例②
A12: 购买方付出的资产，发生或承担的负债、发行的权益性证券的公允价值之和③ | D12: =SUM(D13:D17) -> 0 | F12: =SUM(F13:F17) -> 0 | H12: =SUM(H13:H17) -> 0
A13: 其中：现金
A14: 非现金资产的公允价值
A15: 发行或承担的债务的公允价值
A16: 发行的权益性证券的公允价值
A17: 或有对价的公允价值
A18: 购买日之前持有的股权于购买日的公允价值④
A19: 购买方付出的资产，发生或承担的负债、发行的权益性证券的账面价值之和⑤
A20: 投资方初始投资成本：⑥=③+④ | D20: =D12+D18 -> 0 | F20: =F12+F18 -> 0 | H20: =H12+H18 -> 0
A21: 记入当期损益（营业外收入）⑦=③-⑤ | D21: =D12-D19 -> 0 | F21: =F12-F19 -> 0 | H21: =H12-H19 -> 0
A22: 合并报表中的商誉或损益（或吸收合并时计入母公司报表中的商誉或损益）⑧=⑥-①*② | D22: =D20-D10*D11 -> 0 | F22: =F20-F10*F11 -> 0 | H22: =H20-H10*H11 -> 0
A24: 2、通过多次交易分步实现的非同一控制下企业合并（不构成一揽子交易）
A25: 项目 | D25: M公司 | G25: N公司
A26: 次别 | D26: 1 | E26: 2 | F26: 小计 | G26: 1 | H26: 2 | I26: 小计
A27: 交易日期 | F27: -- | I27: --
A28: 购买比例① | F28: =SUM(D28:E28) -> 0 | I28: =SUM(G28:H28) -> 0
A29: 支付对价② | F29: =SUM(D29:E29) -> 0 | I29: =SUM(G29:H29) -> 0
A30: 每笔交易发生时被投资方可辨认净资产的公允价值③ | F30: -- | I30: --
A31: 每单交易应享有的被投资方可辨认净资产的公允价值的份额 ④=①*③ | D31: =D28*D30 -> 0 | E31: =E28*E30 -> 0 | F31: =SUM(D31:E31) -> 0 | G31: =G28*G30 -> 0 | H31: =H28*H30 -> 0 | I31: =SUM(G31:H31) -> 0
A32: 每单交易应确认的商誉或损益⑤=②-④ | D32: =D29-D31 -> 0 | E32: =E29-E31 -> 0 | F32: =SUM(D32:E32) -> 0 | G32: =G29-G31 -> 0 | H32: =H29-H31 -> 0 | I32: =SUM(G32:H32) -> 0
A33: 因权益法核算确认的长期股权投资其他综合收益、损益调整和其他变动或其他投资确认的计入其他综合收益的公允价值调整⑥ | F33: =SUM(D33:E33) -> 0 | I33: =SUM(G33:H33) -> 0
A34: 合并日母公司长期股权投资的确认金额⑦=②+⑥ | D34: -- | E34: -- | F34: =F29+F33 -> 0 | G34: -- | H34: -- | I34: =I29+I33 -> 0
A36: 3、反向购买
A37: 交易内容 | C37: 会计上的购买方 | D37: 会计上的购买方的股东 | E37: 会计上的被购买方（上市公司） | F37: 会计上的被购买方的原股东（上市公司原股东） | G37: 判断构成反向购买的依据 | H37: 是否构成业务及其判断依据 | I37: 索引号
A41: 三、审计说明
A44: 四、审计结论
A47: 提示：
A48: 3、合并方式取得的长期股权投资初始投资成本：
A49: A、购买方为企业合并发生的审计、法律服务、评估咨询等中介费用以及其他相关管理费用，应当于发生时计入当期损益；购买方作为合并对价发行的权益性证券或债务性证券的交易费用，应当计入权益性证券或债务性证券的初始确认金额。
A50: B、取得投资时点一般会与评估基准日有时间差异，请注意公允价值的调整。
A51: C、如果分步取得对子公司股权投资直至取得控制权的各项交易属于“一揽子交易”，应当将各项交易作为一项取得子公司控制权的交易。
A52: 4、通过多次交易分步实现的非同一控制下企业合并（不构成一揽子交易）
A53: A、通过多次交换交易分步实现非同一控制下企业合并的，在个别财务报表中，以购买日之前所持被购买方的股权投资的账面价值与购买日新增投资成本之和，作为该项投资的初始投资成本。购买日之前持有的股权投资因采用权益法核算而确认的其他综合收益，应当在处置该项投资时采用与被投资单位直接处置相关资产或负债相同的基础进行会计处理；因被投资方除净损益、其他综合收益和利润分配以外的其他所有者权益变动而确认的所有者权益，应当在处置该项投资时转入处置期间的当期损益。购买日之前持有的股权投资按照《企业会计准则第22号——金融工具确认和计量》的有关规定进行会计处理的，原计入其他综合收益的累计公允价值变动应当在改按成本法核算时转入当期损益。

Sheet 子公司后续计量测试表G7-10
A1: 致同会计师事务所
A2: 子公司后续计量测试表
A3: =底稿目录!A2 -> 被审计单位： | D3: =底稿目录!A4 -> 编制人： | F3: =底稿目录!A5 -> 编制日期： | H3: 索引号： | I3: =底稿目录!F16 -> G7-10
A4: =底稿目录!A3 -> 截止日：202X年12月31日 | D4: =底稿目录!A6 -> 复核人： | F4: =底稿目录!A7 -> 复核日期： | H4: 页 次：
A5: 一、审计目标： | C5: 确定子公司长期股权投资及其相关账户后续计量是否正确。
A6: 二、审计过程：
A7: 1、被投资单位分配股利测算
A8: 公司名称 | B8: 分配方案、股东/董事会决议 | C8: 持股比例 | D8: 宣告分派股利日 | E8: 主要股利分配政策 | F8: 宣告分派的股利金额 | G8: 被审计单位应分配股利 | H8: 实际入账股利 | I8: 差异
G9: =C9*F9 -> 0 | I9: =G9-H9 -> 0
G10: =C10*F10 -> 0 | I10: =G10-H10 -> 0
G11: =C11*F11 -> 0 | I11: =G11-H11 -> 0
G12: =C12*F12 -> 0 | I12: =G12-H12 -> 0
G13: =C13*F13 -> 0 | I13: =G13-H13 -> 0
A14: 2、购买少数股东股权的处理
A15: 项 目 | C15: 公司1 | D15: 公司2 | E15: 项 目 | G15: 公司1 | H15: 公司2
A16: 新增日长期股权投资账面价值 | E16: 子公司自购买日(或合并日)开始持续计算的可辨认净资产的公允价值③
A17: 原持股比例 | E17: 按新增持股比例计算应享有子公司自购买日(或合并日)开始持续计算的可辨认净资产的公允价值的份额 ④=③*① | G17: =G16*C18 -> 0 | H17: =H16*D18 -> 0
A18: 新增的持股比例① | E18: 调整合并报表中的资本公积/留存收益⑤=④-② | G18: =G17-C19 -> 0 | H18: =H17-D19 -> 0
A19: 购买成本② | C19: =SUM(C20:C24) -> 0 | D19: =SUM(D20:D24) -> 0 | E19: 其中：调整资本公积
A20: 其中：现金 | E20: 调整盈余公积
A21: 非现金资产的公允价值 | E21: 调整未分配利润
A22: 发行或承担的债务的账面价值 | E22: 索引号
A23: 发行的权益性证券的面值
A24: 或有对价
A25: 购买少数股权后长期股权投资账面价值 | C25: =C16+C19 -> 0 | D25: =D16+D19 -> 0
A27: 3、处置子公司权益但不丧失控制权
A28: 项 目 | C28: 公司1 | D28: 公司2 | E28: 项 目 | G28: 公司1 | H28: 公司2
A29: 处置日长期股权投资账面价值① | E29: 子公司自购买日(或合并日)开始持续计算的可辨认净资产的公允价值⑥
A30: 原持股比例② | E30: 按减少的持股比例计算应享有子公司自购买日(或合并日)开始持续计算的可辨认净资产的公允价值的份额⑦=⑥*③ | G30: =H29*C31 -> 0 | H30: =I29*D31 -> 0
A31: 减少的持股比例③ | E31: 调整合并报表中的资本公积/留存收益 ⑧=⑦-④ | G31: =G30-C32 -> 0 | H31: =H30-D32 -> 0
A32: 处置对价④ | C32: =SUM(C33:C37) -> 0 | D32: =SUM(D33:D37) -> 0 | E32: 其中：调整资本公积
A33: 其中：现金 | E33: 调整盈余公积
A34: 非现金资产的公允价值 | E34: 调整未分配利润
A35: 发行或承担的债务的账面价值 | E35: 索引号
A36: 发行的权益性证券的面值
A37: 或有对价
A38: 计入个别报表的投资收益 ⑤=④-③/②*① | C38: =IF(C30=0,0,C32-C31/C30*C29) -> 0 | D38: =IF(D30=0,0,D32-D31/D30*D29) -> 0
A39: 三、审计说明
A42: 四、审计结论
A45: 提示：
A46: 2、购买少数股东股权的处理
A47: A、母公司个别财务报表中对于自子公司少数股东处新取得的长期股权投资，应当按照《企业会计准则第2 号——长期股权投资》第四条的规定，确定长期股权投资的入账价值。
A48: B、在合并财务报表中，子公司的资产、负债应以购买日（或合并日）开始持续计算的金额反映。母公司新取得的长期股权投资成本与按照新增持股股比例计算应享有子公司自购买日（或合并日）开始持续计算的可辨认净资产份额之间的差额，应当调整合并财务报表中的资本公积（资本溢价或股本溢价），资本公积（资本溢价或股本溢价）的余额不足冲减的，调整留存收益。

Sheet 处置子公司测试表（不包含一揽子交易）G7-11
A1: 致同会计师事务所
A2: 处置子公司测试表（不包含一揽子交易）
A3: =底稿目录!A2 -> 被审计单位： | E3: =底稿目录!A4 -> 编制人： | I3: =底稿目录!A5 -> 编制日期： | K3: 索引号： | L3: =底稿目录!F17 -> G7-11
A4: =底稿目录!A3 -> 截止日：202X年12月31日 | E4: =底稿目录!A6 -> 复核人： | I4: =底稿目录!A7 -> 复核日期： | K4: 页 次：
A5: 一、审计目标： | C5: 确定处置子公司的会计处理是否恰当。
A6: 二、审计过程：
A7: 1.本期处置的子公司基本情况
B8: 企业名称 | C8: 注册地 | D8: 业务性质 | E8: 持股比例% | F8: 表决权比例% | G8: 本期不再成为子公司的原因
B14: 子公司名称 | C14: 股权处置价款 | D14: 原股权比例% | E14: 股权处置比例% | F14: 剩余股权比例% | G14: 剩余股权构成 | H14: 股权处置方式 | I14: 丧失控制权的时点 | J14: 丧失控制权时点的确定依据 | K14: 取得的查验资料 | L14: 索引号
F15: =D15-E15 -> 0 | K15: 股权转让协议、产权交割单、…
F16: =D16-E16 -> 0
F17: =D17-E17 -> 0
F18: =D18-E18 -> 0
A19: 2.1 单体报表
B20: 子公司名称 | C20: 处置日长期股权投资账面价值 | D20: 应转出的长投 | E20: 丧失控制权之日剩余股权的账面价值 | F20: 丧失控制权之日剩余股权的公允价值 | G20: 按公允价值重新计量产生的利得/损失 | H20: 原子公司投资系联营/合营投资追加投资形成，与原联营/合营投资有关的可重分类至损益的OCI和其他净资产变动 | I20: 原子公司投资系金融资产投资追加投资形成，与原金融资产相关的按照公允价值计量的OCI | J20: 原子公司投资系联营/合营投资追加投资形成，与原联营/合营投资有关不可重分类至损益的OCI | K20: 处置子公司应确认的投资收益 | L20: 应转入权益
B21: =B15 -> 0 | D21: =IF(D15=0,0,C21*E15/D15) -> 0 | E21: =C21-D21 -> 0 | G21: =F21-E21 -> 0 | K21: =IF(D15=0,0,IF(G15="联营",G21+H21*E15/D15,IF(G15="合营",G21+H21*E15/D15,G21+I21))) -> 0 | L21: =IF(D15=0,0,IF(G15="联营",J21*E15/D15,IF(G15="合营",J21*E15/D15,J21))) -> 0
B22: =B16 -> 0 | D22: =C22*E16 -> 0 | E22: =C22-D22 -> 0 | G22: =F22-E22 -> 0 | K22: =IF(D16=0,0,IF(G16="联营",G22+H22*E16/D16,IF(G16="合营",G22+H22*E16/D16,G22+I22))) -> 0 | L22: =IF(D16=0,0,IF(G16="联营",J22*E16/D16,IF(G16="合营",J22*E16/D16,J22))) -> 0
B23: =B17 -> 0 | D23: =C23*E17 -> 0 | E23: =C23-D23 -> 0 | G23: =F23-E23 -> 0 | K23: =IF(D17=0,0,IF(G17="联营",G23+H23*E17/D17,IF(G17="合营",G23+H23*E17/D17,G23+I23))) -> 0 | L23: =IF(D17=0,0,IF(G17="联营",J23*E17/D17,IF(G17="合营",J23*E17/D17,J23))) -> 0
B24: =B18 -> 0 | D24: =C24*E18 -> 0 | E24: =C24-D24 -> 0 | G24: =F24-E24 -> 0 | K24: =IF(D18=0,0,IF(G18="联营",G24+H24*E18/D18,IF(G18="合营",G24+H24*E18/D18,G24+I24))) -> 0 | L24: =IF(D18=0,0,IF(G18="联营",J24*E18/D18,IF(G18="合营",J24*E18/D18,J24))) -> 0
A25: 2.2合并报表
B26: 子公司名称 | C26: 处置日合并财务报表层面子公司的净资产 | D26: 处置日合并财务报表层面享有该子公司净资产份额 | E26: 处置价款与处置投资对应的合并财务报表层面享有该子公司净资产份额的差额 | F26: 合并财务报表中与该子公司相关的商誉 | G26: 丧失控制权之日剩余股权的账面价值 | H26: 丧失控制权之日剩余股权的公允价值 | I26: 按公允价值重新计量产生的利得/损失 | J26: 丧失控制权之日剩余股权的公允价值的确定方法及主要假设 | K26: 与原子公司股权投资相关的其他综合收益转入投资损益的金额 | L26: 备注
B27: =B15 -> 0 | C27: 11 | D27: =IF(D15=0,0,C27*E15/D15) -> 0 | E27: =C15-D27 -> 0 | F27: 22 | G27: 4 | H27: =F21 -> 0 | I27: =H27-G27 -> -4 | J27: 5 | K27: =C15+H27-C27-F27 -> -33
B28: =B16 -> 0 | D28: =IF(D16=0,0,C28*E16/D16) -> 0 | E28: =C16-D28 -> 0 | G28: =E22 -> 0 | H28: =F22 -> 0 | I28: =H28-G28 -> 0 | K28: =C16+H28-C28-F28 -> 0
B29: =B17 -> 0 | D29: =IF(D17=0,0,C29*E17/D17) -> 0 | E29: =C17-D29 -> 0 | G29: =E23 -> 0 | H29: =F23 -> 0 | I29: =H29-G29 -> 0 | K29: =C17+H29-C29-F29 -> 0
B30: =B18 -> 0 | D30: =IF(D18=0,0,C30*E18/D18) -> 0 | E30: =C18-D30 -> 0 | G30: =E24 -> 0 | H30: =F24 -> 0 | I30: =H30-G30 -> 0 | K30: =C18+H30-C30-F30 -> 0
A32: 3、单次处置剩余股权为联营、合营时追溯调整为权益法
B33: 被投资单位名称 | C33: 持股比例 | D33: 被投资单位 | H33: 归属于母公司
D34: 原取得投资日至处置日净利润 | E34: 本期净利润 | F34: 其他综合收益 | G34: 其他所有者权益变动 | H34: 期初未分配利润 | I34: 盈余公积 | J34: 投资收益 | K34: 长期投资-其他综合收益 | L34: 长期投资-其他变动
C35: ① | D35: ② | E35: ③ | F35: ④ | G35: ⑤ | H35: ⑥=①*②*90% | I35: ⑦=①*②*10% | J35: ⑧=③×① | K35: ⑨=④×① | L35: ⑩=⑤×①
H36: =C36*D36*90% -> 0 | I36: =D36*C36*10% -> 0 | J36: =C36*E36 -> 0 | K36: =C36*F36 -> 0 | L36: =G36*C36 -> 0
H37: =C37*D37*90% -> 0 | I37: =D37*C37*10% -> 0 | J37: =C37*E37 -> 0 | K37: =C37*F37 -> 0 | L37: =G37*C37 -> 0
H38: =C38*D38*90% -> 0 | I38: =D38*C38*10% -> 0 | J38: =C38*E38 -> 0 | K38: =C38*F38 -> 0 | L38: =G38*C38 -> 0
H39: =C39*D39*90% -> 0 | I39: =D39*C39*10% -> 0 | J39: =C39*E39 -> 0 | K39: =C39*F39 -> 0 | L39: =G39*C39 -> 0
A40: 三、审计说明
A44: 四、审计结论

Sheet 处置子公司测试表（一揽子交易）G7-12
A1: 致同会计师事务所
A2: 处置子公司测试表（一揽子交易）
A3: =底稿目录!A2 -> 被审计单位： | E3: =底稿目录!A4 -> 编制人： | I3: =底稿目录!A5 -> 编制日期： | K3: 索引号： | L3: =底稿目录!F18 -> G7-12
A4: =底稿目录!A3 -> 截止日：202X年12月31日 | E4: =底稿目录!A6 -> 复核人： | I4: =底稿目录!A7 -> 复核日期： | K4: 页 次：
A5: 一、审计目标： | C5: 确定处置子公司的会计处理是否恰当。
A6: 二、审计过程：
A7: 1.本期处置的子公司基本情况
B8: 企业名称 | C8: 注册地 | D8: 业务性质 | E8: 持股比例% | F8: 表决权比例% | G8: 本期不再成为子公司的原因
A14: 2.多次交易分步处置股权至丧失控制权而减少的子公司
B15: 一揽子交易的判断事项 | E15: 公司1 | G15: 公司2 | I15: 公司3 | K15: 公司4
E16: 对应情形 | F16: 结论 | G16: 对应情形 | H16: 结论 | I16: 对应情形 | J16: 结论 | K16: 对应情形 | L16: 结论
B17: 这些交易是同时或者在考虑了彼此影响的情况下订立的
B18: 这些交易整体才能达成一项完整的商业结果
B19: 一项交易的发生取决于其他至少一项交易的发生
B20: 一项交易单独看是不经济的，但是和其他交易一并考虑时是经济的
B21: 结论
B22: 子公司名称 | C22: 股权处置价款 | D22: 原股权比例% | E22: 股权处置比例% | F22: 剩余股权比例% | G22: 剩余股权构成 | H22: 股权处置方式 | I22: 丧失控制权的时点 | J22: 丧失控制权时点的确定依据 | K22: 取得的查验资料 | L22: 索引号
F23: =D23-E23 -> 0 | K23: 股权转让协议、产权交割单、…
F24: =D24-E24 -> 0
F25: =D25-E25 -> 0
F26: =D26-E26 -> 0
A27: 2.1单体报表
B28: 子公司名称 | C28: 处置日长期股权投资账面价值 | D28: 应转出的长投 | E28: 丧失控制权之日剩余股权的账面价值 | F28: 丧失控制权之日剩余股权的公允价值 | G28: 按公允价值重新计量产生的利得/损失 | H28: 原子公司投资系联营/合营投资追加投资形成，与原联营/合营投资有关的可重分类至损益的OCI和其他净资产变动 | I28: 原子公司投资系金融资产投资追加投资形成，与原金融资产相关的按照公允价值计量的OCI | J28: 原子公司投资系联营/合营投资追加投资形成，与原联营/合营投资有关不可重分类至损益的OCI | K28: 处置子公司应确认的投资收益 | L28: 应转入权益
B29: =B23 -> 0 | D29: =IF(D23=0,0,C29*E23/D23) -> 0 | E29: =C29-D29 -> 0 | G29: =F29-E29 -> 0 | K29: =IF(D23=0,0,IF(G23="联营",G29+H29*E23/D23,IF(G23="合营",F29-E29+H29*E23/D23,G29+I29))) -> 0 | L29: =IF(D23=0,0,IF(G23="联营",J29*E23/D23,IF(G23="合营",J29*E23/D23,J29))) -> 0
B30: =B24 -> 0 | D30: =C30*E24 -> 0 | E30: =C30-D30 -> 0 | G30: =F30-E30 -> 0 | K30: =IF(D24=0,0,IF(G24="联营",G30+H30*E24/D24,IF(G24="合营",F30-E30+H30*E24/D24,G30+I30))) -> 0 | L30: =IF(D24=0,0,IF(G24="联营",J30*E24/D24,IF(G24="合营",J30*E24/D24,J30))) -> 0
B31: =B25 -> 0 | D31: =C31*E25 -> 0 | E31: =C31-D31 -> 0 | G31: =F31-E31 -> 0 | K31: =IF(D25=0,0,IF(G25="联营",G31+H31*E25/D25,IF(G25="合营",F31-E31+H31*E25/D25,G31+I31))) -> 0 | L31: =IF(D25=0,0,IF(G25="联营",J31*E25/D25,IF(G25="合营",J31*E25/D25,J31))) -> 0
B32: =B26 -> 0 | D32: =C32*E26 -> 0 | E32: =C32-D32 -> 0 | G32: =F32-E32 -> 0 | K32: =IF(D26=0,0,IF(G26="联营",G32+H32*E26/D26,IF(G26="合营",F32-E32+H32*E26/D26,G32+I32))) -> 0 | L32: =IF(D26=0,0,IF(G26="联营",J32*E26/D26,IF(G26="合营",J32*E26/D26,J32))) -> 0
A33: 2.2合并报表
B34: 子公司名称 | C34: 处置日合并财务报表层面子公司的净资产 | D34: 处置日合并财务报表层面享有该子公司净资产份额 | E34: 处置价款与处置投资对应的合并财务报表层面享有该子公司净资产份额的差额 | F34: 合并财务报表中与该子公司相关的商誉 | G34: 丧失控制权之日剩余股权的账面价值 | H34: 丧失控制权之日剩余股权的公允价值 | I34: 按公允价值重新计量产生的利得/损失 | J34: 丧失控制权之日剩余股权的公允价值的确定方法及主要假设 | K34: 与原子公司股权投资相关的其他综合收益转入投资损益的金额 | L34: 丧失控制权之前的各步交易处置价款与处置投资对应的合并财务报表层面享有该子公司净资产份额的差额
B35: =B23 -> 0 | D35: =IF(D23=0,0,C35*E23/D23) -> 0 | E35: =C23-D35 -> 0 | G35: =E29 -> 0 | H35: =F29 -> 0 | I35: =H35-G35 -> 0 | K35: =C23+H35-C35-F35 -> 0
B36: =B24 -> 0 | D36: =IF(D24=0,0,C36*E24/D24) -> 0 | E36: =C24-D36 -> 0 | G36: =E30 -> 0 | H36: =F30 -> 0 | I36: =H36-G36 -> 0 | K36: =C24+H36-C36-F36 -> 0
B37: =B25 -> 0 | D37: =IF(D25=0,0,C37*E25/D25) -> 0 | E37: =C25-D37 -> 0 | G37: =E31 -> 0 | H37: =F31 -> 0 | I37: =H37-G37 -> 0 | K37: =C25+H37-C37-F37 -> 0
B38: =B26 -> 0 | D38: =IF(D26=0,0,C38*E26/D26) -> 0 | E38: =C26-D38 -> 0 | G38: =E32 -> 0 | H38: =F32 -> 0 | I38: =H38-G38 -> 0 | K38: =C26+H38-C38-F38 -> 0
A39: 2.3剩余股权为联营、合营时追溯调整为权益法
B40: 被投资单位名称 | C40: 持股比例 | D40: 被投资单位 | H40: 归属于母公司
D41: 原取得投资日至处置日净利润 | E41: 本期净利润 | F41: 其他综合收益 | G41: 其他所有者权益变动 | H41: 期初未分配利润 | I41: 盈余公积 | J41: 投资收益 | K41: 长期投资-其他综合收益 | L41: 长期投资-其他变动
C42: ① | D42: ② | E42: ③ | F42: ④ | G42: ⑤ | H42: ⑥=①*②*90% | I42: ⑦=①*②*10% | J42: ⑧=③×① | K42: ⑨=④×① | L42: ⑩=⑤×①
H43: =C43*D43*90% -> 0 | I43: =D43*C43*10% -> 0 | J43: =C43*E43 -> 0 | K43: =C43*F43 -> 0 | L43: =G43*C43 -> 0
H44: =C44*D44*90% -> 0 | I44: =D44*C44*10% -> 0 | J44: =C44*E44 -> 0 | K44: =C44*F44 -> 0 | L44: =G44*C44 -> 0
H45: =C45*D45*90% -> 0 | I45: =D45*C45*10% -> 0 | J45: =C45*E45 -> 0 | K45: =C45*F45 -> 0 | L45: =G45*C45 -> 0
H46: =C46*D46*90% -> 0 | I46: =D46*C46*10% -> 0 | J46: =C46*E46 -> 0 | K46: =C46*F46 -> 0 | L46: =G46*C46 -> 0
A47: 三、审计说明
A51: 四、审计结论

Sheet 合营、联营企业投资成本测试表G7-13
A1: 致同会计师事务所
A2: 合营、联营企业投资成本测试表
A3: =底稿目录!A2 -> 被审计单位： | F3: =底稿目录!A4 -> 编制人： | I3: =底稿目录!A5 -> 编制日期： | L3: 索引号： | M3: =底稿目录!F19 -> G7-13
A4: =底稿目录!A3 -> 截止日：202X年12月31日 | F4: =底稿目录!A6 -> 复核人： | I4: =底稿目录!A7 -> 复核日期： | L4: 页 次：
A5: 一、审计目标： | C5: 确定联营、合营企业的会计处理是否恰当。
A6: 二、审计过程 | C6: 1、检查与长期股权投资相关的原始文件或其他支持文件（股权投资协议及框架协议（如有）、交易双方对于交易事项的审批文件、相关政府机关的批准文件、权利交接手续（特别是董事会改选）、款项的收付凭据）。
C7: 2、综合判断长期股权投资是否满足共同控制/重大影响。
C8: 3、取得被审计单位管理层对被投资单位可辨认净资产公允价值的认定及依据的中介机构报告。检查被投资单位可辨认净资产公允价值的确认依据是否充分；
C9: 4、识别期后发生的长期股权投资的增加，检查至支持性文件，确定是否是被记录在恰当的期间内。
C10: 5、对于不纳入合并范围的被投资单位的预付投资款项或预收处置款项，确认重大条款和金额。
A11: （一）被投资单位基本情况
A12: 被投资单位A：
B13: 出资单位名称 | D13: 注册资本 | H13: 实收资本
D14: 期初注册资本 | E14: 本期增加 | F14: 本期减少 | G14: 期末注册资本 | H14: 期初实收资本 （股本） | I14: 本期增加 | J14: 本期减少 | K14: 期末实收资本 （股本）
B15: 1、本公司 | G15: =D15+E15-F15 -> 0 | K15: =H15+I15-J15 -> 0
B16: 2、 …股东 | G16: =D16+E16-F16 -> 0 | K16: =H16+I16-J16 -> 0
B17: 3、 …股东 | G17: =D17+E17-F17 -> 0 | K17: =H17+I17-J17 -> 0
B18: 合计 | D18: =SUM(D15:D17) -> 0 | E18: =SUM(E15:E17) -> 0 | F18: =SUM(F15:F17) -> 0 | G18: =SUM(G15:G17) -> 0 | H18: =SUM(H15:H17) -> 0 | I18: =SUM(I15:I17) -> 0 | J18: =SUM(J15:J17) -> 0 | K18: =SUM(K15:K17) -> 0
A19: （二）公司对其历次投资情况检查
B20: 1、一次投入投资成本确认：
B21: 被投资单位名称 | C21: 投资时间 | D21: 初始投资成本(支付对价) (A) | E21: 投资发生时被投资单位可辨认净资产公允价值 | G21: 新增投资与应享有的被投资单位可辨认净资产公允价值份额的差额（D）=A-B*C | H21: 确认本次投资的投资成本（E） | I21: 计入营业外收入金额（F）
E22: 金额 (B) | F22: 投资比例 （C)
G23: =D23-E23*F23 -> 0 | H23: =IF(G23>0,D23,D23-G23) -> 0 | I23: =IF(G23<0,-G23,0) -> 0
G24: =D24-E24 -> 0 | H24: =IF(G24>0,D24,D24-G24) -> 0 | I24: =IF(G24<0,-G24,0) -> 0
G25: =D25-E25 -> 0 | H25: =IF(G25>0,D25,D25-G25) -> 0 | I25: =IF(G25<0,-G25,0) -> 0
G26: =D26-E26 -> 0 | H26: =IF(G26>0,D26,D26-G26) -> 0 | I26: =IF(G26<0,-G26,0) -> 0
B27: 合计 | D27: =SUM(D23:D26) -> 0 | E27: =SUM(E23:E26) -> 0 | F27: =SUM(F23:F26) -> 0 | G27: =SUM(G23:G26) -> 0 | H27: =SUM(H23:H26) -> 0 | I27: =IF(G27<0,-G27,0) -> 0
B28: 2、原持有的对被投资单位不具有控制、共同控制或重大影响的金融资产，因追加投资导致持股比例上升,能够对被投资单位施加重大影响或是实施共同控制的,长期股权投资账面价值合计：
B29: 被投资单位名称 | C29: 原投资在追加投资日的公允价值(A) | D29: 原投资比例(B) | E29: 新增投资确认的投资成本（C） | F29: 追加的投资比例(D) | G29: 追加投资时被投资单位可辨认净资产公允价值(E) | H29: 新增投资与应享有的被投资单位可辨认净资产公允价值份额的差额（F）=(A)+(C)-(B+D)*E | I29: 确认本次投资的投资成本（G） | J29: 计入营业外收入金额（H） | K29: 原取得投资后至追加投资的交易日之间被投资单位公允价值的变动
K30: 原取得投资至追加投资当期期初已计入其他综合收益的累计公允价值变动（I） | L30: 追加投资当期期初至追加投资交易日之间的公允价值变动（J） | M30: 转入投资收益：公允价值变动合计（K=I+J）
H31: =C31+E31-(D31+F31)*G31 -> 0 | I31: =IF(H31>0,C31+E31,C31+E31-H31) -> 0 | J31: =IF(H31<0,-H31,0) -> 0 | M31: =K31+L31 -> 0
H32: =C32+E32-(D32+F32)*G32 -> 0 | I32: =IF(H32>0,C32+E32,C32+E32-H32) -> 0 | J32: =IF(H32<0,-H32,0) -> 0 | M32: =K32+L32 -> 0
H33: =C33+E33-(D33+F33)*G33 -> 0 | I33: =IF(H33>0,C33+E33,C33+E33-H33) -> 0 | J33: =IF(H33<0,-H33,0) -> 0 | M33: =K33+L33 -> 0
B34: 合计 | C34: -- | D34: -- | E34: -- | F34: -- | G34: -- | H34: -- | I34: -- | J34: =SUM(J31:J33) -> 0 | K34: -- | L34: -- | M34: =SUM(M31:M33) -> 0
B36: 3、主动增资：投资单位对联营企业的持股比例增加，但被投资单位仍然是投资单位的联营企业或合营企业时，长期股权投资账面价值合计：
B37: 被投资单位名称 | C37: 新增投资时的原账面价值（A） | D37: 其中：原投资的内含商誉（B） | E37: 原投资比例（C） | F37: 新增投资确认的投资成本（D） | G37: 新增投资比例（E） | H37: 新增投资时被投资单位单位可辨认净资产公允价值（F） | I37: 新增投资与应享有的被投资单位可辨认净资产公允价值份额的差额（G）=D-E*F | J37: 确认本次投资的投资成本（H） | K37: 计入营业外收入金额（I）
I38: =F38-G38*H38 -> 0 | J38: =IF((D38+I38)>0,F38,F38-I38-D38) -> 0 | K38: =IF(I38+D38<0,I38-D38,0) -> 0
I39: =F39-G39*H39 -> 0 | J39: =IF((D39+I39)>0,F39,F39-I39-D39) -> 0 | K39: =IF(I39+D39<0,I39-D39,0) -> 0
I40: =F40-G40*H40 -> 0 | J40: =IF((D40+I40)>0,F40,F40-I40-D40) -> 0 | K40: =IF(I40+D40<0,I40-D40,0) -> 0
I41: =F41-G41*H41 -> 0 | J41: =IF((D41+I41)>0,F41,F41-I41-D41) -> 0 | K41: =IF(I41+D41<0,I41-D41,0) -> 0
B42: 合计 | C42: -- | D42: -- | E42: -- | F42: -- | G42: -- | H42: -- | I42: =SUM(I38:I41) -> 0 | J42: =SUM(J38:J41) -> 0 | K42: =SUM(K38:K41) -> 0
A44: （三）取得投资时被投资单位可辨认净资产账面价值与公允价值差异及以后年度账面净利润的调整
B45: 项目 | C45: 取得投资时 | F45: 差异*在取得投资以后期间的调整数 ⊿
C46: 账面价值 | D46: 公允价值 △ | E46: 公允价与账面价值的差异* | F46: ××年 | G46: ××年 | H46: ××年 | I46: ××年 | J46: ××年 | K46: ××年 | L46: … | M46: 合计
B47: 存货 | E47: =C47-D47 -> 0 | L47: =SUM(F47:K47) -> 0 | M47: =SUM(F47:L47) -> 0
B48: 固定资产 | E48: =C48-D48 -> 0 | L48: =SUM(F48:K48) -> 0 | M48: =SUM(F48:L48) -> 0
B49: 无形资产 | E49: =C49-D49 -> 0 | L49: =SUM(F49:K49) -> 0 | M49: =SUM(F49:L49) -> 0
B50: 资产类合计 | C50: =SUM(C47:C49) -> 0 | D50: =SUM(D47:D49) -> 0 | E50: =C50-D50 -> 0 | F50: =D50-E50 -> 0 | G50: =E50-F50 -> 0 | H50: =F50-G50 -> 0 | I50: =G50-H50 -> 0 | J50: =H50-I50 -> 0 | K50: =I50-J50 -> 0 | L50: =J50-K50 -> 0 | M50: =SUM(F50:L50) -> 0
B51: 应付账款 | E51: =C51-D51 -> 0 | L51: =SUM(F51:K51) -> 0 | M51: =SUM(F51:L51) -> 0
B52: 负债类合计 | C52: =SUM(C51:C51) -> 0 | D52: =SUM(D51:D51) -> 0 | E52: =C52-D52 -> 0 | F52: =D52-E52 -> 0 | G52: =E52-F52 -> 0 | H52: =F52-G52 -> 0 | I52: =G52-H52 -> 0 | J52: =H52-I52 -> 0 | K52: =I52-J52 -> 0 | L52: =J52-K52 -> 0 | M52: =SUM(F52:L52) -> 0
B53: 净资产 | C53: =C50-C52 -> 0 | D53: =D50-D52 -> 0 | E53: =C53-D53 -> 0 | F53: =D53-E53 -> 0 | G53: =E53-F53 -> 0 | H53: =F53-G53 -> 0 | I53: =G53-H53 -> 0 | J53: =H53-I53 -> 0 | K53: =I53-J53 -> 0 | L53: =J53-K53 -> 0 | M53: =SUM(F53:L53) -> 0
B54: 当期净利润调整数(差异调整） | M54: =SUM(F54:L54) -> 0
B55: 审计说明：
B56: 1.取得投资时公允价值依据是________________________________________________报告
B57: 2.取得投资时账面价值与公允价值的差异在取得投资后期间内的调整系依据__________________________________________________规定
B58: 3.取得投资时点往往与评估报告基准日有时间差，需要根据评估报告基准日公允价值调整取得时点时账面价值
A60: 三、审计说明
A62: 四、审计结论
A64: 提示：
A65: 2、原持有的对被投资单位不具有控制、共同控制或重大影响的金融资产，因追加投资导致持股比例上升,能够对被投资单位施加重大影响或是实施共同控制的,长期股权投资账面价值合计：
A66: 原持有的对被投资单位的股权投资（不具有控制、共同控制或重大影响的），按照金融工具确认和计量准则进行会计处理的，因追加投资等原因导致持股比例上升，能够对被投资单位施加共同控制或重大影响的，在转按权益法核算时，投资方应当按照金融工具确认和计量准则确定的原股权投资的公允价值加上为取得新增投资而应支付对价的公允价值，作为改按权益法核算的初始投资成本。原持有的股权投资分类为可供出售金融资产的，其公允价值与账面价值之间的差额，以及原计入其他综合收益的累计公允价值变动应当转入改按权益法核算的当期损益。然后，比较上述计算所得的初始投资成本，与按照追加投资后全新的持股比例计算确定的应享有被投资单位在追加投资日可辨认净资产公允价值份额之间的差额，前者大于后者的，不调整长期股权投资的账面价值；前者小于后者的，差额应调整长期股权投资的账面价值，并计入当期营业外收入。
A67: 3、主动增资：投资单位对联营企业的持股比例增加，但被投资单位仍然是投资单位的联营企业或合营企业时，长期股权投资账面价值合计：
A68: 提示：投资方因增加投资等原因对被投资单位的持股比例增加，但被投资单位仍然是投资方的联营企业或合营企业时，投资方应当按照新的持股比例对股权投资继续采用权益法进行核算。在新增投资日，如果新增投资成本大于按新增持股比例计算的被投资单位可辨认净资产于新增投资日的公允价值份额，不调整长期股权投资成本；如果新增投资成本小于按新增持股比例计算的被投资单位可辨认净资产于新增投资日的公允价值份额，应按该差额，调整长期股权投资成本和营业外收入。进行上述调整时，应当综合考虑与原持有投资和追加投资相关的商誉或计入损益的金额。

Sheet 权益法测算表G7-14
A1: 致同会计师事务所 | J1: 致同会计师事务所
A2: 权益法测算表 | J2: 权益法测算表
A3: =底稿目录!A2 -> 被审计单位： | D3: =底稿目录!A4 -> 编制人： | F3: =底稿目录!A5 -> 编制日期： | H3: 索引号： | I3: =底稿目录!F20 -> G7-14 | J3: =A3 -> 被审计单位： | L3: =D3 -> 编制人： | N3: =F3 -> 编制日期： | S3: =H3 -> 索引号： | T3: =I3 -> G7-14
A4: =底稿目录!A3 -> 截止日：202X年12月31日 | D4: =底稿目录!A6 -> 复核人： | F4: =底稿目录!A7 -> 复核日期： | H4: 页 次： | J4: =A4 -> 截止日：202X年12月31日 | L4: =D4 -> 复核人： | N4: =F4 -> 复核日期： | S4: =H4 -> 页 次： | T4: =I4 -> 0
A5: 一、审计目标： | C5: 确定权益法核算的会计处理是否恰当。 | J5: =A5 -> 一、审计目标： | K5: =B5 -> 0 | L5: =C5 -> 确定权益法核算的会计处理是否恰当。
A6: 二、审计过程 | J6: =A6 -> 二、审计过程 | K6: =B6 -> 0 | L6: =C6 -> 0
A7: 1、被投资单位权益法调整测算 | J7: =A7 -> 1、被投资单位权益法调整测算 | K7: =B7 -> 0 | L7: =C7 -> 0
B8: 被投资单位名称 | C8: 持股比例 | D8: 被投资单位 | G8: 测算 | J8: 已宣告发放的归属于被审计单位单位的股利 | K8: 账面确认投资收益 | L8: 差异 | M8: 账面确认的其他综合收益 | N8: 差异 | O8: 账面确认的其他权益变动 | P8: 差异 | Q8: 备注
D9: 本期净利润 | E9: 其他综合收益 | F9: 其他权益变动 | G9: 投资收益 | H9: 长期投资-其他综合收益 | I9: 其他权益变动
C10: ① | D10: ② | E10: ③ | F10: ④ | G10: ⑤=①×② | H10: ⑥=①×③ | I10: ⑦=①×④ | J10: ⑧ | K10: ⑨ | L10: ⑩=⑨-⑤+⑧ | M10: ⑪ | N10: ⑫=⑪-⑥ | O10: ⑬ | P10: ⑭=⑬-⑦
B11: ='明细表G7-2'!B40 -> 0 | C11: ='明细表G7-2'!D40 -> 0 | G11: =C11*D11 -> 0 | H11: =C11*E11 -> 0 | I11: =C11*F11 -> 0 | L11: =K11-G11+J11 -> 0 | N11: =M11-H11 -> 0 | P11: =O11-I11 -> 0
B12: ='明细表G7-2'!B41 -> 0 | C12: ='明细表G7-2'!D41 -> 0 | G12: =C12*D12 -> 0 | H12: =C12*E12 -> 0 | I12: =C12*F12 -> 0 | L12: =K12-G12+J12 -> 0 | N12: =M12-H12 -> 0 | P12: =O12-I12 -> 0
B13: ='明细表G7-2'!B42 -> 0 | C13: ='明细表G7-2'!D42 -> 0 | G13: =C13*D13 -> 0 | H13: =C13*E13 -> 0 | I13: =C13*F13 -> 0 | L13: =K13-G13+J13 -> 0 | N13: =M13-H13 -> 0 | P13: =O13-I13 -> 0
B14: ='明细表G7-2'!B43 -> 0 | C14: ='明细表G7-2'!D43 -> 0 | G14: =C14*D14 -> 0 | H14: =C14*E14 -> 0 | I14: =C14*F14 -> 0 | L14: =K14-G14+J14 -> 0 | N14: =M14-H14 -> 0 | P14: =O14-I14 -> 0
B15: 合计 | D15: =SUM(D11:D14) -> 0 | E15: =SUM(E11:E14) -> 0 | F15: =SUM(F11:F14) -> 0 | G15: =SUM(G11:G14) -> 0 | H15: =SUM(H11:H14) -> 0 | I15: =SUM(I11:I14) -> 0 | J15: =SUM(J11:J14) -> 0 | K15: =SUM(K11:K14) -> 0 | ... P15: =SUM(P11:P14) -> 0
A16: 2、长期股权投资期末余额审核
B17: 被投资单位 | C17: 持股比例 | D17: 投资成本 | G17: 损益调整 | J17: 其他综合收益 | M17: 其他权益变动 | P17: 经审计的被投资单位净资产 | Q17: 按股权比例计算享有被投资单位净资产 | R17: 账面余额 | S17: 与享有净资产差额 | T17: 备注
D18: 期初余额 | E18: 本期增减（+/-）金额 | F18: 期末余额 | G18: 期初余额 | H18: 本期增减（+/-）金额 | I18: 期末余额 | J18: 期初余额 | K18: 本期增减（+/-）金额 | L18: 期末余额 | M18: 期初余额 | N18: 本期增减（+/-）金额 | O18: 期末余额
B19: =B11 -> 0 | C19: =C11 -> 0 | D19: ='明细表G7-2'!AO40 -> 0 | E19: ='明细表G7-2'!AQ40 -> 0 | F19: =D19+E19 -> 0 | H19: ='明细表G7-2'!AR40 -> 0 | I19: =G19+H19 -> 0 | K19: ='明细表G7-2'!AS40 -> 0 | L19: =J19+K19 -> 0 | N19: ='明细表G7-2'!AT40 -> 0 | O19: =M19+N19 -> 0 | Q19: =P19*C19 -> 0 | R19: =O19+L19+I19+F19 -> 0 | S19: =R19-Q19 -> 0
B20: =B12 -> 0 | C20: =C12 -> 0 | D20: ='明细表G7-2'!AO41 -> 0 | E20: ='明细表G7-2'!AQ41 -> 0 | F20: =D20+E20 -> 0 | H20: ='明细表G7-2'!AR41 -> 0 | I20: =G20+H20 -> 0 | K20: ='明细表G7-2'!AS41 -> 0 | L20: =J20+K20 -> 0 | N20: ='明细表G7-2'!AT41 -> 0 | O20: =M20+N20 -> 0 | Q20: =P20*C20 -> 0 | R20: =O20+L20+I20+F20 -> 0 | S20: =R20-Q20 -> 0
B21: =B13 -> 0 | C21: =C13 -> 0 | D21: ='明细表G7-2'!AO42 -> 0 | E21: ='明细表G7-2'!AQ42 -> 0 | F21: =D21+E21 -> 0 | H21: ='明细表G7-2'!AR42 -> 0 | I21: =G21+H21 -> 0 | K21: ='明细表G7-2'!AS42 -> 0 | L21: =J21+K21 -> 0 | N21: ='明细表G7-2'!AT42 -> 0 | O21: =M21+N21 -> 0 | Q21: =P21*C21 -> 0 | R21: =O21+L21+I21+F21 -> 0 | S21: =R21-Q21 -> 0
B22: 合计 | D22: =SUM(D19:D21) -> 0 | E22: =SUM(E19:E21) -> 0 | F22: =SUM(F19:F21) -> 0 | G22: =SUM(G19:G21) -> 0 | H22: =SUM(H19:H21) -> 0 | I22: =SUM(I19:I21) -> 0 | J22: =SUM(J19:J21) -> 0 | K22: =SUM(K19:K21) -> 0 | ... S22: =SUM(S19:S21) -> 0
A23: 3、被投资单位所有者权益账面价值变动及调整情况
B24: 项目 | D24: 年初净资产 | E24: 本期增加 | F24: 本期减少 | G24: 期末净资产
B25: 账面数： | G25: =D25+E25-F25 -> 0
B26: 实收资本（或股本） | G26: =D26+E26-F26 -> 0
B27: 资本公积 | G27: =D27+E27-F27 -> 0
B28: 减：库存股 | G28: =D28+E28-F28 -> 0
B29: 其他综合收益 | G29: =D29+E29-F29 -> 0
B30: 盈余公积 | G30: =D30+E30-F30 -> 0
B31: 专项储备 | G31: =D31+E31-F31 -> 0
B32: 未分配利润 | G32: =D32+E32-F32 -> 0
B33: 归属于母公司所有者权益合计 | D33: =SUM(D26:D27,-D28,D29:D32) -> 0 | E33: =SUM(E26:E27,-E28,E29:E32) -> 0 | F33: =SUM(F26:F27,-F28,F29:F32) -> 0 | G33: =SUM(G26:G27,-G28,G29:G32) -> 0
B34: 少数股东权益 | G34: =D34+E34-F34 -> 0
B35: 所有者权益合计 | D35: =D34+D33 -> 0 | E35: =E34+E33 -> 0 | F35: =F34+F33 -> 0 | G35: =G34+G33 -> 0
B36: 加： | G36: =D36+E36-F36 -> 0
B37: 取得投资时公允价值与账面价值差异调整数（表四） | G37: =D37+E37-F37 -> 0
B38: 本期净利润的其他调整数 | G38: =D38+E38-F38 -> 0
B39: 期初公允价值差异累计调整数 | G39: =D39+E39-F39 -> 0
B40: 减： | G40: =D40+E40-F40 -> 0
B41: 未实现内部交易损益抵消（见内部交易抵销测算表 ） | G41: =D41+E41-F41 -> 0
B42: 调整后所有者权益合计 | D42: =D35+D37+D38+D39-D41 -> 0 | E42: =E35+E37+E38+E39-E41 -> 0 | F42: =F35+F37+F38+F39-F41 -> 0 | G42: =G35+G37+G38+G39-G41 -> 0
G43: =D43+E43-F43 -> 0
B44: 本公司持股比例 | G44: =D44+E44-F44 -> 0
B45: 本公司应享有的所有者权益 | D45: =D42*D44 -> 0 | E45: =E42*E44 -> 0 | F45: =F42*F44 -> 0 | G45: =G42*G44 -> 0
B46: 注：1、上表中被投资单位与投资单位的会计政策应当一致，如不一致应按调整后的账面价值数据填入上表。
B47: 2、请关注本公司持股比例与表决权比例不一致时需要对上表数据调整，如不一致，必须作出说明。
A48: 三、审计说明
A51: 四、审计结论

Sheet 权益法未实现内部交易抵销测算表G7-15
A1: 致同会计师事务所
A2: 权益法未实现内部交易抵销测算表
A3: =底稿目录!A2 -> 被审计单位： | E3: =底稿目录!A4 -> 编制人： | H3: =底稿目录!A5 -> 编制日期： | K3: 索引号： | L3: =底稿目录!F21 -> G7-15
A4: =底稿目录!A3 -> 截止日：202X年12月31日 | E4: =底稿目录!A6 -> 复核人： | H4: =底稿目录!A7 -> 复核日期： | K4: 页 次：
A5: 一、审计目标： | D5: 确定对于投资企业与其联营企业及合营企业之间发生的未实现内部交易损益予以抵消的金额是否正确。
A6: 二、审计过程 | D6: 1、取得与联营、合营企业发生的内部交易明细，了解内部交易所涉及资产目前状态；
D7: 2、测算对被投资单位未实现内部交易抵消是否正确，如有，与适当的管理人员沟通并进一步追踪。
B8: 被投资单位： | D8: 公司 | F8: 投资比例：
A9: 1、未实现的内部顺流交易（①期初有未实现内部损益的项目和②本期发生的期末有未实现内部损益的项目）
A10: 出售项目 | C10: 出售方（投资企业）计入的损益科目 | D10: 购买方（联营或合营企业）计入的资产负债科目 | E10: 出售期间（年份） | F10: 出售金额① | G10: 出售成本② | H10: 期末已计提折旧或其它已实现损益③ | I10: 期末未实现的内部损益④=①-②-③ | J10: 未实现的内部顺流交易应调整的利润 | L10: 备注
J11: 本期数⑤=④-⑥ | K11: 以前年度累计数（根据上年数填列）
A12: 出售库存商品 | C12: 主营业务收入 | D12: 库存商品（固定资产） | I12: =F12-G12-H12 -> 0 | J12: =IF((F12-G12)>0,F12-G12-H12-K12,0) -> 0
A13: 出售固定资产 | C13: 营业外收入 | D13: 固定资产（库存商品） | I13: =F13-G13-H13 -> 0 | J13: =IF((F13-G13)>0,F13-G13-H13-K13,0) -> 0
A14: …… | B14: …… …… | I14: =F14-G14-H14 -> 0 | J14: =IF((F14-G14)>0,F14-G14-H14-K14,0) -> 0
I15: =F15-G15-H15 -> 0 | J15: =IF((F15-G15)>0,F15-G15-H15-K15,0) -> 0
I16: =F16-G16-H16 -> 0 | J16: =IF((F16-G16)>0,F16-G16-H16-K16,0) -> 0
A17: 合计 | F17: =SUM(F12:F16) -> 0 | G17: =SUM(G12:G16) -> 0 | H17: =SUM(H12:H16) -> 0 | I17: =SUM(I12:I16) -> 0 | J17: =SUM(J12:J16) -> 0 | K17: =SUM(K12:K16) -> 0
A18: 2、未实现的内部逆流交易（①期初有未实现内部损益的项目和②本期发生的期末有未实现内部损益的项目）
A19: 出售项目 | C19: 出售方（联营或合营企业）计入的损益科目 | D19: 购买方（投资企业）计入的资产负债科目 | E19: 出售期间（年份） | F19: 出售金额① | G19: 出售成本② | H19: 期末已计提折旧或其它已实现损益③ | I19: 期末未实现的内部损益④=①-②-③ | J19: 未实现的内部顺流交易应调整的利润 | L19: 备注
J20: 本期数⑤=④-⑥ | K20: 以前年度累计数（根据上年数填列）
A21: 出售库存商品 | C21: 主营业务收入 | D21: 库存商品（固定资产） | I21: =F21-G21-H21 -> 0 | J21: =IF((F21-G21)>0,F21-G21-H21-K21,0) -> 0
A22: 出售固定资产 | C22: 营业外收入 | D22: 固定资产（库存商品） | I22: =F22-G22-H22 -> 0 | J22: =IF((F22-G22)>0,F22-G22-H22-K22,0) -> 0
A23: …… | B23: …… …… | I23: =F23-G23-H23 -> 0 | J23: =IF((F23-G23)>0,F23-G23-H23-K23,0) -> 0
I24: =F24-G24-H24 -> 0 | J24: =IF((F24-G24)>0,F24-G24-H24-K24,0) -> 0
I25: =F25-G25-H25 -> 0 | J25: =IF((F25-G25)>0,F25-G25-H25-K25,0) -> 0
A26: 合计 | F26: =SUM(F21:F25) -> 0 | G26: =SUM(G21:G25) -> 0 | H26: =SUM(H21:H25) -> 0 | I26: =SUM(I21:I25) -> 0 | J26: =SUM(J21:J25) -> 0 | K26: =SUM(K21:K25) -> 0
A27: 提示：
A28: 1、投资企业在对被投资单位的净利润进行调整时，应考虑重要性原则，不具有重要性的项目可不予调整。
A29: 2、本表的索引请与“长期股权投资-权益法-合营企业、联营企业 ”审核表 的索引号做交叉索引。
A30: 3、未实现的内部顺流交易：
A31: （1）投资企业与其联营企业及合营企业之间发生的无论是顺流交易还是逆流交易产生的未实现内部交易损失，属于所转让资产发生减值损失的，有关的未实现内部交易损失不应予以抵销。
A32: （2）如果投资企业存在子公司需要编制合并财务报表，在合并财务报表中对本期发生的未实现内部交易损益应在个别报表已确认投资收益的基础上进行以下调整：
C33: 借：主营业务收入（营业外收入等） | F33: →按（本期出售金额（1）*投资比例）确认
C34: 贷：主营业务成本（……） | G34: →按（本期出售成本（2）*投资比例）确认
C35: 投资收益 | G35: →按（本期出售金额（1）-（本期出售成本（2）*投资比例）确认
A36: 4、未实现的内部逆流交易：
A37: （1）投资企业与其联营企业及合营企业之间发生的无论是顺流交易还是逆流交易产生的未实现内部交易损失，属于所转让资产发生减值损失的，有关的未实现内部交易损失不应予以抵销。
A38: （2）如果投资企业存在子公司需要编制合并财务报表，在合并财务报表中，因该未实现内部交易体现在投资企业持有的资产的账面价值当中，应在合并财务报表中进行以下调整：
C39: 借：长期股权投资-损益调整 | F39: →按期末未实现内部损益项目的（出售金额（1）-出售成本（2）-期末已计提折旧或其它已实现损益(3)）确认
C40: 累计折旧（或累计摊销等） | F40: →按未实现内部损益项目的（期末已计提折旧或其它已实现损益(3)）确认
C41: 贷：库存商品（或固定资产等） | G41: →按未实现内部损益项目的（出售金额（1）-出售成本（2））确认

Sheet 未确认投资损失测试表G7-16
A1: 致同会计师事务所
A2: 未确认投资损失测试表
A3: =底稿目录!A2 -> 被审计单位： | E3: =底稿目录!A4 -> 编制人： | G3: =底稿目录!A5 -> 编制日期： | J3: 索引号： | K3: =底稿目录!F22 -> G7-16
A4: =底稿目录!A3 -> 截止日：202X年12月31日 | E4: =底稿目录!A6 -> 复核人： | G4: =底稿目录!A7 -> 复核日期： | J4: 页 次：
A5: 一、审计目标： | C5: 确定对联营、合营企业超额亏损的确认是否恰当。
A6: 二、审计过程： | C6: 1、取得被投资单位财务报表，了解被投资单位的经营情况；
C7: 2、取得被审计单位未确认投资损失备查簿，测算期末未确认投资损失。
A8: 被投资单位名称 | C8: 持股比例 | D8: 账面期末余额 | F8: 被投资单位净资产 | H8: 未确认投资损失 | K8: 备注
D9: 长期投资 | E9: 长期权益 | F9: 期初数 | G9: 期末数 | H9: 期初数 | I9: 本期数 | J9: 期末数
A10: ① | C10: ② | D10: ③ | E10: ④ | F10: ⑤ | G10: ⑥ | H10: ⑦ | I10: ⑧=③+④-（⑥-⑤）×② | J10: ⑨=⑦+⑧
A11: 合营企业
I12: =D12+E12-(G12-F12)*C12 -> 0 | J12: =H12+I12 -> 0
I13: =D13+E13-(G13-F13)*C13 -> 0 | J13: =H13+I13 -> 0
I14: =D14+E14-(G14-F14)*C14 -> 0 | J14: =H14+I14 -> 0
A15: 小 计 | C15: -- | D15: =SUM(D12:D14) -> 0 | E15: =SUM(E12:E14) -> 0 | F15: =SUM(F12:F14) -> 0 | G15: =SUM(G12:G14) -> 0 | H15: =SUM(H12:H14) -> 0 | I15: =SUM(I12:I14) -> 0 | J15: =SUM(J12:J14) -> 0
A16: 联营企业 | I16: =D16+E16-(G16-F16)*C16 -> 0 | J16: =H16+I16 -> 0
I17: =D17+E17-(G17-F17)*C17 -> 0 | J17: =H17+I17 -> 0
I18: =D18+E18-(G18-F18)*C18 -> 0 | J18: =H18+I18 -> 0
I19: =D19+E19-(G19-F19)*C19 -> 0 | J19: =H19+I19 -> 0
A20: 小 计 | C20: -- | D20: =SUM(D17:D19) -> 0 | E20: =SUM(E17:E19) -> 0 | F20: =SUM(F17:F19) -> 0 | G20: =SUM(G17:G19) -> 0 | H20: =SUM(H17:H19) -> 0 | I20: =SUM(I17:I19) -> 0 | J20: =SUM(J17:J19) -> 0
A21: 合计 | D21: =D15+D20 -> 0 | E21: =E15+E20 -> 0 | F21: =F15+F20 -> 0 | G21: =G15+G20 -> 0 | H21: =H15+H20 -> 0 | I21: =I15+I20 -> 0 | J21: =J15+J20 -> 0
A22: 三、审计说明：
A25: 四、审计结论
A29: 编制说明：
A30: 1、账面期末余额—长期权益，通常是指长期应收款。
A31: 2、如果按照投资合同和协议约定被审计单位仍需承担额外损失义务的，则未确认投资损失期末数为计提的预计负债数。
A33: 3、概述、（1）程序的测试情况、结果；
A34: （2）拟调整事项及其调整分录、未调整事项及其影响，审计范围受到限制情况及其影响。
A35: 参考说明：
A36: A、 | C36: 未见异常。
A37: B、 | C37: 除以下重大不符事项应当作为调整事项予以调整外，其余未见异常。
A38: C、 | C38: 由于存在以下重大未调整事项（或审计范围受到限制无法获取充分、适当证据），不可确认。

Sheet 减值测试表G7-17
A1: 致同会计师事务所
A2: 减值测试表
A3: =底稿目录!A2 -> 被审计单位： | E3: =底稿目录!A4 -> 编制人： | G3: =底稿目录!A5 -> 编制日期： | H3: 索引号： | I3: =底稿目录!F23 -> G7-17
A4: =底稿目录!A3 -> 截止日：202X年12月31日 | E4: =底稿目录!A6 -> 复核人： | G4: =底稿目录!A7 -> 复核日期： | H4: 页 次：
A5: 一、审计目标： | C5: 长期股权投资减值准备计提充分、准确。
A6: 二、审计过程：
A7: 1.减值迹象
A8: 考虑事项 | F8: 公司1 | G8: 公司2 | H8: 公司3 | I8: 索引号
A9: 资产的市价当期大幅度下跌，其跌幅明显高于因时间的推移或者正常使用而预计的下跌
A10: 企业经营所处的经济、技术或者法律等环境以及资产所处的市场在当期或者将在近期发生重大变化，从而对企业产生不利影响
A11: 市场利率或者其他市场投资报酬率在当期已经提高，从而影响企业计算资产预计未来现金流量现值的折现率，导致资产可收回金额大幅度降低
A12: 有证据表明资产已经陈旧过时或者其实体已经损坏
A13: 资产已经或者将被闲置、终止使用或者计划提前处置
A14: 企业内部报告的证据表明资产的经济绩效已经低于或者将低于预期，如资产所创造的净现金流量或者实现的营业利润（或者亏损）远远低于（或者高于）预计金额等
A15: 其他
A16: 是否存在减值迹象：
A18: 2.利用专家工作
A19: 序号 | B19: 项目 | D19: 索引号
A20: 1 | B20: 了解专家的资质 | D20: B21
A21: 2 | B21: 利用专家的工作 | D21: C25
A22: 3.减值金额测试
A23: 长期股权投资期末账面余额 | B23: 按公允价值计算 | E23: 公允价值确认依据 | F23: 应计提减值金额 | G23: 实际计提减值金额 | H23: 差异 | I23: 说明/索引号
B24: 被投资单位期末净资产公允价值 | C24: 持股比例 | D24: 按持股比例计算的可享有的期末净资产份额
D25: =C25*B25 -> 0 | F25: =IF(A25-D25>0,A25-D25,0) -> 0 | H25: =F25-G25 -> 0
F26: =IF(A26-D26>0,A26-D26,0) -> 0 | H26: =F26-G26 -> 0
D27: =A27*C27 -> 0 | F27: =IF(A27-D27>0,A27-D27,0) -> 0 | H27: =F27-G27 -> 0
A28: 三、审计说明
A31: 四、审计结论

Sheet 凭证检查表G7-18
A1: 致同会计师事务所
A2: 长期股权投资凭证检查表
A3: =底稿目录!A2 -> 被审计单位： | E3: =底稿目录!A4 -> 编制人： | H3: =底稿目录!A5 -> 编制日期： | P3: 索引号： | Q3: =底稿目录!F24 -> G7-18
A4: =底稿目录!A3 -> 截止日：202X年12月31日 | E4: =底稿目录!A6 -> 复核人： | H4: =底稿目录!A7 -> 复核日期： | P4: 页 次：
A5: 一、审计目标
A6: 1.资产负债表中记录的长期股权投资是存在的，且已经记录在恰当的账户中；2.记录的长期股权投资由被审计单位拥有或控制；
A7: 3.长期股权投资以恰当的金额包括在财务报表中，与之相关的计价或分摊调整已恰当记录，相关披露已得到恰当计量和描述
A8: 二、样本选取标准与规模：
A9: 测试范围： | B9: 如借方发生额所有凭证共XX笔金额XX、贷方发生额所有凭证共XX笔金额XX | G9: 特定样本： | H9: XX金额以上（大额）、关联方/关联交易形成的款项、XX异常款项全部测试，共XX笔；
A10: 抽样总体： | B10: 测试总体扣除特定样本以外的样本，共XX笔、金额XX | G10: 确定的抽样样本量： | H10: 抽取XX笔（如果使用了样本计算器计算样本量，样本量计算过程见<XX>底稿）
A11: 抽样方法： | B11: 随机选样/系统选样/货币单元抽样/随意选样（非统计抽样适用） | G11: 抽样过程： | H11: 使用IDEA（XX抽样工具）选择XX数量占比XX%的样本进行测试，抽样工具中的样本选择过程和结果见XX底稿
A12: 三、测试：
A13: 测试内容说明：1.原始凭证内容完整； 2.有授权批准；3.账务处理正确；4.初始成本计算正确；5.权益法计算正确；6.……
A14: 1.本期发生额检查
A15: 记账凭证 | H15: 支持性文件 | I15: 核对内容 | O15: 索引号 | P15: 是否异常 | Q15: 备注说明
A16: 日期 | B16: 凭证编号 | C16: 业务内容 | D16: 对方科目 | E16: 明细科目 | F16: 借方金额 | G16: 贷方金额 | I16: 1 | J16: 2 | K16: 3 | L16: 4 | M16: 5 | N16: 6
H17: 付款审批单、付款凭单、投资协议……
A27: 合计 | F27: =SUM(F17:F26) -> 0 | G27: =SUM(G17:G26) -> 0
A28: 本期发生额 | F28: ='长期股权投资审定表G7-1'!D22 -> 0 | G28: ='长期股权投资审定表G7-1'!E22 -> 0
A29: 检查比例 | F29: =F27/F28 -> #DIV/0! | G29: =G27/G28 -> #DIV/0!
A30: 2.期后处置、新增检查表
C31: 记账凭证 | H31: 支持性文件 | I31: 核对内容 | O31: 索引号 | P31: 是否异常 | Q31: 备注说明
A32: 日期 | B32: 凭证编号 | C32: 业务内容 | D32: 对方科目 | E32: 对方明细科目 | F32: 借方金额 | G32: 贷方金额 | I32: 1 | J32: 2 | K32: 3 | L32: 4 | M32: 5 | N32: 6
A38: 合计 | F38: =SUM(F33:F37) -> 0 | G38: =SUM(G33:G37) -> 0
A39: 三、审计说明
A41: 五、审计结论：
A44: 编制说明：
A45: 1、概述：（1）程序的测试情况、结果；
A46: （2）拟调整事项及其调整分录、未调整事项及其影响，审计范围受到限制情况及其影响。
A47: 参考结论：
A48: A、 | B48: 未见异常。
A49: B、 | B49: 除以下重大不符事项应当作为调整事项予以调整外，其余未见异常。
A50: C、 | B50: 由于存在以下重大未调整事项（或审计范围受到限制无法获取充分、适当证据），不可确认。
A52: 2、选取测试项目的方法：包括选取全部项目、选取特定项目和审计抽样。
A53: （1） | B53: 当存在下列情形之一时，注册会计师应当考虑选取全部项目进行测试：
B54: （一）总体由少量的大额项目构成；
B55: （二）存在特别风险且其他方法未提供充分、适当的审计证据；
B56: （三）由于信息系统自动执行的计算或其他程序具有重复性，对全部项目进行检查符合成本效益原则。
B58: 特别风险涉及的事项包括但不限于：
B59: （1）舞弊风险（如1141准则的示例）；（2）重大非常规交易（如企业购并、债务重组、非货币性资产交换、
B60: 重大或有事项、持续经营、违反法律法规等）；(3)重大关联交易；(4)重大判断事项（如重大会计估计、
B61: 会计政策及其变更）；(5)重大复杂交易；(6)仅通过实质性程序无法应对的重大错报风险（如日常交易采用
B62: 高度自动化处理）等等。
A64: （2） | B64: 选取的特定项目可能包括：
B65: （一）大额或关键项目；
B66: （二）超过某一金额的全部项目；
B67: （三）被用于获取某些信息的项目；
B68: （四）被用于测试控制活动的项目。
B69: 根据判断选取特定项目，容易产生非抽样风险。
B70: 选取特定项目实施检查，通常是获取审计证据的有效手段，但并不构成审计抽样。
B72: 非抽样风险是指由于某些与样本规模无关的因素而导致注册会计师得出错误结论的可能性。
B73: 注册会计师采用不适当的审计程序，或者误解审计证据而没有发现误差等，均可能导致非抽样风险。
B74: 在实施控制测试时，误差是指控制偏差；在实施细节测试时，误差是指错报。
A76: （3） | B76: 审计抽样，是指注册会计师对某类交易或账户余额中低于百分之百的项目实施审计程序，使所有抽样单元都有被选取的机会。
B77: 统计抽样是指同时具备下列特征的抽样方法：
B78: （一）随机选取样本；
B79: （二）运用概率论评价样本结果，包括计量抽样风险。
B80: 不同时具备上述两个特征的抽样方法为非统计抽样。
B82: 在实施细节测试时，特别是测试高估时，将构成某类交易或账户余额的每一货币单位（如人民币元）作为抽样单元，通常效率很高。
B83: 即在测试存在性时，选择大额项目的效率较高。
B85: 分层是指将一个总体划分为多个子总体的过程，每个子总体由一组具有相同特征（通常为货币金额）的抽样单元组成。
B86: 当实施细节测试时，注册会计师通常按照货币金额对某类交易或账户余额进行分层，以将更多的审计资源投入到大额项目中。
B88: 在统计抽样中，注册会计师应当随机选取样本项目，以使每一抽样单元以已知的机会被选中。
B89: 在非统计抽样中，注册会计师应当运用职业判断选取样本项目。
B91: 注册会计师可以使用统计学公式或运用职业判断，确定样本规模。
B92: 参考：样本规模=账面价值×风险系数/（可容忍错报-（预计错报×扩展系数））
... B95: 预计错报的扩展系数
B96: 误受风险（%） | C96: 扩展系数
B97: 1 | C97: 1.9
B98: 5 | C98: 1.6
B99: 10 | C99: 1.5
