Workbook

Sheet 底稿目录
A1: 底稿开列时，可先在以下单元格填写有关内容，以便其他底稿引用有关数据：
A2: 被审计单位：
A3: 截止日：202X年12月31日 | D3: 序号 | E3: 内容 | F3: 索引号
A4: 编制人： | D4: 1 | E4: 应付票据实质性程序表 | F4: F3A
A5: 编制日期： | D5: 2 | E5: 审定表 | F5: F3-1
A6: 复核人： | D6: 3 | E6: 附注披露信息(上市公司) | G6: 无需打印
A7: 复核日期： | D7: 4 | E7: 附注披露信息(国企) | G7: 无需打印
D8: 5 | E8: 明细表 | F8: F3-2
A9: 关于工作底稿与审计程序索引号对应的说明 | D9: 6 | E9: 调整分录汇总 | F9: F3-3
A10: 1.编制的审计工作底稿应与审计程序对应。审计项目组应根据被审计单位实际情况和风险评估情况在实质性程序表中裁剪、修改或增加审计程序，根据实际执行的审计程序完成相应审计工作底稿，编制的工作底稿中应按自然顺序依次编制索引号，并通过唯一的索引号将与实质性程序表中的程序对应关联（即将工作底稿的索引号填入实质性程序表中的底稿索引号列）。 | D10: 7 | E10: 函证结果汇总表 | F10: F0-1/E0-1
D11: 8 | E11: 核实被函证单位信息 | F11: F0-2/E0-2
D12: 9 | E12: 应付银行承兑汇票发函记录表 | F12: E0-5
D13: 10 | E13: 跟函函证过程控制 | F13: F0-3/E0-7
A14: 2.获取的支持性证据应与审计底稿或程序对应。审计项目组在完成底稿时获取的支持性证据应根据底稿索引号编制下一级按自然顺序排序的索引号（如D1-2-1、D1-2-2、……），并在底稿中说明引用的支持性证据、关联索引号。 | D14: 11 | E14: 函证差异调节表 | F14: F0-4
D15: 12 | E15: 预付及采购替代程序检查表 | F15: F0-5
D16: 13 | E16: 邮件传真回函可靠性验证 | F16: F0-7
A17: 3.工作底稿索引号的编码规则：实质性程序索引号按循环从“D”到“N”,循环内账户以顺序号排列，模板中底稿索引号按账户顺序+自然数顺序（即模板中索引号按二级自然顺序排列，如D1-1、D1-2、D1-3、……D1-N）。 | D17: 14 | E17: 函证程序舞弊风险评价表 | F17: F0-8/E0-8
D18: 15 | E18: 应付票据（带息）利息测算表 | F18: F3-4
D19: 16 | E19: 逾期票据检查表 | F19: F3-5
D20: 17 | E20: 关联方及交易检查表 | F20: F3-6
D21: 18 | E21: 应付票据检查表 | F21: F3-7

Sheet 应付票据实质性程序表F3A 
A1: 致同会计师事务所
A2: 应付票据实质性程序
A3: =底稿目录!A2 -> 被审计单位： | C3: =底稿目录!A4 -> 编制人： | E3: =底稿目录!A5 -> 编制日期： | H3: 索引号： | I3: F3A
A4: =底稿目录!A3 -> 截止日：202X年12月31日 | C4: =底稿目录!A6 -> 复核人： | E4: =底稿目录!A7 -> 复核日期： | H4: 页 次：
A5: 一、本账户涉及的科目
A6: 应付票据
A7: 二、审计目标与认定的对应关系
A8: 审计目标 | G8: 财务报表的认定
A9: A. 资产负债表中记录的应付票据是存在的，且已经记录在恰当的账户中 | G9: 存在
A10: B. 所有应记录的应付票据均已记录，所有应当包括在财务报表中的相关披露均已包括 | G10: 完整性
A11: C. 记录的应付票据由被审计单位拥有或控制 | G11: 权利和义务
A12: D. 应付票据以恰当的金额包括在财务报表中，与之相关的计价或分摊调整已恰当记录，相关披露已得到恰当计量和描述 | G12: 准确性、计价和分摊
A13: E. 应付票据已被恰当地汇总或分解且表述清楚，相关披露在按照企业会计准则的编制基础下是相关的、可理解的 | G13: 列报
A14: 三、计划实施的实质性程序
A15: 序号 | B15: 审计程序 | C15: 程序分类 | D15: 财务报表的认定 | I15: 底稿索引号
D16: 存在 | E16: 完整性 | F16: 权利和 义务 | G16: 准确性、计价和分摊 | H16: 列报 | K16: 根据被审计单位实际情况和风险评估情况裁剪、修改或增加审计程序
A17: 1 | B17: 获取或编制应付票据的明细表，完成以下工作，并编制审定表 （1）复核加计是否正确，与总账、明细账合计数核对是否相符，期初余额与上期审定期末余额是否相符； （2）检查借方余额是否需要重分类、非记账本位币应付票据折算是否正确。 | C17: 常规★ | D17: √ | E17: √ | G17: √ | I17: F3-1 /F3-2
A18: 2 | B18: 将应付票据明细表与应付票据备查簿的相关内容核对相符： （1）核对商业汇票的种类、号数和出票日期、到期日、票面金额、票面利率、已计提的利息等，复核其应存人银行的承兑保证金，并与其他货币资金科目勾稽； （2）检查发票和收货单等原始资料，核实交易、事项交易真实性； | C18: 常规★ | D18: √ | E18: √ | G18: √ | I18: F3-2 /F3-4 /F3-7
A19: 3 | B19: 在使用手工编制、自定义信息报告、系统生成的非固定格式报告等由被审计单位生成的信息时，测试有关信息准确性和完整性，并考虑针对编制和维护由被审计单位生成的信息的相关控制实施控制测试，以评价该信息是否能够为实现审计目的提供基础。 | C19: 常规★ | E19: √ | G19: √ | I19: T1 /F0-1 / | K19: 可参见《审计手册》4.2.6，由被审计单位生成的信息可能是由系统生成的、或手工编制的、或二者兼而有之的方式生成的。例如，由被审计单位生成的信息可能包括： • 不涉及自定义的、由系统生成的报告（如，固定格式报告）； • 可能通过人工自定义的、由系统生成的报告，例如，（计算机）查询信息或特别定制的报告； • 手工编制的信息，例如，汇总信息的电子表格或用以支持分配、计算以及调节的电子表格； • 其他系统生成或手工编制的信息，例如，由被审计单位编制的客户发票； • 通过影印、拍摄、扫描或其他方式转换成电子形式的文件记录。
A20: 4 | B20: 对期初余额的审计，取得应付票据期初余额明细表复核加计是否正确，与总账、明细账合计数是否相符，检查上期应付票据在本期到期付款情况，函证期初余额以及其他必要追加的审计程序。（适用于首次承接） | C20: 备选 | D20: √ | E20: √ | F20: √ | G20: √ | K20: 由被审计单位生成的信息不包括： • 总分类账或明细分类账、试算平衡表、或经审计的财务报表； • 第三方（除了服务机构）的报表或报告，例如，原始银行对账单，或函证的回函； • 外部数据（例如，第三方发布的数据，如，定价来源）。
A21: 5 | B21: 关注会计政策、会计估计合理性、一贯性，关注其是否利用会计政策和会计估计及其变更操纵利润。 | C21: 常规★ | D21: √ | E21: √ | G21: √ | I21: F3-1 /F3-2 | K21: 应付票据中的由被审计单位生成的信息例如：应付票据备查簿、采购合同台账、被函证方信息等
A22: 6 | B22: 获取并阅读被审计单位的企业信用报告（贷款卡），检查其中与应付票据有关的信息是否一致，如果不一致应查明原因并编制差额调节表。 | C22: 常规★ | D22: √ | E22: √ | F22: √ | G22: √ | I22: E1-15
A23: 7 | B23: 对逾期未兑付的票据查明原因，检查相关会计处理是否正确，是否符合适用的财务报告编制基础。 | C23: 常规★ | D23: √ | I23: F3-5
A24: 8 | B24: 实施函证程序： （1）以积极方式对应付票据进行函证，设计询证函、发函前核实被函证单位信息； （2）注册会计师独立收发询证函； （3）编制函证结果汇总表，检查发函、回函物流信息和轨迹、比对回函印章和签字等以核实回函的真实性，检查回函是否相符，对不符事项查明原因确定是否存在错报； （4）如果未收到回函，应当考虑与被询证者联系，要求对方作出回应或再次寄发询证函，无法收到的回函实施替代程序； （5）如果管理层不允许寄发询证函的，询问管理层不允许寄发的原因，并就其原因的正当、合理性收集证据；考虑实施替代审计程序以获取相关、可靠的审计证据； （6）如果管理层不允许寄发询证函的原因不合理、或者认为回函不可靠，评价对评估的重大错报风险以及其他审计程序的性质、时间安排和范围的影响，并确定其对审计工作和审计意见的影响。 | C24: 常规★ | D24: √ | E24: √ | F24: √ | G24: √ | I24: F0
A25: 9 | B25: 针对舞弊风险较大的供应商，考虑对采购额、合同条款、是否存在关联方关系及是否存在补充协议等实施函证程序。 | C25: IPO/上市/新三板/重组/舞弊应对 | D25: √ | E25: √ | F25: √ | G25: √ | I25: F0
A26: 10 | B26: 检查应付关联方款项： （1）了解交易的商业理由、交易事项的目的、价格和条件，考虑对关联方应付票据的合理性、合法性； （2）检查对关联方应付票据的真实性相关的支持性文件、检查会计处理是否正确； （3）考虑向关联方或其他注册会计师函证重大的关联采购交易和余额（包括担保和其他重要信息）； （4）必要时，向与交易相关的人员和机构（如银行、律师）函证或与其讨论有关信息； （5）考虑是否存在未识别的关联方，关联交易和余额披露是否正确。 | C26: 常规★ | D26: √ | E26: √ | F26: √ | G26: √ | H26: √ | I26: F3-6 /F3-7 /F0
A27: 11 | B27: 检查与应付票据有关的的记账凭证和相应的支持性证据以确定交易的真实性，是否按规定进行相应的会计处理和披露。 | C27: 常规★ | D27: √ | F27: √ | G27: √ | I27: F3-7
A28: 12 | B28: 结合票据的函证程序、分析程序及其他检查程序，重点关注票据的真实性及交易的合理性，特别关注票据流转与合同约定、实物流转等是否匹配，以及票据流转的前后手情况。通过网上查验、现场验证等方式，对异常的票据进行重点核查。 | C28: IPO/上市/新三板/重组/舞弊应对 | D28: √ | F28: √
A29: 13 | B29: 根据评估的舞弊风险等因素增加的审计程序。 | C29: IPO/上市/新三板/重组/舞弊应对
A30: 14 | B30: 检查应付票据是否已按企业会计准则或其他适用的规定在财务报表中做出恰当列报和披露。 | C30: 常规★ | H30: √ | I30: A1-1/A1-15 /A1-16

Sheet 审定表F3-1
A1: 致同会计师事务所
A2: 应付票据审定表
A3: =底稿目录!A2 -> 被审计单位： | C3: =底稿目录!A4 -> 编制人： | E3: =底稿目录!A5 -> 编制日期： | I3: 索引号： | J3: =底稿目录!F5 -> F3-1
A4: =底稿目录!A3 -> 截止日：202X年12月31日 | C4: =底稿目录!A6 -> 复核人： | E4: =底稿目录!A7 -> 复核日期： | I4: 页 次：
A5: 项目 | B5: 期初数 | F5: 期末数
B6: 未审数 | C6: 账项调整 | D6: 重分类调整 | E6: 审定数 | F6: 未审数 | G6: 账项调整 | H6: 重分类调整 | I6: 审定数 | J6: 索引
A7: 银行承兑汇票 | B7: =SUMPRODUCT(('明细表F3-2'!$B$15:$B$30=$A7)*('明细表F3-2'!L$15:L$30)) -> 0 | E7: =B7+C7+D7 -> 0 | F7: =SUMPRODUCT(('明细表F3-2'!$B$15:$B$30=$A7)*('明细表F3-2'!O$15:O$30)) -> 0 | G7: =SUMPRODUCT(('明细表F3-2'!$B$15:$B$30=$A7)*('明细表F3-2'!P$15:P$30)) -> 0 | H7: =SUMPRODUCT(('明细表F3-2'!$B$15:$B$30=$A7)*('明细表F3-2'!Q$15:Q$30)) -> 0 | I7: =SUMPRODUCT(('明细表F3-2'!$B$15:$B$30=$A7)*('明细表F3-2'!R$15:R$30)) -> 0 | J7: 111
A8: 商业承兑汇票 | B8: =SUMPRODUCT(('明细表F3-2'!$B$15:$B$30=$A8)*('明细表F3-2'!L$15:L$30)) -> 0 | E8: =B8+C8+D8 -> 0 | F8: =SUMPRODUCT(('明细表F3-2'!$B$15:$B$30=$A8)*('明细表F3-2'!O$15:O$30)) -> 0 | G8: =SUMPRODUCT(('明细表F3-2'!$B$15:$B$30=$A8)*('明细表F3-2'!P$15:P$30)) -> 0 | H8: =SUMPRODUCT(('明细表F3-2'!$B$15:$B$30=$A8)*('明细表F3-2'!Q$15:Q$30)) -> 0 | I8: =SUMPRODUCT(('明细表F3-2'!$B$15:$B$30=$A8)*('明细表F3-2'!R$15:R$30)) -> 0
E9: =B9+C9+D9 -> 0 | I9: =F9+G9+H9 -> 0
E10: =B10+C10+D10 -> 0 | I10: =F10+G10+H10 -> 0
A11: 合计 | B11: =SUM(B7:B10) -> 0 | C11: =SUM(C7:C10) -> 0 | D11: =SUM(D7:D10) -> 0 | E11: =SUM(E7:E10) -> 0 | F11: =SUM(F7:F10) -> 0 | G11: =SUM(G7:G10) -> 0 | H11: =SUM(H7:H10) -> 0 | I11: =SUM(I7:I10) -> 0
A12: 试算平衡表数
A13: 差异数 | E13: =E11-E12 -> 0 | I13: =I11-I12 -> 0
A14: 1、审计说明
A15: （1）应付票据期末余额较期初余额增加（负数为减少）： | D15: =IF(E7=0,0,(I7-E7)/E7) -> 0
A16: 主要原因（比例超过30%的）：
A19: （2）逾期应付票据调整情况说明。
A23: 2、审计结论
A26: 提示：
A27: 逾期的银行承兑汇票转入短期借款；逾期的商业承兑汇票转入应付账款。

Sheet 附注披露信息(上市公司)
A1: 致同会计师事务所
A2: 应付票据附注披露信息（上市公司）
A3: =底稿目录!A2 -> 被审计单位： | B3: =底稿目录!A4 -> 编制人： | D3: =底稿目录!A5 -> 编制日期： | E3: 索引号：
A4: =底稿目录!A3 -> 截止日：202X年12月31日 | B4: =底稿目录!A6 -> 复核人： | D4: =底稿目录!A7 -> 复核日期： | E4: 页次：
A5: 应付票据
A6: 种类 | B6: 期末余额 | C6: 上年年末余额
A7: 银行承兑汇票 | B7: ='审定表F3-1'!I7 -> 0 | C7: ='审定表F3-1'!E7 -> 0
A8: 商业承兑汇票 | B8: ='审定表F3-1'!I8 -> 0 | C8: ='审定表F3-1'!E8 -> 0
A9: 合计 | B9: =SUM(B7:B8) -> 0 | C9: =SUM(C7:C8) -> 0
A10: 说明：本期末已到期未支付的应付票据总额为XXX元。
A11: 【如果法律上认定供应链票据属于《商业汇票承兑、贴现与再贴现管理办法》（中国人民银行中国银行保险监督管理委员会令〔2022〕第4号）的范围、具备《票据法》规定的要件，则出票人应当自法律认定生效日（2023年1月1日）起将其作为“应付票据”进行会计处理，且无需对前期比较期间数据进行追溯调整。】

Sheet 附注披露信息(国企)
A1: 致同会计师事务所
A2: 应付票据附注披露信息（国企）
A3: =底稿目录!A2 -> 被审计单位： | B3: =底稿目录!A4 -> 编制人： | C3: =底稿目录!A5 -> 编制日期： | E3: 索引号：
A4: =底稿目录!A3 -> 截止日：202X年12月31日 | B4: =底稿目录!A6 -> 复核人： | C4: =底稿目录!A7 -> 复核日期： | E4: 页次：
A5: 应付票据
A6: 类别 | B6: 期末余额 | C6: 期初余额
A7: 银行承兑汇票 | B7: ='审定表F3-1'!I7 -> 0 | C7: ='审定表F3-1'!E7 -> 0
A8: 商业承兑汇票 | B8: ='审定表F3-1'!I8 -> 0 | C8: ='审定表F3-1'!E8 -> 0
A9: 合计 | B9: =SUM(B7:B8) -> 0 | C9: =SUM(C7:C8) -> 0
A10: 注：企业应说明本期已到期未支付的应付票据总金额。

Sheet 明细表F3-2
A1: 致同会计师事务所
A2: 期末应付票据明细表
A3: =底稿目录!A2 -> 被审计单位： | F3: =底稿目录!A4 -> 编制人： | O3: =底稿目录!A5 -> 编制日期： | V3: 索引号： | W3: =底稿目录!F8 -> F3-2
A4: =底稿目录!A3 -> 截止日：202X年12月31日 | F4: =底稿目录!A6 -> 复核人： | O4: =底稿目录!A7 -> 复核日期： | V4: 页 次：
A5: 一、审计目标：
A6: 1.资产负债表中记录的应付票据是存在的，且已经记录在恰当的账户中；2.所有应记录的应付票据均已记录，所有应当包括在财务报表中的相关披露均已包括；
A7: 3.应付票据以恰当的金额包括在财务报表中，与之相关的计价或分摊调整已恰当记录，相关披露已得到恰当计量和描述
A8: 二、审计过程：
A9: 1.核对应付票据明细表与应付票据备查簿的相关内容，包括商业汇票的种类、号数和出票日期、到期日、票面金额、票面利率、已计提的利息等，复核其应存人银行的承兑保证金，并与其他货币资金科目勾稽；
A10: 2.获取并阅读被审计单位的企业信用报告（贷款卡），检查其中与应付票据有关的信息是否一致；
A11: 3.对逾期未兑付的票据，了解原因，检查相关会计处理是否正确；询问管理层，审查有关文件并结合购货截止测试，检查应付票据的完整性。
A12: 4.关注票据的真实性及交易的合理性，特别关注票据流转与合同约定、实物流转等是否匹配，以及票据流转的前后手情况。通过网上查验、现场验证等方式，对异常的票据进行重点核查。
A13: 票据号 | B13: 票据类别 | C13: 关联方类型 | D13: 票据关系人 | G13: 票据期限 | J13: 票面利率 | K13: 是否承兑 | L13: 期初余额 | M13: 本期开票 | N13: 本期承兑 | O13: 期末未审数 | P13: 账项调整 | Q13: 重分类调整 | R13: 期末审定数 | S13: 已计利息 | T13: 是否函证 | U13: 票据保证金比例 | V13: 保证金金额 | W13: 备注
D14: 出票人 | E14: 承兑人 | F14: 收款人 | G14: 出票日 | H14: 到期日 | I14: 期限
O15: =L15+M15-N15 -> 0 | R15: =O15+P15+Q15 -> 0
O16: =L16+M16-N16 -> 0 | R16: =O16+P16+Q16 -> 0
O17: =L17+M17-N17 -> 0 | R17: =O17+P17+Q17 -> 0
O18: =L18+M18-N18 -> 0 | R18: =O18+P18+Q18 -> 0
O19: =L19+M19-N19 -> 0 | R19: =O19+P19+Q19 -> 0
O20: =L20+M20-N20 -> 0 | R20: =O20+P20+Q20 -> 0
O21: =L21+M21-N21 -> 0 | R21: =O21+P21+Q21 -> 0
O22: =L22+M22-N22 -> 0 | R22: =O22+P22+Q22 -> 0
O23: =L23+M23-N23 -> 0 | R23: =O23+P23+Q23 -> 0
O24: =L24+M24-N24 -> 0 | R24: =O24+P24+Q24 -> 0
O25: =L25+M25-N25 -> 0 | R25: =O25+P25+Q25 -> 0
O26: =L26+M26-N26 -> 0 | R26: =O26+P26+Q26 -> 0
... O30: =L30+M30-N30 -> 0 | R30: =O30+P30+Q30 -> 0
A31: 合 计 | L31: =SUM(L15:L30) -> 0 | M31: =SUM(M15:M30) -> 0 | N31: =SUM(N15:N30) -> 0 | O31: =SUM(O15:O30) -> 0 | P31: =SUM(P15:P30) -> 0 | Q31: =SUM(Q15:Q30) -> 0 | R31: =SUM(R15:R30) -> 0 | S31: =SUM(S15:S30) -> 0 | V31: =SUM(V15:V30) -> 0
A32: 三、审计说明：
A33: 1.银行承兑汇票保证金与其他货币资金保证金核对……
A36: 四、审计结论：
A40: 编制说明：
A41: 1.票据类别应按商业承兑汇票、银行承兑汇票分别列示。
A42: 2.与收款人是否存在关联关系，在“备注”栏中说明。
A43: 4.审计说明可以概述：（1）程序的测试情况、结果；（2）拟调整事项及其调整分录、未调整事项及其影响，审计范围受到限制情况及其影响。
A44: 5.审计结论可参考：A、未见异常。 B、除上述重大不符事项应当作为调整事项予以调整外，其余未见异常。 C、由于存在以下重大未调整事项（或审计范围受到限制无法获取充分、适当证据），不可确认。

Sheet 调整分录汇总F3-3
A1: 致同会计师事务所
A2: 应付票据调整分录汇总表
A3: =底稿目录!A2 -> 被审计单位： | D3: =底稿目录!A4 -> 编制人： | G3: =底稿目录!A5 -> 编制日期： | I3: 索引号： | J3: =底稿目录!F9 -> F3-3
A4: =底稿目录!A3 -> 截止日：202X年12月31日 | D4: =底稿目录!A6 -> 复核人： | G4: =底稿目录!A7 -> 复核日期： | I4: 页 次：
A5: 调整事项说明 | B5: 类别（报表调整/账项调整/其他） | C5: 报表项目 | D5: 科目名称 | E5: 附注项目 | F5: …… | G5: 借方调整金额 | H5: 贷方调整金额 | I5: 索引 | J5: 备注
A22: 【注：本底稿适用于调整分录较多、较复杂的项目，且仅列示与本报表项目相关的审计调整。项目组可根据项目实际情况选择是否使用该底稿。】

Sheet 应付票据（带息）利息测算表F3-4
A1: 致同会计师事务所
A2: 应付票据（带息）利息测算表
A3: =底稿目录!A2 -> 被审计单位： | D3: =底稿目录!A4 -> 编制人： | G3: =底稿目录!A5 -> 编制日期： | J3: 索引号： | K3: =底稿目录!F18 -> F3-4
A4: =底稿目录!A3 -> 截止日：202X年12月31日 | D4: =底稿目录!A6 -> 复核人： | G4: =底稿目录!A7 -> 复核日期： | J4: 页 次：
A5: 一、审计目标：
A6: 应付票据以恰当的金额包括在财务报表中，与之相关的计价或分摊调整已恰当记录，相关披露已得到恰当计量和描述
A7: 二、审计过程：
A8: 复核带息应付票据利息是否足额计提，其会计处理是否正确。
A9: 票据类别 | B9: 票据号 | C9: 票据期限 | F9: 票面金额 | G9: 票面利率 | H9: 应计利息 | I9: 账面已计利息 | J9: 差异 | K9: 说明
C10: 出票日 | D10: 到期日 | E10: 期限
H11: =ROUND(F11*G11,2) -> 0 | J11: =H11-I11 -> 0
H12: =ROUND(F12*G12,2) -> 0 | J12: =H12-I12 -> 0
H13: =ROUND(F13*G13,2) -> 0 | J13: =H13-I13 -> 0
H14: =ROUND(F14*G14,2) -> 0 | J14: =H14-I14 -> 0
H15: =ROUND(F15*G15,2) -> 0 | J15: =H15-I15 -> 0
H16: =ROUND(F16*G16,2) -> 0 | J16: =H16-I16 -> 0
H17: =ROUND(F17*G17,2) -> 0 | J17: =H17-I17 -> 0
H18: =ROUND(F18*G18,2) -> 0 | J18: =H18-I18 -> 0
H19: =ROUND(F19*G19,2) -> 0 | J19: =H19-I19 -> 0
H20: =ROUND(F20*G20,2) -> 0 | J20: =H20-I20 -> 0
H21: =ROUND(F21*G21,2) -> 0 | J21: =H21-I21 -> 0
H22: =ROUND(F22*G22,2) -> 0 | J22: =H22-I22 -> 0
... H31: =ROUND(F31*G31,2) -> 0 | J31: =H31-I31 -> 0
A32: 合 计 | F32: =SUM(F11:F31) -> 0 | H32: =SUM(H11:H31) -> 0 | I32: =SUM(I11:I31) -> 0 | J32: =SUM(J11:J31) -> 0
A33: 三、审计说明：
A36: 四、审计结论：

Sheet 逾期票据检查F3-5
A1: 致同会计师事务所
A2: 逾期未付票据检查表
A3: =底稿目录!A2 -> 被审计单位： | E3: =底稿目录!A4 -> 编制人： | I3: =底稿目录!A5 -> 编制日期： | N3: 索引号： | O3: =底稿目录!F19 -> F3-5
A4: =底稿目录!A3 -> 截止日：202X年12月31日 | E4: =底稿目录!A6 -> 复核人： | I4: =底稿目录!A7 -> 复核日期： | N4: 页 次：
A5: 票据类别 | B5: 票据号 | C5: 票据关系人 | F5: 票据期限 | I5: 票面利率 | J5: 票面金额 | K5: 期后支付金额 | L5: 借款条件 | M5: 是否调整 | N5: 抵押情况
C6: 出票人 | D6: 承兑人 | E6: 收款人 | F6: 出票日 | G6: 到期日 | H6: 期限 | N6: 物品名称 | O6: 金额
A22: 合计 | J22: =SUM(J7:J21) -> 0 | K22: =SUM(K7:K21) -> 0 | O22: =SUM(O7:O21) -> 0
A23: 1、审计说明：
A24: 逾期票据是否引发了诉讼事项？如确引发了诉讼事项，取得相关诉状
A25: 分析逾期未付票据对公司持续经营的影响程度
A27: 2、审计结论：

Sheet 关联方及交易检查表F3-6
A1: 致同会计师事务所
A2: 应付票据关联方及交易检查表
A3: =底稿目录!A2 -> 被审计单位： | C3: =底稿目录!A4 -> 编制人： | G3: =底稿目录!A5 -> 编制日期： | L3: 索引号： | M3: =底稿目录!F20 -> F3-6
A4: =底稿目录!A3 -> 截止日：202X年12月31日 | C4: =底稿目录!A6 -> 复核人： | G4: =底稿目录!A7 -> 复核日期： | L4: 页 次：
A5: 关注对关联方应付票据的真实性、合理性、合法性、会计处理是否正确，考虑是否存在未识别的关联方，检查关联交易和余额披露是否正确。
A6: 关联方名称 | B6: 关联关系 | C6: 票据类别 | D6: 期初余额 | E6: 借方发生 | F6: 贷方发生 | G6: 期末余额 | H6: 账龄 | I6: 定价政策 | J6: 发生原因（款项性质） | K6: 期后付款金额 | L6: 索引号 | M6: 备注
G7: =D7+F7-E7 -> 0
G8: =D8+F8-E8 -> 0
G9: =D9+F9-E9 -> 0
G10: =D10+F10-E10 -> 0
G11: =D11+F11-E11 -> 0
G12: =D12+F12-E12 -> 0
A13: 合计 | D13: =SUM(D7:D12) -> 0 | E13: =SUM(E7:E12) -> 0 | F13: =SUM(F7:F12) -> 0 | G13: =SUM(G7:G12) -> 0 | K13: =SUM(K7:K12) -> 0
A14: 1、审计说明：
A16: 2、审计结论：
B18: 勿改、勿删
B19: 实际控制人
B20: 控股股东
B21: 控股股东、实际控制人的附属企业
B22: 持有5%以上股份的法人或其他组织
B23: 联营企业
B24: 合营企业
B25: 董高监等关键管理人员
B26: 其他关联方

Sheet 应付票据检查表F3-7
A1: 致同会计师事务所
A2: 应付票据检查表
A3: =底稿目录!A2 -> 被审计单位： | H3: =底稿目录!A4 -> 编制人： | L3: =底稿目录!A5 -> 编制日期： | P3: 索引号： | Q3: =底稿目录!F21 -> F3-7
A4: =底稿目录!A3 -> 截止日：202X年12月31日 | H4: =底稿目录!A6 -> 复核人： | L4: =底稿目录!A7 -> 复核日期： | P4: 页次：
A5: 一、审计目标：
A6: 1.产负债表中记录的应付票据是存在的，且已经记录在恰当的账户中；2.记录的应付票据由被审计单位拥有或控制；
A7: 3.应付票据以恰当的金额包括在财务报表中，与之相关的计价或分摊调整已恰当记录，相关披露已得到恰当计量和描述
A8: 二、样本选取标准与规模：
A9: 测试总体： | B9: 如应付票据借方发生额所有凭证共XX笔金额XX、贷方发生额所有凭证共XX笔金额XX | I9: 特定样本： | J9: XX金额以上（大额）、关联方/关联交易形成的款项、XX异常款项全部测试，共XX笔；
A10: 抽样总体： | B10: 测试范围扣除特定样本以外的样本，共XX笔、金额XX | I10: 确定的抽样样本量： | K10: 抽取XX笔 | L10: （如果使用了样本计算器计算样本量，样本量计算过程见<XX>底稿）
A11: 抽样方法： | B11: 随机选样/系统选样/货币单元抽样/随意选样（非统计抽样适用） | I11: 抽样过程： | J11: 使用IDEA（XX抽样工具）选择XX数量、金额XX的样本进行测试，抽样工具中的样本选择过程和结果见<XX>底稿
A12: 三、测试：
A13: 测试内容说明：1.原始凭证是否齐全； 2.记账凭证与原始凭证是否相符；3.账务处理是否正确；4.是否记录于恰当的会计期间；5.……
A14: 1.本期借方金额检查
A15: 记账凭证 | G15: 票据类别 | H15: 付款审批单 | J15: 银行回单 | M15: …… | N15: 索引号 | O15: 是否异常
A16: 日期 | B16: 凭证编号 | C16: 业务内容 | D16: 对方科目 | E16: 明细科目 | F16: 借方金额 | H16: 日期/编号 | I16: 是否经过恰当审批 | J16: 日期 | K16: 收款方 | L16: 金额 | R16: 检查的关键证据和要素根据被审计单位具体情况修改
A37: 合计 | F37: =SUM(F17:F36) -> 0 | L37: =SUM(L17:L36) -> 0
A38: 2.贷方金额检查
A39: 记账凭证 | G39: 票据类别 | H39: 入库单/验收单 | L39: 采购发票 | O39: …… | P39: 索引号 | Q39: 是否异常
A40: 日期 | B40: 凭证编号 | C40: 业务内容 | D40: 对方科目 | E40: 明细科目 | F40: 贷方金额 | H40: 日期/编号 | I40: 品名 | J40: 单位 | K40: 数量 | L40: 日期/编号 | M40: 对手方名称 | N40: 金额 | R40: 检查的关键证据和要素根据被审计单位具体情况修改
A59: 合计 | F59: =SUM(F41:F58) -> 0 | N59: =SUM(N41:N58) -> 0
A60: 3.资产负债表日后借方检查 | R60: 关注资产负债表日后已偿付的应付票据，检查有无应计而未计人当期的应付票据
A61: 记账凭证 | G61: 票据类别 | H61: 付款审批单 | J61: 银行回单 | M61: …… | N61: 索引号 | O61: 是否异常
A62: 日期 | B62: 凭证编号 | C62: 业务内容 | D62: 对方科目 | E62: 明细科目 | F62: 借方金额 | H62: 日期/编号 | I62: 是否经过恰当审批 | J62: 日期 | K62: 收款方 | L62: 金额 | R62: 检查的关键证据和要素根据被审计单位具体情况修改
A80: 合计 | F80: =SUM(F63:F79) -> 0 | L80: =SUM(L63:L79) -> 0
A81: 四、审计说明：
A82: 1.本期发生额、期末余额检查比例： | D82: 方向 | E82: 账面金额 | F82: 检查金额 | G82: 检查比例 | H82: 如果检查比例较低应扩大检查样本量或说明原因
D83: 本期借方 | E83: ='明细表F3-2'!N31 -> 0 | F83: =F37 -> 0 | G83: =ROUND(F83/E83,4) -> #DIV/0!
D84: 本期贷方 | E84: ='明细表F3-2'!M31 -> 0 | F84: =F59 -> 0 | G84: =ROUND(F84/E84,2) -> #DIV/0!
D85: 期末余额 | E85: ='明细表F3-2'!R31 -> 0 | F85: =F80 -> 0 | G85: =ROUND(F85/E85,2) -> #DIV/0!
A86: 2.……
A88: 五、审计结论：

Sheet GT_Custom
A1: C1 | B1: Custom 1
A2: C2 | B2: Custom 2
A3: C3 | B3: Custom 3
A4: C4 | B4: Custom 4
A5: C5 | B5: Custom 5
A6: C6 | B6: Custom 6
A7: C7 | B7: Custom 7
A8: C8 | B8: Custom 8
