Workbook
Name _Toc12834: '首发业务解答二-删除'!$A$2
Name _Toc2639: '首发业务解答二-删除'!$A$3
Name bs: {#N/A,#N/A,FALSE,"BBPREP"}
Name bs_1: {#N/A,#N/A,FALSE,"BBPREP"}
Name L: {#N/A,#N/A,FALSE,"BBPREP"}
Name s: {#N/A,#N/A,FALSE,"BBPREP"}
Name t: {#N/A,#N/A,FALSE,"BBPREP"}
Name XREF_COLUMN_1: #REF!
Name XREF_COLUMN_2: #REF!
Name XREF_COLUMN_3: #REF!
Name XREF_COLUMN_5: #REF!
Name XRefActiveRow: #REF!
Name XRefCopy1: #REF!
Name XRefCopy1Row: #REF!
Name XRefCopy2Row: #REF!
Name XRefPaste1: #REF!
Name XRefPaste1Row: #REF!
Name XRefPaste2: #REF!
Name XRefPaste2Row: #REF!
Name XRefPaste3: #REF!
Name XRefPaste3Row: #REF!
Name 本循环科目: #REF!
Name 本循环科目: [1]索引!$D$15:$D$76

Sheet 底稿目录
A1: 底稿开列时，可先在以下单元格填写有关内容，以便其他底稿引用有关数据：
A2: 被审计单位： | D2: 序号 | E2: 内容 | F2: 索引号 | G2: 备注
A3: 截止日：202X年12月31日 | D3: 1 | E3: 应付职工薪酬实质性程序表 | F3: J1A
A4: 编制人： | D4: 2 | E4: 应付职工薪酬审定表 | F4: J1-1
A5: 编制日期： | D5: 3 | E5: 应付职工薪酬附注披露表（上市公司） | G5: 无需打印
A6: 复核人： | D6: 4 | E6: 应付职工薪酬附注披露表（国有企业） | G6: 无需打印
A7: 复核日期： | D7: 5 | E7: 应付职工薪酬明细表 | F7: J1-2
D8: 6 | E8: 调整分录汇总表 | F8: J1-3
A9: 关于工作底稿与审计程序索引号对应的说明 | D9: 7 | E9: 应付职工薪酬实质性分析表 | F9: J1-4
A10: 1.编制的审计工作底稿应与审计程序对应。审计项目组应根据被审计单位实际情况和风险评估情况在实质性程序表中裁剪、修改或增加审计程序，根据实际执行的审计程序完成相应审计工作底稿，编制的工作底稿中应按自然顺序依次编制索引号，并通过唯一的索引号将与实质性程序表中的程序对应关联（即将工作底稿的索引号填入实质性程序表中的底稿索引号列）。 | D10: 8 | E10: 应付职工薪酬同行业对比分析表 | F10: J1-5
D11: 9 | E11: 应付职工薪酬计提情况检查表 | F11: J1-6
D12: 10 | E12: 应付职工薪酬成本、费用分配情况检查表 | F12: J1-7
D13: 11 | E13: 应付职工薪酬检查表 | F13: J1-8
A14: 2.获取的支持性证据应与审计底稿或程序对应。审计项目组在完成底稿时获取的支持性证据应根据底稿索引号编制下一级按自然顺序排序的索引号（如D1-2-1、D1-2-2、……），并在底稿中说明引用的支持性证据、关联索引号。 | D14: 12 | E14: 非货币性福利检查表 | F14: J1-9
D15: 13 | E15: 辞退福利检查表 | F15: J1-10
A17: 3.工作底稿索引号的编码规则：实质性程序索引号按循环从“D”到“N”,循环内账户以顺序号排列，模板中底稿索引号按账户顺序+自然数顺序（即模板中索引号按二级自然顺序排列，如D1-1、D1-2、D1-3、……D1-N）。

Sheet 应付职工薪酬实质性程序表 J1A
A1: 致同会计师事务所
A2: 应付职工薪酬实质性程序
A3: =底稿目录!A2 -> 被审计单位： | C3: =底稿目录!A4 -> 编制人： | E3: =底稿目录!A5 -> 编制日期： | H3: 索引号： | I3: =底稿目录!F3 -> J1A
A4: =底稿目录!A3 -> 截止日：202X年12月31日 | C4: =底稿目录!A6 -> 复核人： | E4: =底稿目录!A7 -> 复核日期： | H4: 页 次：
A5: 一、本账户涉及的科目
A6: 应付职工薪酬
A7: 二、审计目标与认定的对应关系
A8: 审计目标 | G8: 财务报表的认定
A9: A. 资产负债表中记录的应付职工薪酬是存在的，且已经记录在恰当的账户中 | G9: 存在
A10: B. 所有应记录的应付职工薪酬均已记录，所有应当包括在财务报表中的相关披露均已包括 | G10: 完整性
A11: C. 记录的应付职工薪酬由被审计单位拥有或控制 | G11: 权利和义务
A12: D. 应付职工薪酬以恰当的金额包括在财务报表中，与之相关的计价或分摊调整已恰当记录，相关披露已得到恰当计量和描述 | G12: 准确性、计价和分摊
A13: E. 应付职工薪酬已被恰当地汇总或分解且表述清楚，相关披露在按照企业会计准则的编制基础下是相关的、可理解的 | G13: 列报与披露
A14: 三、计划实施的实质性程序
A15: 序号 | B15: 审计程序 | C15: 程序分类 | D15: 财务报表的认定 | I15: 底稿索引号
D16: 存在 | E16: 完整性 | F16: 权利和 义务 | G16: 准确性、计价和分摊 | H16: 列报 | J16: 根据被审计单位实际情况和风险评估情况裁剪、修改或增加审计程序
A17: 1 | B17: 获取或编制应付职工薪酬明细表，复核加计是否正确，与总账、明细账合计数核对是否相符，并编制审定表。 | C17: 常规★ | D17: √ | E17: √ | G17: √ | I17: J1-1 /J1-2
A18: 2 | B18: 在使用手工编制、自定义信息报告、系统生成的非固定格式报告等由被审计单位生成的信息时，测试有关信息准确性和完整性，并考虑针对编制和维护由被审计单位生成的信息的相关控制实施控制测试，以评价该信息是否能够为实现审计目的提供基础。 | C18: 常规★ | E18: √ | G18: √ | I18: T1/ | J18: 可参见《审计手册》4.2.6，由被审计单位生成的信息可能是由系统生成的、或手工编制的、或二者兼而有之的方式生成的。例如，由被审计单位生成的信息可能包括： • 不涉及自定义的、由系统生成的报告（如，固定格式报告）； • 可能通过人工自定义的、由系统生成的报告，例如，（计算机）查询信息或特别定制的报告； • 手工编制的信息，例如，汇总信息的电子表格或用以支持分配、计算以及调节的电子表格； • 其他系统生成或手工编制的信息，例如，由被审计单位编制的客户发票； • 通过影印、拍摄、扫描或其他方式转换成电子形式的文件记录。
A19: 3 | B19: 对期初余额的审计，取得应付职工薪酬期初余额明细表复核加计是否正确，与总账、明细账合计数是否相符，检查上期应付职工薪酬在本期支付情况，检查重大薪酬计提支持性文件、发行在外的股票期权清单以及其他必要追加的审计程序。（适用于首次承接） | C19: 备选 | D19: √ | E19: √ | F19: √ | G19: √ | J19: 由被审计单位生成的信息不包括： • 总分类账或明细分类账、试算平衡表、或经审计的财务报表； • 第三方（除了服务机构）的报表或报告，例如，原始银行对账单，或函证的回函； • 外部数据（例如，第三方发布的数据，如，定价来源）。
A20: 4 | B20: 关注会计政策、会计估计合理性、一贯性，关注其是否利用会计政策和会计估计及其变更操纵利润。 | C20: 常规★ | D20: √ | E20: √ | G20: √ | I20: J1-1 /J1-2 /J1-7 | J20: 应付职工薪酬中的由被审计单位生成的信息例如：员工名单、员工信息、员工工时记录等
A21: 5 | B21: 实施实质性分析程序： （1）将本期工资费用与上期工资费用总额进行比较。 （2）结合被审计单位员工人数的变动情况对各部门各月工资费用的发生额进行比较。 | C21: 常规★ | D21: √ | E21: √ | G21: √ | I21: J1-4
A22: 6 | B22: 职工人数分析，人均工资与同地区、同行业对比分析： （1）检查上交社会保险的人数与公司实际发放工资的人数是否一致，分析各部门人员构成（级别）及其变化是否合理、人数是否与企业规模一致；识别公司是否存在未代扣税金或养老金的员工； （2）分析人均工资（可分部门、地区或产品线）是否与同地区同行业的水平一致。 | C22: IPO/上市/新三板/重组/舞弊应对 | D22: √ | E22: √ | G22: √ | I22: J1-5
A23: 7 | B23: 检查应付职工薪酬本期计提金额： (1)对按照职工提供服务情况和工资标准计算的职工薪酬(如工资)，获取工资计算表，将工资标准与有关规定进行核对，选取样本检查劳动合同、考勤记录等。 (2)对国家规定了计提基础和计提比例的职工薪酬(如失业保险金、工伤保险金等)，检查是否按照规定的计提基础和比例计提。 (3)对被审计单位按照历史经验数据和当期计划预计的职工薪酬(如职工福利费)，获取管理层进行估计的资料，分析其合理性。 | C23: 常规★ | D23: √ | E23: √ | G23: √ | I23: J1-6
A24: 8 | B24: 检查应付职工薪酬的确认，与生产成本、制造费用、在建工程等相关账项进行核对，确定会计处理是否符合企业会计准则的规定；分析本期及上期计入成本、费用的工资薪金，关注构成是否异常变化。 | C24: 常规★ | D24: √ | E24: √ | G24: √ | I24: J1-7
A25: 9 | B25: 对本期应付职工薪酬的增加和减少，检查支持性文件，确定会计处理是否正确。 | C25: 常规★ | D25: √ | E25: √ | F25: √ | I25: J1-8
A26: 10 | B26: 检查应付职工薪酬的期后付款情况，并关注在资产负债表日至财务报表批准报出日之间，是否有确凿证据表明需要调整资产负债表日原确认的应付职工薪酬事项。 | C26: 常规★ | D26: √ | E26: √ | F26: √ | I26: J1-8
A27: 11 | B27: 如果存在非货币性福利：取得非货币性福利性文件，了解主要政策、非货币福利方式，会计处理是否正确。 | C27: 备选 | D27: √ | E27: √ | G27: √ | I27: J1-9
A28: 12 | B28: 如果存在辞退福利，取得相关辞退文件、协议： （1）对于职工没有选择权的辞退计划，检查按辞退职工数量、辞退补偿标准计提辞退福利负债金额是否正确； （2）对于自愿接受裁减的建议，检查按接受裁减建议的预计职工数量、辞退补偿标准（该标准确定）等计提辞退福利负债金额是否正确； （3）识别辞退福利中是否包含未予辞退的员工； 检查辞退福利相关的工资薪酬是否已经恰当计入相关费用、会计处理是否正确。 | C28: 备选 | D28: √ | E28: √ | F28: √ | G28: √ | I28: J1-10
A29: 13 | B29: 如果存在股份支付，检查股份支付的分类、会计处理、公允价值计量是否恰当，检查股份支付减少、调整、变更、取消等会计处理是否正确。 | C29: 备选 | D29: √ | E29: √ | F29: √ | G29: √ | H29: √ | I29: J3A
A30: 14 | B30: 取得个人所得税缴税凭证，结合本期工资发放额，判断个人所得税计缴是否在合理的范围，对于股份支付、发放现金股利或自然人股东（高管）留存收益转增股本等情形，测算并确定个人所得税计提是否充分。 | C30: 常规★ | D30: √ | E30: √ | F30: √ | G30: √
A31: 15 | B31: 检查企业是否存在压低员工薪金，阶段性降低人工成本粉饰业绩的情况： （1）将企业在册员工名单与实际工时记录（打卡、考勤记录等）比较，核查是否存在有工时记录，但不属于在册员工，未在企业发放工资的情况；是否存在重复或无效的员工信息； （2）根据企业的薪酬政策，测算每月工资总额及人均工资（分部门、地区或产品线），与企业的实际计提金额对比，分析合理性，并关注报告期是否存在降低的趋势； （3）访谈企业一般销售人员、研发人员、管理人员、车间人员，了解是否存在暂时压低员工薪金，期后补偿的协议或承诺； | C31: IPO/上市/新三板/重组/舞弊应对 | D31: √ | E31: √ | G31: √
A32: 16 | B32: 取得关键管理人员薪酬明细表，分析薪酬结构是否合理、是否存在重大波动，对比与市场平均水平、公司内部其他岗位薪酬是否存在异常，评估是否符合行业惯例和公司薪酬政策，检查披露是否正确。 | C32: IPO/上市/新三板/重组/舞弊应对 | D32: √ | E32: √ | G32: √ | H32: √
A33: 17 | B33: 针对识别的其他舞弊风险等因素增加的审计程序。 | C33: IPO/上市/新三板/重组/舞弊应对
A34: 18 | B34: 检查应付职工薪酬是否已按企业会计准则或其他适用的规定在财务报表中做出恰当列报和披露。 | C34: 常规★ | H34: √ | I34: A 1-1/A1-15 /A1-16

Sheet 应付职工薪酬实质性程序表 J1A-原版
A1: 致同会计师事务所
A2: 应付职工薪酬实质性程序
A3: 客户名称： | C3: 编制人： | E3: 编制日期： | K3: 索引号： | L3: J1A
A4: 截止日：20XX年12月31日 | C4: 复核人： | E4: 复核日期： | K4: 页 次：
A5: 一、本循环涉及的报表账户
A6: 应付职工薪酬
A7: 二、重大错报风险需从实质性程序获取的保证程度
A8: 根据风险评估和内控测试的结果按下列顺序作出判断： | D8: 财务报表的认定 | K8: 说明 | L8: 索引号
D9: 存在 | E9: 完整性 | F9: 权利和义务 | G9: 计价和分摊 | H9: 列报与披露
A10: A资产负债表中记录的应付职工薪酬是存在的。 | D10: √
A11: B所有应当记录的应付职工薪酬均已记录。 | E11: √
A12: C记录的应付职工薪酬是被审计单位应当履行的现时义务。 | F12: √
A13: D应付职工薪酬以恰当的金额包括在财务报表中，与之相关的计价调整已恰当记录。 | G13: √
A14: E应付职工薪酬已按照企业会计准则的规定在财务报表中作出恰当列报和披露。 | H14: √
A15: 三、计划实施的实质性程序
A16: 序号 | B16: 审计程序 | D16: 程序分类 | F16: 审计目标 | K16: 执行情况说明 （含底稿索引）
A17: 一 | B17: 编制审定表 | D17: 常规★ | F17: B | K17: L1 | N17: 获取或编制应付职工薪酬明细表，复核加计是否正确，与总账、明细账合计数核对是否相符，并编制审定表。
A18: 二 | B18: 获取或编制应付职工薪酬明细表。 | D18: 常规★ | E18: 应付职工薪酬 | F18: D | K18: L1-2
A19: 1 | B19: 确定计算的准确性。 | D19: 常规★ | E19: 应付职工薪酬
A20: 2 | B20: 将总金额与总账、明细账合计数核对相符 | D20: 常规★ | E20: 应付职工薪酬
A21: 三 | B21: 在使用被审计单位生成的信息（IPE）时，应当评价该信息对实现审计目的是否足够可靠，包括根据具体情况在必要时实施下列程序： | D21: 常规★ | F21: B | K21: T1 | N21: 在使用被审计单位生成的信息（IPE）时，应当评价该信息对实现审计目的是否足够可靠。 根据具体情况在必要时获取有关信息准确性和完整性的审计证据、评价信息对实现审计目的是否足够准确和详细。
A22: 1 | B22: 获取有关信息准确性和完整性的审计证据。
A23: 2 | B23: 评价信息对实现审计目的是否足够准确和详细。
A24: 四 | B24: 对于上期期末各职工薪酬账户： | D24: 备选 | E24: 应付职工薪酬 | F24: B | K24: L1-2 | N24: 对于上期期末各职工薪酬账户，确定采用的会计政策和程序是适当的。 同时获得、审阅并测试： （1）支持薪酬计提的列表。 （2）重大薪酬计提的支持性文件。 （3）发行在外的股票期权的清单。
A25: 1 | B25: 确定采用的会计政策和程序是适当的。 | D25: 备选 | E25: 应付职工薪酬
A26: 2 | B26: 获得并审阅支持薪酬计提的列表。 | D26: 备选 | E26: 应付职工薪酬
A27: 3 | B27: 测试重大薪酬计提的支持性文件。 | D27: 备选 | E27: 应付职工薪酬
A28: 4 | B28: 获取发行在外的股票期权的清单，并测试与其支持文件跟踪核对一致。 | D28: 备选 | E28: 应付职工薪酬
A29: 五 | B29: 执行分析程序，以确定可能需要执行以下额外审计程序的工资薪酬事项： | D29: 常规★ | E29: 应付职工薪酬 | F29: ABD | K29: L1-3-1、L1-3-2 | N29: 对应付职工薪酬执行分析程序： （1）将本期工资费用与上期工资费用总额进行比较。 （2）结合被审计单位员工人数的变动情况对各部门各月工资费用的发生额进行比较。 （3）针对IPO企业，分析企业报告期人均工资（分部门、地区或产品线）是否与同地区同行业的水平一致。特别关注劳务派遣是否符合规定、是否滥用以规避一线工人。 （4）针对IPO企业，取得企业员工名册与报告期工资计提和发放金额，分析各部门人员构成（级别）及其变化是否合理、人数是否与企业规模一致，核对财务报表有关披露（如现金流量表披露、关键管理人员薪酬披露）的真实性与一致性。 ……
A30: 1 | B30: 将本期工资费用与上期工资费用总额进行比较 | D30: 常规★ | E30: 应付职工薪酬
A31: 2 | B31: 结合被审计单位员工人数的变动情况对各部门各月工资费用的发生额进行比较 | D31: 常规★ | E31: 应付职工薪酬
A32: 3 | B32: 针对IPO企业，分析企业报告期人均工资（分部门、地区或产品线）是否与同地区同行业的水平一致；特别关注劳务派遣是否符合规定、是否滥用以规避一线工人 | D32: IPO/上市公司 | E32: 应付职工薪酬
A33: 4 | B33: 针对IPO企业，取得企业员工名册与报告期工资计提和发放金额，分析各部门人员构成（级别）及其变化是否合理、人数是否与企业规模一致，核对财务报表有关披露（如现金流量表披露、关键管理人员薪酬披露）的真实性与一 | D33: IPO/上市公司 | E33: 应付职工薪酬
A34: 六 | B34: 用下列方式分析性复核应计工资。例如： | D34: 常规 | E34: 应付职工薪酬 | F34: ABCD | N34: 检查应付职工薪酬本期计提金额： （1）获取工资计算表、工资标准及相关规定。 （2）对按照职工提供服务情况和工资标准计算的职工薪酬（如工资），选取样本进行重新计算。 （3）对国家规定了计提基础和计提比例的职工薪酬（如失业保险金、工伤保险金等），检查是否按照规定的计提基础和比例计提。 （4）对被审计单位按照历史经验数据和当期计划预计的职工薪酬（如职工福利费），获取管理层进行估计的资料，分析其合理性。 （5）确定上次支付日期与资产负债报表日期间的天数。 （6）通过确定平均日工资费用并将其应用到应计提的天数，以形成应计工资费用的预期值并与已记录的金额对比。
A35: 1 | B35: 确定上次支付日期与资产负债报表日期间的天数。 | D35: 常规 | E35: 应付职工薪酬
A36: 2 | B36: 通过确定平均日工资费用并将其应用到应计提的天数，以形成应计工资费用的预期值。 | D36: 常规 | E36: 应付职工薪酬
A37: 3 | B37: 与已记录的金额对比。 | D37: 常规 | E37: 应付职工薪酬
A38: 4 | B38: 如果有，调查未被解释的差异。 | D38: 常规 | E38: 应付职工薪酬
A39: 七 | B39: 检查应付职工薪酬本期计提金额： | D39: 常规★ | E39: 应付职工薪酬 | F39: ABD | K39: L1-4-1
A40: 1 | B40: 对按照职工提供服务情况和工资标准计算的职工薪酬（如工资），获取工资计算表，将工资标准与有关规定进行核对，选取样本进行测试。 | D40: 常规★ | E40: 应付职工薪酬
A41: 2 | B41: 对国家规定了计提基础和计提比例的职工薪酬（如失业保险金、工伤保险金等），检查是否按照规定的计提基础和比例计提。 | D41: 常规★ | E41: 应付职工薪酬
A42: 3 | B42: 对被审计单位按照历史经验数据和当期计划预计的职工薪酬（如职工福利费），获取管理层进行估计的资料，分析其合理性。 | D42: 常规★ | E42: 应付职工薪酬
A43: 八 | B43: 检查应付职工薪酬的确认，与生产成本、制造费用、在建工程等相关账项进行核对： | D43: 常规★ | E43: 应付职工薪酬 | F43: ABD | K43: L1-4-2 | N43: 检查应付职工薪酬的确认，与生产成本、制造费用、在建工程等相关账项进行核对： （1）确定会计处理是否符合企业会计准则的规定。 （2）分析计入成本、费用的工资薪金，关注构成是否异常变化、各月之间波动有无异常，如果异常降低，关注是否存在其他方（如关联方）代付工资的情况。
A44: 1 | B44: 确定会计处理是否符合企业会计准则的规定。 | D44: 常规★ | E44: 应付职工薪酬
A45: 2 | B45: 分析计入成本、费用的工资薪金，关注构成是否异常变化、各月之间波动有无异常，如果异常降低，关注是否存在其他方（如关联方）代付工资的情况； | D45: IPO/上市公司 | E45: 应付职工薪酬
A46: 九 | B46: 获取本期支付的奖金和佣金或其他易于导致错报的职工薪酬项目的明细表。 | D46: 常规 | E46: 应付职工薪酬 | F46: ABD | N46: 对于本期计提和支付的重大奖金、佣金、利润分享福利及其他易于导致错报的职工薪酬项目，应当： （1）了解相关计提政策、审批流程的设计与执行有效性。 （2）获取相关项目的支持性文件。 （3）验证计提依据是否充分、合理，是否达到计提和付款条件。 （4）核对计算的准确性和完整性。 （5）对异常波动、异常支付对象等进行分析。 （6）对于尚未支付的项目，确定该项负债是否被正确计算。 （7）执行截止测试，追踪至后续付款。
A47: 1 | B47: 确定计算的准确性。 | D47: 常规 | E47: 应付职工薪酬
A48: 2 | B48: 核对重大异常项目的支持性文件。 | D48: 常规 | E48: 应付职工薪酬
A49: 十 | B49: 取得非货币性福利的明细表 | D49: 备选 | E49: 应付职工薪酬 | F49: ABD | K49: L1-4-3 | N49: 对于非货币性福利： （1）取得非货币性福利的明细表。 （2）复核加计是否正确。 （3）与总账核对是否相符。 （4）确定该福利是否满足确认为负债的标准。 （5）确定负债的计算是否合理。
A50: 1 | B50: 确定计算的准确性。 | D50: 备选 | E50: 应付职工薪酬
A51: 2 | B51: 与总账核对一致。 | D51: 备选 | E51: 应付职工薪酬
A52: 3 | B52: 确定该福利是否满足确认为负债的标准。 | D52: 备选 | E52: 应付职工薪酬
A53: 4 | B53: 确定负债的计算是否合理。 | D53: 备选 | E53: 应付职工薪酬
A54: 十一 | B54: 取得辞退福利的明细表 | D54: 备选 | E54: 应付职工薪酬 | F54: ABD | K54: L1-4-4 | N54: 对于辞退福利福利： （1）取得辞退福利的明细表。 （2）复核加计是否正确。 （3）与总账核对是否相符。 （4）确定该福利是否满足确认为负债的标准。 （5）确定负债的计算是否合理。 （6）对于职工没有选择权的辞退计划，检查按辞退职工数量、辞退补偿标准计提辞退福利负债金额是否正确。 （7）对于自愿接受裁减的建议，检查按接受裁减建议的预计职工数量、辞退补偿标准（该标准确定）等计提辞退福利负债金额是否正确。 （8）识别辞退福利中是否包含未予辞退的员工，检查其工资薪酬是否已经恰当计入相关费用。 （9）检查辞退福利支付凭证是否真实正确。
A55: 1 | B55: 确定计算的准确性。 | D55: 备选 | E55: 应付职工薪酬
A56: 2 | B56: 与总账核对一致。 | D56: 备选 | E56: 应付职工薪酬
A57: 3 | B57: 确定该福利是否满足确认为负债的标准。 | D57: 备选 | E57: 应付职工薪酬
A58: 4 | B58: 确定负债的计算是否合理。 | D58: 备选 | E58: 应付职工薪酬
A59: 5 | B59: 对于职工没有选择权的辞退计划，检查按辞退职工数量、辞退补偿标准计提辞退福利负债金额是否正确 | D59: 备选 | E59: 应付职工薪酬
A60: 6 | B60: 对于自愿接受裁减的建议，检查按接受裁减建议的预计职工数量、辞退补偿标准（该标准确定）等计提辞退福利负债金额是否正确 | D60: 备选 | E60: 应付职工薪酬
A61: 7 | B61: 识别辞退福利中是否包含未予辞退的员工；检查其工资薪酬是否已经恰当计入相关费用。 | D61: 备选 | E61: 应付职工薪酬
A62: 8 | B62: 检查辞退福利支付凭证是否真实正确 | D62: 备选 | E62: 应付职工薪酬
A63: 十二 | B63: 对于带薪休假： | D63: 备选 | E63: 应付职工薪酬 | F63: ABD | K63: L1-5 | N63: 对于带薪休假： （1）确定所有员工均包含在列表中。 （2）确定企业确认带薪休假的方法是否正确。 （3）识别总体中的关键项目。 （4）使用样本计算器从剩余的总体中，设计样本以确定需测试项目的数量。 （5）将小时工资费用率与相关的记录核对。 （6）选取样本进行检查，使用样本评价工具，将错报推断到总体： ①确定样本所达到的精准程度是否能为此程序提供预期程度的保证。 ②确定是否需要追加程序，包括是否需要重新确定总体。 ③在未更正错报汇总表中记录推断的总体错报。 （7）向适当的人员报告未解决的差异。
A64: 1 | B64: 确定所有员工均包含在列表中。 | D64: 备选 | E64: 应付职工薪酬
A65: 2 | B65: 确定企业确认带薪休假的方法是否正确。 | D65: 备选 | E65: 应付职工薪酬
A66: 3 | B66: 识别总体中的关键项目。 | D66: 备选 | E66: 应付职工薪酬
A67: 4 | B67: 使用样本计算器从剩余的总体中，设计样本以确定需测试项目的数量。 | D67: 备选 | E67: 应付职工薪酬
A68: 5 | B68: 采用适当选样方法选取%S的项 | D68: 备选 | E68: 应付职工薪酬
A69: 6 | B69: 将小时工资费用率与相关的记录核对。 | D69: 备选 | E69: 应付职工薪酬
A70: 7 | B70: 向适当的人员报告未解决的差异。 | D70: 备选 | E70: 应付职工薪酬
A71: 8 | B71: 使用样本评价工具，将错报推断到总体。 | D71: 备选 | E71: 应付职工薪酬
A72: （1） | B72: 确定样本所达到的精准程度是否能为此程序提供预期程度的保证。 | D72: 备选 | E72: 应付职工薪酬
A73: （2） | B73: 确定是否需要追加程序，包括是否需要重新确定总体。 | D73: 备选 | E73: 应付职工薪酬
A74: （3） | B74: 在未更正错报汇总表中记录推断的总体错报。 | D74: 备选 | E74: 应付职工薪酬
A75: 十三 | B75: 对于奖金或者利润分享福利： | D75: 备选 | E75: 应付职工薪酬 | F75: ABD | K75: L1-5 | N75: 合并至
A76: 1 | B76: 确定其是否满足将其确认为负债的标准。 | D76: 备选 | E76: 应付职工薪酬
A77: 2 | B77: 如果已支付，追踪至后续付款。 | D77: 备选 | E77: 应付职工薪酬
A78: 3 | B78: 对于尚未支付的福利，确定该项负债是否被正确计算。 | D78: 备选 | E78: 应付职工薪酬
A79: 十四 | B79: 获取股份支付的明细表。 | D79: 备选 | E79: 应付职工薪酬 | F79: ABD | K79: L1-4-5 | N79: 对于股份支付： （1）取得股份支付的明细表。 （2）复核加计是否正确。 （3）与总账核对是否相符。 （4）确定企业是否有政策限制该股份支付薪酬奖励发行的日期。 （5）对新的或修改的股份支付进行分析： ①确定包括在分析中的所有个人都是雇员或其他提供类似服务的人员。 ②将新的股份支付薪酬奖励与董事会会议纪录或其它授权文件相比较。确定是否存在董事会会议记录或其他文件中提及的股份支付薪酬奖励尚未包含在上面的分析之内。如果是，获取该股份支付相关支持性文件，并确定该遗漏是否适当。 ③是否已适当地确认对现有的股份支付薪酬奖励的修改（如有修改）。 （6）选取样本（如需要）： ①取得合同及其他支持性文件。 ②确认主要条款及条件与股份支付薪酬工具是否一致（授予日期、期权的价格、股数、行使日期等）。 ③确定是否授权日与行权日之间存在重大时间间隔，如果有，向适当的人员询问原因。 （7）根据该股份支付薪酬奖励的条款和条件，确定其分类（如分类为权益结算、现金结算、或者二者结合）适当，并判断所采用的会计处理是否能恰当地反映这种分类。 （8）确定是否需要聘请估值专家，以协助评价：企业的专家（无论其是第三方还是内部员工）对该工具估值的工作。完成“专家资质”和“专家工作”的审计程序，以评估估值专家（无论其是第三方还是内部员工）的资质及其工作。
A80: 1 | B80: 确定计算的准确性。 | D80: 备选 | E80: 应付职工薪酬
A81: 2 | B81: 确定企业是否有政策限制该股份支付薪酬奖励发行的日期。 | D81: 备选 | E81: 应付职工薪酬
A82: 3 | B82: 与总账核对一致。 | D82: 备选 | E82: 应付职工薪酬
A83: 4 | B83: 判断选择_____期权，并执行 | D83: 备选 | E83: 应付职工薪酬
A84: （1） | B84: 取得合同。 | D84: 备选 | E84: 应付职工薪酬
A85: （2） | B85: 确认主要条款及条件与股份支付薪酬工具是否一致（即授予日期、期权的价格、股数、行使日期等）。 | D85: 备选 | E85: 应付职工薪酬
A86: （3） | B86: 确定是否授权日与行权日之间存在重大时间间隔，如果有，向适当的人员询问原因。 | D86: 备选 | E86: 应付职工薪酬
A87: 5 | B87: 确定包括在分析中的所有个人都是雇员或其他提供类似服务的人员。 | D87: 备选 | E87: 应付职工薪酬
A88: 6 | B88: 将新的股份支付薪酬奖励与董事会会议纪录或其它授权文件相比较。 | D88: 备选 | E88: 应付职工薪酬
A89: 7 | B89: 确定是否存在：董事会会议记录或其他文件中提及的股份支付薪酬奖励，尚未包含在上面的分析之内。 | D89: 备选 | E89: 应付职工薪酬
A90: 8 | B90: 如果是，获取该股份支付相关支持性文件，并确定该遗漏是否适当。 | D90: 备选 | E90: 应付职工薪酬
A91: 9 | B91: 是否已适当地确认对现有的股份支付薪酬奖励的修改（如有修改）。 | D91: 备选 | E91: 应付职工薪酬
... A96: 12 | B96: 完成“专家资质”和“专家工作”的审计程序，以评估每位精算师（无论其是第三方还是内部员工）的资质及其工作。 | D96: 备选 | E96: 应付职工薪酬
A97: 13 | B97: 考虑下列一个或多个情况能表现为利用股票期权日期倒签等获取不正当利益的股份期权。并考虑这些情况是否会导致财务报表出现重大错报。如果是，重新考虑之前的风险评估是否恰当。 | D97: 备选 | E97: 应付职工薪酬 | N97: 对于利用股票期权日期倒签等获取不正当利益的股份期权： （1）考虑下列一个或多个情况能表现为利用股票期权日期倒签等获取不正当利益的股份期权。并考虑这些情况是否会导致财务报表出现重大错报。如果是，重新考虑之前的风险评估是否恰当： ①企业缺乏现金用于奖励员工 ②过去的股票价格波动性很大 ③期权授予与预定日期不一致，而无规则地出现在期权授予的整个时期之间 ④董事会薪酬委员会只在企业召集时才开会，并且只在企业提议的基础上才制定股份支付薪酬奖励 ⑤授权日后的协议执行良好 （2）识别在报告期内的等待期。 （3）是否为达到不正当目目的，授予日刻意选在一个特定的日期。 （4）确定期权是否授予给符合条件的人。 （5）考虑从治理层或者其相关委员会获取一份关于股份支付批准日期的书面确认函。 （6）如有任何程序表明以利用股票期权倒签等获取不正当利益的股份期权，与项目合伙人讨论是否实施进一步的审计程序。
A98: （1） | B98: 企业缺乏现金用于奖励员工 | D98: 备选 | E98: 应付职工薪酬
A99: （2） | B99: 过去的股票价格波动性很大 | D99: 备选 | E99: 应付职工薪酬
A100: （3） | B100: 期权授予与预定日期不一致，而无规则地出现在期权授予的整个时期之间 | D100: 备选 | E100: 应付职工薪酬
A101: （4） | B101: 董事会薪酬委员会只在企业召集时才开会，并且只在企业提议的基础上才制定股份支付薪酬奖励 | D101: 备选 | E101: 应付职工薪酬
A102: （5） | B102: 授权日后的协议执行良好 | D102: 备选 | E102: 应付职工薪酬
A103: 十五 | B103: 针对利用股票期权日期倒签等获取不正当利益的股份期权，执行下列程序： | D103: 备选 | E103: 应付职工薪酬 | F103: ABCD
A104: 1 | B104: 识别在报告期内的等待期。 | D104: 备选 | E104: 应付职工薪酬
...

Sheet 应付职工薪酬实质性程序表 L1A-原
A1: 致同会计师事务所
A2: 应付职工薪酬实质性程序
A3: =[2]底稿目录!A2 -> 客户名称： | C3: =[2]底稿目录!A4 -> 编制人： | E3: =[2]底稿目录!A5 -> 编制日期： | K3: 索引号： | L3: L1A
A4: =[2]底稿目录!A3 -> 截止日：2022年12月31日 | C4: =[2]底稿目录!A6 -> 复核人： | E4: =[2]底稿目录!A7 -> 复核日期： | K4: 页 次：
A5: 一、本循环涉及的报表账户
A6: 应付职工薪酬
A7: 二、重大错报风险需从实质性程序获取的保证程度
A8: 根据风险评估和内控测试的结果按下列顺序作出判断： | D8: 财务报表的认定 | K8: 说明 | L8: 索引号
D9: 存在 | E9: 完整性 | F9: 权利和义务 | G9: 计价和分摊 | H9: 列报与披露
A10: A资产负债表中记录的应付职工薪酬是存在的。 | D10: √
A11: B所有应当记录的应付职工薪酬均已记录。 | E11: √
A12: C记录的应付职工薪酬是被审计单位应当履行的现时义务。 | F12: √
A13: D应付职工薪酬以恰当的金额包括在财务报表中，与之相关的计价调整已恰当记录。 | G13: √
A14: E应付职工薪酬已按照企业会计准则的规定在财务报表中作出恰当列报和披露。 | H14: √
A15: 三、计划实施的实质性程序
A16: 序号 | B16: 审计程序 | D16: 程序分类 | F16: 审计目标 | K16: 执行情况说明 （含底稿索引）
A17: 一 | B17: 编制审定表 | D17: 常规★ | F17: B | K17: L1 | M17: 整合 | N17: 获取或编制应付职工薪酬明细表，复核加计是否正确，与总账、明细账合计数核对是否相符，并编制审定表。
A18: 二 | B18: 获取或编制应付职工薪酬明细表。 | D18: 常规★ | E18: 应付职工薪酬 | F18: D | K18: L1-2 | M18: 整合
A19: 1 | B19: 确定计算的准确性。 | D19: 常规★ | E19: 应付职工薪酬 | M19: 整合
A20: 2 | B20: 将总金额与总账、明细账合计数核对相符 | D20: 常规★ | E20: 应付职工薪酬 | M20: 整合
A21: 三 | B21: 在使用被审计单位生成的信息（IPE）时，应当评价该信息对实现审计目的是否足够可靠，包括根据具体情况在必要时实施下列程序： | D21: 常规★ | F21: B | K21: T1 | M21: 整合 | N21: 在使用手工编制、自定义信息报告、系统生成的非固定格式报告等由被审计单位生成的信息时，测试有关信息准确性和完整性，并考虑针对编制和维护由被审计单位生成的信息的相关控制实施控制测试，以评价该信息是否能够为实现审计目的提供基础。
A22: 1 | B22: 获取有关信息准确性和完整性的审计证据。 | M22: 整合
A23: 2 | B23: 评价信息对实现审计目的是否足够准确和详细。 | M23: 整合
A24: 四 | B24: 对于上期期末各职工薪酬账户： | D24: 备选 | E24: 应付职工薪酬 | F24: B | K24: L1-2 | M24: 整合 | N24: 对期初余额的审计，取得应付职工薪酬期初余额明细表复核加计是否正确，与总账、明细账合计数是否相符，检查上期应付职工薪酬在本期支付情况，检查重大薪酬计提支持性文件、发行在外的股票期权清单以及其他必要追加的审计程序。（适用于首次承接）
A25: 1 | B25: 确定采用的会计政策和程序是适当的。 | D25: 备选 | E25: 应付职工薪酬 | M25: 整合
A26: 2 | B26: 获得并审阅支持薪酬计提的列表。 | D26: 备选 | E26: 应付职工薪酬 | M26: 整合
A27: 3 | B27: 测试重大薪酬计提的支持性文件。 | D27: 备选 | E27: 应付职工薪酬 | M27: 整合
A28: 4 | B28: 获取发行在外的股票期权的清单，并测试与其支持文件跟踪核对一致。 | D28: 备选 | E28: 应付职工薪酬 | M28: 整合
A29: 五 | B29: 执行分析程序，以确定可能需要执行以下额外审计程序的工资薪酬事项： | D29: 常规★ | E29: 应付职工薪酬 | F29: ABD | K29: L1-3-1、L1-3-2 | M29: 整合 | N29: 实施实质性分析程序： （1）将本期工资费用与上期工资费用总额进行比较。 （2）结合被审计单位员工人数的变动情况对各部门各月工资费用的发生额进行比较。
A30: 1 | B30: 将本期工资费用与上期工资费用总额进行比较 | D30: 常规★ | E30: 应付职工薪酬 | M30: 整合
A31: 2 | B31: 结合被审计单位员工人数的变动情况对各部门各月工资费用的发生额进行比较 | D31: 常规★ | E31: 应付职工薪酬 | M31: 整合
A32: 3 | B32: 针对IPO企业，分析企业报告期人均工资（分部门、地区或产品线）是否与同地区同行业的水平一致；特别关注劳务派遣是否符合规定、是否滥用以规避一线工人 | D32: IPO/上市公司 | E32: 应付职工薪酬 | M32: 舞弊应对，劳务派遣作为提示关注事项 | N32: 职工人数分析，人均工资与同地区、同行业对比分析： （1）检查上交社会保险的人数与公司实际发放工资的人数是否一致，分析各部门人员构成（级别）及其变化是否合理、人数是否与企业规模一致； （2）分析人均工资（可分部门、地区或产品线）是否与同地区同行业的水平一致。
A33: 4 | B33: 针对IPO企业，取得企业员工名册与报告期工资计提和发放金额，分析各部门人员构成（级别）及其变化是否合理、人数是否与企业规模一致，核对财务报表有关披露（如现金流量表披露、关键管理人员薪酬披露）的真实性与一 | D33: IPO/上市公司 | E33: 应付职工薪酬 | M33: 舞弊应对
A34: 六 | B34: 用下列方式分析性复核应计工资。例如： | D34: 常规 | E34: 应付职工薪酬 | F34: ABCD | M34: 删除、月度分析表J1-4作为提示
A35: 1 | B35: 确定上次支付日期与资产负债报表日期间的天数。 | D35: 常规 | E35: 应付职工薪酬 | M35: 删除、月度分析表J1-4作为提示
A36: 2 | B36: 通过确定平均日工资费用并将其应用到应计提的天数，以形成应计工资费用的预期值。 | D36: 常规 | E36: 应付职工薪酬 | M36: 删除、月度分析表J1-4作为提示
A37: 3 | B37: 与已记录的金额对比。 | D37: 常规 | E37: 应付职工薪酬 | M37: 删除、月度分析表J1-4作为提示
A38: 4 | B38: 如果有，调查未被解释的差异。 | D38: 常规 | E38: 应付职工薪酬 | M38: 删除、月度分析表J1-4作为提示
A39: 七 | B39: 检查应付职工薪酬本期计提金额： | D39: 常规★ | E39: 应付职工薪酬 | F39: ABD | K39: L1-4-1 | M39: 整合 | N39: 检查应付职工薪酬本期的发生: (1)对按照职工提供服务情况和工资标准计算的职工薪酬(如工资)，获取工资计算表，将工资标准与有关规定进行核对，选取样本进行测试。 (2)对国家规定了计提基础和计提比例的职工薪酬(如失业保险金、工伤保险金等)，检查是否按照规定的计提基础和比例计提。 (3)对被审计单位按照历史经验数据和当期计划预计的职工薪酬(如职工福利费)，获取管理层进行估计的资料，分析其合理性。
A40: 1 | B40: 对按照职工提供服务情况和工资标准计算的职工薪酬（如工资），获取工资计算表，将工资标准与有关规定进行核对，选取样本进行测试。 | D40: 常规★ | E40: 应付职工薪酬 | M40: 整合
A41: 2 | B41: 对国家规定了计提基础和计提比例的职工薪酬（如失业保险金、工伤保险金等），检查是否按照规定的计提基础和比例计提。 | D41: 常规★ | E41: 应付职工薪酬 | M41: 整合
A42: 3 | B42: 对被审计单位按照历史经验数据和当期计划预计的职工薪酬（如职工福利费），获取管理层进行估计的资料，分析其合理性。 | D42: 常规★ | E42: 应付职工薪酬 | M42: 整合
A43: 八 | B43: 检查应付职工薪酬的确认，与生产成本、制造费用、在建工程等相关账项进行核对： | D43: 常规★ | E43: 应付职工薪酬 | F43: ABD | K43: L1-4-2 | M43: 整合 | N43: 检查应付职工薪酬的确认，与生产成本、制造费用、在建工程等相关账项进行核对，确定会计处理是否符合企业会计准则的规定；分析本期及上期计入成本、费用的工资薪金，关注构成是否异常变化。
A44: 1 | B44: 确定会计处理是否符合企业会计准则的规定。 | D44: 常规★ | E44: 应付职工薪酬 | M44: 整合
A45: 2 | B45: 分析计入成本、费用的工资薪金，关注构成是否异常变化、各月之间波动有无异常，如果异常降低，关注是否存在其他方（如关联方）代付工资的情况； | D45: IPO/上市公司 | E45: 应付职工薪酬 | M45: 整合，各月异常波动作为月度分析表J1-4作为提示
A46: 九 | B46: 获取本期支付的奖金和佣金或其他易于导致错报的职工薪酬项目的明细表。 | D46: 常规 | E46: 应付职工薪酬 | F46: ABD | M46: 删除，作为明细表J1-2 提示
A47: 1 | B47: 确定计算的准确性。 | D47: 常规 | E47: 应付职工薪酬 | M47: 删除，作为明细表J1-2 提示
A48: 2 | B48: 核对重大异常项目的支持性文件。 | D48: 常规 | E48: 应付职工薪酬 | M48: 删除，作为明细表J1-2 提示
A49: 十 | B49: 取得非货币性福利的明细表 | D49: 备选 | E49: 应付职工薪酬 | F49: ABD | K49: L1-4-3 | M49: 整合 | N49: 如果存在非货币性福利：取得非货币性福利性文件，了解主要政策、非货币福利方式，会计处理是否正确。
A50: 1 | B50: 确定计算的准确性。 | D50: 备选 | E50: 应付职工薪酬 | M50: 整合
A51: 2 | B51: 与总账核对一致。 | D51: 备选 | E51: 应付职工薪酬 | M51: 整合
A52: 3 | B52: 确定该福利是否满足确认为负债的标准。 | D52: 备选 | E52: 应付职工薪酬 | M52: 整合
A53: 4 | B53: 确定负债的计算是否合理。 | D53: 备选 | E53: 应付职工薪酬 | M53: 整合
A54: 十一 | B54: 取得辞退福利的明细表 | D54: 备选 | E54: 应付职工薪酬 | F54: ABD | K54: L1-4-4 | M54: 整合 | N54: 如果存在辞退福利，取得相关辞退文件、协议： （1）对于职工没有选择权的辞退计划，检查按辞退职工数量、辞退补偿标准计提辞退福利负债金额是否正确； （2）对于自愿接受裁减的建议，检查按接受裁减建议的预计职工数量、辞退补偿标准（该标准确定）等计提辞退福利负债金额是否正确； （3）识别辞退福利中是否包含未予辞退的员工； 检查辞退福利相关的工资薪酬是否已经恰当计入相关费用、会计处理是否正确。
A55: 1 | B55: 确定计算的准确性。 | D55: 备选 | E55: 应付职工薪酬 | M55: 整合
A56: 2 | B56: 与总账核对一致。 | D56: 备选 | E56: 应付职工薪酬 | M56: 整合
A57: 3 | B57: 确定该福利是否满足确认为负债的标准。 | D57: 备选 | E57: 应付职工薪酬 | M57: 整合
A58: 4 | B58: 确定负债的计算是否合理。 | D58: 备选 | E58: 应付职工薪酬 | M58: 整合
A59: 5 | B59: 对于职工没有选择权的辞退计划，检查按辞退职工数量、辞退补偿标准计提辞退福利负债金额是否正确 | D59: 备选 | E59: 应付职工薪酬 | M59: 整合
A60: 6 | B60: 对于自愿接受裁减的建议，检查按接受裁减建议的预计职工数量、辞退补偿标准（该标准确定）等计提辞退福利负债金额是否正确 | D60: 备选 | E60: 应付职工薪酬 | M60: 整合
A61: 7 | B61: 识别辞退福利中是否包含未予辞退的员工；检查其工资薪酬是否已经恰当计入相关费用。 | D61: 备选 | E61: 应付职工薪酬 | M61: 整合
A62: 8 | B62: 检查辞退福利支付凭证是否真实正确 | D62: 备选 | E62: 应付职工薪酬 | M62: 整合
A63: 十二 | B63: 对于带薪休假： | D63: 备选 | E63: 应付职工薪酬 | F63: ABD | K63: L1-5 | M63: 删除，作为明细表J1-2 提示关注带薪休假
A64: 1 | B64: 确定所有员工均包含在列表中。 | D64: 备选 | E64: 应付职工薪酬 | M64: 删除，作为明细表J1-2 提示关注带薪休假
A65: 2 | B65: 确定企业确认带薪休假的方法是否正确。 | D65: 备选 | E65: 应付职工薪酬 | M65: 删除，作为明细表J1-2 提示关注带薪休假
A66: 3 | B66: 识别总体中的关键项目。 | D66: 备选 | E66: 应付职工薪酬 | M66: 删除，作为明细表J1-2 提示关注带薪休假
A67: 4 | B67: 使用样本计算器从剩余的总体中，设计样本以确定需测试项目的数量。 | D67: 备选 | E67: 应付职工薪酬 | M67: 删除，作为明细表J1-2 提示关注带薪休假
A68: 5 | B68: 采用适当选样方法选取%S的项 | D68: 备选 | E68: 应付职工薪酬 | M68: 删除，作为明细表J1-2 提示关注带薪休假
A69: 6 | B69: 将小时工资费用率与相关的记录核对。 | D69: 备选 | E69: 应付职工薪酬 | M69: 删除，作为明细表J1-2 提示关注带薪休假
A70: 7 | B70: 向适当的人员报告未解决的差异。 | D70: 备选 | E70: 应付职工薪酬 | M70: 删除，作为明细表J1-2 提示关注带薪休假
A71: 8 | B71: 使用样本评价工具，将错报推断到总体。 | D71: 备选 | E71: 应付职工薪酬 | M71: 删除，作为明细表J1-2 提示关注带薪休假
A72: （1） | B72: 确定样本所达到的精准程度是否能为此程序提供预期程度的保证。 | D72: 备选 | E72: 应付职工薪酬 | M72: 删除，作为明细表J1-2 提示关注带薪休假
A73: （2） | B73: 确定是否需要追加程序，包括是否需要重新确定总体。 | D73: 备选 | E73: 应付职工薪酬 | M73: 删除，作为明细表J1-2 提示关注带薪休假
A74: （3） | B74: 在未更正错报汇总表中记录推断的总体错报。 | D74: 备选 | E74: 应付职工薪酬 | M74: 删除，作为明细表J1-2 提示关注带薪休假
A75: 十三 | B75: 对于奖金或者利润分享福利： | D75: 备选 | E75: 应付职工薪酬 | F75: ABD | K75: L1-5 | M75: 删除，作为明细表J1-2 提示
A76: 1 | B76: 确定其是否满足将其确认为负债的标准。 | D76: 备选 | E76: 应付职工薪酬 | M76: 删除，作为明细表J1-2 提示
A77: 2 | B77: 如果已支付，追踪至后续付款。 | D77: 备选 | E77: 应付职工薪酬 | M77: 删除，作为明细表J1-2 提示
A78: 3 | B78: 对于尚未支付的福利，确定该项负债是否被正确计算。 | D78: 备选 | E78: 应付职工薪酬 | M78: 删除，作为明细表J1-2 提示
A79: 十四 | B79: 获取股份支付的明细表。 | D79: 备选 | E79: 应付职工薪酬 | F79: ABD | K79: L1-4-5 | M79: 股份支付单独体现9条程序
A80: 1 | B80: 确定计算的准确性。 | D80: 备选 | E80: 应付职工薪酬 | M80: 股份支付单独体现9条程序
A81: 2 | B81: 确定企业是否有政策限制该股份支付薪酬奖励发行的日期。 | D81: 备选 | E81: 应付职工薪酬 | M81: 股份支付单独体现9条程序
A82: 3 | B82: 与总账核对一致。 | D82: 备选 | E82: 应付职工薪酬 | M82: 股份支付单独体现9条程序
A83: 4 | B83: 判断选择_____期权，并执行 | D83: 备选 | E83: 应付职工薪酬 | M83: 股份支付单独体现9条程序
A84: （1） | B84: 取得合同。 | D84: 备选 | E84: 应付职工薪酬 | M84: 股份支付单独体现9条程序
A85: （2） | B85: 确认主要条款及条件与股份支付薪酬工具是否一致（即授予日期、期权的价格、股数、行使日期等）。 | D85: 备选 | E85: 应付职工薪酬 | M85: 股份支付单独体现9条程序
A86: （3） | B86: 确定是否授权日与行权日之间存在重大时间间隔，如果有，向适当的人员询问原因。 | D86: 备选 | E86: 应付职工薪酬 | M86: 删除，作为股份支付情况表J1-11提示
A87: 5 | B87: 确定包括在分析中的所有个人都是雇员或其他提供类似服务的人员。 | D87: 备选 | E87: 应付职工薪酬 | M87: 删除，作为股份支付情况表J1-11提示
A88: 6 | B88: 将新的股份支付薪酬奖励与董事会会议纪录或其它授权文件相比较。 | D88: 备选 | E88: 应付职工薪酬 | M88: 股份支付单独体现9条程序
A89: 7 | B89: 确定是否存在：董事会会议记录或其他文件中提及的股份支付薪酬奖励，尚未包含在上面的分析之内。 | D89: 备选 | E89: 应付职工薪酬 | M89: 股份支付单独体现9条程序
A90: 8 | B90: 如果是，获取该股份支付相关支持性文件，并确定该遗漏是否适当。 | D90: 备选 | E90: 应付职工薪酬 | M90: 股份支付单独体现9条程序
A91: 9 | B91: 是否已适当地确认对现有的股份支付薪酬奖励的修改（如有修改）。 | D91: 备选 | E91: 应付职工薪酬 | M91: 股份支付单独体现9条程序
... A102: （5） | B102: 授权日后的协议执行良好 | D102: 备选 | E102: 应付职工薪酬 | M102: 删除，作为股份支付情况表J1-11提示
A103: 十五 | B103: 针对利用股票期权日期倒签等获取不正当利益的股份期权，执行下列程序： | D103: 备选 | E103: 应付职工薪酬 | F103: ABCD | M103: 删除，作为股份支付情况表J1-11提示
A104: 1 | B104: 识别在报告期内的等待期。 | D104: 备选 | E104: 应付职工薪酬 | M104: 删除，作为股份支付情况表J1-11提示
A105: 2 | B105: 在报告期内，抽取__授予的股份数量并执行以下程 | D105: 备选 | E105: 应付职工薪酬 | M105: 删除，作为股份支付情况表J1-11提示
A106: 3 | B106: 是否为达到不正当目，授予日刻意选在一个特定的日期。 | D106: 备选 | E106: 应付职工薪酬 | M106: 删除，作为股份支付情况表J1-11提示
A107: 4 | B107: 确定期权是否授予给符合条件的人。 | D107: 备选 | E107: 应付职工薪酬 | M107: 删除，作为股份支付情况表J1-11提示
A108: 5 | B108: 考虑从治理层或者其相关委员会获取一份关于股份支付批准日期的书面确认函。 | D108: 备选 | E108: 应付职工薪酬 | M108: 删除，作为股份支付情况表J1-11提示
A109: 6 | B109: 如有任何程序表明以利用股票期权倒签等获取不正当利益的股份期权，与项目合伙人讨论是否实施进一步的审计程序。 | D109: 备选 | E109: 应付职工薪酬 | M109: 删除，作为股份支付情况表J1-11提示
A110: 十六 | B110: 对于设定提存计划的缴存款： | D110: 备选 | E110: 应付职工薪酬 | F110: ABD | K110: L1-4-1 | M110: 删除，作为设定提存计划提示明细表J1-2
...

Sheet 审定表J1-1 
A1: 致同会计师事务所
A2: 应付职工薪酬审定表
A3: =底稿目录!A2 -> 被审计单位： | D3: =底稿目录!A4 -> 编制人： | G3: =底稿目录!A5 -> 编制日期： | K3: 索引号： | L3: =底稿目录!F4 -> J1-1
A4: =底稿目录!A3 -> 截止日：202X年12月31日 | D4: =底稿目录!A6 -> 复核人： | G4: =底稿目录!A7 -> 复核日期： | K4: 页 次：
A5: （1）短期薪酬
A6: 项目名称 | B6: 期初数 | E6: 期末数 | H6: 本期未审数与上期 审定数的比较 | J6: 本期审定数与上期 审定数的比较 | L6: 原因分析
B7: 未审数 | C7: 账项调整 | D7: 审定数 | E7: 未审数 | F7: 账项调整 | G7: 审定数 | H7: 变动额 | I7: 变动率 | J7: 变动额 | K7: 变动率
A8: 工资、奖金、津贴和补贴 | B8: ='明细表J1-2 '!C13 -> 0 | C8: ='明细表J1-2 '!G13 -> 0 | D8: =B8+C8 -> 0 | E8: ='明细表J1-2 '!F13 -> 0 | F8: ='明细表J1-2 '!G13+'明细表J1-2 '!H13-'明细表J1-2 '!I13 -> 0 | G8: =E8+F8 -> 0 | H8: =E8-B8 -> 0 | I8: =IF(AND(B8=0,E8=0),0,IF(AND(B8=0,E8>0),1,H8/B8)) -> 0 | J8: =G8-D8 -> 0 | K8: =IF(AND(D8=0,G8=0),0,IF(AND(D8=0,G8>0),1,J8/D8)) -> 0
A9: 职工福利费 | B9: ='明细表J1-2 '!C19 -> 0 | C9: ='明细表J1-2 '!G19 -> 0 | D9: =B9+C9 -> 0 | E9: ='明细表J1-2 '!F19 -> 0 | F9: ='明细表J1-2 '!G19+'明细表J1-2 '!H19-'明细表J1-2 '!I19 -> 0 | G9: =E9+F9 -> 0 | H9: =E9-B9 -> 0 | I9: =IF(AND(B9=0,E9=0),0,IF(AND(B9=0,E9>0),1,H9/B9)) -> 0 | J9: =G9-D9 -> 0 | K9: =IF(AND(D9=0,G9=0),0,IF(AND(D9=0,G9>0),1,J9/D9)) -> 0
A10: 社会保险费 | B10: =SUM(B11:B14) -> 0 | C10: =SUM(C11:C14) -> 0 | D10: =B10+C10 -> 0 | E10: =SUM(E11:E14) -> 0 | F10: =SUM(F11:F14) -> 0 | G10: =E10+F10 -> 0 | H10: =E10-B10 -> 0 | I10: =IF(AND(B10=0,E10=0),0,IF(AND(B10=0,E10>0),1,H10/B10)) -> 0 | J10: =G10-D10 -> 0 | K10: =IF(AND(D10=0,G10=0),0,IF(AND(D10=0,G10>0),1,J10/D10)) -> 0
A11: 1.基本医疗保险费 | B11: ='明细表J1-2 '!C21 -> 0 | C11: ='明细表J1-2 '!G21 -> 0 | D11: =B11+C11 -> 0 | E11: ='明细表J1-2 '!F21 -> 0 | F11: ='明细表J1-2 '!G21+'明细表J1-2 '!H21-'明细表J1-2 '!I21 -> 0 | G11: =E11+F11 -> 0 | H11: =E11-B11 -> 0 | I11: =IF(AND(B11=0,E11=0),0,IF(AND(B11=0,E11>0),1,H11/B11)) -> 0 | J11: =G11-D11 -> 0 | K11: =IF(AND(D11=0,G11=0),0,IF(AND(D11=0,G11>0),1,J11/D11)) -> 0
A12: 2.补充医疗保险费 | B12: ='明细表J1-2 '!C22 -> 0 | C12: ='明细表J1-2 '!G22 -> 0 | D12: =B12+C12 -> 0 | E12: ='明细表J1-2 '!F22 -> 0 | F12: ='明细表J1-2 '!G22+'明细表J1-2 '!H22-'明细表J1-2 '!I22 -> 0 | G12: =E12+F12 -> 0 | H12: =E12-B12 -> 0 | I12: =IF(AND(B12=0,E12=0),0,IF(AND(B12=0,E12>0),1,H12/B12)) -> 0 | J12: =G12-D12 -> 0 | K12: =IF(AND(D12=0,G12=0),0,IF(AND(D12=0,G12>0),1,J12/D12)) -> 0
A13: 3.工伤保险费 | B13: ='明细表J1-2 '!C23 -> 0 | C13: ='明细表J1-2 '!G23 -> 0 | D13: =B13+C13 -> 0 | E13: ='明细表J1-2 '!F23 -> 0 | F13: ='明细表J1-2 '!G23+'明细表J1-2 '!H23-'明细表J1-2 '!I23 -> 0 | G13: =E13+F13 -> 0 | H13: =E13-B13 -> 0 | I13: =IF(AND(B13=0,E13=0),0,IF(AND(B13=0,E13>0),1,H13/B13)) -> 0 | J13: =G13-D13 -> 0 | K13: =IF(AND(D13=0,G13=0),0,IF(AND(D13=0,G13>0),1,J13/D13)) -> 0
A14: 4.生育保险费 | B14: ='明细表J1-2 '!C24 -> 0 | C14: ='明细表J1-2 '!G24 -> 0 | D14: =B14+C14 -> 0 | E14: ='明细表J1-2 '!F24 -> 0 | F14: ='明细表J1-2 '!G24+'明细表J1-2 '!H24-'明细表J1-2 '!I24 -> 0 | G14: =E14+F14 -> 0 | H14: =E14-B14 -> 0 | I14: =IF(AND(B14=0,E14=0),0,IF(AND(B14=0,E14>0),1,H14/B14)) -> 0 | J14: =G14-D14 -> 0 | K14: =IF(AND(D14=0,G14=0),0,IF(AND(D14=0,G14>0),1,J14/D14)) -> 0
A15: 住房公积金 | B15: ='明细表J1-2 '!C25 -> 0 | C15: ='明细表J1-2 '!G25 -> 0 | D15: =B15+C15 -> 0 | E15: ='明细表J1-2 '!F25 -> 0 | F15: ='明细表J1-2 '!G25+'明细表J1-2 '!H25-'明细表J1-2 '!I25 -> 0 | G15: =E15+F15 -> 0 | H15: =E15-B15 -> 0 | I15: =IF(AND(B15=0,E15=0),0,IF(AND(B15=0,E15>0),1,H15/B15)) -> 0 | J15: =G15-D15 -> 0 | K15: =IF(AND(D15=0,G15=0),0,IF(AND(D15=0,G15>0),1,J15/D15)) -> 0
A16: 工会经费 | B16: ='明细表J1-2 '!C26 -> 0 | C16: ='明细表J1-2 '!G26 -> 0 | D16: =B16+C16 -> 0 | E16: ='明细表J1-2 '!F26 -> 0 | F16: ='明细表J1-2 '!G26+'明细表J1-2 '!H26-'明细表J1-2 '!I26 -> 0 | G16: =E16+F16 -> 0 | H16: =E16-B16 -> 0 | I16: =IF(AND(B16=0,E16=0),0,IF(AND(B16=0,E16>0),1,H16/B16)) -> 0 | J16: =G16-D16 -> 0 | K16: =IF(AND(D16=0,G16=0),0,IF(AND(D16=0,G16>0),1,J16/D16)) -> 0
A17: 职工教育经费 | B17: ='明细表J1-2 '!C27 -> 0 | C17: ='明细表J1-2 '!G27 -> 0 | D17: =B17+C17 -> 0 | E17: ='明细表J1-2 '!F27 -> 0 | F17: ='明细表J1-2 '!G27+'明细表J1-2 '!H27-'明细表J1-2 '!I27 -> 0 | G17: =E17+F17 -> 0 | H17: =E17-B17 -> 0 | I17: =IF(AND(B17=0,E17=0),0,IF(AND(B17=0,E17>0),1,H17/B17)) -> 0 | J17: =G17-D17 -> 0 | K17: =IF(AND(D17=0,G17=0),0,IF(AND(D17=0,G17>0),1,J17/D17)) -> 0
A18: 短期带薪缺勤 | B18: ='明细表J1-2 '!C28 -> 0 | C18: ='明细表J1-2 '!G28 -> 0 | D18: =B18+C18 -> 0 | E18: ='明细表J1-2 '!F28 -> 0 | F18: ='明细表J1-2 '!G28+'明细表J1-2 '!H28-'明细表J1-2 '!I28 -> 0 | G18: =E18+F18 -> 0 | H18: =E18-B18 -> 0 | I18: =IF(AND(B18=0,E18=0),0,IF(AND(B18=0,E18>0),1,H18/B18)) -> 0 | J18: =G18-D18 -> 0 | K18: =IF(AND(D18=0,G18=0),0,IF(AND(D18=0,G18>0),1,J18/D18)) -> 0
A19: 短期利润分享计划 | B19: ='明细表J1-2 '!C29 -> 0 | C19: ='明细表J1-2 '!G29 -> 0 | D19: =B19+C19 -> 0 | E19: ='明细表J1-2 '!F29 -> 0 | F19: ='明细表J1-2 '!G29+'明细表J1-2 '!H29-'明细表J1-2 '!I29 -> 0 | G19: =E19+F19 -> 0 | H19: =E19-B19 -> 0 | I19: =IF(AND(B19=0,E19=0),0,IF(AND(B19=0,E19>0),1,H19/B19)) -> 0 | J19: =G19-D19 -> 0 | K19: =IF(AND(D19=0,G19=0),0,IF(AND(D19=0,G19>0),1,J19/D19)) -> 0
A20: 非货币性福利 | B20: ='明细表J1-2 '!C30 -> 0 | C20: ='明细表J1-2 '!G30 -> 0 | D20: =B20+C20 -> 0 | E20: ='明细表J1-2 '!F30 -> 0 | F20: ='明细表J1-2 '!G30+'明细表J1-2 '!H30-'明细表J1-2 '!I30 -> 0 | G20: =E20+F20 -> 0 | H20: =E20-B20 -> 0 | I20: =IF(AND(B20=0,E20=0),0,IF(AND(B20=0,E20>0),1,H20/B20)) -> 0 | J20: =G20-D20 -> 0 | K20: =IF(AND(D20=0,G20=0),0,IF(AND(D20=0,G20>0),1,J20/D20)) -> 0
A21: 其他短期薪酬 | B21: ='明细表J1-2 '!C31 -> 0 | C21: ='明细表J1-2 '!G31 -> 0 | D21: =B21+C21 -> 0 | E21: ='明细表J1-2 '!F31 -> 0 | F21: ='明细表J1-2 '!G31+'明细表J1-2 '!H31-'明细表J1-2 '!I31 -> 0 | G21: =E21+F21 -> 0 | H21: =E21-B21 -> 0 | I21: =IF(AND(B21=0,E21=0),0,IF(AND(B21=0,E21>0),1,H21/B21)) -> 0 | J21: =G21-D21 -> 0 | K21: =IF(AND(D21=0,G21=0),0,IF(AND(D21=0,G21>0),1,J21/D21)) -> 0
A22: 合计 | B22: =SUM(B8:B10,B15:B21) -> 0 | C22: =SUM(C8:C10,C15:C21) -> 0 | D22: =SUM(D8:D10,D15:D21) -> 0 | E22: =SUM(E8:E10,E15:E21) -> 0 | F22: =SUM(F8:F10,F15:F21) -> 0 | G22: =SUM(G8:G10,G15:G21) -> 0 | H22: =SUM(H8:H10,H15:H21) -> 0 | I22: =IF(AND(B22=0,E22=0),0,IF(AND(B22=0,E22>0),1,H22/B22)) -> 0 | J22: =SUM(J8:J10,J15:J21) -> 0 | K22: =IF(AND(D22=0,G22=0),0,IF(AND(D22=0,G22>0),1,J22/D22)) -> 0
A23: （2）离职后福利中设定提存计划、其他长期福利中符合设定提存条件的负债
A24: 项 目 | B24: 期初数 | E24: 期末数 | H24: 本期未审数与上期 审定数的比较 | J24: 本期审定数与上期 审定数的比较 | L24: 原因分析
B25: 未审数 | C25: 账项调整 | D25: 审定数 | E25: 未审数 | F25: 账项调整 | G25: 审定数 | H25: 变动额 | I25: 变动率 | J25: 变动额 | K25: 变动率
A26: 离职后福利 | B26: =B27+B28+B29+B30 -> 0 | C26: =C27+C28+C29+C30 -> 0 | D26: =B26+C26 -> 0 | E26: =E27+E28+E29+E30 -> 0 | F26: =F27+F28+F29+F30 -> 0 | G26: =E26+F26 -> 0 | H26: =E26-B26 -> 0 | I26: =IF(AND(B26=0,E26=0),0,IF(AND(B26=0,E26>0),1,H26/B26)) -> 0 | J26: =G26-D26 -> 0 | K26: =IF(AND(D26=0,G26=0),0,IF(AND(D26=0,G26>0),1,J26/D26)) -> 0
A27: 其中：1．基本养老保险费 | B27: ='明细表J1-2 '!C38 -> 0 | C27: ='明细表J1-2 '!G38 -> 0 | D27: =B27+C27 -> 0 | E27: ='明细表J1-2 '!F38 -> 0 | F27: ='明细表J1-2 '!G38+'明细表J1-2 '!H38-'明细表J1-2 '!I38 -> 0 | G27: =E27+F27 -> 0 | H27: =E27-B27 -> 0 | I27: =IF(AND(B27=0,E27=0),0,IF(AND(B27=0,E27>0),1,H27/B27)) -> 0 | J27: =G27-D27 -> 0 | K27: =IF(AND(D27=0,G27=0),0,IF(AND(D27=0,G27>0),1,J27/D27)) -> 0
A28: 2．失业保险费 | B28: ='明细表J1-2 '!C39 -> 0 | C28: ='明细表J1-2 '!G39 -> 0 | D28: =B28+C28 -> 0 | E28: ='明细表J1-2 '!F39 -> 0 | F28: ='明细表J1-2 '!G39+'明细表J1-2 '!H39-'明细表J1-2 '!I39 -> 0 | G28: =E28+F28 -> 0 | H28: =E28-B28 -> 0 | I28: =IF(AND(B28=0,E28=0),0,IF(AND(B28=0,E28>0),1,H28/B28)) -> 0 | J28: =G28-D28 -> 0 | K28: =IF(AND(D28=0,G28=0),0,IF(AND(D28=0,G28>0),1,J28/D28)) -> 0
A29: 3．企业年金缴费 | B29: ='明细表J1-2 '!C40 -> 0 | C29: ='明细表J1-2 '!G40 -> 0 | D29: =B29+C29 -> 0 | E29: ='明细表J1-2 '!F40 -> 0 | F29: ='明细表J1-2 '!G40+'明细表J1-2 '!H40-'明细表J1-2 '!I40 -> 0 | G29: =E29+F29 -> 0 | H29: =E29-B29 -> 0 | I29: =IF(AND(B29=0,E29=0),0,IF(AND(B29=0,E29>0),1,H29/B29)) -> 0 | J29: =G29-D29 -> 0 | K29: =IF(AND(D29=0,G29=0),0,IF(AND(D29=0,G29>0),1,J29/D29)) -> 0
A30: 4．其他 | B30: ='明细表J1-2 '!C41 -> 0 | C30: ='明细表J1-2 '!G41 -> 0 | D30: =B30+C30 -> 0 | E30: ='明细表J1-2 '!F41 -> 0 | F30: ='明细表J1-2 '!G41+'明细表J1-2 '!H41-'明细表J1-2 '!I41 -> 0 | G30: =E30+F30 -> 0 | H30: =E30-B30 -> 0 | I30: =IF(AND(B30=0,E30=0),0,IF(AND(B30=0,E30>0),1,H30/B30)) -> 0 | J30: =G30-D30 -> 0 | K30: =IF(AND(D30=0,G30=0),0,IF(AND(D30=0,G30>0),1,J30/D30)) -> 0
A31: 其他长期职工福利 | B31: =B32+B33 -> 0 | C31: =C32+C33 -> 0 | D31: =B31+C31 -> 0 | E31: =E32+E33 -> 0 | F31: =F32+F33 -> 0 | G31: =E31+F31 -> 0 | H31: =E31-B31 -> 0 | I31: =IF(AND(B31=0,E31=0),0,IF(AND(B31=0,E31>0),1,H31/B31)) -> 0 | J31: =G31-D31 -> 0 | K31: =IF(AND(D31=0,G31=0),0,IF(AND(D31=0,G31>0),1,J31/D31)) -> 0
A32: 其中：1．xxx | B32: ='明细表J1-2 '!C43 -> 0 | C32: ='明细表J1-2 '!G43 -> 0 | D32: =B32+C32 -> 0 | E32: ='明细表J1-2 '!F43 -> 0 | F32: ='明细表J1-2 '!G43+'明细表J1-2 '!H43-'明细表J1-2 '!I43 -> 0 | G32: =E32+F32 -> 0 | H32: =E32-B32 -> 0 | I32: =IF(AND(B32=0,E32=0),0,IF(AND(B32=0,E32>0),1,H32/B32)) -> 0 | J32: =G32-D32 -> 0 | K32: =IF(AND(D32=0,G32=0),0,IF(AND(D32=0,G32>0),1,J32/D32)) -> 0
A33: 2．其他 | B33: ='明细表J1-2 '!C44 -> 0 | C33: ='明细表J1-2 '!G44 -> 0 | D33: =B33+C33 -> 0 | E33: ='明细表J1-2 '!F44 -> 0 | F33: ='明细表J1-2 '!G44+'明细表J1-2 '!H44-'明细表J1-2 '!I44 -> 0 | G33: =E33+F33 -> 0 | H33: =E33-B33 -> 0 | I33: =IF(AND(B33=0,E33=0),0,IF(AND(B33=0,E33>0),1,H33/B33)) -> 0 | J33: =G33-D33 -> 0 | K33: =IF(AND(D33=0,G33=0),0,IF(AND(D33=0,G33>0),1,J33/D33)) -> 0
A34: 合 计 | B34: =B26+B31 -> 0 | C34: =C26+C31 -> 0 | D34: =D26+D31 -> 0 | E34: =E26+E31 -> 0 | F34: =F26+F31 -> 0 | G34: =G26+G31 -> 0 | H34: =H26+H31 -> 0 | I34: =IF(AND(B34=0,E34=0),0,IF(AND(B34=0,E34>0),1,H34/B34)) -> 0 | J34: =J26+J31 -> 0 | K34: =IF(AND(D34=0,G34=0),0,IF(AND(D34=0,G34>0),1,J34/D34)) -> 0
A35: （3）一年内支付的辞退福利
A36: 项 目 | B36: 期初数 | E36: 期末数 | H36: 本期未审数与上期 审定数的比较 | J36: 本期审定数与上期 审定数的比较 | L36: 原因分析
B37: 未审数 | C37: 账项调整 | D37: 审定数 | E37: 未审数 | F37: 账项调整 | G37: 审定数 | H37: 变动额 | I37: 变动率 | J37: 变动额 | K37: 变动率
B38: ='明细表J1-2 '!C50 -> 0 | C38: ='明细表J1-2 '!G50 -> 0 | D38: =B38+C38 -> 0 | E38: ='明细表J1-2 '!F50 -> 0 | F38: ='明细表J1-2 '!G50+'明细表J1-2 '!H50-'明细表J1-2 '!I50 -> 0 | G38: =E38+F38 -> 0 | H38: =E38-B38 -> 0 | I38: =IF(AND(B38=0,E38=0),0,IF(AND(B38=0,E38>0),1,H38/B38)) -> 0 | J38: =G38-D38 -> 0 | K38: =IF(AND(D38=0,G38=0),0,IF(AND(D38=0,G38>0),1,J38/D38)) -> 0
B39: ='明细表J1-2 '!C51 -> 0 | C39: ='明细表J1-2 '!G51 -> 0 | D39: =B39+C39 -> 0 | E39: ='明细表J1-2 '!F51 -> 0 | F39: ='明细表J1-2 '!G51+'明细表J1-2 '!H51-'明细表J1-2 '!I51 -> 0 | G39: =E39+F39 -> 0 | H39: =E39-B39 -> 0 | I39: =IF(AND(B39=0,E39=0),0,IF(AND(B39=0,E39>0),1,H39/B39)) -> 0 | J39: =G39-D39 -> 0 | K39: =IF(AND(D39=0,G39=0),0,IF(AND(D39=0,G39>0),1,J39/D39)) -> 0
B40: ='明细表J1-2 '!C52 -> 0 | C40: ='明细表J1-2 '!G52 -> 0 | D40: =B40+C40 -> 0 | E40: ='明细表J1-2 '!F52 -> 0 | F40: ='明细表J1-2 '!G52+'明细表J1-2 '!H52-'明细表J1-2 '!I52 -> 0 | G40: =E40+F40 -> 0 | H40: =E40-B40 -> 0 | I40: =IF(AND(B40=0,E40=0),0,IF(AND(B40=0,E40>0),1,H40/B40)) -> 0 | J40: =G40-D40 -> 0 | K40: =IF(AND(D40=0,G40=0),0,IF(AND(D40=0,G40>0),1,J40/D40)) -> 0
A41: 合 计 | B41: =SUM(B38:B40) -> 0 | C41: =SUM(C38:C40) -> 0 | D41: =B41+C41 -> 0 | E41: =SUM(E38:E40) -> 0 | F41: =SUM(F38:F40) -> 0 | G41: =E41+F41 -> 0 | H41: =E41-B41 -> 0 | I41: =IF(AND(B41=0,E41=0),0,IF(AND(B41=0,E41>0),1,H41/B41)) -> 0 | J41: =J34+J38 -> 0 | K41: =IF(AND(D41=0,G41=0),0,IF(AND(D41=0,G41>0),1,J41/D41)) -> 0
A42: 试算平衡表数
A43: 差异数 | D43: =D22+D34+D41-D42 -> 0 | G43: =G22+G34+G41-G42 -> 0
A44: 1、审计说明
A47: 2、审计结论

Sheet 附注披露信息（上市公司）
A1: 致同会计师事务所
A2: 应付职工薪酬附注披露信息（上市公司）
A3: =底稿目录!A2 -> 被审计单位： | B3: =底稿目录!A4 -> 编制人： | C3: =底稿目录!A5 -> 编制日期： | D3: 索引号：
A4: =底稿目录!A3 -> 截止日：202X年12月31日 | B4: =底稿目录!A6 -> 复核人： | C4: =底稿目录!A7 -> 复核日期： | D4: 页次：
A5: 应付职工薪酬
A6: 项 目 | B6: 上年年末数 | C6: 本期增加 | D6: 本期减少 | E6: 期末数
A7: 短期薪酬 | B7: ='明细表J1-2 '!J33 -> 0 | C7: ='明细表J1-2 '!K33 -> 0 | D7: ='明细表J1-2 '!L33 -> 0 | E7: ='明细表J1-2 '!M33 -> 0
A8: 离职后福利-设定提存计划 | B8: ='明细表J1-2 '!J46 -> 0 | C8: ='明细表J1-2 '!K46 -> 0 | D8: ='明细表J1-2 '!L46 -> 0 | E8: ='明细表J1-2 '!M46 -> 0
A9: 辞退福利 | B9: ='明细表J1-2 '!J53 -> 0 | C9: ='明细表J1-2 '!K53 -> 0 | D9: ='明细表J1-2 '!L53 -> 0 | E9: ='明细表J1-2 '!M53 -> 0
A10: 一年内到期的其他福利
A12: 合 计 | B12: =SUM(B7:B11) -> 0 | C12: =SUM(C7:C11) -> 0 | D12: =SUM(D7:D11) -> 0 | E12: =SUM(E7:E11) -> 0
A13: 【提示：
A14: 1、辞退福利包括（1）预期在其确认的年度报告期间期末后12个月内完全支付的辞退福利；（2）补偿款超过1年支付的辞退计划将于年度报告期间期末后12个月内支付的款项，例如内退计划将于下一年支付的金额。
A15: 2、一年内到期的其他福利：指一年内到期的其他长期福利（不含设定受益计划）；应根据“长期应付职工薪酬”项目分析填列。
A16: （1）短期薪酬
A17: 项 目 | B17: 上年年末数 | C17: 本期增加 | D17: 本期减少 | E17: 期末数
A18: 工资、奖金、津贴和补贴 | B18: ='明细表J1-2 '!J13 -> 0 | C18: ='明细表J1-2 '!K13 -> 0 | D18: ='明细表J1-2 '!L13 -> 0 | E18: ='明细表J1-2 '!M13 -> 0
A19: 职工福利费 | B19: ='明细表J1-2 '!J19 -> 0 | C19: ='明细表J1-2 '!K19 -> 0 | D19: ='明细表J1-2 '!L19 -> 0 | E19: ='明细表J1-2 '!M19 -> 0
A20: 社会保险费 | B20: =SUM(B21:B27) -> 0 | C20: =SUM(C21:C27) -> 0 | D20: =SUM(D21:D27) -> 0 | E20: =SUM(E21:E27) -> 0
A21: 其中：1．医疗保险费 | B21: ='明细表J1-2 '!J21+'明细表J1-2 '!J22 -> 0 | C21: ='明细表J1-2 '!K21+'明细表J1-2 '!K22 -> 0 | D21: ='明细表J1-2 '!L21+'明细表J1-2 '!L22 -> 0 | E21: ='明细表J1-2 '!M21+'明细表J1-2 '!M22 -> 0
A22: 2．工伤保险费 | B22: ='明细表J1-2 '!J23 -> 0 | C22: ='明细表J1-2 '!K23 -> 0 | D22: ='明细表J1-2 '!L23 -> 0 | E22: ='明细表J1-2 '!M23 -> 0
A23: 3．生育保险费 | B23: ='明细表J1-2 '!J24 -> 0 | C23: ='明细表J1-2 '!K24 -> 0 | D23: ='明细表J1-2 '!L24 -> 0 | E23: ='明细表J1-2 '!M24 -> 0
A24: ……
A28: 住房公积金 | B28: ='明细表J1-2 '!J25 -> 0 | C28: ='明细表J1-2 '!K25 -> 0 | D28: ='明细表J1-2 '!L25 -> 0 | E28: ='明细表J1-2 '!M25 -> 0
A29: 工会经费和职工教育经费 | B29: ='明细表J1-2 '!J26+'明细表J1-2 '!J27 -> 0 | C29: ='明细表J1-2 '!K26+'明细表J1-2 '!K27 -> 0 | D29: ='明细表J1-2 '!L26+'明细表J1-2 '!L27 -> 0 | E29: ='明细表J1-2 '!M26+'明细表J1-2 '!M27 -> 0
A30: 短期带薪缺勤 | B30: ='明细表J1-2 '!J28 -> 0 | C30: ='明细表J1-2 '!K28 -> 0 | D30: ='明细表J1-2 '!L28 -> 0 | E30: ='明细表J1-2 '!M28 -> 0
A31: 短期利润分享计划 | B31: ='明细表J1-2 '!J29 -> 0 | C31: ='明细表J1-2 '!K29 -> 0 | D31: ='明细表J1-2 '!L29 -> 0 | E31: ='明细表J1-2 '!M29 -> 0
A32: 非货币性福利 | B32: ='明细表J1-2 '!J30 -> 0 | C32: ='明细表J1-2 '!K30 -> 0 | D32: ='明细表J1-2 '!L30 -> 0 | E32: ='明细表J1-2 '!M30 -> 0
A33: 其他短期薪酬 | B33: ='明细表J1-2 '!J31 -> 0 | C33: ='明细表J1-2 '!K31 -> 0 | D33: ='明细表J1-2 '!L31 -> 0 | E33: ='明细表J1-2 '!M31 -> 0
A35: 合 计 | B35: =SUM(B18:B20)+SUM(B28:B34) -> 0 | C35: =SUM(C18:C20)+SUM(C28:C34) -> 0 | D35: =SUM(D18:D20)+SUM(D28:D34) -> 0 | E35: =SUM(E18:E20)+SUM(E28:E34) -> 0
A36: 说明：
A37: 1、（企业本期为职工提供的各项非货币性福利形式、其计算依据。）
A38: 2、（企业依据短期利润分享计划提供的职工薪酬计算依据。）
A39: （2）设定提存计划
A40: 项 目 | B40: 上年年末数 | C40: 本期增加 | D40: 本期减少 | E40: 期末数
A41: 离职后福利 | B41: =SUM(B42:B45) -> 0 | C41: =SUM(C42:C45) -> 0 | D41: =SUM(D42:D45) -> 0 | E41: =SUM(E42:E45) -> 0
A42: 其中：1．基本养老保险费 | B42: ='明细表J1-2 '!J38 -> 0 | C42: ='明细表J1-2 '!K38 -> 0 | D42: ='明细表J1-2 '!L38 -> 0 | E42: ='明细表J1-2 '!M38 -> 0
A43: 2．失业保险费 | B43: ='明细表J1-2 '!J39 -> 0 | C43: ='明细表J1-2 '!K39 -> 0 | D43: ='明细表J1-2 '!L39 -> 0 | E43: ='明细表J1-2 '!M39 -> 0
A44: 3．企业年金缴费 | B44: ='明细表J1-2 '!J40 -> 0 | C44: ='明细表J1-2 '!K40 -> 0 | D44: ='明细表J1-2 '!L40 -> 0 | E44: ='明细表J1-2 '!M40 -> 0
A45: 4．其他 | B45: ='明细表J1-2 '!J41 -> 0 | C45: ='明细表J1-2 '!K41 -> 0 | D45: ='明细表J1-2 '!L41 -> 0 | E45: ='明细表J1-2 '!M41 -> 0
A46: 其他长期职工福利（不适用的删除） | B46: ='明细表J1-2 '!J42 -> 0 | C46: ='明细表J1-2 '!K42 -> 0 | D46: ='明细表J1-2 '!L42 -> 0 | E46: ='明细表J1-2 '!M42 -> 0
A47: 其中：1．xxx | B47: ='明细表J1-2 '!J43 -> 0 | C47: ='明细表J1-2 '!K43 -> 0 | D47: ='明细表J1-2 '!L43 -> 0 | E47: ='明细表J1-2 '!M43 -> 0
A48: 2．其他 | B48: ='明细表J1-2 '!J44 -> 0 | C48: ='明细表J1-2 '!K44 -> 0 | D48: ='明细表J1-2 '!L44 -> 0 | E48: ='明细表J1-2 '!M44 -> 0
A49: 合 计 | B49: =B41+B46 -> 0 | C49: =C41+C46 -> 0 | D49: =D41+D46 -> 0 | E49: =E41+E46 -> 0
A50: 说明：（设定提存计划的性质、计算缴费金额的公式或依据）
A51: 【提示：其他长期职工福利指符合设定提存计划条件的其他长期职工福利】
A52: （3）辞退福利
A53: 说明：辞退福利的性质、内容及计算依据。
A54: （注：应付职工薪酬、设定受益计划净负债（净资产）、一年后支付的辞退福利及其他长期职工福利本期减少一般与现金流量中“支付职工”项一致，除非代扣税未交、实物发放等）

Sheet 附注披露信息（国有企业）
A1: 致同会计师事务所
A2: 应付职工薪酬附注披露信息（国有企业）
A3: =底稿目录!A2 -> 被审计单位： | B3: =底稿目录!A4 -> 编制人： | C3: =底稿目录!A5 -> 编制日期： | D3: 索引号：
A4: =底稿目录!A3 -> 截止日：202X年12月31日 | B4: =底稿目录!A6 -> 复核人： | C4: =底稿目录!A7 -> 复核日期： | D4: 页次：
A5: 应付职工薪酬
A6: 应付职工薪酬附注（不适用的删除）
A7: （1）应付职工薪酬列示
A8: 项 目 | B8: 期初余额 | C8: 本期增加 | D8: 本期减少 | E8: 期末余额
A9: 短期薪酬 | B9: ='明细表J1-2 '!J33 -> 0 | C9: ='明细表J1-2 '!K33 -> 0 | D9: ='明细表J1-2 '!L33 -> 0 | E9: =B9+C9-D9 -> 0
A10: 离职后福利-设定提存计划 | B10: ='明细表J1-2 '!J46 -> 0 | C10: ='明细表J1-2 '!K46 -> 0 | D10: ='明细表J1-2 '!L46 -> 0 | E10: =B10+C10-D10 -> 0
A11: 辞退福利 | B11: ='明细表J1-2 '!J53 -> 0 | C11: ='明细表J1-2 '!K53 -> 0 | D11: ='明细表J1-2 '!L53 -> 0 | E11: =B11+C11-D11 -> 0
A12: 一年内到期的其他福利 | E12: =B12+C12-D12 -> 0
A13: 其他
A14: 合 计 | B14: =SUM(B9:B13) -> 0 | C14: =SUM(C9:C13) -> 0 | D14: =SUM(D9:D13) -> 0 | E14: =SUM(E9:E13) -> 0
A15: （2）短期薪酬列示
A16: 项 目 | B16: 期初余额 | C16: 本期增加 | D16: 本期减少 | E16: 期末余额
A17: 工资、奖金、津贴和补贴 | B17: ='明细表J1-2 '!J13 -> 0 | C17: ='明细表J1-2 '!K13 -> 0 | D17: ='明细表J1-2 '!L13 -> 0 | E17: =B17+C17-D17 -> 0
A18: 职工福利费 | B18: ='明细表J1-2 '!J19 -> 0 | C18: ='明细表J1-2 '!K19 -> 0 | D18: ='明细表J1-2 '!L19 -> 0 | E18: =B18+C18-D18 -> 0
A19: 社会保险费 | B19: =SUM(B20:B23) -> 0 | C19: =SUM(C20:C23) -> 0 | D19: =SUM(D20:D23) -> 0 | E19: =B19+C19-D19 -> 0
A20: 其中：医疗保险费 | B20: ='明细表J1-2 '!J21+'明细表J1-2 '!J22 -> 0 | C20: ='明细表J1-2 '!K21+'明细表J1-2 '!K22 -> 0 | D20: ='明细表J1-2 '!L21+'明细表J1-2 '!L22 -> 0 | E20: =B20+C20-D20 -> 0
A21: 工伤保险费 | B21: ='明细表J1-2 '!J23 -> 0 | C21: ='明细表J1-2 '!K23 -> 0 | D21: ='明细表J1-2 '!L23 -> 0 | E21: =B21+C21-D21 -> 0
A22: 生育保险费 | B22: ='明细表J1-2 '!J24 -> 0 | C22: ='明细表J1-2 '!K24 -> 0 | D22: ='明细表J1-2 '!L24 -> 0 | E22: =B22+C22-D22 -> 0
A23: 其他 | E23: =B23+C23-D23 -> 0
A24: 住房公积金 | B24: ='明细表J1-2 '!J25 -> 0 | C24: ='明细表J1-2 '!K25 -> 0 | D24: ='明细表J1-2 '!L25 -> 0 | E24: =B24+C24-D24 -> 0
A25: 工会经费和职工教育经费 | B25: ='明细表J1-2 '!J26+'明细表J1-2 '!J27 -> 0 | C25: ='明细表J1-2 '!K26+'明细表J1-2 '!K27 -> 0 | D25: ='明细表J1-2 '!L26+'明细表J1-2 '!L27 -> 0 | E25: =B25+C25-D25 -> 0
A26: 短期带薪缺勤 | B26: ='明细表J1-2 '!J28 -> 0 | C26: ='明细表J1-2 '!K28 -> 0 | D26: ='明细表J1-2 '!L28 -> 0 | E26: =B26+C26-D26 -> 0
A27: 短期利润分享计划 | B27: ='明细表J1-2 '!J29 -> 0 | C27: ='明细表J1-2 '!K29 -> 0 | D27: ='明细表J1-2 '!L29 -> 0 | E27: =B27+C27-D27 -> 0
A28: 其他短期薪酬 | B28: ='明细表J1-2 '!J30+'明细表J1-2 '!J31 -> 0 | C28: ='明细表J1-2 '!K30+'明细表J1-2 '!K31 -> 0 | D28: ='明细表J1-2 '!L30+'明细表J1-2 '!L31 -> 0 | E28: =B28+C28-D28 -> 0
A29: 合 计 | B29: =SUM(B17:B28)-SUM(B20:B23) -> 0 | C29: =SUM(C17:C28)-SUM(C20:C23) -> 0 | D29: =SUM(D17:D28)-SUM(D20:D23) -> 0 | E29: =SUM(E17:E28)-SUM(E20:E23) -> 0
A30: （3）设定提存计划列示
A31: 项 目 | B31: 期初余额 | C31: 本期增加 | D31: 本期减少 | E31: 期末余额
A32: 离职后福利 | B32: =SUM(B33:B36) -> 0 | C32: =SUM(C33:C36) -> 0 | D32: =SUM(D33:D36) -> 0 | E32: =B32+C32-D32 -> 0
A33: 其中：基本养老保险费 | B33: ='明细表J1-2 '!J38 -> 0 | C33: ='明细表J1-2 '!K38 -> 0 | D33: ='明细表J1-2 '!L38 -> 0 | E33: =B33+C33-D33 -> 0
A34: 失业保险费 | B34: ='明细表J1-2 '!J39 -> 0 | C34: ='明细表J1-2 '!K39 -> 0 | D34: ='明细表J1-2 '!L39 -> 0 | E34: =B34+C34-D34 -> 0
A35: 企业年金缴费 | B35: ='明细表J1-2 '!J40 -> 0 | C35: ='明细表J1-2 '!K40 -> 0 | D35: ='明细表J1-2 '!L40 -> 0 | E35: =B35+C35-D35 -> 0
A36: 其他 | B36: ='明细表J1-2 '!J41 -> 0 | C36: ='明细表J1-2 '!K41 -> 0 | D36: ='明细表J1-2 '!L41 -> 0 | E36: =B36+C36-D36 -> 0
A37: 其他长期职工福利（不适用的删除） | B37: ='明细表J1-2 '!J42 -> 0 | C37: ='明细表J1-2 '!K42 -> 0 | D37: ='明细表J1-2 '!L42 -> 0 | E37: =B37+C37-D37 -> 0
A38: 其中：xxx | B38: ='明细表J1-2 '!J43 -> 0 | C38: ='明细表J1-2 '!K43 -> 0 | D38: ='明细表J1-2 '!L43 -> 0 | E38: =B38+C38-D38 -> 0
A39: 其他 | B39: ='明细表J1-2 '!J44 -> 0 | C39: ='明细表J1-2 '!K44 -> 0 | D39: ='明细表J1-2 '!L44 -> 0 | E39: =B39+C39-D39 -> 0
A40: 合 计 | B40: =B32+B37 -> 0 | C40: =C32+C37 -> 0 | D40: =D32+D37 -> 0 | E40: =E32+E37 -> 0
A41: 说明：
A42: 1.企业本期为职工提供的各项非货币性福利的形式、金额及其计算依据。
A43: 2.企业应说明设立或参与的设定提存计划的性质、计算缴费金额的公式或依据。
A44: 3.存在设定受益计划的企业，应说明设定受益计划的特征及与之相关的风险、在财务报表中确认的金额及其变动、对未来现金流的影响、重大精算假设及有关敏感性分析等。设定受益计划情况详见附注八、47

Sheet 明细表J1-2 
A1: 致同会计师事务所
A2: 应付职工薪酬明细表
A3: =底稿目录!A2 -> 被审计单位： | F3: =底稿目录!A4 -> 编制人： | I3: =底稿目录!A5 -> 编制日期： | M3: 索引号： | N3: =底稿目录!F7 -> J1-2
A4: =底稿目录!A3 -> 截止日：202X年12月31日 | F4: =底稿目录!A6 -> 复核人： | I4: =底稿目录!A7 -> 复核日期： | M4: 页 次：
A5: 一、审计目标:
A6: 1.资产负债表中记录的应付职工薪酬是存在的，且已经记录在恰当的账户中
A7: 2.所有应记录的应付职工薪酬均已记录，所有应当包括在财务报表中的相关披露均已包括
A8: 3.应付职工薪酬以恰当的金额包括在财务报表中，与之相关的计价或分摊调整已恰当记录，相关披露已得到恰当计量和描述
A9: 二、审计过程：
A10: （1）短期薪酬
A11: 序号 | B11: 项目名称 | C11: 未审数 | G11: 期初调整 | H11: 账项调整 | J11: 审定数 | N11: 备注
C12: 期初数 | D12: 本期增加 | E12: 本期减少 | F12: 期末数 | G12: 账项调整 | H12: 本期增加 | I12: 本期减少 | J12: 期初数 | K12: 本期增加 | L12: 本期减少 | M12: 期末数
A13: 一 | B13: 工资、奖金、津贴和补贴 | C13: =SUM(C14:C18) -> 0 | D13: =SUM(D14:D18) -> 0 | E13: =SUM(E14:E18) -> 0 | F13: =C13+D13-E13 -> 0 | G13: =SUM(G14:G18) -> 0 | H13: =SUM(H14:H18) -> 0 | I13: =SUM(I14:I18) -> 0 | J13: =SUM(J14:J18) -> 0 | K13: =SUM(K14:K18) -> 0 | L13: =SUM(L14:L18) -> 0 | M13: =SUM(M14:M18) -> 0
B14: 其中：1.工资 | F14: =C14+D14-E14 -> 0 | J14: =C14+G14 -> 0 | K14: =D14+H14 -> 0 | L14: =E14+I14 -> 0 | M14: =J14+K14-L14 -> 0
B15: 2.奖金 | F15: =C15+D15-E15 -> 0 | J15: =C15+G15 -> 0 | K15: =D15+H15 -> 0 | L15: =E15+I15 -> 0 | M15: =J15+K15-L15 -> 0
B16: 3.津贴 | F16: =C16+D16-E16 -> 0 | J16: =C16+G16 -> 0 | K16: =D16+H16 -> 0 | L16: =E16+I16 -> 0 | M16: =J16+K16-L16 -> 0
B17: 4.补贴 | F17: =C17+D17-E17 -> 0 | J17: =C17+G17 -> 0 | K17: =D17+H17 -> 0 | L17: =E17+I17 -> 0 | M17: =J17+K17-L17 -> 0
B18: 5.其他 | F18: =C18+D18-E18 -> 0 | J18: =C18+G18 -> 0 | K18: =D18+H18 -> 0 | L18: =E18+I18 -> 0 | M18: =J18+K18-L18 -> 0
A19: 二 | B19: 职工福利费 | F19: =C19+D19-E19 -> 0 | J19: =C19+G19 -> 0 | K19: =D19+H19 -> 0 | L19: =E19+I19 -> 0 | M19: =J19+K19-L19 -> 0
A20: 三 | B20: 社会保险费 | C20: =SUM(C21:C24) -> 0 | D20: =SUM(D21:D24) -> 0 | E20: =SUM(E21:E24) -> 0 | F20: =C20+D20-E20 -> 0 | G20: =SUM(G21:G24) -> 0 | H20: =SUM(H21:H24) -> 0 | I20: =SUM(I21:I24) -> 0 | J20: =SUM(J21:J24) -> 0 | K20: =SUM(K21:K24) -> 0 | L20: =SUM(L21:L24) -> 0 | M20: =SUM(M21:M24) -> 0
B21: 1.基本医疗保险费 | F21: =C21+D21-E21 -> 0 | J21: =C21+G21 -> 0 | K21: =D21+H21 -> 0 | L21: =E21+I21 -> 0 | M21: =J21+K21-L21 -> 0
B22: 2.补充医疗保险费 | F22: =C22+D22-E22 -> 0 | J22: =C22+G22 -> 0 | K22: =D22+H22 -> 0 | L22: =E22+I22 -> 0 | M22: =J22+K22-L22 -> 0
B23: 3.工伤保险费 | F23: =C23+D23-E23 -> 0 | J23: =C23+G23 -> 0 | K23: =D23+H23 -> 0 | L23: =E23+I23 -> 0 | M23: =J23+K23-L23 -> 0
B24: 4.生育保险费 | F24: =C24+D24-E24 -> 0 | J24: =C24+G24 -> 0 | K24: =D24+H24 -> 0 | L24: =E24+I24 -> 0 | M24: =J24+K24-L24 -> 0
A25: 四 | B25: 住房公积金 | F25: =C25+D25-E25 -> 0 | J25: =C25+G25 -> 0 | K25: =D25+H25 -> 0 | L25: =E25+I25 -> 0 | M25: =J25+K25-L25 -> 0
A26: 五 | B26: 工会经费 | F26: =C26+D26-E26 -> 0 | J26: =C26+G26 -> 0 | K26: =D26+H26 -> 0 | L26: =E26+I26 -> 0 | M26: =J26+K26-L26 -> 0
A27: 六 | B27: 职工教育经费 | F27: =C27+D27-E27 -> 0 | J27: =C27+G27 -> 0 | K27: =D27+H27 -> 0 | L27: =E27+I27 -> 0 | M27: =J27+K27-L27 -> 0
A28: 七 | B28: 短期带薪缺勤 | F28: =C28+D28-E28 -> 0 | J28: =C28+G28 -> 0 | K28: =D28+H28 -> 0 | L28: =E28+I28 -> 0 | M28: =J28+K28-L28 -> 0
A29: 八 | B29: 短期利润分享计划 | F29: =C29+D29-E29 -> 0 | J29: =C29+G29 -> 0 | K29: =D29+H29 -> 0 | L29: =E29+I29 -> 0 | M29: =J29+K29-L29 -> 0
A30: 九 | B30: 非货币性福利 | F30: =C30+D30-E30 -> 0 | J30: =C30+G30 -> 0 | K30: =D30+H30 -> 0 | L30: =E30+I30 -> 0 | M30: =J30+K30-L30 -> 0
A31: 十 | B31: 其他短期薪酬 | F31: =C31+D31-E31 -> 0 | J31: =C31+G31 -> 0 | K31: =D31+H31 -> 0 | L31: =E31+I31 -> 0 | M31: =J31+K31-L31 -> 0
B32: 其中：以现金结算的股份支付 | F32: =C32+D32-E32 -> 0 | J32: =C32+G32 -> 0 | K32: =D32+H32 -> 0 | L32: =E32+I32 -> 0 | M32: =J32+K32-L32 -> 0
A33: 合计 | C33: =SUM(C13,C19:C20,C25:C31) -> 0 | D33: =SUM(D13,D19:D20,D25:D31) -> 0 | E33: =SUM(E13,E19:E20,E25:E31) -> 0 | F33: =SUM(F13,F19:F20,F25:F31) -> 0 | G33: =SUM(G13,G19:G20,G25:G31) -> 0 | H33: =SUM(H13,H19:H20,H25:H31) -> 0 | I33: =SUM(I13,I19:I20,I25:I31) -> 0 | J33: =SUM(J13,J19:J20,J25:J31) -> 0 | ... M33: =SUM(M13,M19:M20,M25:M31) -> 0
A34: （2）离职后福利中设定提存计划、其他长期福利中符合设定提存条件的负债
A35: 序号 | B35: 项目名称 | C35: 未审数 | G35: 期初调整 | H35: 账项调整 | J35: 审定数 | N35: 备注
C36: 期初数 | D36: 本期增加 | E36: 本期减少 | F36: 期末数 | G36: 账项调整 | H36: 本期增加 | I36: 本期减少 | J36: 期初数 | K36: 本期增加 | L36: 本期减少 | M36: 期末数
A37: 一 | B37: 离职后福利 | C37: =SUM(C38:C41) -> 0 | D37: =SUM(D38:D41) -> 0 | E37: =SUM(E38:E41) -> 0 | F37: =SUM(F38:F41) -> 0 | G37: =SUM(G38:G41) -> 0 | H37: =SUM(H38:H41) -> 0 | I37: =SUM(I38:I41) -> 0 | J37: =SUM(J38:J41) -> 0 | ... M37: =SUM(M38:M41) -> 0
B38: 其中：1．基本养老保险费 | F38: =C38+D38-E38 -> 0 | J38: =C38+G38 -> 0 | K38: =D38+H38 -> 0 | L38: =E38+I38 -> 0 | M38: =J38+K38-L38 -> 0
B39: 2．失业保险费 | F39: =C39+D39-E39 -> 0 | J39: =C39+G39 -> 0 | K39: =D39+H39 -> 0 | L39: =E39+I39 -> 0 | M39: =J39+K39-L39 -> 0
B40: 3．企业年金缴费 | F40: =C40+D40-E40 -> 0 | J40: =C40+G40 -> 0 | K40: =D40+H40 -> 0 | L40: =E40+I40 -> 0 | M40: =J40+K40-L40 -> 0
B41: 4．其他 | F41: =C41+D41-E41 -> 0 | J41: =C41+G41 -> 0 | K41: =D41+H41 -> 0 | L41: =E41+I41 -> 0 | M41: =J41+K41-L41 -> 0
A42: 二 | B42: 其他长期职工福利 | C42: =C43+C44 -> 0 | D42: =D43+D44 -> 0 | E42: =E43+E44 -> 0 | F42: =C42+D42-E42 -> 0 | G42: =G43+G44 -> 0 | H42: =H43+H44 -> 0 | I42: =I43+I44 -> 0 | J42: =J43+J44 -> 0 | K42: =K43+K44 -> 0 | L42: =L43+L44 -> 0 | M42: =M43+M44 -> 0
B43: 其中：1．xxx | F43: =C43+D43-E43 -> 0 | J43: =C43+G43 -> 0 | K43: =D43+H43 -> 0 | L43: =E43+I43 -> 0 | M43: =J43+K43-L43 -> 0
B44: 2．其他 | F44: =C44+D44-E44 -> 0 | J44: =C44+G44 -> 0 | K44: =D44+H44 -> 0 | L44: =E44+I44 -> 0 | M44: =J44+K44-L44 -> 0
F45: =C45+D45-E45 -> 0 | J45: =C45+G45 -> 0 | K45: =D45+H45 -> 0 | L45: =E45+I45 -> 0 | M45: =J45+K45-L45 -> 0
A46: 合计 | C46: =C42+C37 -> 0 | D46: =D42+D37 -> 0 | E46: =E42+E37 -> 0 | F46: =F42+F37 -> 0 | G46: =G42+G37 -> 0 | H46: =H42+H37 -> 0 | I46: =I42+I37 -> 0 | J46: =J42+J37 -> 0 | ... M46: =M42+M37 -> 0
A47: （3）一年内支付的辞退福利
A48: 序号 | B48: 项目名称 | C48: 未审数 | G48: 期初调整 | H48: 账项调整 | J48: 审定数 | N48: 备注
C49: 期初数 | D49: 本期增加 | E49: 本期减少 | F49: 期末数 | G49: 账项调整 | H49: 本期增加 | I49: 本期减少 | J49: 期初数 | K49: 本期增加 | L49: 本期减少 | M49: 期末数
A50: 1 | F50: =C50+D50-E50 -> 0 | J50: =C50+G50 -> 0 | K50: =D50+H50 -> 0 | L50: =E50+I50 -> 0 | M50: =J50+K50-L50 -> 0
F51: =C51+D51-E51 -> 0 | J51: =C51+G51 -> 0 | K51: =D51+H51 -> 0 | L51: =E51+I51 -> 0 | M51: =J51+K51-L51 -> 0
F52: =C52+D52-E52 -> 0 | J52: =C52+G52 -> 0 | K52: =D52+H52 -> 0 | L52: =E52+I52 -> 0 | M52: =J52+K52-L52 -> 0
A53: 合计 | C53: =SUM(C50:C52) -> 0 | D53: =SUM(D50:D52) -> 0 | E53: =SUM(E50:E52) -> 0 | F53: =SUM(F50:F52) -> 0 | G53: =SUM(G50:G52) -> 0 | H53: =SUM(H50:H52) -> 0 | I53: =SUM(I50:I52) -> 0 | J53: =SUM(J50:J52) -> 0 | ... M53: =SUM(M50:M52) -> 0
A54: 三、审计说明：
A56: 四、审计结论：
A59: 提示1：
A60: 1..审计说明可以概述：（1）程序的测试情况、结果；（2）拟调整事项及其调整分录、未调整事项及其影响，审计范围受到限制情况及其影响。
A61: 2.审计结论可参考：A、未见异常。 B、除上述重大不符事项应当作为调整事项予以调整外，其余未见异常。 C、由于存在以下重大未调整事项（或审计范围受到限制无法获取充分、适当证据），不可确认。
A62: 提示2：对于本期计提和支付的重大奖金、佣金、利润分享福利及其他易于导致错报的职工薪酬项目应当：
A63: （1）了解相关计提政策、审批流程的设计与执行有效性；（2）获取相关项目的支持性文件；（3）验证计提依据是否充分、合理，是否达到计提和付款条件；（4）核对计算的准确性和完整性；（5）对异常波动、异常支付对象等进行分析；（6）对于尚未支付的项目，确定该项负债是否被正确计算； （7）执行截止测试，追踪至后续付款。
A64: 提示3：关注带薪休假
A65: 1.确定所有员工均均已包含； 2.确定企业确认带薪休假的方法是否正确； 3.关注小时工资费用率是否合理，并与相关的记录核对
A66: 提示3：对于设定提存计划的缴存款关注
A67: 结合计提比例检查，确定代扣员工缴存款的总额是否合理，是否按时缴纳

Sheet 调整分录汇总表J1-3
A1: 致同会计师事务所
A2: 应付职工薪酬调整分录汇总表
A3: =底稿目录!A2 -> 被审计单位： | D3: =底稿目录!A4 -> 编制人： | G3: =底稿目录!A5 -> 编制日期： | I3: 索引号： | J3: =底稿目录!F8 -> J1-3
A4: =底稿目录!A3 -> 截止日：202X年12月31日 | D4: =底稿目录!A6 -> 复核人： | G4: =底稿目录!A7 -> 复核日期： | I4: 页 次：
A5: 调整事项说明 | B5: 类别（报表调整/账项调整/其他） | C5: 报表项目 | D5: 科目名称 | E5: 附注项目 | F5: …… | G5: 借方调整金额 | H5: 贷方调整金额 | I5: 索引 | J5: 备注
A22: 【注：本底稿适用于调整分录较多、较复杂的项目，且仅列示与本报表项目相关的审计调整。项目组可根据项目实际情况选择是否使用该底稿。】

Sheet 月度分析表J1-4
A1: 致同会计师事务所
A2: 应付职工薪酬实质性分析表
A3: =底稿目录!A2 -> 被审计单位： | F3: =底稿目录!A4 -> 编制人： | J3: =底稿目录!A5 -> 编制日期： | N3: 索引号： | O3: =底稿目录!F9 -> J1-4
A4: =底稿目录!A3 -> 截止日：202X年12月31日 | F4: =底稿目录!A6 -> 复核人： | J4: =底稿目录!A7 -> 复核日期： | N4: 页 次：
A5: 一、审计目标:
A6: 1.资产负债表中记录的应付职工薪酬是存在的，且已经记录在恰当的账户中
A7: 2.所有应记录的应付职工薪酬均已记录，所有应当包括在财务报表中的相关披露均已包括
A8: 3.应付职工薪酬以恰当的金额包括在财务报表中，与之相关的计价或分摊调整已恰当记录，相关披露已得到恰当计量和描述
A9: 二、审计过程：
A10: 应付职工薪酬——工资、奖金、津贴和补贴计提分析
A11: 部门/人员类型 | B11: 1月 | C11: 2月 | D11: 3月 | E11: 4月 | F11: 5月 | G11: 6月 | H11: 7月 | I11: 8月 | J11: 9月 | K11: 10月 | L11: 11月 | M11: 12月 | N11: 合计 | O11: 占比
A12: 本期计提工资 | B12: =SUM(B13:B16) -> 0 | C12: =SUM(C13:C16) -> 0 | D12: =SUM(D13:D16) -> 0 | E12: =SUM(E13:E16) -> 0 | F12: =SUM(F13:F16) -> 0 | G12: =SUM(G13:G16) -> 0 | H12: =SUM(H13:H16) -> 0 | I12: =SUM(I13:I16) -> 0 | ... N12: =SUM(N13:N16) -> 0
A13: A部门 | N13: =SUM(B13:M13) -> 0 | O13: =IF(N13=0,,N13/$N$12) -> 0
A14: B部门 | N14: =SUM(B14:M14) -> 0 | O14: =IF(N14=0,,N14/$N$12) -> 0
A15: C部门 | N15: =SUM(B15:M15) -> 0 | O15: =IF(N15=0,,N15/$N$12) -> 0
A16: …… | N16: =SUM(B16:M16) -> 0 | O16: =IF(N16=0,,N16/$N$12) -> 0
A17: 本期员工数量 | B17: =SUM(B18:B21) -> 0 | C17: =SUM(C18:C21) -> 0 | D17: =SUM(D18:D21) -> 0 | E17: =SUM(E18:E21) -> 0 | F17: =SUM(F18:F21) -> 0 | G17: =SUM(G18:G21) -> 0 | H17: =SUM(H18:H21) -> 0 | I17: =SUM(I18:I21) -> 0 | ... N17: =SUM(N18:N21) -> 0
A18: A部门 | N18: =SUM(B18:M18) -> 0 | O18: =IF(N18=0,,N18/$N$17) -> 0
A19: B部门 | N19: =SUM(B19:M19) -> 0 | O19: =IF(N19=0,,N19/$N$17) -> 0
A20: C部门 | N20: =SUM(B20:M20) -> 0 | O20: =IF(N20=0,,N20/$N$17) -> 0
A21: …… | N21: =SUM(B21:M21) -> 0 | O21: =IF(N21=0,,N21/$N$17) -> 0
A22: 本期人均工资 | B22: =B12/B17 -> #DIV/0! | C22: =C12/C17 -> #DIV/0! | D22: =D12/D17 -> #DIV/0! | E22: =E12/E17 -> #DIV/0! | F22: =F12/F17 -> #DIV/0! | G22: =G12/G17 -> #DIV/0! | H22: =H12/H17 -> #DIV/0! | I22: =I12/I17 -> #DIV/0! | ... N22: =N12/N17 -> #DIV/0!
A23: A部门 | B23: =B13/B18 -> #DIV/0! | C23: =C13/C18 -> #DIV/0! | D23: =D13/D18 -> #DIV/0! | E23: =E13/E18 -> #DIV/0! | F23: =F13/F18 -> #DIV/0! | G23: =G13/G18 -> #DIV/0! | H23: =H13/H18 -> #DIV/0! | I23: =I13/I18 -> #DIV/0! | ... N23: =N13/N18 -> #DIV/0!
A24: B部门 | B24: =B14/B19 -> #DIV/0! | C24: =C14/C19 -> #DIV/0! | D24: =D14/D19 -> #DIV/0! | E24: =E14/E19 -> #DIV/0! | F24: =F14/F19 -> #DIV/0! | G24: =G14/G19 -> #DIV/0! | H24: =H14/H19 -> #DIV/0! | I24: =I14/I19 -> #DIV/0! | ... N24: =N14/N19 -> #DIV/0!
A25: C部门 | B25: =B15/B20 -> #DIV/0! | C25: =C15/C20 -> #DIV/0! | D25: =D15/D20 -> #DIV/0! | E25: =E15/E20 -> #DIV/0! | F25: =F15/F20 -> #DIV/0! | G25: =G15/G20 -> #DIV/0! | H25: =H15/H20 -> #DIV/0! | I25: =I15/I20 -> #DIV/0! | ... N25: =N15/N20 -> #DIV/0!
A26: …… | B26: =B16/B21 -> #DIV/0! | C26: =C16/C21 -> #DIV/0! | D26: =D16/D21 -> #DIV/0! | E26: =E16/E21 -> #DIV/0! | F26: =F16/F21 -> #DIV/0! | G26: =G16/G21 -> #DIV/0! | H26: =H16/H21 -> #DIV/0! | I26: =I16/I21 -> #DIV/0! | ... N26: =N16/N21 -> #DIV/0!
A27: 上期计提工资 | B27: =SUM(B28:B31) -> 0 | C27: =SUM(C28:C31) -> 0 | D27: =SUM(D28:D31) -> 0 | E27: =SUM(E28:E31) -> 0 | F27: =SUM(F28:F31) -> 0 | G27: =SUM(G28:G31) -> 0 | H27: =SUM(H28:H31) -> 0 | I27: =SUM(I28:I31) -> 0 | ... N27: =SUM(N28:N31) -> 0
A28: A部门 | N28: =SUM(B28:M28) -> 0 | O28: =IF(N28=0,,N28/$N$27) -> 0
A29: B部门 | N29: =SUM(B29:M29) -> 0 | O29: =IF(N29=0,,N29/$N$27) -> 0
A30: C部门 | N30: =SUM(B30:M30) -> 0 | O30: =IF(N30=0,,N30/$N$27) -> 0
A31: …… | N31: =SUM(B31:M31) -> 0 | O31: =IF(N31=0,,N31/$N$27) -> 0
A32: 上期员工数量 | B32: =SUM(B33:B36) -> 0 | C32: =SUM(C33:C36) -> 0 | D32: =SUM(D33:D36) -> 0 | E32: =SUM(E33:E36) -> 0 | F32: =SUM(F33:F36) -> 0 | G32: =SUM(G33:G36) -> 0 | H32: =SUM(H33:H36) -> 0 | I32: =SUM(I33:I36) -> 0 | ... N32: =SUM(N33:N36) -> 0
A33: A部门 | N33: =SUM(B33:M33) -> 0 | O33: =IF(N33=0,,N33/$N$32) -> 0
A34: B部门 | N34: =SUM(B34:M34) -> 0 | O34: =IF(N34=0,,N34/$N$32) -> 0
A35: C部门 | N35: =SUM(B35:M35) -> 0 | O35: =IF(N35=0,,N35/$N$32) -> 0
A36: …… | N36: =SUM(B36:M36) -> 0 | O36: =IF(N36=0,,N36/$N$32) -> 0
A37: 上期人均工资 | B37: =B27/B32 -> #DIV/0! | C37: =C27/C32 -> #DIV/0! | D37: =D27/D32 -> #DIV/0! | E37: =E27/E32 -> #DIV/0! | F37: =F27/F32 -> #DIV/0! | G37: =G27/G32 -> #DIV/0! | H37: =H27/H32 -> #DIV/0! | I37: =I27/I32 -> #DIV/0! | ... N37: =N27/N32 -> #DIV/0!
A38: A部门 | B38: =B28/B33 -> #DIV/0! | C38: =C28/C33 -> #DIV/0! | D38: =D28/D33 -> #DIV/0! | E38: =E28/E33 -> #DIV/0! | F38: =F28/F33 -> #DIV/0! | G38: =G28/G33 -> #DIV/0! | H38: =H28/H33 -> #DIV/0! | I38: =I28/I33 -> #DIV/0! | ... N38: =N28/N33 -> #DIV/0!
A39: B部门 | B39: =B29/B34 -> #DIV/0! | C39: =C29/C34 -> #DIV/0! | D39: =D29/D34 -> #DIV/0! | E39: =E29/E34 -> #DIV/0! | F39: =F29/F34 -> #DIV/0! | G39: =G29/G34 -> #DIV/0! | H39: =H29/H34 -> #DIV/0! | I39: =I29/I34 -> #DIV/0! | ... N39: =N29/N34 -> #DIV/0!
A40: C部门 | B40: =B30/B35 -> #DIV/0! | C40: =C30/C35 -> #DIV/0! | D40: =D30/D35 -> #DIV/0! | E40: =E30/E35 -> #DIV/0! | F40: =F30/F35 -> #DIV/0! | G40: =G30/G35 -> #DIV/0! | H40: =H30/H35 -> #DIV/0! | I40: =I30/I35 -> #DIV/0! | ... N40: =N30/N35 -> #DIV/0!
A41: …… | B41: =B31/B36 -> #DIV/0! | C41: =C31/C36 -> #DIV/0! | D41: =D31/D36 -> #DIV/0! | E41: =E31/E36 -> #DIV/0! | F41: =F31/F36 -> #DIV/0! | G41: =G31/G36 -> #DIV/0! | H41: =H31/H36 -> #DIV/0! | I41: =I31/I36 -> #DIV/0! | ... N41: =N31/N36 -> #DIV/0!
A42: 人均工资变动率 | B42: =(B22-B37)/B37 -> #DIV/0! | C42: =(C22-C37)/C37 -> #DIV/0! | D42: =(D22-D37)/D37 -> #DIV/0! | E42: =(E22-E37)/E37 -> #DIV/0! | F42: =(F22-F37)/F37 -> #DIV/0! | G42: =(G22-G37)/G37 -> #DIV/0! | H42: =(H22-H37)/H37 -> #DIV/0! | I42: =(I22-I37)/I37 -> #DIV/0! | ... N42: =(N22-N37)/N37 -> #DIV/0!
A43: A部门 | B43: =(B23-B38)/B38 -> #DIV/0! | C43: =(C23-C38)/C38 -> #DIV/0! | D43: =(D23-D38)/D38 -> #DIV/0! | E43: =(E23-E38)/E38 -> #DIV/0! | F43: =(F23-F38)/F38 -> #DIV/0! | G43: =(G23-G38)/G38 -> #DIV/0! | H43: =(H23-H38)/H38 -> #DIV/0! | I43: =(I23-I38)/I38 -> #DIV/0! | ... N43: =(N23-N38)/N38 -> #DIV/0!
A44: B部门 | B44: =(B24-B39)/B39 -> #DIV/0! | C44: =(C24-C39)/C39 -> #DIV/0! | D44: =(D24-D39)/D39 -> #DIV/0! | E44: =(E24-E39)/E39 -> #DIV/0! | F44: =(F24-F39)/F39 -> #DIV/0! | G44: =(G24-G39)/G39 -> #DIV/0! | H44: =(H24-H39)/H39 -> #DIV/0! | I44: =(I24-I39)/I39 -> #DIV/0! | ... N44: =(N24-N39)/N39 -> #DIV/0!
A45: C部门 | B45: =(B25-B40)/B40 -> #DIV/0! | C45: =(C25-C40)/C40 -> #DIV/0! | D45: =(D25-D40)/D40 -> #DIV/0! | E45: =(E25-E40)/E40 -> #DIV/0! | F45: =(F25-F40)/F40 -> #DIV/0! | G45: =(G25-G40)/G40 -> #DIV/0! | H45: =(H25-H40)/H40 -> #DIV/0! | I45: =(I25-I40)/I40 -> #DIV/0! | ... N45: =(N25-N40)/N40 -> #DIV/0!
A46: …… | B46: =(B26-B41)/B41 -> #DIV/0! | C46: =(C26-C41)/C41 -> #DIV/0! | D46: =(D26-D41)/D41 -> #DIV/0! | E46: =(E26-E41)/E41 -> #DIV/0! | F46: =(F26-F41)/F41 -> #DIV/0! | G46: =(G26-G41)/G41 -> #DIV/0! | H46: =(H26-H41)/H41 -> #DIV/0! | I46: =(I26-I41)/I41 -> #DIV/0! | ... N46: =(N26-N41)/N41 -> #DIV/0!
A47: 本期各月计提占比 | B47: =B12/$N$12 -> #DIV/0! | C47: =C12/$N$12 -> #DIV/0! | D47: =D12/$N$12 -> #DIV/0! | E47: =E12/$N$12 -> #DIV/0! | F47: =F12/$N$12 -> #DIV/0! | G47: =G12/$N$12 -> #DIV/0! | H47: =H12/$N$12 -> #DIV/0! | I47: =I12/$N$12 -> #DIV/0! | ... N47: =N12/$N$12 -> #DIV/0!
A48: 本期实际发放额 | N48: =SUM(B48:M48) -> 0
A49: 本期留存 | B49: =B12-B48 -> 0 | C49: =C12-C48 -> 0 | D49: =D12-D48 -> 0 | E49: =E12-E48 -> 0 | F49: =F12-F48 -> 0 | G49: =G12-G48 -> 0 | H49: =H12-H48 -> 0 | I49: =I12-I48 -> 0 | ... N49: =N12-N48 -> 0
A50: 上年同期留存
A51: 三、审计说明：
A54: 四、审计结论：
A58: 提示：
A59: 1.关注各月之间波动有无异常，如果异常降低，考虑是否存在其他方（如关联方）代付工资的情况。
A60: 2.关注实际薪酬发放日与资产负债表日的间隔时间，考虑本期留存金额是否合理。

Sheet 与同行业对比分析表J1-5
A1: 致同会计师事务所
A2: 应付职工薪酬同行业对比分析表
A3: =底稿目录!A2 -> 被审计单位： | D3: =底稿目录!A4 -> 编制人： | H3: =底稿目录!A5 -> 编制日期： | K3: 索引号： | L3: =底稿目录!F10 -> J1-5
A4: =底稿目录!A3 -> 截止日：202X年12月31日 | D4: =底稿目录!A6 -> 复核人： | H4: =底稿目录!A7 -> 复核日期： | K4: 页 次：
A5: 一、审计目标:
A6: 1.资产负债表中记录的应付职工薪酬是存在的，且已经记录在恰当的账户中
A7: 2.所有应记录的应付职工薪酬均已记录，所有应当包括在财务报表中的相关披露均已包括
A8: 3.应付职工薪酬以恰当的金额包括在财务报表中，与之相关的计价或分摊调整已恰当记录，相关披露已得到恰当计量和描述
A9: 二、审计过程：
A10: 1.分析企业报告期人均工资（分部门、地区或产品线）是否与同地区同行业的水平一致，并与招股书等相关数据核对 | B10: 针对IPO企业，分析企业报告期人均工资（分部门、地区或产品线）是否与同地区同行业的水平一致，并与招股书相关数据核对
A11: 2.分析人员构成及其变化是否合理、人数是否与企业规模一致 | B11: 针对IPO企业，分析人员构成及其变化是否合理、人数是否与企业规模一致
A12: 3.如果存在劳务外包，了解公司劳务外包情况，关注劳务公司的经营合法合规性；劳务公司是否专门或主要为发行人服务，如存在主要为发行人服务的情形的，应关注其合理性及必要性、关联关系的认定及披露是否真实、准确、完整。
A13: 部门/地区/产品线 | B13: 本期计提数 | E13: 上期计提数 | H13: 计提工资总额波动比例 | I13: 人均数波动比例 | J13: 行业人均工资 | K13: 与行业人均工资比较 | L13: 异常波动分析或底稿索引
B14: 人数 | C14: 总额 | D14: 人均数 | E14: 人数 | F14: 总额 | G14: 人均数
A15: 生产人员 | D15: =IF(B15=0,0,C15/B15) -> 0 | G15: =IF(E15=0,0,F15/E15) -> 0 | H15: =IF(AND(F15=0,C15=0),0,IF(AND(F15=0,C15>0),1,(C15-F15)/F15)) -> 0 | I15: =IF(AND(G15=0,D15=0),0,IF(AND(G15=0,D15>0),1,(D15-G15)/G15)) -> 0 | K15: =IF(AND(J15=0,D15=0),0,IF(AND(J15=0,D15>0),1,(D15-J15)/J15)) -> 0
A16: 管理人员 | D16: =IF(B16=0,0,C16/B16) -> 0 | G16: =IF(E16=0,0,F16/E16) -> 0 | H16: =IF(AND(F16=0,C16=0),0,IF(AND(F16=0,C16>0),1,(C16-F16)/F16)) -> 0 | I16: =IF(AND(G16=0,D16=0),0,IF(AND(G16=0,D16>0),1,(D16-G16)/G16)) -> 0 | K16: =IF(AND(J16=0,D16=0),0,IF(AND(J16=0,D16>0),1,(D16-J16)/J16)) -> 0
A17: 销售人员 | D17: =IF(B17=0,0,C17/B17) -> 0 | G17: =IF(E17=0,0,F17/E17) -> 0 | H17: =IF(AND(F17=0,C17=0),0,IF(AND(F17=0,C17>0),1,(C17-F17)/F17)) -> 0 | I17: =IF(AND(G17=0,D17=0),0,IF(AND(G17=0,D17>0),1,(D17-G17)/G17)) -> 0 | K17: =IF(AND(J17=0,D17=0),0,IF(AND(J17=0,D17>0),1,(D17-J17)/J17)) -> 0
D18: =IF(B18=0,0,C18/B18) -> 0 | G18: =IF(E18=0,0,F18/E18) -> 0 | H18: =IF(AND(F18=0,C18=0),0,IF(AND(F18=0,C18>0),1,(C18-F18)/F18)) -> 0 | I18: =IF(AND(G18=0,D18=0),0,IF(AND(G18=0,D18>0),1,(D18-G18)/G18)) -> 0 | K18: =IF(AND(J18=0,D18=0),0,IF(AND(J18=0,D18>0),1,(D18-J18)/J18)) -> 0
D19: =IF(B19=0,0,C19/B19) -> 0 | G19: =IF(E19=0,0,F19/E19) -> 0 | H19: =IF(AND(F19=0,C19=0),0,IF(AND(F19=0,C19>0),1,(C19-F19)/F19)) -> 0 | I19: =IF(AND(G19=0,D19=0),0,IF(AND(G19=0,D19>0),1,(D19-G19)/G19)) -> 0 | K19: =IF(AND(J19=0,D19=0),0,IF(AND(J19=0,D19>0),1,(D19-J19)/J19)) -> 0
D20: =IF(B20=0,0,C20/B20) -> 0 | G20: =IF(E20=0,0,F20/E20) -> 0 | H20: =IF(AND(F20=0,C20=0),0,IF(AND(F20=0,C20>0),1,(C20-F20)/F20)) -> 0 | I20: =IF(AND(G20=0,D20=0),0,IF(AND(G20=0,D20>0),1,(D20-G20)/G20)) -> 0 | K20: =IF(AND(J20=0,D20=0),0,IF(AND(J20=0,D20>0),1,(D20-J20)/J20)) -> 0
D21: =IF(B21=0,0,C21/B21) -> 0 | G21: =IF(E21=0,0,F21/E21) -> 0 | H21: =IF(AND(F21=0,C21=0),0,IF(AND(F21=0,C21>0),1,(C21-F21)/F21)) -> 0 | I21: =IF(AND(G21=0,D21=0),0,IF(AND(G21=0,D21>0),1,(D21-G21)/G21)) -> 0 | K21: =IF(AND(J21=0,D21=0),0,IF(AND(J21=0,D21>0),1,(D21-J21)/J21)) -> 0
D22: =IF(B22=0,0,C22/B22) -> 0 | G22: =IF(E22=0,0,F22/E22) -> 0 | H22: =IF(AND(F22=0,C22=0),0,IF(AND(F22=0,C22>0),1,(C22-F22)/F22)) -> 0 | I22: =IF(AND(G22=0,D22=0),0,IF(AND(G22=0,D22>0),1,(D22-G22)/G22)) -> 0 | K22: =IF(AND(J22=0,D22=0),0,IF(AND(J22=0,D22>0),1,(D22-J22)/J22)) -> 0
D23: =IF(B23=0,0,C23/B23) -> 0 | G23: =IF(E23=0,0,F23/E23) -> 0 | H23: =IF(AND(F23=0,C23=0),0,IF(AND(F23=0,C23>0),1,(C23-F23)/F23)) -> 0 | I23: =IF(AND(G23=0,D23=0),0,IF(AND(G23=0,D23>0),1,(D23-G23)/G23)) -> 0 | K23: =IF(AND(J23=0,D23=0),0,IF(AND(J23=0,D23>0),1,(D23-J23)/J23)) -> 0
D24: =IF(B24=0,0,C24/B24) -> 0 | G24: =IF(E24=0,0,F24/E24) -> 0 | H24: =IF(AND(F24=0,C24=0),0,IF(AND(F24=0,C24>0),1,(C24-F24)/F24)) -> 0 | I24: =IF(AND(G24=0,D24=0),0,IF(AND(G24=0,D24>0),1,(D24-G24)/G24)) -> 0 | K24: =IF(AND(J24=0,D24=0),0,IF(AND(J24=0,D24>0),1,(D24-J24)/J24)) -> 0
D25: =IF(B25=0,0,C25/B25) -> 0 | G25: =IF(E25=0,0,F25/E25) -> 0 | H25: =IF(AND(F25=0,C25=0),0,IF(AND(F25=0,C25>0),1,(C25-F25)/F25)) -> 0 | I25: =IF(AND(G25=0,D25=0),0,IF(AND(G25=0,D25>0),1,(D25-G25)/G25)) -> 0 | K25: =IF(AND(J25=0,D25=0),0,IF(AND(J25=0,D25>0),1,(D25-J25)/J25)) -> 0
A26: 合计 | B26: =SUM(B15:B25) -> 0 | C26: =SUM(C15:C25) -> 0 | D26: =IF(B26=0,0,C26/B26) -> 0 | E26: =SUM(E15:E25) -> 0 | F26: =SUM(F15:F25) -> 0 | G26: =IF(E26=0,0,F26/E26) -> 0 | H26: =IF(AND(F26=0,C26=0),0,IF(AND(F26=0,C26>0),1,(C26-F26)/F26)) -> 0 | I26: =IF(AND(G26=0,D26=0),0,IF(AND(G26=0,D26>0),1,(D26-G26)/G26)) -> 0 | K26: =IF(AND(J26=0,D26=0),0,IF(AND(J26=0,D26>0),1,(D26-J26)/J26)) -> 0
A27: 复核上交社会保险的人数与公司实际发放工资的人数是否一致：
A28: 公司发放工资人数 | D28: 公司实际上交社会保险的人数
A29: 类 别 | C29: 人 数 | D29: 类 别 | F29: 人 数
A30: 公司发放工资人数 | D30: 上交城镇保险人数
D31: 上交小城镇保险人数
D32: 上交农业保险人数
A33: 扣除不上交社保费人数（注：在合法试用期内的职工） | D33: 上交综合保险人数
A34: 小 计 | C34: =C30-C33 -> 0 | D34: 小 计 | F34: =SUM(F30:F33) -> 0
A35: 差 异 | D35: =C34-F34 -> 0
A37: 同行业比较分析
A38: 单位名称 | B38: 生产人数 | C38: 人工成本（生产人员） | D38: 主营业务成本中人工成本 | E38: 收入 | F38: 总成本 | G38: 主营业务成本 | H38: 指标
C39: 人工成本 | E39: 收入 | F39: 成本 | G39: 成本 | H39: 人均产值（收入/人数） | I39: 总成本中人工成本占比 | J39: 主营业务成本总人工成本占比
A40: A | H40: =E40/B40 -> #DIV/0! | I40: =C40/F40 -> #DIV/0! | J40: =D40/G40 -> #DIV/0!
A41: B | H41: =E41/B41 -> #DIV/0! | I41: =C41/F41 -> #DIV/0! | J41: =D41/G41 -> #DIV/0!
A42: C | H42: =E42/B42 -> #DIV/0! | I42: =C42/F42 -> #DIV/0! | J42: =D42/G42 -> #DIV/0!
A43: D | H43: =E43/B43 -> #DIV/0! | I43: =C43/F43 -> #DIV/0! | J43: =D43/G43 -> #DIV/0!
A44: 同行业平均数据 | H44: =AVERAGE(H40:H43) -> #DIV/0! | I44: =AVERAGE(I40:I43) -> #DIV/0! | J44: =AVERAGE(J40:J43) -> #DIV/0!
A45: 被审计单位
A46: 差异 | H46: =H44-H45 -> #DIV/0! | I46: =I44-I45 -> #DIV/0! | J46: =J44-J45 -> #DIV/0!
A48: 单位名称 | B48: 销售人数 | C48: 人工成本（销售人员） | D48: 销售人员平均薪酬 | E48: 管理人数 | F48: 人工成本（管理人员） | G48: 销售人员平均薪酬 | H48: 研发人数 | I48: 人工成本（研发人员） | J48: 研发人员平均薪酬
C49: 人工成本 | F49: 人工成本 | I49: 人工成本
A50: A | D50: =C50/B50 -> #DIV/0! | G50: =F50/E50 -> #DIV/0! | J50: =I50/H50 -> #DIV/0!
A51: B | D51: =C51/B51 -> #DIV/0! | G51: =F51/E51 -> #DIV/0! | J51: =I51/H51 -> #DIV/0!
A52: C | D52: =C52/B52 -> #DIV/0! | G52: =F52/E52 -> #DIV/0! | J52: =I52/H52 -> #DIV/0!
A53: D | D53: =C53/B53 -> #DIV/0! | G53: =F53/E53 -> #DIV/0! | J53: =I53/H53 -> #DIV/0!
A54: 同行业平均数据 | D54: =AVERAGE(D50:D53) -> #DIV/0! | G54: =AVERAGE(G50:G53) -> #DIV/0! | J54: =AVERAGE(J50:J53) -> #DIV/0!
A55: 被审计单位
A56: 差异 | D56: =D54-D55 -> #DIV/0! | G56: =G54-G55 -> #DIV/0! | J56: =J54-J55 -> #DIV/0!
A57: 三、审计说明：
A59: 四、审计结论：
A63: 提示1：《首发业务问答二》问题22、首发企业劳务外包情形，中介机构需重点关注哪些方面内容？
A64: 答：部分首发企业存在将较多的劳务活动交由专门劳务外包公司实施的情况的。中介机构应当充分关注以下方面：
A65: 该等劳务公司的经营合法合规性，比如是否具备必要的专业资质，是否遵循国家环保、税务、劳动保障等法律法规的相关规定；
A66: 劳务公司是否专门或主要为发行人服务，如存在主要为发行人服务的情形的，应关注其合理性及必要性、关联关系的认定及披露是否真实、准确、完整。中介机构对于该类情形应当从实质重于形式角度按关联方的相关要求进行核查，并特别考虑其按规范运行的经营成果对发行人财务数据的影响，以及对发行人是否符合发行条件的影响；
A67: 劳务公司的构成及变动情况，劳务外包合同的主要内容，劳务数量及费用变动是否与发行人经营业绩相匹配，劳务费用定价是否公允，是否存在跨期核算情形。
A68: 提示2：
A69: 特别关注劳务派遣是否符合规定、是否滥用以规避一线工人
A70: 如果公司薪酬明显低于同行业，考虑是否存在其他方（如关联方）代付工资的情况。

Sheet 计提情况检查表J1-6
A1: 致同会计师事务所
A2: 应付职工薪酬计提情况检查表
A3: =底稿目录!A2 -> 被审计单位： | D3: =底稿目录!A4 -> 编制人： | G3: =底稿目录!A5 -> 编制日期： | J3: 索引号： | K3: =底稿目录!F11 -> J1-6
A4: =底稿目录!A3 -> 截止日：202X年12月31日 | D4: =底稿目录!A6 -> 复核人： | G4: =底稿目录!A7 -> 复核日期： | J4: 页 次：
A5: 一、审计目标:
A6: 1.资产负债表中记录的应付职工薪酬是存在的，且已经记录在恰当的账户中
A7: 2.所有应记录的应付职工薪酬均已记录，所有应当包括在财务报表中的相关披露均已包括
A8: 3.应付职工薪酬以恰当的金额包括在财务报表中，与之相关的计价或分摊调整已恰当记录，相关披露已得到恰当计量和描述
A9: 二、审计过程：
A10: 1.了解企业应付职工薪酬各项目计提政策，对按照职工提供服务情况和工资标准计算的职工薪酬（如工资），获取工资计算表，将工资标准与有关规定进行核对，选取样本进行测试。
A11: 2.对国家规定了计提基础和计提比例的职工薪酬（如失业保险金、工伤保险金等），检查是否按照规定的计提基础和比例计提。
A12: 3.分析设定提存计划计提缴存情况，检查是否按照规定的计提基础和比例计提。
A13: 4.对被审计单位按照历史经验数据和当期计划预计的职工薪酬（如职工福利费），获取管理层进行估计的资料，分析其合理性。
A14: （1）短期薪酬
A15: 项目 | C15: 计提基数 | F15: 计提比例 | G15: 应提金额 | H15: 实际计提数 | I15: 差异 | J15: 差异原因 | K15: 结论
C16: 名称 | D16: 金额 | E16: 索引
A17: 一、工资、奖金、津贴和补贴 | G17: =ROUND(D17*F17,2) -> 0 | I17: =G17-H17 -> 0
A18: 其中：1．工资 | G18: =ROUND(D18*F18,2) -> 0 | I18: =G18-H18 -> 0
A19: 2．奖金 | G19: =ROUND(D19*F19,2) -> 0 | I19: =G19-H19 -> 0
A20: 3．津贴 | G20: =ROUND(D20*F20,2) -> 0 | I20: =G20-H20 -> 0
A21: 4．补贴 | G21: =ROUND(D21*F21,2) -> 0 | I21: =G21-H21 -> 0
A22: 二、职工福利费 | G22: =ROUND(D22*F22,2) -> 0 | I22: =G22-H22 -> 0
A23: 三、社会保险费 | G23: =ROUND(D23*F23,2) -> 0 | I23: =G23-H23 -> 0
A24: 其中：1．医疗保险费 | G24: =ROUND(D24*F24,2) -> 0 | I24: =G24-H24 -> 0
A25: 2．年金缴费 | G25: =ROUND(D25*F25,2) -> 0 | I25: =G25-H25 -> 0
A26: 3．工伤保险费 | G26: =ROUND(D26*F26,2) -> 0 | I26: =G26-H26 -> 0
A27: 4．生育保险费 | G27: =ROUND(D27*F27,2) -> 0 | I27: =G27-H27 -> 0
A28: 四、住房公积金 | G28: =ROUND(D28*F28,2) -> 0 | I28: =G28-H28 -> 0
... A35: 十一、其他 | G35: =ROUND(D35*F35,2) -> 0 | I35: =G35-H35 -> 0
G36: =ROUND(D36*F36,2) -> 0 | I36: =G36-H36 -> 0
A37: （2）离职后福利中设定提存计划、其他长期福利中符合设定提存条件的负债
A38: 项目 | C38: 计提基数 | F38: 计提比例 | G38: 应提金额 | H38: 实际计提数 | I38: 差异 | J38: 差异原因 | K38: 结论
C39: 名称 | D39: 金额 | E39: 索引
A40: 一、离职后福利 | G40: =ROUND(D40*F40,2) -> 0 | I40: =G40-H40 -> 0
A41: 其中：1．基本养老保险费 | G41: =ROUND(D41*F41,2) -> 0 | I41: =G41-H41 -> 0
A42: 2．失业保险费 | G42: =ROUND(D42*F42,2) -> 0 | I42: =G42-H42 -> 0
A43: 3．企业年金缴费 | G43: =ROUND(D43*F43,2) -> 0 | I43: =G43-H43 -> 0
A44: 4．其他 | G44: =ROUND(D44*F44,2) -> 0 | I44: =G44-H44 -> 0
A45: 二、其他长期职工福利 | G45: =ROUND(D45*F45,2) -> 0 | I45: =G45-H45 -> 0
A46: 其中：1．xxx | G46: =ROUND(D46*F46,2) -> 0 | I46: =G46-H46 -> 0
A47: 2．其他 | G47: =ROUND(D47*F47,2) -> 0 | I47: =G47-H47 -> 0
A48: 三、审计说明：
A49: 1、公司对社会保险费的核算方法：
A50: 计提，或按实列支
A51: 2、国家关于计缴比例、计缴基数的规定：
A53: 3、相关部门为公司确定的计缴基数的依据：
A55: 4、公司未给员工计缴社会保险的情况：
A57: 5、……
A59: 四、审计结论：

Sheet 分配情况检查表J1-7
A1: 致同会计师事务所
A2: 应付职工薪酬成本、费用分配情况检查表
A3: =底稿目录!A2 -> 被审计单位： | D3: =底稿目录!A4 -> 编制人： | G3: =底稿目录!A5 -> 编制日期： | K3: 索引号： | L3: =底稿目录!F12 -> J1-7
A4: =底稿目录!A3 -> 截止日：202X年12月31日 | D4: =底稿目录!A6 -> 复核人： | G4: =底稿目录!A7 -> 复核日期： | K4: 页 次：
A5: 一、审计目标:
A6: 1.资产负债表中记录的应付职工薪酬是存在的，且已经记录在恰当的账户中
A7: 2.所有应记录的应付职工薪酬均已记录，所有应当包括在财务报表中的相关披露均已包括
A8: 3.应付职工薪酬以恰当的金额包括在财务报表中，与之相关的计价或分摊调整已恰当记录，相关披露已得到恰当计量和描述
A9: 二、审计过程：
A10: 1.被审计单位职工薪酬计提分配政策
A11: （1）工资总额的组成部分：
A12: （2）公司是否执行工效挂钩：
A13: （3）福利政策：
A14: （4）职工薪酬核算、计提分配及支付政策及流程：
A15: 2.应付职工薪酬成本、费用分配情况
A16: 项目名称 | C16: 生产成本 | D16: 制造费用 | E16: 管理费用 | F16: 销售费用 | G16: 其他… | H16: 本期合计 | I16: 本期实际计提数 | J16: 本期差异 | K16: 差异原因 | L16: 结论
A17: (1)短期薪酬 | C17: =SUM(C18:C26) -> 0 | D17: =SUM(D18:D26) -> 0 | E17: =SUM(E18:E26) -> 0 | F17: =SUM(F18:F26) -> 0 | G17: =SUM(G18:G26) -> 0 | H17: =SUM(C17,D17,E17,F17,G17) -> 0 | I17: =SUM(I18:I26) -> 0 | J17: =H17-I17 -> 0
A18: 工资、奖金、津贴和补贴 | H18: =SUM(C18,D18,E18,F18,G18) -> 0 | I18: ='明细表J1-2 '!K13 -> 0 | J18: =H18-I18 -> 0
A19: 职工福利费 | H19: =SUM(C19,D19,E19,F19,G19) -> 0 | I19: ='明细表J1-2 '!K19 -> 0 | J19: =H19-I19 -> 0
A20: 社会保险费 | H20: =SUM(C20,D20,E20,F20,G20) -> 0 | I20: ='明细表J1-2 '!K20 -> 0 | J20: =H20-I20 -> 0
A21: 住房公积金 | H21: =SUM(C21,D21,E21,F21,G21) -> 0 | I21: ='明细表J1-2 '!K25 -> 0 | J21: =H21-I21 -> 0
A22: 工会经费 | H22: =SUM(C22,D22,E22,F22,G22) -> 0 | I22: ='明细表J1-2 '!K26 -> 0 | J22: =H22-I22 -> 0
A23: 职工教育经费 | H23: =SUM(C23,D23,E23,F23,G23) -> 0 | I23: ='明细表J1-2 '!K27 -> 0 | J23: =H23-I23 -> 0
A24: 短期带薪缺勤 | H24: =SUM(C24,D24,E24,F24,G24) -> 0 | I24: ='明细表J1-2 '!K28 -> 0 | J24: =H24-I24 -> 0
A25: 短期利润分享计划 | H25: =SUM(C25,D25,E25,F25,G25) -> 0 | I25: ='明细表J1-2 '!K29 -> 0 | J25: =H25-I25 -> 0
A26: 非货币性福利 | H26: =SUM(C26,D26,E26,F26,G26) -> 0 | I26: ='明细表J1-2 '!K30 -> 0 | J26: =H26-I26 -> 0
A27: （2）离职后福利中设定提存计划、其他长期福利中符合设定提存条件的负债 | C27: =SUM(C28:C29) -> 0 | D27: =SUM(D28:D29) -> 0 | E27: =SUM(E28:E29) -> 0 | F27: =SUM(F28:F29) -> 0 | G27: =SUM(G28:G29) -> 0 | H27: =SUM(C27,D27,E27,F27,G27) -> 0 | I27: =I28+I29 -> 0 | J27: =H27-I27 -> 0
A28: 离职后福利 | H28: =SUM(C28,D28,E28,F28,G28) -> 0 | I28: ='明细表J1-2 '!K37 -> 0 | J28: =H28-I28 -> 0
A29: 其他长期职工福利 | H29: =SUM(C29,D29,E29,F29,G29) -> 0 | I29: ='明细表J1-2 '!K42 -> 0 | J29: =H29-I29 -> 0
A30: （3）一年内支付的辞退福利 | H30: =SUM(C30,D30,E30,F30,G30) -> 0 | I30: ='明细表J1-2 '!K53 -> 0 | J30: =H30-I30 -> 0
A31: （4）其他 | H31: =SUM(C31,D31,E31,F31,G31) -> 0 | J31: =H31-I31 -> 0
A32: 三、审计说明：
A35: 四、审计结论：
A37: 提示：
A38: 1.了解被审计单位工资核算、计提及支付政策及流程，关注是否符合实际经营情况和会计准则的要求，并与前期进行对比，分析其是否保持一贯性。
A39: 2.了解发放标准（高管、销售人员、技术人员、业务人员、生产人员、行政人员），发薪的周期（上发还是下发）、年度及季度奖金计提的原则。
A40: 3.关注职工薪酬的发放方式和发放频率
A41: 4.了解是否存在同一员工同时承担技术服务、研发、销售等多项职责的情况，同时关注此种情况下人工成本分配准确性
A42: 5.检查分配方法与上年是否一致，除因解除与职工的劳动关系给予的补偿直接计入管理费用外，被审计单位是否根据职工提供服务的受益对象，分别对下列情况进行处理：
A43: (1)应由生产产品、提供劳务负担的职工薪酬，计入产品成本或劳务成本；
A44: (2)应由在建工程、无形资产负担的职工薪酬，计入建造固定资产或无形资产；
A45: (3)其他职工薪酬，计入当期损益。

Sheet 检查表J1-8
A1: 致同会计师事务所
A2: 应付职工薪酬检查表
A3: =底稿目录!A2 -> 被审计单位： | E3: =底稿目录!A4 -> 编制人： | J3: =底稿目录!A5 -> 编制日期： | N3: 索引号： | O3: =底稿目录!F13 -> J1-8
A4: =底稿目录!A3 -> 截止日：202X年12月31日 | E4: =底稿目录!A6 -> 复核人： | J4: =底稿目录!A7 -> 复核日期： | N4: 页 次：
A5: 一、测试目标：
A6: 1.资产负债表中记录的应付职工薪酬是存在的，且已经记录在恰当的账户中
A7: 2.所有应记录的应付职工薪酬均已记录，所有应当包括在财务报表中的相关披露均已包括
A8: 3.记录的应付职工薪酬由被审计单位拥有或控制
A9: 二、样本选取标准与规模：
A10: 抽测原因：大额（）关联方（）大额交易频繁（）异常（）其他（）
A11: 三、测试：
A12: 测试内容说明：1.原始凭证是否齐全； 2.记账凭证与原始凭证是否相符；3.账务处理是否正确；4.是否记录于恰当的会计期间；5.……
A13: 1.本期贷方金额检查
A14: 记账凭证 | H14: 职工薪酬计算表 | K14: …… | L14: 索引号 | M14: 是否异常
A15: 项目 | B15: 日期 | C15: 凭证编号 | D15: 业务内容 | E15: 对方科目 | F15: 明细科目 | G15: 贷方金额 | H15: 月份 | I15: 金额 | J15: 是否经过恰当审批
A16: 工资
A17: 奖金或者利润分享福利
A18: ……
A23: 合计 | G23: =SUM(G16:G22) -> 0 | I23: =SUM(I16:I22) -> 0
A24: 2.本期借方金额检查
A25: 记账凭证 | H25: 付款审批单 | J25: 银行回单 | M25: …… | N25: 索引号 | O25: 是否异常
A26: 项目 | B26: 日期 | C26: 凭证编号 | D26: 业务内容 | E26: 对方科目 | F26: 明细科目 | G26: 借方金额 | H26: 日期/编号 | I26: 是否经过恰当审批 | J26: 日期 | K26: 摘要/说明 | L26: 金额
A27: 工资
A28: 奖金或者利润分享福利
A29: ……
A34: 合计 | G34: =SUM(G27:G33) -> 0 | L34: =SUM(L27:L33) -> 0
A35: 3.期后支付情况检查 | P35: 关注期后支付的职工薪酬摘要是否提及上期、支付依据、支付金额是否超过上期计提金额，是否应该归属于报告期、是否已计提
A36: 记账凭证 | H36: 付款审批单 | J36: 银行回单 | M36: …… | N36: 索引号 | O36: 是否跨期
A37: 项目 | B37: 日期 | C37: 凭证编号 | D37: 业务内容 | E37: 对方科目 | F37: 明细科目 | G37: 借方金额 | H37: 日期/编号 | I37: 是否经过恰当审批 | J37: 日期 | K37: 摘要/说明 | L37: 金额
A38: 工资
A39: 奖金或者利润分享福利
A40: ……
A43: 合计 | G43: =SUM(G38:G42) -> 0 | L43: =SUM(L38:L42) -> 0
A44: 四、审计说明：
A45: 1.本期发生额、期末余额检查比例： | D45: 方向 | E45: 账面金额 | F45: 检查金额 | G45: 检查比例 | H45: 如果检查比例较低应扩大检查样本量或说明原因
D46: 本期贷方 | E46: ='明细表J1-2 '!K33 -> 0 | F46: =G23 -> 0 | G46: =ROUND(F46/E46,4) -> #DIV/0!
D47: 本期借方 | E47: ='明细表J1-2 '!L33 -> 0 | F47: =G34 -> 0 | G47: =ROUND(F47/E47,2) -> #DIV/0!
A48: 2.……
A50: 五、审计结论：

Sheet 非货币性福利检查表J1-9
A1: 致同会计师事务所
A2: 应付职工薪酬-非货币性福利检查表
A3: =底稿目录!A2 -> 被审计单位： | D3: =底稿目录!A4 -> 编制人： | H3: =底稿目录!A5 -> 编制日期： | K3: 索引号： | L3: =底稿目录!F14 -> J1-9
A4: =底稿目录!A3 -> 截止日：202X年12月31日 | D4: =底稿目录!A6 -> 复核人： | H4: =底稿目录!A7 -> 复核日期： | K4: 页 次：
A5: 一、审计目标:
A6: 1.资产负债表中记录的应付职工薪酬是存在的，且已经记录在恰当的账户中
A7: 2.所有应记录的应付职工薪酬均已记录，所有应当包括在财务报表中的相关披露均已包括
A8: 3.应付职工薪酬以恰当的金额包括在财务报表中，与之相关的计价或分摊调整已恰当记录，相关披露已得到恰当计量和描述
A9: 二、审计过程：
A10: 1.取得非货币性福利明细，确定计算的准确性； 2.取得非货币性福利性文件，了解主要政策。
A11: 3.确定该福利是否满足确认为负债的标准; 4.确定负债的计算是否合理。
A12: 1、公司非货币性福利政策及其内容：
A14: 2、计提金额的确定：
A16: 3、抽查本期增减变动的准确性性及会计处理的适当性
A17: 日 期 | B17: 凭证种类 | C17: 凭证编号 | D17: 业务内容 | E17: 明细科目 | F17: 对方科目 | G17: 金 额 | I17: 附件 | J17: 非货币性福利形式 | K17: 实物来源 | L17: 结论
G18: 借方 | H18: 贷方
A24: 三、审计说明：
A27: 四、审计结论：

Sheet 辞退福利检查表J1-10
A1: 致同会计师事务所
A2: 应付职工薪酬-辞退福利检查表
A3: =底稿目录!A2 -> 被审计单位： | D3: =底稿目录!A4 -> 编制人： | F3: =底稿目录!A5 -> 编制日期： | I3: 索引号： | J3: =底稿目录!F15 -> J1-10
A4: =底稿目录!A3 -> 截止日：202X年12月31日 | D4: =底稿目录!A6 -> 复核人： | F4: =底稿目录!A7 -> 复核日期： | I4: 页 次：
A5: 一、审计目标:
A6: 1.资产负债表中记录的应付职工薪酬是存在的，且已经记录在恰当的账户中
A7: 2.所有应记录的应付职工薪酬均已记录，所有应当包括在财务报表中的相关披露均已包括
A8: 3.应付职工薪酬以恰当的金额包括在财务报表中，与之相关的计价或分摊调整已恰当记录，相关披露已得到恰当计量和描述
A9: 二、审计过程：
A10: 1.取得辞退福利相关制度、决议、计划、协议，确定该福利是否满足确认为负债的标准，确定负债的计算是否合理
A11: 2.对于职工没有选择权的辞退计划，检查按辞退职工数量、辞退补偿标准计提辞退福利负债金额是否正确
A12: 3.对于自愿接受裁减的建议，检查按接受裁减建议的预计职工数量、辞退补偿标准（该标准确定）等计提辞退福利负债金额是否正确
A13: 4.检查实质性辞退工作在一年内完成,但付款时间超过一年的辞退福利，是否按折现后的金额计量，折现率的选择是否合理
A14: 5.识别辞退福利中是否包含未予辞退的员工；检查其工资薪酬是否已经恰当计入相关费用。
A15: 6.检查辞退福利会计处理是否正确
A16: 1、公司是否制定了关于辞退福利的相关制度，及其内容：
... A22: 4、了解专家资质及利用精算师的工作
A23: 序号 | B23: 项目 | D23: 索引号
A24: 1 | B24: 利用专家的工作 | D24: S12
A25: 2 | B25: 评估专家工作 | D25: S12A
A26: 5、抽查本期增减变动的真实性
A27: 日 期 | B27: 凭证种类 | C27: 凭证编号 | D27: 业务内容 | E27: 明细科目 | F27: 对方明细科目 | G27: 金 额 | I27: 附件 | J27: 结论
G28: 借方 | H28: 贷方
A35: 三、审计说明：
A38: 四、审计结论：
A41: 提示：辞退福利计算中使用的关键假设和主要参数
A42: 1 | B42: 基本工资/生活费增长率
A43: 2 | B43: 社保、公积金增长率
A44: 3 | B44: 死亡率
A45: 4 | B45: 折现率
A46: 折现率为同期限同币种国债利率或高质量公司债券的市场收益率，不存在与辞退福利支付期限相匹配国债利率的，应当以短于辞退福利支付期限的国债利率为基础，并根据国债收益率曲线采用外推法估计超出期限部分的利率，合理确定折现率。

Sheet 股份支付检查表J1-10-删除
A1: 致同会计师事务所
A2: 应付职工薪酬-股份支付检查表
A3: =底稿目录!A2 -> 被审计单位： | H3: =底稿目录!A4 -> 编制人： | N3: =底稿目录!A5 -> 编制日期： | R3: 索引号： | S3: J1-10 | T3: 移至股份支付底稿
A4: =底稿目录!A3 -> 截止日：202X年12月31日 | H4: =底稿目录!A6 -> 复核人： | N4: =底稿目录!A7 -> 复核日期： | R4: 页次：
A5: 一、审计目标:
B6: 确定被审计单位职工薪酬计提的完整性。
A7: 二、审计过程：
A8: 1.取得股份支付明细，确定计算的准确性
A9: 2.取得股份支付薪酬奖励与董事会会议纪录或其他支持性文件，了解主要条款及条件（即授予日期、期权的价格、股数、行使日期等），并确定企业是否有政策限制该股份支付薪酬奖励发行的日期
A10: 3.对新的或修改的股份支付进行分析： ①确定包括在分析中的所有个人都是雇员或其他提供类似服务的人员。 ②将新的股份支付薪酬奖励与董事会会议纪录或其它授权文件相比较。确定是否存在董事会会议记录或其他文件中提及的股份支付薪酬奖励尚未包含在上面的分析之内。如果是，获取该股份支付相关支持性文件，并确定该遗漏是否适当。 ③是否已适当地确认对现有的股份支付薪酬奖励的修改（如有修改）。
A11: 4.选取样本（如需要）： ①取得合同及其他支持性文件。 ②确认主要条款及条件与股份支付薪酬工具是否一致（授予日期、期权的价格、股数、行使日期等）。 ③确定是否授权日与行权日之间存在重大时间间隔，如果有，向适当的人员询问原因。
A12: 5.根据该股份支付薪酬奖励的条款和条件，确定其分类（如分类为权益结算、现金结算、或者二者结合）适当，并判断所采用的会计处理是否能恰当地反映这种分类
A13: 6.了解股份支付公允价值计算相关假设，确定假设的合理性
A14: 7.确定股份支付金额是否正确，会计处理是否正确
A15: 8.确定是否需要聘请估值专家，以协助评价：企业的专家（无论其是第三方还是内部员工）对该工具估值的工作。完成“专家资质”和“专家工作”的审计程序，以评估估值专家（无论其是第三方还是内部员工）的资质及其工作
A16: 1、公司股份支付政策及其内容：
A18: 2、公允价值的确定及相关假设
A20: 3、了解专家资质及利用精算师的工作
A21: 序号 | B21: 项目 | D21: 索引号
A22: 1 | B22: 了解专家的资质 | D22: B21
A23: 2 | B23: 利用专家的工作 | D23: C25
A24: 4、抽查本期增减变动的准确性性及会计处理的适当性
A25: 日 期 | B25: 凭证种类 | C25: 凭证编号 | D25: 业务内容 | E25: 明细科目 | F25: 对方科目 | G25: 金 额 | I25: 结论
G26: 借方 | H26: 贷方
A36: 5、抽查本期增减变动的准确性性及会计处理的适当性
A37: 股份支付种类 | B37: 时间 | C37: 每股股票/每份增值权公允价值 | D37: 每股股票/每份增值权支付现金 | E37: 股份支付总人数 | F37: 离职人数 | G37: 行权人数 | H37: 每人获得的股份数量 | I37: 连续服务年限 | J37: 测算应付职工薪酬金额 | K37: 账面应付职工薪酬金额 | L37: 差异 | M37: 支付现金金额 | N37: 测算当期费用/公允价值变动金额 | O37: 账面记录当期费用/公允价值变动金额 | P37: 差异 | Q37: 是否为雇员或其他提供类似服务的人员 | R37: 主要条款及条件与股份支付薪酬工具是否一致 | S37: 授权日与行权日之间是否存在重大时间间隔
L38: =J38-K38 -> 0 | M38: 0 | P38: =N38-O38 -> 0
L39: =J39-K39 -> 0 | M39: 0 | P39: =N39-O39 -> 0
L40: =J40-K40 -> 0 | M40: 0 | P40: =N40-O40 -> 0
L41: =J41-K41 -> 0 | M41: 0 | P41: =N41-O41 -> 0
L42: =J42-K42 -> 0 | M42: 0 | P42: =N42-O42 -> 0
L43: =J43-K43 -> 0 | M43: 0 | P43: =N43-O43 -> 0
L44: =J44-K44 -> 0 | M44: 0 | P44: =N44-O44 -> 0
A45: 合计 | E45: =SUM(E38:E44) -> 0 | F45: =SUM(F38:F44) -> 0 | G45: =SUM(G38:G44) -> 0 | J45: =SUM(J38:J44) -> 0 | K45: =SUM(K38:K44) -> 0 | L45: =SUM(L38:L44) -> 0 | M45: =SUM(M38:M44) -> 0 | N45: =SUM(N38:N44) -> 0 | O45: =SUM(O38:O44) -> 0 | P45: =SUM(P38:P44) -> 0
A48: 三、审计说明：
A53: 四、审计结论：
A57: 提示：
A58: 注1：检查授予后立即可行权的以现金结算的股份支付，是否在授权日以承担负债的公允价值计入相关成本或费用；
A60: 注2：检查完成等待后的服务或达到规定业绩条件以后才可行权的以现金结算的股份支付，在等待期内的每个资产负债表日，
A61: 是否以可行权情况的最佳估计为基础，按照承担负债的公允价值金额，将当期取得的服务计入成本或费用。在资产负债表日，
A62: 后续信息表明当期承担债务的公允价值与以前估计不同的，是否进行调整。并在可行权日，调整至实际可行权水平；
A64: 注3：检查可行权日之后，以现金结算的股份支付当期公允价值的变动金额，是否借记或贷记“公允价值变动损益”
A66: 注4：检查可行权日，以现金结算的股份支付的金额正确，会计处理恰当。

Sheet 应付职工薪酬余额及期后事项检查表J1-11-删除
A1: 致同会计师事务所
A2: 应付职工薪酬余额及期后事项检查表 | J2: 整合到检查表中
A3: =底稿目录!A2 -> 被审计单位： | D3: =底稿目录!A4 -> 编制人： | F3: =底稿目录!A5 -> 编制日期： | H3: 索引号： | I3: J1-11
A4: =底稿目录!A3 -> 截止日：202X年12月31日 | D4: =底稿目录!A6 -> 复核人： | F4: =底稿目录!A7 -> 复核日期： | H4: 页次：
A5: 一、审计目标:
B6: 确定被审计单位职工薪酬计提的完整性。
A7: 二、审计过程：
A8: 1.检查应付职工薪酬的期后付款情况；
A9: 2.检查资产负债表日至财务报表批准报出日之间职工薪酬发放情况；
A10: 3.确定是否有确凿证据表明需要调整资产负债表日原确认的应付职工薪酬事项。
A11: 项 目 | C11: 期末结余金额 | D11: 结余原因 | E11: 结余性质 | F11: 期后实际支付情况 | H11: 差 异 | I11: 结 论
E12: 拖欠性质/工效挂钩 | F12: 金额 | G12: 索引
H13: =C13-F13 -> 0
H14: =C14-F14 -> 0
H15: =C15-F15 -> 0
H16: =C16-F16 -> 0
H17: =C17-F17 -> 0
H18: =C18-F18 -> 0
H19: =C19-F19 -> 0
H20: =C20-F20 -> 0
H21: =C21-F21 -> 0
H22: =C22-F22 -> 0
H23: =C23-F23 -> 0
H24: =C24-F24 -> 0
... H30: =C30-F30 -> 0
A31: 合 计 | C31: =SUM(C13:C30) -> 0 | F31: =SUM(F13:F30) -> 0 | H31: =SUM(H13:H30) -> 0
A32: 三、审计说明：
A35: 四、审计结论：

Sheet 职工薪酬政策统计表J1-12-删除
A1: 致同会计师事务所
A2: 职工薪酬政策统计表 | I2: 整合到分配情况检查表J1-7、计提情况检查表J1-6
A3: =底稿目录!A2 -> 被审计单位： | C3: =底稿目录!A4 -> 编制人： | E3: =底稿目录!A5 -> 编制日期： | G3: 索引号： | H3: J1-12
A4: =底稿目录!A3 -> 截止日：202X年12月31日 | C4: =底稿目录!A6 -> 复核人： | E4: =底稿目录!A7 -> 复核日期： | G4: 页 次：
A5: 一、审计目标：
A6: 检查应付职工薪酬计价是否正确。
A7: 检查职工薪酬分摊是否合理。
A9: 二、审计过程：
A10: 1.解被审计单位工薪与人事循环和与财务报告相关内部控制
A11: 2.了解被审计单位工资核算、计提及支付政策及流程，关注是否符合实际经营情况和会计准则的要求，并与前期进行对比，分析其是否保持一贯性。
A12: 3.了解发放标准（高管、销售人员、技术人员、业务人员、生产人员、行政人员），发薪的周期（上发还是下发）、年度及季度奖金计提的原则。
A13: 4.关注职工薪酬的发放方式和发放频率
A14: 5.了解是否存在同一员工同时承担技术服务、研发、销售等多项职责的情况，同时关注此种情况下人工成本分配准确性
A15: 6.检查分配方法与上年是否一致，除因解除与职工的劳动关系给予的补偿直接计入管理费用外，被审计单位是否根据职工提供服务的受益对象，分别对下列情况进行处理：
A16: 6.1.应由生产产品、提供劳务负担的职工薪酬，计入产品成本或劳务成本；
A17: 6.2.应由在建工程、无形资产负担的职工薪酬，计入建造固定资产或无形资产；
... A25: 4、社会保险费和住房公积金计提标准：
A26: 项目 | B26: 标准计提基数（企业负担） | C26: 索引号 | D26: 比例 | E26: 本年是否缴纳 | F26: 备注
A35: 5、社会保险费计提标准：
A36: 项目 | B36: 计提基数 | C36: 索引号 | D36: 比例 | E36: 本年是否计提 | F36: 备注
A40: 6、薪酬分配政策：
A41: 6.1薪酬分配概述
A43: 6.2薪酬分配流程
A44: （1）薪酬归集
A46: （2）薪酬分配标准
A49: （3）薪酬分配流程图
A51: 三、审计说明：
A53: 四、审计结论：

Sheet IPO企业薪酬审计提示
A2: 北京注册会计师协会专家委员会专家提示第5号——IPO企业职工薪酬的审计
A3: 职工薪酬作为重要的成本费用项目及舞弊操纵易发领域，是注册会计师在IPO审计中需要特别关注的重点之一。现结合《企业会计准则》、《中国注册会计师执业准则》及相关法规对IPO企业会计核算及规范运作的要求，就IPO职工薪酬审计做如下风险提示。
A5: 本提示仅供事务所及相关业务人员在执行专项核查时参考，不能替代相关法律法规、注册会计师执业准则以及注册会计师个人的职业判断。事务所在执业中应结合项目实际情况、风险导向原则以及注册会计师的职业判断确定，不能直接照搬照抄。
A6: IPO审计专家委员会针对IPO企业职工薪酬的审计，提示如下：
A7: 一、职工薪酬的相关舞弊动机和方法
A8: 考虑到动机不同，企业利用职工薪酬的舞弊可分为盈利操纵和税收操纵。IPO审计重点以防范盈利操纵为主，税收操纵涉及对企业规范运作要求。
A9: 可能存在的舞弊情形主要有以下几种类型：
A10: 1．以侵占财产为目标，如虚增人数冒领工资侵占企业资产等；
A11: 2．以少缴个人所得税为目标，如将工资费用化或虚增人数“化整为零”少缴个人所得税等；
A12: 3．以少缴企业所得税为目标，如虚增人数以虚增薪酬总额、将资本化薪酬费用化、自产产品福利分配不确认收入成本等；
A13: 4．以盈利操纵为目标，如随意改变薪酬标准、延迟或提前确认薪酬费用、利用员工性质分类进行操纵或通过关联方承担薪酬改变费用金额等。
A14: 如果发现相关舞弊情形，除根据审计准则实施进一步程序外，还应考虑舞弊行为对内部控制有效性及规范运作的影响。如果涉及税收风险，则需要考虑相关行为是否构成重大违法等。
... A109: 社会保险和住房公积金管理部门守法证明；实际控制人和大股东对承担相关支出损失的承诺；发行人律师关于欠缴行为不构成重大违法和不对发行构成实际障碍的法律意见。

Sheet IPO企业股权激励工具关注的审计重点-删除
A1: 北京注册会计师协会专家委员会提示[2016]第8号—IPO企业股权激励工具关注的审计重点 | Q1: 移至股份支付底稿
A2: 股权激励计划作为行之有效的激励工具，在众多企业中被广泛采用。企业在实施IPO计划中，已经设定的股权激励工具在财务报表上具有较重要的影响，是IPO审计应关注的重点和难点。
A3: 本提示仅供事务所及相关从业人员在执业中参考，不能替代相关法律法规、注册会计师执业准则及注册会计师职业判断。提示中所涉及的审计时间 、范围和程度等，事务所及相关从业人员在执业中需结合实际情况、风险导向原则以及注册会计师的职业判断确定，不能直接照搬照抄。
A4: 针对有股权激励工具的IPO企业应关注的财务报表影响，IPO审计专家委员会做出如下提示：
A5: 一、关注IPO企业在以往期间的股权激励工具
A6: 《公司法》第一百四十二条中规定公司不得收购本公司股份，但以下情形除外：“将股份奖励给本公司职工；公司依照第一款第(三)项规定收购的本公司股份，不得超过本公司已发行股份总额的百分之五；用于收购的资金应当从公司的税后利润中支出；所收购的股份应当在一年内转让给职工。” 随着《公司法》修订及新会计准则的实施，股权激励计划作为一项行之有效的长期激励工具，已经被众多企业广泛采用。
A7: （一） 对历史财务报表以外信息的关注
A8: 对已经采用股权激励的企业，公司历史财务报表很可能没有体现出其相应的会计处理。启动IPO审计工作计划时，仅从历史财务报表无法发现并辨别公司是否有此事项，需要注册会计师特别关注，并主动与公司管理层及股东讨论询问，在公司历史年度是否存在《企业会计准则第11 号—股份支付》中所明确的股份支付的情形，辨认出是否存在适用的事项。
A9: （二） 深入沟通股份支付的会计影响
A10: 对于IPO企业的股份支付主体，《企业会计准则第11 号—股份支付》规定：“股份支付所指的权益工具是指企业自身权益工具，包括企业本身、企业的母公司或同集团其他会计主体的权益工具。”大多数公司采用企业本身的权益工具，或者企业控股公司。企业控股公司通常为专门设立的股权激励平台公司或者控股壳公司。管理层和股东对股份支付的会计影响的认知可能与准则不一致，注册会计师需要深入沟通讨论。通常如下情形属于股份支付的会计影响事项：
A11: 1.公司向董事、高管、核心员工、员工持股平台或者其他人员，发行的新股股份价格明显低于公允价值。这里，要注意其他人员，包括个人或者公司，也可能落入股份支付的范畴，进而导致股份支付的影响；
A12: 2.股东将其持有的股份以较低的价格转让给如上人士，也属于股份支付会计事项；
A13: 3.股票发行价格低于每股净资产的，亦需格外关注。全国股转系统发布的《挂牌公司股票发行常见问题解答（一）》中，有相应要求。
... A40: 由于公司与被授予对象均签署承诺函，明确认可自本激励计划授予日起3年内全职在公司工作后，才有权享有股权激励计划的相关收益。因此，公司认为股份支付锁定期a为36个月。2015年1月，公司启动A股创业板IPO计划，公司管理层在此时分析判断，自2015年1月IPO启动至上市前被审核的最近一个会计期间截止日，预计将持续24个月，即b为24个月。因此，为确保上市审核时遵守IPO规则中“股权清晰”的要求，公司与相关员工约定“如果公司在原约定的解锁日之前上市，则股份支付相关的股份立即解锁”。公司按照修订服务期条件采用股份支付锁定期与自股份支付授予日至上市成功日之间孰短的原则，应按b即24个月对股份支付的公允价值进行摊销。同时，管理层还需在持续每六个月更新申报材料之时，依据相关外部监管规则和申请过程中环境的动态变化以及公司自身内部IPO成熟度的把握，及时更新对b的估计。

Sheet 首发业务解答二-删除
A1: 首发业务问答（二）
A2: 问题1、股份支付
A3: 问题1、基于企业发展考虑，部分首发企业上市前通过增资或转让股份等形式实现高管或核心技术人员、员工、主要业务伙伴持股。首发企业股份支付成因复杂，公允价值难以计量，与上市公司实施股权激励相比存在较大不同。对此，首发企业及中介机构需重点关注哪些方面？ | B3: 移至股份支付底稿
A4: 答：发行人报告期内为获取职工和其他方提供服务而授予股份的交易，在编制申报会计报表时，应按照《企业会计准则第11号——股份支付》相关规定进行处理。
A5: （1）具体适用情形
A6: 对于报告期内发行人向职工（含持股平台）、客户、供应商等新增股份，以及主要股东及其关联方向职工（含持股平台）、客户、供应商等转让股份，均应考虑是否适用《企业会计准则第11号——股份支付》。对于报告期前的股份支付事项，如对期初未分配利润造成重大影响，也应考虑是否适用《企业会计准则第11号——股份支付》。
A7: 通常情况下，解决股份代持等规范措施导致股份变动，家族内部财产分割、继承、赠与等非交易行为导致股权变动，资产重组、业务并购、持股方式转换、向老股东同比例配售新股等导致股权变动等，在有充分证据支持相关股份获取与发行人获得其服务无关的情况下，一般无需作为股份支付处理。
A8: 对于为发行人提供服务的实际控制人/老股东以低于股份公允价值的价格增资入股事宜，如果根据增资协议，并非所有股东均有权按各自原持股比例获得新增股份，对于实际控制人/老股东超过其原持股比例而获得的新增股份，应属于股份支付；如果增资协议约定，所有股东均有权按各自原持股比例获得新增股份，但股东之间转让新增股份受让权且构成集团内股份支付，导致实际控制人/老股东超过其原持股比例获得的新增股份，也属于股份支付。对于实际控制人/老股东原持股比例，应按照相关股东直接持有与穿透控股平台后间接持有的股份比例合并计算。
A9: （2）确定公允价值
A10: 存在股份支付事项的，发行人及申报会计师应按照企业会计准则规定的原则确定权益工具的公允价值。在确定公允价值时，可合理考虑入股时间阶段、业绩基础与变动预期、市场环境变化、行业特点、同行业并购重组市盈率水平、股份支付实施或发生当年市盈率与市净率指标等因素的影响；也可优先参考熟悉情况并按公平原则自愿交易的各方最近达成的入股价格或相似股权价格确定公允价值，如近期合理的PE入股价；也可采用恰当的估值技术确定公允价值，但要避免采取有争议的、结果显失公平的估值技术或公允价值确定方法，如明显增长预期下按照成本法评估的每股净资产价值或账面净资产。
A11: （3）计量方式
A12: 确认股份支付费用时，对增资或受让的股份立即授予或转让完成且没有明确约定服务期等限制条件的，原则上应当一次性计入发生当期，并作为偶发事项计入非经常性损益。对设定服务期等限制条件的股份支付，股份支付费用可采用恰当的方法在服务期内进行分摊，并计入经常性损益。
A13: （4）披露与核查
A14: 发行人应在招股说明书及报表附注中披露股份支付的形成原因、权益工具的公允价值及确认方法。保荐机构及申报会计师应对首发企业报告期内发生的股份变动是否适用《企业会计准则第11号——股份支付》进行核查，并对以下问题发表明确意见：股份支付相关权益工具公允价值的计量方法及结果是否合理，与同期可比公司估值是否存在重大差异及原因；对于存在与股权所有权或收益权等相关的限制性条件的，相关条件是否真实、可行，服务期的判断是否准确，服务期各年/期确认的员工服务成本或费用是否准确；发行人报告期内股份支付相关会计处理是否符合《企业会计准则》相关规定。

Sheet GT_Custom
A1: C1 | B1: Custom 1
A2: C2 | B2: Custom 2
A3: C3 | B3: Custom 3
A4: C4 | B4: Custom 4
A5: C5 | B5: Custom 5
A6: C6 | B6: Custom 6
A7: C7 | B7: Custom 7
A8: C8 | B8: Custom 8
