Workbook
Name _.dbf: #REF!
Name _00510: #REF!
Name _1、: #REF!
Name _1、受本循环影响的相关交易和账户余额: #REF!
Name _13: #REF!
Name _1w6_: #REF!
Name _1固定资产数据库_筛选打印: #REF!
Name _2、主要业务活动: #REF!
Name _2、注册会计师通常应在本循环中了解与上述业务活动相关的内部控制_如果计划在其他业务循环中对上述: #REF!
Name _2其他资产_开办费除外_明细表: #REF!
Name _3余额表_一级_.dbf: #REF!
Name _DAT1: #REF!
Name _DAT10: #REF!
Name _DAT11: #REF!
Name _DAT2: #REF!
Name _DAT3: #REF!
Name _DAT4: #REF!
Name _DAT5: #REF!
Name _DAT6: #REF!
Name _DAT7: #REF!
Name _DAT8: #REF!
Name _DAT9: #REF!
Name _Toc12834: 首发业务解答二!$A$2
Name _Toc2639: 首发业务解答二!$A$3
Name _YE1: #REF!
Name _YS1: #REF!
Name _YS2: #REF!
Name A: #REF!
Name a1c1: #REF!,#REF!
Name aa: #REF!
Name aaa: #REF!
Name agmmt: #REF!
Name agmt: #REF!
Name agmt1: #REF!
Name al: #REF!
Name avg_days: #REF!
Name a暗暗: #REF!
Name b: #REF!
Name BD: #REF!
Name beg_day: #REF!
Name beg_day1: #REF!
Name CarryKnown: #REF!
Name CarryKnownTable: #REF!
Name CarryLikely: #REF!
Name CarryLikelyTable: #REF!
Name Carryover_Effect_of_Prior_Year: #REF!
Name CarryoverTitle: #REF!
Name CC_Instruction: #REF!
Name CE_CarryKnownProtection: #REF!
Name CE_CarryKnownTable: #REF!
Name CE_CarryLikely1Protection: #REF!
Name CE_CarryLikely1Table: #REF!
Name CE_CarryLikely2Protection: #REF!
Name CE_CarryLikely2Table: #REF!
Name CE_CarryTaxable: #REF!
Name CE_Desc: #REF!
Name CE_Income: #REF!
Name CE_KeepFormat: #REF!
Name CE_KnownChange: #REF!
Name CE_KnownFormulaProtection: #REF!

Sheet 底稿目录
A1: 底稿开列时，可先在以下单元格填写有关内容，以便其他底稿引用有关数据：
A2: 被审计单位： | D2: 序号 | E2: 内容 | F2: 索引号 | G2: 备注
A3: 截止日：202X年12月31日 | D3: 1 | E3: 股份支付实质性程序表 | F3: J3A
A4: 编制人： | D4: 2 | E4: 应付职工薪酬-股份支付情况表 | F4: J3-1
A5: 编制日期： | D5: 3 | E5: 应付职工薪酬-股份支付检查表 | F5: J3-2
A6: 复核人：
A7: 复核日期：
A9: 关于工作底稿与审计程序索引号对应的说明
A10: 1.编制的审计工作底稿应与审计程序对应。审计项目组应根据被审计单位实际情况和风险评估情况在实质性程序表中裁剪、修改或增加审计程序，根据实际执行的审计程序完成相应审计工作底稿，编制的工作底稿中应按自然顺序依次编制索引号，并通过唯一的索引号将与实质性程序表中的程序对应关联（即将工作底稿的索引号填入实质性程序表中的底稿索引号列）。
A14: 2.获取的支持性证据应与审计底稿或程序对应。审计项目组在完成底稿时获取的支持性证据应根据底稿索引号编制下一级按自然顺序排序的索引号（如D1-2-1、D1-2-2、……），并在底稿中说明引用的支持性证据、关联索引号。
A17: 3.工作底稿索引号的编码规则：实质性程序索引号按循环从“D”到“N”,循环内账户以顺序号排列，模板中底稿索引号按账户顺序+自然数顺序（即模板中索引号按二级自然顺序排列，如D1-1、D1-2、D1-3、……D1-N）。

Sheet 股份支付实质性程序表 J3A
A1: 致同会计师事务所
A2: 股份支付实质性程序表
A3: =底稿目录!A2 -> 被审计单位： | C3: =底稿目录!A4 -> 编制人： | E3: =底稿目录!A5 -> 编制日期： | H3: 索引号： | I3: =底稿目录!F3 -> J3A
A4: =底稿目录!A3 -> 截止日：202X年12月31日 | C4: =底稿目录!A6 -> 复核人： | E4: =底稿目录!A7 -> 复核日期： | H4: 页 次：
A5: 一、本账户涉及的科目
A6: 应付职工薪酬
A7: 二、审计目标与认定的对应关系
A8: 审计目标 | G8: 财务报表的认定
A9: A. 资产负债表中记录的应付职工薪酬是存在的，且已经记录在恰当的账户中 | G9: 存在
A10: B. 所有应记录的应付职工薪酬均已记录，所有应当包括在财务报表中的相关披露均已包括 | G10: 完整性
A11: C. 记录的应付职工薪酬由被审计单位拥有或控制 | G11: 权利和义务
A12: D. 应付职工薪酬以恰当的金额包括在财务报表中，与之相关的计价或分摊调整已恰当记录，相关披露已得到恰当计量和描述 | G12: 准确性、计价和分摊
A13: E. 应付职工薪酬已被恰当地汇总或分解且表述清楚，相关披露在按照企业会计准则的编制基础下是相关的、可理解的 | G13: 列报与披露
A14: 三、计划实施的实质性程序
A15: 序号 | B15: 审计程序 | C15: 程序分类 | D15: 财务报表的认定 | I15: 底稿索引号
D16: 存在 | E16: 完整性 | F16: 权利和 义务 | G16: 准确性、计价和分摊 | H16: 列报
A17: 1 | B17: 检查股份支付的相关决议、协议，并结合业务内容，判断其作为一项为股份支付是否恰当。 | C17: 常规★ | D17: √ | E17: √ | F17: √ | I17: J3-1
A18: 2 | B18: 判断股份支付的分类是否恰当： (1)股份支付的授予日确认是否恰当； (2)股份支付划分为以权益结算还是以现金结算的类别是否恰当； (3)股份支付划分为授予后立即可行权的还是完成等待期内的服务或达到规定业绩条件才可行权的类别是否恰当 。 | C18: 常规★ | D18: √ | E18: √ | F18: √ | G18: √ | H18: √ | I18: J3-1
A19: 3 | B19: 复核股份支付使用相关假设是否合理，公允价值计量是否符合企业会计准则的规定，必要时聘请估值专家对公允价值进行评估。 | C19: 常规★ | G19: √ | I19: J3-1
A20: 4 | B20: 检查股份支付确认的会计处理是否恰当，包括计入管理费用、生产成本、资本公积等会计科目是否符合企业会计准则的规定。 | C20: 常规★ | H20: √ | I20: J3-1
A21: 5 | B21: 检查完成等待期内的服务或达到规定业绩条件才可行权的股份支付在等待期内的每个资声负债表日的会计处理是否恰当。 （1）以权益结算的股份支付是否以对可行权权益工具数量的最佳估计为墓础，按照权益工具授予日的公允价值，将当期取得的服务计入相关报表项目； （2）以现金结算的股份支付是否以可行权情况的最佳估计为基础，按照承担负债的公允价值金额，将当期取得的服务计入相关报表项目； （3）后续信息表明可行权权益工具的数量或当期承担债务的公允价值与以前估计不同的，是否进行调整，并在可行权日，调整至实际可行权的权益工具数量或实际可行权水平。 | C21: 常规★ | D21: √ | E21: √ | F21: √ | G21: √ | H21: √ | I21: J3-2
A22: 6 | B22: 对本期股份支付的减少，检查至实际以现金结算的股份支付金额或企业根据实际行权的权益工具数量等信息的支持性文件，确定会计处理是否正确；对于股份支付安排的取消获取相关支持性文件并检查会计处理是否恰当。 | C22: 常规★ | D22: √ | E22: √ | F22: √ | G22: √ | I22: J3-2
A23: 7 | B23: 检查股份支付的修改、变更及采用新股份支付替代取消的原股份支付相关会计处理是否恰当。 | C23: 常规★ | D23: √ | E23: √ | F23: √ | G23: √ | I23: J3-2
A24: 8 | B24: 针对识别的其他舞弊风险等因素增加的审计程序。 | C24: IPO/上市/新三板/重组/舞弊应对
A25: 9 | B25: 检查股份支付是否已按企业会计准则或其他适用的规定在财务报表中做出恰当列报和披露。 | C25: 常规★ | H25: √ | I25: A 1-1/A1-15 /A1-16

Sheet 股份支付情况表J3-1
A1: 致同会计师事务所
A2: 应付职工薪酬-股份支付情况表
A3: =底稿目录!A2 -> 被审计单位： | E3: =底稿目录!A4 -> 编制人： | I3: =底稿目录!A5 -> 编制日期： | M3: 索引号： | N3: =底稿目录!F4 -> J3-1
A4: =底稿目录!A3 -> 截止日：202X年12月31日 | E4: =底稿目录!A6 -> 复核人： | I4: =底稿目录!A7 -> 复核日期： | M4: 页 次：
A5: 一、审计目标:
A6: 1.资产负债表中记录的应付职工薪酬是存在的，且已经记录在恰当的账户中
A7: 2.所有应记录的应付职工薪酬均已记录，所有应当包括在财务报表中的相关披露均已包括
A8: 3.记录的应付职工薪酬由被审计单位拥有或控制
A9: 4.应付职工薪酬以恰当的金额包括在财务报表中，与之相关的计价或分摊调整已恰当记录，相关披露已得到恰当计量和描述
A10: 5.应付职工薪酬已被恰当地汇总或分解且表述清楚，相关披露在按照企业会计准则的编制基础下是相关的、可理解的
A11: 二、审计过程：
A12: 1.公司股份支付决议及其内容：
A14: 2.公允价值的确定及相关假设
A16: 3.了解专家资质及利用精算师的工作
A17: 序号 | B17: 项目 | D17: 索引号
A18: 1 | B18: 利用专家的工作 | D18: S12
A19: 2 | B19: 评估专家工作 | D19: S12A
A20: 股份支付项目名称 | B20: 类型 | C20: 授予日 | D20: 批准部门 | E20: 行权日 | F20: 权益工具数量 | G20: 等待期 | H20: 公允价值确定方法和数据来源 | I20: 协议变更/取消情况 | J20: 资产负债表日估计更新情况 | K20: 剩余等待期限 | L20: 协议索引号 | M20: 股份支付计算表索引号 | N20: 结论
B21: 以权益工具结算
A28: 三、审计说明：
A29: 1.被审计单位确认以现金/权益结算的股份支付XX元，计入应付职工薪酬/资本公积，同时分配计入管理费用XX元、销售费用XX元、……
A31: 四、审计结论：
A35: 提示1：股份支付主要审计过程和关注要点
A36: 1.取得股份支付薪酬奖励与董事会会议纪录或其他支持性文件，了解主要条款及条件（即授予日期、期权的价格、股数、行使日期等），并确定企业是否有政策限制该股份支付薪酬奖励发行的日期，关注确定是否授权日与行权日之间存在重大时间间隔；取得股份支付的所有个人都是雇员或其他提供类似服务的人员，并且复核条件；
A37: 2.根据该股份支付薪酬奖励的条款和条件，确定其分类（如分类为权益结算、现金结算、或者二者结合）适当，并判断所采用的会计处理是否能恰当地反映这种分类
A38: 3.检查授予后立即可行权的以现金结算的股份支付，是否在授权日以承担负债的公允价值计入相关成本或费用；
A39: 4.对新的或修改的股份支付进行分析： ①确定包括在分析中的所有个人都是雇员或其他提供类似服务的人员。 ②将新的股份支付薪酬奖励与董事会会议纪录或其它授权文件相比较。确定是否存在董事会会议记录或其他文件中提及的股份支付薪酬奖励尚未包含在上面的分析之内。如果是，获取该股份支付相关支持性文件，并确定该遗漏是否适当。 ③是否已适当地确认对现有的股份支付薪酬奖励的修改（如有修改）。
A40: 5.选取样本（如需要）： ①取得合同及其他支持性文件。 ②确认主要条款及条件与股份支付薪酬工具是否一致（授予日期、期权的价格、股数、行使日期等）。 ③确定是否授权日与行权日之间存在重大时间间隔，如果有，向适当的人员询问原因。
A41: 6.了解股份支付公允价值计算相关假设，确定假设的合理性
A42: 7.确定是否需要聘请估值专家，以协助评价：企业的专家（无论其是第三方还是内部员工）对该工具估值的工作。完成“专家资质”和“专家工作”的审计程序，以评估估值专家（无论其是第三方还是内部员工）的资质及其工作
A43: 8.考虑公司是否存在缺乏现金用于奖励员工、过去的股票价格波动性很大、授予日刻意选在一个特定的日期、期权授予与预定日期不一致，而无规则地出现在期权授予的整个时期之间等情况，表明利用股票期权日期倒签等获取不正当利益的股份期权；

Sheet 股份支付检查表J3-2
A1: 致同会计师事务所
A2: 应付职工薪酬-股份支付检查表
A3: =底稿目录!A2 -> 被审计单位： | H3: =底稿目录!A4 -> 编制人： | N3: =底稿目录!A5 -> 编制日期： | R3: 索引号： | S3: =底稿目录!F5 -> J3-2
A4: =底稿目录!A3 -> 截止日：202X年12月31日 | H4: =底稿目录!A6 -> 复核人： | N4: =底稿目录!A7 -> 复核日期： | R4: 页次：
A5: 一、审计目标:
A6: 1.资产负债表中记录的应付职工薪酬是存在的，且已经记录在恰当的账户中
A7: 2.所有应记录的应付职工薪酬均已记录，所有应当包括在财务报表中的相关披露均已包括
A8: 3.记录的应付职工薪酬由被审计单位拥有或控制
A9: 4.应付职工薪酬以恰当的金额包括在财务报表中，与之相关的计价或分摊调整已恰当记录，相关披露已得到恰当计量和描述
A10: 5.应付职工薪酬已被恰当地汇总或分解且表述清楚，相关披露在按照企业会计准则的编制基础下是相关的、可理解的
A11: 二、审计过程：
A12: 1.抽查本期增减变动的准确性性及会计处理的适当性
A13: 股份支付种类 | B13: 时间 | C13: 每股股票/每份增值权公允价值 | D13: 每股股票/每份增值权支付现金 | E13: 股份支付总人数 | F13: 离职人数 | G13: 行权人数 | H13: 每人获得的股份数量 | I13: 连续服务年限 | J13: 测算应付职工薪酬金额 | K13: 账面应付职工薪酬金额 | L13: 差异 | M13: 支付现金金额 | N13: 测算当期费用/公允价值变动金额 | O13: 账面记录当期费用/公允价值变动金额 | P13: 差异 | Q13: 是否为雇员或其他提供类似服务的人员 | R13: 主要条款及条件与股份支付薪酬工具是否一致 | S13: 授权日与行权日之间是否存在重大时间间隔
L14: =J14-K14 -> 0 | M14: 0 | P14: =N14-O14 -> 0
L15: =J15-K15 -> 0 | M15: 0 | P15: =N15-O15 -> 0
L16: =J16-K16 -> 0 | M16: 0 | P16: =N16-O16 -> 0
L17: =J17-K17 -> 0 | M17: 0 | P17: =N17-O17 -> 0
L18: =J18-K18 -> 0 | M18: 0 | P18: =N18-O18 -> 0
A19: 合计 | E19: =SUM(E14:E18) -> 0 | F19: =SUM(F14:F18) -> 0 | G19: =SUM(G14:G18) -> 0 | J19: =SUM(J14:J18) -> 0 | K19: =SUM(K14:K18) -> 0 | L19: =SUM(L14:L18) -> 0 | M19: =SUM(M14:M18) -> 0 | N19: =SUM(N14:N18) -> 0 | O19: =SUM(O14:O18) -> 0 | P19: =SUM(P14:P18) -> 0
A21: 2.抽查本期增减变动的准确性性及会计处理的适当性
A22: 日 期 | B22: 凭证种类 | C22: 凭证编号 | D22: 业务内容 | E22: 明细科目 | F22: 对方科目 | G22: 金 额 | I22: 附件 | J22: 结论
G23: 借方 | H23: 贷方
A31: 三、审计说明：
A34: 四、审计结论：
A37: 提示：
A38: 1.检查完成等待后的服务或达到规定业绩条件以后才可行权的以现金结算的股份支付，在等待期内的每个资产负债表日，
A39: 是否以可行权情况的最佳估计为基础，按照承担负债的公允价值金额，将当期取得的服务计入成本或费用。在资产负债表日，
A40: 后续信息表明当期承担债务的公允价值与以前估计不同的，是否进行调整。并在可行权日，调整至实际可行权水平；
A41: 2.检查可行权日之后，以现金结算的股份支付当期公允价值的变动金额，是否借记或贷记“公允价值变动损益”

Sheet IPO企业股权激励工具关注的审计重点
A1: 北京注册会计师协会专家委员会提示[2016]第8号—IPO企业股权激励工具关注的审计重点
A2: 股权激励计划作为行之有效的激励工具，在众多企业中被广泛采用。企业在实施IPO计划中，已经设定的股权激励工具在财务报表上具有较重要的影响，是IPO审计应关注的重点和难点。
A3: 本提示仅供事务所及相关从业人员在执业中参考，不能替代相关法律法规、注册会计师执业准则及注册会计师职业判断。提示中所涉及的审计时间 、范围和程度等，事务所及相关从业人员在执业中需结合实际情况、风险导向原则以及注册会计师的职业判断确定，不能直接照搬照抄。
A4: 针对有股权激励工具的IPO企业应关注的财务报表影响，IPO审计专家委员会做出如下提示：
A5: 一、关注IPO企业在以往期间的股权激励工具
A6: 《公司法》第一百四十二条中规定公司不得收购本公司股份，但以下情形除外：“将股份奖励给本公司职工；公司依照第一款第(三)项规定收购的本公司股份，不得超过本公司已发行股份总额的百分之五；用于收购的资金应当从公司的税后利润中支出；所收购的股份应当在一年内转让给职工。” 随着《公司法》修订及新会计准则的实施，股权激励计划作为一项行之有效的长期激励工具，已经被众多企业广泛采用。
A7: （一） 对历史财务报表以外信息的关注
A8: 对已经采用股权激励的企业，公司历史财务报表很可能没有体现出其相应的会计处理。启动IPO审计工作计划时，仅从历史财务报表无法发现并辨别公司是否有此事项，需要注册会计师特别关注，并主动与公司管理层及股东讨论询问，在公司历史年度是否存在《企业会计准则第11 号—股份支付》中所明确的股份支付的情形，辨认出是否存在适用的事项。
A9: （二） 深入沟通股份支付的会计影响
A10: 对于IPO企业的股份支付主体，《企业会计准则第11 号—股份支付》规定：“股份支付所指的权益工具是指企业自身权益工具，包括企业本身、企业的母公司或同集团其他会计主体的权益工具。”大多数公司采用企业本身的权益工具，或者企业控股公司。企业控股公司通常为专门设立的股权激励平台公司或者控股壳公司。管理层和股东对股份支付的会计影响的认知可能与准则不一致，注册会计师需要深入沟通讨论。通常如下情形属于股份支付的会计影响事项：
A11: 1.公司向董事、高管、核心员工、员工持股平台或者其他人员，发行的新股股份价格明显低于公允价值。这里，要注意其他人员，包括个人或者公司，也可能落入股份支付的范畴，进而导致股份支付的影响；
A12: 2.股东将其持有的股份以较低的价格转让给如上人士，也属于股份支付会计事项；
... A40: 由于公司与被授予对象均签署承诺函，明确认可自本激励计划授予日起3年内全职在公司工作后，才有权享有股权激励计划的相关收益。因此，公司认为股份支付锁定期a为36个月。2015年1月，公司启动A股创业板IPO计划，公司管理层在此时分析判断，自2015年1月IPO启动至上市前被审核的最近一个会计期间截止日，预计将持续24个月，即b为24个月。因此，为确保上市审核时遵守IPO规则中“股权清晰”的要求，公司与相关员工约定“如果公司在原约定的解锁日之前上市，则股份支付相关的股份立即解锁”。公司按照修订服务期条件采用股份支付锁定期与自股份支付授予日至上市成功日之间孰短的原则，应按b即24个月对股份支付的公允价值进行摊销。同时，管理层还需在持续每六个月更新申报材料之时，依据相关外部监管规则和申请过程中环境的动态变化以及公司自身内部IPO成熟度的把握，及时更新对b的估计。

Sheet 首发业务解答二
A1: 首发业务问答（二）
A2: 问题1、股份支付
A3: 问题1、基于企业发展考虑，部分首发企业上市前通过增资或转让股份等形式实现高管或核心技术人员、员工、主要业务伙伴持股。首发企业股份支付成因复杂，公允价值难以计量，与上市公司实施股权激励相比存在较大不同。对此，首发企业及中介机构需重点关注哪些方面？
A4: 答：发行人报告期内为获取职工和其他方提供服务而授予股份的交易，在编制申报会计报表时，应按照《企业会计准则第11号——股份支付》相关规定进行处理。
A5: （1）具体适用情形
A6: 对于报告期内发行人向职工（含持股平台）、客户、供应商等新增股份，以及主要股东及其关联方向职工（含持股平台）、客户、供应商等转让股份，均应考虑是否适用《企业会计准则第11号——股份支付》。对于报告期前的股份支付事项，如对期初未分配利润造成重大影响，也应考虑是否适用《企业会计准则第11号——股份支付》。
A7: 通常情况下，解决股份代持等规范措施导致股份变动，家族内部财产分割、继承、赠与等非交易行为导致股权变动，资产重组、业务并购、持股方式转换、向老股东同比例配售新股等导致股权变动等，在有充分证据支持相关股份获取与发行人获得其服务无关的情况下，一般无需作为股份支付处理。
A8: 对于为发行人提供服务的实际控制人/老股东以低于股份公允价值的价格增资入股事宜，如果根据增资协议，并非所有股东均有权按各自原持股比例获得新增股份，对于实际控制人/老股东超过其原持股比例而获得的新增股份，应属于股份支付；如果增资协议约定，所有股东均有权按各自原持股比例获得新增股份，但股东之间转让新增股份受让权且构成集团内股份支付，导致实际控制人/老股东超过其原持股比例获得的新增股份，也属于股份支付。对于实际控制人/老股东原持股比例，应按照相关股东直接持有与穿透控股平台后间接持有的股份比例合并计算。
A9: （2）确定公允价值
A10: 存在股份支付事项的，发行人及申报会计师应按照企业会计准则规定的原则确定权益工具的公允价值。在确定公允价值时，可合理考虑入股时间阶段、业绩基础与变动预期、市场环境变化、行业特点、同行业并购重组市盈率水平、股份支付实施或发生当年市盈率与市净率指标等因素的影响；也可优先参考熟悉情况并按公平原则自愿交易的各方最近达成的入股价格或相似股权价格确定公允价值，如近期合理的PE入股价；也可采用恰当的估值技术确定公允价值，但要避免采取有争议的、结果显失公平的估值技术或公允价值确定方法，如明显增长预期下按照成本法评估的每股净资产价值或账面净资产。
A11: （3）计量方式
A12: 确认股份支付费用时，对增资或受让的股份立即授予或转让完成且没有明确约定服务期等限制条件的，原则上应当一次性计入发生当期，并作为偶发事项计入非经常性损益。对设定服务期等限制条件的股份支付，股份支付费用可采用恰当的方法在服务期内进行分摊，并计入经常性损益。
... A14: 发行人应在招股说明书及报表附注中披露股份支付的形成原因、权益工具的公允价值及确认方法。保荐机构及申报会计师应对首发企业报告期内发生的股份变动是否适用《企业会计准则第11号——股份支付》进行核查，并对以下问题发表明确意见：股份支付相关权益工具公允价值的计量方法及结果是否合理，与同期可比公司估值是否存在重大差异及原因；对于存在与股权所有权或收益权等相关的限制性条件的，相关条件是否真实、可行，服务期的判断是否准确，服务期各年/期确认的员工服务成本或费用是否准确；发行人报告期内股份支付相关会计处理是否符合《企业会计准则》相关规定。
